{"diags":"Participant 0:\n/usr/bin/iperf3 -p 5201 -B 172.16.0.2 -c 172.16.0.1 -t 60 --json --rsa-public-key-path /var/run/pscheduler-server/runner/tmp/tmp54675cpn/tmp5e9gymw4/public-key --username 2U6qJqMAKeK5n0cKXo6A\n\n{\n    \"end\": {\n        \"cpu_utilization_percent\": {\n            \"host_system\": 0.0580931864891447, \n            \"host_total\": 0.07259818132854105, \n            \"host_user\": 0.014504994839396363, \n            \"remote_system\": 0.7172010449307492, \n            \"remote_total\": 0.9695711289810193, \n            \"remote_user\": 0.25236841783420366\n        }, \n        \"receiver_tcp_congestion\": \"htcp\", \n        \"sender_tcp_congestion\": \"htcp\", \n        \"streams\": [\n            {\n                \"receiver\": {\n                    \"bits_per_second\": 4494354.60213354, \n                    \"bytes\": 33716728, \n                    \"end\": 60.016142, \n                    \"seconds\": 60.001635, \n                    \"sender\": true, \n                    \"socket\": 5, \n                    \"start\": 0\n                }, \n                \"sender\": {\n                    \"bits_per_second\": 4928172.907288277, \n                    \"bytes\": 36962304, \n                    \"end\": 60.001635, \n                    \"max_rtt\": 518131, \n                    \"max_snd_cwnd\": 402544, \n                    \"max_snd_wnd\": 0, \n                    \"mean_rtt\": 104483, \n                    \"min_rtt\": 17818, \n                    \"retransmits\": 1048, \n                    \"seconds\": 60.001635, \n                    \"sender\": true, \n                    \"socket\": 5, \n                    \"start\": 0\n                }\n            }\n        ], \n        \"sum_received\": {\n            \"bits_per_second\": 4494354.60213354, \n            \"bytes\": 33716728, \n            \"end\": 60.016142, \n            \"seconds\": 60.016142, \n            \"sender\": true, \n            \"start\": 0\n        }, \n        \"sum_sent\": {\n            \"bits_per_second\": 4928172.907288277, \n            \"bytes\": 36962304, \n            \"end\": 60.001635, \n            \"retransmits\": 1048, \n            \"seconds\": 60.001635, \n            \"sender\": true, \n            \"start\": 0\n        }\n    }, \n    \"intervals\": [\n        {\n            \"streams\": [\n                {\n                    \"bits_per_second\": 44037420.17446564, \n                    \"bytes\": 5505024, \n                    \"end\": 1.000063, \n                    \"omitted\": false, \n                    \"pmtu\": 1500, \n                    \"retransmits\": 342, \n                    \"rtt\": 145332, \n                    \"rttvar\": 2293, \n                    \"seconds\": 1.0000629425048828, \n                    \"sender\": true, \n                    \"snd_cwnd\": 402544, \n                    \"snd_wnd\": -1, \n                    \"socket\": 5, \n                    \"start\": 0\n                }\n            ], \n            \"sum\": {\n                \"bits_per_second\": 44037420.17446564, \n                \"bytes\": 5505024, \n                \"end\": 1.000063, \n                \"omitted\": false, \n                \"retransmits\": 342, \n                \"seconds\": 1.0000629425048828, \n                \"sender\": true, \n                \"start\": 0\n            }\n        }, \n        {\n            \"streams\": [\n                {\n                    \"bits_per_second\": 20971122.507534184, \n                    \"bytes\": 2621440, \n                    \"end\": 2.000082, \n                    \"omitted\": false, \n                    \"pmtu\": 1500, \n                    \"retransmits\": 6, \n                    \"rtt\": 83919, \n                    \"rttvar\": 10643, \n                    \"seconds\": 1.0000189542770386, \n                    \"sender\": true, \n                    \"snd_cwnd\": 214304, \n                    \"snd_wnd\": -1, \n                    \"socket\": 5, \n                    \"start\": 1.000063\n                }\n            ], \n            \"sum\": {\n                \"bits_per_second\": 20971122.507534184, \n                \"bytes\": 2621440, \n                \"end\": 2.000082, \n                \"omitted\": false, \n                \"retransmits\": 6, \n                \"seconds\": 1.0000189542770386, \n                \"sender\": true, \n                \"start\": 1.000063\n            }\n        }, \n        {\n            \"streams\": [\n                {\n                    \"bits_per_second\": 10485540.004615687, \n                    \"bytes\": 1310720, \n                    \"end\": 3.000103, \n                    \"omitted\": false, \n                    \"pmtu\": 1500, \n                    \"retransmits\": 57, \n                    \"rtt\": 51588, \n                    \"rttvar\": 842, \n                    \"seconds\": 1.000020980834961, \n                    \"sender\": true, \n                    \"snd_cwnd\": 127424, \n                    \"snd_wnd\": -1, \n                    \"socket\": 5, \n                    \"start\": 2.000082\n                }\n            ], \n            \"sum\": {\n                \"bits_per_second\": 10485540.004615687, \n                \"bytes\": 1310720, \n                \"end\": 3.000103, \n                \"omitted\": false, \n                \"retransmits\": 57, \n                \"seconds\": 1.000020980834961, \n                \"sender\": true, \n                \"start\": 2.000082\n            }\n        }, \n        {\n            \"streams\": [\n                {\n                    \"bits_per_second\": 20972442.540580925, \n                    \"bytes\": 2621440, \n                    \"end\": 4.000059, \n                    \"omitted\": false, \n                    \"pmtu\": 1500, \n                    \"retransmits\": 51, \n                    \"rtt\": 38289, \n                    \"rttvar\": 551, \n                    \"seconds\": 0.9999560117721558, \n                    \"sender\": true, \n                    \"snd_cwnd\": 81088, \n                    \"snd_wnd\": -1, \n                    \"socket\": 5, \n                    \"start\": 3.000103\n                }\n            ], \n            \"sum\": {\n                \"bits_per_second\": 20972442.540580925, \n                \"bytes\": 2621440, \n                \"end\": 4.000059, \n                \"omitted\": false, \n                \"retransmits\": 51, \n                \"seconds\": 0.9999560117721558, \n                \"sender\": true, \n                \"start\": 3.000103\n            }\n        }, \n        {\n            \"streams\": [\n                {\n                    \"bits_per_second\": 10485100.041539438, \n                    \"bytes\": 1310720, \n                    \"end\": 5.000122, \n                    \"omitted\": false, \n                    \"pmtu\": 1500, \n                    \"retransmits\": 27, \n                    \"rtt\": 133657, \n                    \"rttvar\": 110861, \n                    \"seconds\": 1.0000629425048828, \n                    \"sender\": true, \n                    \"snd_cwnd\": 39096, \n                    \"snd_wnd\": -1, \n                    \"socket\": 5, \n                    \"start\": 4.000059\n                }\n            ], \n            \"sum\": {\n                \"bits_per_second\": 10485100.041539438, \n                \"bytes\": 1310720, \n                \"end\": 5.000122, \n                \"omitted\": false, \n                \"retransmits\": 27, \n                \"seconds\": 1.0000629425048828, \n                \"sender\": true, \n                \"start\": 4.000059\n            }\n        }, \n        {\n            \"streams\": [\n                {\n                    \"bits_per_second\": 0, \n                    \"bytes\": 0, \n                    \"end\": 6.000078, \n                    \"omitted\": false, \n                    \"pmtu\": 1500, \n                    \"retransmits\": 55, \n                    \"rtt\": 28945, \n                    \"rttvar\": 658, \n                    \"seconds\": 0.9999560117721558, \n                    \"sender\": true, \n                    \"snd_cwnd\": 62264, \n                    \"snd_wnd\": -1, \n                    \"socket\": 5, \n                    \"start\": 5.000122\n                }\n            ], \n            \"sum\": {\n                \"bits_per_second\": 0, \n                \"bytes\": 0, \n                \"end\": 6.000078, \n                \"omitted\": false, \n                \"retransmits\": 55, \n                \"seconds\": 0.9999560117721558, \n                \"sender\": true, \n                \"start\": 5.000122\n            }\n        }, \n        {\n            \"streams\": [\n                {\n                    \"bits_per_second\": 20971855.00535139, \n                    \"bytes\": 2621440, \n                    \"end\": 7.000062, \n                    \"omitted\": false, \n                    \"pmtu\": 1500, \n                    \"retransmits\": 0, \n                    \"rtt\": 45768, \n                    \"rttvar\": 330, \n                    \"seconds\": 0.9999840259552002, \n                    \"sender\": true, \n                    \"snd_cwnd\": 98464, \n                    \"snd_wnd\": -1, \n                    \"socket\": 5, \n                    \"start\": 6.000078\n                }\n            ], \n            \"sum\": {\n                \"bits_per_second\": 20971855.00535139, \n                \"bytes\": 2621440, \n                \"end\": 7.000062, \n                \"omitted\": false, \n                \"retransmits\": 0, \n                \"seconds\": 0.9999840259552002, \n                \"sender\": true, \n                \"start\": 6.000078\n            }\n        }, \n        {\n            \"streams\": [\n                {\n                    \"bits_per_second\": 10485896.25177043, \n                    \"bytes\": 1310720, \n                    \"end\": 8.000049, \n                    \"omitted\": false, \n                    \"pmtu\": 1500, \n                    \"retransmits\": 22, \n                    \"rtt\": 126558, \n                    \"rttvar\": 93187, \n                    \"seconds\": 0.999987006187439, \n                    \"sender\": true, \n                    \"snd_cwnd\": 11584, \n                    \"snd_wnd\": -1, \n                    \"socket\": 5, \n                    \"start\": 7.000062\n                }\n            ], \n            \"sum\": {\n                \"bits_per_second\": 10485896.25177043, \n                \"bytes\": 1310720, \n                \"end\": 8.000049, \n                \"omitted\": false, \n                \"retransmits\": 22, \n                \"seconds\": 0.999987006187439, \n                \"sender\": true, \n                \"start\": 7.000062\n            }\n        }, \n        {\n            \"streams\": [\n                {\n                    \"bits_per_second\": 0, \n                    \"bytes\": 0, \n                    \"end\": 9.000025, \n                    \"omitted\": false, \n                    \"pmtu\": 1500, \n                    \"retransmits\": 7, \n                    \"rtt\": 103126, \n                    \"rttvar\": 76313, \n                    \"seconds\": 0.9999759793281555, \n                    \"sender\": true, \n                    \"snd_cwnd\": 5792, \n                    \"snd_wnd\": -1, \n                    \"socket\": 5, \n                    \"start\": 8.000049\n                }\n            ], \n            \"sum\": {\n                \"bits_per_second\": 0, \n                \"bytes\": 0, \n                \"end\": 9.000025, \n                \"omitted\": false, \n                \"retransmits\": 7, \n                \"seconds\": 0.9999759793281555, \n                \"sender\": true, \n                \"start\": 8.000049\n            }\n        }, \n        {\n            \"streams\": [\n                {\n                    \"bits_per_second\": 0, \n                    \"bytes\": 0, \n                    \"end\": 10.000081, \n                    \"omitted\": false, \n                    \"pmtu\": 1500, \n                    \"retransmits\": 5, \n                    \"rtt\": 518131, \n                    \"rttvar\": 656038, \n                    \"seconds\": 1.0000560283660889, \n                    \"sender\": true, \n                    \"snd_cwnd\": 2896, \n                    \"snd_wnd\": -1, \n                    \"socket\": 5, \n                    \"start\": 9.000025\n                }\n            ], \n            \"sum\": {\n                \"bits_per_second\": 0, \n                \"bytes\": 0, \n                \"end\": 10.000081, \n                \"omitted\": false, \n                \"retransmits\": 5, \n                \"seconds\": 1.0000560283660889, \n                \"sender\": true, \n                \"start\": 9.000025\n            }\n        }, \n        {\n            \"streams\": [\n                {\n                    \"bits_per_second\": 0, \n                    \"bytes\": 0, \n                    \"end\": 11.000097, \n                    \"omitted\": false, \n                    \"pmtu\": 1500, \n                    \"retransmits\": 0, \n                    \"rtt\": 518131, \n                    \"rttvar\": 656038, \n                    \"seconds\": 1.0000159740448, \n                    \"sender\": true, \n                    \"snd_cwnd\": 2896, \n                    \"snd_wnd\": -1, \n                    \"socket\": 5, \n                    \"start\": 10.000081\n                }\n            ], \n            \"sum\": {\n                \"bits_per_second\": 0, \n                \"bytes\": 0, \n                \"end\": 11.000097, \n                \"omitted\": false, \n                \"retransmits\": 0, \n                \"seconds\": 1.0000159740448, \n                \"sender\": true, \n                \"start\": 10.000081\n            }\n        }, \n        {\n            \"streams\": [\n                {\n                    \"bits_per_second\": 0, \n                    \"bytes\": 0, \n                    \"end\": 12.000058, \n                    \"omitted\": false, \n                    \"pmtu\": 1500, \n                    \"retransmits\": 0, \n                    \"rtt\": 518131, \n                    \"rttvar\": 656038, \n                    \"seconds\": 0.999961018562317, \n                    \"sender\": true, \n                    \"snd_cwnd\": 2896, \n                    \"snd_wnd\": -1, \n                    \"socket\": 5, \n                    \"start\": 11.000097\n                }\n            ], \n            \"sum\": {\n                \"bits_per_second\": 0, \n                \"bytes\": 0, \n                \"end\": 12.000058, \n                \"omitted\": false, \n                \"retransmits\": 0, \n                \"seconds\": 0.999961018562317, \n                \"sender\": true, \n                \"start\": 11.000097\n            }\n        }, \n        {\n            \"streams\": [\n                {\n                    \"bits_per_second\": 0, \n                    \"bytes\": 0, \n                    \"end\": 13.000119, \n                    \"omitted\": false, \n                    \"pmtu\": 1500, \n                    \"retransmits\": 0, \n                    \"rtt\": 518131, \n                    \"rttvar\": 656038, \n                    \"seconds\": 1.00006103515625, \n                    \"sender\": true, \n                    \"snd_cwnd\": 2896, \n                    \"snd_wnd\": -1, \n                    \"socket\": 5, \n                    \"start\": 12.000058\n                }\n            ], \n            \"sum\": {\n                \"bits_per_second\": 0, \n                \"bytes\": 0, \n                \"end\": 13.000119, \n                \"omitted\": false, \n                \"retransmits\": 0, \n                \"seconds\": 1.00006103515625, \n                \"sender\": true, \n                \"start\": 12.000058\n            }\n        }, \n        {\n            \"streams\": [\n                {\n                    \"bits_per_second\": 0, \n                    \"bytes\": 0, \n                    \"end\": 14.000061, \n                    \"omitted\": false, \n                    \"pmtu\": 1500, \n                    \"retransmits\": 51, \n                    \"rtt\": 21358, \n                    \"rttvar\": 4205, \n                    \"seconds\": 0.9999420046806335, \n                    \"sender\": true, \n                    \"snd_cwnd\": 14480, \n                    \"snd_wnd\": -1, \n                    \"socket\": 5, \n                    \"start\": 13.000119\n                }\n            ], \n            \"sum\": {\n                \"bits_per_second\": 0, \n                \"bytes\": 0, \n                \"end\": 14.000061, \n                \"omitted\": false, \n                \"retransmits\": 51, \n                \"seconds\": 0.9999420046806335, \n                \"sender\": true, \n                \"start\": 13.000119\n            }\n        }, \n        {\n            \"streams\": [\n                {\n                    \"bits_per_second\": 0, \n                    \"bytes\": 0, \n                    \"end\": 15.000033, \n                    \"omitted\": false, \n                    \"pmtu\": 1500, \n                    \"retransmits\": 0, \n                    \"rtt\": 21358, \n                    \"rttvar\": 4205, \n                    \"seconds\": 0.9999719858169556, \n                    \"sender\": true, \n                    \"snd_cwnd\": 14480, \n                    \"snd_wnd\": -1, \n                    \"socket\": 5, \n                    \"start\": 14.000061\n                }\n            ], \n            \"sum\": {\n                \"bits_per_second\": 0, \n                \"bytes\": 0, \n                \"end\": 15.000033, \n                \"omitted\": false, \n                \"retransmits\": 0, \n                \"seconds\": 0.9999719858169556, \n                \"sender\": true, \n                \"start\": 14.000061\n            }\n        }, \n        {\n            \"streams\": [\n                {\n                    \"bits_per_second\": 0, \n                    \"bytes\": 0, \n                    \"end\": 16.000059, \n                    \"omitted\": false, \n                    \"pmtu\": 1500, \n                    \"retransmits\": 1, \n                    \"rtt\": 21358, \n                    \"rttvar\": 4205, \n                    \"seconds\": 1.000025987625122, \n                    \"sender\": true, \n                    \"snd_cwnd\": 1448, \n                    \"snd_wnd\": -1, \n                    \"socket\": 5, \n                    \"start\": 15.000033\n                }\n            ], \n            \"sum\": {\n                \"bits_per_second\": 0, \n                \"bytes\": 0, \n                \"end\": 16.000059, \n                \"omitted\": false, \n                \"retransmits\": 1, \n                \"seconds\": 1.000025987625122, \n                \"sender\": true, \n                \"start\": 15.000033\n            }\n        }, \n        {\n            \"streams\": [\n                {\n                    \"bits_per_second\": 0, \n                    \"bytes\": 0, \n                    \"end\": 17.000071, \n                    \"omitted\": false, \n                    \"pmtu\": 1500, \n                    \"retransmits\": 0, \n                    \"rtt\": 21358, \n                    \"rttvar\": 4205, \n                    \"seconds\": 1.0000120401382446, \n                    \"sender\": true, \n                    \"snd_cwnd\": 1448, \n                    \"snd_wnd\": -1, \n                    \"socket\": 5, \n                    \"start\": 16.000059\n                }\n            ], \n            \"sum\": {\n                \"bits_per_second\": 0, \n                \"bytes\": 0, \n                \"end\": 17.000071, \n                \"omitted\": false, \n                \"retransmits\": 0, \n                \"seconds\": 1.0000120401382446, \n                \"sender\": true, \n                \"start\": 16.000059\n            }\n        }, \n        {\n            \"streams\": [\n                {\n                    \"bits_per_second\": 0, \n                    \"bytes\": 0, \n                    \"end\": 18.000035, \n                    \"omitted\": false, \n                    \"pmtu\": 1500, \n                    \"retransmits\": 0, \n                    \"rtt\": 21358, \n                    \"rttvar\": 4205, \n                    \"seconds\": 0.9999639987945557, \n                    \"sender\": true, \n                    \"snd_cwnd\": 1448, \n                    \"snd_wnd\": -1, \n                    \"socket\": 5, \n                    \"start\": 17.000071\n                }\n            ], \n            \"sum\": {\n                \"bits_per_second\": 0, \n                \"bytes\": 0, \n                \"end\": 18.000035, \n                \"omitted\": false, \n                \"retransmits\": 0, \n                \"seconds\": 0.9999639987945557, \n                \"sender\": true, \n                \"start\": 17.000071\n            }\n        }, \n        {\n            \"streams\": [\n                {\n                    \"bits_per_second\": 0, \n                    \"bytes\": 0, \n                    \"end\": 19.00077, \n                    \"omitted\": false, \n                    \"pmtu\": 1500, \n                    \"retransmits\": 11, \n                    \"rtt\": 36009, \n                    \"rttvar\": 2130, \n                    \"seconds\": 1.00073504447937, \n                    \"sender\": true, \n                    \"snd_cwnd\": 13032, \n                    \"snd_wnd\": -1, \n                    \"socket\": 5, \n                    \"start\": 18.000035\n                }\n            ], \n            \"sum\": {\n                \"bits_per_second\": 0, \n                \"bytes\": 0, \n                \"end\": 19.00077, \n                \"omitted\": false, \n                \"retransmits\": 11, \n                \"seconds\": 1.00073504447937, \n                \"sender\": true, \n                \"start\": 18.000035\n            }\n        }, \n        {\n            \"streams\": [\n                {\n                    \"bits_per_second\": 10493441.247708984, \n                    \"bytes\": 1310720, \n                    \"end\": 20.000038, \n                    \"omitted\": false, \n                    \"pmtu\": 1500, \n                    \"retransmits\": 0, \n                    \"rtt\": 24651, \n                    \"rttvar\": 287, \n                    \"seconds\": 0.9992679953575134, \n                    \"sender\": true, \n                    \"snd_cwnd\": 69504, \n                    \"snd_wnd\": -1, \n                    \"socket\": 5, \n                    \"start\": 19.00077\n                }\n            ], \n            \"sum\": {\n                \"bits_per_second\": 10493441.247708984, \n                \"bytes\": 1310720, \n                \"end\": 20.000038, \n                \"omitted\": false, \n                \"retransmits\": 0, \n                \"seconds\": 0.9992679953575134, \n                \"sender\": true, \n                \"start\": 19.00077\n            }\n        }, \n        {\n            \"streams\": [\n                {\n                    \"bits_per_second\": 10485403.762103057, \n                    \"bytes\": 1310720, \n                    \"end\": 21.000072, \n                    \"omitted\": false, \n                    \"pmtu\": 1500, \n                    \"retransmits\": 1, \n                    \"rtt\": 33234, \n                    \"rttvar\": 313, \n                    \"seconds\": 1.000033974647522, \n                    \"sender\": true, \n                    \"snd_cwnd\": 1448, \n                    \"snd_wnd\": -1, \n                    \"socket\": 5, \n                    \"start\": 20.000038\n                }\n            ], \n            \"sum\": {\n                \"bits_per_second\": 10485403.762103057, \n                \"bytes\": 1310720, \n                \"end\": 21.000072, \n                \"omitted\": false, \n                \"retransmits\": 1, \n                \"seconds\": 1.000033974647522, \n                \"sender\": true, \n                \"start\": 20.000038\n            }\n        }, \n        {\n            \"streams\": [\n                {\n                    \"bits_per_second\": 0, \n                    \"bytes\": 0, \n                    \"end\": 22.000027, \n                    \"omitted\": false, \n                    \"pmtu\": 1500, \n                    \"retransmits\": 1, \n                    \"rtt\": 33234, \n                    \"rttvar\": 313, \n                    \"seconds\": 0.9999549984931946, \n                    \"sender\": true, \n                    \"snd_cwnd\": 1448, \n                    \"snd_wnd\": -1, \n                    \"socket\": 5, \n                    \"start\": 21.000072\n                }\n            ], \n            \"sum\": {\n                \"bits_per_second\": 0, \n                \"bytes\": 0, \n                \"end\": 22.000027, \n                \"omitted\": false, \n                \"retransmits\": 1, \n                \"seconds\": 0.9999549984931946, \n                \"sender\": true, \n                \"start\": 21.000072\n            }\n        }, \n        {\n            \"streams\": [\n                {\n                    \"bits_per_second\": 0, \n                    \"bytes\": 0, \n                    \"end\": 23.000035, \n                    \"omitted\": false, \n                    \"pmtu\": 1500, \n                    \"retransmits\": 1, \n                    \"rtt\": 33234, \n                    \"rttvar\": 313, \n                    \"seconds\": 1.0000079870224, \n                    \"sender\": true, \n                    \"snd_cwnd\": 1448, \n                    \"snd_wnd\": -1, \n                    \"socket\": 5, \n                    \"start\": 22.000027\n                }\n            ], \n            \"sum\": {\n                \"bits_per_second\": 0, \n                \"bytes\": 0, \n                \"end\": 23.000035, \n                \"omitted\": false, \n                \"retransmits\": 1, \n                \"seconds\": 1.0000079870224, \n                \"sender\": true, \n                \"start\": 22.000027\n            }\n        }, \n        {\n            \"streams\": [\n                {\n                    \"bits_per_second\": 0, \n                    \"bytes\": 0, \n                    \"end\": 24.000056, \n                    \"omitted\": false, \n                    \"pmtu\": 1500, \n                    \"retransmits\": 0, \n                    \"rtt\": 33234, \n                    \"rttvar\": 313, \n                    \"seconds\": 1.000020980834961, \n                    \"sender\": true, \n                    \"snd_cwnd\": 1448, \n                    \"snd_wnd\": -1, \n                    \"socket\": 5, \n                    \"start\": 23.000035\n                }\n            ], \n            \"sum\": {\n                \"bits_per_second\": 0, \n                \"bytes\": 0, \n                \"end\": 24.000056, \n                \"omitted\": false, \n                \"retransmits\": 0, \n                \"seconds\": 1.000020980834961, \n                \"sender\": true, \n                \"start\": 23.000035\n            }\n        }, \n        {\n            \"streams\": [\n                {\n                    \"bits_per_second\": 0, \n                    \"bytes\": 0, \n                    \"end\": 25.00013, \n                    \"omitted\": false, \n                    \"pmtu\": 1500, \n                    \"retransmits\": 8, \n                    \"rtt\": 32031, \n                    \"rttvar\": 2597, \n                    \"seconds\": 1.000074028968811, \n                    \"sender\": true, \n                    \"snd_cwnd\": 1448, \n                    \"snd_wnd\": -1, \n                    \"socket\": 5, \n                    \"start\": 24.000056\n                }\n            ], \n            \"sum\": {\n                \"bits_per_second\": 0, \n                \"bytes\": 0, \n                \"end\": 25.00013, \n                \"omitted\": false, \n                \"retransmits\": 8, \n                \"seconds\": 1.000074028968811, \n                \"sender\": true, \n                \"start\": 24.000056\n            }\n        }, \n        {\n            \"streams\": [\n                {\n                    \"bits_per_second\": 0, \n                    \"bytes\": 0, \n                    \"end\": 26.000029, \n                    \"omitted\": false, \n                    \"pmtu\": 1500, \n                    \"retransmits\": 18, \n                    \"rtt\": 37180, \n                    \"rttvar\": 3698, \n                    \"seconds\": 0.9998990297317505, \n                    \"sender\": true, \n                    \"snd_cwnd\": 1448, \n                    \"snd_wnd\": -1, \n                    \"socket\": 5, \n                    \"start\": 25.00013\n                }\n            ], \n            \"sum\": {\n                \"bits_per_second\": 0, \n                \"bytes\": 0, \n                \"end\": 26.000029, \n                \"omitted\": false, \n                \"retransmits\": 18, \n                \"seconds\": 0.9998990297317505, \n                \"sender\": true, \n                \"start\": 25.00013\n            }\n        }, \n        {\n            \"streams\": [\n                {\n                    \"bits_per_second\": 0, \n                    \"bytes\": 0, \n                    \"end\": 27.00006, \n                    \"omitted\": false, \n                    \"pmtu\": 1500, \n                    \"retransmits\": 1, \n                    \"rtt\": 361484, \n                    \"rttvar\": 423808, \n                    \"seconds\": 1.0000309944152832, \n                    \"sender\": true, \n                    \"snd_cwnd\": 4344, \n                    \"snd_wnd\": -1, \n                    \"socket\": 5, \n                    \"start\": 26.000029\n                }\n            ], \n            \"sum\": {\n                \"bits_per_second\": 0, \n                \"bytes\": 0, \n                \"end\": 27.00006, \n                \"omitted\": false, \n                \"retransmits\": 1, \n                \"seconds\": 1.0000309944152832, \n                \"sender\": true, \n                \"start\": 26.000029\n            }\n        }, \n        {\n            \"streams\": [\n                {\n                    \"bits_per_second\": 0, \n                    \"bytes\": 0, \n                    \"end\": 28.000026, \n                    \"omitted\": false, \n                    \"pmtu\": 1500, \n                    \"retransmits\": 0, \n                    \"rtt\": 361484, \n                    \"rttvar\": 423808, \n                    \"seconds\": 0.999966025352478, \n                    \"sender\": true, \n                    \"snd_cwnd\": 4344, \n                    \"snd_wnd\": -1, \n                    \"socket\": 5, \n                    \"start\": 27.00006\n                }\n            ], \n            \"sum\": {\n                \"bits_per_second\": 0, \n                \"bytes\": 0, \n                \"end\": 28.000026, \n                \"omitted\": false, \n                \"retransmits\": 0, \n                \"seconds\": 0.999966025352478, \n                \"sender\": true, \n                \"start\": 27.00006\n            }\n        }, \n        {\n            \"streams\": [\n                {\n                    \"bits_per_second\": 0, \n                    \"bytes\": 0, \n                    \"end\": 29.000087, \n                    \"omitted\": false, \n                    \"pmtu\": 1500, \n                    \"retransmits\": 1, \n                    \"rtt\": 361484, \n                    \"rttvar\": 423808, \n                    \"seconds\": 1.00006103515625, \n                    \"sender\": true, \n                    \"snd_cwnd\": 1448, \n                    \"snd_wnd\": -1, \n                    \"socket\": 5, \n                    \"start\": 28.000026\n                }\n            ], \n            \"sum\": {\n                \"bits_per_second\": 0, \n                \"bytes\": 0, \n                \"end\": 29.000087, \n                \"omitted\": false, \n                \"retransmits\": 1, \n                \"seconds\": 1.00006103515625, \n                \"sender\": true, \n                \"start\": 28.000026\n            }\n        }, \n        {\n            \"streams\": [\n                {\n                    \"bits_per_second\": 0, \n                    \"bytes\": 0, \n                    \"end\": 30.00134, \n                    \"omitted\": false, \n                    \"pmtu\": 1500, \n                    \"retransmits\": 0, \n                    \"rtt\": 361484, \n                    \"rttvar\": 423808, \n                    \"seconds\": 1.0012530088424683, \n                    \"sender\": true, \n                    \"snd_cwnd\": 1448, \n                    \"snd_wnd\": -1, \n                    \"socket\": 5, \n                    \"start\": 29.000087\n                }\n            ], \n            \"sum\": {\n                \"bits_per_second\": 0, \n                \"bytes\": 0, \n                \"end\": 30.00134, \n                \"omitted\": false, \n                \"retransmits\": 0, \n                \"seconds\": 1.0012530088424683, \n                \"sender\": true, \n                \"start\": 29.000087\n            }\n        }, \n        {\n            \"streams\": [\n                {\n                    \"bits_per_second\": 0, \n                    \"bytes\": 0, \n                    \"end\": 31.000023, \n                    \"omitted\": false, \n                    \"pmtu\": 1500, \n                    \"retransmits\": 0, \n                    \"rtt\": 361484, \n                    \"rttvar\": 423808, \n                    \"seconds\": 0.998682975769043, \n                    \"sender\": true, \n                    \"snd_cwnd\": 1448, \n                    \"snd_wnd\": -1, \n                    \"socket\": 5, \n                    \"start\": 30.00134\n                }\n            ], \n            \"sum\": {\n                \"bits_per_second\": 0, \n                \"bytes\": 0, \n                \"end\": 31.000023, \n                \"omitted\": false, \n                \"retransmits\": 0, \n                \"seconds\": 0.998682975769043, \n                \"sender\": true, \n                \"start\": 30.00134\n            }\n        }, \n        {\n            \"streams\": [\n                {\n                    \"bits_per_second\": 0, \n                    \"bytes\": 0, \n                    \"end\": 32.000803, \n                    \"omitted\": false, \n                    \"pmtu\": 1500, \n                    \"retransmits\": 0, \n                    \"rtt\": 361484, \n                    \"rttvar\": 423808, \n                    \"seconds\": 1.0007799863815308, \n                    \"sender\": true, \n                    \"snd_cwnd\": 1448, \n                    \"snd_wnd\": -1, \n                    \"socket\": 5, \n                    \"start\": 31.000023\n                }\n            ], \n            \"sum\": {\n                \"bits_per_second\": 0, \n                \"bytes\": 0, \n                \"end\": 32.000803, \n                \"omitted\": false, \n                \"retransmits\": 0, \n                \"seconds\": 1.0007799863815308, \n                \"sender\": true, \n                \"start\": 31.000023\n            }\n        }, \n        {\n            \"streams\": [\n                {\n                    \"bits_per_second\": 0, \n                    \"bytes\": 0, \n                    \"end\": 33.000126, \n                    \"omitted\": false, \n                    \"pmtu\": 1500, \n                    \"retransmits\": 47, \n                    \"rtt\": 24001, \n                    \"rttvar\": 4433, \n                    \"seconds\": 0.999323010444641, \n                    \"sender\": true, \n                    \"snd_cwnd\": 17376, \n                    \"snd_wnd\": -1, \n                    \"socket\": 5, \n                    \"start\": 32.000803\n                }\n            ], \n            \"sum\": {\n                \"bits_per_second\": 0, \n                \"bytes\": 0, \n                \"end\": 33.000126, \n                \"omitted\": false, \n                \"retransmits\": 47, \n                \"seconds\": 0.999323010444641, \n                \"sender\": true, \n                \"start\": 32.000803\n            }\n        }, \n        {\n            \"streams\": [\n                {\n                    \"bits_per_second\": 20971835.004731487, \n                    \"bytes\": 2621440, \n                    \"end\": 34.000111, \n                    \"omitted\": false, \n                    \"pmtu\": 1500, \n                    \"retransmits\": 0, \n                    \"rtt\": 27598, \n                    \"rttvar\": 577, \n                    \"seconds\": 0.9999849796295166, \n                    \"sender\": true, \n                    \"snd_cwnd\": 78192, \n                    \"snd_wnd\": -1, \n                    \"socket\": 5, \n                    \"start\": 33.000126\n                }\n            ], \n            \"sum\": {\n                \"bits_per_second\": 20971835.004731487, \n                \"bytes\": 2621440, \n                \"end\": 34.000111, \n                \"omitted\": false, \n                \"retransmits\": 0, \n                \"seconds\": 0.9999849796295166, \n                \"sender\": true, \n                \"start\": 33.000126\n            }\n        }, \n        {\n            \"streams\": [\n                {\n                    \"bits_per_second\": 0, \n                    \"bytes\": 0, \n                    \"end\": 35.000042, \n                    \"omitted\": false, \n                    \"pmtu\": 1500, \n                    \"retransmits\": 31, \n                    \"rtt\": 18512, \n                    \"rttvar\": 1018, \n                    \"seconds\": 0.99993097782135, \n                    \"sender\": true, \n                    \"snd_cwnd\": 1448, \n                    \"snd_wnd\": -1, \n                    \"socket\": 5, \n                    \"start\": 34.000111\n                }\n            ], \n            \"sum\": {\n                \"bits_per_second\": 0, \n                \"bytes\": 0, \n                \"end\": 35.000042, \n                \"omitted\": false, \n                \"retransmits\": 31, \n                \"seconds\": 0.99993097782135, \n                \"sender\": true, \n                \"start\": 34.000111\n            }\n        }, \n        {\n            \"streams\": [\n                {\n                    \"bits_per_second\": 0, \n                    \"bytes\": 0, \n                    \"end\": 36.00009, \n                    \"omitted\": false, \n                    \"pmtu\": 1500, \n                    \"retransmits\": 1, \n                    \"rtt\": 18512, \n                    \"rttvar\": 1018, \n                    \"seconds\": 1.000048041343689, \n                    \"sender\": true, \n                    \"snd_cwnd\": 1448, \n                    \"snd_wnd\": -1, \n                    \"socket\": 5, \n                    \"start\": 35.000042\n                }\n            ], \n            \"sum\": {\n                \"bits_per_second\": 0, \n                \"bytes\": 0, \n                \"end\": 36.00009, \n                \"omitted\": false, \n                \"retransmits\": 1, \n                \"seconds\": 1.000048041343689, \n                \"sender\": true, \n                \"start\": 35.000042\n            }\n        }, \n        {\n            \"streams\": [\n                {\n                    \"bits_per_second\": 10485508.756020075, \n                    \"bytes\": 1310720, \n                    \"end\": 37.000114, \n                    \"omitted\": false, \n                    \"pmtu\": 1500, \n                    \"retransmits\": 31, \n                    \"rtt\": 25974, \n                    \"rttvar\": 345, \n                    \"seconds\": 1.0000239610672, \n                    \"sender\": true, \n                    \"snd_cwnd\": 56472, \n                    \"snd_wnd\": -1, \n                    \"socket\": 5, \n                    \"start\": 36.00009\n                }\n            ], \n            \"sum\": {\n                \"bits_per_second\": 10485508.756020075, \n                \"bytes\": 1310720, \n                \"end\": 37.000114, \n                \"omitted\": false, \n                \"retransmits\": 31, \n                \"seconds\": 1.0000239610672, \n                \"sender\": true, \n                \"start\": 36.00009\n            }\n        }, \n        {\n            \"streams\": [\n                {\n                    \"bits_per_second\": 20967975.59914117, \n                    \"bytes\": 2621440, \n                    \"end\": 38.000283, \n                    \"omitted\": false, \n                    \"pmtu\": 1500, \n                    \"retransmits\": 0, \n                    \"rtt\": 39003, \n                    \"rttvar\": 669, \n                    \"seconds\": 1.000169038772583, \n                    \"sender\": true, \n                    \"snd_cwnd\": 97016, \n                    \"snd_wnd\": -1, \n                    \"socket\": 5, \n                    \"start\": 37.000114\n                }\n            ], \n            \"sum\": {\n                \"bits_per_second\": 20967975.59914117, \n                \"bytes\": 2621440, \n                \"end\": 38.000283, \n                \"omitted\": false, \n                \"retransmits\": 0, \n                \"seconds\": 1.000169038772583, \n                \"sender\": true, \n                \"start\": 37.000114\n            }\n        }, \n        {\n            \"streams\": [\n                {\n                    \"bits_per_second\": 20973407.66989598, \n                    \"bytes\": 2621440, \n                    \"end\": 39.000193, \n                    \"omitted\": false, \n                    \"pmtu\": 1500, \n                    \"retransmits\": 0, \n                    \"rtt\": 50913, \n                    \"rttvar\": 258, \n                    \"seconds\": 0.999909996986389, \n                    \"sender\": true, \n                    \"snd_cwnd\": 127424, \n                    \"snd_wnd\": -1, \n                    \"socket\": 5, \n                    \"start\": 38.000283\n                }\n            ], \n            \"sum\": {\n                \"bits_per_second\": 20973407.66989598, \n                \"bytes\": 2621440, \n                \"end\": 39.000193, \n                \"omitted\": false, \n                \"retransmits\": 0, \n                \"seconds\": 0.999909996986389, \n                \"sender\": true, \n                \"start\": 38.000283\n            }\n        }, \n        {\n            \"streams\": [\n                {\n                    \"bits_per_second\": 20971666.251019917, \n                    \"bytes\": 2621440, \n                    \"end\": 40.000186, \n                    \"omitted\": false, \n                    \"pmtu\": 1500, \n                    \"retransmits\": 0, \n                    \"rtt\": 64938, \n                    \"rttvar\": 591, \n                    \"seconds\": 0.9999930262565613, \n                    \"sender\": true, \n                    \"snd_cwnd\": 181000, \n                    \"snd_wnd\": -1, \n                    \"socket\": 5, \n                    \"start\": 39.000193\n                }\n            ], \n            \"sum\": {\n                \"bits_per_second\": 20971666.251019917, \n                \"bytes\": 2621440, \n                \"end\": 40.000186, \n                \"omitted\": false, \n                \"retransmits\": 0, \n                \"seconds\": 0.9999930262565613, \n                \"sender\": true, \n                \"start\": 39.000193\n            }\n        }, \n        {\n            \"streams\": [\n                {\n                    \"bits_per_second\": 20971100.00841124, \n                    \"bytes\": 2621440, \n                    \"end\": 41.000206, \n                    \"omitted\": false, \n                    \"pmtu\": 1500, \n                    \"retransmits\": 0, \n                    \"rtt\": 87154, \n                    \"rttvar\": 656, \n                    \"seconds\": 1.0000200271606445, \n                    \"sender\": true, \n                    \"snd_cwnd\": 243264, \n                    \"snd_wnd\": -1, \n                    \"socket\": 5, \n                    \"start\": 40.000186\n                }\n            ], \n            \"sum\": {\n                \"bits_per_second\": 20971100.00841124, \n                \"bytes\": 2621440, \n                \"end\": 41.000206, \n                \"omitted\": false, \n                \"retransmits\": 0, \n                \"seconds\": 1.0000200271606445, \n                \"sender\": true, \n                \"start\": 40.000186\n            }\n        }, \n        {\n            \"streams\": [\n                {\n                    \"bits_per_second\": 10483862.843308909, \n                    \"bytes\": 1310720, \n                    \"end\": 42.000387, \n                    \"omitted\": false, \n                    \"pmtu\": 1500, \n                    \"retransmits\": 60, \n                    \"rtt\": 48603, \n                    \"rttvar\": 1065, \n                    \"seconds\": 1.000180959701538, \n                    \"sender\": true, \n                    \"snd_cwnd\": 131768, \n                    \"snd_wnd\": -1, \n                    \"socket\": 5, \n                    \"start\": 41.000206\n                }\n            ], \n            \"sum\": {\n                \"bits_per_second\": 10483862.843308909, \n                \"bytes\": 1310720, \n                \"end\": 42.000387, \n                \"omitted\": false, \n                \"retransmits\": 60, \n                \"seconds\": 1.000180959701538, \n                \"sender\": true, \n                \"start\": 41.000206\n            }\n        }, \n        {\n            \"streams\": [\n                {\n                    \"bits_per_second\": 0, \n                    \"bytes\": 0, \n                    \"end\": 43.001048, \n                    \"omitted\": false, \n                    \"pmtu\": 1500, \n                    \"retransmits\": 1, \n                    \"rtt\": 48603, \n                    \"rttvar\": 1065, \n                    \"seconds\": 1.000661015510559, \n                    \"sender\": true, \n                    \"snd_cwnd\": 1448, \n                    \"snd_wnd\": -1, \n                    \"socket\": 5, \n                    \"start\": 42.000387\n                }\n            ], \n            \"sum\": {\n                \"bits_per_second\": 0, \n                \"bytes\": 0, \n                \"end\": 43.001048, \n                \"omitted\": false, \n                \"retransmits\": 1, \n                \"seconds\": 1.000661015510559, \n                \"sender\": true, \n                \"start\": 42.000387\n            }\n        }, \n        {\n            \"streams\": [\n                {\n                    \"bits_per_second\": 0, \n                    \"bytes\": 0, \n                    \"end\": 44.00105, \n                    \"omitted\": false, \n                    \"pmtu\": 1500, \n                    \"retransmits\": 51, \n                    \"rtt\": 33310, \n                    \"rttvar\": 9212, \n                    \"seconds\": 1.0000020265579224, \n                    \"sender\": true, \n                    \"snd_cwnd\": 65160, \n                    \"snd_wnd\": -1, \n                    \"socket\": 5, \n                    \"start\": 43.001048\n                }\n            ], \n            \"sum\": {\n                \"bits_per_second\": 0, \n                \"bytes\": 0, \n                \"end\": 44.00105, \n                \"omitted\": false, \n                \"retransmits\": 51, \n                \"seconds\": 1.0000020265579224, \n                \"sender\": true, \n                \"start\": 43.001048\n            }\n        }, \n        {\n            \"streams\": [\n                {\n                    \"bits_per_second\": 0, \n                    \"bytes\": 0, \n                    \"end\": 45.001064, \n                    \"omitted\": false, \n                    \"pmtu\": 1500, \n                    \"retransmits\": 0, \n                    \"rtt\": 33310, \n                    \"rttvar\": 9212, \n                    \"seconds\": 1.0000139474868774, \n                    \"sender\": true, \n                    \"snd_cwnd\": 65160, \n                    \"snd_wnd\": -1, \n                    \"socket\": 5, \n                    \"start\": 44.00105\n                }\n            ], \n            \"sum\": {\n                \"bits_per_second\": 0, \n                \"bytes\": 0, \n                \"end\": 45.001064, \n                \"omitted\": false, \n                \"retransmits\": 0, \n                \"seconds\": 1.0000139474868774, \n                \"sender\": true, \n                \"start\": 44.00105\n            }\n        }, \n        {\n            \"streams\": [\n                {\n                    \"bits_per_second\": 0, \n                    \"bytes\": 0, \n                    \"end\": 46.001052, \n                    \"omitted\": false, \n                    \"pmtu\": 1500, \n                    \"retransmits\": 0, \n                    \"rtt\": 33310, \n                    \"rttvar\": 9212, \n                    \"seconds\": 0.9999880194664, \n                    \"sender\": true, \n                    \"snd_cwnd\": 65160, \n                    \"snd_wnd\": -1, \n                    \"socket\": 5, \n                    \"start\": 45.001064\n                }\n            ], \n            \"sum\": {\n                \"bits_per_second\": 0, \n                \"bytes\": 0, \n                \"end\": 46.001052, \n                \"omitted\": false, \n                \"retransmits\": 0, \n                \"seconds\": 0.9999880194664, \n                \"sender\": true, \n                \"start\": 45.001064\n            }\n        }, \n        {\n            \"streams\": [\n                {\n                    \"bits_per_second\": 0, \n                    \"bytes\": 0, \n                    \"end\": 47.001074, \n                    \"omitted\": false, \n                    \"pmtu\": 1500, \n                    \"retransmits\": 0, \n                    \"rtt\": 33310, \n                    \"rttvar\": 9212, \n                    \"seconds\": 1.000022053718567, \n                    \"sender\": true, \n                    \"snd_cwnd\": 65160, \n                    \"snd_wnd\": -1, \n                    \"socket\": 5, \n                    \"start\": 46.001052\n                }\n            ], \n            \"sum\": {\n                \"bits_per_second\": 0, \n                \"bytes\": 0, \n                \"end\": 47.001074, \n                \"omitted\": false, \n                \"retransmits\": 0, \n                \"seconds\": 1.000022053718567, \n                \"sender\": true, \n                \"start\": 46.001052\n            }\n        }, \n        {\n            \"streams\": [\n                {\n                    \"bits_per_second\": 0, \n                    \"bytes\": 0, \n                    \"end\": 48.001049, \n                    \"omitted\": false, \n                    \"pmtu\": 1500, \n                    \"retransmits\": 0, \n                    \"rtt\": 33310, \n                    \"rttvar\": 9212, \n                    \"seconds\": 0.999975025653839, \n                    \"sender\": true, \n                    \"snd_cwnd\": 65160, \n                    \"snd_wnd\": -1, \n                    \"socket\": 5, \n                    \"start\": 47.001074\n                }\n            ], \n            \"sum\": {\n                \"bits_per_second\": 0, \n                \"bytes\": 0, \n                \"end\": 48.001049, \n                \"omitted\": false, \n                \"retransmits\": 0, \n                \"seconds\": 0.999975025653839, \n                \"sender\": true, \n                \"start\": 47.001074\n            }\n        }, \n        {\n            \"streams\": [\n                {\n                    \"bits_per_second\": 10495121.475281572, \n                    \"bytes\": 1310720, \n                    \"end\": 49.000157, \n                    \"omitted\": false, \n                    \"pmtu\": 1500, \n                    \"retransmits\": 45, \n                    \"rtt\": 22563, \n                    \"rttvar\": 684, \n                    \"seconds\": 0.9991080164909363, \n                    \"sender\": true, \n                    \"snd_cwnd\": 63712, \n                    \"snd_wnd\": -1, \n                    \"socket\": 5, \n                    \"start\": 48.001049\n                }\n            ], \n            \"sum\": {\n                \"bits_per_second\": 10495121.475281572, \n                \"bytes\": 1310720, \n                \"end\": 49.000157, \n                \"omitted\": false, \n                \"retransmits\": 45, \n                \"seconds\": 0.9991080164909363, \n                \"sender\": true, \n                \"start\": 48.001049\n            }\n        }, \n        {\n            \"streams\": [\n                {\n                    \"bits_per_second\": 0, \n                    \"bytes\": 0, \n                    \"end\": 50.001041, \n                    \"omitted\": false, \n                    \"pmtu\": 1500, \n                    \"retransmits\": 2, \n                    \"rtt\": 25141, \n                    \"rttvar\": 1116, \n                    \"seconds\": 1.0008840560913086, \n                    \"sender\": true, \n                    \"snd_cwnd\": 1448, \n                    \"snd_wnd\": -1, \n                    \"socket\": 5, \n                    \"start\": 49.000157\n                }\n            ], \n            \"sum\": {\n                \"bits_per_second\": 0, \n                \"bytes\": 0, \n                \"end\": 50.001041, \n                \"omitted\": false, \n                \"retransmits\": 2, \n                \"seconds\": 1.0008840560913086, \n                \"sender\": true, \n                \"start\": 49.000157\n            }\n        }, \n        {\n            \"streams\": [\n                {\n                    \"bits_per_second\": 0, \n                    \"bytes\": 0, \n                    \"end\": 51.001066, \n                    \"omitted\": false, \n                    \"pmtu\": 1500, \n                    \"retransmits\": 1, \n                    \"rtt\": 25141, \n                    \"rttvar\": 1116, \n                    \"seconds\": 1.0000250339508057, \n                    \"sender\": true, \n                    \"snd_cwnd\": 1448, \n                    \"snd_wnd\": -1, \n                    \"socket\": 5, \n                    \"start\": 50.001041\n                }\n            ], \n            \"sum\": {\n                \"bits_per_second\": 0, \n                \"bytes\": 0, \n                \"end\": 51.001066, \n                \"omitted\": false, \n                \"retransmits\": 1, \n                \"seconds\": 1.0000250339508057, \n                \"sender\": true, \n                \"start\": 50.001041\n            }\n        }, \n        {\n            \"streams\": [\n                {\n                    \"bits_per_second\": 0, \n                    \"bytes\": 0, \n                    \"end\": 52.001049, \n                    \"omitted\": false, \n                    \"pmtu\": 1500, \n                    \"retransmits\": 0, \n                    \"rtt\": 25141, \n                    \"rttvar\": 1116, \n                    \"seconds\": 0.999983012676239, \n                    \"sender\": true, \n                    \"snd_cwnd\": 1448, \n                    \"snd_wnd\": -1, \n                    \"socket\": 5, \n                    \"start\": 51.001066\n                }\n            ], \n            \"sum\": {\n                \"bits_per_second\": 0, \n                \"bytes\": 0, \n                \"end\": 52.001049, \n                \"omitted\": false, \n                \"retransmits\": 0, \n                \"seconds\": 0.999983012676239, \n                \"sender\": true, \n                \"start\": 51.001066\n            }\n        }, \n        {\n            \"streams\": [\n                {\n                    \"bits_per_second\": 0, \n                    \"bytes\": 0, \n                    \"end\": 53.001102, \n                    \"omitted\": false, \n                    \"pmtu\": 1500, \n                    \"retransmits\": 48, \n                    \"rtt\": 17818, \n                    \"rttvar\": 2160, \n                    \"seconds\": 1.00005304813385, \n                    \"sender\": true, \n                    \"snd_cwnd\": 41992, \n                    \"snd_wnd\": -1, \n                    \"socket\": 5, \n                    \"start\": 52.001049\n                }\n            ], \n            \"sum\": {\n                \"bits_per_second\": 0, \n                \"bytes\": 0, \n                \"end\": 53.001102, \n                \"omitted\": false, \n                \"retransmits\": 48, \n                \"seconds\": 1.00005304813385, \n                \"sender\": true, \n                \"start\": 52.001049\n            }\n        }, \n        {\n            \"streams\": [\n                {\n                    \"bits_per_second\": 0, \n                    \"bytes\": 0, \n                    \"end\": 54.00108, \n                    \"omitted\": false, \n                    \"pmtu\": 1500, \n                    \"retransmits\": 2, \n                    \"rtt\": 18751, \n                    \"rttvar\": 2160, \n                    \"seconds\": 0.999978005886078, \n                    \"sender\": true, \n                    \"snd_cwnd\": 1448, \n                    \"snd_wnd\": -1, \n                    \"socket\": 5, \n                    \"start\": 53.001102\n                }\n            ], \n            \"sum\": {\n                \"bits_per_second\": 0, \n                \"bytes\": 0, \n                \"end\": 54.00108, \n                \"omitted\": false, \n                \"retransmits\": 2, \n                \"seconds\": 0.999978005886078, \n                \"sender\": true, \n                \"start\": 53.001102\n            }\n        }, \n        {\n            \"streams\": [\n                {\n                    \"bits_per_second\": 0, \n                    \"bytes\": 0, \n                    \"end\": 55.00107, \n                    \"omitted\": false, \n                    \"pmtu\": 1500, \n                    \"retransmits\": 1, \n                    \"rtt\": 18751, \n                    \"rttvar\": 2160, \n                    \"seconds\": 0.9999899864196777, \n                    \"sender\": true, \n                    \"snd_cwnd\": 1448, \n                    \"snd_wnd\": -1, \n                    \"socket\": 5, \n                    \"start\": 54.00108\n                }\n            ], \n            \"sum\": {\n                \"bits_per_second\": 0, \n                \"bytes\": 0, \n                \"end\": 55.00107, \n                \"omitted\": false, \n                \"retransmits\": 1, \n                \"seconds\": 0.9999899864196777, \n                \"sender\": true, \n                \"start\": 54.00108\n            }\n        }, \n        {\n            \"streams\": [\n                {\n                    \"bits_per_second\": 0, \n                    \"bytes\": 0, \n                    \"end\": 56.001047, \n                    \"omitted\": false, \n                    \"pmtu\": 1500, \n                    \"retransmits\": 0, \n                    \"rtt\": 18751, \n                    \"rttvar\": 2160, \n                    \"seconds\": 0.9999769926071167, \n                    \"sender\": true, \n                    \"snd_cwnd\": 1448, \n                    \"snd_wnd\": -1, \n                    \"socket\": 5, \n                    \"start\": 55.00107\n                }\n            ], \n            \"sum\": {\n                \"bits_per_second\": 0, \n                \"bytes\": 0, \n                \"end\": 56.001047, \n                \"omitted\": false, \n                \"retransmits\": 0, \n                \"seconds\": 0.9999769926071167, \n                \"sender\": true, \n                \"start\": 55.00107\n            }\n        }, \n        {\n            \"streams\": [\n                {\n                    \"bits_per_second\": 0, \n                    \"bytes\": 0, \n                    \"end\": 57.001057, \n                    \"omitted\": false, \n                    \"pmtu\": 1500, \n                    \"retransmits\": 34, \n                    \"rtt\": 22252, \n                    \"rttvar\": 13165, \n                    \"seconds\": 1.0000100135803223, \n                    \"sender\": true, \n                    \"snd_cwnd\": 1448, \n                    \"snd_wnd\": -1, \n                    \"socket\": 5, \n                    \"start\": 56.001047\n                }\n            ], \n            \"sum\": {\n                \"bits_per_second\": 0, \n                \"bytes\": 0, \n                \"end\": 57.001057, \n                \"omitted\": false, \n                \"retransmits\": 34, \n                \"seconds\": 1.0000100135803223, \n                \"sender\": true, \n                \"start\": 56.001047\n            }\n        }, \n        {\n            \"streams\": [\n                {\n                    \"bits_per_second\": 0, \n                    \"bytes\": 0, \n                    \"end\": 58.001052, \n                    \"omitted\": false, \n                    \"pmtu\": 1500, \n                    \"retransmits\": 1, \n                    \"rtt\": 22252, \n                    \"rttvar\": 13165, \n                    \"seconds\": 0.999994993209839, \n                    \"sender\": true, \n                    \"snd_cwnd\": 1448, \n                    \"snd_wnd\": -1, \n                    \"socket\": 5, \n                    \"start\": 57.001057\n                }\n            ], \n            \"sum\": {\n                \"bits_per_second\": 0, \n                \"bytes\": 0, \n                \"end\": 58.001052, \n                \"omitted\": false, \n                \"retransmits\": 1, \n                \"seconds\": 0.999994993209839, \n                \"sender\": true, \n                \"start\": 57.001057\n            }\n        }, \n        {\n            \"streams\": [\n                {\n                    \"bits_per_second\": 0, \n                    \"bytes\": 0, \n                    \"end\": 59.00106, \n                    \"omitted\": false, \n                    \"pmtu\": 1500, \n                    \"retransmits\": 1, \n                    \"rtt\": 22252, \n                    \"rttvar\": 13165, \n                    \"seconds\": 1.0000079870224, \n                    \"sender\": true, \n                    \"snd_cwnd\": 1448, \n                    \"snd_wnd\": -1, \n                    \"socket\": 5, \n                    \"start\": 58.001052\n                }\n            ], \n            \"sum\": {\n                \"bits_per_second\": 0, \n                \"bytes\": 0, \n                \"end\": 59.00106, \n                \"omitted\": false, \n                \"retransmits\": 1, \n                \"seconds\": 1.0000079870224, \n                \"sender\": true, \n                \"start\": 58.001052\n            }\n        }, \n        {\n            \"streams\": [\n                {\n                    \"bits_per_second\": 0, \n                    \"bytes\": 0, \n                    \"end\": 60.001635, \n                    \"omitted\": false, \n                    \"pmtu\": 1500, \n                    \"retransmits\": 25, \n                    \"rtt\": 41646, \n                    \"rttvar\": 10368, \n                    \"seconds\": 1.0005749464035034, \n                    \"sender\": true, \n                    \"snd_cwnd\": 8688, \n                    \"snd_wnd\": -1, \n                    \"socket\": 5, \n                    \"start\": 59.00106\n                }\n            ], \n            \"sum\": {\n                \"bits_per_second\": 0, \n                \"bytes\": 0, \n                \"end\": 60.001635, \n                \"omitted\": false, \n                \"retransmits\": 25, \n                \"seconds\": 1.0005749464035034, \n                \"sender\": true, \n                \"start\": 59.00106\n            }\n        }\n    ], \n    \"start\": {\n        \"connected\": [\n            {\n                \"local_host\": \"172.16.0.2\", \n                \"local_port\": 55713, \n                \"remote_host\": \"172.16.0.1\", \n                \"remote_port\": 5201, \n                \"socket\": 5\n            }\n        ], \n        \"connecting_to\": {\n            \"host\": \"172.16.0.1\", \n            \"port\": 5201\n        }, \n        \"cookie\": \"pkvako3mx3bbkywvh26h7vs4gfuiogf7m3ms\", \n        \"fq_rate\": 0, \n        \"rcvbuf_actual\": 87380, \n        \"sndbuf_actual\": 65536, \n        \"sock_bufsize\": 0, \n        \"system_info\": \"REDACTED\", \n        \"target_bitrate\": 0, \n        \"tcp_mss_default\": 1448, \n        \"test_start\": {\n            \"bidir\": 0, \n            \"blksize\": 131072, \n            \"blocks\": 0, \n            \"bytes\": 0, \n            \"duration\": 60, \n            \"fqrate\": 0, \n            \"num_streams\": 1, \n            \"omit\": 0, \n            \"protocol\": \"TCP\", \n            \"reverse\": 0, \n            \"target_bitrate\": 0, \n            \"tos\": 0\n        }, \n        \"timestamp\": {\n            \"time\": \"Wed, 16 Oct 2024 03:04:16 GMT\", \n            \"timesecs\": 1729047856\n        }, \n        \"version\": \"iperf 3.14\"\n    }\n}\nParticipant 1:\n/usr/bin/iperf3 --use-pkcs1-padding -s -1 --idle-timeout 60 --json -p 5201 -B 172.16.0.1 --authorized-users-path /var/pscheduler-server/runner/tmp/tmprxml_wdh/tmp5mnx_hzd/credentials --rsa-private-key-path /var/pscheduler-server/runner/tmp/tmprxml_wdh/tmp5mnx_hzd/private-key\n\n{\n    \"end\": {\n        \"cpu_utilization_percent\": {\n            \"host_system\": 0.7172010449307492, \n            \"host_total\": 0.9695711289810193, \n            \"host_user\": 0.25236841783420366, \n            \"remote_system\": 0, \n            \"remote_total\": 0, \n            \"remote_user\": 0\n        }, \n        \"receiver_tcp_congestion\": \"htcp\", \n        \"streams\": [\n            {\n                \"receiver\": {\n                    \"bits_per_second\": 4494354.60213354, \n                    \"bytes\": 33716728, \n                    \"end\": 60.016142, \n                    \"seconds\": 60.016142, \n                    \"sender\": false, \n                    \"socket\": 5, \n                    \"start\": 0\n                }, \n                \"sender\": {\n                    \"bits_per_second\": 0, \n                    \"bytes\": 0, \n                    \"end\": 60.016142, \n                    \"seconds\": 60.016142, \n                    \"sender\": false, \n                    \"socket\": 5, \n                    \"start\": 0\n                }\n            }\n        ], \n        \"sum_received\": {\n            \"bits_per_second\": 4494354.60213354, \n            \"bytes\": 33716728, \n            \"end\": 60.016142, \n            \"seconds\": 60.016142, \n            \"sender\": false, \n            \"start\": 0\n        }, \n        \"sum_sent\": {\n            \"bits_per_second\": 0, \n            \"bytes\": 0, \n            \"end\": 60.016142, \n            \"seconds\": 60.016142, \n            \"sender\": false, \n            \"start\": 0\n        }\n    }, \n    \"intervals\": [\n        {\n            \"streams\": [\n                {\n                    \"bits_per_second\": 12568797.849506574, \n                    \"bytes\": 1572864, \n                    \"end\": 1.001123, \n                    \"omitted\": false, \n                    \"seconds\": 1.0011229515075684, \n                    \"sender\": false, \n                    \"socket\": 5, \n                    \"start\": 0\n                }\n            ], \n            \"sum\": {\n                \"bits_per_second\": 12568797.849506574, \n                \"bytes\": 1572864, \n                \"end\": 1.001123, \n                \"omitted\": false, \n                \"seconds\": 1.0011229515075684, \n                \"sender\": false, \n                \"start\": 0\n            }\n        }, \n        {\n            \"streams\": [\n                {\n                    \"bits_per_second\": 19923082.938468922, \n                    \"bytes\": 2490368, \n                    \"end\": 2.001116, \n                    \"omitted\": false, \n                    \"seconds\": 0.9999930262565613, \n                    \"sender\": false, \n                    \"socket\": 5, \n                    \"start\": 1.001123\n                }\n            ], \n            \"sum\": {\n                \"bits_per_second\": 19923082.938468922, \n                \"bytes\": 2490368, \n                \"end\": 2.001116, \n                \"omitted\": false, \n                \"seconds\": 0.9999930262565613, \n                \"sender\": false, \n                \"start\": 1.001123\n            }\n        }, \n        {\n            \"streams\": [\n                {\n                    \"bits_per_second\": 15728923.130096512, \n                    \"bytes\": 1966080, \n                    \"end\": 3.001098, \n                    \"omitted\": false, \n                    \"seconds\": 0.9999819993972778, \n                    \"sender\": false, \n                    \"socket\": 5, \n                    \"start\": 2.001116\n                }\n            ], \n            \"sum\": {\n                \"bits_per_second\": 15728923.130096512, \n                \"bytes\": 1966080, \n                \"end\": 3.001098, \n                \"omitted\": false, \n                \"seconds\": 0.9999819993972778, \n                \"sender\": false, \n                \"start\": 2.001116\n            }\n        }, \n        {\n            \"streams\": [\n                {\n                    \"bits_per_second\": 13630779.536822552, \n                    \"bytes\": 1703936, \n                    \"end\": 4.00115, \n                    \"omitted\": false, \n                    \"seconds\": 1.0000519752502441, \n                    \"sender\": false, \n                    \"socket\": 5, \n                    \"start\": 3.001098\n                }\n            ], \n            \"sum\": {\n                \"bits_per_second\": 13630779.536822552, \n                \"bytes\": 1703936, \n                \"end\": 4.00115, \n                \"omitted\": false, \n                \"seconds\": 1.0000519752502441, \n                \"sender\": false, \n                \"start\": 3.001098\n            }\n        }, \n        {\n            \"streams\": [\n                {\n                    \"bits_per_second\": 12583956.836752033, \n                    \"bytes\": 1572864, \n                    \"end\": 5.001067, \n                    \"omitted\": false, \n                    \"seconds\": 0.999916970729828, \n                    \"sender\": false, \n                    \"socket\": 5, \n                    \"start\": 4.00115\n                }\n            ], \n            \"sum\": {\n                \"bits_per_second\": 12583956.836752033, \n                \"bytes\": 1572864, \n                \"end\": 5.001067, \n                \"omitted\": false, \n                \"seconds\": 0.999916970729828, \n                \"sender\": false, \n                \"start\": 4.00115\n            }\n        }, \n        {\n            \"streams\": [\n                {\n                    \"bits_per_second\": 4198157.787665835, \n                    \"bytes\": 524288, \n                    \"end\": 6.000149, \n                    \"omitted\": false, \n                    \"seconds\": 0.9990820288658142, \n                    \"sender\": false, \n                    \"socket\": 5, \n                    \"start\": 5.001067\n                }\n            ], \n            \"sum\": {\n                \"bits_per_second\": 4198157.787665835, \n                \"bytes\": 524288, \n                \"end\": 6.000149, \n                \"omitted\": false, \n                \"seconds\": 0.9990820288658142, \n                \"sender\": false, \n                \"start\": 5.001067\n            }\n        }, \n        {\n            \"streams\": [\n                {\n                    \"bits_per_second\": 16777585.008116007, \n                    \"bytes\": 2097152, \n                    \"end\": 7.000127, \n                    \"omitted\": false, \n                    \"seconds\": 0.999978005886078, \n                    \"sender\": false, \n                    \"socket\": 5, \n                    \"start\": 6.000149\n                }\n            ], \n            \"sum\": {\n                \"bits_per_second\": 16777585.008116007, \n                \"bytes\": 2097152, \n                \"end\": 7.000127, \n                \"omitted\": false, \n                \"seconds\": 0.999978005886078, \n                \"sender\": false, \n                \"start\": 6.000149\n            }\n        }, \n        {\n            \"streams\": [\n                {\n                    \"bits_per_second\": 9427530.135632386, \n                    \"bytes\": 1179648, \n                    \"end\": 8.001151, \n                    \"omitted\": false, \n                    \"seconds\": 1.0010240077972412, \n                    \"sender\": false, \n                    \"socket\": 5, \n                    \"start\": 7.000127\n                }\n            ], \n            \"sum\": {\n                \"bits_per_second\": 9427530.135632386, \n                \"bytes\": 1179648, \n                \"end\": 8.001151, \n                \"omitted\": false, \n                \"seconds\": 1.0010240077972412, \n                \"sender\": false, \n                \"start\": 7.000127\n            }\n        }, \n        {\n            \"streams\": [\n                {\n                    \"bits_per_second\": 0, \n                    \"bytes\": 0, \n                    \"end\": 9.001162, \n                    \"omitted\": false, \n                    \"seconds\": 1.0000109672546387, \n                    \"sender\": false, \n                    \"socket\": 5, \n                    \"start\": 8.001151\n                }\n            ], \n            \"sum\": {\n                \"bits_per_second\": 0, \n                \"bytes\": 0, \n                \"end\": 9.001162, \n                \"omitted\": false, \n                \"seconds\": 1.0000109672546387, \n                \"sender\": false, \n                \"start\": 8.001151\n            }\n        }, \n        {\n            \"streams\": [\n                {\n                    \"bits_per_second\": 0, \n                    \"bytes\": 0, \n                    \"end\": 10.000766, \n                    \"omitted\": false, \n                    \"seconds\": 0.9996039867401123, \n                    \"sender\": false, \n                    \"socket\": 5, \n                    \"start\": 9.001162\n                }\n            ], \n            \"sum\": {\n                \"bits_per_second\": 0, \n                \"bytes\": 0, \n                \"end\": 10.000766, \n                \"omitted\": false, \n                \"seconds\": 0.9996039867401123, \n                \"sender\": false, \n                \"start\": 9.001162\n            }\n        }, \n        {\n            \"streams\": [\n                {\n                    \"bits_per_second\": 0, \n                    \"bytes\": 0, \n                    \"end\": 11.001136, \n                    \"omitted\": false, \n                    \"seconds\": 1.0003700256347656, \n                    \"sender\": false, \n                    \"socket\": 5, \n                    \"start\": 10.000766\n                }\n            ], \n            \"sum\": {\n                \"bits_per_second\": 0, \n                \"bytes\": 0, \n                \"end\": 11.001136, \n                \"omitted\": false, \n                \"seconds\": 1.0003700256347656, \n                \"sender\": false, \n                \"start\": 10.000766\n            }\n        }, \n        {\n            \"streams\": [\n                {\n                    \"bits_per_second\": 0, \n                    \"bytes\": 0, \n                    \"end\": 12.001154, \n                    \"omitted\": false, \n                    \"seconds\": 1.0000180006027222, \n                    \"sender\": false, \n                    \"socket\": 5, \n                    \"start\": 11.001136\n                }\n            ], \n            \"sum\": {\n                \"bits_per_second\": 0, \n                \"bytes\": 0, \n                \"end\": 12.001154, \n                \"omitted\": false, \n                \"seconds\": 1.0000180006027222, \n                \"sender\": false, \n                \"start\": 11.001136\n            }\n        }, \n        {\n            \"streams\": [\n                {\n                    \"bits_per_second\": 0, \n                    \"bytes\": 0, \n                    \"end\": 13.00115, \n                    \"omitted\": false, \n                    \"seconds\": 0.9999960064888, \n                    \"sender\": false, \n                    \"socket\": 5, \n                    \"start\": 12.001154\n                }\n            ], \n            \"sum\": {\n                \"bits_per_second\": 0, \n                \"bytes\": 0, \n                \"end\": 13.00115, \n                \"omitted\": false, \n                \"seconds\": 0.9999960064888, \n                \"sender\": false, \n                \"start\": 12.001154\n            }\n        }, \n        {\n            \"streams\": [\n                {\n                    \"bits_per_second\": 1048493.1315495708, \n                    \"bytes\": 131072, \n                    \"end\": 14.001229, \n                    \"omitted\": false, \n                    \"seconds\": 1.0000790357589722, \n                    \"sender\": false, \n                    \"socket\": 5, \n                    \"start\": 13.00115\n                }\n            ], \n            \"sum\": {\n                \"bits_per_second\": 1048493.1315495708, \n                \"bytes\": 131072, \n                \"end\": 14.001229, \n                \"omitted\": false, \n                \"seconds\": 1.0000790357589722, \n                \"sender\": false, \n                \"start\": 13.00115\n            }\n        }, \n        {\n            \"streams\": [\n                {\n                    \"bits_per_second\": 0, \n                    \"bytes\": 0, \n                    \"end\": 15.001137, \n                    \"omitted\": false, \n                    \"seconds\": 0.9999079704284668, \n                    \"sender\": false, \n                    \"socket\": 5, \n                    \"start\": 14.001229\n                }\n            ], \n            \"sum\": {\n                \"bits_per_second\": 0, \n                \"bytes\": 0, \n                \"end\": 15.001137, \n                \"omitted\": false, \n                \"seconds\": 0.9999079704284668, \n                \"sender\": false, \n                \"start\": 14.001229\n            }\n        }, \n        {\n            \"streams\": [\n                {\n                    \"bits_per_second\": 0, \n                    \"bytes\": 0, \n                    \"end\": 16.001139, \n                    \"omitted\": false, \n                    \"seconds\": 1.0000020265579224, \n                    \"sender\": false, \n                    \"socket\": 5, \n                    \"start\": 15.001137\n                }\n            ], \n            \"sum\": {\n                \"bits_per_second\": 0, \n                \"bytes\": 0, \n                \"end\": 16.001139, \n                \"omitted\": false, \n                \"seconds\": 1.0000020265579224, \n                \"sender\": false, \n                \"start\": 15.001137\n            }\n        }, \n        {\n            \"streams\": [\n                {\n                    \"bits_per_second\": 0, \n                    \"bytes\": 0, \n                    \"end\": 17.000086, \n                    \"omitted\": false, \n                    \"seconds\": 0.998947024345398, \n                    \"sender\": false, \n                    \"socket\": 5, \n                    \"start\": 16.001139\n                }\n            ], \n            \"sum\": {\n                \"bits_per_second\": 0, \n                \"bytes\": 0, \n                \"end\": 17.000086, \n                \"omitted\": false, \n                \"seconds\": 0.998947024345398, \n                \"sender\": false, \n                \"start\": 16.001139\n            }\n        }, \n        {\n            \"streams\": [\n                {\n                    \"bits_per_second\": 0, \n                    \"bytes\": 0, \n                    \"end\": 18.001129, \n                    \"omitted\": false, \n                    \"seconds\": 1.00104296207428, \n                    \"sender\": false, \n                    \"socket\": 5, \n                    \"start\": 17.000086\n                }\n            ], \n            \"sum\": {\n                \"bits_per_second\": 0, \n                \"bytes\": 0, \n                \"end\": 18.001129, \n                \"omitted\": false, \n                \"seconds\": 1.00104296207428, \n                \"sender\": false, \n                \"start\": 17.000086\n            }\n        }, \n        {\n            \"streams\": [\n                {\n                    \"bits_per_second\": 1048604.3132644838, \n                    \"bytes\": 131072, \n                    \"end\": 19.001102, \n                    \"omitted\": false, \n                    \"seconds\": 0.9999729990959167, \n                    \"sender\": false, \n                    \"socket\": 5, \n                    \"start\": 18.001129\n                }\n            ], \n            \"sum\": {\n                \"bits_per_second\": 1048604.3132644838, \n                \"bytes\": 131072, \n                \"end\": 19.001102, \n                \"omitted\": false, \n                \"seconds\": 0.9999729990959167, \n                \"sender\": false, \n                \"start\": 18.001129\n            }\n        }, \n        {\n            \"streams\": [\n                {\n                    \"bits_per_second\": 13631392.125674317, \n                    \"bytes\": 1703936, \n                    \"end\": 20.001109, \n                    \"omitted\": false, \n                    \"seconds\": 1.0000070333480835, \n                    \"sender\": false, \n                    \"socket\": 5, \n                    \"start\": 19.001102\n                }\n            ], \n            \"sum\": {\n                \"bits_per_second\": 13631392.125674317, \n                \"bytes\": 1703936, \n                \"end\": 20.001109, \n                \"omitted\": false, \n                \"seconds\": 1.0000070333480835, \n                \"sender\": false, \n                \"start\": 19.001102\n            }\n        }, \n        {\n            \"streams\": [\n                {\n                    \"bits_per_second\": 11534151.752943171, \n                    \"bytes\": 1441792, \n                    \"end\": 21.001125, \n                    \"omitted\": false, \n                    \"seconds\": 1.0000159740448, \n                    \"sender\": false, \n                    \"socket\": 5, \n                    \"start\": 20.001109\n                }\n            ], \n            \"sum\": {\n                \"bits_per_second\": 11534151.752943171, \n                \"bytes\": 1441792, \n                \"end\": 21.001125, \n                \"omitted\": false, \n                \"seconds\": 1.0000159740448, \n                \"sender\": false, \n                \"start\": 20.001109\n            }\n        }, \n        {\n            \"streams\": [\n                {\n                    \"bits_per_second\": 0, \n                    \"bytes\": 0, \n                    \"end\": 22.001209, \n                    \"omitted\": false, \n                    \"seconds\": 1.0000840425491333, \n                    \"sender\": false, \n                    \"socket\": 5, \n                    \"start\": 21.001125\n                }\n            ], \n            \"sum\": {\n                \"bits_per_second\": 0, \n                \"bytes\": 0, \n                \"end\": 22.001209, \n                \"omitted\": false, \n                \"seconds\": 1.0000840425491333, \n                \"sender\": false, \n                \"start\": 21.001125\n            }\n        }, \n        {\n            \"streams\": [\n                {\n                    \"bits_per_second\": 0, \n                    \"bytes\": 0, \n                    \"end\": 23.001131, \n                    \"omitted\": false, \n                    \"seconds\": 0.999921977519989, \n                    \"sender\": false, \n                    \"socket\": 5, \n                    \"start\": 22.001209\n                }\n            ], \n            \"sum\": {\n                \"bits_per_second\": 0, \n                \"bytes\": 0, \n                \"end\": 23.001131, \n                \"omitted\": false, \n                \"seconds\": 0.999921977519989, \n                \"sender\": false, \n                \"start\": 22.001209\n            }\n        }, \n        {\n            \"streams\": [\n                {\n                    \"bits_per_second\": 0, \n                    \"bytes\": 0, \n                    \"end\": 24.001137, \n                    \"omitted\": false, \n                    \"seconds\": 1.0000059604644775, \n                    \"sender\": false, \n                    \"socket\": 5, \n                    \"start\": 23.001131\n                }\n            ], \n            \"sum\": {\n                \"bits_per_second\": 0, \n                \"bytes\": 0, \n                \"end\": 24.001137, \n                \"omitted\": false, \n                \"seconds\": 1.0000059604644775, \n                \"sender\": false, \n                \"start\": 23.001131\n            }\n        }, \n        {\n            \"streams\": [\n                {\n                    \"bits_per_second\": 0, \n                    \"bytes\": 0, \n                    \"end\": 25.001137, \n                    \"omitted\": false, \n                    \"seconds\": 1, \n                    \"sender\": false, \n                    \"socket\": 5, \n                    \"start\": 24.001137\n                }\n            ], \n            \"sum\": {\n                \"bits_per_second\": 0, \n                \"bytes\": 0, \n                \"end\": 25.001137, \n                \"omitted\": false, \n                \"seconds\": 1, \n                \"sender\": false, \n                \"start\": 24.001137\n            }\n        }, \n        {\n            \"streams\": [\n                {\n                    \"bits_per_second\": 0, \n                    \"bytes\": 0, \n                    \"end\": 26.00113, \n                    \"omitted\": false, \n                    \"seconds\": 0.9999930262565613, \n                    \"sender\": false, \n                    \"socket\": 5, \n                    \"start\": 25.001137\n                }\n            ], \n            \"sum\": {\n                \"bits_per_second\": 0, \n                \"bytes\": 0, \n                \"end\": 26.00113, \n                \"omitted\": false, \n                \"seconds\": 0.9999930262565613, \n                \"sender\": false, \n                \"start\": 25.001137\n            }\n        }, \n        {\n            \"streams\": [\n                {\n                    \"bits_per_second\": 0, \n                    \"bytes\": 0, \n                    \"end\": 27.000099, \n                    \"omitted\": false, \n                    \"seconds\": 0.99896901845932, \n                    \"sender\": false, \n                    \"socket\": 5, \n                    \"start\": 26.00113\n                }\n            ], \n            \"sum\": {\n                \"bits_per_second\": 0, \n                \"bytes\": 0, \n                \"end\": 27.000099, \n                \"omitted\": false, \n                \"seconds\": 0.99896901845932, \n                \"sender\": false, \n                \"start\": 26.00113\n            }\n        }, \n        {\n            \"streams\": [\n                {\n                    \"bits_per_second\": 0, \n                    \"bytes\": 0, \n                    \"end\": 28.001168, \n                    \"omitted\": false, \n                    \"seconds\": 1.0010689496994019, \n                    \"sender\": false, \n                    \"socket\": 5, \n                    \"start\": 27.000099\n                }\n            ], \n            \"sum\": {\n                \"bits_per_second\": 0, \n                \"bytes\": 0, \n                \"end\": 28.001168, \n                \"omitted\": false, \n                \"seconds\": 1.0010689496994019, \n                \"sender\": false, \n                \"start\": 27.000099\n            }\n        }, \n        {\n            \"streams\": [\n                {\n                    \"bits_per_second\": 0, \n                    \"bytes\": 0, \n                    \"end\": 29.001153, \n                    \"omitted\": false, \n                    \"seconds\": 0.9999849796295166, \n                    \"sender\": false, \n                    \"socket\": 5, \n                    \"start\": 28.001168\n                }\n            ], \n            \"sum\": {\n                \"bits_per_second\": 0, \n                \"bytes\": 0, \n                \"end\": 29.001153, \n                \"omitted\": false, \n                \"seconds\": 0.9999849796295166, \n                \"sender\": false, \n                \"start\": 28.001168\n            }\n        }, \n        {\n            \"streams\": [\n                {\n                    \"bits_per_second\": 0, \n                    \"bytes\": 0, \n                    \"end\": 30.000826, \n                    \"omitted\": false, \n                    \"seconds\": 0.9996730089187622, \n                    \"sender\": false, \n                    \"socket\": 5, \n                    \"start\": 29.001153\n                }\n            ], \n            \"sum\": {\n                \"bits_per_second\": 0, \n                \"bytes\": 0, \n                \"end\": 30.000826, \n                \"omitted\": false, \n                \"seconds\": 0.9996730089187622, \n                \"sender\": false, \n                \"start\": 29.001153\n            }\n        }, \n        {\n            \"streams\": [\n                {\n                    \"bits_per_second\": 249716.596293162, \n                    \"bytes\": 31224, \n                    \"end\": 31.001128, \n                    \"omitted\": false, \n                    \"seconds\": 1.0003019571304321, \n                    \"sender\": false, \n                    \"socket\": 5, \n                    \"start\": 30.000826\n                }\n            ], \n            \"sum\": {\n                \"bits_per_second\": 249716.596293162, \n                \"bytes\": 31224, \n                \"end\": 31.001128, \n                \"omitted\": false, \n                \"seconds\": 1.0003019571304321, \n                \"sender\": false, \n                \"start\": 30.000826\n            }\n        }, \n        {\n            \"streams\": [\n                {\n                    \"bits_per_second\": 0, \n                    \"bytes\": 0, \n                    \"end\": 32.001096, \n                    \"omitted\": false, \n                    \"seconds\": 0.9999679923057556, \n                    \"sender\": false, \n                    \"socket\": 5, \n                    \"start\": 31.001128\n                }\n            ], \n            \"sum\": {\n                \"bits_per_second\": 0, \n                \"bytes\": 0, \n                \"end\": 32.001096, \n                \"omitted\": false, \n                \"seconds\": 0.9999679923057556, \n                \"sender\": false, \n                \"start\": 31.001128\n            }\n        }, \n        {\n            \"streams\": [\n                {\n                    \"bits_per_second\": 1048592.7502675694, \n                    \"bytes\": 131072, \n                    \"end\": 33.00108, \n                    \"omitted\": false, \n                    \"seconds\": 0.9999840259552002, \n                    \"sender\": false, \n                    \"socket\": 5, \n                    \"start\": 32.001096\n                }\n            ], \n            \"sum\": {\n                \"bits_per_second\": 1048592.7502675694, \n                \"bytes\": 131072, \n                \"end\": 33.00108, \n                \"omitted\": false, \n                \"seconds\": 0.9999840259552002, \n                \"sender\": false, \n                \"start\": 32.001096\n            }\n        }, \n        {\n            \"streams\": [\n                {\n                    \"bits_per_second\": 16777518.00543628, \n                    \"bytes\": 2097152, \n                    \"end\": 34.001062, \n                    \"omitted\": false, \n                    \"seconds\": 0.9999819993972778, \n                    \"sender\": false, \n                    \"socket\": 5, \n                    \"start\": 33.00108\n                }\n            ], \n            \"sum\": {\n                \"bits_per_second\": 16777518.00543628, \n                \"bytes\": 2097152, \n                \"end\": 34.001062, \n                \"omitted\": false, \n                \"seconds\": 0.9999819993972778, \n                \"sender\": false, \n                \"start\": 33.00108\n            }\n        }, \n        {\n            \"streams\": [\n                {\n                    \"bits_per_second\": 3145621.128630917, \n                    \"bytes\": 393216, \n                    \"end\": 35.001096, \n                    \"omitted\": false, \n                    \"seconds\": 1.000033974647522, \n                    \"sender\": false, \n                    \"socket\": 5, \n                    \"start\": 34.001062\n                }\n            ], \n            \"sum\": {\n                \"bits_per_second\": 3145621.128630917, \n                \"bytes\": 393216, \n                \"end\": 35.001096, \n                \"omitted\": false, \n                \"seconds\": 1.000033974647522, \n                \"sender\": false, \n                \"start\": 34.001062\n            }\n        }, \n        {\n            \"streams\": [\n                {\n                    \"bits_per_second\": 0, \n                    \"bytes\": 0, \n                    \"end\": 36.001184, \n                    \"omitted\": false, \n                    \"seconds\": 1.0000879764556885, \n                    \"sender\": false, \n                    \"socket\": 5, \n                    \"start\": 35.001096\n                }\n            ], \n            \"sum\": {\n                \"bits_per_second\": 0, \n                \"bytes\": 0, \n                \"end\": 36.001184, \n                \"omitted\": false, \n                \"seconds\": 1.0000879764556885, \n                \"sender\": false, \n                \"start\": 35.001096\n            }\n        }, \n        {\n            \"streams\": [\n                {\n                    \"bits_per_second\": 8397349.59996291, \n                    \"bytes\": 1048576, \n                    \"end\": 37.000143, \n                    \"omitted\": false, \n                    \"seconds\": 0.9989590048789978, \n                    \"sender\": false, \n                    \"socket\": 5, \n                    \"start\": 36.001184\n                }\n            ], \n            \"sum\": {\n                \"bits_per_second\": 8397349.59996291, \n                \"bytes\": 1048576, \n                \"end\": 37.000143, \n                \"omitted\": false, \n                \"seconds\": 0.9989590048789978, \n                \"sender\": false, \n                \"start\": 36.001184\n            }\n        }, \n        {\n            \"streams\": [\n                {\n                    \"bits_per_second\": 18873783.01813117, \n                    \"bytes\": 2359296, \n                    \"end\": 38.000174, \n                    \"omitted\": false, \n                    \"seconds\": 1.0000309944152832, \n                    \"sender\": false, \n                    \"socket\": 5, \n                    \"start\": 37.000143\n                }\n            ], \n            \"sum\": {\n                \"bits_per_second\": 18873783.01813117, \n                \"bytes\": 2359296, \n                \"end\": 38.000174, \n                \"omitted\": false, \n                \"seconds\": 1.0000309944152832, \n                \"sender\": false, \n                \"start\": 37.000143\n            }\n        }, \n        {\n            \"streams\": [\n                {\n                    \"bits_per_second\": 18856888.203272264, \n                    \"bytes\": 2359296, \n                    \"end\": 39.001101, \n                    \"omitted\": false, \n                    \"seconds\": 1.0009269714355469, \n                    \"sender\": false, \n                    \"socket\": 5, \n                    \"start\": 38.000174\n                }\n            ], \n            \"sum\": {\n                \"bits_per_second\": 18856888.203272264, \n                \"bytes\": 2359296, \n                \"end\": 39.001101, \n                \"omitted\": false, \n                \"seconds\": 1.0009269714355469, \n                \"sender\": false, \n                \"start\": 38.000174\n            }\n        }, \n        {\n            \"streams\": [\n                {\n                    \"bits_per_second\": 20971290.002522442, \n                    \"bytes\": 2621440, \n                    \"end\": 40.001112, \n                    \"omitted\": false, \n                    \"seconds\": 1.0000109672546387, \n                    \"sender\": false, \n                    \"socket\": 5, \n                    \"start\": 39.001101\n                }\n            ], \n            \"sum\": {\n                \"bits_per_second\": 20971290.002522442, \n                \"bytes\": 2621440, \n                \"end\": 40.001112, \n                \"omitted\": false, \n                \"seconds\": 1.0000109672546387, \n                \"sender\": false, \n                \"start\": 39.001101\n            }\n        }, \n        {\n            \"streams\": [\n                {\n                    \"bits_per_second\": 22027497.049188748, \n                    \"bytes\": 2752512, \n                    \"end\": 41.000776, \n                    \"omitted\": false, \n                    \"seconds\": 0.999664008617401, \n                    \"sender\": false, \n                    \"socket\": 5, \n                    \"start\": 40.001112\n                }\n            ], \n            \"sum\": {\n                \"bits_per_second\": 22027497.049188748, \n                \"bytes\": 2752512, \n                \"end\": 41.000776, \n                \"omitted\": false, \n                \"seconds\": 0.999664008617401, \n                \"sender\": false, \n                \"start\": 40.001112\n            }\n        }, \n        {\n            \"streams\": [\n                {\n                    \"bits_per_second\": 9433796.71623262, \n                    \"bytes\": 1179648, \n                    \"end\": 42.001135, \n                    \"omitted\": false, \n                    \"seconds\": 1.000359058380127, \n                    \"sender\": false, \n                    \"socket\": 5, \n                    \"start\": 41.000776\n                }\n            ], \n            \"sum\": {\n                \"bits_per_second\": 9433796.71623262, \n                \"bytes\": 1179648, \n                \"end\": 42.001135, \n                \"omitted\": false, \n                \"seconds\": 1.000359058380127, \n                \"sender\": false, \n                \"start\": 41.000776\n            }\n        }, \n        {\n            \"streams\": [\n                {\n                    \"bits_per_second\": 0, \n                    \"bytes\": 0, \n                    \"end\": 43.001134, \n                    \"omitted\": false, \n                    \"seconds\": 0.9999989867210388, \n                    \"sender\": false, \n                    \"socket\": 5, \n                    \"start\": 42.001135\n                }\n            ], \n            \"sum\": {\n                \"bits_per_second\": 0, \n                \"bytes\": 0, \n                \"end\": 43.001134, \n                \"omitted\": false, \n                \"seconds\": 0.9999989867210388, \n                \"sender\": false, \n                \"start\": 42.001135\n            }\n        }, \n        {\n            \"streams\": [\n                {\n                    \"bits_per_second\": 1048611.626210388, \n                    \"bytes\": 131072, \n                    \"end\": 44.0011, \n                    \"omitted\": false, \n                    \"seconds\": 0.999966025352478, \n                    \"sender\": false, \n                    \"socket\": 5, \n                    \"start\": 43.001134\n                }\n            ], \n            \"sum\": {\n                \"bits_per_second\": 1048611.626210388, \n                \"bytes\": 131072, \n                \"end\": 44.0011, \n                \"omitted\": false, \n                \"seconds\": 0.999966025352478, \n                \"sender\": false, \n                \"start\": 43.001134\n            }\n        }, \n        {\n            \"streams\": [\n                {\n                    \"bits_per_second\": 0, \n                    \"bytes\": 0, \n                    \"end\": 45.000728, \n                    \"omitted\": false, \n                    \"seconds\": 0.9996280074119568, \n                    \"sender\": false, \n                    \"socket\": 5, \n                    \"start\": 44.0011\n                }\n            ], \n            \"sum\": {\n                \"bits_per_second\": 0, \n                \"bytes\": 0, \n                \"end\": 45.000728, \n                \"omitted\": false, \n                \"seconds\": 0.9996280074119568, \n                \"sender\": false, \n                \"start\": 44.0011\n            }\n        }, \n        {\n            \"streams\": [\n                {\n                    \"bits_per_second\": 0, \n                    \"bytes\": 0, \n                    \"end\": 46.001131, \n                    \"omitted\": false, \n                    \"seconds\": 1.0004030466079712, \n                    \"sender\": false, \n                    \"socket\": 5, \n                    \"start\": 45.000728\n                }\n            ], \n            \"sum\": {\n                \"bits_per_second\": 0, \n                \"bytes\": 0, \n                \"end\": 46.001131, \n                \"omitted\": false, \n                \"seconds\": 1.0004030466079712, \n                \"sender\": false, \n                \"start\": 45.000728\n            }\n        }, \n        {\n            \"streams\": [\n                {\n                    \"bits_per_second\": 0, \n                    \"bytes\": 0, \n                    \"end\": 47.001128, \n                    \"omitted\": false, \n                    \"seconds\": 0.9999970197677612, \n                    \"sender\": false, \n                    \"socket\": 5, \n                    \"start\": 46.001131\n                }\n            ], \n            \"sum\": {\n                \"bits_per_second\": 0, \n                \"bytes\": 0, \n                \"end\": 47.001128, \n                \"omitted\": false, \n                \"seconds\": 0.9999970197677612, \n                \"sender\": false, \n                \"start\": 46.001131\n            }\n        }, \n        {\n            \"streams\": [\n                {\n                    \"bits_per_second\": 0, \n                    \"bytes\": 0, \n                    \"end\": 48.001145, \n                    \"omitted\": false, \n                    \"seconds\": 1.0000170469284058, \n                    \"sender\": false, \n                    \"socket\": 5, \n                    \"start\": 47.001128\n                }\n            ], \n            \"sum\": {\n                \"bits_per_second\": 0, \n                \"bytes\": 0, \n                \"end\": 48.001145, \n                \"omitted\": false, \n                \"seconds\": 1.0000170469284058, \n                \"sender\": false, \n                \"start\": 47.001128\n            }\n        }, \n        {\n            \"streams\": [\n                {\n                    \"bits_per_second\": 8389128.03223619, \n                    \"bytes\": 1048576, \n                    \"end\": 49.001083, \n                    \"omitted\": false, \n                    \"seconds\": 0.9999380111694336, \n                    \"sender\": false, \n                    \"socket\": 5, \n                    \"start\": 48.001145\n                }\n            ], \n            \"sum\": {\n                \"bits_per_second\": 8389128.03223619, \n                \"bytes\": 1048576, \n                \"end\": 49.001083, \n                \"omitted\": false, \n                \"seconds\": 0.9999380111694336, \n                \"sender\": false, \n                \"start\": 48.001145\n            }\n        }, \n        {\n            \"streams\": [\n                {\n                    \"bits_per_second\": 2097068.0033644282, \n                    \"bytes\": 262144, \n                    \"end\": 50.001123, \n                    \"omitted\": false, \n                    \"seconds\": 1.000040054321289, \n                    \"sender\": false, \n                    \"socket\": 5, \n                    \"start\": 49.001083\n                }\n            ], \n            \"sum\": {\n                \"bits_per_second\": 2097068.0033644282, \n                \"bytes\": 262144, \n                \"end\": 50.001123, \n                \"omitted\": false, \n                \"seconds\": 1.000040054321289, \n                \"sender\": false, \n                \"start\": 49.001083\n            }\n        }, \n        {\n            \"streams\": [\n                {\n                    \"bits_per_second\": 0, \n                    \"bytes\": 0, \n                    \"end\": 51.000142, \n                    \"omitted\": false, \n                    \"seconds\": 0.9990190267562866, \n                    \"sender\": false, \n                    \"socket\": 5, \n                    \"start\": 50.001123\n                }\n            ], \n            \"sum\": {\n                \"bits_per_second\": 0, \n                \"bytes\": 0, \n                \"end\": 51.000142, \n                \"omitted\": false, \n                \"seconds\": 0.9990190267562866, \n                \"sender\": false, \n                \"start\": 50.001123\n            }\n        }, \n        {\n            \"streams\": [\n                {\n                    \"bits_per_second\": 0, \n                    \"bytes\": 0, \n                    \"end\": 52.001142, \n                    \"omitted\": false, \n                    \"seconds\": 1.0010000467300415, \n                    \"sender\": false, \n                    \"socket\": 5, \n                    \"start\": 51.000142\n                }\n            ], \n            \"sum\": {\n                \"bits_per_second\": 0, \n                \"bytes\": 0, \n                \"end\": 52.001142, \n                \"omitted\": false, \n                \"seconds\": 1.0010000467300415, \n                \"sender\": false, \n                \"start\": 51.000142\n            }\n        }, \n        {\n            \"streams\": [\n                {\n                    \"bits_per_second\": 2097177.1253010146, \n                    \"bytes\": 262144, \n                    \"end\": 53.00113, \n                    \"omitted\": false, \n                    \"seconds\": 0.9999880194664, \n                    \"sender\": false, \n                    \"socket\": 5, \n                    \"start\": 52.001142\n                }\n            ], \n            \"sum\": {\n                \"bits_per_second\": 2097177.1253010146, \n                \"bytes\": 262144, \n                \"end\": 53.00113, \n                \"omitted\": false, \n                \"seconds\": 0.9999880194664, \n                \"sender\": false, \n                \"start\": 52.001142\n            }\n        }, \n        {\n            \"streams\": [\n                {\n                    \"bits_per_second\": 2099207.136992043, \n                    \"bytes\": 262144, \n                    \"end\": 54.000151, \n                    \"omitted\": false, \n                    \"seconds\": 0.9990209937095642, \n                    \"sender\": false, \n                    \"socket\": 5, \n                    \"start\": 53.00113\n                }\n            ], \n            \"sum\": {\n                \"bits_per_second\": 2099207.136992043, \n                \"bytes\": 262144, \n                \"end\": 54.000151, \n                \"omitted\": false, \n                \"seconds\": 0.9990209937095642, \n                \"sender\": false, \n                \"start\": 53.00113\n            }\n        }, \n        {\n            \"streams\": [\n                {\n                    \"bits_per_second\": 0, \n                    \"bytes\": 0, \n                    \"end\": 55.001112, \n                    \"omitted\": false, \n                    \"seconds\": 1.0009609460830688, \n                    \"sender\": false, \n                    \"socket\": 5, \n                    \"start\": 54.000151\n                }\n            ], \n            \"sum\": {\n                \"bits_per_second\": 0, \n                \"bytes\": 0, \n                \"end\": 55.001112, \n                \"omitted\": false, \n                \"seconds\": 1.0009609460830688, \n                \"sender\": false, \n                \"start\": 54.000151\n            }\n        }, \n        {\n            \"streams\": [\n                {\n                    \"bits_per_second\": 0, \n                    \"bytes\": 0, \n                    \"end\": 56.001131, \n                    \"omitted\": false, \n                    \"seconds\": 1.0000189542770386, \n                    \"sender\": false, \n                    \"socket\": 5, \n                    \"start\": 55.001112\n                }\n            ], \n            \"sum\": {\n                \"bits_per_second\": 0, \n                \"bytes\": 0, \n                \"end\": 56.001131, \n                \"omitted\": false, \n                \"seconds\": 1.0000189542770386, \n                \"sender\": false, \n                \"start\": 55.001112\n            }\n        }, \n        {\n            \"streams\": [\n                {\n                    \"bits_per_second\": 1048542.5010702268, \n                    \"bytes\": 131072, \n                    \"end\": 57.001163, \n                    \"omitted\": false, \n                    \"seconds\": 1.0000319480895996, \n                    \"sender\": false, \n                    \"socket\": 5, \n                    \"start\": 56.001131\n                }\n            ], \n            \"sum\": {\n                \"bits_per_second\": 1048542.5010702268, \n                \"bytes\": 131072, \n                \"end\": 57.001163, \n                \"omitted\": false, \n                \"seconds\": 1.0000319480895996, \n                \"sender\": false, \n                \"start\": 56.001131\n            }\n        }, \n        {\n            \"streams\": [\n                {\n                    \"bits_per_second\": 0, \n                    \"bytes\": 0, \n                    \"end\": 58.001105, \n                    \"omitted\": false, \n                    \"seconds\": 0.9999420046806335, \n                    \"sender\": false, \n                    \"socket\": 5, \n                    \"start\": 57.001163\n                }\n            ], \n            \"sum\": {\n                \"bits_per_second\": 0, \n                \"bytes\": 0, \n                \"end\": 58.001105, \n                \"omitted\": false, \n                \"seconds\": 0.9999420046806335, \n                \"sender\": false, \n                \"start\": 57.001163\n            }\n        }, \n        {\n            \"streams\": [\n                {\n                    \"bits_per_second\": 0, \n                    \"bytes\": 0, \n                    \"end\": 59.000771, \n                    \"omitted\": false, \n                    \"seconds\": 0.9996659755706787, \n                    \"sender\": false, \n                    \"socket\": 5, \n                    \"start\": 58.001105\n                }\n            ], \n            \"sum\": {\n                \"bits_per_second\": 0, \n                \"bytes\": 0, \n                \"end\": 59.000771, \n                \"omitted\": false, \n                \"seconds\": 0.9996659755706787, \n                \"sender\": false, \n                \"start\": 58.001105\n            }\n        }, \n        {\n            \"streams\": [\n                {\n                    \"bits_per_second\": 1048159.9151719186, \n                    \"bytes\": 131072, \n                    \"end\": 60.001168, \n                    \"omitted\": false, \n                    \"seconds\": 1.000396966934204, \n                    \"sender\": false, \n                    \"socket\": 5, \n                    \"start\": 59.000771\n                }\n            ], \n            \"sum\": {\n                \"bits_per_second\": 1048159.9151719186, \n                \"bytes\": 131072, \n                \"end\": 60.001168, \n                \"omitted\": false, \n                \"seconds\": 1.000396966934204, \n                \"sender\": false, \n                \"start\": 59.000771\n            }\n        }\n    ], \n    \"start\": {\n        \"accepted_connection\": {\n            \"host\": \"172.16.0.2\", \n            \"port\": 33167\n        }, \n        \"connected\": [\n            {\n                \"local_host\": \"172.16.0.1\", \n                \"local_port\": 5201, \n                \"remote_host\": \"172.16.0.2\", \n                \"remote_port\": 55713, \n                \"socket\": 5\n            }\n        ], \n        \"cookie\": \"pkvako3mx3bbkywvh26h7vs4gfuiogf7m3ms\", \n        \"fq_rate\": 0, \n        \"rcvbuf_actual\": 87380, \n        \"sndbuf_actual\": 65536, \n        \"sock_bufsize\": 0, \n        \"system_info\": \"REDACTED\", \n        \"target_bitrate\": 0, \n        \"tcp_mss_default\": 0, \n        \"test_start\": {\n            \"bidir\": 0, \n            \"blksize\": 131072, \n            \"blocks\": 0, \n            \"bytes\": 0, \n            \"duration\": 60, \n            \"fqrate\": 0, \n            \"interval\": 1, \n            \"num_streams\": 1, \n            \"omit\": 0, \n            \"protocol\": \"TCP\", \n            \"reverse\": 0, \n            \"target_bitrate\": 0, \n            \"tos\": 0\n        }, \n        \"timestamp\": {\n            \"time\": \"Wed, 16 Oct 2024 03:04:16 GMT\", \n            \"timesecs\": 1729047856\n        }, \n        \"version\": \"iperf 3.17.1\"\n    }\n}\n","summary":{"streams":[{"end":60.001635,"rtt":104483,"start":0,"stream-id":5,"retransmits":1048,"throughput-bits":4928172.907288277,"throughput-bytes":36962304}],"summary":{"end":60.001635,"start":0,"retransmits":1048,"throughput-bits":4928172.907288277,"throughput-bytes":36962304,"receiver-throughput-bits":4494354.60213354}},"intervals":[{"streams":[{"end":1.000063,"rtt":145332,"start":0,"omitted":false,"stream-id":5,"retransmits":342,"tcp-window-size":402544,"throughput-bits":44037420.17446564,"throughput-bytes":5505024}],"summary":{"end":1.000063,"start":0,"omitted":false,"retransmits":342,"throughput-bits":44037420.17446564,"throughput-bytes":5505024}},{"streams":[{"end":2.000082,"rtt":83919,"start":1.000063,"omitted":false,"stream-id":5,"retransmits":6,"tcp-window-size":214304,"throughput-bits":20971122.507534184,"throughput-bytes":2621440}],"summary":{"end":2.000082,"start":1.000063,"omitted":false,"retransmits":6,"throughput-bits":20971122.507534184,"throughput-bytes":2621440}},{"streams":[{"end":3.000103,"rtt":51588,"start":2.000082,"omitted":false,"stream-id":5,"retransmits":57,"tcp-window-size":127424,"throughput-bits":10485540.004615687,"throughput-bytes":1310720}],"summary":{"end":3.000103,"start":2.000082,"omitted":false,"retransmits":57,"throughput-bits":10485540.004615687,"throughput-bytes":1310720}},{"streams":[{"end":4.000059,"rtt":38289,"start":3.000103,"omitted":false,"stream-id":5,"retransmits":51,"tcp-window-size":81088,"throughput-bits":20972442.540580925,"throughput-bytes":2621440}],"summary":{"end":4.000059,"start":3.000103,"omitted":false,"retransmits":51,"throughput-bits":20972442.540580925,"throughput-bytes":2621440}},{"streams":[{"end":5.000122,"rtt":133657,"start":4.000059,"omitted":false,"stream-id":5,"retransmits":27,"tcp-window-size":39096,"throughput-bits":10485100.041539438,"throughput-bytes":1310720}],"summary":{"end":5.000122,"start":4.000059,"omitted":false,"retransmits":27,"throughput-bits":10485100.041539438,"throughput-bytes":1310720}},{"streams":[{"end":6.000078,"rtt":28945,"start":5.000122,"omitted":false,"stream-id":5,"retransmits":55,"tcp-window-size":62264,"throughput-bits":0,"throughput-bytes":0}],"summary":{"end":6.000078,"start":5.000122,"omitted":false,"retransmits":55,"throughput-bits":0,"throughput-bytes":0}},{"streams":[{"end":7.000062,"rtt":45768,"start":6.000078,"omitted":false,"stream-id":5,"retransmits":0,"tcp-window-size":98464,"throughput-bits":20971855.00535139,"throughput-bytes":2621440}],"summary":{"end":7.000062,"start":6.000078,"omitted":false,"retransmits":0,"throughput-bits":20971855.00535139,"throughput-bytes":2621440}},{"streams":[{"end":8.000049,"rtt":126558,"start":7.000062,"omitted":false,"stream-id":5,"retransmits":22,"tcp-window-size":11584,"throughput-bits":10485896.25177043,"throughput-bytes":1310720}],"summary":{"end":8.000049,"start":7.000062,"omitted":false,"retransmits":22,"throughput-bits":10485896.25177043,"throughput-bytes":1310720}},{"streams":[{"end":9.000025,"rtt":103126,"start":8.000049,"omitted":false,"stream-id":5,"retransmits":7,"tcp-window-size":5792,"throughput-bits":0,"throughput-bytes":0}],"summary":{"end":9.000025,"start":8.000049,"omitted":false,"retransmits":7,"throughput-bits":0,"throughput-bytes":0}},{"streams":[{"end":10.000081,"rtt":518131,"start":9.000025,"omitted":false,"stream-id":5,"retransmits":5,"tcp-window-size":2896,"throughput-bits":0,"throughput-bytes":0}],"summary":{"end":10.000081,"start":9.000025,"omitted":false,"retransmits":5,"throughput-bits":0,"throughput-bytes":0}},{"streams":[{"end":11.000097,"rtt":518131,"start":10.000081,"omitted":false,"stream-id":5,"retransmits":0,"tcp-window-size":2896,"throughput-bits":0,"throughput-bytes":0}],"summary":{"end":11.000097,"start":10.000081,"omitted":false,"retransmits":0,"throughput-bits":0,"throughput-bytes":0}},{"streams":[{"end":12.000058,"rtt":518131,"start":11.000097,"omitted":false,"stream-id":5,"retransmits":0,"tcp-window-size":2896,"throughput-bits":0,"throughput-bytes":0}],"summary":{"end":12.000058,"start":11.000097,"omitted":false,"retransmits":0,"throughput-bits":0,"throughput-bytes":0}},{"streams":[{"end":13.000119,"rtt":518131,"start":12.000058,"omitted":false,"stream-id":5,"retransmits":0,"tcp-window-size":2896,"throughput-bits":0,"throughput-bytes":0}],"summary":{"end":13.000119,"start":12.000058,"omitted":false,"retransmits":0,"throughput-bits":0,"throughput-bytes":0}},{"streams":[{"end":14.000061,"rtt":21358,"start":13.000119,"omitted":false,"stream-id":5,"retransmits":51,"tcp-window-size":14480,"throughput-bits":0,"throughput-bytes":0}],"summary":{"end":14.000061,"start":13.000119,"omitted":false,"retransmits":51,"throughput-bits":0,"throughput-bytes":0}},{"streams":[{"end":15.000033,"rtt":21358,"start":14.000061,"omitted":false,"stream-id":5,"retransmits":0,"tcp-window-size":14480,"throughput-bits":0,"throughput-bytes":0}],"summary":{"end":15.000033,"start":14.000061,"omitted":false,"retransmits":0,"throughput-bits":0,"throughput-bytes":0}},{"streams":[{"end":16.000059,"rtt":21358,"start":15.000033,"omitted":false,"stream-id":5,"retransmits":1,"tcp-window-size":1448,"throughput-bits":0,"throughput-bytes":0}],"summary":{"end":16.000059,"start":15.000033,"omitted":false,"retransmits":1,"throughput-bits":0,"throughput-bytes":0}},{"streams":[{"end":17.000071,"rtt":21358,"start":16.000059,"omitted":false,"stream-id":5,"retransmits":0,"tcp-window-size":1448,"throughput-bits":0,"throughput-bytes":0}],"summary":{"end":17.000071,"start":16.000059,"omitted":false,"retransmits":0,"throughput-bits":0,"throughput-bytes":0}},{"streams":[{"end":18.000035,"rtt":21358,"start":17.000071,"omitted":false,"stream-id":5,"retransmits":0,"tcp-window-size":1448,"throughput-bits":0,"throughput-bytes":0}],"summary":{"end":18.000035,"start":17.000071,"omitted":false,"retransmits":0,"throughput-bits":0,"throughput-bytes":0}},{"streams":[{"end":19.00077,"rtt":36009,"start":18.000035,"omitted":false,"stream-id":5,"retransmits":11,"tcp-window-size":13032,"throughput-bits":0,"throughput-bytes":0}],"summary":{"end":19.00077,"start":18.000035,"omitted":false,"retransmits":11,"throughput-bits":0,"throughput-bytes":0}},{"streams":[{"end":20.000038,"rtt":24651,"start":19.00077,"omitted":false,"stream-id":5,"retransmits":0,"tcp-window-size":69504,"throughput-bits":10493441.247708984,"throughput-bytes":1310720}],"summary":{"end":20.000038,"start":19.00077,"omitted":false,"retransmits":0,"throughput-bits":10493441.247708984,"throughput-bytes":1310720}},{"streams":[{"end":21.000072,"rtt":33234,"start":20.000038,"omitted":false,"stream-id":5,"retransmits":1,"tcp-window-size":1448,"throughput-bits":10485403.762103057,"throughput-bytes":1310720}],"summary":{"end":21.000072,"start":20.000038,"omitted":false,"retransmits":1,"throughput-bits":10485403.762103057,"throughput-bytes":1310720}},{"streams":[{"end":22.000027,"rtt":33234,"start":21.000072,"omitted":false,"stream-id":5,"retransmits":1,"tcp-window-size":1448,"throughput-bits":0,"throughput-bytes":0}],"summary":{"end":22.000027,"start":21.000072,"omitted":false,"retransmits":1,"throughput-bits":0,"throughput-bytes":0}},{"streams":[{"end":23.000035,"rtt":33234,"start":22.000027,"omitted":false,"stream-id":5,"retransmits":1,"tcp-window-size":1448,"throughput-bits":0,"throughput-bytes":0}],"summary":{"end":23.000035,"start":22.000027,"omitted":false,"retransmits":1,"throughput-bits":0,"throughput-bytes":0}},{"streams":[{"end":24.000056,"rtt":33234,"start":23.000035,"omitted":false,"stream-id":5,"retransmits":0,"tcp-window-size":1448,"throughput-bits":0,"throughput-bytes":0}],"summary":{"end":24.000056,"start":23.000035,"omitted":false,"retransmits":0,"throughput-bits":0,"throughput-bytes":0}},{"streams":[{"end":25.00013,"rtt":32031,"start":24.000056,"omitted":false,"stream-id":5,"retransmits":8,"tcp-window-size":1448,"throughput-bits":0,"throughput-bytes":0}],"summary":{"end":25.00013,"start":24.000056,"omitted":false,"retransmits":8,"throughput-bits":0,"throughput-bytes":0}},{"streams":[{"end":26.000029,"rtt":37180,"start":25.00013,"omitted":false,"stream-id":5,"retransmits":18,"tcp-window-size":1448,"throughput-bits":0,"throughput-bytes":0}],"summary":{"end":26.000029,"start":25.00013,"omitted":false,"retransmits":18,"throughput-bits":0,"throughput-bytes":0}},{"streams":[{"end":27.00006,"rtt":361484,"start":26.000029,"omitted":false,"stream-id":5,"retransmits":1,"tcp-window-size":4344,"throughput-bits":0,"throughput-bytes":0}],"summary":{"end":27.00006,"start":26.000029,"omitted":false,"retransmits":1,"throughput-bits":0,"throughput-bytes":0}},{"streams":[{"end":28.000026,"rtt":361484,"start":27.00006,"omitted":false,"stream-id":5,"retransmits":0,"tcp-window-size":4344,"throughput-bits":0,"throughput-bytes":0}],"summary":{"end":28.000026,"start":27.00006,"omitted":false,"retransmits":0,"throughput-bits":0,"throughput-bytes":0}},{"streams":[{"end":29.000087,"rtt":361484,"start":28.000026,"omitted":false,"stream-id":5,"retransmits":1,"tcp-window-size":1448,"throughput-bits":0,"throughput-bytes":0}],"summary":{"end":29.000087,"start":28.000026,"omitted":false,"retransmits":1,"throughput-bits":0,"throughput-bytes":0}},{"streams":[{"end":30.00134,"rtt":361484,"start":29.000087,"omitted":false,"stream-id":5,"retransmits":0,"tcp-window-size":1448,"throughput-bits":0,"throughput-bytes":0}],"summary":{"end":30.00134,"start":29.000087,"omitted":false,"retransmits":0,"throughput-bits":0,"throughput-bytes":0}},{"streams":[{"end":31.000023,"rtt":361484,"start":30.00134,"omitted":false,"stream-id":5,"retransmits":0,"tcp-window-size":1448,"throughput-bits":0,"throughput-bytes":0}],"summary":{"end":31.000023,"start":30.00134,"omitted":false,"retransmits":0,"throughput-bits":0,"throughput-bytes":0}},{"streams":[{"end":32.000803,"rtt":361484,"start":31.000023,"omitted":false,"stream-id":5,"retransmits":0,"tcp-window-size":1448,"throughput-bits":0,"throughput-bytes":0}],"summary":{"end":32.000803,"start":31.000023,"omitted":false,"retransmits":0,"throughput-bits":0,"throughput-bytes":0}},{"streams":[{"end":33.000126,"rtt":24001,"start":32.000803,"omitted":false,"stream-id":5,"retransmits":47,"tcp-window-size":17376,"throughput-bits":0,"throughput-bytes":0}],"summary":{"end":33.000126,"start":32.000803,"omitted":false,"retransmits":47,"throughput-bits":0,"throughput-bytes":0}},{"streams":[{"end":34.000111,"rtt":27598,"start":33.000126,"omitted":false,"stream-id":5,"retransmits":0,"tcp-window-size":78192,"throughput-bits":20971835.004731487,"throughput-bytes":2621440}],"summary":{"end":34.000111,"start":33.000126,"omitted":false,"retransmits":0,"throughput-bits":20971835.004731487,"throughput-bytes":2621440}},{"streams":[{"end":35.000042,"rtt":18512,"start":34.000111,"omitted":false,"stream-id":5,"retransmits":31,"tcp-window-size":1448,"throughput-bits":0,"throughput-bytes":0}],"summary":{"end":35.000042,"start":34.000111,"omitted":false,"retransmits":31,"throughput-bits":0,"throughput-bytes":0}},{"streams":[{"end":36.00009,"rtt":18512,"start":35.000042,"omitted":false,"stream-id":5,"retransmits":1,"tcp-window-size":1448,"throughput-bits":0,"throughput-bytes":0}],"summary":{"end":36.00009,"start":35.000042,"omitted":false,"retransmits":1,"throughput-bits":0,"throughput-bytes":0}},{"streams":[{"end":37.000114,"rtt":25974,"start":36.00009,"omitted":false,"stream-id":5,"retransmits":31,"tcp-window-size":56472,"throughput-bits":10485508.756020075,"throughput-bytes":1310720}],"summary":{"end":37.000114,"start":36.00009,"omitted":false,"retransmits":31,"throughput-bits":10485508.756020075,"throughput-bytes":1310720}},{"streams":[{"end":38.000283,"rtt":39003,"start":37.000114,"omitted":false,"stream-id":5,"retransmits":0,"tcp-window-size":97016,"throughput-bits":20967975.59914117,"throughput-bytes":2621440}],"summary":{"end":38.000283,"start":37.000114,"omitted":false,"retransmits":0,"throughput-bits":20967975.59914117,"throughput-bytes":2621440}},{"streams":[{"end":39.000193,"rtt":50913,"start":38.000283,"omitted":false,"stream-id":5,"retransmits":0,"tcp-window-size":127424,"throughput-bits":20973407.66989598,"throughput-bytes":2621440}],"summary":{"end":39.000193,"start":38.000283,"omitted":false,"retransmits":0,"throughput-bits":20973407.66989598,"throughput-bytes":2621440}},{"streams":[{"end":40.000186,"rtt":64938,"start":39.000193,"omitted":false,"stream-id":5,"retransmits":0,"tcp-window-size":181000,"throughput-bits":20971666.251019917,"throughput-bytes":2621440}],"summary":{"end":40.000186,"start":39.000193,"omitted":false,"retransmits":0,"throughput-bits":20971666.251019917,"throughput-bytes":2621440}},{"streams":[{"end":41.000206,"rtt":87154,"start":40.000186,"omitted":false,"stream-id":5,"retransmits":0,"tcp-window-size":243264,"throughput-bits":20971100.00841124,"throughput-bytes":2621440}],"summary":{"end":41.000206,"start":40.000186,"omitted":false,"retransmits":0,"throughput-bits":20971100.00841124,"throughput-bytes":2621440}},{"streams":[{"end":42.000387,"rtt":48603,"start":41.000206,"omitted":false,"stream-id":5,"retransmits":60,"tcp-window-size":131768,"throughput-bits":10483862.843308909,"throughput-bytes":1310720}],"summary":{"end":42.000387,"start":41.000206,"omitted":false,"retransmits":60,"throughput-bits":10483862.843308909,"throughput-bytes":1310720}},{"streams":[{"end":43.001048,"rtt":48603,"start":42.000387,"omitted":false,"stream-id":5,"retransmits":1,"tcp-window-size":1448,"throughput-bits":0,"throughput-bytes":0}],"summary":{"end":43.001048,"start":42.000387,"omitted":false,"retransmits":1,"throughput-bits":0,"throughput-bytes":0}},{"streams":[{"end":44.00105,"rtt":33310,"start":43.001048,"omitted":false,"stream-id":5,"retransmits":51,"tcp-window-size":65160,"throughput-bits":0,"throughput-bytes":0}],"summary":{"end":44.00105,"start":43.001048,"omitted":false,"retransmits":51,"throughput-bits":0,"throughput-bytes":0}},{"streams":[{"end":45.001064,"rtt":33310,"start":44.00105,"omitted":false,"stream-id":5,"retransmits":0,"tcp-window-size":65160,"throughput-bits":0,"throughput-bytes":0}],"summary":{"end":45.001064,"start":44.00105,"omitted":false,"retransmits":0,"throughput-bits":0,"throughput-bytes":0}},{"streams":[{"end":46.001052,"rtt":33310,"start":45.001064,"omitted":false,"stream-id":5,"retransmits":0,"tcp-window-size":65160,"throughput-bits":0,"throughput-bytes":0}],"summary":{"end":46.001052,"start":45.001064,"omitted":false,"retransmits":0,"throughput-bits":0,"throughput-bytes":0}},{"streams":[{"end":47.001074,"rtt":33310,"start":46.001052,"omitted":false,"stream-id":5,"retransmits":0,"tcp-window-size":65160,"throughput-bits":0,"throughput-bytes":0}],"summary":{"end":47.001074,"start":46.001052,"omitted":false,"retransmits":0,"throughput-bits":0,"throughput-bytes":0}},{"streams":[{"end":48.001049,"rtt":33310,"start":47.001074,"omitted":false,"stream-id":5,"retransmits":0,"tcp-window-size":65160,"throughput-bits":0,"throughput-bytes":0}],"summary":{"end":48.001049,"start":47.001074,"omitted":false,"retransmits":0,"throughput-bits":0,"throughput-bytes":0}},{"streams":[{"end":49.000157,"rtt":22563,"start":48.001049,"omitted":false,"stream-id":5,"retransmits":45,"tcp-window-size":63712,"throughput-bits":10495121.475281572,"throughput-bytes":1310720}],"summary":{"end":49.000157,"start":48.001049,"omitted":false,"retransmits":45,"throughput-bits":10495121.475281572,"throughput-bytes":1310720}},{"streams":[{"end":50.001041,"rtt":25141,"start":49.000157,"omitted":false,"stream-id":5,"retransmits":2,"tcp-window-size":1448,"throughput-bits":0,"throughput-bytes":0}],"summary":{"end":50.001041,"start":49.000157,"omitted":false,"retransmits":2,"throughput-bits":0,"throughput-bytes":0}},{"streams":[{"end":51.001066,"rtt":25141,"start":50.001041,"omitted":false,"stream-id":5,"retransmits":1,"tcp-window-size":1448,"throughput-bits":0,"throughput-bytes":0}],"summary":{"end":51.001066,"start":50.001041,"omitted":false,"retransmits":1,"throughput-bits":0,"throughput-bytes":0}},{"streams":[{"end":52.001049,"rtt":25141,"start":51.001066,"omitted":false,"stream-id":5,"retransmits":0,"tcp-window-size":1448,"throughput-bits":0,"throughput-bytes":0}],"summary":{"end":52.001049,"start":51.001066,"omitted":false,"retransmits":0,"throughput-bits":0,"throughput-bytes":0}},{"streams":[{"end":53.001102,"rtt":17818,"start":52.001049,"omitted":false,"stream-id":5,"retransmits":48,"tcp-window-size":41992,"throughput-bits":0,"throughput-bytes":0}],"summary":{"end":53.001102,"start":52.001049,"omitted":false,"retransmits":48,"throughput-bits":0,"throughput-bytes":0}},{"streams":[{"end":54.00108,"rtt":18751,"start":53.001102,"omitted":false,"stream-id":5,"retransmits":2,"tcp-window-size":1448,"throughput-bits":0,"throughput-bytes":0}],"summary":{"end":54.00108,"start":53.001102,"omitted":false,"retransmits":2,"throughput-bits":0,"throughput-bytes":0}},{"streams":[{"end":55.00107,"rtt":18751,"start":54.00108,"omitted":false,"stream-id":5,"retransmits":1,"tcp-window-size":1448,"throughput-bits":0,"throughput-bytes":0}],"summary":{"end":55.00107,"start":54.00108,"omitted":false,"retransmits":1,"throughput-bits":0,"throughput-bytes":0}},{"streams":[{"end":56.001047,"rtt":18751,"start":55.00107,"omitted":false,"stream-id":5,"retransmits":0,"tcp-window-size":1448,"throughput-bits":0,"throughput-bytes":0}],"summary":{"end":56.001047,"start":55.00107,"omitted":false,"retransmits":0,"throughput-bits":0,"throughput-bytes":0}},{"streams":[{"end":57.001057,"rtt":22252,"start":56.001047,"omitted":false,"stream-id":5,"retransmits":34,"tcp-window-size":1448,"throughput-bits":0,"throughput-bytes":0}],"summary":{"end":57.001057,"start":56.001047,"omitted":false,"retransmits":34,"throughput-bits":0,"throughput-bytes":0}},{"streams":[{"end":58.001052,"rtt":22252,"start":57.001057,"omitted":false,"stream-id":5,"retransmits":1,"tcp-window-size":1448,"throughput-bits":0,"throughput-bytes":0}],"summary":{"end":58.001052,"start":57.001057,"omitted":false,"retransmits":1,"throughput-bits":0,"throughput-bytes":0}},{"streams":[{"end":59.00106,"rtt":22252,"start":58.001052,"omitted":false,"stream-id":5,"retransmits":1,"tcp-window-size":1448,"throughput-bits":0,"throughput-bytes":0}],"summary":{"end":59.00106,"start":58.001052,"omitted":false,"retransmits":1,"throughput-bits":0,"throughput-bytes":0}},{"streams":[{"end":60.001635,"rtt":41646,"start":59.00106,"omitted":false,"stream-id":5,"retransmits":25,"tcp-window-size":8688,"throughput-bits":0,"throughput-bytes":0}],"summary":{"end":60.001635,"start":59.00106,"omitted":false,"retransmits":25,"throughput-bits":0,"throughput-bytes":0}}],"succeeded":true}
