{"diags":"Participant 0:\n/usr/bin/iperf3 -p 5201 -B 172.16.0.2 -c 172.16.0.1 -t 60 --json --rsa-public-key-path /var/run/pscheduler-server/runner/tmp/tmp48tx3yvp/tmp7t2o0zrh/public-key --username QgdMISE4R2IHDCOeaSia\n\n{\n    \"end\": {\n        \"cpu_utilization_percent\": {\n            \"host_system\": 0.05394120097948396, \n            \"host_total\": 0.06575139390808685, \n            \"host_user\": 0.01180852905245065, \n            \"remote_system\": 0.398405466385812, \n            \"remote_total\": 0.451342676599775, \n            \"remote_user\": 0.05294039814628748\n        }, \n        \"receiver_tcp_congestion\": \"htcp\", \n        \"sender_tcp_congestion\": \"htcp\", \n        \"streams\": [\n            {\n                \"receiver\": {\n                    \"bits_per_second\": 1602200.5940591472, \n                    \"bytes\": 12564560, \n                    \"end\": 62.736514, \n                    \"seconds\": 60.000172, \n                    \"sender\": true, \n                    \"socket\": 5, \n                    \"start\": 0\n                }, \n                \"sender\": {\n                    \"bits_per_second\": 1839147.7944429894, \n                    \"bytes\": 13793648, \n                    \"end\": 60.000172, \n                    \"max_rtt\": 468998, \n                    \"max_snd_cwnd\": 133216, \n                    \"max_snd_wnd\": 0, \n                    \"mean_rtt\": 37804, \n                    \"min_rtt\": 14036, \n                    \"retransmits\": 583, \n                    \"seconds\": 60.000172, \n                    \"sender\": true, \n                    \"socket\": 5, \n                    \"start\": 0\n                }\n            }\n        ], \n        \"sum_received\": {\n            \"bits_per_second\": 1602200.5940591472, \n            \"bytes\": 12564560, \n            \"end\": 62.736514, \n            \"seconds\": 62.736514, \n            \"sender\": true, \n            \"start\": 0\n        }, \n        \"sum_sent\": {\n            \"bits_per_second\": 1839147.7944429894, \n            \"bytes\": 13793648, \n            \"end\": 60.000172, \n            \"retransmits\": 583, \n            \"seconds\": 60.000172, \n            \"sender\": true, \n            \"start\": 0\n        }\n    }, \n    \"intervals\": [\n        {\n            \"streams\": [\n                {\n                    \"bits_per_second\": 16503418.9118112, \n                    \"bytes\": 2064848, \n                    \"end\": 1.000931, \n                    \"omitted\": false, \n                    \"pmtu\": 1500, \n                    \"retransmits\": 1, \n                    \"rtt\": 54275, \n                    \"rttvar\": 1910, \n                    \"seconds\": 1.0009310245513916, \n                    \"sender\": true, \n                    \"snd_cwnd\": 1448, \n                    \"snd_wnd\": -1, \n                    \"socket\": 5, \n                    \"start\": 0\n                }\n            ], \n            \"sum\": {\n                \"bits_per_second\": 16503418.9118112, \n                \"bytes\": 2064848, \n                \"end\": 1.000931, \n                \"omitted\": false, \n                \"retransmits\": 1, \n                \"seconds\": 1.0009310245513916, \n                \"sender\": true, \n                \"start\": 0\n            }\n        }, \n        {\n            \"streams\": [\n                {\n                    \"bits_per_second\": 0, \n                    \"bytes\": 0, \n                    \"end\": 2.001049, \n                    \"omitted\": false, \n                    \"pmtu\": 1500, \n                    \"retransmits\": 1, \n                    \"rtt\": 54275, \n                    \"rttvar\": 1910, \n                    \"seconds\": 1.0001180171966553, \n                    \"sender\": true, \n                    \"snd_cwnd\": 1448, \n                    \"snd_wnd\": -1, \n                    \"socket\": 5, \n                    \"start\": 1.000931\n                }\n            ], \n            \"sum\": {\n                \"bits_per_second\": 0, \n                \"bytes\": 0, \n                \"end\": 2.001049, \n                \"omitted\": false, \n                \"retransmits\": 1, \n                \"seconds\": 1.0001180171966553, \n                \"sender\": true, \n                \"start\": 1.000931\n            }\n        }, \n        {\n            \"streams\": [\n                {\n                    \"bits_per_second\": 0, \n                    \"bytes\": 0, \n                    \"end\": 3.001049, \n                    \"omitted\": false, \n                    \"pmtu\": 1500, \n                    \"retransmits\": 1, \n                    \"rtt\": 54275, \n                    \"rttvar\": 1910, \n                    \"seconds\": 1, \n                    \"sender\": true, \n                    \"snd_cwnd\": 1448, \n                    \"snd_wnd\": -1, \n                    \"socket\": 5, \n                    \"start\": 2.001049\n                }\n            ], \n            \"sum\": {\n                \"bits_per_second\": 0, \n                \"bytes\": 0, \n                \"end\": 3.001049, \n                \"omitted\": false, \n                \"retransmits\": 1, \n                \"seconds\": 1, \n                \"sender\": true, \n                \"start\": 2.001049\n            }\n        }, \n        {\n            \"streams\": [\n                {\n                    \"bits_per_second\": 0, \n                    \"bytes\": 0, \n                    \"end\": 4.001046, \n                    \"omitted\": false, \n                    \"pmtu\": 1500, \n                    \"retransmits\": 0, \n                    \"rtt\": 54275, \n                    \"rttvar\": 1910, \n                    \"seconds\": 0.9999970197677612, \n                    \"sender\": true, \n                    \"snd_cwnd\": 1448, \n                    \"snd_wnd\": -1, \n                    \"socket\": 5, \n                    \"start\": 3.001049\n                }\n            ], \n            \"sum\": {\n                \"bits_per_second\": 0, \n                \"bytes\": 0, \n                \"end\": 4.001046, \n                \"omitted\": false, \n                \"retransmits\": 0, \n                \"seconds\": 0.9999970197677612, \n                \"sender\": true, \n                \"start\": 3.001049\n            }\n        }, \n        {\n            \"streams\": [\n                {\n                    \"bits_per_second\": 0, \n                    \"bytes\": 0, \n                    \"end\": 5.001052, \n                    \"omitted\": false, \n                    \"pmtu\": 1500, \n                    \"retransmits\": 60, \n                    \"rtt\": 35922, \n                    \"rttvar\": 11986, \n                    \"seconds\": 1.0000059604644775, \n                    \"sender\": true, \n                    \"snd_cwnd\": 5792, \n                    \"snd_wnd\": -1, \n                    \"socket\": 5, \n                    \"start\": 4.001046\n                }\n            ], \n            \"sum\": {\n                \"bits_per_second\": 0, \n                \"bytes\": 0, \n                \"end\": 5.001052, \n                \"omitted\": false, \n                \"retransmits\": 60, \n                \"seconds\": 1.0000059604644775, \n                \"sender\": true, \n                \"start\": 4.001046\n            }\n        }, \n        {\n            \"streams\": [\n                {\n                    \"bits_per_second\": 0, \n                    \"bytes\": 0, \n                    \"end\": 6.001048, \n                    \"omitted\": false, \n                    \"pmtu\": 1500, \n                    \"retransmits\": 169, \n                    \"rtt\": 14036, \n                    \"rttvar\": 2828, \n                    \"seconds\": 0.9999960064888, \n                    \"sender\": true, \n                    \"snd_cwnd\": 1448, \n                    \"snd_wnd\": -1, \n                    \"socket\": 5, \n                    \"start\": 5.001052\n                }\n            ], \n            \"sum\": {\n                \"bits_per_second\": 0, \n                \"bytes\": 0, \n                \"end\": 6.001048, \n                \"omitted\": false, \n                \"retransmits\": 169, \n                \"seconds\": 0.9999960064888, \n                \"sender\": true, \n                \"start\": 5.001052\n            }\n        }, \n        {\n            \"streams\": [\n                {\n                    \"bits_per_second\": 0, \n                    \"bytes\": 0, \n                    \"end\": 7.001051, \n                    \"omitted\": false, \n                    \"pmtu\": 1500, \n                    \"retransmits\": 36, \n                    \"rtt\": 34552, \n                    \"rttvar\": 16247, \n                    \"seconds\": 1.0000029802322388, \n                    \"sender\": true, \n                    \"snd_cwnd\": 1448, \n                    \"snd_wnd\": -1, \n                    \"socket\": 5, \n                    \"start\": 6.001048\n                }\n            ], \n            \"sum\": {\n                \"bits_per_second\": 0, \n                \"bytes\": 0, \n                \"end\": 7.001051, \n                \"omitted\": false, \n                \"retransmits\": 36, \n                \"seconds\": 1.0000029802322388, \n                \"sender\": true, \n                \"start\": 6.001048\n            }\n        }, \n        {\n            \"streams\": [\n                {\n                    \"bits_per_second\": 0, \n                    \"bytes\": 0, \n                    \"end\": 8.001167, \n                    \"omitted\": false, \n                    \"pmtu\": 1500, \n                    \"retransmits\": 1, \n                    \"rtt\": 34552, \n                    \"rttvar\": 16247, \n                    \"seconds\": 1.000115990638733, \n                    \"sender\": true, \n                    \"snd_cwnd\": 1448, \n                    \"snd_wnd\": -1, \n                    \"socket\": 5, \n                    \"start\": 7.001051\n                }\n            ], \n            \"sum\": {\n                \"bits_per_second\": 0, \n                \"bytes\": 0, \n                \"end\": 8.001167, \n                \"omitted\": false, \n                \"retransmits\": 1, \n                \"seconds\": 1.000115990638733, \n                \"sender\": true, \n                \"start\": 7.001051\n            }\n        }, \n        {\n            \"streams\": [\n                {\n                    \"bits_per_second\": 5216101.799363448, \n                    \"bytes\": 651600, \n                    \"end\": 9.000534, \n                    \"omitted\": false, \n                    \"pmtu\": 1500, \n                    \"retransmits\": 20, \n                    \"rtt\": 21267, \n                    \"rttvar\": 1993, \n                    \"seconds\": 0.9993669986724854, \n                    \"sender\": true, \n                    \"snd_cwnd\": 28960, \n                    \"snd_wnd\": -1, \n                    \"socket\": 5, \n                    \"start\": 8.001167\n                }\n            ], \n            \"sum\": {\n                \"bits_per_second\": 5216101.799363448, \n                \"bytes\": 651600, \n                \"end\": 9.000534, \n                \"omitted\": false, \n                \"retransmits\": 20, \n                \"seconds\": 0.9993669986724854, \n                \"sender\": true, \n                \"start\": 8.001167\n            }\n        }, \n        {\n            \"streams\": [\n                {\n                    \"bits_per_second\": 0, \n                    \"bytes\": 0, \n                    \"end\": 10.001055, \n                    \"omitted\": false, \n                    \"pmtu\": 1500, \n                    \"retransmits\": 22, \n                    \"rtt\": 23261, \n                    \"rttvar\": 3669, \n                    \"seconds\": 1.000520944595337, \n                    \"sender\": true, \n                    \"snd_cwnd\": 1448, \n                    \"snd_wnd\": -1, \n                    \"socket\": 5, \n                    \"start\": 9.000534\n                }\n            ], \n            \"sum\": {\n                \"bits_per_second\": 0, \n                \"bytes\": 0, \n                \"end\": 10.001055, \n                \"omitted\": false, \n                \"retransmits\": 22, \n                \"seconds\": 1.000520944595337, \n                \"sender\": true, \n                \"start\": 9.000534\n            }\n        }, \n        {\n            \"streams\": [\n                {\n                    \"bits_per_second\": 0, \n                    \"bytes\": 0, \n                    \"end\": 11.001053, \n                    \"omitted\": false, \n                    \"pmtu\": 1500, \n                    \"retransmits\": 1, \n                    \"rtt\": 23261, \n                    \"rttvar\": 3669, \n                    \"seconds\": 0.9999979734420776, \n                    \"sender\": true, \n                    \"snd_cwnd\": 1448, \n                    \"snd_wnd\": -1, \n                    \"socket\": 5, \n                    \"start\": 10.001055\n                }\n            ], \n            \"sum\": {\n                \"bits_per_second\": 0, \n                \"bytes\": 0, \n                \"end\": 11.001053, \n                \"omitted\": false, \n                \"retransmits\": 1, \n                \"seconds\": 0.9999979734420776, \n                \"sender\": true, \n                \"start\": 10.001055\n            }\n        }, \n        {\n            \"streams\": [\n                {\n                    \"bits_per_second\": 0, \n                    \"bytes\": 0, \n                    \"end\": 12.001055, \n                    \"omitted\": false, \n                    \"pmtu\": 1500, \n                    \"retransmits\": 1, \n                    \"rtt\": 23261, \n                    \"rttvar\": 3669, \n                    \"seconds\": 1.0000020265579224, \n                    \"sender\": true, \n                    \"snd_cwnd\": 1448, \n                    \"snd_wnd\": -1, \n                    \"socket\": 5, \n                    \"start\": 11.001053\n                }\n            ], \n            \"sum\": {\n                \"bits_per_second\": 0, \n                \"bytes\": 0, \n                \"end\": 12.001055, \n                \"omitted\": false, \n                \"retransmits\": 1, \n                \"seconds\": 1.0000020265579224, \n                \"sender\": true, \n                \"start\": 11.001053\n            }\n        }, \n        {\n            \"streams\": [\n                {\n                    \"bits_per_second\": 0, \n                    \"bytes\": 0, \n                    \"end\": 13.001051, \n                    \"omitted\": false, \n                    \"pmtu\": 1500, \n                    \"retransmits\": 0, \n                    \"rtt\": 23261, \n                    \"rttvar\": 3669, \n                    \"seconds\": 0.9999960064888, \n                    \"sender\": true, \n                    \"snd_cwnd\": 1448, \n                    \"snd_wnd\": -1, \n                    \"socket\": 5, \n                    \"start\": 12.001055\n                }\n            ], \n            \"sum\": {\n                \"bits_per_second\": 0, \n                \"bytes\": 0, \n                \"end\": 13.001051, \n                \"omitted\": false, \n                \"retransmits\": 0, \n                \"seconds\": 0.9999960064888, \n                \"sender\": true, \n                \"start\": 12.001055\n            }\n        }, \n        {\n            \"streams\": [\n                {\n                    \"bits_per_second\": 0, \n                    \"bytes\": 0, \n                    \"end\": 14.00105, \n                    \"omitted\": false, \n                    \"pmtu\": 1500, \n                    \"retransmits\": 1, \n                    \"rtt\": 23261, \n                    \"rttvar\": 3669, \n                    \"seconds\": 0.9999989867210388, \n                    \"sender\": true, \n                    \"snd_cwnd\": 1448, \n                    \"snd_wnd\": -1, \n                    \"socket\": 5, \n                    \"start\": 13.001051\n                }\n            ], \n            \"sum\": {\n                \"bits_per_second\": 0, \n                \"bytes\": 0, \n                \"end\": 14.00105, \n                \"omitted\": false, \n                \"retransmits\": 1, \n                \"seconds\": 0.9999989867210388, \n                \"sender\": true, \n                \"start\": 13.001051\n            }\n        }, \n        {\n            \"streams\": [\n                {\n                    \"bits_per_second\": 0, \n                    \"bytes\": 0, \n                    \"end\": 15.001047, \n                    \"omitted\": false, \n                    \"pmtu\": 1500, \n                    \"retransmits\": 0, \n                    \"rtt\": 23261, \n                    \"rttvar\": 3669, \n                    \"seconds\": 0.9999970197677612, \n                    \"sender\": true, \n                    \"snd_cwnd\": 1448, \n                    \"snd_wnd\": -1, \n                    \"socket\": 5, \n                    \"start\": 14.00105\n                }\n            ], \n            \"sum\": {\n                \"bits_per_second\": 0, \n                \"bytes\": 0, \n                \"end\": 15.001047, \n                \"omitted\": false, \n                \"retransmits\": 0, \n                \"seconds\": 0.9999970197677612, \n                \"sender\": true, \n                \"start\": 14.00105\n            }\n        }, \n        {\n            \"streams\": [\n                {\n                    \"bits_per_second\": 0, \n                    \"bytes\": 0, \n                    \"end\": 16.00105, \n                    \"omitted\": false, \n                    \"pmtu\": 1500, \n                    \"retransmits\": 0, \n                    \"rtt\": 23261, \n                    \"rttvar\": 3669, \n                    \"seconds\": 1.0000029802322388, \n                    \"sender\": true, \n                    \"snd_cwnd\": 1448, \n                    \"snd_wnd\": -1, \n                    \"socket\": 5, \n                    \"start\": 15.001047\n                }\n            ], \n            \"sum\": {\n                \"bits_per_second\": 0, \n                \"bytes\": 0, \n                \"end\": 16.00105, \n                \"omitted\": false, \n                \"retransmits\": 0, \n                \"seconds\": 1.0000029802322388, \n                \"sender\": true, \n                \"start\": 15.001047\n            }\n        }, \n        {\n            \"streams\": [\n                {\n                    \"bits_per_second\": 0, \n                    \"bytes\": 0, \n                    \"end\": 17.001049, \n                    \"omitted\": false, \n                    \"pmtu\": 1500, \n                    \"retransmits\": 1, \n                    \"rtt\": 25228, \n                    \"rttvar\": 6686, \n                    \"seconds\": 0.9999989867210388, \n                    \"sender\": true, \n                    \"snd_cwnd\": 2896, \n                    \"snd_wnd\": -1, \n                    \"socket\": 5, \n                    \"start\": 16.00105\n                }\n            ], \n            \"sum\": {\n                \"bits_per_second\": 0, \n                \"bytes\": 0, \n                \"end\": 17.001049, \n                \"omitted\": false, \n                \"retransmits\": 1, \n                \"seconds\": 0.9999989867210388, \n                \"sender\": true, \n                \"start\": 16.00105\n            }\n        }, \n        {\n            \"streams\": [\n                {\n                    \"bits_per_second\": 0, \n                    \"bytes\": 0, \n                    \"end\": 18.000289, \n                    \"omitted\": false, \n                    \"pmtu\": 1500, \n                    \"retransmits\": 12, \n                    \"rtt\": 38653, \n                    \"rttvar\": 3602, \n                    \"seconds\": 0.999239981174469, \n                    \"sender\": true, \n                    \"snd_cwnd\": 1448, \n                    \"snd_wnd\": -1, \n                    \"socket\": 5, \n                    \"start\": 17.001049\n                }\n            ], \n            \"sum\": {\n                \"bits_per_second\": 0, \n                \"bytes\": 0, \n                \"end\": 18.000289, \n                \"omitted\": false, \n                \"retransmits\": 12, \n                \"seconds\": 0.999239981174469, \n                \"sender\": true, \n                \"start\": 17.001049\n            }\n        }, \n        {\n            \"streams\": [\n                {\n                    \"bits_per_second\": 0, \n                    \"bytes\": 0, \n                    \"end\": 19.001045, \n                    \"omitted\": false, \n                    \"pmtu\": 1500, \n                    \"retransmits\": 1, \n                    \"rtt\": 468998, \n                    \"rttvar\": 595497, \n                    \"seconds\": 1.000756025314331, \n                    \"sender\": true, \n                    \"snd_cwnd\": 11584, \n                    \"snd_wnd\": -1, \n                    \"socket\": 5, \n                    \"start\": 18.000289\n                }\n            ], \n            \"sum\": {\n                \"bits_per_second\": 0, \n                \"bytes\": 0, \n                \"end\": 19.001045, \n                \"omitted\": false, \n                \"retransmits\": 1, \n                \"seconds\": 1.000756025314331, \n                \"sender\": true, \n                \"start\": 18.000289\n            }\n        }, \n        {\n            \"streams\": [\n                {\n                    \"bits_per_second\": 0, \n                    \"bytes\": 0, \n                    \"end\": 20.001053, \n                    \"omitted\": false, \n                    \"pmtu\": 1500, \n                    \"retransmits\": 8, \n                    \"rtt\": 61945, \n                    \"rttvar\": 29592, \n                    \"seconds\": 1.0000079870224, \n                    \"sender\": true, \n                    \"snd_cwnd\": 10136, \n                    \"snd_wnd\": -1, \n                    \"socket\": 5, \n                    \"start\": 19.001045\n                }\n            ], \n            \"sum\": {\n                \"bits_per_second\": 0, \n                \"bytes\": 0, \n                \"end\": 20.001053, \n                \"omitted\": false, \n                \"retransmits\": 8, \n                \"seconds\": 1.0000079870224, \n                \"sender\": true, \n                \"start\": 19.001045\n            }\n        }, \n        {\n            \"streams\": [\n                {\n                    \"bits_per_second\": 0, \n                    \"bytes\": 0, \n                    \"end\": 21.001072, \n                    \"omitted\": false, \n                    \"pmtu\": 1500, \n                    \"retransmits\": 0, \n                    \"rtt\": 61945, \n                    \"rttvar\": 29592, \n                    \"seconds\": 1.0000189542770386, \n                    \"sender\": true, \n                    \"snd_cwnd\": 10136, \n                    \"snd_wnd\": -1, \n                    \"socket\": 5, \n                    \"start\": 20.001053\n                }\n            ], \n            \"sum\": {\n                \"bits_per_second\": 0, \n                \"bytes\": 0, \n                \"end\": 21.001072, \n                \"omitted\": false, \n                \"retransmits\": 0, \n                \"seconds\": 1.0000189542770386, \n                \"sender\": true, \n                \"start\": 20.001053\n            }\n        }, \n        {\n            \"streams\": [\n                {\n                    \"bits_per_second\": 0, \n                    \"bytes\": 0, \n                    \"end\": 22.001052, \n                    \"omitted\": false, \n                    \"pmtu\": 1500, \n                    \"retransmits\": 1, \n                    \"rtt\": 24747, \n                    \"rttvar\": 12900, \n                    \"seconds\": 0.9999799728393555, \n                    \"sender\": true, \n                    \"snd_cwnd\": 26064, \n                    \"snd_wnd\": -1, \n                    \"socket\": 5, \n                    \"start\": 21.001072\n                }\n            ], \n            \"sum\": {\n                \"bits_per_second\": 0, \n                \"bytes\": 0, \n                \"end\": 22.001052, \n                \"omitted\": false, \n                \"retransmits\": 1, \n                \"seconds\": 0.9999799728393555, \n                \"sender\": true, \n                \"start\": 21.001072\n            }\n        }, \n        {\n            \"streams\": [\n                {\n                    \"bits_per_second\": 0, \n                    \"bytes\": 0, \n                    \"end\": 23.00105, \n                    \"omitted\": false, \n                    \"pmtu\": 1500, \n                    \"retransmits\": 2, \n                    \"rtt\": 24747, \n                    \"rttvar\": 12900, \n                    \"seconds\": 0.9999979734420776, \n                    \"sender\": true, \n                    \"snd_cwnd\": 1448, \n                    \"snd_wnd\": -1, \n                    \"socket\": 5, \n                    \"start\": 22.001052\n                }\n            ], \n            \"sum\": {\n                \"bits_per_second\": 0, \n                \"bytes\": 0, \n                \"end\": 23.00105, \n                \"omitted\": false, \n                \"retransmits\": 2, \n                \"seconds\": 0.9999979734420776, \n                \"sender\": true, \n                \"start\": 22.001052\n            }\n        }, \n        {\n            \"streams\": [\n                {\n                    \"bits_per_second\": 0, \n                    \"bytes\": 0, \n                    \"end\": 24.001047, \n                    \"omitted\": false, \n                    \"pmtu\": 1500, \n                    \"retransmits\": 0, \n                    \"rtt\": 24747, \n                    \"rttvar\": 12900, \n                    \"seconds\": 0.9999970197677612, \n                    \"sender\": true, \n                    \"snd_cwnd\": 1448, \n                    \"snd_wnd\": -1, \n                    \"socket\": 5, \n                    \"start\": 23.00105\n                }\n            ], \n            \"sum\": {\n                \"bits_per_second\": 0, \n                \"bytes\": 0, \n                \"end\": 24.001047, \n                \"omitted\": false, \n                \"retransmits\": 0, \n                \"seconds\": 0.9999970197677612, \n                \"sender\": true, \n                \"start\": 23.00105\n            }\n        }, \n        {\n            \"streams\": [\n                {\n                    \"bits_per_second\": 0, \n                    \"bytes\": 0, \n                    \"end\": 25.001051, \n                    \"omitted\": false, \n                    \"pmtu\": 1500, \n                    \"retransmits\": 1, \n                    \"rtt\": 24747, \n                    \"rttvar\": 12900, \n                    \"seconds\": 1.0000040531158447, \n                    \"sender\": true, \n                    \"snd_cwnd\": 1448, \n                    \"snd_wnd\": -1, \n                    \"socket\": 5, \n                    \"start\": 24.001047\n                }\n            ], \n            \"sum\": {\n                \"bits_per_second\": 0, \n                \"bytes\": 0, \n                \"end\": 25.001051, \n                \"omitted\": false, \n                \"retransmits\": 1, \n                \"seconds\": 1.0000040531158447, \n                \"sender\": true, \n                \"start\": 24.001047\n            }\n        }, \n        {\n            \"streams\": [\n                {\n                    \"bits_per_second\": 5215673.759760573, \n                    \"bytes\": 651600, \n                    \"end\": 26.0005, \n                    \"omitted\": false, \n                    \"pmtu\": 1500, \n                    \"retransmits\": 18, \n                    \"rtt\": 22767, \n                    \"rttvar\": 13370, \n                    \"seconds\": 0.9994490146636963, \n                    \"sender\": true, \n                    \"snd_cwnd\": 30408, \n                    \"snd_wnd\": -1, \n                    \"socket\": 5, \n                    \"start\": 25.001051\n                }\n            ], \n            \"sum\": {\n                \"bits_per_second\": 5215673.759760573, \n                \"bytes\": 651600, \n                \"end\": 26.0005, \n                \"omitted\": false, \n                \"retransmits\": 18, \n                \"seconds\": 0.9994490146636963, \n                \"sender\": true, \n                \"start\": 25.001051\n            }\n        }, \n        {\n            \"streams\": [\n                {\n                    \"bits_per_second\": 0, \n                    \"bytes\": 0, \n                    \"end\": 27.001067, \n                    \"omitted\": false, \n                    \"pmtu\": 1500, \n                    \"retransmits\": 2, \n                    \"rtt\": 22767, \n                    \"rttvar\": 13370, \n                    \"seconds\": 1.0005669593811035, \n                    \"sender\": true, \n                    \"snd_cwnd\": 1448, \n                    \"snd_wnd\": -1, \n                    \"socket\": 5, \n                    \"start\": 26.0005\n                }\n            ], \n            \"sum\": {\n                \"bits_per_second\": 0, \n                \"bytes\": 0, \n                \"end\": 27.001067, \n                \"omitted\": false, \n                \"retransmits\": 2, \n                \"seconds\": 1.0005669593811035, \n                \"sender\": true, \n                \"start\": 26.0005\n            }\n        }, \n        {\n            \"streams\": [\n                {\n                    \"bits_per_second\": 0, \n                    \"bytes\": 0, \n                    \"end\": 28.001048, \n                    \"omitted\": false, \n                    \"pmtu\": 1500, \n                    \"retransmits\": 1, \n                    \"rtt\": 22767, \n                    \"rttvar\": 13370, \n                    \"seconds\": 0.9999809861183167, \n                    \"sender\": true, \n                    \"snd_cwnd\": 1448, \n                    \"snd_wnd\": -1, \n                    \"socket\": 5, \n                    \"start\": 27.001067\n                }\n            ], \n            \"sum\": {\n                \"bits_per_second\": 0, \n                \"bytes\": 0, \n                \"end\": 28.001048, \n                \"omitted\": false, \n                \"retransmits\": 1, \n                \"seconds\": 0.9999809861183167, \n                \"sender\": true, \n                \"start\": 27.001067\n            }\n        }, \n        {\n            \"streams\": [\n                {\n                    \"bits_per_second\": 0, \n                    \"bytes\": 0, \n                    \"end\": 29.001051, \n                    \"omitted\": false, \n                    \"pmtu\": 1500, \n                    \"retransmits\": 0, \n                    \"rtt\": 22767, \n                    \"rttvar\": 13370, \n                    \"seconds\": 1.0000029802322388, \n                    \"sender\": true, \n                    \"snd_cwnd\": 1448, \n                    \"snd_wnd\": -1, \n                    \"socket\": 5, \n                    \"start\": 28.001048\n                }\n            ], \n            \"sum\": {\n                \"bits_per_second\": 0, \n                \"bytes\": 0, \n                \"end\": 29.001051, \n                \"omitted\": false, \n                \"retransmits\": 0, \n                \"seconds\": 1.0000029802322388, \n                \"sender\": true, \n                \"start\": 28.001048\n            }\n        }, \n        {\n            \"streams\": [\n                {\n                    \"bits_per_second\": 0, \n                    \"bytes\": 0, \n                    \"end\": 30.000991, \n                    \"omitted\": false, \n                    \"pmtu\": 1500, \n                    \"retransmits\": 1, \n                    \"rtt\": 22767, \n                    \"rttvar\": 13370, \n                    \"seconds\": 0.9999399781227112, \n                    \"sender\": true, \n                    \"snd_cwnd\": 1448, \n                    \"snd_wnd\": -1, \n                    \"socket\": 5, \n                    \"start\": 29.001051\n                }\n            ], \n            \"sum\": {\n                \"bits_per_second\": 0, \n                \"bytes\": 0, \n                \"end\": 30.000991, \n                \"omitted\": false, \n                \"retransmits\": 1, \n                \"seconds\": 0.9999399781227112, \n                \"sender\": true, \n                \"start\": 29.001051\n            }\n        }, \n        {\n            \"streams\": [\n                {\n                    \"bits_per_second\": 0, \n                    \"bytes\": 0, \n                    \"end\": 31.001047, \n                    \"omitted\": false, \n                    \"pmtu\": 1500, \n                    \"retransmits\": 0, \n                    \"rtt\": 22767, \n                    \"rttvar\": 13370, \n                    \"seconds\": 1.0000560283660889, \n                    \"sender\": true, \n                    \"snd_cwnd\": 1448, \n                    \"snd_wnd\": -1, \n                    \"socket\": 5, \n                    \"start\": 30.000991\n                }\n            ], \n            \"sum\": {\n                \"bits_per_second\": 0, \n                \"bytes\": 0, \n                \"end\": 31.001047, \n                \"omitted\": false, \n                \"retransmits\": 0, \n                \"seconds\": 1.0000560283660889, \n                \"sender\": true, \n                \"start\": 30.000991\n            }\n        }, \n        {\n            \"streams\": [\n                {\n                    \"bits_per_second\": 0, \n                    \"bytes\": 0, \n                    \"end\": 32.000981, \n                    \"omitted\": false, \n                    \"pmtu\": 1500, \n                    \"retransmits\": 0, \n                    \"rtt\": 22767, \n                    \"rttvar\": 13370, \n                    \"seconds\": 0.9999340176582336, \n                    \"sender\": true, \n                    \"snd_cwnd\": 1448, \n                    \"snd_wnd\": -1, \n                    \"socket\": 5, \n                    \"start\": 31.001047\n                }\n            ], \n            \"sum\": {\n                \"bits_per_second\": 0, \n                \"bytes\": 0, \n                \"end\": 32.000981, \n                \"omitted\": false, \n                \"retransmits\": 0, \n                \"seconds\": 0.9999340176582336, \n                \"sender\": true, \n                \"start\": 31.001047\n            }\n        }, \n        {\n            \"streams\": [\n                {\n                    \"bits_per_second\": 0, \n                    \"bytes\": 0, \n                    \"end\": 33.001042, \n                    \"omitted\": false, \n                    \"pmtu\": 1500, \n                    \"retransmits\": 0, \n                    \"rtt\": 22767, \n                    \"rttvar\": 13370, \n                    \"seconds\": 1.00006103515625, \n                    \"sender\": true, \n                    \"snd_cwnd\": 1448, \n                    \"snd_wnd\": -1, \n                    \"socket\": 5, \n                    \"start\": 32.000981\n                }\n            ], \n            \"sum\": {\n                \"bits_per_second\": 0, \n                \"bytes\": 0, \n                \"end\": 33.001042, \n                \"omitted\": false, \n                \"retransmits\": 0, \n                \"seconds\": 1.00006103515625, \n                \"sender\": true, \n                \"start\": 32.000981\n            }\n        }, \n        {\n            \"streams\": [\n                {\n                    \"bits_per_second\": 0, \n                    \"bytes\": 0, \n                    \"end\": 34.001052, \n                    \"omitted\": false, \n                    \"pmtu\": 1500, \n                    \"retransmits\": 21, \n                    \"rtt\": 24799, \n                    \"rttvar\": 6521, \n                    \"seconds\": 1.0000100135803223, \n                    \"sender\": true, \n                    \"snd_cwnd\": 26064, \n                    \"snd_wnd\": -1, \n                    \"socket\": 5, \n                    \"start\": 33.001042\n                }\n            ], \n            \"sum\": {\n                \"bits_per_second\": 0, \n                \"bytes\": 0, \n                \"end\": 34.001052, \n                \"omitted\": false, \n                \"retransmits\": 21, \n                \"seconds\": 1.0000100135803223, \n                \"sender\": true, \n                \"start\": 33.001042\n            }\n        }, \n        {\n            \"streams\": [\n                {\n                    \"bits_per_second\": 0, \n                    \"bytes\": 0, \n                    \"end\": 35.001049, \n                    \"omitted\": false, \n                    \"pmtu\": 1500, \n                    \"retransmits\": 2, \n                    \"rtt\": 28179, \n                    \"rttvar\": 11649, \n                    \"seconds\": 0.9999970197677612, \n                    \"sender\": true, \n                    \"snd_cwnd\": 1448, \n                    \"snd_wnd\": -1, \n                    \"socket\": 5, \n                    \"start\": 34.001052\n                }\n            ], \n            \"sum\": {\n                \"bits_per_second\": 0, \n                \"bytes\": 0, \n                \"end\": 35.001049, \n                \"omitted\": false, \n                \"retransmits\": 2, \n                \"seconds\": 0.9999970197677612, \n                \"sender\": true, \n                \"start\": 34.001052\n            }\n        }, \n        {\n            \"streams\": [\n                {\n                    \"bits_per_second\": 0, \n                    \"bytes\": 0, \n                    \"end\": 36.001051, \n                    \"omitted\": false, \n                    \"pmtu\": 1500, \n                    \"retransmits\": 1, \n                    \"rtt\": 28179, \n                    \"rttvar\": 11649, \n                    \"seconds\": 1.0000020265579224, \n                    \"sender\": true, \n                    \"snd_cwnd\": 1448, \n                    \"snd_wnd\": -1, \n                    \"socket\": 5, \n                    \"start\": 35.001049\n                }\n            ], \n            \"sum\": {\n                \"bits_per_second\": 0, \n                \"bytes\": 0, \n                \"end\": 36.001051, \n                \"omitted\": false, \n                \"retransmits\": 1, \n                \"seconds\": 1.0000020265579224, \n                \"sender\": true, \n                \"start\": 35.001049\n            }\n        }, \n        {\n            \"streams\": [\n                {\n                    \"bits_per_second\": 0, \n                    \"bytes\": 0, \n                    \"end\": 37.001053, \n                    \"omitted\": false, \n                    \"pmtu\": 1500, \n                    \"retransmits\": 21, \n                    \"rtt\": 22357, \n                    \"rttvar\": 5324, \n                    \"seconds\": 1.0000020265579224, \n                    \"sender\": true, \n                    \"snd_cwnd\": 14480, \n                    \"snd_wnd\": -1, \n                    \"socket\": 5, \n                    \"start\": 36.001051\n                }\n            ], \n            \"sum\": {\n                \"bits_per_second\": 0, \n                \"bytes\": 0, \n                \"end\": 37.001053, \n                \"omitted\": false, \n                \"retransmits\": 21, \n                \"seconds\": 1.0000020265579224, \n                \"sender\": true, \n                \"start\": 36.001051\n            }\n        }, \n        {\n            \"streams\": [\n                {\n                    \"bits_per_second\": 5213352.49576196, \n                    \"bytes\": 651600, \n                    \"end\": 38.000947, \n                    \"omitted\": false, \n                    \"pmtu\": 1500, \n                    \"retransmits\": 15, \n                    \"rtt\": 59677, \n                    \"rttvar\": 40652, \n                    \"seconds\": 0.9998940229415894, \n                    \"sender\": true, \n                    \"snd_cwnd\": 10136, \n                    \"snd_wnd\": -1, \n                    \"socket\": 5, \n                    \"start\": 37.001053\n                }\n            ], \n            \"sum\": {\n                \"bits_per_second\": 5213352.49576196, \n                \"bytes\": 651600, \n                \"end\": 38.000947, \n                \"omitted\": false, \n                \"retransmits\": 15, \n                \"seconds\": 0.9998940229415894, \n                \"sender\": true, \n                \"start\": 37.001053\n            }\n        }, \n        {\n            \"streams\": [\n                {\n                    \"bits_per_second\": 5215204.11690713, \n                    \"bytes\": 651600, \n                    \"end\": 39.000486, \n                    \"omitted\": false, \n                    \"pmtu\": 1500, \n                    \"retransmits\": 0, \n                    \"rtt\": 27462, \n                    \"rttvar\": 11041, \n                    \"seconds\": 0.999539017677307, \n                    \"sender\": true, \n                    \"snd_cwnd\": 55024, \n                    \"snd_wnd\": -1, \n                    \"socket\": 5, \n                    \"start\": 38.000947\n                }\n            ], \n            \"sum\": {\n                \"bits_per_second\": 5215204.11690713, \n                \"bytes\": 651600, \n                \"end\": 39.000486, \n                \"omitted\": false, \n                \"retransmits\": 0, \n                \"seconds\": 0.999539017677307, \n                \"sender\": true, \n                \"start\": 38.000947\n            }\n        }, \n        {\n            \"streams\": [\n                {\n                    \"bits_per_second\": 0, \n                    \"bytes\": 0, \n                    \"end\": 40.001053, \n                    \"omitted\": false, \n                    \"pmtu\": 1500, \n                    \"retransmits\": 2, \n                    \"rtt\": 27462, \n                    \"rttvar\": 11041, \n                    \"seconds\": 1.0005669593811035, \n                    \"sender\": true, \n                    \"snd_cwnd\": 1448, \n                    \"snd_wnd\": -1, \n                    \"socket\": 5, \n                    \"start\": 39.000486\n                }\n            ], \n            \"sum\": {\n                \"bits_per_second\": 0, \n                \"bytes\": 0, \n                \"end\": 40.001053, \n                \"omitted\": false, \n                \"retransmits\": 2, \n                \"seconds\": 1.0005669593811035, \n                \"sender\": true, \n                \"start\": 39.000486\n            }\n        }, \n        {\n            \"streams\": [\n                {\n                    \"bits_per_second\": 0, \n                    \"bytes\": 0, \n                    \"end\": 41.001042, \n                    \"omitted\": false, \n                    \"pmtu\": 1500, \n                    \"retransmits\": 1, \n                    \"rtt\": 27462, \n                    \"rttvar\": 11041, \n                    \"seconds\": 0.9999889731407166, \n                    \"sender\": true, \n                    \"snd_cwnd\": 1448, \n                    \"snd_wnd\": -1, \n                    \"socket\": 5, \n                    \"start\": 40.001053\n                }\n            ], \n            \"sum\": {\n                \"bits_per_second\": 0, \n                \"bytes\": 0, \n                \"end\": 41.001042, \n                \"omitted\": false, \n                \"retransmits\": 1, \n                \"seconds\": 0.9999889731407166, \n                \"sender\": true, \n                \"start\": 40.001053\n            }\n        }, \n        {\n            \"streams\": [\n                {\n                    \"bits_per_second\": 0, \n                    \"bytes\": 0, \n                    \"end\": 42.001059, \n                    \"omitted\": false, \n                    \"pmtu\": 1500, \n                    \"retransmits\": 0, \n                    \"rtt\": 27462, \n                    \"rttvar\": 11041, \n                    \"seconds\": 1.0000170469284058, \n                    \"sender\": true, \n                    \"snd_cwnd\": 1448, \n                    \"snd_wnd\": -1, \n                    \"socket\": 5, \n                    \"start\": 41.001042\n                }\n            ], \n            \"sum\": {\n                \"bits_per_second\": 0, \n                \"bytes\": 0, \n                \"end\": 42.001059, \n                \"omitted\": false, \n                \"retransmits\": 0, \n                \"seconds\": 1.0000170469284058, \n                \"sender\": true, \n                \"start\": 41.001042\n            }\n        }, \n        {\n            \"streams\": [\n                {\n                    \"bits_per_second\": 5216268.865855715, \n                    \"bytes\": 651600, \n                    \"end\": 43.000394, \n                    \"omitted\": false, \n                    \"pmtu\": 1500, \n                    \"retransmits\": 39, \n                    \"rtt\": 22948, \n                    \"rttvar\": 5534, \n                    \"seconds\": 0.999334990978241, \n                    \"sender\": true, \n                    \"snd_cwnd\": 37648, \n                    \"snd_wnd\": -1, \n                    \"socket\": 5, \n                    \"start\": 42.001059\n                }\n            ], \n            \"sum\": {\n                \"bits_per_second\": 5216268.865855715, \n                \"bytes\": 651600, \n                \"end\": 43.000394, \n                \"omitted\": false, \n                \"retransmits\": 39, \n                \"seconds\": 0.999334990978241, \n                \"sender\": true, \n                \"start\": 42.001059\n            }\n        }, \n        {\n            \"streams\": [\n                {\n                    \"bits_per_second\": 0, \n                    \"bytes\": 0, \n                    \"end\": 44.00105, \n                    \"omitted\": false, \n                    \"pmtu\": 1500, \n                    \"retransmits\": 2, \n                    \"rtt\": 22948, \n                    \"rttvar\": 5534, \n                    \"seconds\": 1.000656008720398, \n                    \"sender\": true, \n                    \"snd_cwnd\": 1448, \n                    \"snd_wnd\": -1, \n                    \"socket\": 5, \n                    \"start\": 43.000394\n                }\n            ], \n            \"sum\": {\n                \"bits_per_second\": 0, \n                \"bytes\": 0, \n                \"end\": 44.00105, \n                \"omitted\": false, \n                \"retransmits\": 2, \n                \"seconds\": 1.000656008720398, \n                \"sender\": true, \n                \"start\": 43.000394\n            }\n        }, \n        {\n            \"streams\": [\n                {\n                    \"bits_per_second\": 0, \n                    \"bytes\": 0, \n                    \"end\": 45.00042, \n                    \"omitted\": false, \n                    \"pmtu\": 1500, \n                    \"retransmits\": 1, \n                    \"rtt\": 22948, \n                    \"rttvar\": 5534, \n                    \"seconds\": 0.999369978904724, \n                    \"sender\": true, \n                    \"snd_cwnd\": 1448, \n                    \"snd_wnd\": -1, \n                    \"socket\": 5, \n                    \"start\": 44.00105\n                }\n            ], \n            \"sum\": {\n                \"bits_per_second\": 0, \n                \"bytes\": 0, \n                \"end\": 45.00042, \n                \"omitted\": false, \n                \"retransmits\": 1, \n                \"seconds\": 0.999369978904724, \n                \"sender\": true, \n                \"start\": 44.00105\n            }\n        }, \n        {\n            \"streams\": [\n                {\n                    \"bits_per_second\": 0, \n                    \"bytes\": 0, \n                    \"end\": 46.001043, \n                    \"omitted\": false, \n                    \"pmtu\": 1500, \n                    \"retransmits\": 0, \n                    \"rtt\": 22948, \n                    \"rttvar\": 5534, \n                    \"seconds\": 1.0006229877471924, \n                    \"sender\": true, \n                    \"snd_cwnd\": 1448, \n                    \"snd_wnd\": -1, \n                    \"socket\": 5, \n                    \"start\": 45.00042\n                }\n            ], \n            \"sum\": {\n                \"bits_per_second\": 0, \n                \"bytes\": 0, \n                \"end\": 46.001043, \n                \"omitted\": false, \n                \"retransmits\": 0, \n                \"seconds\": 1.0006229877471924, \n                \"sender\": true, \n                \"start\": 45.00042\n            }\n        }, \n        {\n            \"streams\": [\n                {\n                    \"bits_per_second\": 0, \n                    \"bytes\": 0, \n                    \"end\": 47.001052, \n                    \"omitted\": false, \n                    \"pmtu\": 1500, \n                    \"retransmits\": 28, \n                    \"rtt\": 32654, \n                    \"rttvar\": 17683, \n                    \"seconds\": 1.0000089406967163, \n                    \"sender\": true, \n                    \"snd_cwnd\": 2896, \n                    \"snd_wnd\": -1, \n                    \"socket\": 5, \n                    \"start\": 46.001043\n                }\n            ], \n            \"sum\": {\n                \"bits_per_second\": 0, \n                \"bytes\": 0, \n                \"end\": 47.001052, \n                \"omitted\": false, \n                \"retransmits\": 28, \n                \"seconds\": 1.0000089406967163, \n                \"sender\": true, \n                \"start\": 46.001043\n            }\n        }, \n        {\n            \"streams\": [\n                {\n                    \"bits_per_second\": 0, \n                    \"bytes\": 0, \n                    \"end\": 48.001046, \n                    \"omitted\": false, \n                    \"pmtu\": 1500, \n                    \"retransmits\": 17, \n                    \"rtt\": 28120, \n                    \"rttvar\": 7418, \n                    \"seconds\": 0.9999939799308777, \n                    \"sender\": true, \n                    \"snd_cwnd\": 1448, \n                    \"snd_wnd\": -1, \n                    \"socket\": 5, \n                    \"start\": 47.001052\n                }\n            ], \n            \"sum\": {\n                \"bits_per_second\": 0, \n                \"bytes\": 0, \n                \"end\": 48.001046, \n                \"omitted\": false, \n                \"retransmits\": 17, \n                \"seconds\": 0.9999939799308777, \n                \"sender\": true, \n                \"start\": 47.001052\n            }\n        }, \n        {\n            \"streams\": [\n                {\n                    \"bits_per_second\": 0, \n                    \"bytes\": 0, \n                    \"end\": 49.001042, \n                    \"omitted\": false, \n                    \"pmtu\": 1500, \n                    \"retransmits\": 1, \n                    \"rtt\": 28120, \n                    \"rttvar\": 7418, \n                    \"seconds\": 0.9999960064888, \n                    \"sender\": true, \n                    \"snd_cwnd\": 1448, \n                    \"snd_wnd\": -1, \n                    \"socket\": 5, \n                    \"start\": 48.001046\n                }\n            ], \n            \"sum\": {\n                \"bits_per_second\": 0, \n                \"bytes\": 0, \n                \"end\": 49.001042, \n                \"omitted\": false, \n                \"retransmits\": 1, \n                \"seconds\": 0.9999960064888, \n                \"sender\": true, \n                \"start\": 48.001046\n            }\n        }, \n        {\n            \"streams\": [\n                {\n                    \"bits_per_second\": 0, \n                    \"bytes\": 0, \n                    \"end\": 50.001044, \n                    \"omitted\": false, \n                    \"pmtu\": 1500, \n                    \"retransmits\": 1, \n                    \"rtt\": 28120, \n                    \"rttvar\": 7418, \n                    \"seconds\": 1.0000020265579224, \n                    \"sender\": true, \n                    \"snd_cwnd\": 1448, \n                    \"snd_wnd\": -1, \n                    \"socket\": 5, \n                    \"start\": 49.001042\n                }\n            ], \n            \"sum\": {\n                \"bits_per_second\": 0, \n                \"bytes\": 0, \n                \"end\": 50.001044, \n                \"omitted\": false, \n                \"retransmits\": 1, \n                \"seconds\": 1.0000020265579224, \n                \"sender\": true, \n                \"start\": 49.001042\n            }\n        }, \n        {\n            \"streams\": [\n                {\n                    \"bits_per_second\": 0, \n                    \"bytes\": 0, \n                    \"end\": 51.001049, \n                    \"omitted\": false, \n                    \"pmtu\": 1500, \n                    \"retransmits\": 1, \n                    \"rtt\": 28120, \n                    \"rttvar\": 7418, \n                    \"seconds\": 1.0000050067901611, \n                    \"sender\": true, \n                    \"snd_cwnd\": 1448, \n                    \"snd_wnd\": -1, \n                    \"socket\": 5, \n                    \"start\": 50.001044\n                }\n            ], \n            \"sum\": {\n                \"bits_per_second\": 0, \n                \"bytes\": 0, \n                \"end\": 51.001049, \n                \"omitted\": false, \n                \"retransmits\": 1, \n                \"seconds\": 1.0000050067901611, \n                \"sender\": true, \n                \"start\": 50.001044\n            }\n        }, \n        {\n            \"streams\": [\n                {\n                    \"bits_per_second\": 0, \n                    \"bytes\": 0, \n                    \"end\": 52.000169, \n                    \"omitted\": false, \n                    \"pmtu\": 1500, \n                    \"retransmits\": 0, \n                    \"rtt\": 28120, \n                    \"rttvar\": 7418, \n                    \"seconds\": 0.999119997024536, \n                    \"sender\": true, \n                    \"snd_cwnd\": 1448, \n                    \"snd_wnd\": -1, \n                    \"socket\": 5, \n                    \"start\": 51.001049\n                }\n            ], \n            \"sum\": {\n                \"bits_per_second\": 0, \n                \"bytes\": 0, \n                \"end\": 52.000169, \n                \"omitted\": false, \n                \"retransmits\": 0, \n                \"seconds\": 0.999119997024536, \n                \"sender\": true, \n                \"start\": 51.001049\n            }\n        }, \n        {\n            \"streams\": [\n                {\n                    \"bits_per_second\": 0, \n                    \"bytes\": 0, \n                    \"end\": 53.000956, \n                    \"omitted\": false, \n                    \"pmtu\": 1500, \n                    \"retransmits\": 0, \n                    \"rtt\": 28120, \n                    \"rttvar\": 7418, \n                    \"seconds\": 1.0007870197296143, \n                    \"sender\": true, \n                    \"snd_cwnd\": 1448, \n                    \"snd_wnd\": -1, \n                    \"socket\": 5, \n                    \"start\": 52.000169\n                }\n            ], \n            \"sum\": {\n                \"bits_per_second\": 0, \n                \"bytes\": 0, \n                \"end\": 53.000956, \n                \"omitted\": false, \n                \"retransmits\": 0, \n                \"seconds\": 1.0007870197296143, \n                \"sender\": true, \n                \"start\": 52.000169\n            }\n        }, \n        {\n            \"streams\": [\n                {\n                    \"bits_per_second\": 0, \n                    \"bytes\": 0, \n                    \"end\": 54.000989, \n                    \"omitted\": false, \n                    \"pmtu\": 1500, \n                    \"retransmits\": 0, \n                    \"rtt\": 28120, \n                    \"rttvar\": 7418, \n                    \"seconds\": 1.0000330209732056, \n                    \"sender\": true, \n                    \"snd_cwnd\": 1448, \n                    \"snd_wnd\": -1, \n                    \"socket\": 5, \n                    \"start\": 53.000956\n                }\n            ], \n            \"sum\": {\n                \"bits_per_second\": 0, \n                \"bytes\": 0, \n                \"end\": 54.000989, \n                \"omitted\": false, \n                \"retransmits\": 0, \n                \"seconds\": 1.0000330209732056, \n                \"sender\": true, \n                \"start\": 53.000956\n            }\n        }, \n        {\n            \"streams\": [\n                {\n                    \"bits_per_second\": 0, \n                    \"bytes\": 0, \n                    \"end\": 55.001052, \n                    \"omitted\": false, \n                    \"pmtu\": 1500, \n                    \"retransmits\": 14, \n                    \"rtt\": 34175, \n                    \"rttvar\": 7194, \n                    \"seconds\": 1.0000629425048828, \n                    \"sender\": true, \n                    \"snd_cwnd\": 10136, \n                    \"snd_wnd\": -1, \n                    \"socket\": 5, \n                    \"start\": 54.000989\n                }\n            ], \n            \"sum\": {\n                \"bits_per_second\": 0, \n                \"bytes\": 0, \n                \"end\": 55.001052, \n                \"omitted\": false, \n                \"retransmits\": 14, \n                \"seconds\": 1.0000629425048828, \n                \"sender\": true, \n                \"start\": 54.000989\n            }\n        }, \n        {\n            \"streams\": [\n                {\n                    \"bits_per_second\": 15653191.828587677, \n                    \"bytes\": 1954800, \n                    \"end\": 56.000107, \n                    \"omitted\": false, \n                    \"pmtu\": 1500, \n                    \"retransmits\": 1, \n                    \"rtt\": 22697, \n                    \"rttvar\": 785, \n                    \"seconds\": 0.999055027961731, \n                    \"sender\": true, \n                    \"snd_cwnd\": 63712, \n                    \"snd_wnd\": -1, \n                    \"socket\": 5, \n                    \"start\": 55.001052\n                }\n            ], \n            \"sum\": {\n                \"bits_per_second\": 15653191.828587677, \n                \"bytes\": 1954800, \n                \"end\": 56.000107, \n                \"omitted\": false, \n                \"retransmits\": 1, \n                \"seconds\": 0.999055027961731, \n                \"sender\": true, \n                \"start\": 55.001052\n            }\n        }, \n        {\n            \"streams\": [\n                {\n                    \"bits_per_second\": 5211815.244583766, \n                    \"bytes\": 651600, \n                    \"end\": 57.000296, \n                    \"omitted\": false, \n                    \"pmtu\": 1500, \n                    \"retransmits\": 52, \n                    \"rtt\": 18571, \n                    \"rttvar\": 770, \n                    \"seconds\": 1.000188946723938, \n                    \"sender\": true, \n                    \"snd_cwnd\": 53576, \n                    \"snd_wnd\": -1, \n                    \"socket\": 5, \n                    \"start\": 56.000107\n                }\n            ], \n            \"sum\": {\n                \"bits_per_second\": 5211815.244583766, \n                \"bytes\": 651600, \n                \"end\": 57.000296, \n                \"omitted\": false, \n                \"retransmits\": 52, \n                \"seconds\": 1.000188946723938, \n                \"sender\": true, \n                \"start\": 56.000107\n            }\n        }, \n        {\n            \"streams\": [\n                {\n                    \"bits_per_second\": 20845551.63273082, \n                    \"bytes\": 2606400, \n                    \"end\": 58.000567, \n                    \"omitted\": false, \n                    \"pmtu\": 1500, \n                    \"retransmits\": 0, \n                    \"rtt\": 36541, \n                    \"rttvar\": 566, \n                    \"seconds\": 1.000270962715149, \n                    \"sender\": true, \n                    \"snd_cwnd\": 101360, \n                    \"snd_wnd\": -1, \n                    \"socket\": 5, \n                    \"start\": 57.000296\n                }\n            ], \n            \"sum\": {\n                \"bits_per_second\": 20845551.63273082, \n                \"bytes\": 2606400, \n                \"end\": 58.000567, \n                \"omitted\": false, \n                \"retransmits\": 0, \n                \"seconds\": 1.000270962715149, \n                \"sender\": true, \n                \"start\": 57.000296\n            }\n        }, \n        {\n            \"streams\": [\n                {\n                    \"bits_per_second\": 26075995.705059268, \n                    \"bytes\": 3258000, \n                    \"end\": 59.000107, \n                    \"omitted\": false, \n                    \"pmtu\": 1500, \n                    \"retransmits\": 0, \n                    \"rtt\": 48164, \n                    \"rttvar\": 783, \n                    \"seconds\": 0.9995399713516235, \n                    \"sender\": true, \n                    \"snd_cwnd\": 133216, \n                    \"snd_wnd\": -1, \n                    \"socket\": 5, \n                    \"start\": 58.000567\n                }\n            ], \n            \"sum\": {\n                \"bits_per_second\": 26075995.705059268, \n                \"bytes\": 3258000, \n                \"end\": 59.000107, \n                \"omitted\": false, \n                \"retransmits\": 0, \n                \"seconds\": 0.9995399713516235, \n                \"sender\": true, \n                \"start\": 58.000567\n            }\n        }, \n        {\n            \"streams\": [\n                {\n                    \"bits_per_second\": 0, \n                    \"bytes\": 0, \n                    \"end\": 60.000172, \n                    \"omitted\": false, \n                    \"pmtu\": 1500, \n                    \"retransmits\": 1, \n                    \"rtt\": 55676, \n                    \"rttvar\": 9794, \n                    \"seconds\": 1.0000649690628052, \n                    \"sender\": true, \n                    \"snd_cwnd\": 1448, \n                    \"snd_wnd\": -1, \n                    \"socket\": 5, \n                    \"start\": 59.000107\n                }\n            ], \n            \"sum\": {\n                \"bits_per_second\": 0, \n                \"bytes\": 0, \n                \"end\": 60.000172, \n                \"omitted\": false, \n                \"retransmits\": 1, \n                \"seconds\": 1.0000649690628052, \n                \"sender\": true, \n                \"start\": 59.000107\n            }\n        }\n    ], \n    \"start\": {\n        \"connected\": [\n            {\n                \"local_host\": \"172.16.0.2\", \n                \"local_port\": 41663, \n                \"remote_host\": \"172.16.0.1\", \n                \"remote_port\": 5201, \n                \"socket\": 5\n            }\n        ], \n        \"connecting_to\": {\n            \"host\": \"172.16.0.1\", \n            \"port\": 5201\n        }, \n        \"cookie\": \"jmol27fivntj5lxsedetlza6hmuvllack7es\", \n        \"fq_rate\": 0, \n        \"rcvbuf_actual\": 87380, \n        \"sndbuf_actual\": 65536, \n        \"sock_bufsize\": 0, \n        \"system_info\": \"REDACTED\", \n        \"target_bitrate\": 0, \n        \"tcp_mss_default\": 1448, \n        \"test_start\": {\n            \"bidir\": 0, \n            \"blksize\": 131072, \n            \"blocks\": 0, \n            \"bytes\": 0, \n            \"duration\": 60, \n            \"fqrate\": 0, \n            \"num_streams\": 1, \n            \"omit\": 0, \n            \"protocol\": \"TCP\", \n            \"reverse\": 0, \n            \"target_bitrate\": 0, \n            \"tos\": 0\n        }, \n        \"timestamp\": {\n            \"time\": \"Wed, 16 Oct 2024 02:45:09 GMT\", \n            \"timesecs\": 1729046709\n        }, \n        \"version\": \"iperf 3.14\"\n    }\n}\nParticipant 1:\n/usr/bin/iperf3 --use-pkcs1-padding -s -1 --idle-timeout 60 --json -p 5201 -B 172.16.0.1 --authorized-users-path /var/pscheduler-server/runner/tmp/tmp9gy1jfr9/tmpio2q4i7t/credentials --rsa-private-key-path /var/pscheduler-server/runner/tmp/tmp9gy1jfr9/tmpio2q4i7t/private-key\n\n{\n    \"end\": {\n        \"cpu_utilization_percent\": {\n            \"host_system\": 0.398405466385812, \n            \"host_total\": 0.451342676599775, \n            \"host_user\": 0.05294039814628748, \n            \"remote_system\": 0, \n            \"remote_total\": 0, \n            \"remote_user\": 0\n        }, \n        \"receiver_tcp_congestion\": \"htcp\", \n        \"streams\": [\n            {\n                \"receiver\": {\n                    \"bits_per_second\": 1602200.5940591472, \n                    \"bytes\": 12564560, \n                    \"end\": 62.736514, \n                    \"seconds\": 62.736514, \n                    \"sender\": false, \n                    \"socket\": 5, \n                    \"start\": 0\n                }, \n                \"sender\": {\n                    \"bits_per_second\": 0, \n                    \"bytes\": 0, \n                    \"end\": 62.736514, \n                    \"seconds\": 62.736514, \n                    \"sender\": false, \n                    \"socket\": 5, \n                    \"start\": 0\n                }\n            }\n        ], \n        \"sum_received\": {\n            \"bits_per_second\": 1602200.5940591472, \n            \"bytes\": 12564560, \n            \"end\": 62.736514, \n            \"seconds\": 62.736514, \n            \"sender\": false, \n            \"start\": 0\n        }, \n        \"sum_sent\": {\n            \"bits_per_second\": 0, \n            \"bytes\": 0, \n            \"end\": 62.736514, \n            \"seconds\": 62.736514, \n            \"sender\": false, \n            \"start\": 0\n        }\n    }, \n    \"intervals\": [\n        {\n            \"streams\": [\n                {\n                    \"bits_per_second\": 2094812.1136321148, \n                    \"bytes\": 262144, \n                    \"end\": 1.001117, \n                    \"omitted\": false, \n                    \"seconds\": 1.0011169910430908, \n                    \"sender\": false, \n                    \"socket\": 5, \n                    \"start\": 0\n                }\n            ], \n            \"sum\": {\n                \"bits_per_second\": 2094812.1136321148, \n                \"bytes\": 262144, \n                \"end\": 1.001117, \n                \"omitted\": false, \n                \"seconds\": 1.0011169910430908, \n                \"sender\": false, \n                \"start\": 0\n            }\n        }, \n        {\n            \"streams\": [\n                {\n                    \"bits_per_second\": 0, \n                    \"bytes\": 0, \n                    \"end\": 2.000207, \n                    \"omitted\": false, \n                    \"seconds\": 0.999090015888214, \n                    \"sender\": false, \n                    \"socket\": 5, \n                    \"start\": 1.001117\n                }\n            ], \n            \"sum\": {\n                \"bits_per_second\": 0, \n                \"bytes\": 0, \n                \"end\": 2.000207, \n                \"omitted\": false, \n                \"seconds\": 0.999090015888214, \n                \"sender\": false, \n                \"start\": 1.001117\n            }\n        }, \n        {\n            \"streams\": [\n                {\n                    \"bits_per_second\": 0, \n                    \"bytes\": 0, \n                    \"end\": 3.001132, \n                    \"omitted\": false, \n                    \"seconds\": 1.0009249448776245, \n                    \"sender\": false, \n                    \"socket\": 5, \n                    \"start\": 2.000207\n                }\n            ], \n            \"sum\": {\n                \"bits_per_second\": 0, \n                \"bytes\": 0, \n                \"end\": 3.001132, \n                \"omitted\": false, \n                \"seconds\": 1.0009249448776245, \n                \"sender\": false, \n                \"start\": 2.000207\n            }\n        }, \n        {\n            \"streams\": [\n                {\n                    \"bits_per_second\": 0, \n                    \"bytes\": 0, \n                    \"end\": 4.001105, \n                    \"omitted\": false, \n                    \"seconds\": 0.9999729990959167, \n                    \"sender\": false, \n                    \"socket\": 5, \n                    \"start\": 3.001132\n                }\n            ], \n            \"sum\": {\n                \"bits_per_second\": 0, \n                \"bytes\": 0, \n                \"end\": 4.001105, \n                \"omitted\": false, \n                \"seconds\": 0.9999729990959167, \n                \"sender\": false, \n                \"start\": 3.001132\n            }\n        }, \n        {\n            \"streams\": [\n                {\n                    \"bits_per_second\": 0, \n                    \"bytes\": 0, \n                    \"end\": 5.00111, \n                    \"omitted\": false, \n                    \"seconds\": 1.0000050067901611, \n                    \"sender\": false, \n                    \"socket\": 5, \n                    \"start\": 4.001105\n                }\n            ], \n            \"sum\": {\n                \"bits_per_second\": 0, \n                \"bytes\": 0, \n                \"end\": 5.00111, \n                \"omitted\": false, \n                \"seconds\": 1.0000050067901611, \n                \"sender\": false, \n                \"start\": 4.001105\n            }\n        }, \n        {\n            \"streams\": [\n                {\n                    \"bits_per_second\": 2097078.5025759032, \n                    \"bytes\": 262144, \n                    \"end\": 6.001145, \n                    \"omitted\": false, \n                    \"seconds\": 1.000035047531128, \n                    \"sender\": false, \n                    \"socket\": 5, \n                    \"start\": 5.00111\n                }\n            ], \n            \"sum\": {\n                \"bits_per_second\": 2097078.5025759032, \n                \"bytes\": 262144, \n                \"end\": 6.001145, \n                \"omitted\": false, \n                \"seconds\": 1.000035047531128, \n                \"sender\": false, \n                \"start\": 5.00111\n            }\n        }, \n        {\n            \"streams\": [\n                {\n                    \"bits_per_second\": 0, \n                    \"bytes\": 0, \n                    \"end\": 7.000137, \n                    \"omitted\": false, \n                    \"seconds\": 0.9989920258522034, \n                    \"sender\": false, \n                    \"socket\": 5, \n                    \"start\": 6.001145\n                }\n            ], \n            \"sum\": {\n                \"bits_per_second\": 0, \n                \"bytes\": 0, \n                \"end\": 7.000137, \n                \"omitted\": false, \n                \"seconds\": 0.9989920258522034, \n                \"sender\": false, \n                \"start\": 6.001145\n            }\n        }, \n        {\n            \"streams\": [\n                {\n                    \"bits_per_second\": 0, \n                    \"bytes\": 0, \n                    \"end\": 8.001126, \n                    \"omitted\": false, \n                    \"seconds\": 1.0009889602661133, \n                    \"sender\": false, \n                    \"socket\": 5, \n                    \"start\": 7.000137\n                }\n            ], \n            \"sum\": {\n                \"bits_per_second\": 0, \n                \"bytes\": 0, \n                \"end\": 8.001126, \n                \"omitted\": false, \n                \"seconds\": 1.0009889602661133, \n                \"sender\": false, \n                \"start\": 7.000137\n            }\n        }, \n        {\n            \"streams\": [\n                {\n                    \"bits_per_second\": 4194304, \n                    \"bytes\": 524288, \n                    \"end\": 9.001126, \n                    \"omitted\": false, \n                    \"seconds\": 1, \n                    \"sender\": false, \n                    \"socket\": 5, \n                    \"start\": 8.001126\n                }\n            ], \n            \"sum\": {\n                \"bits_per_second\": 4194304, \n                \"bytes\": 524288, \n                \"end\": 9.001126, \n                \"omitted\": false, \n                \"seconds\": 1, \n                \"sender\": false, \n                \"start\": 8.001126\n            }\n        }, \n        {\n            \"streams\": [\n                {\n                    \"bits_per_second\": 0, \n                    \"bytes\": 0, \n                    \"end\": 10.00111, \n                    \"omitted\": false, \n                    \"seconds\": 0.9999840259552002, \n                    \"sender\": false, \n                    \"socket\": 5, \n                    \"start\": 9.001126\n                }\n            ], \n            \"sum\": {\n                \"bits_per_second\": 0, \n                \"bytes\": 0, \n                \"end\": 10.00111, \n                \"omitted\": false, \n                \"seconds\": 0.9999840259552002, \n                \"sender\": false, \n                \"start\": 9.001126\n            }\n        }, \n        {\n            \"streams\": [\n                {\n                    \"bits_per_second\": 0, \n                    \"bytes\": 0, \n                    \"end\": 11.001148, \n                    \"omitted\": false, \n                    \"seconds\": 1.0000380277633667, \n                    \"sender\": false, \n                    \"socket\": 5, \n                    \"start\": 10.00111\n                }\n            ], \n            \"sum\": {\n                \"bits_per_second\": 0, \n                \"bytes\": 0, \n                \"end\": 11.001148, \n                \"omitted\": false, \n                \"seconds\": 1.0000380277633667, \n                \"sender\": false, \n                \"start\": 10.00111\n            }\n        }, \n        {\n            \"streams\": [\n                {\n                    \"bits_per_second\": 0, \n                    \"bytes\": 0, \n                    \"end\": 12.001138, \n                    \"omitted\": false, \n                    \"seconds\": 0.9999899864196777, \n                    \"sender\": false, \n                    \"socket\": 5, \n                    \"start\": 11.001148\n                }\n            ], \n            \"sum\": {\n                \"bits_per_second\": 0, \n                \"bytes\": 0, \n                \"end\": 12.001138, \n                \"omitted\": false, \n                \"seconds\": 0.9999899864196777, \n                \"sender\": false, \n                \"start\": 11.001148\n            }\n        }, \n        {\n            \"streams\": [\n                {\n                    \"bits_per_second\": 0, \n                    \"bytes\": 0, \n                    \"end\": 13.000107, \n                    \"omitted\": false, \n                    \"seconds\": 0.99896901845932, \n                    \"sender\": false, \n                    \"socket\": 5, \n                    \"start\": 12.001138\n                }\n            ], \n            \"sum\": {\n                \"bits_per_second\": 0, \n                \"bytes\": 0, \n                \"end\": 13.000107, \n                \"omitted\": false, \n                \"seconds\": 0.99896901845932, \n                \"sender\": false, \n                \"start\": 12.001138\n            }\n        }, \n        {\n            \"streams\": [\n                {\n                    \"bits_per_second\": 0, \n                    \"bytes\": 0, \n                    \"end\": 14.001118, \n                    \"omitted\": false, \n                    \"seconds\": 1.00101101398468, \n                    \"sender\": false, \n                    \"socket\": 5, \n                    \"start\": 13.000107\n                }\n            ], \n            \"sum\": {\n                \"bits_per_second\": 0, \n                \"bytes\": 0, \n                \"end\": 14.001118, \n                \"omitted\": false, \n                \"seconds\": 1.00101101398468, \n                \"sender\": false, \n                \"start\": 13.000107\n            }\n        }, \n        {\n            \"streams\": [\n                {\n                    \"bits_per_second\": 0, \n                    \"bytes\": 0, \n                    \"end\": 15.001131, \n                    \"omitted\": false, \n                    \"seconds\": 1.000012993812561, \n                    \"sender\": false, \n                    \"socket\": 5, \n                    \"start\": 14.001118\n                }\n            ], \n            \"sum\": {\n                \"bits_per_second\": 0, \n                \"bytes\": 0, \n                \"end\": 15.001131, \n                \"omitted\": false, \n                \"seconds\": 1.000012993812561, \n                \"sender\": false, \n                \"start\": 14.001118\n            }\n        }, \n        {\n            \"streams\": [\n                {\n                    \"bits_per_second\": 0, \n                    \"bytes\": 0, \n                    \"end\": 16.001158, \n                    \"omitted\": false, \n                    \"seconds\": 1.0000269412994385, \n                    \"sender\": false, \n                    \"socket\": 5, \n                    \"start\": 15.001131\n                }\n            ], \n            \"sum\": {\n                \"bits_per_second\": 0, \n                \"bytes\": 0, \n                \"end\": 16.001158, \n                \"omitted\": false, \n                \"seconds\": 1.0000269412994385, \n                \"sender\": false, \n                \"start\": 15.001131\n            }\n        }, \n        {\n            \"streams\": [\n                {\n                    \"bits_per_second\": 0, \n                    \"bytes\": 0, \n                    \"end\": 17.00111, \n                    \"omitted\": false, \n                    \"seconds\": 0.9999520182609558, \n                    \"sender\": false, \n                    \"socket\": 5, \n                    \"start\": 16.001158\n                }\n            ], \n            \"sum\": {\n                \"bits_per_second\": 0, \n                \"bytes\": 0, \n                \"end\": 17.00111, \n                \"omitted\": false, \n                \"seconds\": 0.9999520182609558, \n                \"sender\": false, \n                \"start\": 16.001158\n            }\n        }, \n        {\n            \"streams\": [\n                {\n                    \"bits_per_second\": 0, \n                    \"bytes\": 0, \n                    \"end\": 18.001095, \n                    \"omitted\": false, \n                    \"seconds\": 0.9999849796295166, \n                    \"sender\": false, \n                    \"socket\": 5, \n                    \"start\": 17.00111\n                }\n            ], \n            \"sum\": {\n                \"bits_per_second\": 0, \n                \"bytes\": 0, \n                \"end\": 18.001095, \n                \"omitted\": false, \n                \"seconds\": 0.9999849796295166, \n                \"sender\": false, \n                \"start\": 17.00111\n            }\n        }, \n        {\n            \"streams\": [\n                {\n                    \"bits_per_second\": 901768.1161848034, \n                    \"bytes\": 112720, \n                    \"end\": 19.001086, \n                    \"omitted\": false, \n                    \"seconds\": 0.999990999698639, \n                    \"sender\": false, \n                    \"socket\": 5, \n                    \"start\": 18.001095\n                }\n            ], \n            \"sum\": {\n                \"bits_per_second\": 901768.1161848034, \n                \"bytes\": 112720, \n                \"end\": 19.001086, \n                \"omitted\": false, \n                \"seconds\": 0.999990999698639, \n                \"sender\": false, \n                \"start\": 18.001095\n            }\n        }, \n        {\n            \"streams\": [\n                {\n                    \"bits_per_second\": 0, \n                    \"bytes\": 0, \n                    \"end\": 20.000078, \n                    \"omitted\": false, \n                    \"seconds\": 0.9989920258522034, \n                    \"sender\": false, \n                    \"socket\": 5, \n                    \"start\": 19.001086\n                }\n            ], \n            \"sum\": {\n                \"bits_per_second\": 0, \n                \"bytes\": 0, \n                \"end\": 20.000078, \n                \"omitted\": false, \n                \"seconds\": 0.9989920258522034, \n                \"sender\": false, \n                \"start\": 19.001086\n            }\n        }, \n        {\n            \"streams\": [\n                {\n                    \"bits_per_second\": 0, \n                    \"bytes\": 0, \n                    \"end\": 21.001126, \n                    \"omitted\": false, \n                    \"seconds\": 1.001047968864441, \n                    \"sender\": false, \n                    \"socket\": 5, \n                    \"start\": 20.000078\n                }\n            ], \n            \"sum\": {\n                \"bits_per_second\": 0, \n                \"bytes\": 0, \n                \"end\": 21.001126, \n                \"omitted\": false, \n                \"seconds\": 1.001047968864441, \n                \"sender\": false, \n                \"start\": 20.000078\n            }\n        }, \n        {\n            \"streams\": [\n                {\n                    \"bits_per_second\": 2097256.8802448823, \n                    \"bytes\": 262144, \n                    \"end\": 22.001076, \n                    \"omitted\": false, \n                    \"seconds\": 0.9999499917030334, \n                    \"sender\": false, \n                    \"socket\": 5, \n                    \"start\": 21.001126\n                }\n            ], \n            \"sum\": {\n                \"bits_per_second\": 2097256.8802448823, \n                \"bytes\": 262144, \n                \"end\": 22.001076, \n                \"omitted\": false, \n                \"seconds\": 0.9999499917030334, \n                \"sender\": false, \n                \"start\": 21.001126\n            }\n        }, \n        {\n            \"streams\": [\n                {\n                    \"bits_per_second\": 0, \n                    \"bytes\": 0, \n                    \"end\": 23.001103, \n                    \"omitted\": false, \n                    \"seconds\": 1.0000269412994385, \n                    \"sender\": false, \n                    \"socket\": 5, \n                    \"start\": 22.001076\n                }\n            ], \n            \"sum\": {\n                \"bits_per_second\": 0, \n                \"bytes\": 0, \n                \"end\": 23.001103, \n                \"omitted\": false, \n                \"seconds\": 1.0000269412994385, \n                \"sender\": false, \n                \"start\": 22.001076\n            }\n        }, \n        {\n            \"streams\": [\n                {\n                    \"bits_per_second\": 0, \n                    \"bytes\": 0, \n                    \"end\": 24.001103, \n                    \"omitted\": false, \n                    \"seconds\": 1, \n                    \"sender\": false, \n                    \"socket\": 5, \n                    \"start\": 23.001103\n                }\n            ], \n            \"sum\": {\n                \"bits_per_second\": 0, \n                \"bytes\": 0, \n                \"end\": 24.001103, \n                \"omitted\": false, \n                \"seconds\": 1, \n                \"sender\": false, \n                \"start\": 23.001103\n            }\n        }, \n        {\n            \"streams\": [\n                {\n                    \"bits_per_second\": 0, \n                    \"bytes\": 0, \n                    \"end\": 25.000146, \n                    \"omitted\": false, \n                    \"seconds\": 0.9990429878234863, \n                    \"sender\": false, \n                    \"socket\": 5, \n                    \"start\": 24.001103\n                }\n            ], \n            \"sum\": {\n                \"bits_per_second\": 0, \n                \"bytes\": 0, \n                \"end\": 25.000146, \n                \"omitted\": false, \n                \"seconds\": 0.9990429878234863, \n                \"sender\": false, \n                \"start\": 24.001103\n            }\n        }, \n        {\n            \"streams\": [\n                {\n                    \"bits_per_second\": 2095048.611761063, \n                    \"bytes\": 262144, \n                    \"end\": 26.00115, \n                    \"omitted\": false, \n                    \"seconds\": 1.0010039806365967, \n                    \"sender\": false, \n                    \"socket\": 5, \n                    \"start\": 25.000146\n                }\n            ], \n            \"sum\": {\n                \"bits_per_second\": 2095048.611761063, \n                \"bytes\": 262144, \n                \"end\": 26.00115, \n                \"omitted\": false, \n                \"seconds\": 1.0010039806365967, \n                \"sender\": false, \n                \"start\": 25.000146\n            }\n        }, \n        {\n            \"streams\": [\n                {\n                    \"bits_per_second\": 0, \n                    \"bytes\": 0, \n                    \"end\": 27.001103, \n                    \"omitted\": false, \n                    \"seconds\": 0.9999529719352722, \n                    \"sender\": false, \n                    \"socket\": 5, \n                    \"start\": 26.00115\n                }\n            ], \n            \"sum\": {\n                \"bits_per_second\": 0, \n                \"bytes\": 0, \n                \"end\": 27.001103, \n                \"omitted\": false, \n                \"seconds\": 0.9999529719352722, \n                \"sender\": false, \n                \"start\": 26.00115\n            }\n        }, \n        {\n            \"streams\": [\n                {\n                    \"bits_per_second\": 0, \n                    \"bytes\": 0, \n                    \"end\": 28.001204, \n                    \"omitted\": false, \n                    \"seconds\": 1.0001009702682495, \n                    \"sender\": false, \n                    \"socket\": 5, \n                    \"start\": 27.001103\n                }\n            ], \n            \"sum\": {\n                \"bits_per_second\": 0, \n                \"bytes\": 0, \n                \"end\": 28.001204, \n                \"omitted\": false, \n                \"seconds\": 1.0001009702682495, \n                \"sender\": false, \n                \"start\": 27.001103\n            }\n        }, \n        {\n            \"streams\": [\n                {\n                    \"bits_per_second\": 0, \n                    \"bytes\": 0, \n                    \"end\": 29.00108, \n                    \"omitted\": false, \n                    \"seconds\": 0.9998760223388672, \n                    \"sender\": false, \n                    \"socket\": 5, \n                    \"start\": 28.001204\n                }\n            ], \n            \"sum\": {\n                \"bits_per_second\": 0, \n                \"bytes\": 0, \n                \"end\": 29.00108, \n                \"omitted\": false, \n                \"seconds\": 0.9998760223388672, \n                \"sender\": false, \n                \"start\": 28.001204\n            }\n        }, \n        {\n            \"streams\": [\n                {\n                    \"bits_per_second\": 0, \n                    \"bytes\": 0, \n                    \"end\": 30.001117, \n                    \"omitted\": false, \n                    \"seconds\": 1.0000369548797607, \n                    \"sender\": false, \n                    \"socket\": 5, \n                    \"start\": 29.00108\n                }\n            ], \n            \"sum\": {\n                \"bits_per_second\": 0, \n                \"bytes\": 0, \n                \"end\": 30.001117, \n                \"omitted\": false, \n                \"seconds\": 1.0000369548797607, \n                \"sender\": false, \n                \"start\": 29.00108\n            }\n        }, \n        {\n            \"streams\": [\n                {\n                    \"bits_per_second\": 0, \n                    \"bytes\": 0, \n                    \"end\": 31.000169, \n                    \"omitted\": false, \n                    \"seconds\": 0.9990519881248474, \n                    \"sender\": false, \n                    \"socket\": 5, \n                    \"start\": 30.001117\n                }\n            ], \n            \"sum\": {\n                \"bits_per_second\": 0, \n                \"bytes\": 0, \n                \"end\": 31.000169, \n                \"omitted\": false, \n                \"seconds\": 0.9990519881248474, \n                \"sender\": false, \n                \"start\": 30.001117\n            }\n        }, \n        {\n            \"streams\": [\n                {\n                    \"bits_per_second\": 0, \n                    \"bytes\": 0, \n                    \"end\": 32.001097, \n                    \"omitted\": false, \n                    \"seconds\": 1.0009280443191528, \n                    \"sender\": false, \n                    \"socket\": 5, \n                    \"start\": 31.000169\n                }\n            ], \n            \"sum\": {\n                \"bits_per_second\": 0, \n                \"bytes\": 0, \n                \"end\": 32.001097, \n                \"omitted\": false, \n                \"seconds\": 1.0009280443191528, \n                \"sender\": false, \n                \"start\": 31.000169\n            }\n        }, \n        {\n            \"streams\": [\n                {\n                    \"bits_per_second\": 0, \n                    \"bytes\": 0, \n                    \"end\": 33.001152, \n                    \"omitted\": false, \n                    \"seconds\": 1.000054955482483, \n                    \"sender\": false, \n                    \"socket\": 5, \n                    \"start\": 32.001097\n                }\n            ], \n            \"sum\": {\n                \"bits_per_second\": 0, \n                \"bytes\": 0, \n                \"end\": 33.001152, \n                \"omitted\": false, \n                \"seconds\": 1.000054955482483, \n                \"sender\": false, \n                \"start\": 32.001097\n            }\n        }, \n        {\n            \"streams\": [\n                {\n                    \"bits_per_second\": 2097187.6256051837, \n                    \"bytes\": 262144, \n                    \"end\": 34.001135, \n                    \"omitted\": false, \n                    \"seconds\": 0.999983012676239, \n                    \"sender\": false, \n                    \"socket\": 5, \n                    \"start\": 33.001152\n                }\n            ], \n            \"sum\": {\n                \"bits_per_second\": 2097187.6256051837, \n                \"bytes\": 262144, \n                \"end\": 34.001135, \n                \"omitted\": false, \n                \"seconds\": 0.999983012676239, \n                \"sender\": false, \n                \"start\": 33.001152\n            }\n        }, \n        {\n            \"streams\": [\n                {\n                    \"bits_per_second\": 0, \n                    \"bytes\": 0, \n                    \"end\": 35.0012, \n                    \"omitted\": false, \n                    \"seconds\": 1.0000649690628052, \n                    \"sender\": false, \n                    \"socket\": 5, \n                    \"start\": 34.001135\n                }\n            ], \n            \"sum\": {\n                \"bits_per_second\": 0, \n                \"bytes\": 0, \n                \"end\": 35.0012, \n                \"omitted\": false, \n                \"seconds\": 1.0000649690628052, \n                \"sender\": false, \n                \"start\": 34.001135\n            }\n        }, \n        {\n            \"streams\": [\n                {\n                    \"bits_per_second\": 0, \n                    \"bytes\": 0, \n                    \"end\": 36.00125, \n                    \"omitted\": false, \n                    \"seconds\": 1.0000499486923218, \n                    \"sender\": false, \n                    \"socket\": 5, \n                    \"start\": 35.0012\n                }\n            ], \n            \"sum\": {\n                \"bits_per_second\": 0, \n                \"bytes\": 0, \n                \"end\": 36.00125, \n                \"omitted\": false, \n                \"seconds\": 1.0000499486923218, \n                \"sender\": false, \n                \"start\": 35.0012\n            }\n        }, \n        {\n            \"streams\": [\n                {\n                    \"bits_per_second\": 1048692.387917179, \n                    \"bytes\": 131072, \n                    \"end\": 37.001139, \n                    \"omitted\": false, \n                    \"seconds\": 0.9998890161514282, \n                    \"sender\": false, \n                    \"socket\": 5, \n                    \"start\": 36.00125\n                }\n            ], \n            \"sum\": {\n                \"bits_per_second\": 1048692.387917179, \n                \"bytes\": 131072, \n                \"end\": 37.001139, \n                \"omitted\": false, \n                \"seconds\": 0.9998890161514282, \n                \"sender\": false, \n                \"start\": 36.00125\n            }\n        }, \n        {\n            \"streams\": [\n                {\n                    \"bits_per_second\": 1048582.312538002, \n                    \"bytes\": 131072, \n                    \"end\": 38.001133, \n                    \"omitted\": false, \n                    \"seconds\": 0.9999939799308777, \n                    \"sender\": false, \n                    \"socket\": 5, \n                    \"start\": 37.001139\n                }\n            ], \n            \"sum\": {\n                \"bits_per_second\": 1048582.312538002, \n                \"bytes\": 131072, \n                \"end\": 38.001133, \n                \"omitted\": false, \n                \"seconds\": 0.9999939799308777, \n                \"sender\": false, \n                \"start\": 37.001139\n            }\n        }, \n        {\n            \"streams\": [\n                {\n                    \"bits_per_second\": 8388776.00336463, \n                    \"bytes\": 1048576, \n                    \"end\": 39.001113, \n                    \"omitted\": false, \n                    \"seconds\": 0.9999799728393555, \n                    \"sender\": false, \n                    \"socket\": 5, \n                    \"start\": 38.001133\n                }\n            ], \n            \"sum\": {\n                \"bits_per_second\": 8388776.00336463, \n                \"bytes\": 1048576, \n                \"end\": 39.001113, \n                \"omitted\": false, \n                \"seconds\": 0.9999799728393555, \n                \"sender\": false, \n                \"start\": 38.001133\n            }\n        }, \n        {\n            \"streams\": [\n                {\n                    \"bits_per_second\": 0, \n                    \"bytes\": 0, \n                    \"end\": 40.001209, \n                    \"omitted\": false, \n                    \"seconds\": 1.0000959634780884, \n                    \"sender\": false, \n                    \"socket\": 5, \n                    \"start\": 39.001113\n                }\n            ], \n            \"sum\": {\n                \"bits_per_second\": 0, \n                \"bytes\": 0, \n                \"end\": 40.001209, \n                \"omitted\": false, \n                \"seconds\": 1.0000959634780884, \n                \"sender\": false, \n                \"start\": 39.001113\n            }\n        }, \n        {\n            \"streams\": [\n                {\n                    \"bits_per_second\": 0, \n                    \"bytes\": 0, \n                    \"end\": 41.001045, \n                    \"omitted\": false, \n                    \"seconds\": 0.999836027622223, \n                    \"sender\": false, \n                    \"socket\": 5, \n                    \"start\": 40.001209\n                }\n            ], \n            \"sum\": {\n                \"bits_per_second\": 0, \n                \"bytes\": 0, \n                \"end\": 41.001045, \n                \"omitted\": false, \n                \"seconds\": 0.999836027622223, \n                \"sender\": false, \n                \"start\": 40.001209\n            }\n        }, \n        {\n            \"streams\": [\n                {\n                    \"bits_per_second\": 0, \n                    \"bytes\": 0, \n                    \"end\": 42.001093, \n                    \"omitted\": false, \n                    \"seconds\": 1.000048041343689, \n                    \"sender\": false, \n                    \"socket\": 5, \n                    \"start\": 41.001045\n                }\n            ], \n            \"sum\": {\n                \"bits_per_second\": 0, \n                \"bytes\": 0, \n                \"end\": 42.001093, \n                \"omitted\": false, \n                \"seconds\": 1.000048041343689, \n                \"sender\": false, \n                \"start\": 41.001045\n            }\n        }, \n        {\n            \"streams\": [\n                {\n                    \"bits_per_second\": 3145567.5081885452, \n                    \"bytes\": 393216, \n                    \"end\": 43.001144, \n                    \"omitted\": false, \n                    \"seconds\": 1.0000510215759277, \n                    \"sender\": false, \n                    \"socket\": 5, \n                    \"start\": 42.001093\n                }\n            ], \n            \"sum\": {\n                \"bits_per_second\": 3145567.5081885452, \n                \"bytes\": 393216, \n                \"end\": 43.001144, \n                \"omitted\": false, \n                \"seconds\": 1.0000510215759277, \n                \"sender\": false, \n                \"start\": 42.001093\n            }\n        }, \n        {\n            \"streams\": [\n                {\n                    \"bits_per_second\": 0, \n                    \"bytes\": 0, \n                    \"end\": 44.001125, \n                    \"omitted\": false, \n                    \"seconds\": 0.9999809861183167, \n                    \"sender\": false, \n                    \"socket\": 5, \n                    \"start\": 43.001144\n                }\n            ], \n            \"sum\": {\n                \"bits_per_second\": 0, \n                \"bytes\": 0, \n                \"end\": 44.001125, \n                \"omitted\": false, \n                \"seconds\": 0.9999809861183167, \n                \"sender\": false, \n                \"start\": 43.001144\n            }\n        }, \n        {\n            \"streams\": [\n                {\n                    \"bits_per_second\": 0, \n                    \"bytes\": 0, \n                    \"end\": 45.001111, \n                    \"omitted\": false, \n                    \"seconds\": 0.9999859929084778, \n                    \"sender\": false, \n                    \"socket\": 5, \n                    \"start\": 44.001125\n                }\n            ], \n            \"sum\": {\n                \"bits_per_second\": 0, \n                \"bytes\": 0, \n                \"end\": 45.001111, \n                \"omitted\": false, \n                \"seconds\": 0.9999859929084778, \n                \"sender\": false, \n                \"start\": 44.001125\n            }\n        }, \n        {\n            \"streams\": [\n                {\n                    \"bits_per_second\": 0, \n                    \"bytes\": 0, \n                    \"end\": 46.001122, \n                    \"omitted\": false, \n                    \"seconds\": 1.0000109672546387, \n                    \"sender\": false, \n                    \"socket\": 5, \n                    \"start\": 45.001111\n                }\n            ], \n            \"sum\": {\n                \"bits_per_second\": 0, \n                \"bytes\": 0, \n                \"end\": 46.001122, \n                \"omitted\": false, \n                \"seconds\": 1.0000109672546387, \n                \"sender\": false, \n                \"start\": 45.001111\n            }\n        }, \n        {\n            \"streams\": [\n                {\n                    \"bits_per_second\": 1048586.5001051438, \n                    \"bytes\": 131072, \n                    \"end\": 47.001112, \n                    \"omitted\": false, \n                    \"seconds\": 0.9999899864196777, \n                    \"sender\": false, \n                    \"socket\": 5, \n                    \"start\": 46.001122\n                }\n            ], \n            \"sum\": {\n                \"bits_per_second\": 1048586.5001051438, \n                \"bytes\": 131072, \n                \"end\": 47.001112, \n                \"omitted\": false, \n                \"seconds\": 0.9999899864196777, \n                \"sender\": false, \n                \"start\": 46.001122\n            }\n        }, \n        {\n            \"streams\": [\n                {\n                    \"bits_per_second\": 1048569.7500372527, \n                    \"bytes\": 131072, \n                    \"end\": 48.001118, \n                    \"omitted\": false, \n                    \"seconds\": 1.0000059604644775, \n                    \"sender\": false, \n                    \"socket\": 5, \n                    \"start\": 47.001112\n                }\n            ], \n            \"sum\": {\n                \"bits_per_second\": 1048569.7500372527, \n                \"bytes\": 131072, \n                \"end\": 48.001118, \n                \"omitted\": false, \n                \"seconds\": 1.0000059604644775, \n                \"sender\": false, \n                \"start\": 47.001112\n            }\n        }, \n        {\n            \"streams\": [\n                {\n                    \"bits_per_second\": 0, \n                    \"bytes\": 0, \n                    \"end\": 49.000056, \n                    \"omitted\": false, \n                    \"seconds\": 0.998938024044037, \n                    \"sender\": false, \n                    \"socket\": 5, \n                    \"start\": 48.001118\n                }\n            ], \n            \"sum\": {\n                \"bits_per_second\": 0, \n                \"bytes\": 0, \n                \"end\": 49.000056, \n                \"omitted\": false, \n                \"seconds\": 0.998938024044037, \n                \"sender\": false, \n                \"start\": 48.001118\n            }\n        }, \n        {\n            \"streams\": [\n                {\n                    \"bits_per_second\": 0, \n                    \"bytes\": 0, \n                    \"end\": 50.000142, \n                    \"omitted\": false, \n                    \"seconds\": 1.0000859498977661, \n                    \"sender\": false, \n                    \"socket\": 5, \n                    \"start\": 49.000056\n                }\n            ], \n            \"sum\": {\n                \"bits_per_second\": 0, \n                \"bytes\": 0, \n                \"end\": 50.000142, \n                \"omitted\": false, \n                \"seconds\": 1.0000859498977661, \n                \"sender\": false, \n                \"start\": 49.000056\n            }\n        }, \n        {\n            \"streams\": [\n                {\n                    \"bits_per_second\": 0, \n                    \"bytes\": 0, \n                    \"end\": 51.000077, \n                    \"omitted\": false, \n                    \"seconds\": 0.99993497133255, \n                    \"sender\": false, \n                    \"socket\": 5, \n                    \"start\": 50.000142\n                }\n            ], \n            \"sum\": {\n                \"bits_per_second\": 0, \n                \"bytes\": 0, \n                \"end\": 51.000077, \n                \"omitted\": false, \n                \"seconds\": 0.99993497133255, \n                \"sender\": false, \n                \"start\": 50.000142\n            }\n        }, \n        {\n            \"streams\": [\n                {\n                    \"bits_per_second\": 0, \n                    \"bytes\": 0, \n                    \"end\": 52.001084, \n                    \"omitted\": false, \n                    \"seconds\": 1.0010069608688354, \n                    \"sender\": false, \n                    \"socket\": 5, \n                    \"start\": 51.000077\n                }\n            ], \n            \"sum\": {\n                \"bits_per_second\": 0, \n                \"bytes\": 0, \n                \"end\": 52.001084, \n                \"omitted\": false, \n                \"seconds\": 1.0010069608688354, \n                \"sender\": false, \n                \"start\": 51.000077\n            }\n        }, \n        {\n            \"streams\": [\n                {\n                    \"bits_per_second\": 0, \n                    \"bytes\": 0, \n                    \"end\": 53.001095, \n                    \"omitted\": false, \n                    \"seconds\": 1.0000109672546387, \n                    \"sender\": false, \n                    \"socket\": 5, \n                    \"start\": 52.001084\n                }\n            ], \n            \"sum\": {\n                \"bits_per_second\": 0, \n                \"bytes\": 0, \n                \"end\": 53.001095, \n                \"omitted\": false, \n                \"seconds\": 1.0000109672546387, \n                \"sender\": false, \n                \"start\": 52.001084\n            }\n        }, \n        {\n            \"streams\": [\n                {\n                    \"bits_per_second\": 0, \n                    \"bytes\": 0, \n                    \"end\": 54.001113, \n                    \"omitted\": false, \n                    \"seconds\": 1.0000180006027222, \n                    \"sender\": false, \n                    \"socket\": 5, \n                    \"start\": 53.001095\n                }\n            ], \n            \"sum\": {\n                \"bits_per_second\": 0, \n                \"bytes\": 0, \n                \"end\": 54.001113, \n                \"omitted\": false, \n                \"seconds\": 1.0000180006027222, \n                \"sender\": false, \n                \"start\": 53.001095\n            }\n        }, \n        {\n            \"streams\": [\n                {\n                    \"bits_per_second\": 0, \n                    \"bytes\": 0, \n                    \"end\": 55.001131, \n                    \"omitted\": false, \n                    \"seconds\": 1.0000180006027222, \n                    \"sender\": false, \n                    \"socket\": 5, \n                    \"start\": 54.001113\n                }\n            ], \n            \"sum\": {\n                \"bits_per_second\": 0, \n                \"bytes\": 0, \n                \"end\": 55.001131, \n                \"omitted\": false, \n                \"seconds\": 1.0000180006027222, \n                \"sender\": false, \n                \"start\": 54.001113\n            }\n        }, \n        {\n            \"streams\": [\n                {\n                    \"bits_per_second\": 12583415.270128146, \n                    \"bytes\": 1572864, \n                    \"end\": 56.001091, \n                    \"omitted\": false, \n                    \"seconds\": 0.9999600052833557, \n                    \"sender\": false, \n                    \"socket\": 5, \n                    \"start\": 55.001131\n                }\n            ], \n            \"sum\": {\n                \"bits_per_second\": 12583415.270128146, \n                \"bytes\": 1572864, \n                \"end\": 56.001091, \n                \"omitted\": false, \n                \"seconds\": 0.9999600052833557, \n                \"sender\": false, \n                \"start\": 55.001131\n            }\n        }, \n        {\n            \"streams\": [\n                {\n                    \"bits_per_second\": 8388776.00336463, \n                    \"bytes\": 1048576, \n                    \"end\": 57.001071, \n                    \"omitted\": false, \n                    \"seconds\": 0.9999799728393555, \n                    \"sender\": false, \n                    \"socket\": 5, \n                    \"start\": 56.001091\n                }\n            ], \n            \"sum\": {\n                \"bits_per_second\": 8388776.00336463, \n                \"bytes\": 1048576, \n                \"end\": 57.001071, \n                \"omitted\": false, \n                \"seconds\": 0.9999799728393555, \n                \"sender\": false, \n                \"start\": 56.001091\n            }\n        }, \n        {\n            \"streams\": [\n                {\n                    \"bits_per_second\": 22028356.03478854, \n                    \"bytes\": 2752512, \n                    \"end\": 58.000696, \n                    \"omitted\": false, \n                    \"seconds\": 0.999625027179718, \n                    \"sender\": false, \n                    \"socket\": 5, \n                    \"start\": 57.001071\n                }\n            ], \n            \"sum\": {\n                \"bits_per_second\": 22028356.03478854, \n                \"bytes\": 2752512, \n                \"end\": 58.000696, \n                \"omitted\": false, \n                \"seconds\": 0.999625027179718, \n                \"sender\": false, \n                \"start\": 57.001071\n            }\n        }, \n        {\n            \"streams\": [\n                {\n                    \"bits_per_second\": 20983690.809225116, \n                    \"bytes\": 2621440, \n                    \"end\": 59.000116, \n                    \"omitted\": false, \n                    \"seconds\": 0.9994199872016907, \n                    \"sender\": false, \n                    \"socket\": 5, \n                    \"start\": 58.000696\n                }\n            ], \n            \"sum\": {\n                \"bits_per_second\": 20983690.809225116, \n                \"bytes\": 2621440, \n                \"end\": 59.000116, \n                \"omitted\": false, \n                \"seconds\": 0.9994199872016907, \n                \"sender\": false, \n                \"start\": 58.000696\n            }\n        }, \n        {\n            \"streams\": [\n                {\n                    \"bits_per_second\": 5237615.91568647, \n                    \"bytes\": 655360, \n                    \"end\": 60.001121, \n                    \"omitted\": false, \n                    \"seconds\": 1.0010050535202026, \n                    \"sender\": false, \n                    \"socket\": 5, \n                    \"start\": 59.000116\n                }\n            ], \n            \"sum\": {\n                \"bits_per_second\": 5237615.91568647, \n                \"bytes\": 655360, \n                \"end\": 60.001121, \n                \"omitted\": false, \n                \"seconds\": 1.0010050535202026, \n                \"sender\": false, \n                \"start\": 59.000116\n            }\n        }, \n        {\n            \"streams\": [\n                {\n                    \"bits_per_second\": 0, \n                    \"bytes\": 0, \n                    \"end\": 61.001153, \n                    \"omitted\": false, \n                    \"seconds\": 1.0000319480895996, \n                    \"sender\": false, \n                    \"socket\": 5, \n                    \"start\": 60.001121\n                }\n            ], \n            \"sum\": {\n                \"bits_per_second\": 0, \n                \"bytes\": 0, \n                \"end\": 61.001153, \n                \"omitted\": false, \n                \"seconds\": 1.0000319480895996, \n                \"sender\": false, \n                \"start\": 60.001121\n            }\n        }, \n        {\n            \"streams\": [\n                {\n                    \"bits_per_second\": 0, \n                    \"bytes\": 0, \n                    \"end\": 62.001101, \n                    \"omitted\": false, \n                    \"seconds\": 0.999948024749756, \n                    \"sender\": false, \n                    \"socket\": 5, \n                    \"start\": 61.001153\n                }\n            ], \n            \"sum\": {\n                \"bits_per_second\": 0, \n                \"bytes\": 0, \n                \"end\": 62.001101, \n                \"omitted\": false, \n                \"seconds\": 0.999948024749756, \n                \"sender\": false, \n                \"start\": 61.001153\n            }\n        }, \n        {\n            \"streams\": [\n                {\n                    \"bits_per_second\": 0, \n                    \"bytes\": 0, \n                    \"end\": 62.736514, \n                    \"omitted\": false, \n                    \"seconds\": 0.7354130148887634, \n                    \"sender\": false, \n                    \"socket\": 5, \n                    \"start\": 62.001101\n                }\n            ], \n            \"sum\": {\n                \"bits_per_second\": 0, \n                \"bytes\": 0, \n                \"end\": 62.736514, \n                \"omitted\": false, \n                \"seconds\": 0.7354130148887634, \n                \"sender\": false, \n                \"start\": 62.001101\n            }\n        }\n    ], \n    \"start\": {\n        \"accepted_connection\": {\n            \"host\": \"172.16.0.2\", \n            \"port\": 55205\n        }, \n        \"connected\": [\n            {\n                \"local_host\": \"172.16.0.1\", \n                \"local_port\": 5201, \n                \"remote_host\": \"172.16.0.2\", \n                \"remote_port\": 41663, \n                \"socket\": 5\n            }\n        ], \n        \"cookie\": \"jmol27fivntj5lxsedetlza6hmuvllack7es\", \n        \"fq_rate\": 0, \n        \"rcvbuf_actual\": 87380, \n        \"sndbuf_actual\": 65536, \n        \"sock_bufsize\": 0, \n        \"system_info\": \"REDACTED\", \n        \"target_bitrate\": 0, \n        \"tcp_mss_default\": 0, \n        \"test_start\": {\n            \"bidir\": 0, \n            \"blksize\": 131072, \n            \"blocks\": 0, \n            \"bytes\": 0, \n            \"duration\": 60, \n            \"fqrate\": 0, \n            \"interval\": 1, \n            \"num_streams\": 1, \n            \"omit\": 0, \n            \"protocol\": \"TCP\", \n            \"reverse\": 0, \n            \"target_bitrate\": 0, \n            \"tos\": 0\n        }, \n        \"timestamp\": {\n            \"time\": \"Wed, 16 Oct 2024 02:45:09 GMT\", \n            \"timesecs\": 1729046709\n        }, \n        \"version\": \"iperf 3.17.1\"\n    }\n}\n","summary":{"streams":[{"end":60.000172,"rtt":37804,"start":0,"stream-id":5,"retransmits":583,"throughput-bits":1839147.7944429894,"throughput-bytes":13793648}],"summary":{"end":60.000172,"start":0,"retransmits":583,"throughput-bits":1839147.7944429894,"throughput-bytes":13793648,"receiver-throughput-bits":1602200.5940591472}},"intervals":[{"streams":[{"end":1.000931,"rtt":54275,"start":0,"omitted":false,"stream-id":5,"retransmits":1,"tcp-window-size":1448,"throughput-bits":16503418.9118112,"throughput-bytes":2064848}],"summary":{"end":1.000931,"start":0,"omitted":false,"retransmits":1,"throughput-bits":16503418.9118112,"throughput-bytes":2064848}},{"streams":[{"end":2.001049,"rtt":54275,"start":1.000931,"omitted":false,"stream-id":5,"retransmits":1,"tcp-window-size":1448,"throughput-bits":0,"throughput-bytes":0}],"summary":{"end":2.001049,"start":1.000931,"omitted":false,"retransmits":1,"throughput-bits":0,"throughput-bytes":0}},{"streams":[{"end":3.001049,"rtt":54275,"start":2.001049,"omitted":false,"stream-id":5,"retransmits":1,"tcp-window-size":1448,"throughput-bits":0,"throughput-bytes":0}],"summary":{"end":3.001049,"start":2.001049,"omitted":false,"retransmits":1,"throughput-bits":0,"throughput-bytes":0}},{"streams":[{"end":4.001046,"rtt":54275,"start":3.001049,"omitted":false,"stream-id":5,"retransmits":0,"tcp-window-size":1448,"throughput-bits":0,"throughput-bytes":0}],"summary":{"end":4.001046,"start":3.001049,"omitted":false,"retransmits":0,"throughput-bits":0,"throughput-bytes":0}},{"streams":[{"end":5.001052,"rtt":35922,"start":4.001046,"omitted":false,"stream-id":5,"retransmits":60,"tcp-window-size":5792,"throughput-bits":0,"throughput-bytes":0}],"summary":{"end":5.001052,"start":4.001046,"omitted":false,"retransmits":60,"throughput-bits":0,"throughput-bytes":0}},{"streams":[{"end":6.001048,"rtt":14036,"start":5.001052,"omitted":false,"stream-id":5,"retransmits":169,"tcp-window-size":1448,"throughput-bits":0,"throughput-bytes":0}],"summary":{"end":6.001048,"start":5.001052,"omitted":false,"retransmits":169,"throughput-bits":0,"throughput-bytes":0}},{"streams":[{"end":7.001051,"rtt":34552,"start":6.001048,"omitted":false,"stream-id":5,"retransmits":36,"tcp-window-size":1448,"throughput-bits":0,"throughput-bytes":0}],"summary":{"end":7.001051,"start":6.001048,"omitted":false,"retransmits":36,"throughput-bits":0,"throughput-bytes":0}},{"streams":[{"end":8.001167,"rtt":34552,"start":7.001051,"omitted":false,"stream-id":5,"retransmits":1,"tcp-window-size":1448,"throughput-bits":0,"throughput-bytes":0}],"summary":{"end":8.001167,"start":7.001051,"omitted":false,"retransmits":1,"throughput-bits":0,"throughput-bytes":0}},{"streams":[{"end":9.000534,"rtt":21267,"start":8.001167,"omitted":false,"stream-id":5,"retransmits":20,"tcp-window-size":28960,"throughput-bits":5216101.799363448,"throughput-bytes":651600}],"summary":{"end":9.000534,"start":8.001167,"omitted":false,"retransmits":20,"throughput-bits":5216101.799363448,"throughput-bytes":651600}},{"streams":[{"end":10.001055,"rtt":23261,"start":9.000534,"omitted":false,"stream-id":5,"retransmits":22,"tcp-window-size":1448,"throughput-bits":0,"throughput-bytes":0}],"summary":{"end":10.001055,"start":9.000534,"omitted":false,"retransmits":22,"throughput-bits":0,"throughput-bytes":0}},{"streams":[{"end":11.001053,"rtt":23261,"start":10.001055,"omitted":false,"stream-id":5,"retransmits":1,"tcp-window-size":1448,"throughput-bits":0,"throughput-bytes":0}],"summary":{"end":11.001053,"start":10.001055,"omitted":false,"retransmits":1,"throughput-bits":0,"throughput-bytes":0}},{"streams":[{"end":12.001055,"rtt":23261,"start":11.001053,"omitted":false,"stream-id":5,"retransmits":1,"tcp-window-size":1448,"throughput-bits":0,"throughput-bytes":0}],"summary":{"end":12.001055,"start":11.001053,"omitted":false,"retransmits":1,"throughput-bits":0,"throughput-bytes":0}},{"streams":[{"end":13.001051,"rtt":23261,"start":12.001055,"omitted":false,"stream-id":5,"retransmits":0,"tcp-window-size":1448,"throughput-bits":0,"throughput-bytes":0}],"summary":{"end":13.001051,"start":12.001055,"omitted":false,"retransmits":0,"throughput-bits":0,"throughput-bytes":0}},{"streams":[{"end":14.00105,"rtt":23261,"start":13.001051,"omitted":false,"stream-id":5,"retransmits":1,"tcp-window-size":1448,"throughput-bits":0,"throughput-bytes":0}],"summary":{"end":14.00105,"start":13.001051,"omitted":false,"retransmits":1,"throughput-bits":0,"throughput-bytes":0}},{"streams":[{"end":15.001047,"rtt":23261,"start":14.00105,"omitted":false,"stream-id":5,"retransmits":0,"tcp-window-size":1448,"throughput-bits":0,"throughput-bytes":0}],"summary":{"end":15.001047,"start":14.00105,"omitted":false,"retransmits":0,"throughput-bits":0,"throughput-bytes":0}},{"streams":[{"end":16.00105,"rtt":23261,"start":15.001047,"omitted":false,"stream-id":5,"retransmits":0,"tcp-window-size":1448,"throughput-bits":0,"throughput-bytes":0}],"summary":{"end":16.00105,"start":15.001047,"omitted":false,"retransmits":0,"throughput-bits":0,"throughput-bytes":0}},{"streams":[{"end":17.001049,"rtt":25228,"start":16.00105,"omitted":false,"stream-id":5,"retransmits":1,"tcp-window-size":2896,"throughput-bits":0,"throughput-bytes":0}],"summary":{"end":17.001049,"start":16.00105,"omitted":false,"retransmits":1,"throughput-bits":0,"throughput-bytes":0}},{"streams":[{"end":18.000289,"rtt":38653,"start":17.001049,"omitted":false,"stream-id":5,"retransmits":12,"tcp-window-size":1448,"throughput-bits":0,"throughput-bytes":0}],"summary":{"end":18.000289,"start":17.001049,"omitted":false,"retransmits":12,"throughput-bits":0,"throughput-bytes":0}},{"streams":[{"end":19.001045,"rtt":468998,"start":18.000289,"omitted":false,"stream-id":5,"retransmits":1,"tcp-window-size":11584,"throughput-bits":0,"throughput-bytes":0}],"summary":{"end":19.001045,"start":18.000289,"omitted":false,"retransmits":1,"throughput-bits":0,"throughput-bytes":0}},{"streams":[{"end":20.001053,"rtt":61945,"start":19.001045,"omitted":false,"stream-id":5,"retransmits":8,"tcp-window-size":10136,"throughput-bits":0,"throughput-bytes":0}],"summary":{"end":20.001053,"start":19.001045,"omitted":false,"retransmits":8,"throughput-bits":0,"throughput-bytes":0}},{"streams":[{"end":21.001072,"rtt":61945,"start":20.001053,"omitted":false,"stream-id":5,"retransmits":0,"tcp-window-size":10136,"throughput-bits":0,"throughput-bytes":0}],"summary":{"end":21.001072,"start":20.001053,"omitted":false,"retransmits":0,"throughput-bits":0,"throughput-bytes":0}},{"streams":[{"end":22.001052,"rtt":24747,"start":21.001072,"omitted":false,"stream-id":5,"retransmits":1,"tcp-window-size":26064,"throughput-bits":0,"throughput-bytes":0}],"summary":{"end":22.001052,"start":21.001072,"omitted":false,"retransmits":1,"throughput-bits":0,"throughput-bytes":0}},{"streams":[{"end":23.00105,"rtt":24747,"start":22.001052,"omitted":false,"stream-id":5,"retransmits":2,"tcp-window-size":1448,"throughput-bits":0,"throughput-bytes":0}],"summary":{"end":23.00105,"start":22.001052,"omitted":false,"retransmits":2,"throughput-bits":0,"throughput-bytes":0}},{"streams":[{"end":24.001047,"rtt":24747,"start":23.00105,"omitted":false,"stream-id":5,"retransmits":0,"tcp-window-size":1448,"throughput-bits":0,"throughput-bytes":0}],"summary":{"end":24.001047,"start":23.00105,"omitted":false,"retransmits":0,"throughput-bits":0,"throughput-bytes":0}},{"streams":[{"end":25.001051,"rtt":24747,"start":24.001047,"omitted":false,"stream-id":5,"retransmits":1,"tcp-window-size":1448,"throughput-bits":0,"throughput-bytes":0}],"summary":{"end":25.001051,"start":24.001047,"omitted":false,"retransmits":1,"throughput-bits":0,"throughput-bytes":0}},{"streams":[{"end":26.0005,"rtt":22767,"start":25.001051,"omitted":false,"stream-id":5,"retransmits":18,"tcp-window-size":30408,"throughput-bits":5215673.759760573,"throughput-bytes":651600}],"summary":{"end":26.0005,"start":25.001051,"omitted":false,"retransmits":18,"throughput-bits":5215673.759760573,"throughput-bytes":651600}},{"streams":[{"end":27.001067,"rtt":22767,"start":26.0005,"omitted":false,"stream-id":5,"retransmits":2,"tcp-window-size":1448,"throughput-bits":0,"throughput-bytes":0}],"summary":{"end":27.001067,"start":26.0005,"omitted":false,"retransmits":2,"throughput-bits":0,"throughput-bytes":0}},{"streams":[{"end":28.001048,"rtt":22767,"start":27.001067,"omitted":false,"stream-id":5,"retransmits":1,"tcp-window-size":1448,"throughput-bits":0,"throughput-bytes":0}],"summary":{"end":28.001048,"start":27.001067,"omitted":false,"retransmits":1,"throughput-bits":0,"throughput-bytes":0}},{"streams":[{"end":29.001051,"rtt":22767,"start":28.001048,"omitted":false,"stream-id":5,"retransmits":0,"tcp-window-size":1448,"throughput-bits":0,"throughput-bytes":0}],"summary":{"end":29.001051,"start":28.001048,"omitted":false,"retransmits":0,"throughput-bits":0,"throughput-bytes":0}},{"streams":[{"end":30.000991,"rtt":22767,"start":29.001051,"omitted":false,"stream-id":5,"retransmits":1,"tcp-window-size":1448,"throughput-bits":0,"throughput-bytes":0}],"summary":{"end":30.000991,"start":29.001051,"omitted":false,"retransmits":1,"throughput-bits":0,"throughput-bytes":0}},{"streams":[{"end":31.001047,"rtt":22767,"start":30.000991,"omitted":false,"stream-id":5,"retransmits":0,"tcp-window-size":1448,"throughput-bits":0,"throughput-bytes":0}],"summary":{"end":31.001047,"start":30.000991,"omitted":false,"retransmits":0,"throughput-bits":0,"throughput-bytes":0}},{"streams":[{"end":32.000981,"rtt":22767,"start":31.001047,"omitted":false,"stream-id":5,"retransmits":0,"tcp-window-size":1448,"throughput-bits":0,"throughput-bytes":0}],"summary":{"end":32.000981,"start":31.001047,"omitted":false,"retransmits":0,"throughput-bits":0,"throughput-bytes":0}},{"streams":[{"end":33.001042,"rtt":22767,"start":32.000981,"omitted":false,"stream-id":5,"retransmits":0,"tcp-window-size":1448,"throughput-bits":0,"throughput-bytes":0}],"summary":{"end":33.001042,"start":32.000981,"omitted":false,"retransmits":0,"throughput-bits":0,"throughput-bytes":0}},{"streams":[{"end":34.001052,"rtt":24799,"start":33.001042,"omitted":false,"stream-id":5,"retransmits":21,"tcp-window-size":26064,"throughput-bits":0,"throughput-bytes":0}],"summary":{"end":34.001052,"start":33.001042,"omitted":false,"retransmits":21,"throughput-bits":0,"throughput-bytes":0}},{"streams":[{"end":35.001049,"rtt":28179,"start":34.001052,"omitted":false,"stream-id":5,"retransmits":2,"tcp-window-size":1448,"throughput-bits":0,"throughput-bytes":0}],"summary":{"end":35.001049,"start":34.001052,"omitted":false,"retransmits":2,"throughput-bits":0,"throughput-bytes":0}},{"streams":[{"end":36.001051,"rtt":28179,"start":35.001049,"omitted":false,"stream-id":5,"retransmits":1,"tcp-window-size":1448,"throughput-bits":0,"throughput-bytes":0}],"summary":{"end":36.001051,"start":35.001049,"omitted":false,"retransmits":1,"throughput-bits":0,"throughput-bytes":0}},{"streams":[{"end":37.001053,"rtt":22357,"start":36.001051,"omitted":false,"stream-id":5,"retransmits":21,"tcp-window-size":14480,"throughput-bits":0,"throughput-bytes":0}],"summary":{"end":37.001053,"start":36.001051,"omitted":false,"retransmits":21,"throughput-bits":0,"throughput-bytes":0}},{"streams":[{"end":38.000947,"rtt":59677,"start":37.001053,"omitted":false,"stream-id":5,"retransmits":15,"tcp-window-size":10136,"throughput-bits":5213352.49576196,"throughput-bytes":651600}],"summary":{"end":38.000947,"start":37.001053,"omitted":false,"retransmits":15,"throughput-bits":5213352.49576196,"throughput-bytes":651600}},{"streams":[{"end":39.000486,"rtt":27462,"start":38.000947,"omitted":false,"stream-id":5,"retransmits":0,"tcp-window-size":55024,"throughput-bits":5215204.11690713,"throughput-bytes":651600}],"summary":{"end":39.000486,"start":38.000947,"omitted":false,"retransmits":0,"throughput-bits":5215204.11690713,"throughput-bytes":651600}},{"streams":[{"end":40.001053,"rtt":27462,"start":39.000486,"omitted":false,"stream-id":5,"retransmits":2,"tcp-window-size":1448,"throughput-bits":0,"throughput-bytes":0}],"summary":{"end":40.001053,"start":39.000486,"omitted":false,"retransmits":2,"throughput-bits":0,"throughput-bytes":0}},{"streams":[{"end":41.001042,"rtt":27462,"start":40.001053,"omitted":false,"stream-id":5,"retransmits":1,"tcp-window-size":1448,"throughput-bits":0,"throughput-bytes":0}],"summary":{"end":41.001042,"start":40.001053,"omitted":false,"retransmits":1,"throughput-bits":0,"throughput-bytes":0}},{"streams":[{"end":42.001059,"rtt":27462,"start":41.001042,"omitted":false,"stream-id":5,"retransmits":0,"tcp-window-size":1448,"throughput-bits":0,"throughput-bytes":0}],"summary":{"end":42.001059,"start":41.001042,"omitted":false,"retransmits":0,"throughput-bits":0,"throughput-bytes":0}},{"streams":[{"end":43.000394,"rtt":22948,"start":42.001059,"omitted":false,"stream-id":5,"retransmits":39,"tcp-window-size":37648,"throughput-bits":5216268.865855715,"throughput-bytes":651600}],"summary":{"end":43.000394,"start":42.001059,"omitted":false,"retransmits":39,"throughput-bits":5216268.865855715,"throughput-bytes":651600}},{"streams":[{"end":44.00105,"rtt":22948,"start":43.000394,"omitted":false,"stream-id":5,"retransmits":2,"tcp-window-size":1448,"throughput-bits":0,"throughput-bytes":0}],"summary":{"end":44.00105,"start":43.000394,"omitted":false,"retransmits":2,"throughput-bits":0,"throughput-bytes":0}},{"streams":[{"end":45.00042,"rtt":22948,"start":44.00105,"omitted":false,"stream-id":5,"retransmits":1,"tcp-window-size":1448,"throughput-bits":0,"throughput-bytes":0}],"summary":{"end":45.00042,"start":44.00105,"omitted":false,"retransmits":1,"throughput-bits":0,"throughput-bytes":0}},{"streams":[{"end":46.001043,"rtt":22948,"start":45.00042,"omitted":false,"stream-id":5,"retransmits":0,"tcp-window-size":1448,"throughput-bits":0,"throughput-bytes":0}],"summary":{"end":46.001043,"start":45.00042,"omitted":false,"retransmits":0,"throughput-bits":0,"throughput-bytes":0}},{"streams":[{"end":47.001052,"rtt":32654,"start":46.001043,"omitted":false,"stream-id":5,"retransmits":28,"tcp-window-size":2896,"throughput-bits":0,"throughput-bytes":0}],"summary":{"end":47.001052,"start":46.001043,"omitted":false,"retransmits":28,"throughput-bits":0,"throughput-bytes":0}},{"streams":[{"end":48.001046,"rtt":28120,"start":47.001052,"omitted":false,"stream-id":5,"retransmits":17,"tcp-window-size":1448,"throughput-bits":0,"throughput-bytes":0}],"summary":{"end":48.001046,"start":47.001052,"omitted":false,"retransmits":17,"throughput-bits":0,"throughput-bytes":0}},{"streams":[{"end":49.001042,"rtt":28120,"start":48.001046,"omitted":false,"stream-id":5,"retransmits":1,"tcp-window-size":1448,"throughput-bits":0,"throughput-bytes":0}],"summary":{"end":49.001042,"start":48.001046,"omitted":false,"retransmits":1,"throughput-bits":0,"throughput-bytes":0}},{"streams":[{"end":50.001044,"rtt":28120,"start":49.001042,"omitted":false,"stream-id":5,"retransmits":1,"tcp-window-size":1448,"throughput-bits":0,"throughput-bytes":0}],"summary":{"end":50.001044,"start":49.001042,"omitted":false,"retransmits":1,"throughput-bits":0,"throughput-bytes":0}},{"streams":[{"end":51.001049,"rtt":28120,"start":50.001044,"omitted":false,"stream-id":5,"retransmits":1,"tcp-window-size":1448,"throughput-bits":0,"throughput-bytes":0}],"summary":{"end":51.001049,"start":50.001044,"omitted":false,"retransmits":1,"throughput-bits":0,"throughput-bytes":0}},{"streams":[{"end":52.000169,"rtt":28120,"start":51.001049,"omitted":false,"stream-id":5,"retransmits":0,"tcp-window-size":1448,"throughput-bits":0,"throughput-bytes":0}],"summary":{"end":52.000169,"start":51.001049,"omitted":false,"retransmits":0,"throughput-bits":0,"throughput-bytes":0}},{"streams":[{"end":53.000956,"rtt":28120,"start":52.000169,"omitted":false,"stream-id":5,"retransmits":0,"tcp-window-size":1448,"throughput-bits":0,"throughput-bytes":0}],"summary":{"end":53.000956,"start":52.000169,"omitted":false,"retransmits":0,"throughput-bits":0,"throughput-bytes":0}},{"streams":[{"end":54.000989,"rtt":28120,"start":53.000956,"omitted":false,"stream-id":5,"retransmits":0,"tcp-window-size":1448,"throughput-bits":0,"throughput-bytes":0}],"summary":{"end":54.000989,"start":53.000956,"omitted":false,"retransmits":0,"throughput-bits":0,"throughput-bytes":0}},{"streams":[{"end":55.001052,"rtt":34175,"start":54.000989,"omitted":false,"stream-id":5,"retransmits":14,"tcp-window-size":10136,"throughput-bits":0,"throughput-bytes":0}],"summary":{"end":55.001052,"start":54.000989,"omitted":false,"retransmits":14,"throughput-bits":0,"throughput-bytes":0}},{"streams":[{"end":56.000107,"rtt":22697,"start":55.001052,"omitted":false,"stream-id":5,"retransmits":1,"tcp-window-size":63712,"throughput-bits":15653191.828587677,"throughput-bytes":1954800}],"summary":{"end":56.000107,"start":55.001052,"omitted":false,"retransmits":1,"throughput-bits":15653191.828587677,"throughput-bytes":1954800}},{"streams":[{"end":57.000296,"rtt":18571,"start":56.000107,"omitted":false,"stream-id":5,"retransmits":52,"tcp-window-size":53576,"throughput-bits":5211815.244583766,"throughput-bytes":651600}],"summary":{"end":57.000296,"start":56.000107,"omitted":false,"retransmits":52,"throughput-bits":5211815.244583766,"throughput-bytes":651600}},{"streams":[{"end":58.000567,"rtt":36541,"start":57.000296,"omitted":false,"stream-id":5,"retransmits":0,"tcp-window-size":101360,"throughput-bits":20845551.63273082,"throughput-bytes":2606400}],"summary":{"end":58.000567,"start":57.000296,"omitted":false,"retransmits":0,"throughput-bits":20845551.63273082,"throughput-bytes":2606400}},{"streams":[{"end":59.000107,"rtt":48164,"start":58.000567,"omitted":false,"stream-id":5,"retransmits":0,"tcp-window-size":133216,"throughput-bits":26075995.705059268,"throughput-bytes":3258000}],"summary":{"end":59.000107,"start":58.000567,"omitted":false,"retransmits":0,"throughput-bits":26075995.705059268,"throughput-bytes":3258000}},{"streams":[{"end":60.000172,"rtt":55676,"start":59.000107,"omitted":false,"stream-id":5,"retransmits":1,"tcp-window-size":1448,"throughput-bits":0,"throughput-bytes":0}],"summary":{"end":60.000172,"start":59.000107,"omitted":false,"retransmits":1,"throughput-bits":0,"throughput-bytes":0}}],"succeeded":true}
