{"diags":"Participant 0:\n/usr/bin/iperf3 -p 5201 -B 172.16.0.2 -c 172.16.0.1 -t 60 --json --rsa-public-key-path /var/run/pscheduler-server/runner/tmp/tmpr4ww9hvh/tmpzif7so2b/public-key --username RFrTANVQVyoyLZUARCOD\n\n{\n    \"end\": {\n        \"cpu_utilization_percent\": {\n            \"host_system\": 0.0658572962137462, \n            \"host_total\": 0.0780963511111318, \n            \"host_user\": 0.012239054897385606, \n            \"remote_system\": 0.47636170529665256, \n            \"remote_total\": 0.6449191044078136, \n            \"remote_user\": 0.1685524021528096\n        }, \n        \"receiver_tcp_congestion\": \"htcp\", \n        \"sender_tcp_congestion\": \"htcp\", \n        \"streams\": [\n            {\n                \"receiver\": {\n                    \"bits_per_second\": 3075857.549410338, \n                    \"bytes\": 23082936, \n                    \"end\": 60.036424, \n                    \"seconds\": 60.001069, \n                    \"sender\": true, \n                    \"socket\": 5, \n                    \"start\": 0\n                }, \n                \"sender\": {\n                    \"bits_per_second\": 3266629.799545738, \n                    \"bytes\": 24500160, \n                    \"end\": 60.001069, \n                    \"max_rtt\": 102352, \n                    \"max_snd_cwnd\": 285256, \n                    \"max_snd_wnd\": 0, \n                    \"mean_rtt\": 40821, \n                    \"min_rtt\": 16843, \n                    \"retransmits\": 412, \n                    \"seconds\": 60.001069, \n                    \"sender\": true, \n                    \"socket\": 5, \n                    \"start\": 0\n                }\n            }\n        ], \n        \"sum_received\": {\n            \"bits_per_second\": 3075857.549410338, \n            \"bytes\": 23082936, \n            \"end\": 60.036424, \n            \"seconds\": 60.036424, \n            \"sender\": true, \n            \"start\": 0\n        }, \n        \"sum_sent\": {\n            \"bits_per_second\": 3266629.799545738, \n            \"bytes\": 24500160, \n            \"end\": 60.001069, \n            \"retransmits\": 412, \n            \"seconds\": 60.001069, \n            \"sender\": true, \n            \"start\": 0\n        }\n    }, \n    \"intervals\": [\n        {\n            \"streams\": [\n                {\n                    \"bits_per_second\": 1330763.973035489, \n                    \"bytes\": 166520, \n                    \"end\": 1.001049, \n                    \"omitted\": false, \n                    \"pmtu\": 1500, \n                    \"retransmits\": 2, \n                    \"rtt\": 22328, \n                    \"rttvar\": 2687, \n                    \"seconds\": 1.0010490417480469, \n                    \"sender\": true, \n                    \"snd_cwnd\": 1448, \n                    \"snd_wnd\": -1, \n                    \"socket\": 5, \n                    \"start\": 0\n                }\n            ], \n            \"sum\": {\n                \"bits_per_second\": 1330763.973035489, \n                \"bytes\": 166520, \n                \"end\": 1.001049, \n                \"omitted\": false, \n                \"retransmits\": 2, \n                \"seconds\": 1.0010490417480469, \n                \"sender\": true, \n                \"start\": 0\n            }\n        }, \n        {\n            \"streams\": [\n                {\n                    \"bits_per_second\": 0, \n                    \"bytes\": 0, \n                    \"end\": 2.001054, \n                    \"omitted\": false, \n                    \"pmtu\": 1500, \n                    \"retransmits\": 1, \n                    \"rtt\": 22328, \n                    \"rttvar\": 2687, \n                    \"seconds\": 1.0000050067901611, \n                    \"sender\": true, \n                    \"snd_cwnd\": 1448, \n                    \"snd_wnd\": -1, \n                    \"socket\": 5, \n                    \"start\": 1.001049\n                }\n            ], \n            \"sum\": {\n                \"bits_per_second\": 0, \n                \"bytes\": 0, \n                \"end\": 2.001054, \n                \"omitted\": false, \n                \"retransmits\": 1, \n                \"seconds\": 1.0000050067901611, \n                \"sender\": true, \n                \"start\": 1.001049\n            }\n        }, \n        {\n            \"streams\": [\n                {\n                    \"bits_per_second\": 0, \n                    \"bytes\": 0, \n                    \"end\": 3.001079, \n                    \"omitted\": false, \n                    \"pmtu\": 1500, \n                    \"retransmits\": 0, \n                    \"rtt\": 22328, \n                    \"rttvar\": 2687, \n                    \"seconds\": 1.0000250339508057, \n                    \"sender\": true, \n                    \"snd_cwnd\": 1448, \n                    \"snd_wnd\": -1, \n                    \"socket\": 5, \n                    \"start\": 2.001054\n                }\n            ], \n            \"sum\": {\n                \"bits_per_second\": 0, \n                \"bytes\": 0, \n                \"end\": 3.001079, \n                \"omitted\": false, \n                \"retransmits\": 0, \n                \"seconds\": 1.0000250339508057, \n                \"sender\": true, \n                \"start\": 2.001054\n            }\n        }, \n        {\n            \"streams\": [\n                {\n                    \"bits_per_second\": 1797272.3635222015, \n                    \"bytes\": 224440, \n                    \"end\": 4.000104, \n                    \"omitted\": false, \n                    \"pmtu\": 1500, \n                    \"retransmits\": 19, \n                    \"rtt\": 21175, \n                    \"rttvar\": 8952, \n                    \"seconds\": 0.999024987220764, \n                    \"sender\": true, \n                    \"snd_cwnd\": 27512, \n                    \"snd_wnd\": -1, \n                    \"socket\": 5, \n                    \"start\": 3.001079\n                }\n            ], \n            \"sum\": {\n                \"bits_per_second\": 1797272.3635222015, \n                \"bytes\": 224440, \n                \"end\": 4.000104, \n                \"omitted\": false, \n                \"retransmits\": 19, \n                \"seconds\": 0.999024987220764, \n                \"sender\": true, \n                \"start\": 3.001079\n            }\n        }, \n        {\n            \"streams\": [\n                {\n                    \"bits_per_second\": 20851200, \n                    \"bytes\": 2606400, \n                    \"end\": 5.000104, \n                    \"omitted\": false, \n                    \"pmtu\": 1500, \n                    \"retransmits\": 0, \n                    \"rtt\": 30692, \n                    \"rttvar\": 553, \n                    \"seconds\": 1, \n                    \"sender\": true, \n                    \"snd_cwnd\": 85432, \n                    \"snd_wnd\": -1, \n                    \"socket\": 5, \n                    \"start\": 4.000104\n                }\n            ], \n            \"sum\": {\n                \"bits_per_second\": 20851200, \n                \"bytes\": 2606400, \n                \"end\": 5.000104, \n                \"omitted\": false, \n                \"retransmits\": 0, \n                \"seconds\": 1, \n                \"sender\": true, \n                \"start\": 4.000104\n            }\n        }, \n        {\n            \"streams\": [\n                {\n                    \"bits_per_second\": 22414345.280474074, \n                    \"bytes\": 2801880, \n                    \"end\": 6.000135, \n                    \"omitted\": false, \n                    \"pmtu\": 1500, \n                    \"retransmits\": 0, \n                    \"rtt\": 43798, \n                    \"rttvar\": 657, \n                    \"seconds\": 1.0000309944152832, \n                    \"sender\": true, \n                    \"snd_cwnd\": 121632, \n                    \"snd_wnd\": -1, \n                    \"socket\": 5, \n                    \"start\": 5.000104\n                }\n            ], \n            \"sum\": {\n                \"bits_per_second\": 22414345.280474074, \n                \"bytes\": 2801880, \n                \"end\": 6.000135, \n                \"omitted\": false, \n                \"retransmits\": 0, \n                \"seconds\": 1.0000309944152832, \n                \"sender\": true, \n                \"start\": 5.000104\n            }\n        }, \n        {\n            \"streams\": [\n                {\n                    \"bits_per_second\": 23979431.704206336, \n                    \"bytes\": 2997360, \n                    \"end\": 7.000112, \n                    \"omitted\": false, \n                    \"pmtu\": 1500, \n                    \"retransmits\": 0, \n                    \"rtt\": 59955, \n                    \"rttvar\": 754, \n                    \"seconds\": 0.9999769926071167, \n                    \"sender\": true, \n                    \"snd_cwnd\": 166520, \n                    \"snd_wnd\": -1, \n                    \"socket\": 5, \n                    \"start\": 6.000135\n                }\n            ], \n            \"sum\": {\n                \"bits_per_second\": 23979431.704206336, \n                \"bytes\": 2997360, \n                \"end\": 7.000112, \n                \"omitted\": false, \n                \"retransmits\": 0, \n                \"seconds\": 0.9999769926071167, \n                \"sender\": true, \n                \"start\": 6.000135\n            }\n        }, \n        {\n            \"streams\": [\n                {\n                    \"bits_per_second\": 23456638.090288274, \n                    \"bytes\": 2932200, \n                    \"end\": 8.000153, \n                    \"omitted\": false, \n                    \"pmtu\": 1500, \n                    \"retransmits\": 0, \n                    \"rtt\": 80659, \n                    \"rttvar\": 476, \n                    \"seconds\": 1.0000410079956055, \n                    \"sender\": true, \n                    \"snd_cwnd\": 227336, \n                    \"snd_wnd\": -1, \n                    \"socket\": 5, \n                    \"start\": 7.000112\n                }\n            ], \n            \"sum\": {\n                \"bits_per_second\": 23456638.090288274, \n                \"bytes\": 2932200, \n                \"end\": 8.000153, \n                \"omitted\": false, \n                \"retransmits\": 0, \n                \"seconds\": 1.0000410079956055, \n                \"sender\": true, \n                \"start\": 7.000112\n            }\n        }, \n        {\n            \"streams\": [\n                {\n                    \"bits_per_second\": 20847946.78297771, \n                    \"bytes\": 2606400, \n                    \"end\": 9.000309, \n                    \"omitted\": false, \n                    \"pmtu\": 1500, \n                    \"retransmits\": 0, \n                    \"rtt\": 102352, \n                    \"rttvar\": 735, \n                    \"seconds\": 1.000156044960022, \n                    \"sender\": true, \n                    \"snd_cwnd\": 285256, \n                    \"snd_wnd\": -1, \n                    \"socket\": 5, \n                    \"start\": 8.000153\n                }\n            ], \n            \"sum\": {\n                \"bits_per_second\": 20847946.78297771, \n                \"bytes\": 2606400, \n                \"end\": 9.000309, \n                \"omitted\": false, \n                \"retransmits\": 0, \n                \"seconds\": 1.000156044960022, \n                \"sender\": true, \n                \"start\": 8.000153\n            }\n        }, \n        {\n            \"streams\": [\n                {\n                    \"bits_per_second\": 15119690.233139092, \n                    \"bytes\": 1889640, \n                    \"end\": 10.000139, \n                    \"omitted\": false, \n                    \"pmtu\": 1500, \n                    \"retransmits\": 77, \n                    \"rtt\": 56039, \n                    \"rttvar\": 451, \n                    \"seconds\": 0.9998300075531006, \n                    \"sender\": true, \n                    \"snd_cwnd\": 154936, \n                    \"snd_wnd\": -1, \n                    \"socket\": 5, \n                    \"start\": 9.000309\n                }\n            ], \n            \"sum\": {\n                \"bits_per_second\": 15119690.233139092, \n                \"bytes\": 1889640, \n                \"end\": 10.000139, \n                \"omitted\": false, \n                \"retransmits\": 77, \n                \"seconds\": 0.9998300075531006, \n                \"sender\": true, \n                \"start\": 9.000309\n            }\n        }, \n        {\n            \"streams\": [\n                {\n                    \"bits_per_second\": 0, \n                    \"bytes\": 0, \n                    \"end\": 11.001059, \n                    \"omitted\": false, \n                    \"pmtu\": 1500, \n                    \"retransmits\": 1, \n                    \"rtt\": 63288, \n                    \"rttvar\": 12058, \n                    \"seconds\": 1.000920057296753, \n                    \"sender\": true, \n                    \"snd_cwnd\": 1448, \n                    \"snd_wnd\": -1, \n                    \"socket\": 5, \n                    \"start\": 10.000139\n                }\n            ], \n            \"sum\": {\n                \"bits_per_second\": 0, \n                \"bytes\": 0, \n                \"end\": 11.001059, \n                \"omitted\": false, \n                \"retransmits\": 1, \n                \"seconds\": 1.000920057296753, \n                \"sender\": true, \n                \"start\": 10.000139\n            }\n        }, \n        {\n            \"streams\": [\n                {\n                    \"bits_per_second\": 9913390.66226342, \n                    \"bytes\": 1238040, \n                    \"end\": 12.000144, \n                    \"omitted\": false, \n                    \"pmtu\": 1500, \n                    \"retransmits\": 49, \n                    \"rtt\": 32590, \n                    \"rttvar\": 696, \n                    \"seconds\": 0.999085009098053, \n                    \"sender\": true, \n                    \"snd_cwnd\": 89776, \n                    \"snd_wnd\": -1, \n                    \"socket\": 5, \n                    \"start\": 11.001059\n                }\n            ], \n            \"sum\": {\n                \"bits_per_second\": 9913390.66226342, \n                \"bytes\": 1238040, \n                \"end\": 12.000144, \n                \"omitted\": false, \n                \"retransmits\": 49, \n                \"seconds\": 0.999085009098053, \n                \"sender\": true, \n                \"start\": 11.001059\n            }\n        }, \n        {\n            \"streams\": [\n                {\n                    \"bits_per_second\": 9380919.71689901, \n                    \"bytes\": 1172880, \n                    \"end\": 13.00037, \n                    \"omitted\": false, \n                    \"pmtu\": 1500, \n                    \"retransmits\": 31, \n                    \"rtt\": 27405, \n                    \"rttvar\": 10830, \n                    \"seconds\": 1.0002260208129883, \n                    \"sender\": true, \n                    \"snd_cwnd\": 56472, \n                    \"snd_wnd\": -1, \n                    \"socket\": 5, \n                    \"start\": 12.000144\n                }\n            ], \n            \"sum\": {\n                \"bits_per_second\": 9380919.71689901, \n                \"bytes\": 1172880, \n                \"end\": 13.00037, \n                \"omitted\": false, \n                \"retransmits\": 31, \n                \"seconds\": 1.0002260208129883, \n                \"sender\": true, \n                \"start\": 12.000144\n            }\n        }, \n        {\n            \"streams\": [\n                {\n                    \"bits_per_second\": 0, \n                    \"bytes\": 0, \n                    \"end\": 14.001059, \n                    \"omitted\": false, \n                    \"pmtu\": 1500, \n                    \"retransmits\": 2, \n                    \"rtt\": 27405, \n                    \"rttvar\": 10830, \n                    \"seconds\": 1.0006890296936035, \n                    \"sender\": true, \n                    \"snd_cwnd\": 1448, \n                    \"snd_wnd\": -1, \n                    \"socket\": 5, \n                    \"start\": 13.00037\n                }\n            ], \n            \"sum\": {\n                \"bits_per_second\": 0, \n                \"bytes\": 0, \n                \"end\": 14.001059, \n                \"omitted\": false, \n                \"retransmits\": 2, \n                \"seconds\": 1.0006890296936035, \n                \"sender\": true, \n                \"start\": 13.00037\n            }\n        }, \n        {\n            \"streams\": [\n                {\n                    \"bits_per_second\": 0, \n                    \"bytes\": 0, \n                    \"end\": 15.001058, \n                    \"omitted\": false, \n                    \"pmtu\": 1500, \n                    \"retransmits\": 0, \n                    \"rtt\": 27405, \n                    \"rttvar\": 10830, \n                    \"seconds\": 0.9999989867210388, \n                    \"sender\": true, \n                    \"snd_cwnd\": 1448, \n                    \"snd_wnd\": -1, \n                    \"socket\": 5, \n                    \"start\": 14.001059\n                }\n            ], \n            \"sum\": {\n                \"bits_per_second\": 0, \n                \"bytes\": 0, \n                \"end\": 15.001058, \n                \"omitted\": false, \n                \"retransmits\": 0, \n                \"seconds\": 0.9999989867210388, \n                \"sender\": true, \n                \"start\": 14.001059\n            }\n        }, \n        {\n            \"streams\": [\n                {\n                    \"bits_per_second\": 0, \n                    \"bytes\": 0, \n                    \"end\": 16.001064, \n                    \"omitted\": false, \n                    \"pmtu\": 1500, \n                    \"retransmits\": 41, \n                    \"rtt\": 16843, \n                    \"rttvar\": 6002, \n                    \"seconds\": 1.0000059604644775, \n                    \"sender\": true, \n                    \"snd_cwnd\": 1448, \n                    \"snd_wnd\": -1, \n                    \"socket\": 5, \n                    \"start\": 15.001058\n                }\n            ], \n            \"sum\": {\n                \"bits_per_second\": 0, \n                \"bytes\": 0, \n                \"end\": 16.001064, \n                \"omitted\": false, \n                \"retransmits\": 41, \n                \"seconds\": 1.0000059604644775, \n                \"sender\": true, \n                \"start\": 15.001058\n            }\n        }, \n        {\n            \"streams\": [\n                {\n                    \"bits_per_second\": 0, \n                    \"bytes\": 0, \n                    \"end\": 17.001061, \n                    \"omitted\": false, \n                    \"pmtu\": 1500, \n                    \"retransmits\": 1, \n                    \"rtt\": 16843, \n                    \"rttvar\": 6002, \n                    \"seconds\": 0.9999970197677612, \n                    \"sender\": true, \n                    \"snd_cwnd\": 1448, \n                    \"snd_wnd\": -1, \n                    \"socket\": 5, \n                    \"start\": 16.001064\n                }\n            ], \n            \"sum\": {\n                \"bits_per_second\": 0, \n                \"bytes\": 0, \n                \"end\": 17.001061, \n                \"omitted\": false, \n                \"retransmits\": 1, \n                \"seconds\": 0.9999970197677612, \n                \"sender\": true, \n                \"start\": 16.001064\n            }\n        }, \n        {\n            \"streams\": [\n                {\n                    \"bits_per_second\": 0, \n                    \"bytes\": 0, \n                    \"end\": 18.001064, \n                    \"omitted\": false, \n                    \"pmtu\": 1500, \n                    \"retransmits\": 1, \n                    \"rtt\": 16843, \n                    \"rttvar\": 6002, \n                    \"seconds\": 1.0000029802322388, \n                    \"sender\": true, \n                    \"snd_cwnd\": 1448, \n                    \"snd_wnd\": -1, \n                    \"socket\": 5, \n                    \"start\": 17.001061\n                }\n            ], \n            \"sum\": {\n                \"bits_per_second\": 0, \n                \"bytes\": 0, \n                \"end\": 18.001064, \n                \"omitted\": false, \n                \"retransmits\": 1, \n                \"seconds\": 1.0000029802322388, \n                \"sender\": true, \n                \"start\": 17.001061\n            }\n        }, \n        {\n            \"streams\": [\n                {\n                    \"bits_per_second\": 0, \n                    \"bytes\": 0, \n                    \"end\": 19.001057, \n                    \"omitted\": false, \n                    \"pmtu\": 1500, \n                    \"retransmits\": 0, \n                    \"rtt\": 16843, \n                    \"rttvar\": 6002, \n                    \"seconds\": 0.9999930262565613, \n                    \"sender\": true, \n                    \"snd_cwnd\": 1448, \n                    \"snd_wnd\": -1, \n                    \"socket\": 5, \n                    \"start\": 18.001064\n                }\n            ], \n            \"sum\": {\n                \"bits_per_second\": 0, \n                \"bytes\": 0, \n                \"end\": 19.001057, \n                \"omitted\": false, \n                \"retransmits\": 0, \n                \"seconds\": 0.9999930262565613, \n                \"sender\": true, \n                \"start\": 18.001064\n            }\n        }, \n        {\n            \"streams\": [\n                {\n                    \"bits_per_second\": 4693782.510011104, \n                    \"bytes\": 586440, \n                    \"end\": 20.000575, \n                    \"omitted\": false, \n                    \"pmtu\": 1500, \n                    \"retransmits\": 26, \n                    \"rtt\": 20163, \n                    \"rttvar\": 1073, \n                    \"seconds\": 0.9995179772377014, \n                    \"sender\": true, \n                    \"snd_cwnd\": 1448, \n                    \"snd_wnd\": -1, \n                    \"socket\": 5, \n                    \"start\": 19.001057\n                }\n            ], \n            \"sum\": {\n                \"bits_per_second\": 4693782.510011104, \n                \"bytes\": 586440, \n                \"end\": 20.000575, \n                \"omitted\": false, \n                \"retransmits\": 26, \n                \"seconds\": 0.9995179772377014, \n                \"sender\": true, \n                \"start\": 19.001057\n            }\n        }, \n        {\n            \"streams\": [\n                {\n                    \"bits_per_second\": 0, \n                    \"bytes\": 0, \n                    \"end\": 21.000435, \n                    \"omitted\": false, \n                    \"pmtu\": 1500, \n                    \"retransmits\": 1, \n                    \"rtt\": 20163, \n                    \"rttvar\": 1073, \n                    \"seconds\": 0.9998599886894226, \n                    \"sender\": true, \n                    \"snd_cwnd\": 1448, \n                    \"snd_wnd\": -1, \n                    \"socket\": 5, \n                    \"start\": 20.000575\n                }\n            ], \n            \"sum\": {\n                \"bits_per_second\": 0, \n                \"bytes\": 0, \n                \"end\": 21.000435, \n                \"omitted\": false, \n                \"retransmits\": 1, \n                \"seconds\": 0.9998599886894226, \n                \"sender\": true, \n                \"start\": 20.000575\n            }\n        }, \n        {\n            \"streams\": [\n                {\n                    \"bits_per_second\": 0, \n                    \"bytes\": 0, \n                    \"end\": 22.001053, \n                    \"omitted\": false, \n                    \"pmtu\": 1500, \n                    \"retransmits\": 32, \n                    \"rtt\": 49178, \n                    \"rttvar\": 42229, \n                    \"seconds\": 1.0006179809570312, \n                    \"sender\": true, \n                    \"snd_cwnd\": 21720, \n                    \"snd_wnd\": -1, \n                    \"socket\": 5, \n                    \"start\": 21.000435\n                }\n            ], \n            \"sum\": {\n                \"bits_per_second\": 0, \n                \"bytes\": 0, \n                \"end\": 22.001053, \n                \"omitted\": false, \n                \"retransmits\": 32, \n                \"seconds\": 1.0006179809570312, \n                \"sender\": true, \n                \"start\": 21.000435\n            }\n        }, \n        {\n            \"streams\": [\n                {\n                    \"bits_per_second\": 0, \n                    \"bytes\": 0, \n                    \"end\": 23.001052, \n                    \"omitted\": false, \n                    \"pmtu\": 1500, \n                    \"retransmits\": 0, \n                    \"rtt\": 49178, \n                    \"rttvar\": 42229, \n                    \"seconds\": 0.9999989867210388, \n                    \"sender\": true, \n                    \"snd_cwnd\": 21720, \n                    \"snd_wnd\": -1, \n                    \"socket\": 5, \n                    \"start\": 22.001053\n                }\n            ], \n            \"sum\": {\n                \"bits_per_second\": 0, \n                \"bytes\": 0, \n                \"end\": 23.001052, \n                \"omitted\": false, \n                \"retransmits\": 0, \n                \"seconds\": 0.9999989867210388, \n                \"sender\": true, \n                \"start\": 22.001053\n            }\n        }, \n        {\n            \"streams\": [\n                {\n                    \"bits_per_second\": 0, \n                    \"bytes\": 0, \n                    \"end\": 24.001052, \n                    \"omitted\": false, \n                    \"pmtu\": 1500, \n                    \"retransmits\": 1, \n                    \"rtt\": 49178, \n                    \"rttvar\": 42229, \n                    \"seconds\": 1, \n                    \"sender\": true, \n                    \"snd_cwnd\": 1448, \n                    \"snd_wnd\": -1, \n                    \"socket\": 5, \n                    \"start\": 23.001052\n                }\n            ], \n            \"sum\": {\n                \"bits_per_second\": 0, \n                \"bytes\": 0, \n                \"end\": 24.001052, \n                \"omitted\": false, \n                \"retransmits\": 1, \n                \"seconds\": 1, \n                \"sender\": true, \n                \"start\": 23.001052\n            }\n        }, \n        {\n            \"streams\": [\n                {\n                    \"bits_per_second\": 0, \n                    \"bytes\": 0, \n                    \"end\": 25.001051, \n                    \"omitted\": false, \n                    \"pmtu\": 1500, \n                    \"retransmits\": 0, \n                    \"rtt\": 49178, \n                    \"rttvar\": 42229, \n                    \"seconds\": 0.9999989867210388, \n                    \"sender\": true, \n                    \"snd_cwnd\": 1448, \n                    \"snd_wnd\": -1, \n                    \"socket\": 5, \n                    \"start\": 24.001052\n                }\n            ], \n            \"sum\": {\n                \"bits_per_second\": 0, \n                \"bytes\": 0, \n                \"end\": 25.001051, \n                \"omitted\": false, \n                \"retransmits\": 0, \n                \"seconds\": 0.9999989867210388, \n                \"sender\": true, \n                \"start\": 24.001052\n            }\n        }, \n        {\n            \"streams\": [\n                {\n                    \"bits_per_second\": 0, \n                    \"bytes\": 0, \n                    \"end\": 26.001051, \n                    \"omitted\": false, \n                    \"pmtu\": 1500, \n                    \"retransmits\": 0, \n                    \"rtt\": 49178, \n                    \"rttvar\": 42229, \n                    \"seconds\": 1, \n                    \"sender\": true, \n                    \"snd_cwnd\": 1448, \n                    \"snd_wnd\": -1, \n                    \"socket\": 5, \n                    \"start\": 25.001051\n                }\n            ], \n            \"sum\": {\n                \"bits_per_second\": 0, \n                \"bytes\": 0, \n                \"end\": 26.001051, \n                \"omitted\": false, \n                \"retransmits\": 0, \n                \"seconds\": 1, \n                \"sender\": true, \n                \"start\": 25.001051\n            }\n        }, \n        {\n            \"streams\": [\n                {\n                    \"bits_per_second\": 0, \n                    \"bytes\": 0, \n                    \"end\": 27.001051, \n                    \"omitted\": false, \n                    \"pmtu\": 1500, \n                    \"retransmits\": 0, \n                    \"rtt\": 49178, \n                    \"rttvar\": 42229, \n                    \"seconds\": 1, \n                    \"sender\": true, \n                    \"snd_cwnd\": 1448, \n                    \"snd_wnd\": -1, \n                    \"socket\": 5, \n                    \"start\": 26.001051\n                }\n            ], \n            \"sum\": {\n                \"bits_per_second\": 0, \n                \"bytes\": 0, \n                \"end\": 27.001051, \n                \"omitted\": false, \n                \"retransmits\": 0, \n                \"seconds\": 1, \n                \"sender\": true, \n                \"start\": 26.001051\n            }\n        }, \n        {\n            \"streams\": [\n                {\n                    \"bits_per_second\": 0, \n                    \"bytes\": 0, \n                    \"end\": 28.001052, \n                    \"omitted\": false, \n                    \"pmtu\": 1500, \n                    \"retransmits\": 1, \n                    \"rtt\": 49178, \n                    \"rttvar\": 42229, \n                    \"seconds\": 1.0000009536743164, \n                    \"sender\": true, \n                    \"snd_cwnd\": 1448, \n                    \"snd_wnd\": -1, \n                    \"socket\": 5, \n                    \"start\": 27.001051\n                }\n            ], \n            \"sum\": {\n                \"bits_per_second\": 0, \n                \"bytes\": 0, \n                \"end\": 28.001052, \n                \"omitted\": false, \n                \"retransmits\": 1, \n                \"seconds\": 1.0000009536743164, \n                \"sender\": true, \n                \"start\": 27.001051\n            }\n        }, \n        {\n            \"streams\": [\n                {\n                    \"bits_per_second\": 0, \n                    \"bytes\": 0, \n                    \"end\": 29.001052, \n                    \"omitted\": false, \n                    \"pmtu\": 1500, \n                    \"retransmits\": 0, \n                    \"rtt\": 49178, \n                    \"rttvar\": 42229, \n                    \"seconds\": 1, \n                    \"sender\": true, \n                    \"snd_cwnd\": 1448, \n                    \"snd_wnd\": -1, \n                    \"socket\": 5, \n                    \"start\": 28.001052\n                }\n            ], \n            \"sum\": {\n                \"bits_per_second\": 0, \n                \"bytes\": 0, \n                \"end\": 29.001052, \n                \"omitted\": false, \n                \"retransmits\": 0, \n                \"seconds\": 1, \n                \"sender\": true, \n                \"start\": 28.001052\n            }\n        }, \n        {\n            \"streams\": [\n                {\n                    \"bits_per_second\": 0, \n                    \"bytes\": 0, \n                    \"end\": 30.001052, \n                    \"omitted\": false, \n                    \"pmtu\": 1500, \n                    \"retransmits\": 0, \n                    \"rtt\": 49178, \n                    \"rttvar\": 42229, \n                    \"seconds\": 1, \n                    \"sender\": true, \n                    \"snd_cwnd\": 1448, \n                    \"snd_wnd\": -1, \n                    \"socket\": 5, \n                    \"start\": 29.001052\n                }\n            ], \n            \"sum\": {\n                \"bits_per_second\": 0, \n                \"bytes\": 0, \n                \"end\": 30.001052, \n                \"omitted\": false, \n                \"retransmits\": 0, \n                \"seconds\": 1, \n                \"sender\": true, \n                \"start\": 29.001052\n            }\n        }, \n        {\n            \"streams\": [\n                {\n                    \"bits_per_second\": 0, \n                    \"bytes\": 0, \n                    \"end\": 31.001054, \n                    \"omitted\": false, \n                    \"pmtu\": 1500, \n                    \"retransmits\": 0, \n                    \"rtt\": 49178, \n                    \"rttvar\": 42229, \n                    \"seconds\": 1.0000020265579224, \n                    \"sender\": true, \n                    \"snd_cwnd\": 1448, \n                    \"snd_wnd\": -1, \n                    \"socket\": 5, \n                    \"start\": 30.001052\n                }\n            ], \n            \"sum\": {\n                \"bits_per_second\": 0, \n                \"bytes\": 0, \n                \"end\": 31.001054, \n                \"omitted\": false, \n                \"retransmits\": 0, \n                \"seconds\": 1.0000020265579224, \n                \"sender\": true, \n                \"start\": 30.001052\n            }\n        }, \n        {\n            \"streams\": [\n                {\n                    \"bits_per_second\": 0, \n                    \"bytes\": 0, \n                    \"end\": 32.001049, \n                    \"omitted\": false, \n                    \"pmtu\": 1500, \n                    \"retransmits\": 0, \n                    \"rtt\": 49178, \n                    \"rttvar\": 42229, \n                    \"seconds\": 0.999994993209839, \n                    \"sender\": true, \n                    \"snd_cwnd\": 1448, \n                    \"snd_wnd\": -1, \n                    \"socket\": 5, \n                    \"start\": 31.001054\n                }\n            ], \n            \"sum\": {\n                \"bits_per_second\": 0, \n                \"bytes\": 0, \n                \"end\": 32.001049, \n                \"omitted\": false, \n                \"retransmits\": 0, \n                \"seconds\": 0.999994993209839, \n                \"sender\": true, \n                \"start\": 31.001054\n            }\n        }, \n        {\n            \"streams\": [\n                {\n                    \"bits_per_second\": 0, \n                    \"bytes\": 0, \n                    \"end\": 33.000616, \n                    \"omitted\": false, \n                    \"pmtu\": 1500, \n                    \"retransmits\": 0, \n                    \"rtt\": 49178, \n                    \"rttvar\": 42229, \n                    \"seconds\": 0.9995669722557068, \n                    \"sender\": true, \n                    \"snd_cwnd\": 1448, \n                    \"snd_wnd\": -1, \n                    \"socket\": 5, \n                    \"start\": 32.001049\n                }\n            ], \n            \"sum\": {\n                \"bits_per_second\": 0, \n                \"bytes\": 0, \n                \"end\": 33.000616, \n                \"omitted\": false, \n                \"retransmits\": 0, \n                \"seconds\": 0.9995669722557068, \n                \"sender\": true, \n                \"start\": 32.001049\n            }\n        }, \n        {\n            \"streams\": [\n                {\n                    \"bits_per_second\": 0, \n                    \"bytes\": 0, \n                    \"end\": 34.001046, \n                    \"omitted\": false, \n                    \"pmtu\": 1500, \n                    \"retransmits\": 0, \n                    \"rtt\": 49178, \n                    \"rttvar\": 42229, \n                    \"seconds\": 1.00042998790741, \n                    \"sender\": true, \n                    \"snd_cwnd\": 1448, \n                    \"snd_wnd\": -1, \n                    \"socket\": 5, \n                    \"start\": 33.000616\n                }\n            ], \n            \"sum\": {\n                \"bits_per_second\": 0, \n                \"bytes\": 0, \n                \"end\": 34.001046, \n                \"omitted\": false, \n                \"retransmits\": 0, \n                \"seconds\": 1.00042998790741, \n                \"sender\": true, \n                \"start\": 33.000616\n            }\n        }, \n        {\n            \"streams\": [\n                {\n                    \"bits_per_second\": 0, \n                    \"bytes\": 0, \n                    \"end\": 35.001047, \n                    \"omitted\": false, \n                    \"pmtu\": 1500, \n                    \"retransmits\": 0, \n                    \"rtt\": 49178, \n                    \"rttvar\": 42229, \n                    \"seconds\": 1.0000009536743164, \n                    \"sender\": true, \n                    \"snd_cwnd\": 1448, \n                    \"snd_wnd\": -1, \n                    \"socket\": 5, \n                    \"start\": 34.001046\n                }\n            ], \n            \"sum\": {\n                \"bits_per_second\": 0, \n                \"bytes\": 0, \n                \"end\": 35.001047, \n                \"omitted\": false, \n                \"retransmits\": 0, \n                \"seconds\": 1.0000009536743164, \n                \"sender\": true, \n                \"start\": 34.001046\n            }\n        }, \n        {\n            \"streams\": [\n                {\n                    \"bits_per_second\": 0, \n                    \"bytes\": 0, \n                    \"end\": 36.000603, \n                    \"omitted\": false, \n                    \"pmtu\": 1500, \n                    \"retransmits\": 1, \n                    \"rtt\": 49178, \n                    \"rttvar\": 42229, \n                    \"seconds\": 0.999556005001068, \n                    \"sender\": true, \n                    \"snd_cwnd\": 1448, \n                    \"snd_wnd\": -1, \n                    \"socket\": 5, \n                    \"start\": 35.001047\n                }\n            ], \n            \"sum\": {\n                \"bits_per_second\": 0, \n                \"bytes\": 0, \n                \"end\": 36.000603, \n                \"omitted\": false, \n                \"retransmits\": 1, \n                \"seconds\": 0.999556005001068, \n                \"sender\": true, \n                \"start\": 35.001047\n            }\n        }, \n        {\n            \"streams\": [\n                {\n                    \"bits_per_second\": 0, \n                    \"bytes\": 0, \n                    \"end\": 37.000957, \n                    \"omitted\": false, \n                    \"pmtu\": 1500, \n                    \"retransmits\": 0, \n                    \"rtt\": 49178, \n                    \"rttvar\": 42229, \n                    \"seconds\": 1.0003540515899658, \n                    \"sender\": true, \n                    \"snd_cwnd\": 1448, \n                    \"snd_wnd\": -1, \n                    \"socket\": 5, \n                    \"start\": 36.000603\n                }\n            ], \n            \"sum\": {\n                \"bits_per_second\": 0, \n                \"bytes\": 0, \n                \"end\": 37.000957, \n                \"omitted\": false, \n                \"retransmits\": 0, \n                \"seconds\": 1.0003540515899658, \n                \"sender\": true, \n                \"start\": 36.000603\n            }\n        }, \n        {\n            \"streams\": [\n                {\n                    \"bits_per_second\": 0, \n                    \"bytes\": 0, \n                    \"end\": 38.001048, \n                    \"omitted\": false, \n                    \"pmtu\": 1500, \n                    \"retransmits\": 0, \n                    \"rtt\": 49178, \n                    \"rttvar\": 42229, \n                    \"seconds\": 1.0000909566879272, \n                    \"sender\": true, \n                    \"snd_cwnd\": 1448, \n                    \"snd_wnd\": -1, \n                    \"socket\": 5, \n                    \"start\": 37.000957\n                }\n            ], \n            \"sum\": {\n                \"bits_per_second\": 0, \n                \"bytes\": 0, \n                \"end\": 38.001048, \n                \"omitted\": false, \n                \"retransmits\": 0, \n                \"seconds\": 1.0000909566879272, \n                \"sender\": true, \n                \"start\": 37.000957\n            }\n        }, \n        {\n            \"streams\": [\n                {\n                    \"bits_per_second\": 0, \n                    \"bytes\": 0, \n                    \"end\": 39.001053, \n                    \"omitted\": false, \n                    \"pmtu\": 1500, \n                    \"retransmits\": 0, \n                    \"rtt\": 49178, \n                    \"rttvar\": 42229, \n                    \"seconds\": 1.0000050067901611, \n                    \"sender\": true, \n                    \"snd_cwnd\": 1448, \n                    \"snd_wnd\": -1, \n                    \"socket\": 5, \n                    \"start\": 38.001048\n                }\n            ], \n            \"sum\": {\n                \"bits_per_second\": 0, \n                \"bytes\": 0, \n                \"end\": 39.001053, \n                \"omitted\": false, \n                \"retransmits\": 0, \n                \"seconds\": 1.0000050067901611, \n                \"sender\": true, \n                \"start\": 38.001048\n            }\n        }, \n        {\n            \"streams\": [\n                {\n                    \"bits_per_second\": 0, \n                    \"bytes\": 0, \n                    \"end\": 40.001048, \n                    \"omitted\": false, \n                    \"pmtu\": 1500, \n                    \"retransmits\": 0, \n                    \"rtt\": 49178, \n                    \"rttvar\": 42229, \n                    \"seconds\": 0.999994993209839, \n                    \"sender\": true, \n                    \"snd_cwnd\": 1448, \n                    \"snd_wnd\": -1, \n                    \"socket\": 5, \n                    \"start\": 39.001053\n                }\n            ], \n            \"sum\": {\n                \"bits_per_second\": 0, \n                \"bytes\": 0, \n                \"end\": 40.001048, \n                \"omitted\": false, \n                \"retransmits\": 0, \n                \"seconds\": 0.999994993209839, \n                \"sender\": true, \n                \"start\": 39.001053\n            }\n        }, \n        {\n            \"streams\": [\n                {\n                    \"bits_per_second\": 0, \n                    \"bytes\": 0, \n                    \"end\": 41.001052, \n                    \"omitted\": false, \n                    \"pmtu\": 1500, \n                    \"retransmits\": 0, \n                    \"rtt\": 49178, \n                    \"rttvar\": 42229, \n                    \"seconds\": 1.0000040531158447, \n                    \"sender\": true, \n                    \"snd_cwnd\": 1448, \n                    \"snd_wnd\": -1, \n                    \"socket\": 5, \n                    \"start\": 40.001048\n                }\n            ], \n            \"sum\": {\n                \"bits_per_second\": 0, \n                \"bytes\": 0, \n                \"end\": 41.001052, \n                \"omitted\": false, \n                \"retransmits\": 0, \n                \"seconds\": 1.0000040531158447, \n                \"sender\": true, \n                \"start\": 40.001048\n            }\n        }, \n        {\n            \"streams\": [\n                {\n                    \"bits_per_second\": 0, \n                    \"bytes\": 0, \n                    \"end\": 42.001053, \n                    \"omitted\": false, \n                    \"pmtu\": 1500, \n                    \"retransmits\": 0, \n                    \"rtt\": 49178, \n                    \"rttvar\": 42229, \n                    \"seconds\": 1.0000009536743164, \n                    \"sender\": true, \n                    \"snd_cwnd\": 1448, \n                    \"snd_wnd\": -1, \n                    \"socket\": 5, \n                    \"start\": 41.001052\n                }\n            ], \n            \"sum\": {\n                \"bits_per_second\": 0, \n                \"bytes\": 0, \n                \"end\": 42.001053, \n                \"omitted\": false, \n                \"retransmits\": 0, \n                \"seconds\": 1.0000009536743164, \n                \"sender\": true, \n                \"start\": 41.001052\n            }\n        }, \n        {\n            \"streams\": [\n                {\n                    \"bits_per_second\": 0, \n                    \"bytes\": 0, \n                    \"end\": 43.001061, \n                    \"omitted\": false, \n                    \"pmtu\": 1500, \n                    \"retransmits\": 0, \n                    \"rtt\": 49178, \n                    \"rttvar\": 42229, \n                    \"seconds\": 1.0000079870224, \n                    \"sender\": true, \n                    \"snd_cwnd\": 1448, \n                    \"snd_wnd\": -1, \n                    \"socket\": 5, \n                    \"start\": 42.001053\n                }\n            ], \n            \"sum\": {\n                \"bits_per_second\": 0, \n                \"bytes\": 0, \n                \"end\": 43.001061, \n                \"omitted\": false, \n                \"retransmits\": 0, \n                \"seconds\": 1.0000079870224, \n                \"sender\": true, \n                \"start\": 42.001053\n            }\n        }, \n        {\n            \"streams\": [\n                {\n                    \"bits_per_second\": 0, \n                    \"bytes\": 0, \n                    \"end\": 44.001058, \n                    \"omitted\": false, \n                    \"pmtu\": 1500, \n                    \"retransmits\": 0, \n                    \"rtt\": 49178, \n                    \"rttvar\": 42229, \n                    \"seconds\": 0.9999970197677612, \n                    \"sender\": true, \n                    \"snd_cwnd\": 1448, \n                    \"snd_wnd\": -1, \n                    \"socket\": 5, \n                    \"start\": 43.001061\n                }\n            ], \n            \"sum\": {\n                \"bits_per_second\": 0, \n                \"bytes\": 0, \n                \"end\": 44.001058, \n                \"omitted\": false, \n                \"retransmits\": 0, \n                \"seconds\": 0.9999970197677612, \n                \"sender\": true, \n                \"start\": 43.001061\n            }\n        }, \n        {\n            \"streams\": [\n                {\n                    \"bits_per_second\": 0, \n                    \"bytes\": 0, \n                    \"end\": 45.00106, \n                    \"omitted\": false, \n                    \"pmtu\": 1500, \n                    \"retransmits\": 0, \n                    \"rtt\": 49178, \n                    \"rttvar\": 42229, \n                    \"seconds\": 1.0000020265579224, \n                    \"sender\": true, \n                    \"snd_cwnd\": 1448, \n                    \"snd_wnd\": -1, \n                    \"socket\": 5, \n                    \"start\": 44.001058\n                }\n            ], \n            \"sum\": {\n                \"bits_per_second\": 0, \n                \"bytes\": 0, \n                \"end\": 45.00106, \n                \"omitted\": false, \n                \"retransmits\": 0, \n                \"seconds\": 1.0000020265579224, \n                \"sender\": true, \n                \"start\": 44.001058\n            }\n        }, \n        {\n            \"streams\": [\n                {\n                    \"bits_per_second\": 0, \n                    \"bytes\": 0, \n                    \"end\": 46.00106, \n                    \"omitted\": false, \n                    \"pmtu\": 1500, \n                    \"retransmits\": 0, \n                    \"rtt\": 49178, \n                    \"rttvar\": 42229, \n                    \"seconds\": 1, \n                    \"sender\": true, \n                    \"snd_cwnd\": 1448, \n                    \"snd_wnd\": -1, \n                    \"socket\": 5, \n                    \"start\": 45.00106\n                }\n            ], \n            \"sum\": {\n                \"bits_per_second\": 0, \n                \"bytes\": 0, \n                \"end\": 46.00106, \n                \"omitted\": false, \n                \"retransmits\": 0, \n                \"seconds\": 1, \n                \"sender\": true, \n                \"start\": 45.00106\n            }\n        }, \n        {\n            \"streams\": [\n                {\n                    \"bits_per_second\": 0, \n                    \"bytes\": 0, \n                    \"end\": 47.00106, \n                    \"omitted\": false, \n                    \"pmtu\": 1500, \n                    \"retransmits\": 0, \n                    \"rtt\": 49178, \n                    \"rttvar\": 42229, \n                    \"seconds\": 1, \n                    \"sender\": true, \n                    \"snd_cwnd\": 1448, \n                    \"snd_wnd\": -1, \n                    \"socket\": 5, \n                    \"start\": 46.00106\n                }\n            ], \n            \"sum\": {\n                \"bits_per_second\": 0, \n                \"bytes\": 0, \n                \"end\": 47.00106, \n                \"omitted\": false, \n                \"retransmits\": 0, \n                \"seconds\": 1, \n                \"sender\": true, \n                \"start\": 46.00106\n            }\n        }, \n        {\n            \"streams\": [\n                {\n                    \"bits_per_second\": 0, \n                    \"bytes\": 0, \n                    \"end\": 48.001054, \n                    \"omitted\": false, \n                    \"pmtu\": 1500, \n                    \"retransmits\": 0, \n                    \"rtt\": 49178, \n                    \"rttvar\": 42229, \n                    \"seconds\": 0.9999939799308777, \n                    \"sender\": true, \n                    \"snd_cwnd\": 1448, \n                    \"snd_wnd\": -1, \n                    \"socket\": 5, \n                    \"start\": 47.00106\n                }\n            ], \n            \"sum\": {\n                \"bits_per_second\": 0, \n                \"bytes\": 0, \n                \"end\": 48.001054, \n                \"omitted\": false, \n                \"retransmits\": 0, \n                \"seconds\": 0.9999939799308777, \n                \"sender\": true, \n                \"start\": 47.00106\n            }\n        }, \n        {\n            \"streams\": [\n                {\n                    \"bits_per_second\": 0, \n                    \"bytes\": 0, \n                    \"end\": 49.001061, \n                    \"omitted\": false, \n                    \"pmtu\": 1500, \n                    \"retransmits\": 0, \n                    \"rtt\": 49178, \n                    \"rttvar\": 42229, \n                    \"seconds\": 1.0000070333480835, \n                    \"sender\": true, \n                    \"snd_cwnd\": 1448, \n                    \"snd_wnd\": -1, \n                    \"socket\": 5, \n                    \"start\": 48.001054\n                }\n            ], \n            \"sum\": {\n                \"bits_per_second\": 0, \n                \"bytes\": 0, \n                \"end\": 49.001061, \n                \"omitted\": false, \n                \"retransmits\": 0, \n                \"seconds\": 1.0000070333480835, \n                \"sender\": true, \n                \"start\": 48.001054\n            }\n        }, \n        {\n            \"streams\": [\n                {\n                    \"bits_per_second\": 0, \n                    \"bytes\": 0, \n                    \"end\": 50.001076, \n                    \"omitted\": false, \n                    \"pmtu\": 1500, \n                    \"retransmits\": 1, \n                    \"rtt\": 49178, \n                    \"rttvar\": 42229, \n                    \"seconds\": 1.0000150203704834, \n                    \"sender\": true, \n                    \"snd_cwnd\": 1448, \n                    \"snd_wnd\": -1, \n                    \"socket\": 5, \n                    \"start\": 49.001061\n                }\n            ], \n            \"sum\": {\n                \"bits_per_second\": 0, \n                \"bytes\": 0, \n                \"end\": 50.001076, \n                \"omitted\": false, \n                \"retransmits\": 1, \n                \"seconds\": 1.0000150203704834, \n                \"sender\": true, \n                \"start\": 49.001061\n            }\n        }, \n        {\n            \"streams\": [\n                {\n                    \"bits_per_second\": 4693326.867017392, \n                    \"bytes\": 586440, \n                    \"end\": 51.000691, \n                    \"omitted\": false, \n                    \"pmtu\": 1500, \n                    \"retransmits\": 15, \n                    \"rtt\": 24228, \n                    \"rttvar\": 15150, \n                    \"seconds\": 0.9996150135993958, \n                    \"sender\": true, \n                    \"snd_cwnd\": 1448, \n                    \"snd_wnd\": -1, \n                    \"socket\": 5, \n                    \"start\": 50.001076\n                }\n            ], \n            \"sum\": {\n                \"bits_per_second\": 4693326.867017392, \n                \"bytes\": 586440, \n                \"end\": 51.000691, \n                \"omitted\": false, \n                \"retransmits\": 15, \n                \"seconds\": 0.9996150135993958, \n                \"sender\": true, \n                \"start\": 50.001076\n            }\n        }, \n        {\n            \"streams\": [\n                {\n                    \"bits_per_second\": 0, \n                    \"bytes\": 0, \n                    \"end\": 52.00106, \n                    \"omitted\": false, \n                    \"pmtu\": 1500, \n                    \"retransmits\": 1, \n                    \"rtt\": 24228, \n                    \"rttvar\": 15150, \n                    \"seconds\": 1.00036895275116, \n                    \"sender\": true, \n                    \"snd_cwnd\": 1448, \n                    \"snd_wnd\": -1, \n                    \"socket\": 5, \n                    \"start\": 51.000691\n                }\n            ], \n            \"sum\": {\n                \"bits_per_second\": 0, \n                \"bytes\": 0, \n                \"end\": 52.00106, \n                \"omitted\": false, \n                \"retransmits\": 1, \n                \"seconds\": 1.00036895275116, \n                \"sender\": true, \n                \"start\": 51.000691\n            }\n        }, \n        {\n            \"streams\": [\n                {\n                    \"bits_per_second\": 0, \n                    \"bytes\": 0, \n                    \"end\": 53.001056, \n                    \"omitted\": false, \n                    \"pmtu\": 1500, \n                    \"retransmits\": 27, \n                    \"rtt\": 23005, \n                    \"rttvar\": 3789, \n                    \"seconds\": 0.9999960064888, \n                    \"sender\": true, \n                    \"snd_cwnd\": 17376, \n                    \"snd_wnd\": -1, \n                    \"socket\": 5, \n                    \"start\": 52.00106\n                }\n            ], \n            \"sum\": {\n                \"bits_per_second\": 0, \n                \"bytes\": 0, \n                \"end\": 53.001056, \n                \"omitted\": false, \n                \"retransmits\": 27, \n                \"seconds\": 0.9999960064888, \n                \"sender\": true, \n                \"start\": 52.00106\n            }\n        }, \n        {\n            \"streams\": [\n                {\n                    \"bits_per_second\": 4692538.377079424, \n                    \"bytes\": 586440, \n                    \"end\": 54.000839, \n                    \"omitted\": false, \n                    \"pmtu\": 1500, \n                    \"retransmits\": 25, \n                    \"rtt\": 17574, \n                    \"rttvar\": 5389, \n                    \"seconds\": 0.9997829794883728, \n                    \"sender\": true, \n                    \"snd_cwnd\": 21720, \n                    \"snd_wnd\": -1, \n                    \"socket\": 5, \n                    \"start\": 53.001056\n                }\n            ], \n            \"sum\": {\n                \"bits_per_second\": 4692538.377079424, \n                \"bytes\": 586440, \n                \"end\": 54.000839, \n                \"omitted\": false, \n                \"retransmits\": 25, \n                \"seconds\": 0.9997829794883728, \n                \"sender\": true, \n                \"start\": 53.001056\n            }\n        }, \n        {\n            \"streams\": [\n                {\n                    \"bits_per_second\": 14082403.975135544, \n                    \"bytes\": 1759320, \n                    \"end\": 55.000282, \n                    \"omitted\": false, \n                    \"pmtu\": 1500, \n                    \"retransmits\": 0, \n                    \"rtt\": 27730, \n                    \"rttvar\": 419, \n                    \"seconds\": 0.999442994594574, \n                    \"sender\": true, \n                    \"snd_cwnd\": 78192, \n                    \"snd_wnd\": -1, \n                    \"socket\": 5, \n                    \"start\": 54.000839\n                }\n            ], \n            \"sum\": {\n                \"bits_per_second\": 14082403.975135544, \n                \"bytes\": 1759320, \n                \"end\": 55.000282, \n                \"omitted\": false, \n                \"retransmits\": 0, \n                \"seconds\": 0.999442994594574, \n                \"sender\": true, \n                \"start\": 54.000839\n            }\n        }, \n        {\n            \"streams\": [\n                {\n                    \"bits_per_second\": 18764185.375169184, \n                    \"bytes\": 2345760, \n                    \"end\": 56.000383, \n                    \"omitted\": false, \n                    \"pmtu\": 1500, \n                    \"retransmits\": 1, \n                    \"rtt\": 38716, \n                    \"rttvar\": 1401, \n                    \"seconds\": 1.0001009702682495, \n                    \"sender\": true, \n                    \"snd_cwnd\": 1448, \n                    \"snd_wnd\": -1, \n                    \"socket\": 5, \n                    \"start\": 55.000282\n                }\n            ], \n            \"sum\": {\n                \"bits_per_second\": 18764185.375169184, \n                \"bytes\": 2345760, \n                \"end\": 56.000383, \n                \"omitted\": false, \n                \"retransmits\": 1, \n                \"seconds\": 1.0001009702682495, \n                \"sender\": true, \n                \"start\": 55.000282\n            }\n        }, \n        {\n            \"streams\": [\n                {\n                    \"bits_per_second\": 0, \n                    \"bytes\": 0, \n                    \"end\": 57.001032, \n                    \"omitted\": false, \n                    \"pmtu\": 1500, \n                    \"retransmits\": 1, \n                    \"rtt\": 38716, \n                    \"rttvar\": 1401, \n                    \"seconds\": 1.0006489753723145, \n                    \"sender\": true, \n                    \"snd_cwnd\": 1448, \n                    \"snd_wnd\": -1, \n                    \"socket\": 5, \n                    \"start\": 56.000383\n                }\n            ], \n            \"sum\": {\n                \"bits_per_second\": 0, \n                \"bytes\": 0, \n                \"end\": 57.001032, \n                \"omitted\": false, \n                \"retransmits\": 1, \n                \"seconds\": 1.0006489753723145, \n                \"sender\": true, \n                \"start\": 56.000383\n            }\n        }, \n        {\n            \"streams\": [\n                {\n                    \"bits_per_second\": 0, \n                    \"bytes\": 0, \n                    \"end\": 58.001056, \n                    \"omitted\": false, \n                    \"pmtu\": 1500, \n                    \"retransmits\": 1, \n                    \"rtt\": 38716, \n                    \"rttvar\": 1401, \n                    \"seconds\": 1.0000239610672, \n                    \"sender\": true, \n                    \"snd_cwnd\": 1448, \n                    \"snd_wnd\": -1, \n                    \"socket\": 5, \n                    \"start\": 57.001032\n                }\n            ], \n            \"sum\": {\n                \"bits_per_second\": 0, \n                \"bytes\": 0, \n                \"end\": 58.001056, \n                \"omitted\": false, \n                \"retransmits\": 1, \n                \"seconds\": 1.0000239610672, \n                \"sender\": true, \n                \"start\": 57.001032\n            }\n        }, \n        {\n            \"streams\": [\n                {\n                    \"bits_per_second\": 0, \n                    \"bytes\": 0, \n                    \"end\": 59.001048, \n                    \"omitted\": false, \n                    \"pmtu\": 1500, \n                    \"retransmits\": 53, \n                    \"rtt\": 21388, \n                    \"rttvar\": 417, \n                    \"seconds\": 0.9999920129776, \n                    \"sender\": true, \n                    \"snd_cwnd\": 55024, \n                    \"snd_wnd\": -1, \n                    \"socket\": 5, \n                    \"start\": 58.001056\n                }\n            ], \n            \"sum\": {\n                \"bits_per_second\": 0, \n                \"bytes\": 0, \n                \"end\": 59.001048, \n                \"omitted\": false, \n                \"retransmits\": 53, \n                \"seconds\": 0.9999920129776, \n                \"sender\": true, \n                \"start\": 58.001056\n            }\n        }, \n        {\n            \"streams\": [\n                {\n                    \"bits_per_second\": 0, \n                    \"bytes\": 0, \n                    \"end\": 60.001069, \n                    \"omitted\": false, \n                    \"pmtu\": 1500, \n                    \"retransmits\": 0, \n                    \"rtt\": 21388, \n                    \"rttvar\": 417, \n                    \"seconds\": 1.000020980834961, \n                    \"sender\": true, \n                    \"snd_cwnd\": 55024, \n                    \"snd_wnd\": -1, \n                    \"socket\": 5, \n                    \"start\": 59.001048\n                }\n            ], \n            \"sum\": {\n                \"bits_per_second\": 0, \n                \"bytes\": 0, \n                \"end\": 60.001069, \n                \"omitted\": false, \n                \"retransmits\": 0, \n                \"seconds\": 1.000020980834961, \n                \"sender\": true, \n                \"start\": 59.001048\n            }\n        }\n    ], \n    \"start\": {\n        \"connected\": [\n            {\n                \"local_host\": \"172.16.0.2\", \n                \"local_port\": 42157, \n                \"remote_host\": \"172.16.0.1\", \n                \"remote_port\": 5201, \n                \"socket\": 5\n            }\n        ], \n        \"connecting_to\": {\n            \"host\": \"172.16.0.1\", \n            \"port\": 5201\n        }, \n        \"cookie\": \"szk6saqk7e7rpb2viaeobbikjq57tvh5spvu\", \n        \"fq_rate\": 0, \n        \"rcvbuf_actual\": 87380, \n        \"sndbuf_actual\": 65536, \n        \"sock_bufsize\": 0, \n        \"system_info\": \"REDACTED\", \n        \"target_bitrate\": 0, \n        \"tcp_mss_default\": 1448, \n        \"test_start\": {\n            \"bidir\": 0, \n            \"blksize\": 131072, \n            \"blocks\": 0, \n            \"bytes\": 0, \n            \"duration\": 60, \n            \"fqrate\": 0, \n            \"num_streams\": 1, \n            \"omit\": 0, \n            \"protocol\": \"TCP\", \n            \"reverse\": 0, \n            \"target_bitrate\": 0, \n            \"tos\": 0\n        }, \n        \"timestamp\": {\n            \"time\": \"Wed, 16 Oct 2024 03:08:16 GMT\", \n            \"timesecs\": 1729048096\n        }, \n        \"version\": \"iperf 3.14\"\n    }\n}\nParticipant 1:\n/usr/bin/iperf3 --use-pkcs1-padding -s -1 --idle-timeout 60 --json -p 5201 -B 172.16.0.1 --authorized-users-path /var/pscheduler-server/runner/tmp/tmpwhi_uf5n/tmppn9uy1hs/credentials --rsa-private-key-path /var/pscheduler-server/runner/tmp/tmpwhi_uf5n/tmppn9uy1hs/private-key\n\n{\n    \"end\": {\n        \"cpu_utilization_percent\": {\n            \"host_system\": 0.47636170529665256, \n            \"host_total\": 0.6449191044078136, \n            \"host_user\": 0.1685524021528096, \n            \"remote_system\": 0, \n            \"remote_total\": 0, \n            \"remote_user\": 0\n        }, \n        \"receiver_tcp_congestion\": \"htcp\", \n        \"streams\": [\n            {\n                \"receiver\": {\n                    \"bits_per_second\": 3075857.549410338, \n                    \"bytes\": 23082936, \n                    \"end\": 60.036424, \n                    \"seconds\": 60.036424, \n                    \"sender\": false, \n                    \"socket\": 5, \n                    \"start\": 0\n                }, \n                \"sender\": {\n                    \"bits_per_second\": 0, \n                    \"bytes\": 0, \n                    \"end\": 60.036424, \n                    \"seconds\": 60.036424, \n                    \"sender\": false, \n                    \"socket\": 5, \n                    \"start\": 0\n                }\n            }\n        ], \n        \"sum_received\": {\n            \"bits_per_second\": 3075857.549410338, \n            \"bytes\": 23082936, \n            \"end\": 60.036424, \n            \"seconds\": 60.036424, \n            \"sender\": false, \n            \"start\": 0\n        }, \n        \"sum_sent\": {\n            \"bits_per_second\": 0, \n            \"bytes\": 0, \n            \"end\": 60.036424, \n            \"seconds\": 60.036424, \n            \"sender\": false, \n            \"start\": 0\n        }\n    }, \n    \"intervals\": [\n        {\n            \"streams\": [\n                {\n                    \"bits_per_second\": 0, \n                    \"bytes\": 0, \n                    \"end\": 1.000384, \n                    \"omitted\": false, \n                    \"seconds\": 1.000383973121643, \n                    \"sender\": false, \n                    \"socket\": 5, \n                    \"start\": 0\n                }\n            ], \n            \"sum\": {\n                \"bits_per_second\": 0, \n                \"bytes\": 0, \n                \"end\": 1.000384, \n                \"omitted\": false, \n                \"seconds\": 1.000383973121643, \n                \"sender\": false, \n                \"start\": 0\n            }\n        }, \n        {\n            \"streams\": [\n                {\n                    \"bits_per_second\": 0, \n                    \"bytes\": 0, \n                    \"end\": 2.001115, \n                    \"omitted\": false, \n                    \"seconds\": 1.0007309913635254, \n                    \"sender\": false, \n                    \"socket\": 5, \n                    \"start\": 1.000384\n                }\n            ], \n            \"sum\": {\n                \"bits_per_second\": 0, \n                \"bytes\": 0, \n                \"end\": 2.001115, \n                \"omitted\": false, \n                \"seconds\": 1.0007309913635254, \n                \"sender\": false, \n                \"start\": 1.000384\n            }\n        }, \n        {\n            \"streams\": [\n                {\n                    \"bits_per_second\": 0, \n                    \"bytes\": 0, \n                    \"end\": 3.001277, \n                    \"omitted\": false, \n                    \"seconds\": 1.0001620054244995, \n                    \"sender\": false, \n                    \"socket\": 5, \n                    \"start\": 2.001115\n                }\n            ], \n            \"sum\": {\n                \"bits_per_second\": 0, \n                \"bytes\": 0, \n                \"end\": 3.001277, \n                \"omitted\": false, \n                \"seconds\": 1.0001620054244995, \n                \"sender\": false, \n                \"start\": 2.001115\n            }\n        }, \n        {\n            \"streams\": [\n                {\n                    \"bits_per_second\": 1048706.0161190943, \n                    \"bytes\": 131072, \n                    \"end\": 4.001153, \n                    \"omitted\": false, \n                    \"seconds\": 0.9998760223388672, \n                    \"sender\": false, \n                    \"socket\": 5, \n                    \"start\": 3.001277\n                }\n            ], \n            \"sum\": {\n                \"bits_per_second\": 1048706.0161190943, \n                \"bytes\": 131072, \n                \"end\": 4.001153, \n                \"omitted\": false, \n                \"seconds\": 0.9998760223388672, \n                \"sender\": false, \n                \"start\": 3.001277\n            }\n        }, \n        {\n            \"streams\": [\n                {\n                    \"bits_per_second\": 19939174.89978733, \n                    \"bytes\": 2490368, \n                    \"end\": 5.000339, \n                    \"omitted\": false, \n                    \"seconds\": 0.9991859793663025, \n                    \"sender\": false, \n                    \"socket\": 5, \n                    \"start\": 4.001153\n                }\n            ], \n            \"sum\": {\n                \"bits_per_second\": 19939174.89978733, \n                \"bytes\": 2490368, \n                \"end\": 5.000339, \n                \"omitted\": false, \n                \"seconds\": 0.9991859793663025, \n                \"sender\": false, \n                \"start\": 4.001153\n            }\n        }, \n        {\n            \"streams\": [\n                {\n                    \"bits_per_second\": 20955971.53631663, \n                    \"bytes\": 2621440, \n                    \"end\": 6.001081, \n                    \"omitted\": false, \n                    \"seconds\": 1.000741958618164, \n                    \"sender\": false, \n                    \"socket\": 5, \n                    \"start\": 5.000339\n                }\n            ], \n            \"sum\": {\n                \"bits_per_second\": 20955971.53631663, \n                \"bytes\": 2621440, \n                \"end\": 6.001081, \n                \"omitted\": false, \n                \"seconds\": 1.000741958618164, \n                \"sender\": false, \n                \"start\": 5.000339\n            }\n        }, \n        {\n            \"streams\": [\n                {\n                    \"bits_per_second\": 22020075.000020027, \n                    \"bytes\": 2752512, \n                    \"end\": 7.001082, \n                    \"omitted\": false, \n                    \"seconds\": 1.0000009536743164, \n                    \"sender\": false, \n                    \"socket\": 5, \n                    \"start\": 6.001081\n                }\n            ], \n            \"sum\": {\n                \"bits_per_second\": 22020075.000020027, \n                \"bytes\": 2752512, \n                \"end\": 7.001082, \n                \"omitted\": false, \n                \"seconds\": 1.0000009536743164, \n                \"sender\": false, \n                \"start\": 6.001081\n            }\n        }, \n        {\n            \"streams\": [\n                {\n                    \"bits_per_second\": 22020030.375195578, \n                    \"bytes\": 2752512, \n                    \"end\": 8.001085, \n                    \"omitted\": false, \n                    \"seconds\": 1.0000029802322388, \n                    \"sender\": false, \n                    \"socket\": 5, \n                    \"start\": 7.001082\n                }\n            ], \n            \"sum\": {\n                \"bits_per_second\": 22020030.375195578, \n                \"bytes\": 2752512, \n                \"end\": 8.001085, \n                \"omitted\": false, \n                \"seconds\": 1.0000029802322388, \n                \"sender\": false, \n                \"start\": 7.001082\n            }\n        }, \n        {\n            \"streams\": [\n                {\n                    \"bits_per_second\": 19921450.2370063, \n                    \"bytes\": 2490368, \n                    \"end\": 9.00116, \n                    \"omitted\": false, \n                    \"seconds\": 1.0000749826431274, \n                    \"sender\": false, \n                    \"socket\": 5, \n                    \"start\": 8.001085\n                }\n            ], \n            \"sum\": {\n                \"bits_per_second\": 19921450.2370063, \n                \"bytes\": 2490368, \n                \"end\": 9.00116, \n                \"omitted\": false, \n                \"seconds\": 1.0000749826431274, \n                \"sender\": false, \n                \"start\": 8.001085\n            }\n        }, \n        {\n            \"streams\": [\n                {\n                    \"bits_per_second\": 12584019.097398505, \n                    \"bytes\": 1572864, \n                    \"end\": 10.001072, \n                    \"omitted\": false, \n                    \"seconds\": 0.9999120235443115, \n                    \"sender\": false, \n                    \"socket\": 5, \n                    \"start\": 9.00116\n                }\n            ], \n            \"sum\": {\n                \"bits_per_second\": 12584019.097398505, \n                \"bytes\": 1572864, \n                \"end\": 10.001072, \n                \"omitted\": false, \n                \"seconds\": 0.9999120235443115, \n                \"sender\": false, \n                \"start\": 9.00116\n            }\n        }, \n        {\n            \"streams\": [\n                {\n                    \"bits_per_second\": 2097005.260268238, \n                    \"bytes\": 262144, \n                    \"end\": 11.001142, \n                    \"omitted\": false, \n                    \"seconds\": 1.0000699758529663, \n                    \"sender\": false, \n                    \"socket\": 5, \n                    \"start\": 10.001072\n                }\n            ], \n            \"sum\": {\n                \"bits_per_second\": 2097005.260268238, \n                \"bytes\": 262144, \n                \"end\": 11.001142, \n                \"omitted\": false, \n                \"seconds\": 1.0000699758529663, \n                \"sender\": false, \n                \"start\": 10.001072\n            }\n        }, \n        {\n            \"streams\": [\n                {\n                    \"bits_per_second\": 7340127.3762393, \n                    \"bytes\": 917504, \n                    \"end\": 12.001129, \n                    \"omitted\": false, \n                    \"seconds\": 0.999987006187439, \n                    \"sender\": false, \n                    \"socket\": 5, \n                    \"start\": 11.001142\n                }\n            ], \n            \"sum\": {\n                \"bits_per_second\": 7340127.3762393, \n                \"bytes\": 917504, \n                \"end\": 12.001129, \n                \"omitted\": false, \n                \"seconds\": 0.999987006187439, \n                \"sender\": false, \n                \"start\": 11.001142\n            }\n        }, \n        {\n            \"streams\": [\n                {\n                    \"bits_per_second\": 8388750.502420735, \n                    \"bytes\": 1048576, \n                    \"end\": 13.001112, \n                    \"omitted\": false, \n                    \"seconds\": 0.999983012676239, \n                    \"sender\": false, \n                    \"socket\": 5, \n                    \"start\": 12.001129\n                }\n            ], \n            \"sum\": {\n                \"bits_per_second\": 8388750.502420735, \n                \"bytes\": 1048576, \n                \"end\": 13.001112, \n                \"omitted\": false, \n                \"seconds\": 0.999983012676239, \n                \"sender\": false, \n                \"start\": 12.001129\n            }\n        }, \n        {\n            \"streams\": [\n                {\n                    \"bits_per_second\": 0, \n                    \"bytes\": 0, \n                    \"end\": 14.001099, \n                    \"omitted\": false, \n                    \"seconds\": 0.999987006187439, \n                    \"sender\": false, \n                    \"socket\": 5, \n                    \"start\": 13.001112\n                }\n            ], \n            \"sum\": {\n                \"bits_per_second\": 0, \n                \"bytes\": 0, \n                \"end\": 14.001099, \n                \"omitted\": false, \n                \"seconds\": 0.999987006187439, \n                \"sender\": false, \n                \"start\": 13.001112\n            }\n        }, \n        {\n            \"streams\": [\n                {\n                    \"bits_per_second\": 0, \n                    \"bytes\": 0, \n                    \"end\": 15.001107, \n                    \"omitted\": false, \n                    \"seconds\": 1.0000079870224, \n                    \"sender\": false, \n                    \"socket\": 5, \n                    \"start\": 14.001099\n                }\n            ], \n            \"sum\": {\n                \"bits_per_second\": 0, \n                \"bytes\": 0, \n                \"end\": 15.001107, \n                \"omitted\": false, \n                \"seconds\": 1.0000079870224, \n                \"sender\": false, \n                \"start\": 14.001099\n            }\n        }, \n        {\n            \"streams\": [\n                {\n                    \"bits_per_second\": 1048528.8771177919, \n                    \"bytes\": 131072, \n                    \"end\": 16.001152, \n                    \"omitted\": false, \n                    \"seconds\": 1.0000449419021606, \n                    \"sender\": false, \n                    \"socket\": 5, \n                    \"start\": 15.001107\n                }\n            ], \n            \"sum\": {\n                \"bits_per_second\": 1048528.8771177919, \n                \"bytes\": 131072, \n                \"end\": 16.001152, \n                \"omitted\": false, \n                \"seconds\": 1.0000449419021606, \n                \"sender\": false, \n                \"start\": 15.001107\n            }\n        }, \n        {\n            \"streams\": [\n                {\n                    \"bits_per_second\": 0, \n                    \"bytes\": 0, \n                    \"end\": 17.001118, \n                    \"omitted\": false, \n                    \"seconds\": 0.999966025352478, \n                    \"sender\": false, \n                    \"socket\": 5, \n                    \"start\": 16.001152\n                }\n            ], \n            \"sum\": {\n                \"bits_per_second\": 0, \n                \"bytes\": 0, \n                \"end\": 17.001118, \n                \"omitted\": false, \n                \"seconds\": 0.999966025352478, \n                \"sender\": false, \n                \"start\": 16.001152\n            }\n        }, \n        {\n            \"streams\": [\n                {\n                    \"bits_per_second\": 0, \n                    \"bytes\": 0, \n                    \"end\": 18.000057, \n                    \"omitted\": false, \n                    \"seconds\": 0.9989389777183533, \n                    \"sender\": false, \n                    \"socket\": 5, \n                    \"start\": 17.001118\n                }\n            ], \n            \"sum\": {\n                \"bits_per_second\": 0, \n                \"bytes\": 0, \n                \"end\": 18.000057, \n                \"omitted\": false, \n                \"seconds\": 0.9989389777183533, \n                \"sender\": false, \n                \"start\": 17.001118\n            }\n        }, \n        {\n            \"streams\": [\n                {\n                    \"bits_per_second\": 0, \n                    \"bytes\": 0, \n                    \"end\": 19.000171, \n                    \"omitted\": false, \n                    \"seconds\": 1.0001139640808105, \n                    \"sender\": false, \n                    \"socket\": 5, \n                    \"start\": 18.000057\n                }\n            ], \n            \"sum\": {\n                \"bits_per_second\": 0, \n                \"bytes\": 0, \n                \"end\": 19.000171, \n                \"omitted\": false, \n                \"seconds\": 1.0001139640808105, \n                \"sender\": false, \n                \"start\": 18.000057\n            }\n        }, \n        {\n            \"streams\": [\n                {\n                    \"bits_per_second\": 5237783.708621291, \n                    \"bytes\": 655360, \n                    \"end\": 20.001144, \n                    \"omitted\": false, \n                    \"seconds\": 1.0009729862213135, \n                    \"sender\": false, \n                    \"socket\": 5, \n                    \"start\": 19.000171\n                }\n            ], \n            \"sum\": {\n                \"bits_per_second\": 5237783.708621291, \n                \"bytes\": 655360, \n                \"end\": 20.001144, \n                \"omitted\": false, \n                \"seconds\": 1.0009729862213135, \n                \"sender\": false, \n                \"start\": 19.000171\n            }\n        }, \n        {\n            \"streams\": [\n                {\n                    \"bits_per_second\": 0, \n                    \"bytes\": 0, \n                    \"end\": 21.001099, \n                    \"omitted\": false, \n                    \"seconds\": 0.9999549984931946, \n                    \"sender\": false, \n                    \"socket\": 5, \n                    \"start\": 20.001144\n                }\n            ], \n            \"sum\": {\n                \"bits_per_second\": 0, \n                \"bytes\": 0, \n                \"end\": 21.001099, \n                \"omitted\": false, \n                \"seconds\": 0.9999549984931946, \n                \"sender\": false, \n                \"start\": 20.001144\n            }\n        }, \n        {\n            \"streams\": [\n                {\n                    \"bits_per_second\": 1049556.290596106, \n                    \"bytes\": 131072, \n                    \"end\": 22.000165, \n                    \"omitted\": false, \n                    \"seconds\": 0.9990659952163696, \n                    \"sender\": false, \n                    \"socket\": 5, \n                    \"start\": 21.001099\n                }\n            ], \n            \"sum\": {\n                \"bits_per_second\": 1049556.290596106, \n                \"bytes\": 131072, \n                \"end\": 22.000165, \n                \"omitted\": false, \n                \"seconds\": 0.9990659952163696, \n                \"sender\": false, \n                \"start\": 21.001099\n            }\n        }, \n        {\n            \"streams\": [\n                {\n                    \"bits_per_second\": 0, \n                    \"bytes\": 0, \n                    \"end\": 23.000201, \n                    \"omitted\": false, \n                    \"seconds\": 1.0000360012054443, \n                    \"sender\": false, \n                    \"socket\": 5, \n                    \"start\": 22.000165\n                }\n            ], \n            \"sum\": {\n                \"bits_per_second\": 0, \n                \"bytes\": 0, \n                \"end\": 23.000201, \n                \"omitted\": false, \n                \"seconds\": 1.0000360012054443, \n                \"sender\": false, \n                \"start\": 22.000165\n            }\n        }, \n        {\n            \"streams\": [\n                {\n                    \"bits_per_second\": 0, \n                    \"bytes\": 0, \n                    \"end\": 24.000259, \n                    \"omitted\": false, \n                    \"seconds\": 1.0000580549240112, \n                    \"sender\": false, \n                    \"socket\": 5, \n                    \"start\": 23.000201\n                }\n            ], \n            \"sum\": {\n                \"bits_per_second\": 0, \n                \"bytes\": 0, \n                \"end\": 24.000259, \n                \"omitted\": false, \n                \"seconds\": 1.0000580549240112, \n                \"sender\": false, \n                \"start\": 23.000201\n            }\n        }, \n        {\n            \"streams\": [\n                {\n                    \"bits_per_second\": 0, \n                    \"bytes\": 0, \n                    \"end\": 25.001096, \n                    \"omitted\": false, \n                    \"seconds\": 1.000836968421936, \n                    \"sender\": false, \n                    \"socket\": 5, \n                    \"start\": 24.000259\n                }\n            ], \n            \"sum\": {\n                \"bits_per_second\": 0, \n                \"bytes\": 0, \n                \"end\": 25.001096, \n                \"omitted\": false, \n                \"seconds\": 1.000836968421936, \n                \"sender\": false, \n                \"start\": 24.000259\n            }\n        }, \n        {\n            \"streams\": [\n                {\n                    \"bits_per_second\": 0, \n                    \"bytes\": 0, \n                    \"end\": 26.001152, \n                    \"omitted\": false, \n                    \"seconds\": 1.0000560283660889, \n                    \"sender\": false, \n                    \"socket\": 5, \n                    \"start\": 25.001096\n                }\n            ], \n            \"sum\": {\n                \"bits_per_second\": 0, \n                \"bytes\": 0, \n                \"end\": 26.001152, \n                \"omitted\": false, \n                \"seconds\": 1.0000560283660889, \n                \"sender\": false, \n                \"start\": 25.001096\n            }\n        }, \n        {\n            \"streams\": [\n                {\n                    \"bits_per_second\": 0, \n                    \"bytes\": 0, \n                    \"end\": 27.001146, \n                    \"omitted\": false, \n                    \"seconds\": 0.9999939799308777, \n                    \"sender\": false, \n                    \"socket\": 5, \n                    \"start\": 26.001152\n                }\n            ], \n            \"sum\": {\n                \"bits_per_second\": 0, \n                \"bytes\": 0, \n                \"end\": 27.001146, \n                \"omitted\": false, \n                \"seconds\": 0.9999939799308777, \n                \"sender\": false, \n                \"start\": 26.001152\n            }\n        }, \n        {\n            \"streams\": [\n                {\n                    \"bits_per_second\": 0, \n                    \"bytes\": 0, \n                    \"end\": 28.001149, \n                    \"omitted\": false, \n                    \"seconds\": 1.0000029802322388, \n                    \"sender\": false, \n                    \"socket\": 5, \n                    \"start\": 27.001146\n                }\n            ], \n            \"sum\": {\n                \"bits_per_second\": 0, \n                \"bytes\": 0, \n                \"end\": 28.001149, \n                \"omitted\": false, \n                \"seconds\": 1.0000029802322388, \n                \"sender\": false, \n                \"start\": 27.001146\n            }\n        }, \n        {\n            \"streams\": [\n                {\n                    \"bits_per_second\": 0, \n                    \"bytes\": 0, \n                    \"end\": 29.0011, \n                    \"omitted\": false, \n                    \"seconds\": 0.9999510049819946, \n                    \"sender\": false, \n                    \"socket\": 5, \n                    \"start\": 28.001149\n                }\n            ], \n            \"sum\": {\n                \"bits_per_second\": 0, \n                \"bytes\": 0, \n                \"end\": 29.0011, \n                \"omitted\": false, \n                \"seconds\": 0.9999510049819946, \n                \"sender\": false, \n                \"start\": 28.001149\n            }\n        }, \n        {\n            \"streams\": [\n                {\n                    \"bits_per_second\": 0, \n                    \"bytes\": 0, \n                    \"end\": 30.001135, \n                    \"omitted\": false, \n                    \"seconds\": 1.000035047531128, \n                    \"sender\": false, \n                    \"socket\": 5, \n                    \"start\": 29.0011\n                }\n            ], \n            \"sum\": {\n                \"bits_per_second\": 0, \n                \"bytes\": 0, \n                \"end\": 30.001135, \n                \"omitted\": false, \n                \"seconds\": 1.000035047531128, \n                \"sender\": false, \n                \"start\": 29.0011\n            }\n        }, \n        {\n            \"streams\": [\n                {\n                    \"bits_per_second\": 0, \n                    \"bytes\": 0, \n                    \"end\": 31.001123, \n                    \"omitted\": false, \n                    \"seconds\": 0.9999880194664, \n                    \"sender\": false, \n                    \"socket\": 5, \n                    \"start\": 30.001135\n                }\n            ], \n            \"sum\": {\n                \"bits_per_second\": 0, \n                \"bytes\": 0, \n                \"end\": 31.001123, \n                \"omitted\": false, \n                \"seconds\": 0.9999880194664, \n                \"sender\": false, \n                \"start\": 30.001135\n            }\n        }, \n        {\n            \"streams\": [\n                {\n                    \"bits_per_second\": 114100.81925661219, \n                    \"bytes\": 14264, \n                    \"end\": 32.001221, \n                    \"omitted\": false, \n                    \"seconds\": 1.0000979900360107, \n                    \"sender\": false, \n                    \"socket\": 5, \n                    \"start\": 31.001123\n                }\n            ], \n            \"sum\": {\n                \"bits_per_second\": 114100.81925661219, \n                \"bytes\": 14264, \n                \"end\": 32.001221, \n                \"omitted\": false, \n                \"seconds\": 1.0000979900360107, \n                \"sender\": false, \n                \"start\": 31.001123\n            }\n        }, \n        {\n            \"streams\": [\n                {\n                    \"bits_per_second\": 0, \n                    \"bytes\": 0, \n                    \"end\": 33.001144, \n                    \"omitted\": false, \n                    \"seconds\": 0.9999229907989502, \n                    \"sender\": false, \n                    \"socket\": 5, \n                    \"start\": 32.001221\n                }\n            ], \n            \"sum\": {\n                \"bits_per_second\": 0, \n                \"bytes\": 0, \n                \"end\": 33.001144, \n                \"omitted\": false, \n                \"seconds\": 0.9999229907989502, \n                \"sender\": false, \n                \"start\": 32.001221\n            }\n        }, \n        {\n            \"streams\": [\n                {\n                    \"bits_per_second\": 0, \n                    \"bytes\": 0, \n                    \"end\": 34.001116, \n                    \"omitted\": false, \n                    \"seconds\": 0.9999719858169556, \n                    \"sender\": false, \n                    \"socket\": 5, \n                    \"start\": 33.001144\n                }\n            ], \n            \"sum\": {\n                \"bits_per_second\": 0, \n                \"bytes\": 0, \n                \"end\": 34.001116, \n                \"omitted\": false, \n                \"seconds\": 0.9999719858169556, \n                \"sender\": false, \n                \"start\": 33.001144\n            }\n        }, \n        {\n            \"streams\": [\n                {\n                    \"bits_per_second\": 0, \n                    \"bytes\": 0, \n                    \"end\": 35.001145, \n                    \"omitted\": false, \n                    \"seconds\": 1.0000289678573608, \n                    \"sender\": false, \n                    \"socket\": 5, \n                    \"start\": 34.001116\n                }\n            ], \n            \"sum\": {\n                \"bits_per_second\": 0, \n                \"bytes\": 0, \n                \"end\": 35.001145, \n                \"omitted\": false, \n                \"seconds\": 1.0000289678573608, \n                \"sender\": false, \n                \"start\": 34.001116\n            }\n        }, \n        {\n            \"streams\": [\n                {\n                    \"bits_per_second\": 0, \n                    \"bytes\": 0, \n                    \"end\": 36.001114, \n                    \"omitted\": false, \n                    \"seconds\": 0.9999690055847168, \n                    \"sender\": false, \n                    \"socket\": 5, \n                    \"start\": 35.001145\n                }\n            ], \n            \"sum\": {\n                \"bits_per_second\": 0, \n                \"bytes\": 0, \n                \"end\": 36.001114, \n                \"omitted\": false, \n                \"seconds\": 0.9999690055847168, \n                \"sender\": false, \n                \"start\": 35.001145\n            }\n        }, \n        {\n            \"streams\": [\n                {\n                    \"bits_per_second\": 0, \n                    \"bytes\": 0, \n                    \"end\": 37.001124, \n                    \"omitted\": false, \n                    \"seconds\": 1.0000100135803223, \n                    \"sender\": false, \n                    \"socket\": 5, \n                    \"start\": 36.001114\n                }\n            ], \n            \"sum\": {\n                \"bits_per_second\": 0, \n                \"bytes\": 0, \n                \"end\": 37.001124, \n                \"omitted\": false, \n                \"seconds\": 1.0000100135803223, \n                \"sender\": false, \n                \"start\": 36.001114\n            }\n        }, \n        {\n            \"streams\": [\n                {\n                    \"bits_per_second\": 0, \n                    \"bytes\": 0, \n                    \"end\": 38.001148, \n                    \"omitted\": false, \n                    \"seconds\": 1.0000239610672, \n                    \"sender\": false, \n                    \"socket\": 5, \n                    \"start\": 37.001124\n                }\n            ], \n            \"sum\": {\n                \"bits_per_second\": 0, \n                \"bytes\": 0, \n                \"end\": 38.001148, \n                \"omitted\": false, \n                \"seconds\": 1.0000239610672, \n                \"sender\": false, \n                \"start\": 37.001124\n            }\n        }, \n        {\n            \"streams\": [\n                {\n                    \"bits_per_second\": 0, \n                    \"bytes\": 0, \n                    \"end\": 39.00112, \n                    \"omitted\": false, \n                    \"seconds\": 0.9999719858169556, \n                    \"sender\": false, \n                    \"socket\": 5, \n                    \"start\": 38.001148\n                }\n            ], \n            \"sum\": {\n                \"bits_per_second\": 0, \n                \"bytes\": 0, \n                \"end\": 39.00112, \n                \"omitted\": false, \n                \"seconds\": 0.9999719858169556, \n                \"sender\": false, \n                \"start\": 38.001148\n            }\n        }, \n        {\n            \"streams\": [\n                {\n                    \"bits_per_second\": 0, \n                    \"bytes\": 0, \n                    \"end\": 40.001125, \n                    \"omitted\": false, \n                    \"seconds\": 1.0000050067901611, \n                    \"sender\": false, \n                    \"socket\": 5, \n                    \"start\": 39.00112\n                }\n            ], \n            \"sum\": {\n                \"bits_per_second\": 0, \n                \"bytes\": 0, \n                \"end\": 40.001125, \n                \"omitted\": false, \n                \"seconds\": 1.0000050067901611, \n                \"sender\": false, \n                \"start\": 39.00112\n            }\n        }, \n        {\n            \"streams\": [\n                {\n                    \"bits_per_second\": 0, \n                    \"bytes\": 0, \n                    \"end\": 41.000142, \n                    \"omitted\": false, \n                    \"seconds\": 0.9990170001983643, \n                    \"sender\": false, \n                    \"socket\": 5, \n                    \"start\": 40.001125\n                }\n            ], \n            \"sum\": {\n                \"bits_per_second\": 0, \n                \"bytes\": 0, \n                \"end\": 41.000142, \n                \"omitted\": false, \n                \"seconds\": 0.9990170001983643, \n                \"sender\": false, \n                \"start\": 40.001125\n            }\n        }, \n        {\n            \"streams\": [\n                {\n                    \"bits_per_second\": 0, \n                    \"bytes\": 0, \n                    \"end\": 42.000117, \n                    \"omitted\": false, \n                    \"seconds\": 0.999975025653839, \n                    \"sender\": false, \n                    \"socket\": 5, \n                    \"start\": 41.000142\n                }\n            ], \n            \"sum\": {\n                \"bits_per_second\": 0, \n                \"bytes\": 0, \n                \"end\": 42.000117, \n                \"omitted\": false, \n                \"seconds\": 0.999975025653839, \n                \"sender\": false, \n                \"start\": 41.000142\n            }\n        }, \n        {\n            \"streams\": [\n                {\n                    \"bits_per_second\": 0, \n                    \"bytes\": 0, \n                    \"end\": 43.000381, \n                    \"omitted\": false, \n                    \"seconds\": 1.000264048576355, \n                    \"sender\": false, \n                    \"socket\": 5, \n                    \"start\": 42.000117\n                }\n            ], \n            \"sum\": {\n                \"bits_per_second\": 0, \n                \"bytes\": 0, \n                \"end\": 43.000381, \n                \"omitted\": false, \n                \"seconds\": 1.000264048576355, \n                \"sender\": false, \n                \"start\": 42.000117\n            }\n        }, \n        {\n            \"streams\": [\n                {\n                    \"bits_per_second\": 0, \n                    \"bytes\": 0, \n                    \"end\": 44.000209, \n                    \"omitted\": false, \n                    \"seconds\": 0.9998279809951782, \n                    \"sender\": false, \n                    \"socket\": 5, \n                    \"start\": 43.000381\n                }\n            ], \n            \"sum\": {\n                \"bits_per_second\": 0, \n                \"bytes\": 0, \n                \"end\": 44.000209, \n                \"omitted\": false, \n                \"seconds\": 0.9998279809951782, \n                \"sender\": false, \n                \"start\": 43.000381\n            }\n        }, \n        {\n            \"streams\": [\n                {\n                    \"bits_per_second\": 0, \n                    \"bytes\": 0, \n                    \"end\": 45.000056, \n                    \"omitted\": false, \n                    \"seconds\": 0.9998469948768616, \n                    \"sender\": false, \n                    \"socket\": 5, \n                    \"start\": 44.000209\n                }\n            ], \n            \"sum\": {\n                \"bits_per_second\": 0, \n                \"bytes\": 0, \n                \"end\": 45.000056, \n                \"omitted\": false, \n                \"seconds\": 0.9998469948768616, \n                \"sender\": false, \n                \"start\": 44.000209\n            }\n        }, \n        {\n            \"streams\": [\n                {\n                    \"bits_per_second\": 0, \n                    \"bytes\": 0, \n                    \"end\": 46.000294, \n                    \"omitted\": false, \n                    \"seconds\": 1.0002379417419434, \n                    \"sender\": false, \n                    \"socket\": 5, \n                    \"start\": 45.000056\n                }\n            ], \n            \"sum\": {\n                \"bits_per_second\": 0, \n                \"bytes\": 0, \n                \"end\": 46.000294, \n                \"omitted\": false, \n                \"seconds\": 1.0002379417419434, \n                \"sender\": false, \n                \"start\": 45.000056\n            }\n        }, \n        {\n            \"streams\": [\n                {\n                    \"bits_per_second\": 0, \n                    \"bytes\": 0, \n                    \"end\": 47.000107, \n                    \"omitted\": false, \n                    \"seconds\": 0.9998130202293396, \n                    \"sender\": false, \n                    \"socket\": 5, \n                    \"start\": 46.000294\n                }\n            ], \n            \"sum\": {\n                \"bits_per_second\": 0, \n                \"bytes\": 0, \n                \"end\": 47.000107, \n                \"omitted\": false, \n                \"seconds\": 0.9998130202293396, \n                \"sender\": false, \n                \"start\": 46.000294\n            }\n        }, \n        {\n            \"streams\": [\n                {\n                    \"bits_per_second\": 0, \n                    \"bytes\": 0, \n                    \"end\": 48.00031, \n                    \"omitted\": false, \n                    \"seconds\": 1.000203013420105, \n                    \"sender\": false, \n                    \"socket\": 5, \n                    \"start\": 47.000107\n                }\n            ], \n            \"sum\": {\n                \"bits_per_second\": 0, \n                \"bytes\": 0, \n                \"end\": 48.00031, \n                \"omitted\": false, \n                \"seconds\": 1.000203013420105, \n                \"sender\": false, \n                \"start\": 47.000107\n            }\n        }, \n        {\n            \"streams\": [\n                {\n                    \"bits_per_second\": 0, \n                    \"bytes\": 0, \n                    \"end\": 49.0011, \n                    \"omitted\": false, \n                    \"seconds\": 1.000789999961853, \n                    \"sender\": false, \n                    \"socket\": 5, \n                    \"start\": 48.00031\n                }\n            ], \n            \"sum\": {\n                \"bits_per_second\": 0, \n                \"bytes\": 0, \n                \"end\": 49.0011, \n                \"omitted\": false, \n                \"seconds\": 1.000789999961853, \n                \"sender\": false, \n                \"start\": 48.00031\n            }\n        }, \n        {\n            \"streams\": [\n                {\n                    \"bits_per_second\": 0, \n                    \"bytes\": 0, \n                    \"end\": 50.001128, \n                    \"omitted\": false, \n                    \"seconds\": 1.0000280141830444, \n                    \"sender\": false, \n                    \"socket\": 5, \n                    \"start\": 49.0011\n                }\n            ], \n            \"sum\": {\n                \"bits_per_second\": 0, \n                \"bytes\": 0, \n                \"end\": 50.001128, \n                \"omitted\": false, \n                \"seconds\": 1.0000280141830444, \n                \"sender\": false, \n                \"start\": 49.0011\n            }\n        }, \n        {\n            \"streams\": [\n                {\n                    \"bits_per_second\": 2097240.12870328, \n                    \"bytes\": 262144, \n                    \"end\": 51.001086, \n                    \"omitted\": false, \n                    \"seconds\": 0.9999579787254333, \n                    \"sender\": false, \n                    \"socket\": 5, \n                    \"start\": 50.001128\n                }\n            ], \n            \"sum\": {\n                \"bits_per_second\": 2097240.12870328, \n                \"bytes\": 262144, \n                \"end\": 51.001086, \n                \"omitted\": false, \n                \"seconds\": 0.9999579787254333, \n                \"sender\": false, \n                \"start\": 50.001128\n            }\n        }, \n        {\n            \"streams\": [\n                {\n                    \"bits_per_second\": 0, \n                    \"bytes\": 0, \n                    \"end\": 52.001123, \n                    \"omitted\": false, \n                    \"seconds\": 1.0000369548797607, \n                    \"sender\": false, \n                    \"socket\": 5, \n                    \"start\": 51.001086\n                }\n            ], \n            \"sum\": {\n                \"bits_per_second\": 0, \n                \"bytes\": 0, \n                \"end\": 52.001123, \n                \"omitted\": false, \n                \"seconds\": 1.0000369548797607, \n                \"sender\": false, \n                \"start\": 51.001086\n            }\n        }, \n        {\n            \"streams\": [\n                {\n                    \"bits_per_second\": 2096986.2630991417, \n                    \"bytes\": 262144, \n                    \"end\": 53.001202, \n                    \"omitted\": false, \n                    \"seconds\": 1.0000790357589722, \n                    \"sender\": false, \n                    \"socket\": 5, \n                    \"start\": 52.001123\n                }\n            ], \n            \"sum\": {\n                \"bits_per_second\": 2096986.2630991417, \n                \"bytes\": 262144, \n                \"end\": 53.001202, \n                \"omitted\": false, \n                \"seconds\": 1.0000790357589722, \n                \"sender\": false, \n                \"start\": 52.001123\n            }\n        }, \n        {\n            \"streams\": [\n                {\n                    \"bits_per_second\": 3146001.77382456, \n                    \"bytes\": 393216, \n                    \"end\": 54.001115, \n                    \"omitted\": false, \n                    \"seconds\": 0.999912977218628, \n                    \"sender\": false, \n                    \"socket\": 5, \n                    \"start\": 53.001202\n                }\n            ], \n            \"sum\": {\n                \"bits_per_second\": 3146001.77382456, \n                \"bytes\": 393216, \n                \"end\": 54.001115, \n                \"omitted\": false, \n                \"seconds\": 0.999912977218628, \n                \"sender\": false, \n                \"start\": 53.001202\n            }\n        }, \n        {\n            \"streams\": [\n                {\n                    \"bits_per_second\": 16776578.024260791, \n                    \"bytes\": 2097152, \n                    \"end\": 55.001153, \n                    \"omitted\": false, \n                    \"seconds\": 1.0000380277633667, \n                    \"sender\": false, \n                    \"socket\": 5, \n                    \"start\": 54.001115\n                }\n            ], \n            \"sum\": {\n                \"bits_per_second\": 16776578.024260791, \n                \"bytes\": 2097152, \n                \"end\": 55.001153, \n                \"omitted\": false, \n                \"seconds\": 1.0000380277633667, \n                \"sender\": false, \n                \"start\": 54.001115\n            }\n        }, \n        {\n            \"streams\": [\n                {\n                    \"bits_per_second\": 14680592.519027323, \n                    \"bytes\": 1835008, \n                    \"end\": 56.001117, \n                    \"omitted\": false, \n                    \"seconds\": 0.9999639987945557, \n                    \"sender\": false, \n                    \"socket\": 5, \n                    \"start\": 55.001153\n                }\n            ], \n            \"sum\": {\n                \"bits_per_second\": 14680592.519027323, \n                \"bytes\": 1835008, \n                \"end\": 56.001117, \n                \"omitted\": false, \n                \"seconds\": 0.9999639987945557, \n                \"sender\": false, \n                \"start\": 55.001153\n            }\n        }, \n        {\n            \"streams\": [\n                {\n                    \"bits_per_second\": 0, \n                    \"bytes\": 0, \n                    \"end\": 57.001097, \n                    \"omitted\": false, \n                    \"seconds\": 0.9999799728393555, \n                    \"sender\": false, \n                    \"socket\": 5, \n                    \"start\": 56.001117\n                }\n            ], \n            \"sum\": {\n                \"bits_per_second\": 0, \n                \"bytes\": 0, \n                \"end\": 57.001097, \n                \"omitted\": false, \n                \"seconds\": 0.9999799728393555, \n                \"sender\": false, \n                \"start\": 56.001117\n            }\n        }, \n        {\n            \"streams\": [\n                {\n                    \"bits_per_second\": 0, \n                    \"bytes\": 0, \n                    \"end\": 58.001123, \n                    \"omitted\": false, \n                    \"seconds\": 1.000025987625122, \n                    \"sender\": false, \n                    \"socket\": 5, \n                    \"start\": 57.001097\n                }\n            ], \n            \"sum\": {\n                \"bits_per_second\": 0, \n                \"bytes\": 0, \n                \"end\": 58.001123, \n                \"omitted\": false, \n                \"seconds\": 1.000025987625122, \n                \"sender\": false, \n                \"start\": 57.001097\n            }\n        }, \n        {\n            \"streams\": [\n                {\n                    \"bits_per_second\": 2097105.751019962, \n                    \"bytes\": 262144, \n                    \"end\": 59.001145, \n                    \"omitted\": false, \n                    \"seconds\": 1.000022053718567, \n                    \"sender\": false, \n                    \"socket\": 5, \n                    \"start\": 58.001123\n                }\n            ], \n            \"sum\": {\n                \"bits_per_second\": 2097105.751019962, \n                \"bytes\": 262144, \n                \"end\": 59.001145, \n                \"omitted\": false, \n                \"seconds\": 1.000022053718567, \n                \"sender\": false, \n                \"start\": 58.001123\n            }\n        }, \n        {\n            \"streams\": [\n                {\n                    \"bits_per_second\": 0, \n                    \"bytes\": 0, \n                    \"end\": 60.001104, \n                    \"omitted\": false, \n                    \"seconds\": 0.9999589920043945, \n                    \"sender\": false, \n                    \"socket\": 5, \n                    \"start\": 59.001145\n                }\n            ], \n            \"sum\": {\n                \"bits_per_second\": 0, \n                \"bytes\": 0, \n                \"end\": 60.001104, \n                \"omitted\": false, \n                \"seconds\": 0.9999589920043945, \n                \"sender\": false, \n                \"start\": 59.001145\n            }\n        }\n    ], \n    \"start\": {\n        \"accepted_connection\": {\n            \"host\": \"172.16.0.2\", \n            \"port\": 58643\n        }, \n        \"connected\": [\n            {\n                \"local_host\": \"172.16.0.1\", \n                \"local_port\": 5201, \n                \"remote_host\": \"172.16.0.2\", \n                \"remote_port\": 42157, \n                \"socket\": 5\n            }\n        ], \n        \"cookie\": \"szk6saqk7e7rpb2viaeobbikjq57tvh5spvu\", \n        \"fq_rate\": 0, \n        \"rcvbuf_actual\": 87380, \n        \"sndbuf_actual\": 65536, \n        \"sock_bufsize\": 0, \n        \"system_info\": \"REDACTED\", \n        \"target_bitrate\": 0, \n        \"tcp_mss_default\": 0, \n        \"test_start\": {\n            \"bidir\": 0, \n            \"blksize\": 131072, \n            \"blocks\": 0, \n            \"bytes\": 0, \n            \"duration\": 60, \n            \"fqrate\": 0, \n            \"interval\": 1, \n            \"num_streams\": 1, \n            \"omit\": 0, \n            \"protocol\": \"TCP\", \n            \"reverse\": 0, \n            \"target_bitrate\": 0, \n            \"tos\": 0\n        }, \n        \"timestamp\": {\n            \"time\": \"Wed, 16 Oct 2024 03:08:16 GMT\", \n            \"timesecs\": 1729048096\n        }, \n        \"version\": \"iperf 3.17.1\"\n    }\n}\n","summary":{"streams":[{"end":60.001069,"rtt":40821,"start":0,"stream-id":5,"retransmits":412,"throughput-bits":3266629.799545738,"throughput-bytes":24500160}],"summary":{"end":60.001069,"start":0,"retransmits":412,"throughput-bits":3266629.799545738,"throughput-bytes":24500160,"receiver-throughput-bits":3075857.549410338}},"intervals":[{"streams":[{"end":1.001049,"rtt":22328,"start":0,"omitted":false,"stream-id":5,"retransmits":2,"tcp-window-size":1448,"throughput-bits":1330763.973035489,"throughput-bytes":166520}],"summary":{"end":1.001049,"start":0,"omitted":false,"retransmits":2,"throughput-bits":1330763.973035489,"throughput-bytes":166520}},{"streams":[{"end":2.001054,"rtt":22328,"start":1.001049,"omitted":false,"stream-id":5,"retransmits":1,"tcp-window-size":1448,"throughput-bits":0,"throughput-bytes":0}],"summary":{"end":2.001054,"start":1.001049,"omitted":false,"retransmits":1,"throughput-bits":0,"throughput-bytes":0}},{"streams":[{"end":3.001079,"rtt":22328,"start":2.001054,"omitted":false,"stream-id":5,"retransmits":0,"tcp-window-size":1448,"throughput-bits":0,"throughput-bytes":0}],"summary":{"end":3.001079,"start":2.001054,"omitted":false,"retransmits":0,"throughput-bits":0,"throughput-bytes":0}},{"streams":[{"end":4.000104,"rtt":21175,"start":3.001079,"omitted":false,"stream-id":5,"retransmits":19,"tcp-window-size":27512,"throughput-bits":1797272.3635222015,"throughput-bytes":224440}],"summary":{"end":4.000104,"start":3.001079,"omitted":false,"retransmits":19,"throughput-bits":1797272.3635222015,"throughput-bytes":224440}},{"streams":[{"end":5.000104,"rtt":30692,"start":4.000104,"omitted":false,"stream-id":5,"retransmits":0,"tcp-window-size":85432,"throughput-bits":20851200,"throughput-bytes":2606400}],"summary":{"end":5.000104,"start":4.000104,"omitted":false,"retransmits":0,"throughput-bits":20851200,"throughput-bytes":2606400}},{"streams":[{"end":6.000135,"rtt":43798,"start":5.000104,"omitted":false,"stream-id":5,"retransmits":0,"tcp-window-size":121632,"throughput-bits":22414345.280474074,"throughput-bytes":2801880}],"summary":{"end":6.000135,"start":5.000104,"omitted":false,"retransmits":0,"throughput-bits":22414345.280474074,"throughput-bytes":2801880}},{"streams":[{"end":7.000112,"rtt":59955,"start":6.000135,"omitted":false,"stream-id":5,"retransmits":0,"tcp-window-size":166520,"throughput-bits":23979431.704206336,"throughput-bytes":2997360}],"summary":{"end":7.000112,"start":6.000135,"omitted":false,"retransmits":0,"throughput-bits":23979431.704206336,"throughput-bytes":2997360}},{"streams":[{"end":8.000153,"rtt":80659,"start":7.000112,"omitted":false,"stream-id":5,"retransmits":0,"tcp-window-size":227336,"throughput-bits":23456638.090288274,"throughput-bytes":2932200}],"summary":{"end":8.000153,"start":7.000112,"omitted":false,"retransmits":0,"throughput-bits":23456638.090288274,"throughput-bytes":2932200}},{"streams":[{"end":9.000309,"rtt":102352,"start":8.000153,"omitted":false,"stream-id":5,"retransmits":0,"tcp-window-size":285256,"throughput-bits":20847946.78297771,"throughput-bytes":2606400}],"summary":{"end":9.000309,"start":8.000153,"omitted":false,"retransmits":0,"throughput-bits":20847946.78297771,"throughput-bytes":2606400}},{"streams":[{"end":10.000139,"rtt":56039,"start":9.000309,"omitted":false,"stream-id":5,"retransmits":77,"tcp-window-size":154936,"throughput-bits":15119690.233139092,"throughput-bytes":1889640}],"summary":{"end":10.000139,"start":9.000309,"omitted":false,"retransmits":77,"throughput-bits":15119690.233139092,"throughput-bytes":1889640}},{"streams":[{"end":11.001059,"rtt":63288,"start":10.000139,"omitted":false,"stream-id":5,"retransmits":1,"tcp-window-size":1448,"throughput-bits":0,"throughput-bytes":0}],"summary":{"end":11.001059,"start":10.000139,"omitted":false,"retransmits":1,"throughput-bits":0,"throughput-bytes":0}},{"streams":[{"end":12.000144,"rtt":32590,"start":11.001059,"omitted":false,"stream-id":5,"retransmits":49,"tcp-window-size":89776,"throughput-bits":9913390.66226342,"throughput-bytes":1238040}],"summary":{"end":12.000144,"start":11.001059,"omitted":false,"retransmits":49,"throughput-bits":9913390.66226342,"throughput-bytes":1238040}},{"streams":[{"end":13.00037,"rtt":27405,"start":12.000144,"omitted":false,"stream-id":5,"retransmits":31,"tcp-window-size":56472,"throughput-bits":9380919.71689901,"throughput-bytes":1172880}],"summary":{"end":13.00037,"start":12.000144,"omitted":false,"retransmits":31,"throughput-bits":9380919.71689901,"throughput-bytes":1172880}},{"streams":[{"end":14.001059,"rtt":27405,"start":13.00037,"omitted":false,"stream-id":5,"retransmits":2,"tcp-window-size":1448,"throughput-bits":0,"throughput-bytes":0}],"summary":{"end":14.001059,"start":13.00037,"omitted":false,"retransmits":2,"throughput-bits":0,"throughput-bytes":0}},{"streams":[{"end":15.001058,"rtt":27405,"start":14.001059,"omitted":false,"stream-id":5,"retransmits":0,"tcp-window-size":1448,"throughput-bits":0,"throughput-bytes":0}],"summary":{"end":15.001058,"start":14.001059,"omitted":false,"retransmits":0,"throughput-bits":0,"throughput-bytes":0}},{"streams":[{"end":16.001064,"rtt":16843,"start":15.001058,"omitted":false,"stream-id":5,"retransmits":41,"tcp-window-size":1448,"throughput-bits":0,"throughput-bytes":0}],"summary":{"end":16.001064,"start":15.001058,"omitted":false,"retransmits":41,"throughput-bits":0,"throughput-bytes":0}},{"streams":[{"end":17.001061,"rtt":16843,"start":16.001064,"omitted":false,"stream-id":5,"retransmits":1,"tcp-window-size":1448,"throughput-bits":0,"throughput-bytes":0}],"summary":{"end":17.001061,"start":16.001064,"omitted":false,"retransmits":1,"throughput-bits":0,"throughput-bytes":0}},{"streams":[{"end":18.001064,"rtt":16843,"start":17.001061,"omitted":false,"stream-id":5,"retransmits":1,"tcp-window-size":1448,"throughput-bits":0,"throughput-bytes":0}],"summary":{"end":18.001064,"start":17.001061,"omitted":false,"retransmits":1,"throughput-bits":0,"throughput-bytes":0}},{"streams":[{"end":19.001057,"rtt":16843,"start":18.001064,"omitted":false,"stream-id":5,"retransmits":0,"tcp-window-size":1448,"throughput-bits":0,"throughput-bytes":0}],"summary":{"end":19.001057,"start":18.001064,"omitted":false,"retransmits":0,"throughput-bits":0,"throughput-bytes":0}},{"streams":[{"end":20.000575,"rtt":20163,"start":19.001057,"omitted":false,"stream-id":5,"retransmits":26,"tcp-window-size":1448,"throughput-bits":4693782.510011104,"throughput-bytes":586440}],"summary":{"end":20.000575,"start":19.001057,"omitted":false,"retransmits":26,"throughput-bits":4693782.510011104,"throughput-bytes":586440}},{"streams":[{"end":21.000435,"rtt":20163,"start":20.000575,"omitted":false,"stream-id":5,"retransmits":1,"tcp-window-size":1448,"throughput-bits":0,"throughput-bytes":0}],"summary":{"end":21.000435,"start":20.000575,"omitted":false,"retransmits":1,"throughput-bits":0,"throughput-bytes":0}},{"streams":[{"end":22.001053,"rtt":49178,"start":21.000435,"omitted":false,"stream-id":5,"retransmits":32,"tcp-window-size":21720,"throughput-bits":0,"throughput-bytes":0}],"summary":{"end":22.001053,"start":21.000435,"omitted":false,"retransmits":32,"throughput-bits":0,"throughput-bytes":0}},{"streams":[{"end":23.001052,"rtt":49178,"start":22.001053,"omitted":false,"stream-id":5,"retransmits":0,"tcp-window-size":21720,"throughput-bits":0,"throughput-bytes":0}],"summary":{"end":23.001052,"start":22.001053,"omitted":false,"retransmits":0,"throughput-bits":0,"throughput-bytes":0}},{"streams":[{"end":24.001052,"rtt":49178,"start":23.001052,"omitted":false,"stream-id":5,"retransmits":1,"tcp-window-size":1448,"throughput-bits":0,"throughput-bytes":0}],"summary":{"end":24.001052,"start":23.001052,"omitted":false,"retransmits":1,"throughput-bits":0,"throughput-bytes":0}},{"streams":[{"end":25.001051,"rtt":49178,"start":24.001052,"omitted":false,"stream-id":5,"retransmits":0,"tcp-window-size":1448,"throughput-bits":0,"throughput-bytes":0}],"summary":{"end":25.001051,"start":24.001052,"omitted":false,"retransmits":0,"throughput-bits":0,"throughput-bytes":0}},{"streams":[{"end":26.001051,"rtt":49178,"start":25.001051,"omitted":false,"stream-id":5,"retransmits":0,"tcp-window-size":1448,"throughput-bits":0,"throughput-bytes":0}],"summary":{"end":26.001051,"start":25.001051,"omitted":false,"retransmits":0,"throughput-bits":0,"throughput-bytes":0}},{"streams":[{"end":27.001051,"rtt":49178,"start":26.001051,"omitted":false,"stream-id":5,"retransmits":0,"tcp-window-size":1448,"throughput-bits":0,"throughput-bytes":0}],"summary":{"end":27.001051,"start":26.001051,"omitted":false,"retransmits":0,"throughput-bits":0,"throughput-bytes":0}},{"streams":[{"end":28.001052,"rtt":49178,"start":27.001051,"omitted":false,"stream-id":5,"retransmits":1,"tcp-window-size":1448,"throughput-bits":0,"throughput-bytes":0}],"summary":{"end":28.001052,"start":27.001051,"omitted":false,"retransmits":1,"throughput-bits":0,"throughput-bytes":0}},{"streams":[{"end":29.001052,"rtt":49178,"start":28.001052,"omitted":false,"stream-id":5,"retransmits":0,"tcp-window-size":1448,"throughput-bits":0,"throughput-bytes":0}],"summary":{"end":29.001052,"start":28.001052,"omitted":false,"retransmits":0,"throughput-bits":0,"throughput-bytes":0}},{"streams":[{"end":30.001052,"rtt":49178,"start":29.001052,"omitted":false,"stream-id":5,"retransmits":0,"tcp-window-size":1448,"throughput-bits":0,"throughput-bytes":0}],"summary":{"end":30.001052,"start":29.001052,"omitted":false,"retransmits":0,"throughput-bits":0,"throughput-bytes":0}},{"streams":[{"end":31.001054,"rtt":49178,"start":30.001052,"omitted":false,"stream-id":5,"retransmits":0,"tcp-window-size":1448,"throughput-bits":0,"throughput-bytes":0}],"summary":{"end":31.001054,"start":30.001052,"omitted":false,"retransmits":0,"throughput-bits":0,"throughput-bytes":0}},{"streams":[{"end":32.001049,"rtt":49178,"start":31.001054,"omitted":false,"stream-id":5,"retransmits":0,"tcp-window-size":1448,"throughput-bits":0,"throughput-bytes":0}],"summary":{"end":32.001049,"start":31.001054,"omitted":false,"retransmits":0,"throughput-bits":0,"throughput-bytes":0}},{"streams":[{"end":33.000616,"rtt":49178,"start":32.001049,"omitted":false,"stream-id":5,"retransmits":0,"tcp-window-size":1448,"throughput-bits":0,"throughput-bytes":0}],"summary":{"end":33.000616,"start":32.001049,"omitted":false,"retransmits":0,"throughput-bits":0,"throughput-bytes":0}},{"streams":[{"end":34.001046,"rtt":49178,"start":33.000616,"omitted":false,"stream-id":5,"retransmits":0,"tcp-window-size":1448,"throughput-bits":0,"throughput-bytes":0}],"summary":{"end":34.001046,"start":33.000616,"omitted":false,"retransmits":0,"throughput-bits":0,"throughput-bytes":0}},{"streams":[{"end":35.001047,"rtt":49178,"start":34.001046,"omitted":false,"stream-id":5,"retransmits":0,"tcp-window-size":1448,"throughput-bits":0,"throughput-bytes":0}],"summary":{"end":35.001047,"start":34.001046,"omitted":false,"retransmits":0,"throughput-bits":0,"throughput-bytes":0}},{"streams":[{"end":36.000603,"rtt":49178,"start":35.001047,"omitted":false,"stream-id":5,"retransmits":1,"tcp-window-size":1448,"throughput-bits":0,"throughput-bytes":0}],"summary":{"end":36.000603,"start":35.001047,"omitted":false,"retransmits":1,"throughput-bits":0,"throughput-bytes":0}},{"streams":[{"end":37.000957,"rtt":49178,"start":36.000603,"omitted":false,"stream-id":5,"retransmits":0,"tcp-window-size":1448,"throughput-bits":0,"throughput-bytes":0}],"summary":{"end":37.000957,"start":36.000603,"omitted":false,"retransmits":0,"throughput-bits":0,"throughput-bytes":0}},{"streams":[{"end":38.001048,"rtt":49178,"start":37.000957,"omitted":false,"stream-id":5,"retransmits":0,"tcp-window-size":1448,"throughput-bits":0,"throughput-bytes":0}],"summary":{"end":38.001048,"start":37.000957,"omitted":false,"retransmits":0,"throughput-bits":0,"throughput-bytes":0}},{"streams":[{"end":39.001053,"rtt":49178,"start":38.001048,"omitted":false,"stream-id":5,"retransmits":0,"tcp-window-size":1448,"throughput-bits":0,"throughput-bytes":0}],"summary":{"end":39.001053,"start":38.001048,"omitted":false,"retransmits":0,"throughput-bits":0,"throughput-bytes":0}},{"streams":[{"end":40.001048,"rtt":49178,"start":39.001053,"omitted":false,"stream-id":5,"retransmits":0,"tcp-window-size":1448,"throughput-bits":0,"throughput-bytes":0}],"summary":{"end":40.001048,"start":39.001053,"omitted":false,"retransmits":0,"throughput-bits":0,"throughput-bytes":0}},{"streams":[{"end":41.001052,"rtt":49178,"start":40.001048,"omitted":false,"stream-id":5,"retransmits":0,"tcp-window-size":1448,"throughput-bits":0,"throughput-bytes":0}],"summary":{"end":41.001052,"start":40.001048,"omitted":false,"retransmits":0,"throughput-bits":0,"throughput-bytes":0}},{"streams":[{"end":42.001053,"rtt":49178,"start":41.001052,"omitted":false,"stream-id":5,"retransmits":0,"tcp-window-size":1448,"throughput-bits":0,"throughput-bytes":0}],"summary":{"end":42.001053,"start":41.001052,"omitted":false,"retransmits":0,"throughput-bits":0,"throughput-bytes":0}},{"streams":[{"end":43.001061,"rtt":49178,"start":42.001053,"omitted":false,"stream-id":5,"retransmits":0,"tcp-window-size":1448,"throughput-bits":0,"throughput-bytes":0}],"summary":{"end":43.001061,"start":42.001053,"omitted":false,"retransmits":0,"throughput-bits":0,"throughput-bytes":0}},{"streams":[{"end":44.001058,"rtt":49178,"start":43.001061,"omitted":false,"stream-id":5,"retransmits":0,"tcp-window-size":1448,"throughput-bits":0,"throughput-bytes":0}],"summary":{"end":44.001058,"start":43.001061,"omitted":false,"retransmits":0,"throughput-bits":0,"throughput-bytes":0}},{"streams":[{"end":45.00106,"rtt":49178,"start":44.001058,"omitted":false,"stream-id":5,"retransmits":0,"tcp-window-size":1448,"throughput-bits":0,"throughput-bytes":0}],"summary":{"end":45.00106,"start":44.001058,"omitted":false,"retransmits":0,"throughput-bits":0,"throughput-bytes":0}},{"streams":[{"end":46.00106,"rtt":49178,"start":45.00106,"omitted":false,"stream-id":5,"retransmits":0,"tcp-window-size":1448,"throughput-bits":0,"throughput-bytes":0}],"summary":{"end":46.00106,"start":45.00106,"omitted":false,"retransmits":0,"throughput-bits":0,"throughput-bytes":0}},{"streams":[{"end":47.00106,"rtt":49178,"start":46.00106,"omitted":false,"stream-id":5,"retransmits":0,"tcp-window-size":1448,"throughput-bits":0,"throughput-bytes":0}],"summary":{"end":47.00106,"start":46.00106,"omitted":false,"retransmits":0,"throughput-bits":0,"throughput-bytes":0}},{"streams":[{"end":48.001054,"rtt":49178,"start":47.00106,"omitted":false,"stream-id":5,"retransmits":0,"tcp-window-size":1448,"throughput-bits":0,"throughput-bytes":0}],"summary":{"end":48.001054,"start":47.00106,"omitted":false,"retransmits":0,"throughput-bits":0,"throughput-bytes":0}},{"streams":[{"end":49.001061,"rtt":49178,"start":48.001054,"omitted":false,"stream-id":5,"retransmits":0,"tcp-window-size":1448,"throughput-bits":0,"throughput-bytes":0}],"summary":{"end":49.001061,"start":48.001054,"omitted":false,"retransmits":0,"throughput-bits":0,"throughput-bytes":0}},{"streams":[{"end":50.001076,"rtt":49178,"start":49.001061,"omitted":false,"stream-id":5,"retransmits":1,"tcp-window-size":1448,"throughput-bits":0,"throughput-bytes":0}],"summary":{"end":50.001076,"start":49.001061,"omitted":false,"retransmits":1,"throughput-bits":0,"throughput-bytes":0}},{"streams":[{"end":51.000691,"rtt":24228,"start":50.001076,"omitted":false,"stream-id":5,"retransmits":15,"tcp-window-size":1448,"throughput-bits":4693326.867017392,"throughput-bytes":586440}],"summary":{"end":51.000691,"start":50.001076,"omitted":false,"retransmits":15,"throughput-bits":4693326.867017392,"throughput-bytes":586440}},{"streams":[{"end":52.00106,"rtt":24228,"start":51.000691,"omitted":false,"stream-id":5,"retransmits":1,"tcp-window-size":1448,"throughput-bits":0,"throughput-bytes":0}],"summary":{"end":52.00106,"start":51.000691,"omitted":false,"retransmits":1,"throughput-bits":0,"throughput-bytes":0}},{"streams":[{"end":53.001056,"rtt":23005,"start":52.00106,"omitted":false,"stream-id":5,"retransmits":27,"tcp-window-size":17376,"throughput-bits":0,"throughput-bytes":0}],"summary":{"end":53.001056,"start":52.00106,"omitted":false,"retransmits":27,"throughput-bits":0,"throughput-bytes":0}},{"streams":[{"end":54.000839,"rtt":17574,"start":53.001056,"omitted":false,"stream-id":5,"retransmits":25,"tcp-window-size":21720,"throughput-bits":4692538.377079424,"throughput-bytes":586440}],"summary":{"end":54.000839,"start":53.001056,"omitted":false,"retransmits":25,"throughput-bits":4692538.377079424,"throughput-bytes":586440}},{"streams":[{"end":55.000282,"rtt":27730,"start":54.000839,"omitted":false,"stream-id":5,"retransmits":0,"tcp-window-size":78192,"throughput-bits":14082403.975135544,"throughput-bytes":1759320}],"summary":{"end":55.000282,"start":54.000839,"omitted":false,"retransmits":0,"throughput-bits":14082403.975135544,"throughput-bytes":1759320}},{"streams":[{"end":56.000383,"rtt":38716,"start":55.000282,"omitted":false,"stream-id":5,"retransmits":1,"tcp-window-size":1448,"throughput-bits":18764185.375169184,"throughput-bytes":2345760}],"summary":{"end":56.000383,"start":55.000282,"omitted":false,"retransmits":1,"throughput-bits":18764185.375169184,"throughput-bytes":2345760}},{"streams":[{"end":57.001032,"rtt":38716,"start":56.000383,"omitted":false,"stream-id":5,"retransmits":1,"tcp-window-size":1448,"throughput-bits":0,"throughput-bytes":0}],"summary":{"end":57.001032,"start":56.000383,"omitted":false,"retransmits":1,"throughput-bits":0,"throughput-bytes":0}},{"streams":[{"end":58.001056,"rtt":38716,"start":57.001032,"omitted":false,"stream-id":5,"retransmits":1,"tcp-window-size":1448,"throughput-bits":0,"throughput-bytes":0}],"summary":{"end":58.001056,"start":57.001032,"omitted":false,"retransmits":1,"throughput-bits":0,"throughput-bytes":0}},{"streams":[{"end":59.001048,"rtt":21388,"start":58.001056,"omitted":false,"stream-id":5,"retransmits":53,"tcp-window-size":55024,"throughput-bits":0,"throughput-bytes":0}],"summary":{"end":59.001048,"start":58.001056,"omitted":false,"retransmits":53,"throughput-bits":0,"throughput-bytes":0}},{"streams":[{"end":60.001069,"rtt":21388,"start":59.001048,"omitted":false,"stream-id":5,"retransmits":0,"tcp-window-size":55024,"throughput-bits":0,"throughput-bytes":0}],"summary":{"end":60.001069,"start":59.001048,"omitted":false,"retransmits":0,"throughput-bits":0,"throughput-bytes":0}}],"succeeded":true}
