{"diags":"Participant 0:\n/usr/bin/iperf3 -p 5201 -B 172.16.0.2 -c 172.16.0.1 -t 10 --json --rsa-public-key-path /var/run/pscheduler-server/runner/tmp/tmpj6ka5_ae/tmp_rkby3v9/public-key --username wRR4BEIJWIxQEFKMVuLp\n\n{\n    \"end\": {\n        \"cpu_utilization_percent\": {\n            \"host_system\": 0.283700702917345, \n            \"host_total\": 0.3547270910028436, \n            \"host_user\": 0.07102638808549866, \n            \"remote_system\": 0.545770643783205, \n            \"remote_total\": 0.7860454199562774, \n            \"remote_user\": 0.24024527771471116\n        }, \n        \"receiver_tcp_congestion\": \"htcp\", \n        \"sender_tcp_congestion\": \"htcp\", \n        \"streams\": [\n            {\n                \"receiver\": {\n                    \"bits_per_second\": 10621533.056794005, \n                    \"bytes\": 13502600, \n                    \"end\": 10.169982, \n                    \"seconds\": 10.000863, \n                    \"sender\": true, \n                    \"socket\": 5, \n                    \"start\": 0\n                }, \n                \"sender\": {\n                    \"bits_per_second\": 13210917.497819938, \n                    \"bytes\": 16515072, \n                    \"end\": 10.000863, \n                    \"max_rtt\": 410151, \n                    \"max_snd_cwnd\": 401096, \n                    \"max_snd_wnd\": 0, \n                    \"mean_rtt\": 225638, \n                    \"min_rtt\": 138505, \n                    \"retransmits\": 296, \n                    \"seconds\": 10.000863, \n                    \"sender\": true, \n                    \"socket\": 5, \n                    \"start\": 0\n                }\n            }\n        ], \n        \"sum_received\": {\n            \"bits_per_second\": 10621533.056794005, \n            \"bytes\": 13502600, \n            \"end\": 10.169982, \n            \"seconds\": 10.169982, \n            \"sender\": true, \n            \"start\": 0\n        }, \n        \"sum_sent\": {\n            \"bits_per_second\": 13210917.497819938, \n            \"bytes\": 16515072, \n            \"end\": 10.000863, \n            \"retransmits\": 296, \n            \"seconds\": 10.000863, \n            \"sender\": true, \n            \"start\": 0\n        }\n    }, \n    \"intervals\": [\n        {\n            \"streams\": [\n                {\n                    \"bits_per_second\": 37729683.62089037, \n                    \"bytes\": 4718592, \n                    \"end\": 1.000505, \n                    \"omitted\": false, \n                    \"pmtu\": 1500, \n                    \"retransmits\": 280, \n                    \"rtt\": 138505, \n                    \"rttvar\": 668, \n                    \"seconds\": 1.000504970550537, \n                    \"sender\": true, \n                    \"snd_cwnd\": 401096, \n                    \"snd_wnd\": -1, \n                    \"socket\": 5, \n                    \"start\": 0\n                }\n            ], \n            \"sum\": {\n                \"bits_per_second\": 37729683.62089037, \n                \"bytes\": 4718592, \n                \"end\": 1.000505, \n                \"omitted\": false, \n                \"retransmits\": 280, \n                \"seconds\": 1.000504970550537, \n                \"sender\": true, \n                \"start\": 0\n            }\n        }, \n        {\n            \"streams\": [\n                {\n                    \"bits_per_second\": 20966803.5609532, \n                    \"bytes\": 2621440, \n                    \"end\": 2.00073, \n                    \"omitted\": false, \n                    \"pmtu\": 1500, \n                    \"retransmits\": 4, \n                    \"rtt\": 141957, \n                    \"rttvar\": 1174, \n                    \"seconds\": 1.0002249479293823, \n                    \"sender\": true, \n                    \"snd_cwnd\": 207064, \n                    \"snd_wnd\": -1, \n                    \"socket\": 5, \n                    \"start\": 1.000505\n                }\n            ], \n            \"sum\": {\n                \"bits_per_second\": 20966803.5609532, \n                \"bytes\": 2621440, \n                \"end\": 2.00073, \n                \"omitted\": false, \n                \"retransmits\": 4, \n                \"seconds\": 1.0002249479293823, \n                \"sender\": true, \n                \"start\": 1.000505\n            }\n        }, \n        {\n            \"streams\": [\n                {\n                    \"bits_per_second\": 10489840.337169193, \n                    \"bytes\": 1310720, \n                    \"end\": 3.000341, \n                    \"omitted\": false, \n                    \"pmtu\": 1500, \n                    \"retransmits\": 0, \n                    \"rtt\": 167084, \n                    \"rttvar\": 445, \n                    \"seconds\": 0.9996110200881958, \n                    \"sender\": true, \n                    \"snd_cwnd\": 215752, \n                    \"snd_wnd\": -1, \n                    \"socket\": 5, \n                    \"start\": 2.00073\n                }\n            ], \n            \"sum\": {\n                \"bits_per_second\": 10489840.337169193, \n                \"bytes\": 1310720, \n                \"end\": 3.000341, \n                \"omitted\": false, \n                \"retransmits\": 0, \n                \"seconds\": 0.9996110200881958, \n                \"sender\": true, \n                \"start\": 2.00073\n            }\n        }, \n        {\n            \"streams\": [\n                {\n                    \"bits_per_second\": 10486315.654443312, \n                    \"bytes\": 1310720, \n                    \"end\": 4.000288, \n                    \"omitted\": false, \n                    \"pmtu\": 1500, \n                    \"retransmits\": 0, \n                    \"rtt\": 216483, \n                    \"rttvar\": 6363, \n                    \"seconds\": 0.9999470114707947, \n                    \"sender\": true, \n                    \"snd_cwnd\": 225888, \n                    \"snd_wnd\": -1, \n                    \"socket\": 5, \n                    \"start\": 3.000341\n                }\n            ], \n            \"sum\": {\n                \"bits_per_second\": 10486315.654443312, \n                \"bytes\": 1310720, \n                \"end\": 4.000288, \n                \"omitted\": false, \n                \"retransmits\": 0, \n                \"seconds\": 0.9999470114707947, \n                \"sender\": true, \n                \"start\": 3.000341\n            }\n        }, \n        {\n            \"streams\": [\n                {\n                    \"bits_per_second\": 10487207.074674241, \n                    \"bytes\": 1310720, \n                    \"end\": 5.00015, \n                    \"omitted\": false, \n                    \"pmtu\": 1500, \n                    \"retransmits\": 0, \n                    \"rtt\": 208601, \n                    \"rttvar\": 3411, \n                    \"seconds\": 0.999862015247345, \n                    \"sender\": true, \n                    \"snd_cwnd\": 247608, \n                    \"snd_wnd\": -1, \n                    \"socket\": 5, \n                    \"start\": 4.000288\n                }\n            ], \n            \"sum\": {\n                \"bits_per_second\": 10487207.074674241, \n                \"bytes\": 1310720, \n                \"end\": 5.00015, \n                \"omitted\": false, \n                \"retransmits\": 0, \n                \"seconds\": 0.999862015247345, \n                \"sender\": true, \n                \"start\": 4.000288\n            }\n        }, \n        {\n            \"streams\": [\n                {\n                    \"bits_per_second\": 10485676.250668908, \n                    \"bytes\": 1310720, \n                    \"end\": 6.000158, \n                    \"omitted\": false, \n                    \"pmtu\": 1500, \n                    \"retransmits\": 0, \n                    \"rtt\": 265793, \n                    \"rttvar\": 5863, \n                    \"seconds\": 1.0000079870224, \n                    \"sender\": true, \n                    \"snd_cwnd\": 280912, \n                    \"snd_wnd\": -1, \n                    \"socket\": 5, \n                    \"start\": 5.00015\n                }\n            ], \n            \"sum\": {\n                \"bits_per_second\": 10485676.250668908, \n                \"bytes\": 1310720, \n                \"end\": 6.000158, \n                \"omitted\": false, \n                \"retransmits\": 0, \n                \"seconds\": 1.0000079870224, \n                \"sender\": true, \n                \"start\": 5.00015\n            }\n        }, \n        {\n            \"streams\": [\n                {\n                    \"bits_per_second\": 10486945.133932468, \n                    \"bytes\": 1310720, \n                    \"end\": 7.000045, \n                    \"omitted\": false, \n                    \"pmtu\": 1500, \n                    \"retransmits\": 0, \n                    \"rtt\": 223354, \n                    \"rttvar\": 3898, \n                    \"seconds\": 0.999886989593506, \n                    \"sender\": true, \n                    \"snd_cwnd\": 325800, \n                    \"snd_wnd\": -1, \n                    \"socket\": 5, \n                    \"start\": 6.000158\n                }\n            ], \n            \"sum\": {\n                \"bits_per_second\": 10486945.133932468, \n                \"bytes\": 1310720, \n                \"end\": 7.000045, \n                \"omitted\": false, \n                \"retransmits\": 0, \n                \"seconds\": 0.999886989593506, \n                \"sender\": true, \n                \"start\": 6.000158\n            }\n        }, \n        {\n            \"streams\": [\n                {\n                    \"bits_per_second\": 10485425.010702267, \n                    \"bytes\": 1310720, \n                    \"end\": 8.000077, \n                    \"omitted\": false, \n                    \"pmtu\": 1500, \n                    \"retransmits\": 0, \n                    \"rtt\": 410151, \n                    \"rttvar\": 1863, \n                    \"seconds\": 1.0000319480895996, \n                    \"sender\": true, \n                    \"snd_cwnd\": 360552, \n                    \"snd_wnd\": -1, \n                    \"socket\": 5, \n                    \"start\": 7.000045\n                }\n            ], \n            \"sum\": {\n                \"bits_per_second\": 10485425.010702267, \n                \"bytes\": 1310720, \n                \"end\": 8.000077, \n                \"omitted\": false, \n                \"retransmits\": 0, \n                \"seconds\": 1.0000319480895996, \n                \"sender\": true, \n                \"start\": 7.000045\n            }\n        }, \n        {\n            \"streams\": [\n                {\n                    \"bits_per_second\": 0, \n                    \"bytes\": 0, \n                    \"end\": 9.000818, \n                    \"omitted\": false, \n                    \"pmtu\": 1500, \n                    \"retransmits\": 0, \n                    \"rtt\": 314791, \n                    \"rttvar\": 1684, \n                    \"seconds\": 1.0007410049438477, \n                    \"sender\": true, \n                    \"snd_cwnd\": 401096, \n                    \"snd_wnd\": -1, \n                    \"socket\": 5, \n                    \"start\": 8.000077\n                }\n            ], \n            \"sum\": {\n                \"bits_per_second\": 0, \n                \"bytes\": 0, \n                \"end\": 9.000818, \n                \"omitted\": false, \n                \"retransmits\": 0, \n                \"seconds\": 1.0007410049438477, \n                \"sender\": true, \n                \"start\": 8.000077\n            }\n        }, \n        {\n            \"streams\": [\n                {\n                    \"bits_per_second\": 10485288.77117792, \n                    \"bytes\": 1310720, \n                    \"end\": 10.000863, \n                    \"omitted\": false, \n                    \"pmtu\": 1500, \n                    \"retransmits\": 12, \n                    \"rtt\": 169669, \n                    \"rttvar\": 702, \n                    \"seconds\": 1.0000449419021606, \n                    \"sender\": true, \n                    \"snd_cwnd\": 209960, \n                    \"snd_wnd\": -1, \n                    \"socket\": 5, \n                    \"start\": 9.000818\n                }\n            ], \n            \"sum\": {\n                \"bits_per_second\": 10485288.77117792, \n                \"bytes\": 1310720, \n                \"end\": 10.000863, \n                \"omitted\": false, \n                \"retransmits\": 12, \n                \"seconds\": 1.0000449419021606, \n                \"sender\": true, \n                \"start\": 9.000818\n            }\n        }\n    ], \n    \"start\": {\n        \"connected\": [\n            {\n                \"local_host\": \"172.16.0.2\", \n                \"local_port\": 49903, \n                \"remote_host\": \"172.16.0.1\", \n                \"remote_port\": 5201, \n                \"socket\": 5\n            }\n        ], \n        \"connecting_to\": {\n            \"host\": \"172.16.0.1\", \n            \"port\": 5201\n        }, \n        \"cookie\": \"d3ua3mj5kphlcfyn5t5ifezealnm3o2vcg4k\", \n        \"fq_rate\": 0, \n        \"rcvbuf_actual\": 87380, \n        \"sndbuf_actual\": 65536, \n        \"sock_bufsize\": 0, \n        \"system_info\": \"REDACTED\", \n        \"target_bitrate\": 0, \n        \"tcp_mss_default\": 1448, \n        \"test_start\": {\n            \"bidir\": 0, \n            \"blksize\": 131072, \n            \"blocks\": 0, \n            \"bytes\": 0, \n            \"duration\": 10, \n            \"fqrate\": 0, \n            \"num_streams\": 1, \n            \"omit\": 0, \n            \"protocol\": \"TCP\", \n            \"reverse\": 0, \n            \"target_bitrate\": 0, \n            \"tos\": 0\n        }, \n        \"timestamp\": {\n            \"time\": \"Sat, 12 Oct 2024 02:28:18 GMT\", \n            \"timesecs\": 1728700098\n        }, \n        \"version\": \"iperf 3.14\"\n    }\n}\nParticipant 1:\n/usr/bin/iperf3 -s -1 --idle-timeout 10 --json -p 5201 -B 172.16.0.1 --authorized-users-path /var/run/pscheduler-server/runner/tmp/tmppw2lrkep/tmpjpjyu3vn/credentials --rsa-private-key-path /var/run/pscheduler-server/runner/tmp/tmppw2lrkep/tmpjpjyu3vn/private-key\n\n{\n    \"end\": {\n        \"cpu_utilization_percent\": {\n            \"host_system\": 0.545770643783205, \n            \"host_total\": 0.7860454199562774, \n            \"host_user\": 0.24024527771471116, \n            \"remote_system\": 0, \n            \"remote_total\": 0, \n            \"remote_user\": 0\n        }, \n        \"receiver_tcp_congestion\": \"htcp\", \n        \"streams\": [\n            {\n                \"receiver\": {\n                    \"bits_per_second\": 10621533.056794005, \n                    \"bytes\": 13502600, \n                    \"end\": 10.169982, \n                    \"seconds\": 10.169982, \n                    \"sender\": false, \n                    \"socket\": 5, \n                    \"start\": 0\n                }, \n                \"sender\": {\n                    \"bits_per_second\": 0, \n                    \"bytes\": 0, \n                    \"end\": 10.169982, \n                    \"seconds\": 10.169982, \n                    \"sender\": false, \n                    \"socket\": 5, \n                    \"start\": 0\n                }\n            }\n        ], \n        \"sum_received\": {\n            \"bits_per_second\": 10621533.056794005, \n            \"bytes\": 13502600, \n            \"end\": 10.169982, \n            \"seconds\": 10.169982, \n            \"sender\": false, \n            \"start\": 0\n        }, \n        \"sum_sent\": {\n            \"bits_per_second\": 0, \n            \"bytes\": 0, \n            \"end\": 10.169982, \n            \"seconds\": 10.169982, \n            \"sender\": false, \n            \"start\": 0\n        }\n    }, \n    \"intervals\": [\n        {\n            \"streams\": [\n                {\n                    \"bits_per_second\": 12232079.900006628, \n                    \"bytes\": 1529088, \n                    \"end\": 1.000051, \n                    \"omitted\": false, \n                    \"seconds\": 1.0000510215759277, \n                    \"sender\": false, \n                    \"socket\": 5, \n                    \"start\": 0\n                }\n            ], \n            \"sum\": {\n                \"bits_per_second\": 12232079.900006628, \n                \"bytes\": 1529088, \n                \"end\": 1.000051, \n                \"omitted\": false, \n                \"seconds\": 1.0000510215759277, \n                \"sender\": false, \n                \"start\": 0\n            }\n        }, \n        {\n            \"streams\": [\n                {\n                    \"bits_per_second\": 14421820.398540476, \n                    \"bytes\": 1802760, \n                    \"end\": 2.000069, \n                    \"omitted\": false, \n                    \"seconds\": 1.0000180006027222, \n                    \"sender\": false, \n                    \"socket\": 5, \n                    \"start\": 1.000051\n                }\n            ], \n            \"sum\": {\n                \"bits_per_second\": 14421820.398540476, \n                \"bytes\": 1802760, \n                \"end\": 2.000069, \n                \"omitted\": false, \n                \"seconds\": 1.0000180006027222, \n                \"sender\": false, \n                \"start\": 1.000051\n            }\n        }, \n        {\n            \"streams\": [\n                {\n                    \"bits_per_second\": 10666975.370923169, \n                    \"bytes\": 1335056, \n                    \"end\": 3.001332, \n                    \"omitted\": false, \n                    \"seconds\": 1.0012630224227905, \n                    \"sender\": false, \n                    \"socket\": 5, \n                    \"start\": 2.000069\n                }\n            ], \n            \"sum\": {\n                \"bits_per_second\": 10666975.370923169, \n                \"bytes\": 1335056, \n                \"end\": 3.001332, \n                \"omitted\": false, \n                \"seconds\": 1.0012630224227905, \n                \"sender\": false, \n                \"start\": 2.000069\n            }\n        }, \n        {\n            \"streams\": [\n                {\n                    \"bits_per_second\": 9290080.68569976, \n                    \"bytes\": 1159848, \n                    \"end\": 4.000116, \n                    \"omitted\": false, \n                    \"seconds\": 0.9987840056419373, \n                    \"sender\": false, \n                    \"socket\": 5, \n                    \"start\": 3.001332\n                }\n            ], \n            \"sum\": {\n                \"bits_per_second\": 9290080.68569976, \n                \"bytes\": 1159848, \n                \"end\": 4.000116, \n                \"omitted\": false, \n                \"seconds\": 0.9987840056419373, \n                \"sender\": false, \n                \"start\": 3.001332\n            }\n        }, \n        {\n            \"streams\": [\n                {\n                    \"bits_per_second\": 9793835.30134908, \n                    \"bytes\": 1225008, \n                    \"end\": 5.000752, \n                    \"omitted\": false, \n                    \"seconds\": 1.0006359815597534, \n                    \"sender\": false, \n                    \"socket\": 5, \n                    \"start\": 4.000116\n                }\n            ], \n            \"sum\": {\n                \"bits_per_second\": 9793835.30134908, \n                \"bytes\": 1225008, \n                \"end\": 5.000752, \n                \"omitted\": false, \n                \"seconds\": 1.0006359815597534, \n                \"sender\": false, \n                \"start\": 4.000116\n            }\n        }, \n        {\n            \"streams\": [\n                {\n                    \"bits_per_second\": 10618164.664063234, \n                    \"bytes\": 1326368, \n                    \"end\": 6.000072, \n                    \"omitted\": false, \n                    \"seconds\": 0.9993199706077576, \n                    \"sender\": false, \n                    \"socket\": 5, \n                    \"start\": 5.000752\n                }\n            ], \n            \"sum\": {\n                \"bits_per_second\": 10618164.664063234, \n                \"bytes\": 1326368, \n                \"end\": 6.000072, \n                \"omitted\": false, \n                \"seconds\": 0.9993199706077576, \n                \"sender\": false, \n                \"start\": 5.000752\n            }\n        }, \n        {\n            \"streams\": [\n                {\n                    \"bits_per_second\": 11746246.713217141, \n                    \"bytes\": 1468272, \n                    \"end\": 7.000066, \n                    \"omitted\": false, \n                    \"seconds\": 0.9999939799308777, \n                    \"sender\": false, \n                    \"socket\": 5, \n                    \"start\": 6.000072\n                }\n            ], \n            \"sum\": {\n                \"bits_per_second\": 11746246.713217141, \n                \"bytes\": 1468272, \n                \"end\": 7.000066, \n                \"omitted\": false, \n                \"seconds\": 0.9999939799308777, \n                \"sender\": false, \n                \"start\": 6.000072\n            }\n        }, \n        {\n            \"streams\": [\n                {\n                    \"bits_per_second\": 8826408.25178152, \n                    \"bytes\": 1103376, \n                    \"end\": 8.000134, \n                    \"omitted\": false, \n                    \"seconds\": 1.000067949295044, \n                    \"sender\": false, \n                    \"socket\": 5, \n                    \"start\": 7.000066\n                }\n            ], \n            \"sum\": {\n                \"bits_per_second\": 8826408.25178152, \n                \"bytes\": 1103376, \n                \"end\": 8.000134, \n                \"omitted\": false, \n                \"seconds\": 1.000067949295044, \n                \"sender\": false, \n                \"start\": 7.000066\n            }\n        }, \n        {\n            \"streams\": [\n                {\n                    \"bits_per_second\": 8561226.61831107, \n                    \"bytes\": 1070072, \n                    \"end\": 9.000058, \n                    \"omitted\": false, \n                    \"seconds\": 0.9999240040779114, \n                    \"sender\": false, \n                    \"socket\": 5, \n                    \"start\": 8.000134\n                }\n            ], \n            \"sum\": {\n                \"bits_per_second\": 8561226.61831107, \n                \"bytes\": 1070072, \n                \"end\": 9.000058, \n                \"omitted\": false, \n                \"seconds\": 0.9999240040779114, \n                \"sender\": false, \n                \"start\": 8.000134\n            }\n        }, \n        {\n            \"streams\": [\n                {\n                    \"bits_per_second\": 10228620.787442079, \n                    \"bytes\": 1278584, \n                    \"end\": 10.000063, \n                    \"omitted\": false, \n                    \"seconds\": 1.0000050067901611, \n                    \"sender\": false, \n                    \"socket\": 5, \n                    \"start\": 9.000058\n                }\n            ], \n            \"sum\": {\n                \"bits_per_second\": 10228620.787442079, \n                \"bytes\": 1278584, \n                \"end\": 10.000063, \n                \"omitted\": false, \n                \"seconds\": 1.0000050067901611, \n                \"sender\": false, \n                \"start\": 9.000058\n            }\n        }, \n        {\n            \"streams\": [\n                {\n                    \"bits_per_second\": 9612486.001465395, \n                    \"bytes\": 204168, \n                    \"end\": 10.169982, \n                    \"omitted\": false, \n                    \"seconds\": 0.1699189990758896, \n                    \"sender\": false, \n                    \"socket\": 5, \n                    \"start\": 10.000063\n                }\n            ], \n            \"sum\": {\n                \"bits_per_second\": 9612486.001465395, \n                \"bytes\": 204168, \n                \"end\": 10.169982, \n                \"omitted\": false, \n                \"seconds\": 0.1699189990758896, \n                \"sender\": false, \n                \"start\": 10.000063\n            }\n        }\n    ], \n    \"start\": {\n        \"accepted_connection\": {\n            \"host\": \"172.16.0.2\", \n            \"port\": 39399\n        }, \n        \"connected\": [\n            {\n                \"local_host\": \"172.16.0.1\", \n                \"local_port\": 5201, \n                \"remote_host\": \"172.16.0.2\", \n                \"remote_port\": 49903, \n                \"socket\": 5\n            }\n        ], \n        \"cookie\": \"d3ua3mj5kphlcfyn5t5ifezealnm3o2vcg4k\", \n        \"fq_rate\": 0, \n        \"rcvbuf_actual\": 87380, \n        \"sndbuf_actual\": 65536, \n        \"sock_bufsize\": 0, \n        \"system_info\": \"REDACTED\", \n        \"target_bitrate\": 0, \n        \"tcp_mss_default\": 0, \n        \"test_start\": {\n            \"bidir\": 0, \n            \"blksize\": 131072, \n            \"blocks\": 0, \n            \"bytes\": 0, \n            \"duration\": 10, \n            \"fqrate\": 0, \n            \"num_streams\": 1, \n            \"omit\": 0, \n            \"protocol\": \"TCP\", \n            \"reverse\": 0, \n            \"target_bitrate\": 0, \n            \"tos\": 0\n        }, \n        \"timestamp\": {\n            \"time\": \"Sat, 12 Oct 2024 02:28:18 GMT\", \n            \"timesecs\": 1728700098\n        }, \n        \"version\": \"iperf 3.14\"\n    }\n}\n","summary":{"streams":[{"end":10.000863,"rtt":225638,"start":0,"stream-id":5,"retransmits":296,"throughput-bits":13210917.497819938,"throughput-bytes":16515072}],"summary":{"end":10.000863,"start":0,"retransmits":296,"throughput-bits":13210917.497819938,"throughput-bytes":16515072,"receiver-throughput-bits":10621533.056794005}},"intervals":[{"streams":[{"end":1.000505,"rtt":138505,"start":0,"omitted":false,"stream-id":5,"retransmits":280,"tcp-window-size":401096,"throughput-bits":37729683.62089037,"throughput-bytes":4718592}],"summary":{"end":1.000505,"start":0,"omitted":false,"retransmits":280,"throughput-bits":37729683.62089037,"throughput-bytes":4718592}},{"streams":[{"end":2.00073,"rtt":141957,"start":1.000505,"omitted":false,"stream-id":5,"retransmits":4,"tcp-window-size":207064,"throughput-bits":20966803.5609532,"throughput-bytes":2621440}],"summary":{"end":2.00073,"start":1.000505,"omitted":false,"retransmits":4,"throughput-bits":20966803.5609532,"throughput-bytes":2621440}},{"streams":[{"end":3.000341,"rtt":167084,"start":2.00073,"omitted":false,"stream-id":5,"retransmits":0,"tcp-window-size":215752,"throughput-bits":10489840.337169193,"throughput-bytes":1310720}],"summary":{"end":3.000341,"start":2.00073,"omitted":false,"retransmits":0,"throughput-bits":10489840.337169193,"throughput-bytes":1310720}},{"streams":[{"end":4.000288,"rtt":216483,"start":3.000341,"omitted":false,"stream-id":5,"retransmits":0,"tcp-window-size":225888,"throughput-bits":10486315.654443312,"throughput-bytes":1310720}],"summary":{"end":4.000288,"start":3.000341,"omitted":false,"retransmits":0,"throughput-bits":10486315.654443312,"throughput-bytes":1310720}},{"streams":[{"end":5.00015,"rtt":208601,"start":4.000288,"omitted":false,"stream-id":5,"retransmits":0,"tcp-window-size":247608,"throughput-bits":10487207.074674241,"throughput-bytes":1310720}],"summary":{"end":5.00015,"start":4.000288,"omitted":false,"retransmits":0,"throughput-bits":10487207.074674241,"throughput-bytes":1310720}},{"streams":[{"end":6.000158,"rtt":265793,"start":5.00015,"omitted":false,"stream-id":5,"retransmits":0,"tcp-window-size":280912,"throughput-bits":10485676.250668908,"throughput-bytes":1310720}],"summary":{"end":6.000158,"start":5.00015,"omitted":false,"retransmits":0,"throughput-bits":10485676.250668908,"throughput-bytes":1310720}},{"streams":[{"end":7.000045,"rtt":223354,"start":6.000158,"omitted":false,"stream-id":5,"retransmits":0,"tcp-window-size":325800,"throughput-bits":10486945.133932468,"throughput-bytes":1310720}],"summary":{"end":7.000045,"start":6.000158,"omitted":false,"retransmits":0,"throughput-bits":10486945.133932468,"throughput-bytes":1310720}},{"streams":[{"end":8.000077,"rtt":410151,"start":7.000045,"omitted":false,"stream-id":5,"retransmits":0,"tcp-window-size":360552,"throughput-bits":10485425.010702267,"throughput-bytes":1310720}],"summary":{"end":8.000077,"start":7.000045,"omitted":false,"retransmits":0,"throughput-bits":10485425.010702267,"throughput-bytes":1310720}},{"streams":[{"end":9.000818,"rtt":314791,"start":8.000077,"omitted":false,"stream-id":5,"retransmits":0,"tcp-window-size":401096,"throughput-bits":0,"throughput-bytes":0}],"summary":{"end":9.000818,"start":8.000077,"omitted":false,"retransmits":0,"throughput-bits":0,"throughput-bytes":0}},{"streams":[{"end":10.000863,"rtt":169669,"start":9.000818,"omitted":false,"stream-id":5,"retransmits":12,"tcp-window-size":209960,"throughput-bits":10485288.77117792,"throughput-bytes":1310720}],"summary":{"end":10.000863,"start":9.000818,"omitted":false,"retransmits":12,"throughput-bits":10485288.77117792,"throughput-bytes":1310720}}],"succeeded":true}
