{"diags":"Participant 0:\n/usr/bin/iperf3 -p 5201 -c 172.16.0.1 -t 10 --json --rsa-public-key-path /var/run/pscheduler-server/runner/tmp/tmp1wlae3ap/tmpkqomeryc/public-key --username 0ULgEh5YF5xcnM1fbQ1s\n\n{\n    \"end\": {\n        \"cpu_utilization_percent\": {\n            \"host_system\": 0.17423739756461032, \n            \"host_total\": 0.28478147825230044, \n            \"host_user\": 0.1105341965603039, \n            \"remote_system\": 1.490671685784692, \n            \"remote_total\": 1.8079152595004675, \n            \"remote_user\": 0.317223674479538\n        }, \n        \"receiver_tcp_congestion\": \"htcp\", \n        \"sender_tcp_congestion\": \"htcp\", \n        \"streams\": [\n            {\n                \"receiver\": {\n                    \"bits_per_second\": 15367189.222533979, \n                    \"bytes\": 19306184, \n                    \"end\": 10.0506, \n                    \"seconds\": 10.000161, \n                    \"sender\": true, \n                    \"socket\": 5, \n                    \"start\": 0\n                }, \n                \"sender\": {\n                    \"bits_per_second\": 18664352.303927906, \n                    \"bytes\": 23330816, \n                    \"end\": 10.000161, \n                    \"max_rtt\": 145758, \n                    \"max_snd_cwnd\": 250504, \n                    \"max_snd_wnd\": 0, \n                    \"mean_rtt\": 58624, \n                    \"min_rtt\": 31418, \n                    \"retransmits\": 574, \n                    \"seconds\": 10.000161, \n                    \"sender\": true, \n                    \"socket\": 5, \n                    \"start\": 0\n                }\n            }\n        ], \n        \"sum_received\": {\n            \"bits_per_second\": 15367189.222533979, \n            \"bytes\": 19306184, \n            \"end\": 10.0506, \n            \"seconds\": 10.0506, \n            \"sender\": true, \n            \"start\": 0\n        }, \n        \"sum_sent\": {\n            \"bits_per_second\": 18664352.303927906, \n            \"bytes\": 23330816, \n            \"end\": 10.000161, \n            \"retransmits\": 574, \n            \"seconds\": 10.000161, \n            \"sender\": true, \n            \"start\": 0\n        }\n    }, \n    \"intervals\": [\n        {\n            \"streams\": [\n                {\n                    \"bits_per_second\": 39818413.95663297, \n                    \"bytes\": 4980736, \n                    \"end\": 1.00069, \n                    \"omitted\": false, \n                    \"pmtu\": 1500, \n                    \"retransmits\": 280, \n                    \"rtt\": 145758, \n                    \"rttvar\": 917, \n                    \"seconds\": 1.00068998336792, \n                    \"sender\": true, \n                    \"snd_cwnd\": 250504, \n                    \"snd_wnd\": -1, \n                    \"socket\": 5, \n                    \"start\": 0\n                }\n            ], \n            \"sum\": {\n                \"bits_per_second\": 39818413.95663297, \n                \"bytes\": 4980736, \n                \"end\": 1.00069, \n                \"omitted\": false, \n                \"retransmits\": 280, \n                \"seconds\": 1.00068998336792, \n                \"sender\": true, \n                \"start\": 0\n            }\n        }, \n        {\n            \"streams\": [\n                {\n                    \"bits_per_second\": 20974246.60445239, \n                    \"bytes\": 2621440, \n                    \"end\": 2.00056, \n                    \"omitted\": false, \n                    \"pmtu\": 1500, \n                    \"retransmits\": 59, \n                    \"rtt\": 87113, \n                    \"rttvar\": 295, \n                    \"seconds\": 0.999870002269745, \n                    \"sender\": true, \n                    \"snd_cwnd\": 214304, \n                    \"snd_wnd\": -1, \n                    \"socket\": 5, \n                    \"start\": 1.00069\n                }\n            ], \n            \"sum\": {\n                \"bits_per_second\": 20974246.60445239, \n                \"bytes\": 2621440, \n                \"end\": 2.00056, \n                \"omitted\": false, \n                \"retransmits\": 59, \n                \"seconds\": 0.999870002269745, \n                \"sender\": true, \n                \"start\": 1.00069\n            }\n        }, \n        {\n            \"streams\": [\n                {\n                    \"bits_per_second\": 20977141.50646526, \n                    \"bytes\": 2621440, \n                    \"end\": 3.000292, \n                    \"omitted\": false, \n                    \"pmtu\": 1500, \n                    \"retransmits\": 57, \n                    \"rtt\": 48630, \n                    \"rttvar\": 745, \n                    \"seconds\": 0.99973201751709, \n                    \"sender\": true, \n                    \"snd_cwnd\": 117288, \n                    \"snd_wnd\": -1, \n                    \"socket\": 5, \n                    \"start\": 2.00056\n                }\n            ], \n            \"sum\": {\n                \"bits_per_second\": 20977141.50646526, \n                \"bytes\": 2621440, \n                \"end\": 3.000292, \n                \"omitted\": false, \n                \"retransmits\": 57, \n                \"seconds\": 0.99973201751709, \n                \"sender\": true, \n                \"start\": 2.00056\n            }\n        }, \n        {\n            \"streams\": [\n                {\n                    \"bits_per_second\": 10481346.85814107, \n                    \"bytes\": 1310720, \n                    \"end\": 4.000713, \n                    \"omitted\": false, \n                    \"pmtu\": 1500, \n                    \"retransmits\": 0, \n                    \"rtt\": 58521, \n                    \"rttvar\": 1697, \n                    \"seconds\": 1.0004210472106934, \n                    \"sender\": true, \n                    \"snd_cwnd\": 139008, \n                    \"snd_wnd\": -1, \n                    \"socket\": 5, \n                    \"start\": 3.000292\n                }\n            ], \n            \"sum\": {\n                \"bits_per_second\": 10481346.85814107, \n                \"bytes\": 1310720, \n                \"end\": 4.000713, \n                \"omitted\": false, \n                \"retransmits\": 0, \n                \"seconds\": 1.0004210472106934, \n                \"sender\": true, \n                \"start\": 3.000292\n            }\n        }, \n        {\n            \"streams\": [\n                {\n                    \"bits_per_second\": 20980835.38598479, \n                    \"bytes\": 2621440, \n                    \"end\": 5.000269, \n                    \"omitted\": false, \n                    \"pmtu\": 1500, \n                    \"retransmits\": 51, \n                    \"rtt\": 46573, \n                    \"rttvar\": 659, \n                    \"seconds\": 0.999556005001068, \n                    \"sender\": true, \n                    \"snd_cwnd\": 98464, \n                    \"snd_wnd\": -1, \n                    \"socket\": 5, \n                    \"start\": 4.000713\n                }\n            ], \n            \"sum\": {\n                \"bits_per_second\": 20980835.38598479, \n                \"bytes\": 2621440, \n                \"end\": 5.000269, \n                \"omitted\": false, \n                \"retransmits\": 51, \n                \"seconds\": 0.999556005001068, \n                \"sender\": true, \n                \"start\": 4.000713\n            }\n        }, \n        {\n            \"streams\": [\n                {\n                    \"bits_per_second\": 10484627.622300887, \n                    \"bytes\": 1310720, \n                    \"end\": 6.000377, \n                    \"omitted\": false, \n                    \"pmtu\": 1500, \n                    \"retransmits\": 47, \n                    \"rtt\": 32859, \n                    \"rttvar\": 343, \n                    \"seconds\": 1.000108003616333, \n                    \"sender\": true, \n                    \"snd_cwnd\": 69504, \n                    \"snd_wnd\": -1, \n                    \"socket\": 5, \n                    \"start\": 5.000269\n                }\n            ], \n            \"sum\": {\n                \"bits_per_second\": 10484627.622300887, \n                \"bytes\": 1310720, \n                \"end\": 6.000377, \n                \"omitted\": false, \n                \"retransmits\": 47, \n                \"seconds\": 1.000108003616333, \n                \"sender\": true, \n                \"start\": 5.000269\n            }\n        }, \n        {\n            \"streams\": [\n                {\n                    \"bits_per_second\": 10481976.36576229, \n                    \"bytes\": 1310720, \n                    \"end\": 7.000738, \n                    \"omitted\": false, \n                    \"pmtu\": 1500, \n                    \"retransmits\": 37, \n                    \"rtt\": 45024, \n                    \"rttvar\": 1963, \n                    \"seconds\": 1.00036096572876, \n                    \"sender\": true, \n                    \"snd_cwnd\": 47784, \n                    \"snd_wnd\": -1, \n                    \"socket\": 5, \n                    \"start\": 6.000377\n                }\n            ], \n            \"sum\": {\n                \"bits_per_second\": 10481976.36576229, \n                \"bytes\": 1310720, \n                \"end\": 7.000738, \n                \"omitted\": false, \n                \"retransmits\": 37, \n                \"seconds\": 1.00036096572876, \n                \"sender\": true, \n                \"start\": 6.000377\n            }\n        }, \n        {\n            \"streams\": [\n                {\n                    \"bits_per_second\": 20980500.09366826, \n                    \"bytes\": 2621440, \n                    \"end\": 8.00031, \n                    \"omitted\": false, \n                    \"pmtu\": 1500, \n                    \"retransmits\": 0, \n                    \"rtt\": 42197, \n                    \"rttvar\": 613, \n                    \"seconds\": 0.999571979045868, \n                    \"sender\": true, \n                    \"snd_cwnd\": 88328, \n                    \"snd_wnd\": -1, \n                    \"socket\": 5, \n                    \"start\": 7.000738\n                }\n            ], \n            \"sum\": {\n                \"bits_per_second\": 20980500.09366826, \n                \"bytes\": 2621440, \n                \"end\": 8.00031, \n                \"omitted\": false, \n                \"retransmits\": 0, \n                \"seconds\": 0.999571979045868, \n                \"sender\": true, \n                \"start\": 7.000738\n            }\n        }, \n        {\n            \"streams\": [\n                {\n                    \"bits_per_second\": 10484355.188232472, \n                    \"bytes\": 1310720, \n                    \"end\": 9.000444, \n                    \"omitted\": false, \n                    \"pmtu\": 1500, \n                    \"retransmits\": 43, \n                    \"rtt\": 31418, \n                    \"rttvar\": 933, \n                    \"seconds\": 1.000133991241455, \n                    \"sender\": true, \n                    \"snd_cwnd\": 68056, \n                    \"snd_wnd\": -1, \n                    \"socket\": 5, \n                    \"start\": 8.00031\n                }\n            ], \n            \"sum\": {\n                \"bits_per_second\": 10484355.188232472, \n                \"bytes\": 1310720, \n                \"end\": 9.000444, \n                \"omitted\": false, \n                \"retransmits\": 43, \n                \"seconds\": 1.000133991241455, \n                \"sender\": true, \n                \"start\": 8.00031\n            }\n        }, \n        {\n            \"streams\": [\n                {\n                    \"bits_per_second\": 20977456.68009741, \n                    \"bytes\": 2621440, \n                    \"end\": 10.000161, \n                    \"omitted\": false, \n                    \"pmtu\": 1500, \n                    \"retransmits\": 0, \n                    \"rtt\": 48150, \n                    \"rttvar\": 417, \n                    \"seconds\": 0.9997169971466064, \n                    \"sender\": true, \n                    \"snd_cwnd\": 101360, \n                    \"snd_wnd\": -1, \n                    \"socket\": 5, \n                    \"start\": 9.000444\n                }\n            ], \n            \"sum\": {\n                \"bits_per_second\": 20977456.68009741, \n                \"bytes\": 2621440, \n                \"end\": 10.000161, \n                \"omitted\": false, \n                \"retransmits\": 0, \n                \"seconds\": 0.9997169971466064, \n                \"sender\": true, \n                \"start\": 9.000444\n            }\n        }\n    ], \n    \"start\": {\n        \"connected\": [\n            {\n                \"local_host\": \"172.16.0.2\", \n                \"local_port\": 47990, \n                \"remote_host\": \"172.16.0.1\", \n                \"remote_port\": 5201, \n                \"socket\": 5\n            }\n        ], \n        \"connecting_to\": {\n            \"host\": \"172.16.0.1\", \n            \"port\": 5201\n        }, \n        \"cookie\": \"oaab64p2dixbnudwt7engzsvj4bxxjkxenmd\", \n        \"fq_rate\": 0, \n        \"rcvbuf_actual\": 87380, \n        \"sndbuf_actual\": 65536, \n        \"sock_bufsize\": 0, \n        \"system_info\": \"REDACTED\", \n        \"target_bitrate\": 0, \n        \"tcp_mss_default\": 1448, \n        \"test_start\": {\n            \"bidir\": 0, \n            \"blksize\": 131072, \n            \"blocks\": 0, \n            \"bytes\": 0, \n            \"duration\": 10, \n            \"fqrate\": 0, \n            \"num_streams\": 1, \n            \"omit\": 0, \n            \"protocol\": \"TCP\", \n            \"reverse\": 0, \n            \"target_bitrate\": 0, \n            \"tos\": 0\n        }, \n        \"timestamp\": {\n            \"time\": \"Thu, 05 Sep 2024 02:10:45 GMT\", \n            \"timesecs\": 1725502245\n        }, \n        \"version\": \"iperf 3.14\"\n    }\n}\nParticipant 1:\n/usr/bin/iperf3 -s -1 --idle-timeout 10 --json -p 5201 --authorized-users-path /var/run/pscheduler-server/runner/tmp/tmpaix8uqtb/tmpdty5evmp/credentials --rsa-private-key-path /var/run/pscheduler-server/runner/tmp/tmpaix8uqtb/tmpdty5evmp/private-key\n\n{\n    \"end\": {\n        \"cpu_utilization_percent\": {\n            \"host_system\": 1.490671685784692, \n            \"host_total\": 1.8079152595004675, \n            \"host_user\": 0.317223674479538, \n            \"remote_system\": 0, \n            \"remote_total\": 0, \n            \"remote_user\": 0\n        }, \n        \"receiver_tcp_congestion\": \"htcp\", \n        \"streams\": [\n            {\n                \"receiver\": {\n                    \"bits_per_second\": 15367189.222533979, \n                    \"bytes\": 19306184, \n                    \"end\": 10.0506, \n                    \"seconds\": 10.0506, \n                    \"sender\": false, \n                    \"socket\": 5, \n                    \"start\": 0\n                }, \n                \"sender\": {\n                    \"bits_per_second\": 0, \n                    \"bytes\": 0, \n                    \"end\": 10.0506, \n                    \"seconds\": 10.0506, \n                    \"sender\": false, \n                    \"socket\": 5, \n                    \"start\": 0\n                }\n            }\n        ], \n        \"sum_received\": {\n            \"bits_per_second\": 15367189.222533979, \n            \"bytes\": 19306184, \n            \"end\": 10.0506, \n            \"seconds\": 10.0506, \n            \"sender\": false, \n            \"start\": 0\n        }, \n        \"sum_sent\": {\n            \"bits_per_second\": 0, \n            \"bytes\": 0, \n            \"end\": 10.0506, \n            \"seconds\": 10.0506, \n            \"sender\": false, \n            \"start\": 0\n        }\n    }, \n    \"intervals\": [\n        {\n            \"streams\": [\n                {\n                    \"bits_per_second\": 14825740.2624745, \n                    \"bytes\": 1853440, \n                    \"end\": 1.00012, \n                    \"omitted\": false, \n                    \"seconds\": 1.0001200437545776, \n                    \"sender\": false, \n                    \"socket\": 5, \n                    \"start\": 0\n                }\n            ], \n            \"sum\": {\n                \"bits_per_second\": 14825740.2624745, \n                \"bytes\": 1853440, \n                \"end\": 1.00012, \n                \"omitted\": false, \n                \"seconds\": 1.0001200437545776, \n                \"sender\": false, \n                \"start\": 0\n            }\n        }, \n        {\n            \"streams\": [\n                {\n                    \"bits_per_second\": 20990879.86966479, \n                    \"bytes\": 2623776, \n                    \"end\": 2.000088, \n                    \"omitted\": false, \n                    \"seconds\": 0.9999679923057556, \n                    \"sender\": false, \n                    \"socket\": 5, \n                    \"start\": 1.00012\n                }\n            ], \n            \"sum\": {\n                \"bits_per_second\": 20990879.86966479, \n                \"bytes\": 2623776, \n                \"end\": 2.000088, \n                \"omitted\": false, \n                \"seconds\": 0.9999679923057556, \n                \"sender\": false, \n                \"start\": 1.00012\n            }\n        }, \n        {\n            \"streams\": [\n                {\n                    \"bits_per_second\": 14955288.08218859, \n                    \"bytes\": 1869368, \n                    \"end\": 3.000065, \n                    \"omitted\": false, \n                    \"seconds\": 0.9999769926071167, \n                    \"sender\": false, \n                    \"socket\": 5, \n                    \"start\": 2.000088\n                }\n            ], \n            \"sum\": {\n                \"bits_per_second\": 14955288.08218859, \n                \"bytes\": 1869368, \n                \"end\": 3.000065, \n                \"omitted\": false, \n                \"seconds\": 0.9999769926071167, \n                \"sender\": false, \n                \"start\": 2.000088\n            }\n        }, \n        {\n            \"streams\": [\n                {\n                    \"bits_per_second\": 15846182.84129134, \n                    \"bytes\": 1980864, \n                    \"end\": 4.000111, \n                    \"omitted\": false, \n                    \"seconds\": 1.0000460147857666, \n                    \"sender\": false, \n                    \"socket\": 5, \n                    \"start\": 3.000065\n                }\n            ], \n            \"sum\": {\n                \"bits_per_second\": 15846182.84129134, \n                \"bytes\": 1980864, \n                \"end\": 4.000111, \n                \"omitted\": false, \n                \"seconds\": 1.0000460147857666, \n                \"sender\": false, \n                \"start\": 3.000065\n            }\n        }, \n        {\n            \"streams\": [\n                {\n                    \"bits_per_second\": 15141029.835029388, \n                    \"bytes\": 1892536, \n                    \"end\": 5.000062, \n                    \"omitted\": false, \n                    \"seconds\": 0.9999510049819946, \n                    \"sender\": false, \n                    \"socket\": 5, \n                    \"start\": 4.000111\n                }\n            ], \n            \"sum\": {\n                \"bits_per_second\": 15141029.835029388, \n                \"bytes\": 1892536, \n                \"end\": 5.000062, \n                \"omitted\": false, \n                \"seconds\": 0.9999510049819946, \n                \"sender\": false, \n                \"start\": 4.000111\n            }\n        }, \n        {\n            \"streams\": [\n                {\n                    \"bits_per_second\": 12140044.301251478, \n                    \"bytes\": 1517504, \n                    \"end\": 6.000061, \n                    \"omitted\": false, \n                    \"seconds\": 0.9999989867210388, \n                    \"sender\": false, \n                    \"socket\": 5, \n                    \"start\": 5.000062\n                }\n            ], \n            \"sum\": {\n                \"bits_per_second\": 12140044.301251478, \n                \"bytes\": 1517504, \n                \"end\": 6.000061, \n                \"omitted\": false, \n                \"seconds\": 0.9999989867210388, \n                \"sender\": false, \n                \"start\": 5.000062\n            }\n        }, \n        {\n            \"streams\": [\n                {\n                    \"bits_per_second\": 13518473.208062043, \n                    \"bytes\": 1689816, \n                    \"end\": 7.000065, \n                    \"omitted\": false, \n                    \"seconds\": 1.0000040531158447, \n                    \"sender\": false, \n                    \"socket\": 5, \n                    \"start\": 6.000061\n                }\n            ], \n            \"sum\": {\n                \"bits_per_second\": 13518473.208062043, \n                \"bytes\": 1689816, \n                \"end\": 7.000065, \n                \"omitted\": false, \n                \"seconds\": 1.0000040531158447, \n                \"sender\": false, \n                \"start\": 6.000061\n            }\n        }, \n        {\n            \"streams\": [\n                {\n                    \"bits_per_second\": 16900328.70189984, \n                    \"bytes\": 2112632, \n                    \"end\": 8.000108, \n                    \"omitted\": false, \n                    \"seconds\": 1.0000430345535278, \n                    \"sender\": false, \n                    \"socket\": 5, \n                    \"start\": 7.000065\n                }\n            ], \n            \"sum\": {\n                \"bits_per_second\": 16900328.70189984, \n                \"bytes\": 2112632, \n                \"end\": 8.000108, \n                \"omitted\": false, \n                \"seconds\": 1.0000430345535278, \n                \"sender\": false, \n                \"start\": 7.000065\n            }\n        }, \n        {\n            \"streams\": [\n                {\n                    \"bits_per_second\": 12777509.951502634, \n                    \"bytes\": 1597144, \n                    \"end\": 9.00008, \n                    \"omitted\": false, \n                    \"seconds\": 0.9999719858169556, \n                    \"sender\": false, \n                    \"socket\": 5, \n                    \"start\": 8.000108\n                }\n            ], \n            \"sum\": {\n                \"bits_per_second\": 12777509.951502634, \n                \"bytes\": 1597144, \n                \"end\": 9.00008, \n                \"omitted\": false, \n                \"seconds\": 0.9999719858169556, \n                \"sender\": false, \n                \"start\": 8.000108\n            }\n        }, \n        {\n            \"streams\": [\n                {\n                    \"bits_per_second\": 16529508.874639828, \n                    \"bytes\": 2066296, \n                    \"end\": 10.000132, \n                    \"omitted\": false, \n                    \"seconds\": 1.0000519752502441, \n                    \"sender\": false, \n                    \"socket\": 5, \n                    \"start\": 9.00008\n                }\n            ], \n            \"sum\": {\n                \"bits_per_second\": 16529508.874639828, \n                \"bytes\": 2066296, \n                \"end\": 10.000132, \n                \"omitted\": false, \n                \"seconds\": 1.0000519752502441, \n                \"sender\": false, \n                \"start\": 9.00008\n            }\n        }, \n        {\n            \"streams\": [\n                {\n                    \"bits_per_second\": 16296742.00118414, \n                    \"bytes\": 102808, \n                    \"end\": 10.0506, \n                    \"omitted\": false, \n                    \"seconds\": 0.05046800151467323, \n                    \"sender\": false, \n                    \"socket\": 5, \n                    \"start\": 10.000132\n                }\n            ], \n            \"sum\": {\n                \"bits_per_second\": 16296742.00118414, \n                \"bytes\": 102808, \n                \"end\": 10.0506, \n                \"omitted\": false, \n                \"seconds\": 0.05046800151467323, \n                \"sender\": false, \n                \"start\": 10.000132\n            }\n        }\n    ], \n    \"start\": {\n        \"accepted_connection\": {\n            \"host\": \"172.16.0.2\", \n            \"port\": 47988\n        }, \n        \"connected\": [\n            {\n                \"local_host\": \"172.16.0.1\", \n                \"local_port\": 5201, \n                \"remote_host\": \"172.16.0.2\", \n                \"remote_port\": 47990, \n                \"socket\": 5\n            }\n        ], \n        \"cookie\": \"oaab64p2dixbnudwt7engzsvj4bxxjkxenmd\", \n        \"fq_rate\": 0, \n        \"rcvbuf_actual\": 87380, \n        \"sndbuf_actual\": 65536, \n        \"sock_bufsize\": 0, \n        \"system_info\": \"REDACTED\", \n        \"target_bitrate\": 0, \n        \"tcp_mss_default\": 0, \n        \"test_start\": {\n            \"bidir\": 0, \n            \"blksize\": 131072, \n            \"blocks\": 0, \n            \"bytes\": 0, \n            \"duration\": 10, \n            \"fqrate\": 0, \n            \"num_streams\": 1, \n            \"omit\": 0, \n            \"protocol\": \"TCP\", \n            \"reverse\": 0, \n            \"target_bitrate\": 0, \n            \"tos\": 0\n        }, \n        \"timestamp\": {\n            \"time\": \"Thu, 05 Sep 2024 02:10:45 GMT\", \n            \"timesecs\": 1725502245\n        }, \n        \"version\": \"iperf 3.14\"\n    }\n}\n","summary":{"streams":[{"end":10.000161,"rtt":58624,"start":0,"stream-id":5,"retransmits":574,"throughput-bits":18664352.303927906,"throughput-bytes":23330816}],"summary":{"end":10.000161,"start":0,"retransmits":574,"throughput-bits":18664352.303927906,"throughput-bytes":23330816,"receiver-throughput-bits":15367189.222533979}},"intervals":[{"streams":[{"end":1.00069,"rtt":145758,"start":0,"omitted":false,"stream-id":5,"retransmits":280,"tcp-window-size":250504,"throughput-bits":39818413.95663297,"throughput-bytes":4980736}],"summary":{"end":1.00069,"start":0,"omitted":false,"retransmits":280,"throughput-bits":39818413.95663297,"throughput-bytes":4980736}},{"streams":[{"end":2.00056,"rtt":87113,"start":1.00069,"omitted":false,"stream-id":5,"retransmits":59,"tcp-window-size":214304,"throughput-bits":20974246.60445239,"throughput-bytes":2621440}],"summary":{"end":2.00056,"start":1.00069,"omitted":false,"retransmits":59,"throughput-bits":20974246.60445239,"throughput-bytes":2621440}},{"streams":[{"end":3.000292,"rtt":48630,"start":2.00056,"omitted":false,"stream-id":5,"retransmits":57,"tcp-window-size":117288,"throughput-bits":20977141.50646526,"throughput-bytes":2621440}],"summary":{"end":3.000292,"start":2.00056,"omitted":false,"retransmits":57,"throughput-bits":20977141.50646526,"throughput-bytes":2621440}},{"streams":[{"end":4.000713,"rtt":58521,"start":3.000292,"omitted":false,"stream-id":5,"retransmits":0,"tcp-window-size":139008,"throughput-bits":10481346.85814107,"throughput-bytes":1310720}],"summary":{"end":4.000713,"start":3.000292,"omitted":false,"retransmits":0,"throughput-bits":10481346.85814107,"throughput-bytes":1310720}},{"streams":[{"end":5.000269,"rtt":46573,"start":4.000713,"omitted":false,"stream-id":5,"retransmits":51,"tcp-window-size":98464,"throughput-bits":20980835.38598479,"throughput-bytes":2621440}],"summary":{"end":5.000269,"start":4.000713,"omitted":false,"retransmits":51,"throughput-bits":20980835.38598479,"throughput-bytes":2621440}},{"streams":[{"end":6.000377,"rtt":32859,"start":5.000269,"omitted":false,"stream-id":5,"retransmits":47,"tcp-window-size":69504,"throughput-bits":10484627.622300887,"throughput-bytes":1310720}],"summary":{"end":6.000377,"start":5.000269,"omitted":false,"retransmits":47,"throughput-bits":10484627.622300887,"throughput-bytes":1310720}},{"streams":[{"end":7.000738,"rtt":45024,"start":6.000377,"omitted":false,"stream-id":5,"retransmits":37,"tcp-window-size":47784,"throughput-bits":10481976.36576229,"throughput-bytes":1310720}],"summary":{"end":7.000738,"start":6.000377,"omitted":false,"retransmits":37,"throughput-bits":10481976.36576229,"throughput-bytes":1310720}},{"streams":[{"end":8.00031,"rtt":42197,"start":7.000738,"omitted":false,"stream-id":5,"retransmits":0,"tcp-window-size":88328,"throughput-bits":20980500.09366826,"throughput-bytes":2621440}],"summary":{"end":8.00031,"start":7.000738,"omitted":false,"retransmits":0,"throughput-bits":20980500.09366826,"throughput-bytes":2621440}},{"streams":[{"end":9.000444,"rtt":31418,"start":8.00031,"omitted":false,"stream-id":5,"retransmits":43,"tcp-window-size":68056,"throughput-bits":10484355.188232472,"throughput-bytes":1310720}],"summary":{"end":9.000444,"start":8.00031,"omitted":false,"retransmits":43,"throughput-bits":10484355.188232472,"throughput-bytes":1310720}},{"streams":[{"end":10.000161,"rtt":48150,"start":9.000444,"omitted":false,"stream-id":5,"retransmits":0,"tcp-window-size":101360,"throughput-bits":20977456.68009741,"throughput-bytes":2621440}],"summary":{"end":10.000161,"start":9.000444,"omitted":false,"retransmits":0,"throughput-bits":20977456.68009741,"throughput-bytes":2621440}}],"succeeded":true}
