{"diags":"Participant 0:\n/usr/bin/iperf3 -p 5201 -c 172.16.0.1 -t 10 --json --rsa-public-key-path /var/run/pscheduler-server/runner/tmp/tmp2gs3a6hc/tmph53bmfy9/public-key --username uW5yEUod4o2lg00I1f5q\n\n{\n    \"end\": {\n        \"cpu_utilization_percent\": {\n            \"host_system\": 0.2559439530753911, \n            \"host_total\": 0.3219617532324122, \n            \"host_user\": 0.0659980017464178, \n            \"remote_system\": 3.31772229476717, \n            \"remote_total\": 5.20290980561918, \n            \"remote_user\": 1.8851875108520106\n        }, \n        \"receiver_tcp_congestion\": \"htcp\", \n        \"sender_tcp_congestion\": \"htcp\", \n        \"streams\": [\n            {\n                \"receiver\": {\n                    \"bits_per_second\": 20861094.2961357, \n                    \"bytes\": 26311608, \n                    \"end\": 10.090212, \n                    \"seconds\": 10.000038, \n                    \"sender\": true, \n                    \"socket\": 5, \n                    \"start\": 0\n                }, \n                \"sender\": {\n                    \"bits_per_second\": 23488013.145550046, \n                    \"bytes\": 29360128, \n                    \"end\": 10.000038, \n                    \"max_rtt\": 285193, \n                    \"max_snd_cwnd\": 388064, \n                    \"max_snd_wnd\": 0, \n                    \"mean_rtt\": 115050, \n                    \"min_rtt\": 77232, \n                    \"retransmits\": 352, \n                    \"seconds\": 10.000038, \n                    \"sender\": true, \n                    \"socket\": 5, \n                    \"start\": 0\n                }\n            }\n        ], \n        \"sum_received\": {\n            \"bits_per_second\": 20861094.2961357, \n            \"bytes\": 26311608, \n            \"end\": 10.090212, \n            \"seconds\": 10.090212, \n            \"sender\": true, \n            \"start\": 0\n        }, \n        \"sum_sent\": {\n            \"bits_per_second\": 23488013.145550046, \n            \"bytes\": 29360128, \n            \"end\": 10.000038, \n            \"retransmits\": 352, \n            \"seconds\": 10.000038, \n            \"sender\": true, \n            \"start\": 0\n        }\n    }, \n    \"intervals\": [\n        {\n            \"streams\": [\n                {\n                    \"bits_per_second\": 35594915.46857228, \n                    \"bytes\": 4456448, \n                    \"end\": 1.001592, \n                    \"omitted\": false, \n                    \"pmtu\": 1500, \n                    \"retransmits\": 328, \n                    \"rtt\": 285193, \n                    \"rttvar\": 1960, \n                    \"seconds\": 1.0015920400619507, \n                    \"sender\": true, \n                    \"snd_cwnd\": 305528, \n                    \"snd_wnd\": -1, \n                    \"socket\": 5, \n                    \"start\": 0\n                }\n            ], \n            \"sum\": {\n                \"bits_per_second\": 35594915.46857228, \n                \"bytes\": 4456448, \n                \"end\": 1.001592, \n                \"omitted\": false, \n                \"retransmits\": 328, \n                \"seconds\": 1.0015920400619507, \n                \"sender\": true, \n                \"start\": 0\n            }\n        }, \n        {\n            \"streams\": [\n                {\n                    \"bits_per_second\": 31501255.76518514, \n                    \"bytes\": 3932160, \n                    \"end\": 2.000196, \n                    \"omitted\": false, \n                    \"pmtu\": 1500, \n                    \"retransmits\": 17, \n                    \"rtt\": 77481, \n                    \"rttvar\": 523, \n                    \"seconds\": 0.9986039996147156, \n                    \"sender\": true, \n                    \"snd_cwnd\": 212856, \n                    \"snd_wnd\": -1, \n                    \"socket\": 5, \n                    \"start\": 1.001592\n                }\n            ], \n            \"sum\": {\n                \"bits_per_second\": 31501255.76518514, \n                \"bytes\": 3932160, \n                \"end\": 2.000196, \n                \"omitted\": false, \n                \"retransmits\": 17, \n                \"seconds\": 0.9986039996147156, \n                \"sender\": true, \n                \"start\": 1.001592\n            }\n        }, \n        {\n            \"streams\": [\n                {\n                    \"bits_per_second\": 20970890.0189251, \n                    \"bytes\": 2621440, \n                    \"end\": 3.000226, \n                    \"omitted\": false, \n                    \"pmtu\": 1500, \n                    \"retransmits\": 0, \n                    \"rtt\": 84273, \n                    \"rttvar\": 415, \n                    \"seconds\": 1.0000300407409668, \n                    \"sender\": true, \n                    \"snd_cwnd\": 230232, \n                    \"snd_wnd\": -1, \n                    \"socket\": 5, \n                    \"start\": 2.000196\n                }\n            ], \n            \"sum\": {\n                \"bits_per_second\": 20970890.0189251, \n                \"bytes\": 2621440, \n                \"end\": 3.000226, \n                \"omitted\": false, \n                \"retransmits\": 0, \n                \"seconds\": 1.0000300407409668, \n                \"sender\": true, \n                \"start\": 2.000196\n            }\n        }, \n        {\n            \"streams\": [\n                {\n                    \"bits_per_second\": 20970890.0189251, \n                    \"bytes\": 2621440, \n                    \"end\": 4.000256, \n                    \"omitted\": false, \n                    \"pmtu\": 1500, \n                    \"retransmits\": 0, \n                    \"rtt\": 90573, \n                    \"rttvar\": 860, \n                    \"seconds\": 1.0000300407409668, \n                    \"sender\": true, \n                    \"snd_cwnd\": 250504, \n                    \"snd_wnd\": -1, \n                    \"socket\": 5, \n                    \"start\": 3.000226\n                }\n            ], \n            \"sum\": {\n                \"bits_per_second\": 20970890.0189251, \n                \"bytes\": 2621440, \n                \"end\": 4.000256, \n                \"omitted\": false, \n                \"retransmits\": 0, \n                \"seconds\": 1.0000300407409668, \n                \"sender\": true, \n                \"start\": 3.000226\n            }\n        }, \n        {\n            \"streams\": [\n                {\n                    \"bits_per_second\": 20959866.479265776, \n                    \"bytes\": 2621440, \n                    \"end\": 5.000812, \n                    \"omitted\": false, \n                    \"pmtu\": 1500, \n                    \"retransmits\": 0, \n                    \"rtt\": 103131, \n                    \"rttvar\": 879, \n                    \"seconds\": 1.0005559921264648, \n                    \"sender\": true, \n                    \"snd_cwnd\": 285256, \n                    \"snd_wnd\": -1, \n                    \"socket\": 5, \n                    \"start\": 4.000256\n                }\n            ], \n            \"sum\": {\n                \"bits_per_second\": 20959866.479265776, \n                \"bytes\": 2621440, \n                \"end\": 5.000812, \n                \"omitted\": false, \n                \"retransmits\": 0, \n                \"seconds\": 1.0005559921264648, \n                \"sender\": true, \n                \"start\": 4.000256\n            }\n        }, \n        {\n            \"streams\": [\n                {\n                    \"bits_per_second\": 20987890.26858656, \n                    \"bytes\": 2621440, \n                    \"end\": 6.000032, \n                    \"omitted\": false, \n                    \"pmtu\": 1500, \n                    \"retransmits\": 0, \n                    \"rtt\": 120081, \n                    \"rttvar\": 90, \n                    \"seconds\": 0.9992200136184692, \n                    \"sender\": true, \n                    \"snd_cwnd\": 331592, \n                    \"snd_wnd\": -1, \n                    \"socket\": 5, \n                    \"start\": 5.000812\n                }\n            ], \n            \"sum\": {\n                \"bits_per_second\": 20987890.26858656, \n                \"bytes\": 2621440, \n                \"end\": 6.000032, \n                \"omitted\": false, \n                \"retransmits\": 0, \n                \"seconds\": 0.9992200136184692, \n                \"sender\": true, \n                \"start\": 5.000812\n            }\n        }, \n        {\n            \"streams\": [\n                {\n                    \"bits_per_second\": 20969990.111614667, \n                    \"bytes\": 2621440, \n                    \"end\": 7.000105, \n                    \"omitted\": false, \n                    \"pmtu\": 1500, \n                    \"retransmits\": 0, \n                    \"rtt\": 139575, \n                    \"rttvar\": 1104, \n                    \"seconds\": 1.000072956085205, \n                    \"sender\": true, \n                    \"snd_cwnd\": 388064, \n                    \"snd_wnd\": -1, \n                    \"socket\": 5, \n                    \"start\": 6.000032\n                }\n            ], \n            \"sum\": {\n                \"bits_per_second\": 20969990.111614667, \n                \"bytes\": 2621440, \n                \"end\": 7.000105, \n                \"omitted\": false, \n                \"retransmits\": 0, \n                \"seconds\": 1.000072956085205, \n                \"sender\": true, \n                \"start\": 6.000032\n            }\n        }, \n        {\n            \"streams\": [\n                {\n                    \"bits_per_second\": 20971500.000019073, \n                    \"bytes\": 2621440, \n                    \"end\": 8.000106, \n                    \"omitted\": false, \n                    \"pmtu\": 1500, \n                    \"retransmits\": 7, \n                    \"rtt\": 77232, \n                    \"rttvar\": 596, \n                    \"seconds\": 1.0000009536743164, \n                    \"sender\": true, \n                    \"snd_cwnd\": 211408, \n                    \"snd_wnd\": -1, \n                    \"socket\": 5, \n                    \"start\": 7.000105\n                }\n            ], \n            \"sum\": {\n                \"bits_per_second\": 20971500.000019073, \n                \"bytes\": 2621440, \n                \"end\": 8.000106, \n                \"omitted\": false, \n                \"retransmits\": 7, \n                \"seconds\": 1.0000009536743164, \n                \"sender\": true, \n                \"start\": 7.000105\n            }\n        }, \n        {\n            \"streams\": [\n                {\n                    \"bits_per_second\": 20971646.250760037, \n                    \"bytes\": 2621440, \n                    \"end\": 9.0001, \n                    \"omitted\": false, \n                    \"pmtu\": 1500, \n                    \"retransmits\": 0, \n                    \"rtt\": 83315, \n                    \"rttvar\": 578, \n                    \"seconds\": 0.9999939799308777, \n                    \"sender\": true, \n                    \"snd_cwnd\": 228784, \n                    \"snd_wnd\": -1, \n                    \"socket\": 5, \n                    \"start\": 8.000106\n                }\n            ], \n            \"sum\": {\n                \"bits_per_second\": 20971646.250760037, \n                \"bytes\": 2621440, \n                \"end\": 9.0001, \n                \"omitted\": false, \n                \"retransmits\": 0, \n                \"seconds\": 0.9999939799308777, \n                \"sender\": true, \n                \"start\": 8.000106\n            }\n        }, \n        {\n            \"streams\": [\n                {\n                    \"bits_per_second\": 20972820.080590475, \n                    \"bytes\": 2621440, \n                    \"end\": 10.000038, \n                    \"omitted\": false, \n                    \"pmtu\": 1500, \n                    \"retransmits\": 0, \n                    \"rtt\": 89654, \n                    \"rttvar\": 339, \n                    \"seconds\": 0.9999380111694336, \n                    \"sender\": true, \n                    \"snd_cwnd\": 246160, \n                    \"snd_wnd\": -1, \n                    \"socket\": 5, \n                    \"start\": 9.0001\n                }\n            ], \n            \"sum\": {\n                \"bits_per_second\": 20972820.080590475, \n                \"bytes\": 2621440, \n                \"end\": 10.000038, \n                \"omitted\": false, \n                \"retransmits\": 0, \n                \"seconds\": 0.9999380111694336, \n                \"sender\": true, \n                \"start\": 9.0001\n            }\n        }\n    ], \n    \"start\": {\n        \"connected\": [\n            {\n                \"local_host\": \"172.16.0.2\", \n                \"local_port\": 51064, \n                \"remote_host\": \"172.16.0.1\", \n                \"remote_port\": 5201, \n                \"socket\": 5\n            }\n        ], \n        \"connecting_to\": {\n            \"host\": \"172.16.0.1\", \n            \"port\": 5201\n        }, \n        \"cookie\": \"26wfxauey3fsxw5ow6n6e4ugajrvmnj3oqum\", \n        \"fq_rate\": 0, \n        \"rcvbuf_actual\": 87380, \n        \"sndbuf_actual\": 65536, \n        \"sock_bufsize\": 0, \n        \"system_info\": \"REDACTED\", \n        \"target_bitrate\": 0, \n        \"tcp_mss_default\": 1448, \n        \"test_start\": {\n            \"bidir\": 0, \n            \"blksize\": 131072, \n            \"blocks\": 0, \n            \"bytes\": 0, \n            \"duration\": 10, \n            \"fqrate\": 0, \n            \"num_streams\": 1, \n            \"omit\": 0, \n            \"protocol\": \"TCP\", \n            \"reverse\": 0, \n            \"target_bitrate\": 0, \n            \"tos\": 0\n        }, \n        \"timestamp\": {\n            \"time\": \"Wed, 11 Sep 2024 18:21:25 GMT\", \n            \"timesecs\": 1726078885\n        }, \n        \"version\": \"iperf 3.14\"\n    }\n}\nParticipant 1:\n/usr/bin/iperf3 -s -1 --idle-timeout 10 --json -p 5201 --authorized-users-path /var/run/pscheduler-server/runner/tmp/tmp5szpk5lx/tmp_3nkeixr/credentials --rsa-private-key-path /var/run/pscheduler-server/runner/tmp/tmp5szpk5lx/tmp_3nkeixr/private-key\n\n{\n    \"end\": {\n        \"cpu_utilization_percent\": {\n            \"host_system\": 3.31772229476717, \n            \"host_total\": 5.20290980561918, \n            \"host_user\": 1.8851875108520106, \n            \"remote_system\": 0, \n            \"remote_total\": 0, \n            \"remote_user\": 0\n        }, \n        \"receiver_tcp_congestion\": \"htcp\", \n        \"streams\": [\n            {\n                \"receiver\": {\n                    \"bits_per_second\": 20861094.2961357, \n                    \"bytes\": 26311608, \n                    \"end\": 10.090212, \n                    \"seconds\": 10.090212, \n                    \"sender\": false, \n                    \"socket\": 5, \n                    \"start\": 0\n                }, \n                \"sender\": {\n                    \"bits_per_second\": 0, \n                    \"bytes\": 0, \n                    \"end\": 10.090212, \n                    \"seconds\": 10.090212, \n                    \"sender\": false, \n                    \"socket\": 5, \n                    \"start\": 0\n                }\n            }\n        ], \n        \"sum_received\": {\n            \"bits_per_second\": 20861094.2961357, \n            \"bytes\": 26311608, \n            \"end\": 10.090212, \n            \"seconds\": 10.090212, \n            \"sender\": false, \n            \"start\": 0\n        }, \n        \"sum_sent\": {\n            \"bits_per_second\": 0, \n            \"bytes\": 0, \n            \"end\": 10.090212, \n            \"seconds\": 10.090212, \n            \"sender\": false, \n            \"start\": 0\n        }\n    }, \n    \"intervals\": [\n        {\n            \"streams\": [\n                {\n                    \"bits_per_second\": 12159892.076478181, \n                    \"bytes\": 1520400, \n                    \"end\": 1.000272, \n                    \"omitted\": false, \n                    \"seconds\": 1.0002720355987549, \n                    \"sender\": false, \n                    \"socket\": 5, \n                    \"start\": 0\n                }\n            ], \n            \"sum\": {\n                \"bits_per_second\": 12159892.076478181, \n                \"bytes\": 1520400, \n                \"end\": 1.000272, \n                \"omitted\": false, \n                \"seconds\": 1.0002720355987549, \n                \"sender\": false, \n                \"start\": 0\n            }\n        }, \n        {\n            \"streams\": [\n                {\n                    \"bits_per_second\": 22927486.93503, \n                    \"bytes\": 2865592, \n                    \"end\": 2.000152, \n                    \"omitted\": false, \n                    \"seconds\": 0.999880015850067, \n                    \"sender\": false, \n                    \"socket\": 5, \n                    \"start\": 1.000272\n                }\n            ], \n            \"sum\": {\n                \"bits_per_second\": 22927486.93503, \n                \"bytes\": 2865592, \n                \"end\": 2.000152, \n                \"omitted\": false, \n                \"seconds\": 0.999880015850067, \n                \"sender\": false, \n                \"start\": 1.000272\n            }\n        }, \n        {\n            \"streams\": [\n                {\n                    \"bits_per_second\": 21674683.318410054, \n                    \"bytes\": 2709208, \n                    \"end\": 3.000105, \n                    \"omitted\": false, \n                    \"seconds\": 0.9999529719352722, \n                    \"sender\": false, \n                    \"socket\": 5, \n                    \"start\": 2.000152\n                }\n            ], \n            \"sum\": {\n                \"bits_per_second\": 21674683.318410054, \n                \"bytes\": 2709208, \n                \"end\": 3.000105, \n                \"omitted\": false, \n                \"seconds\": 0.9999529719352722, \n                \"sender\": false, \n                \"start\": 2.000152\n            }\n        }, \n        {\n            \"streams\": [\n                {\n                    \"bits_per_second\": 21697287.227202415, \n                    \"bytes\": 2712104, \n                    \"end\": 4.000084, \n                    \"omitted\": false, \n                    \"seconds\": 0.999979019165039, \n                    \"sender\": false, \n                    \"socket\": 5, \n                    \"start\": 3.000105\n                }\n            ], \n            \"sum\": {\n                \"bits_per_second\": 21697287.227202415, \n                \"bytes\": 2712104, \n                \"end\": 4.000084, \n                \"omitted\": false, \n                \"seconds\": 0.999979019165039, \n                \"sender\": false, \n                \"start\": 3.000105\n            }\n        }, \n        {\n            \"streams\": [\n                {\n                    \"bits_per_second\": 21661344.06347059, \n                    \"bytes\": 2707760, \n                    \"end\": 5.000118, \n                    \"omitted\": false, \n                    \"seconds\": 1.000033974647522, \n                    \"sender\": false, \n                    \"socket\": 5, \n                    \"start\": 4.000084\n                }\n            ], \n            \"sum\": {\n                \"bits_per_second\": 21661344.06347059, \n                \"bytes\": 2707760, \n                \"end\": 5.000118, \n                \"omitted\": false, \n                \"seconds\": 1.000033974647522, \n                \"sender\": false, \n                \"start\": 4.000084\n            }\n        }, \n        {\n            \"streams\": [\n                {\n                    \"bits_per_second\": 21697266.534642436, \n                    \"bytes\": 2712104, \n                    \"end\": 6.000098, \n                    \"omitted\": false, \n                    \"seconds\": 0.9999799728393555, \n                    \"sender\": false, \n                    \"socket\": 5, \n                    \"start\": 5.000118\n                }\n            ], \n            \"sum\": {\n                \"bits_per_second\": 21697266.534642436, \n                \"bytes\": 2712104, \n                \"end\": 6.000098, \n                \"omitted\": false, \n                \"seconds\": 0.9999799728393555, \n                \"sender\": false, \n                \"start\": 5.000118\n            }\n        }, \n        {\n            \"streams\": [\n                {\n                    \"bits_per_second\": 21660889.615360178, \n                    \"bytes\": 2707760, \n                    \"end\": 7.000153, \n                    \"omitted\": false, \n                    \"seconds\": 1.000054955482483, \n                    \"sender\": false, \n                    \"socket\": 5, \n                    \"start\": 6.000098\n                }\n            ], \n            \"sum\": {\n                \"bits_per_second\": 21660889.615360178, \n                \"bytes\": 2707760, \n                \"end\": 7.000153, \n                \"omitted\": false, \n                \"seconds\": 1.000054955482483, \n                \"sender\": false, \n                \"start\": 6.000098\n            }\n        }, \n        {\n            \"streams\": [\n                {\n                    \"bits_per_second\": 21685789.588415954, \n                    \"bytes\": 2710656, \n                    \"end\": 8.000128, \n                    \"omitted\": false, \n                    \"seconds\": 0.999975025653839, \n                    \"sender\": false, \n                    \"socket\": 5, \n                    \"start\": 7.000153\n                }\n            ], \n            \"sum\": {\n                \"bits_per_second\": 21685789.588415954, \n                \"bytes\": 2710656, \n                \"end\": 8.000128, \n                \"omitted\": false, \n                \"seconds\": 0.999975025653839, \n                \"sender\": false, \n                \"start\": 7.000153\n            }\n        }, \n        {\n            \"streams\": [\n                {\n                    \"bits_per_second\": 21686223.912752993, \n                    \"bytes\": 2710656, \n                    \"end\": 9.000083, \n                    \"omitted\": false, \n                    \"seconds\": 0.9999549984931946, \n                    \"sender\": false, \n                    \"socket\": 5, \n                    \"start\": 8.000128\n                }\n            ], \n            \"sum\": {\n                \"bits_per_second\": 21686223.912752993, \n                \"bytes\": 2710656, \n                \"end\": 9.000083, \n                \"omitted\": false, \n                \"seconds\": 0.9999549984931946, \n                \"sender\": false, \n                \"start\": 8.000128\n            }\n        }, \n        {\n            \"streams\": [\n                {\n                    \"bits_per_second\": 21673338.458426744, \n                    \"bytes\": 2709208, \n                    \"end\": 10.000098, \n                    \"omitted\": false, \n                    \"seconds\": 1.0000150203704834, \n                    \"sender\": false, \n                    \"socket\": 5, \n                    \"start\": 9.000083\n                }\n            ], \n            \"sum\": {\n                \"bits_per_second\": 21673338.458426744, \n                \"bytes\": 2709208, \n                \"end\": 10.000098, \n                \"omitted\": false, \n                \"seconds\": 1.0000150203704834, \n                \"sender\": false, \n                \"start\": 9.000083\n            }\n        }, \n        {\n            \"streams\": [\n                {\n                    \"bits_per_second\": 21853208.7746633, \n                    \"bytes\": 246160, \n                    \"end\": 10.090212, \n                    \"omitted\": false, \n                    \"seconds\": 0.09011399745941162, \n                    \"sender\": false, \n                    \"socket\": 5, \n                    \"start\": 10.000098\n                }\n            ], \n            \"sum\": {\n                \"bits_per_second\": 21853208.7746633, \n                \"bytes\": 246160, \n                \"end\": 10.090212, \n                \"omitted\": false, \n                \"seconds\": 0.09011399745941162, \n                \"sender\": false, \n                \"start\": 10.000098\n            }\n        }\n    ], \n    \"start\": {\n        \"accepted_connection\": {\n            \"host\": \"172.16.0.2\", \n            \"port\": 51050\n        }, \n        \"connected\": [\n            {\n                \"local_host\": \"172.16.0.1\", \n                \"local_port\": 5201, \n                \"remote_host\": \"172.16.0.2\", \n                \"remote_port\": 51064, \n                \"socket\": 5\n            }\n        ], \n        \"cookie\": \"26wfxauey3fsxw5ow6n6e4ugajrvmnj3oqum\", \n        \"fq_rate\": 0, \n        \"rcvbuf_actual\": 87380, \n        \"sndbuf_actual\": 65536, \n        \"sock_bufsize\": 0, \n        \"system_info\": \"REDACTED\", \n        \"target_bitrate\": 0, \n        \"tcp_mss_default\": 0, \n        \"test_start\": {\n            \"bidir\": 0, \n            \"blksize\": 131072, \n            \"blocks\": 0, \n            \"bytes\": 0, \n            \"duration\": 10, \n            \"fqrate\": 0, \n            \"num_streams\": 1, \n            \"omit\": 0, \n            \"protocol\": \"TCP\", \n            \"reverse\": 0, \n            \"target_bitrate\": 0, \n            \"tos\": 0\n        }, \n        \"timestamp\": {\n            \"time\": \"Wed, 11 Sep 2024 18:21:25 GMT\", \n            \"timesecs\": 1726078885\n        }, \n        \"version\": \"iperf 3.14\"\n    }\n}\n","summary":{"streams":[{"end":10.000038,"rtt":115050,"start":0,"stream-id":5,"retransmits":352,"throughput-bits":23488013.145550046,"throughput-bytes":29360128}],"summary":{"end":10.000038,"start":0,"retransmits":352,"throughput-bits":23488013.145550046,"throughput-bytes":29360128,"receiver-throughput-bits":20861094.2961357}},"intervals":[{"streams":[{"end":1.001592,"rtt":285193,"start":0,"omitted":false,"stream-id":5,"retransmits":328,"tcp-window-size":305528,"throughput-bits":35594915.46857228,"throughput-bytes":4456448}],"summary":{"end":1.001592,"start":0,"omitted":false,"retransmits":328,"throughput-bits":35594915.46857228,"throughput-bytes":4456448}},{"streams":[{"end":2.000196,"rtt":77481,"start":1.001592,"omitted":false,"stream-id":5,"retransmits":17,"tcp-window-size":212856,"throughput-bits":31501255.76518514,"throughput-bytes":3932160}],"summary":{"end":2.000196,"start":1.001592,"omitted":false,"retransmits":17,"throughput-bits":31501255.76518514,"throughput-bytes":3932160}},{"streams":[{"end":3.000226,"rtt":84273,"start":2.000196,"omitted":false,"stream-id":5,"retransmits":0,"tcp-window-size":230232,"throughput-bits":20970890.0189251,"throughput-bytes":2621440}],"summary":{"end":3.000226,"start":2.000196,"omitted":false,"retransmits":0,"throughput-bits":20970890.0189251,"throughput-bytes":2621440}},{"streams":[{"end":4.000256,"rtt":90573,"start":3.000226,"omitted":false,"stream-id":5,"retransmits":0,"tcp-window-size":250504,"throughput-bits":20970890.0189251,"throughput-bytes":2621440}],"summary":{"end":4.000256,"start":3.000226,"omitted":false,"retransmits":0,"throughput-bits":20970890.0189251,"throughput-bytes":2621440}},{"streams":[{"end":5.000812,"rtt":103131,"start":4.000256,"omitted":false,"stream-id":5,"retransmits":0,"tcp-window-size":285256,"throughput-bits":20959866.479265776,"throughput-bytes":2621440}],"summary":{"end":5.000812,"start":4.000256,"omitted":false,"retransmits":0,"throughput-bits":20959866.479265776,"throughput-bytes":2621440}},{"streams":[{"end":6.000032,"rtt":120081,"start":5.000812,"omitted":false,"stream-id":5,"retransmits":0,"tcp-window-size":331592,"throughput-bits":20987890.26858656,"throughput-bytes":2621440}],"summary":{"end":6.000032,"start":5.000812,"omitted":false,"retransmits":0,"throughput-bits":20987890.26858656,"throughput-bytes":2621440}},{"streams":[{"end":7.000105,"rtt":139575,"start":6.000032,"omitted":false,"stream-id":5,"retransmits":0,"tcp-window-size":388064,"throughput-bits":20969990.111614667,"throughput-bytes":2621440}],"summary":{"end":7.000105,"start":6.000032,"omitted":false,"retransmits":0,"throughput-bits":20969990.111614667,"throughput-bytes":2621440}},{"streams":[{"end":8.000106,"rtt":77232,"start":7.000105,"omitted":false,"stream-id":5,"retransmits":7,"tcp-window-size":211408,"throughput-bits":20971500.000019073,"throughput-bytes":2621440}],"summary":{"end":8.000106,"start":7.000105,"omitted":false,"retransmits":7,"throughput-bits":20971500.000019073,"throughput-bytes":2621440}},{"streams":[{"end":9.0001,"rtt":83315,"start":8.000106,"omitted":false,"stream-id":5,"retransmits":0,"tcp-window-size":228784,"throughput-bits":20971646.250760037,"throughput-bytes":2621440}],"summary":{"end":9.0001,"start":8.000106,"omitted":false,"retransmits":0,"throughput-bits":20971646.250760037,"throughput-bytes":2621440}},{"streams":[{"end":10.000038,"rtt":89654,"start":9.0001,"omitted":false,"stream-id":5,"retransmits":0,"tcp-window-size":246160,"throughput-bits":20972820.080590475,"throughput-bytes":2621440}],"summary":{"end":10.000038,"start":9.0001,"omitted":false,"retransmits":0,"throughput-bits":20972820.080590475,"throughput-bytes":2621440}}],"succeeded":true}
