{"diags":"Participant 0:\n/usr/bin/iperf3 -p 5201 -B 172.16.0.2 -c 172.16.0.1 -t 10 --json --rsa-public-key-path /var/run/pscheduler-server/runner/tmp/tmpoxuduw99/tmprl41e9i0/public-key --username eXpH0jCJIOXQQVMDYwca\n\n{\n    \"end\": {\n        \"cpu_utilization_percent\": {\n            \"host_system\": 0.18031548992962168, \n            \"host_total\": 0.3606605883140758, \n            \"host_user\": 0.18031548992962168, \n            \"remote_system\": 0.6920714210060913, \n            \"remote_total\": 0.7452849475475816, \n            \"remote_user\": 0.05323323160593812\n        }, \n        \"receiver_tcp_congestion\": \"htcp\", \n        \"sender_tcp_congestion\": \"htcp\", \n        \"streams\": [\n            {\n                \"receiver\": {\n                    \"bits_per_second\": 10974921.529406596, \n                    \"bytes\": 13923968, \n                    \"end\": 10.149662, \n                    \"seconds\": 10.000141, \n                    \"sender\": true, \n                    \"socket\": 5, \n                    \"start\": 0\n                }, \n                \"sender\": {\n                    \"bits_per_second\": 13945864.1633153, \n                    \"bytes\": 17432576, \n                    \"end\": 10.000141, \n                    \"max_rtt\": 273632, \n                    \"max_snd_cwnd\": 399648, \n                    \"max_snd_wnd\": 0, \n                    \"mean_rtt\": 199093, \n                    \"min_rtt\": 118296, \n                    \"retransmits\": 296, \n                    \"seconds\": 10.000141, \n                    \"sender\": true, \n                    \"socket\": 5, \n                    \"start\": 0\n                }\n            }\n        ], \n        \"sum_received\": {\n            \"bits_per_second\": 10974921.529406596, \n            \"bytes\": 13923968, \n            \"end\": 10.149662, \n            \"seconds\": 10.149662, \n            \"sender\": true, \n            \"start\": 0\n        }, \n        \"sum_sent\": {\n            \"bits_per_second\": 13945864.1633153, \n            \"bytes\": 17432576, \n            \"end\": 10.000141, \n            \"retransmits\": 296, \n            \"seconds\": 10.000141, \n            \"sender\": true, \n            \"start\": 0\n        }\n    }, \n    \"intervals\": [\n        {\n            \"streams\": [\n                {\n                    \"bits_per_second\": 34597299.94174774, \n                    \"bytes\": 4325376, \n                    \"end\": 1.000165, \n                    \"omitted\": false, \n                    \"pmtu\": 1500, \n                    \"retransmits\": 280, \n                    \"rtt\": 273632, \n                    \"rttvar\": 542, \n                    \"seconds\": 1.0001649856567383, \n                    \"sender\": true, \n                    \"snd_cwnd\": 266432, \n                    \"snd_wnd\": -1, \n                    \"socket\": 5, \n                    \"start\": 0\n                }\n            ], \n            \"sum\": {\n                \"bits_per_second\": 34597299.94174774, \n                \"bytes\": 4325376, \n                \"end\": 1.000165, \n                \"omitted\": false, \n                \"retransmits\": 280, \n                \"seconds\": 1.0001649856567383, \n                \"sender\": true, \n                \"start\": 0\n            }\n        }, \n        {\n            \"streams\": [\n                {\n                    \"bits_per_second\": 20971603.750334457, \n                    \"bytes\": 2621440, \n                    \"end\": 2.000161, \n                    \"omitted\": false, \n                    \"pmtu\": 1500, \n                    \"retransmits\": 4, \n                    \"rtt\": 177623, \n                    \"rttvar\": 354, \n                    \"seconds\": 0.9999960064888, \n                    \"sender\": true, \n                    \"snd_cwnd\": 202720, \n                    \"snd_wnd\": -1, \n                    \"socket\": 5, \n                    \"start\": 1.000165\n                }\n            ], \n            \"sum\": {\n                \"bits_per_second\": 20971603.750334457, \n                \"bytes\": 2621440, \n                \"end\": 2.000161, \n                \"omitted\": false, \n                \"retransmits\": 4, \n                \"seconds\": 0.9999960064888, \n                \"sender\": true, \n                \"start\": 1.000165\n            }\n        }, \n        {\n            \"streams\": [\n                {\n                    \"bits_per_second\": 10485613.752039792, \n                    \"bytes\": 1310720, \n                    \"end\": 3.000175, \n                    \"omitted\": false, \n                    \"pmtu\": 1500, \n                    \"retransmits\": 0, \n                    \"rtt\": 118296, \n                    \"rttvar\": 2533, \n                    \"seconds\": 1.0000139474868774, \n                    \"sender\": true, \n                    \"snd_cwnd\": 212856, \n                    \"snd_wnd\": -1, \n                    \"socket\": 5, \n                    \"start\": 2.000161\n                }\n            ], \n            \"sum\": {\n                \"bits_per_second\": 10485613.752039792, \n                \"bytes\": 1310720, \n                \"end\": 3.000175, \n                \"omitted\": false, \n                \"retransmits\": 0, \n                \"seconds\": 1.0000139474868774, \n                \"sender\": true, \n                \"start\": 2.000161\n            }\n        }, \n        {\n            \"streams\": [\n                {\n                    \"bits_per_second\": 10486725.08881671, \n                    \"bytes\": 1310720, \n                    \"end\": 4.000083, \n                    \"omitted\": false, \n                    \"pmtu\": 1500, \n                    \"retransmits\": 0, \n                    \"rtt\": 215855, \n                    \"rttvar\": 681, \n                    \"seconds\": 0.9999079704284668, \n                    \"sender\": true, \n                    \"snd_cwnd\": 222992, \n                    \"snd_wnd\": -1, \n                    \"socket\": 5, \n                    \"start\": 3.000175\n                }\n            ], \n            \"sum\": {\n                \"bits_per_second\": 10486725.08881671, \n                \"bytes\": 1310720, \n                \"end\": 4.000083, \n                \"omitted\": false, \n                \"retransmits\": 0, \n                \"seconds\": 0.9999079704284668, \n                \"sender\": true, \n                \"start\": 3.000175\n            }\n        }, \n        {\n            \"streams\": [\n                {\n                    \"bits_per_second\": 10485655.001051415, \n                    \"bytes\": 1310720, \n                    \"end\": 5.000093, \n                    \"omitted\": false, \n                    \"pmtu\": 1500, \n                    \"retransmits\": 0, \n                    \"rtt\": 181054, \n                    \"rttvar\": 1245, \n                    \"seconds\": 1.0000100135803223, \n                    \"sender\": true, \n                    \"snd_cwnd\": 253400, \n                    \"snd_wnd\": -1, \n                    \"socket\": 5, \n                    \"start\": 4.000083\n                }\n            ], \n            \"sum\": {\n                \"bits_per_second\": 10485655.001051415, \n                \"bytes\": 1310720, \n                \"end\": 5.000093, \n                \"omitted\": false, \n                \"retransmits\": 0, \n                \"seconds\": 1.0000100135803223, \n                \"sender\": true, \n                \"start\": 4.000083\n            }\n        }, \n        {\n            \"streams\": [\n                {\n                    \"bits_per_second\": 0, \n                    \"bytes\": 0, \n                    \"end\": 6.00091, \n                    \"omitted\": false, \n                    \"pmtu\": 1500, \n                    \"retransmits\": 0, \n                    \"rtt\": 230285, \n                    \"rttvar\": 2750, \n                    \"seconds\": 1.0008169412612915, \n                    \"sender\": true, \n                    \"snd_cwnd\": 289600, \n                    \"snd_wnd\": -1, \n                    \"socket\": 5, \n                    \"start\": 5.000093\n                }\n            ], \n            \"sum\": {\n                \"bits_per_second\": 0, \n                \"bytes\": 0, \n                \"end\": 6.00091, \n                \"omitted\": false, \n                \"retransmits\": 0, \n                \"seconds\": 1.0008169412612915, \n                \"sender\": true, \n                \"start\": 5.000093\n            }\n        }, \n        {\n            \"streams\": [\n                {\n                    \"bits_per_second\": 20988961.99443617, \n                    \"bytes\": 2621440, \n                    \"end\": 7.000079, \n                    \"omitted\": false, \n                    \"pmtu\": 1500, \n                    \"retransmits\": 0, \n                    \"rtt\": 221057, \n                    \"rttvar\": 1257, \n                    \"seconds\": 0.9991689920425415, \n                    \"sender\": true, \n                    \"snd_cwnd\": 340280, \n                    \"snd_wnd\": -1, \n                    \"socket\": 5, \n                    \"start\": 6.00091\n                }\n            ], \n            \"sum\": {\n                \"bits_per_second\": 20988961.99443617, \n                \"bytes\": 2621440, \n                \"end\": 7.000079, \n                \"omitted\": false, \n                \"retransmits\": 0, \n                \"seconds\": 0.9991689920425415, \n                \"sender\": true, \n                \"start\": 6.00091\n            }\n        }, \n        {\n            \"streams\": [\n                {\n                    \"bits_per_second\": 10484250.217415972, \n                    \"bytes\": 1310720, \n                    \"end\": 8.000223, \n                    \"omitted\": false, \n                    \"pmtu\": 1500, \n                    \"retransmits\": 0, \n                    \"rtt\": 223123, \n                    \"rttvar\": 1264, \n                    \"seconds\": 1.0001440048217773, \n                    \"sender\": true, \n                    \"snd_cwnd\": 399648, \n                    \"snd_wnd\": -1, \n                    \"socket\": 5, \n                    \"start\": 7.000079\n                }\n            ], \n            \"sum\": {\n                \"bits_per_second\": 10484250.217415972, \n                \"bytes\": 1310720, \n                \"end\": 8.000223, \n                \"omitted\": false, \n                \"retransmits\": 0, \n                \"seconds\": 1.0001440048217773, \n                \"sender\": true, \n                \"start\": 7.000079\n            }\n        }, \n        {\n            \"streams\": [\n                {\n                    \"bits_per_second\": 10485927.502675695, \n                    \"bytes\": 1310720, \n                    \"end\": 9.000207, \n                    \"omitted\": false, \n                    \"pmtu\": 1500, \n                    \"retransmits\": 12, \n                    \"rtt\": 169580, \n                    \"rttvar\": 2220, \n                    \"seconds\": 0.9999840259552002, \n                    \"sender\": true, \n                    \"snd_cwnd\": 211408, \n                    \"snd_wnd\": -1, \n                    \"socket\": 5, \n                    \"start\": 8.000223\n                }\n            ], \n            \"sum\": {\n                \"bits_per_second\": 10485927.502675695, \n                \"bytes\": 1310720, \n                \"end\": 9.000207, \n                \"omitted\": false, \n                \"retransmits\": 12, \n                \"seconds\": 0.9999840259552002, \n                \"sender\": true, \n                \"start\": 8.000223\n            }\n        }, \n        {\n            \"streams\": [\n                {\n                    \"bits_per_second\": 10486451.920654545, \n                    \"bytes\": 1310720, \n                    \"end\": 10.000141, \n                    \"omitted\": false, \n                    \"pmtu\": 1500, \n                    \"retransmits\": 0, \n                    \"rtt\": 180432, \n                    \"rttvar\": 2531, \n                    \"seconds\": 0.9999340176582336, \n                    \"sender\": true, \n                    \"snd_cwnd\": 220096, \n                    \"snd_wnd\": -1, \n                    \"socket\": 5, \n                    \"start\": 9.000207\n                }\n            ], \n            \"sum\": {\n                \"bits_per_second\": 10486451.920654545, \n                \"bytes\": 1310720, \n                \"end\": 10.000141, \n                \"omitted\": false, \n                \"retransmits\": 0, \n                \"seconds\": 0.9999340176582336, \n                \"sender\": true, \n                \"start\": 9.000207\n            }\n        }\n    ], \n    \"start\": {\n        \"connected\": [\n            {\n                \"local_host\": \"172.16.0.2\", \n                \"local_port\": 37151, \n                \"remote_host\": \"172.16.0.1\", \n                \"remote_port\": 5201, \n                \"socket\": 5\n            }\n        ], \n        \"connecting_to\": {\n            \"host\": \"172.16.0.1\", \n            \"port\": 5201\n        }, \n        \"cookie\": \"5nbyesefh6naz2hriwjlwidicgpbx3okxewg\", \n        \"fq_rate\": 0, \n        \"rcvbuf_actual\": 87380, \n        \"sndbuf_actual\": 65536, \n        \"sock_bufsize\": 0, \n        \"system_info\": \"REDACTED\", \n        \"target_bitrate\": 0, \n        \"tcp_mss_default\": 1448, \n        \"test_start\": {\n            \"bidir\": 0, \n            \"blksize\": 131072, \n            \"blocks\": 0, \n            \"bytes\": 0, \n            \"duration\": 10, \n            \"fqrate\": 0, \n            \"num_streams\": 1, \n            \"omit\": 0, \n            \"protocol\": \"TCP\", \n            \"reverse\": 0, \n            \"target_bitrate\": 0, \n            \"tos\": 0\n        }, \n        \"timestamp\": {\n            \"time\": \"Sat, 12 Oct 2024 02:36:18 GMT\", \n            \"timesecs\": 1728700578\n        }, \n        \"version\": \"iperf 3.14\"\n    }\n}\nParticipant 1:\n/usr/bin/iperf3 -s -1 --idle-timeout 10 --json -p 5201 -B 172.16.0.1 --authorized-users-path /var/run/pscheduler-server/runner/tmp/tmp81e09kfl/tmpiyipni40/credentials --rsa-private-key-path /var/run/pscheduler-server/runner/tmp/tmp81e09kfl/tmpiyipni40/private-key\n\n{\n    \"end\": {\n        \"cpu_utilization_percent\": {\n            \"host_system\": 0.6920714210060913, \n            \"host_total\": 0.7452849475475816, \n            \"host_user\": 0.05323323160593812, \n            \"remote_system\": 0, \n            \"remote_total\": 0, \n            \"remote_user\": 0\n        }, \n        \"receiver_tcp_congestion\": \"htcp\", \n        \"streams\": [\n            {\n                \"receiver\": {\n                    \"bits_per_second\": 10974921.529406596, \n                    \"bytes\": 13923968, \n                    \"end\": 10.149662, \n                    \"seconds\": 10.149662, \n                    \"sender\": false, \n                    \"socket\": 5, \n                    \"start\": 0\n                }, \n                \"sender\": {\n                    \"bits_per_second\": 0, \n                    \"bytes\": 0, \n                    \"end\": 10.149662, \n                    \"seconds\": 10.149662, \n                    \"sender\": false, \n                    \"socket\": 5, \n                    \"start\": 0\n                }\n            }\n        ], \n        \"sum_received\": {\n            \"bits_per_second\": 10974921.529406596, \n            \"bytes\": 13923968, \n            \"end\": 10.149662, \n            \"seconds\": 10.149662, \n            \"sender\": false, \n            \"start\": 0\n        }, \n        \"sum_sent\": {\n            \"bits_per_second\": 0, \n            \"bytes\": 0, \n            \"end\": 10.149662, \n            \"seconds\": 10.149662, \n            \"sender\": false, \n            \"start\": 0\n        }\n    }, \n    \"intervals\": [\n        {\n            \"streams\": [\n                {\n                    \"bits_per_second\": 6299082.085422116, \n                    \"bytes\": 787712, \n                    \"end\": 1.000415, \n                    \"omitted\": false, \n                    \"seconds\": 1.0004149675369263, \n                    \"sender\": false, \n                    \"socket\": 5, \n                    \"start\": 0\n                }\n            ], \n            \"sum\": {\n                \"bits_per_second\": 6299082.085422116, \n                \"bytes\": 787712, \n                \"end\": 1.000415, \n                \"omitted\": false, \n                \"seconds\": 1.0004149675369263, \n                \"sender\": false, \n                \"start\": 0\n            }\n        }, \n        {\n            \"streams\": [\n                {\n                    \"bits_per_second\": 16455154.032825386, \n                    \"bytes\": 2056160, \n                    \"end\": 2.000058, \n                    \"omitted\": false, \n                    \"seconds\": 0.9996430277824402, \n                    \"sender\": false, \n                    \"socket\": 5, \n                    \"start\": 1.000415\n                }\n            ], \n            \"sum\": {\n                \"bits_per_second\": 16455154.032825386, \n                \"bytes\": 2056160, \n                \"end\": 2.000058, \n                \"omitted\": false, \n                \"seconds\": 0.9996430277824402, \n                \"sender\": false, \n                \"start\": 1.000415\n            }\n        }, \n        {\n            \"streams\": [\n                {\n                    \"bits_per_second\": 10969752.460614193, \n                    \"bytes\": 1371256, \n                    \"end\": 3.000085, \n                    \"omitted\": false, \n                    \"seconds\": 1.0000269412994385, \n                    \"sender\": false, \n                    \"socket\": 5, \n                    \"start\": 2.000058\n                }\n            ], \n            \"sum\": {\n                \"bits_per_second\": 10969752.460614193, \n                \"bytes\": 1371256, \n                \"end\": 3.000085, \n                \"omitted\": false, \n                \"seconds\": 1.0000269412994385, \n                \"sender\": false, \n                \"start\": 2.000058\n            }\n        }, \n        {\n            \"streams\": [\n                {\n                    \"bits_per_second\": 8340638.587915274, \n                    \"bytes\": 1042560, \n                    \"end\": 4.000066, \n                    \"omitted\": false, \n                    \"seconds\": 0.9999809861183167, \n                    \"sender\": false, \n                    \"socket\": 5, \n                    \"start\": 3.000085\n                }\n            ], \n            \"sum\": {\n                \"bits_per_second\": 8340638.587915274, \n                \"bytes\": 1042560, \n                \"end\": 4.000066, \n                \"omitted\": false, \n                \"seconds\": 0.9999809861183167, \n                \"sender\": false, \n                \"start\": 3.000085\n            }\n        }, \n        {\n            \"streams\": [\n                {\n                    \"bits_per_second\": 10993205.516062245, \n                    \"bytes\": 1374152, \n                    \"end\": 5.000067, \n                    \"omitted\": false, \n                    \"seconds\": 1.0000009536743164, \n                    \"sender\": false, \n                    \"socket\": 5, \n                    \"start\": 4.000066\n                }\n            ], \n            \"sum\": {\n                \"bits_per_second\": 10993205.516062245, \n                \"bytes\": 1374152, \n                \"end\": 5.000067, \n                \"omitted\": false, \n                \"seconds\": 1.0000009536743164, \n                \"sender\": false, \n                \"start\": 4.000066\n            }\n        }, \n        {\n            \"streams\": [\n                {\n                    \"bits_per_second\": 9325623.60053671, \n                    \"bytes\": 1165640, \n                    \"end\": 6.000013, \n                    \"omitted\": false, \n                    \"seconds\": 0.9999459981918335, \n                    \"sender\": false, \n                    \"socket\": 5, \n                    \"start\": 5.000067\n                }\n            ], \n            \"sum\": {\n                \"bits_per_second\": 9325623.60053671, \n                \"bytes\": 1165640, \n                \"end\": 6.000013, \n                \"omitted\": false, \n                \"seconds\": 0.9999459981918335, \n                \"sender\": false, \n                \"start\": 5.000067\n            }\n        }, \n        {\n            \"streams\": [\n                {\n                    \"bits_per_second\": 11571872.48696901, \n                    \"bytes\": 1446552, \n                    \"end\": 7.00006, \n                    \"omitted\": false, \n                    \"seconds\": 1.000046968460083, \n                    \"sender\": false, \n                    \"socket\": 5, \n                    \"start\": 6.000013\n                }\n            ], \n            \"sum\": {\n                \"bits_per_second\": 11571872.48696901, \n                \"bytes\": 1446552, \n                \"end\": 7.00006, \n                \"omitted\": false, \n                \"seconds\": 1.000046968460083, \n                \"sender\": false, \n                \"start\": 6.000013\n            }\n        }, \n        {\n            \"streams\": [\n                {\n                    \"bits_per_second\": 12534289.193696082, \n                    \"bytes\": 1566736, \n                    \"end\": 8.000028, \n                    \"omitted\": false, \n                    \"seconds\": 0.9999679923057556, \n                    \"sender\": false, \n                    \"socket\": 5, \n                    \"start\": 7.00006\n                }\n            ], \n            \"sum\": {\n                \"bits_per_second\": 12534289.193696082, \n                \"bytes\": 1566736, \n                \"end\": 8.000028, \n                \"omitted\": false, \n                \"seconds\": 0.9999679923057556, \n                \"sender\": false, \n                \"start\": 7.00006\n            }\n        }, \n        {\n            \"streams\": [\n                {\n                    \"bits_per_second\": 12159357.353360204, \n                    \"bytes\": 1520400, \n                    \"end\": 9.000344, \n                    \"omitted\": false, \n                    \"seconds\": 1.0003160238265991, \n                    \"sender\": false, \n                    \"socket\": 5, \n                    \"start\": 8.000028\n                }\n            ], \n            \"sum\": {\n                \"bits_per_second\": 12159357.353360204, \n                \"bytes\": 1520400, \n                \"end\": 9.000344, \n                \"omitted\": false, \n                \"seconds\": 1.0003160238265991, \n                \"sender\": false, \n                \"start\": 8.000028\n            }\n        }, \n        {\n            \"streams\": [\n                {\n                    \"bits_per_second\": 11100402.383810872, \n                    \"bytes\": 1387184, \n                    \"end\": 10.00008, \n                    \"omitted\": false, \n                    \"seconds\": 0.9997360110282898, \n                    \"sender\": false, \n                    \"socket\": 5, \n                    \"start\": 9.000344\n                }\n            ], \n            \"sum\": {\n                \"bits_per_second\": 11100402.383810872, \n                \"bytes\": 1387184, \n                \"end\": 10.00008, \n                \"omitted\": false, \n                \"seconds\": 0.9997360110282898, \n                \"sender\": false, \n                \"start\": 9.000344\n            }\n        }, \n        {\n            \"streams\": [\n                {\n                    \"bits_per_second\": 10996831.273430761, \n                    \"bytes\": 205616, \n                    \"end\": 10.149662, \n                    \"omitted\": false, \n                    \"seconds\": 0.14958199858665466, \n                    \"sender\": false, \n                    \"socket\": 5, \n                    \"start\": 10.00008\n                }\n            ], \n            \"sum\": {\n                \"bits_per_second\": 10996831.273430761, \n                \"bytes\": 205616, \n                \"end\": 10.149662, \n                \"omitted\": false, \n                \"seconds\": 0.14958199858665466, \n                \"sender\": false, \n                \"start\": 10.00008\n            }\n        }\n    ], \n    \"start\": {\n        \"accepted_connection\": {\n            \"host\": \"172.16.0.2\", \n            \"port\": 34167\n        }, \n        \"connected\": [\n            {\n                \"local_host\": \"172.16.0.1\", \n                \"local_port\": 5201, \n                \"remote_host\": \"172.16.0.2\", \n                \"remote_port\": 37151, \n                \"socket\": 5\n            }\n        ], \n        \"cookie\": \"5nbyesefh6naz2hriwjlwidicgpbx3okxewg\", \n        \"fq_rate\": 0, \n        \"rcvbuf_actual\": 87380, \n        \"sndbuf_actual\": 65536, \n        \"sock_bufsize\": 0, \n        \"system_info\": \"REDACTED\", \n        \"target_bitrate\": 0, \n        \"tcp_mss_default\": 0, \n        \"test_start\": {\n            \"bidir\": 0, \n            \"blksize\": 131072, \n            \"blocks\": 0, \n            \"bytes\": 0, \n            \"duration\": 10, \n            \"fqrate\": 0, \n            \"num_streams\": 1, \n            \"omit\": 0, \n            \"protocol\": \"TCP\", \n            \"reverse\": 0, \n            \"target_bitrate\": 0, \n            \"tos\": 0\n        }, \n        \"timestamp\": {\n            \"time\": \"Sat, 12 Oct 2024 02:36:18 GMT\", \n            \"timesecs\": 1728700578\n        }, \n        \"version\": \"iperf 3.14\"\n    }\n}\n","summary":{"streams":[{"end":10.000141,"rtt":199093,"start":0,"stream-id":5,"retransmits":296,"throughput-bits":13945864.1633153,"throughput-bytes":17432576}],"summary":{"end":10.000141,"start":0,"retransmits":296,"throughput-bits":13945864.1633153,"throughput-bytes":17432576,"receiver-throughput-bits":10974921.529406596}},"intervals":[{"streams":[{"end":1.000165,"rtt":273632,"start":0,"omitted":false,"stream-id":5,"retransmits":280,"tcp-window-size":266432,"throughput-bits":34597299.94174774,"throughput-bytes":4325376}],"summary":{"end":1.000165,"start":0,"omitted":false,"retransmits":280,"throughput-bits":34597299.94174774,"throughput-bytes":4325376}},{"streams":[{"end":2.000161,"rtt":177623,"start":1.000165,"omitted":false,"stream-id":5,"retransmits":4,"tcp-window-size":202720,"throughput-bits":20971603.750334457,"throughput-bytes":2621440}],"summary":{"end":2.000161,"start":1.000165,"omitted":false,"retransmits":4,"throughput-bits":20971603.750334457,"throughput-bytes":2621440}},{"streams":[{"end":3.000175,"rtt":118296,"start":2.000161,"omitted":false,"stream-id":5,"retransmits":0,"tcp-window-size":212856,"throughput-bits":10485613.752039792,"throughput-bytes":1310720}],"summary":{"end":3.000175,"start":2.000161,"omitted":false,"retransmits":0,"throughput-bits":10485613.752039792,"throughput-bytes":1310720}},{"streams":[{"end":4.000083,"rtt":215855,"start":3.000175,"omitted":false,"stream-id":5,"retransmits":0,"tcp-window-size":222992,"throughput-bits":10486725.08881671,"throughput-bytes":1310720}],"summary":{"end":4.000083,"start":3.000175,"omitted":false,"retransmits":0,"throughput-bits":10486725.08881671,"throughput-bytes":1310720}},{"streams":[{"end":5.000093,"rtt":181054,"start":4.000083,"omitted":false,"stream-id":5,"retransmits":0,"tcp-window-size":253400,"throughput-bits":10485655.001051415,"throughput-bytes":1310720}],"summary":{"end":5.000093,"start":4.000083,"omitted":false,"retransmits":0,"throughput-bits":10485655.001051415,"throughput-bytes":1310720}},{"streams":[{"end":6.00091,"rtt":230285,"start":5.000093,"omitted":false,"stream-id":5,"retransmits":0,"tcp-window-size":289600,"throughput-bits":0,"throughput-bytes":0}],"summary":{"end":6.00091,"start":5.000093,"omitted":false,"retransmits":0,"throughput-bits":0,"throughput-bytes":0}},{"streams":[{"end":7.000079,"rtt":221057,"start":6.00091,"omitted":false,"stream-id":5,"retransmits":0,"tcp-window-size":340280,"throughput-bits":20988961.99443617,"throughput-bytes":2621440}],"summary":{"end":7.000079,"start":6.00091,"omitted":false,"retransmits":0,"throughput-bits":20988961.99443617,"throughput-bytes":2621440}},{"streams":[{"end":8.000223,"rtt":223123,"start":7.000079,"omitted":false,"stream-id":5,"retransmits":0,"tcp-window-size":399648,"throughput-bits":10484250.217415972,"throughput-bytes":1310720}],"summary":{"end":8.000223,"start":7.000079,"omitted":false,"retransmits":0,"throughput-bits":10484250.217415972,"throughput-bytes":1310720}},{"streams":[{"end":9.000207,"rtt":169580,"start":8.000223,"omitted":false,"stream-id":5,"retransmits":12,"tcp-window-size":211408,"throughput-bits":10485927.502675695,"throughput-bytes":1310720}],"summary":{"end":9.000207,"start":8.000223,"omitted":false,"retransmits":12,"throughput-bits":10485927.502675695,"throughput-bytes":1310720}},{"streams":[{"end":10.000141,"rtt":180432,"start":9.000207,"omitted":false,"stream-id":5,"retransmits":0,"tcp-window-size":220096,"throughput-bits":10486451.920654545,"throughput-bytes":1310720}],"summary":{"end":10.000141,"start":9.000207,"omitted":false,"retransmits":0,"throughput-bits":10486451.920654545,"throughput-bytes":1310720}}],"succeeded":true}
