{"diags":"Participant 0:\n/usr/bin/iperf3 -p 5201 -B 172.16.0.2 -c 172.16.0.1 -t 60 --json --rsa-public-key-path /var/run/pscheduler-server/runner/tmp/tmpalyq53ck/tmpyzsqddhc/public-key --username vRSNl0MwXw4bvXiXEKpB\n\n{\n    \"end\": {\n        \"cpu_utilization_percent\": {\n            \"host_system\": 0.04137735943831145, \n            \"host_total\": 0.041375695625555084, \n            \"host_user\": 0, \n            \"remote_system\": 0.11636238818639824, \n            \"remote_total\": 0.13940985016370305, \n            \"remote_user\": 0.0230541192453514\n        }, \n        \"receiver_tcp_congestion\": \"htcp\", \n        \"sender_tcp_congestion\": \"htcp\", \n        \"streams\": [\n            {\n                \"receiver\": {\n                    \"bits_per_second\": 673353.97609769, \n                    \"bytes\": 5057280, \n                    \"end\": 60.084653, \n                    \"seconds\": 60.001024, \n                    \"sender\": true, \n                    \"socket\": 5, \n                    \"start\": 0\n                }, \n                \"sender\": {\n                    \"bits_per_second\": 1135937.9466590437, \n                    \"bytes\": 8519680, \n                    \"end\": 60.001024, \n                    \"max_rtt\": 2294262, \n                    \"max_snd_cwnd\": 402544, \n                    \"max_snd_wnd\": 0, \n                    \"mean_rtt\": 424775, \n                    \"min_rtt\": 17526, \n                    \"retransmits\": 1079, \n                    \"seconds\": 60.001024, \n                    \"sender\": true, \n                    \"socket\": 5, \n                    \"start\": 0\n                }\n            }\n        ], \n        \"sum_received\": {\n            \"bits_per_second\": 673353.97609769, \n            \"bytes\": 5057280, \n            \"end\": 60.084653, \n            \"seconds\": 60.084653, \n            \"sender\": true, \n            \"start\": 0\n        }, \n        \"sum_sent\": {\n            \"bits_per_second\": 1135937.9466590437, \n            \"bytes\": 8519680, \n            \"end\": 60.001024, \n            \"retransmits\": 1079, \n            \"seconds\": 60.001024, \n            \"sender\": true, \n            \"start\": 0\n        }\n    }, \n    \"intervals\": [\n        {\n            \"streams\": [\n                {\n                    \"bits_per_second\": 36674378.7486314, \n                    \"bytes\": 4587520, \n                    \"end\": 1.000703, \n                    \"omitted\": false, \n                    \"pmtu\": 1500, \n                    \"retransmits\": 138, \n                    \"rtt\": 323430, \n                    \"rttvar\": 111161, \n                    \"seconds\": 1.000702977180481, \n                    \"sender\": true, \n                    \"snd_cwnd\": 160728, \n                    \"snd_wnd\": -1, \n                    \"socket\": 5, \n                    \"start\": 0\n                }\n            ], \n            \"sum\": {\n                \"bits_per_second\": 36674378.7486314, \n                \"bytes\": 4587520, \n                \"end\": 1.000703, \n                \"omitted\": false, \n                \"retransmits\": 138, \n                \"seconds\": 1.000702977180481, \n                \"sender\": true, \n                \"start\": 0\n            }\n        }, \n        {\n            \"streams\": [\n                {\n                    \"bits_per_second\": 0, \n                    \"bytes\": 0, \n                    \"end\": 2.00079, \n                    \"omitted\": false, \n                    \"pmtu\": 1500, \n                    \"retransmits\": 259, \n                    \"rtt\": 123082, \n                    \"rttvar\": 3200, \n                    \"seconds\": 1.000087022781372, \n                    \"sender\": true, \n                    \"snd_cwnd\": 402544, \n                    \"snd_wnd\": -1, \n                    \"socket\": 5, \n                    \"start\": 1.000703\n                }\n            ], \n            \"sum\": {\n                \"bits_per_second\": 0, \n                \"bytes\": 0, \n                \"end\": 2.00079, \n                \"omitted\": false, \n                \"retransmits\": 259, \n                \"seconds\": 1.000087022781372, \n                \"sender\": true, \n                \"start\": 1.000703\n            }\n        }, \n        {\n            \"streams\": [\n                {\n                    \"bits_per_second\": 0, \n                    \"bytes\": 0, \n                    \"end\": 3.001015, \n                    \"omitted\": false, \n                    \"pmtu\": 1500, \n                    \"retransmits\": 1, \n                    \"rtt\": 123082, \n                    \"rttvar\": 3200, \n                    \"seconds\": 1.0002249479293823, \n                    \"sender\": true, \n                    \"snd_cwnd\": 1448, \n                    \"snd_wnd\": -1, \n                    \"socket\": 5, \n                    \"start\": 2.00079\n                }\n            ], \n            \"sum\": {\n                \"bits_per_second\": 0, \n                \"bytes\": 0, \n                \"end\": 3.001015, \n                \"omitted\": false, \n                \"retransmits\": 1, \n                \"seconds\": 1.0002249479293823, \n                \"sender\": true, \n                \"start\": 2.00079\n            }\n        }, \n        {\n            \"streams\": [\n                {\n                    \"bits_per_second\": 0, \n                    \"bytes\": 0, \n                    \"end\": 4.001015, \n                    \"omitted\": false, \n                    \"pmtu\": 1500, \n                    \"retransmits\": 0, \n                    \"rtt\": 123082, \n                    \"rttvar\": 3200, \n                    \"seconds\": 1, \n                    \"sender\": true, \n                    \"snd_cwnd\": 1448, \n                    \"snd_wnd\": -1, \n                    \"socket\": 5, \n                    \"start\": 3.001015\n                }\n            ], \n            \"sum\": {\n                \"bits_per_second\": 0, \n                \"bytes\": 0, \n                \"end\": 4.001015, \n                \"omitted\": false, \n                \"retransmits\": 0, \n                \"seconds\": 1, \n                \"sender\": true, \n                \"start\": 3.001015\n            }\n        }, \n        {\n            \"streams\": [\n                {\n                    \"bits_per_second\": 0, \n                    \"bytes\": 0, \n                    \"end\": 5.001017, \n                    \"omitted\": false, \n                    \"pmtu\": 1500, \n                    \"retransmits\": 1, \n                    \"rtt\": 123082, \n                    \"rttvar\": 3200, \n                    \"seconds\": 1.0000020265579224, \n                    \"sender\": true, \n                    \"snd_cwnd\": 1448, \n                    \"snd_wnd\": -1, \n                    \"socket\": 5, \n                    \"start\": 4.001015\n                }\n            ], \n            \"sum\": {\n                \"bits_per_second\": 0, \n                \"bytes\": 0, \n                \"end\": 5.001017, \n                \"omitted\": false, \n                \"retransmits\": 1, \n                \"seconds\": 1.0000020265579224, \n                \"sender\": true, \n                \"start\": 4.001015\n            }\n        }, \n        {\n            \"streams\": [\n                {\n                    \"bits_per_second\": 0, \n                    \"bytes\": 0, \n                    \"end\": 6.001015, \n                    \"omitted\": false, \n                    \"pmtu\": 1500, \n                    \"retransmits\": 0, \n                    \"rtt\": 123082, \n                    \"rttvar\": 3200, \n                    \"seconds\": 0.9999979734420776, \n                    \"sender\": true, \n                    \"snd_cwnd\": 1448, \n                    \"snd_wnd\": -1, \n                    \"socket\": 5, \n                    \"start\": 5.001017\n                }\n            ], \n            \"sum\": {\n                \"bits_per_second\": 0, \n                \"bytes\": 0, \n                \"end\": 6.001015, \n                \"omitted\": false, \n                \"retransmits\": 0, \n                \"seconds\": 0.9999979734420776, \n                \"sender\": true, \n                \"start\": 5.001017\n            }\n        }, \n        {\n            \"streams\": [\n                {\n                    \"bits_per_second\": 0, \n                    \"bytes\": 0, \n                    \"end\": 7.001018, \n                    \"omitted\": false, \n                    \"pmtu\": 1500, \n                    \"retransmits\": 0, \n                    \"rtt\": 123082, \n                    \"rttvar\": 3200, \n                    \"seconds\": 1.0000029802322388, \n                    \"sender\": true, \n                    \"snd_cwnd\": 1448, \n                    \"snd_wnd\": -1, \n                    \"socket\": 5, \n                    \"start\": 6.001015\n                }\n            ], \n            \"sum\": {\n                \"bits_per_second\": 0, \n                \"bytes\": 0, \n                \"end\": 7.001018, \n                \"omitted\": false, \n                \"retransmits\": 0, \n                \"seconds\": 1.0000029802322388, \n                \"sender\": true, \n                \"start\": 6.001015\n            }\n        }, \n        {\n            \"streams\": [\n                {\n                    \"bits_per_second\": 0, \n                    \"bytes\": 0, \n                    \"end\": 8.001017, \n                    \"omitted\": false, \n                    \"pmtu\": 1500, \n                    \"retransmits\": 0, \n                    \"rtt\": 123082, \n                    \"rttvar\": 3200, \n                    \"seconds\": 0.9999989867210388, \n                    \"sender\": true, \n                    \"snd_cwnd\": 1448, \n                    \"snd_wnd\": -1, \n                    \"socket\": 5, \n                    \"start\": 7.001018\n                }\n            ], \n            \"sum\": {\n                \"bits_per_second\": 0, \n                \"bytes\": 0, \n                \"end\": 8.001017, \n                \"omitted\": false, \n                \"retransmits\": 0, \n                \"seconds\": 0.9999989867210388, \n                \"sender\": true, \n                \"start\": 7.001018\n            }\n        }, \n        {\n            \"streams\": [\n                {\n                    \"bits_per_second\": 10495331.854633555, \n                    \"bytes\": 1310720, \n                    \"end\": 9.000105, \n                    \"omitted\": false, \n                    \"pmtu\": 1500, \n                    \"retransmits\": 278, \n                    \"rtt\": 66955, \n                    \"rttvar\": 1413, \n                    \"seconds\": 0.9990879893302917, \n                    \"sender\": true, \n                    \"snd_cwnd\": 379376, \n                    \"snd_wnd\": -1, \n                    \"socket\": 5, \n                    \"start\": 8.001017\n                }\n            ], \n            \"sum\": {\n                \"bits_per_second\": 10495331.854633555, \n                \"bytes\": 1310720, \n                \"end\": 9.000105, \n                \"omitted\": false, \n                \"retransmits\": 278, \n                \"seconds\": 0.9990879893302917, \n                \"sender\": true, \n                \"start\": 8.001017\n            }\n        }, \n        {\n            \"streams\": [\n                {\n                    \"bits_per_second\": 0, \n                    \"bytes\": 0, \n                    \"end\": 10.001019, \n                    \"omitted\": false, \n                    \"pmtu\": 1500, \n                    \"retransmits\": 4, \n                    \"rtt\": 145667, \n                    \"rttvar\": 660, \n                    \"seconds\": 1.0009139776229858, \n                    \"sender\": true, \n                    \"snd_cwnd\": 1448, \n                    \"snd_wnd\": -1, \n                    \"socket\": 5, \n                    \"start\": 9.000105\n                }\n            ], \n            \"sum\": {\n                \"bits_per_second\": 0, \n                \"bytes\": 0, \n                \"end\": 10.001019, \n                \"omitted\": false, \n                \"retransmits\": 4, \n                \"seconds\": 1.0009139776229858, \n                \"sender\": true, \n                \"start\": 9.000105\n            }\n        }, \n        {\n            \"streams\": [\n                {\n                    \"bits_per_second\": 0, \n                    \"bytes\": 0, \n                    \"end\": 11.001017, \n                    \"omitted\": false, \n                    \"pmtu\": 1500, \n                    \"retransmits\": 0, \n                    \"rtt\": 145667, \n                    \"rttvar\": 660, \n                    \"seconds\": 0.9999979734420776, \n                    \"sender\": true, \n                    \"snd_cwnd\": 1448, \n                    \"snd_wnd\": -1, \n                    \"socket\": 5, \n                    \"start\": 10.001019\n                }\n            ], \n            \"sum\": {\n                \"bits_per_second\": 0, \n                \"bytes\": 0, \n                \"end\": 11.001017, \n                \"omitted\": false, \n                \"retransmits\": 0, \n                \"seconds\": 0.9999979734420776, \n                \"sender\": true, \n                \"start\": 10.001019\n            }\n        }, \n        {\n            \"streams\": [\n                {\n                    \"bits_per_second\": 0, \n                    \"bytes\": 0, \n                    \"end\": 12.001024, \n                    \"omitted\": false, \n                    \"pmtu\": 1500, \n                    \"retransmits\": 0, \n                    \"rtt\": 2294262, \n                    \"rttvar\": 1384, \n                    \"seconds\": 1.0000070333480835, \n                    \"sender\": true, \n                    \"snd_cwnd\": 1448, \n                    \"snd_wnd\": -1, \n                    \"socket\": 5, \n                    \"start\": 11.001017\n                }\n            ], \n            \"sum\": {\n                \"bits_per_second\": 0, \n                \"bytes\": 0, \n                \"end\": 12.001024, \n                \"omitted\": false, \n                \"retransmits\": 0, \n                \"seconds\": 1.0000070333480835, \n                \"sender\": true, \n                \"start\": 11.001017\n            }\n        }, \n        {\n            \"streams\": [\n                {\n                    \"bits_per_second\": 0, \n                    \"bytes\": 0, \n                    \"end\": 13.001018, \n                    \"omitted\": false, \n                    \"pmtu\": 1500, \n                    \"retransmits\": 0, \n                    \"rtt\": 2294262, \n                    \"rttvar\": 1384, \n                    \"seconds\": 0.9999939799308777, \n                    \"sender\": true, \n                    \"snd_cwnd\": 1448, \n                    \"snd_wnd\": -1, \n                    \"socket\": 5, \n                    \"start\": 12.001024\n                }\n            ], \n            \"sum\": {\n                \"bits_per_second\": 0, \n                \"bytes\": 0, \n                \"end\": 13.001018, \n                \"omitted\": false, \n                \"retransmits\": 0, \n                \"seconds\": 0.9999939799308777, \n                \"sender\": true, \n                \"start\": 12.001024\n            }\n        }, \n        {\n            \"streams\": [\n                {\n                    \"bits_per_second\": 0, \n                    \"bytes\": 0, \n                    \"end\": 14.001017, \n                    \"omitted\": false, \n                    \"pmtu\": 1500, \n                    \"retransmits\": 0, \n                    \"rtt\": 2294262, \n                    \"rttvar\": 1384, \n                    \"seconds\": 0.9999989867210388, \n                    \"sender\": true, \n                    \"snd_cwnd\": 1448, \n                    \"snd_wnd\": -1, \n                    \"socket\": 5, \n                    \"start\": 13.001018\n                }\n            ], \n            \"sum\": {\n                \"bits_per_second\": 0, \n                \"bytes\": 0, \n                \"end\": 14.001017, \n                \"omitted\": false, \n                \"retransmits\": 0, \n                \"seconds\": 0.9999989867210388, \n                \"sender\": true, \n                \"start\": 13.001018\n            }\n        }, \n        {\n            \"streams\": [\n                {\n                    \"bits_per_second\": 0, \n                    \"bytes\": 0, \n                    \"end\": 15.001017, \n                    \"omitted\": false, \n                    \"pmtu\": 1500, \n                    \"retransmits\": 0, \n                    \"rtt\": 2294262, \n                    \"rttvar\": 1384, \n                    \"seconds\": 1, \n                    \"sender\": true, \n                    \"snd_cwnd\": 1448, \n                    \"snd_wnd\": -1, \n                    \"socket\": 5, \n                    \"start\": 14.001017\n                }\n            ], \n            \"sum\": {\n                \"bits_per_second\": 0, \n                \"bytes\": 0, \n                \"end\": 15.001017, \n                \"omitted\": false, \n                \"retransmits\": 0, \n                \"seconds\": 1, \n                \"sender\": true, \n                \"start\": 14.001017\n            }\n        }, \n        {\n            \"streams\": [\n                {\n                    \"bits_per_second\": 0, \n                    \"bytes\": 0, \n                    \"end\": 16.001016, \n                    \"omitted\": false, \n                    \"pmtu\": 1500, \n                    \"retransmits\": 0, \n                    \"rtt\": 2294262, \n                    \"rttvar\": 1384, \n                    \"seconds\": 0.9999989867210388, \n                    \"sender\": true, \n                    \"snd_cwnd\": 1448, \n                    \"snd_wnd\": -1, \n                    \"socket\": 5, \n                    \"start\": 15.001017\n                }\n            ], \n            \"sum\": {\n                \"bits_per_second\": 0, \n                \"bytes\": 0, \n                \"end\": 16.001016, \n                \"omitted\": false, \n                \"retransmits\": 0, \n                \"seconds\": 0.9999989867210388, \n                \"sender\": true, \n                \"start\": 15.001017\n            }\n        }, \n        {\n            \"streams\": [\n                {\n                    \"bits_per_second\": 0, \n                    \"bytes\": 0, \n                    \"end\": 17.001015, \n                    \"omitted\": false, \n                    \"pmtu\": 1500, \n                    \"retransmits\": 0, \n                    \"rtt\": 2294262, \n                    \"rttvar\": 1384, \n                    \"seconds\": 0.9999989867210388, \n                    \"sender\": true, \n                    \"snd_cwnd\": 1448, \n                    \"snd_wnd\": -1, \n                    \"socket\": 5, \n                    \"start\": 16.001016\n                }\n            ], \n            \"sum\": {\n                \"bits_per_second\": 0, \n                \"bytes\": 0, \n                \"end\": 17.001015, \n                \"omitted\": false, \n                \"retransmits\": 0, \n                \"seconds\": 0.9999989867210388, \n                \"sender\": true, \n                \"start\": 16.001016\n            }\n        }, \n        {\n            \"streams\": [\n                {\n                    \"bits_per_second\": 0, \n                    \"bytes\": 0, \n                    \"end\": 18.001016, \n                    \"omitted\": false, \n                    \"pmtu\": 1500, \n                    \"retransmits\": 0, \n                    \"rtt\": 2294262, \n                    \"rttvar\": 1384, \n                    \"seconds\": 1.0000009536743164, \n                    \"sender\": true, \n                    \"snd_cwnd\": 1448, \n                    \"snd_wnd\": -1, \n                    \"socket\": 5, \n                    \"start\": 17.001015\n                }\n            ], \n            \"sum\": {\n                \"bits_per_second\": 0, \n                \"bytes\": 0, \n                \"end\": 18.001016, \n                \"omitted\": false, \n                \"retransmits\": 0, \n                \"seconds\": 1.0000009536743164, \n                \"sender\": true, \n                \"start\": 17.001015\n            }\n        }, \n        {\n            \"streams\": [\n                {\n                    \"bits_per_second\": 0, \n                    \"bytes\": 0, \n                    \"end\": 19.001016, \n                    \"omitted\": false, \n                    \"pmtu\": 1500, \n                    \"retransmits\": 97, \n                    \"rtt\": 27779, \n                    \"rttvar\": 2060, \n                    \"seconds\": 1, \n                    \"sender\": true, \n                    \"snd_cwnd\": 143352, \n                    \"snd_wnd\": -1, \n                    \"socket\": 5, \n                    \"start\": 18.001016\n                }\n            ], \n            \"sum\": {\n                \"bits_per_second\": 0, \n                \"bytes\": 0, \n                \"end\": 19.001016, \n                \"omitted\": false, \n                \"retransmits\": 97, \n                \"seconds\": 1, \n                \"sender\": true, \n                \"start\": 18.001016\n            }\n        }, \n        {\n            \"streams\": [\n                {\n                    \"bits_per_second\": 0, \n                    \"bytes\": 0, \n                    \"end\": 20.001016, \n                    \"omitted\": false, \n                    \"pmtu\": 1500, \n                    \"retransmits\": 0, \n                    \"rtt\": 27779, \n                    \"rttvar\": 2060, \n                    \"seconds\": 1, \n                    \"sender\": true, \n                    \"snd_cwnd\": 143352, \n                    \"snd_wnd\": -1, \n                    \"socket\": 5, \n                    \"start\": 19.001016\n                }\n            ], \n            \"sum\": {\n                \"bits_per_second\": 0, \n                \"bytes\": 0, \n                \"end\": 20.001016, \n                \"omitted\": false, \n                \"retransmits\": 0, \n                \"seconds\": 1, \n                \"sender\": true, \n                \"start\": 19.001016\n            }\n        }, \n        {\n            \"streams\": [\n                {\n                    \"bits_per_second\": 0, \n                    \"bytes\": 0, \n                    \"end\": 21.001017, \n                    \"omitted\": false, \n                    \"pmtu\": 1500, \n                    \"retransmits\": 6, \n                    \"rtt\": 1060822, \n                    \"rttvar\": 1022504, \n                    \"seconds\": 1.0000009536743164, \n                    \"sender\": true, \n                    \"snd_cwnd\": 11584, \n                    \"snd_wnd\": -1, \n                    \"socket\": 5, \n                    \"start\": 20.001016\n                }\n            ], \n            \"sum\": {\n                \"bits_per_second\": 0, \n                \"bytes\": 0, \n                \"end\": 21.001017, \n                \"omitted\": false, \n                \"retransmits\": 6, \n                \"seconds\": 1.0000009536743164, \n                \"sender\": true, \n                \"start\": 20.001016\n            }\n        }, \n        {\n            \"streams\": [\n                {\n                    \"bits_per_second\": 0, \n                    \"bytes\": 0, \n                    \"end\": 22.001016, \n                    \"omitted\": false, \n                    \"pmtu\": 1500, \n                    \"retransmits\": 0, \n                    \"rtt\": 1060822, \n                    \"rttvar\": 1022504, \n                    \"seconds\": 0.9999989867210388, \n                    \"sender\": true, \n                    \"snd_cwnd\": 11584, \n                    \"snd_wnd\": -1, \n                    \"socket\": 5, \n                    \"start\": 21.001017\n                }\n            ], \n            \"sum\": {\n                \"bits_per_second\": 0, \n                \"bytes\": 0, \n                \"end\": 22.001016, \n                \"omitted\": false, \n                \"retransmits\": 0, \n                \"seconds\": 0.9999989867210388, \n                \"sender\": true, \n                \"start\": 21.001017\n            }\n        }, \n        {\n            \"streams\": [\n                {\n                    \"bits_per_second\": 0, \n                    \"bytes\": 0, \n                    \"end\": 23.001031, \n                    \"omitted\": false, \n                    \"pmtu\": 1500, \n                    \"retransmits\": 0, \n                    \"rtt\": 1060822, \n                    \"rttvar\": 1022504, \n                    \"seconds\": 1.0000150203704834, \n                    \"sender\": true, \n                    \"snd_cwnd\": 11584, \n                    \"snd_wnd\": -1, \n                    \"socket\": 5, \n                    \"start\": 22.001016\n                }\n            ], \n            \"sum\": {\n                \"bits_per_second\": 0, \n                \"bytes\": 0, \n                \"end\": 23.001031, \n                \"omitted\": false, \n                \"retransmits\": 0, \n                \"seconds\": 1.0000150203704834, \n                \"sender\": true, \n                \"start\": 22.001016\n            }\n        }, \n        {\n            \"streams\": [\n                {\n                    \"bits_per_second\": 0, \n                    \"bytes\": 0, \n                    \"end\": 24.001015, \n                    \"omitted\": false, \n                    \"pmtu\": 1500, \n                    \"retransmits\": 0, \n                    \"rtt\": 1060822, \n                    \"rttvar\": 1022504, \n                    \"seconds\": 0.9999840259552002, \n                    \"sender\": true, \n                    \"snd_cwnd\": 11584, \n                    \"snd_wnd\": -1, \n                    \"socket\": 5, \n                    \"start\": 23.001031\n                }\n            ], \n            \"sum\": {\n                \"bits_per_second\": 0, \n                \"bytes\": 0, \n                \"end\": 24.001015, \n                \"omitted\": false, \n                \"retransmits\": 0, \n                \"seconds\": 0.9999840259552002, \n                \"sender\": true, \n                \"start\": 23.001031\n            }\n        }, \n        {\n            \"streams\": [\n                {\n                    \"bits_per_second\": 0, \n                    \"bytes\": 0, \n                    \"end\": 25.001026, \n                    \"omitted\": false, \n                    \"pmtu\": 1500, \n                    \"retransmits\": 0, \n                    \"rtt\": 1060822, \n                    \"rttvar\": 1022504, \n                    \"seconds\": 1.0000109672546387, \n                    \"sender\": true, \n                    \"snd_cwnd\": 11584, \n                    \"snd_wnd\": -1, \n                    \"socket\": 5, \n                    \"start\": 24.001015\n                }\n            ], \n            \"sum\": {\n                \"bits_per_second\": 0, \n                \"bytes\": 0, \n                \"end\": 25.001026, \n                \"omitted\": false, \n                \"retransmits\": 0, \n                \"seconds\": 1.0000109672546387, \n                \"sender\": true, \n                \"start\": 24.001015\n            }\n        }, \n        {\n            \"streams\": [\n                {\n                    \"bits_per_second\": 0, \n                    \"bytes\": 0, \n                    \"end\": 26.001015, \n                    \"omitted\": false, \n                    \"pmtu\": 1500, \n                    \"retransmits\": 0, \n                    \"rtt\": 1060822, \n                    \"rttvar\": 1022504, \n                    \"seconds\": 0.9999889731407166, \n                    \"sender\": true, \n                    \"snd_cwnd\": 11584, \n                    \"snd_wnd\": -1, \n                    \"socket\": 5, \n                    \"start\": 25.001026\n                }\n            ], \n            \"sum\": {\n                \"bits_per_second\": 0, \n                \"bytes\": 0, \n                \"end\": 26.001015, \n                \"omitted\": false, \n                \"retransmits\": 0, \n                \"seconds\": 0.9999889731407166, \n                \"sender\": true, \n                \"start\": 25.001026\n            }\n        }, \n        {\n            \"streams\": [\n                {\n                    \"bits_per_second\": 10488570.75323263, \n                    \"bytes\": 1310720, \n                    \"end\": 27.000747, \n                    \"omitted\": false, \n                    \"pmtu\": 1500, \n                    \"retransmits\": 94, \n                    \"rtt\": 34187, \n                    \"rttvar\": 602, \n                    \"seconds\": 0.99973201751709, \n                    \"sender\": true, \n                    \"snd_cwnd\": 72400, \n                    \"snd_wnd\": -1, \n                    \"socket\": 5, \n                    \"start\": 26.001015\n                }\n            ], \n            \"sum\": {\n                \"bits_per_second\": 10488570.75323263, \n                \"bytes\": 1310720, \n                \"end\": 27.000747, \n                \"omitted\": false, \n                \"retransmits\": 94, \n                \"seconds\": 0.99973201751709, \n                \"sender\": true, \n                \"start\": 26.001015\n            }\n        }, \n        {\n            \"streams\": [\n                {\n                    \"bits_per_second\": 0, \n                    \"bytes\": 0, \n                    \"end\": 28.001018, \n                    \"omitted\": false, \n                    \"pmtu\": 1500, \n                    \"retransmits\": 0, \n                    \"rtt\": 34187, \n                    \"rttvar\": 602, \n                    \"seconds\": 1.000270962715149, \n                    \"sender\": true, \n                    \"snd_cwnd\": 72400, \n                    \"snd_wnd\": -1, \n                    \"socket\": 5, \n                    \"start\": 27.000747\n                }\n            ], \n            \"sum\": {\n                \"bits_per_second\": 0, \n                \"bytes\": 0, \n                \"end\": 28.001018, \n                \"omitted\": false, \n                \"retransmits\": 0, \n                \"seconds\": 1.000270962715149, \n                \"sender\": true, \n                \"start\": 27.000747\n            }\n        }, \n        {\n            \"streams\": [\n                {\n                    \"bits_per_second\": 0, \n                    \"bytes\": 0, \n                    \"end\": 29.001016, \n                    \"omitted\": false, \n                    \"pmtu\": 1500, \n                    \"retransmits\": 44, \n                    \"rtt\": 35815, \n                    \"rttvar\": 14415, \n                    \"seconds\": 0.9999979734420776, \n                    \"sender\": true, \n                    \"snd_cwnd\": 2896, \n                    \"snd_wnd\": -1, \n                    \"socket\": 5, \n                    \"start\": 28.001018\n                }\n            ], \n            \"sum\": {\n                \"bits_per_second\": 0, \n                \"bytes\": 0, \n                \"end\": 29.001016, \n                \"omitted\": false, \n                \"retransmits\": 44, \n                \"seconds\": 0.9999979734420776, \n                \"sender\": true, \n                \"start\": 28.001018\n            }\n        }, \n        {\n            \"streams\": [\n                {\n                    \"bits_per_second\": 10493903.194060532, \n                    \"bytes\": 1310720, \n                    \"end\": 30.00024, \n                    \"omitted\": false, \n                    \"pmtu\": 1500, \n                    \"retransmits\": 59, \n                    \"rtt\": 21359, \n                    \"rttvar\": 5183, \n                    \"seconds\": 0.9992240071296692, \n                    \"sender\": true, \n                    \"snd_cwnd\": 27512, \n                    \"snd_wnd\": -1, \n                    \"socket\": 5, \n                    \"start\": 29.001016\n                }\n            ], \n            \"sum\": {\n                \"bits_per_second\": 10493903.194060532, \n                \"bytes\": 1310720, \n                \"end\": 30.00024, \n                \"omitted\": false, \n                \"retransmits\": 59, \n                \"seconds\": 0.9992240071296692, \n                \"sender\": true, \n                \"start\": 29.001016\n            }\n        }, \n        {\n            \"streams\": [\n                {\n                    \"bits_per_second\": 0, \n                    \"bytes\": 0, \n                    \"end\": 31.001018, \n                    \"omitted\": false, \n                    \"pmtu\": 1500, \n                    \"retransmits\": 2, \n                    \"rtt\": 19754, \n                    \"rttvar\": 6943, \n                    \"seconds\": 1.0007779598236084, \n                    \"sender\": true, \n                    \"snd_cwnd\": 1448, \n                    \"snd_wnd\": -1, \n                    \"socket\": 5, \n                    \"start\": 30.00024\n                }\n            ], \n            \"sum\": {\n                \"bits_per_second\": 0, \n                \"bytes\": 0, \n                \"end\": 31.001018, \n                \"omitted\": false, \n                \"retransmits\": 2, \n                \"seconds\": 1.0007779598236084, \n                \"sender\": true, \n                \"start\": 30.00024\n            }\n        }, \n        {\n            \"streams\": [\n                {\n                    \"bits_per_second\": 0, \n                    \"bytes\": 0, \n                    \"end\": 32.001016, \n                    \"omitted\": false, \n                    \"pmtu\": 1500, \n                    \"retransmits\": 1, \n                    \"rtt\": 19754, \n                    \"rttvar\": 6943, \n                    \"seconds\": 0.9999979734420776, \n                    \"sender\": true, \n                    \"snd_cwnd\": 1448, \n                    \"snd_wnd\": -1, \n                    \"socket\": 5, \n                    \"start\": 31.001018\n                }\n            ], \n            \"sum\": {\n                \"bits_per_second\": 0, \n                \"bytes\": 0, \n                \"end\": 32.001016, \n                \"omitted\": false, \n                \"retransmits\": 1, \n                \"seconds\": 0.9999979734420776, \n                \"sender\": true, \n                \"start\": 31.001018\n            }\n        }, \n        {\n            \"streams\": [\n                {\n                    \"bits_per_second\": 0, \n                    \"bytes\": 0, \n                    \"end\": 33.001028, \n                    \"omitted\": false, \n                    \"pmtu\": 1500, \n                    \"retransmits\": 0, \n                    \"rtt\": 19754, \n                    \"rttvar\": 6943, \n                    \"seconds\": 1.0000120401382446, \n                    \"sender\": true, \n                    \"snd_cwnd\": 1448, \n                    \"snd_wnd\": -1, \n                    \"socket\": 5, \n                    \"start\": 32.001016\n                }\n            ], \n            \"sum\": {\n                \"bits_per_second\": 0, \n                \"bytes\": 0, \n                \"end\": 33.001028, \n                \"omitted\": false, \n                \"retransmits\": 0, \n                \"seconds\": 1.0000120401382446, \n                \"sender\": true, \n                \"start\": 32.001016\n            }\n        }, \n        {\n            \"streams\": [\n                {\n                    \"bits_per_second\": 0, \n                    \"bytes\": 0, \n                    \"end\": 34.001031, \n                    \"omitted\": false, \n                    \"pmtu\": 1500, \n                    \"retransmits\": 1, \n                    \"rtt\": 19754, \n                    \"rttvar\": 6943, \n                    \"seconds\": 1.0000029802322388, \n                    \"sender\": true, \n                    \"snd_cwnd\": 1448, \n                    \"snd_wnd\": -1, \n                    \"socket\": 5, \n                    \"start\": 33.001028\n                }\n            ], \n            \"sum\": {\n                \"bits_per_second\": 0, \n                \"bytes\": 0, \n                \"end\": 34.001031, \n                \"omitted\": false, \n                \"retransmits\": 1, \n                \"seconds\": 1.0000029802322388, \n                \"sender\": true, \n                \"start\": 33.001028\n            }\n        }, \n        {\n            \"streams\": [\n                {\n                    \"bits_per_second\": 0, \n                    \"bytes\": 0, \n                    \"end\": 35.001017, \n                    \"omitted\": false, \n                    \"pmtu\": 1500, \n                    \"retransmits\": 0, \n                    \"rtt\": 19754, \n                    \"rttvar\": 6943, \n                    \"seconds\": 0.9999859929084778, \n                    \"sender\": true, \n                    \"snd_cwnd\": 1448, \n                    \"snd_wnd\": -1, \n                    \"socket\": 5, \n                    \"start\": 34.001031\n                }\n            ], \n            \"sum\": {\n                \"bits_per_second\": 0, \n                \"bytes\": 0, \n                \"end\": 35.001017, \n                \"omitted\": false, \n                \"retransmits\": 0, \n                \"seconds\": 0.9999859929084778, \n                \"sender\": true, \n                \"start\": 34.001031\n            }\n        }, \n        {\n            \"streams\": [\n                {\n                    \"bits_per_second\": 0, \n                    \"bytes\": 0, \n                    \"end\": 36.001032, \n                    \"omitted\": false, \n                    \"pmtu\": 1500, \n                    \"retransmits\": 0, \n                    \"rtt\": 19754, \n                    \"rttvar\": 6943, \n                    \"seconds\": 1.0000150203704834, \n                    \"sender\": true, \n                    \"snd_cwnd\": 1448, \n                    \"snd_wnd\": -1, \n                    \"socket\": 5, \n                    \"start\": 35.001017\n                }\n            ], \n            \"sum\": {\n                \"bits_per_second\": 0, \n                \"bytes\": 0, \n                \"end\": 36.001032, \n                \"omitted\": false, \n                \"retransmits\": 0, \n                \"seconds\": 1.0000150203704834, \n                \"sender\": true, \n                \"start\": 35.001017\n            }\n        }, \n        {\n            \"streams\": [\n                {\n                    \"bits_per_second\": 0, \n                    \"bytes\": 0, \n                    \"end\": 37.001018, \n                    \"omitted\": false, \n                    \"pmtu\": 1500, \n                    \"retransmits\": 0, \n                    \"rtt\": 19754, \n                    \"rttvar\": 6943, \n                    \"seconds\": 0.9999859929084778, \n                    \"sender\": true, \n                    \"snd_cwnd\": 1448, \n                    \"snd_wnd\": -1, \n                    \"socket\": 5, \n                    \"start\": 36.001032\n                }\n            ], \n            \"sum\": {\n                \"bits_per_second\": 0, \n                \"bytes\": 0, \n                \"end\": 37.001018, \n                \"omitted\": false, \n                \"retransmits\": 0, \n                \"seconds\": 0.9999859929084778, \n                \"sender\": true, \n                \"start\": 36.001032\n            }\n        }, \n        {\n            \"streams\": [\n                {\n                    \"bits_per_second\": 0, \n                    \"bytes\": 0, \n                    \"end\": 38.001022, \n                    \"omitted\": false, \n                    \"pmtu\": 1500, \n                    \"retransmits\": 1, \n                    \"rtt\": 19754, \n                    \"rttvar\": 6943, \n                    \"seconds\": 1.0000040531158447, \n                    \"sender\": true, \n                    \"snd_cwnd\": 1448, \n                    \"snd_wnd\": -1, \n                    \"socket\": 5, \n                    \"start\": 37.001018\n                }\n            ], \n            \"sum\": {\n                \"bits_per_second\": 0, \n                \"bytes\": 0, \n                \"end\": 38.001022, \n                \"omitted\": false, \n                \"retransmits\": 1, \n                \"seconds\": 1.0000040531158447, \n                \"sender\": true, \n                \"start\": 37.001018\n            }\n        }, \n        {\n            \"streams\": [\n                {\n                    \"bits_per_second\": 0, \n                    \"bytes\": 0, \n                    \"end\": 39.001017, \n                    \"omitted\": false, \n                    \"pmtu\": 1500, \n                    \"retransmits\": 0, \n                    \"rtt\": 19754, \n                    \"rttvar\": 6943, \n                    \"seconds\": 0.999994993209839, \n                    \"sender\": true, \n                    \"snd_cwnd\": 1448, \n                    \"snd_wnd\": -1, \n                    \"socket\": 5, \n                    \"start\": 38.001022\n                }\n            ], \n            \"sum\": {\n                \"bits_per_second\": 0, \n                \"bytes\": 0, \n                \"end\": 39.001017, \n                \"omitted\": false, \n                \"retransmits\": 0, \n                \"seconds\": 0.999994993209839, \n                \"sender\": true, \n                \"start\": 38.001022\n            }\n        }, \n        {\n            \"streams\": [\n                {\n                    \"bits_per_second\": 0, \n                    \"bytes\": 0, \n                    \"end\": 40.001019, \n                    \"omitted\": false, \n                    \"pmtu\": 1500, \n                    \"retransmits\": 0, \n                    \"rtt\": 19754, \n                    \"rttvar\": 6943, \n                    \"seconds\": 1.0000020265579224, \n                    \"sender\": true, \n                    \"snd_cwnd\": 1448, \n                    \"snd_wnd\": -1, \n                    \"socket\": 5, \n                    \"start\": 39.001017\n                }\n            ], \n            \"sum\": {\n                \"bits_per_second\": 0, \n                \"bytes\": 0, \n                \"end\": 40.001019, \n                \"omitted\": false, \n                \"retransmits\": 0, \n                \"seconds\": 1.0000020265579224, \n                \"sender\": true, \n                \"start\": 39.001017\n            }\n        }, \n        {\n            \"streams\": [\n                {\n                    \"bits_per_second\": 0, \n                    \"bytes\": 0, \n                    \"end\": 41.00102, \n                    \"omitted\": false, \n                    \"pmtu\": 1500, \n                    \"retransmits\": 0, \n                    \"rtt\": 19754, \n                    \"rttvar\": 6943, \n                    \"seconds\": 1.0000009536743164, \n                    \"sender\": true, \n                    \"snd_cwnd\": 1448, \n                    \"snd_wnd\": -1, \n                    \"socket\": 5, \n                    \"start\": 40.001019\n                }\n            ], \n            \"sum\": {\n                \"bits_per_second\": 0, \n                \"bytes\": 0, \n                \"end\": 41.00102, \n                \"omitted\": false, \n                \"retransmits\": 0, \n                \"seconds\": 1.0000009536743164, \n                \"sender\": true, \n                \"start\": 40.001019\n            }\n        }, \n        {\n            \"streams\": [\n                {\n                    \"bits_per_second\": 0, \n                    \"bytes\": 0, \n                    \"end\": 42.001018, \n                    \"omitted\": false, \n                    \"pmtu\": 1500, \n                    \"retransmits\": 0, \n                    \"rtt\": 19754, \n                    \"rttvar\": 6943, \n                    \"seconds\": 0.9999979734420776, \n                    \"sender\": true, \n                    \"snd_cwnd\": 1448, \n                    \"snd_wnd\": -1, \n                    \"socket\": 5, \n                    \"start\": 41.00102\n                }\n            ], \n            \"sum\": {\n                \"bits_per_second\": 0, \n                \"bytes\": 0, \n                \"end\": 42.001018, \n                \"omitted\": false, \n                \"retransmits\": 0, \n                \"seconds\": 0.9999979734420776, \n                \"sender\": true, \n                \"start\": 41.00102\n            }\n        }, \n        {\n            \"streams\": [\n                {\n                    \"bits_per_second\": 0, \n                    \"bytes\": 0, \n                    \"end\": 43.001022, \n                    \"omitted\": false, \n                    \"pmtu\": 1500, \n                    \"retransmits\": 0, \n                    \"rtt\": 19754, \n                    \"rttvar\": 6943, \n                    \"seconds\": 1.0000040531158447, \n                    \"sender\": true, \n                    \"snd_cwnd\": 1448, \n                    \"snd_wnd\": -1, \n                    \"socket\": 5, \n                    \"start\": 42.001018\n                }\n            ], \n            \"sum\": {\n                \"bits_per_second\": 0, \n                \"bytes\": 0, \n                \"end\": 43.001022, \n                \"omitted\": false, \n                \"retransmits\": 0, \n                \"seconds\": 1.0000040531158447, \n                \"sender\": true, \n                \"start\": 42.001018\n            }\n        }, \n        {\n            \"streams\": [\n                {\n                    \"bits_per_second\": 0, \n                    \"bytes\": 0, \n                    \"end\": 44.001019, \n                    \"omitted\": false, \n                    \"pmtu\": 1500, \n                    \"retransmits\": 0, \n                    \"rtt\": 19754, \n                    \"rttvar\": 6943, \n                    \"seconds\": 0.9999970197677612, \n                    \"sender\": true, \n                    \"snd_cwnd\": 1448, \n                    \"snd_wnd\": -1, \n                    \"socket\": 5, \n                    \"start\": 43.001022\n                }\n            ], \n            \"sum\": {\n                \"bits_per_second\": 0, \n                \"bytes\": 0, \n                \"end\": 44.001019, \n                \"omitted\": false, \n                \"retransmits\": 0, \n                \"seconds\": 0.9999970197677612, \n                \"sender\": true, \n                \"start\": 43.001022\n            }\n        }, \n        {\n            \"streams\": [\n                {\n                    \"bits_per_second\": 0, \n                    \"bytes\": 0, \n                    \"end\": 45.001015, \n                    \"omitted\": false, \n                    \"pmtu\": 1500, \n                    \"retransmits\": 24, \n                    \"rtt\": 30347, \n                    \"rttvar\": 6235, \n                    \"seconds\": 0.9999960064888, \n                    \"sender\": true, \n                    \"snd_cwnd\": 17376, \n                    \"snd_wnd\": -1, \n                    \"socket\": 5, \n                    \"start\": 44.001019\n                }\n            ], \n            \"sum\": {\n                \"bits_per_second\": 0, \n                \"bytes\": 0, \n                \"end\": 45.001015, \n                \"omitted\": false, \n                \"retransmits\": 24, \n                \"seconds\": 0.9999960064888, \n                \"sender\": true, \n                \"start\": 44.001019\n            }\n        }, \n        {\n            \"streams\": [\n                {\n                    \"bits_per_second\": 0, \n                    \"bytes\": 0, \n                    \"end\": 46.001014, \n                    \"omitted\": false, \n                    \"pmtu\": 1500, \n                    \"retransmits\": 2, \n                    \"rtt\": 23433, \n                    \"rttvar\": 6052, \n                    \"seconds\": 0.9999989867210388, \n                    \"sender\": true, \n                    \"snd_cwnd\": 1448, \n                    \"snd_wnd\": -1, \n                    \"socket\": 5, \n                    \"start\": 45.001015\n                }\n            ], \n            \"sum\": {\n                \"bits_per_second\": 0, \n                \"bytes\": 0, \n                \"end\": 46.001014, \n                \"omitted\": false, \n                \"retransmits\": 2, \n                \"seconds\": 0.9999989867210388, \n                \"sender\": true, \n                \"start\": 45.001015\n            }\n        }, \n        {\n            \"streams\": [\n                {\n                    \"bits_per_second\": 0, \n                    \"bytes\": 0, \n                    \"end\": 47.001021, \n                    \"omitted\": false, \n                    \"pmtu\": 1500, \n                    \"retransmits\": 1, \n                    \"rtt\": 23433, \n                    \"rttvar\": 6052, \n                    \"seconds\": 1.0000070333480835, \n                    \"sender\": true, \n                    \"snd_cwnd\": 1448, \n                    \"snd_wnd\": -1, \n                    \"socket\": 5, \n                    \"start\": 46.001014\n                }\n            ], \n            \"sum\": {\n                \"bits_per_second\": 0, \n                \"bytes\": 0, \n                \"end\": 47.001021, \n                \"omitted\": false, \n                \"retransmits\": 1, \n                \"seconds\": 1.0000070333480835, \n                \"sender\": true, \n                \"start\": 46.001014\n            }\n        }, \n        {\n            \"streams\": [\n                {\n                    \"bits_per_second\": 0, \n                    \"bytes\": 0, \n                    \"end\": 48.001016, \n                    \"omitted\": false, \n                    \"pmtu\": 1500, \n                    \"retransmits\": 0, \n                    \"rtt\": 23433, \n                    \"rttvar\": 6052, \n                    \"seconds\": 0.999994993209839, \n                    \"sender\": true, \n                    \"snd_cwnd\": 1448, \n                    \"snd_wnd\": -1, \n                    \"socket\": 5, \n                    \"start\": 47.001021\n                }\n            ], \n            \"sum\": {\n                \"bits_per_second\": 0, \n                \"bytes\": 0, \n                \"end\": 48.001016, \n                \"omitted\": false, \n                \"retransmits\": 0, \n                \"seconds\": 0.999994993209839, \n                \"sender\": true, \n                \"start\": 47.001021\n            }\n        }, \n        {\n            \"streams\": [\n                {\n                    \"bits_per_second\": 0, \n                    \"bytes\": 0, \n                    \"end\": 49.001017, \n                    \"omitted\": false, \n                    \"pmtu\": 1500, \n                    \"retransmits\": 15, \n                    \"rtt\": 24462, \n                    \"rttvar\": 4596, \n                    \"seconds\": 1.0000009536743164, \n                    \"sender\": true, \n                    \"snd_cwnd\": 17376, \n                    \"snd_wnd\": -1, \n                    \"socket\": 5, \n                    \"start\": 48.001016\n                }\n            ], \n            \"sum\": {\n                \"bits_per_second\": 0, \n                \"bytes\": 0, \n                \"end\": 49.001017, \n                \"omitted\": false, \n                \"retransmits\": 15, \n                \"seconds\": 1.0000009536743164, \n                \"sender\": true, \n                \"start\": 48.001016\n            }\n        }, \n        {\n            \"streams\": [\n                {\n                    \"bits_per_second\": 0, \n                    \"bytes\": 0, \n                    \"end\": 50.001016, \n                    \"omitted\": false, \n                    \"pmtu\": 1500, \n                    \"retransmits\": 11, \n                    \"rtt\": 49840, \n                    \"rttvar\": 20830, \n                    \"seconds\": 0.9999989867210388, \n                    \"sender\": true, \n                    \"snd_cwnd\": 1448, \n                    \"snd_wnd\": -1, \n                    \"socket\": 5, \n                    \"start\": 49.001017\n                }\n            ], \n            \"sum\": {\n                \"bits_per_second\": 0, \n                \"bytes\": 0, \n                \"end\": 50.001016, \n                \"omitted\": false, \n                \"retransmits\": 11, \n                \"seconds\": 0.9999989867210388, \n                \"sender\": true, \n                \"start\": 49.001017\n            }\n        }, \n        {\n            \"streams\": [\n                {\n                    \"bits_per_second\": 0, \n                    \"bytes\": 0, \n                    \"end\": 51.001017, \n                    \"omitted\": false, \n                    \"pmtu\": 1500, \n                    \"retransmits\": 1, \n                    \"rtt\": 173746, \n                    \"rttvar\": 274674, \n                    \"seconds\": 1.0000009536743164, \n                    \"sender\": true, \n                    \"snd_cwnd\": 18824, \n                    \"snd_wnd\": -1, \n                    \"socket\": 5, \n                    \"start\": 50.001016\n                }\n            ], \n            \"sum\": {\n                \"bits_per_second\": 0, \n                \"bytes\": 0, \n                \"end\": 51.001017, \n                \"omitted\": false, \n                \"retransmits\": 1, \n                \"seconds\": 1.0000009536743164, \n                \"sender\": true, \n                \"start\": 50.001016\n            }\n        }, \n        {\n            \"streams\": [\n                {\n                    \"bits_per_second\": 0, \n                    \"bytes\": 0, \n                    \"end\": 52.001019, \n                    \"omitted\": false, \n                    \"pmtu\": 1500, \n                    \"retransmits\": 0, \n                    \"rtt\": 173746, \n                    \"rttvar\": 274674, \n                    \"seconds\": 1.0000020265579224, \n                    \"sender\": true, \n                    \"snd_cwnd\": 18824, \n                    \"snd_wnd\": -1, \n                    \"socket\": 5, \n                    \"start\": 51.001017\n                }\n            ], \n            \"sum\": {\n                \"bits_per_second\": 0, \n                \"bytes\": 0, \n                \"end\": 52.001019, \n                \"omitted\": false, \n                \"retransmits\": 0, \n                \"seconds\": 1.0000020265579224, \n                \"sender\": true, \n                \"start\": 51.001017\n            }\n        }, \n        {\n            \"streams\": [\n                {\n                    \"bits_per_second\": 0, \n                    \"bytes\": 0, \n                    \"end\": 53.001016, \n                    \"omitted\": false, \n                    \"pmtu\": 1500, \n                    \"retransmits\": 0, \n                    \"rtt\": 173746, \n                    \"rttvar\": 274674, \n                    \"seconds\": 0.9999970197677612, \n                    \"sender\": true, \n                    \"snd_cwnd\": 18824, \n                    \"snd_wnd\": -1, \n                    \"socket\": 5, \n                    \"start\": 52.001019\n                }\n            ], \n            \"sum\": {\n                \"bits_per_second\": 0, \n                \"bytes\": 0, \n                \"end\": 53.001016, \n                \"omitted\": false, \n                \"retransmits\": 0, \n                \"seconds\": 0.9999970197677612, \n                \"sender\": true, \n                \"start\": 52.001019\n            }\n        }, \n        {\n            \"streams\": [\n                {\n                    \"bits_per_second\": 0, \n                    \"bytes\": 0, \n                    \"end\": 54.001015, \n                    \"omitted\": false, \n                    \"pmtu\": 1500, \n                    \"retransmits\": 0, \n                    \"rtt\": 173746, \n                    \"rttvar\": 274674, \n                    \"seconds\": 0.9999989867210388, \n                    \"sender\": true, \n                    \"snd_cwnd\": 18824, \n                    \"snd_wnd\": -1, \n                    \"socket\": 5, \n                    \"start\": 53.001016\n                }\n            ], \n            \"sum\": {\n                \"bits_per_second\": 0, \n                \"bytes\": 0, \n                \"end\": 54.001015, \n                \"omitted\": false, \n                \"retransmits\": 0, \n                \"seconds\": 0.9999989867210388, \n                \"sender\": true, \n                \"start\": 53.001016\n            }\n        }, \n        {\n            \"streams\": [\n                {\n                    \"bits_per_second\": 0, \n                    \"bytes\": 0, \n                    \"end\": 55.000542, \n                    \"omitted\": false, \n                    \"pmtu\": 1500, \n                    \"retransmits\": 14, \n                    \"rtt\": 36543, \n                    \"rttvar\": 15537, \n                    \"seconds\": 0.9995269775390625, \n                    \"sender\": true, \n                    \"snd_cwnd\": 13032, \n                    \"snd_wnd\": -1, \n                    \"socket\": 5, \n                    \"start\": 54.001015\n                }\n            ], \n            \"sum\": {\n                \"bits_per_second\": 0, \n                \"bytes\": 0, \n                \"end\": 55.000542, \n                \"omitted\": false, \n                \"retransmits\": 14, \n                \"seconds\": 0.9995269775390625, \n                \"sender\": true, \n                \"start\": 54.001015\n            }\n        }, \n        {\n            \"streams\": [\n                {\n                    \"bits_per_second\": 0, \n                    \"bytes\": 0, \n                    \"end\": 56.001017, \n                    \"omitted\": false, \n                    \"pmtu\": 1500, \n                    \"retransmits\": 0, \n                    \"rtt\": 36543, \n                    \"rttvar\": 15537, \n                    \"seconds\": 1.00047504901886, \n                    \"sender\": true, \n                    \"snd_cwnd\": 13032, \n                    \"snd_wnd\": -1, \n                    \"socket\": 5, \n                    \"start\": 55.000542\n                }\n            ], \n            \"sum\": {\n                \"bits_per_second\": 0, \n                \"bytes\": 0, \n                \"end\": 56.001017, \n                \"omitted\": false, \n                \"retransmits\": 0, \n                \"seconds\": 1.00047504901886, \n                \"sender\": true, \n                \"start\": 55.000542\n            }\n        }, \n        {\n            \"streams\": [\n                {\n                    \"bits_per_second\": 0, \n                    \"bytes\": 0, \n                    \"end\": 57.001015, \n                    \"omitted\": false, \n                    \"pmtu\": 1500, \n                    \"retransmits\": 11, \n                    \"rtt\": 32044, \n                    \"rttvar\": 4383, \n                    \"seconds\": 0.9999979734420776, \n                    \"sender\": true, \n                    \"snd_cwnd\": 1448, \n                    \"snd_wnd\": -1, \n                    \"socket\": 5, \n                    \"start\": 56.001017\n                }\n            ], \n            \"sum\": {\n                \"bits_per_second\": 0, \n                \"bytes\": 0, \n                \"end\": 57.001015, \n                \"omitted\": false, \n                \"retransmits\": 11, \n                \"seconds\": 0.9999979734420776, \n                \"sender\": true, \n                \"start\": 56.001017\n            }\n        }, \n        {\n            \"streams\": [\n                {\n                    \"bits_per_second\": 0, \n                    \"bytes\": 0, \n                    \"end\": 58.001026, \n                    \"omitted\": false, \n                    \"pmtu\": 1500, \n                    \"retransmits\": 1, \n                    \"rtt\": 32044, \n                    \"rttvar\": 4383, \n                    \"seconds\": 1.0000109672546387, \n                    \"sender\": true, \n                    \"snd_cwnd\": 1448, \n                    \"snd_wnd\": -1, \n                    \"socket\": 5, \n                    \"start\": 57.001015\n                }\n            ], \n            \"sum\": {\n                \"bits_per_second\": 0, \n                \"bytes\": 0, \n                \"end\": 58.001026, \n                \"omitted\": false, \n                \"retransmits\": 1, \n                \"seconds\": 1.0000109672546387, \n                \"sender\": true, \n                \"start\": 57.001015\n            }\n        }, \n        {\n            \"streams\": [\n                {\n                    \"bits_per_second\": 0, \n                    \"bytes\": 0, \n                    \"end\": 59.001016, \n                    \"omitted\": false, \n                    \"pmtu\": 1500, \n                    \"retransmits\": 12, \n                    \"rtt\": 36175, \n                    \"rttvar\": 6926, \n                    \"seconds\": 0.9999899864196777, \n                    \"sender\": true, \n                    \"snd_cwnd\": 10136, \n                    \"snd_wnd\": -1, \n                    \"socket\": 5, \n                    \"start\": 58.001026\n                }\n            ], \n            \"sum\": {\n                \"bits_per_second\": 0, \n                \"bytes\": 0, \n                \"end\": 59.001016, \n                \"omitted\": false, \n                \"retransmits\": 12, \n                \"seconds\": 0.9999899864196777, \n                \"sender\": true, \n                \"start\": 58.001026\n            }\n        }, \n        {\n            \"streams\": [\n                {\n                    \"bits_per_second\": 0, \n                    \"bytes\": 0, \n                    \"end\": 60.001024, \n                    \"omitted\": false, \n                    \"pmtu\": 1500, \n                    \"retransmits\": 1, \n                    \"rtt\": 17526, \n                    \"rttvar\": 1036, \n                    \"seconds\": 1.0000079870224, \n                    \"sender\": true, \n                    \"snd_cwnd\": 1448, \n                    \"snd_wnd\": -1, \n                    \"socket\": 5, \n                    \"start\": 59.001016\n                }\n            ], \n            \"sum\": {\n                \"bits_per_second\": 0, \n                \"bytes\": 0, \n                \"end\": 60.001024, \n                \"omitted\": false, \n                \"retransmits\": 1, \n                \"seconds\": 1.0000079870224, \n                \"sender\": true, \n                \"start\": 59.001016\n            }\n        }\n    ], \n    \"start\": {\n        \"connected\": [\n            {\n                \"local_host\": \"172.16.0.2\", \n                \"local_port\": 56053, \n                \"remote_host\": \"172.16.0.1\", \n                \"remote_port\": 5201, \n                \"socket\": 5\n            }\n        ], \n        \"connecting_to\": {\n            \"host\": \"172.16.0.1\", \n            \"port\": 5201\n        }, \n        \"cookie\": \"6h4jyqh3hqienslj2uwtmn36bbda5iw3zn33\", \n        \"fq_rate\": 0, \n        \"rcvbuf_actual\": 87380, \n        \"sndbuf_actual\": 65536, \n        \"sock_bufsize\": 0, \n        \"system_info\": \"REDACTED\", \n        \"target_bitrate\": 0, \n        \"tcp_mss_default\": 1448, \n        \"test_start\": {\n            \"bidir\": 0, \n            \"blksize\": 131072, \n            \"blocks\": 0, \n            \"bytes\": 0, \n            \"duration\": 60, \n            \"fqrate\": 0, \n            \"num_streams\": 1, \n            \"omit\": 0, \n            \"protocol\": \"TCP\", \n            \"reverse\": 0, \n            \"target_bitrate\": 0, \n            \"tos\": 0\n        }, \n        \"timestamp\": {\n            \"time\": \"Wed, 16 Oct 2024 02:49:09 GMT\", \n            \"timesecs\": 1729046949\n        }, \n        \"version\": \"iperf 3.14\"\n    }\n}\nParticipant 1:\n/usr/bin/iperf3 --use-pkcs1-padding -s -1 --idle-timeout 60 --json -p 5201 -B 172.16.0.1 --authorized-users-path /var/pscheduler-server/runner/tmp/tmpnota5ag1/tmpikh3wpnp/credentials --rsa-private-key-path /var/pscheduler-server/runner/tmp/tmpnota5ag1/tmpikh3wpnp/private-key\n\n{\n    \"end\": {\n        \"cpu_utilization_percent\": {\n            \"host_system\": 0.11636238818639824, \n            \"host_total\": 0.13940985016370305, \n            \"host_user\": 0.0230541192453514, \n            \"remote_system\": 0, \n            \"remote_total\": 0, \n            \"remote_user\": 0\n        }, \n        \"receiver_tcp_congestion\": \"htcp\", \n        \"streams\": [\n            {\n                \"receiver\": {\n                    \"bits_per_second\": 673353.97609769, \n                    \"bytes\": 5057280, \n                    \"end\": 60.084653, \n                    \"seconds\": 60.084653, \n                    \"sender\": false, \n                    \"socket\": 5, \n                    \"start\": 0\n                }, \n                \"sender\": {\n                    \"bits_per_second\": 0, \n                    \"bytes\": 0, \n                    \"end\": 60.084653, \n                    \"seconds\": 60.084653, \n                    \"sender\": false, \n                    \"socket\": 5, \n                    \"start\": 0\n                }\n            }\n        ], \n        \"sum_received\": {\n            \"bits_per_second\": 673353.97609769, \n            \"bytes\": 5057280, \n            \"end\": 60.084653, \n            \"seconds\": 60.084653, \n            \"sender\": false, \n            \"start\": 0\n        }, \n        \"sum_sent\": {\n            \"bits_per_second\": 0, \n            \"bytes\": 0, \n            \"end\": 60.084653, \n            \"seconds\": 60.084653, \n            \"sender\": false, \n            \"start\": 0\n        }\n    }, \n    \"intervals\": [\n        {\n            \"streams\": [\n                {\n                    \"bits_per_second\": 6290329.701666366, \n                    \"bytes\": 786432, \n                    \"end\": 1.000179, \n                    \"omitted\": false, \n                    \"seconds\": 1.0001790523529053, \n                    \"sender\": false, \n                    \"socket\": 5, \n                    \"start\": 0\n                }\n            ], \n            \"sum\": {\n                \"bits_per_second\": 6290329.701666366, \n                \"bytes\": 786432, \n                \"end\": 1.000179, \n                \"omitted\": false, \n                \"seconds\": 1.0001790523529053, \n                \"sender\": false, \n                \"start\": 0\n            }\n        }, \n        {\n            \"streams\": [\n                {\n                    \"bits_per_second\": 5237877.901931718, \n                    \"bytes\": 655360, \n                    \"end\": 2.001134, \n                    \"omitted\": false, \n                    \"seconds\": 1.0009549856185913, \n                    \"sender\": false, \n                    \"socket\": 5, \n                    \"start\": 1.000179\n                }\n            ], \n            \"sum\": {\n                \"bits_per_second\": 5237877.901931718, \n                \"bytes\": 655360, \n                \"end\": 2.001134, \n                \"omitted\": false, \n                \"seconds\": 1.0009549856185913, \n                \"sender\": false, \n                \"start\": 1.000179\n            }\n        }, \n        {\n            \"streams\": [\n                {\n                    \"bits_per_second\": 0, \n                    \"bytes\": 0, \n                    \"end\": 3.00116, \n                    \"omitted\": false, \n                    \"seconds\": 1.000025987625122, \n                    \"sender\": false, \n                    \"socket\": 5, \n                    \"start\": 2.001134\n                }\n            ], \n            \"sum\": {\n                \"bits_per_second\": 0, \n                \"bytes\": 0, \n                \"end\": 3.00116, \n                \"omitted\": false, \n                \"seconds\": 1.000025987625122, \n                \"sender\": false, \n                \"start\": 2.001134\n            }\n        }, \n        {\n            \"streams\": [\n                {\n                    \"bits_per_second\": 0, \n                    \"bytes\": 0, \n                    \"end\": 4.001184, \n                    \"omitted\": false, \n                    \"seconds\": 1.0000239610672, \n                    \"sender\": false, \n                    \"socket\": 5, \n                    \"start\": 3.00116\n                }\n            ], \n            \"sum\": {\n                \"bits_per_second\": 0, \n                \"bytes\": 0, \n                \"end\": 4.001184, \n                \"omitted\": false, \n                \"seconds\": 1.0000239610672, \n                \"sender\": false, \n                \"start\": 3.00116\n            }\n        }, \n        {\n            \"streams\": [\n                {\n                    \"bits_per_second\": 0, \n                    \"bytes\": 0, \n                    \"end\": 5.001173, \n                    \"omitted\": false, \n                    \"seconds\": 0.9999889731407166, \n                    \"sender\": false, \n                    \"socket\": 5, \n                    \"start\": 4.001184\n                }\n            ], \n            \"sum\": {\n                \"bits_per_second\": 0, \n                \"bytes\": 0, \n                \"end\": 5.001173, \n                \"omitted\": false, \n                \"seconds\": 0.9999889731407166, \n                \"sender\": false, \n                \"start\": 4.001184\n            }\n        }, \n        {\n            \"streams\": [\n                {\n                    \"bits_per_second\": 0, \n                    \"bytes\": 0, \n                    \"end\": 6.001068, \n                    \"omitted\": false, \n                    \"seconds\": 0.9998949766159058, \n                    \"sender\": false, \n                    \"socket\": 5, \n                    \"start\": 5.001173\n                }\n            ], \n            \"sum\": {\n                \"bits_per_second\": 0, \n                \"bytes\": 0, \n                \"end\": 6.001068, \n                \"omitted\": false, \n                \"seconds\": 0.9998949766159058, \n                \"sender\": false, \n                \"start\": 5.001173\n            }\n        }, \n        {\n            \"streams\": [\n                {\n                    \"bits_per_second\": 0, \n                    \"bytes\": 0, \n                    \"end\": 7.001172, \n                    \"omitted\": false, \n                    \"seconds\": 1.0001039505004883, \n                    \"sender\": false, \n                    \"socket\": 5, \n                    \"start\": 6.001068\n                }\n            ], \n            \"sum\": {\n                \"bits_per_second\": 0, \n                \"bytes\": 0, \n                \"end\": 7.001172, \n                \"omitted\": false, \n                \"seconds\": 1.0001039505004883, \n                \"sender\": false, \n                \"start\": 6.001068\n            }\n        }, \n        {\n            \"streams\": [\n                {\n                    \"bits_per_second\": 0, \n                    \"bytes\": 0, \n                    \"end\": 8.001133, \n                    \"omitted\": false, \n                    \"seconds\": 0.999961018562317, \n                    \"sender\": false, \n                    \"socket\": 5, \n                    \"start\": 7.001172\n                }\n            ], \n            \"sum\": {\n                \"bits_per_second\": 0, \n                \"bytes\": 0, \n                \"end\": 8.001133, \n                \"omitted\": false, \n                \"seconds\": 0.999961018562317, \n                \"sender\": false, \n                \"start\": 7.001172\n            }\n        }, \n        {\n            \"streams\": [\n                {\n                    \"bits_per_second\": 3145721.62501292, \n                    \"bytes\": 393216, \n                    \"end\": 9.001135, \n                    \"omitted\": false, \n                    \"seconds\": 1.0000020265579224, \n                    \"sender\": false, \n                    \"socket\": 5, \n                    \"start\": 8.001133\n                }\n            ], \n            \"sum\": {\n                \"bits_per_second\": 3145721.62501292, \n                \"bytes\": 393216, \n                \"end\": 9.001135, \n                \"omitted\": false, \n                \"seconds\": 1.0000020265579224, \n                \"sender\": false, \n                \"start\": 8.001133\n            }\n        }, \n        {\n            \"streams\": [\n                {\n                    \"bits_per_second\": 3145479.3946487126, \n                    \"bytes\": 393216, \n                    \"end\": 10.001214, \n                    \"omitted\": false, \n                    \"seconds\": 1.0000790357589722, \n                    \"sender\": false, \n                    \"socket\": 5, \n                    \"start\": 9.001135\n                }\n            ], \n            \"sum\": {\n                \"bits_per_second\": 3145479.3946487126, \n                \"bytes\": 393216, \n                \"end\": 10.001214, \n                \"omitted\": false, \n                \"seconds\": 1.0000790357589722, \n                \"sender\": false, \n                \"start\": 9.001135\n            }\n        }, \n        {\n            \"streams\": [\n                {\n                    \"bits_per_second\": 0, \n                    \"bytes\": 0, \n                    \"end\": 11.001139, \n                    \"omitted\": false, \n                    \"seconds\": 0.9999250173568726, \n                    \"sender\": false, \n                    \"socket\": 5, \n                    \"start\": 10.001214\n                }\n            ], \n            \"sum\": {\n                \"bits_per_second\": 0, \n                \"bytes\": 0, \n                \"end\": 11.001139, \n                \"omitted\": false, \n                \"seconds\": 0.9999250173568726, \n                \"sender\": false, \n                \"start\": 10.001214\n            }\n        }, \n        {\n            \"streams\": [\n                {\n                    \"bits_per_second\": 0, \n                    \"bytes\": 0, \n                    \"end\": 12.00116, \n                    \"omitted\": false, \n                    \"seconds\": 1.000020980834961, \n                    \"sender\": false, \n                    \"socket\": 5, \n                    \"start\": 11.001139\n                }\n            ], \n            \"sum\": {\n                \"bits_per_second\": 0, \n                \"bytes\": 0, \n                \"end\": 12.00116, \n                \"omitted\": false, \n                \"seconds\": 1.000020980834961, \n                \"sender\": false, \n                \"start\": 11.001139\n            }\n        }, \n        {\n            \"streams\": [\n                {\n                    \"bits_per_second\": 0, \n                    \"bytes\": 0, \n                    \"end\": 13.001112, \n                    \"omitted\": false, \n                    \"seconds\": 0.9999520182609558, \n                    \"sender\": false, \n                    \"socket\": 5, \n                    \"start\": 12.00116\n                }\n            ], \n            \"sum\": {\n                \"bits_per_second\": 0, \n                \"bytes\": 0, \n                \"end\": 13.001112, \n                \"omitted\": false, \n                \"seconds\": 0.9999520182609558, \n                \"sender\": false, \n                \"start\": 12.00116\n            }\n        }, \n        {\n            \"streams\": [\n                {\n                    \"bits_per_second\": 0, \n                    \"bytes\": 0, \n                    \"end\": 14.001078, \n                    \"omitted\": false, \n                    \"seconds\": 0.999966025352478, \n                    \"sender\": false, \n                    \"socket\": 5, \n                    \"start\": 13.001112\n                }\n            ], \n            \"sum\": {\n                \"bits_per_second\": 0, \n                \"bytes\": 0, \n                \"end\": 14.001078, \n                \"omitted\": false, \n                \"seconds\": 0.999966025352478, \n                \"sender\": false, \n                \"start\": 13.001112\n            }\n        }, \n        {\n            \"streams\": [\n                {\n                    \"bits_per_second\": 0, \n                    \"bytes\": 0, \n                    \"end\": 15.001084, \n                    \"omitted\": false, \n                    \"seconds\": 1.0000059604644775, \n                    \"sender\": false, \n                    \"socket\": 5, \n                    \"start\": 14.001078\n                }\n            ], \n            \"sum\": {\n                \"bits_per_second\": 0, \n                \"bytes\": 0, \n                \"end\": 15.001084, \n                \"omitted\": false, \n                \"seconds\": 1.0000059604644775, \n                \"sender\": false, \n                \"start\": 14.001078\n            }\n        }, \n        {\n            \"streams\": [\n                {\n                    \"bits_per_second\": 0, \n                    \"bytes\": 0, \n                    \"end\": 16.001157, \n                    \"omitted\": false, \n                    \"seconds\": 1.000072956085205, \n                    \"sender\": false, \n                    \"socket\": 5, \n                    \"start\": 15.001084\n                }\n            ], \n            \"sum\": {\n                \"bits_per_second\": 0, \n                \"bytes\": 0, \n                \"end\": 16.001157, \n                \"omitted\": false, \n                \"seconds\": 1.000072956085205, \n                \"sender\": false, \n                \"start\": 15.001084\n            }\n        }, \n        {\n            \"streams\": [\n                {\n                    \"bits_per_second\": 0, \n                    \"bytes\": 0, \n                    \"end\": 17.001087, \n                    \"omitted\": false, \n                    \"seconds\": 0.9999300241470337, \n                    \"sender\": false, \n                    \"socket\": 5, \n                    \"start\": 16.001157\n                }\n            ], \n            \"sum\": {\n                \"bits_per_second\": 0, \n                \"bytes\": 0, \n                \"end\": 17.001087, \n                \"omitted\": false, \n                \"seconds\": 0.9999300241470337, \n                \"sender\": false, \n                \"start\": 16.001157\n            }\n        }, \n        {\n            \"streams\": [\n                {\n                    \"bits_per_second\": 0, \n                    \"bytes\": 0, \n                    \"end\": 18.001136, \n                    \"omitted\": false, \n                    \"seconds\": 1.0000489950180054, \n                    \"sender\": false, \n                    \"socket\": 5, \n                    \"start\": 17.001087\n                }\n            ], \n            \"sum\": {\n                \"bits_per_second\": 0, \n                \"bytes\": 0, \n                \"end\": 18.001136, \n                \"omitted\": false, \n                \"seconds\": 1.0000489950180054, \n                \"sender\": false, \n                \"start\": 17.001087\n            }\n        }, \n        {\n            \"streams\": [\n                {\n                    \"bits_per_second\": 3145916.823833561, \n                    \"bytes\": 393216, \n                    \"end\": 19.001076, \n                    \"omitted\": false, \n                    \"seconds\": 0.9999399781227112, \n                    \"sender\": false, \n                    \"socket\": 5, \n                    \"start\": 18.001136\n                }\n            ], \n            \"sum\": {\n                \"bits_per_second\": 3145916.823833561, \n                \"bytes\": 393216, \n                \"end\": 19.001076, \n                \"omitted\": false, \n                \"seconds\": 0.9999399781227112, \n                \"sender\": false, \n                \"start\": 18.001136\n            }\n        }, \n        {\n            \"streams\": [\n                {\n                    \"bits_per_second\": 0, \n                    \"bytes\": 0, \n                    \"end\": 20.000087, \n                    \"omitted\": false, \n                    \"seconds\": 0.999010980129242, \n                    \"sender\": false, \n                    \"socket\": 5, \n                    \"start\": 19.001076\n                }\n            ], \n            \"sum\": {\n                \"bits_per_second\": 0, \n                \"bytes\": 0, \n                \"end\": 20.000087, \n                \"omitted\": false, \n                \"seconds\": 0.999010980129242, \n                \"sender\": false, \n                \"start\": 19.001076\n            }\n        }, \n        {\n            \"streams\": [\n                {\n                    \"bits_per_second\": 0, \n                    \"bytes\": 0, \n                    \"end\": 21.001119, \n                    \"omitted\": false, \n                    \"seconds\": 1.0010319948196411, \n                    \"sender\": false, \n                    \"socket\": 5, \n                    \"start\": 20.000087\n                }\n            ], \n            \"sum\": {\n                \"bits_per_second\": 0, \n                \"bytes\": 0, \n                \"end\": 21.001119, \n                \"omitted\": false, \n                \"seconds\": 1.0010319948196411, \n                \"sender\": false, \n                \"start\": 20.000087\n            }\n        }, \n        {\n            \"streams\": [\n                {\n                    \"bits_per_second\": 0, \n                    \"bytes\": 0, \n                    \"end\": 22.001198, \n                    \"omitted\": false, \n                    \"seconds\": 1.0000790357589722, \n                    \"sender\": false, \n                    \"socket\": 5, \n                    \"start\": 21.001119\n                }\n            ], \n            \"sum\": {\n                \"bits_per_second\": 0, \n                \"bytes\": 0, \n                \"end\": 22.001198, \n                \"omitted\": false, \n                \"seconds\": 1.0000790357589722, \n                \"sender\": false, \n                \"start\": 21.001119\n            }\n        }, \n        {\n            \"streams\": [\n                {\n                    \"bits_per_second\": 0, \n                    \"bytes\": 0, \n                    \"end\": 23.001139, \n                    \"omitted\": false, \n                    \"seconds\": 0.9999409914016724, \n                    \"sender\": false, \n                    \"socket\": 5, \n                    \"start\": 22.001198\n                }\n            ], \n            \"sum\": {\n                \"bits_per_second\": 0, \n                \"bytes\": 0, \n                \"end\": 23.001139, \n                \"omitted\": false, \n                \"seconds\": 0.9999409914016724, \n                \"sender\": false, \n                \"start\": 22.001198\n            }\n        }, \n        {\n            \"streams\": [\n                {\n                    \"bits_per_second\": 0, \n                    \"bytes\": 0, \n                    \"end\": 24.001163, \n                    \"omitted\": false, \n                    \"seconds\": 1.0000239610672, \n                    \"sender\": false, \n                    \"socket\": 5, \n                    \"start\": 23.001139\n                }\n            ], \n            \"sum\": {\n                \"bits_per_second\": 0, \n                \"bytes\": 0, \n                \"end\": 24.001163, \n                \"omitted\": false, \n                \"seconds\": 1.0000239610672, \n                \"sender\": false, \n                \"start\": 23.001139\n            }\n        }, \n        {\n            \"streams\": [\n                {\n                    \"bits_per_second\": 0, \n                    \"bytes\": 0, \n                    \"end\": 25.001133, \n                    \"omitted\": false, \n                    \"seconds\": 0.999970018863678, \n                    \"sender\": false, \n                    \"socket\": 5, \n                    \"start\": 24.001163\n                }\n            ], \n            \"sum\": {\n                \"bits_per_second\": 0, \n                \"bytes\": 0, \n                \"end\": 25.001133, \n                \"omitted\": false, \n                \"seconds\": 0.999970018863678, \n                \"sender\": false, \n                \"start\": 24.001163\n            }\n        }, \n        {\n            \"streams\": [\n                {\n                    \"bits_per_second\": 0, \n                    \"bytes\": 0, \n                    \"end\": 26.001176, \n                    \"omitted\": false, \n                    \"seconds\": 1.0000430345535278, \n                    \"sender\": false, \n                    \"socket\": 5, \n                    \"start\": 25.001133\n                }\n            ], \n            \"sum\": {\n                \"bits_per_second\": 0, \n                \"bytes\": 0, \n                \"end\": 26.001176, \n                \"omitted\": false, \n                \"seconds\": 1.0000430345535278, \n                \"sender\": false, \n                \"start\": 25.001133\n            }\n        }, \n        {\n            \"streams\": [\n                {\n                    \"bits_per_second\": 2097248.5044406313, \n                    \"bytes\": 262144, \n                    \"end\": 27.00113, \n                    \"omitted\": false, \n                    \"seconds\": 0.9999539852142334, \n                    \"sender\": false, \n                    \"socket\": 5, \n                    \"start\": 26.001176\n                }\n            ], \n            \"sum\": {\n                \"bits_per_second\": 2097248.5044406313, \n                \"bytes\": 262144, \n                \"end\": 27.00113, \n                \"omitted\": false, \n                \"seconds\": 0.9999539852142334, \n                \"sender\": false, \n                \"start\": 26.001176\n            }\n        }, \n        {\n            \"streams\": [\n                {\n                    \"bits_per_second\": 0, \n                    \"bytes\": 0, \n                    \"end\": 28.001187, \n                    \"omitted\": false, \n                    \"seconds\": 1.0000569820404053, \n                    \"sender\": false, \n                    \"socket\": 5, \n                    \"start\": 27.00113\n                }\n            ], \n            \"sum\": {\n                \"bits_per_second\": 0, \n                \"bytes\": 0, \n                \"end\": 28.001187, \n                \"omitted\": false, \n                \"seconds\": 1.0000569820404053, \n                \"sender\": false, \n                \"start\": 27.00113\n            }\n        }, \n        {\n            \"streams\": [\n                {\n                    \"bits_per_second\": 7340920.232473846, \n                    \"bytes\": 917504, \n                    \"end\": 29.001066, \n                    \"omitted\": false, \n                    \"seconds\": 0.999879002571106, \n                    \"sender\": false, \n                    \"socket\": 5, \n                    \"start\": 28.001187\n                }\n            ], \n            \"sum\": {\n                \"bits_per_second\": 7340920.232473846, \n                \"bytes\": 917504, \n                \"end\": 29.001066, \n                \"omitted\": false, \n                \"seconds\": 0.999879002571106, \n                \"sender\": false, \n                \"start\": 28.001187\n            }\n        }, \n        {\n            \"streams\": [\n                {\n                    \"bits_per_second\": 3145510.8899854063, \n                    \"bytes\": 393216, \n                    \"end\": 30.001135, \n                    \"omitted\": false, \n                    \"seconds\": 1.00006902217865, \n                    \"sender\": false, \n                    \"socket\": 5, \n                    \"start\": 29.001066\n                }\n            ], \n            \"sum\": {\n                \"bits_per_second\": 3145510.8899854063, \n                \"bytes\": 393216, \n                \"end\": 30.001135, \n                \"omitted\": false, \n                \"seconds\": 1.00006902217865, \n                \"sender\": false, \n                \"start\": 29.001066\n            }\n        }, \n        {\n            \"streams\": [\n                {\n                    \"bits_per_second\": 1048637.8786513724, \n                    \"bytes\": 131072, \n                    \"end\": 31.001076, \n                    \"omitted\": false, \n                    \"seconds\": 0.9999409914016724, \n                    \"sender\": false, \n                    \"socket\": 5, \n                    \"start\": 30.001135\n                }\n            ], \n            \"sum\": {\n                \"bits_per_second\": 1048637.8786513724, \n                \"bytes\": 131072, \n                \"end\": 31.001076, \n                \"omitted\": false, \n                \"seconds\": 0.9999409914016724, \n                \"sender\": false, \n                \"start\": 30.001135\n            }\n        }, \n        {\n            \"streams\": [\n                {\n                    \"bits_per_second\": 0, \n                    \"bytes\": 0, \n                    \"end\": 32.00111, \n                    \"omitted\": false, \n                    \"seconds\": 1.000033974647522, \n                    \"sender\": false, \n                    \"socket\": 5, \n                    \"start\": 31.001076\n                }\n            ], \n            \"sum\": {\n                \"bits_per_second\": 0, \n                \"bytes\": 0, \n                \"end\": 32.00111, \n                \"omitted\": false, \n                \"seconds\": 1.000033974647522, \n                \"sender\": false, \n                \"start\": 31.001076\n            }\n        }, \n        {\n            \"streams\": [\n                {\n                    \"bits_per_second\": 0, \n                    \"bytes\": 0, \n                    \"end\": 33.000076, \n                    \"omitted\": false, \n                    \"seconds\": 0.9989659786224365, \n                    \"sender\": false, \n                    \"socket\": 5, \n                    \"start\": 32.00111\n                }\n            ], \n            \"sum\": {\n                \"bits_per_second\": 0, \n                \"bytes\": 0, \n                \"end\": 33.000076, \n                \"omitted\": false, \n                \"seconds\": 0.9989659786224365, \n                \"sender\": false, \n                \"start\": 32.00111\n            }\n        }, \n        {\n            \"streams\": [\n                {\n                    \"bits_per_second\": 0, \n                    \"bytes\": 0, \n                    \"end\": 34.000051, \n                    \"omitted\": false, \n                    \"seconds\": 0.999975025653839, \n                    \"sender\": false, \n                    \"socket\": 5, \n                    \"start\": 33.000076\n                }\n            ], \n            \"sum\": {\n                \"bits_per_second\": 0, \n                \"bytes\": 0, \n                \"end\": 34.000051, \n                \"omitted\": false, \n                \"seconds\": 0.999975025653839, \n                \"sender\": false, \n                \"start\": 33.000076\n            }\n        }, \n        {\n            \"streams\": [\n                {\n                    \"bits_per_second\": 0, \n                    \"bytes\": 0, \n                    \"end\": 35.000157, \n                    \"omitted\": false, \n                    \"seconds\": 1.0001059770584106, \n                    \"sender\": false, \n                    \"socket\": 5, \n                    \"start\": 34.000051\n                }\n            ], \n            \"sum\": {\n                \"bits_per_second\": 0, \n                \"bytes\": 0, \n                \"end\": 35.000157, \n                \"omitted\": false, \n                \"seconds\": 1.0001059770584106, \n                \"sender\": false, \n                \"start\": 34.000051\n            }\n        }, \n        {\n            \"streams\": [\n                {\n                    \"bits_per_second\": 0, \n                    \"bytes\": 0, \n                    \"end\": 36.000084, \n                    \"omitted\": false, \n                    \"seconds\": 0.99992698431015, \n                    \"sender\": false, \n                    \"socket\": 5, \n                    \"start\": 35.000157\n                }\n            ], \n            \"sum\": {\n                \"bits_per_second\": 0, \n                \"bytes\": 0, \n                \"end\": 36.000084, \n                \"omitted\": false, \n                \"seconds\": 0.99992698431015, \n                \"sender\": false, \n                \"start\": 35.000157\n            }\n        }, \n        {\n            \"streams\": [\n                {\n                    \"bits_per_second\": 0, \n                    \"bytes\": 0, \n                    \"end\": 37.000055, \n                    \"omitted\": false, \n                    \"seconds\": 0.9999709725379944, \n                    \"sender\": false, \n                    \"socket\": 5, \n                    \"start\": 36.000084\n                }\n            ], \n            \"sum\": {\n                \"bits_per_second\": 0, \n                \"bytes\": 0, \n                \"end\": 37.000055, \n                \"omitted\": false, \n                \"seconds\": 0.9999709725379944, \n                \"sender\": false, \n                \"start\": 36.000084\n            }\n        }, \n        {\n            \"streams\": [\n                {\n                    \"bits_per_second\": 0, \n                    \"bytes\": 0, \n                    \"end\": 38.000146, \n                    \"omitted\": false, \n                    \"seconds\": 1.0000909566879272, \n                    \"sender\": false, \n                    \"socket\": 5, \n                    \"start\": 37.000055\n                }\n            ], \n            \"sum\": {\n                \"bits_per_second\": 0, \n                \"bytes\": 0, \n                \"end\": 38.000146, \n                \"omitted\": false, \n                \"seconds\": 1.0000909566879272, \n                \"sender\": false, \n                \"start\": 37.000055\n            }\n        }, \n        {\n            \"streams\": [\n                {\n                    \"bits_per_second\": 0, \n                    \"bytes\": 0, \n                    \"end\": 39.001146, \n                    \"omitted\": false, \n                    \"seconds\": 1.0010000467300415, \n                    \"sender\": false, \n                    \"socket\": 5, \n                    \"start\": 38.000146\n                }\n            ], \n            \"sum\": {\n                \"bits_per_second\": 0, \n                \"bytes\": 0, \n                \"end\": 39.001146, \n                \"omitted\": false, \n                \"seconds\": 1.0010000467300415, \n                \"sender\": false, \n                \"start\": 38.000146\n            }\n        }, \n        {\n            \"streams\": [\n                {\n                    \"bits_per_second\": 0, \n                    \"bytes\": 0, \n                    \"end\": 40.001153, \n                    \"omitted\": false, \n                    \"seconds\": 1.0000070333480835, \n                    \"sender\": false, \n                    \"socket\": 5, \n                    \"start\": 39.001146\n                }\n            ], \n            \"sum\": {\n                \"bits_per_second\": 0, \n                \"bytes\": 0, \n                \"end\": 40.001153, \n                \"omitted\": false, \n                \"seconds\": 1.0000070333480835, \n                \"sender\": false, \n                \"start\": 39.001146\n            }\n        }, \n        {\n            \"streams\": [\n                {\n                    \"bits_per_second\": 612317.1089217586, \n                    \"bytes\": 76544, \n                    \"end\": 41.00121, \n                    \"omitted\": false, \n                    \"seconds\": 1.0000569820404053, \n                    \"sender\": false, \n                    \"socket\": 5, \n                    \"start\": 40.001153\n                }\n            ], \n            \"sum\": {\n                \"bits_per_second\": 612317.1089217586, \n                \"bytes\": 76544, \n                \"end\": 41.00121, \n                \"omitted\": false, \n                \"seconds\": 1.0000569820404053, \n                \"sender\": false, \n                \"start\": 40.001153\n            }\n        }, \n        {\n            \"streams\": [\n                {\n                    \"bits_per_second\": 0, \n                    \"bytes\": 0, \n                    \"end\": 42.001157, \n                    \"omitted\": false, \n                    \"seconds\": 0.9999470114707947, \n                    \"sender\": false, \n                    \"socket\": 5, \n                    \"start\": 41.00121\n                }\n            ], \n            \"sum\": {\n                \"bits_per_second\": 0, \n                \"bytes\": 0, \n                \"end\": 42.001157, \n                \"omitted\": false, \n                \"seconds\": 0.9999470114707947, \n                \"sender\": false, \n                \"start\": 41.00121\n            }\n        }, \n        {\n            \"streams\": [\n                {\n                    \"bits_per_second\": 0, \n                    \"bytes\": 0, \n                    \"end\": 43.001146, \n                    \"omitted\": false, \n                    \"seconds\": 0.9999889731407166, \n                    \"sender\": false, \n                    \"socket\": 5, \n                    \"start\": 42.001157\n                }\n            ], \n            \"sum\": {\n                \"bits_per_second\": 0, \n                \"bytes\": 0, \n                \"end\": 43.001146, \n                \"omitted\": false, \n                \"seconds\": 0.9999889731407166, \n                \"sender\": false, \n                \"start\": 42.001157\n            }\n        }, \n        {\n            \"streams\": [\n                {\n                    \"bits_per_second\": 0, \n                    \"bytes\": 0, \n                    \"end\": 44.001224, \n                    \"omitted\": false, \n                    \"seconds\": 1.0000779628753662, \n                    \"sender\": false, \n                    \"socket\": 5, \n                    \"start\": 43.001146\n                }\n            ], \n            \"sum\": {\n                \"bits_per_second\": 0, \n                \"bytes\": 0, \n                \"end\": 44.001224, \n                \"omitted\": false, \n                \"seconds\": 1.0000779628753662, \n                \"sender\": false, \n                \"start\": 43.001146\n            }\n        }, \n        {\n            \"streams\": [\n                {\n                    \"bits_per_second\": 0, \n                    \"bytes\": 0, \n                    \"end\": 45.001197, \n                    \"omitted\": false, \n                    \"seconds\": 0.9999729990959167, \n                    \"sender\": false, \n                    \"socket\": 5, \n                    \"start\": 44.001224\n                }\n            ], \n            \"sum\": {\n                \"bits_per_second\": 0, \n                \"bytes\": 0, \n                \"end\": 45.001197, \n                \"omitted\": false, \n                \"seconds\": 0.9999729990959167, \n                \"sender\": false, \n                \"start\": 44.001224\n            }\n        }, \n        {\n            \"streams\": [\n                {\n                    \"bits_per_second\": 0, \n                    \"bytes\": 0, \n                    \"end\": 46.001073, \n                    \"omitted\": false, \n                    \"seconds\": 0.9998760223388672, \n                    \"sender\": false, \n                    \"socket\": 5, \n                    \"start\": 45.001197\n                }\n            ], \n            \"sum\": {\n                \"bits_per_second\": 0, \n                \"bytes\": 0, \n                \"end\": 46.001073, \n                \"omitted\": false, \n                \"seconds\": 0.9998760223388672, \n                \"sender\": false, \n                \"start\": 45.001197\n            }\n        }, \n        {\n            \"streams\": [\n                {\n                    \"bits_per_second\": 0, \n                    \"bytes\": 0, \n                    \"end\": 47.00115, \n                    \"omitted\": false, \n                    \"seconds\": 1.00007700920105, \n                    \"sender\": false, \n                    \"socket\": 5, \n                    \"start\": 46.001073\n                }\n            ], \n            \"sum\": {\n                \"bits_per_second\": 0, \n                \"bytes\": 0, \n                \"end\": 47.00115, \n                \"omitted\": false, \n                \"seconds\": 1.00007700920105, \n                \"sender\": false, \n                \"start\": 46.001073\n            }\n        }, \n        {\n            \"streams\": [\n                {\n                    \"bits_per_second\": 0, \n                    \"bytes\": 0, \n                    \"end\": 48.001088, \n                    \"omitted\": false, \n                    \"seconds\": 0.9999380111694336, \n                    \"sender\": false, \n                    \"socket\": 5, \n                    \"start\": 47.00115\n                }\n            ], \n            \"sum\": {\n                \"bits_per_second\": 0, \n                \"bytes\": 0, \n                \"end\": 48.001088, \n                \"omitted\": false, \n                \"seconds\": 0.9999380111694336, \n                \"sender\": false, \n                \"start\": 47.00115\n            }\n        }, \n        {\n            \"streams\": [\n                {\n                    \"bits_per_second\": 1048582.312538002, \n                    \"bytes\": 131072, \n                    \"end\": 49.001082, \n                    \"omitted\": false, \n                    \"seconds\": 0.9999939799308777, \n                    \"sender\": false, \n                    \"socket\": 5, \n                    \"start\": 48.001088\n                }\n            ], \n            \"sum\": {\n                \"bits_per_second\": 1048582.312538002, \n                \"bytes\": 131072, \n                \"end\": 49.001082, \n                \"omitted\": false, \n                \"seconds\": 0.9999939799308777, \n                \"sender\": false, \n                \"start\": 48.001088\n            }\n        }, \n        {\n            \"streams\": [\n                {\n                    \"bits_per_second\": 0, \n                    \"bytes\": 0, \n                    \"end\": 50.001166, \n                    \"omitted\": false, \n                    \"seconds\": 1.0000840425491333, \n                    \"sender\": false, \n                    \"socket\": 5, \n                    \"start\": 49.001082\n                }\n            ], \n            \"sum\": {\n                \"bits_per_second\": 0, \n                \"bytes\": 0, \n                \"end\": 50.001166, \n                \"omitted\": false, \n                \"seconds\": 1.0000840425491333, \n                \"sender\": false, \n                \"start\": 49.001082\n            }\n        }, \n        {\n            \"streams\": [\n                {\n                    \"bits_per_second\": 0, \n                    \"bytes\": 0, \n                    \"end\": 51.001136, \n                    \"omitted\": false, \n                    \"seconds\": 0.999970018863678, \n                    \"sender\": false, \n                    \"socket\": 5, \n                    \"start\": 50.001166\n                }\n            ], \n            \"sum\": {\n                \"bits_per_second\": 0, \n                \"bytes\": 0, \n                \"end\": 51.001136, \n                \"omitted\": false, \n                \"seconds\": 0.999970018863678, \n                \"sender\": false, \n                \"start\": 50.001166\n            }\n        }, \n        {\n            \"streams\": [\n                {\n                    \"bits_per_second\": 0, \n                    \"bytes\": 0, \n                    \"end\": 52.001051, \n                    \"omitted\": false, \n                    \"seconds\": 0.9999150037765503, \n                    \"sender\": false, \n                    \"socket\": 5, \n                    \"start\": 51.001136\n                }\n            ], \n            \"sum\": {\n                \"bits_per_second\": 0, \n                \"bytes\": 0, \n                \"end\": 52.001051, \n                \"omitted\": false, \n                \"seconds\": 0.9999150037765503, \n                \"sender\": false, \n                \"start\": 51.001136\n            }\n        }, \n        {\n            \"streams\": [\n                {\n                    \"bits_per_second\": 0, \n                    \"bytes\": 0, \n                    \"end\": 53.001083, \n                    \"omitted\": false, \n                    \"seconds\": 1.0000319480895996, \n                    \"sender\": false, \n                    \"socket\": 5, \n                    \"start\": 52.001051\n                }\n            ], \n            \"sum\": {\n                \"bits_per_second\": 0, \n                \"bytes\": 0, \n                \"end\": 53.001083, \n                \"omitted\": false, \n                \"seconds\": 1.0000319480895996, \n                \"sender\": false, \n                \"start\": 52.001051\n            }\n        }, \n        {\n            \"streams\": [\n                {\n                    \"bits_per_second\": 0, \n                    \"bytes\": 0, \n                    \"end\": 54.001168, \n                    \"omitted\": false, \n                    \"seconds\": 1.00008499622345, \n                    \"sender\": false, \n                    \"socket\": 5, \n                    \"start\": 53.001083\n                }\n            ], \n            \"sum\": {\n                \"bits_per_second\": 0, \n                \"bytes\": 0, \n                \"end\": 54.001168, \n                \"omitted\": false, \n                \"seconds\": 1.00008499622345, \n                \"sender\": false, \n                \"start\": 53.001083\n            }\n        }, \n        {\n            \"streams\": [\n                {\n                    \"bits_per_second\": 1049622.48084862, \n                    \"bytes\": 131072, \n                    \"end\": 55.000171, \n                    \"omitted\": false, \n                    \"seconds\": 0.999002993106842, \n                    \"sender\": false, \n                    \"socket\": 5, \n                    \"start\": 54.001168\n                }\n            ], \n            \"sum\": {\n                \"bits_per_second\": 1049622.48084862, \n                \"bytes\": 131072, \n                \"end\": 55.000171, \n                \"omitted\": false, \n                \"seconds\": 0.999002993106842, \n                \"sender\": false, \n                \"start\": 54.001168\n            }\n        }, \n        {\n            \"streams\": [\n                {\n                    \"bits_per_second\": 0, \n                    \"bytes\": 0, \n                    \"end\": 56.000173, \n                    \"omitted\": false, \n                    \"seconds\": 1.0000020265579224, \n                    \"sender\": false, \n                    \"socket\": 5, \n                    \"start\": 55.000171\n                }\n            ], \n            \"sum\": {\n                \"bits_per_second\": 0, \n                \"bytes\": 0, \n                \"end\": 56.000173, \n                \"omitted\": false, \n                \"seconds\": 1.0000020265579224, \n                \"sender\": false, \n                \"start\": 55.000171\n            }\n        }, \n        {\n            \"streams\": [\n                {\n                    \"bits_per_second\": 0, \n                    \"bytes\": 0, \n                    \"end\": 57.001199, \n                    \"omitted\": false, \n                    \"seconds\": 1.0010260343551636, \n                    \"sender\": false, \n                    \"socket\": 5, \n                    \"start\": 56.000173\n                }\n            ], \n            \"sum\": {\n                \"bits_per_second\": 0, \n                \"bytes\": 0, \n                \"end\": 57.001199, \n                \"omitted\": false, \n                \"seconds\": 1.0010260343551636, \n                \"sender\": false, \n                \"start\": 56.000173\n            }\n        }, \n        {\n            \"streams\": [\n                {\n                    \"bits_per_second\": 0, \n                    \"bytes\": 0, \n                    \"end\": 58.001073, \n                    \"omitted\": false, \n                    \"seconds\": 0.9998739957809448, \n                    \"sender\": false, \n                    \"socket\": 5, \n                    \"start\": 57.001199\n                }\n            ], \n            \"sum\": {\n                \"bits_per_second\": 0, \n                \"bytes\": 0, \n                \"end\": 58.001073, \n                \"omitted\": false, \n                \"seconds\": 0.9998739957809448, \n                \"sender\": false, \n                \"start\": 57.001199\n            }\n        }, \n        {\n            \"streams\": [\n                {\n                    \"bits_per_second\": 1048498.3807460733, \n                    \"bytes\": 131072, \n                    \"end\": 59.001147, \n                    \"omitted\": false, \n                    \"seconds\": 1.000074028968811, \n                    \"sender\": false, \n                    \"socket\": 5, \n                    \"start\": 58.001073\n                }\n            ], \n            \"sum\": {\n                \"bits_per_second\": 1048498.3807460733, \n                \"bytes\": 131072, \n                \"end\": 59.001147, \n                \"omitted\": false, \n                \"seconds\": 1.000074028968811, \n                \"sender\": false, \n                \"start\": 58.001073\n            }\n        }, \n        {\n            \"streams\": [\n                {\n                    \"bits_per_second\": 2097101.7512040148, \n                    \"bytes\": 262144, \n                    \"end\": 60.001171, \n                    \"omitted\": false, \n                    \"seconds\": 1.0000239610672, \n                    \"sender\": false, \n                    \"socket\": 5, \n                    \"start\": 59.001147\n                }\n            ], \n            \"sum\": {\n                \"bits_per_second\": 2097101.7512040148, \n                \"bytes\": 262144, \n                \"end\": 60.001171, \n                \"omitted\": false, \n                \"seconds\": 1.0000239610672, \n                \"sender\": false, \n                \"start\": 59.001147\n            }\n        }\n    ], \n    \"start\": {\n        \"accepted_connection\": {\n            \"host\": \"172.16.0.2\", \n            \"port\": 43879\n        }, \n        \"connected\": [\n            {\n                \"local_host\": \"172.16.0.1\", \n                \"local_port\": 5201, \n                \"remote_host\": \"172.16.0.2\", \n                \"remote_port\": 56053, \n                \"socket\": 5\n            }\n        ], \n        \"cookie\": \"6h4jyqh3hqienslj2uwtmn36bbda5iw3zn33\", \n        \"fq_rate\": 0, \n        \"rcvbuf_actual\": 87380, \n        \"sndbuf_actual\": 65536, \n        \"sock_bufsize\": 0, \n        \"system_info\": \"REDACTED\", \n        \"target_bitrate\": 0, \n        \"tcp_mss_default\": 0, \n        \"test_start\": {\n            \"bidir\": 0, \n            \"blksize\": 131072, \n            \"blocks\": 0, \n            \"bytes\": 0, \n            \"duration\": 60, \n            \"fqrate\": 0, \n            \"interval\": 1, \n            \"num_streams\": 1, \n            \"omit\": 0, \n            \"protocol\": \"TCP\", \n            \"reverse\": 0, \n            \"target_bitrate\": 0, \n            \"tos\": 0\n        }, \n        \"timestamp\": {\n            \"time\": \"Wed, 16 Oct 2024 02:49:09 GMT\", \n            \"timesecs\": 1729046949\n        }, \n        \"version\": \"iperf 3.17.1\"\n    }\n}\n","summary":{"streams":[{"end":60.001024,"rtt":424775,"start":0,"stream-id":5,"retransmits":1079,"throughput-bits":1135937.9466590437,"throughput-bytes":8519680}],"summary":{"end":60.001024,"start":0,"retransmits":1079,"throughput-bits":1135937.9466590437,"throughput-bytes":8519680,"receiver-throughput-bits":673353.97609769}},"intervals":[{"streams":[{"end":1.000703,"rtt":323430,"start":0,"omitted":false,"stream-id":5,"retransmits":138,"tcp-window-size":160728,"throughput-bits":36674378.7486314,"throughput-bytes":4587520}],"summary":{"end":1.000703,"start":0,"omitted":false,"retransmits":138,"throughput-bits":36674378.7486314,"throughput-bytes":4587520}},{"streams":[{"end":2.00079,"rtt":123082,"start":1.000703,"omitted":false,"stream-id":5,"retransmits":259,"tcp-window-size":402544,"throughput-bits":0,"throughput-bytes":0}],"summary":{"end":2.00079,"start":1.000703,"omitted":false,"retransmits":259,"throughput-bits":0,"throughput-bytes":0}},{"streams":[{"end":3.001015,"rtt":123082,"start":2.00079,"omitted":false,"stream-id":5,"retransmits":1,"tcp-window-size":1448,"throughput-bits":0,"throughput-bytes":0}],"summary":{"end":3.001015,"start":2.00079,"omitted":false,"retransmits":1,"throughput-bits":0,"throughput-bytes":0}},{"streams":[{"end":4.001015,"rtt":123082,"start":3.001015,"omitted":false,"stream-id":5,"retransmits":0,"tcp-window-size":1448,"throughput-bits":0,"throughput-bytes":0}],"summary":{"end":4.001015,"start":3.001015,"omitted":false,"retransmits":0,"throughput-bits":0,"throughput-bytes":0}},{"streams":[{"end":5.001017,"rtt":123082,"start":4.001015,"omitted":false,"stream-id":5,"retransmits":1,"tcp-window-size":1448,"throughput-bits":0,"throughput-bytes":0}],"summary":{"end":5.001017,"start":4.001015,"omitted":false,"retransmits":1,"throughput-bits":0,"throughput-bytes":0}},{"streams":[{"end":6.001015,"rtt":123082,"start":5.001017,"omitted":false,"stream-id":5,"retransmits":0,"tcp-window-size":1448,"throughput-bits":0,"throughput-bytes":0}],"summary":{"end":6.001015,"start":5.001017,"omitted":false,"retransmits":0,"throughput-bits":0,"throughput-bytes":0}},{"streams":[{"end":7.001018,"rtt":123082,"start":6.001015,"omitted":false,"stream-id":5,"retransmits":0,"tcp-window-size":1448,"throughput-bits":0,"throughput-bytes":0}],"summary":{"end":7.001018,"start":6.001015,"omitted":false,"retransmits":0,"throughput-bits":0,"throughput-bytes":0}},{"streams":[{"end":8.001017,"rtt":123082,"start":7.001018,"omitted":false,"stream-id":5,"retransmits":0,"tcp-window-size":1448,"throughput-bits":0,"throughput-bytes":0}],"summary":{"end":8.001017,"start":7.001018,"omitted":false,"retransmits":0,"throughput-bits":0,"throughput-bytes":0}},{"streams":[{"end":9.000105,"rtt":66955,"start":8.001017,"omitted":false,"stream-id":5,"retransmits":278,"tcp-window-size":379376,"throughput-bits":10495331.854633555,"throughput-bytes":1310720}],"summary":{"end":9.000105,"start":8.001017,"omitted":false,"retransmits":278,"throughput-bits":10495331.854633555,"throughput-bytes":1310720}},{"streams":[{"end":10.001019,"rtt":145667,"start":9.000105,"omitted":false,"stream-id":5,"retransmits":4,"tcp-window-size":1448,"throughput-bits":0,"throughput-bytes":0}],"summary":{"end":10.001019,"start":9.000105,"omitted":false,"retransmits":4,"throughput-bits":0,"throughput-bytes":0}},{"streams":[{"end":11.001017,"rtt":145667,"start":10.001019,"omitted":false,"stream-id":5,"retransmits":0,"tcp-window-size":1448,"throughput-bits":0,"throughput-bytes":0}],"summary":{"end":11.001017,"start":10.001019,"omitted":false,"retransmits":0,"throughput-bits":0,"throughput-bytes":0}},{"streams":[{"end":12.001024,"rtt":2294262,"start":11.001017,"omitted":false,"stream-id":5,"retransmits":0,"tcp-window-size":1448,"throughput-bits":0,"throughput-bytes":0}],"summary":{"end":12.001024,"start":11.001017,"omitted":false,"retransmits":0,"throughput-bits":0,"throughput-bytes":0}},{"streams":[{"end":13.001018,"rtt":2294262,"start":12.001024,"omitted":false,"stream-id":5,"retransmits":0,"tcp-window-size":1448,"throughput-bits":0,"throughput-bytes":0}],"summary":{"end":13.001018,"start":12.001024,"omitted":false,"retransmits":0,"throughput-bits":0,"throughput-bytes":0}},{"streams":[{"end":14.001017,"rtt":2294262,"start":13.001018,"omitted":false,"stream-id":5,"retransmits":0,"tcp-window-size":1448,"throughput-bits":0,"throughput-bytes":0}],"summary":{"end":14.001017,"start":13.001018,"omitted":false,"retransmits":0,"throughput-bits":0,"throughput-bytes":0}},{"streams":[{"end":15.001017,"rtt":2294262,"start":14.001017,"omitted":false,"stream-id":5,"retransmits":0,"tcp-window-size":1448,"throughput-bits":0,"throughput-bytes":0}],"summary":{"end":15.001017,"start":14.001017,"omitted":false,"retransmits":0,"throughput-bits":0,"throughput-bytes":0}},{"streams":[{"end":16.001016,"rtt":2294262,"start":15.001017,"omitted":false,"stream-id":5,"retransmits":0,"tcp-window-size":1448,"throughput-bits":0,"throughput-bytes":0}],"summary":{"end":16.001016,"start":15.001017,"omitted":false,"retransmits":0,"throughput-bits":0,"throughput-bytes":0}},{"streams":[{"end":17.001015,"rtt":2294262,"start":16.001016,"omitted":false,"stream-id":5,"retransmits":0,"tcp-window-size":1448,"throughput-bits":0,"throughput-bytes":0}],"summary":{"end":17.001015,"start":16.001016,"omitted":false,"retransmits":0,"throughput-bits":0,"throughput-bytes":0}},{"streams":[{"end":18.001016,"rtt":2294262,"start":17.001015,"omitted":false,"stream-id":5,"retransmits":0,"tcp-window-size":1448,"throughput-bits":0,"throughput-bytes":0}],"summary":{"end":18.001016,"start":17.001015,"omitted":false,"retransmits":0,"throughput-bits":0,"throughput-bytes":0}},{"streams":[{"end":19.001016,"rtt":27779,"start":18.001016,"omitted":false,"stream-id":5,"retransmits":97,"tcp-window-size":143352,"throughput-bits":0,"throughput-bytes":0}],"summary":{"end":19.001016,"start":18.001016,"omitted":false,"retransmits":97,"throughput-bits":0,"throughput-bytes":0}},{"streams":[{"end":20.001016,"rtt":27779,"start":19.001016,"omitted":false,"stream-id":5,"retransmits":0,"tcp-window-size":143352,"throughput-bits":0,"throughput-bytes":0}],"summary":{"end":20.001016,"start":19.001016,"omitted":false,"retransmits":0,"throughput-bits":0,"throughput-bytes":0}},{"streams":[{"end":21.001017,"rtt":1060822,"start":20.001016,"omitted":false,"stream-id":5,"retransmits":6,"tcp-window-size":11584,"throughput-bits":0,"throughput-bytes":0}],"summary":{"end":21.001017,"start":20.001016,"omitted":false,"retransmits":6,"throughput-bits":0,"throughput-bytes":0}},{"streams":[{"end":22.001016,"rtt":1060822,"start":21.001017,"omitted":false,"stream-id":5,"retransmits":0,"tcp-window-size":11584,"throughput-bits":0,"throughput-bytes":0}],"summary":{"end":22.001016,"start":21.001017,"omitted":false,"retransmits":0,"throughput-bits":0,"throughput-bytes":0}},{"streams":[{"end":23.001031,"rtt":1060822,"start":22.001016,"omitted":false,"stream-id":5,"retransmits":0,"tcp-window-size":11584,"throughput-bits":0,"throughput-bytes":0}],"summary":{"end":23.001031,"start":22.001016,"omitted":false,"retransmits":0,"throughput-bits":0,"throughput-bytes":0}},{"streams":[{"end":24.001015,"rtt":1060822,"start":23.001031,"omitted":false,"stream-id":5,"retransmits":0,"tcp-window-size":11584,"throughput-bits":0,"throughput-bytes":0}],"summary":{"end":24.001015,"start":23.001031,"omitted":false,"retransmits":0,"throughput-bits":0,"throughput-bytes":0}},{"streams":[{"end":25.001026,"rtt":1060822,"start":24.001015,"omitted":false,"stream-id":5,"retransmits":0,"tcp-window-size":11584,"throughput-bits":0,"throughput-bytes":0}],"summary":{"end":25.001026,"start":24.001015,"omitted":false,"retransmits":0,"throughput-bits":0,"throughput-bytes":0}},{"streams":[{"end":26.001015,"rtt":1060822,"start":25.001026,"omitted":false,"stream-id":5,"retransmits":0,"tcp-window-size":11584,"throughput-bits":0,"throughput-bytes":0}],"summary":{"end":26.001015,"start":25.001026,"omitted":false,"retransmits":0,"throughput-bits":0,"throughput-bytes":0}},{"streams":[{"end":27.000747,"rtt":34187,"start":26.001015,"omitted":false,"stream-id":5,"retransmits":94,"tcp-window-size":72400,"throughput-bits":10488570.75323263,"throughput-bytes":1310720}],"summary":{"end":27.000747,"start":26.001015,"omitted":false,"retransmits":94,"throughput-bits":10488570.75323263,"throughput-bytes":1310720}},{"streams":[{"end":28.001018,"rtt":34187,"start":27.000747,"omitted":false,"stream-id":5,"retransmits":0,"tcp-window-size":72400,"throughput-bits":0,"throughput-bytes":0}],"summary":{"end":28.001018,"start":27.000747,"omitted":false,"retransmits":0,"throughput-bits":0,"throughput-bytes":0}},{"streams":[{"end":29.001016,"rtt":35815,"start":28.001018,"omitted":false,"stream-id":5,"retransmits":44,"tcp-window-size":2896,"throughput-bits":0,"throughput-bytes":0}],"summary":{"end":29.001016,"start":28.001018,"omitted":false,"retransmits":44,"throughput-bits":0,"throughput-bytes":0}},{"streams":[{"end":30.00024,"rtt":21359,"start":29.001016,"omitted":false,"stream-id":5,"retransmits":59,"tcp-window-size":27512,"throughput-bits":10493903.194060532,"throughput-bytes":1310720}],"summary":{"end":30.00024,"start":29.001016,"omitted":false,"retransmits":59,"throughput-bits":10493903.194060532,"throughput-bytes":1310720}},{"streams":[{"end":31.001018,"rtt":19754,"start":30.00024,"omitted":false,"stream-id":5,"retransmits":2,"tcp-window-size":1448,"throughput-bits":0,"throughput-bytes":0}],"summary":{"end":31.001018,"start":30.00024,"omitted":false,"retransmits":2,"throughput-bits":0,"throughput-bytes":0}},{"streams":[{"end":32.001016,"rtt":19754,"start":31.001018,"omitted":false,"stream-id":5,"retransmits":1,"tcp-window-size":1448,"throughput-bits":0,"throughput-bytes":0}],"summary":{"end":32.001016,"start":31.001018,"omitted":false,"retransmits":1,"throughput-bits":0,"throughput-bytes":0}},{"streams":[{"end":33.001028,"rtt":19754,"start":32.001016,"omitted":false,"stream-id":5,"retransmits":0,"tcp-window-size":1448,"throughput-bits":0,"throughput-bytes":0}],"summary":{"end":33.001028,"start":32.001016,"omitted":false,"retransmits":0,"throughput-bits":0,"throughput-bytes":0}},{"streams":[{"end":34.001031,"rtt":19754,"start":33.001028,"omitted":false,"stream-id":5,"retransmits":1,"tcp-window-size":1448,"throughput-bits":0,"throughput-bytes":0}],"summary":{"end":34.001031,"start":33.001028,"omitted":false,"retransmits":1,"throughput-bits":0,"throughput-bytes":0}},{"streams":[{"end":35.001017,"rtt":19754,"start":34.001031,"omitted":false,"stream-id":5,"retransmits":0,"tcp-window-size":1448,"throughput-bits":0,"throughput-bytes":0}],"summary":{"end":35.001017,"start":34.001031,"omitted":false,"retransmits":0,"throughput-bits":0,"throughput-bytes":0}},{"streams":[{"end":36.001032,"rtt":19754,"start":35.001017,"omitted":false,"stream-id":5,"retransmits":0,"tcp-window-size":1448,"throughput-bits":0,"throughput-bytes":0}],"summary":{"end":36.001032,"start":35.001017,"omitted":false,"retransmits":0,"throughput-bits":0,"throughput-bytes":0}},{"streams":[{"end":37.001018,"rtt":19754,"start":36.001032,"omitted":false,"stream-id":5,"retransmits":0,"tcp-window-size":1448,"throughput-bits":0,"throughput-bytes":0}],"summary":{"end":37.001018,"start":36.001032,"omitted":false,"retransmits":0,"throughput-bits":0,"throughput-bytes":0}},{"streams":[{"end":38.001022,"rtt":19754,"start":37.001018,"omitted":false,"stream-id":5,"retransmits":1,"tcp-window-size":1448,"throughput-bits":0,"throughput-bytes":0}],"summary":{"end":38.001022,"start":37.001018,"omitted":false,"retransmits":1,"throughput-bits":0,"throughput-bytes":0}},{"streams":[{"end":39.001017,"rtt":19754,"start":38.001022,"omitted":false,"stream-id":5,"retransmits":0,"tcp-window-size":1448,"throughput-bits":0,"throughput-bytes":0}],"summary":{"end":39.001017,"start":38.001022,"omitted":false,"retransmits":0,"throughput-bits":0,"throughput-bytes":0}},{"streams":[{"end":40.001019,"rtt":19754,"start":39.001017,"omitted":false,"stream-id":5,"retransmits":0,"tcp-window-size":1448,"throughput-bits":0,"throughput-bytes":0}],"summary":{"end":40.001019,"start":39.001017,"omitted":false,"retransmits":0,"throughput-bits":0,"throughput-bytes":0}},{"streams":[{"end":41.00102,"rtt":19754,"start":40.001019,"omitted":false,"stream-id":5,"retransmits":0,"tcp-window-size":1448,"throughput-bits":0,"throughput-bytes":0}],"summary":{"end":41.00102,"start":40.001019,"omitted":false,"retransmits":0,"throughput-bits":0,"throughput-bytes":0}},{"streams":[{"end":42.001018,"rtt":19754,"start":41.00102,"omitted":false,"stream-id":5,"retransmits":0,"tcp-window-size":1448,"throughput-bits":0,"throughput-bytes":0}],"summary":{"end":42.001018,"start":41.00102,"omitted":false,"retransmits":0,"throughput-bits":0,"throughput-bytes":0}},{"streams":[{"end":43.001022,"rtt":19754,"start":42.001018,"omitted":false,"stream-id":5,"retransmits":0,"tcp-window-size":1448,"throughput-bits":0,"throughput-bytes":0}],"summary":{"end":43.001022,"start":42.001018,"omitted":false,"retransmits":0,"throughput-bits":0,"throughput-bytes":0}},{"streams":[{"end":44.001019,"rtt":19754,"start":43.001022,"omitted":false,"stream-id":5,"retransmits":0,"tcp-window-size":1448,"throughput-bits":0,"throughput-bytes":0}],"summary":{"end":44.001019,"start":43.001022,"omitted":false,"retransmits":0,"throughput-bits":0,"throughput-bytes":0}},{"streams":[{"end":45.001015,"rtt":30347,"start":44.001019,"omitted":false,"stream-id":5,"retransmits":24,"tcp-window-size":17376,"throughput-bits":0,"throughput-bytes":0}],"summary":{"end":45.001015,"start":44.001019,"omitted":false,"retransmits":24,"throughput-bits":0,"throughput-bytes":0}},{"streams":[{"end":46.001014,"rtt":23433,"start":45.001015,"omitted":false,"stream-id":5,"retransmits":2,"tcp-window-size":1448,"throughput-bits":0,"throughput-bytes":0}],"summary":{"end":46.001014,"start":45.001015,"omitted":false,"retransmits":2,"throughput-bits":0,"throughput-bytes":0}},{"streams":[{"end":47.001021,"rtt":23433,"start":46.001014,"omitted":false,"stream-id":5,"retransmits":1,"tcp-window-size":1448,"throughput-bits":0,"throughput-bytes":0}],"summary":{"end":47.001021,"start":46.001014,"omitted":false,"retransmits":1,"throughput-bits":0,"throughput-bytes":0}},{"streams":[{"end":48.001016,"rtt":23433,"start":47.001021,"omitted":false,"stream-id":5,"retransmits":0,"tcp-window-size":1448,"throughput-bits":0,"throughput-bytes":0}],"summary":{"end":48.001016,"start":47.001021,"omitted":false,"retransmits":0,"throughput-bits":0,"throughput-bytes":0}},{"streams":[{"end":49.001017,"rtt":24462,"start":48.001016,"omitted":false,"stream-id":5,"retransmits":15,"tcp-window-size":17376,"throughput-bits":0,"throughput-bytes":0}],"summary":{"end":49.001017,"start":48.001016,"omitted":false,"retransmits":15,"throughput-bits":0,"throughput-bytes":0}},{"streams":[{"end":50.001016,"rtt":49840,"start":49.001017,"omitted":false,"stream-id":5,"retransmits":11,"tcp-window-size":1448,"throughput-bits":0,"throughput-bytes":0}],"summary":{"end":50.001016,"start":49.001017,"omitted":false,"retransmits":11,"throughput-bits":0,"throughput-bytes":0}},{"streams":[{"end":51.001017,"rtt":173746,"start":50.001016,"omitted":false,"stream-id":5,"retransmits":1,"tcp-window-size":18824,"throughput-bits":0,"throughput-bytes":0}],"summary":{"end":51.001017,"start":50.001016,"omitted":false,"retransmits":1,"throughput-bits":0,"throughput-bytes":0}},{"streams":[{"end":52.001019,"rtt":173746,"start":51.001017,"omitted":false,"stream-id":5,"retransmits":0,"tcp-window-size":18824,"throughput-bits":0,"throughput-bytes":0}],"summary":{"end":52.001019,"start":51.001017,"omitted":false,"retransmits":0,"throughput-bits":0,"throughput-bytes":0}},{"streams":[{"end":53.001016,"rtt":173746,"start":52.001019,"omitted":false,"stream-id":5,"retransmits":0,"tcp-window-size":18824,"throughput-bits":0,"throughput-bytes":0}],"summary":{"end":53.001016,"start":52.001019,"omitted":false,"retransmits":0,"throughput-bits":0,"throughput-bytes":0}},{"streams":[{"end":54.001015,"rtt":173746,"start":53.001016,"omitted":false,"stream-id":5,"retransmits":0,"tcp-window-size":18824,"throughput-bits":0,"throughput-bytes":0}],"summary":{"end":54.001015,"start":53.001016,"omitted":false,"retransmits":0,"throughput-bits":0,"throughput-bytes":0}},{"streams":[{"end":55.000542,"rtt":36543,"start":54.001015,"omitted":false,"stream-id":5,"retransmits":14,"tcp-window-size":13032,"throughput-bits":0,"throughput-bytes":0}],"summary":{"end":55.000542,"start":54.001015,"omitted":false,"retransmits":14,"throughput-bits":0,"throughput-bytes":0}},{"streams":[{"end":56.001017,"rtt":36543,"start":55.000542,"omitted":false,"stream-id":5,"retransmits":0,"tcp-window-size":13032,"throughput-bits":0,"throughput-bytes":0}],"summary":{"end":56.001017,"start":55.000542,"omitted":false,"retransmits":0,"throughput-bits":0,"throughput-bytes":0}},{"streams":[{"end":57.001015,"rtt":32044,"start":56.001017,"omitted":false,"stream-id":5,"retransmits":11,"tcp-window-size":1448,"throughput-bits":0,"throughput-bytes":0}],"summary":{"end":57.001015,"start":56.001017,"omitted":false,"retransmits":11,"throughput-bits":0,"throughput-bytes":0}},{"streams":[{"end":58.001026,"rtt":32044,"start":57.001015,"omitted":false,"stream-id":5,"retransmits":1,"tcp-window-size":1448,"throughput-bits":0,"throughput-bytes":0}],"summary":{"end":58.001026,"start":57.001015,"omitted":false,"retransmits":1,"throughput-bits":0,"throughput-bytes":0}},{"streams":[{"end":59.001016,"rtt":36175,"start":58.001026,"omitted":false,"stream-id":5,"retransmits":12,"tcp-window-size":10136,"throughput-bits":0,"throughput-bytes":0}],"summary":{"end":59.001016,"start":58.001026,"omitted":false,"retransmits":12,"throughput-bits":0,"throughput-bytes":0}},{"streams":[{"end":60.001024,"rtt":17526,"start":59.001016,"omitted":false,"stream-id":5,"retransmits":1,"tcp-window-size":1448,"throughput-bits":0,"throughput-bytes":0}],"summary":{"end":60.001024,"start":59.001016,"omitted":false,"retransmits":1,"throughput-bits":0,"throughput-bytes":0}}],"succeeded":true}
