{"diags":"Participant 0:\n/usr/bin/iperf3 -p 5201 -B 172.16.0.2 -c 172.16.0.1 -t 10 --json --rsa-public-key-path /var/run/pscheduler-server/runner/tmp/tmpoh_k8vtf/tmpi4dil4cj/public-key --username 0A2HciVbyVmTEuuxZ7wZ\n\n{\n    \"end\": {\n        \"cpu_utilization_percent\": {\n            \"host_system\": 0.23246241747282909, \n            \"host_total\": 0.3087283444426478, \n            \"host_user\": 0.0762758046964046, \n            \"remote_system\": 0.5559259953902428, \n            \"remote_total\": 0.709203283510326, \n            \"remote_user\": 0.15328714898524795\n        }, \n        \"receiver_tcp_congestion\": \"htcp\", \n        \"sender_tcp_congestion\": \"htcp\", \n        \"streams\": [\n            {\n                \"receiver\": {\n                    \"bits_per_second\": 12470332.571382252, \n                    \"bytes\": 15807816, \n                    \"end\": 10.141071, \n                    \"seconds\": 10.001023, \n                    \"sender\": true, \n                    \"socket\": 5, \n                    \"start\": 0\n                }, \n                \"sender\": {\n                    \"bits_per_second\": 14888256.131397758, \n                    \"bytes\": 18612224, \n                    \"end\": 10.001023, \n                    \"max_rtt\": 220616, \n                    \"max_snd_cwnd\": 385168, \n                    \"max_snd_wnd\": 0, \n                    \"mean_rtt\": 167246, \n                    \"min_rtt\": 94018, \n                    \"retransmits\": 284, \n                    \"seconds\": 10.001023, \n                    \"sender\": true, \n                    \"socket\": 5, \n                    \"start\": 0\n                }\n            }\n        ], \n        \"sum_received\": {\n            \"bits_per_second\": 12470332.571382252, \n            \"bytes\": 15807816, \n            \"end\": 10.141071, \n            \"seconds\": 10.141071, \n            \"sender\": true, \n            \"start\": 0\n        }, \n        \"sum_sent\": {\n            \"bits_per_second\": 14888256.131397758, \n            \"bytes\": 18612224, \n            \"end\": 10.001023, \n            \"retransmits\": 284, \n            \"seconds\": 10.001023, \n            \"sender\": true, \n            \"start\": 0\n        }\n    }, \n    \"intervals\": [\n        {\n            \"streams\": [\n                {\n                    \"bits_per_second\": 44033457.28004523, \n                    \"bytes\": 5505024, \n                    \"end\": 1.000153, \n                    \"omitted\": false, \n                    \"pmtu\": 1500, \n                    \"retransmits\": 273, \n                    \"rtt\": 195947, \n                    \"rttvar\": 1078, \n                    \"seconds\": 1.0001529455184937, \n                    \"sender\": true, \n                    \"snd_cwnd\": 367792, \n                    \"snd_wnd\": -1, \n                    \"socket\": 5, \n                    \"start\": 0\n                }\n            ], \n            \"sum\": {\n                \"bits_per_second\": 44033457.28004523, \n                \"bytes\": 5505024, \n                \"end\": 1.000153, \n                \"omitted\": false, \n                \"retransmits\": 273, \n                \"seconds\": 1.0001529455184937, \n                \"sender\": true, \n                \"start\": 0\n            }\n        }, \n        {\n            \"streams\": [\n                {\n                    \"bits_per_second\": 10486053.7582294, \n                    \"bytes\": 1310720, \n                    \"end\": 2.000125, \n                    \"omitted\": false, \n                    \"pmtu\": 1500, \n                    \"retransmits\": 0, \n                    \"rtt\": 94018, \n                    \"rttvar\": 6639, \n                    \"seconds\": 0.9999719858169556, \n                    \"sender\": true, \n                    \"snd_cwnd\": 207064, \n                    \"snd_wnd\": -1, \n                    \"socket\": 5, \n                    \"start\": 1.000153\n                }\n            ], \n            \"sum\": {\n                \"bits_per_second\": 10486053.7582294, \n                \"bytes\": 1310720, \n                \"end\": 2.000125, \n                \"omitted\": false, \n                \"retransmits\": 0, \n                \"seconds\": 0.9999719858169556, \n                \"sender\": true, \n                \"start\": 1.000153\n            }\n        }, \n        {\n            \"streams\": [\n                {\n                    \"bits_per_second\": 10476802.65824974, \n                    \"bytes\": 1310720, \n                    \"end\": 3.00098, \n                    \"omitted\": false, \n                    \"pmtu\": 1500, \n                    \"retransmits\": 0, \n                    \"rtt\": 146519, \n                    \"rttvar\": 961, \n                    \"seconds\": 1.0008549690246582, \n                    \"sender\": true, \n                    \"snd_cwnd\": 217200, \n                    \"snd_wnd\": -1, \n                    \"socket\": 5, \n                    \"start\": 2.000125\n                }\n            ], \n            \"sum\": {\n                \"bits_per_second\": 10476802.65824974, \n                \"bytes\": 1310720, \n                \"end\": 3.00098, \n                \"omitted\": false, \n                \"retransmits\": 0, \n                \"seconds\": 1.0008549690246582, \n                \"sender\": true, \n                \"start\": 2.000125\n            }\n        }, \n        {\n            \"streams\": [\n                {\n                    \"bits_per_second\": 20987134.116671342, \n                    \"bytes\": 2621440, \n                    \"end\": 4.000236, \n                    \"omitted\": false, \n                    \"pmtu\": 1500, \n                    \"retransmits\": 0, \n                    \"rtt\": 126752, \n                    \"rttvar\": 640, \n                    \"seconds\": 0.9992560148239136, \n                    \"sender\": true, \n                    \"snd_cwnd\": 238920, \n                    \"snd_wnd\": -1, \n                    \"socket\": 5, \n                    \"start\": 3.00098\n                }\n            ], \n            \"sum\": {\n                \"bits_per_second\": 20987134.116671342, \n                \"bytes\": 2621440, \n                \"end\": 4.000236, \n                \"omitted\": false, \n                \"retransmits\": 0, \n                \"seconds\": 0.9992560148239136, \n                \"sender\": true, \n                \"start\": 3.00098\n            }\n        }, \n        {\n            \"streams\": [\n                {\n                    \"bits_per_second\": 10485131.287699018, \n                    \"bytes\": 1310720, \n                    \"end\": 5.000296, \n                    \"omitted\": false, \n                    \"pmtu\": 1500, \n                    \"retransmits\": 0, \n                    \"rtt\": 162526, \n                    \"rttvar\": 947, \n                    \"seconds\": 1.000059962272644, \n                    \"sender\": true, \n                    \"snd_cwnd\": 273672, \n                    \"snd_wnd\": -1, \n                    \"socket\": 5, \n                    \"start\": 4.000236\n                }\n            ], \n            \"sum\": {\n                \"bits_per_second\": 10485131.287699018, \n                \"bytes\": 1310720, \n                \"end\": 5.000296, \n                \"omitted\": false, \n                \"retransmits\": 0, \n                \"seconds\": 1.000059962272644, \n                \"sender\": true, \n                \"start\": 4.000236\n            }\n        }, \n        {\n            \"streams\": [\n                {\n                    \"bits_per_second\": 10483694.157080453, \n                    \"bytes\": 1310720, \n                    \"end\": 6.000493, \n                    \"omitted\": false, \n                    \"pmtu\": 1500, \n                    \"retransmits\": 0, \n                    \"rtt\": 175402, \n                    \"rttvar\": 1540, \n                    \"seconds\": 1.0001970529556274, \n                    \"sender\": true, \n                    \"snd_cwnd\": 324352, \n                    \"snd_wnd\": -1, \n                    \"socket\": 5, \n                    \"start\": 5.000296\n                }\n            ], \n            \"sum\": {\n                \"bits_per_second\": 10483694.157080453, \n                \"bytes\": 1310720, \n                \"end\": 6.000493, \n                \"omitted\": false, \n                \"retransmits\": 0, \n                \"seconds\": 1.0001970529556274, \n                \"sender\": true, \n                \"start\": 5.000296\n            }\n        }, \n        {\n            \"streams\": [\n                {\n                    \"bits_per_second\": 20980395.0042525, \n                    \"bytes\": 2621440, \n                    \"end\": 7.00007, \n                    \"omitted\": false, \n                    \"pmtu\": 1500, \n                    \"retransmits\": 0, \n                    \"rtt\": 217572, \n                    \"rttvar\": 691, \n                    \"seconds\": 0.999576985836029, \n                    \"sender\": true, \n                    \"snd_cwnd\": 385168, \n                    \"snd_wnd\": -1, \n                    \"socket\": 5, \n                    \"start\": 6.000493\n                }\n            ], \n            \"sum\": {\n                \"bits_per_second\": 20980395.0042525, \n                \"bytes\": 2621440, \n                \"end\": 7.00007, \n                \"omitted\": false, \n                \"retransmits\": 0, \n                \"seconds\": 0.999576985836029, \n                \"sender\": true, \n                \"start\": 6.000493\n            }\n        }, \n        {\n            \"streams\": [\n                {\n                    \"bits_per_second\": 0, \n                    \"bytes\": 0, \n                    \"end\": 8.001058, \n                    \"omitted\": false, \n                    \"pmtu\": 1500, \n                    \"retransmits\": 11, \n                    \"rtt\": 220616, \n                    \"rttvar\": 14965, \n                    \"seconds\": 1.0009880065917969, \n                    \"sender\": true, \n                    \"snd_cwnd\": 205616, \n                    \"snd_wnd\": -1, \n                    \"socket\": 5, \n                    \"start\": 7.00007\n                }\n            ], \n            \"sum\": {\n                \"bits_per_second\": 0, \n                \"bytes\": 0, \n                \"end\": 8.001058, \n                \"omitted\": false, \n                \"retransmits\": 11, \n                \"seconds\": 1.0009880065917969, \n                \"sender\": true, \n                \"start\": 7.00007\n            }\n        }, \n        {\n            \"streams\": [\n                {\n                    \"bits_per_second\": 10486116.26210388, \n                    \"bytes\": 1310720, \n                    \"end\": 9.001024, \n                    \"omitted\": false, \n                    \"pmtu\": 1500, \n                    \"retransmits\": 0, \n                    \"rtt\": 153901, \n                    \"rttvar\": 1282, \n                    \"seconds\": 0.999966025352478, \n                    \"sender\": true, \n                    \"snd_cwnd\": 214304, \n                    \"snd_wnd\": -1, \n                    \"socket\": 5, \n                    \"start\": 8.001058\n                }\n            ], \n            \"sum\": {\n                \"bits_per_second\": 10486116.26210388, \n                \"bytes\": 1310720, \n                \"end\": 9.001024, \n                \"omitted\": false, \n                \"retransmits\": 0, \n                \"seconds\": 0.999966025352478, \n                \"sender\": true, \n                \"start\": 8.001058\n            }\n        }, \n        {\n            \"streams\": [\n                {\n                    \"bits_per_second\": 10485770.625010766, \n                    \"bytes\": 1310720, \n                    \"end\": 10.001023, \n                    \"omitted\": false, \n                    \"pmtu\": 1500, \n                    \"retransmits\": 0, \n                    \"rtt\": 179208, \n                    \"rttvar\": 1652, \n                    \"seconds\": 0.9999989867210388, \n                    \"sender\": true, \n                    \"snd_cwnd\": 222992, \n                    \"snd_wnd\": -1, \n                    \"socket\": 5, \n                    \"start\": 9.001024\n                }\n            ], \n            \"sum\": {\n                \"bits_per_second\": 10485770.625010766, \n                \"bytes\": 1310720, \n                \"end\": 10.001023, \n                \"omitted\": false, \n                \"retransmits\": 0, \n                \"seconds\": 0.9999989867210388, \n                \"sender\": true, \n                \"start\": 9.001024\n            }\n        }\n    ], \n    \"start\": {\n        \"connected\": [\n            {\n                \"local_host\": \"172.16.0.2\", \n                \"local_port\": 59969, \n                \"remote_host\": \"172.16.0.1\", \n                \"remote_port\": 5201, \n                \"socket\": 5\n            }\n        ], \n        \"connecting_to\": {\n            \"host\": \"172.16.0.1\", \n            \"port\": 5201\n        }, \n        \"cookie\": \"ac4s4xbijneucohillwdtfye235gikozdau7\", \n        \"fq_rate\": 0, \n        \"rcvbuf_actual\": 87380, \n        \"sndbuf_actual\": 65536, \n        \"sock_bufsize\": 0, \n        \"system_info\": \"REDACTED\", \n        \"target_bitrate\": 0, \n        \"tcp_mss_default\": 1448, \n        \"test_start\": {\n            \"bidir\": 0, \n            \"blksize\": 131072, \n            \"blocks\": 0, \n            \"bytes\": 0, \n            \"duration\": 10, \n            \"fqrate\": 0, \n            \"num_streams\": 1, \n            \"omit\": 0, \n            \"protocol\": \"TCP\", \n            \"reverse\": 0, \n            \"target_bitrate\": 0, \n            \"tos\": 0\n        }, \n        \"timestamp\": {\n            \"time\": \"Sat, 12 Oct 2024 02:30:18 GMT\", \n            \"timesecs\": 1728700218\n        }, \n        \"version\": \"iperf 3.14\"\n    }\n}\nParticipant 1:\n/usr/bin/iperf3 -s -1 --idle-timeout 10 --json -p 5201 -B 172.16.0.1 --authorized-users-path /var/run/pscheduler-server/runner/tmp/tmp_s4sk16p/tmpfi3m8zj2/credentials --rsa-private-key-path /var/run/pscheduler-server/runner/tmp/tmp_s4sk16p/tmpfi3m8zj2/private-key\n\n{\n    \"end\": {\n        \"cpu_utilization_percent\": {\n            \"host_system\": 0.5559259953902428, \n            \"host_total\": 0.709203283510326, \n            \"host_user\": 0.15328714898524795, \n            \"remote_system\": 0, \n            \"remote_total\": 0, \n            \"remote_user\": 0\n        }, \n        \"receiver_tcp_congestion\": \"htcp\", \n        \"streams\": [\n            {\n                \"receiver\": {\n                    \"bits_per_second\": 12470332.571382252, \n                    \"bytes\": 15807816, \n                    \"end\": 10.141071, \n                    \"seconds\": 10.141071, \n                    \"sender\": false, \n                    \"socket\": 5, \n                    \"start\": 0\n                }, \n                \"sender\": {\n                    \"bits_per_second\": 0, \n                    \"bytes\": 0, \n                    \"end\": 10.141071, \n                    \"seconds\": 10.141071, \n                    \"sender\": false, \n                    \"socket\": 5, \n                    \"start\": 0\n                }\n            }\n        ], \n        \"sum_received\": {\n            \"bits_per_second\": 12470332.571382252, \n            \"bytes\": 15807816, \n            \"end\": 10.141071, \n            \"seconds\": 10.141071, \n            \"sender\": false, \n            \"start\": 0\n        }, \n        \"sum_sent\": {\n            \"bits_per_second\": 0, \n            \"bytes\": 0, \n            \"end\": 10.141071, \n            \"seconds\": 10.141071, \n            \"sender\": false, \n            \"start\": 0\n        }\n    }, \n    \"intervals\": [\n        {\n            \"streams\": [\n                {\n                    \"bits_per_second\": 14791540.750811271, \n                    \"bytes\": 1849096, \n                    \"end\": 1.000083, \n                    \"omitted\": false, \n                    \"seconds\": 1.0000829696655273, \n                    \"sender\": false, \n                    \"socket\": 5, \n                    \"start\": 0\n                }\n            ], \n            \"sum\": {\n                \"bits_per_second\": 14791540.750811271, \n                \"bytes\": 1849096, \n                \"end\": 1.000083, \n                \"omitted\": false, \n                \"seconds\": 1.0000829696655273, \n                \"sender\": false, \n                \"start\": 0\n            }\n        }, \n        {\n            \"streams\": [\n                {\n                    \"bits_per_second\": 13425627.13429544, \n                    \"bytes\": 1678232, \n                    \"end\": 2.0001, \n                    \"omitted\": false, \n                    \"seconds\": 1.0000170469284058, \n                    \"sender\": false, \n                    \"socket\": 5, \n                    \"start\": 1.000083\n                }\n            ], \n            \"sum\": {\n                \"bits_per_second\": 13425627.13429544, \n                \"bytes\": 1678232, \n                \"end\": 2.0001, \n                \"omitted\": false, \n                \"seconds\": 1.0000170469284058, \n                \"sender\": false, \n                \"start\": 1.000083\n            }\n        }, \n        {\n            \"streams\": [\n                {\n                    \"bits_per_second\": 11526471.607810047, \n                    \"bytes\": 1440760, \n                    \"end\": 3.000066, \n                    \"omitted\": false, \n                    \"seconds\": 0.999966025352478, \n                    \"sender\": false, \n                    \"socket\": 5, \n                    \"start\": 2.0001\n                }\n            ], \n            \"sum\": {\n                \"bits_per_second\": 11526471.607810047, \n                \"bytes\": 1440760, \n                \"end\": 3.000066, \n                \"omitted\": false, \n                \"seconds\": 0.999966025352478, \n                \"sender\": false, \n                \"start\": 2.0001\n            }\n        }, \n        {\n            \"streams\": [\n                {\n                    \"bits_per_second\": 13577045.230159035, \n                    \"bytes\": 1697056, \n                    \"end\": 4.000022, \n                    \"omitted\": false, \n                    \"seconds\": 0.9999560117721558, \n                    \"sender\": false, \n                    \"socket\": 5, \n                    \"start\": 3.000066\n                }\n            ], \n            \"sum\": {\n                \"bits_per_second\": 13577045.230159035, \n                \"bytes\": 1697056, \n                \"end\": 4.000022, \n                \"omitted\": false, \n                \"seconds\": 0.9999560117721558, \n                \"sender\": false, \n                \"start\": 3.000066\n            }\n        }, \n        {\n            \"streams\": [\n                {\n                    \"bits_per_second\": 12197463.438880507, \n                    \"bytes\": 1524744, \n                    \"end\": 5.000062, \n                    \"omitted\": false, \n                    \"seconds\": 1.000040054321289, \n                    \"sender\": false, \n                    \"socket\": 5, \n                    \"start\": 4.000022\n                }\n            ], \n            \"sum\": {\n                \"bits_per_second\": 12197463.438880507, \n                \"bytes\": 1524744, \n                \"end\": 5.000062, \n                \"omitted\": false, \n                \"seconds\": 1.000040054321289, \n                \"sender\": false, \n                \"start\": 4.000022\n            }\n        }, \n        {\n            \"streams\": [\n                {\n                    \"bits_per_second\": 13854533.366741348, \n                    \"bytes\": 1731808, \n                    \"end\": 6.000057, \n                    \"omitted\": false, \n                    \"seconds\": 0.999994993209839, \n                    \"sender\": false, \n                    \"socket\": 5, \n                    \"start\": 5.000062\n                }\n            ], \n            \"sum\": {\n                \"bits_per_second\": 13854533.366741348, \n                \"bytes\": 1731808, \n                \"end\": 6.000057, \n                \"omitted\": false, \n                \"seconds\": 0.999994993209839, \n                \"sender\": false, \n                \"start\": 5.000062\n            }\n        }, \n        {\n            \"streams\": [\n                {\n                    \"bits_per_second\": 14480535.98957357, \n                    \"bytes\": 1810000, \n                    \"end\": 7.00002, \n                    \"omitted\": false, \n                    \"seconds\": 0.9999629855155945, \n                    \"sender\": false, \n                    \"socket\": 5, \n                    \"start\": 6.000057\n                }\n            ], \n            \"sum\": {\n                \"bits_per_second\": 14480535.98957357, \n                \"bytes\": 1810000, \n                \"end\": 7.00002, \n                \"omitted\": false, \n                \"seconds\": 0.9999629855155945, \n                \"sender\": false, \n                \"start\": 6.000057\n            }\n        }, \n        {\n            \"streams\": [\n                {\n                    \"bits_per_second\": 8966016, \n                    \"bytes\": 1120752, \n                    \"end\": 8.00002, \n                    \"omitted\": false, \n                    \"seconds\": 1, \n                    \"sender\": false, \n                    \"socket\": 5, \n                    \"start\": 7.00002\n                }\n            ], \n            \"sum\": {\n                \"bits_per_second\": 8966016, \n                \"bytes\": 1120752, \n                \"end\": 8.00002, \n                \"omitted\": false, \n                \"seconds\": 1, \n                \"sender\": false, \n                \"start\": 7.00002\n            }\n        }, \n        {\n            \"streams\": [\n                {\n                    \"bits_per_second\": 11201224.595660143, \n                    \"bytes\": 1400216, \n                    \"end\": 9.000065, \n                    \"omitted\": false, \n                    \"seconds\": 1.0000449419021606, \n                    \"sender\": false, \n                    \"socket\": 5, \n                    \"start\": 8.00002\n                }\n            ], \n            \"sum\": {\n                \"bits_per_second\": 11201224.595660143, \n                \"bytes\": 1400216, \n                \"end\": 9.000065, \n                \"omitted\": false, \n                \"seconds\": 1.0000449419021606, \n                \"sender\": false, \n                \"start\": 8.00002\n            }\n        }, \n        {\n            \"streams\": [\n                {\n                    \"bits_per_second\": 10726762.261594957, \n                    \"bytes\": 1340848, \n                    \"end\": 10.000067, \n                    \"omitted\": false, \n                    \"seconds\": 1.0000020265579224, \n                    \"sender\": false, \n                    \"socket\": 5, \n                    \"start\": 9.000065\n                }\n            ], \n            \"sum\": {\n                \"bits_per_second\": 10726762.261594957, \n                \"bytes\": 1340848, \n                \"end\": 10.000067, \n                \"omitted\": false, \n                \"seconds\": 1.0000020265579224, \n                \"sender\": false, \n                \"start\": 9.000065\n            }\n        }, \n        {\n            \"streams\": [\n                {\n                    \"bits_per_second\": 12158747.60296231, \n                    \"bytes\": 214304, \n                    \"end\": 10.141071, \n                    \"omitted\": false, \n                    \"seconds\": 0.14100399613380432, \n                    \"sender\": false, \n                    \"socket\": 5, \n                    \"start\": 10.000067\n                }\n            ], \n            \"sum\": {\n                \"bits_per_second\": 12158747.60296231, \n                \"bytes\": 214304, \n                \"end\": 10.141071, \n                \"omitted\": false, \n                \"seconds\": 0.14100399613380432, \n                \"sender\": false, \n                \"start\": 10.000067\n            }\n        }\n    ], \n    \"start\": {\n        \"accepted_connection\": {\n            \"host\": \"172.16.0.2\", \n            \"port\": 36823\n        }, \n        \"connected\": [\n            {\n                \"local_host\": \"172.16.0.1\", \n                \"local_port\": 5201, \n                \"remote_host\": \"172.16.0.2\", \n                \"remote_port\": 59969, \n                \"socket\": 5\n            }\n        ], \n        \"cookie\": \"ac4s4xbijneucohillwdtfye235gikozdau7\", \n        \"fq_rate\": 0, \n        \"rcvbuf_actual\": 87380, \n        \"sndbuf_actual\": 65536, \n        \"sock_bufsize\": 0, \n        \"system_info\": \"REDACTED\", \n        \"target_bitrate\": 0, \n        \"tcp_mss_default\": 0, \n        \"test_start\": {\n            \"bidir\": 0, \n            \"blksize\": 131072, \n            \"blocks\": 0, \n            \"bytes\": 0, \n            \"duration\": 10, \n            \"fqrate\": 0, \n            \"num_streams\": 1, \n            \"omit\": 0, \n            \"protocol\": \"TCP\", \n            \"reverse\": 0, \n            \"target_bitrate\": 0, \n            \"tos\": 0\n        }, \n        \"timestamp\": {\n            \"time\": \"Sat, 12 Oct 2024 02:30:18 GMT\", \n            \"timesecs\": 1728700218\n        }, \n        \"version\": \"iperf 3.14\"\n    }\n}\n","summary":{"streams":[{"end":10.001023,"rtt":167246,"start":0,"stream-id":5,"retransmits":284,"throughput-bits":14888256.131397758,"throughput-bytes":18612224}],"summary":{"end":10.001023,"start":0,"retransmits":284,"throughput-bits":14888256.131397758,"throughput-bytes":18612224,"receiver-throughput-bits":12470332.571382252}},"intervals":[{"streams":[{"end":1.000153,"rtt":195947,"start":0,"omitted":false,"stream-id":5,"retransmits":273,"tcp-window-size":367792,"throughput-bits":44033457.28004523,"throughput-bytes":5505024}],"summary":{"end":1.000153,"start":0,"omitted":false,"retransmits":273,"throughput-bits":44033457.28004523,"throughput-bytes":5505024}},{"streams":[{"end":2.000125,"rtt":94018,"start":1.000153,"omitted":false,"stream-id":5,"retransmits":0,"tcp-window-size":207064,"throughput-bits":10486053.7582294,"throughput-bytes":1310720}],"summary":{"end":2.000125,"start":1.000153,"omitted":false,"retransmits":0,"throughput-bits":10486053.7582294,"throughput-bytes":1310720}},{"streams":[{"end":3.00098,"rtt":146519,"start":2.000125,"omitted":false,"stream-id":5,"retransmits":0,"tcp-window-size":217200,"throughput-bits":10476802.65824974,"throughput-bytes":1310720}],"summary":{"end":3.00098,"start":2.000125,"omitted":false,"retransmits":0,"throughput-bits":10476802.65824974,"throughput-bytes":1310720}},{"streams":[{"end":4.000236,"rtt":126752,"start":3.00098,"omitted":false,"stream-id":5,"retransmits":0,"tcp-window-size":238920,"throughput-bits":20987134.116671342,"throughput-bytes":2621440}],"summary":{"end":4.000236,"start":3.00098,"omitted":false,"retransmits":0,"throughput-bits":20987134.116671342,"throughput-bytes":2621440}},{"streams":[{"end":5.000296,"rtt":162526,"start":4.000236,"omitted":false,"stream-id":5,"retransmits":0,"tcp-window-size":273672,"throughput-bits":10485131.287699018,"throughput-bytes":1310720}],"summary":{"end":5.000296,"start":4.000236,"omitted":false,"retransmits":0,"throughput-bits":10485131.287699018,"throughput-bytes":1310720}},{"streams":[{"end":6.000493,"rtt":175402,"start":5.000296,"omitted":false,"stream-id":5,"retransmits":0,"tcp-window-size":324352,"throughput-bits":10483694.157080453,"throughput-bytes":1310720}],"summary":{"end":6.000493,"start":5.000296,"omitted":false,"retransmits":0,"throughput-bits":10483694.157080453,"throughput-bytes":1310720}},{"streams":[{"end":7.00007,"rtt":217572,"start":6.000493,"omitted":false,"stream-id":5,"retransmits":0,"tcp-window-size":385168,"throughput-bits":20980395.0042525,"throughput-bytes":2621440}],"summary":{"end":7.00007,"start":6.000493,"omitted":false,"retransmits":0,"throughput-bits":20980395.0042525,"throughput-bytes":2621440}},{"streams":[{"end":8.001058,"rtt":220616,"start":7.00007,"omitted":false,"stream-id":5,"retransmits":11,"tcp-window-size":205616,"throughput-bits":0,"throughput-bytes":0}],"summary":{"end":8.001058,"start":7.00007,"omitted":false,"retransmits":11,"throughput-bits":0,"throughput-bytes":0}},{"streams":[{"end":9.001024,"rtt":153901,"start":8.001058,"omitted":false,"stream-id":5,"retransmits":0,"tcp-window-size":214304,"throughput-bits":10486116.26210388,"throughput-bytes":1310720}],"summary":{"end":9.001024,"start":8.001058,"omitted":false,"retransmits":0,"throughput-bits":10486116.26210388,"throughput-bytes":1310720}},{"streams":[{"end":10.001023,"rtt":179208,"start":9.001024,"omitted":false,"stream-id":5,"retransmits":0,"tcp-window-size":222992,"throughput-bits":10485770.625010766,"throughput-bytes":1310720}],"summary":{"end":10.001023,"start":9.001024,"omitted":false,"retransmits":0,"throughput-bits":10485770.625010766,"throughput-bytes":1310720}}],"succeeded":true}
