{"diags":"Participant 0:\n/usr/bin/iperf3 -p 5201 -c 172.16.0.1 -t 10 --json --rsa-public-key-path /var/run/pscheduler-server/runner/tmp/tmplgeolrgy/tmpg1b_193h/public-key --username 2OVFb247GUn6ujXRw7FS\n\n{\n    \"end\": {\n        \"cpu_utilization_percent\": {\n            \"host_system\": 0.18258371348919725, \n            \"host_total\": 0.20263099537477033, \n            \"host_user\": 0.020037381993283913, \n            \"remote_system\": 0.02015074897433451, \n            \"remote_total\": 0.0302452056101517, \n            \"remote_user\": 0.010075374487167254\n        }, \n        \"receiver_tcp_congestion\": \"htcp\", \n        \"sender_tcp_congestion\": \"htcp\", \n        \"streams\": [\n            {\n                \"receiver\": {\n                    \"bits_per_second\": 162470.9079079827, \n                    \"bytes\": 212856, \n                    \"end\": 10.480941, \n                    \"seconds\": 10.000053, \n                    \"sender\": true, \n                    \"socket\": 5, \n                    \"start\": 0\n                }, \n                \"sender\": {\n                    \"bits_per_second\": 922081.5129679813, \n                    \"bytes\": 1152608, \n                    \"end\": 10.000053, \n                    \"max_rtt\": 39943, \n                    \"max_snd_cwnd\": 1448, \n                    \"max_snd_wnd\": 0, \n                    \"mean_rtt\": 39943, \n                    \"min_rtt\": 39943, \n                    \"retransmits\": 5, \n                    \"seconds\": 10.000053, \n                    \"sender\": true, \n                    \"socket\": 5, \n                    \"start\": 0\n                }\n            }\n        ], \n        \"sum_received\": {\n            \"bits_per_second\": 162470.9079079827, \n            \"bytes\": 212856, \n            \"end\": 10.480941, \n            \"seconds\": 10.480941, \n            \"sender\": true, \n            \"start\": 0\n        }, \n        \"sum_sent\": {\n            \"bits_per_second\": 922081.5129679813, \n            \"bytes\": 1152608, \n            \"end\": 10.000053, \n            \"retransmits\": 5, \n            \"seconds\": 10.000053, \n            \"sender\": true, \n            \"start\": 0\n        }\n    }, \n    \"intervals\": [\n        {\n            \"streams\": [\n                {\n                    \"bits_per_second\": 9220292.44485386, \n                    \"bytes\": 1152608, \n                    \"end\": 1.000062, \n                    \"omitted\": false, \n                    \"pmtu\": 1500, \n                    \"retransmits\": 2, \n                    \"rtt\": 39943, \n                    \"rttvar\": 574, \n                    \"seconds\": 1.0000619888305664, \n                    \"sender\": true, \n                    \"snd_cwnd\": 1448, \n                    \"snd_wnd\": -1, \n                    \"socket\": 5, \n                    \"start\": 0\n                }\n            ], \n            \"sum\": {\n                \"bits_per_second\": 9220292.44485386, \n                \"bytes\": 1152608, \n                \"end\": 1.000062, \n                \"omitted\": false, \n                \"retransmits\": 2, \n                \"seconds\": 1.0000619888305664, \n                \"sender\": true, \n                \"start\": 0\n            }\n        }, \n        {\n            \"streams\": [\n                {\n                    \"bits_per_second\": 0, \n                    \"bytes\": 0, \n                    \"end\": 2.000093, \n                    \"omitted\": false, \n                    \"pmtu\": 1500, \n                    \"retransmits\": 1, \n                    \"rtt\": 39943, \n                    \"rttvar\": 574, \n                    \"seconds\": 1.0000309944152832, \n                    \"sender\": true, \n                    \"snd_cwnd\": 1448, \n                    \"snd_wnd\": -1, \n                    \"socket\": 5, \n                    \"start\": 1.000062\n                }\n            ], \n            \"sum\": {\n                \"bits_per_second\": 0, \n                \"bytes\": 0, \n                \"end\": 2.000093, \n                \"omitted\": false, \n                \"retransmits\": 1, \n                \"seconds\": 1.0000309944152832, \n                \"sender\": true, \n                \"start\": 1.000062\n            }\n        }, \n        {\n            \"streams\": [\n                {\n                    \"bits_per_second\": 0, \n                    \"bytes\": 0, \n                    \"end\": 3.000101, \n                    \"omitted\": false, \n                    \"pmtu\": 1500, \n                    \"retransmits\": 0, \n                    \"rtt\": 39943, \n                    \"rttvar\": 574, \n                    \"seconds\": 1.0000079870224, \n                    \"sender\": true, \n                    \"snd_cwnd\": 1448, \n                    \"snd_wnd\": -1, \n                    \"socket\": 5, \n                    \"start\": 2.000093\n                }\n            ], \n            \"sum\": {\n                \"bits_per_second\": 0, \n                \"bytes\": 0, \n                \"end\": 3.000101, \n                \"omitted\": false, \n                \"retransmits\": 0, \n                \"seconds\": 1.0000079870224, \n                \"sender\": true, \n                \"start\": 2.000093\n            }\n        }, \n        {\n            \"streams\": [\n                {\n                    \"bits_per_second\": 0, \n                    \"bytes\": 0, \n                    \"end\": 4.00012, \n                    \"omitted\": false, \n                    \"pmtu\": 1500, \n                    \"retransmits\": 1, \n                    \"rtt\": 39943, \n                    \"rttvar\": 574, \n                    \"seconds\": 1.0000189542770386, \n                    \"sender\": true, \n                    \"snd_cwnd\": 1024, \n                    \"snd_wnd\": -1, \n                    \"socket\": 5, \n                    \"start\": 3.000101\n                }\n            ], \n            \"sum\": {\n                \"bits_per_second\": 0, \n                \"bytes\": 0, \n                \"end\": 4.00012, \n                \"omitted\": false, \n                \"retransmits\": 1, \n                \"seconds\": 1.0000189542770386, \n                \"sender\": true, \n                \"start\": 3.000101\n            }\n        }, \n        {\n            \"streams\": [\n                {\n                    \"bits_per_second\": 0, \n                    \"bytes\": 0, \n                    \"end\": 5.000037, \n                    \"omitted\": false, \n                    \"pmtu\": 1500, \n                    \"retransmits\": 0, \n                    \"rtt\": 39943, \n                    \"rttvar\": 574, \n                    \"seconds\": 0.999916970729828, \n                    \"sender\": true, \n                    \"snd_cwnd\": 1024, \n                    \"snd_wnd\": -1, \n                    \"socket\": 5, \n                    \"start\": 4.00012\n                }\n            ], \n            \"sum\": {\n                \"bits_per_second\": 0, \n                \"bytes\": 0, \n                \"end\": 5.000037, \n                \"omitted\": false, \n                \"retransmits\": 0, \n                \"seconds\": 0.999916970729828, \n                \"sender\": true, \n                \"start\": 4.00012\n            }\n        }, \n        {\n            \"streams\": [\n                {\n                    \"bits_per_second\": 0, \n                    \"bytes\": 0, \n                    \"end\": 6.000117, \n                    \"omitted\": false, \n                    \"pmtu\": 1500, \n                    \"retransmits\": 0, \n                    \"rtt\": 39943, \n                    \"rttvar\": 574, \n                    \"seconds\": 1.0000799894332886, \n                    \"sender\": true, \n                    \"snd_cwnd\": 1024, \n                    \"snd_wnd\": -1, \n                    \"socket\": 5, \n                    \"start\": 5.000037\n                }\n            ], \n            \"sum\": {\n                \"bits_per_second\": 0, \n                \"bytes\": 0, \n                \"end\": 6.000117, \n                \"omitted\": false, \n                \"retransmits\": 0, \n                \"seconds\": 1.0000799894332886, \n                \"sender\": true, \n                \"start\": 5.000037\n            }\n        }, \n        {\n            \"streams\": [\n                {\n                    \"bits_per_second\": 0, \n                    \"bytes\": 0, \n                    \"end\": 7.000083, \n                    \"omitted\": false, \n                    \"pmtu\": 1500, \n                    \"retransmits\": 0, \n                    \"rtt\": 39943, \n                    \"rttvar\": 574, \n                    \"seconds\": 0.999966025352478, \n                    \"sender\": true, \n                    \"snd_cwnd\": 1024, \n                    \"snd_wnd\": -1, \n                    \"socket\": 5, \n                    \"start\": 6.000117\n                }\n            ], \n            \"sum\": {\n                \"bits_per_second\": 0, \n                \"bytes\": 0, \n                \"end\": 7.000083, \n                \"omitted\": false, \n                \"retransmits\": 0, \n                \"seconds\": 0.999966025352478, \n                \"sender\": true, \n                \"start\": 6.000117\n            }\n        }, \n        {\n            \"streams\": [\n                {\n                    \"bits_per_second\": 0, \n                    \"bytes\": 0, \n                    \"end\": 8.000074, \n                    \"omitted\": false, \n                    \"pmtu\": 1500, \n                    \"retransmits\": 1, \n                    \"rtt\": 39943, \n                    \"rttvar\": 574, \n                    \"seconds\": 0.999990999698639, \n                    \"sender\": true, \n                    \"snd_cwnd\": 512, \n                    \"snd_wnd\": -1, \n                    \"socket\": 5, \n                    \"start\": 7.000083\n                }\n            ], \n            \"sum\": {\n                \"bits_per_second\": 0, \n                \"bytes\": 0, \n                \"end\": 8.000074, \n                \"omitted\": false, \n                \"retransmits\": 1, \n                \"seconds\": 0.999990999698639, \n                \"sender\": true, \n                \"start\": 7.000083\n            }\n        }, \n        {\n            \"streams\": [\n                {\n                    \"bits_per_second\": 0, \n                    \"bytes\": 0, \n                    \"end\": 9.000058, \n                    \"omitted\": false, \n                    \"pmtu\": 1500, \n                    \"retransmits\": 0, \n                    \"rtt\": 39943, \n                    \"rttvar\": 574, \n                    \"seconds\": 0.9999840259552002, \n                    \"sender\": true, \n                    \"snd_cwnd\": 512, \n                    \"snd_wnd\": -1, \n                    \"socket\": 5, \n                    \"start\": 8.000074\n                }\n            ], \n            \"sum\": {\n                \"bits_per_second\": 0, \n                \"bytes\": 0, \n                \"end\": 9.000058, \n                \"omitted\": false, \n                \"retransmits\": 0, \n                \"seconds\": 0.9999840259552002, \n                \"sender\": true, \n                \"start\": 8.000074\n            }\n        }, \n        {\n            \"streams\": [\n                {\n                    \"bits_per_second\": 0, \n                    \"bytes\": 0, \n                    \"end\": 10.000053, \n                    \"omitted\": false, \n                    \"pmtu\": 1500, \n                    \"retransmits\": 0, \n                    \"rtt\": 39943, \n                    \"rttvar\": 574, \n                    \"seconds\": 0.999994993209839, \n                    \"sender\": true, \n                    \"snd_cwnd\": 512, \n                    \"snd_wnd\": -1, \n                    \"socket\": 5, \n                    \"start\": 9.000058\n                }\n            ], \n            \"sum\": {\n                \"bits_per_second\": 0, \n                \"bytes\": 0, \n                \"end\": 10.000053, \n                \"omitted\": false, \n                \"retransmits\": 0, \n                \"seconds\": 0.999994993209839, \n                \"sender\": true, \n                \"start\": 9.000058\n            }\n        }\n    ], \n    \"start\": {\n        \"connected\": [\n            {\n                \"local_host\": \"172.16.0.2\", \n                \"local_port\": 44668, \n                \"remote_host\": \"172.16.0.1\", \n                \"remote_port\": 5201, \n                \"socket\": 5\n            }\n        ], \n        \"connecting_to\": {\n            \"host\": \"172.16.0.1\", \n            \"port\": 5201\n        }, \n        \"cookie\": \"syutg5nx2v2vdlvgod6bvdfiif4ij7uluiew\", \n        \"fq_rate\": 0, \n        \"rcvbuf_actual\": 87380, \n        \"sndbuf_actual\": 65536, \n        \"sock_bufsize\": 0, \n        \"system_info\": \"REDACTED\", \n        \"target_bitrate\": 0, \n        \"tcp_mss_default\": 1448, \n        \"test_start\": {\n            \"bidir\": 0, \n            \"blksize\": 131072, \n            \"blocks\": 0, \n            \"bytes\": 0, \n            \"duration\": 10, \n            \"fqrate\": 0, \n            \"num_streams\": 1, \n            \"omit\": 0, \n            \"protocol\": \"TCP\", \n            \"reverse\": 0, \n            \"target_bitrate\": 0, \n            \"tos\": 0\n        }, \n        \"timestamp\": {\n            \"time\": \"Wed, 04 Sep 2024 22:15:32 GMT\", \n            \"timesecs\": 1725488132\n        }, \n        \"version\": \"iperf 3.14\"\n    }\n}\nParticipant 1:\n/usr/bin/iperf3 -s -1 --idle-timeout 10 --json -p 5201 --authorized-users-path /var/run/pscheduler-server/runner/tmp/tmpjl71_wix/tmp30gq8p36/credentials --rsa-private-key-path /var/run/pscheduler-server/runner/tmp/tmpjl71_wix/tmp30gq8p36/private-key\n\n{\n    \"end\": {\n        \"cpu_utilization_percent\": {\n            \"host_system\": 0.02015074897433451, \n            \"host_total\": 0.0302452056101517, \n            \"host_user\": 0.010075374487167254, \n            \"remote_system\": 0, \n            \"remote_total\": 0, \n            \"remote_user\": 0\n        }, \n        \"receiver_tcp_congestion\": \"htcp\", \n        \"streams\": [\n            {\n                \"receiver\": {\n                    \"bits_per_second\": 162470.9079079827, \n                    \"bytes\": 212856, \n                    \"end\": 10.480941, \n                    \"seconds\": 10.480941, \n                    \"sender\": false, \n                    \"socket\": 5, \n                    \"start\": 0\n                }, \n                \"sender\": {\n                    \"bits_per_second\": 0, \n                    \"bytes\": 0, \n                    \"end\": 10.480941, \n                    \"seconds\": 10.480941, \n                    \"sender\": false, \n                    \"socket\": 5, \n                    \"start\": 0\n                }\n            }\n        ], \n        \"sum_received\": {\n            \"bits_per_second\": 162470.9079079827, \n            \"bytes\": 212856, \n            \"end\": 10.480941, \n            \"seconds\": 10.480941, \n            \"sender\": false, \n            \"start\": 0\n        }, \n        \"sum_sent\": {\n            \"bits_per_second\": 0, \n            \"bytes\": 0, \n            \"end\": 10.480941, \n            \"seconds\": 10.480941, \n            \"sender\": false, \n            \"start\": 0\n        }\n    }, \n    \"intervals\": [\n        {\n            \"streams\": [\n                {\n                    \"bits_per_second\": 1701264.0813718422, \n                    \"bytes\": 212856, \n                    \"end\": 1.000931, \n                    \"omitted\": false, \n                    \"seconds\": 1.0009310245513916, \n                    \"sender\": false, \n                    \"socket\": 5, \n                    \"start\": 0\n                }\n            ], \n            \"sum\": {\n                \"bits_per_second\": 1701264.0813718422, \n                \"bytes\": 212856, \n                \"end\": 1.000931, \n                \"omitted\": false, \n                \"seconds\": 1.0009310245513916, \n                \"sender\": false, \n                \"start\": 0\n            }\n        }, \n        {\n            \"streams\": [\n                {\n                    \"bits_per_second\": 0, \n                    \"bytes\": 0, \n                    \"end\": 2.001057, \n                    \"omitted\": false, \n                    \"seconds\": 1.0001260042190552, \n                    \"sender\": false, \n                    \"socket\": 5, \n                    \"start\": 1.000931\n                }\n            ], \n            \"sum\": {\n                \"bits_per_second\": 0, \n                \"bytes\": 0, \n                \"end\": 2.001057, \n                \"omitted\": false, \n                \"seconds\": 1.0001260042190552, \n                \"sender\": false, \n                \"start\": 1.000931\n            }\n        }, \n        {\n            \"streams\": [\n                {\n                    \"bits_per_second\": 0, \n                    \"bytes\": 0, \n                    \"end\": 3.001071, \n                    \"omitted\": false, \n                    \"seconds\": 1.0000139474868774, \n                    \"sender\": false, \n                    \"socket\": 5, \n                    \"start\": 2.001057\n                }\n            ], \n            \"sum\": {\n                \"bits_per_second\": 0, \n                \"bytes\": 0, \n                \"end\": 3.001071, \n                \"omitted\": false, \n                \"seconds\": 1.0000139474868774, \n                \"sender\": false, \n                \"start\": 2.001057\n            }\n        }, \n        {\n            \"streams\": [\n                {\n                    \"bits_per_second\": 0, \n                    \"bytes\": 0, \n                    \"end\": 4.001073, \n                    \"omitted\": false, \n                    \"seconds\": 1.0000020265579224, \n                    \"sender\": false, \n                    \"socket\": 5, \n                    \"start\": 3.001071\n                }\n            ], \n            \"sum\": {\n                \"bits_per_second\": 0, \n                \"bytes\": 0, \n                \"end\": 4.001073, \n                \"omitted\": false, \n                \"seconds\": 1.0000020265579224, \n                \"sender\": false, \n                \"start\": 3.001071\n            }\n        }, \n        {\n            \"streams\": [\n                {\n                    \"bits_per_second\": 0, \n                    \"bytes\": 0, \n                    \"end\": 5.001066, \n                    \"omitted\": false, \n                    \"seconds\": 0.9999930262565613, \n                    \"sender\": false, \n                    \"socket\": 5, \n                    \"start\": 4.001073\n                }\n            ], \n            \"sum\": {\n                \"bits_per_second\": 0, \n                \"bytes\": 0, \n                \"end\": 5.001066, \n                \"omitted\": false, \n                \"seconds\": 0.9999930262565613, \n                \"sender\": false, \n                \"start\": 4.001073\n            }\n        }, \n        {\n            \"streams\": [\n                {\n                    \"bits_per_second\": 0, \n                    \"bytes\": 0, \n                    \"end\": 6.001113, \n                    \"omitted\": false, \n                    \"seconds\": 1.000046968460083, \n                    \"sender\": false, \n                    \"socket\": 5, \n                    \"start\": 5.001066\n                }\n            ], \n            \"sum\": {\n                \"bits_per_second\": 0, \n                \"bytes\": 0, \n                \"end\": 6.001113, \n                \"omitted\": false, \n                \"seconds\": 1.000046968460083, \n                \"sender\": false, \n                \"start\": 5.001066\n            }\n        }, \n        {\n            \"streams\": [\n                {\n                    \"bits_per_second\": 0, \n                    \"bytes\": 0, \n                    \"end\": 7.001054, \n                    \"omitted\": false, \n                    \"seconds\": 0.9999409914016724, \n                    \"sender\": false, \n                    \"socket\": 5, \n                    \"start\": 6.001113\n                }\n            ], \n            \"sum\": {\n                \"bits_per_second\": 0, \n                \"bytes\": 0, \n                \"end\": 7.001054, \n                \"omitted\": false, \n                \"seconds\": 0.9999409914016724, \n                \"sender\": false, \n                \"start\": 6.001113\n            }\n        }, \n        {\n            \"streams\": [\n                {\n                    \"bits_per_second\": 0, \n                    \"bytes\": 0, \n                    \"end\": 8.001057, \n                    \"omitted\": false, \n                    \"seconds\": 1.0000029802322388, \n                    \"sender\": false, \n                    \"socket\": 5, \n                    \"start\": 7.001054\n                }\n            ], \n            \"sum\": {\n                \"bits_per_second\": 0, \n                \"bytes\": 0, \n                \"end\": 8.001057, \n                \"omitted\": false, \n                \"seconds\": 1.0000029802322388, \n                \"sender\": false, \n                \"start\": 7.001054\n            }\n        }, \n        {\n            \"streams\": [\n                {\n                    \"bits_per_second\": 0, \n                    \"bytes\": 0, \n                    \"end\": 9.001089, \n                    \"omitted\": false, \n                    \"seconds\": 1.0000319480895996, \n                    \"sender\": false, \n                    \"socket\": 5, \n                    \"start\": 8.001057\n                }\n            ], \n            \"sum\": {\n                \"bits_per_second\": 0, \n                \"bytes\": 0, \n                \"end\": 9.001089, \n                \"omitted\": false, \n                \"seconds\": 1.0000319480895996, \n                \"sender\": false, \n                \"start\": 8.001057\n            }\n        }, \n        {\n            \"streams\": [\n                {\n                    \"bits_per_second\": 0, \n                    \"bytes\": 0, \n                    \"end\": 10.001064, \n                    \"omitted\": false, \n                    \"seconds\": 0.999975025653839, \n                    \"sender\": false, \n                    \"socket\": 5, \n                    \"start\": 9.001089\n                }\n            ], \n            \"sum\": {\n                \"bits_per_second\": 0, \n                \"bytes\": 0, \n                \"end\": 10.001064, \n                \"omitted\": false, \n                \"seconds\": 0.999975025653839, \n                \"sender\": false, \n                \"start\": 9.001089\n            }\n        }, \n        {\n            \"streams\": [\n                {\n                    \"bits_per_second\": 0, \n                    \"bytes\": 0, \n                    \"end\": 10.480941, \n                    \"omitted\": false, \n                    \"seconds\": 0.47987699508667, \n                    \"sender\": false, \n                    \"socket\": 5, \n                    \"start\": 10.001064\n                }\n            ], \n            \"sum\": {\n                \"bits_per_second\": 0, \n                \"bytes\": 0, \n                \"end\": 10.480941, \n                \"omitted\": false, \n                \"seconds\": 0.47987699508667, \n                \"sender\": false, \n                \"start\": 10.001064\n            }\n        }\n    ], \n    \"start\": {\n        \"accepted_connection\": {\n            \"host\": \"172.16.0.2\", \n            \"port\": 44664\n        }, \n        \"connected\": [\n            {\n                \"local_host\": \"172.16.0.1\", \n                \"local_port\": 5201, \n                \"remote_host\": \"172.16.0.2\", \n                \"remote_port\": 44668, \n                \"socket\": 5\n            }\n        ], \n        \"cookie\": \"syutg5nx2v2vdlvgod6bvdfiif4ij7uluiew\", \n        \"fq_rate\": 0, \n        \"rcvbuf_actual\": 87380, \n        \"sndbuf_actual\": 65536, \n        \"sock_bufsize\": 0, \n        \"system_info\": \"REDACTED\", \n        \"target_bitrate\": 0, \n        \"tcp_mss_default\": 0, \n        \"test_start\": {\n            \"bidir\": 0, \n            \"blksize\": 131072, \n            \"blocks\": 0, \n            \"bytes\": 0, \n            \"duration\": 10, \n            \"fqrate\": 0, \n            \"num_streams\": 1, \n            \"omit\": 0, \n            \"protocol\": \"TCP\", \n            \"reverse\": 0, \n            \"target_bitrate\": 0, \n            \"tos\": 0\n        }, \n        \"timestamp\": {\n            \"time\": \"Wed, 04 Sep 2024 22:15:32 GMT\", \n            \"timesecs\": 1725488132\n        }, \n        \"version\": \"iperf 3.14\"\n    }\n}\n","summary":{"streams":[{"end":10.000053,"rtt":39943,"start":0,"stream-id":5,"retransmits":5,"throughput-bits":922081.5129679813,"throughput-bytes":1152608}],"summary":{"end":10.000053,"start":0,"retransmits":5,"throughput-bits":922081.5129679813,"throughput-bytes":1152608,"receiver-throughput-bits":162470.9079079827}},"intervals":[{"streams":[{"end":1.000062,"rtt":39943,"start":0,"omitted":false,"stream-id":5,"retransmits":2,"tcp-window-size":1448,"throughput-bits":9220292.44485386,"throughput-bytes":1152608}],"summary":{"end":1.000062,"start":0,"omitted":false,"retransmits":2,"throughput-bits":9220292.44485386,"throughput-bytes":1152608}},{"streams":[{"end":2.000093,"rtt":39943,"start":1.000062,"omitted":false,"stream-id":5,"retransmits":1,"tcp-window-size":1448,"throughput-bits":0,"throughput-bytes":0}],"summary":{"end":2.000093,"start":1.000062,"omitted":false,"retransmits":1,"throughput-bits":0,"throughput-bytes":0}},{"streams":[{"end":3.000101,"rtt":39943,"start":2.000093,"omitted":false,"stream-id":5,"retransmits":0,"tcp-window-size":1448,"throughput-bits":0,"throughput-bytes":0}],"summary":{"end":3.000101,"start":2.000093,"omitted":false,"retransmits":0,"throughput-bits":0,"throughput-bytes":0}},{"streams":[{"end":4.00012,"rtt":39943,"start":3.000101,"omitted":false,"stream-id":5,"retransmits":1,"tcp-window-size":1024,"throughput-bits":0,"throughput-bytes":0}],"summary":{"end":4.00012,"start":3.000101,"omitted":false,"retransmits":1,"throughput-bits":0,"throughput-bytes":0}},{"streams":[{"end":5.000037,"rtt":39943,"start":4.00012,"omitted":false,"stream-id":5,"retransmits":0,"tcp-window-size":1024,"throughput-bits":0,"throughput-bytes":0}],"summary":{"end":5.000037,"start":4.00012,"omitted":false,"retransmits":0,"throughput-bits":0,"throughput-bytes":0}},{"streams":[{"end":6.000117,"rtt":39943,"start":5.000037,"omitted":false,"stream-id":5,"retransmits":0,"tcp-window-size":1024,"throughput-bits":0,"throughput-bytes":0}],"summary":{"end":6.000117,"start":5.000037,"omitted":false,"retransmits":0,"throughput-bits":0,"throughput-bytes":0}},{"streams":[{"end":7.000083,"rtt":39943,"start":6.000117,"omitted":false,"stream-id":5,"retransmits":0,"tcp-window-size":1024,"throughput-bits":0,"throughput-bytes":0}],"summary":{"end":7.000083,"start":6.000117,"omitted":false,"retransmits":0,"throughput-bits":0,"throughput-bytes":0}},{"streams":[{"end":8.000074,"rtt":39943,"start":7.000083,"omitted":false,"stream-id":5,"retransmits":1,"tcp-window-size":512,"throughput-bits":0,"throughput-bytes":0}],"summary":{"end":8.000074,"start":7.000083,"omitted":false,"retransmits":1,"throughput-bits":0,"throughput-bytes":0}},{"streams":[{"end":9.000058,"rtt":39943,"start":8.000074,"omitted":false,"stream-id":5,"retransmits":0,"tcp-window-size":512,"throughput-bits":0,"throughput-bytes":0}],"summary":{"end":9.000058,"start":8.000074,"omitted":false,"retransmits":0,"throughput-bits":0,"throughput-bytes":0}},{"streams":[{"end":10.000053,"rtt":39943,"start":9.000058,"omitted":false,"stream-id":5,"retransmits":0,"tcp-window-size":512,"throughput-bits":0,"throughput-bytes":0}],"summary":{"end":10.000053,"start":9.000058,"omitted":false,"retransmits":0,"throughput-bits":0,"throughput-bytes":0}}],"succeeded":true}
