{"diags":"Participant 0:\n/usr/bin/iperf3 -p 5201 -B 172.16.0.2 -c 172.16.0.1 -t 10 --json --rsa-public-key-path /var/run/pscheduler-server/runner/tmp/tmp1gzdrpck/tmp01ltefj1/public-key --username RnsqdJM0WcouJp4nufBf\n\n{\n    \"end\": {\n        \"cpu_utilization_percent\": {\n            \"host_system\": 0.24239809880740137, \n            \"host_total\": 0.24240799260735268, \n            \"host_user\": 0, \n            \"remote_system\": 0.816692971098717, \n            \"remote_total\": 0.9789743063297046, \n            \"remote_user\": 0.16227143580225417\n        }, \n        \"receiver_tcp_congestion\": \"htcp\", \n        \"sender_tcp_congestion\": \"htcp\", \n        \"streams\": [\n            {\n                \"receiver\": {\n                    \"bits_per_second\": 11647569.099682167, \n                    \"bytes\": 14707336, \n                    \"end\": 10.101566, \n                    \"seconds\": 10.000116, \n                    \"sender\": true, \n                    \"socket\": 5, \n                    \"start\": 0\n                }, \n                \"sender\": {\n                    \"bits_per_second\": 14889606.480564825, \n                    \"bytes\": 18612224, \n                    \"end\": 10.000116, \n                    \"max_rtt\": 226023, \n                    \"max_snd_cwnd\": 398200, \n                    \"max_snd_wnd\": 0, \n                    \"mean_rtt\": 171962, \n                    \"min_rtt\": 108023, \n                    \"retransmits\": 288, \n                    \"seconds\": 10.000116, \n                    \"sender\": true, \n                    \"socket\": 5, \n                    \"start\": 0\n                }\n            }\n        ], \n        \"sum_received\": {\n            \"bits_per_second\": 11647569.099682167, \n            \"bytes\": 14707336, \n            \"end\": 10.101566, \n            \"seconds\": 10.101566, \n            \"sender\": true, \n            \"start\": 0\n        }, \n        \"sum_sent\": {\n            \"bits_per_second\": 14889606.480564825, \n            \"bytes\": 18612224, \n            \"end\": 10.000116, \n            \"retransmits\": 288, \n            \"seconds\": 10.000116, \n            \"sender\": true, \n            \"start\": 0\n        }\n    }, \n    \"intervals\": [\n        {\n            \"streams\": [\n                {\n                    \"bits_per_second\": 33552320.1329262, \n                    \"bytes\": 4194304, \n                    \"end\": 1.000063, \n                    \"omitted\": false, \n                    \"pmtu\": 1500, \n                    \"retransmits\": 277, \n                    \"rtt\": 164620, \n                    \"rttvar\": 3228, \n                    \"seconds\": 1.0000629425048828, \n                    \"sender\": true, \n                    \"snd_cwnd\": 398200, \n                    \"snd_wnd\": -1, \n                    \"socket\": 5, \n                    \"start\": 0\n                }\n            ], \n            \"sum\": {\n                \"bits_per_second\": 33552320.1329262, \n                \"bytes\": 4194304, \n                \"end\": 1.000063, \n                \"omitted\": false, \n                \"retransmits\": 277, \n                \"seconds\": 1.0000629425048828, \n                \"sender\": true, \n                \"start\": 0\n            }\n        }, \n        {\n            \"streams\": [\n                {\n                    \"bits_per_second\": 20966781.07109656, \n                    \"bytes\": 2621440, \n                    \"end\": 2.000289, \n                    \"omitted\": false, \n                    \"pmtu\": 1500, \n                    \"retransmits\": 2, \n                    \"rtt\": 140172, \n                    \"rttvar\": 1169, \n                    \"seconds\": 1.0002260208129883, \n                    \"sender\": true, \n                    \"snd_cwnd\": 201272, \n                    \"snd_wnd\": -1, \n                    \"socket\": 5, \n                    \"start\": 1.000063\n                }\n            ], \n            \"sum\": {\n                \"bits_per_second\": 20966781.07109656, \n                \"bytes\": 2621440, \n                \"end\": 2.000289, \n                \"omitted\": false, \n                \"retransmits\": 2, \n                \"seconds\": 1.0002260208129883, \n                \"sender\": true, \n                \"start\": 1.000063\n            }\n        }, \n        {\n            \"streams\": [\n                {\n                    \"bits_per_second\": 10483600.444854653, \n                    \"bytes\": 1310720, \n                    \"end\": 3.000495, \n                    \"omitted\": false, \n                    \"pmtu\": 1500, \n                    \"retransmits\": 0, \n                    \"rtt\": 142586, \n                    \"rttvar\": 4021, \n                    \"seconds\": 1.0002059936523438, \n                    \"sender\": true, \n                    \"snd_cwnd\": 211408, \n                    \"snd_wnd\": -1, \n                    \"socket\": 5, \n                    \"start\": 2.000289\n                }\n            ], \n            \"sum\": {\n                \"bits_per_second\": 10483600.444854653, \n                \"bytes\": 1310720, \n                \"end\": 3.000495, \n                \"omitted\": false, \n                \"retransmits\": 0, \n                \"seconds\": 1.0002059936523438, \n                \"sender\": true, \n                \"start\": 2.000289\n            }\n        }, \n        {\n            \"streams\": [\n                {\n                    \"bits_per_second\": 10490722.347301733, \n                    \"bytes\": 1310720, \n                    \"end\": 4.000022, \n                    \"omitted\": false, \n                    \"pmtu\": 1500, \n                    \"retransmits\": 0, \n                    \"rtt\": 210594, \n                    \"rttvar\": 1639, \n                    \"seconds\": 0.9995269775390625, \n                    \"sender\": true, \n                    \"snd_cwnd\": 220096, \n                    \"snd_wnd\": -1, \n                    \"socket\": 5, \n                    \"start\": 3.000495\n                }\n            ], \n            \"sum\": {\n                \"bits_per_second\": 10490722.347301733, \n                \"bytes\": 1310720, \n                \"end\": 4.000022, \n                \"omitted\": false, \n                \"retransmits\": 0, \n                \"seconds\": 0.9995269775390625, \n                \"sender\": true, \n                \"start\": 3.000495\n            }\n        }, \n        {\n            \"streams\": [\n                {\n                    \"bits_per_second\": 10481745.287712881, \n                    \"bytes\": 1310720, \n                    \"end\": 5.000405, \n                    \"omitted\": false, \n                    \"pmtu\": 1500, \n                    \"retransmits\": 0, \n                    \"rtt\": 123387, \n                    \"rttvar\": 2421, \n                    \"seconds\": 1.0003830194473267, \n                    \"sender\": true, \n                    \"snd_cwnd\": 234576, \n                    \"snd_wnd\": -1, \n                    \"socket\": 5, \n                    \"start\": 4.000022\n                }\n            ], \n            \"sum\": {\n                \"bits_per_second\": 10481745.287712881, \n                \"bytes\": 1310720, \n                \"end\": 5.000405, \n                \"omitted\": false, \n                \"retransmits\": 0, \n                \"seconds\": 1.0003830194473267, \n                \"sender\": true, \n                \"start\": 4.000022\n            }\n        }, \n        {\n            \"streams\": [\n                {\n                    \"bits_per_second\": 10485561.253767092, \n                    \"bytes\": 1310720, \n                    \"end\": 6.000424, \n                    \"omitted\": false, \n                    \"pmtu\": 1500, \n                    \"retransmits\": 0, \n                    \"rtt\": 219928, \n                    \"rttvar\": 898, \n                    \"seconds\": 1.0000189542770386, \n                    \"sender\": true, \n                    \"snd_cwnd\": 256296, \n                    \"snd_wnd\": -1, \n                    \"socket\": 5, \n                    \"start\": 5.000405\n                }\n            ], \n            \"sum\": {\n                \"bits_per_second\": 10485561.253767092, \n                \"bytes\": 1310720, \n                \"end\": 6.000424, \n                \"omitted\": false, \n                \"retransmits\": 0, \n                \"seconds\": 1.0000189542770386, \n                \"sender\": true, \n                \"start\": 5.000405\n            }\n        }, \n        {\n            \"streams\": [\n                {\n                    \"bits_per_second\": 10486242.522203157, \n                    \"bytes\": 1310720, \n                    \"end\": 7.000378, \n                    \"omitted\": false, \n                    \"pmtu\": 1500, \n                    \"retransmits\": 0, \n                    \"rtt\": 185985, \n                    \"rttvar\": 928, \n                    \"seconds\": 0.9999539852142334, \n                    \"sender\": true, \n                    \"snd_cwnd\": 288152, \n                    \"snd_wnd\": -1, \n                    \"socket\": 5, \n                    \"start\": 6.000424\n                }\n            ], \n            \"sum\": {\n                \"bits_per_second\": 10486242.522203157, \n                \"bytes\": 1310720, \n                \"end\": 7.000378, \n                \"omitted\": false, \n                \"retransmits\": 0, \n                \"seconds\": 0.9999539852142334, \n                \"sender\": true, \n                \"start\": 6.000424\n            }\n        }, \n        {\n            \"streams\": [\n                {\n                    \"bits_per_second\": 10482301.14132414, \n                    \"bytes\": 1310720, \n                    \"end\": 8.000708, \n                    \"omitted\": false, \n                    \"pmtu\": 1500, \n                    \"retransmits\": 0, \n                    \"rtt\": 198304, \n                    \"rttvar\": 1886, \n                    \"seconds\": 1.0003299713134766, \n                    \"sender\": true, \n                    \"snd_cwnd\": 330144, \n                    \"snd_wnd\": -1, \n                    \"socket\": 5, \n                    \"start\": 7.000378\n                }\n            ], \n            \"sum\": {\n                \"bits_per_second\": 10482301.14132414, \n                \"bytes\": 1310720, \n                \"end\": 8.000708, \n                \"omitted\": false, \n                \"retransmits\": 0, \n                \"seconds\": 1.0003299713134766, \n                \"sender\": true, \n                \"start\": 7.000378\n            }\n        }, \n        {\n            \"streams\": [\n                {\n                    \"bits_per_second\": 10492096.952353608, \n                    \"bytes\": 1310720, \n                    \"end\": 9.000104, \n                    \"omitted\": false, \n                    \"pmtu\": 1500, \n                    \"retransmits\": 0, \n                    \"rtt\": 226023, \n                    \"rttvar\": 2958, \n                    \"seconds\": 0.999396026134491, \n                    \"sender\": true, \n                    \"snd_cwnd\": 379376, \n                    \"snd_wnd\": -1, \n                    \"socket\": 5, \n                    \"start\": 8.000708\n                }\n            ], \n            \"sum\": {\n                \"bits_per_second\": 10492096.952353608, \n                \"bytes\": 1310720, \n                \"end\": 9.000104, \n                \"omitted\": false, \n                \"retransmits\": 0, \n                \"seconds\": 0.999396026134491, \n                \"sender\": true, \n                \"start\": 8.000708\n            }\n        }, \n        {\n            \"streams\": [\n                {\n                    \"bits_per_second\": 20971267.5030401, \n                    \"bytes\": 2621440, \n                    \"end\": 10.000116, \n                    \"omitted\": false, \n                    \"pmtu\": 1500, \n                    \"retransmits\": 9, \n                    \"rtt\": 108023, \n                    \"rttvar\": 259, \n                    \"seconds\": 1.0000120401382446, \n                    \"sender\": true, \n                    \"snd_cwnd\": 205616, \n                    \"snd_wnd\": -1, \n                    \"socket\": 5, \n                    \"start\": 9.000104\n                }\n            ], \n            \"sum\": {\n                \"bits_per_second\": 20971267.5030401, \n                \"bytes\": 2621440, \n                \"end\": 10.000116, \n                \"omitted\": false, \n                \"retransmits\": 9, \n                \"seconds\": 1.0000120401382446, \n                \"sender\": true, \n                \"start\": 9.000104\n            }\n        }\n    ], \n    \"start\": {\n        \"connected\": [\n            {\n                \"local_host\": \"172.16.0.2\", \n                \"local_port\": 54089, \n                \"remote_host\": \"172.16.0.1\", \n                \"remote_port\": 5201, \n                \"socket\": 5\n            }\n        ], \n        \"connecting_to\": {\n            \"host\": \"172.16.0.1\", \n            \"port\": 5201\n        }, \n        \"cookie\": \"lqepuia52zdc6mmwjomiq6vuzt3n6qbpzoke\", \n        \"fq_rate\": 0, \n        \"rcvbuf_actual\": 87380, \n        \"sndbuf_actual\": 65536, \n        \"sock_bufsize\": 0, \n        \"system_info\": \"REDACTED\", \n        \"target_bitrate\": 0, \n        \"tcp_mss_default\": 1448, \n        \"test_start\": {\n            \"bidir\": 0, \n            \"blksize\": 131072, \n            \"blocks\": 0, \n            \"bytes\": 0, \n            \"duration\": 10, \n            \"fqrate\": 0, \n            \"num_streams\": 1, \n            \"omit\": 0, \n            \"protocol\": \"TCP\", \n            \"reverse\": 0, \n            \"target_bitrate\": 0, \n            \"tos\": 0\n        }, \n        \"timestamp\": {\n            \"time\": \"Sat, 12 Oct 2024 02:24:18 GMT\", \n            \"timesecs\": 1728699858\n        }, \n        \"version\": \"iperf 3.14\"\n    }\n}\nParticipant 1:\n/usr/bin/iperf3 -s -1 --idle-timeout 10 --json -p 5201 -B 172.16.0.1 --authorized-users-path /var/run/pscheduler-server/runner/tmp/tmpwziuzce_/tmp6j1828hx/credentials --rsa-private-key-path /var/run/pscheduler-server/runner/tmp/tmpwziuzce_/tmp6j1828hx/private-key\n\n{\n    \"end\": {\n        \"cpu_utilization_percent\": {\n            \"host_system\": 0.816692971098717, \n            \"host_total\": 0.9789743063297046, \n            \"host_user\": 0.16227143580225417, \n            \"remote_system\": 0, \n            \"remote_total\": 0, \n            \"remote_user\": 0\n        }, \n        \"receiver_tcp_congestion\": \"htcp\", \n        \"streams\": [\n            {\n                \"receiver\": {\n                    \"bits_per_second\": 11647569.099682167, \n                    \"bytes\": 14707336, \n                    \"end\": 10.101566, \n                    \"seconds\": 10.101566, \n                    \"sender\": false, \n                    \"socket\": 5, \n                    \"start\": 0\n                }, \n                \"sender\": {\n                    \"bits_per_second\": 0, \n                    \"bytes\": 0, \n                    \"end\": 10.101566, \n                    \"seconds\": 10.101566, \n                    \"sender\": false, \n                    \"socket\": 5, \n                    \"start\": 0\n                }\n            }\n        ], \n        \"sum_received\": {\n            \"bits_per_second\": 11647569.099682167, \n            \"bytes\": 14707336, \n            \"end\": 10.101566, \n            \"seconds\": 10.101566, \n            \"sender\": false, \n            \"start\": 0\n        }, \n        \"sum_sent\": {\n            \"bits_per_second\": 0, \n            \"bytes\": 0, \n            \"end\": 10.101566, \n            \"seconds\": 10.101566, \n            \"sender\": false, \n            \"start\": 0\n        }\n    }, \n    \"intervals\": [\n        {\n            \"streams\": [\n                {\n                    \"bits_per_second\": 9475437.51687758, \n                    \"bytes\": 1184464, \n                    \"end\": 1.000029, \n                    \"omitted\": false, \n                    \"seconds\": 1.0000289678573608, \n                    \"sender\": false, \n                    \"socket\": 5, \n                    \"start\": 0\n                }\n            ], \n            \"sum\": {\n                \"bits_per_second\": 9475437.51687758, \n                \"bytes\": 1184464, \n                \"end\": 1.000029, \n                \"omitted\": false, \n                \"seconds\": 1.0000289678573608, \n                \"sender\": false, \n                \"start\": 0\n            }\n        }, \n        {\n            \"streams\": [\n                {\n                    \"bits_per_second\": 13471707.002308523, \n                    \"bytes\": 1684024, \n                    \"end\": 2.000065, \n                    \"omitted\": false, \n                    \"seconds\": 1.0000360012054443, \n                    \"sender\": false, \n                    \"socket\": 5, \n                    \"start\": 1.000029\n                }\n            ], \n            \"sum\": {\n                \"bits_per_second\": 13471707.002308523, \n                \"bytes\": 1684024, \n                \"end\": 2.000065, \n                \"omitted\": false, \n                \"seconds\": 1.0000360012054443, \n                \"sender\": false, \n                \"start\": 1.000029\n            }\n        }, \n        {\n            \"streams\": [\n                {\n                    \"bits_per_second\": 11525906.876608556, \n                    \"bytes\": 1440760, \n                    \"end\": 3.00008, \n                    \"omitted\": false, \n                    \"seconds\": 1.0000150203704834, \n                    \"sender\": false, \n                    \"socket\": 5, \n                    \"start\": 2.000065\n                }\n            ], \n            \"sum\": {\n                \"bits_per_second\": 11525906.876608556, \n                \"bytes\": 1440760, \n                \"end\": 3.00008, \n                \"omitted\": false, \n                \"seconds\": 1.0000150203704834, \n                \"sender\": false, \n                \"start\": 2.000065\n            }\n        }, \n        {\n            \"streams\": [\n                {\n                    \"bits_per_second\": 10598406.111510493, \n                    \"bytes\": 1324920, \n                    \"end\": 4.00017, \n                    \"omitted\": false, \n                    \"seconds\": 1.0000900030136108, \n                    \"sender\": false, \n                    \"socket\": 5, \n                    \"start\": 3.00008\n                }\n            ], \n            \"sum\": {\n                \"bits_per_second\": 10598406.111510493, \n                \"bytes\": 1324920, \n                \"end\": 4.00017, \n                \"omitted\": false, \n                \"seconds\": 1.0000900030136108, \n                \"sender\": false, \n                \"start\": 3.00008\n            }\n        }, \n        {\n            \"streams\": [\n                {\n                    \"bits_per_second\": 10867400.357136654, \n                    \"bytes\": 1358224, \n                    \"end\": 5.000022, \n                    \"omitted\": false, \n                    \"seconds\": 0.9998520016670227, \n                    \"sender\": false, \n                    \"socket\": 5, \n                    \"start\": 4.00017\n                }\n            ], \n            \"sum\": {\n                \"bits_per_second\": 10867400.357136654, \n                \"bytes\": 1358224, \n                \"end\": 5.000022, \n                \"omitted\": false, \n                \"seconds\": 0.9998520016670227, \n                \"sender\": false, \n                \"start\": 4.00017\n            }\n        }, \n        {\n            \"streams\": [\n                {\n                    \"bits_per_second\": 9324700.93020312, \n                    \"bytes\": 1165640, \n                    \"end\": 6.000067, \n                    \"omitted\": false, \n                    \"seconds\": 1.0000449419021606, \n                    \"sender\": false, \n                    \"socket\": 5, \n                    \"start\": 5.000022\n                }\n            ], \n            \"sum\": {\n                \"bits_per_second\": 9324700.93020312, \n                \"bytes\": 1165640, \n                \"end\": 6.000067, \n                \"omitted\": false, \n                \"seconds\": 1.0000449419021606, \n                \"sender\": false, \n                \"start\": 5.000022\n            }\n        }, \n        {\n            \"streams\": [\n                {\n                    \"bits_per_second\": 11490925.271438861, \n                    \"bytes\": 1436416, \n                    \"end\": 7.000102, \n                    \"omitted\": false, \n                    \"seconds\": 1.000035047531128, \n                    \"sender\": false, \n                    \"socket\": 5, \n                    \"start\": 6.000067\n                }\n            ], \n            \"sum\": {\n                \"bits_per_second\": 11490925.271438861, \n                \"bytes\": 1436416, \n                \"end\": 7.000102, \n                \"omitted\": false, \n                \"seconds\": 1.000035047531128, \n                \"sender\": false, \n                \"start\": 6.000067\n            }\n        }, \n        {\n            \"streams\": [\n                {\n                    \"bits_per_second\": 12464982.091517907, \n                    \"bytes\": 1558048, \n                    \"end\": 8.000054, \n                    \"omitted\": false, \n                    \"seconds\": 0.9999520182609558, \n                    \"sender\": false, \n                    \"socket\": 5, \n                    \"start\": 7.000102\n                }\n            ], \n            \"sum\": {\n                \"bits_per_second\": 12464982.091517907, \n                \"bytes\": 1558048, \n                \"end\": 8.000054, \n                \"omitted\": false, \n                \"seconds\": 0.9999520182609558, \n                \"sender\": false, \n                \"start\": 7.000102\n            }\n        }, \n        {\n            \"streams\": [\n                {\n                    \"bits_per_second\": 13530044.25790753, \n                    \"bytes\": 1691264, \n                    \"end\": 9.000059, \n                    \"omitted\": false, \n                    \"seconds\": 1.0000050067901611, \n                    \"sender\": false, \n                    \"socket\": 5, \n                    \"start\": 8.000054\n                }\n            ], \n            \"sum\": {\n                \"bits_per_second\": 13530044.25790753, \n                \"bytes\": 1691264, \n                \"end\": 9.000059, \n                \"omitted\": false, \n                \"seconds\": 1.0000050067901611, \n                \"sender\": false, \n                \"start\": 8.000054\n            }\n        }, \n        {\n            \"streams\": [\n                {\n                    \"bits_per_second\": 13368510.511055855, \n                    \"bytes\": 1670992, \n                    \"end\": 10.000016, \n                    \"omitted\": false, \n                    \"seconds\": 0.999957025051117, \n                    \"sender\": false, \n                    \"socket\": 5, \n                    \"start\": 9.000059\n                }\n            ], \n            \"sum\": {\n                \"bits_per_second\": 13368510.511055855, \n                \"bytes\": 1670992, \n                \"end\": 10.000016, \n                \"omitted\": false, \n                \"seconds\": 0.999957025051117, \n                \"sender\": false, \n                \"start\": 9.000059\n            }\n        }, \n        {\n            \"streams\": [\n                {\n                    \"bits_per_second\": 15171561.117375517, \n                    \"bytes\": 192584, \n                    \"end\": 10.101566, \n                    \"omitted\": false, \n                    \"seconds\": 0.10154999792575836, \n                    \"sender\": false, \n                    \"socket\": 5, \n                    \"start\": 10.000016\n                }\n            ], \n            \"sum\": {\n                \"bits_per_second\": 15171561.117375517, \n                \"bytes\": 192584, \n                \"end\": 10.101566, \n                \"omitted\": false, \n                \"seconds\": 0.10154999792575836, \n                \"sender\": false, \n                \"start\": 10.000016\n            }\n        }\n    ], \n    \"start\": {\n        \"accepted_connection\": {\n            \"host\": \"172.16.0.2\", \n            \"port\": 36105\n        }, \n        \"connected\": [\n            {\n                \"local_host\": \"172.16.0.1\", \n                \"local_port\": 5201, \n                \"remote_host\": \"172.16.0.2\", \n                \"remote_port\": 54089, \n                \"socket\": 5\n            }\n        ], \n        \"cookie\": \"lqepuia52zdc6mmwjomiq6vuzt3n6qbpzoke\", \n        \"fq_rate\": 0, \n        \"rcvbuf_actual\": 87380, \n        \"sndbuf_actual\": 65536, \n        \"sock_bufsize\": 0, \n        \"system_info\": \"REDACTED\", \n        \"target_bitrate\": 0, \n        \"tcp_mss_default\": 0, \n        \"test_start\": {\n            \"bidir\": 0, \n            \"blksize\": 131072, \n            \"blocks\": 0, \n            \"bytes\": 0, \n            \"duration\": 10, \n            \"fqrate\": 0, \n            \"num_streams\": 1, \n            \"omit\": 0, \n            \"protocol\": \"TCP\", \n            \"reverse\": 0, \n            \"target_bitrate\": 0, \n            \"tos\": 0\n        }, \n        \"timestamp\": {\n            \"time\": \"Sat, 12 Oct 2024 02:24:18 GMT\", \n            \"timesecs\": 1728699858\n        }, \n        \"version\": \"iperf 3.14\"\n    }\n}\n","summary":{"streams":[{"end":10.000116,"rtt":171962,"start":0,"stream-id":5,"retransmits":288,"throughput-bits":14889606.480564825,"throughput-bytes":18612224}],"summary":{"end":10.000116,"start":0,"retransmits":288,"throughput-bits":14889606.480564825,"throughput-bytes":18612224,"receiver-throughput-bits":11647569.099682167}},"intervals":[{"streams":[{"end":1.000063,"rtt":164620,"start":0,"omitted":false,"stream-id":5,"retransmits":277,"tcp-window-size":398200,"throughput-bits":33552320.1329262,"throughput-bytes":4194304}],"summary":{"end":1.000063,"start":0,"omitted":false,"retransmits":277,"throughput-bits":33552320.1329262,"throughput-bytes":4194304}},{"streams":[{"end":2.000289,"rtt":140172,"start":1.000063,"omitted":false,"stream-id":5,"retransmits":2,"tcp-window-size":201272,"throughput-bits":20966781.07109656,"throughput-bytes":2621440}],"summary":{"end":2.000289,"start":1.000063,"omitted":false,"retransmits":2,"throughput-bits":20966781.07109656,"throughput-bytes":2621440}},{"streams":[{"end":3.000495,"rtt":142586,"start":2.000289,"omitted":false,"stream-id":5,"retransmits":0,"tcp-window-size":211408,"throughput-bits":10483600.444854653,"throughput-bytes":1310720}],"summary":{"end":3.000495,"start":2.000289,"omitted":false,"retransmits":0,"throughput-bits":10483600.444854653,"throughput-bytes":1310720}},{"streams":[{"end":4.000022,"rtt":210594,"start":3.000495,"omitted":false,"stream-id":5,"retransmits":0,"tcp-window-size":220096,"throughput-bits":10490722.347301733,"throughput-bytes":1310720}],"summary":{"end":4.000022,"start":3.000495,"omitted":false,"retransmits":0,"throughput-bits":10490722.347301733,"throughput-bytes":1310720}},{"streams":[{"end":5.000405,"rtt":123387,"start":4.000022,"omitted":false,"stream-id":5,"retransmits":0,"tcp-window-size":234576,"throughput-bits":10481745.287712881,"throughput-bytes":1310720}],"summary":{"end":5.000405,"start":4.000022,"omitted":false,"retransmits":0,"throughput-bits":10481745.287712881,"throughput-bytes":1310720}},{"streams":[{"end":6.000424,"rtt":219928,"start":5.000405,"omitted":false,"stream-id":5,"retransmits":0,"tcp-window-size":256296,"throughput-bits":10485561.253767092,"throughput-bytes":1310720}],"summary":{"end":6.000424,"start":5.000405,"omitted":false,"retransmits":0,"throughput-bits":10485561.253767092,"throughput-bytes":1310720}},{"streams":[{"end":7.000378,"rtt":185985,"start":6.000424,"omitted":false,"stream-id":5,"retransmits":0,"tcp-window-size":288152,"throughput-bits":10486242.522203157,"throughput-bytes":1310720}],"summary":{"end":7.000378,"start":6.000424,"omitted":false,"retransmits":0,"throughput-bits":10486242.522203157,"throughput-bytes":1310720}},{"streams":[{"end":8.000708,"rtt":198304,"start":7.000378,"omitted":false,"stream-id":5,"retransmits":0,"tcp-window-size":330144,"throughput-bits":10482301.14132414,"throughput-bytes":1310720}],"summary":{"end":8.000708,"start":7.000378,"omitted":false,"retransmits":0,"throughput-bits":10482301.14132414,"throughput-bytes":1310720}},{"streams":[{"end":9.000104,"rtt":226023,"start":8.000708,"omitted":false,"stream-id":5,"retransmits":0,"tcp-window-size":379376,"throughput-bits":10492096.952353608,"throughput-bytes":1310720}],"summary":{"end":9.000104,"start":8.000708,"omitted":false,"retransmits":0,"throughput-bits":10492096.952353608,"throughput-bytes":1310720}},{"streams":[{"end":10.000116,"rtt":108023,"start":9.000104,"omitted":false,"stream-id":5,"retransmits":9,"tcp-window-size":205616,"throughput-bits":20971267.5030401,"throughput-bytes":2621440}],"summary":{"end":10.000116,"start":9.000104,"omitted":false,"retransmits":9,"throughput-bits":20971267.5030401,"throughput-bytes":2621440}}],"succeeded":true}
