{"diags":"Participant 0:\n/usr/bin/iperf3 -p 5201 -B 172.16.0.2 -c 172.16.0.1 -t 10 --json --rsa-public-key-path /var/run/pscheduler-server/runner/tmp/tmpmqo17dqd/tmppngsbt9b/public-key --username Qk8gksR9rrYbzgNpH7qZ\n\n{\n    \"end\": {\n        \"cpu_utilization_percent\": {\n            \"host_system\": 0.2262024229314123, \n            \"host_total\": 0.351786113097072, \n            \"host_user\": 0.12557383428038535, \n            \"remote_system\": 0.7318867773992134, \n            \"remote_total\": 0.738092212769604, \n            \"remote_user\": 0.0061955854729773\n        }, \n        \"receiver_tcp_congestion\": \"htcp\", \n        \"sender_tcp_congestion\": \"htcp\", \n        \"streams\": [\n            {\n                \"receiver\": {\n                    \"bits_per_second\": 12212391.0158068, \n                    \"bytes\": 15497944, \n                    \"end\": 10.152275, \n                    \"seconds\": 10.00057, \n                    \"sender\": true, \n                    \"socket\": 5, \n                    \"start\": 0\n                }, \n                \"sender\": {\n                    \"bits_per_second\": 14993782.1544172, \n                    \"bytes\": 18743296, \n                    \"end\": 10.00057, \n                    \"max_rtt\": 374343, \n                    \"max_snd_cwnd\": 472048, \n                    \"max_snd_wnd\": 0, \n                    \"mean_rtt\": 193694, \n                    \"min_rtt\": 98833, \n                    \"retransmits\": 296, \n                    \"seconds\": 10.00057, \n                    \"sender\": true, \n                    \"socket\": 5, \n                    \"start\": 0\n                }\n            }\n        ], \n        \"sum_received\": {\n            \"bits_per_second\": 12212391.0158068, \n            \"bytes\": 15497944, \n            \"end\": 10.152275, \n            \"seconds\": 10.152275, \n            \"sender\": true, \n            \"start\": 0\n        }, \n        \"sum_sent\": {\n            \"bits_per_second\": 14993782.1544172, \n            \"bytes\": 18743296, \n            \"end\": 10.00057, \n            \"retransmits\": 296, \n            \"seconds\": 10.00057, \n            \"sender\": true, \n            \"start\": 0\n        }\n    }, \n    \"intervals\": [\n        {\n            \"streams\": [\n                {\n                    \"bits_per_second\": 34595258.86076267, \n                    \"bytes\": 4325376, \n                    \"end\": 1.000224, \n                    \"omitted\": false, \n                    \"pmtu\": 1500, \n                    \"retransmits\": 74, \n                    \"rtt\": 247350, \n                    \"rttvar\": 748, \n                    \"seconds\": 1.000223994255066, \n                    \"sender\": true, \n                    \"snd_cwnd\": 472048, \n                    \"snd_wnd\": -1, \n                    \"socket\": 5, \n                    \"start\": 0\n                }\n            ], \n            \"sum\": {\n                \"bits_per_second\": 34595258.86076267, \n                \"bytes\": 4325376, \n                \"end\": 1.000224, \n                \"omitted\": false, \n                \"retransmits\": 74, \n                \"seconds\": 1.000223994255066, \n                \"sender\": true, \n                \"start\": 0\n            }\n        }, \n        {\n            \"streams\": [\n                {\n                    \"bits_per_second\": 10486525.68090672, \n                    \"bytes\": 1310720, \n                    \"end\": 2.000151, \n                    \"omitted\": false, \n                    \"pmtu\": 1500, \n                    \"retransmits\": 212, \n                    \"rtt\": 374343, \n                    \"rttvar\": 1084, \n                    \"seconds\": 0.99992698431015, \n                    \"sender\": true, \n                    \"snd_cwnd\": 251952, \n                    \"snd_wnd\": -1, \n                    \"socket\": 5, \n                    \"start\": 1.000224\n                }\n            ], \n            \"sum\": {\n                \"bits_per_second\": 10486525.68090672, \n                \"bytes\": 1310720, \n                \"end\": 2.000151, \n                \"omitted\": false, \n                \"retransmits\": 212, \n                \"seconds\": 0.99992698431015, \n                \"sender\": true, \n                \"start\": 1.000224\n            }\n        }, \n        {\n            \"streams\": [\n                {\n                    \"bits_per_second\": 10480488.901067542, \n                    \"bytes\": 1310720, \n                    \"end\": 3.000654, \n                    \"omitted\": false, \n                    \"pmtu\": 1500, \n                    \"retransmits\": 0, \n                    \"rtt\": 170541, \n                    \"rttvar\": 10171, \n                    \"seconds\": 1.0005029439926147, \n                    \"sender\": true, \n                    \"snd_cwnd\": 205616, \n                    \"snd_wnd\": -1, \n                    \"socket\": 5, \n                    \"start\": 2.000151\n                }\n            ], \n            \"sum\": {\n                \"bits_per_second\": 10480488.901067542, \n                \"bytes\": 1310720, \n                \"end\": 3.000654, \n                \"omitted\": false, \n                \"retransmits\": 0, \n                \"seconds\": 1.0005029439926147, \n                \"sender\": true, \n                \"start\": 2.000151\n            }\n        }, \n        {\n            \"streams\": [\n                {\n                    \"bits_per_second\": 10485508.756020075, \n                    \"bytes\": 1310720, \n                    \"end\": 4.000678, \n                    \"omitted\": false, \n                    \"pmtu\": 1500, \n                    \"retransmits\": 0, \n                    \"rtt\": 98833, \n                    \"rttvar\": 469, \n                    \"seconds\": 1.0000239610672, \n                    \"sender\": true, \n                    \"snd_cwnd\": 217200, \n                    \"snd_wnd\": -1, \n                    \"socket\": 5, \n                    \"start\": 3.000654\n                }\n            ], \n            \"sum\": {\n                \"bits_per_second\": 10485508.756020075, \n                \"bytes\": 1310720, \n                \"end\": 4.000678, \n                \"omitted\": false, \n                \"retransmits\": 0, \n                \"seconds\": 1.0000239610672, \n                \"sender\": true, \n                \"start\": 3.000654\n            }\n        }, \n        {\n            \"streams\": [\n                {\n                    \"bits_per_second\": 20978716.218480907, \n                    \"bytes\": 2621440, \n                    \"end\": 5.000335, \n                    \"omitted\": false, \n                    \"pmtu\": 1500, \n                    \"retransmits\": 0, \n                    \"rtt\": 102189, \n                    \"rttvar\": 447, \n                    \"seconds\": 0.9996569752693176, \n                    \"sender\": true, \n                    \"snd_cwnd\": 247608, \n                    \"snd_wnd\": -1, \n                    \"socket\": 5, \n                    \"start\": 4.000678\n                }\n            ], \n            \"sum\": {\n                \"bits_per_second\": 20978716.218480907, \n                \"bytes\": 2621440, \n                \"end\": 5.000335, \n                \"omitted\": false, \n                \"retransmits\": 0, \n                \"seconds\": 0.9996569752693176, \n                \"sender\": true, \n                \"start\": 4.000678\n            }\n        }, \n        {\n            \"streams\": [\n                {\n                    \"bits_per_second\": 10480949.707711376, \n                    \"bytes\": 1310720, \n                    \"end\": 6.000794, \n                    \"omitted\": false, \n                    \"pmtu\": 1500, \n                    \"retransmits\": 0, \n                    \"rtt\": 211416, \n                    \"rttvar\": 1692, \n                    \"seconds\": 1.0004589557647705, \n                    \"sender\": true, \n                    \"snd_cwnd\": 282360, \n                    \"snd_wnd\": -1, \n                    \"socket\": 5, \n                    \"start\": 5.000335\n                }\n            ], \n            \"sum\": {\n                \"bits_per_second\": 10480949.707711376, \n                \"bytes\": 1310720, \n                \"end\": 6.000794, \n                \"omitted\": false, \n                \"retransmits\": 0, \n                \"seconds\": 1.0004589557647705, \n                \"sender\": true, \n                \"start\": 5.000335\n            }\n        }, \n        {\n            \"streams\": [\n                {\n                    \"bits_per_second\": 10479912.013285853, \n                    \"bytes\": 1310720, \n                    \"end\": 7.001352, \n                    \"omitted\": false, \n                    \"pmtu\": 1500, \n                    \"retransmits\": 0, \n                    \"rtt\": 189608, \n                    \"rttvar\": 815, \n                    \"seconds\": 1.0005580186843872, \n                    \"sender\": true, \n                    \"snd_cwnd\": 325800, \n                    \"snd_wnd\": -1, \n                    \"socket\": 5, \n                    \"start\": 6.000794\n                }\n            ], \n            \"sum\": {\n                \"bits_per_second\": 10479912.013285853, \n                \"bytes\": 1310720, \n                \"end\": 7.001352, \n                \"omitted\": false, \n                \"retransmits\": 0, \n                \"seconds\": 1.0005580186843872, \n                \"sender\": true, \n                \"start\": 6.000794\n            }\n        }, \n        {\n            \"streams\": [\n                {\n                    \"bits_per_second\": 20996841.78758909, \n                    \"bytes\": 2621440, \n                    \"end\": 8.000146, \n                    \"omitted\": false, \n                    \"pmtu\": 1500, \n                    \"retransmits\": 0, \n                    \"rtt\": 238384, \n                    \"rttvar\": 1250, \n                    \"seconds\": 0.9987940192222595, \n                    \"sender\": true, \n                    \"snd_cwnd\": 385168, \n                    \"snd_wnd\": -1, \n                    \"socket\": 5, \n                    \"start\": 7.001352\n                }\n            ], \n            \"sum\": {\n                \"bits_per_second\": 20996841.78758909, \n                \"bytes\": 2621440, \n                \"end\": 8.000146, \n                \"omitted\": false, \n                \"retransmits\": 0, \n                \"seconds\": 0.9987940192222595, \n                \"sender\": true, \n                \"start\": 7.001352\n            }\n        }, \n        {\n            \"streams\": [\n                {\n                    \"bits_per_second\": 10483485.493479, \n                    \"bytes\": 1310720, \n                    \"end\": 9.000363, \n                    \"omitted\": false, \n                    \"pmtu\": 1500, \n                    \"retransmits\": 10, \n                    \"rtt\": 144185, \n                    \"rttvar\": 1213, \n                    \"seconds\": 1.0002169609069824, \n                    \"sender\": true, \n                    \"snd_cwnd\": 205616, \n                    \"snd_wnd\": -1, \n                    \"socket\": 5, \n                    \"start\": 8.000146\n                }\n            ], \n            \"sum\": {\n                \"bits_per_second\": 10483485.493479, \n                \"bytes\": 1310720, \n                \"end\": 9.000363, \n                \"omitted\": false, \n                \"retransmits\": 10, \n                \"seconds\": 1.0002169609069824, \n                \"sender\": true, \n                \"start\": 8.000146\n            }\n        }, \n        {\n            \"streams\": [\n                {\n                    \"bits_per_second\": 10483590.448982783, \n                    \"bytes\": 1310720, \n                    \"end\": 10.00057, \n                    \"omitted\": false, \n                    \"pmtu\": 1500, \n                    \"retransmits\": 0, \n                    \"rtt\": 160092, \n                    \"rttvar\": 3586, \n                    \"seconds\": 1.00020694732666, \n                    \"sender\": true, \n                    \"snd_cwnd\": 217200, \n                    \"snd_wnd\": -1, \n                    \"socket\": 5, \n                    \"start\": 9.000363\n                }\n            ], \n            \"sum\": {\n                \"bits_per_second\": 10483590.448982783, \n                \"bytes\": 1310720, \n                \"end\": 10.00057, \n                \"omitted\": false, \n                \"retransmits\": 0, \n                \"seconds\": 1.00020694732666, \n                \"sender\": true, \n                \"start\": 9.000363\n            }\n        }\n    ], \n    \"start\": {\n        \"connected\": [\n            {\n                \"local_host\": \"172.16.0.2\", \n                \"local_port\": 50847, \n                \"remote_host\": \"172.16.0.1\", \n                \"remote_port\": 5201, \n                \"socket\": 5\n            }\n        ], \n        \"connecting_to\": {\n            \"host\": \"172.16.0.1\", \n            \"port\": 5201\n        }, \n        \"cookie\": \"epliu7sn7p6tndgyyrn7o22z3h2j4jm6n5lk\", \n        \"fq_rate\": 0, \n        \"rcvbuf_actual\": 87380, \n        \"sndbuf_actual\": 65536, \n        \"sock_bufsize\": 0, \n        \"system_info\": \"REDACTED\", \n        \"target_bitrate\": 0, \n        \"tcp_mss_default\": 1448, \n        \"test_start\": {\n            \"bidir\": 0, \n            \"blksize\": 131072, \n            \"blocks\": 0, \n            \"bytes\": 0, \n            \"duration\": 10, \n            \"fqrate\": 0, \n            \"num_streams\": 1, \n            \"omit\": 0, \n            \"protocol\": \"TCP\", \n            \"reverse\": 0, \n            \"target_bitrate\": 0, \n            \"tos\": 0\n        }, \n        \"timestamp\": {\n            \"time\": \"Sat, 12 Oct 2024 02:20:18 GMT\", \n            \"timesecs\": 1728699618\n        }, \n        \"version\": \"iperf 3.14\"\n    }\n}\nParticipant 1:\n/usr/bin/iperf3 -s -1 --idle-timeout 10 --json -p 5201 -B 172.16.0.1 --authorized-users-path /var/run/pscheduler-server/runner/tmp/tmpxtn8tdgq/tmpft8gm04t/credentials --rsa-private-key-path /var/run/pscheduler-server/runner/tmp/tmpxtn8tdgq/tmpft8gm04t/private-key\n\n{\n    \"end\": {\n        \"cpu_utilization_percent\": {\n            \"host_system\": 0.7318867773992134, \n            \"host_total\": 0.738092212769604, \n            \"host_user\": 0.0061955854729773, \n            \"remote_system\": 0, \n            \"remote_total\": 0, \n            \"remote_user\": 0\n        }, \n        \"receiver_tcp_congestion\": \"htcp\", \n        \"streams\": [\n            {\n                \"receiver\": {\n                    \"bits_per_second\": 12212391.0158068, \n                    \"bytes\": 15497944, \n                    \"end\": 10.152275, \n                    \"seconds\": 10.152275, \n                    \"sender\": false, \n                    \"socket\": 5, \n                    \"start\": 0\n                }, \n                \"sender\": {\n                    \"bits_per_second\": 0, \n                    \"bytes\": 0, \n                    \"end\": 10.152275, \n                    \"seconds\": 10.152275, \n                    \"sender\": false, \n                    \"socket\": 5, \n                    \"start\": 0\n                }\n            }\n        ], \n        \"sum_received\": {\n            \"bits_per_second\": 12212391.0158068, \n            \"bytes\": 15497944, \n            \"end\": 10.152275, \n            \"seconds\": 10.152275, \n            \"sender\": false, \n            \"start\": 0\n        }, \n        \"sum_sent\": {\n            \"bits_per_second\": 0, \n            \"bytes\": 0, \n            \"end\": 10.152275, \n            \"seconds\": 10.152275, \n            \"sender\": false, \n            \"start\": 0\n        }\n    }, \n    \"intervals\": [\n        {\n            \"streams\": [\n                {\n                    \"bits_per_second\": 6277498.289510922, \n                    \"bytes\": 784816, \n                    \"end\": 1.000164, \n                    \"omitted\": false, \n                    \"seconds\": 1.0001640319824219, \n                    \"sender\": false, \n                    \"socket\": 5, \n                    \"start\": 0\n                }\n            ], \n            \"sum\": {\n                \"bits_per_second\": 6277498.289510922, \n                \"bytes\": 784816, \n                \"end\": 1.000164, \n                \"omitted\": false, \n                \"seconds\": 1.0001640319824219, \n                \"sender\": false, \n                \"start\": 0\n            }\n        }, \n        {\n            \"streams\": [\n                {\n                    \"bits_per_second\": 9383941.074950203, \n                    \"bytes\": 1172880, \n                    \"end\": 2.000068, \n                    \"omitted\": false, \n                    \"seconds\": 0.999903976917267, \n                    \"sender\": false, \n                    \"socket\": 5, \n                    \"start\": 1.000164\n                }\n            ], \n            \"sum\": {\n                \"bits_per_second\": 9383941.074950203, \n                \"bytes\": 1172880, \n                \"end\": 2.000068, \n                \"omitted\": false, \n                \"seconds\": 0.999903976917267, \n                \"sender\": false, \n                \"start\": 1.000164\n            }\n        }, \n        {\n            \"streams\": [\n                {\n                    \"bits_per_second\": 10854273.3434758, \n                    \"bytes\": 1356776, \n                    \"end\": 3.000062, \n                    \"omitted\": false, \n                    \"seconds\": 0.9999939799308777, \n                    \"sender\": false, \n                    \"socket\": 5, \n                    \"start\": 2.000068\n                }\n            ], \n            \"sum\": {\n                \"bits_per_second\": 10854273.3434758, \n                \"bytes\": 1356776, \n                \"end\": 3.000062, \n                \"omitted\": false, \n                \"seconds\": 0.9999939799308777, \n                \"sender\": false, \n                \"start\": 2.000068\n            }\n        }, \n        {\n            \"streams\": [\n                {\n                    \"bits_per_second\": 14247949.729623668, \n                    \"bytes\": 1781040, \n                    \"end\": 4.000088, \n                    \"omitted\": false, \n                    \"seconds\": 1.000025987625122, \n                    \"sender\": false, \n                    \"socket\": 5, \n                    \"start\": 3.000062\n                }\n            ], \n            \"sum\": {\n                \"bits_per_second\": 14247949.729623668, \n                \"bytes\": 1781040, \n                \"end\": 4.000088, \n                \"omitted\": false, \n                \"seconds\": 1.000025987625122, \n                \"sender\": false, \n                \"start\": 3.000062\n            }\n        }, \n        {\n            \"streams\": [\n                {\n                    \"bits_per_second\": 17294722.324376363, \n                    \"bytes\": 2161864, \n                    \"end\": 5.000099, \n                    \"omitted\": false, \n                    \"seconds\": 1.0000109672546387, \n                    \"sender\": false, \n                    \"socket\": 5, \n                    \"start\": 4.000088\n                }\n            ], \n            \"sum\": {\n                \"bits_per_second\": 17294722.324376363, \n                \"bytes\": 2161864, \n                \"end\": 5.000099, \n                \"omitted\": false, \n                \"seconds\": 1.0000109672546387, \n                \"sender\": false, \n                \"start\": 4.000088\n            }\n        }, \n        {\n            \"streams\": [\n                {\n                    \"bits_per_second\": 12592110.470953451, \n                    \"bytes\": 1573976, \n                    \"end\": 6.000075, \n                    \"omitted\": false, \n                    \"seconds\": 0.9999759793281555, \n                    \"sender\": false, \n                    \"socket\": 5, \n                    \"start\": 5.000099\n                }\n            ], \n            \"sum\": {\n                \"bits_per_second\": 12592110.470953451, \n                \"bytes\": 1573976, \n                \"end\": 6.000075, \n                \"omitted\": false, \n                \"seconds\": 0.9999759793281555, \n                \"sender\": false, \n                \"start\": 5.000099\n            }\n        }, \n        {\n            \"streams\": [\n                {\n                    \"bits_per_second\": 11340826.579435924, \n                    \"bytes\": 1417592, \n                    \"end\": 7.000067, \n                    \"omitted\": false, \n                    \"seconds\": 0.9999920129776, \n                    \"sender\": false, \n                    \"socket\": 5, \n                    \"start\": 6.000075\n                }\n            ], \n            \"sum\": {\n                \"bits_per_second\": 11340826.579435924, \n                \"bytes\": 1417592, \n                \"end\": 7.000067, \n                \"omitted\": false, \n                \"seconds\": 0.9999920129776, \n                \"sender\": false, \n                \"start\": 6.000075\n            }\n        }, \n        {\n            \"streams\": [\n                {\n                    \"bits_per_second\": 14051630.699600063, \n                    \"bytes\": 1756424, \n                    \"end\": 8.00005, \n                    \"omitted\": false, \n                    \"seconds\": 0.999983012676239, \n                    \"sender\": false, \n                    \"socket\": 5, \n                    \"start\": 7.000067\n                }\n            ], \n            \"sum\": {\n                \"bits_per_second\": 14051630.699600063, \n                \"bytes\": 1756424, \n                \"end\": 8.00005, \n                \"omitted\": false, \n                \"seconds\": 0.999983012676239, \n                \"sender\": false, \n                \"start\": 7.000067\n            }\n        }, \n        {\n            \"streams\": [\n                {\n                    \"bits_per_second\": 13067052.638813889, \n                    \"bytes\": 1633344, \n                    \"end\": 9.000027, \n                    \"omitted\": false, \n                    \"seconds\": 0.9999769926071167, \n                    \"sender\": false, \n                    \"socket\": 5, \n                    \"start\": 8.00005\n                }\n            ], \n            \"sum\": {\n                \"bits_per_second\": 13067052.638813889, \n                \"bytes\": 1633344, \n                \"end\": 9.000027, \n                \"omitted\": false, \n                \"seconds\": 0.9999769926071167, \n                \"sender\": false, \n                \"start\": 8.00005\n            }\n        }, \n        {\n            \"streams\": [\n                {\n                    \"bits_per_second\": 13193568.900753535, \n                    \"bytes\": 1649272, \n                    \"end\": 10.000073, \n                    \"omitted\": false, \n                    \"seconds\": 1.0000460147857666, \n                    \"sender\": false, \n                    \"socket\": 5, \n                    \"start\": 9.000027\n                }\n            ], \n            \"sum\": {\n                \"bits_per_second\": 13193568.900753535, \n                \"bytes\": 1649272, \n                \"end\": 10.000073, \n                \"omitted\": false, \n                \"seconds\": 1.0000460147857666, \n                \"sender\": false, \n                \"start\": 9.000027\n            }\n        }, \n        {\n            \"streams\": [\n                {\n                    \"bits_per_second\": 11035860.582522029, \n                    \"bytes\": 209960, \n                    \"end\": 10.152275, \n                    \"omitted\": false, \n                    \"seconds\": 0.15220199525356293, \n                    \"sender\": false, \n                    \"socket\": 5, \n                    \"start\": 10.000073\n                }\n            ], \n            \"sum\": {\n                \"bits_per_second\": 11035860.582522029, \n                \"bytes\": 209960, \n                \"end\": 10.152275, \n                \"omitted\": false, \n                \"seconds\": 0.15220199525356293, \n                \"sender\": false, \n                \"start\": 10.000073\n            }\n        }\n    ], \n    \"start\": {\n        \"accepted_connection\": {\n            \"host\": \"172.16.0.2\", \n            \"port\": 59839\n        }, \n        \"connected\": [\n            {\n                \"local_host\": \"172.16.0.1\", \n                \"local_port\": 5201, \n                \"remote_host\": \"172.16.0.2\", \n                \"remote_port\": 50847, \n                \"socket\": 5\n            }\n        ], \n        \"cookie\": \"epliu7sn7p6tndgyyrn7o22z3h2j4jm6n5lk\", \n        \"fq_rate\": 0, \n        \"rcvbuf_actual\": 87380, \n        \"sndbuf_actual\": 65536, \n        \"sock_bufsize\": 0, \n        \"system_info\": \"REDACTED\", \n        \"target_bitrate\": 0, \n        \"tcp_mss_default\": 0, \n        \"test_start\": {\n            \"bidir\": 0, \n            \"blksize\": 131072, \n            \"blocks\": 0, \n            \"bytes\": 0, \n            \"duration\": 10, \n            \"fqrate\": 0, \n            \"num_streams\": 1, \n            \"omit\": 0, \n            \"protocol\": \"TCP\", \n            \"reverse\": 0, \n            \"target_bitrate\": 0, \n            \"tos\": 0\n        }, \n        \"timestamp\": {\n            \"time\": \"Sat, 12 Oct 2024 02:20:18 GMT\", \n            \"timesecs\": 1728699618\n        }, \n        \"version\": \"iperf 3.14\"\n    }\n}\n","summary":{"streams":[{"end":10.00057,"rtt":193694,"start":0,"stream-id":5,"retransmits":296,"throughput-bits":14993782.1544172,"throughput-bytes":18743296}],"summary":{"end":10.00057,"start":0,"retransmits":296,"throughput-bits":14993782.1544172,"throughput-bytes":18743296,"receiver-throughput-bits":12212391.0158068}},"intervals":[{"streams":[{"end":1.000224,"rtt":247350,"start":0,"omitted":false,"stream-id":5,"retransmits":74,"tcp-window-size":472048,"throughput-bits":34595258.86076267,"throughput-bytes":4325376}],"summary":{"end":1.000224,"start":0,"omitted":false,"retransmits":74,"throughput-bits":34595258.86076267,"throughput-bytes":4325376}},{"streams":[{"end":2.000151,"rtt":374343,"start":1.000224,"omitted":false,"stream-id":5,"retransmits":212,"tcp-window-size":251952,"throughput-bits":10486525.68090672,"throughput-bytes":1310720}],"summary":{"end":2.000151,"start":1.000224,"omitted":false,"retransmits":212,"throughput-bits":10486525.68090672,"throughput-bytes":1310720}},{"streams":[{"end":3.000654,"rtt":170541,"start":2.000151,"omitted":false,"stream-id":5,"retransmits":0,"tcp-window-size":205616,"throughput-bits":10480488.901067542,"throughput-bytes":1310720}],"summary":{"end":3.000654,"start":2.000151,"omitted":false,"retransmits":0,"throughput-bits":10480488.901067542,"throughput-bytes":1310720}},{"streams":[{"end":4.000678,"rtt":98833,"start":3.000654,"omitted":false,"stream-id":5,"retransmits":0,"tcp-window-size":217200,"throughput-bits":10485508.756020075,"throughput-bytes":1310720}],"summary":{"end":4.000678,"start":3.000654,"omitted":false,"retransmits":0,"throughput-bits":10485508.756020075,"throughput-bytes":1310720}},{"streams":[{"end":5.000335,"rtt":102189,"start":4.000678,"omitted":false,"stream-id":5,"retransmits":0,"tcp-window-size":247608,"throughput-bits":20978716.218480907,"throughput-bytes":2621440}],"summary":{"end":5.000335,"start":4.000678,"omitted":false,"retransmits":0,"throughput-bits":20978716.218480907,"throughput-bytes":2621440}},{"streams":[{"end":6.000794,"rtt":211416,"start":5.000335,"omitted":false,"stream-id":5,"retransmits":0,"tcp-window-size":282360,"throughput-bits":10480949.707711376,"throughput-bytes":1310720}],"summary":{"end":6.000794,"start":5.000335,"omitted":false,"retransmits":0,"throughput-bits":10480949.707711376,"throughput-bytes":1310720}},{"streams":[{"end":7.001352,"rtt":189608,"start":6.000794,"omitted":false,"stream-id":5,"retransmits":0,"tcp-window-size":325800,"throughput-bits":10479912.013285853,"throughput-bytes":1310720}],"summary":{"end":7.001352,"start":6.000794,"omitted":false,"retransmits":0,"throughput-bits":10479912.013285853,"throughput-bytes":1310720}},{"streams":[{"end":8.000146,"rtt":238384,"start":7.001352,"omitted":false,"stream-id":5,"retransmits":0,"tcp-window-size":385168,"throughput-bits":20996841.78758909,"throughput-bytes":2621440}],"summary":{"end":8.000146,"start":7.001352,"omitted":false,"retransmits":0,"throughput-bits":20996841.78758909,"throughput-bytes":2621440}},{"streams":[{"end":9.000363,"rtt":144185,"start":8.000146,"omitted":false,"stream-id":5,"retransmits":10,"tcp-window-size":205616,"throughput-bits":10483485.493479,"throughput-bytes":1310720}],"summary":{"end":9.000363,"start":8.000146,"omitted":false,"retransmits":10,"throughput-bits":10483485.493479,"throughput-bytes":1310720}},{"streams":[{"end":10.00057,"rtt":160092,"start":9.000363,"omitted":false,"stream-id":5,"retransmits":0,"tcp-window-size":217200,"throughput-bits":10483590.448982783,"throughput-bytes":1310720}],"summary":{"end":10.00057,"start":9.000363,"omitted":false,"retransmits":0,"throughput-bits":10483590.448982783,"throughput-bytes":1310720}}],"succeeded":true}
