{"diags":"Participant 0:\n/usr/bin/iperf3 -p 5201 -B 10.0.0.1 -c 10.0.0.2 -t 60 --json --rsa-public-key-path /var/run/pscheduler-server/runner/tmp/tmp4_eh5jem/tmpg55gwirx/public-key --username wvJtWXyplI1nkYU7n45l\n\n{\n    \"end\": {\n        \"cpu_utilization_percent\": {\n            \"host_system\": 2.0524128073726833, \n            \"host_total\": 2.0867273701074813, \n            \"host_user\": 0.03431456273479815, \n            \"remote_system\": 5.198483892741943, \n            \"remote_total\": 5.87487734077871, \n            \"remote_user\": 0.6763934480367667\n        }, \n        \"receiver_tcp_congestion\": \"htcp\", \n        \"sender_tcp_congestion\": \"htcp\", \n        \"streams\": [\n            {\n                \"receiver\": {\n                    \"bits_per_second\": 865535251.554414, \n                    \"bytes\": 6499843216, \n                    \"end\": 60.076982, \n                    \"seconds\": 60.000092, \n                    \"sender\": true, \n                    \"socket\": 5, \n                    \"start\": 0\n                }, \n                \"sender\": {\n                    \"bits_per_second\": 867013736.1789378, \n                    \"bytes\": 6502612992, \n                    \"end\": 60.000092, \n                    \"max_rtt\": 77094, \n                    \"max_snd_cwnd\": 16698336, \n                    \"max_snd_wnd\": 0, \n                    \"mean_rtt\": 77087, \n                    \"min_rtt\": 77080, \n                    \"retransmits\": 0, \n                    \"seconds\": 60.000092, \n                    \"sender\": true, \n                    \"socket\": 5, \n                    \"start\": 0\n                }\n            }\n        ], \n        \"sum_received\": {\n            \"bits_per_second\": 865535251.554414, \n            \"bytes\": 6499843216, \n            \"end\": 60.076982, \n            \"seconds\": 60.076982, \n            \"sender\": true, \n            \"start\": 0\n        }, \n        \"sum_sent\": {\n            \"bits_per_second\": 867013736.1789378, \n            \"bytes\": 6502612992, \n            \"end\": 60.000092, \n            \"retransmits\": 0, \n            \"seconds\": 60.000092, \n            \"sender\": true, \n            \"start\": 0\n        }\n    }, \n    \"intervals\": [\n        {\n            \"streams\": [\n                {\n                    \"bits_per_second\": 955183049.584048, \n                    \"bytes\": 119406592, \n                    \"end\": 1.000073, \n                    \"omitted\": false, \n                    \"pmtu\": 1500, \n                    \"retransmits\": 0, \n                    \"rtt\": 77088, \n                    \"rttvar\": 8, \n                    \"seconds\": 1.000072956085205, \n                    \"sender\": true, \n                    \"snd_cwnd\": 16698336, \n                    \"snd_wnd\": -1, \n                    \"socket\": 5, \n                    \"start\": 0\n                }\n            ], \n            \"sum\": {\n                \"bits_per_second\": 955183049.584048, \n                \"bytes\": 119406592, \n                \"end\": 1.000073, \n                \"omitted\": false, \n                \"retransmits\": 0, \n                \"seconds\": 1.000072956085205, \n                \"sender\": true, \n                \"start\": 0\n            }\n        }, \n        {\n            \"streams\": [\n                {\n                    \"bits_per_second\": 870227619.4034243, \n                    \"bytes\": 108789760, \n                    \"end\": 2.000177, \n                    \"omitted\": false, \n                    \"pmtu\": 1500, \n                    \"retransmits\": 0, \n                    \"rtt\": 77084, \n                    \"rttvar\": 10, \n                    \"seconds\": 1.0001039505004883, \n                    \"sender\": true, \n                    \"snd_cwnd\": 16698336, \n                    \"snd_wnd\": -1, \n                    \"socket\": 5, \n                    \"start\": 1.000073\n                }\n            ], \n            \"sum\": {\n                \"bits_per_second\": 870227619.4034243, \n                \"bytes\": 108789760, \n                \"end\": 2.000177, \n                \"omitted\": false, \n                \"retransmits\": 0, \n                \"seconds\": 1.0001039505004883, \n                \"sender\": true, \n                \"start\": 1.000073\n            }\n        }, \n        {\n            \"streams\": [\n                {\n                    \"bits_per_second\": 859918326.1020374, \n                    \"bytes\": 107479040, \n                    \"end\": 3.000077, \n                    \"omitted\": false, \n                    \"pmtu\": 1500, \n                    \"retransmits\": 0, \n                    \"rtt\": 77085, \n                    \"rttvar\": 3, \n                    \"seconds\": 0.999899983406067, \n                    \"sender\": true, \n                    \"snd_cwnd\": 16698336, \n                    \"snd_wnd\": -1, \n                    \"socket\": 5, \n                    \"start\": 2.000177\n                }\n            ], \n            \"sum\": {\n                \"bits_per_second\": 859918326.1020374, \n                \"bytes\": 107479040, \n                \"end\": 3.000077, \n                \"omitted\": false, \n                \"retransmits\": 0, \n                \"seconds\": 0.999899983406067, \n                \"sender\": true, \n                \"start\": 2.000177\n            }\n        }, \n        {\n            \"streams\": [\n                {\n                    \"bits_per_second\": 870226685.848523, \n                    \"bytes\": 108789760, \n                    \"end\": 4.000182, \n                    \"omitted\": false, \n                    \"pmtu\": 1500, \n                    \"retransmits\": 0, \n                    \"rtt\": 77080, \n                    \"rttvar\": 12, \n                    \"seconds\": 1.0001050233840942, \n                    \"sender\": true, \n                    \"snd_cwnd\": 16698336, \n                    \"snd_wnd\": -1, \n                    \"socket\": 5, \n                    \"start\": 3.000077\n                }\n            ], \n            \"sum\": {\n                \"bits_per_second\": 870226685.848523, \n                \"bytes\": 108789760, \n                \"end\": 4.000182, \n                \"omitted\": false, \n                \"retransmits\": 0, \n                \"seconds\": 1.0001050233840942, \n                \"sender\": true, \n                \"start\": 3.000077\n            }\n        }, \n        {\n            \"streams\": [\n                {\n                    \"bits_per_second\": 859904537.3150227, \n                    \"bytes\": 107479040, \n                    \"end\": 5.000098, \n                    \"omitted\": false, \n                    \"pmtu\": 1500, \n                    \"retransmits\": 0, \n                    \"rtt\": 77090, \n                    \"rttvar\": 5, \n                    \"seconds\": 0.9999160170555115, \n                    \"sender\": true, \n                    \"snd_cwnd\": 16698336, \n                    \"snd_wnd\": -1, \n                    \"socket\": 5, \n                    \"start\": 4.000182\n                }\n            ], \n            \"sum\": {\n                \"bits_per_second\": 859904537.3150227, \n                \"bytes\": 107479040, \n                \"end\": 5.000098, \n                \"omitted\": false, \n                \"retransmits\": 0, \n                \"seconds\": 0.9999160170555115, \n                \"sender\": true, \n                \"start\": 4.000182\n            }\n        }, \n        {\n            \"streams\": [\n                {\n                    \"bits_per_second\": 870354653.4118614, \n                    \"bytes\": 108789760, \n                    \"end\": 6.000056, \n                    \"omitted\": false, \n                    \"pmtu\": 1500, \n                    \"retransmits\": 0, \n                    \"rtt\": 77081, \n                    \"rttvar\": 4, \n                    \"seconds\": 0.9999579787254333, \n                    \"sender\": true, \n                    \"snd_cwnd\": 16698336, \n                    \"snd_wnd\": -1, \n                    \"socket\": 5, \n                    \"start\": 5.000098\n                }\n            ], \n            \"sum\": {\n                \"bits_per_second\": 870354653.4118614, \n                \"bytes\": 108789760, \n                \"end\": 6.000056, \n                \"omitted\": false, \n                \"retransmits\": 0, \n                \"seconds\": 0.9999579787254333, \n                \"sender\": true, \n                \"start\": 5.000098\n            }\n        }, \n        {\n            \"streams\": [\n                {\n                    \"bits_per_second\": 870313722.521817, \n                    \"bytes\": 108789760, \n                    \"end\": 7.000061, \n                    \"omitted\": false, \n                    \"pmtu\": 1500, \n                    \"retransmits\": 0, \n                    \"rtt\": 77085, \n                    \"rttvar\": 8, \n                    \"seconds\": 1.0000050067901611, \n                    \"sender\": true, \n                    \"snd_cwnd\": 16698336, \n                    \"snd_wnd\": -1, \n                    \"socket\": 5, \n                    \"start\": 6.000056\n                }\n            ], \n            \"sum\": {\n                \"bits_per_second\": 870313722.521817, \n                \"bytes\": 108789760, \n                \"end\": 7.000061, \n                \"omitted\": false, \n                \"retransmits\": 0, \n                \"seconds\": 1.0000050067901611, \n                \"sender\": true, \n                \"start\": 6.000056\n            }\n        }, \n        {\n            \"streams\": [\n                {\n                    \"bits_per_second\": 859836625.0215544, \n                    \"bytes\": 107479040, \n                    \"end\": 8.000056, \n                    \"omitted\": false, \n                    \"pmtu\": 1500, \n                    \"retransmits\": 0, \n                    \"rtt\": 77084, \n                    \"rttvar\": 8, \n                    \"seconds\": 0.999994993209839, \n                    \"sender\": true, \n                    \"snd_cwnd\": 16698336, \n                    \"snd_wnd\": -1, \n                    \"socket\": 5, \n                    \"start\": 7.000061\n                }\n            ], \n            \"sum\": {\n                \"bits_per_second\": 859836625.0215544, \n                \"bytes\": 107479040, \n                \"end\": 8.000056, \n                \"omitted\": false, \n                \"retransmits\": 0, \n                \"seconds\": 0.999994993209839, \n                \"sender\": true, \n                \"start\": 7.000061\n            }\n        }, \n        {\n            \"streams\": [\n                {\n                    \"bits_per_second\": 870297226.749666, \n                    \"bytes\": 108789760, \n                    \"end\": 9.00008, \n                    \"omitted\": false, \n                    \"pmtu\": 1500, \n                    \"retransmits\": 0, \n                    \"rtt\": 77088, \n                    \"rttvar\": 8, \n                    \"seconds\": 1.0000239610672, \n                    \"sender\": true, \n                    \"snd_cwnd\": 16698336, \n                    \"snd_wnd\": -1, \n                    \"socket\": 5, \n                    \"start\": 8.000056\n                }\n            ], \n            \"sum\": {\n                \"bits_per_second\": 870297226.749666, \n                \"bytes\": 108789760, \n                \"end\": 9.00008, \n                \"omitted\": false, \n                \"retransmits\": 0, \n                \"seconds\": 1.0000239610672, \n                \"sender\": true, \n                \"start\": 8.000056\n            }\n        }, \n        {\n            \"streams\": [\n                {\n                    \"bits_per_second\": 859751455.105839, \n                    \"bytes\": 107479040, \n                    \"end\": 10.000174, \n                    \"omitted\": false, \n                    \"pmtu\": 1500, \n                    \"retransmits\": 0, \n                    \"rtt\": 77084, \n                    \"rttvar\": 7, \n                    \"seconds\": 1.0000940561294556, \n                    \"sender\": true, \n                    \"snd_cwnd\": 16698336, \n                    \"snd_wnd\": -1, \n                    \"socket\": 5, \n                    \"start\": 9.00008\n                }\n            ], \n            \"sum\": {\n                \"bits_per_second\": 859751455.105839, \n                \"bytes\": 107479040, \n                \"end\": 10.000174, \n                \"omitted\": false, \n                \"retransmits\": 0, \n                \"seconds\": 1.0000940561294556, \n                \"sender\": true, \n                \"start\": 9.00008\n            }\n        }, \n        {\n            \"streams\": [\n                {\n                    \"bits_per_second\": 870416446.1163948, \n                    \"bytes\": 108789760, \n                    \"end\": 11.000061, \n                    \"omitted\": false, \n                    \"pmtu\": 1500, \n                    \"retransmits\": 0, \n                    \"rtt\": 77088, \n                    \"rttvar\": 12, \n                    \"seconds\": 0.999886989593506, \n                    \"sender\": true, \n                    \"snd_cwnd\": 16698336, \n                    \"snd_wnd\": -1, \n                    \"socket\": 5, \n                    \"start\": 10.000174\n                }\n            ], \n            \"sum\": {\n                \"bits_per_second\": 870416446.1163948, \n                \"bytes\": 108789760, \n                \"end\": 11.000061, \n                \"omitted\": false, \n                \"retransmits\": 0, \n                \"seconds\": 0.999886989593506, \n                \"sender\": true, \n                \"start\": 10.000174\n            }\n        }, \n        {\n            \"streams\": [\n                {\n                    \"bits_per_second\": 859826272.542534, \n                    \"bytes\": 107479040, \n                    \"end\": 12.000068, \n                    \"omitted\": false, \n                    \"pmtu\": 1500, \n                    \"retransmits\": 0, \n                    \"rtt\": 77086, \n                    \"rttvar\": 8, \n                    \"seconds\": 1.0000070333480835, \n                    \"sender\": true, \n                    \"snd_cwnd\": 16698336, \n                    \"snd_wnd\": -1, \n                    \"socket\": 5, \n                    \"start\": 11.000061\n                }\n            ], \n            \"sum\": {\n                \"bits_per_second\": 859826272.542534, \n                \"bytes\": 107479040, \n                \"end\": 12.000068, \n                \"omitted\": false, \n                \"retransmits\": 0, \n                \"seconds\": 1.0000070333480835, \n                \"sender\": true, \n                \"start\": 11.000061\n            }\n        }, \n        {\n            \"streams\": [\n                {\n                    \"bits_per_second\": 870203243.904309, \n                    \"bytes\": 108789760, \n                    \"end\": 13.0002, \n                    \"omitted\": false, \n                    \"pmtu\": 1500, \n                    \"retransmits\": 0, \n                    \"rtt\": 77081, \n                    \"rttvar\": 12, \n                    \"seconds\": 1.0001319646835327, \n                    \"sender\": true, \n                    \"snd_cwnd\": 16698336, \n                    \"snd_wnd\": -1, \n                    \"socket\": 5, \n                    \"start\": 12.000068\n                }\n            ], \n            \"sum\": {\n                \"bits_per_second\": 870203243.904309, \n                \"bytes\": 108789760, \n                \"end\": 13.0002, \n                \"omitted\": false, \n                \"retransmits\": 0, \n                \"seconds\": 1.0001319646835327, \n                \"sender\": true, \n                \"start\": 12.000068\n            }\n        }, \n        {\n            \"streams\": [\n                {\n                    \"bits_per_second\": 859935498.6298002, \n                    \"bytes\": 107479040, \n                    \"end\": 14.00008, \n                    \"omitted\": false, \n                    \"pmtu\": 1500, \n                    \"retransmits\": 0, \n                    \"rtt\": 77091, \n                    \"rttvar\": 7, \n                    \"seconds\": 0.999880015850067, \n                    \"sender\": true, \n                    \"snd_cwnd\": 16698336, \n                    \"snd_wnd\": -1, \n                    \"socket\": 5, \n                    \"start\": 13.0002\n                }\n            ], \n            \"sum\": {\n                \"bits_per_second\": 859935498.6298002, \n                \"bytes\": 107479040, \n                \"end\": 14.00008, \n                \"omitted\": false, \n                \"retransmits\": 0, \n                \"seconds\": 0.999880015850067, \n                \"sender\": true, \n                \"start\": 13.0002\n            }\n        }, \n        {\n            \"streams\": [\n                {\n                    \"bits_per_second\": 870337222.296018, \n                    \"bytes\": 108789760, \n                    \"end\": 15.000058, \n                    \"omitted\": false, \n                    \"pmtu\": 1500, \n                    \"retransmits\": 0, \n                    \"rtt\": 77084, \n                    \"rttvar\": 7, \n                    \"seconds\": 0.999978005886078, \n                    \"sender\": true, \n                    \"snd_cwnd\": 16698336, \n                    \"snd_wnd\": -1, \n                    \"socket\": 5, \n                    \"start\": 14.00008\n                }\n            ], \n            \"sum\": {\n                \"bits_per_second\": 870337222.296018, \n                \"bytes\": 108789760, \n                \"end\": 15.000058, \n                \"omitted\": false, \n                \"retransmits\": 0, \n                \"seconds\": 0.999978005886078, \n                \"sender\": true, \n                \"start\": 14.00008\n            }\n        }, \n        {\n            \"streams\": [\n                {\n                    \"bits_per_second\": 859818585.2194, \n                    \"bytes\": 107479040, \n                    \"end\": 16.000074, \n                    \"omitted\": false, \n                    \"pmtu\": 1500, \n                    \"retransmits\": 0, \n                    \"rtt\": 77090, \n                    \"rttvar\": 5, \n                    \"seconds\": 1.0000159740448, \n                    \"sender\": true, \n                    \"snd_cwnd\": 16698336, \n                    \"snd_wnd\": -1, \n                    \"socket\": 5, \n                    \"start\": 15.000058\n                }\n            ], \n            \"sum\": {\n                \"bits_per_second\": 859818585.2194, \n                \"bytes\": 107479040, \n                \"end\": 16.000074, \n                \"omitted\": false, \n                \"retransmits\": 0, \n                \"seconds\": 1.0000159740448, \n                \"sender\": true, \n                \"start\": 15.000058\n            }\n        }, \n        {\n            \"streams\": [\n                {\n                    \"bits_per_second\": 870331982.7220827, \n                    \"bytes\": 108789760, \n                    \"end\": 17.000058, \n                    \"omitted\": false, \n                    \"pmtu\": 1500, \n                    \"retransmits\": 0, \n                    \"rtt\": 77094, \n                    \"rttvar\": 7, \n                    \"seconds\": 0.9999840259552002, \n                    \"sender\": true, \n                    \"snd_cwnd\": 16698336, \n                    \"snd_wnd\": -1, \n                    \"socket\": 5, \n                    \"start\": 16.000074\n                }\n            ], \n            \"sum\": {\n                \"bits_per_second\": 870331982.7220827, \n                \"bytes\": 108789760, \n                \"end\": 17.000058, \n                \"omitted\": false, \n                \"retransmits\": 0, \n                \"seconds\": 0.9999840259552002, \n                \"sender\": true, \n                \"start\": 16.000074\n            }\n        }, \n        {\n            \"streams\": [\n                {\n                    \"bits_per_second\": 870335510.3490804, \n                    \"bytes\": 108789760, \n                    \"end\": 18.000038, \n                    \"omitted\": false, \n                    \"pmtu\": 1500, \n                    \"retransmits\": 0, \n                    \"rtt\": 77088, \n                    \"rttvar\": 10, \n                    \"seconds\": 0.9999799728393555, \n                    \"sender\": true, \n                    \"snd_cwnd\": 16698336, \n                    \"snd_wnd\": -1, \n                    \"socket\": 5, \n                    \"start\": 17.000058\n                }\n            ], \n            \"sum\": {\n                \"bits_per_second\": 870335510.3490804, \n                \"bytes\": 108789760, \n                \"end\": 18.000038, \n                \"omitted\": false, \n                \"retransmits\": 0, \n                \"seconds\": 0.9999799728393555, \n                \"sender\": true, \n                \"start\": 17.000058\n            }\n        }, \n        {\n            \"streams\": [\n                {\n                    \"bits_per_second\": 859738645.2065517, \n                    \"bytes\": 107479040, \n                    \"end\": 19.000147, \n                    \"omitted\": false, \n                    \"pmtu\": 1500, \n                    \"retransmits\": 0, \n                    \"rtt\": 77088, \n                    \"rttvar\": 12, \n                    \"seconds\": 1.0001089572906494, \n                    \"sender\": true, \n                    \"snd_cwnd\": 16698336, \n                    \"snd_wnd\": -1, \n                    \"socket\": 5, \n                    \"start\": 18.000038\n                }\n            ], \n            \"sum\": {\n                \"bits_per_second\": 859738645.2065517, \n                \"bytes\": 107479040, \n                \"end\": 19.000147, \n                \"omitted\": false, \n                \"retransmits\": 0, \n                \"seconds\": 1.0001089572906494, \n                \"sender\": true, \n                \"start\": 18.000038\n            }\n        }, \n        {\n            \"streams\": [\n                {\n                    \"bits_per_second\": 870394654.23673, \n                    \"bytes\": 108789760, \n                    \"end\": 20.000059, \n                    \"omitted\": false, \n                    \"pmtu\": 1500, \n                    \"retransmits\": 0, \n                    \"rtt\": 77089, \n                    \"rttvar\": 7, \n                    \"seconds\": 0.9999120235443115, \n                    \"sender\": true, \n                    \"snd_cwnd\": 16698336, \n                    \"snd_wnd\": -1, \n                    \"socket\": 5, \n                    \"start\": 19.000147\n                }\n            ], \n            \"sum\": {\n                \"bits_per_second\": 870394654.23673, \n                \"bytes\": 108789760, \n                \"end\": 20.000059, \n                \"omitted\": false, \n                \"retransmits\": 0, \n                \"seconds\": 0.9999120235443115, \n                \"sender\": true, \n                \"start\": 19.000147\n            }\n        }, \n        {\n            \"streams\": [\n                {\n                    \"bits_per_second\": 859816842.7785993, \n                    \"bytes\": 107479040, \n                    \"end\": 21.000077, \n                    \"omitted\": false, \n                    \"pmtu\": 1500, \n                    \"retransmits\": 0, \n                    \"rtt\": 77089, \n                    \"rttvar\": 5, \n                    \"seconds\": 1.0000180006027222, \n                    \"sender\": true, \n                    \"snd_cwnd\": 16698336, \n                    \"snd_wnd\": -1, \n                    \"socket\": 5, \n                    \"start\": 20.000059\n                }\n            ], \n            \"sum\": {\n                \"bits_per_second\": 859816842.7785993, \n                \"bytes\": 107479040, \n                \"end\": 21.000077, \n                \"omitted\": false, \n                \"retransmits\": 0, \n                \"seconds\": 1.0000180006027222, \n                \"sender\": true, \n                \"start\": 20.000059\n            }\n        }, \n        {\n            \"streams\": [\n                {\n                    \"bits_per_second\": 870334628.43965, \n                    \"bytes\": 108789760, \n                    \"end\": 22.000058, \n                    \"omitted\": false, \n                    \"pmtu\": 1500, \n                    \"retransmits\": 0, \n                    \"rtt\": 77087, \n                    \"rttvar\": 10, \n                    \"seconds\": 0.9999809861183167, \n                    \"sender\": true, \n                    \"snd_cwnd\": 16698336, \n                    \"snd_wnd\": -1, \n                    \"socket\": 5, \n                    \"start\": 21.000077\n                }\n            ], \n            \"sum\": {\n                \"bits_per_second\": 870334628.43965, \n                \"bytes\": 108789760, \n                \"end\": 22.000058, \n                \"omitted\": false, \n                \"retransmits\": 0, \n                \"seconds\": 0.9999809861183167, \n                \"sender\": true, \n                \"start\": 21.000077\n            }\n        }, \n        {\n            \"streams\": [\n                {\n                    \"bits_per_second\": 859818585.2194, \n                    \"bytes\": 107479040, \n                    \"end\": 23.000074, \n                    \"omitted\": false, \n                    \"pmtu\": 1500, \n                    \"retransmits\": 0, \n                    \"rtt\": 77090, \n                    \"rttvar\": 7, \n                    \"seconds\": 1.0000159740448, \n                    \"sender\": true, \n                    \"snd_cwnd\": 16698336, \n                    \"snd_wnd\": -1, \n                    \"socket\": 5, \n                    \"start\": 22.000058\n                }\n            ], \n            \"sum\": {\n                \"bits_per_second\": 859818585.2194, \n                \"bytes\": 107479040, \n                \"end\": 23.000074, \n                \"omitted\": false, \n                \"retransmits\": 0, \n                \"seconds\": 1.0000159740448, \n                \"sender\": true, \n                \"start\": 22.000058\n            }\n        }, \n        {\n            \"streams\": [\n                {\n                    \"bits_per_second\": 870329388.8969457, \n                    \"bytes\": 108789760, \n                    \"end\": 24.000061, \n                    \"omitted\": false, \n                    \"pmtu\": 1500, \n                    \"retransmits\": 0, \n                    \"rtt\": 77090, \n                    \"rttvar\": 9, \n                    \"seconds\": 0.999987006187439, \n                    \"sender\": true, \n                    \"snd_cwnd\": 16698336, \n                    \"snd_wnd\": -1, \n                    \"socket\": 5, \n                    \"start\": 23.000074\n                }\n            ], \n            \"sum\": {\n                \"bits_per_second\": 870329388.8969457, \n                \"bytes\": 108789760, \n                \"end\": 24.000061, \n                \"omitted\": false, \n                \"retransmits\": 0, \n                \"seconds\": 0.999987006187439, \n                \"sender\": true, \n                \"start\": 23.000074\n            }\n        }, \n        {\n            \"streams\": [\n                {\n                    \"bits_per_second\": 859825452.5548505, \n                    \"bytes\": 107479040, \n                    \"end\": 25.000069, \n                    \"omitted\": false, \n                    \"pmtu\": 1500, \n                    \"retransmits\": 0, \n                    \"rtt\": 77089, \n                    \"rttvar\": 6, \n                    \"seconds\": 1.0000079870224, \n                    \"sender\": true, \n                    \"snd_cwnd\": 16698336, \n                    \"snd_wnd\": -1, \n                    \"socket\": 5, \n                    \"start\": 24.000061\n                }\n            ], \n            \"sum\": {\n                \"bits_per_second\": 859825452.5548505, \n                \"bytes\": 107479040, \n                \"end\": 25.000069, \n                \"omitted\": false, \n                \"retransmits\": 0, \n                \"seconds\": 1.0000079870224, \n                \"sender\": true, \n                \"start\": 24.000061\n            }\n        }, \n        {\n            \"streams\": [\n                {\n                    \"bits_per_second\": 870314552.5142974, \n                    \"bytes\": 108789760, \n                    \"end\": 26.000073, \n                    \"omitted\": false, \n                    \"pmtu\": 1500, \n                    \"retransmits\": 0, \n                    \"rtt\": 77092, \n                    \"rttvar\": 13, \n                    \"seconds\": 1.0000040531158447, \n                    \"sender\": true, \n                    \"snd_cwnd\": 16698336, \n                    \"snd_wnd\": -1, \n                    \"socket\": 5, \n                    \"start\": 25.000069\n                }\n            ], \n            \"sum\": {\n                \"bits_per_second\": 870314552.5142974, \n                \"bytes\": 108789760, \n                \"end\": 26.000073, \n                \"omitted\": false, \n                \"retransmits\": 0, \n                \"seconds\": 1.0000040531158447, \n                \"sender\": true, \n                \"start\": 25.000069\n            }\n        }, \n        {\n            \"streams\": [\n                {\n                    \"bits_per_second\": 859840930.0862178, \n                    \"bytes\": 107479040, \n                    \"end\": 27.000063, \n                    \"omitted\": false, \n                    \"pmtu\": 1500, \n                    \"retransmits\": 0, \n                    \"rtt\": 77084, \n                    \"rttvar\": 8, \n                    \"seconds\": 0.9999899864196777, \n                    \"sender\": true, \n                    \"snd_cwnd\": 16698336, \n                    \"snd_wnd\": -1, \n                    \"socket\": 5, \n                    \"start\": 26.000073\n                }\n            ], \n            \"sum\": {\n                \"bits_per_second\": 859840930.0862178, \n                \"bytes\": 107479040, \n                \"end\": 27.000063, \n                \"omitted\": false, \n                \"retransmits\": 0, \n                \"seconds\": 0.9999899864196777, \n                \"sender\": true, \n                \"start\": 26.000073\n            }\n        }, \n        {\n            \"streams\": [\n                {\n                    \"bits_per_second\": 870302414.031997, \n                    \"bytes\": 108789760, \n                    \"end\": 28.000081, \n                    \"omitted\": false, \n                    \"pmtu\": 1500, \n                    \"retransmits\": 0, \n                    \"rtt\": 77089, \n                    \"rttvar\": 8, \n                    \"seconds\": 1.0000180006027222, \n                    \"sender\": true, \n                    \"snd_cwnd\": 16698336, \n                    \"snd_wnd\": -1, \n                    \"socket\": 5, \n                    \"start\": 27.000063\n                }\n            ], \n            \"sum\": {\n                \"bits_per_second\": 870302414.031997, \n                \"bytes\": 108789760, \n                \"end\": 28.000081, \n                \"omitted\": false, \n                \"retransmits\": 0, \n                \"seconds\": 1.0000180006027222, \n                \"sender\": true, \n                \"start\": 27.000063\n            }\n        }, \n        {\n            \"streams\": [\n                {\n                    \"bits_per_second\": 870335510.3490804, \n                    \"bytes\": 108789760, \n                    \"end\": 29.000061, \n                    \"omitted\": false, \n                    \"pmtu\": 1500, \n                    \"retransmits\": 0, \n                    \"rtt\": 77084, \n                    \"rttvar\": 5, \n                    \"seconds\": 0.9999799728393555, \n                    \"sender\": true, \n                    \"snd_cwnd\": 16698336, \n                    \"snd_wnd\": -1, \n                    \"socket\": 5, \n                    \"start\": 28.000081\n                }\n            ], \n            \"sum\": {\n                \"bits_per_second\": 870335510.3490804, \n                \"bytes\": 108789760, \n                \"end\": 29.000061, \n                \"omitted\": false, \n                \"retransmits\": 0, \n                \"seconds\": 0.9999799728393555, \n                \"sender\": true, \n                \"start\": 28.000081\n            }\n        }, \n        {\n            \"streams\": [\n                {\n                    \"bits_per_second\": 859821967.624644, \n                    \"bytes\": 107479040, \n                    \"end\": 30.000073, \n                    \"omitted\": false, \n                    \"pmtu\": 1500, \n                    \"retransmits\": 0, \n                    \"rtt\": 77090, \n                    \"rttvar\": 9, \n                    \"seconds\": 1.0000120401382446, \n                    \"sender\": true, \n                    \"snd_cwnd\": 16698336, \n                    \"snd_wnd\": -1, \n                    \"socket\": 5, \n                    \"start\": 29.000061\n                }\n            ], \n            \"sum\": {\n                \"bits_per_second\": 859821967.624644, \n                \"bytes\": 107479040, \n                \"end\": 30.000073, \n                \"omitted\": false, \n                \"retransmits\": 0, \n                \"seconds\": 1.0000120401382446, \n                \"sender\": true, \n                \"start\": 29.000061\n            }\n        }, \n        {\n            \"streams\": [\n                {\n                    \"bits_per_second\": 870326795.0872692, \n                    \"bytes\": 108789760, \n                    \"end\": 31.000063, \n                    \"omitted\": false, \n                    \"pmtu\": 1500, \n                    \"retransmits\": 0, \n                    \"rtt\": 77089, \n                    \"rttvar\": 5, \n                    \"seconds\": 0.9999899864196777, \n                    \"sender\": true, \n                    \"snd_cwnd\": 16698336, \n                    \"snd_wnd\": -1, \n                    \"socket\": 5, \n                    \"start\": 30.000073\n                }\n            ], \n            \"sum\": {\n                \"bits_per_second\": 870326795.0872692, \n                \"bytes\": 108789760, \n                \"end\": 31.000063, \n                \"omitted\": false, \n                \"retransmits\": 0, \n                \"seconds\": 0.9999899864196777, \n                \"sender\": true, \n                \"start\": 30.000073\n            }\n        }, \n        {\n            \"streams\": [\n                {\n                    \"bits_per_second\": 859838316.2918166, \n                    \"bytes\": 107479040, \n                    \"end\": 32.000056, \n                    \"omitted\": false, \n                    \"pmtu\": 1500, \n                    \"retransmits\": 0, \n                    \"rtt\": 77089, \n                    \"rttvar\": 7, \n                    \"seconds\": 0.9999930262565613, \n                    \"sender\": true, \n                    \"snd_cwnd\": 16698336, \n                    \"snd_wnd\": -1, \n                    \"socket\": 5, \n                    \"start\": 31.000063\n                }\n            ], \n            \"sum\": {\n                \"bits_per_second\": 859838316.2918166, \n                \"bytes\": 107479040, \n                \"end\": 32.000056, \n                \"omitted\": false, \n                \"retransmits\": 0, \n                \"seconds\": 0.9999930262565613, \n                \"sender\": true, \n                \"start\": 31.000063\n            }\n        }, \n        {\n            \"streams\": [\n                {\n                    \"bits_per_second\": 870296293.0454135, \n                    \"bytes\": 108789760, \n                    \"end\": 33.000081, \n                    \"omitted\": false, \n                    \"pmtu\": 1500, \n                    \"retransmits\": 0, \n                    \"rtt\": 77089, \n                    \"rttvar\": 8, \n                    \"seconds\": 1.0000250339508057, \n                    \"sender\": true, \n                    \"snd_cwnd\": 16698336, \n                    \"snd_wnd\": -1, \n                    \"socket\": 5, \n                    \"start\": 32.000056\n                }\n            ], \n            \"sum\": {\n                \"bits_per_second\": 870296293.0454135, \n                \"bytes\": 108789760, \n                \"end\": 33.000081, \n                \"omitted\": false, \n                \"retransmits\": 0, \n                \"seconds\": 1.0000250339508057, \n                \"sender\": true, \n                \"start\": 32.000056\n            }\n        }, \n        {\n            \"streams\": [\n                {\n                    \"bits_per_second\": 859840058.8196517, \n                    \"bytes\": 107479040, \n                    \"end\": 34.000072, \n                    \"omitted\": false, \n                    \"pmtu\": 1500, \n                    \"retransmits\": 0, \n                    \"rtt\": 77088, \n                    \"rttvar\": 8, \n                    \"seconds\": 0.999990999698639, \n                    \"sender\": true, \n                    \"snd_cwnd\": 16698336, \n                    \"snd_wnd\": -1, \n                    \"socket\": 5, \n                    \"start\": 33.000081\n                }\n            ], \n            \"sum\": {\n                \"bits_per_second\": 859840058.8196517, \n                \"bytes\": 107479040, \n                \"end\": 34.000072, \n                \"omitted\": false, \n                \"retransmits\": 0, \n                \"seconds\": 0.999990999698639, \n                \"sender\": true, \n                \"start\": 33.000081\n            }\n        }, \n        {\n            \"streams\": [\n                {\n                    \"bits_per_second\": 870329388.8969457, \n                    \"bytes\": 108789760, \n                    \"end\": 35.000059, \n                    \"omitted\": false, \n                    \"pmtu\": 1500, \n                    \"retransmits\": 0, \n                    \"rtt\": 77088, \n                    \"rttvar\": 9, \n                    \"seconds\": 0.999987006187439, \n                    \"sender\": true, \n                    \"snd_cwnd\": 16698336, \n                    \"snd_wnd\": -1, \n                    \"socket\": 5, \n                    \"start\": 34.000072\n                }\n            ], \n            \"sum\": {\n                \"bits_per_second\": 870329388.8969457, \n                \"bytes\": 108789760, \n                \"end\": 35.000059, \n                \"omitted\": false, \n                \"retransmits\": 0, \n                \"seconds\": 0.999987006187439, \n                \"sender\": true, \n                \"start\": 34.000072\n            }\n        }, \n        {\n            \"streams\": [\n                {\n                    \"bits_per_second\": 859830577.5035312, \n                    \"bytes\": 107479040, \n                    \"end\": 36.000061, \n                    \"omitted\": false, \n                    \"pmtu\": 1500, \n                    \"retransmits\": 0, \n                    \"rtt\": 77089, \n                    \"rttvar\": 7, \n                    \"seconds\": 1.0000020265579224, \n                    \"sender\": true, \n                    \"snd_cwnd\": 16698336, \n                    \"snd_wnd\": -1, \n                    \"socket\": 5, \n                    \"start\": 35.000059\n                }\n            ], \n            \"sum\": {\n                \"bits_per_second\": 859830577.5035312, \n                \"bytes\": 107479040, \n                \"end\": 36.000061, \n                \"omitted\": false, \n                \"retransmits\": 0, \n                \"seconds\": 1.0000020265579224, \n                \"sender\": true, \n                \"start\": 35.000059\n            }\n        }, \n        {\n            \"streams\": [\n                {\n                    \"bits_per_second\": 870307601.376164, \n                    \"bytes\": 108789760, \n                    \"end\": 37.000073, \n                    \"omitted\": false, \n                    \"pmtu\": 1500, \n                    \"retransmits\": 0, \n                    \"rtt\": 77091, \n                    \"rttvar\": 2, \n                    \"seconds\": 1.0000120401382446, \n                    \"sender\": true, \n                    \"snd_cwnd\": 16698336, \n                    \"snd_wnd\": -1, \n                    \"socket\": 5, \n                    \"start\": 36.000061\n                }\n            ], \n            \"sum\": {\n                \"bits_per_second\": 870307601.376164, \n                \"bytes\": 108789760, \n                \"end\": 37.000073, \n                \"omitted\": false, \n                \"retransmits\": 0, \n                \"seconds\": 1.0000120401382446, \n                \"sender\": true, \n                \"start\": 36.000061\n            }\n        }, \n        {\n            \"streams\": [\n                {\n                    \"bits_per_second\": 859754119.612848, \n                    \"bytes\": 107479040, \n                    \"end\": 38.000164, \n                    \"omitted\": false, \n                    \"pmtu\": 1500, \n                    \"retransmits\": 0, \n                    \"rtt\": 77087, \n                    \"rttvar\": 11, \n                    \"seconds\": 1.0000909566879272, \n                    \"sender\": true, \n                    \"snd_cwnd\": 16698336, \n                    \"snd_wnd\": -1, \n                    \"socket\": 5, \n                    \"start\": 37.000073\n                }\n            ], \n            \"sum\": {\n                \"bits_per_second\": 859754119.612848, \n                \"bytes\": 107479040, \n                \"end\": 38.000164, \n                \"omitted\": false, \n                \"retransmits\": 0, \n                \"seconds\": 1.0000909566879272, \n                \"sender\": true, \n                \"start\": 37.000073\n            }\n        }, \n        {\n            \"streams\": [\n                {\n                    \"bits_per_second\": 870407729.2335865, \n                    \"bytes\": 108789760, \n                    \"end\": 39.000061, \n                    \"omitted\": false, \n                    \"pmtu\": 1500, \n                    \"retransmits\": 0, \n                    \"rtt\": 77087, \n                    \"rttvar\": 9, \n                    \"seconds\": 0.999897003173828, \n                    \"sender\": true, \n                    \"snd_cwnd\": 16698336, \n                    \"snd_wnd\": -1, \n                    \"socket\": 5, \n                    \"start\": 38.000164\n                }\n            ], \n            \"sum\": {\n                \"bits_per_second\": 870407729.2335865, \n                \"bytes\": 108789760, \n                \"end\": 39.000061, \n                \"omitted\": false, \n                \"retransmits\": 0, \n                \"seconds\": 0.999897003173828, \n                \"sender\": true, \n                \"start\": 38.000164\n            }\n        }, \n        {\n            \"streams\": [\n                {\n                    \"bits_per_second\": 870312892.5309197, \n                    \"bytes\": 108789760, \n                    \"end\": 40.000067, \n                    \"omitted\": false, \n                    \"pmtu\": 1500, \n                    \"retransmits\": 0, \n                    \"rtt\": 77087, \n                    \"rttvar\": 6, \n                    \"seconds\": 1.0000059604644775, \n                    \"sender\": true, \n                    \"snd_cwnd\": 16698336, \n                    \"snd_wnd\": -1, \n                    \"socket\": 5, \n                    \"start\": 39.000061\n                }\n            ], \n            \"sum\": {\n                \"bits_per_second\": 870312892.5309197, \n                \"bytes\": 108789760, \n                \"end\": 40.000067, \n                \"omitted\": false, \n                \"retransmits\": 0, \n                \"seconds\": 1.0000059604644775, \n                \"sender\": true, \n                \"start\": 39.000061\n            }\n        }, \n        {\n            \"streams\": [\n                {\n                    \"bits_per_second\": 859835753.7637128, \n                    \"bytes\": 107479040, \n                    \"end\": 41.000063, \n                    \"omitted\": false, \n                    \"pmtu\": 1500, \n                    \"retransmits\": 0, \n                    \"rtt\": 77091, \n                    \"rttvar\": 9, \n                    \"seconds\": 0.9999960064888, \n                    \"sender\": true, \n                    \"snd_cwnd\": 16698336, \n                    \"snd_wnd\": -1, \n                    \"socket\": 5, \n                    \"start\": 40.000067\n                }\n            ], \n            \"sum\": {\n                \"bits_per_second\": 859835753.7637128, \n                \"bytes\": 107479040, \n                \"end\": 41.000063, \n                \"omitted\": false, \n                \"retransmits\": 0, \n                \"seconds\": 0.9999960064888, \n                \"sender\": true, \n                \"start\": 40.000067\n            }\n        }, \n        {\n            \"streams\": [\n                {\n                    \"bits_per_second\": 870311958.7930526, \n                    \"bytes\": 108789760, \n                    \"end\": 42.00007, \n                    \"omitted\": false, \n                    \"pmtu\": 1500, \n                    \"retransmits\": 0, \n                    \"rtt\": 77090, \n                    \"rttvar\": 10, \n                    \"seconds\": 1.0000070333480835, \n                    \"sender\": true, \n                    \"snd_cwnd\": 16698336, \n                    \"snd_wnd\": -1, \n                    \"socket\": 5, \n                    \"start\": 41.000063\n                }\n            ], \n            \"sum\": {\n                \"bits_per_second\": 870311958.7930526, \n                \"bytes\": 108789760, \n                \"end\": 42.00007, \n                \"omitted\": false, \n                \"retransmits\": 0, \n                \"seconds\": 1.0000070333480835, \n                \"sender\": true, \n                \"start\": 41.000063\n            }\n        }, \n        {\n            \"streams\": [\n                {\n                    \"bits_per_second\": 859840930.0862178, \n                    \"bytes\": 107479040, \n                    \"end\": 43.00006, \n                    \"omitted\": false, \n                    \"pmtu\": 1500, \n                    \"retransmits\": 0, \n                    \"rtt\": 77086, \n                    \"rttvar\": 9, \n                    \"seconds\": 0.9999899864196777, \n                    \"sender\": true, \n                    \"snd_cwnd\": 16698336, \n                    \"snd_wnd\": -1, \n                    \"socket\": 5, \n                    \"start\": 42.00007\n                }\n            ], \n            \"sum\": {\n                \"bits_per_second\": 859840930.0862178, \n                \"bytes\": 107479040, \n                \"end\": 43.00006, \n                \"omitted\": false, \n                \"retransmits\": 0, \n                \"seconds\": 0.9999899864196777, \n                \"sender\": true, \n                \"start\": 42.00007\n            }\n        }, \n        {\n            \"streams\": [\n                {\n                    \"bits_per_second\": 870313722.521817, \n                    \"bytes\": 108789760, \n                    \"end\": 44.000065, \n                    \"omitted\": false, \n                    \"pmtu\": 1500, \n                    \"retransmits\": 0, \n                    \"rtt\": 77091, \n                    \"rttvar\": 13, \n                    \"seconds\": 1.0000050067901611, \n                    \"sender\": true, \n                    \"snd_cwnd\": 16698336, \n                    \"snd_wnd\": -1, \n                    \"socket\": 5, \n                    \"start\": 43.00006\n                }\n            ], \n            \"sum\": {\n                \"bits_per_second\": 870313722.521817, \n                \"bytes\": 108789760, \n                \"end\": 44.000065, \n                \"omitted\": false, \n                \"retransmits\": 0, \n                \"seconds\": 1.0000050067901611, \n                \"sender\": true, \n                \"start\": 43.00006\n            }\n        }, \n        {\n            \"streams\": [\n                {\n                    \"bits_per_second\": 859715383.4054582, \n                    \"bytes\": 107479040, \n                    \"end\": 45.000201, \n                    \"omitted\": false, \n                    \"pmtu\": 1500, \n                    \"retransmits\": 0, \n                    \"rtt\": 77086, \n                    \"rttvar\": 5, \n                    \"seconds\": 1.0001360177993774, \n                    \"sender\": true, \n                    \"snd_cwnd\": 16698336, \n                    \"snd_wnd\": -1, \n                    \"socket\": 5, \n                    \"start\": 44.000065\n                }\n            ], \n            \"sum\": {\n                \"bits_per_second\": 859715383.4054582, \n                \"bytes\": 107479040, \n                \"end\": 45.000201, \n                \"omitted\": false, \n                \"retransmits\": 0, \n                \"seconds\": 1.0001360177993774, \n                \"sender\": true, \n                \"start\": 44.000065\n            }\n        }, \n        {\n            \"streams\": [\n                {\n                    \"bits_per_second\": 870439069.317277, \n                    \"bytes\": 108789760, \n                    \"end\": 46.000062, \n                    \"omitted\": false, \n                    \"pmtu\": 1500, \n                    \"retransmits\": 0, \n                    \"rtt\": 77094, \n                    \"rttvar\": 7, \n                    \"seconds\": 0.9998610019683838, \n                    \"sender\": true, \n                    \"snd_cwnd\": 16698336, \n                    \"snd_wnd\": -1, \n                    \"socket\": 5, \n                    \"start\": 45.000201\n                }\n            ], \n            \"sum\": {\n                \"bits_per_second\": 870439069.317277, \n                \"bytes\": 108789760, \n                \"end\": 46.000062, \n                \"omitted\": false, \n                \"retransmits\": 0, \n                \"seconds\": 0.9998610019683838, \n                \"sender\": true, \n                \"start\": 45.000201\n            }\n        }, \n        {\n            \"streams\": [\n                {\n                    \"bits_per_second\": 859804850.877586, \n                    \"bytes\": 107479040, \n                    \"end\": 47.000094, \n                    \"omitted\": false, \n                    \"pmtu\": 1500, \n                    \"retransmits\": 0, \n                    \"rtt\": 77085, \n                    \"rttvar\": 8, \n                    \"seconds\": 1.0000319480895996, \n                    \"sender\": true, \n                    \"snd_cwnd\": 16698336, \n                    \"snd_wnd\": -1, \n                    \"socket\": 5, \n                    \"start\": 46.000062\n                }\n            ], \n            \"sum\": {\n                \"bits_per_second\": 859804850.877586, \n                \"bytes\": 107479040, \n                \"end\": 47.000094, \n                \"omitted\": false, \n                \"retransmits\": 0, \n                \"seconds\": 1.0000319480895996, \n                \"sender\": true, \n                \"start\": 46.000062\n            }\n        }, \n        {\n            \"streams\": [\n                {\n                    \"bits_per_second\": 870354653.4118614, \n                    \"bytes\": 108789760, \n                    \"end\": 48.000052, \n                    \"omitted\": false, \n                    \"pmtu\": 1500, \n                    \"retransmits\": 0, \n                    \"rtt\": 77090, \n                    \"rttvar\": 6, \n                    \"seconds\": 0.9999579787254333, \n                    \"sender\": true, \n                    \"snd_cwnd\": 16698336, \n                    \"snd_wnd\": -1, \n                    \"socket\": 5, \n                    \"start\": 47.000094\n                }\n            ], \n            \"sum\": {\n                \"bits_per_second\": 870354653.4118614, \n                \"bytes\": 108789760, \n                \"end\": 48.000052, \n                \"omitted\": false, \n                \"retransmits\": 0, \n                \"seconds\": 0.9999579787254333, \n                \"sender\": true, \n                \"start\": 47.000094\n            }\n        }, \n        {\n            \"streams\": [\n                {\n                    \"bits_per_second\": 859821147.6451715, \n                    \"bytes\": 107479040, \n                    \"end\": 49.000065, \n                    \"omitted\": false, \n                    \"pmtu\": 1500, \n                    \"retransmits\": 0, \n                    \"rtt\": 77086, \n                    \"rttvar\": 8, \n                    \"seconds\": 1.000012993812561, \n                    \"sender\": true, \n                    \"snd_cwnd\": 16698336, \n                    \"snd_wnd\": -1, \n                    \"socket\": 5, \n                    \"start\": 48.000052\n                }\n            ], \n            \"sum\": {\n                \"bits_per_second\": 859821147.6451715, \n                \"bytes\": 107479040, \n                \"end\": 49.000065, \n                \"omitted\": false, \n                \"retransmits\": 0, \n                \"seconds\": 1.000012993812561, \n                \"sender\": true, \n                \"start\": 48.000052\n            }\n        }, \n        {\n            \"streams\": [\n                {\n                    \"bits_per_second\": 870325913.195501, \n                    \"bytes\": 108789760, \n                    \"end\": 50.000056, \n                    \"omitted\": false, \n                    \"pmtu\": 1500, \n                    \"retransmits\": 0, \n                    \"rtt\": 77090, \n                    \"rttvar\": 10, \n                    \"seconds\": 0.999990999698639, \n                    \"sender\": true, \n                    \"snd_cwnd\": 16698336, \n                    \"snd_wnd\": -1, \n                    \"socket\": 5, \n                    \"start\": 49.000065\n                }\n            ], \n            \"sum\": {\n                \"bits_per_second\": 870325913.195501, \n                \"bytes\": 108789760, \n                \"end\": 50.000056, \n                \"omitted\": false, \n                \"retransmits\": 0, \n                \"seconds\": 0.999990999698639, \n                \"sender\": true, \n                \"start\": 49.000065\n            }\n        }, \n        {\n            \"streams\": [\n                {\n                    \"bits_per_second\": 870311958.7930526, \n                    \"bytes\": 108789760, \n                    \"end\": 51.000063, \n                    \"omitted\": false, \n                    \"pmtu\": 1500, \n                    \"retransmits\": 0, \n                    \"rtt\": 77085, \n                    \"rttvar\": 7, \n                    \"seconds\": 1.0000070333480835, \n                    \"sender\": true, \n                    \"snd_cwnd\": 16698336, \n                    \"snd_wnd\": -1, \n                    \"socket\": 5, \n                    \"start\": 50.000056\n                }\n            ], \n            \"sum\": {\n                \"bits_per_second\": 870311958.7930526, \n                \"bytes\": 108789760, \n                \"end\": 51.000063, \n                \"omitted\": false, \n                \"retransmits\": 0, \n                \"seconds\": 1.0000070333480835, \n                \"sender\": true, \n                \"start\": 50.000056\n            }\n        }, \n        {\n            \"streams\": [\n                {\n                    \"bits_per_second\": 859742026.9828782, \n                    \"bytes\": 107479040, \n                    \"end\": 52.000168, \n                    \"omitted\": false, \n                    \"pmtu\": 1500, \n                    \"retransmits\": 0, \n                    \"rtt\": 77088, \n                    \"rttvar\": 5, \n                    \"seconds\": 1.0001050233840942, \n                    \"sender\": true, \n                    \"snd_cwnd\": 16698336, \n                    \"snd_wnd\": -1, \n                    \"socket\": 5, \n                    \"start\": 51.000063\n                }\n            ], \n            \"sum\": {\n                \"bits_per_second\": 859742026.9828782, \n                \"bytes\": 107479040, \n                \"end\": 52.000168, \n                \"omitted\": false, \n                \"retransmits\": 0, \n                \"seconds\": 1.0001050233840942, \n                \"sender\": true, \n                \"start\": 51.000063\n            }\n        }, \n        {\n            \"streams\": [\n                {\n                    \"bits_per_second\": 870405965.1237845, \n                    \"bytes\": 108789760, \n                    \"end\": 53.000067, \n                    \"omitted\": false, \n                    \"pmtu\": 1500, \n                    \"retransmits\": 0, \n                    \"rtt\": 77084, \n                    \"rttvar\": 11, \n                    \"seconds\": 0.9998990297317505, \n                    \"sender\": true, \n                    \"snd_cwnd\": 16698336, \n                    \"snd_wnd\": -1, \n                    \"socket\": 5, \n                    \"start\": 52.000168\n                }\n            ], \n            \"sum\": {\n                \"bits_per_second\": 870405965.1237845, \n                \"bytes\": 108789760, \n                \"end\": 53.000067, \n                \"omitted\": false, \n                \"retransmits\": 0, \n                \"seconds\": 0.9998990297317505, \n                \"sender\": true, \n                \"start\": 52.000168\n            }\n        }, \n        {\n            \"streams\": [\n                {\n                    \"bits_per_second\": 859730037.1686776, \n                    \"bytes\": 107479040, \n                    \"end\": 54.000186, \n                    \"omitted\": false, \n                    \"pmtu\": 1500, \n                    \"retransmits\": 0, \n                    \"rtt\": 77083, \n                    \"rttvar\": 6, \n                    \"seconds\": 1.0001189708709717, \n                    \"sender\": true, \n                    \"snd_cwnd\": 16698336, \n                    \"snd_wnd\": -1, \n                    \"socket\": 5, \n                    \"start\": 53.000067\n                }\n            ], \n            \"sum\": {\n                \"bits_per_second\": 859730037.1686776, \n                \"bytes\": 107479040, \n                \"end\": 54.000186, \n                \"omitted\": false, \n                \"retransmits\": 0, \n                \"seconds\": 1.0001189708709717, \n                \"sender\": true, \n                \"start\": 53.000067\n            }\n        }, \n        {\n            \"streams\": [\n                {\n                    \"bits_per_second\": 870399894.565285, \n                    \"bytes\": 108789760, \n                    \"end\": 55.000092, \n                    \"omitted\": false, \n                    \"pmtu\": 1500, \n                    \"retransmits\": 0, \n                    \"rtt\": 77083, \n                    \"rttvar\": 8, \n                    \"seconds\": 0.9999060034751892, \n                    \"sender\": true, \n                    \"snd_cwnd\": 16698336, \n                    \"snd_wnd\": -1, \n                    \"socket\": 5, \n                    \"start\": 54.000186\n                }\n            ], \n            \"sum\": {\n                \"bits_per_second\": 870399894.565285, \n                \"bytes\": 108789760, \n                \"end\": 55.000092, \n                \"omitted\": false, \n                \"retransmits\": 0, \n                \"seconds\": 0.9999060034751892, \n                \"sender\": true, \n                \"start\": 54.000186\n            }\n        }, \n        {\n            \"streams\": [\n                {\n                    \"bits_per_second\": 859762728.132982, \n                    \"bytes\": 107479040, \n                    \"end\": 56.000173, \n                    \"omitted\": false, \n                    \"pmtu\": 1500, \n                    \"retransmits\": 0, \n                    \"rtt\": 77087, \n                    \"rttvar\": 7, \n                    \"seconds\": 1.000080943107605, \n                    \"sender\": true, \n                    \"snd_cwnd\": 16698336, \n                    \"snd_wnd\": -1, \n                    \"socket\": 5, \n                    \"start\": 55.000092\n                }\n            ], \n            \"sum\": {\n                \"bits_per_second\": 859762728.132982, \n                \"bytes\": 107479040, \n                \"end\": 56.000173, \n                \"omitted\": false, \n                \"retransmits\": 0, \n                \"seconds\": 1.000080943107605, \n                \"sender\": true, \n                \"start\": 55.000092\n            }\n        }, \n        {\n            \"streams\": [\n                {\n                    \"bits_per_second\": 870412087.6531665, \n                    \"bytes\": 108789760, \n                    \"end\": 57.000065, \n                    \"omitted\": false, \n                    \"pmtu\": 1500, \n                    \"retransmits\": 0, \n                    \"rtt\": 77085, \n                    \"rttvar\": 7, \n                    \"seconds\": 0.999891996383667, \n                    \"sender\": true, \n                    \"snd_cwnd\": 16698336, \n                    \"snd_wnd\": -1, \n                    \"socket\": 5, \n                    \"start\": 56.000173\n                }\n            ], \n            \"sum\": {\n                \"bits_per_second\": 870412087.6531665, \n                \"bytes\": 108789760, \n                \"end\": 57.000065, \n                \"omitted\": false, \n                \"retransmits\": 0, \n                \"seconds\": 0.999891996383667, \n                \"sender\": true, \n                \"start\": 56.000173\n            }\n        }, \n        {\n            \"streams\": [\n                {\n                    \"bits_per_second\": 859821967.624644, \n                    \"bytes\": 107479040, \n                    \"end\": 58.000077, \n                    \"omitted\": false, \n                    \"pmtu\": 1500, \n                    \"retransmits\": 0, \n                    \"rtt\": 77089, \n                    \"rttvar\": 6, \n                    \"seconds\": 1.0000120401382446, \n                    \"sender\": true, \n                    \"snd_cwnd\": 16698336, \n                    \"snd_wnd\": -1, \n                    \"socket\": 5, \n                    \"start\": 57.000065\n                }\n            ], \n            \"sum\": {\n                \"bits_per_second\": 859821967.624644, \n                \"bytes\": 107479040, \n                \"end\": 58.000077, \n                \"omitted\": false, \n                \"retransmits\": 0, \n                \"seconds\": 1.0000120401382446, \n                \"sender\": true, \n                \"start\": 57.000065\n            }\n        }, \n        {\n            \"streams\": [\n                {\n                    \"bits_per_second\": 870241519.2355447, \n                    \"bytes\": 108789760, \n                    \"end\": 59.000165, \n                    \"omitted\": false, \n                    \"pmtu\": 1500, \n                    \"retransmits\": 0, \n                    \"rtt\": 77081, \n                    \"rttvar\": 5, \n                    \"seconds\": 1.0000879764556885, \n                    \"sender\": true, \n                    \"snd_cwnd\": 16698336, \n                    \"snd_wnd\": -1, \n                    \"socket\": 5, \n                    \"start\": 58.000077\n                }\n            ], \n            \"sum\": {\n                \"bits_per_second\": 870241519.2355447, \n                \"bytes\": 108789760, \n                \"end\": 59.000165, \n                \"omitted\": false, \n                \"retransmits\": 0, \n                \"seconds\": 1.0000879764556885, \n                \"sender\": true, \n                \"start\": 58.000077\n            }\n        }, \n        {\n            \"streams\": [\n                {\n                    \"bits_per_second\": 859895105.834351, \n                    \"bytes\": 107479040, \n                    \"end\": 60.000092, \n                    \"omitted\": false, \n                    \"pmtu\": 1500, \n                    \"retransmits\": 0, \n                    \"rtt\": 77086, \n                    \"rttvar\": 7, \n                    \"seconds\": 0.99992698431015, \n                    \"sender\": true, \n                    \"snd_cwnd\": 16698336, \n                    \"snd_wnd\": -1, \n                    \"socket\": 5, \n                    \"start\": 59.000165\n                }\n            ], \n            \"sum\": {\n                \"bits_per_second\": 859895105.834351, \n                \"bytes\": 107479040, \n                \"end\": 60.000092, \n                \"omitted\": false, \n                \"retransmits\": 0, \n                \"seconds\": 0.99992698431015, \n                \"sender\": true, \n                \"start\": 59.000165\n            }\n        }\n    ], \n    \"start\": {\n        \"connected\": [\n            {\n                \"local_host\": \"10.0.0.1\", \n                \"local_port\": 37209, \n                \"remote_host\": \"10.0.0.2\", \n                \"remote_port\": 5201, \n                \"socket\": 5\n            }\n        ], \n        \"connecting_to\": {\n            \"host\": \"10.0.0.2\", \n            \"port\": 5201\n        }, \n        \"cookie\": \"57g2xjwzh4hbs77nruywotc6hhbgkhsbf2sq\", \n        \"fq_rate\": 0, \n        \"rcvbuf_actual\": 87380, \n        \"sndbuf_actual\": 87380, \n        \"sock_bufsize\": 0, \n        \"system_info\": \"REDACTED\", \n        \"target_bitrate\": 0, \n        \"tcp_mss_default\": 1448, \n        \"test_start\": {\n            \"bidir\": 0, \n            \"blksize\": 131072, \n            \"blocks\": 0, \n            \"bytes\": 0, \n            \"duration\": 60, \n            \"fqrate\": 0, \n            \"num_streams\": 1, \n            \"omit\": 0, \n            \"protocol\": \"TCP\", \n            \"reverse\": 0, \n            \"target_bitrate\": 0, \n            \"tos\": 0\n        }, \n        \"timestamp\": {\n            \"time\": \"Wed, 17 Apr 2024 01:14:34 GMT\", \n            \"timesecs\": 1713316474\n        }, \n        \"version\": \"iperf 3.14\"\n    }\n}\nParticipant 1:\n/usr/bin/iperf3 -s -1 --idle-timeout 60 --json -p 5201 -B 10.0.0.2 --authorized-users-path /var/run/pscheduler-server/runner/tmp/tmp7viu2dc_/tmpm0p3rkvt/credentials --rsa-private-key-path /var/run/pscheduler-server/runner/tmp/tmp7viu2dc_/tmpm0p3rkvt/private-key\n\n{\n    \"end\": {\n        \"cpu_utilization_percent\": {\n            \"host_system\": 5.198483892741943, \n            \"host_total\": 5.87487734077871, \n            \"host_user\": 0.6763934480367667, \n            \"remote_system\": 0, \n            \"remote_total\": 0, \n            \"remote_user\": 0\n        }, \n        \"receiver_tcp_congestion\": \"htcp\", \n        \"streams\": [\n            {\n                \"receiver\": {\n                    \"bits_per_second\": 865535251.554414, \n                    \"bytes\": 6499843216, \n                    \"end\": 60.076982, \n                    \"seconds\": 60.076982, \n                    \"sender\": false, \n                    \"socket\": 5, \n                    \"start\": 0\n                }, \n                \"sender\": {\n                    \"bits_per_second\": 0, \n                    \"bytes\": 0, \n                    \"end\": 60.076982, \n                    \"seconds\": 60.076982, \n                    \"sender\": false, \n                    \"socket\": 5, \n                    \"start\": 0\n                }\n            }\n        ], \n        \"sum_received\": {\n            \"bits_per_second\": 865535251.554414, \n            \"bytes\": 6499843216, \n            \"end\": 60.076982, \n            \"seconds\": 60.076982, \n            \"sender\": false, \n            \"start\": 0\n        }, \n        \"sum_sent\": {\n            \"bits_per_second\": 0, \n            \"bytes\": 0, \n            \"end\": 60.076982, \n            \"seconds\": 60.076982, \n            \"sender\": false, \n            \"start\": 0\n        }\n    }, \n    \"intervals\": [\n        {\n            \"streams\": [\n                {\n                    \"bits_per_second\": 865282158.5096616, \n                    \"bytes\": 108168496, \n                    \"end\": 1.000076, \n                    \"omitted\": false, \n                    \"seconds\": 1.0000760555267334, \n                    \"sender\": false, \n                    \"socket\": 5, \n                    \"start\": 0\n                }\n            ], \n            \"sum\": {\n                \"bits_per_second\": 865282158.5096616, \n                \"bytes\": 108168496, \n                \"end\": 1.000076, \n                \"omitted\": false, \n                \"seconds\": 1.0000760555267334, \n                \"sender\": false, \n                \"start\": 0\n            }\n        }, \n        {\n            \"streams\": [\n                {\n                    \"bits_per_second\": 865336920.853448, \n                    \"bytes\": 108165600, \n                    \"end\": 2.000062, \n                    \"omitted\": false, \n                    \"seconds\": 0.9999859929084778, \n                    \"sender\": false, \n                    \"socket\": 5, \n                    \"start\": 1.000076\n                }\n            ], \n            \"sum\": {\n                \"bits_per_second\": 865336920.853448, \n                \"bytes\": 108165600, \n                \"end\": 2.000062, \n                \"omitted\": false, \n                \"seconds\": 0.9999859929084778, \n                \"sender\": false, \n                \"start\": 1.000076\n            }\n        }, \n        {\n            \"streams\": [\n                {\n                    \"bits_per_second\": 865306645.1440877, \n                    \"bytes\": 108165600, \n                    \"end\": 3.000083, \n                    \"omitted\": false, \n                    \"seconds\": 1.000020980834961, \n                    \"sender\": false, \n                    \"socket\": 5, \n                    \"start\": 2.000062\n                }\n            ], \n            \"sum\": {\n                \"bits_per_second\": 865306645.1440877, \n                \"bytes\": 108165600, \n                \"end\": 3.000083, \n                \"omitted\": false, \n                \"seconds\": 1.000020980834961, \n                \"sender\": false, \n                \"start\": 2.000062\n            }\n        }, \n        {\n            \"streams\": [\n                {\n                    \"bits_per_second\": 865865123.936177, \n                    \"bytes\": 108230760, \n                    \"end\": 4.000061, \n                    \"omitted\": false, \n                    \"seconds\": 0.999978005886078, \n                    \"sender\": false, \n                    \"socket\": 5, \n                    \"start\": 3.000083\n                }\n            ], \n            \"sum\": {\n                \"bits_per_second\": 865865123.936177, \n                \"bytes\": 108230760, \n                \"end\": 4.000061, \n                \"omitted\": false, \n                \"seconds\": 0.999978005886078, \n                \"sender\": false, \n                \"start\": 3.000083\n            }\n        }, \n        {\n            \"streams\": [\n                {\n                    \"bits_per_second\": 865306645.1440877, \n                    \"bytes\": 108165600, \n                    \"end\": 5.000082, \n                    \"omitted\": false, \n                    \"seconds\": 1.000020980834961, \n                    \"sender\": false, \n                    \"socket\": 5, \n                    \"start\": 4.000061\n                }\n            ], \n            \"sum\": {\n                \"bits_per_second\": 865306645.1440877, \n                \"bytes\": 108165600, \n                \"end\": 5.000082, \n                \"omitted\": false, \n                \"seconds\": 1.000020980834961, \n                \"sender\": false, \n                \"start\": 4.000061\n            }\n        }, \n        {\n            \"streams\": [\n                {\n                    \"bits_per_second\": 865864246.5548556, \n                    \"bytes\": 108230760, \n                    \"end\": 6.000061, \n                    \"omitted\": false, \n                    \"seconds\": 0.999979019165039, \n                    \"sender\": false, \n                    \"socket\": 5, \n                    \"start\": 5.000082\n                }\n            ], \n            \"sum\": {\n                \"bits_per_second\": 865864246.5548556, \n                \"bytes\": 108230760, \n                \"end\": 6.000061, \n                \"omitted\": false, \n                \"seconds\": 0.999979019165039, \n                \"sender\": false, \n                \"start\": 5.000082\n            }\n        }, \n        {\n            \"streams\": [\n                {\n                    \"bits_per_second\": 865311802.6961398, \n                    \"bytes\": 108165600, \n                    \"end\": 7.000076, \n                    \"omitted\": false, \n                    \"seconds\": 1.0000150203704834, \n                    \"sender\": false, \n                    \"socket\": 5, \n                    \"start\": 6.000061\n                }\n            ], \n            \"sum\": {\n                \"bits_per_second\": 865311802.6961398, \n                \"bytes\": 108165600, \n                \"end\": 7.000076, \n                \"omitted\": false, \n                \"seconds\": 1.0000150203704834, \n                \"sender\": false, \n                \"start\": 6.000061\n            }\n        }, \n        {\n            \"streams\": [\n                {\n                    \"bits_per_second\": 865839990.245964, \n                    \"bytes\": 108230760, \n                    \"end\": 8.000083, \n                    \"omitted\": false, \n                    \"seconds\": 1.0000070333480835, \n                    \"sender\": false, \n                    \"socket\": 5, \n                    \"start\": 7.000076\n                }\n            ], \n            \"sum\": {\n                \"bits_per_second\": 865839990.245964, \n                \"bytes\": 108230760, \n                \"end\": 8.000083, \n                \"omitted\": false, \n                \"seconds\": 1.0000070333480835, \n                \"sender\": false, \n                \"start\": 7.000076\n            }\n        }, \n        {\n            \"streams\": [\n                {\n                    \"bits_per_second\": 865342955.6177365, \n                    \"bytes\": 108165600, \n                    \"end\": 9.000062, \n                    \"omitted\": false, \n                    \"seconds\": 0.999979019165039, \n                    \"sender\": false, \n                    \"socket\": 5, \n                    \"start\": 8.000083\n                }\n            ], \n            \"sum\": {\n                \"bits_per_second\": 865342955.6177365, \n                \"bytes\": 108165600, \n                \"end\": 9.000062, \n                \"omitted\": false, \n                \"seconds\": 0.999979019165039, \n                \"sender\": false, \n                \"start\": 8.000083\n            }\n        }, \n        {\n            \"streams\": [\n                {\n                    \"bits_per_second\": 865310977.48368, \n                    \"bytes\": 108165600, \n                    \"end\": 10.000078, \n                    \"omitted\": false, \n                    \"seconds\": 1.0000159740448, \n                    \"sender\": false, \n                    \"socket\": 5, \n                    \"start\": 9.000062\n                }\n            ], \n            \"sum\": {\n                \"bits_per_second\": 865310977.48368, \n                \"bytes\": 108165600, \n                \"end\": 10.000078, \n                \"omitted\": false, \n                \"seconds\": 1.0000159740448, \n                \"sender\": false, \n                \"start\": 9.000062\n            }\n        }, \n        {\n            \"streams\": [\n                {\n                    \"bits_per_second\": 865858208.155167, \n                    \"bytes\": 108230760, \n                    \"end\": 11.000064, \n                    \"omitted\": false, \n                    \"seconds\": 0.9999859929084778, \n                    \"sender\": false, \n                    \"socket\": 5, \n                    \"start\": 10.000078\n                }\n            ], \n            \"sum\": {\n                \"bits_per_second\": 865858208.155167, \n                \"bytes\": 108230760, \n                \"end\": 11.000064, \n                \"omitted\": false, \n                \"seconds\": 0.9999859929084778, \n                \"sender\": false, \n                \"start\": 10.000078\n            }\n        }, \n        {\n            \"streams\": [\n                {\n                    \"bits_per_second\": 865303138.0438102, \n                    \"bytes\": 108165600, \n                    \"end\": 12.000089, \n                    \"omitted\": false, \n                    \"seconds\": 1.0000250339508057, \n                    \"sender\": false, \n                    \"socket\": 5, \n                    \"start\": 11.000064\n                }\n            ], \n            \"sum\": {\n                \"bits_per_second\": 865303138.0438102, \n                \"bytes\": 108165600, \n                \"end\": 12.000089, \n                \"omitted\": false, \n                \"seconds\": 1.0000250339508057, \n                \"sender\": false, \n                \"start\": 11.000064\n            }\n        }, \n        {\n            \"streams\": [\n                {\n                    \"bits_per_second\": 865868581.8681105, \n                    \"bytes\": 108230760, \n                    \"end\": 13.000063, \n                    \"omitted\": false, \n                    \"seconds\": 0.999974012374878, \n                    \"sender\": false, \n                    \"socket\": 5, \n                    \"start\": 12.000089\n                }\n            ], \n            \"sum\": {\n                \"bits_per_second\": 865868581.8681105, \n                \"bytes\": 108230760, \n                \"end\": 13.000063, \n                \"omitted\": false, \n                \"seconds\": 0.999974012374878, \n                \"sender\": false, \n                \"start\": 12.000089\n            }\n        }, \n        {\n            \"streams\": [\n                {\n                    \"bits_per_second\": 865323974.76275, \n                    \"bytes\": 108165600, \n                    \"end\": 14.000064, \n                    \"omitted\": false, \n                    \"seconds\": 1.0000009536743164, \n                    \"sender\": false, \n                    \"socket\": 5, \n                    \"start\": 13.000063\n                }\n            ], \n            \"sum\": {\n                \"bits_per_second\": 865323974.76275, \n                \"bytes\": 108165600, \n                \"end\": 14.000064, \n                \"omitted\": false, \n                \"seconds\": 1.0000009536743164, \n                \"sender\": false, \n                \"start\": 13.000063\n            }\n        }, \n        {\n            \"streams\": [\n                {\n                    \"bits_per_second\": 865829668.824589, \n                    \"bytes\": 108230760, \n                    \"end\": 15.000083, \n                    \"omitted\": false, \n                    \"seconds\": 1.0000189542770386, \n                    \"sender\": false, \n                    \"socket\": 5, \n                    \"start\": 14.000064\n                }\n            ], \n            \"sum\": {\n                \"bits_per_second\": 865829668.824589, \n                \"bytes\": 108230760, \n                \"end\": 15.000083, \n                \"omitted\": false, \n                \"seconds\": 1.0000189542770386, \n                \"sender\": false, \n                \"start\": 14.000064\n            }\n        }, \n        {\n            \"streams\": [\n                {\n                    \"bits_per_second\": 865341253.4962097, \n                    \"bytes\": 108165600, \n                    \"end\": 16.000064, \n                    \"omitted\": false, \n                    \"seconds\": 0.9999809861183167, \n                    \"sender\": false, \n                    \"socket\": 5, \n                    \"start\": 15.000083\n                }\n            ], \n            \"sum\": {\n                \"bits_per_second\": 865341253.4962097, \n                \"bytes\": 108165600, \n                \"end\": 16.000064, \n                \"omitted\": false, \n                \"seconds\": 0.9999809861183167, \n                \"sender\": false, \n                \"start\": 15.000083\n            }\n        }, \n        {\n            \"streams\": [\n                {\n                    \"bits_per_second\": 865308398.704887, \n                    \"bytes\": 108165600, \n                    \"end\": 17.000083, \n                    \"omitted\": false, \n                    \"seconds\": 1.0000189542770386, \n                    \"sender\": false, \n                    \"socket\": 5, \n                    \"start\": 16.000064\n                }\n            ], \n            \"sum\": {\n                \"bits_per_second\": 865308398.704887, \n                \"bytes\": 108165600, \n                \"end\": 17.000083, \n                \"omitted\": false, \n                \"seconds\": 1.0000189542770386, \n                \"sender\": false, \n                \"start\": 16.000064\n            }\n        }, \n        {\n            \"streams\": [\n                {\n                    \"bits_per_second\": 865772492.6077617, \n                    \"bytes\": 108230760, \n                    \"end\": 18.000168, \n                    \"omitted\": false, \n                    \"seconds\": 1.00008499622345, \n                    \"sender\": false, \n                    \"socket\": 5, \n                    \"start\": 17.000083\n                }\n            ], \n            \"sum\": {\n                \"bits_per_second\": 865772492.6077617, \n                \"bytes\": 108230760, \n                \"end\": 18.000168, \n                \"omitted\": false, \n                \"seconds\": 1.00008499622345, \n                \"sender\": false, \n                \"start\": 17.000083\n            }\n        }, \n        {\n            \"streams\": [\n                {\n                    \"bits_per_second\": 865399232.557379, \n                    \"bytes\": 108165600, \n                    \"end\": 19.000082, \n                    \"omitted\": false, \n                    \"seconds\": 0.999913990497589, \n                    \"sender\": false, \n                    \"socket\": 5, \n                    \"start\": 18.000168\n                }\n            ], \n            \"sum\": {\n                \"bits_per_second\": 865399232.557379, \n                \"bytes\": 108165600, \n                \"end\": 19.000082, \n                \"omitted\": false, \n                \"seconds\": 0.999913990497589, \n                \"sender\": false, \n                \"start\": 18.000168\n            }\n        }, \n        {\n            \"streams\": [\n                {\n                    \"bits_per_second\": 865863420.7858243, \n                    \"bytes\": 108230760, \n                    \"end\": 20.000062, \n                    \"omitted\": false, \n                    \"seconds\": 0.9999799728393555, \n                    \"sender\": false, \n                    \"socket\": 5, \n                    \"start\": 19.000082\n                }\n            ], \n            \"sum\": {\n                \"bits_per_second\": 865863420.7858243, \n                \"bytes\": 108230760, \n                \"end\": 20.000062, \n                \"omitted\": false, \n                \"seconds\": 0.9999799728393555, \n                \"sender\": false, \n                \"start\": 19.000082\n            }\n        }, \n        {\n            \"streams\": [\n                {\n                    \"bits_per_second\": 865307470.3482844, \n                    \"bytes\": 108165600, \n                    \"end\": 21.000082, \n                    \"omitted\": false, \n                    \"seconds\": 1.0000200271606445, \n                    \"sender\": false, \n                    \"socket\": 5, \n                    \"start\": 20.000062\n                }\n            ], \n            \"sum\": {\n                \"bits_per_second\": 865307470.3482844, \n                \"bytes\": 108165600, \n                \"end\": 21.000082, \n                \"omitted\": false, \n                \"seconds\": 1.0000200271606445, \n                \"sender\": false, \n                \"start\": 20.000062\n            }\n        }, \n        {\n            \"streams\": [\n                {\n                    \"bits_per_second\": 865851292.4846303, \n                    \"bytes\": 108230760, \n                    \"end\": 22.000076, \n                    \"omitted\": false, \n                    \"seconds\": 0.9999939799308777, \n                    \"sender\": false, \n                    \"socket\": 5, \n                    \"start\": 21.000082\n                }\n            ], \n            \"sum\": {\n                \"bits_per_second\": 865851292.4846303, \n                \"bytes\": 108230760, \n                \"end\": 22.000076, \n                \"omitted\": false, \n                \"seconds\": 0.9999939799308777, \n                \"sender\": false, \n                \"start\": 21.000082\n            }\n        }, \n        {\n            \"streams\": [\n                {\n                    \"bits_per_second\": 865336044.0143583, \n                    \"bytes\": 108165600, \n                    \"end\": 23.000063, \n                    \"omitted\": false, \n                    \"seconds\": 0.999987006187439, \n                    \"sender\": false, \n                    \"socket\": 5, \n                    \"start\": 22.000076\n                }\n            ], \n            \"sum\": {\n                \"bits_per_second\": 865336044.0143583, \n                \"bytes\": 108165600, \n                \"end\": 23.000063, \n                \"omitted\": false, \n                \"seconds\": 0.999987006187439, \n                \"sender\": false, \n                \"start\": 22.000076\n            }\n        }, \n        {\n            \"streams\": [\n                {\n                    \"bits_per_second\": 865305716.7912476, \n                    \"bytes\": 108165600, \n                    \"end\": 24.000085, \n                    \"omitted\": false, \n                    \"seconds\": 1.000022053718567, \n                    \"sender\": false, \n                    \"socket\": 5, \n                    \"start\": 23.000063\n                }\n            ], \n            \"sum\": {\n                \"bits_per_second\": 865305716.7912476, \n                \"bytes\": 108165600, \n                \"end\": 24.000085, \n                \"omitted\": false, \n                \"seconds\": 1.000022053718567, \n                \"sender\": false, \n                \"start\": 23.000063\n            }\n        }, \n        {\n            \"streams\": [\n                {\n                    \"bits_per_second\": 865862543.4079545, \n                    \"bytes\": 108230760, \n                    \"end\": 25.000066, \n                    \"omitted\": false, \n                    \"seconds\": 0.9999809861183167, \n                    \"sender\": false, \n                    \"socket\": 5, \n                    \"start\": 24.000085\n                }\n            ], \n            \"sum\": {\n                \"bits_per_second\": 865862543.4079545, \n                \"bytes\": 108230760, \n                \"end\": 25.000066, \n                \"omitted\": false, \n                \"seconds\": 0.9999809861183167, \n                \"sender\": false, \n                \"start\": 24.000085\n            }\n        }, \n        {\n            \"streams\": [\n                {\n                    \"bits_per_second\": 865310049.121544, \n                    \"bytes\": 108165600, \n                    \"end\": 26.000083, \n                    \"omitted\": false, \n                    \"seconds\": 1.0000170469284058, \n                    \"sender\": false, \n                    \"socket\": 5, \n                    \"start\": 25.000066\n                }\n            ], \n            \"sum\": {\n                \"bits_per_second\": 865310049.121544, \n                \"bytes\": 108165600, \n                \"end\": 26.000083, \n                \"omitted\": false, \n                \"seconds\": 1.0000170469284058, \n                \"sender\": false, \n                \"start\": 25.000066\n            }\n        }, \n        {\n            \"streams\": [\n                {\n                    \"bits_per_second\": 865894594.659344, \n                    \"bytes\": 108230760, \n                    \"end\": 27.000027, \n                    \"omitted\": false, \n                    \"seconds\": 0.999943971633911, \n                    \"sender\": false, \n                    \"socket\": 5, \n                    \"start\": 26.000083\n                }\n            ], \n            \"sum\": {\n                \"bits_per_second\": 865894594.659344, \n                \"bytes\": 108230760, \n                \"end\": 27.000027, \n                \"omitted\": false, \n                \"seconds\": 0.999943971633911, \n                \"sender\": false, \n                \"start\": 26.000083\n            }\n        }, \n        {\n            \"streams\": [\n                {\n                    \"bits_per_second\": 865292823.2077606, \n                    \"bytes\": 108165600, \n                    \"end\": 28.000064, \n                    \"omitted\": false, \n                    \"seconds\": 1.0000369548797607, \n                    \"sender\": false, \n                    \"socket\": 5, \n                    \"start\": 27.000027\n                }\n            ], \n            \"sum\": {\n                \"bits_per_second\": 865292823.2077606, \n                \"bytes\": 108165600, \n                \"end\": 28.000064, \n                \"omitted\": false, \n                \"seconds\": 1.0000369548797607, \n                \"sender\": false, \n                \"start\": 27.000027\n            }\n        }, \n        {\n            \"streams\": [\n                {\n                    \"bits_per_second\": 865835655.219014, \n                    \"bytes\": 108230760, \n                    \"end\": 29.000076, \n                    \"omitted\": false, \n                    \"seconds\": 1.0000120401382446, \n                    \"sender\": false, \n                    \"socket\": 5, \n                    \"start\": 28.000064\n                }\n            ], \n            \"sum\": {\n                \"bits_per_second\": 865835655.219014, \n                \"bytes\": 108230760, \n                \"end\": 29.000076, \n                \"omitted\": false, \n                \"seconds\": 1.0000120401382446, \n                \"sender\": false, \n                \"start\": 28.000064\n            }\n        }, \n        {\n            \"streams\": [\n                {\n                    \"bits_per_second\": 865336044.0143583, \n                    \"bytes\": 108165600, \n                    \"end\": 30.000063, \n                    \"omitted\": false, \n                    \"seconds\": 0.999987006187439, \n                    \"sender\": false, \n                    \"socket\": 5, \n                    \"start\": 29.000076\n                }\n            ], \n            \"sum\": {\n                \"bits_per_second\": 865336044.0143583, \n                \"bytes\": 108165600, \n                \"end\": 30.000063, \n                \"omitted\": false, \n                \"seconds\": 0.999987006187439, \n                \"sender\": false, \n                \"start\": 29.000076\n            }\n        }, \n        {\n            \"streams\": [\n                {\n                    \"bits_per_second\": 865307470.3482844, \n                    \"bytes\": 108165600, \n                    \"end\": 31.000083, \n                    \"omitted\": false, \n                    \"seconds\": 1.0000200271606445, \n                    \"sender\": false, \n                    \"socket\": 5, \n                    \"start\": 30.000063\n                }\n            ], \n            \"sum\": {\n                \"bits_per_second\": 865307470.3482844, \n                \"bytes\": 108165600, \n                \"end\": 31.000083, \n                \"omitted\": false, \n                \"seconds\": 1.0000200271606445, \n                \"sender\": false, \n                \"start\": 30.000063\n            }\n        }, \n        {\n            \"streams\": [\n                {\n                    \"bits_per_second\": 865864246.5548556, \n                    \"bytes\": 108230760, \n                    \"end\": 32.000062, \n                    \"omitted\": false, \n                    \"seconds\": 0.999979019165039, \n                    \"sender\": false, \n                    \"socket\": 5, \n                    \"start\": 31.000083\n                }\n            ], \n            \"sum\": {\n                \"bits_per_second\": 865864246.5548556, \n                \"bytes\": 108230760, \n                \"end\": 32.000062, \n                \"omitted\": false, \n                \"seconds\": 0.999979019165039, \n                \"sender\": false, \n                \"start\": 31.000083\n            }\n        }, \n        {\n            \"streams\": [\n                {\n                    \"bits_per_second\": 865307470.3482844, \n                    \"bytes\": 108165600, \n                    \"end\": 33.000082, \n                    \"omitted\": false, \n                    \"seconds\": 1.0000200271606445, \n                    \"sender\": false, \n                    \"socket\": 5, \n                    \"start\": 32.000062\n                }\n            ], \n            \"sum\": {\n                \"bits_per_second\": 865307470.3482844, \n                \"bytes\": 108165600, \n                \"end\": 33.000082, \n                \"omitted\": false, \n                \"seconds\": 1.0000200271606445, \n                \"sender\": false, \n                \"start\": 32.000062\n            }\n        }, \n        {\n            \"streams\": [\n                {\n                    \"bits_per_second\": 865862543.4079545, \n                    \"bytes\": 108230760, \n                    \"end\": 34.000063, \n                    \"omitted\": false, \n                    \"seconds\": 0.9999809861183167, \n                    \"sender\": false, \n                    \"socket\": 5, \n                    \"start\": 33.000082\n                }\n            ], \n            \"sum\": {\n                \"bits_per_second\": 865862543.4079545, \n                \"bytes\": 108230760, \n                \"end\": 34.000063, \n                \"omitted\": false, \n                \"seconds\": 0.9999809861183167, \n                \"sender\": false, \n                \"start\": 33.000082\n            }\n        }, \n        {\n            \"streams\": [\n                {\n                    \"bits_per_second\": 865309223.9124285, \n                    \"bytes\": 108165600, \n                    \"end\": 35.000081, \n                    \"omitted\": false, \n                    \"seconds\": 1.0000180006027222, \n                    \"sender\": false, \n                    \"socket\": 5, \n                    \"start\": 34.000063\n                }\n            ], \n            \"sum\": {\n                \"bits_per_second\": 865309223.9124285, \n                \"bytes\": 108165600, \n                \"end\": 35.000081, \n                \"omitted\": false, \n                \"seconds\": 1.0000180006027222, \n                \"sender\": false, \n                \"start\": 34.000063\n            }\n        }, \n        {\n            \"streams\": [\n                {\n                    \"bits_per_second\": 865859911.2850132, \n                    \"bytes\": 108230760, \n                    \"end\": 36.000065, \n                    \"omitted\": false, \n                    \"seconds\": 0.9999840259552002, \n                    \"sender\": false, \n                    \"socket\": 5, \n                    \"start\": 35.000081\n                }\n            ], \n            \"sum\": {\n                \"bits_per_second\": 865859911.2850132, \n                \"bytes\": 108230760, \n                \"end\": 36.000065, \n                \"omitted\": false, \n                \"seconds\": 0.9999840259552002, \n                \"sender\": false, \n                \"start\": 35.000081\n            }\n        }, \n        {\n            \"streams\": [\n                {\n                    \"bits_per_second\": 865326553.6343827, \n                    \"bytes\": 108165600, \n                    \"end\": 37.000063, \n                    \"omitted\": false, \n                    \"seconds\": 0.9999979734420776, \n                    \"sender\": false, \n                    \"socket\": 5, \n                    \"start\": 36.000065\n                }\n            ], \n            \"sum\": {\n                \"bits_per_second\": 865326553.6343827, \n                \"bytes\": 108165600, \n                \"end\": 37.000063, \n                \"omitted\": false, \n                \"seconds\": 0.9999979734420776, \n                \"sender\": false, \n                \"start\": 36.000065\n            }\n        }, \n        {\n            \"streams\": [\n                {\n                    \"bits_per_second\": 865305716.7912476, \n                    \"bytes\": 108165600, \n                    \"end\": 38.000085, \n                    \"omitted\": false, \n                    \"seconds\": 1.000022053718567, \n                    \"sender\": false, \n                    \"socket\": 5, \n                    \"start\": 37.000063\n                }\n            ], \n            \"sum\": {\n                \"bits_per_second\": 865305716.7912476, \n                \"bytes\": 108165600, \n                \"end\": 38.000085, \n                \"omitted\": false, \n                \"seconds\": 1.000022053718567, \n                \"sender\": false, \n                \"start\": 37.000063\n            }\n        }, \n        {\n            \"streams\": [\n                {\n                    \"bits_per_second\": 865865123.936177, \n                    \"bytes\": 108230760, \n                    \"end\": 39.000063, \n                    \"omitted\": false, \n                    \"seconds\": 0.999978005886078, \n                    \"sender\": false, \n                    \"socket\": 5, \n                    \"start\": 38.000085\n                }\n            ], \n            \"sum\": {\n                \"bits_per_second\": 865865123.936177, \n                \"bytes\": 108230760, \n                \"end\": 39.000063, \n                \"omitted\": false, \n                \"seconds\": 0.999978005886078, \n                \"sender\": false, \n                \"start\": 38.000085\n            }\n        }, \n        {\n            \"streams\": [\n                {\n                    \"bits_per_second\": 865312731.0620387, \n                    \"bytes\": 108165600, \n                    \"end\": 40.000077, \n                    \"omitted\": false, \n                    \"seconds\": 1.0000139474868774, \n                    \"sender\": false, \n                    \"socket\": 5, \n                    \"start\": 39.000063\n                }\n            ], \n            \"sum\": {\n                \"bits_per_second\": 865312731.0620387, \n                \"bytes\": 108165600, \n                \"end\": 40.000077, \n                \"omitted\": false, \n                \"seconds\": 1.0000139474868774, \n                \"sender\": false, \n                \"start\": 39.000063\n            }\n        }, \n        {\n            \"streams\": [\n                {\n                    \"bits_per_second\": 865859085.524251, \n                    \"bytes\": 108230760, \n                    \"end\": 41.000062, \n                    \"omitted\": false, \n                    \"seconds\": 0.9999849796295166, \n                    \"sender\": false, \n                    \"socket\": 5, \n                    \"start\": 40.000077\n                }\n            ], \n            \"sum\": {\n                \"bits_per_second\": 865859085.524251, \n                \"bytes\": 108230760, \n                \"end\": 41.000062, \n                \"omitted\": false, \n                \"seconds\": 0.9999849796295166, \n                \"sender\": false, \n                \"start\": 40.000077\n            }\n        }, \n        {\n            \"streams\": [\n                {\n                    \"bits_per_second\": 865323974.76275, \n                    \"bytes\": 108165600, \n                    \"end\": 42.000063, \n                    \"omitted\": false, \n                    \"seconds\": 1.0000009536743164, \n                    \"sender\": false, \n                    \"socket\": 5, \n                    \"start\": 41.000062\n                }\n            ], \n            \"sum\": {\n                \"bits_per_second\": 865323974.76275, \n                \"bytes\": 108165600, \n                \"end\": 42.000063, \n                \"omitted\": false, \n                \"seconds\": 1.0000009536743164, \n                \"sender\": false, \n                \"start\": 41.000062\n            }\n        }, \n        {\n            \"streams\": [\n                {\n                    \"bits_per_second\": 865841744.9120705, \n                    \"bytes\": 108230760, \n                    \"end\": 43.000068, \n                    \"omitted\": false, \n                    \"seconds\": 1.0000050067901611, \n                    \"sender\": false, \n                    \"socket\": 5, \n                    \"start\": 42.000063\n                }\n            ], \n            \"sum\": {\n                \"bits_per_second\": 865841744.9120705, \n                \"bytes\": 108230760, \n                \"end\": 43.000068, \n                \"omitted\": false, \n                \"seconds\": 1.0000050067901611, \n                \"sender\": false, \n                \"start\": 42.000063\n            }\n        }, \n        {\n            \"streams\": [\n                {\n                    \"bits_per_second\": 865328255.6980808, \n                    \"bytes\": 108165600, \n                    \"end\": 44.000064, \n                    \"omitted\": false, \n                    \"seconds\": 0.9999960064888, \n                    \"sender\": false, \n                    \"socket\": 5, \n                    \"start\": 43.000068\n                }\n            ], \n            \"sum\": {\n                \"bits_per_second\": 865328255.6980808, \n                \"bytes\": 108165600, \n                \"end\": 44.000064, \n                \"omitted\": false, \n                \"seconds\": 0.9999960064888, \n                \"sender\": false, \n                \"start\": 43.000068\n            }\n        }, \n        {\n            \"streams\": [\n                {\n                    \"bits_per_second\": 865310049.121544, \n                    \"bytes\": 108165600, \n                    \"end\": 45.000081, \n                    \"omitted\": false, \n                    \"seconds\": 1.0000170469284058, \n                    \"sender\": false, \n                    \"socket\": 5, \n                    \"start\": 44.000064\n                }\n            ], \n            \"sum\": {\n                \"bits_per_second\": 865310049.121544, \n                \"bytes\": 108165600, \n                \"end\": 45.000081, \n                \"omitted\": false, \n                \"seconds\": 1.0000170469284058, \n                \"sender\": false, \n                \"start\": 44.000064\n            }\n        }, \n        {\n            \"streams\": [\n                {\n                    \"bits_per_second\": 865861666.0318626, \n                    \"bytes\": 108230760, \n                    \"end\": 46.000063, \n                    \"omitted\": false, \n                    \"seconds\": 0.9999819993972778, \n                    \"sender\": false, \n                    \"socket\": 5, \n                    \"start\": 45.000081\n                }\n            ], \n            \"sum\": {\n                \"bits_per_second\": 865861666.0318626, \n                \"bytes\": 108230760, \n                \"end\": 46.000063, \n                \"omitted\": false, \n                \"seconds\": 0.9999819993972778, \n                \"sender\": false, \n                \"start\": 45.000081\n            }\n        }, \n        {\n            \"streams\": [\n                {\n                    \"bits_per_second\": 865308398.704887, \n                    \"bytes\": 108165600, \n                    \"end\": 47.000082, \n                    \"omitted\": false, \n                    \"seconds\": 1.0000189542770386, \n                    \"sender\": false, \n                    \"socket\": 5, \n                    \"start\": 46.000063\n                }\n            ], \n            \"sum\": {\n                \"bits_per_second\": 865308398.704887, \n                \"bytes\": 108165600, \n                \"end\": 47.000082, \n                \"omitted\": false, \n                \"seconds\": 1.0000189542770386, \n                \"sender\": false, \n                \"start\": 46.000063\n            }\n        }, \n        {\n            \"streams\": [\n                {\n                    \"bits_per_second\": 865867704.4797813, \n                    \"bytes\": 108230760, \n                    \"end\": 48.000057, \n                    \"omitted\": false, \n                    \"seconds\": 0.999975025653839, \n                    \"sender\": false, \n                    \"socket\": 5, \n                    \"start\": 47.000082\n                }\n            ], \n            \"sum\": {\n                \"bits_per_second\": 865867704.4797813, \n                \"bytes\": 108230760, \n                \"end\": 48.000057, \n                \"omitted\": false, \n                \"seconds\": 0.999975025653839, \n                \"sender\": false, \n                \"start\": 47.000082\n            }\n        }, \n        {\n            \"streams\": [\n                {\n                    \"bits_per_second\": 865304066.391117, \n                    \"bytes\": 108165600, \n                    \"end\": 49.000081, \n                    \"omitted\": false, \n                    \"seconds\": 1.0000239610672, \n                    \"sender\": false, \n                    \"socket\": 5, \n                    \"start\": 48.000057\n                }\n            ], \n            \"sum\": {\n                \"bits_per_second\": 865304066.391117, \n                \"bytes\": 108165600, \n                \"end\": 49.000081, \n                \"omitted\": false, \n                \"seconds\": 1.0000239610672, \n                \"sender\": false, \n                \"start\": 48.000057\n            }\n        }, \n        {\n            \"streams\": [\n                {\n                    \"bits_per_second\": 865855627.668166, \n                    \"bytes\": 108230760, \n                    \"end\": 50.00007, \n                    \"omitted\": false, \n                    \"seconds\": 0.9999889731407166, \n                    \"sender\": false, \n                    \"socket\": 5, \n                    \"start\": 49.000081\n                }\n            ], \n            \"sum\": {\n                \"bits_per_second\": 865855627.668166, \n                \"bytes\": 108230760, \n                \"end\": 50.00007, \n                \"omitted\": false, \n                \"seconds\": 0.9999889731407166, \n                \"sender\": false, \n                \"start\": 49.000081\n            }\n        }, \n        {\n            \"streams\": [\n                {\n                    \"bits_per_second\": 865245171.8575628, \n                    \"bytes\": 108165600, \n                    \"end\": 51.000162, \n                    \"omitted\": false, \n                    \"seconds\": 1.0000920295715332, \n                    \"sender\": false, \n                    \"socket\": 5, \n                    \"start\": 50.00007\n                }\n            ], \n            \"sum\": {\n                \"bits_per_second\": 865245171.8575628, \n                \"bytes\": 108165600, \n                \"end\": 51.000162, \n                \"omitted\": false, \n                \"seconds\": 1.0000920295715332, \n                \"sender\": false, \n                \"start\": 50.00007\n            }\n        }, \n        {\n            \"streams\": [\n                {\n                    \"bits_per_second\": 865389689.206232, \n                    \"bytes\": 108165600, \n                    \"end\": 52.000087, \n                    \"omitted\": false, \n                    \"seconds\": 0.9999250173568726, \n                    \"sender\": false, \n                    \"socket\": 5, \n                    \"start\": 51.000162\n                }\n            ], \n            \"sum\": {\n                \"bits_per_second\": 865389689.206232, \n                \"bytes\": 108165600, \n                \"end\": 52.000087, \n                \"omitted\": false, \n                \"seconds\": 0.9999250173568726, \n                \"sender\": false, \n                \"start\": 51.000162\n            }\n        }, \n        {\n            \"streams\": [\n                {\n                    \"bits_per_second\": 865868581.8681105, \n                    \"bytes\": 108230760, \n                    \"end\": 53.000061, \n                    \"omitted\": false, \n                    \"seconds\": 0.999974012374878, \n                    \"sender\": false, \n                    \"socket\": 5, \n                    \"start\": 52.000087\n                }\n            ], \n            \"sum\": {\n                \"bits_per_second\": 865868581.8681105, \n                \"bytes\": 108230760, \n                \"end\": 53.000061, \n                \"omitted\": false, \n                \"seconds\": 0.999974012374878, \n                \"sender\": false, \n                \"start\": 52.000087\n            }\n        }, \n        {\n            \"streams\": [\n                {\n                    \"bits_per_second\": 865306645.1440877, \n                    \"bytes\": 108165600, \n                    \"end\": 54.000082, \n                    \"omitted\": false, \n                    \"seconds\": 1.000020980834961, \n                    \"sender\": false, \n                    \"socket\": 5, \n                    \"start\": 53.000061\n                }\n            ], \n            \"sum\": {\n                \"bits_per_second\": 865306645.1440877, \n                \"bytes\": 108165600, \n                \"end\": 54.000082, \n                \"omitted\": false, \n                \"seconds\": 1.000020980834961, \n                \"sender\": false, \n                \"start\": 53.000061\n            }\n        }, \n        {\n            \"streams\": [\n                {\n                    \"bits_per_second\": 865865123.936177, \n                    \"bytes\": 108230760, \n                    \"end\": 55.00006, \n                    \"omitted\": false, \n                    \"seconds\": 0.999978005886078, \n                    \"sender\": false, \n                    \"socket\": 5, \n                    \"start\": 54.000082\n                }\n            ], \n            \"sum\": {\n                \"bits_per_second\": 865865123.936177, \n                \"bytes\": 108230760, \n                \"end\": 55.00006, \n                \"omitted\": false, \n                \"seconds\": 0.999978005886078, \n                \"sender\": false, \n                \"start\": 54.000082\n            }\n        }, \n        {\n            \"streams\": [\n                {\n                    \"bits_per_second\": 865310049.121544, \n                    \"bytes\": 108165600, \n                    \"end\": 56.000077, \n                    \"omitted\": false, \n                    \"seconds\": 1.0000170469284058, \n                    \"sender\": false, \n                    \"socket\": 5, \n                    \"start\": 55.00006\n                }\n            ], \n            \"sum\": {\n                \"bits_per_second\": 865310049.121544, \n                \"bytes\": 108165600, \n                \"end\": 56.000077, \n                \"omitted\": false, \n                \"seconds\": 1.0000170469284058, \n                \"sender\": false, \n                \"start\": 55.00006\n            }\n        }, \n        {\n            \"streams\": [\n                {\n                    \"bits_per_second\": 865859085.524251, \n                    \"bytes\": 108230760, \n                    \"end\": 57.000062, \n                    \"omitted\": false, \n                    \"seconds\": 0.9999849796295166, \n                    \"sender\": false, \n                    \"socket\": 5, \n                    \"start\": 56.000077\n                }\n            ], \n            \"sum\": {\n                \"bits_per_second\": 865859085.524251, \n                \"bytes\": 108230760, \n                \"end\": 57.000062, \n                \"omitted\": false, \n                \"seconds\": 0.9999849796295166, \n                \"sender\": false, \n                \"start\": 56.000077\n            }\n        }, \n        {\n            \"streams\": [\n                {\n                    \"bits_per_second\": 865326553.6343827, \n                    \"bytes\": 108165600, \n                    \"end\": 58.00006, \n                    \"omitted\": false, \n                    \"seconds\": 0.9999979734420776, \n                    \"sender\": false, \n                    \"socket\": 5, \n                    \"start\": 57.000062\n                }\n            ], \n            \"sum\": {\n                \"bits_per_second\": 865326553.6343827, \n                \"bytes\": 108165600, \n                \"end\": 58.00006, \n                \"omitted\": false, \n                \"seconds\": 0.9999979734420776, \n                \"sender\": false, \n                \"start\": 57.000062\n            }\n        }, \n        {\n            \"streams\": [\n                {\n                    \"bits_per_second\": 865306645.1440877, \n                    \"bytes\": 108165600, \n                    \"end\": 59.000081, \n                    \"omitted\": false, \n                    \"seconds\": 1.000020980834961, \n                    \"sender\": false, \n                    \"socket\": 5, \n                    \"start\": 58.00006\n                }\n            ], \n            \"sum\": {\n                \"bits_per_second\": 865306645.1440877, \n                \"bytes\": 108165600, \n                \"end\": 59.000081, \n                \"omitted\": false, \n                \"seconds\": 1.000020980834961, \n                \"sender\": false, \n                \"start\": 58.00006\n            }\n        }, \n        {\n            \"streams\": [\n                {\n                    \"bits_per_second\": 865862543.4079545, \n                    \"bytes\": 108230760, \n                    \"end\": 60.000062, \n                    \"omitted\": false, \n                    \"seconds\": 0.9999809861183167, \n                    \"sender\": false, \n                    \"socket\": 5, \n                    \"start\": 59.000081\n                }\n            ], \n            \"sum\": {\n                \"bits_per_second\": 865862543.4079545, \n                \"bytes\": 108230760, \n                \"end\": 60.000062, \n                \"omitted\": false, \n                \"seconds\": 0.9999809861183167, \n                \"sender\": false, \n                \"start\": 59.000081\n            }\n        }, \n        {\n            \"streams\": [\n                {\n                    \"bits_per_second\": 860667676.5099514, \n                    \"bytes\": 8275320, \n                    \"end\": 60.076982, \n                    \"omitted\": false, \n                    \"seconds\": 0.0769200026988983, \n                    \"sender\": false, \n                    \"socket\": 5, \n                    \"start\": 60.000062\n                }\n            ], \n            \"sum\": {\n                \"bits_per_second\": 860667676.5099514, \n                \"bytes\": 8275320, \n                \"end\": 60.076982, \n                \"omitted\": false, \n                \"seconds\": 0.0769200026988983, \n                \"sender\": false, \n                \"start\": 60.000062\n            }\n        }\n    ], \n    \"start\": {\n        \"accepted_connection\": {\n            \"host\": \"10.0.0.1\", \n            \"port\": 41169\n        }, \n        \"connected\": [\n            {\n                \"local_host\": \"10.0.0.2\", \n                \"local_port\": 5201, \n                \"remote_host\": \"10.0.0.1\", \n                \"remote_port\": 37209, \n                \"socket\": 5\n            }\n        ], \n        \"cookie\": \"57g2xjwzh4hbs77nruywotc6hhbgkhsbf2sq\", \n        \"fq_rate\": 0, \n        \"rcvbuf_actual\": 87380, \n        \"sndbuf_actual\": 87380, \n        \"sock_bufsize\": 0, \n        \"system_info\": \"REDACTED\", \n        \"target_bitrate\": 0, \n        \"tcp_mss_default\": 0, \n        \"test_start\": {\n            \"bidir\": 0, \n            \"blksize\": 131072, \n            \"blocks\": 0, \n            \"bytes\": 0, \n            \"duration\": 60, \n            \"fqrate\": 0, \n            \"num_streams\": 1, \n            \"omit\": 0, \n            \"protocol\": \"TCP\", \n            \"reverse\": 0, \n            \"target_bitrate\": 0, \n            \"tos\": 0\n        }, \n        \"timestamp\": {\n            \"time\": \"Wed, 17 Apr 2024 01:14:34 GMT\", \n            \"timesecs\": 1713316474\n        }, \n        \"version\": \"iperf 3.14\"\n    }\n}\n","summary":{"streams":[{"end":60.000092,"rtt":77087,"start":0,"stream-id":5,"retransmits":0,"throughput-bits":867013736.1789378,"throughput-bytes":6502612992}],"summary":{"end":60.000092,"start":0,"retransmits":0,"throughput-bits":867013736.1789378,"throughput-bytes":6502612992,"receiver-throughput-bits":865535251.554414}},"intervals":[{"streams":[{"end":1.000073,"rtt":77088,"start":0,"omitted":false,"stream-id":5,"retransmits":0,"tcp-window-size":16698336,"throughput-bits":955183049.584048,"throughput-bytes":119406592}],"summary":{"end":1.000073,"start":0,"omitted":false,"retransmits":0,"throughput-bits":955183049.584048,"throughput-bytes":119406592}},{"streams":[{"end":2.000177,"rtt":77084,"start":1.000073,"omitted":false,"stream-id":5,"retransmits":0,"tcp-window-size":16698336,"throughput-bits":870227619.4034243,"throughput-bytes":108789760}],"summary":{"end":2.000177,"start":1.000073,"omitted":false,"retransmits":0,"throughput-bits":870227619.4034243,"throughput-bytes":108789760}},{"streams":[{"end":3.000077,"rtt":77085,"start":2.000177,"omitted":false,"stream-id":5,"retransmits":0,"tcp-window-size":16698336,"throughput-bits":859918326.1020374,"throughput-bytes":107479040}],"summary":{"end":3.000077,"start":2.000177,"omitted":false,"retransmits":0,"throughput-bits":859918326.1020374,"throughput-bytes":107479040}},{"streams":[{"end":4.000182,"rtt":77080,"start":3.000077,"omitted":false,"stream-id":5,"retransmits":0,"tcp-window-size":16698336,"throughput-bits":870226685.848523,"throughput-bytes":108789760}],"summary":{"end":4.000182,"start":3.000077,"omitted":false,"retransmits":0,"throughput-bits":870226685.848523,"throughput-bytes":108789760}},{"streams":[{"end":5.000098,"rtt":77090,"start":4.000182,"omitted":false,"stream-id":5,"retransmits":0,"tcp-window-size":16698336,"throughput-bits":859904537.3150227,"throughput-bytes":107479040}],"summary":{"end":5.000098,"start":4.000182,"omitted":false,"retransmits":0,"throughput-bits":859904537.3150227,"throughput-bytes":107479040}},{"streams":[{"end":6.000056,"rtt":77081,"start":5.000098,"omitted":false,"stream-id":5,"retransmits":0,"tcp-window-size":16698336,"throughput-bits":870354653.4118614,"throughput-bytes":108789760}],"summary":{"end":6.000056,"start":5.000098,"omitted":false,"retransmits":0,"throughput-bits":870354653.4118614,"throughput-bytes":108789760}},{"streams":[{"end":7.000061,"rtt":77085,"start":6.000056,"omitted":false,"stream-id":5,"retransmits":0,"tcp-window-size":16698336,"throughput-bits":870313722.521817,"throughput-bytes":108789760}],"summary":{"end":7.000061,"start":6.000056,"omitted":false,"retransmits":0,"throughput-bits":870313722.521817,"throughput-bytes":108789760}},{"streams":[{"end":8.000056,"rtt":77084,"start":7.000061,"omitted":false,"stream-id":5,"retransmits":0,"tcp-window-size":16698336,"throughput-bits":859836625.0215544,"throughput-bytes":107479040}],"summary":{"end":8.000056,"start":7.000061,"omitted":false,"retransmits":0,"throughput-bits":859836625.0215544,"throughput-bytes":107479040}},{"streams":[{"end":9.00008,"rtt":77088,"start":8.000056,"omitted":false,"stream-id":5,"retransmits":0,"tcp-window-size":16698336,"throughput-bits":870297226.749666,"throughput-bytes":108789760}],"summary":{"end":9.00008,"start":8.000056,"omitted":false,"retransmits":0,"throughput-bits":870297226.749666,"throughput-bytes":108789760}},{"streams":[{"end":10.000174,"rtt":77084,"start":9.00008,"omitted":false,"stream-id":5,"retransmits":0,"tcp-window-size":16698336,"throughput-bits":859751455.105839,"throughput-bytes":107479040}],"summary":{"end":10.000174,"start":9.00008,"omitted":false,"retransmits":0,"throughput-bits":859751455.105839,"throughput-bytes":107479040}},{"streams":[{"end":11.000061,"rtt":77088,"start":10.000174,"omitted":false,"stream-id":5,"retransmits":0,"tcp-window-size":16698336,"throughput-bits":870416446.1163948,"throughput-bytes":108789760}],"summary":{"end":11.000061,"start":10.000174,"omitted":false,"retransmits":0,"throughput-bits":870416446.1163948,"throughput-bytes":108789760}},{"streams":[{"end":12.000068,"rtt":77086,"start":11.000061,"omitted":false,"stream-id":5,"retransmits":0,"tcp-window-size":16698336,"throughput-bits":859826272.542534,"throughput-bytes":107479040}],"summary":{"end":12.000068,"start":11.000061,"omitted":false,"retransmits":0,"throughput-bits":859826272.542534,"throughput-bytes":107479040}},{"streams":[{"end":13.0002,"rtt":77081,"start":12.000068,"omitted":false,"stream-id":5,"retransmits":0,"tcp-window-size":16698336,"throughput-bits":870203243.904309,"throughput-bytes":108789760}],"summary":{"end":13.0002,"start":12.000068,"omitted":false,"retransmits":0,"throughput-bits":870203243.904309,"throughput-bytes":108789760}},{"streams":[{"end":14.00008,"rtt":77091,"start":13.0002,"omitted":false,"stream-id":5,"retransmits":0,"tcp-window-size":16698336,"throughput-bits":859935498.6298002,"throughput-bytes":107479040}],"summary":{"end":14.00008,"start":13.0002,"omitted":false,"retransmits":0,"throughput-bits":859935498.6298002,"throughput-bytes":107479040}},{"streams":[{"end":15.000058,"rtt":77084,"start":14.00008,"omitted":false,"stream-id":5,"retransmits":0,"tcp-window-size":16698336,"throughput-bits":870337222.296018,"throughput-bytes":108789760}],"summary":{"end":15.000058,"start":14.00008,"omitted":false,"retransmits":0,"throughput-bits":870337222.296018,"throughput-bytes":108789760}},{"streams":[{"end":16.000074,"rtt":77090,"start":15.000058,"omitted":false,"stream-id":5,"retransmits":0,"tcp-window-size":16698336,"throughput-bits":859818585.2194,"throughput-bytes":107479040}],"summary":{"end":16.000074,"start":15.000058,"omitted":false,"retransmits":0,"throughput-bits":859818585.2194,"throughput-bytes":107479040}},{"streams":[{"end":17.000058,"rtt":77094,"start":16.000074,"omitted":false,"stream-id":5,"retransmits":0,"tcp-window-size":16698336,"throughput-bits":870331982.7220827,"throughput-bytes":108789760}],"summary":{"end":17.000058,"start":16.000074,"omitted":false,"retransmits":0,"throughput-bits":870331982.7220827,"throughput-bytes":108789760}},{"streams":[{"end":18.000038,"rtt":77088,"start":17.000058,"omitted":false,"stream-id":5,"retransmits":0,"tcp-window-size":16698336,"throughput-bits":870335510.3490804,"throughput-bytes":108789760}],"summary":{"end":18.000038,"start":17.000058,"omitted":false,"retransmits":0,"throughput-bits":870335510.3490804,"throughput-bytes":108789760}},{"streams":[{"end":19.000147,"rtt":77088,"start":18.000038,"omitted":false,"stream-id":5,"retransmits":0,"tcp-window-size":16698336,"throughput-bits":859738645.2065517,"throughput-bytes":107479040}],"summary":{"end":19.000147,"start":18.000038,"omitted":false,"retransmits":0,"throughput-bits":859738645.2065517,"throughput-bytes":107479040}},{"streams":[{"end":20.000059,"rtt":77089,"start":19.000147,"omitted":false,"stream-id":5,"retransmits":0,"tcp-window-size":16698336,"throughput-bits":870394654.23673,"throughput-bytes":108789760}],"summary":{"end":20.000059,"start":19.000147,"omitted":false,"retransmits":0,"throughput-bits":870394654.23673,"throughput-bytes":108789760}},{"streams":[{"end":21.000077,"rtt":77089,"start":20.000059,"omitted":false,"stream-id":5,"retransmits":0,"tcp-window-size":16698336,"throughput-bits":859816842.7785993,"throughput-bytes":107479040}],"summary":{"end":21.000077,"start":20.000059,"omitted":false,"retransmits":0,"throughput-bits":859816842.7785993,"throughput-bytes":107479040}},{"streams":[{"end":22.000058,"rtt":77087,"start":21.000077,"omitted":false,"stream-id":5,"retransmits":0,"tcp-window-size":16698336,"throughput-bits":870334628.43965,"throughput-bytes":108789760}],"summary":{"end":22.000058,"start":21.000077,"omitted":false,"retransmits":0,"throughput-bits":870334628.43965,"throughput-bytes":108789760}},{"streams":[{"end":23.000074,"rtt":77090,"start":22.000058,"omitted":false,"stream-id":5,"retransmits":0,"tcp-window-size":16698336,"throughput-bits":859818585.2194,"throughput-bytes":107479040}],"summary":{"end":23.000074,"start":22.000058,"omitted":false,"retransmits":0,"throughput-bits":859818585.2194,"throughput-bytes":107479040}},{"streams":[{"end":24.000061,"rtt":77090,"start":23.000074,"omitted":false,"stream-id":5,"retransmits":0,"tcp-window-size":16698336,"throughput-bits":870329388.8969457,"throughput-bytes":108789760}],"summary":{"end":24.000061,"start":23.000074,"omitted":false,"retransmits":0,"throughput-bits":870329388.8969457,"throughput-bytes":108789760}},{"streams":[{"end":25.000069,"rtt":77089,"start":24.000061,"omitted":false,"stream-id":5,"retransmits":0,"tcp-window-size":16698336,"throughput-bits":859825452.5548505,"throughput-bytes":107479040}],"summary":{"end":25.000069,"start":24.000061,"omitted":false,"retransmits":0,"throughput-bits":859825452.5548505,"throughput-bytes":107479040}},{"streams":[{"end":26.000073,"rtt":77092,"start":25.000069,"omitted":false,"stream-id":5,"retransmits":0,"tcp-window-size":16698336,"throughput-bits":870314552.5142974,"throughput-bytes":108789760}],"summary":{"end":26.000073,"start":25.000069,"omitted":false,"retransmits":0,"throughput-bits":870314552.5142974,"throughput-bytes":108789760}},{"streams":[{"end":27.000063,"rtt":77084,"start":26.000073,"omitted":false,"stream-id":5,"retransmits":0,"tcp-window-size":16698336,"throughput-bits":859840930.0862178,"throughput-bytes":107479040}],"summary":{"end":27.000063,"start":26.000073,"omitted":false,"retransmits":0,"throughput-bits":859840930.0862178,"throughput-bytes":107479040}},{"streams":[{"end":28.000081,"rtt":77089,"start":27.000063,"omitted":false,"stream-id":5,"retransmits":0,"tcp-window-size":16698336,"throughput-bits":870302414.031997,"throughput-bytes":108789760}],"summary":{"end":28.000081,"start":27.000063,"omitted":false,"retransmits":0,"throughput-bits":870302414.031997,"throughput-bytes":108789760}},{"streams":[{"end":29.000061,"rtt":77084,"start":28.000081,"omitted":false,"stream-id":5,"retransmits":0,"tcp-window-size":16698336,"throughput-bits":870335510.3490804,"throughput-bytes":108789760}],"summary":{"end":29.000061,"start":28.000081,"omitted":false,"retransmits":0,"throughput-bits":870335510.3490804,"throughput-bytes":108789760}},{"streams":[{"end":30.000073,"rtt":77090,"start":29.000061,"omitted":false,"stream-id":5,"retransmits":0,"tcp-window-size":16698336,"throughput-bits":859821967.624644,"throughput-bytes":107479040}],"summary":{"end":30.000073,"start":29.000061,"omitted":false,"retransmits":0,"throughput-bits":859821967.624644,"throughput-bytes":107479040}},{"streams":[{"end":31.000063,"rtt":77089,"start":30.000073,"omitted":false,"stream-id":5,"retransmits":0,"tcp-window-size":16698336,"throughput-bits":870326795.0872692,"throughput-bytes":108789760}],"summary":{"end":31.000063,"start":30.000073,"omitted":false,"retransmits":0,"throughput-bits":870326795.0872692,"throughput-bytes":108789760}},{"streams":[{"end":32.000056,"rtt":77089,"start":31.000063,"omitted":false,"stream-id":5,"retransmits":0,"tcp-window-size":16698336,"throughput-bits":859838316.2918166,"throughput-bytes":107479040}],"summary":{"end":32.000056,"start":31.000063,"omitted":false,"retransmits":0,"throughput-bits":859838316.2918166,"throughput-bytes":107479040}},{"streams":[{"end":33.000081,"rtt":77089,"start":32.000056,"omitted":false,"stream-id":5,"retransmits":0,"tcp-window-size":16698336,"throughput-bits":870296293.0454135,"throughput-bytes":108789760}],"summary":{"end":33.000081,"start":32.000056,"omitted":false,"retransmits":0,"throughput-bits":870296293.0454135,"throughput-bytes":108789760}},{"streams":[{"end":34.000072,"rtt":77088,"start":33.000081,"omitted":false,"stream-id":5,"retransmits":0,"tcp-window-size":16698336,"throughput-bits":859840058.8196517,"throughput-bytes":107479040}],"summary":{"end":34.000072,"start":33.000081,"omitted":false,"retransmits":0,"throughput-bits":859840058.8196517,"throughput-bytes":107479040}},{"streams":[{"end":35.000059,"rtt":77088,"start":34.000072,"omitted":false,"stream-id":5,"retransmits":0,"tcp-window-size":16698336,"throughput-bits":870329388.8969457,"throughput-bytes":108789760}],"summary":{"end":35.000059,"start":34.000072,"omitted":false,"retransmits":0,"throughput-bits":870329388.8969457,"throughput-bytes":108789760}},{"streams":[{"end":36.000061,"rtt":77089,"start":35.000059,"omitted":false,"stream-id":5,"retransmits":0,"tcp-window-size":16698336,"throughput-bits":859830577.5035312,"throughput-bytes":107479040}],"summary":{"end":36.000061,"start":35.000059,"omitted":false,"retransmits":0,"throughput-bits":859830577.5035312,"throughput-bytes":107479040}},{"streams":[{"end":37.000073,"rtt":77091,"start":36.000061,"omitted":false,"stream-id":5,"retransmits":0,"tcp-window-size":16698336,"throughput-bits":870307601.376164,"throughput-bytes":108789760}],"summary":{"end":37.000073,"start":36.000061,"omitted":false,"retransmits":0,"throughput-bits":870307601.376164,"throughput-bytes":108789760}},{"streams":[{"end":38.000164,"rtt":77087,"start":37.000073,"omitted":false,"stream-id":5,"retransmits":0,"tcp-window-size":16698336,"throughput-bits":859754119.612848,"throughput-bytes":107479040}],"summary":{"end":38.000164,"start":37.000073,"omitted":false,"retransmits":0,"throughput-bits":859754119.612848,"throughput-bytes":107479040}},{"streams":[{"end":39.000061,"rtt":77087,"start":38.000164,"omitted":false,"stream-id":5,"retransmits":0,"tcp-window-size":16698336,"throughput-bits":870407729.2335865,"throughput-bytes":108789760}],"summary":{"end":39.000061,"start":38.000164,"omitted":false,"retransmits":0,"throughput-bits":870407729.2335865,"throughput-bytes":108789760}},{"streams":[{"end":40.000067,"rtt":77087,"start":39.000061,"omitted":false,"stream-id":5,"retransmits":0,"tcp-window-size":16698336,"throughput-bits":870312892.5309197,"throughput-bytes":108789760}],"summary":{"end":40.000067,"start":39.000061,"omitted":false,"retransmits":0,"throughput-bits":870312892.5309197,"throughput-bytes":108789760}},{"streams":[{"end":41.000063,"rtt":77091,"start":40.000067,"omitted":false,"stream-id":5,"retransmits":0,"tcp-window-size":16698336,"throughput-bits":859835753.7637128,"throughput-bytes":107479040}],"summary":{"end":41.000063,"start":40.000067,"omitted":false,"retransmits":0,"throughput-bits":859835753.7637128,"throughput-bytes":107479040}},{"streams":[{"end":42.00007,"rtt":77090,"start":41.000063,"omitted":false,"stream-id":5,"retransmits":0,"tcp-window-size":16698336,"throughput-bits":870311958.7930526,"throughput-bytes":108789760}],"summary":{"end":42.00007,"start":41.000063,"omitted":false,"retransmits":0,"throughput-bits":870311958.7930526,"throughput-bytes":108789760}},{"streams":[{"end":43.00006,"rtt":77086,"start":42.00007,"omitted":false,"stream-id":5,"retransmits":0,"tcp-window-size":16698336,"throughput-bits":859840930.0862178,"throughput-bytes":107479040}],"summary":{"end":43.00006,"start":42.00007,"omitted":false,"retransmits":0,"throughput-bits":859840930.0862178,"throughput-bytes":107479040}},{"streams":[{"end":44.000065,"rtt":77091,"start":43.00006,"omitted":false,"stream-id":5,"retransmits":0,"tcp-window-size":16698336,"throughput-bits":870313722.521817,"throughput-bytes":108789760}],"summary":{"end":44.000065,"start":43.00006,"omitted":false,"retransmits":0,"throughput-bits":870313722.521817,"throughput-bytes":108789760}},{"streams":[{"end":45.000201,"rtt":77086,"start":44.000065,"omitted":false,"stream-id":5,"retransmits":0,"tcp-window-size":16698336,"throughput-bits":859715383.4054582,"throughput-bytes":107479040}],"summary":{"end":45.000201,"start":44.000065,"omitted":false,"retransmits":0,"throughput-bits":859715383.4054582,"throughput-bytes":107479040}},{"streams":[{"end":46.000062,"rtt":77094,"start":45.000201,"omitted":false,"stream-id":5,"retransmits":0,"tcp-window-size":16698336,"throughput-bits":870439069.317277,"throughput-bytes":108789760}],"summary":{"end":46.000062,"start":45.000201,"omitted":false,"retransmits":0,"throughput-bits":870439069.317277,"throughput-bytes":108789760}},{"streams":[{"end":47.000094,"rtt":77085,"start":46.000062,"omitted":false,"stream-id":5,"retransmits":0,"tcp-window-size":16698336,"throughput-bits":859804850.877586,"throughput-bytes":107479040}],"summary":{"end":47.000094,"start":46.000062,"omitted":false,"retransmits":0,"throughput-bits":859804850.877586,"throughput-bytes":107479040}},{"streams":[{"end":48.000052,"rtt":77090,"start":47.000094,"omitted":false,"stream-id":5,"retransmits":0,"tcp-window-size":16698336,"throughput-bits":870354653.4118614,"throughput-bytes":108789760}],"summary":{"end":48.000052,"start":47.000094,"omitted":false,"retransmits":0,"throughput-bits":870354653.4118614,"throughput-bytes":108789760}},{"streams":[{"end":49.000065,"rtt":77086,"start":48.000052,"omitted":false,"stream-id":5,"retransmits":0,"tcp-window-size":16698336,"throughput-bits":859821147.6451715,"throughput-bytes":107479040}],"summary":{"end":49.000065,"start":48.000052,"omitted":false,"retransmits":0,"throughput-bits":859821147.6451715,"throughput-bytes":107479040}},{"streams":[{"end":50.000056,"rtt":77090,"start":49.000065,"omitted":false,"stream-id":5,"retransmits":0,"tcp-window-size":16698336,"throughput-bits":870325913.195501,"throughput-bytes":108789760}],"summary":{"end":50.000056,"start":49.000065,"omitted":false,"retransmits":0,"throughput-bits":870325913.195501,"throughput-bytes":108789760}},{"streams":[{"end":51.000063,"rtt":77085,"start":50.000056,"omitted":false,"stream-id":5,"retransmits":0,"tcp-window-size":16698336,"throughput-bits":870311958.7930526,"throughput-bytes":108789760}],"summary":{"end":51.000063,"start":50.000056,"omitted":false,"retransmits":0,"throughput-bits":870311958.7930526,"throughput-bytes":108789760}},{"streams":[{"end":52.000168,"rtt":77088,"start":51.000063,"omitted":false,"stream-id":5,"retransmits":0,"tcp-window-size":16698336,"throughput-bits":859742026.9828782,"throughput-bytes":107479040}],"summary":{"end":52.000168,"start":51.000063,"omitted":false,"retransmits":0,"throughput-bits":859742026.9828782,"throughput-bytes":107479040}},{"streams":[{"end":53.000067,"rtt":77084,"start":52.000168,"omitted":false,"stream-id":5,"retransmits":0,"tcp-window-size":16698336,"throughput-bits":870405965.1237845,"throughput-bytes":108789760}],"summary":{"end":53.000067,"start":52.000168,"omitted":false,"retransmits":0,"throughput-bits":870405965.1237845,"throughput-bytes":108789760}},{"streams":[{"end":54.000186,"rtt":77083,"start":53.000067,"omitted":false,"stream-id":5,"retransmits":0,"tcp-window-size":16698336,"throughput-bits":859730037.1686776,"throughput-bytes":107479040}],"summary":{"end":54.000186,"start":53.000067,"omitted":false,"retransmits":0,"throughput-bits":859730037.1686776,"throughput-bytes":107479040}},{"streams":[{"end":55.000092,"rtt":77083,"start":54.000186,"omitted":false,"stream-id":5,"retransmits":0,"tcp-window-size":16698336,"throughput-bits":870399894.565285,"throughput-bytes":108789760}],"summary":{"end":55.000092,"start":54.000186,"omitted":false,"retransmits":0,"throughput-bits":870399894.565285,"throughput-bytes":108789760}},{"streams":[{"end":56.000173,"rtt":77087,"start":55.000092,"omitted":false,"stream-id":5,"retransmits":0,"tcp-window-size":16698336,"throughput-bits":859762728.132982,"throughput-bytes":107479040}],"summary":{"end":56.000173,"start":55.000092,"omitted":false,"retransmits":0,"throughput-bits":859762728.132982,"throughput-bytes":107479040}},{"streams":[{"end":57.000065,"rtt":77085,"start":56.000173,"omitted":false,"stream-id":5,"retransmits":0,"tcp-window-size":16698336,"throughput-bits":870412087.6531665,"throughput-bytes":108789760}],"summary":{"end":57.000065,"start":56.000173,"omitted":false,"retransmits":0,"throughput-bits":870412087.6531665,"throughput-bytes":108789760}},{"streams":[{"end":58.000077,"rtt":77089,"start":57.000065,"omitted":false,"stream-id":5,"retransmits":0,"tcp-window-size":16698336,"throughput-bits":859821967.624644,"throughput-bytes":107479040}],"summary":{"end":58.000077,"start":57.000065,"omitted":false,"retransmits":0,"throughput-bits":859821967.624644,"throughput-bytes":107479040}},{"streams":[{"end":59.000165,"rtt":77081,"start":58.000077,"omitted":false,"stream-id":5,"retransmits":0,"tcp-window-size":16698336,"throughput-bits":870241519.2355447,"throughput-bytes":108789760}],"summary":{"end":59.000165,"start":58.000077,"omitted":false,"retransmits":0,"throughput-bits":870241519.2355447,"throughput-bytes":108789760}},{"streams":[{"end":60.000092,"rtt":77086,"start":59.000165,"omitted":false,"stream-id":5,"retransmits":0,"tcp-window-size":16698336,"throughput-bits":859895105.834351,"throughput-bytes":107479040}],"summary":{"end":60.000092,"start":59.000165,"omitted":false,"retransmits":0,"throughput-bits":859895105.834351,"throughput-bytes":107479040}}],"succeeded":true}
