{"diags":"Participant 0:\n/usr/bin/iperf3 -p 5201 -c 172.16.0.1 -t 10 --json --rsa-public-key-path /var/run/pscheduler-server/runner/tmp/tmp9qzsi7t3/tmpjzsx8b5i/public-key --username PdqZeThwYknwgAJE3xFr\n\n{\n    \"end\": {\n        \"cpu_utilization_percent\": {\n            \"host_system\": 0.24144719404518705, \n            \"host_total\": 0.274328606799393, \n            \"host_user\": 0.032871511696466044, \n            \"remote_system\": 4.562399788197987, \n            \"remote_total\": 5.66385949673224, \n            \"remote_user\": 1.1014497927096876\n        }, \n        \"receiver_tcp_congestion\": \"htcp\", \n        \"sender_tcp_congestion\": \"htcp\", \n        \"streams\": [\n            {\n                \"receiver\": {\n                    \"bits_per_second\": 20950333.82314488, \n                    \"bytes\": 26410072, \n                    \"end\": 10.084831, \n                    \"seconds\": 10.000079, \n                    \"sender\": true, \n                    \"socket\": 5, \n                    \"start\": 0\n                }, \n                \"sender\": {\n                    \"bits_per_second\": 24326771.018508956, \n                    \"bytes\": 30408704, \n                    \"end\": 10.000079, \n                    \"max_rtt\": 139317, \n                    \"max_snd_cwnd\": 393856, \n                    \"max_snd_wnd\": 0, \n                    \"mean_rtt\": 83116, \n                    \"min_rtt\": 43488, \n                    \"retransmits\": 305, \n                    \"seconds\": 10.000079, \n                    \"sender\": true, \n                    \"socket\": 5, \n                    \"start\": 0\n                }\n            }\n        ], \n        \"sum_received\": {\n            \"bits_per_second\": 20950333.82314488, \n            \"bytes\": 26410072, \n            \"end\": 10.084831, \n            \"seconds\": 10.084831, \n            \"sender\": true, \n            \"start\": 0\n        }, \n        \"sum_sent\": {\n            \"bits_per_second\": 24326771.018508956, \n            \"bytes\": 30408704, \n            \"end\": 10.000079, \n            \"retransmits\": 305, \n            \"seconds\": 10.000079, \n            \"sender\": true, \n            \"start\": 0\n        }\n    }, \n    \"intervals\": [\n        {\n            \"streams\": [\n                {\n                    \"bits_per_second\": 54521974.29019813, \n                    \"bytes\": 6815744, \n                    \"end\": 1.000073, \n                    \"omitted\": false, \n                    \"pmtu\": 1500, \n                    \"retransmits\": 281, \n                    \"rtt\": 74606, \n                    \"rttvar\": 567, \n                    \"seconds\": 1.000072956085205, \n                    \"sender\": true, \n                    \"snd_cwnd\": 202720, \n                    \"snd_wnd\": -1, \n                    \"socket\": 5, \n                    \"start\": 0\n                }\n            ], \n            \"sum\": {\n                \"bits_per_second\": 54521974.29019813, \n                \"bytes\": 6815744, \n                \"end\": 1.000073, \n                \"omitted\": false, \n                \"retransmits\": 281, \n                \"seconds\": 1.000072956085205, \n                \"sender\": true, \n                \"start\": 0\n            }\n        }, \n        {\n            \"streams\": [\n                {\n                    \"bits_per_second\": 10483349.304350842, \n                    \"bytes\": 1310720, \n                    \"end\": 2.000303, \n                    \"omitted\": false, \n                    \"pmtu\": 1500, \n                    \"retransmits\": 17, \n                    \"rtt\": 43488, \n                    \"rttvar\": 663, \n                    \"seconds\": 1.0002299547195435, \n                    \"sender\": true, \n                    \"snd_cwnd\": 120184, \n                    \"snd_wnd\": -1, \n                    \"socket\": 5, \n                    \"start\": 1.000073\n                }\n            ], \n            \"sum\": {\n                \"bits_per_second\": 10483349.304350842, \n                \"bytes\": 1310720, \n                \"end\": 2.000303, \n                \"omitted\": false, \n                \"retransmits\": 17, \n                \"seconds\": 1.0002299547195435, \n                \"sender\": true, \n                \"start\": 1.000073\n            }\n        }, \n        {\n            \"streams\": [\n                {\n                    \"bits_per_second\": 20970785.025759034, \n                    \"bytes\": 2621440, \n                    \"end\": 3.000338, \n                    \"omitted\": false, \n                    \"pmtu\": 1500, \n                    \"retransmits\": 0, \n                    \"rtt\": 53902, \n                    \"rttvar\": 306, \n                    \"seconds\": 1.000035047531128, \n                    \"sender\": true, \n                    \"snd_cwnd\": 149144, \n                    \"snd_wnd\": -1, \n                    \"socket\": 5, \n                    \"start\": 2.000303\n                }\n            ], \n            \"sum\": {\n                \"bits_per_second\": 20970785.025759034, \n                \"bytes\": 2621440, \n                \"end\": 3.000338, \n                \"omitted\": false, \n                \"retransmits\": 0, \n                \"seconds\": 1.000035047531128, \n                \"sender\": true, \n                \"start\": 2.000303\n            }\n        }, \n        {\n            \"streams\": [\n                {\n                    \"bits_per_second\": 20976701.279784646, \n                    \"bytes\": 2621440, \n                    \"end\": 4.000091, \n                    \"omitted\": false, \n                    \"pmtu\": 1500, \n                    \"retransmits\": 0, \n                    \"rtt\": 62744, \n                    \"rttvar\": 450, \n                    \"seconds\": 0.9997529983520508, \n                    \"sender\": true, \n                    \"snd_cwnd\": 172312, \n                    \"snd_wnd\": -1, \n                    \"socket\": 5, \n                    \"start\": 3.000338\n                }\n            ], \n            \"sum\": {\n                \"bits_per_second\": 20976701.279784646, \n                \"bytes\": 2621440, \n                \"end\": 4.000091, \n                \"omitted\": false, \n                \"retransmits\": 0, \n                \"seconds\": 0.9997529983520508, \n                \"sender\": true, \n                \"start\": 3.000338\n            }\n        }, \n        {\n            \"streams\": [\n                {\n                    \"bits_per_second\": 20965209.399512555, \n                    \"bytes\": 2621440, \n                    \"end\": 5.000392, \n                    \"omitted\": false, \n                    \"pmtu\": 1500, \n                    \"retransmits\": 0, \n                    \"rtt\": 77851, \n                    \"rttvar\": 317, \n                    \"seconds\": 1.0003010034561157, \n                    \"sender\": true, \n                    \"snd_cwnd\": 215752, \n                    \"snd_wnd\": -1, \n                    \"socket\": 5, \n                    \"start\": 4.000091\n                }\n            ], \n            \"sum\": {\n                \"bits_per_second\": 20965209.399512555, \n                \"bytes\": 2621440, \n                \"end\": 5.000392, \n                \"omitted\": false, \n                \"retransmits\": 0, \n                \"seconds\": 1.0003010034561157, \n                \"sender\": true, \n                \"start\": 4.000091\n            }\n        }, \n        {\n            \"streams\": [\n                {\n                    \"bits_per_second\": 20971037.51110081, \n                    \"bytes\": 2621440, \n                    \"end\": 6.000415, \n                    \"omitted\": false, \n                    \"pmtu\": 1500, \n                    \"retransmits\": 0, \n                    \"rtt\": 96928, \n                    \"rttvar\": 817, \n                    \"seconds\": 1.0000230073928833, \n                    \"sender\": true, \n                    \"snd_cwnd\": 269328, \n                    \"snd_wnd\": -1, \n                    \"socket\": 5, \n                    \"start\": 5.000392\n                }\n            ], \n            \"sum\": {\n                \"bits_per_second\": 20971037.51110081, \n                \"bytes\": 2621440, \n                \"end\": 6.000415, \n                \"omitted\": false, \n                \"retransmits\": 0, \n                \"seconds\": 1.0000230073928833, \n                \"sender\": true, \n                \"start\": 5.000392\n            }\n        }, \n        {\n            \"streams\": [\n                {\n                    \"bits_per_second\": 20978652.42491673, \n                    \"bytes\": 2621440, \n                    \"end\": 7.000075, \n                    \"omitted\": false, \n                    \"pmtu\": 1500, \n                    \"retransmits\": 0, \n                    \"rtt\": 118456, \n                    \"rttvar\": 532, \n                    \"seconds\": 0.9996600151062012, \n                    \"sender\": true, \n                    \"snd_cwnd\": 328696, \n                    \"snd_wnd\": -1, \n                    \"socket\": 5, \n                    \"start\": 6.000415\n                }\n            ], \n            \"sum\": {\n                \"bits_per_second\": 20978652.42491673, \n                \"bytes\": 2621440, \n                \"end\": 7.000075, \n                \"omitted\": false, \n                \"retransmits\": 0, \n                \"seconds\": 0.9996600151062012, \n                \"sender\": true, \n                \"start\": 6.000415\n            }\n        }, \n        {\n            \"streams\": [\n                {\n                    \"bits_per_second\": 20971477.50008613, \n                    \"bytes\": 2621440, \n                    \"end\": 8.000077, \n                    \"omitted\": false, \n                    \"pmtu\": 1500, \n                    \"retransmits\": 0, \n                    \"rtt\": 139317, \n                    \"rttvar\": 1361, \n                    \"seconds\": 1.0000020265579224, \n                    \"sender\": true, \n                    \"snd_cwnd\": 393856, \n                    \"snd_wnd\": -1, \n                    \"socket\": 5, \n                    \"start\": 7.000075\n                }\n            ], \n            \"sum\": {\n                \"bits_per_second\": 20971477.50008613, \n                \"bytes\": 2621440, \n                \"end\": 8.000077, \n                \"omitted\": false, \n                \"retransmits\": 0, \n                \"seconds\": 1.0000020265579224, \n                \"sender\": true, \n                \"start\": 7.000075\n            }\n        }, \n        {\n            \"streams\": [\n                {\n                    \"bits_per_second\": 31457280, \n                    \"bytes\": 3932160, \n                    \"end\": 9.000077, \n                    \"omitted\": false, \n                    \"pmtu\": 1500, \n                    \"retransmits\": 7, \n                    \"rtt\": 78890, \n                    \"rttvar\": 241, \n                    \"seconds\": 1, \n                    \"sender\": true, \n                    \"snd_cwnd\": 214304, \n                    \"snd_wnd\": -1, \n                    \"socket\": 5, \n                    \"start\": 8.000077\n                }\n            ], \n            \"sum\": {\n                \"bits_per_second\": 31457280, \n                \"bytes\": 3932160, \n                \"end\": 9.000077, \n                \"omitted\": false, \n                \"retransmits\": 7, \n                \"seconds\": 1, \n                \"sender\": true, \n                \"start\": 8.000077\n            }\n        }, \n        {\n            \"streams\": [\n                {\n                    \"bits_per_second\": 20971477.50008613, \n                    \"bytes\": 2621440, \n                    \"end\": 10.000079, \n                    \"omitted\": false, \n                    \"pmtu\": 1500, \n                    \"retransmits\": 0, \n                    \"rtt\": 84984, \n                    \"rttvar\": 529, \n                    \"seconds\": 1.0000020265579224, \n                    \"sender\": true, \n                    \"snd_cwnd\": 231680, \n                    \"snd_wnd\": -1, \n                    \"socket\": 5, \n                    \"start\": 9.000077\n                }\n            ], \n            \"sum\": {\n                \"bits_per_second\": 20971477.50008613, \n                \"bytes\": 2621440, \n                \"end\": 10.000079, \n                \"omitted\": false, \n                \"retransmits\": 0, \n                \"seconds\": 1.0000020265579224, \n                \"sender\": true, \n                \"start\": 9.000077\n            }\n        }\n    ], \n    \"start\": {\n        \"connected\": [\n            {\n                \"local_host\": \"172.16.0.2\", \n                \"local_port\": 40564, \n                \"remote_host\": \"172.16.0.1\", \n                \"remote_port\": 5201, \n                \"socket\": 5\n            }\n        ], \n        \"connecting_to\": {\n            \"host\": \"172.16.0.1\", \n            \"port\": 5201\n        }, \n        \"cookie\": \"knlh7sn5swsxzljhrv7mpvqzj4cm5khlbzpb\", \n        \"fq_rate\": 0, \n        \"rcvbuf_actual\": 87380, \n        \"sndbuf_actual\": 65536, \n        \"sock_bufsize\": 0, \n        \"system_info\": \"REDACTED\", \n        \"target_bitrate\": 0, \n        \"tcp_mss_default\": 1448, \n        \"test_start\": {\n            \"bidir\": 0, \n            \"blksize\": 131072, \n            \"blocks\": 0, \n            \"bytes\": 0, \n            \"duration\": 10, \n            \"fqrate\": 0, \n            \"num_streams\": 1, \n            \"omit\": 0, \n            \"protocol\": \"TCP\", \n            \"reverse\": 0, \n            \"target_bitrate\": 0, \n            \"tos\": 0\n        }, \n        \"timestamp\": {\n            \"time\": \"Wed, 21 Aug 2024 16:10:49 GMT\", \n            \"timesecs\": 1724256649\n        }, \n        \"version\": \"iperf 3.14\"\n    }\n}\nParticipant 1:\n/usr/bin/iperf3 -s -1 --idle-timeout 10 --json -p 5201 --authorized-users-path /var/run/pscheduler-server/runner/tmp/tmpmmrfksh8/tmpzulzn466/credentials --rsa-private-key-path /var/run/pscheduler-server/runner/tmp/tmpmmrfksh8/tmpzulzn466/private-key\n\n{\n    \"end\": {\n        \"cpu_utilization_percent\": {\n            \"host_system\": 4.562399788197987, \n            \"host_total\": 5.66385949673224, \n            \"host_user\": 1.1014497927096876, \n            \"remote_system\": 0, \n            \"remote_total\": 0, \n            \"remote_user\": 0\n        }, \n        \"receiver_tcp_congestion\": \"htcp\", \n        \"streams\": [\n            {\n                \"receiver\": {\n                    \"bits_per_second\": 20950333.82314488, \n                    \"bytes\": 26410072, \n                    \"end\": 10.084831, \n                    \"seconds\": 10.084831, \n                    \"sender\": false, \n                    \"socket\": 5, \n                    \"start\": 0\n                }, \n                \"sender\": {\n                    \"bits_per_second\": 0, \n                    \"bytes\": 0, \n                    \"end\": 10.084831, \n                    \"seconds\": 10.084831, \n                    \"sender\": false, \n                    \"socket\": 5, \n                    \"start\": 0\n                }\n            }\n        ], \n        \"sum_received\": {\n            \"bits_per_second\": 20950333.82314488, \n            \"bytes\": 26410072, \n            \"end\": 10.084831, \n            \"seconds\": 10.084831, \n            \"sender\": false, \n            \"start\": 0\n        }, \n        \"sum_sent\": {\n            \"bits_per_second\": 0, \n            \"bytes\": 0, \n            \"end\": 10.084831, \n            \"seconds\": 10.084831, \n            \"sender\": false, \n            \"start\": 0\n        }\n    }, \n    \"intervals\": [\n        {\n            \"streams\": [\n                {\n                    \"bits_per_second\": 20617787.22860382, \n                    \"bytes\": 2577440, \n                    \"end\": 1.000084, \n                    \"omitted\": false, \n                    \"seconds\": 1.0000840425491333, \n                    \"sender\": false, \n                    \"socket\": 5, \n                    \"start\": 0\n                }\n            ], \n            \"sum\": {\n                \"bits_per_second\": 20617787.22860382, \n                \"bytes\": 2577440, \n                \"end\": 1.000084, \n                \"omitted\": false, \n                \"seconds\": 1.0000840425491333, \n                \"sender\": false, \n                \"start\": 0\n            }\n        }, \n        {\n            \"streams\": [\n                {\n                    \"bits_per_second\": 15406304.93412553, \n                    \"bytes\": 1925840, \n                    \"end\": 2.000111, \n                    \"omitted\": false, \n                    \"seconds\": 1.0000269412994385, \n                    \"sender\": false, \n                    \"socket\": 5, \n                    \"start\": 1.000084\n                }\n            ], \n            \"sum\": {\n                \"bits_per_second\": 15406304.93412553, \n                \"bytes\": 1925840, \n                \"end\": 2.000111, \n                \"omitted\": false, \n                \"seconds\": 1.0000269412994385, \n                \"sender\": false, \n                \"start\": 1.000084\n            }\n        }, \n        {\n            \"streams\": [\n                {\n                    \"bits_per_second\": 21685291.946500193, \n                    \"bytes\": 2710656, \n                    \"end\": 3.000109, \n                    \"omitted\": false, \n                    \"seconds\": 0.9999979734420776, \n                    \"sender\": false, \n                    \"socket\": 5, \n                    \"start\": 2.000111\n                }\n            ], \n            \"sum\": {\n                \"bits_per_second\": 21685291.946500193, \n                \"bytes\": 2710656, \n                \"end\": 3.000109, \n                \"omitted\": false, \n                \"seconds\": 0.9999979734420776, \n                \"sender\": false, \n                \"start\": 2.000111\n            }\n        }, \n        {\n            \"streams\": [\n                {\n                    \"bits_per_second\": 21674400.380113166, \n                    \"bytes\": 2709208, \n                    \"end\": 4.000075, \n                    \"omitted\": false, \n                    \"seconds\": 0.999966025352478, \n                    \"sender\": false, \n                    \"socket\": 5, \n                    \"start\": 3.000109\n                }\n            ], \n            \"sum\": {\n                \"bits_per_second\": 21674400.380113166, \n                \"bytes\": 2709208, \n                \"end\": 4.000075, \n                \"omitted\": false, \n                \"seconds\": 0.999966025352478, \n                \"sender\": false, \n                \"start\": 3.000109\n            }\n        }, \n        {\n            \"streams\": [\n                {\n                    \"bits_per_second\": 21684663.786979694, \n                    \"bytes\": 2710656, \n                    \"end\": 5.000102, \n                    \"omitted\": false, \n                    \"seconds\": 1.0000269412994385, \n                    \"sender\": false, \n                    \"socket\": 5, \n                    \"start\": 4.000075\n                }\n            ], \n            \"sum\": {\n                \"bits_per_second\": 21684663.786979694, \n                \"bytes\": 2710656, \n                \"end\": 5.000102, \n                \"omitted\": false, \n                \"seconds\": 1.0000269412994385, \n                \"sender\": false, \n                \"start\": 4.000075\n            }\n        }, \n        {\n            \"streams\": [\n                {\n                    \"bits_per_second\": 21674379.709111623, \n                    \"bytes\": 2709208, \n                    \"end\": 6.000069, \n                    \"omitted\": false, \n                    \"seconds\": 0.9999669790267944, \n                    \"sender\": false, \n                    \"socket\": 5, \n                    \"start\": 5.000102\n                }\n            ], \n            \"sum\": {\n                \"bits_per_second\": 21674379.709111623, \n                \"bytes\": 2709208, \n                \"end\": 6.000069, \n                \"omitted\": false, \n                \"seconds\": 0.9999669790267944, \n                \"sender\": false, \n                \"start\": 5.000102\n            }\n        }, \n        {\n            \"streams\": [\n                {\n                    \"bits_per_second\": 21684575.899249338, \n                    \"bytes\": 2710656, \n                    \"end\": 7.0001, \n                    \"omitted\": false, \n                    \"seconds\": 1.0000309944152832, \n                    \"sender\": false, \n                    \"socket\": 5, \n                    \"start\": 6.000069\n                }\n            ], \n            \"sum\": {\n                \"bits_per_second\": 21684575.899249338, \n                \"bytes\": 2710656, \n                \"end\": 7.0001, \n                \"omitted\": false, \n                \"seconds\": 1.0000309944152832, \n                \"sender\": false, \n                \"start\": 6.000069\n            }\n        }, \n        {\n            \"streams\": [\n                {\n                    \"bits_per_second\": 21672992.258277517, \n                    \"bytes\": 2709208, \n                    \"end\": 8.000131, \n                    \"omitted\": false, \n                    \"seconds\": 1.0000309944152832, \n                    \"sender\": false, \n                    \"socket\": 5, \n                    \"start\": 7.0001\n                }\n            ], \n            \"sum\": {\n                \"bits_per_second\": 21672992.258277517, \n                \"bytes\": 2709208, \n                \"end\": 8.000131, \n                \"omitted\": false, \n                \"seconds\": 1.0000309944152832, \n                \"sender\": false, \n                \"start\": 7.0001\n            }\n        }, \n        {\n            \"streams\": [\n                {\n                    \"bits_per_second\": 21685529.77770922, \n                    \"bytes\": 2710656, \n                    \"end\": 9.000118, \n                    \"omitted\": false, \n                    \"seconds\": 0.999987006187439, \n                    \"sender\": false, \n                    \"socket\": 5, \n                    \"start\": 8.000131\n                }\n            ], \n            \"sum\": {\n                \"bits_per_second\": 21685529.77770922, \n                \"bytes\": 2710656, \n                \"end\": 9.000118, \n                \"omitted\": false, \n                \"seconds\": 0.999987006187439, \n                \"sender\": false, \n                \"start\": 8.000131\n            }\n        }, \n        {\n            \"streams\": [\n                {\n                    \"bits_per_second\": 21671344.0838724, \n                    \"bytes\": 2709208, \n                    \"end\": 10.000225, \n                    \"omitted\": false, \n                    \"seconds\": 1.0001070499420166, \n                    \"sender\": false, \n                    \"socket\": 5, \n                    \"start\": 9.000118\n                }\n            ], \n            \"sum\": {\n                \"bits_per_second\": 21671344.0838724, \n                \"bytes\": 2709208, \n                \"end\": 10.000225, \n                \"omitted\": false, \n                \"seconds\": 1.0001070499420166, \n                \"sender\": false, \n                \"start\": 9.000118\n            }\n        }, \n        {\n            \"streams\": [\n                {\n                    \"bits_per_second\": 21495969.7331379, \n                    \"bytes\": 227336, \n                    \"end\": 10.084831, \n                    \"omitted\": false, \n                    \"seconds\": 0.08460599929094315, \n                    \"sender\": false, \n                    \"socket\": 5, \n                    \"start\": 10.000225\n                }\n            ], \n            \"sum\": {\n                \"bits_per_second\": 21495969.7331379, \n                \"bytes\": 227336, \n                \"end\": 10.084831, \n                \"omitted\": false, \n                \"seconds\": 0.08460599929094315, \n                \"sender\": false, \n                \"start\": 10.000225\n            }\n        }\n    ], \n    \"start\": {\n        \"accepted_connection\": {\n            \"host\": \"172.16.0.2\", \n            \"port\": 40550\n        }, \n        \"connected\": [\n            {\n                \"local_host\": \"172.16.0.1\", \n                \"local_port\": 5201, \n                \"remote_host\": \"172.16.0.2\", \n                \"remote_port\": 40564, \n                \"socket\": 5\n            }\n        ], \n        \"cookie\": \"knlh7sn5swsxzljhrv7mpvqzj4cm5khlbzpb\", \n        \"fq_rate\": 0, \n        \"rcvbuf_actual\": 87380, \n        \"sndbuf_actual\": 65536, \n        \"sock_bufsize\": 0, \n        \"system_info\": \"REDACTED\", \n        \"target_bitrate\": 0, \n        \"tcp_mss_default\": 0, \n        \"test_start\": {\n            \"bidir\": 0, \n            \"blksize\": 131072, \n            \"blocks\": 0, \n            \"bytes\": 0, \n            \"duration\": 10, \n            \"fqrate\": 0, \n            \"num_streams\": 1, \n            \"omit\": 0, \n            \"protocol\": \"TCP\", \n            \"reverse\": 0, \n            \"target_bitrate\": 0, \n            \"tos\": 0\n        }, \n        \"timestamp\": {\n            \"time\": \"Wed, 21 Aug 2024 16:10:49 GMT\", \n            \"timesecs\": 1724256649\n        }, \n        \"version\": \"iperf 3.14\"\n    }\n}\n","summary":{"streams":[{"end":10.000079,"rtt":83116,"start":0,"stream-id":5,"retransmits":305,"throughput-bits":24326771.018508956,"throughput-bytes":30408704}],"summary":{"end":10.000079,"start":0,"retransmits":305,"throughput-bits":24326771.018508956,"throughput-bytes":30408704,"receiver-throughput-bits":20950333.82314488}},"intervals":[{"streams":[{"end":1.000073,"rtt":74606,"start":0,"omitted":false,"stream-id":5,"retransmits":281,"tcp-window-size":202720,"throughput-bits":54521974.29019813,"throughput-bytes":6815744}],"summary":{"end":1.000073,"start":0,"omitted":false,"retransmits":281,"throughput-bits":54521974.29019813,"throughput-bytes":6815744}},{"streams":[{"end":2.000303,"rtt":43488,"start":1.000073,"omitted":false,"stream-id":5,"retransmits":17,"tcp-window-size":120184,"throughput-bits":10483349.304350842,"throughput-bytes":1310720}],"summary":{"end":2.000303,"start":1.000073,"omitted":false,"retransmits":17,"throughput-bits":10483349.304350842,"throughput-bytes":1310720}},{"streams":[{"end":3.000338,"rtt":53902,"start":2.000303,"omitted":false,"stream-id":5,"retransmits":0,"tcp-window-size":149144,"throughput-bits":20970785.025759034,"throughput-bytes":2621440}],"summary":{"end":3.000338,"start":2.000303,"omitted":false,"retransmits":0,"throughput-bits":20970785.025759034,"throughput-bytes":2621440}},{"streams":[{"end":4.000091,"rtt":62744,"start":3.000338,"omitted":false,"stream-id":5,"retransmits":0,"tcp-window-size":172312,"throughput-bits":20976701.279784646,"throughput-bytes":2621440}],"summary":{"end":4.000091,"start":3.000338,"omitted":false,"retransmits":0,"throughput-bits":20976701.279784646,"throughput-bytes":2621440}},{"streams":[{"end":5.000392,"rtt":77851,"start":4.000091,"omitted":false,"stream-id":5,"retransmits":0,"tcp-window-size":215752,"throughput-bits":20965209.399512555,"throughput-bytes":2621440}],"summary":{"end":5.000392,"start":4.000091,"omitted":false,"retransmits":0,"throughput-bits":20965209.399512555,"throughput-bytes":2621440}},{"streams":[{"end":6.000415,"rtt":96928,"start":5.000392,"omitted":false,"stream-id":5,"retransmits":0,"tcp-window-size":269328,"throughput-bits":20971037.51110081,"throughput-bytes":2621440}],"summary":{"end":6.000415,"start":5.000392,"omitted":false,"retransmits":0,"throughput-bits":20971037.51110081,"throughput-bytes":2621440}},{"streams":[{"end":7.000075,"rtt":118456,"start":6.000415,"omitted":false,"stream-id":5,"retransmits":0,"tcp-window-size":328696,"throughput-bits":20978652.42491673,"throughput-bytes":2621440}],"summary":{"end":7.000075,"start":6.000415,"omitted":false,"retransmits":0,"throughput-bits":20978652.42491673,"throughput-bytes":2621440}},{"streams":[{"end":8.000077,"rtt":139317,"start":7.000075,"omitted":false,"stream-id":5,"retransmits":0,"tcp-window-size":393856,"throughput-bits":20971477.50008613,"throughput-bytes":2621440}],"summary":{"end":8.000077,"start":7.000075,"omitted":false,"retransmits":0,"throughput-bits":20971477.50008613,"throughput-bytes":2621440}},{"streams":[{"end":9.000077,"rtt":78890,"start":8.000077,"omitted":false,"stream-id":5,"retransmits":7,"tcp-window-size":214304,"throughput-bits":31457280,"throughput-bytes":3932160}],"summary":{"end":9.000077,"start":8.000077,"omitted":false,"retransmits":7,"throughput-bits":31457280,"throughput-bytes":3932160}},{"streams":[{"end":10.000079,"rtt":84984,"start":9.000077,"omitted":false,"stream-id":5,"retransmits":0,"tcp-window-size":231680,"throughput-bits":20971477.50008613,"throughput-bytes":2621440}],"summary":{"end":10.000079,"start":9.000077,"omitted":false,"retransmits":0,"throughput-bits":20971477.50008613,"throughput-bytes":2621440}}],"succeeded":true}
