{"diags":"Participant 0:\n/usr/bin/iperf3 -p 5201 -B 10.0.0.1 -c 10.0.0.2 -t 60 --json --rsa-public-key-path /var/run/pscheduler-server/runner/tmp/tmpg52b7s_n/tmpehvu8gs7/public-key --username wyTapEt041uiAyM4JHSy\n\n{\n    \"end\": {\n        \"cpu_utilization_percent\": {\n            \"host_system\": 1.952478347046161, \n            \"host_total\": 2.0014812010437035, \n            \"host_user\": 0.049001187517215786, \n            \"remote_system\": 5.013827027668187, \n            \"remote_total\": 5.44612128225052, \n            \"remote_user\": 0.4322992481819511\n        }, \n        \"receiver_tcp_congestion\": \"htcp\", \n        \"sender_tcp_congestion\": \"htcp\", \n        \"streams\": [\n            {\n                \"receiver\": {\n                    \"bits_per_second\": 865527842.5013117, \n                    \"bytes\": 6499778056, \n                    \"end\": 60.076894, \n                    \"seconds\": 60.000073, \n                    \"sender\": true, \n                    \"socket\": 5, \n                    \"start\": 0\n                }, \n                \"sender\": {\n                    \"bits_per_second\": 867014010.7329535, \n                    \"bytes\": 6502612992, \n                    \"end\": 60.000073, \n                    \"max_rtt\": 77105, \n                    \"max_snd_cwnd\": 16698336, \n                    \"max_snd_wnd\": 0, \n                    \"mean_rtt\": 77087, \n                    \"min_rtt\": 77082, \n                    \"retransmits\": 0, \n                    \"seconds\": 60.000073, \n                    \"sender\": true, \n                    \"socket\": 5, \n                    \"start\": 0\n                }\n            }\n        ], \n        \"sum_received\": {\n            \"bits_per_second\": 865527842.5013117, \n            \"bytes\": 6499778056, \n            \"end\": 60.076894, \n            \"seconds\": 60.076894, \n            \"sender\": true, \n            \"start\": 0\n        }, \n        \"sum_sent\": {\n            \"bits_per_second\": 867014010.7329535, \n            \"bytes\": 6502612992, \n            \"end\": 60.000073, \n            \"retransmits\": 0, \n            \"seconds\": 60.000073, \n            \"sender\": true, \n            \"start\": 0\n        }\n    }, \n    \"intervals\": [\n        {\n            \"streams\": [\n                {\n                    \"bits_per_second\": 955229847.6734288, \n                    \"bytes\": 119406592, \n                    \"end\": 1.000024, \n                    \"omitted\": false, \n                    \"pmtu\": 1500, \n                    \"retransmits\": 0, \n                    \"rtt\": 77086, \n                    \"rttvar\": 8, \n                    \"seconds\": 1.0000239610672, \n                    \"sender\": true, \n                    \"snd_cwnd\": 16698336, \n                    \"snd_wnd\": -1, \n                    \"socket\": 5, \n                    \"start\": 0\n                }\n            ], \n            \"sum\": {\n                \"bits_per_second\": 955229847.6734288, \n                \"bytes\": 119406592, \n                \"end\": 1.000024, \n                \"omitted\": false, \n                \"retransmits\": 0, \n                \"seconds\": 1.0000239610672, \n                \"sender\": true, \n                \"start\": 0\n            }\n        }, \n        {\n            \"streams\": [\n                {\n                    \"bits_per_second\": 870284155.0724424, \n                    \"bytes\": 108789760, \n                    \"end\": 2.000063, \n                    \"omitted\": false, \n                    \"pmtu\": 1500, \n                    \"retransmits\": 0, \n                    \"rtt\": 77088, \n                    \"rttvar\": 7, \n                    \"seconds\": 1.000038981437683, \n                    \"sender\": true, \n                    \"snd_cwnd\": 16698336, \n                    \"snd_wnd\": -1, \n                    \"socket\": 5, \n                    \"start\": 1.000024\n                }\n            ], \n            \"sum\": {\n                \"bits_per_second\": 870284155.0724424, \n                \"bytes\": 108789760, \n                \"end\": 2.000063, \n                \"omitted\": false, \n                \"retransmits\": 0, \n                \"seconds\": 1.000038981437683, \n                \"sender\": true, \n                \"start\": 1.000024\n            }\n        }, \n        {\n            \"streams\": [\n                {\n                    \"bits_per_second\": 859840930.0862178, \n                    \"bytes\": 107479040, \n                    \"end\": 3.000053, \n                    \"omitted\": false, \n                    \"pmtu\": 1500, \n                    \"retransmits\": 0, \n                    \"rtt\": 77082, \n                    \"rttvar\": 7, \n                    \"seconds\": 0.9999899864196777, \n                    \"sender\": true, \n                    \"snd_cwnd\": 16698336, \n                    \"snd_wnd\": -1, \n                    \"socket\": 5, \n                    \"start\": 2.000063\n                }\n            ], \n            \"sum\": {\n                \"bits_per_second\": 859840930.0862178, \n                \"bytes\": 107479040, \n                \"end\": 3.000053, \n                \"omitted\": false, \n                \"retransmits\": 0, \n                \"seconds\": 0.9999899864196777, \n                \"sender\": true, \n                \"start\": 2.000063\n            }\n        }, \n        {\n            \"streams\": [\n                {\n                    \"bits_per_second\": 870308535.1046813, \n                    \"bytes\": 108789760, \n                    \"end\": 4.000064, \n                    \"omitted\": false, \n                    \"pmtu\": 1500, \n                    \"retransmits\": 0, \n                    \"rtt\": 77089, \n                    \"rttvar\": 9, \n                    \"seconds\": 1.0000109672546387, \n                    \"sender\": true, \n                    \"snd_cwnd\": 16698336, \n                    \"snd_wnd\": -1, \n                    \"socket\": 5, \n                    \"start\": 3.000053\n                }\n            ], \n            \"sum\": {\n                \"bits_per_second\": 870308535.1046813, \n                \"bytes\": 108789760, \n                \"end\": 4.000064, \n                \"omitted\": false, \n                \"retransmits\": 0, \n                \"seconds\": 1.0000109672546387, \n                \"sender\": true, \n                \"start\": 3.000053\n            }\n        }, \n        {\n            \"streams\": [\n                {\n                    \"bits_per_second\": 859824632.568731, \n                    \"bytes\": 107479040, \n                    \"end\": 5.000073, \n                    \"omitted\": false, \n                    \"pmtu\": 1500, \n                    \"retransmits\": 0, \n                    \"rtt\": 77087, \n                    \"rttvar\": 11, \n                    \"seconds\": 1.0000089406967163, \n                    \"sender\": true, \n                    \"snd_cwnd\": 16698336, \n                    \"snd_wnd\": -1, \n                    \"socket\": 5, \n                    \"start\": 4.000064\n                }\n            ], \n            \"sum\": {\n                \"bits_per_second\": 859824632.568731, \n                \"bytes\": 107479040, \n                \"end\": 5.000073, \n                \"omitted\": false, \n                \"retransmits\": 0, \n                \"seconds\": 1.0000089406967163, \n                \"sender\": true, \n                \"start\": 4.000064\n            }\n        }, \n        {\n            \"streams\": [\n                {\n                    \"bits_per_second\": 870326795.0872692, \n                    \"bytes\": 108789760, \n                    \"end\": 6.000063, \n                    \"omitted\": false, \n                    \"pmtu\": 1500, \n                    \"retransmits\": 0, \n                    \"rtt\": 77088, \n                    \"rttvar\": 4, \n                    \"seconds\": 0.9999899864196777, \n                    \"sender\": true, \n                    \"snd_cwnd\": 16698336, \n                    \"snd_wnd\": -1, \n                    \"socket\": 5, \n                    \"start\": 5.000073\n                }\n            ], \n            \"sum\": {\n                \"bits_per_second\": 870326795.0872692, \n                \"bytes\": 108789760, \n                \"end\": 6.000063, \n                \"omitted\": false, \n                \"retransmits\": 0, \n                \"seconds\": 0.9999899864196777, \n                \"sender\": true, \n                \"start\": 5.000073\n            }\n        }, \n        {\n            \"streams\": [\n                {\n                    \"bits_per_second\": 870318961.8758936, \n                    \"bytes\": 108789760, \n                    \"end\": 7.000062, \n                    \"omitted\": false, \n                    \"pmtu\": 1500, \n                    \"retransmits\": 0, \n                    \"rtt\": 77088, \n                    \"rttvar\": 5, \n                    \"seconds\": 0.9999989867210388, \n                    \"sender\": true, \n                    \"snd_cwnd\": 16698336, \n                    \"snd_wnd\": -1, \n                    \"socket\": 5, \n                    \"start\": 6.000063\n                }\n            ], \n            \"sum\": {\n                \"bits_per_second\": 870318961.8758936, \n                \"bytes\": 108789760, \n                \"end\": 7.000062, \n                \"omitted\": false, \n                \"retransmits\": 0, \n                \"seconds\": 0.9999989867210388, \n                \"sender\": true, \n                \"start\": 6.000063\n            }\n        }, \n        {\n            \"streams\": [\n                {\n                    \"bits_per_second\": 859858099.5228994, \n                    \"bytes\": 107479040, \n                    \"end\": 8.000032, \n                    \"omitted\": false, \n                    \"pmtu\": 1500, \n                    \"retransmits\": 0, \n                    \"rtt\": 77085, \n                    \"rttvar\": 7, \n                    \"seconds\": 0.999970018863678, \n                    \"sender\": true, \n                    \"snd_cwnd\": 16698336, \n                    \"snd_wnd\": -1, \n                    \"socket\": 5, \n                    \"start\": 7.000062\n                }\n            ], \n            \"sum\": {\n                \"bits_per_second\": 859858099.5228994, \n                \"bytes\": 107479040, \n                \"end\": 8.000032, \n                \"omitted\": false, \n                \"retransmits\": 0, \n                \"seconds\": 0.999970018863678, \n                \"sender\": true, \n                \"start\": 7.000062\n            }\n        }, \n        {\n            \"streams\": [\n                {\n                    \"bits_per_second\": 870279797.9339602, \n                    \"bytes\": 108789760, \n                    \"end\": 9.000076, \n                    \"omitted\": false, \n                    \"pmtu\": 1500, \n                    \"retransmits\": 0, \n                    \"rtt\": 77094, \n                    \"rttvar\": 10, \n                    \"seconds\": 1.0000439882278442, \n                    \"sender\": true, \n                    \"snd_cwnd\": 16698336, \n                    \"snd_wnd\": -1, \n                    \"socket\": 5, \n                    \"start\": 8.000032\n                }\n            ], \n            \"sum\": {\n                \"bits_per_second\": 870279797.9339602, \n                \"bytes\": 108789760, \n                \"end\": 9.000076, \n                \"omitted\": false, \n                \"retransmits\": 0, \n                \"seconds\": 1.0000439882278442, \n                \"sender\": true, \n                \"start\": 8.000032\n            }\n        }, \n        {\n            \"streams\": [\n                {\n                    \"bits_per_second\": 859771234.340059, \n                    \"bytes\": 107479040, \n                    \"end\": 10.000147, \n                    \"omitted\": false, \n                    \"pmtu\": 1500, \n                    \"retransmits\": 0, \n                    \"rtt\": 77087, \n                    \"rttvar\": 7, \n                    \"seconds\": 1.0000710487365723, \n                    \"sender\": true, \n                    \"snd_cwnd\": 16698336, \n                    \"snd_wnd\": -1, \n                    \"socket\": 5, \n                    \"start\": 9.000076\n                }\n            ], \n            \"sum\": {\n                \"bits_per_second\": 859771234.340059, \n                \"bytes\": 107479040, \n                \"end\": 10.000147, \n                \"omitted\": false, \n                \"retransmits\": 0, \n                \"seconds\": 1.0000710487365723, \n                \"sender\": true, \n                \"start\": 9.000076\n            }\n        }, \n        {\n            \"streams\": [\n                {\n                    \"bits_per_second\": 870391178.0139865, \n                    \"bytes\": 108789760, \n                    \"end\": 11.000063, \n                    \"omitted\": false, \n                    \"pmtu\": 1500, \n                    \"retransmits\": 0, \n                    \"rtt\": 77089, \n                    \"rttvar\": 8, \n                    \"seconds\": 0.9999160170555115, \n                    \"sender\": true, \n                    \"snd_cwnd\": 16698336, \n                    \"snd_wnd\": -1, \n                    \"socket\": 5, \n                    \"start\": 10.000147\n                }\n            ], \n            \"sum\": {\n                \"bits_per_second\": 870391178.0139865, \n                \"bytes\": 108789760, \n                \"end\": 11.000063, \n                \"omitted\": false, \n                \"retransmits\": 0, \n                \"seconds\": 0.9999160170555115, \n                \"sender\": true, \n                \"start\": 10.000147\n            }\n        }, \n        {\n            \"streams\": [\n                {\n                    \"bits_per_second\": 859816842.7785993, \n                    \"bytes\": 107479040, \n                    \"end\": 12.000081, \n                    \"omitted\": false, \n                    \"pmtu\": 1500, \n                    \"retransmits\": 0, \n                    \"rtt\": 77086, \n                    \"rttvar\": 7, \n                    \"seconds\": 1.0000180006027222, \n                    \"sender\": true, \n                    \"snd_cwnd\": 16698336, \n                    \"snd_wnd\": -1, \n                    \"socket\": 5, \n                    \"start\": 11.000063\n                }\n            ], \n            \"sum\": {\n                \"bits_per_second\": 859816842.7785993, \n                \"bytes\": 107479040, \n                \"end\": 12.000081, \n                \"omitted\": false, \n                \"retransmits\": 0, \n                \"seconds\": 1.0000180006027222, \n                \"sender\": true, \n                \"start\": 11.000063\n            }\n        }, \n        {\n            \"streams\": [\n                {\n                    \"bits_per_second\": 870353771.4636353, \n                    \"bytes\": 108789760, \n                    \"end\": 13.00004, \n                    \"omitted\": false, \n                    \"pmtu\": 1500, \n                    \"retransmits\": 0, \n                    \"rtt\": 77089, \n                    \"rttvar\": 6, \n                    \"seconds\": 0.9999589920043945, \n                    \"sender\": true, \n                    \"snd_cwnd\": 16698336, \n                    \"snd_wnd\": -1, \n                    \"socket\": 5, \n                    \"start\": 12.000081\n                }\n            ], \n            \"sum\": {\n                \"bits_per_second\": 870353771.4636353, \n                \"bytes\": 108789760, \n                \"end\": 13.00004, \n                \"omitted\": false, \n                \"retransmits\": 0, \n                \"seconds\": 0.9999589920043945, \n                \"sender\": true, \n                \"start\": 12.000081\n            }\n        }, \n        {\n            \"streams\": [\n                {\n                    \"bits_per_second\": 859797881.3794156, \n                    \"bytes\": 107479040, \n                    \"end\": 14.00008, \n                    \"omitted\": false, \n                    \"pmtu\": 1500, \n                    \"retransmits\": 0, \n                    \"rtt\": 77087, \n                    \"rttvar\": 6, \n                    \"seconds\": 1.000040054321289, \n                    \"sender\": true, \n                    \"snd_cwnd\": 16698336, \n                    \"snd_wnd\": -1, \n                    \"socket\": 5, \n                    \"start\": 13.00004\n                }\n            ], \n            \"sum\": {\n                \"bits_per_second\": 859797881.3794156, \n                \"bytes\": 107479040, \n                \"end\": 14.00008, \n                \"omitted\": false, \n                \"retransmits\": 0, \n                \"seconds\": 1.000040054321289, \n                \"sender\": true, \n                \"start\": 13.00004\n            }\n        }, \n        {\n            \"streams\": [\n                {\n                    \"bits_per_second\": 870290275.8882883, \n                    \"bytes\": 108789760, \n                    \"end\": 15.000112, \n                    \"omitted\": false, \n                    \"pmtu\": 1500, \n                    \"retransmits\": 0, \n                    \"rtt\": 77085, \n                    \"rttvar\": 7, \n                    \"seconds\": 1.0000319480895996, \n                    \"sender\": true, \n                    \"snd_cwnd\": 16698336, \n                    \"snd_wnd\": -1, \n                    \"socket\": 5, \n                    \"start\": 14.00008\n                }\n            ], \n            \"sum\": {\n                \"bits_per_second\": 870290275.8882883, \n                \"bytes\": 108789760, \n                \"end\": 15.000112, \n                \"omitted\": false, \n                \"retransmits\": 0, \n                \"seconds\": 1.0000319480895996, \n                \"sender\": true, \n                \"start\": 14.00008\n            }\n        }, \n        {\n            \"streams\": [\n                {\n                    \"bits_per_second\": 859865018.74346, \n                    \"bytes\": 107479040, \n                    \"end\": 16.000074, \n                    \"omitted\": false, \n                    \"pmtu\": 1500, \n                    \"retransmits\": 0, \n                    \"rtt\": 77091, \n                    \"rttvar\": 8, \n                    \"seconds\": 0.9999619722366333, \n                    \"sender\": true, \n                    \"snd_cwnd\": 16698336, \n                    \"snd_wnd\": -1, \n                    \"socket\": 5, \n                    \"start\": 15.000112\n                }\n            ], \n            \"sum\": {\n                \"bits_per_second\": 859865018.74346, \n                \"bytes\": 107479040, \n                \"end\": 16.000074, \n                \"omitted\": false, \n                \"retransmits\": 0, \n                \"seconds\": 0.9999619722366333, \n                \"sender\": true, \n                \"start\": 15.000112\n            }\n        }, \n        {\n            \"streams\": [\n                {\n                    \"bits_per_second\": 870307601.376164, \n                    \"bytes\": 108789760, \n                    \"end\": 17.000086, \n                    \"omitted\": false, \n                    \"pmtu\": 1500, \n                    \"retransmits\": 0, \n                    \"rtt\": 77089, \n                    \"rttvar\": 4, \n                    \"seconds\": 1.0000120401382446, \n                    \"sender\": true, \n                    \"snd_cwnd\": 16698336, \n                    \"snd_wnd\": -1, \n                    \"socket\": 5, \n                    \"start\": 16.000074\n                }\n            ], \n            \"sum\": {\n                \"bits_per_second\": 870307601.376164, \n                \"bytes\": 108789760, \n                \"end\": 17.000086, \n                \"omitted\": false, \n                \"retransmits\": 0, \n                \"seconds\": 1.0000120401382446, \n                \"sender\": true, \n                \"start\": 16.000074\n            }\n        }, \n        {\n            \"streams\": [\n                {\n                    \"bits_per_second\": 870162275.3971807, \n                    \"bytes\": 108789760, \n                    \"end\": 18.000265, \n                    \"omitted\": false, \n                    \"pmtu\": 1500, \n                    \"retransmits\": 0, \n                    \"rtt\": 77105, \n                    \"rttvar\": 9, \n                    \"seconds\": 1.0001790523529053, \n                    \"sender\": true, \n                    \"snd_cwnd\": 16698336, \n                    \"snd_wnd\": -1, \n                    \"socket\": 5, \n                    \"start\": 17.000086\n                }\n            ], \n            \"sum\": {\n                \"bits_per_second\": 870162275.3971807, \n                \"bytes\": 108789760, \n                \"end\": 18.000265, \n                \"omitted\": false, \n                \"retransmits\": 0, \n                \"seconds\": 1.0001790523529053, \n                \"sender\": true, \n                \"start\": 17.000086\n            }\n        }, \n        {\n            \"streams\": [\n                {\n                    \"bits_per_second\": 860003477.8138125, \n                    \"bytes\": 107479040, \n                    \"end\": 19.000066, \n                    \"omitted\": false, \n                    \"pmtu\": 1500, \n                    \"retransmits\": 0, \n                    \"rtt\": 77088, \n                    \"rttvar\": 9, \n                    \"seconds\": 0.999800980091095, \n                    \"sender\": true, \n                    \"snd_cwnd\": 16698336, \n                    \"snd_wnd\": -1, \n                    \"socket\": 5, \n                    \"start\": 18.000265\n                }\n            ], \n            \"sum\": {\n                \"bits_per_second\": 860003477.8138125, \n                \"bytes\": 107479040, \n                \"end\": 19.000066, \n                \"omitted\": false, \n                \"retransmits\": 0, \n                \"seconds\": 0.999800980091095, \n                \"sender\": true, \n                \"start\": 18.000265\n            }\n        }, \n        {\n            \"streams\": [\n                {\n                    \"bits_per_second\": 870314552.5142974, \n                    \"bytes\": 108789760, \n                    \"end\": 20.00007, \n                    \"omitted\": false, \n                    \"pmtu\": 1500, \n                    \"retransmits\": 0, \n                    \"rtt\": 77090, \n                    \"rttvar\": 14, \n                    \"seconds\": 1.0000040531158447, \n                    \"sender\": true, \n                    \"snd_cwnd\": 16698336, \n                    \"snd_wnd\": -1, \n                    \"socket\": 5, \n                    \"start\": 19.000066\n                }\n            ], \n            \"sum\": {\n                \"bits_per_second\": 870314552.5142974, \n                \"bytes\": 108789760, \n                \"end\": 20.00007, \n                \"omitted\": false, \n                \"retransmits\": 0, \n                \"seconds\": 1.0000040531158447, \n                \"sender\": true, \n                \"start\": 19.000066\n            }\n        }, \n        {\n            \"streams\": [\n                {\n                    \"bits_per_second\": 859762728.132982, \n                    \"bytes\": 107479040, \n                    \"end\": 21.000151, \n                    \"omitted\": false, \n                    \"pmtu\": 1500, \n                    \"retransmits\": 0, \n                    \"rtt\": 77089, \n                    \"rttvar\": 10, \n                    \"seconds\": 1.000080943107605, \n                    \"sender\": true, \n                    \"snd_cwnd\": 16698336, \n                    \"snd_wnd\": -1, \n                    \"socket\": 5, \n                    \"start\": 20.00007\n                }\n            ], \n            \"sum\": {\n                \"bits_per_second\": 859762728.132982, \n                \"bytes\": 107479040, \n                \"end\": 21.000151, \n                \"omitted\": false, \n                \"retransmits\": 0, \n                \"seconds\": 1.000080943107605, \n                \"sender\": true, \n                \"start\": 20.00007\n            }\n        }, \n        {\n            \"streams\": [\n                {\n                    \"bits_per_second\": 870392060.038024, \n                    \"bytes\": 108789760, \n                    \"end\": 22.000066, \n                    \"omitted\": false, \n                    \"pmtu\": 1500, \n                    \"retransmits\": 0, \n                    \"rtt\": 77086, \n                    \"rttvar\": 7, \n                    \"seconds\": 0.9999150037765503, \n                    \"sender\": true, \n                    \"snd_cwnd\": 16698336, \n                    \"snd_wnd\": -1, \n                    \"socket\": 5, \n                    \"start\": 21.000151\n                }\n            ], \n            \"sum\": {\n                \"bits_per_second\": 870392060.038024, \n                \"bytes\": 108789760, \n                \"end\": 22.000066, \n                \"omitted\": false, \n                \"retransmits\": 0, \n                \"seconds\": 0.9999150037765503, \n                \"sender\": true, \n                \"start\": 21.000151\n            }\n        }, \n        {\n            \"streams\": [\n                {\n                    \"bits_per_second\": 859833191.250883, \n                    \"bytes\": 107479040, \n                    \"end\": 23.000065, \n                    \"omitted\": false, \n                    \"pmtu\": 1500, \n                    \"retransmits\": 0, \n                    \"rtt\": 77086, \n                    \"rttvar\": 7, \n                    \"seconds\": 0.9999989867210388, \n                    \"sender\": true, \n                    \"snd_cwnd\": 16698336, \n                    \"snd_wnd\": -1, \n                    \"socket\": 5, \n                    \"start\": 22.000066\n                }\n            ], \n            \"sum\": {\n                \"bits_per_second\": 859833191.250883, \n                \"bytes\": 107479040, \n                \"end\": 23.000065, \n                \"omitted\": false, \n                \"retransmits\": 0, \n                \"seconds\": 0.9999989867210388, \n                \"sender\": true, \n                \"start\": 22.000066\n            }\n        }, \n        {\n            \"streams\": [\n                {\n                    \"bits_per_second\": 870303244.0029082, \n                    \"bytes\": 108789760, \n                    \"end\": 24.000082, \n                    \"omitted\": false, \n                    \"pmtu\": 1500, \n                    \"retransmits\": 0, \n                    \"rtt\": 77085, \n                    \"rttvar\": 9, \n                    \"seconds\": 1.0000170469284058, \n                    \"sender\": true, \n                    \"snd_cwnd\": 16698336, \n                    \"snd_wnd\": -1, \n                    \"socket\": 5, \n                    \"start\": 23.000065\n                }\n            ], \n            \"sum\": {\n                \"bits_per_second\": 870303244.0029082, \n                \"bytes\": 108789760, \n                \"end\": 24.000082, \n                \"omitted\": false, \n                \"retransmits\": 0, \n                \"seconds\": 1.0000170469284058, \n                \"sender\": true, \n                \"start\": 23.000065\n            }\n        }, \n        {\n            \"streams\": [\n                {\n                    \"bits_per_second\": 859874449.5641388, \n                    \"bytes\": 107479040, \n                    \"end\": 25.000033, \n                    \"omitted\": false, \n                    \"pmtu\": 1500, \n                    \"retransmits\": 0, \n                    \"rtt\": 77086, \n                    \"rttvar\": 7, \n                    \"seconds\": 0.9999510049819946, \n                    \"sender\": true, \n                    \"snd_cwnd\": 16698336, \n                    \"snd_wnd\": -1, \n                    \"socket\": 5, \n                    \"start\": 24.000082\n                }\n            ], \n            \"sum\": {\n                \"bits_per_second\": 859874449.5641388, \n                \"bytes\": 107479040, \n                \"end\": 25.000033, \n                \"omitted\": false, \n                \"retransmits\": 0, \n                \"seconds\": 0.9999510049819946, \n                \"sender\": true, \n                \"start\": 24.000082\n            }\n        }, \n        {\n            \"streams\": [\n                {\n                    \"bits_per_second\": 870271083.7878804, \n                    \"bytes\": 108789760, \n                    \"end\": 26.000087, \n                    \"omitted\": false, \n                    \"pmtu\": 1500, \n                    \"retransmits\": 0, \n                    \"rtt\": 77089, \n                    \"rttvar\": 10, \n                    \"seconds\": 1.0000540018081665, \n                    \"sender\": true, \n                    \"snd_cwnd\": 16698336, \n                    \"snd_wnd\": -1, \n                    \"socket\": 5, \n                    \"start\": 25.000033\n                }\n            ], \n            \"sum\": {\n                \"bits_per_second\": 870271083.7878804, \n                \"bytes\": 108789760, \n                \"end\": 26.000087, \n                \"omitted\": false, \n                \"retransmits\": 0, \n                \"seconds\": 1.0000540018081665, \n                \"sender\": true, \n                \"start\": 25.000033\n            }\n        }, \n        {\n            \"streams\": [\n                {\n                    \"bits_per_second\": 859852102.9551542, \n                    \"bytes\": 107479040, \n                    \"end\": 27.000064, \n                    \"omitted\": false, \n                    \"pmtu\": 1500, \n                    \"retransmits\": 0, \n                    \"rtt\": 77084, \n                    \"rttvar\": 9, \n                    \"seconds\": 0.9999769926071167, \n                    \"sender\": true, \n                    \"snd_cwnd\": 16698336, \n                    \"snd_wnd\": -1, \n                    \"socket\": 5, \n                    \"start\": 26.000087\n                }\n            ], \n            \"sum\": {\n                \"bits_per_second\": 859852102.9551542, \n                \"bytes\": 107479040, \n                \"end\": 27.000064, \n                \"omitted\": false, \n                \"retransmits\": 0, \n                \"seconds\": 0.9999769926071167, \n                \"sender\": true, \n                \"start\": 26.000087\n            }\n        }, \n        {\n            \"streams\": [\n                {\n                    \"bits_per_second\": 870296293.0454135, \n                    \"bytes\": 108789760, \n                    \"end\": 28.000089, \n                    \"omitted\": false, \n                    \"pmtu\": 1500, \n                    \"retransmits\": 0, \n                    \"rtt\": 77094, \n                    \"rttvar\": 12, \n                    \"seconds\": 1.0000250339508057, \n                    \"sender\": true, \n                    \"snd_cwnd\": 16698336, \n                    \"snd_wnd\": -1, \n                    \"socket\": 5, \n                    \"start\": 27.000064\n                }\n            ], \n            \"sum\": {\n                \"bits_per_second\": 870296293.0454135, \n                \"bytes\": 108789760, \n                \"end\": 28.000089, \n                \"omitted\": false, \n                \"retransmits\": 0, \n                \"seconds\": 1.0000250339508057, \n                \"sender\": true, \n                \"start\": 27.000064\n            }\n        }, \n        {\n            \"streams\": [\n                {\n                    \"bits_per_second\": 870343343.8583457, \n                    \"bytes\": 108789760, \n                    \"end\": 29.00006, \n                    \"omitted\": false, \n                    \"pmtu\": 1500, \n                    \"retransmits\": 0, \n                    \"rtt\": 77084, \n                    \"rttvar\": 5, \n                    \"seconds\": 0.9999709725379944, \n                    \"sender\": true, \n                    \"snd_cwnd\": 16698336, \n                    \"snd_wnd\": -1, \n                    \"socket\": 5, \n                    \"start\": 28.000089\n                }\n            ], \n            \"sum\": {\n                \"bits_per_second\": 870343343.8583457, \n                \"bytes\": 108789760, \n                \"end\": 29.00006, \n                \"omitted\": false, \n                \"retransmits\": 0, \n                \"seconds\": 0.9999709725379944, \n                \"sender\": true, \n                \"start\": 28.000089\n            }\n        }, \n        {\n            \"streams\": [\n                {\n                    \"bits_per_second\": 859835753.7637128, \n                    \"bytes\": 107479040, \n                    \"end\": 30.000056, \n                    \"omitted\": false, \n                    \"pmtu\": 1500, \n                    \"retransmits\": 0, \n                    \"rtt\": 77085, \n                    \"rttvar\": 8, \n                    \"seconds\": 0.9999960064888, \n                    \"sender\": true, \n                    \"snd_cwnd\": 16698336, \n                    \"snd_wnd\": -1, \n                    \"socket\": 5, \n                    \"start\": 29.00006\n                }\n            ], \n            \"sum\": {\n                \"bits_per_second\": 859835753.7637128, \n                \"bytes\": 107479040, \n                \"end\": 30.000056, \n                \"omitted\": false, \n                \"retransmits\": 0, \n                \"seconds\": 0.9999960064888, \n                \"sender\": true, \n                \"start\": 29.00006\n            }\n        }, \n        {\n            \"streams\": [\n                {\n                    \"bits_per_second\": 870311958.7930526, \n                    \"bytes\": 108789760, \n                    \"end\": 31.000063, \n                    \"omitted\": false, \n                    \"pmtu\": 1500, \n                    \"retransmits\": 0, \n                    \"rtt\": 77087, \n                    \"rttvar\": 5, \n                    \"seconds\": 1.0000070333480835, \n                    \"sender\": true, \n                    \"snd_cwnd\": 16698336, \n                    \"snd_wnd\": -1, \n                    \"socket\": 5, \n                    \"start\": 30.000056\n                }\n            ], \n            \"sum\": {\n                \"bits_per_second\": 870311958.7930526, \n                \"bytes\": 108789760, \n                \"end\": 31.000063, \n                \"omitted\": false, \n                \"retransmits\": 0, \n                \"seconds\": 1.0000070333480835, \n                \"sender\": true, \n                \"start\": 30.000056\n            }\n        }, \n        {\n            \"streams\": [\n                {\n                    \"bits_per_second\": 859832320, \n                    \"bytes\": 107479040, \n                    \"end\": 32.000063, \n                    \"omitted\": false, \n                    \"pmtu\": 1500, \n                    \"retransmits\": 0, \n                    \"rtt\": 77090, \n                    \"rttvar\": 7, \n                    \"seconds\": 1, \n                    \"sender\": true, \n                    \"snd_cwnd\": 16698336, \n                    \"snd_wnd\": -1, \n                    \"socket\": 5, \n                    \"start\": 31.000063\n                }\n            ], \n            \"sum\": {\n                \"bits_per_second\": 859832320, \n                \"bytes\": 107479040, \n                \"end\": 32.000063, \n                \"omitted\": false, \n                \"retransmits\": 0, \n                \"seconds\": 1, \n                \"sender\": true, \n                \"start\": 31.000063\n            }\n        }, \n        {\n            \"streams\": [\n                {\n                    \"bits_per_second\": 870318080, \n                    \"bytes\": 108789760, \n                    \"end\": 33.000063, \n                    \"omitted\": false, \n                    \"pmtu\": 1500, \n                    \"retransmits\": 0, \n                    \"rtt\": 77087, \n                    \"rttvar\": 8, \n                    \"seconds\": 1, \n                    \"sender\": true, \n                    \"snd_cwnd\": 16698336, \n                    \"snd_wnd\": -1, \n                    \"socket\": 5, \n                    \"start\": 32.000063\n                }\n            ], \n            \"sum\": {\n                \"bits_per_second\": 870318080, \n                \"bytes\": 108789760, \n                \"end\": 33.000063, \n                \"omitted\": false, \n                \"retransmits\": 0, \n                \"seconds\": 1, \n                \"sender\": true, \n                \"start\": 32.000063\n            }\n        }, \n        {\n            \"streams\": [\n                {\n                    \"bits_per_second\": 859742026.9828782, \n                    \"bytes\": 107479040, \n                    \"end\": 34.000168, \n                    \"omitted\": false, \n                    \"pmtu\": 1500, \n                    \"retransmits\": 0, \n                    \"rtt\": 77086, \n                    \"rttvar\": 7, \n                    \"seconds\": 1.0001050233840942, \n                    \"sender\": true, \n                    \"snd_cwnd\": 16698336, \n                    \"snd_wnd\": -1, \n                    \"socket\": 5, \n                    \"start\": 33.000063\n                }\n            ], \n            \"sum\": {\n                \"bits_per_second\": 859742026.9828782, \n                \"bytes\": 107479040, \n                \"end\": 34.000168, \n                \"omitted\": false, \n                \"retransmits\": 0, \n                \"seconds\": 1.0001050233840942, \n                \"sender\": true, \n                \"start\": 33.000063\n            }\n        }, \n        {\n            \"streams\": [\n                {\n                    \"bits_per_second\": 870392060.038024, \n                    \"bytes\": 108789760, \n                    \"end\": 35.000083, \n                    \"omitted\": false, \n                    \"pmtu\": 1500, \n                    \"retransmits\": 0, \n                    \"rtt\": 77084, \n                    \"rttvar\": 8, \n                    \"seconds\": 0.9999150037765503, \n                    \"sender\": true, \n                    \"snd_cwnd\": 16698336, \n                    \"snd_wnd\": -1, \n                    \"socket\": 5, \n                    \"start\": 34.000168\n                }\n            ], \n            \"sum\": {\n                \"bits_per_second\": 870392060.038024, \n                \"bytes\": 108789760, \n                \"end\": 35.000083, \n                \"omitted\": false, \n                \"retransmits\": 0, \n                \"seconds\": 0.9999150037765503, \n                \"sender\": true, \n                \"start\": 34.000168\n            }\n        }, \n        {\n            \"streams\": [\n                {\n                    \"bits_per_second\": 859836625.0215544, \n                    \"bytes\": 107479040, \n                    \"end\": 36.000078, \n                    \"omitted\": false, \n                    \"pmtu\": 1500, \n                    \"retransmits\": 0, \n                    \"rtt\": 77084, \n                    \"rttvar\": 7, \n                    \"seconds\": 0.999994993209839, \n                    \"sender\": true, \n                    \"snd_cwnd\": 16698336, \n                    \"snd_wnd\": -1, \n                    \"socket\": 5, \n                    \"start\": 35.000083\n                }\n            ], \n            \"sum\": {\n                \"bits_per_second\": 859836625.0215544, \n                \"bytes\": 107479040, \n                \"end\": 36.000078, \n                \"omitted\": false, \n                \"retransmits\": 0, \n                \"seconds\": 0.999994993209839, \n                \"sender\": true, \n                \"start\": 35.000083\n            }\n        }, \n        {\n            \"streams\": [\n                {\n                    \"bits_per_second\": 870269320.23193, \n                    \"bytes\": 108789760, \n                    \"end\": 37.000134, \n                    \"omitted\": false, \n                    \"pmtu\": 1500, \n                    \"retransmits\": 0, \n                    \"rtt\": 77087, \n                    \"rttvar\": 6, \n                    \"seconds\": 1.0000560283660889, \n                    \"sender\": true, \n                    \"snd_cwnd\": 16698336, \n                    \"snd_wnd\": -1, \n                    \"socket\": 5, \n                    \"start\": 36.000078\n                }\n            ], \n            \"sum\": {\n                \"bits_per_second\": 870269320.23193, \n                \"bytes\": 108789760, \n                \"end\": 37.000134, \n                \"omitted\": false, \n                \"retransmits\": 0, \n                \"seconds\": 1.0000560283660889, \n                \"sender\": true, \n                \"start\": 36.000078\n            }\n        }, \n        {\n            \"streams\": [\n                {\n                    \"bits_per_second\": 859891671.5965765, \n                    \"bytes\": 107479040, \n                    \"end\": 38.000065, \n                    \"omitted\": false, \n                    \"pmtu\": 1500, \n                    \"retransmits\": 0, \n                    \"rtt\": 77088, \n                    \"rttvar\": 7, \n                    \"seconds\": 0.99993097782135, \n                    \"sender\": true, \n                    \"snd_cwnd\": 16698336, \n                    \"snd_wnd\": -1, \n                    \"socket\": 5, \n                    \"start\": 37.000134\n                }\n            ], \n            \"sum\": {\n                \"bits_per_second\": 859891671.5965765, \n                \"bytes\": 107479040, \n                \"end\": 38.000065, \n                \"omitted\": false, \n                \"retransmits\": 0, \n                \"seconds\": 0.99993097782135, \n                \"sender\": true, \n                \"start\": 37.000134\n            }\n        }, \n        {\n            \"streams\": [\n                {\n                    \"bits_per_second\": 870298886.673284, \n                    \"bytes\": 108789760, \n                    \"end\": 39.000087, \n                    \"omitted\": false, \n                    \"pmtu\": 1500, \n                    \"retransmits\": 0, \n                    \"rtt\": 77093, \n                    \"rttvar\": 9, \n                    \"seconds\": 1.000022053718567, \n                    \"sender\": true, \n                    \"snd_cwnd\": 16698336, \n                    \"snd_wnd\": -1, \n                    \"socket\": 5, \n                    \"start\": 38.000065\n                }\n            ], \n            \"sum\": {\n                \"bits_per_second\": 870298886.673284, \n                \"bytes\": 108789760, \n                \"end\": 39.000087, \n                \"omitted\": false, \n                \"retransmits\": 0, \n                \"seconds\": 1.000022053718567, \n                \"sender\": true, \n                \"start\": 38.000065\n            }\n        }, \n        {\n            \"streams\": [\n                {\n                    \"bits_per_second\": 870224922.472508, \n                    \"bytes\": 108789760, \n                    \"end\": 40.000194, \n                    \"omitted\": false, \n                    \"pmtu\": 1500, \n                    \"retransmits\": 0, \n                    \"rtt\": 77090, \n                    \"rttvar\": 7, \n                    \"seconds\": 1.0001070499420166, \n                    \"sender\": true, \n                    \"snd_cwnd\": 16698336, \n                    \"snd_wnd\": -1, \n                    \"socket\": 5, \n                    \"start\": 39.000087\n                }\n            ], \n            \"sum\": {\n                \"bits_per_second\": 870224922.472508, \n                \"bytes\": 108789760, \n                \"end\": 40.000194, \n                \"omitted\": false, \n                \"retransmits\": 0, \n                \"seconds\": 1.0001070499420166, \n                \"sender\": true, \n                \"start\": 39.000087\n            }\n        }, \n        {\n            \"streams\": [\n                {\n                    \"bits_per_second\": 859928629.5363914, \n                    \"bytes\": 107479040, \n                    \"end\": 41.000082, \n                    \"omitted\": false, \n                    \"pmtu\": 1500, \n                    \"retransmits\": 0, \n                    \"rtt\": 77087, \n                    \"rttvar\": 7, \n                    \"seconds\": 0.999888002872467, \n                    \"sender\": true, \n                    \"snd_cwnd\": 16698336, \n                    \"snd_wnd\": -1, \n                    \"socket\": 5, \n                    \"start\": 40.000194\n                }\n            ], \n            \"sum\": {\n                \"bits_per_second\": 859928629.5363914, \n                \"bytes\": 107479040, \n                \"end\": 41.000082, \n                \"omitted\": false, \n                \"retransmits\": 0, \n                \"seconds\": 0.999888002872467, \n                \"sender\": true, \n                \"start\": 40.000194\n            }\n        }, \n        {\n            \"streams\": [\n                {\n                    \"bits_per_second\": 870319843.7535744, \n                    \"bytes\": 108789760, \n                    \"end\": 42.00008, \n                    \"omitted\": false, \n                    \"pmtu\": 1500, \n                    \"retransmits\": 0, \n                    \"rtt\": 77088, \n                    \"rttvar\": 12, \n                    \"seconds\": 0.9999979734420776, \n                    \"sender\": true, \n                    \"snd_cwnd\": 16698336, \n                    \"snd_wnd\": -1, \n                    \"socket\": 5, \n                    \"start\": 41.000082\n                }\n            ], \n            \"sum\": {\n                \"bits_per_second\": 870319843.7535744, \n                \"bytes\": 108789760, \n                \"end\": 42.00008, \n                \"omitted\": false, \n                \"retransmits\": 0, \n                \"seconds\": 0.9999979734420776, \n                \"sender\": true, \n                \"start\": 41.000082\n            }\n        }, \n        {\n            \"streams\": [\n                {\n                    \"bits_per_second\": 859818585.2194, \n                    \"bytes\": 107479040, \n                    \"end\": 43.000096, \n                    \"omitted\": false, \n                    \"pmtu\": 1500, \n                    \"retransmits\": 0, \n                    \"rtt\": 77090, \n                    \"rttvar\": 5, \n                    \"seconds\": 1.0000159740448, \n                    \"sender\": true, \n                    \"snd_cwnd\": 16698336, \n                    \"snd_wnd\": -1, \n                    \"socket\": 5, \n                    \"start\": 42.00008\n                }\n            ], \n            \"sum\": {\n                \"bits_per_second\": 859818585.2194, \n                \"bytes\": 107479040, \n                \"end\": 43.000096, \n                \"omitted\": false, \n                \"retransmits\": 0, \n                \"seconds\": 1.0000159740448, \n                \"sender\": true, \n                \"start\": 42.00008\n            }\n        }, \n        {\n            \"streams\": [\n                {\n                    \"bits_per_second\": 870348531.6904415, \n                    \"bytes\": 108789760, \n                    \"end\": 44.000061, \n                    \"omitted\": false, \n                    \"pmtu\": 1500, \n                    \"retransmits\": 0, \n                    \"rtt\": 77094, \n                    \"rttvar\": 11, \n                    \"seconds\": 0.999965012073517, \n                    \"sender\": true, \n                    \"snd_cwnd\": 16698336, \n                    \"snd_wnd\": -1, \n                    \"socket\": 5, \n                    \"start\": 43.000096\n                }\n            ], \n            \"sum\": {\n                \"bits_per_second\": 870348531.6904415, \n                \"bytes\": 108789760, \n                \"end\": 44.000061, \n                \"omitted\": false, \n                \"retransmits\": 0, \n                \"seconds\": 0.999965012073517, \n                \"sender\": true, \n                \"start\": 43.000096\n            }\n        }, \n        {\n            \"streams\": [\n                {\n                    \"bits_per_second\": 859829757.5076368, \n                    \"bytes\": 107479040, \n                    \"end\": 45.000064, \n                    \"omitted\": false, \n                    \"pmtu\": 1500, \n                    \"retransmits\": 0, \n                    \"rtt\": 77085, \n                    \"rttvar\": 4, \n                    \"seconds\": 1.0000029802322388, \n                    \"sender\": true, \n                    \"snd_cwnd\": 16698336, \n                    \"snd_wnd\": -1, \n                    \"socket\": 5, \n                    \"start\": 44.000061\n                }\n            ], \n            \"sum\": {\n                \"bits_per_second\": 859829757.5076368, \n                \"bytes\": 107479040, \n                \"end\": 45.000064, \n                \"omitted\": false, \n                \"retransmits\": 0, \n                \"seconds\": 1.0000029802322388, \n                \"sender\": true, \n                \"start\": 44.000061\n            }\n        }, \n        {\n            \"streams\": [\n                {\n                    \"bits_per_second\": 870316316.2535744, \n                    \"bytes\": 108789760, \n                    \"end\": 46.000066, \n                    \"omitted\": false, \n                    \"pmtu\": 1500, \n                    \"retransmits\": 0, \n                    \"rtt\": 77086, \n                    \"rttvar\": 7, \n                    \"seconds\": 1.0000020265579224, \n                    \"sender\": true, \n                    \"snd_cwnd\": 16698336, \n                    \"snd_wnd\": -1, \n                    \"socket\": 5, \n                    \"start\": 45.000064\n                }\n            ], \n            \"sum\": {\n                \"bits_per_second\": 870316316.2535744, \n                \"bytes\": 108789760, \n                \"end\": 46.000066, \n                \"omitted\": false, \n                \"retransmits\": 0, \n                \"seconds\": 1.0000020265579224, \n                \"sender\": true, \n                \"start\": 45.000064\n            }\n        }, \n        {\n            \"streams\": [\n                {\n                    \"bits_per_second\": 859830577.5035312, \n                    \"bytes\": 107479040, \n                    \"end\": 47.000068, \n                    \"omitted\": false, \n                    \"pmtu\": 1500, \n                    \"retransmits\": 0, \n                    \"rtt\": 77084, \n                    \"rttvar\": 4, \n                    \"seconds\": 1.0000020265579224, \n                    \"sender\": true, \n                    \"snd_cwnd\": 16698336, \n                    \"snd_wnd\": -1, \n                    \"socket\": 5, \n                    \"start\": 46.000066\n                }\n            ], \n            \"sum\": {\n                \"bits_per_second\": 859830577.5035312, \n                \"bytes\": 107479040, \n                \"end\": 47.000068, \n                \"omitted\": false, \n                \"retransmits\": 0, \n                \"seconds\": 1.0000020265579224, \n                \"sender\": true, \n                \"start\": 46.000066\n            }\n        }, \n        {\n            \"streams\": [\n                {\n                    \"bits_per_second\": 870323319.4065416, \n                    \"bytes\": 108789760, \n                    \"end\": 48.000062, \n                    \"omitted\": false, \n                    \"pmtu\": 1500, \n                    \"retransmits\": 0, \n                    \"rtt\": 77087, \n                    \"rttvar\": 12, \n                    \"seconds\": 0.9999939799308777, \n                    \"sender\": true, \n                    \"snd_cwnd\": 16698336, \n                    \"snd_wnd\": -1, \n                    \"socket\": 5, \n                    \"start\": 47.000068\n                }\n            ], \n            \"sum\": {\n                \"bits_per_second\": 870323319.4065416, \n                \"bytes\": 108789760, \n                \"end\": 48.000062, \n                \"omitted\": false, \n                \"retransmits\": 0, \n                \"seconds\": 0.9999939799308777, \n                \"sender\": true, \n                \"start\": 47.000068\n            }\n        }, \n        {\n            \"streams\": [\n                {\n                    \"bits_per_second\": 859811717.993646, \n                    \"bytes\": 107479040, \n                    \"end\": 49.000086, \n                    \"omitted\": false, \n                    \"pmtu\": 1500, \n                    \"retransmits\": 0, \n                    \"rtt\": 77090, \n                    \"rttvar\": 8, \n                    \"seconds\": 1.0000239610672, \n                    \"sender\": true, \n                    \"snd_cwnd\": 16698336, \n                    \"snd_wnd\": -1, \n                    \"socket\": 5, \n                    \"start\": 48.000062\n                }\n            ], \n            \"sum\": {\n                \"bits_per_second\": 859811717.993646, \n                \"bytes\": 107479040, \n                \"end\": 49.000086, \n                \"omitted\": false, \n                \"retransmits\": 0, \n                \"seconds\": 1.0000239610672, \n                \"sender\": true, \n                \"start\": 48.000062\n            }\n        }, \n        {\n            \"streams\": [\n                {\n                    \"bits_per_second\": 870334628.43965, \n                    \"bytes\": 108789760, \n                    \"end\": 50.000067, \n                    \"omitted\": false, \n                    \"pmtu\": 1500, \n                    \"retransmits\": 0, \n                    \"rtt\": 77088, \n                    \"rttvar\": 8, \n                    \"seconds\": 0.9999809861183167, \n                    \"sender\": true, \n                    \"snd_cwnd\": 16698336, \n                    \"snd_wnd\": -1, \n                    \"socket\": 5, \n                    \"start\": 49.000086\n                }\n            ], \n            \"sum\": {\n                \"bits_per_second\": 870334628.43965, \n                \"bytes\": 108789760, \n                \"end\": 50.000067, \n                \"omitted\": false, \n                \"retransmits\": 0, \n                \"seconds\": 0.9999809861183167, \n                \"sender\": true, \n                \"start\": 49.000086\n            }\n        }, \n        {\n            \"streams\": [\n                {\n                    \"bits_per_second\": 859830577.5035312, \n                    \"bytes\": 107479040, \n                    \"end\": 51.000069, \n                    \"omitted\": false, \n                    \"pmtu\": 1500, \n                    \"retransmits\": 0, \n                    \"rtt\": 77086, \n                    \"rttvar\": 10, \n                    \"seconds\": 1.0000020265579224, \n                    \"sender\": true, \n                    \"snd_cwnd\": 16698336, \n                    \"snd_wnd\": -1, \n                    \"socket\": 5, \n                    \"start\": 50.000067\n                }\n            ], \n            \"sum\": {\n                \"bits_per_second\": 859830577.5035312, \n                \"bytes\": 107479040, \n                \"end\": 51.000069, \n                \"omitted\": false, \n                \"retransmits\": 0, \n                \"seconds\": 1.0000020265579224, \n                \"sender\": true, \n                \"start\": 50.000067\n            }\n        }, \n        {\n            \"streams\": [\n                {\n                    \"bits_per_second\": 870320673.75773, \n                    \"bytes\": 108789760, \n                    \"end\": 52.000066, \n                    \"omitted\": false, \n                    \"pmtu\": 1500, \n                    \"retransmits\": 0, \n                    \"rtt\": 77085, \n                    \"rttvar\": 8, \n                    \"seconds\": 0.9999970197677612, \n                    \"sender\": true, \n                    \"snd_cwnd\": 16698336, \n                    \"snd_wnd\": -1, \n                    \"socket\": 5, \n                    \"start\": 51.000069\n                }\n            ], \n            \"sum\": {\n                \"bits_per_second\": 870320673.75773, \n                \"bytes\": 108789760, \n                \"end\": 52.000066, \n                \"omitted\": false, \n                \"retransmits\": 0, \n                \"seconds\": 0.9999970197677612, \n                \"sender\": true, \n                \"start\": 51.000069\n            }\n        }, \n        {\n            \"streams\": [\n                {\n                    \"bits_per_second\": 870320673.75773, \n                    \"bytes\": 108789760, \n                    \"end\": 53.000063, \n                    \"omitted\": false, \n                    \"pmtu\": 1500, \n                    \"retransmits\": 0, \n                    \"rtt\": 77089, \n                    \"rttvar\": 9, \n                    \"seconds\": 0.9999970197677612, \n                    \"sender\": true, \n                    \"snd_cwnd\": 16698336, \n                    \"snd_wnd\": -1, \n                    \"socket\": 5, \n                    \"start\": 52.000066\n                }\n            ], \n            \"sum\": {\n                \"bits_per_second\": 870320673.75773, \n                \"bytes\": 108789760, \n                \"end\": 53.000063, \n                \"omitted\": false, \n                \"retransmits\": 0, \n                \"seconds\": 0.9999970197677612, \n                \"sender\": true, \n                \"start\": 52.000066\n            }\n        }, \n        {\n            \"streams\": [\n                {\n                    \"bits_per_second\": 859831500.000782, \n                    \"bytes\": 107479040, \n                    \"end\": 54.000064, \n                    \"omitted\": false, \n                    \"pmtu\": 1500, \n                    \"retransmits\": 0, \n                    \"rtt\": 77082, \n                    \"rttvar\": 4, \n                    \"seconds\": 1.0000009536743164, \n                    \"sender\": true, \n                    \"snd_cwnd\": 16698336, \n                    \"snd_wnd\": -1, \n                    \"socket\": 5, \n                    \"start\": 53.000063\n                }\n            ], \n            \"sum\": {\n                \"bits_per_second\": 859831500.000782, \n                \"bytes\": 107479040, \n                \"end\": 54.000064, \n                \"omitted\": false, \n                \"retransmits\": 0, \n                \"seconds\": 1.0000009536743164, \n                \"sender\": true, \n                \"start\": 53.000063\n            }\n        }, \n        {\n            \"streams\": [\n                {\n                    \"bits_per_second\": 870318080, \n                    \"bytes\": 108789760, \n                    \"end\": 55.000064, \n                    \"omitted\": false, \n                    \"pmtu\": 1500, \n                    \"retransmits\": 0, \n                    \"rtt\": 77087, \n                    \"rttvar\": 10, \n                    \"seconds\": 1, \n                    \"sender\": true, \n                    \"snd_cwnd\": 16698336, \n                    \"snd_wnd\": -1, \n                    \"socket\": 5, \n                    \"start\": 54.000064\n                }\n            ], \n            \"sum\": {\n                \"bits_per_second\": 870318080, \n                \"bytes\": 108789760, \n                \"end\": 55.000064, \n                \"omitted\": false, \n                \"retransmits\": 0, \n                \"seconds\": 1, \n                \"sender\": true, \n                \"start\": 54.000064\n            }\n        }, \n        {\n            \"streams\": [\n                {\n                    \"bits_per_second\": 859777281.0233414, \n                    \"bytes\": 107479040, \n                    \"end\": 56.000128, \n                    \"omitted\": false, \n                    \"pmtu\": 1500, \n                    \"retransmits\": 0, \n                    \"rtt\": 77086, \n                    \"rttvar\": 6, \n                    \"seconds\": 1.0000640153884888, \n                    \"sender\": true, \n                    \"snd_cwnd\": 16698336, \n                    \"snd_wnd\": -1, \n                    \"socket\": 5, \n                    \"start\": 55.000064\n                }\n            ], \n            \"sum\": {\n                \"bits_per_second\": 859777281.0233414, \n                \"bytes\": 107479040, \n                \"end\": 56.000128, \n                \"omitted\": false, \n                \"retransmits\": 0, \n                \"seconds\": 1.0000640153884888, \n                \"sender\": true, \n                \"start\": 55.000064\n            }\n        }, \n        {\n            \"streams\": [\n                {\n                    \"bits_per_second\": 870366845.2322363, \n                    \"bytes\": 108789760, \n                    \"end\": 57.000072, \n                    \"omitted\": false, \n                    \"pmtu\": 1500, \n                    \"retransmits\": 0, \n                    \"rtt\": 77087, \n                    \"rttvar\": 12, \n                    \"seconds\": 0.999943971633911, \n                    \"sender\": true, \n                    \"snd_cwnd\": 16698336, \n                    \"snd_wnd\": -1, \n                    \"socket\": 5, \n                    \"start\": 56.000128\n                }\n            ], \n            \"sum\": {\n                \"bits_per_second\": 870366845.2322363, \n                \"bytes\": 108789760, \n                \"end\": 57.000072, \n                \"omitted\": false, \n                \"retransmits\": 0, \n                \"seconds\": 0.999943971633911, \n                \"sender\": true, \n                \"start\": 56.000128\n            }\n        }, \n        {\n            \"streams\": [\n                {\n                    \"bits_per_second\": 859822890.10342, \n                    \"bytes\": 107479040, \n                    \"end\": 58.000083, \n                    \"omitted\": false, \n                    \"pmtu\": 1500, \n                    \"retransmits\": 0, \n                    \"rtt\": 77088, \n                    \"rttvar\": 12, \n                    \"seconds\": 1.0000109672546387, \n                    \"sender\": true, \n                    \"snd_cwnd\": 16698336, \n                    \"snd_wnd\": -1, \n                    \"socket\": 5, \n                    \"start\": 57.000072\n                }\n            ], \n            \"sum\": {\n                \"bits_per_second\": 859822890.10342, \n                \"bytes\": 107479040, \n                \"end\": 58.000083, \n                \"omitted\": false, \n                \"retransmits\": 0, \n                \"seconds\": 1.0000109672546387, \n                \"sender\": true, \n                \"start\": 57.000072\n            }\n        }, \n        {\n            \"streams\": [\n                {\n                    \"bits_per_second\": 870333746.532007, \n                    \"bytes\": 108789760, \n                    \"end\": 59.000065, \n                    \"omitted\": false, \n                    \"pmtu\": 1500, \n                    \"retransmits\": 0, \n                    \"rtt\": 77088, \n                    \"rttvar\": 6, \n                    \"seconds\": 0.9999819993972778, \n                    \"sender\": true, \n                    \"snd_cwnd\": 16698336, \n                    \"snd_wnd\": -1, \n                    \"socket\": 5, \n                    \"start\": 58.000083\n                }\n            ], \n            \"sum\": {\n                \"bits_per_second\": 870333746.532007, \n                \"bytes\": 108789760, \n                \"end\": 59.000065, \n                \"omitted\": false, \n                \"retransmits\": 0, \n                \"seconds\": 0.9999819993972778, \n                \"sender\": true, \n                \"start\": 58.000083\n            }\n        }, \n        {\n            \"streams\": [\n                {\n                    \"bits_per_second\": 859825452.5548505, \n                    \"bytes\": 107479040, \n                    \"end\": 60.000073, \n                    \"omitted\": false, \n                    \"pmtu\": 1500, \n                    \"retransmits\": 0, \n                    \"rtt\": 77084, \n                    \"rttvar\": 7, \n                    \"seconds\": 1.0000079870224, \n                    \"sender\": true, \n                    \"snd_cwnd\": 16698336, \n                    \"snd_wnd\": -1, \n                    \"socket\": 5, \n                    \"start\": 59.000065\n                }\n            ], \n            \"sum\": {\n                \"bits_per_second\": 859825452.5548505, \n                \"bytes\": 107479040, \n                \"end\": 60.000073, \n                \"omitted\": false, \n                \"retransmits\": 0, \n                \"seconds\": 1.0000079870224, \n                \"sender\": true, \n                \"start\": 59.000065\n            }\n        }\n    ], \n    \"start\": {\n        \"connected\": [\n            {\n                \"local_host\": \"10.0.0.1\", \n                \"local_port\": 58493, \n                \"remote_host\": \"10.0.0.2\", \n                \"remote_port\": 5201, \n                \"socket\": 5\n            }\n        ], \n        \"connecting_to\": {\n            \"host\": \"10.0.0.2\", \n            \"port\": 5201\n        }, \n        \"cookie\": \"tomnts2rqu2hk36lrqrm7noam53gkmnta3av\", \n        \"fq_rate\": 0, \n        \"rcvbuf_actual\": 87380, \n        \"sndbuf_actual\": 87380, \n        \"sock_bufsize\": 0, \n        \"system_info\": \"REDACTED\", \n        \"target_bitrate\": 0, \n        \"tcp_mss_default\": 1448, \n        \"test_start\": {\n            \"bidir\": 0, \n            \"blksize\": 131072, \n            \"blocks\": 0, \n            \"bytes\": 0, \n            \"duration\": 60, \n            \"fqrate\": 0, \n            \"num_streams\": 1, \n            \"omit\": 0, \n            \"protocol\": \"TCP\", \n            \"reverse\": 0, \n            \"target_bitrate\": 0, \n            \"tos\": 0\n        }, \n        \"timestamp\": {\n            \"time\": \"Wed, 17 Apr 2024 01:10:34 GMT\", \n            \"timesecs\": 1713316234\n        }, \n        \"version\": \"iperf 3.14\"\n    }\n}\nParticipant 1:\n/usr/bin/iperf3 -s -1 --idle-timeout 60 --json -p 5201 -B 10.0.0.2 --authorized-users-path /var/run/pscheduler-server/runner/tmp/tmpqemm6lju/tmp5uf2aea7/credentials --rsa-private-key-path /var/run/pscheduler-server/runner/tmp/tmpqemm6lju/tmp5uf2aea7/private-key\n\n{\n    \"end\": {\n        \"cpu_utilization_percent\": {\n            \"host_system\": 5.013827027668187, \n            \"host_total\": 5.44612128225052, \n            \"host_user\": 0.4322992481819511, \n            \"remote_system\": 0, \n            \"remote_total\": 0, \n            \"remote_user\": 0\n        }, \n        \"receiver_tcp_congestion\": \"htcp\", \n        \"streams\": [\n            {\n                \"receiver\": {\n                    \"bits_per_second\": 865527842.5013117, \n                    \"bytes\": 6499778056, \n                    \"end\": 60.076894, \n                    \"seconds\": 60.076894, \n                    \"sender\": false, \n                    \"socket\": 5, \n                    \"start\": 0\n                }, \n                \"sender\": {\n                    \"bits_per_second\": 0, \n                    \"bytes\": 0, \n                    \"end\": 60.076894, \n                    \"seconds\": 60.076894, \n                    \"sender\": false, \n                    \"socket\": 5, \n                    \"start\": 0\n                }\n            }\n        ], \n        \"sum_received\": {\n            \"bits_per_second\": 865527842.5013117, \n            \"bytes\": 6499778056, \n            \"end\": 60.076894, \n            \"seconds\": 60.076894, \n            \"sender\": false, \n            \"start\": 0\n        }, \n        \"sum_sent\": {\n            \"bits_per_second\": 0, \n            \"bytes\": 0, \n            \"end\": 60.076894, \n            \"seconds\": 60.076894, \n            \"sender\": false, \n            \"start\": 0\n        }\n    }, \n    \"intervals\": [\n        {\n            \"streams\": [\n                {\n                    \"bits_per_second\": 865295154.5750382, \n                    \"bytes\": 108168496, \n                    \"end\": 1.000061, \n                    \"omitted\": false, \n                    \"seconds\": 1.00006103515625, \n                    \"sender\": false, \n                    \"socket\": 5, \n                    \"start\": 0\n                }\n            ], \n            \"sum\": {\n                \"bits_per_second\": 865295154.5750382, \n                \"bytes\": 108168496, \n                \"end\": 1.000061, \n                \"omitted\": false, \n                \"seconds\": 1.00006103515625, \n                \"sender\": false, \n                \"start\": 0\n            }\n        }, \n        {\n            \"streams\": [\n                {\n                    \"bits_per_second\": 865324800, \n                    \"bytes\": 108165600, \n                    \"end\": 2.000061, \n                    \"omitted\": false, \n                    \"seconds\": 1, \n                    \"sender\": false, \n                    \"socket\": 5, \n                    \"start\": 1.000061\n                }\n            ], \n            \"sum\": {\n                \"bits_per_second\": 865324800, \n                \"bytes\": 108165600, \n                \"end\": 2.000061, \n                \"omitted\": false, \n                \"seconds\": 1, \n                \"sender\": false, \n                \"start\": 1.000061\n            }\n        }, \n        {\n            \"streams\": [\n                {\n                    \"bits_per_second\": 865302312.8478764, \n                    \"bytes\": 108165600, \n                    \"end\": 3.000087, \n                    \"omitted\": false, \n                    \"seconds\": 1.000025987625122, \n                    \"sender\": false, \n                    \"socket\": 5, \n                    \"start\": 2.000061\n                }\n            ], \n            \"sum\": {\n                \"bits_per_second\": 865302312.8478764, \n                \"bytes\": 108165600, \n                \"end\": 3.000087, \n                \"omitted\": false, \n                \"seconds\": 1.000025987625122, \n                \"sender\": false, \n                \"start\": 2.000061\n            }\n        }, \n        {\n            \"streams\": [\n                {\n                    \"bits_per_second\": 865868581.8681105, \n                    \"bytes\": 108230760, \n                    \"end\": 4.000061, \n                    \"omitted\": false, \n                    \"seconds\": 0.999974012374878, \n                    \"sender\": false, \n                    \"socket\": 5, \n                    \"start\": 3.000087\n                }\n            ], \n            \"sum\": {\n                \"bits_per_second\": 865868581.8681105, \n                \"bytes\": 108230760, \n                \"end\": 4.000061, \n                \"omitted\": false, \n                \"seconds\": 0.999974012374878, \n                \"sender\": false, \n                \"start\": 3.000087\n            }\n        }, \n        {\n            \"streams\": [\n                {\n                    \"bits_per_second\": 865312731.0620387, \n                    \"bytes\": 108165600, \n                    \"end\": 5.000075, \n                    \"omitted\": false, \n                    \"seconds\": 1.0000139474868774, \n                    \"sender\": false, \n                    \"socket\": 5, \n                    \"start\": 4.000061\n                }\n            ], \n            \"sum\": {\n                \"bits_per_second\": 865312731.0620387, \n                \"bytes\": 108165600, \n                \"end\": 5.000075, \n                \"omitted\": false, \n                \"seconds\": 1.0000139474868774, \n                \"sender\": false, \n                \"start\": 4.000061\n            }\n        }, \n        {\n            \"streams\": [\n                {\n                    \"bits_per_second\": 865858208.155167, \n                    \"bytes\": 108230760, \n                    \"end\": 6.000061, \n                    \"omitted\": false, \n                    \"seconds\": 0.9999859929084778, \n                    \"sender\": false, \n                    \"socket\": 5, \n                    \"start\": 5.000075\n                }\n            ], \n            \"sum\": {\n                \"bits_per_second\": 865858208.155167, \n                \"bytes\": 108230760, \n                \"end\": 6.000061, \n                \"omitted\": false, \n                \"seconds\": 0.9999859929084778, \n                \"sender\": false, \n                \"start\": 5.000075\n            }\n        }, \n        {\n            \"streams\": [\n                {\n                    \"bits_per_second\": 865312731.0620387, \n                    \"bytes\": 108165600, \n                    \"end\": 7.000075, \n                    \"omitted\": false, \n                    \"seconds\": 1.0000139474868774, \n                    \"sender\": false, \n                    \"socket\": 5, \n                    \"start\": 6.000061\n                }\n            ], \n            \"sum\": {\n                \"bits_per_second\": 865312731.0620387, \n                \"bytes\": 108165600, \n                \"end\": 7.000075, \n                \"omitted\": false, \n                \"seconds\": 1.0000139474868774, \n                \"sender\": false, \n                \"start\": 6.000061\n            }\n        }, \n        {\n            \"streams\": [\n                {\n                    \"bits_per_second\": 865840919.185958, \n                    \"bytes\": 108230760, \n                    \"end\": 8.000081, \n                    \"omitted\": false, \n                    \"seconds\": 1.0000059604644775, \n                    \"sender\": false, \n                    \"socket\": 5, \n                    \"start\": 7.000075\n                }\n            ], \n            \"sum\": {\n                \"bits_per_second\": 865840919.185958, \n                \"bytes\": 108230760, \n                \"end\": 8.000081, \n                \"omitted\": false, \n                \"seconds\": 1.0000059604644775, \n                \"sender\": false, \n                \"start\": 7.000075\n            }\n        }, \n        {\n            \"streams\": [\n                {\n                    \"bits_per_second\": 865342130.345857, \n                    \"bytes\": 108165600, \n                    \"end\": 9.000061, \n                    \"omitted\": false, \n                    \"seconds\": 0.9999799728393555, \n                    \"sender\": false, \n                    \"socket\": 5, \n                    \"start\": 8.000081\n                }\n            ], \n            \"sum\": {\n                \"bits_per_second\": 865342130.345857, \n                \"bytes\": 108165600, \n                \"end\": 9.000061, \n                \"omitted\": false, \n                \"seconds\": 0.9999799728393555, \n                \"sender\": false, \n                \"start\": 8.000081\n            }\n        }, \n        {\n            \"streams\": [\n                {\n                    \"bits_per_second\": 865308398.704887, \n                    \"bytes\": 108165600, \n                    \"end\": 10.00008, \n                    \"omitted\": false, \n                    \"seconds\": 1.0000189542770386, \n                    \"sender\": false, \n                    \"socket\": 5, \n                    \"start\": 9.000061\n                }\n            ], \n            \"sum\": {\n                \"bits_per_second\": 865308398.704887, \n                \"bytes\": 108165600, \n                \"end\": 10.00008, \n                \"omitted\": false, \n                \"seconds\": 1.0000189542770386, \n                \"sender\": false, \n                \"start\": 9.000061\n            }\n        }, \n        {\n            \"streams\": [\n                {\n                    \"bits_per_second\": 865862543.4079545, \n                    \"bytes\": 108230760, \n                    \"end\": 11.000061, \n                    \"omitted\": false, \n                    \"seconds\": 0.9999809861183167, \n                    \"sender\": false, \n                    \"socket\": 5, \n                    \"start\": 10.00008\n                }\n            ], \n            \"sum\": {\n                \"bits_per_second\": 865862543.4079545, \n                \"bytes\": 108230760, \n                \"end\": 11.000061, \n                \"omitted\": false, \n                \"seconds\": 0.9999809861183167, \n                \"sender\": false, \n                \"start\": 10.00008\n            }\n        }, \n        {\n            \"streams\": [\n                {\n                    \"bits_per_second\": 865322221.1388197, \n                    \"bytes\": 108165600, \n                    \"end\": 12.000064, \n                    \"omitted\": false, \n                    \"seconds\": 1.0000029802322388, \n                    \"sender\": false, \n                    \"socket\": 5, \n                    \"start\": 11.000061\n                }\n            ], \n            \"sum\": {\n                \"bits_per_second\": 865322221.1388197, \n                \"bytes\": 108165600, \n                \"end\": 12.000064, \n                \"omitted\": false, \n                \"seconds\": 1.0000029802322388, \n                \"sender\": false, \n                \"start\": 11.000061\n            }\n        }, \n        {\n            \"streams\": [\n                {\n                    \"bits_per_second\": 865859911.2850132, \n                    \"bytes\": 108230760, \n                    \"end\": 13.000048, \n                    \"omitted\": false, \n                    \"seconds\": 0.9999840259552002, \n                    \"sender\": false, \n                    \"socket\": 5, \n                    \"start\": 12.000064\n                }\n            ], \n            \"sum\": {\n                \"bits_per_second\": 865859911.2850132, \n                \"bytes\": 108230760, \n                \"end\": 13.000048, \n                \"omitted\": false, \n                \"seconds\": 0.9999840259552002, \n                \"sender\": false, \n                \"start\": 12.000064\n            }\n        }, \n        {\n            \"streams\": [\n                {\n                    \"bits_per_second\": 865314381.4952217, \n                    \"bytes\": 108165600, \n                    \"end\": 14.00006, \n                    \"omitted\": false, \n                    \"seconds\": 1.0000120401382446, \n                    \"sender\": false, \n                    \"socket\": 5, \n                    \"start\": 13.000048\n                }\n            ], \n            \"sum\": {\n                \"bits_per_second\": 865314381.4952217, \n                \"bytes\": 108165600, \n                \"end\": 14.00006, \n                \"omitted\": false, \n                \"seconds\": 1.0000120401382446, \n                \"sender\": false, \n                \"start\": 13.000048\n            }\n        }, \n        {\n            \"streams\": [\n                {\n                    \"bits_per_second\": 865323974.76275, \n                    \"bytes\": 108165600, \n                    \"end\": 15.000061, \n                    \"omitted\": false, \n                    \"seconds\": 1.0000009536743164, \n                    \"sender\": false, \n                    \"socket\": 5, \n                    \"start\": 14.00006\n                }\n            ], \n            \"sum\": {\n                \"bits_per_second\": 865323974.76275, \n                \"bytes\": 108165600, \n                \"end\": 15.000061, \n                \"omitted\": false, \n                \"seconds\": 1.0000009536743164, \n                \"sender\": false, \n                \"start\": 14.00006\n            }\n        }, \n        {\n            \"streams\": [\n                {\n                    \"bits_per_second\": 865846080, \n                    \"bytes\": 108230760, \n                    \"end\": 16.000061, \n                    \"omitted\": false, \n                    \"seconds\": 1, \n                    \"sender\": false, \n                    \"socket\": 5, \n                    \"start\": 15.000061\n                }\n            ], \n            \"sum\": {\n                \"bits_per_second\": 865846080, \n                \"bytes\": 108230760, \n                \"end\": 16.000061, \n                \"omitted\": false, \n                \"seconds\": 1, \n                \"sender\": false, \n                \"start\": 15.000061\n            }\n        }, \n        {\n            \"streams\": [\n                {\n                    \"bits_per_second\": 865324800, \n                    \"bytes\": 108165600, \n                    \"end\": 17.000061, \n                    \"omitted\": false, \n                    \"seconds\": 1, \n                    \"sender\": false, \n                    \"socket\": 5, \n                    \"start\": 16.000061\n                }\n            ], \n            \"sum\": {\n                \"bits_per_second\": 865324800, \n                \"bytes\": 108165600, \n                \"end\": 17.000061, \n                \"omitted\": false, \n                \"seconds\": 1, \n                \"sender\": false, \n                \"start\": 16.000061\n            }\n        }, \n        {\n            \"streams\": [\n                {\n                    \"bits_per_second\": 865842570.639758, \n                    \"bytes\": 108230760, \n                    \"end\": 18.000065, \n                    \"omitted\": false, \n                    \"seconds\": 1.0000040531158447, \n                    \"sender\": false, \n                    \"socket\": 5, \n                    \"start\": 17.000061\n                }\n            ], \n            \"sum\": {\n                \"bits_per_second\": 865842570.639758, \n                \"bytes\": 108230760, \n                \"end\": 18.000065, \n                \"omitted\": false, \n                \"seconds\": 1.0000040531158447, \n                \"sender\": false, \n                \"start\": 17.000061\n            }\n        }, \n        {\n            \"streams\": [\n                {\n                    \"bits_per_second\": 865326553.6343827, \n                    \"bytes\": 108165600, \n                    \"end\": 19.000063, \n                    \"omitted\": false, \n                    \"seconds\": 0.9999979734420776, \n                    \"sender\": false, \n                    \"socket\": 5, \n                    \"start\": 18.000065\n                }\n            ], \n            \"sum\": {\n                \"bits_per_second\": 865326553.6343827, \n                \"bytes\": 108165600, \n                \"end\": 19.000063, \n                \"omitted\": false, \n                \"seconds\": 0.9999979734420776, \n                \"sender\": false, \n                \"start\": 18.000065\n            }\n        }, \n        {\n            \"streams\": [\n                {\n                    \"bits_per_second\": 865304891.5903953, \n                    \"bytes\": 108165600, \n                    \"end\": 20.000086, \n                    \"omitted\": false, \n                    \"seconds\": 1.0000230073928833, \n                    \"sender\": false, \n                    \"socket\": 5, \n                    \"start\": 19.000063\n                }\n            ], \n            \"sum\": {\n                \"bits_per_second\": 865304891.5903953, \n                \"bytes\": 108165600, \n                \"end\": 20.000086, \n                \"omitted\": false, \n                \"seconds\": 1.0000230073928833, \n                \"sender\": false, \n                \"start\": 19.000063\n            }\n        }, \n        {\n            \"streams\": [\n                {\n                    \"bits_per_second\": 865866878.7041544, \n                    \"bytes\": 108230760, \n                    \"end\": 21.000062, \n                    \"omitted\": false, \n                    \"seconds\": 0.9999759793281555, \n                    \"sender\": false, \n                    \"socket\": 5, \n                    \"start\": 20.000086\n                }\n            ], \n            \"sum\": {\n                \"bits_per_second\": 865866878.7041544, \n                \"bytes\": 108230760, \n                \"end\": 21.000062, \n                \"omitted\": false, \n                \"seconds\": 0.9999759793281555, \n                \"sender\": false, \n                \"start\": 20.000086\n            }\n        }, \n        {\n            \"streams\": [\n                {\n                    \"bits_per_second\": 865307470.3482844, \n                    \"bytes\": 108165600, \n                    \"end\": 22.000082, \n                    \"omitted\": false, \n                    \"seconds\": 1.0000200271606445, \n                    \"sender\": false, \n                    \"socket\": 5, \n                    \"start\": 21.000062\n                }\n            ], \n            \"sum\": {\n                \"bits_per_second\": 865307470.3482844, \n                \"bytes\": 108165600, \n                \"end\": 22.000082, \n                \"omitted\": false, \n                \"seconds\": 1.0000200271606445, \n                \"sender\": false, \n                \"start\": 21.000062\n            }\n        }, \n        {\n            \"streams\": [\n                {\n                    \"bits_per_second\": 865864246.5548556, \n                    \"bytes\": 108230760, \n                    \"end\": 23.000061, \n                    \"omitted\": false, \n                    \"seconds\": 0.999979019165039, \n                    \"sender\": false, \n                    \"socket\": 5, \n                    \"start\": 22.000082\n                }\n            ], \n            \"sum\": {\n                \"bits_per_second\": 865864246.5548556, \n                \"bytes\": 108230760, \n                \"end\": 23.000061, \n                \"omitted\": false, \n                \"seconds\": 0.999979019165039, \n                \"sender\": false, \n                \"start\": 22.000082\n            }\n        }, \n        {\n            \"streams\": [\n                {\n                    \"bits_per_second\": 865307470.3482844, \n                    \"bytes\": 108165600, \n                    \"end\": 24.000081, \n                    \"omitted\": false, \n                    \"seconds\": 1.0000200271606445, \n                    \"sender\": false, \n                    \"socket\": 5, \n                    \"start\": 23.000061\n                }\n            ], \n            \"sum\": {\n                \"bits_per_second\": 865307470.3482844, \n                \"bytes\": 108165600, \n                \"end\": 24.000081, \n                \"omitted\": false, \n                \"seconds\": 1.0000200271606445, \n                \"sender\": false, \n                \"start\": 23.000061\n            }\n        }, \n        {\n            \"streams\": [\n                {\n                    \"bits_per_second\": 865861666.0318626, \n                    \"bytes\": 108230760, \n                    \"end\": 25.000063, \n                    \"omitted\": false, \n                    \"seconds\": 0.9999819993972778, \n                    \"sender\": false, \n                    \"socket\": 5, \n                    \"start\": 24.000081\n                }\n            ], \n            \"sum\": {\n                \"bits_per_second\": 865861666.0318626, \n                \"bytes\": 108230760, \n                \"end\": 25.000063, \n                \"omitted\": false, \n                \"seconds\": 0.9999819993972778, \n                \"sender\": false, \n                \"start\": 24.000081\n            }\n        }, \n        {\n            \"streams\": [\n                {\n                    \"bits_per_second\": 865326553.6343827, \n                    \"bytes\": 108165600, \n                    \"end\": 26.000061, \n                    \"omitted\": false, \n                    \"seconds\": 0.9999979734420776, \n                    \"sender\": false, \n                    \"socket\": 5, \n                    \"start\": 25.000063\n                }\n            ], \n            \"sum\": {\n                \"bits_per_second\": 865326553.6343827, \n                \"bytes\": 108165600, \n                \"end\": 26.000061, \n                \"omitted\": false, \n                \"seconds\": 0.9999979734420776, \n                \"sender\": false, \n                \"start\": 25.000063\n            }\n        }, \n        {\n            \"streams\": [\n                {\n                    \"bits_per_second\": 865310977.48368, \n                    \"bytes\": 108165600, \n                    \"end\": 27.000077, \n                    \"omitted\": false, \n                    \"seconds\": 1.0000159740448, \n                    \"sender\": false, \n                    \"socket\": 5, \n                    \"start\": 26.000061\n                }\n            ], \n            \"sum\": {\n                \"bits_per_second\": 865310977.48368, \n                \"bytes\": 108165600, \n                \"end\": 27.000077, \n                \"omitted\": false, \n                \"seconds\": 1.0000159740448, \n                \"sender\": false, \n                \"start\": 26.000061\n            }\n        }, \n        {\n            \"streams\": [\n                {\n                    \"bits_per_second\": 865859911.2850132, \n                    \"bytes\": 108230760, \n                    \"end\": 28.000061, \n                    \"omitted\": false, \n                    \"seconds\": 0.9999840259552002, \n                    \"sender\": false, \n                    \"socket\": 5, \n                    \"start\": 27.000077\n                }\n            ], \n            \"sum\": {\n                \"bits_per_second\": 865859911.2850132, \n                \"bytes\": 108230760, \n                \"end\": 28.000061, \n                \"omitted\": false, \n                \"seconds\": 0.9999840259552002, \n                \"sender\": false, \n                \"start\": 27.000077\n            }\n        }, \n        {\n            \"streams\": [\n                {\n                    \"bits_per_second\": 865312731.0620387, \n                    \"bytes\": 108165600, \n                    \"end\": 29.000075, \n                    \"omitted\": false, \n                    \"seconds\": 1.0000139474868774, \n                    \"sender\": false, \n                    \"socket\": 5, \n                    \"start\": 28.000061\n                }\n            ], \n            \"sum\": {\n                \"bits_per_second\": 865312731.0620387, \n                \"bytes\": 108165600, \n                \"end\": 29.000075, \n                \"omitted\": false, \n                \"seconds\": 1.0000139474868774, \n                \"sender\": false, \n                \"start\": 28.000061\n            }\n        }, \n        {\n            \"streams\": [\n                {\n                    \"bits_per_second\": 865860788.657549, \n                    \"bytes\": 108230760, \n                    \"end\": 30.000058, \n                    \"omitted\": false, \n                    \"seconds\": 0.999983012676239, \n                    \"sender\": false, \n                    \"socket\": 5, \n                    \"start\": 29.000075\n                }\n            ], \n            \"sum\": {\n                \"bits_per_second\": 865860788.657549, \n                \"bytes\": 108230760, \n                \"end\": 30.000058, \n                \"omitted\": false, \n                \"seconds\": 0.999983012676239, \n                \"sender\": false, \n                \"start\": 29.000075\n            }\n        }, \n        {\n            \"streams\": [\n                {\n                    \"bits_per_second\": 865323046.372725, \n                    \"bytes\": 108165600, \n                    \"end\": 31.00006, \n                    \"omitted\": false, \n                    \"seconds\": 1.0000020265579224, \n                    \"sender\": false, \n                    \"socket\": 5, \n                    \"start\": 30.000058\n                }\n            ], \n            \"sum\": {\n                \"bits_per_second\": 865323046.372725, \n                \"bytes\": 108165600, \n                \"end\": 31.00006, \n                \"omitted\": false, \n                \"seconds\": 1.0000020265579224, \n                \"sender\": false, \n                \"start\": 30.000058\n            }\n        }, \n        {\n            \"streams\": [\n                {\n                    \"bits_per_second\": 865305716.7912476, \n                    \"bytes\": 108165600, \n                    \"end\": 32.000082, \n                    \"omitted\": false, \n                    \"seconds\": 1.000022053718567, \n                    \"sender\": false, \n                    \"socket\": 5, \n                    \"start\": 31.00006\n                }\n            ], \n            \"sum\": {\n                \"bits_per_second\": 865305716.7912476, \n                \"bytes\": 108165600, \n                \"end\": 32.000082, \n                \"omitted\": false, \n                \"seconds\": 1.000022053718567, \n                \"sender\": false, \n                \"start\": 31.00006\n            }\n        }, \n        {\n            \"streams\": [\n                {\n                    \"bits_per_second\": 865864246.5548556, \n                    \"bytes\": 108230760, \n                    \"end\": 33.000061, \n                    \"omitted\": false, \n                    \"seconds\": 0.999979019165039, \n                    \"sender\": false, \n                    \"socket\": 5, \n                    \"start\": 32.000082\n                }\n            ], \n            \"sum\": {\n                \"bits_per_second\": 865864246.5548556, \n                \"bytes\": 108230760, \n                \"end\": 33.000061, \n                \"omitted\": false, \n                \"seconds\": 0.999979019165039, \n                \"sender\": false, \n                \"start\": 32.000082\n            }\n        }, \n        {\n            \"streams\": [\n                {\n                    \"bits_per_second\": 865306645.1440877, \n                    \"bytes\": 108165600, \n                    \"end\": 34.000082, \n                    \"omitted\": false, \n                    \"seconds\": 1.000020980834961, \n                    \"sender\": false, \n                    \"socket\": 5, \n                    \"start\": 33.000061\n                }\n            ], \n            \"sum\": {\n                \"bits_per_second\": 865306645.1440877, \n                \"bytes\": 108165600, \n                \"end\": 34.000082, \n                \"omitted\": false, \n                \"seconds\": 1.000020980834961, \n                \"sender\": false, \n                \"start\": 33.000061\n            }\n        }, \n        {\n            \"streams\": [\n                {\n                    \"bits_per_second\": 865865123.936177, \n                    \"bytes\": 108230760, \n                    \"end\": 35.00006, \n                    \"omitted\": false, \n                    \"seconds\": 0.999978005886078, \n                    \"sender\": false, \n                    \"socket\": 5, \n                    \"start\": 34.000082\n                }\n            ], \n            \"sum\": {\n                \"bits_per_second\": 865865123.936177, \n                \"bytes\": 108230760, \n                \"end\": 35.00006, \n                \"omitted\": false, \n                \"seconds\": 0.999978005886078, \n                \"sender\": false, \n                \"start\": 34.000082\n            }\n        }, \n        {\n            \"streams\": [\n                {\n                    \"bits_per_second\": 865321292.7525575, \n                    \"bytes\": 108165600, \n                    \"end\": 36.000064, \n                    \"omitted\": false, \n                    \"seconds\": 1.0000040531158447, \n                    \"sender\": false, \n                    \"socket\": 5, \n                    \"start\": 35.00006\n                }\n            ], \n            \"sum\": {\n                \"bits_per_second\": 865321292.7525575, \n                \"bytes\": 108165600, \n                \"end\": 36.000064, \n                \"omitted\": false, \n                \"seconds\": 1.0000040531158447, \n                \"sender\": false, \n                \"start\": 35.00006\n            }\n        }, \n        {\n            \"streams\": [\n                {\n                    \"bits_per_second\": 865847834.690789, \n                    \"bytes\": 108230760, \n                    \"end\": 37.000062, \n                    \"omitted\": false, \n                    \"seconds\": 0.9999979734420776, \n                    \"sender\": false, \n                    \"socket\": 5, \n                    \"start\": 36.000064\n                }\n            ], \n            \"sum\": {\n                \"bits_per_second\": 865847834.690789, \n                \"bytes\": 108230760, \n                \"end\": 37.000062, \n                \"omitted\": false, \n                \"seconds\": 0.9999979734420776, \n                \"sender\": false, \n                \"start\": 36.000064\n            }\n        }, \n        {\n            \"streams\": [\n                {\n                    \"bits_per_second\": 865326553.6343827, \n                    \"bytes\": 108165600, \n                    \"end\": 38.00006, \n                    \"omitted\": false, \n                    \"seconds\": 0.9999979734420776, \n                    \"sender\": false, \n                    \"socket\": 5, \n                    \"start\": 37.000062\n                }\n            ], \n            \"sum\": {\n                \"bits_per_second\": 865326553.6343827, \n                \"bytes\": 108165600, \n                \"end\": 38.00006, \n                \"omitted\": false, \n                \"seconds\": 0.9999979734420776, \n                \"sender\": false, \n                \"start\": 37.000062\n            }\n        }, \n        {\n            \"streams\": [\n                {\n                    \"bits_per_second\": 865322221.1388197, \n                    \"bytes\": 108165600, \n                    \"end\": 39.000063, \n                    \"omitted\": false, \n                    \"seconds\": 1.0000029802322388, \n                    \"sender\": false, \n                    \"socket\": 5, \n                    \"start\": 38.00006\n                }\n            ], \n            \"sum\": {\n                \"bits_per_second\": 865322221.1388197, \n                \"bytes\": 108165600, \n                \"end\": 39.000063, \n                \"omitted\": false, \n                \"seconds\": 1.0000029802322388, \n                \"sender\": false, \n                \"start\": 38.00006\n            }\n        }, \n        {\n            \"streams\": [\n                {\n                    \"bits_per_second\": 865846080, \n                    \"bytes\": 108230760, \n                    \"end\": 40.000063, \n                    \"omitted\": false, \n                    \"seconds\": 1, \n                    \"sender\": false, \n                    \"socket\": 5, \n                    \"start\": 39.000063\n                }\n            ], \n            \"sum\": {\n                \"bits_per_second\": 865846080, \n                \"bytes\": 108230760, \n                \"end\": 40.000063, \n                \"omitted\": false, \n                \"seconds\": 1, \n                \"sender\": false, \n                \"start\": 39.000063\n            }\n        }, \n        {\n            \"streams\": [\n                {\n                    \"bits_per_second\": 865309223.9124285, \n                    \"bytes\": 108165600, \n                    \"end\": 41.000081, \n                    \"omitted\": false, \n                    \"seconds\": 1.0000180006027222, \n                    \"sender\": false, \n                    \"socket\": 5, \n                    \"start\": 40.000063\n                }\n            ], \n            \"sum\": {\n                \"bits_per_second\": 865309223.9124285, \n                \"bytes\": 108165600, \n                \"end\": 41.000081, \n                \"omitted\": false, \n                \"seconds\": 1.0000180006027222, \n                \"sender\": false, \n                \"start\": 40.000063\n            }\n        }, \n        {\n            \"streams\": [\n                {\n                    \"bits_per_second\": 865849537.7798266, \n                    \"bytes\": 108230760, \n                    \"end\": 42.000077, \n                    \"omitted\": false, \n                    \"seconds\": 0.9999960064888, \n                    \"sender\": false, \n                    \"socket\": 5, \n                    \"start\": 41.000081\n                }\n            ], \n            \"sum\": {\n                \"bits_per_second\": 865849537.7798266, \n                \"bytes\": 108230760, \n                \"end\": 42.000077, \n                \"omitted\": false, \n                \"seconds\": 0.9999960064888, \n                \"sender\": false, \n                \"start\": 41.000081\n            }\n        }, \n        {\n            \"streams\": [\n                {\n                    \"bits_per_second\": 865338622.95793, \n                    \"bytes\": 108165600, \n                    \"end\": 43.000061, \n                    \"omitted\": false, \n                    \"seconds\": 0.9999840259552002, \n                    \"sender\": false, \n                    \"socket\": 5, \n                    \"start\": 42.000077\n                }\n            ], \n            \"sum\": {\n                \"bits_per_second\": 865338622.95793, \n                \"bytes\": 108165600, \n                \"end\": 43.000061, \n                \"omitted\": false, \n                \"seconds\": 0.9999840259552002, \n                \"sender\": false, \n                \"start\": 42.000077\n            }\n        }, \n        {\n            \"streams\": [\n                {\n                    \"bits_per_second\": 865308398.704887, \n                    \"bytes\": 108165600, \n                    \"end\": 44.00008, \n                    \"omitted\": false, \n                    \"seconds\": 1.0000189542770386, \n                    \"sender\": false, \n                    \"socket\": 5, \n                    \"start\": 43.000061\n                }\n            ], \n            \"sum\": {\n                \"bits_per_second\": 865308398.704887, \n                \"bytes\": 108165600, \n                \"end\": 44.00008, \n                \"omitted\": false, \n                \"seconds\": 1.0000189542770386, \n                \"sender\": false, \n                \"start\": 43.000061\n            }\n        }, \n        {\n            \"streams\": [\n                {\n                    \"bits_per_second\": 865862543.4079545, \n                    \"bytes\": 108230760, \n                    \"end\": 45.000061, \n                    \"omitted\": false, \n                    \"seconds\": 0.9999809861183167, \n                    \"sender\": false, \n                    \"socket\": 5, \n                    \"start\": 44.00008\n                }\n            ], \n            \"sum\": {\n                \"bits_per_second\": 865862543.4079545, \n                \"bytes\": 108230760, \n                \"end\": 45.000061, \n                \"omitted\": false, \n                \"seconds\": 0.9999809861183167, \n                \"sender\": false, \n                \"start\": 44.00008\n            }\n        }, \n        {\n            \"streams\": [\n                {\n                    \"bits_per_second\": 865309223.9124285, \n                    \"bytes\": 108165600, \n                    \"end\": 46.000079, \n                    \"omitted\": false, \n                    \"seconds\": 1.0000180006027222, \n                    \"sender\": false, \n                    \"socket\": 5, \n                    \"start\": 45.000061\n                }\n            ], \n            \"sum\": {\n                \"bits_per_second\": 865309223.9124285, \n                \"bytes\": 108165600, \n                \"end\": 46.000079, \n                \"omitted\": false, \n                \"seconds\": 1.0000180006027222, \n                \"sender\": false, \n                \"start\": 45.000061\n            }\n        }, \n        {\n            \"streams\": [\n                {\n                    \"bits_per_second\": 865862543.4079545, \n                    \"bytes\": 108230760, \n                    \"end\": 47.00006, \n                    \"omitted\": false, \n                    \"seconds\": 0.9999809861183167, \n                    \"sender\": false, \n                    \"socket\": 5, \n                    \"start\": 46.000079\n                }\n            ], \n            \"sum\": {\n                \"bits_per_second\": 865862543.4079545, \n                \"bytes\": 108230760, \n                \"end\": 47.00006, \n                \"omitted\": false, \n                \"seconds\": 0.9999809861183167, \n                \"sender\": false, \n                \"start\": 46.000079\n            }\n        }, \n        {\n            \"streams\": [\n                {\n                    \"bits_per_second\": 865326553.6343827, \n                    \"bytes\": 108165600, \n                    \"end\": 48.000058, \n                    \"omitted\": false, \n                    \"seconds\": 0.9999979734420776, \n                    \"sender\": false, \n                    \"socket\": 5, \n                    \"start\": 47.00006\n                }\n            ], \n            \"sum\": {\n                \"bits_per_second\": 865326553.6343827, \n                \"bytes\": 108165600, \n                \"end\": 48.000058, \n                \"omitted\": false, \n                \"seconds\": 0.9999979734420776, \n                \"sender\": false, \n                \"start\": 47.00006\n            }\n        }, \n        {\n            \"streams\": [\n                {\n                    \"bits_per_second\": 865813155.0622195, \n                    \"bytes\": 108230760, \n                    \"end\": 49.000096, \n                    \"omitted\": false, \n                    \"seconds\": 1.0000380277633667, \n                    \"sender\": false, \n                    \"socket\": 5, \n                    \"start\": 48.000058\n                }\n            ], \n            \"sum\": {\n                \"bits_per_second\": 865813155.0622195, \n                \"bytes\": 108230760, \n                \"end\": 49.000096, \n                \"omitted\": false, \n                \"seconds\": 1.0000380277633667, \n                \"sender\": false, \n                \"start\": 48.000058\n            }\n        }, \n        {\n            \"streams\": [\n                {\n                    \"bits_per_second\": 865355076.9798152, \n                    \"bytes\": 108165600, \n                    \"end\": 50.000061, \n                    \"omitted\": false, \n                    \"seconds\": 0.999965012073517, \n                    \"sender\": false, \n                    \"socket\": 5, \n                    \"start\": 49.000096\n                }\n            ], \n            \"sum\": {\n                \"bits_per_second\": 865355076.9798152, \n                \"bytes\": 108165600, \n                \"end\": 50.000061, \n                \"omitted\": false, \n                \"seconds\": 0.999965012073517, \n                \"sender\": false, \n                \"start\": 49.000096\n            }\n        }, \n        {\n            \"streams\": [\n                {\n                    \"bits_per_second\": 865306645.1440877, \n                    \"bytes\": 108165600, \n                    \"end\": 51.000082, \n                    \"omitted\": false, \n                    \"seconds\": 1.000020980834961, \n                    \"sender\": false, \n                    \"socket\": 5, \n                    \"start\": 50.000061\n                }\n            ], \n            \"sum\": {\n                \"bits_per_second\": 865306645.1440877, \n                \"bytes\": 108165600, \n                \"end\": 51.000082, \n                \"omitted\": false, \n                \"seconds\": 1.000020980834961, \n                \"sender\": false, \n                \"start\": 50.000061\n            }\n        }, \n        {\n            \"streams\": [\n                {\n                    \"bits_per_second\": 865885046.1317962, \n                    \"bytes\": 108230760, \n                    \"end\": 52.000037, \n                    \"omitted\": false, \n                    \"seconds\": 0.9999549984931946, \n                    \"sender\": false, \n                    \"socket\": 5, \n                    \"start\": 51.000082\n                }\n            ], \n            \"sum\": {\n                \"bits_per_second\": 865885046.1317962, \n                \"bytes\": 108230760, \n                \"end\": 52.000037, \n                \"omitted\": false, \n                \"seconds\": 0.9999549984931946, \n                \"sender\": false, \n                \"start\": 51.000082\n            }\n        }, \n        {\n            \"streams\": [\n                {\n                    \"bits_per_second\": 865291069.7100884, \n                    \"bytes\": 108165600, \n                    \"end\": 53.000076, \n                    \"omitted\": false, \n                    \"seconds\": 1.000038981437683, \n                    \"sender\": false, \n                    \"socket\": 5, \n                    \"start\": 52.000037\n                }\n            ], \n            \"sum\": {\n                \"bits_per_second\": 865291069.7100884, \n                \"bytes\": 108165600, \n                \"end\": 53.000076, \n                \"omitted\": false, \n                \"seconds\": 1.000038981437683, \n                \"sender\": false, \n                \"start\": 52.000037\n            }\n        }, \n        {\n            \"streams\": [\n                {\n                    \"bits_per_second\": 865845254.265619, \n                    \"bytes\": 108230760, \n                    \"end\": 54.000077, \n                    \"omitted\": false, \n                    \"seconds\": 1.0000009536743164, \n                    \"sender\": false, \n                    \"socket\": 5, \n                    \"start\": 53.000076\n                }\n            ], \n            \"sum\": {\n                \"bits_per_second\": 865845254.265619, \n                \"bytes\": 108230760, \n                \"end\": 54.000077, \n                \"omitted\": false, \n                \"seconds\": 1.0000009536743164, \n                \"sender\": false, \n                \"start\": 53.000076\n            }\n        }, \n        {\n            \"streams\": [\n                {\n                    \"bits_per_second\": 865338622.95793, \n                    \"bytes\": 108165600, \n                    \"end\": 55.000061, \n                    \"omitted\": false, \n                    \"seconds\": 0.9999840259552002, \n                    \"sender\": false, \n                    \"socket\": 5, \n                    \"start\": 54.000077\n                }\n            ], \n            \"sum\": {\n                \"bits_per_second\": 865338622.95793, \n                \"bytes\": 108165600, \n                \"end\": 55.000061, \n                \"omitted\": false, \n                \"seconds\": 0.9999840259552002, \n                \"sender\": false, \n                \"start\": 54.000077\n            }\n        }, \n        {\n            \"streams\": [\n                {\n                    \"bits_per_second\": 865307470.3482844, \n                    \"bytes\": 108165600, \n                    \"end\": 56.000081, \n                    \"omitted\": false, \n                    \"seconds\": 1.0000200271606445, \n                    \"sender\": false, \n                    \"socket\": 5, \n                    \"start\": 55.000061\n                }\n            ], \n            \"sum\": {\n                \"bits_per_second\": 865307470.3482844, \n                \"bytes\": 108165600, \n                \"end\": 56.000081, \n                \"omitted\": false, \n                \"seconds\": 1.0000200271606445, \n                \"sender\": false, \n                \"start\": 55.000061\n            }\n        }, \n        {\n            \"streams\": [\n                {\n                    \"bits_per_second\": 865860788.657549, \n                    \"bytes\": 108230760, \n                    \"end\": 57.000064, \n                    \"omitted\": false, \n                    \"seconds\": 0.999983012676239, \n                    \"sender\": false, \n                    \"socket\": 5, \n                    \"start\": 56.000081\n                }\n            ], \n            \"sum\": {\n                \"bits_per_second\": 865860788.657549, \n                \"bytes\": 108230760, \n                \"end\": 57.000064, \n                \"omitted\": false, \n                \"seconds\": 0.999983012676239, \n                \"sender\": false, \n                \"start\": 56.000081\n            }\n        }, \n        {\n            \"streams\": [\n                {\n                    \"bits_per_second\": 865311802.6961398, \n                    \"bytes\": 108165600, \n                    \"end\": 58.000079, \n                    \"omitted\": false, \n                    \"seconds\": 1.0000150203704834, \n                    \"sender\": false, \n                    \"socket\": 5, \n                    \"start\": 57.000064\n                }\n            ], \n            \"sum\": {\n                \"bits_per_second\": 865311802.6961398, \n                \"bytes\": 108165600, \n                \"end\": 58.000079, \n                \"omitted\": false, \n                \"seconds\": 1.0000150203704834, \n                \"sender\": false, \n                \"start\": 57.000064\n            }\n        }, \n        {\n            \"streams\": [\n                {\n                    \"bits_per_second\": 865885046.1317962, \n                    \"bytes\": 108230760, \n                    \"end\": 59.000034, \n                    \"omitted\": false, \n                    \"seconds\": 0.9999549984931946, \n                    \"sender\": false, \n                    \"socket\": 5, \n                    \"start\": 58.000079\n                }\n            ], \n            \"sum\": {\n                \"bits_per_second\": 865885046.1317962, \n                \"bytes\": 108230760, \n                \"end\": 59.000034, \n                \"omitted\": false, \n                \"seconds\": 0.9999549984931946, \n                \"sender\": false, \n                \"start\": 58.000079\n            }\n        }, \n        {\n            \"streams\": [\n                {\n                    \"bits_per_second\": 865297980.5950457, \n                    \"bytes\": 108165600, \n                    \"end\": 60.000065, \n                    \"omitted\": false, \n                    \"seconds\": 1.0000309944152832, \n                    \"sender\": false, \n                    \"socket\": 5, \n                    \"start\": 59.000034\n                }\n            ], \n            \"sum\": {\n                \"bits_per_second\": 865297980.5950457, \n                \"bytes\": 108165600, \n                \"end\": 60.000065, \n                \"omitted\": false, \n                \"seconds\": 1.0000309944152832, \n                \"sender\": false, \n                \"start\": 59.000034\n            }\n        }, \n        {\n            \"streams\": [\n                {\n                    \"bits_per_second\": 861687108.6875384, \n                    \"bytes\": 8275320, \n                    \"end\": 60.076894, \n                    \"omitted\": false, \n                    \"seconds\": 0.0768290013074875, \n                    \"sender\": false, \n                    \"socket\": 5, \n                    \"start\": 60.000065\n                }\n            ], \n            \"sum\": {\n                \"bits_per_second\": 861687108.6875384, \n                \"bytes\": 8275320, \n                \"end\": 60.076894, \n                \"omitted\": false, \n                \"seconds\": 0.0768290013074875, \n                \"sender\": false, \n                \"start\": 60.000065\n            }\n        }\n    ], \n    \"start\": {\n        \"accepted_connection\": {\n            \"host\": \"10.0.0.1\", \n            \"port\": 60615\n        }, \n        \"connected\": [\n            {\n                \"local_host\": \"10.0.0.2\", \n                \"local_port\": 5201, \n                \"remote_host\": \"10.0.0.1\", \n                \"remote_port\": 58493, \n                \"socket\": 5\n            }\n        ], \n        \"cookie\": \"tomnts2rqu2hk36lrqrm7noam53gkmnta3av\", \n        \"fq_rate\": 0, \n        \"rcvbuf_actual\": 87380, \n        \"sndbuf_actual\": 87380, \n        \"sock_bufsize\": 0, \n        \"system_info\": \"REDACTED\", \n        \"target_bitrate\": 0, \n        \"tcp_mss_default\": 0, \n        \"test_start\": {\n            \"bidir\": 0, \n            \"blksize\": 131072, \n            \"blocks\": 0, \n            \"bytes\": 0, \n            \"duration\": 60, \n            \"fqrate\": 0, \n            \"num_streams\": 1, \n            \"omit\": 0, \n            \"protocol\": \"TCP\", \n            \"reverse\": 0, \n            \"target_bitrate\": 0, \n            \"tos\": 0\n        }, \n        \"timestamp\": {\n            \"time\": \"Wed, 17 Apr 2024 01:10:34 GMT\", \n            \"timesecs\": 1713316234\n        }, \n        \"version\": \"iperf 3.14\"\n    }\n}\n","summary":{"streams":[{"end":60.000073,"rtt":77087,"start":0,"stream-id":5,"retransmits":0,"throughput-bits":867014010.7329535,"throughput-bytes":6502612992}],"summary":{"end":60.000073,"start":0,"retransmits":0,"throughput-bits":867014010.7329535,"throughput-bytes":6502612992,"receiver-throughput-bits":865527842.5013117}},"intervals":[{"streams":[{"end":1.000024,"rtt":77086,"start":0,"omitted":false,"stream-id":5,"retransmits":0,"tcp-window-size":16698336,"throughput-bits":955229847.6734288,"throughput-bytes":119406592}],"summary":{"end":1.000024,"start":0,"omitted":false,"retransmits":0,"throughput-bits":955229847.6734288,"throughput-bytes":119406592}},{"streams":[{"end":2.000063,"rtt":77088,"start":1.000024,"omitted":false,"stream-id":5,"retransmits":0,"tcp-window-size":16698336,"throughput-bits":870284155.0724424,"throughput-bytes":108789760}],"summary":{"end":2.000063,"start":1.000024,"omitted":false,"retransmits":0,"throughput-bits":870284155.0724424,"throughput-bytes":108789760}},{"streams":[{"end":3.000053,"rtt":77082,"start":2.000063,"omitted":false,"stream-id":5,"retransmits":0,"tcp-window-size":16698336,"throughput-bits":859840930.0862178,"throughput-bytes":107479040}],"summary":{"end":3.000053,"start":2.000063,"omitted":false,"retransmits":0,"throughput-bits":859840930.0862178,"throughput-bytes":107479040}},{"streams":[{"end":4.000064,"rtt":77089,"start":3.000053,"omitted":false,"stream-id":5,"retransmits":0,"tcp-window-size":16698336,"throughput-bits":870308535.1046813,"throughput-bytes":108789760}],"summary":{"end":4.000064,"start":3.000053,"omitted":false,"retransmits":0,"throughput-bits":870308535.1046813,"throughput-bytes":108789760}},{"streams":[{"end":5.000073,"rtt":77087,"start":4.000064,"omitted":false,"stream-id":5,"retransmits":0,"tcp-window-size":16698336,"throughput-bits":859824632.568731,"throughput-bytes":107479040}],"summary":{"end":5.000073,"start":4.000064,"omitted":false,"retransmits":0,"throughput-bits":859824632.568731,"throughput-bytes":107479040}},{"streams":[{"end":6.000063,"rtt":77088,"start":5.000073,"omitted":false,"stream-id":5,"retransmits":0,"tcp-window-size":16698336,"throughput-bits":870326795.0872692,"throughput-bytes":108789760}],"summary":{"end":6.000063,"start":5.000073,"omitted":false,"retransmits":0,"throughput-bits":870326795.0872692,"throughput-bytes":108789760}},{"streams":[{"end":7.000062,"rtt":77088,"start":6.000063,"omitted":false,"stream-id":5,"retransmits":0,"tcp-window-size":16698336,"throughput-bits":870318961.8758936,"throughput-bytes":108789760}],"summary":{"end":7.000062,"start":6.000063,"omitted":false,"retransmits":0,"throughput-bits":870318961.8758936,"throughput-bytes":108789760}},{"streams":[{"end":8.000032,"rtt":77085,"start":7.000062,"omitted":false,"stream-id":5,"retransmits":0,"tcp-window-size":16698336,"throughput-bits":859858099.5228994,"throughput-bytes":107479040}],"summary":{"end":8.000032,"start":7.000062,"omitted":false,"retransmits":0,"throughput-bits":859858099.5228994,"throughput-bytes":107479040}},{"streams":[{"end":9.000076,"rtt":77094,"start":8.000032,"omitted":false,"stream-id":5,"retransmits":0,"tcp-window-size":16698336,"throughput-bits":870279797.9339602,"throughput-bytes":108789760}],"summary":{"end":9.000076,"start":8.000032,"omitted":false,"retransmits":0,"throughput-bits":870279797.9339602,"throughput-bytes":108789760}},{"streams":[{"end":10.000147,"rtt":77087,"start":9.000076,"omitted":false,"stream-id":5,"retransmits":0,"tcp-window-size":16698336,"throughput-bits":859771234.340059,"throughput-bytes":107479040}],"summary":{"end":10.000147,"start":9.000076,"omitted":false,"retransmits":0,"throughput-bits":859771234.340059,"throughput-bytes":107479040}},{"streams":[{"end":11.000063,"rtt":77089,"start":10.000147,"omitted":false,"stream-id":5,"retransmits":0,"tcp-window-size":16698336,"throughput-bits":870391178.0139865,"throughput-bytes":108789760}],"summary":{"end":11.000063,"start":10.000147,"omitted":false,"retransmits":0,"throughput-bits":870391178.0139865,"throughput-bytes":108789760}},{"streams":[{"end":12.000081,"rtt":77086,"start":11.000063,"omitted":false,"stream-id":5,"retransmits":0,"tcp-window-size":16698336,"throughput-bits":859816842.7785993,"throughput-bytes":107479040}],"summary":{"end":12.000081,"start":11.000063,"omitted":false,"retransmits":0,"throughput-bits":859816842.7785993,"throughput-bytes":107479040}},{"streams":[{"end":13.00004,"rtt":77089,"start":12.000081,"omitted":false,"stream-id":5,"retransmits":0,"tcp-window-size":16698336,"throughput-bits":870353771.4636353,"throughput-bytes":108789760}],"summary":{"end":13.00004,"start":12.000081,"omitted":false,"retransmits":0,"throughput-bits":870353771.4636353,"throughput-bytes":108789760}},{"streams":[{"end":14.00008,"rtt":77087,"start":13.00004,"omitted":false,"stream-id":5,"retransmits":0,"tcp-window-size":16698336,"throughput-bits":859797881.3794156,"throughput-bytes":107479040}],"summary":{"end":14.00008,"start":13.00004,"omitted":false,"retransmits":0,"throughput-bits":859797881.3794156,"throughput-bytes":107479040}},{"streams":[{"end":15.000112,"rtt":77085,"start":14.00008,"omitted":false,"stream-id":5,"retransmits":0,"tcp-window-size":16698336,"throughput-bits":870290275.8882883,"throughput-bytes":108789760}],"summary":{"end":15.000112,"start":14.00008,"omitted":false,"retransmits":0,"throughput-bits":870290275.8882883,"throughput-bytes":108789760}},{"streams":[{"end":16.000074,"rtt":77091,"start":15.000112,"omitted":false,"stream-id":5,"retransmits":0,"tcp-window-size":16698336,"throughput-bits":859865018.74346,"throughput-bytes":107479040}],"summary":{"end":16.000074,"start":15.000112,"omitted":false,"retransmits":0,"throughput-bits":859865018.74346,"throughput-bytes":107479040}},{"streams":[{"end":17.000086,"rtt":77089,"start":16.000074,"omitted":false,"stream-id":5,"retransmits":0,"tcp-window-size":16698336,"throughput-bits":870307601.376164,"throughput-bytes":108789760}],"summary":{"end":17.000086,"start":16.000074,"omitted":false,"retransmits":0,"throughput-bits":870307601.376164,"throughput-bytes":108789760}},{"streams":[{"end":18.000265,"rtt":77105,"start":17.000086,"omitted":false,"stream-id":5,"retransmits":0,"tcp-window-size":16698336,"throughput-bits":870162275.3971807,"throughput-bytes":108789760}],"summary":{"end":18.000265,"start":17.000086,"omitted":false,"retransmits":0,"throughput-bits":870162275.3971807,"throughput-bytes":108789760}},{"streams":[{"end":19.000066,"rtt":77088,"start":18.000265,"omitted":false,"stream-id":5,"retransmits":0,"tcp-window-size":16698336,"throughput-bits":860003477.8138125,"throughput-bytes":107479040}],"summary":{"end":19.000066,"start":18.000265,"omitted":false,"retransmits":0,"throughput-bits":860003477.8138125,"throughput-bytes":107479040}},{"streams":[{"end":20.00007,"rtt":77090,"start":19.000066,"omitted":false,"stream-id":5,"retransmits":0,"tcp-window-size":16698336,"throughput-bits":870314552.5142974,"throughput-bytes":108789760}],"summary":{"end":20.00007,"start":19.000066,"omitted":false,"retransmits":0,"throughput-bits":870314552.5142974,"throughput-bytes":108789760}},{"streams":[{"end":21.000151,"rtt":77089,"start":20.00007,"omitted":false,"stream-id":5,"retransmits":0,"tcp-window-size":16698336,"throughput-bits":859762728.132982,"throughput-bytes":107479040}],"summary":{"end":21.000151,"start":20.00007,"omitted":false,"retransmits":0,"throughput-bits":859762728.132982,"throughput-bytes":107479040}},{"streams":[{"end":22.000066,"rtt":77086,"start":21.000151,"omitted":false,"stream-id":5,"retransmits":0,"tcp-window-size":16698336,"throughput-bits":870392060.038024,"throughput-bytes":108789760}],"summary":{"end":22.000066,"start":21.000151,"omitted":false,"retransmits":0,"throughput-bits":870392060.038024,"throughput-bytes":108789760}},{"streams":[{"end":23.000065,"rtt":77086,"start":22.000066,"omitted":false,"stream-id":5,"retransmits":0,"tcp-window-size":16698336,"throughput-bits":859833191.250883,"throughput-bytes":107479040}],"summary":{"end":23.000065,"start":22.000066,"omitted":false,"retransmits":0,"throughput-bits":859833191.250883,"throughput-bytes":107479040}},{"streams":[{"end":24.000082,"rtt":77085,"start":23.000065,"omitted":false,"stream-id":5,"retransmits":0,"tcp-window-size":16698336,"throughput-bits":870303244.0029082,"throughput-bytes":108789760}],"summary":{"end":24.000082,"start":23.000065,"omitted":false,"retransmits":0,"throughput-bits":870303244.0029082,"throughput-bytes":108789760}},{"streams":[{"end":25.000033,"rtt":77086,"start":24.000082,"omitted":false,"stream-id":5,"retransmits":0,"tcp-window-size":16698336,"throughput-bits":859874449.5641388,"throughput-bytes":107479040}],"summary":{"end":25.000033,"start":24.000082,"omitted":false,"retransmits":0,"throughput-bits":859874449.5641388,"throughput-bytes":107479040}},{"streams":[{"end":26.000087,"rtt":77089,"start":25.000033,"omitted":false,"stream-id":5,"retransmits":0,"tcp-window-size":16698336,"throughput-bits":870271083.7878804,"throughput-bytes":108789760}],"summary":{"end":26.000087,"start":25.000033,"omitted":false,"retransmits":0,"throughput-bits":870271083.7878804,"throughput-bytes":108789760}},{"streams":[{"end":27.000064,"rtt":77084,"start":26.000087,"omitted":false,"stream-id":5,"retransmits":0,"tcp-window-size":16698336,"throughput-bits":859852102.9551542,"throughput-bytes":107479040}],"summary":{"end":27.000064,"start":26.000087,"omitted":false,"retransmits":0,"throughput-bits":859852102.9551542,"throughput-bytes":107479040}},{"streams":[{"end":28.000089,"rtt":77094,"start":27.000064,"omitted":false,"stream-id":5,"retransmits":0,"tcp-window-size":16698336,"throughput-bits":870296293.0454135,"throughput-bytes":108789760}],"summary":{"end":28.000089,"start":27.000064,"omitted":false,"retransmits":0,"throughput-bits":870296293.0454135,"throughput-bytes":108789760}},{"streams":[{"end":29.00006,"rtt":77084,"start":28.000089,"omitted":false,"stream-id":5,"retransmits":0,"tcp-window-size":16698336,"throughput-bits":870343343.8583457,"throughput-bytes":108789760}],"summary":{"end":29.00006,"start":28.000089,"omitted":false,"retransmits":0,"throughput-bits":870343343.8583457,"throughput-bytes":108789760}},{"streams":[{"end":30.000056,"rtt":77085,"start":29.00006,"omitted":false,"stream-id":5,"retransmits":0,"tcp-window-size":16698336,"throughput-bits":859835753.7637128,"throughput-bytes":107479040}],"summary":{"end":30.000056,"start":29.00006,"omitted":false,"retransmits":0,"throughput-bits":859835753.7637128,"throughput-bytes":107479040}},{"streams":[{"end":31.000063,"rtt":77087,"start":30.000056,"omitted":false,"stream-id":5,"retransmits":0,"tcp-window-size":16698336,"throughput-bits":870311958.7930526,"throughput-bytes":108789760}],"summary":{"end":31.000063,"start":30.000056,"omitted":false,"retransmits":0,"throughput-bits":870311958.7930526,"throughput-bytes":108789760}},{"streams":[{"end":32.000063,"rtt":77090,"start":31.000063,"omitted":false,"stream-id":5,"retransmits":0,"tcp-window-size":16698336,"throughput-bits":859832320,"throughput-bytes":107479040}],"summary":{"end":32.000063,"start":31.000063,"omitted":false,"retransmits":0,"throughput-bits":859832320,"throughput-bytes":107479040}},{"streams":[{"end":33.000063,"rtt":77087,"start":32.000063,"omitted":false,"stream-id":5,"retransmits":0,"tcp-window-size":16698336,"throughput-bits":870318080,"throughput-bytes":108789760}],"summary":{"end":33.000063,"start":32.000063,"omitted":false,"retransmits":0,"throughput-bits":870318080,"throughput-bytes":108789760}},{"streams":[{"end":34.000168,"rtt":77086,"start":33.000063,"omitted":false,"stream-id":5,"retransmits":0,"tcp-window-size":16698336,"throughput-bits":859742026.9828782,"throughput-bytes":107479040}],"summary":{"end":34.000168,"start":33.000063,"omitted":false,"retransmits":0,"throughput-bits":859742026.9828782,"throughput-bytes":107479040}},{"streams":[{"end":35.000083,"rtt":77084,"start":34.000168,"omitted":false,"stream-id":5,"retransmits":0,"tcp-window-size":16698336,"throughput-bits":870392060.038024,"throughput-bytes":108789760}],"summary":{"end":35.000083,"start":34.000168,"omitted":false,"retransmits":0,"throughput-bits":870392060.038024,"throughput-bytes":108789760}},{"streams":[{"end":36.000078,"rtt":77084,"start":35.000083,"omitted":false,"stream-id":5,"retransmits":0,"tcp-window-size":16698336,"throughput-bits":859836625.0215544,"throughput-bytes":107479040}],"summary":{"end":36.000078,"start":35.000083,"omitted":false,"retransmits":0,"throughput-bits":859836625.0215544,"throughput-bytes":107479040}},{"streams":[{"end":37.000134,"rtt":77087,"start":36.000078,"omitted":false,"stream-id":5,"retransmits":0,"tcp-window-size":16698336,"throughput-bits":870269320.23193,"throughput-bytes":108789760}],"summary":{"end":37.000134,"start":36.000078,"omitted":false,"retransmits":0,"throughput-bits":870269320.23193,"throughput-bytes":108789760}},{"streams":[{"end":38.000065,"rtt":77088,"start":37.000134,"omitted":false,"stream-id":5,"retransmits":0,"tcp-window-size":16698336,"throughput-bits":859891671.5965765,"throughput-bytes":107479040}],"summary":{"end":38.000065,"start":37.000134,"omitted":false,"retransmits":0,"throughput-bits":859891671.5965765,"throughput-bytes":107479040}},{"streams":[{"end":39.000087,"rtt":77093,"start":38.000065,"omitted":false,"stream-id":5,"retransmits":0,"tcp-window-size":16698336,"throughput-bits":870298886.673284,"throughput-bytes":108789760}],"summary":{"end":39.000087,"start":38.000065,"omitted":false,"retransmits":0,"throughput-bits":870298886.673284,"throughput-bytes":108789760}},{"streams":[{"end":40.000194,"rtt":77090,"start":39.000087,"omitted":false,"stream-id":5,"retransmits":0,"tcp-window-size":16698336,"throughput-bits":870224922.472508,"throughput-bytes":108789760}],"summary":{"end":40.000194,"start":39.000087,"omitted":false,"retransmits":0,"throughput-bits":870224922.472508,"throughput-bytes":108789760}},{"streams":[{"end":41.000082,"rtt":77087,"start":40.000194,"omitted":false,"stream-id":5,"retransmits":0,"tcp-window-size":16698336,"throughput-bits":859928629.5363914,"throughput-bytes":107479040}],"summary":{"end":41.000082,"start":40.000194,"omitted":false,"retransmits":0,"throughput-bits":859928629.5363914,"throughput-bytes":107479040}},{"streams":[{"end":42.00008,"rtt":77088,"start":41.000082,"omitted":false,"stream-id":5,"retransmits":0,"tcp-window-size":16698336,"throughput-bits":870319843.7535744,"throughput-bytes":108789760}],"summary":{"end":42.00008,"start":41.000082,"omitted":false,"retransmits":0,"throughput-bits":870319843.7535744,"throughput-bytes":108789760}},{"streams":[{"end":43.000096,"rtt":77090,"start":42.00008,"omitted":false,"stream-id":5,"retransmits":0,"tcp-window-size":16698336,"throughput-bits":859818585.2194,"throughput-bytes":107479040}],"summary":{"end":43.000096,"start":42.00008,"omitted":false,"retransmits":0,"throughput-bits":859818585.2194,"throughput-bytes":107479040}},{"streams":[{"end":44.000061,"rtt":77094,"start":43.000096,"omitted":false,"stream-id":5,"retransmits":0,"tcp-window-size":16698336,"throughput-bits":870348531.6904415,"throughput-bytes":108789760}],"summary":{"end":44.000061,"start":43.000096,"omitted":false,"retransmits":0,"throughput-bits":870348531.6904415,"throughput-bytes":108789760}},{"streams":[{"end":45.000064,"rtt":77085,"start":44.000061,"omitted":false,"stream-id":5,"retransmits":0,"tcp-window-size":16698336,"throughput-bits":859829757.5076368,"throughput-bytes":107479040}],"summary":{"end":45.000064,"start":44.000061,"omitted":false,"retransmits":0,"throughput-bits":859829757.5076368,"throughput-bytes":107479040}},{"streams":[{"end":46.000066,"rtt":77086,"start":45.000064,"omitted":false,"stream-id":5,"retransmits":0,"tcp-window-size":16698336,"throughput-bits":870316316.2535744,"throughput-bytes":108789760}],"summary":{"end":46.000066,"start":45.000064,"omitted":false,"retransmits":0,"throughput-bits":870316316.2535744,"throughput-bytes":108789760}},{"streams":[{"end":47.000068,"rtt":77084,"start":46.000066,"omitted":false,"stream-id":5,"retransmits":0,"tcp-window-size":16698336,"throughput-bits":859830577.5035312,"throughput-bytes":107479040}],"summary":{"end":47.000068,"start":46.000066,"omitted":false,"retransmits":0,"throughput-bits":859830577.5035312,"throughput-bytes":107479040}},{"streams":[{"end":48.000062,"rtt":77087,"start":47.000068,"omitted":false,"stream-id":5,"retransmits":0,"tcp-window-size":16698336,"throughput-bits":870323319.4065416,"throughput-bytes":108789760}],"summary":{"end":48.000062,"start":47.000068,"omitted":false,"retransmits":0,"throughput-bits":870323319.4065416,"throughput-bytes":108789760}},{"streams":[{"end":49.000086,"rtt":77090,"start":48.000062,"omitted":false,"stream-id":5,"retransmits":0,"tcp-window-size":16698336,"throughput-bits":859811717.993646,"throughput-bytes":107479040}],"summary":{"end":49.000086,"start":48.000062,"omitted":false,"retransmits":0,"throughput-bits":859811717.993646,"throughput-bytes":107479040}},{"streams":[{"end":50.000067,"rtt":77088,"start":49.000086,"omitted":false,"stream-id":5,"retransmits":0,"tcp-window-size":16698336,"throughput-bits":870334628.43965,"throughput-bytes":108789760}],"summary":{"end":50.000067,"start":49.000086,"omitted":false,"retransmits":0,"throughput-bits":870334628.43965,"throughput-bytes":108789760}},{"streams":[{"end":51.000069,"rtt":77086,"start":50.000067,"omitted":false,"stream-id":5,"retransmits":0,"tcp-window-size":16698336,"throughput-bits":859830577.5035312,"throughput-bytes":107479040}],"summary":{"end":51.000069,"start":50.000067,"omitted":false,"retransmits":0,"throughput-bits":859830577.5035312,"throughput-bytes":107479040}},{"streams":[{"end":52.000066,"rtt":77085,"start":51.000069,"omitted":false,"stream-id":5,"retransmits":0,"tcp-window-size":16698336,"throughput-bits":870320673.75773,"throughput-bytes":108789760}],"summary":{"end":52.000066,"start":51.000069,"omitted":false,"retransmits":0,"throughput-bits":870320673.75773,"throughput-bytes":108789760}},{"streams":[{"end":53.000063,"rtt":77089,"start":52.000066,"omitted":false,"stream-id":5,"retransmits":0,"tcp-window-size":16698336,"throughput-bits":870320673.75773,"throughput-bytes":108789760}],"summary":{"end":53.000063,"start":52.000066,"omitted":false,"retransmits":0,"throughput-bits":870320673.75773,"throughput-bytes":108789760}},{"streams":[{"end":54.000064,"rtt":77082,"start":53.000063,"omitted":false,"stream-id":5,"retransmits":0,"tcp-window-size":16698336,"throughput-bits":859831500.000782,"throughput-bytes":107479040}],"summary":{"end":54.000064,"start":53.000063,"omitted":false,"retransmits":0,"throughput-bits":859831500.000782,"throughput-bytes":107479040}},{"streams":[{"end":55.000064,"rtt":77087,"start":54.000064,"omitted":false,"stream-id":5,"retransmits":0,"tcp-window-size":16698336,"throughput-bits":870318080,"throughput-bytes":108789760}],"summary":{"end":55.000064,"start":54.000064,"omitted":false,"retransmits":0,"throughput-bits":870318080,"throughput-bytes":108789760}},{"streams":[{"end":56.000128,"rtt":77086,"start":55.000064,"omitted":false,"stream-id":5,"retransmits":0,"tcp-window-size":16698336,"throughput-bits":859777281.0233414,"throughput-bytes":107479040}],"summary":{"end":56.000128,"start":55.000064,"omitted":false,"retransmits":0,"throughput-bits":859777281.0233414,"throughput-bytes":107479040}},{"streams":[{"end":57.000072,"rtt":77087,"start":56.000128,"omitted":false,"stream-id":5,"retransmits":0,"tcp-window-size":16698336,"throughput-bits":870366845.2322363,"throughput-bytes":108789760}],"summary":{"end":57.000072,"start":56.000128,"omitted":false,"retransmits":0,"throughput-bits":870366845.2322363,"throughput-bytes":108789760}},{"streams":[{"end":58.000083,"rtt":77088,"start":57.000072,"omitted":false,"stream-id":5,"retransmits":0,"tcp-window-size":16698336,"throughput-bits":859822890.10342,"throughput-bytes":107479040}],"summary":{"end":58.000083,"start":57.000072,"omitted":false,"retransmits":0,"throughput-bits":859822890.10342,"throughput-bytes":107479040}},{"streams":[{"end":59.000065,"rtt":77088,"start":58.000083,"omitted":false,"stream-id":5,"retransmits":0,"tcp-window-size":16698336,"throughput-bits":870333746.532007,"throughput-bytes":108789760}],"summary":{"end":59.000065,"start":58.000083,"omitted":false,"retransmits":0,"throughput-bits":870333746.532007,"throughput-bytes":108789760}},{"streams":[{"end":60.000073,"rtt":77084,"start":59.000065,"omitted":false,"stream-id":5,"retransmits":0,"tcp-window-size":16698336,"throughput-bits":859825452.5548505,"throughput-bytes":107479040}],"summary":{"end":60.000073,"start":59.000065,"omitted":false,"retransmits":0,"throughput-bits":859825452.5548505,"throughput-bytes":107479040}}],"succeeded":true}
