{"diags":"Participant 0:\n/usr/bin/iperf3 -p 5201 -B 172.16.0.2 -c 172.16.0.1 -t 60 --json --rsa-public-key-path /var/run/pscheduler-server/runner/tmp/tmp954na__6/tmpdphrxc72/public-key --username ZAUFkyTxqiUI4euoVdhY\n\n{\n    \"end\": {\n        \"cpu_utilization_percent\": {\n            \"host_system\": 0.0536513748767945, \n            \"host_total\": 0.0664677409586635, \n            \"host_user\": 0.012814702266981061, \n            \"remote_system\": 0.46974617320752765, \n            \"remote_total\": 0.568124829133167, \n            \"remote_user\": 0.09839031492728963\n        }, \n        \"receiver_tcp_congestion\": \"htcp\", \n        \"sender_tcp_congestion\": \"htcp\", \n        \"streams\": [\n            {\n                \"receiver\": {\n                    \"bits_per_second\": 2734376.4144364535, \n                    \"bytes\": 20521280, \n                    \"end\": 60.039371, \n                    \"seconds\": 60.001061, \n                    \"sender\": true, \n                    \"socket\": 5, \n                    \"start\": 0\n                }, \n                \"sender\": {\n                    \"bits_per_second\": 2816213.6666216617, \n                    \"bytes\": 21121976, \n                    \"end\": 60.001061, \n                    \"max_rtt\": 140717, \n                    \"max_snd_cwnd\": 111496, \n                    \"max_snd_wnd\": 0, \n                    \"mean_rtt\": 48718, \n                    \"min_rtt\": 17623, \n                    \"retransmits\": 618, \n                    \"seconds\": 60.001061, \n                    \"sender\": true, \n                    \"socket\": 5, \n                    \"start\": 0\n                }\n            }\n        ], \n        \"sum_received\": {\n            \"bits_per_second\": 2734376.4144364535, \n            \"bytes\": 20521280, \n            \"end\": 60.039371, \n            \"seconds\": 60.039371, \n            \"sender\": true, \n            \"start\": 0\n        }, \n        \"sum_sent\": {\n            \"bits_per_second\": 2816213.6666216617, \n            \"bytes\": 21121976, \n            \"end\": 60.001061, \n            \"retransmits\": 618, \n            \"seconds\": 60.001061, \n            \"sender\": true, \n            \"start\": 0\n        }\n    }, \n    \"intervals\": [\n        {\n            \"streams\": [\n                {\n                    \"bits_per_second\": 2962615.4121132283, \n                    \"bytes\": 370688, \n                    \"end\": 1.000975, \n                    \"omitted\": false, \n                    \"pmtu\": 1500, \n                    \"retransmits\": 42, \n                    \"rtt\": 25681, \n                    \"rttvar\": 7863, \n                    \"seconds\": 1.0009750127792358, \n                    \"sender\": true, \n                    \"snd_cwnd\": 30408, \n                    \"snd_wnd\": -1, \n                    \"socket\": 5, \n                    \"start\": 0\n                }\n            ], \n            \"sum\": {\n                \"bits_per_second\": 2962615.4121132283, \n                \"bytes\": 370688, \n                \"end\": 1.000975, \n                \"omitted\": false, \n                \"retransmits\": 42, \n                \"seconds\": 1.0009750127792358, \n                \"sender\": true, \n                \"start\": 0\n            }\n        }, \n        {\n            \"streams\": [\n                {\n                    \"bits_per_second\": 0, \n                    \"bytes\": 0, \n                    \"end\": 2.001061, \n                    \"omitted\": false, \n                    \"pmtu\": 1500, \n                    \"retransmits\": 10, \n                    \"rtt\": 40597, \n                    \"rttvar\": 2806, \n                    \"seconds\": 1.0000859498977661, \n                    \"sender\": true, \n                    \"snd_cwnd\": 1448, \n                    \"snd_wnd\": -1, \n                    \"socket\": 5, \n                    \"start\": 1.000975\n                }\n            ], \n            \"sum\": {\n                \"bits_per_second\": 0, \n                \"bytes\": 0, \n                \"end\": 2.001061, \n                \"omitted\": false, \n                \"retransmits\": 10, \n                \"seconds\": 1.0000859498977661, \n                \"sender\": true, \n                \"start\": 1.000975\n            }\n        }, \n        {\n            \"streams\": [\n                {\n                    \"bits_per_second\": 2852453.6797643644, \n                    \"bytes\": 356208, \n                    \"end\": 3.000083, \n                    \"omitted\": false, \n                    \"pmtu\": 1500, \n                    \"retransmits\": 23, \n                    \"rtt\": 25368, \n                    \"rttvar\": 5899, \n                    \"seconds\": 0.9990220069885254, \n                    \"sender\": true, \n                    \"snd_cwnd\": 26064, \n                    \"snd_wnd\": -1, \n                    \"socket\": 5, \n                    \"start\": 2.001061\n                }\n            ], \n            \"sum\": {\n                \"bits_per_second\": 2852453.6797643644, \n                \"bytes\": 356208, \n                \"end\": 3.000083, \n                \"omitted\": false, \n                \"retransmits\": 23, \n                \"seconds\": 0.9990220069885254, \n                \"sender\": true, \n                \"start\": 2.001061\n            }\n        }, \n        {\n            \"streams\": [\n                {\n                    \"bits_per_second\": 0, \n                    \"bytes\": 0, \n                    \"end\": 4.001038, \n                    \"omitted\": false, \n                    \"pmtu\": 1500, \n                    \"retransmits\": 20, \n                    \"rtt\": 30970, \n                    \"rttvar\": 14619, \n                    \"seconds\": 1.0009549856185913, \n                    \"sender\": true, \n                    \"snd_cwnd\": 15928, \n                    \"snd_wnd\": -1, \n                    \"socket\": 5, \n                    \"start\": 3.000083\n                }\n            ], \n            \"sum\": {\n                \"bits_per_second\": 0, \n                \"bytes\": 0, \n                \"end\": 4.001038, \n                \"omitted\": false, \n                \"retransmits\": 20, \n                \"seconds\": 1.0009549856185913, \n                \"sender\": true, \n                \"start\": 3.000083\n            }\n        }, \n        {\n            \"streams\": [\n                {\n                    \"bits_per_second\": 6261088.839324264, \n                    \"bytes\": 781920, \n                    \"end\": 5.000123, \n                    \"omitted\": false, \n                    \"pmtu\": 1500, \n                    \"retransmits\": 12, \n                    \"rtt\": 20809, \n                    \"rttvar\": 894, \n                    \"seconds\": 0.999085009098053, \n                    \"sender\": true, \n                    \"snd_cwnd\": 41992, \n                    \"snd_wnd\": -1, \n                    \"socket\": 5, \n                    \"start\": 4.001038\n                }\n            ], \n            \"sum\": {\n                \"bits_per_second\": 6261088.839324264, \n                \"bytes\": 781920, \n                \"end\": 5.000123, \n                \"omitted\": false, \n                \"retransmits\": 12, \n                \"seconds\": 0.999085009098053, \n                \"sender\": true, \n                \"start\": 4.001038\n            }\n        }, \n        {\n            \"streams\": [\n                {\n                    \"bits_per_second\": 15638290.010462925, \n                    \"bytes\": 1954800, \n                    \"end\": 6.00013, \n                    \"omitted\": false, \n                    \"pmtu\": 1500, \n                    \"retransmits\": 0, \n                    \"rtt\": 39977, \n                    \"rttvar\": 713, \n                    \"seconds\": 1.0000070333480835, \n                    \"sender\": true, \n                    \"snd_cwnd\": 85432, \n                    \"snd_wnd\": -1, \n                    \"socket\": 5, \n                    \"start\": 5.000123\n                }\n            ], \n            \"sum\": {\n                \"bits_per_second\": 15638290.010462925, \n                \"bytes\": 1954800, \n                \"end\": 6.00013, \n                \"omitted\": false, \n                \"retransmits\": 0, \n                \"seconds\": 1.0000070333480835, \n                \"sender\": true, \n                \"start\": 5.000123\n            }\n        }, \n        {\n            \"streams\": [\n                {\n                    \"bits_per_second\": 11988421.029487368, \n                    \"bytes\": 1498680, \n                    \"end\": 7.000215, \n                    \"omitted\": false, \n                    \"pmtu\": 1500, \n                    \"retransmits\": 1, \n                    \"rtt\": 49279, \n                    \"rttvar\": 684, \n                    \"seconds\": 1.00008499622345, \n                    \"sender\": true, \n                    \"snd_cwnd\": 1448, \n                    \"snd_wnd\": -1, \n                    \"socket\": 5, \n                    \"start\": 6.00013\n                }\n            ], \n            \"sum\": {\n                \"bits_per_second\": 11988421.029487368, \n                \"bytes\": 1498680, \n                \"end\": 7.000215, \n                \"omitted\": false, \n                \"retransmits\": 1, \n                \"seconds\": 1.00008499622345, \n                \"sender\": true, \n                \"start\": 6.00013\n            }\n        }, \n        {\n            \"streams\": [\n                {\n                    \"bits_per_second\": 0, \n                    \"bytes\": 0, \n                    \"end\": 8.001058, \n                    \"omitted\": false, \n                    \"pmtu\": 1500, \n                    \"retransmits\": 1, \n                    \"rtt\": 49279, \n                    \"rttvar\": 684, \n                    \"seconds\": 1.0008430480957031, \n                    \"sender\": true, \n                    \"snd_cwnd\": 1448, \n                    \"snd_wnd\": -1, \n                    \"socket\": 5, \n                    \"start\": 7.000215\n                }\n            ], \n            \"sum\": {\n                \"bits_per_second\": 0, \n                \"bytes\": 0, \n                \"end\": 8.001058, \n                \"omitted\": false, \n                \"retransmits\": 1, \n                \"seconds\": 1.0008430480957031, \n                \"sender\": true, \n                \"start\": 7.000215\n            }\n        }, \n        {\n            \"streams\": [\n                {\n                    \"bits_per_second\": 0, \n                    \"bytes\": 0, \n                    \"end\": 9.001055, \n                    \"omitted\": false, \n                    \"pmtu\": 1500, \n                    \"retransmits\": 1, \n                    \"rtt\": 49279, \n                    \"rttvar\": 684, \n                    \"seconds\": 0.9999970197677612, \n                    \"sender\": true, \n                    \"snd_cwnd\": 1448, \n                    \"snd_wnd\": -1, \n                    \"socket\": 5, \n                    \"start\": 8.001058\n                }\n            ], \n            \"sum\": {\n                \"bits_per_second\": 0, \n                \"bytes\": 0, \n                \"end\": 9.001055, \n                \"omitted\": false, \n                \"retransmits\": 1, \n                \"seconds\": 0.9999970197677612, \n                \"sender\": true, \n                \"start\": 8.001058\n            }\n        }, \n        {\n            \"streams\": [\n                {\n                    \"bits_per_second\": 0, \n                    \"bytes\": 0, \n                    \"end\": 10.001058, \n                    \"omitted\": false, \n                    \"pmtu\": 1500, \n                    \"retransmits\": 0, \n                    \"rtt\": 49279, \n                    \"rttvar\": 684, \n                    \"seconds\": 1.0000029802322388, \n                    \"sender\": true, \n                    \"snd_cwnd\": 1448, \n                    \"snd_wnd\": -1, \n                    \"socket\": 5, \n                    \"start\": 9.001055\n                }\n            ], \n            \"sum\": {\n                \"bits_per_second\": 0, \n                \"bytes\": 0, \n                \"end\": 10.001058, \n                \"omitted\": false, \n                \"retransmits\": 0, \n                \"seconds\": 1.0000029802322388, \n                \"sender\": true, \n                \"start\": 9.001055\n            }\n        }, \n        {\n            \"streams\": [\n                {\n                    \"bits_per_second\": 0, \n                    \"bytes\": 0, \n                    \"end\": 11.001056, \n                    \"omitted\": false, \n                    \"pmtu\": 1500, \n                    \"retransmits\": 20, \n                    \"rtt\": 35533, \n                    \"rttvar\": 2422, \n                    \"seconds\": 0.9999979734420776, \n                    \"sender\": true, \n                    \"snd_cwnd\": 1448, \n                    \"snd_wnd\": -1, \n                    \"socket\": 5, \n                    \"start\": 10.001058\n                }\n            ], \n            \"sum\": {\n                \"bits_per_second\": 0, \n                \"bytes\": 0, \n                \"end\": 11.001056, \n                \"omitted\": false, \n                \"retransmits\": 20, \n                \"seconds\": 0.9999979734420776, \n                \"sender\": true, \n                \"start\": 10.001058\n            }\n        }, \n        {\n            \"streams\": [\n                {\n                    \"bits_per_second\": 0, \n                    \"bytes\": 0, \n                    \"end\": 12.001064, \n                    \"omitted\": false, \n                    \"pmtu\": 1500, \n                    \"retransmits\": 13, \n                    \"rtt\": 33813, \n                    \"rttvar\": 7201, \n                    \"seconds\": 1.0000079870224, \n                    \"sender\": true, \n                    \"snd_cwnd\": 1448, \n                    \"snd_wnd\": -1, \n                    \"socket\": 5, \n                    \"start\": 11.001056\n                }\n            ], \n            \"sum\": {\n                \"bits_per_second\": 0, \n                \"bytes\": 0, \n                \"end\": 12.001064, \n                \"omitted\": false, \n                \"retransmits\": 13, \n                \"seconds\": 1.0000079870224, \n                \"sender\": true, \n                \"start\": 11.001056\n            }\n        }, \n        {\n            \"streams\": [\n                {\n                    \"bits_per_second\": 0, \n                    \"bytes\": 0, \n                    \"end\": 13.001057, \n                    \"omitted\": false, \n                    \"pmtu\": 1500, \n                    \"retransmits\": 38, \n                    \"rtt\": 25834, \n                    \"rttvar\": 8007, \n                    \"seconds\": 0.9999930262565613, \n                    \"sender\": true, \n                    \"snd_cwnd\": 10136, \n                    \"snd_wnd\": -1, \n                    \"socket\": 5, \n                    \"start\": 12.001064\n                }\n            ], \n            \"sum\": {\n                \"bits_per_second\": 0, \n                \"bytes\": 0, \n                \"end\": 13.001057, \n                \"omitted\": false, \n                \"retransmits\": 38, \n                \"seconds\": 0.9999930262565613, \n                \"sender\": true, \n                \"start\": 12.001064\n            }\n        }, \n        {\n            \"streams\": [\n                {\n                    \"bits_per_second\": 0, \n                    \"bytes\": 0, \n                    \"end\": 14.000154, \n                    \"omitted\": false, \n                    \"pmtu\": 1500, \n                    \"retransmits\": 14, \n                    \"rtt\": 26313, \n                    \"rttvar\": 4231, \n                    \"seconds\": 0.9990969896316528, \n                    \"sender\": true, \n                    \"snd_cwnd\": 14480, \n                    \"snd_wnd\": -1, \n                    \"socket\": 5, \n                    \"start\": 13.001057\n                }\n            ], \n            \"sum\": {\n                \"bits_per_second\": 0, \n                \"bytes\": 0, \n                \"end\": 14.000154, \n                \"omitted\": false, \n                \"retransmits\": 14, \n                \"seconds\": 0.9990969896316528, \n                \"sender\": true, \n                \"start\": 13.001057\n            }\n        }, \n        {\n            \"streams\": [\n                {\n                    \"bits_per_second\": 0, \n                    \"bytes\": 0, \n                    \"end\": 15.001034, \n                    \"omitted\": false, \n                    \"pmtu\": 1500, \n                    \"retransmits\": 1, \n                    \"rtt\": 26313, \n                    \"rttvar\": 4231, \n                    \"seconds\": 1.0008800029754639, \n                    \"sender\": true, \n                    \"snd_cwnd\": 1448, \n                    \"snd_wnd\": -1, \n                    \"socket\": 5, \n                    \"start\": 14.000154\n                }\n            ], \n            \"sum\": {\n                \"bits_per_second\": 0, \n                \"bytes\": 0, \n                \"end\": 15.001034, \n                \"omitted\": false, \n                \"retransmits\": 1, \n                \"seconds\": 1.0008800029754639, \n                \"sender\": true, \n                \"start\": 14.000154\n            }\n        }, \n        {\n            \"streams\": [\n                {\n                    \"bits_per_second\": 0, \n                    \"bytes\": 0, \n                    \"end\": 16.001061, \n                    \"omitted\": false, \n                    \"pmtu\": 1500, \n                    \"retransmits\": 0, \n                    \"rtt\": 26313, \n                    \"rttvar\": 4231, \n                    \"seconds\": 1.0000269412994385, \n                    \"sender\": true, \n                    \"snd_cwnd\": 1448, \n                    \"snd_wnd\": -1, \n                    \"socket\": 5, \n                    \"start\": 15.001034\n                }\n            ], \n            \"sum\": {\n                \"bits_per_second\": 0, \n                \"bytes\": 0, \n                \"end\": 16.001061, \n                \"omitted\": false, \n                \"retransmits\": 0, \n                \"seconds\": 1.0000269412994385, \n                \"sender\": true, \n                \"start\": 15.001034\n            }\n        }, \n        {\n            \"streams\": [\n                {\n                    \"bits_per_second\": 0, \n                    \"bytes\": 0, \n                    \"end\": 17.001058, \n                    \"omitted\": false, \n                    \"pmtu\": 1500, \n                    \"retransmits\": 0, \n                    \"rtt\": 26313, \n                    \"rttvar\": 4231, \n                    \"seconds\": 0.9999970197677612, \n                    \"sender\": true, \n                    \"snd_cwnd\": 1448, \n                    \"snd_wnd\": -1, \n                    \"socket\": 5, \n                    \"start\": 16.001061\n                }\n            ], \n            \"sum\": {\n                \"bits_per_second\": 0, \n                \"bytes\": 0, \n                \"end\": 17.001058, \n                \"omitted\": false, \n                \"retransmits\": 0, \n                \"seconds\": 0.9999970197677612, \n                \"sender\": true, \n                \"start\": 16.001061\n            }\n        }, \n        {\n            \"streams\": [\n                {\n                    \"bits_per_second\": 0, \n                    \"bytes\": 0, \n                    \"end\": 18.001054, \n                    \"omitted\": false, \n                    \"pmtu\": 1500, \n                    \"retransmits\": 11, \n                    \"rtt\": 33049, \n                    \"rttvar\": 7629, \n                    \"seconds\": 0.9999960064888, \n                    \"sender\": true, \n                    \"snd_cwnd\": 7240, \n                    \"snd_wnd\": -1, \n                    \"socket\": 5, \n                    \"start\": 17.001058\n                }\n            ], \n            \"sum\": {\n                \"bits_per_second\": 0, \n                \"bytes\": 0, \n                \"end\": 18.001054, \n                \"omitted\": false, \n                \"retransmits\": 11, \n                \"seconds\": 0.9999960064888, \n                \"sender\": true, \n                \"start\": 17.001058\n            }\n        }, \n        {\n            \"streams\": [\n                {\n                    \"bits_per_second\": 0, \n                    \"bytes\": 0, \n                    \"end\": 19.00106, \n                    \"omitted\": false, \n                    \"pmtu\": 1500, \n                    \"retransmits\": 1, \n                    \"rtt\": 32837, \n                    \"rttvar\": 12227, \n                    \"seconds\": 1.0000059604644775, \n                    \"sender\": true, \n                    \"snd_cwnd\": 1448, \n                    \"snd_wnd\": -1, \n                    \"socket\": 5, \n                    \"start\": 18.001054\n                }\n            ], \n            \"sum\": {\n                \"bits_per_second\": 0, \n                \"bytes\": 0, \n                \"end\": 19.00106, \n                \"omitted\": false, \n                \"retransmits\": 1, \n                \"seconds\": 1.0000059604644775, \n                \"sender\": true, \n                \"start\": 18.001054\n            }\n        }, \n        {\n            \"streams\": [\n                {\n                    \"bits_per_second\": 0, \n                    \"bytes\": 0, \n                    \"end\": 20.001054, \n                    \"omitted\": false, \n                    \"pmtu\": 1500, \n                    \"retransmits\": 1, \n                    \"rtt\": 32837, \n                    \"rttvar\": 12227, \n                    \"seconds\": 0.9999939799308777, \n                    \"sender\": true, \n                    \"snd_cwnd\": 1448, \n                    \"snd_wnd\": -1, \n                    \"socket\": 5, \n                    \"start\": 19.00106\n                }\n            ], \n            \"sum\": {\n                \"bits_per_second\": 0, \n                \"bytes\": 0, \n                \"end\": 20.001054, \n                \"omitted\": false, \n                \"retransmits\": 1, \n                \"seconds\": 0.9999939799308777, \n                \"sender\": true, \n                \"start\": 19.00106\n            }\n        }, \n        {\n            \"streams\": [\n                {\n                    \"bits_per_second\": 0, \n                    \"bytes\": 0, \n                    \"end\": 21.001055, \n                    \"omitted\": false, \n                    \"pmtu\": 1500, \n                    \"retransmits\": 0, \n                    \"rtt\": 32837, \n                    \"rttvar\": 12227, \n                    \"seconds\": 1.0000009536743164, \n                    \"sender\": true, \n                    \"snd_cwnd\": 1448, \n                    \"snd_wnd\": -1, \n                    \"socket\": 5, \n                    \"start\": 20.001054\n                }\n            ], \n            \"sum\": {\n                \"bits_per_second\": 0, \n                \"bytes\": 0, \n                \"end\": 21.001055, \n                \"omitted\": false, \n                \"retransmits\": 0, \n                \"seconds\": 1.0000009536743164, \n                \"sender\": true, \n                \"start\": 20.001054\n            }\n        }, \n        {\n            \"streams\": [\n                {\n                    \"bits_per_second\": 0, \n                    \"bytes\": 0, \n                    \"end\": 22.001054, \n                    \"omitted\": false, \n                    \"pmtu\": 1500, \n                    \"retransmits\": 0, \n                    \"rtt\": 32837, \n                    \"rttvar\": 12227, \n                    \"seconds\": 0.9999989867210388, \n                    \"sender\": true, \n                    \"snd_cwnd\": 1448, \n                    \"snd_wnd\": -1, \n                    \"socket\": 5, \n                    \"start\": 21.001055\n                }\n            ], \n            \"sum\": {\n                \"bits_per_second\": 0, \n                \"bytes\": 0, \n                \"end\": 22.001054, \n                \"omitted\": false, \n                \"retransmits\": 0, \n                \"seconds\": 0.9999989867210388, \n                \"sender\": true, \n                \"start\": 21.001055\n            }\n        }, \n        {\n            \"streams\": [\n                {\n                    \"bits_per_second\": 4173683.2381212017, \n                    \"bytes\": 521280, \n                    \"end\": 23.000229, \n                    \"omitted\": false, \n                    \"pmtu\": 1500, \n                    \"retransmits\": 9, \n                    \"rtt\": 29215, \n                    \"rttvar\": 8239, \n                    \"seconds\": 0.9991750121116638, \n                    \"sender\": true, \n                    \"snd_cwnd\": 34752, \n                    \"snd_wnd\": -1, \n                    \"socket\": 5, \n                    \"start\": 22.001054\n                }\n            ], \n            \"sum\": {\n                \"bits_per_second\": 4173683.2381212017, \n                \"bytes\": 521280, \n                \"end\": 23.000229, \n                \"omitted\": false, \n                \"retransmits\": 9, \n                \"seconds\": 0.9991750121116638, \n                \"sender\": true, \n                \"start\": 22.001054\n            }\n        }, \n        {\n            \"streams\": [\n                {\n                    \"bits_per_second\": 6253921.881147774, \n                    \"bytes\": 781920, \n                    \"end\": 24.000459, \n                    \"omitted\": false, \n                    \"pmtu\": 1500, \n                    \"retransmits\": 3, \n                    \"rtt\": 25333, \n                    \"rttvar\": 10531, \n                    \"seconds\": 1.0002299547195435, \n                    \"sender\": true, \n                    \"snd_cwnd\": 27512, \n                    \"snd_wnd\": -1, \n                    \"socket\": 5, \n                    \"start\": 23.000229\n                }\n            ], \n            \"sum\": {\n                \"bits_per_second\": 6253921.881147774, \n                \"bytes\": 781920, \n                \"end\": 24.000459, \n                \"omitted\": false, \n                \"retransmits\": 3, \n                \"seconds\": 1.0002299547195435, \n                \"sender\": true, \n                \"start\": 23.000229\n            }\n        }, \n        {\n            \"streams\": [\n                {\n                    \"bits_per_second\": 0, \n                    \"bytes\": 0, \n                    \"end\": 25.001067, \n                    \"omitted\": false, \n                    \"pmtu\": 1500, \n                    \"retransmits\": 3, \n                    \"rtt\": 91747, \n                    \"rttvar\": 120017, \n                    \"seconds\": 1.000607967376709, \n                    \"sender\": true, \n                    \"snd_cwnd\": 2896, \n                    \"snd_wnd\": -1, \n                    \"socket\": 5, \n                    \"start\": 24.000459\n                }\n            ], \n            \"sum\": {\n                \"bits_per_second\": 0, \n                \"bytes\": 0, \n                \"end\": 25.001067, \n                \"omitted\": false, \n                \"retransmits\": 3, \n                \"seconds\": 1.000607967376709, \n                \"sender\": true, \n                \"start\": 24.000459\n            }\n        }, \n        {\n            \"streams\": [\n                {\n                    \"bits_per_second\": 12522704.38057509, \n                    \"bytes\": 1563840, \n                    \"end\": 26.00011, \n                    \"omitted\": false, \n                    \"pmtu\": 1500, \n                    \"retransmits\": 17, \n                    \"rtt\": 25375, \n                    \"rttvar\": 593, \n                    \"seconds\": 0.9990429878234863, \n                    \"sender\": true, \n                    \"snd_cwnd\": 65160, \n                    \"snd_wnd\": -1, \n                    \"socket\": 5, \n                    \"start\": 25.001067\n                }\n            ], \n            \"sum\": {\n                \"bits_per_second\": 12522704.38057509, \n                \"bytes\": 1563840, \n                \"end\": 26.00011, \n                \"omitted\": false, \n                \"retransmits\": 17, \n                \"seconds\": 0.9990429878234863, \n                \"sender\": true, \n                \"start\": 25.001067\n            }\n        }, \n        {\n            \"streams\": [\n                {\n                    \"bits_per_second\": 18766099.015293315, \n                    \"bytes\": 2345760, \n                    \"end\": 27.000109, \n                    \"omitted\": false, \n                    \"pmtu\": 1500, \n                    \"retransmits\": 0, \n                    \"rtt\": 41975, \n                    \"rttvar\": 237, \n                    \"seconds\": 0.9999989867210388, \n                    \"sender\": true, \n                    \"snd_cwnd\": 104256, \n                    \"snd_wnd\": -1, \n                    \"socket\": 5, \n                    \"start\": 26.00011\n                }\n            ], \n            \"sum\": {\n                \"bits_per_second\": 18766099.015293315, \n                \"bytes\": 2345760, \n                \"end\": 27.000109, \n                \"omitted\": false, \n                \"retransmits\": 0, \n                \"seconds\": 0.9999989867210388, \n                \"sender\": true, \n                \"start\": 26.00011\n            }\n        }, \n        {\n            \"streams\": [\n                {\n                    \"bits_per_second\": 10420639.74741561, \n                    \"bytes\": 1303200, \n                    \"end\": 28.000585, \n                    \"omitted\": false, \n                    \"pmtu\": 1500, \n                    \"retransmits\": 22, \n                    \"rtt\": 43211, \n                    \"rttvar\": 7307, \n                    \"seconds\": 1.0004760026931763, \n                    \"sender\": true, \n                    \"snd_cwnd\": 59368, \n                    \"snd_wnd\": -1, \n                    \"socket\": 5, \n                    \"start\": 27.000109\n                }\n            ], \n            \"sum\": {\n                \"bits_per_second\": 10420639.74741561, \n                \"bytes\": 1303200, \n                \"end\": 28.000585, \n                \"omitted\": false, \n                \"retransmits\": 22, \n                \"seconds\": 1.0004760026931763, \n                \"sender\": true, \n                \"start\": 27.000109\n            }\n        }, \n        {\n            \"streams\": [\n                {\n                    \"bits_per_second\": 0, \n                    \"bytes\": 0, \n                    \"end\": 29.001027, \n                    \"omitted\": false, \n                    \"pmtu\": 1500, \n                    \"retransmits\": 1, \n                    \"rtt\": 43211, \n                    \"rttvar\": 7307, \n                    \"seconds\": 1.0004420280456543, \n                    \"sender\": true, \n                    \"snd_cwnd\": 1448, \n                    \"snd_wnd\": -1, \n                    \"socket\": 5, \n                    \"start\": 28.000585\n                }\n            ], \n            \"sum\": {\n                \"bits_per_second\": 0, \n                \"bytes\": 0, \n                \"end\": 29.001027, \n                \"omitted\": false, \n                \"retransmits\": 1, \n                \"seconds\": 1.0004420280456543, \n                \"sender\": true, \n                \"start\": 28.000585\n            }\n        }, \n        {\n            \"streams\": [\n                {\n                    \"bits_per_second\": 0, \n                    \"bytes\": 0, \n                    \"end\": 30.000926, \n                    \"omitted\": false, \n                    \"pmtu\": 1500, \n                    \"retransmits\": 1, \n                    \"rtt\": 43211, \n                    \"rttvar\": 7307, \n                    \"seconds\": 0.9998990297317505, \n                    \"sender\": true, \n                    \"snd_cwnd\": 1448, \n                    \"snd_wnd\": -1, \n                    \"socket\": 5, \n                    \"start\": 29.001027\n                }\n            ], \n            \"sum\": {\n                \"bits_per_second\": 0, \n                \"bytes\": 0, \n                \"end\": 30.000926, \n                \"omitted\": false, \n                \"retransmits\": 1, \n                \"seconds\": 0.9998990297317505, \n                \"sender\": true, \n                \"start\": 29.001027\n            }\n        }, \n        {\n            \"streams\": [\n                {\n                    \"bits_per_second\": 0, \n                    \"bytes\": 0, \n                    \"end\": 31.001024, \n                    \"omitted\": false, \n                    \"pmtu\": 1500, \n                    \"retransmits\": 0, \n                    \"rtt\": 43211, \n                    \"rttvar\": 7307, \n                    \"seconds\": 1.0000979900360107, \n                    \"sender\": true, \n                    \"snd_cwnd\": 1448, \n                    \"snd_wnd\": -1, \n                    \"socket\": 5, \n                    \"start\": 30.000926\n                }\n            ], \n            \"sum\": {\n                \"bits_per_second\": 0, \n                \"bytes\": 0, \n                \"end\": 31.001024, \n                \"omitted\": false, \n                \"retransmits\": 0, \n                \"seconds\": 1.0000979900360107, \n                \"sender\": true, \n                \"start\": 30.000926\n            }\n        }, \n        {\n            \"streams\": [\n                {\n                    \"bits_per_second\": 2086856.30876625, \n                    \"bytes\": 260640, \n                    \"end\": 32.000192, \n                    \"omitted\": false, \n                    \"pmtu\": 1500, \n                    \"retransmits\": 41, \n                    \"rtt\": 27917, \n                    \"rttvar\": 8656, \n                    \"seconds\": 0.9991679787635803, \n                    \"sender\": true, \n                    \"snd_cwnd\": 33304, \n                    \"snd_wnd\": -1, \n                    \"socket\": 5, \n                    \"start\": 31.001024\n                }\n            ], \n            \"sum\": {\n                \"bits_per_second\": 2086856.30876625, \n                \"bytes\": 260640, \n                \"end\": 32.000192, \n                \"omitted\": false, \n                \"retransmits\": 41, \n                \"seconds\": 0.9991679787635803, \n                \"sender\": true, \n                \"start\": 31.001024\n            }\n        }, \n        {\n            \"streams\": [\n                {\n                    \"bits_per_second\": 8341230.735903455, \n                    \"bytes\": 1042560, \n                    \"end\": 33.000102, \n                    \"omitted\": false, \n                    \"pmtu\": 1500, \n                    \"retransmits\": 32, \n                    \"rtt\": 17623, \n                    \"rttvar\": 1160, \n                    \"seconds\": 0.999909996986389, \n                    \"sender\": true, \n                    \"snd_cwnd\": 46336, \n                    \"snd_wnd\": -1, \n                    \"socket\": 5, \n                    \"start\": 32.000192\n                }\n            ], \n            \"sum\": {\n                \"bits_per_second\": 8341230.735903455, \n                \"bytes\": 1042560, \n                \"end\": 33.000102, \n                \"omitted\": false, \n                \"retransmits\": 32, \n                \"seconds\": 0.999909996986389, \n                \"sender\": true, \n                \"start\": 32.000192\n            }\n        }, \n        {\n            \"streams\": [\n                {\n                    \"bits_per_second\": 8335845.335625963, \n                    \"bytes\": 1042560, \n                    \"end\": 34.000658, \n                    \"omitted\": false, \n                    \"pmtu\": 1500, \n                    \"retransmits\": 1, \n                    \"rtt\": 28327, \n                    \"rttvar\": 928, \n                    \"seconds\": 1.0005559921264648, \n                    \"sender\": true, \n                    \"snd_cwnd\": 1448, \n                    \"snd_wnd\": -1, \n                    \"socket\": 5, \n                    \"start\": 33.000102\n                }\n            ], \n            \"sum\": {\n                \"bits_per_second\": 8335845.335625963, \n                \"bytes\": 1042560, \n                \"end\": 34.000658, \n                \"omitted\": false, \n                \"retransmits\": 1, \n                \"seconds\": 1.0005559921264648, \n                \"sender\": true, \n                \"start\": 33.000102\n            }\n        }, \n        {\n            \"streams\": [\n                {\n                    \"bits_per_second\": 0, \n                    \"bytes\": 0, \n                    \"end\": 35.001024, \n                    \"omitted\": false, \n                    \"pmtu\": 1500, \n                    \"retransmits\": 1, \n                    \"rtt\": 28327, \n                    \"rttvar\": 928, \n                    \"seconds\": 1.000365972518921, \n                    \"sender\": true, \n                    \"snd_cwnd\": 1448, \n                    \"snd_wnd\": -1, \n                    \"socket\": 5, \n                    \"start\": 34.000658\n                }\n            ], \n            \"sum\": {\n                \"bits_per_second\": 0, \n                \"bytes\": 0, \n                \"end\": 35.001024, \n                \"omitted\": false, \n                \"retransmits\": 1, \n                \"seconds\": 1.000365972518921, \n                \"sender\": true, \n                \"start\": 34.000658\n            }\n        }, \n        {\n            \"streams\": [\n                {\n                    \"bits_per_second\": 2086133.8950216775, \n                    \"bytes\": 260640, \n                    \"end\": 36.000538, \n                    \"omitted\": false, \n                    \"pmtu\": 1500, \n                    \"retransmits\": 48, \n                    \"rtt\": 18738, \n                    \"rttvar\": 1102, \n                    \"seconds\": 0.9995139837265015, \n                    \"sender\": true, \n                    \"snd_cwnd\": 36200, \n                    \"snd_wnd\": -1, \n                    \"socket\": 5, \n                    \"start\": 35.001024\n                }\n            ], \n            \"sum\": {\n                \"bits_per_second\": 2086133.8950216775, \n                \"bytes\": 260640, \n                \"end\": 36.000538, \n                \"omitted\": false, \n                \"retransmits\": 48, \n                \"seconds\": 0.9995139837265015, \n                \"sender\": true, \n                \"start\": 35.001024\n            }\n        }, \n        {\n            \"streams\": [\n                {\n                    \"bits_per_second\": 0, \n                    \"bytes\": 0, \n                    \"end\": 37.001023, \n                    \"omitted\": false, \n                    \"pmtu\": 1500, \n                    \"retransmits\": 0, \n                    \"rtt\": 18738, \n                    \"rttvar\": 1102, \n                    \"seconds\": 1.0004849433898926, \n                    \"sender\": true, \n                    \"snd_cwnd\": 36200, \n                    \"snd_wnd\": -1, \n                    \"socket\": 5, \n                    \"start\": 36.000538\n                }\n            ], \n            \"sum\": {\n                \"bits_per_second\": 0, \n                \"bytes\": 0, \n                \"end\": 37.001023, \n                \"omitted\": false, \n                \"retransmits\": 0, \n                \"seconds\": 1.0004849433898926, \n                \"sender\": true, \n                \"start\": 36.000538\n            }\n        }, \n        {\n            \"streams\": [\n                {\n                    \"bits_per_second\": 0, \n                    \"bytes\": 0, \n                    \"end\": 38.001025, \n                    \"omitted\": false, \n                    \"pmtu\": 1500, \n                    \"retransmits\": 0, \n                    \"rtt\": 18738, \n                    \"rttvar\": 1102, \n                    \"seconds\": 1.0000020265579224, \n                    \"sender\": true, \n                    \"snd_cwnd\": 36200, \n                    \"snd_wnd\": -1, \n                    \"socket\": 5, \n                    \"start\": 37.001023\n                }\n            ], \n            \"sum\": {\n                \"bits_per_second\": 0, \n                \"bytes\": 0, \n                \"end\": 38.001025, \n                \"omitted\": false, \n                \"retransmits\": 0, \n                \"seconds\": 1.0000020265579224, \n                \"sender\": true, \n                \"start\": 37.001023\n            }\n        }, \n        {\n            \"streams\": [\n                {\n                    \"bits_per_second\": 4173975.8057916025, \n                    \"bytes\": 521280, \n                    \"end\": 39.00013, \n                    \"omitted\": false, \n                    \"pmtu\": 1500, \n                    \"retransmits\": 25, \n                    \"rtt\": 22699, \n                    \"rttvar\": 2053, \n                    \"seconds\": 0.9991049766540527, \n                    \"sender\": true, \n                    \"snd_cwnd\": 43440, \n                    \"snd_wnd\": -1, \n                    \"socket\": 5, \n                    \"start\": 38.001025\n                }\n            ], \n            \"sum\": {\n                \"bits_per_second\": 4173975.8057916025, \n                \"bytes\": 521280, \n                \"end\": 39.00013, \n                \"omitted\": false, \n                \"retransmits\": 25, \n                \"seconds\": 0.9991049766540527, \n                \"sender\": true, \n                \"start\": 38.001025\n            }\n        }, \n        {\n            \"streams\": [\n                {\n                    \"bits_per_second\": 4170415.246164116, \n                    \"bytes\": 521280, \n                    \"end\": 40.000088, \n                    \"omitted\": false, \n                    \"pmtu\": 1500, \n                    \"retransmits\": 38, \n                    \"rtt\": 27383, \n                    \"rttvar\": 13738, \n                    \"seconds\": 0.9999579787254333, \n                    \"sender\": true, \n                    \"snd_cwnd\": 30408, \n                    \"snd_wnd\": -1, \n                    \"socket\": 5, \n                    \"start\": 39.00013\n                }\n            ], \n            \"sum\": {\n                \"bits_per_second\": 4170415.246164116, \n                \"bytes\": 521280, \n                \"end\": 40.000088, \n                \"omitted\": false, \n                \"retransmits\": 38, \n                \"seconds\": 0.9999579787254333, \n                \"sender\": true, \n                \"start\": 39.00013\n            }\n        }, \n        {\n            \"streams\": [\n                {\n                    \"bits_per_second\": 4169852.273600887, \n                    \"bytes\": 521280, \n                    \"end\": 41.000181, \n                    \"omitted\": false, \n                    \"pmtu\": 1500, \n                    \"retransmits\": 16, \n                    \"rtt\": 25255, \n                    \"rttvar\": 6699, \n                    \"seconds\": 1.0000929832458496, \n                    \"sender\": true, \n                    \"snd_cwnd\": 1448, \n                    \"snd_wnd\": -1, \n                    \"socket\": 5, \n                    \"start\": 40.000088\n                }\n            ], \n            \"sum\": {\n                \"bits_per_second\": 4169852.273600887, \n                \"bytes\": 521280, \n                \"end\": 41.000181, \n                \"omitted\": false, \n                \"retransmits\": 16, \n                \"seconds\": 1.0000929832458496, \n                \"sender\": true, \n                \"start\": 40.000088\n            }\n        }, \n        {\n            \"streams\": [\n                {\n                    \"bits_per_second\": 0, \n                    \"bytes\": 0, \n                    \"end\": 42.001138, \n                    \"omitted\": false, \n                    \"pmtu\": 1500, \n                    \"retransmits\": 1, \n                    \"rtt\": 25255, \n                    \"rttvar\": 6699, \n                    \"seconds\": 1.0009570121765137, \n                    \"sender\": true, \n                    \"snd_cwnd\": 1448, \n                    \"snd_wnd\": -1, \n                    \"socket\": 5, \n                    \"start\": 41.000181\n                }\n            ], \n            \"sum\": {\n                \"bits_per_second\": 0, \n                \"bytes\": 0, \n                \"end\": 42.001138, \n                \"omitted\": false, \n                \"retransmits\": 1, \n                \"seconds\": 1.0009570121765137, \n                \"sender\": true, \n                \"start\": 41.000181\n            }\n        }, \n        {\n            \"streams\": [\n                {\n                    \"bits_per_second\": 6257575.131444075, \n                    \"bytes\": 781920, \n                    \"end\": 43.000784, \n                    \"omitted\": false, \n                    \"pmtu\": 1500, \n                    \"retransmits\": 23, \n                    \"rtt\": 19454, \n                    \"rttvar\": 858, \n                    \"seconds\": 0.999646008014679, \n                    \"sender\": true, \n                    \"snd_cwnd\": 50680, \n                    \"snd_wnd\": -1, \n                    \"socket\": 5, \n                    \"start\": 42.001138\n                }\n            ], \n            \"sum\": {\n                \"bits_per_second\": 6257575.131444075, \n                \"bytes\": 781920, \n                \"end\": 43.000784, \n                \"omitted\": false, \n                \"retransmits\": 23, \n                \"seconds\": 0.999646008014679, \n                \"sender\": true, \n                \"start\": 42.001138\n            }\n        }, \n        {\n            \"streams\": [\n                {\n                    \"bits_per_second\": 16691358.51183687, \n                    \"bytes\": 2085120, \n                    \"end\": 44.000161, \n                    \"omitted\": false, \n                    \"pmtu\": 1500, \n                    \"retransmits\": 0, \n                    \"rtt\": 37119, \n                    \"rttvar\": 589, \n                    \"seconds\": 0.9993770122528076, \n                    \"sender\": true, \n                    \"snd_cwnd\": 92672, \n                    \"snd_wnd\": -1, \n                    \"socket\": 5, \n                    \"start\": 43.000784\n                }\n            ], \n            \"sum\": {\n                \"bits_per_second\": 16691358.51183687, \n                \"bytes\": 2085120, \n                \"end\": 44.000161, \n                \"omitted\": false, \n                \"retransmits\": 0, \n                \"seconds\": 0.9993770122528076, \n                \"sender\": true, \n                \"start\": 43.000784\n            }\n        }, \n        {\n            \"streams\": [\n                {\n                    \"bits_per_second\": 12510682.715260044, \n                    \"bytes\": 1563840, \n                    \"end\": 45.000164, \n                    \"omitted\": false, \n                    \"pmtu\": 1500, \n                    \"retransmits\": 0, \n                    \"rtt\": 59315, \n                    \"rttvar\": 5781, \n                    \"seconds\": 1.0000029802322388, \n                    \"sender\": true, \n                    \"snd_cwnd\": 111496, \n                    \"snd_wnd\": -1, \n                    \"socket\": 5, \n                    \"start\": 44.000161\n                }\n            ], \n            \"sum\": {\n                \"bits_per_second\": 12510682.715260044, \n                \"bytes\": 1563840, \n                \"end\": 45.000164, \n                \"omitted\": false, \n                \"retransmits\": 0, \n                \"seconds\": 1.0000029802322388, \n                \"sender\": true, \n                \"start\": 44.000161\n            }\n        }, \n        {\n            \"streams\": [\n                {\n                    \"bits_per_second\": 0, \n                    \"bytes\": 0, \n                    \"end\": 46.000982, \n                    \"omitted\": false, \n                    \"pmtu\": 1500, \n                    \"retransmits\": 5, \n                    \"rtt\": 140717, \n                    \"rttvar\": 107654, \n                    \"seconds\": 1.0008180141448975, \n                    \"sender\": true, \n                    \"snd_cwnd\": 1448, \n                    \"snd_wnd\": -1, \n                    \"socket\": 5, \n                    \"start\": 45.000164\n                }\n            ], \n            \"sum\": {\n                \"bits_per_second\": 0, \n                \"bytes\": 0, \n                \"end\": 46.000982, \n                \"omitted\": false, \n                \"retransmits\": 5, \n                \"seconds\": 1.0008180141448975, \n                \"sender\": true, \n                \"start\": 45.000164\n            }\n        }, \n        {\n            \"streams\": [\n                {\n                    \"bits_per_second\": 0, \n                    \"bytes\": 0, \n                    \"end\": 47.001075, \n                    \"omitted\": false, \n                    \"pmtu\": 1500, \n                    \"retransmits\": 1, \n                    \"rtt\": 140717, \n                    \"rttvar\": 107654, \n                    \"seconds\": 1.0000929832458496, \n                    \"sender\": true, \n                    \"snd_cwnd\": 1448, \n                    \"snd_wnd\": -1, \n                    \"socket\": 5, \n                    \"start\": 46.000982\n                }\n            ], \n            \"sum\": {\n                \"bits_per_second\": 0, \n                \"bytes\": 0, \n                \"end\": 47.001075, \n                \"omitted\": false, \n                \"retransmits\": 1, \n                \"seconds\": 1.0000929832458496, \n                \"sender\": true, \n                \"start\": 46.000982\n            }\n        }, \n        {\n            \"streams\": [\n                {\n                    \"bits_per_second\": 0, \n                    \"bytes\": 0, \n                    \"end\": 48.001077, \n                    \"omitted\": false, \n                    \"pmtu\": 1500, \n                    \"retransmits\": 0, \n                    \"rtt\": 140717, \n                    \"rttvar\": 107654, \n                    \"seconds\": 1.0000020265579224, \n                    \"sender\": true, \n                    \"snd_cwnd\": 1448, \n                    \"snd_wnd\": -1, \n                    \"socket\": 5, \n                    \"start\": 47.001075\n                }\n            ], \n            \"sum\": {\n                \"bits_per_second\": 0, \n                \"bytes\": 0, \n                \"end\": 48.001077, \n                \"omitted\": false, \n                \"retransmits\": 0, \n                \"seconds\": 1.0000020265579224, \n                \"sender\": true, \n                \"start\": 47.001075\n            }\n        }, \n        {\n            \"streams\": [\n                {\n                    \"bits_per_second\": 0, \n                    \"bytes\": 0, \n                    \"end\": 49.001055, \n                    \"omitted\": false, \n                    \"pmtu\": 1500, \n                    \"retransmits\": 0, \n                    \"rtt\": 140717, \n                    \"rttvar\": 107654, \n                    \"seconds\": 0.999978005886078, \n                    \"sender\": true, \n                    \"snd_cwnd\": 1448, \n                    \"snd_wnd\": -1, \n                    \"socket\": 5, \n                    \"start\": 48.001077\n                }\n            ], \n            \"sum\": {\n                \"bits_per_second\": 0, \n                \"bytes\": 0, \n                \"end\": 49.001055, \n                \"omitted\": false, \n                \"retransmits\": 0, \n                \"seconds\": 0.999978005886078, \n                \"sender\": true, \n                \"start\": 48.001077\n            }\n        }, \n        {\n            \"streams\": [\n                {\n                    \"bits_per_second\": 0, \n                    \"bytes\": 0, \n                    \"end\": 50.001072, \n                    \"omitted\": false, \n                    \"pmtu\": 1500, \n                    \"retransmits\": 1, \n                    \"rtt\": 140717, \n                    \"rttvar\": 107654, \n                    \"seconds\": 1.0000170469284058, \n                    \"sender\": true, \n                    \"snd_cwnd\": 1448, \n                    \"snd_wnd\": -1, \n                    \"socket\": 5, \n                    \"start\": 49.001055\n                }\n            ], \n            \"sum\": {\n                \"bits_per_second\": 0, \n                \"bytes\": 0, \n                \"end\": 50.001072, \n                \"omitted\": false, \n                \"retransmits\": 1, \n                \"seconds\": 1.0000170469284058, \n                \"sender\": true, \n                \"start\": 49.001055\n            }\n        }, \n        {\n            \"streams\": [\n                {\n                    \"bits_per_second\": 0, \n                    \"bytes\": 0, \n                    \"end\": 51.000215, \n                    \"omitted\": false, \n                    \"pmtu\": 1500, \n                    \"retransmits\": 0, \n                    \"rtt\": 140717, \n                    \"rttvar\": 107654, \n                    \"seconds\": 0.9991430044174194, \n                    \"sender\": true, \n                    \"snd_cwnd\": 1448, \n                    \"snd_wnd\": -1, \n                    \"socket\": 5, \n                    \"start\": 50.001072\n                }\n            ], \n            \"sum\": {\n                \"bits_per_second\": 0, \n                \"bytes\": 0, \n                \"end\": 51.000215, \n                \"omitted\": false, \n                \"retransmits\": 0, \n                \"seconds\": 0.9991430044174194, \n                \"sender\": true, \n                \"start\": 50.001072\n            }\n        }, \n        {\n            \"streams\": [\n                {\n                    \"bits_per_second\": 0, \n                    \"bytes\": 0, \n                    \"end\": 52.000652, \n                    \"omitted\": false, \n                    \"pmtu\": 1500, \n                    \"retransmits\": 0, \n                    \"rtt\": 140717, \n                    \"rttvar\": 107654, \n                    \"seconds\": 1.0004370212554932, \n                    \"sender\": true, \n                    \"snd_cwnd\": 1448, \n                    \"snd_wnd\": -1, \n                    \"socket\": 5, \n                    \"start\": 51.000215\n                }\n            ], \n            \"sum\": {\n                \"bits_per_second\": 0, \n                \"bytes\": 0, \n                \"end\": 52.000652, \n                \"omitted\": false, \n                \"retransmits\": 0, \n                \"seconds\": 1.0004370212554932, \n                \"sender\": true, \n                \"start\": 51.000215\n            }\n        }, \n        {\n            \"streams\": [\n                {\n                    \"bits_per_second\": 0, \n                    \"bytes\": 0, \n                    \"end\": 53.001092, \n                    \"omitted\": false, \n                    \"pmtu\": 1500, \n                    \"retransmits\": 0, \n                    \"rtt\": 140717, \n                    \"rttvar\": 107654, \n                    \"seconds\": 1.000440001487732, \n                    \"sender\": true, \n                    \"snd_cwnd\": 1448, \n                    \"snd_wnd\": -1, \n                    \"socket\": 5, \n                    \"start\": 52.000652\n                }\n            ], \n            \"sum\": {\n                \"bits_per_second\": 0, \n                \"bytes\": 0, \n                \"end\": 53.001092, \n                \"omitted\": false, \n                \"retransmits\": 0, \n                \"seconds\": 1.000440001487732, \n                \"sender\": true, \n                \"start\": 52.000652\n            }\n        }, \n        {\n            \"streams\": [\n                {\n                    \"bits_per_second\": 0, \n                    \"bytes\": 0, \n                    \"end\": 54.000935, \n                    \"omitted\": false, \n                    \"pmtu\": 1500, \n                    \"retransmits\": 1, \n                    \"rtt\": 127752, \n                    \"rttvar\": 106670, \n                    \"seconds\": 0.9998430013656616, \n                    \"sender\": true, \n                    \"snd_cwnd\": 2896, \n                    \"snd_wnd\": -1, \n                    \"socket\": 5, \n                    \"start\": 53.001092\n                }\n            ], \n            \"sum\": {\n                \"bits_per_second\": 0, \n                \"bytes\": 0, \n                \"end\": 54.000935, \n                \"omitted\": false, \n                \"retransmits\": 1, \n                \"seconds\": 0.9998430013656616, \n                \"sender\": true, \n                \"start\": 53.001092\n            }\n        }, \n        {\n            \"streams\": [\n                {\n                    \"bits_per_second\": 0, \n                    \"bytes\": 0, \n                    \"end\": 55.001081, \n                    \"omitted\": false, \n                    \"pmtu\": 1500, \n                    \"retransmits\": 64, \n                    \"rtt\": 22070, \n                    \"rttvar\": 5441, \n                    \"seconds\": 1.0001460313797, \n                    \"sender\": true, \n                    \"snd_cwnd\": 13032, \n                    \"snd_wnd\": -1, \n                    \"socket\": 5, \n                    \"start\": 54.000935\n                }\n            ], \n            \"sum\": {\n                \"bits_per_second\": 0, \n                \"bytes\": 0, \n                \"end\": 55.001081, \n                \"omitted\": false, \n                \"retransmits\": 64, \n                \"seconds\": 1.0001460313797, \n                \"sender\": true, \n                \"start\": 54.000935\n            }\n        }, \n        {\n            \"streams\": [\n                {\n                    \"bits_per_second\": 4174322.458191753, \n                    \"bytes\": 521280, \n                    \"end\": 56.000103, \n                    \"omitted\": false, \n                    \"pmtu\": 1500, \n                    \"retransmits\": 23, \n                    \"rtt\": 49153, \n                    \"rttvar\": 46391, \n                    \"seconds\": 0.9990220069885254, \n                    \"sender\": true, \n                    \"snd_cwnd\": 11584, \n                    \"snd_wnd\": -1, \n                    \"socket\": 5, \n                    \"start\": 55.001081\n                }\n            ], \n            \"sum\": {\n                \"bits_per_second\": 4174322.458191753, \n                \"bytes\": 521280, \n                \"end\": 56.000103, \n                \"omitted\": false, \n                \"retransmits\": 23, \n                \"seconds\": 0.9990220069885254, \n                \"sender\": true, \n                \"start\": 55.001081\n            }\n        }, \n        {\n            \"streams\": [\n                {\n                    \"bits_per_second\": 4168289.175345611, \n                    \"bytes\": 521280, \n                    \"end\": 57.000571, \n                    \"omitted\": false, \n                    \"pmtu\": 1500, \n                    \"retransmits\": 29, \n                    \"rtt\": 22926, \n                    \"rttvar\": 2411, \n                    \"seconds\": 1.0004680156707764, \n                    \"sender\": true, \n                    \"snd_cwnd\": 20272, \n                    \"snd_wnd\": -1, \n                    \"socket\": 5, \n                    \"start\": 56.000103\n                }\n            ], \n            \"sum\": {\n                \"bits_per_second\": 4168289.175345611, \n                \"bytes\": 521280, \n                \"end\": 57.000571, \n                \"omitted\": false, \n                \"retransmits\": 29, \n                \"seconds\": 1.0004680156707764, \n                \"sender\": true, \n                \"start\": 56.000103\n            }\n        }, \n        {\n            \"streams\": [\n                {\n                    \"bits_per_second\": 0, \n                    \"bytes\": 0, \n                    \"end\": 58.001079, \n                    \"omitted\": false, \n                    \"pmtu\": 1500, \n                    \"retransmits\": 2, \n                    \"rtt\": 22926, \n                    \"rttvar\": 2411, \n                    \"seconds\": 1.0005079507827759, \n                    \"sender\": true, \n                    \"snd_cwnd\": 1448, \n                    \"snd_wnd\": -1, \n                    \"socket\": 5, \n                    \"start\": 57.000571\n                }\n            ], \n            \"sum\": {\n                \"bits_per_second\": 0, \n                \"bytes\": 0, \n                \"end\": 58.001079, \n                \"omitted\": false, \n                \"retransmits\": 2, \n                \"seconds\": 1.0005079507827759, \n                \"sender\": true, \n                \"start\": 57.000571\n            }\n        }, \n        {\n            \"streams\": [\n                {\n                    \"bits_per_second\": 0, \n                    \"bytes\": 0, \n                    \"end\": 59.001048, \n                    \"omitted\": false, \n                    \"pmtu\": 1500, \n                    \"retransmits\": 1, \n                    \"rtt\": 22926, \n                    \"rttvar\": 2411, \n                    \"seconds\": 0.9999690055847168, \n                    \"sender\": true, \n                    \"snd_cwnd\": 1448, \n                    \"snd_wnd\": -1, \n                    \"socket\": 5, \n                    \"start\": 58.001079\n                }\n            ], \n            \"sum\": {\n                \"bits_per_second\": 0, \n                \"bytes\": 0, \n                \"end\": 59.001048, \n                \"omitted\": false, \n                \"retransmits\": 1, \n                \"seconds\": 0.9999690055847168, \n                \"sender\": true, \n                \"start\": 58.001079\n            }\n        }, \n        {\n            \"streams\": [\n                {\n                    \"bits_per_second\": 0, \n                    \"bytes\": 0, \n                    \"end\": 60.001061, \n                    \"omitted\": false, \n                    \"pmtu\": 1500, \n                    \"retransmits\": 0, \n                    \"rtt\": 22926, \n                    \"rttvar\": 2411, \n                    \"seconds\": 1.000012993812561, \n                    \"sender\": true, \n                    \"snd_cwnd\": 1448, \n                    \"snd_wnd\": -1, \n                    \"socket\": 5, \n                    \"start\": 59.001048\n                }\n            ], \n            \"sum\": {\n                \"bits_per_second\": 0, \n                \"bytes\": 0, \n                \"end\": 60.001061, \n                \"omitted\": false, \n                \"retransmits\": 0, \n                \"seconds\": 1.000012993812561, \n                \"sender\": true, \n                \"start\": 59.001048\n            }\n        }\n    ], \n    \"start\": {\n        \"connected\": [\n            {\n                \"local_host\": \"172.16.0.2\", \n                \"local_port\": 57947, \n                \"remote_host\": \"172.16.0.1\", \n                \"remote_port\": 5201, \n                \"socket\": 5\n            }\n        ], \n        \"connecting_to\": {\n            \"host\": \"172.16.0.1\", \n            \"port\": 5201\n        }, \n        \"cookie\": \"u4xqtzwuyxmxqnpbzqunq5njvygzizylp7ok\", \n        \"fq_rate\": 0, \n        \"rcvbuf_actual\": 87380, \n        \"sndbuf_actual\": 65536, \n        \"sock_bufsize\": 0, \n        \"system_info\": \"REDACTED\", \n        \"target_bitrate\": 0, \n        \"tcp_mss_default\": 1448, \n        \"test_start\": {\n            \"bidir\": 0, \n            \"blksize\": 131072, \n            \"blocks\": 0, \n            \"bytes\": 0, \n            \"duration\": 60, \n            \"fqrate\": 0, \n            \"num_streams\": 1, \n            \"omit\": 0, \n            \"protocol\": \"TCP\", \n            \"reverse\": 0, \n            \"target_bitrate\": 0, \n            \"tos\": 0\n        }, \n        \"timestamp\": {\n            \"time\": \"Sun, 20 Oct 2024 17:36:26 GMT\", \n            \"timesecs\": 1729445786\n        }, \n        \"version\": \"iperf 3.14\"\n    }\n}\nParticipant 1:\n/usr/bin/iperf3 --use-pkcs1-padding -s -1 --idle-timeout 60 --json -p 5201 -B 172.16.0.1 --authorized-users-path /var/pscheduler-server/runner/tmp/tmpot7bw1pz/tmp5d4syt4f/credentials --rsa-private-key-path /var/pscheduler-server/runner/tmp/tmpot7bw1pz/tmp5d4syt4f/private-key\n\n{\n    \"end\": {\n        \"cpu_utilization_percent\": {\n            \"host_system\": 0.46974617320752765, \n            \"host_total\": 0.568124829133167, \n            \"host_user\": 0.09839031492728963, \n            \"remote_system\": 0, \n            \"remote_total\": 0, \n            \"remote_user\": 0\n        }, \n        \"receiver_tcp_congestion\": \"htcp\", \n        \"streams\": [\n            {\n                \"receiver\": {\n                    \"bits_per_second\": 2734376.4144364535, \n                    \"bytes\": 20521280, \n                    \"end\": 60.039371, \n                    \"seconds\": 60.039371, \n                    \"sender\": false, \n                    \"socket\": 5, \n                    \"start\": 0\n                }, \n                \"sender\": {\n                    \"bits_per_second\": 0, \n                    \"bytes\": 0, \n                    \"end\": 60.039371, \n                    \"seconds\": 60.039371, \n                    \"sender\": false, \n                    \"socket\": 5, \n                    \"start\": 0\n                }\n            }\n        ], \n        \"sum_received\": {\n            \"bits_per_second\": 2734376.4144364535, \n            \"bytes\": 20521280, \n            \"end\": 60.039371, \n            \"seconds\": 60.039371, \n            \"sender\": false, \n            \"start\": 0\n        }, \n        \"sum_sent\": {\n            \"bits_per_second\": 0, \n            \"bytes\": 0, \n            \"end\": 60.039371, \n            \"seconds\": 60.039371, \n            \"sender\": false, \n            \"start\": 0\n        }\n    }, \n    \"intervals\": [\n        {\n            \"streams\": [\n                {\n                    \"bits_per_second\": 0, \n                    \"bytes\": 0, \n                    \"end\": 1.001096, \n                    \"omitted\": false, \n                    \"seconds\": 1.00109601020813, \n                    \"sender\": false, \n                    \"socket\": 5, \n                    \"start\": 0\n                }\n            ], \n            \"sum\": {\n                \"bits_per_second\": 0, \n                \"bytes\": 0, \n                \"end\": 1.001096, \n                \"omitted\": false, \n                \"seconds\": 1.00109601020813, \n                \"sender\": false, \n                \"start\": 0\n            }\n        }, \n        {\n            \"streams\": [\n                {\n                    \"bits_per_second\": 0, \n                    \"bytes\": 0, \n                    \"end\": 2.001122, \n                    \"omitted\": false, \n                    \"seconds\": 1.000025987625122, \n                    \"sender\": false, \n                    \"socket\": 5, \n                    \"start\": 1.001096\n                }\n            ], \n            \"sum\": {\n                \"bits_per_second\": 0, \n                \"bytes\": 0, \n                \"end\": 2.001122, \n                \"omitted\": false, \n                \"seconds\": 1.000025987625122, \n                \"sender\": false, \n                \"start\": 1.001096\n            }\n        }, \n        {\n            \"streams\": [\n                {\n                    \"bits_per_second\": 2099152.5315439017, \n                    \"bytes\": 262144, \n                    \"end\": 3.000169, \n                    \"omitted\": false, \n                    \"seconds\": 0.9990469813346863, \n                    \"sender\": false, \n                    \"socket\": 5, \n                    \"start\": 2.001122\n                }\n            ], \n            \"sum\": {\n                \"bits_per_second\": 2099152.5315439017, \n                \"bytes\": 262144, \n                \"end\": 3.000169, \n                \"omitted\": false, \n                \"seconds\": 0.9990469813346863, \n                \"sender\": false, \n                \"start\": 2.001122\n            }\n        }, \n        {\n            \"streams\": [\n                {\n                    \"bits_per_second\": 1047609.017561081, \n                    \"bytes\": 131072, \n                    \"end\": 4.001092, \n                    \"omitted\": false, \n                    \"seconds\": 1.0009230375289917, \n                    \"sender\": false, \n                    \"socket\": 5, \n                    \"start\": 3.000169\n                }\n            ], \n            \"sum\": {\n                \"bits_per_second\": 1047609.017561081, \n                \"bytes\": 131072, \n                \"end\": 4.001092, \n                \"omitted\": false, \n                \"seconds\": 1.0009230375289917, \n                \"sender\": false, \n                \"start\": 3.000169\n            }\n        }, \n        {\n            \"streams\": [\n                {\n                    \"bits_per_second\": 5242822.50063061, \n                    \"bytes\": 655360, \n                    \"end\": 5.001103, \n                    \"omitted\": false, \n                    \"seconds\": 1.0000109672546387, \n                    \"sender\": false, \n                    \"socket\": 5, \n                    \"start\": 4.001092\n                }\n            ], \n            \"sum\": {\n                \"bits_per_second\": 5242822.50063061, \n                \"bytes\": 655360, \n                \"end\": 5.001103, \n                \"omitted\": false, \n                \"seconds\": 1.0000109672546387, \n                \"sender\": false, \n                \"start\": 4.001092\n            }\n        }, \n        {\n            \"streams\": [\n                {\n                    \"bits_per_second\": 15728482.501577124, \n                    \"bytes\": 1966080, \n                    \"end\": 6.001113, \n                    \"omitted\": false, \n                    \"seconds\": 1.0000100135803223, \n                    \"sender\": false, \n                    \"socket\": 5, \n                    \"start\": 5.001103\n                }\n            ], \n            \"sum\": {\n                \"bits_per_second\": 15728482.501577124, \n                \"bytes\": 1966080, \n                \"end\": 6.001113, \n                \"omitted\": false, \n                \"seconds\": 1.0000100135803223, \n                \"sender\": false, \n                \"start\": 5.001103\n            }\n        }, \n        {\n            \"streams\": [\n                {\n                    \"bits_per_second\": 10485141.286509415, \n                    \"bytes\": 1310720, \n                    \"end\": 7.001172, \n                    \"omitted\": false, \n                    \"seconds\": 1.0000590085983276, \n                    \"sender\": false, \n                    \"socket\": 5, \n                    \"start\": 6.001113\n                }\n            ], \n            \"sum\": {\n                \"bits_per_second\": 10485141.286509415, \n                \"bytes\": 1310720, \n                \"end\": 7.001172, \n                \"omitted\": false, \n                \"seconds\": 1.0000590085983276, \n                \"sender\": false, \n                \"start\": 6.001113\n            }\n        }, \n        {\n            \"streams\": [\n                {\n                    \"bits_per_second\": 0, \n                    \"bytes\": 0, \n                    \"end\": 8.001124, \n                    \"omitted\": false, \n                    \"seconds\": 0.9999520182609558, \n                    \"sender\": false, \n                    \"socket\": 5, \n                    \"start\": 7.001172\n                }\n            ], \n            \"sum\": {\n                \"bits_per_second\": 0, \n                \"bytes\": 0, \n                \"end\": 8.001124, \n                \"omitted\": false, \n                \"seconds\": 0.9999520182609558, \n                \"sender\": false, \n                \"start\": 7.001172\n            }\n        }, \n        {\n            \"streams\": [\n                {\n                    \"bits_per_second\": 0, \n                    \"bytes\": 0, \n                    \"end\": 9.001149, \n                    \"omitted\": false, \n                    \"seconds\": 1.0000250339508057, \n                    \"sender\": false, \n                    \"socket\": 5, \n                    \"start\": 8.001124\n                }\n            ], \n            \"sum\": {\n                \"bits_per_second\": 0, \n                \"bytes\": 0, \n                \"end\": 9.001149, \n                \"omitted\": false, \n                \"seconds\": 1.0000250339508057, \n                \"sender\": false, \n                \"start\": 8.001124\n            }\n        }, \n        {\n            \"streams\": [\n                {\n                    \"bits_per_second\": 0, \n                    \"bytes\": 0, \n                    \"end\": 10.001143, \n                    \"omitted\": false, \n                    \"seconds\": 0.9999939799308777, \n                    \"sender\": false, \n                    \"socket\": 5, \n                    \"start\": 9.001149\n                }\n            ], \n            \"sum\": {\n                \"bits_per_second\": 0, \n                \"bytes\": 0, \n                \"end\": 10.001143, \n                \"omitted\": false, \n                \"seconds\": 0.9999939799308777, \n                \"sender\": false, \n                \"start\": 9.001149\n            }\n        }, \n        {\n            \"streams\": [\n                {\n                    \"bits_per_second\": 0, \n                    \"bytes\": 0, \n                    \"end\": 11.001136, \n                    \"omitted\": false, \n                    \"seconds\": 0.9999930262565613, \n                    \"sender\": false, \n                    \"socket\": 5, \n                    \"start\": 10.001143\n                }\n            ], \n            \"sum\": {\n                \"bits_per_second\": 0, \n                \"bytes\": 0, \n                \"end\": 11.001136, \n                \"omitted\": false, \n                \"seconds\": 0.9999930262565613, \n                \"sender\": false, \n                \"start\": 10.001143\n            }\n        }, \n        {\n            \"streams\": [\n                {\n                    \"bits_per_second\": 0, \n                    \"bytes\": 0, \n                    \"end\": 12.001126, \n                    \"omitted\": false, \n                    \"seconds\": 0.9999899864196777, \n                    \"sender\": false, \n                    \"socket\": 5, \n                    \"start\": 11.001136\n                }\n            ], \n            \"sum\": {\n                \"bits_per_second\": 0, \n                \"bytes\": 0, \n                \"end\": 12.001126, \n                \"omitted\": false, \n                \"seconds\": 0.9999899864196777, \n                \"sender\": false, \n                \"start\": 11.001136\n            }\n        }, \n        {\n            \"streams\": [\n                {\n                    \"bits_per_second\": 0, \n                    \"bytes\": 0, \n                    \"end\": 13.001099, \n                    \"omitted\": false, \n                    \"seconds\": 0.9999729990959167, \n                    \"sender\": false, \n                    \"socket\": 5, \n                    \"start\": 12.001126\n                }\n            ], \n            \"sum\": {\n                \"bits_per_second\": 0, \n                \"bytes\": 0, \n                \"end\": 13.001099, \n                \"omitted\": false, \n                \"seconds\": 0.9999729990959167, \n                \"sender\": false, \n                \"start\": 12.001126\n            }\n        }, \n        {\n            \"streams\": [\n                {\n                    \"bits_per_second\": 1048575.0000009537, \n                    \"bytes\": 131072, \n                    \"end\": 14.0011, \n                    \"omitted\": false, \n                    \"seconds\": 1.0000009536743164, \n                    \"sender\": false, \n                    \"socket\": 5, \n                    \"start\": 13.001099\n                }\n            ], \n            \"sum\": {\n                \"bits_per_second\": 1048575.0000009537, \n                \"bytes\": 131072, \n                \"end\": 14.0011, \n                \"omitted\": false, \n                \"seconds\": 1.0000009536743164, \n                \"sender\": false, \n                \"start\": 13.001099\n            }\n        }, \n        {\n            \"streams\": [\n                {\n                    \"bits_per_second\": 0, \n                    \"bytes\": 0, \n                    \"end\": 15.001137, \n                    \"omitted\": false, \n                    \"seconds\": 1.0000369548797607, \n                    \"sender\": false, \n                    \"socket\": 5, \n                    \"start\": 14.0011\n                }\n            ], \n            \"sum\": {\n                \"bits_per_second\": 0, \n                \"bytes\": 0, \n                \"end\": 15.001137, \n                \"omitted\": false, \n                \"seconds\": 1.0000369548797607, \n                \"sender\": false, \n                \"start\": 14.0011\n            }\n        }, \n        {\n            \"streams\": [\n                {\n                    \"bits_per_second\": 0, \n                    \"bytes\": 0, \n                    \"end\": 16.001165, \n                    \"omitted\": false, \n                    \"seconds\": 1.0000280141830444, \n                    \"sender\": false, \n                    \"socket\": 5, \n                    \"start\": 15.001137\n                }\n            ], \n            \"sum\": {\n                \"bits_per_second\": 0, \n                \"bytes\": 0, \n                \"end\": 16.001165, \n                \"omitted\": false, \n                \"seconds\": 1.0000280141830444, \n                \"sender\": false, \n                \"start\": 15.001137\n            }\n        }, \n        {\n            \"streams\": [\n                {\n                    \"bits_per_second\": 0, \n                    \"bytes\": 0, \n                    \"end\": 17.001152, \n                    \"omitted\": false, \n                    \"seconds\": 0.999987006187439, \n                    \"sender\": false, \n                    \"socket\": 5, \n                    \"start\": 16.001165\n                }\n            ], \n            \"sum\": {\n                \"bits_per_second\": 0, \n                \"bytes\": 0, \n                \"end\": 17.001152, \n                \"omitted\": false, \n                \"seconds\": 0.999987006187439, \n                \"sender\": false, \n                \"start\": 16.001165\n            }\n        }, \n        {\n            \"streams\": [\n                {\n                    \"bits_per_second\": 0, \n                    \"bytes\": 0, \n                    \"end\": 18.001101, \n                    \"omitted\": false, \n                    \"seconds\": 0.9999489784240723, \n                    \"sender\": false, \n                    \"socket\": 5, \n                    \"start\": 17.001152\n                }\n            ], \n            \"sum\": {\n                \"bits_per_second\": 0, \n                \"bytes\": 0, \n                \"end\": 18.001101, \n                \"omitted\": false, \n                \"seconds\": 0.9999489784240723, \n                \"sender\": false, \n                \"start\": 17.001152\n            }\n        }, \n        {\n            \"streams\": [\n                {\n                    \"bits_per_second\": 0, \n                    \"bytes\": 0, \n                    \"end\": 19.001121, \n                    \"omitted\": false, \n                    \"seconds\": 1.0000200271606445, \n                    \"sender\": false, \n                    \"socket\": 5, \n                    \"start\": 18.001101\n                }\n            ], \n            \"sum\": {\n                \"bits_per_second\": 0, \n                \"bytes\": 0, \n                \"end\": 19.001121, \n                \"omitted\": false, \n                \"seconds\": 1.0000200271606445, \n                \"sender\": false, \n                \"start\": 18.001101\n            }\n        }, \n        {\n            \"streams\": [\n                {\n                    \"bits_per_second\": 0, \n                    \"bytes\": 0, \n                    \"end\": 20.001123, \n                    \"omitted\": false, \n                    \"seconds\": 1.0000020265579224, \n                    \"sender\": false, \n                    \"socket\": 5, \n                    \"start\": 19.001121\n                }\n            ], \n            \"sum\": {\n                \"bits_per_second\": 0, \n                \"bytes\": 0, \n                \"end\": 20.001123, \n                \"omitted\": false, \n                \"seconds\": 1.0000020265579224, \n                \"sender\": false, \n                \"start\": 19.001121\n            }\n        }, \n        {\n            \"streams\": [\n                {\n                    \"bits_per_second\": 0, \n                    \"bytes\": 0, \n                    \"end\": 21.001118, \n                    \"omitted\": false, \n                    \"seconds\": 0.999994993209839, \n                    \"sender\": false, \n                    \"socket\": 5, \n                    \"start\": 20.001123\n                }\n            ], \n            \"sum\": {\n                \"bits_per_second\": 0, \n                \"bytes\": 0, \n                \"end\": 21.001118, \n                \"omitted\": false, \n                \"seconds\": 0.999994993209839, \n                \"sender\": false, \n                \"start\": 20.001123\n            }\n        }, \n        {\n            \"streams\": [\n                {\n                    \"bits_per_second\": 0, \n                    \"bytes\": 0, \n                    \"end\": 22.001117, \n                    \"omitted\": false, \n                    \"seconds\": 0.9999989867210388, \n                    \"sender\": false, \n                    \"socket\": 5, \n                    \"start\": 21.001118\n                }\n            ], \n            \"sum\": {\n                \"bits_per_second\": 0, \n                \"bytes\": 0, \n                \"end\": 22.001117, \n                \"omitted\": false, \n                \"seconds\": 0.9999989867210388, \n                \"sender\": false, \n                \"start\": 21.001118\n            }\n        }, \n        {\n            \"streams\": [\n                {\n                    \"bits_per_second\": 4194065.013617932, \n                    \"bytes\": 524288, \n                    \"end\": 23.001174, \n                    \"omitted\": false, \n                    \"seconds\": 1.0000569820404053, \n                    \"sender\": false, \n                    \"socket\": 5, \n                    \"start\": 22.001117\n                }\n            ], \n            \"sum\": {\n                \"bits_per_second\": 4194065.013617932, \n                \"bytes\": 524288, \n                \"end\": 23.001174, \n                \"omitted\": false, \n                \"seconds\": 1.0000569820404053, \n                \"sender\": false, \n                \"start\": 22.001117\n            }\n        }, \n        {\n            \"streams\": [\n                {\n                    \"bits_per_second\": 5248532.650383698, \n                    \"bytes\": 655360, \n                    \"end\": 24.000097, \n                    \"omitted\": false, \n                    \"seconds\": 0.9989230036735535, \n                    \"sender\": false, \n                    \"socket\": 5, \n                    \"start\": 23.001174\n                }\n            ], \n            \"sum\": {\n                \"bits_per_second\": 5248532.650383698, \n                \"bytes\": 655360, \n                \"end\": 24.000097, \n                \"omitted\": false, \n                \"seconds\": 0.9989230036735535, \n                \"sender\": false, \n                \"start\": 23.001174\n            }\n        }, \n        {\n            \"streams\": [\n                {\n                    \"bits_per_second\": 0, \n                    \"bytes\": 0, \n                    \"end\": 25.000184, \n                    \"omitted\": false, \n                    \"seconds\": 1.000087022781372, \n                    \"sender\": false, \n                    \"socket\": 5, \n                    \"start\": 24.000097\n                }\n            ], \n            \"sum\": {\n                \"bits_per_second\": 0, \n                \"bytes\": 0, \n                \"end\": 25.000184, \n                \"omitted\": false, \n                \"seconds\": 1.000087022781372, \n                \"sender\": false, \n                \"start\": 24.000097\n            }\n        }, \n        {\n            \"streams\": [\n                {\n                    \"bits_per_second\": 11534831.708803061, \n                    \"bytes\": 1441792, \n                    \"end\": 26.000141, \n                    \"omitted\": false, \n                    \"seconds\": 0.999957025051117, \n                    \"sender\": false, \n                    \"socket\": 5, \n                    \"start\": 25.000184\n                }\n            ], \n            \"sum\": {\n                \"bits_per_second\": 11534831.708803061, \n                \"bytes\": 1441792, \n                \"end\": 26.000141, \n                \"omitted\": false, \n                \"seconds\": 0.999957025051117, \n                \"sender\": false, \n                \"start\": 25.000184\n            }\n        }, \n        {\n            \"streams\": [\n                {\n                    \"bits_per_second\": 19924418.98419156, \n                    \"bytes\": 2490368, \n                    \"end\": 27.000067, \n                    \"omitted\": false, \n                    \"seconds\": 0.999925971031189, \n                    \"sender\": false, \n                    \"socket\": 5, \n                    \"start\": 26.000141\n                }\n            ], \n            \"sum\": {\n                \"bits_per_second\": 19924418.98419156, \n                \"bytes\": 2490368, \n                \"end\": 27.000067, \n                \"omitted\": false, \n                \"seconds\": 0.999925971031189, \n                \"sender\": false, \n                \"start\": 26.000141\n            }\n        }, \n        {\n            \"streams\": [\n                {\n                    \"bits_per_second\": 11533702.159832992, \n                    \"bytes\": 1441792, \n                    \"end\": 28.000122, \n                    \"omitted\": false, \n                    \"seconds\": 1.000054955482483, \n                    \"sender\": false, \n                    \"socket\": 5, \n                    \"start\": 27.000067\n                }\n            ], \n            \"sum\": {\n                \"bits_per_second\": 11533702.159832992, \n                \"bytes\": 1441792, \n                \"end\": 28.000122, \n                \"omitted\": false, \n                \"seconds\": 1.000054955482483, \n                \"sender\": false, \n                \"start\": 27.000067\n            }\n        }, \n        {\n            \"streams\": [\n                {\n                    \"bits_per_second\": 0, \n                    \"bytes\": 0, \n                    \"end\": 29.000151, \n                    \"omitted\": false, \n                    \"seconds\": 1.0000289678573608, \n                    \"sender\": false, \n                    \"socket\": 5, \n                    \"start\": 28.000122\n                }\n            ], \n            \"sum\": {\n                \"bits_per_second\": 0, \n                \"bytes\": 0, \n                \"end\": 29.000151, \n                \"omitted\": false, \n                \"seconds\": 1.0000289678573608, \n                \"sender\": false, \n                \"start\": 28.000122\n            }\n        }, \n        {\n            \"streams\": [\n                {\n                    \"bits_per_second\": 0, \n                    \"bytes\": 0, \n                    \"end\": 30.001105, \n                    \"omitted\": false, \n                    \"seconds\": 1.000954031944275, \n                    \"sender\": false, \n                    \"socket\": 5, \n                    \"start\": 29.000151\n                }\n            ], \n            \"sum\": {\n                \"bits_per_second\": 0, \n                \"bytes\": 0, \n                \"end\": 30.001105, \n                \"omitted\": false, \n                \"seconds\": 1.000954031944275, \n                \"sender\": false, \n                \"start\": 29.000151\n            }\n        }, \n        {\n            \"streams\": [\n                {\n                    \"bits_per_second\": 0, \n                    \"bytes\": 0, \n                    \"end\": 31.001131, \n                    \"omitted\": false, \n                    \"seconds\": 1.000025987625122, \n                    \"sender\": false, \n                    \"socket\": 5, \n                    \"start\": 30.001105\n                }\n            ], \n            \"sum\": {\n                \"bits_per_second\": 0, \n                \"bytes\": 0, \n                \"end\": 31.001131, \n                \"omitted\": false, \n                \"seconds\": 1.000025987625122, \n                \"sender\": false, \n                \"start\": 30.001105\n            }\n        }, \n        {\n            \"streams\": [\n                {\n                    \"bits_per_second\": 1048563.3751520049, \n                    \"bytes\": 131072, \n                    \"end\": 32.001143, \n                    \"omitted\": false, \n                    \"seconds\": 1.0000120401382446, \n                    \"sender\": false, \n                    \"socket\": 5, \n                    \"start\": 31.001131\n                }\n            ], \n            \"sum\": {\n                \"bits_per_second\": 1048563.3751520049, \n                \"bytes\": 131072, \n                \"end\": 32.001143, \n                \"omitted\": false, \n                \"seconds\": 1.0000120401382446, \n                \"sender\": false, \n                \"start\": 31.001131\n            }\n        }, \n        {\n            \"streams\": [\n                {\n                    \"bits_per_second\": 8388893.009683104, \n                    \"bytes\": 1048576, \n                    \"end\": 33.001109, \n                    \"omitted\": false, \n                    \"seconds\": 0.999966025352478, \n                    \"sender\": false, \n                    \"socket\": 5, \n                    \"start\": 32.001143\n                }\n            ], \n            \"sum\": {\n                \"bits_per_second\": 8388893.009683104, \n                \"bytes\": 1048576, \n                \"end\": 33.001109, \n                \"omitted\": false, \n                \"seconds\": 0.999966025352478, \n                \"sender\": false, \n                \"start\": 32.001143\n            }\n        }, \n        {\n            \"streams\": [\n                {\n                    \"bits_per_second\": 8388558.00029802, \n                    \"bytes\": 1048576, \n                    \"end\": 34.001115, \n                    \"omitted\": false, \n                    \"seconds\": 1.0000059604644775, \n                    \"sender\": false, \n                    \"socket\": 5, \n                    \"start\": 33.001109\n                }\n            ], \n            \"sum\": {\n                \"bits_per_second\": 8388558.00029802, \n                \"bytes\": 1048576, \n                \"end\": 34.001115, \n                \"omitted\": false, \n                \"seconds\": 1.0000059604644775, \n                \"sender\": false, \n                \"start\": 33.001109\n            }\n        }, \n        {\n            \"streams\": [\n                {\n                    \"bits_per_second\": 0, \n                    \"bytes\": 0, \n                    \"end\": 35.0011, \n                    \"omitted\": false, \n                    \"seconds\": 0.9999849796295166, \n                    \"sender\": false, \n                    \"socket\": 5, \n                    \"start\": 34.001115\n                }\n            ], \n            \"sum\": {\n                \"bits_per_second\": 0, \n                \"bytes\": 0, \n                \"end\": 35.0011, \n                \"omitted\": false, \n                \"seconds\": 0.9999849796295166, \n                \"sender\": false, \n                \"start\": 34.001115\n            }\n        }, \n        {\n            \"streams\": [\n                {\n                    \"bits_per_second\": 1048571.7500172256, \n                    \"bytes\": 131072, \n                    \"end\": 36.001104, \n                    \"omitted\": false, \n                    \"seconds\": 1.0000040531158447, \n                    \"sender\": false, \n                    \"socket\": 5, \n                    \"start\": 35.0011\n                }\n            ], \n            \"sum\": {\n                \"bits_per_second\": 1048571.7500172256, \n                \"bytes\": 131072, \n                \"end\": 36.001104, \n                \"omitted\": false, \n                \"seconds\": 1.0000040531158447, \n                \"sender\": false, \n                \"start\": 35.0011\n            }\n        }, \n        {\n            \"streams\": [\n                {\n                    \"bits_per_second\": 0, \n                    \"bytes\": 0, \n                    \"end\": 37.00113, \n                    \"omitted\": false, \n                    \"seconds\": 1.000025987625122, \n                    \"sender\": false, \n                    \"socket\": 5, \n                    \"start\": 36.001104\n                }\n            ], \n            \"sum\": {\n                \"bits_per_second\": 0, \n                \"bytes\": 0, \n                \"end\": 37.00113, \n                \"omitted\": false, \n                \"seconds\": 1.000025987625122, \n                \"sender\": false, \n                \"start\": 36.001104\n            }\n        }, \n        {\n            \"streams\": [\n                {\n                    \"bits_per_second\": 0, \n                    \"bytes\": 0, \n                    \"end\": 38.001096, \n                    \"omitted\": false, \n                    \"seconds\": 0.999966025352478, \n                    \"sender\": false, \n                    \"socket\": 5, \n                    \"start\": 37.00113\n                }\n            ], \n            \"sum\": {\n                \"bits_per_second\": 0, \n                \"bytes\": 0, \n                \"end\": 38.001096, \n                \"omitted\": false, \n                \"seconds\": 0.999966025352478, \n                \"sender\": false, \n                \"start\": 37.00113\n            }\n        }, \n        {\n            \"streams\": [\n                {\n                    \"bits_per_second\": 5242245.701748458, \n                    \"bytes\": 655360, \n                    \"end\": 39.001217, \n                    \"omitted\": false, \n                    \"seconds\": 1.000120997428894, \n                    \"sender\": false, \n                    \"socket\": 5, \n                    \"start\": 38.001096\n                }\n            ], \n            \"sum\": {\n                \"bits_per_second\": 5242245.701748458, \n                \"bytes\": 655360, \n                \"end\": 39.001217, \n                \"omitted\": false, \n                \"seconds\": 1.000120997428894, \n                \"sender\": false, \n                \"start\": 38.001096\n            }\n        }, \n        {\n            \"streams\": [\n                {\n                    \"bits_per_second\": 4194761.29985341, \n                    \"bytes\": 524288, \n                    \"end\": 40.001108, \n                    \"omitted\": false, \n                    \"seconds\": 0.9998909831047058, \n                    \"sender\": false, \n                    \"socket\": 5, \n                    \"start\": 39.001217\n                }\n            ], \n            \"sum\": {\n                \"bits_per_second\": 4194761.29985341, \n                \"bytes\": 524288, \n                \"end\": 40.001108, \n                \"omitted\": false, \n                \"seconds\": 0.9998909831047058, \n                \"sender\": false, \n                \"start\": 39.001217\n            }\n        }, \n        {\n            \"streams\": [\n                {\n                    \"bits_per_second\": 3145624.12842994, \n                    \"bytes\": 393216, \n                    \"end\": 41.001141, \n                    \"omitted\": false, \n                    \"seconds\": 1.0000330209732056, \n                    \"sender\": false, \n                    \"socket\": 5, \n                    \"start\": 40.001108\n                }\n            ], \n            \"sum\": {\n                \"bits_per_second\": 3145624.12842994, \n                \"bytes\": 393216, \n                \"end\": 41.001141, \n                \"omitted\": false, \n                \"seconds\": 1.0000330209732056, \n                \"sender\": false, \n                \"start\": 40.001108\n            }\n        }, \n        {\n            \"streams\": [\n                {\n                    \"bits_per_second\": 0, \n                    \"bytes\": 0, \n                    \"end\": 42.001134, \n                    \"omitted\": false, \n                    \"seconds\": 0.9999930262565613, \n                    \"sender\": false, \n                    \"socket\": 5, \n                    \"start\": 41.001141\n                }\n            ], \n            \"sum\": {\n                \"bits_per_second\": 0, \n                \"bytes\": 0, \n                \"end\": 42.001134, \n                \"omitted\": false, \n                \"seconds\": 0.9999930262565613, \n                \"sender\": false, \n                \"start\": 41.001141\n            }\n        }, \n        {\n            \"streams\": [\n                {\n                    \"bits_per_second\": 7340179.00294405, \n                    \"bytes\": 917504, \n                    \"end\": 43.001114, \n                    \"omitted\": false, \n                    \"seconds\": 0.9999799728393555, \n                    \"sender\": false, \n                    \"socket\": 5, \n                    \"start\": 42.001134\n                }\n            ], \n            \"sum\": {\n                \"bits_per_second\": 7340179.00294405, \n                \"bytes\": 917504, \n                \"end\": 43.001114, \n                \"omitted\": false, \n                \"seconds\": 0.9999799728393555, \n                \"sender\": false, \n                \"start\": 42.001134\n            }\n        }, \n        {\n            \"streams\": [\n                {\n                    \"bits_per_second\": 16777048.001682265, \n                    \"bytes\": 2097152, \n                    \"end\": 44.001124, \n                    \"omitted\": false, \n                    \"seconds\": 1.0000100135803223, \n                    \"sender\": false, \n                    \"socket\": 5, \n                    \"start\": 43.001114\n                }\n            ], \n            \"sum\": {\n                \"bits_per_second\": 16777048.001682265, \n                \"bytes\": 2097152, \n                \"end\": 44.001124, \n                \"omitted\": false, \n                \"seconds\": 1.0000100135803223, \n                \"sender\": false, \n                \"start\": 43.001114\n            }\n        }, \n        {\n            \"streams\": [\n                {\n                    \"bits_per_second\": 11539505.565906128, \n                    \"bytes\": 1441792, \n                    \"end\": 45.000676, \n                    \"omitted\": false, \n                    \"seconds\": 0.999552011489868, \n                    \"sender\": false, \n                    \"socket\": 5, \n                    \"start\": 44.001124\n                }\n            ], \n            \"sum\": {\n                \"bits_per_second\": 11539505.565906128, \n                \"bytes\": 1441792, \n                \"end\": 45.000676, \n                \"omitted\": false, \n                \"seconds\": 0.999552011489868, \n                \"sender\": false, \n                \"start\": 44.001124\n            }\n        }, \n        {\n            \"streams\": [\n                {\n                    \"bits_per_second\": 0, \n                    \"bytes\": 0, \n                    \"end\": 46.001145, \n                    \"omitted\": false, \n                    \"seconds\": 1.0004689693450928, \n                    \"sender\": false, \n                    \"socket\": 5, \n                    \"start\": 45.000676\n                }\n            ], \n            \"sum\": {\n                \"bits_per_second\": 0, \n                \"bytes\": 0, \n                \"end\": 46.001145, \n                \"omitted\": false, \n                \"seconds\": 1.0004689693450928, \n                \"sender\": false, \n                \"start\": 45.000676\n            }\n        }, \n        {\n            \"streams\": [\n                {\n                    \"bits_per_second\": 0, \n                    \"bytes\": 0, \n                    \"end\": 47.001132, \n                    \"omitted\": false, \n                    \"seconds\": 0.999987006187439, \n                    \"sender\": false, \n                    \"socket\": 5, \n                    \"start\": 46.001145\n                }\n            ], \n            \"sum\": {\n                \"bits_per_second\": 0, \n                \"bytes\": 0, \n                \"end\": 47.001132, \n                \"omitted\": false, \n                \"seconds\": 0.999987006187439, \n                \"sender\": false, \n                \"start\": 46.001145\n            }\n        }, \n        {\n            \"streams\": [\n                {\n                    \"bits_per_second\": 0, \n                    \"bytes\": 0, \n                    \"end\": 48.001182, \n                    \"omitted\": false, \n                    \"seconds\": 1.0000499486923218, \n                    \"sender\": false, \n                    \"socket\": 5, \n                    \"start\": 47.001132\n                }\n            ], \n            \"sum\": {\n                \"bits_per_second\": 0, \n                \"bytes\": 0, \n                \"end\": 48.001182, \n                \"omitted\": false, \n                \"seconds\": 1.0000499486923218, \n                \"sender\": false, \n                \"start\": 47.001132\n            }\n        }, \n        {\n            \"streams\": [\n                {\n                    \"bits_per_second\": 0, \n                    \"bytes\": 0, \n                    \"end\": 49.001118, \n                    \"omitted\": false, \n                    \"seconds\": 0.9999359846115112, \n                    \"sender\": false, \n                    \"socket\": 5, \n                    \"start\": 48.001182\n                }\n            ], \n            \"sum\": {\n                \"bits_per_second\": 0, \n                \"bytes\": 0, \n                \"end\": 49.001118, \n                \"omitted\": false, \n                \"seconds\": 0.9999359846115112, \n                \"sender\": false, \n                \"start\": 48.001182\n            }\n        }, \n        {\n            \"streams\": [\n                {\n                    \"bits_per_second\": 0, \n                    \"bytes\": 0, \n                    \"end\": 50.001158, \n                    \"omitted\": false, \n                    \"seconds\": 1.000040054321289, \n                    \"sender\": false, \n                    \"socket\": 5, \n                    \"start\": 49.001118\n                }\n            ], \n            \"sum\": {\n                \"bits_per_second\": 0, \n                \"bytes\": 0, \n                \"end\": 50.001158, \n                \"omitted\": false, \n                \"seconds\": 1.000040054321289, \n                \"sender\": false, \n                \"start\": 49.001118\n            }\n        }, \n        {\n            \"streams\": [\n                {\n                    \"bits_per_second\": 0, \n                    \"bytes\": 0, \n                    \"end\": 51.001144, \n                    \"omitted\": false, \n                    \"seconds\": 0.9999859929084778, \n                    \"sender\": false, \n                    \"socket\": 5, \n                    \"start\": 50.001158\n                }\n            ], \n            \"sum\": {\n                \"bits_per_second\": 0, \n                \"bytes\": 0, \n                \"end\": 51.001144, \n                \"omitted\": false, \n                \"seconds\": 0.9999859929084778, \n                \"sender\": false, \n                \"start\": 50.001158\n            }\n        }, \n        {\n            \"streams\": [\n                {\n                    \"bits_per_second\": 0, \n                    \"bytes\": 0, \n                    \"end\": 52.001118, \n                    \"omitted\": false, \n                    \"seconds\": 0.999974012374878, \n                    \"sender\": false, \n                    \"socket\": 5, \n                    \"start\": 51.001144\n                }\n            ], \n            \"sum\": {\n                \"bits_per_second\": 0, \n                \"bytes\": 0, \n                \"end\": 52.001118, \n                \"omitted\": false, \n                \"seconds\": 0.999974012374878, \n                \"sender\": false, \n                \"start\": 51.001144\n            }\n        }, \n        {\n            \"streams\": [\n                {\n                    \"bits_per_second\": 0, \n                    \"bytes\": 0, \n                    \"end\": 53.001156, \n                    \"omitted\": false, \n                    \"seconds\": 1.0000380277633667, \n                    \"sender\": false, \n                    \"socket\": 5, \n                    \"start\": 52.001118\n                }\n            ], \n            \"sum\": {\n                \"bits_per_second\": 0, \n                \"bytes\": 0, \n                \"end\": 53.001156, \n                \"omitted\": false, \n                \"seconds\": 1.0000380277633667, \n                \"sender\": false, \n                \"start\": 52.001118\n            }\n        }, \n        {\n            \"streams\": [\n                {\n                    \"bits_per_second\": 0, \n                    \"bytes\": 0, \n                    \"end\": 54.00114, \n                    \"omitted\": false, \n                    \"seconds\": 0.9999840259552002, \n                    \"sender\": false, \n                    \"socket\": 5, \n                    \"start\": 53.001156\n                }\n            ], \n            \"sum\": {\n                \"bits_per_second\": 0, \n                \"bytes\": 0, \n                \"end\": 54.00114, \n                \"omitted\": false, \n                \"seconds\": 0.9999840259552002, \n                \"sender\": false, \n                \"start\": 53.001156\n            }\n        }, \n        {\n            \"streams\": [\n                {\n                    \"bits_per_second\": 592404.126721396, \n                    \"bytes\": 74048, \n                    \"end\": 55.001106, \n                    \"omitted\": false, \n                    \"seconds\": 0.999966025352478, \n                    \"sender\": false, \n                    \"socket\": 5, \n                    \"start\": 54.00114\n                }\n            ], \n            \"sum\": {\n                \"bits_per_second\": 592404.126721396, \n                \"bytes\": 74048, \n                \"end\": 55.001106, \n                \"omitted\": false, \n                \"seconds\": 0.999966025352478, \n                \"sender\": false, \n                \"start\": 54.00114\n            }\n        }, \n        {\n            \"streams\": [\n                {\n                    \"bits_per_second\": 3145929.387891924, \n                    \"bytes\": 393216, \n                    \"end\": 56.001042, \n                    \"omitted\": false, \n                    \"seconds\": 0.9999359846115112, \n                    \"sender\": false, \n                    \"socket\": 5, \n                    \"start\": 55.001106\n                }\n            ], \n            \"sum\": {\n                \"bits_per_second\": 3145929.387891924, \n                \"bytes\": 393216, \n                \"end\": 56.001042, \n                \"omitted\": false, \n                \"seconds\": 0.9999359846115112, \n                \"sender\": false, \n                \"start\": 55.001106\n            }\n        }, \n        {\n            \"streams\": [\n                {\n                    \"bits_per_second\": 5242423.78970069, \n                    \"bytes\": 655360, \n                    \"end\": 57.001129, \n                    \"omitted\": false, \n                    \"seconds\": 1.000087022781372, \n                    \"sender\": false, \n                    \"socket\": 5, \n                    \"start\": 56.001042\n                }\n            ], \n            \"sum\": {\n                \"bits_per_second\": 5242423.78970069, \n                \"bytes\": 655360, \n                \"end\": 57.001129, \n                \"omitted\": false, \n                \"seconds\": 1.000087022781372, \n                \"sender\": false, \n                \"start\": 56.001042\n            }\n        }, \n        {\n            \"streams\": [\n                {\n                    \"bits_per_second\": 0, \n                    \"bytes\": 0, \n                    \"end\": 58.001219, \n                    \"omitted\": false, \n                    \"seconds\": 1.0000900030136108, \n                    \"sender\": false, \n                    \"socket\": 5, \n                    \"start\": 57.001129\n                }\n            ], \n            \"sum\": {\n                \"bits_per_second\": 0, \n                \"bytes\": 0, \n                \"end\": 58.001219, \n                \"omitted\": false, \n                \"seconds\": 1.0000900030136108, \n                \"sender\": false, \n                \"start\": 57.001129\n            }\n        }, \n        {\n            \"streams\": [\n                {\n                    \"bits_per_second\": 0, \n                    \"bytes\": 0, \n                    \"end\": 59.001124, \n                    \"omitted\": false, \n                    \"seconds\": 0.999904990196228, \n                    \"sender\": false, \n                    \"socket\": 5, \n                    \"start\": 58.001219\n                }\n            ], \n            \"sum\": {\n                \"bits_per_second\": 0, \n                \"bytes\": 0, \n                \"end\": 59.001124, \n                \"omitted\": false, \n                \"seconds\": 0.999904990196228, \n                \"sender\": false, \n                \"start\": 58.001219\n            }\n        }, \n        {\n            \"streams\": [\n                {\n                    \"bits_per_second\": 0, \n                    \"bytes\": 0, \n                    \"end\": 60.001116, \n                    \"omitted\": false, \n                    \"seconds\": 0.9999920129776, \n                    \"sender\": false, \n                    \"socket\": 5, \n                    \"start\": 59.001124\n                }\n            ], \n            \"sum\": {\n                \"bits_per_second\": 0, \n                \"bytes\": 0, \n                \"end\": 60.001116, \n                \"omitted\": false, \n                \"seconds\": 0.9999920129776, \n                \"sender\": false, \n                \"start\": 59.001124\n            }\n        }\n    ], \n    \"start\": {\n        \"accepted_connection\": {\n            \"host\": \"172.16.0.2\", \n            \"port\": 38545\n        }, \n        \"connected\": [\n            {\n                \"local_host\": \"172.16.0.1\", \n                \"local_port\": 5201, \n                \"remote_host\": \"172.16.0.2\", \n                \"remote_port\": 57947, \n                \"socket\": 5\n            }\n        ], \n        \"cookie\": \"u4xqtzwuyxmxqnpbzqunq5njvygzizylp7ok\", \n        \"fq_rate\": 0, \n        \"rcvbuf_actual\": 87380, \n        \"sndbuf_actual\": 65536, \n        \"sock_bufsize\": 0, \n        \"system_info\": \"REDACTED\", \n        \"target_bitrate\": 0, \n        \"tcp_mss_default\": 0, \n        \"test_start\": {\n            \"bidir\": 0, \n            \"blksize\": 131072, \n            \"blocks\": 0, \n            \"bytes\": 0, \n            \"duration\": 60, \n            \"fqrate\": 0, \n            \"interval\": 1, \n            \"num_streams\": 1, \n            \"omit\": 0, \n            \"protocol\": \"TCP\", \n            \"reverse\": 0, \n            \"target_bitrate\": 0, \n            \"tos\": 0\n        }, \n        \"timestamp\": {\n            \"time\": \"Sun, 20 Oct 2024 17:36:26 GMT\", \n            \"timesecs\": 1729445786\n        }, \n        \"version\": \"iperf 3.17.1\"\n    }\n}\n","summary":{"streams":[{"end":60.001061,"rtt":48718,"start":0,"stream-id":5,"retransmits":618,"throughput-bits":2816213.6666216617,"throughput-bytes":21121976}],"summary":{"end":60.001061,"start":0,"retransmits":618,"throughput-bits":2816213.6666216617,"throughput-bytes":21121976,"receiver-throughput-bits":2734376.4144364535}},"intervals":[{"streams":[{"end":1.000975,"rtt":25681,"start":0,"omitted":false,"stream-id":5,"retransmits":42,"tcp-window-size":30408,"throughput-bits":2962615.4121132283,"throughput-bytes":370688}],"summary":{"end":1.000975,"start":0,"omitted":false,"retransmits":42,"throughput-bits":2962615.4121132283,"throughput-bytes":370688}},{"streams":[{"end":2.001061,"rtt":40597,"start":1.000975,"omitted":false,"stream-id":5,"retransmits":10,"tcp-window-size":1448,"throughput-bits":0,"throughput-bytes":0}],"summary":{"end":2.001061,"start":1.000975,"omitted":false,"retransmits":10,"throughput-bits":0,"throughput-bytes":0}},{"streams":[{"end":3.000083,"rtt":25368,"start":2.001061,"omitted":false,"stream-id":5,"retransmits":23,"tcp-window-size":26064,"throughput-bits":2852453.6797643644,"throughput-bytes":356208}],"summary":{"end":3.000083,"start":2.001061,"omitted":false,"retransmits":23,"throughput-bits":2852453.6797643644,"throughput-bytes":356208}},{"streams":[{"end":4.001038,"rtt":30970,"start":3.000083,"omitted":false,"stream-id":5,"retransmits":20,"tcp-window-size":15928,"throughput-bits":0,"throughput-bytes":0}],"summary":{"end":4.001038,"start":3.000083,"omitted":false,"retransmits":20,"throughput-bits":0,"throughput-bytes":0}},{"streams":[{"end":5.000123,"rtt":20809,"start":4.001038,"omitted":false,"stream-id":5,"retransmits":12,"tcp-window-size":41992,"throughput-bits":6261088.839324264,"throughput-bytes":781920}],"summary":{"end":5.000123,"start":4.001038,"omitted":false,"retransmits":12,"throughput-bits":6261088.839324264,"throughput-bytes":781920}},{"streams":[{"end":6.00013,"rtt":39977,"start":5.000123,"omitted":false,"stream-id":5,"retransmits":0,"tcp-window-size":85432,"throughput-bits":15638290.010462925,"throughput-bytes":1954800}],"summary":{"end":6.00013,"start":5.000123,"omitted":false,"retransmits":0,"throughput-bits":15638290.010462925,"throughput-bytes":1954800}},{"streams":[{"end":7.000215,"rtt":49279,"start":6.00013,"omitted":false,"stream-id":5,"retransmits":1,"tcp-window-size":1448,"throughput-bits":11988421.029487368,"throughput-bytes":1498680}],"summary":{"end":7.000215,"start":6.00013,"omitted":false,"retransmits":1,"throughput-bits":11988421.029487368,"throughput-bytes":1498680}},{"streams":[{"end":8.001058,"rtt":49279,"start":7.000215,"omitted":false,"stream-id":5,"retransmits":1,"tcp-window-size":1448,"throughput-bits":0,"throughput-bytes":0}],"summary":{"end":8.001058,"start":7.000215,"omitted":false,"retransmits":1,"throughput-bits":0,"throughput-bytes":0}},{"streams":[{"end":9.001055,"rtt":49279,"start":8.001058,"omitted":false,"stream-id":5,"retransmits":1,"tcp-window-size":1448,"throughput-bits":0,"throughput-bytes":0}],"summary":{"end":9.001055,"start":8.001058,"omitted":false,"retransmits":1,"throughput-bits":0,"throughput-bytes":0}},{"streams":[{"end":10.001058,"rtt":49279,"start":9.001055,"omitted":false,"stream-id":5,"retransmits":0,"tcp-window-size":1448,"throughput-bits":0,"throughput-bytes":0}],"summary":{"end":10.001058,"start":9.001055,"omitted":false,"retransmits":0,"throughput-bits":0,"throughput-bytes":0}},{"streams":[{"end":11.001056,"rtt":35533,"start":10.001058,"omitted":false,"stream-id":5,"retransmits":20,"tcp-window-size":1448,"throughput-bits":0,"throughput-bytes":0}],"summary":{"end":11.001056,"start":10.001058,"omitted":false,"retransmits":20,"throughput-bits":0,"throughput-bytes":0}},{"streams":[{"end":12.001064,"rtt":33813,"start":11.001056,"omitted":false,"stream-id":5,"retransmits":13,"tcp-window-size":1448,"throughput-bits":0,"throughput-bytes":0}],"summary":{"end":12.001064,"start":11.001056,"omitted":false,"retransmits":13,"throughput-bits":0,"throughput-bytes":0}},{"streams":[{"end":13.001057,"rtt":25834,"start":12.001064,"omitted":false,"stream-id":5,"retransmits":38,"tcp-window-size":10136,"throughput-bits":0,"throughput-bytes":0}],"summary":{"end":13.001057,"start":12.001064,"omitted":false,"retransmits":38,"throughput-bits":0,"throughput-bytes":0}},{"streams":[{"end":14.000154,"rtt":26313,"start":13.001057,"omitted":false,"stream-id":5,"retransmits":14,"tcp-window-size":14480,"throughput-bits":0,"throughput-bytes":0}],"summary":{"end":14.000154,"start":13.001057,"omitted":false,"retransmits":14,"throughput-bits":0,"throughput-bytes":0}},{"streams":[{"end":15.001034,"rtt":26313,"start":14.000154,"omitted":false,"stream-id":5,"retransmits":1,"tcp-window-size":1448,"throughput-bits":0,"throughput-bytes":0}],"summary":{"end":15.001034,"start":14.000154,"omitted":false,"retransmits":1,"throughput-bits":0,"throughput-bytes":0}},{"streams":[{"end":16.001061,"rtt":26313,"start":15.001034,"omitted":false,"stream-id":5,"retransmits":0,"tcp-window-size":1448,"throughput-bits":0,"throughput-bytes":0}],"summary":{"end":16.001061,"start":15.001034,"omitted":false,"retransmits":0,"throughput-bits":0,"throughput-bytes":0}},{"streams":[{"end":17.001058,"rtt":26313,"start":16.001061,"omitted":false,"stream-id":5,"retransmits":0,"tcp-window-size":1448,"throughput-bits":0,"throughput-bytes":0}],"summary":{"end":17.001058,"start":16.001061,"omitted":false,"retransmits":0,"throughput-bits":0,"throughput-bytes":0}},{"streams":[{"end":18.001054,"rtt":33049,"start":17.001058,"omitted":false,"stream-id":5,"retransmits":11,"tcp-window-size":7240,"throughput-bits":0,"throughput-bytes":0}],"summary":{"end":18.001054,"start":17.001058,"omitted":false,"retransmits":11,"throughput-bits":0,"throughput-bytes":0}},{"streams":[{"end":19.00106,"rtt":32837,"start":18.001054,"omitted":false,"stream-id":5,"retransmits":1,"tcp-window-size":1448,"throughput-bits":0,"throughput-bytes":0}],"summary":{"end":19.00106,"start":18.001054,"omitted":false,"retransmits":1,"throughput-bits":0,"throughput-bytes":0}},{"streams":[{"end":20.001054,"rtt":32837,"start":19.00106,"omitted":false,"stream-id":5,"retransmits":1,"tcp-window-size":1448,"throughput-bits":0,"throughput-bytes":0}],"summary":{"end":20.001054,"start":19.00106,"omitted":false,"retransmits":1,"throughput-bits":0,"throughput-bytes":0}},{"streams":[{"end":21.001055,"rtt":32837,"start":20.001054,"omitted":false,"stream-id":5,"retransmits":0,"tcp-window-size":1448,"throughput-bits":0,"throughput-bytes":0}],"summary":{"end":21.001055,"start":20.001054,"omitted":false,"retransmits":0,"throughput-bits":0,"throughput-bytes":0}},{"streams":[{"end":22.001054,"rtt":32837,"start":21.001055,"omitted":false,"stream-id":5,"retransmits":0,"tcp-window-size":1448,"throughput-bits":0,"throughput-bytes":0}],"summary":{"end":22.001054,"start":21.001055,"omitted":false,"retransmits":0,"throughput-bits":0,"throughput-bytes":0}},{"streams":[{"end":23.000229,"rtt":29215,"start":22.001054,"omitted":false,"stream-id":5,"retransmits":9,"tcp-window-size":34752,"throughput-bits":4173683.2381212017,"throughput-bytes":521280}],"summary":{"end":23.000229,"start":22.001054,"omitted":false,"retransmits":9,"throughput-bits":4173683.2381212017,"throughput-bytes":521280}},{"streams":[{"end":24.000459,"rtt":25333,"start":23.000229,"omitted":false,"stream-id":5,"retransmits":3,"tcp-window-size":27512,"throughput-bits":6253921.881147774,"throughput-bytes":781920}],"summary":{"end":24.000459,"start":23.000229,"omitted":false,"retransmits":3,"throughput-bits":6253921.881147774,"throughput-bytes":781920}},{"streams":[{"end":25.001067,"rtt":91747,"start":24.000459,"omitted":false,"stream-id":5,"retransmits":3,"tcp-window-size":2896,"throughput-bits":0,"throughput-bytes":0}],"summary":{"end":25.001067,"start":24.000459,"omitted":false,"retransmits":3,"throughput-bits":0,"throughput-bytes":0}},{"streams":[{"end":26.00011,"rtt":25375,"start":25.001067,"omitted":false,"stream-id":5,"retransmits":17,"tcp-window-size":65160,"throughput-bits":12522704.38057509,"throughput-bytes":1563840}],"summary":{"end":26.00011,"start":25.001067,"omitted":false,"retransmits":17,"throughput-bits":12522704.38057509,"throughput-bytes":1563840}},{"streams":[{"end":27.000109,"rtt":41975,"start":26.00011,"omitted":false,"stream-id":5,"retransmits":0,"tcp-window-size":104256,"throughput-bits":18766099.015293315,"throughput-bytes":2345760}],"summary":{"end":27.000109,"start":26.00011,"omitted":false,"retransmits":0,"throughput-bits":18766099.015293315,"throughput-bytes":2345760}},{"streams":[{"end":28.000585,"rtt":43211,"start":27.000109,"omitted":false,"stream-id":5,"retransmits":22,"tcp-window-size":59368,"throughput-bits":10420639.74741561,"throughput-bytes":1303200}],"summary":{"end":28.000585,"start":27.000109,"omitted":false,"retransmits":22,"throughput-bits":10420639.74741561,"throughput-bytes":1303200}},{"streams":[{"end":29.001027,"rtt":43211,"start":28.000585,"omitted":false,"stream-id":5,"retransmits":1,"tcp-window-size":1448,"throughput-bits":0,"throughput-bytes":0}],"summary":{"end":29.001027,"start":28.000585,"omitted":false,"retransmits":1,"throughput-bits":0,"throughput-bytes":0}},{"streams":[{"end":30.000926,"rtt":43211,"start":29.001027,"omitted":false,"stream-id":5,"retransmits":1,"tcp-window-size":1448,"throughput-bits":0,"throughput-bytes":0}],"summary":{"end":30.000926,"start":29.001027,"omitted":false,"retransmits":1,"throughput-bits":0,"throughput-bytes":0}},{"streams":[{"end":31.001024,"rtt":43211,"start":30.000926,"omitted":false,"stream-id":5,"retransmits":0,"tcp-window-size":1448,"throughput-bits":0,"throughput-bytes":0}],"summary":{"end":31.001024,"start":30.000926,"omitted":false,"retransmits":0,"throughput-bits":0,"throughput-bytes":0}},{"streams":[{"end":32.000192,"rtt":27917,"start":31.001024,"omitted":false,"stream-id":5,"retransmits":41,"tcp-window-size":33304,"throughput-bits":2086856.30876625,"throughput-bytes":260640}],"summary":{"end":32.000192,"start":31.001024,"omitted":false,"retransmits":41,"throughput-bits":2086856.30876625,"throughput-bytes":260640}},{"streams":[{"end":33.000102,"rtt":17623,"start":32.000192,"omitted":false,"stream-id":5,"retransmits":32,"tcp-window-size":46336,"throughput-bits":8341230.735903455,"throughput-bytes":1042560}],"summary":{"end":33.000102,"start":32.000192,"omitted":false,"retransmits":32,"throughput-bits":8341230.735903455,"throughput-bytes":1042560}},{"streams":[{"end":34.000658,"rtt":28327,"start":33.000102,"omitted":false,"stream-id":5,"retransmits":1,"tcp-window-size":1448,"throughput-bits":8335845.335625963,"throughput-bytes":1042560}],"summary":{"end":34.000658,"start":33.000102,"omitted":false,"retransmits":1,"throughput-bits":8335845.335625963,"throughput-bytes":1042560}},{"streams":[{"end":35.001024,"rtt":28327,"start":34.000658,"omitted":false,"stream-id":5,"retransmits":1,"tcp-window-size":1448,"throughput-bits":0,"throughput-bytes":0}],"summary":{"end":35.001024,"start":34.000658,"omitted":false,"retransmits":1,"throughput-bits":0,"throughput-bytes":0}},{"streams":[{"end":36.000538,"rtt":18738,"start":35.001024,"omitted":false,"stream-id":5,"retransmits":48,"tcp-window-size":36200,"throughput-bits":2086133.8950216775,"throughput-bytes":260640}],"summary":{"end":36.000538,"start":35.001024,"omitted":false,"retransmits":48,"throughput-bits":2086133.8950216775,"throughput-bytes":260640}},{"streams":[{"end":37.001023,"rtt":18738,"start":36.000538,"omitted":false,"stream-id":5,"retransmits":0,"tcp-window-size":36200,"throughput-bits":0,"throughput-bytes":0}],"summary":{"end":37.001023,"start":36.000538,"omitted":false,"retransmits":0,"throughput-bits":0,"throughput-bytes":0}},{"streams":[{"end":38.001025,"rtt":18738,"start":37.001023,"omitted":false,"stream-id":5,"retransmits":0,"tcp-window-size":36200,"throughput-bits":0,"throughput-bytes":0}],"summary":{"end":38.001025,"start":37.001023,"omitted":false,"retransmits":0,"throughput-bits":0,"throughput-bytes":0}},{"streams":[{"end":39.00013,"rtt":22699,"start":38.001025,"omitted":false,"stream-id":5,"retransmits":25,"tcp-window-size":43440,"throughput-bits":4173975.8057916025,"throughput-bytes":521280}],"summary":{"end":39.00013,"start":38.001025,"omitted":false,"retransmits":25,"throughput-bits":4173975.8057916025,"throughput-bytes":521280}},{"streams":[{"end":40.000088,"rtt":27383,"start":39.00013,"omitted":false,"stream-id":5,"retransmits":38,"tcp-window-size":30408,"throughput-bits":4170415.246164116,"throughput-bytes":521280}],"summary":{"end":40.000088,"start":39.00013,"omitted":false,"retransmits":38,"throughput-bits":4170415.246164116,"throughput-bytes":521280}},{"streams":[{"end":41.000181,"rtt":25255,"start":40.000088,"omitted":false,"stream-id":5,"retransmits":16,"tcp-window-size":1448,"throughput-bits":4169852.273600887,"throughput-bytes":521280}],"summary":{"end":41.000181,"start":40.000088,"omitted":false,"retransmits":16,"throughput-bits":4169852.273600887,"throughput-bytes":521280}},{"streams":[{"end":42.001138,"rtt":25255,"start":41.000181,"omitted":false,"stream-id":5,"retransmits":1,"tcp-window-size":1448,"throughput-bits":0,"throughput-bytes":0}],"summary":{"end":42.001138,"start":41.000181,"omitted":false,"retransmits":1,"throughput-bits":0,"throughput-bytes":0}},{"streams":[{"end":43.000784,"rtt":19454,"start":42.001138,"omitted":false,"stream-id":5,"retransmits":23,"tcp-window-size":50680,"throughput-bits":6257575.131444075,"throughput-bytes":781920}],"summary":{"end":43.000784,"start":42.001138,"omitted":false,"retransmits":23,"throughput-bits":6257575.131444075,"throughput-bytes":781920}},{"streams":[{"end":44.000161,"rtt":37119,"start":43.000784,"omitted":false,"stream-id":5,"retransmits":0,"tcp-window-size":92672,"throughput-bits":16691358.51183687,"throughput-bytes":2085120}],"summary":{"end":44.000161,"start":43.000784,"omitted":false,"retransmits":0,"throughput-bits":16691358.51183687,"throughput-bytes":2085120}},{"streams":[{"end":45.000164,"rtt":59315,"start":44.000161,"omitted":false,"stream-id":5,"retransmits":0,"tcp-window-size":111496,"throughput-bits":12510682.715260044,"throughput-bytes":1563840}],"summary":{"end":45.000164,"start":44.000161,"omitted":false,"retransmits":0,"throughput-bits":12510682.715260044,"throughput-bytes":1563840}},{"streams":[{"end":46.000982,"rtt":140717,"start":45.000164,"omitted":false,"stream-id":5,"retransmits":5,"tcp-window-size":1448,"throughput-bits":0,"throughput-bytes":0}],"summary":{"end":46.000982,"start":45.000164,"omitted":false,"retransmits":5,"throughput-bits":0,"throughput-bytes":0}},{"streams":[{"end":47.001075,"rtt":140717,"start":46.000982,"omitted":false,"stream-id":5,"retransmits":1,"tcp-window-size":1448,"throughput-bits":0,"throughput-bytes":0}],"summary":{"end":47.001075,"start":46.000982,"omitted":false,"retransmits":1,"throughput-bits":0,"throughput-bytes":0}},{"streams":[{"end":48.001077,"rtt":140717,"start":47.001075,"omitted":false,"stream-id":5,"retransmits":0,"tcp-window-size":1448,"throughput-bits":0,"throughput-bytes":0}],"summary":{"end":48.001077,"start":47.001075,"omitted":false,"retransmits":0,"throughput-bits":0,"throughput-bytes":0}},{"streams":[{"end":49.001055,"rtt":140717,"start":48.001077,"omitted":false,"stream-id":5,"retransmits":0,"tcp-window-size":1448,"throughput-bits":0,"throughput-bytes":0}],"summary":{"end":49.001055,"start":48.001077,"omitted":false,"retransmits":0,"throughput-bits":0,"throughput-bytes":0}},{"streams":[{"end":50.001072,"rtt":140717,"start":49.001055,"omitted":false,"stream-id":5,"retransmits":1,"tcp-window-size":1448,"throughput-bits":0,"throughput-bytes":0}],"summary":{"end":50.001072,"start":49.001055,"omitted":false,"retransmits":1,"throughput-bits":0,"throughput-bytes":0}},{"streams":[{"end":51.000215,"rtt":140717,"start":50.001072,"omitted":false,"stream-id":5,"retransmits":0,"tcp-window-size":1448,"throughput-bits":0,"throughput-bytes":0}],"summary":{"end":51.000215,"start":50.001072,"omitted":false,"retransmits":0,"throughput-bits":0,"throughput-bytes":0}},{"streams":[{"end":52.000652,"rtt":140717,"start":51.000215,"omitted":false,"stream-id":5,"retransmits":0,"tcp-window-size":1448,"throughput-bits":0,"throughput-bytes":0}],"summary":{"end":52.000652,"start":51.000215,"omitted":false,"retransmits":0,"throughput-bits":0,"throughput-bytes":0}},{"streams":[{"end":53.001092,"rtt":140717,"start":52.000652,"omitted":false,"stream-id":5,"retransmits":0,"tcp-window-size":1448,"throughput-bits":0,"throughput-bytes":0}],"summary":{"end":53.001092,"start":52.000652,"omitted":false,"retransmits":0,"throughput-bits":0,"throughput-bytes":0}},{"streams":[{"end":54.000935,"rtt":127752,"start":53.001092,"omitted":false,"stream-id":5,"retransmits":1,"tcp-window-size":2896,"throughput-bits":0,"throughput-bytes":0}],"summary":{"end":54.000935,"start":53.001092,"omitted":false,"retransmits":1,"throughput-bits":0,"throughput-bytes":0}},{"streams":[{"end":55.001081,"rtt":22070,"start":54.000935,"omitted":false,"stream-id":5,"retransmits":64,"tcp-window-size":13032,"throughput-bits":0,"throughput-bytes":0}],"summary":{"end":55.001081,"start":54.000935,"omitted":false,"retransmits":64,"throughput-bits":0,"throughput-bytes":0}},{"streams":[{"end":56.000103,"rtt":49153,"start":55.001081,"omitted":false,"stream-id":5,"retransmits":23,"tcp-window-size":11584,"throughput-bits":4174322.458191753,"throughput-bytes":521280}],"summary":{"end":56.000103,"start":55.001081,"omitted":false,"retransmits":23,"throughput-bits":4174322.458191753,"throughput-bytes":521280}},{"streams":[{"end":57.000571,"rtt":22926,"start":56.000103,"omitted":false,"stream-id":5,"retransmits":29,"tcp-window-size":20272,"throughput-bits":4168289.175345611,"throughput-bytes":521280}],"summary":{"end":57.000571,"start":56.000103,"omitted":false,"retransmits":29,"throughput-bits":4168289.175345611,"throughput-bytes":521280}},{"streams":[{"end":58.001079,"rtt":22926,"start":57.000571,"omitted":false,"stream-id":5,"retransmits":2,"tcp-window-size":1448,"throughput-bits":0,"throughput-bytes":0}],"summary":{"end":58.001079,"start":57.000571,"omitted":false,"retransmits":2,"throughput-bits":0,"throughput-bytes":0}},{"streams":[{"end":59.001048,"rtt":22926,"start":58.001079,"omitted":false,"stream-id":5,"retransmits":1,"tcp-window-size":1448,"throughput-bits":0,"throughput-bytes":0}],"summary":{"end":59.001048,"start":58.001079,"omitted":false,"retransmits":1,"throughput-bits":0,"throughput-bytes":0}},{"streams":[{"end":60.001061,"rtt":22926,"start":59.001048,"omitted":false,"stream-id":5,"retransmits":0,"tcp-window-size":1448,"throughput-bits":0,"throughput-bytes":0}],"summary":{"end":60.001061,"start":59.001048,"omitted":false,"retransmits":0,"throughput-bits":0,"throughput-bytes":0}}],"succeeded":true}
