{"diags":"Participant 0:\n/usr/bin/iperf3 -p 5201 -B 172.16.0.2 -c 172.16.0.1 -t 10 --json --rsa-public-key-path /var/run/pscheduler-server/runner/tmp/tmpvbvjxs9y/tmp_6ker5fj/public-key --username HL5MCqmyaV4zZ4ogYGh2\n\n{\n    \"end\": {\n        \"cpu_utilization_percent\": {\n            \"host_system\": 0.2634943927041625, \n            \"host_total\": 0.30033756606626155, \n            \"host_user\": 0.03683329318688806, \n            \"remote_system\": 0.575088066819269, \n            \"remote_total\": 0.8441186541620362, \n            \"remote_user\": 0.2690207450003607\n        }, \n        \"receiver_tcp_congestion\": \"htcp\", \n        \"sender_tcp_congestion\": \"htcp\", \n        \"streams\": [\n            {\n                \"receiver\": {\n                    \"bits_per_second\": 10013857.278456967, \n                    \"bytes\": 12717784, \n                    \"end\": 10.160148, \n                    \"seconds\": 10.000052, \n                    \"sender\": true, \n                    \"socket\": 5, \n                    \"start\": 0\n                }, \n                \"sender\": {\n                    \"bits_per_second\": 13316845.952401048, \n                    \"bytes\": 16646144, \n                    \"end\": 10.000052, \n                    \"max_rtt\": 458072, \n                    \"max_snd_cwnd\": 366344, \n                    \"max_snd_wnd\": 0, \n                    \"mean_rtt\": 225274, \n                    \"min_rtt\": 98587, \n                    \"retransmits\": 287, \n                    \"seconds\": 10.000052, \n                    \"sender\": true, \n                    \"socket\": 5, \n                    \"start\": 0\n                }\n            }\n        ], \n        \"sum_received\": {\n            \"bits_per_second\": 10013857.278456967, \n            \"bytes\": 12717784, \n            \"end\": 10.160148, \n            \"seconds\": 10.160148, \n            \"sender\": true, \n            \"start\": 0\n        }, \n        \"sum_sent\": {\n            \"bits_per_second\": 13316845.952401048, \n            \"bytes\": 16646144, \n            \"end\": 10.000052, \n            \"retransmits\": 287, \n            \"seconds\": 10.000052, \n            \"sender\": true, \n            \"start\": 0\n        }\n    }, \n    \"intervals\": [\n        {\n            \"streams\": [\n                {\n                    \"bits_per_second\": 29093372.59669214, \n                    \"bytes\": 3640272, \n                    \"end\": 1.00099, \n                    \"omitted\": false, \n                    \"pmtu\": 1500, \n                    \"retransmits\": 143, \n                    \"rtt\": 312763, \n                    \"rttvar\": 995, \n                    \"seconds\": 1.0009900331497192, \n                    \"sender\": true, \n                    \"snd_cwnd\": 321456, \n                    \"snd_wnd\": -1, \n                    \"socket\": 5, \n                    \"start\": 0\n                }\n            ], \n            \"sum\": {\n                \"bits_per_second\": 29093372.59669214, \n                \"bytes\": 3640272, \n                \"end\": 1.00099, \n                \"omitted\": false, \n                \"retransmits\": 143, \n                \"seconds\": 1.0009900331497192, \n                \"sender\": true, \n                \"start\": 0\n            }\n        }, \n        {\n            \"streams\": [\n                {\n                    \"bits_per_second\": 20178289.733628258, \n                    \"bytes\": 2520112, \n                    \"end\": 2.000128, \n                    \"omitted\": false, \n                    \"pmtu\": 1500, \n                    \"retransmits\": 133, \n                    \"rtt\": 98587, \n                    \"rttvar\": 1084, \n                    \"seconds\": 0.9991379976272583, \n                    \"sender\": true, \n                    \"snd_cwnd\": 201272, \n                    \"snd_wnd\": -1, \n                    \"socket\": 5, \n                    \"start\": 1.00099\n                }\n            ], \n            \"sum\": {\n                \"bits_per_second\": 20178289.733628258, \n                \"bytes\": 2520112, \n                \"end\": 2.000128, \n                \"omitted\": false, \n                \"retransmits\": 133, \n                \"seconds\": 0.9991379976272583, \n                \"sender\": true, \n                \"start\": 1.00099\n            }\n        }, \n        {\n            \"streams\": [\n                {\n                    \"bits_per_second\": 10486829.48406978, \n                    \"bytes\": 1310720, \n                    \"end\": 3.000026, \n                    \"omitted\": false, \n                    \"pmtu\": 1500, \n                    \"retransmits\": 0, \n                    \"rtt\": 177101, \n                    \"rttvar\": 7940, \n                    \"seconds\": 0.9998980164527893, \n                    \"sender\": true, \n                    \"snd_cwnd\": 212856, \n                    \"snd_wnd\": -1, \n                    \"socket\": 5, \n                    \"start\": 2.000128\n                }\n            ], \n            \"sum\": {\n                \"bits_per_second\": 10486829.48406978, \n                \"bytes\": 1310720, \n                \"end\": 3.000026, \n                \"omitted\": false, \n                \"retransmits\": 0, \n                \"seconds\": 0.9998980164527893, \n                \"sender\": true, \n                \"start\": 2.000128\n            }\n        }, \n        {\n            \"streams\": [\n                {\n                    \"bits_per_second\": 10475808.20399551, \n                    \"bytes\": 1310720, \n                    \"end\": 4.000976, \n                    \"omitted\": false, \n                    \"pmtu\": 1500, \n                    \"retransmits\": 0, \n                    \"rtt\": 183643, \n                    \"rttvar\": 5096, \n                    \"seconds\": 1.00094997882843, \n                    \"sender\": true, \n                    \"snd_cwnd\": 224440, \n                    \"snd_wnd\": -1, \n                    \"socket\": 5, \n                    \"start\": 3.000026\n                }\n            ], \n            \"sum\": {\n                \"bits_per_second\": 10475808.20399551, \n                \"bytes\": 1310720, \n                \"end\": 4.000976, \n                \"omitted\": false, \n                \"retransmits\": 0, \n                \"seconds\": 1.00094997882843, \n                \"sender\": true, \n                \"start\": 3.000026\n            }\n        }, \n        {\n            \"streams\": [\n                {\n                    \"bits_per_second\": 10494586.173001591, \n                    \"bytes\": 1310720, \n                    \"end\": 5.000135, \n                    \"omitted\": false, \n                    \"pmtu\": 1500, \n                    \"retransmits\": 0, \n                    \"rtt\": 153150, \n                    \"rttvar\": 3651, \n                    \"seconds\": 0.9991589784622192, \n                    \"sender\": true, \n                    \"snd_cwnd\": 247608, \n                    \"snd_wnd\": -1, \n                    \"socket\": 5, \n                    \"start\": 4.000976\n                }\n            ], \n            \"sum\": {\n                \"bits_per_second\": 10494586.173001591, \n                \"bytes\": 1310720, \n                \"end\": 5.000135, \n                \"omitted\": false, \n                \"retransmits\": 0, \n                \"seconds\": 0.9991589784622192, \n                \"sender\": true, \n                \"start\": 4.000976\n            }\n        }, \n        {\n            \"streams\": [\n                {\n                    \"bits_per_second\": 10485183.781666357, \n                    \"bytes\": 1310720, \n                    \"end\": 6.00019, \n                    \"omitted\": false, \n                    \"pmtu\": 1500, \n                    \"retransmits\": 0, \n                    \"rtt\": 175944, \n                    \"rttvar\": 394, \n                    \"seconds\": 1.000054955482483, \n                    \"sender\": true, \n                    \"snd_cwnd\": 283808, \n                    \"snd_wnd\": -1, \n                    \"socket\": 5, \n                    \"start\": 5.000135\n                }\n            ], \n            \"sum\": {\n                \"bits_per_second\": 10485183.781666357, \n                \"bytes\": 1310720, \n                \"end\": 6.00019, \n                \"omitted\": false, \n                \"retransmits\": 0, \n                \"seconds\": 1.000054955482483, \n                \"sender\": true, \n                \"start\": 5.000135\n            }\n        }, \n        {\n            \"streams\": [\n                {\n                    \"bits_per_second\": 10484690.109175032, \n                    \"bytes\": 1310720, \n                    \"end\": 7.000292, \n                    \"omitted\": false, \n                    \"pmtu\": 1500, \n                    \"retransmits\": 0, \n                    \"rtt\": 202655, \n                    \"rttvar\": 5216, \n                    \"seconds\": 1.0001020431518555, \n                    \"sender\": true, \n                    \"snd_cwnd\": 333040, \n                    \"snd_wnd\": -1, \n                    \"socket\": 5, \n                    \"start\": 6.00019\n                }\n            ], \n            \"sum\": {\n                \"bits_per_second\": 10484690.109175032, \n                \"bytes\": 1310720, \n                \"end\": 7.000292, \n                \"omitted\": false, \n                \"retransmits\": 0, \n                \"seconds\": 1.0001020431518555, \n                \"sender\": true, \n                \"start\": 6.00019\n            }\n        }, \n        {\n            \"streams\": [\n                {\n                    \"bits_per_second\": 10482793.339573367, \n                    \"bytes\": 1310720, \n                    \"end\": 8.000575, \n                    \"omitted\": false, \n                    \"pmtu\": 1500, \n                    \"retransmits\": 0, \n                    \"rtt\": 458072, \n                    \"rttvar\": 2791, \n                    \"seconds\": 1.0002830028533936, \n                    \"sender\": true, \n                    \"snd_cwnd\": 366344, \n                    \"snd_wnd\": -1, \n                    \"socket\": 5, \n                    \"start\": 7.000292\n                }\n            ], \n            \"sum\": {\n                \"bits_per_second\": 10482793.339573367, \n                \"bytes\": 1310720, \n                \"end\": 8.000575, \n                \"omitted\": false, \n                \"retransmits\": 0, \n                \"seconds\": 1.0002830028533936, \n                \"sender\": true, \n                \"start\": 7.000292\n            }\n        }, \n        {\n            \"streams\": [\n                {\n                    \"bits_per_second\": 10488644.54329507, \n                    \"bytes\": 1310720, \n                    \"end\": 9.0003, \n                    \"omitted\": false, \n                    \"pmtu\": 1500, \n                    \"retransmits\": 2, \n                    \"rtt\": 335562, \n                    \"rttvar\": 6149, \n                    \"seconds\": 0.9997249841690063, \n                    \"sender\": true, \n                    \"snd_cwnd\": 347520, \n                    \"snd_wnd\": -1, \n                    \"socket\": 5, \n                    \"start\": 8.000575\n                }\n            ], \n            \"sum\": {\n                \"bits_per_second\": 10488644.54329507, \n                \"bytes\": 1310720, \n                \"end\": 9.0003, \n                \"omitted\": false, \n                \"retransmits\": 2, \n                \"seconds\": 0.9997249841690063, \n                \"sender\": true, \n                \"start\": 8.000575\n            }\n        }, \n        {\n            \"streams\": [\n                {\n                    \"bits_per_second\": 10488361.270153828, \n                    \"bytes\": 1310720, \n                    \"end\": 10.000052, \n                    \"omitted\": false, \n                    \"pmtu\": 1500, \n                    \"retransmits\": 9, \n                    \"rtt\": 155267, \n                    \"rttvar\": 5554, \n                    \"seconds\": 0.9997519850730896, \n                    \"sender\": true, \n                    \"snd_cwnd\": 209960, \n                    \"snd_wnd\": -1, \n                    \"socket\": 5, \n                    \"start\": 9.0003\n                }\n            ], \n            \"sum\": {\n                \"bits_per_second\": 10488361.270153828, \n                \"bytes\": 1310720, \n                \"end\": 10.000052, \n                \"omitted\": false, \n                \"retransmits\": 9, \n                \"seconds\": 0.9997519850730896, \n                \"sender\": true, \n                \"start\": 9.0003\n            }\n        }\n    ], \n    \"start\": {\n        \"connected\": [\n            {\n                \"local_host\": \"172.16.0.2\", \n                \"local_port\": 33077, \n                \"remote_host\": \"172.16.0.1\", \n                \"remote_port\": 5201, \n                \"socket\": 5\n            }\n        ], \n        \"connecting_to\": {\n            \"host\": \"172.16.0.1\", \n            \"port\": 5201\n        }, \n        \"cookie\": \"ki5list7rlyy3ccxk26xssah3rcgkdquzacw\", \n        \"fq_rate\": 0, \n        \"rcvbuf_actual\": 87380, \n        \"sndbuf_actual\": 65536, \n        \"sock_bufsize\": 0, \n        \"system_info\": \"REDACTED\", \n        \"target_bitrate\": 0, \n        \"tcp_mss_default\": 1448, \n        \"test_start\": {\n            \"bidir\": 0, \n            \"blksize\": 131072, \n            \"blocks\": 0, \n            \"bytes\": 0, \n            \"duration\": 10, \n            \"fqrate\": 0, \n            \"num_streams\": 1, \n            \"omit\": 0, \n            \"protocol\": \"TCP\", \n            \"reverse\": 0, \n            \"target_bitrate\": 0, \n            \"tos\": 0\n        }, \n        \"timestamp\": {\n            \"time\": \"Sat, 12 Oct 2024 02:26:18 GMT\", \n            \"timesecs\": 1728699978\n        }, \n        \"version\": \"iperf 3.14\"\n    }\n}\nParticipant 1:\n/usr/bin/iperf3 -s -1 --idle-timeout 10 --json -p 5201 -B 172.16.0.1 --authorized-users-path /var/run/pscheduler-server/runner/tmp/tmpw2latvi2/tmpd2mgjy4j/credentials --rsa-private-key-path /var/run/pscheduler-server/runner/tmp/tmpw2latvi2/tmpd2mgjy4j/private-key\n\n{\n    \"end\": {\n        \"cpu_utilization_percent\": {\n            \"host_system\": 0.575088066819269, \n            \"host_total\": 0.8441186541620362, \n            \"host_user\": 0.2690207450003607, \n            \"remote_system\": 0, \n            \"remote_total\": 0, \n            \"remote_user\": 0\n        }, \n        \"receiver_tcp_congestion\": \"htcp\", \n        \"streams\": [\n            {\n                \"receiver\": {\n                    \"bits_per_second\": 10013857.278456967, \n                    \"bytes\": 12717784, \n                    \"end\": 10.160148, \n                    \"seconds\": 10.160148, \n                    \"sender\": false, \n                    \"socket\": 5, \n                    \"start\": 0\n                }, \n                \"sender\": {\n                    \"bits_per_second\": 0, \n                    \"bytes\": 0, \n                    \"end\": 10.160148, \n                    \"seconds\": 10.160148, \n                    \"sender\": false, \n                    \"socket\": 5, \n                    \"start\": 0\n                }\n            }\n        ], \n        \"sum_received\": {\n            \"bits_per_second\": 10013857.278456967, \n            \"bytes\": 12717784, \n            \"end\": 10.160148, \n            \"seconds\": 10.160148, \n            \"sender\": false, \n            \"start\": 0\n        }, \n        \"sum_sent\": {\n            \"bits_per_second\": 0, \n            \"bytes\": 0, \n            \"end\": 10.160148, \n            \"seconds\": 10.160148, \n            \"sender\": false, \n            \"start\": 0\n        }\n    }, \n    \"intervals\": [\n        {\n            \"streams\": [\n                {\n                    \"bits_per_second\": 6228367.489313906, \n                    \"bytes\": 779024, \n                    \"end\": 1.000614, \n                    \"omitted\": false, \n                    \"seconds\": 1.000614047050476, \n                    \"sender\": false, \n                    \"socket\": 5, \n                    \"start\": 0\n                }\n            ], \n            \"sum\": {\n                \"bits_per_second\": 6228367.489313906, \n                \"bytes\": 779024, \n                \"end\": 1.000614, \n                \"omitted\": false, \n                \"seconds\": 1.000614047050476, \n                \"sender\": false, \n                \"start\": 0\n            }\n        }, \n        {\n            \"streams\": [\n                {\n                    \"bits_per_second\": 14402022.941120304, \n                    \"bytes\": 1799864, \n                    \"end\": 2.000398, \n                    \"omitted\": false, \n                    \"seconds\": 0.999783992767334, \n                    \"sender\": false, \n                    \"socket\": 5, \n                    \"start\": 1.000614\n                }\n            ], \n            \"sum\": {\n                \"bits_per_second\": 14402022.941120304, \n                \"bytes\": 1799864, \n                \"end\": 2.000398, \n                \"omitted\": false, \n                \"seconds\": 0.999783992767334, \n                \"sender\": false, \n                \"start\": 1.000614\n            }\n        }, \n        {\n            \"streams\": [\n                {\n                    \"bits_per_second\": 13912578.874765608, \n                    \"bytes\": 1739048, \n                    \"end\": 3.000384, \n                    \"omitted\": false, \n                    \"seconds\": 0.9999859929084778, \n                    \"sender\": false, \n                    \"socket\": 5, \n                    \"start\": 2.000398\n                }\n            ], \n            \"sum\": {\n                \"bits_per_second\": 13912578.874765608, \n                \"bytes\": 1739048, \n                \"end\": 3.000384, \n                \"omitted\": false, \n                \"seconds\": 0.9999859929084778, \n                \"sender\": false, \n                \"start\": 2.000398\n            }\n        }, \n        {\n            \"streams\": [\n                {\n                    \"bits_per_second\": 9927110.49419121, \n                    \"bytes\": 1240936, \n                    \"end\": 4.000422, \n                    \"omitted\": false, \n                    \"seconds\": 1.0000380277633667, \n                    \"sender\": false, \n                    \"socket\": 5, \n                    \"start\": 3.000384\n                }\n            ], \n            \"sum\": {\n                \"bits_per_second\": 9927110.49419121, \n                \"bytes\": 1240936, \n                \"end\": 4.000422, \n                \"omitted\": false, \n                \"seconds\": 1.0000380277633667, \n                \"sender\": false, \n                \"start\": 3.000384\n            }\n        }, \n        {\n            \"streams\": [\n                {\n                    \"bits_per_second\": 8780285.770788977, \n                    \"bytes\": 1097584, \n                    \"end\": 5.000466, \n                    \"omitted\": false, \n                    \"seconds\": 1.0000439882278442, \n                    \"sender\": false, \n                    \"socket\": 5, \n                    \"start\": 4.000422\n                }\n            ], \n            \"sum\": {\n                \"bits_per_second\": 8780285.770788977, \n                \"bytes\": 1097584, \n                \"end\": 5.000466, \n                \"omitted\": false, \n                \"seconds\": 1.0000439882278442, \n                \"sender\": false, \n                \"start\": 4.000422\n            }\n        }, \n        {\n            \"streams\": [\n                {\n                    \"bits_per_second\": 9905082.782511413, \n                    \"bytes\": 1238040, \n                    \"end\": 6.000389, \n                    \"omitted\": false, \n                    \"seconds\": 0.9999229907989502, \n                    \"sender\": false, \n                    \"socket\": 5, \n                    \"start\": 5.000466\n                }\n            ], \n            \"sum\": {\n                \"bits_per_second\": 9905082.782511413, \n                \"bytes\": 1238040, \n                \"end\": 6.000389, \n                \"omitted\": false, \n                \"seconds\": 0.9999229907989502, \n                \"sender\": false, \n                \"start\": 5.000466\n            }\n        }, \n        {\n            \"streams\": [\n                {\n                    \"bits_per_second\": 11294309.7920947, \n                    \"bytes\": 1411800, \n                    \"end\": 7.000397, \n                    \"omitted\": false, \n                    \"seconds\": 1.0000079870224, \n                    \"sender\": false, \n                    \"socket\": 5, \n                    \"start\": 6.000389\n                }\n            ], \n            \"sum\": {\n                \"bits_per_second\": 11294309.7920947, \n                \"bytes\": 1411800, \n                \"end\": 7.000397, \n                \"omitted\": false, \n                \"seconds\": 1.0000079870224, \n                \"sender\": false, \n                \"start\": 6.000389\n            }\n        }, \n        {\n            \"streams\": [\n                {\n                    \"bits_per_second\": 7089351.37719175, \n                    \"bytes\": 886176, \n                    \"end\": 8.000405, \n                    \"omitted\": false, \n                    \"seconds\": 1.0000079870224, \n                    \"sender\": false, \n                    \"socket\": 5, \n                    \"start\": 7.000397\n                }\n            ], \n            \"sum\": {\n                \"bits_per_second\": 7089351.37719175, \n                \"bytes\": 886176, \n                \"end\": 8.000405, \n                \"omitted\": false, \n                \"seconds\": 1.0000079870224, \n                \"sender\": false, \n                \"start\": 7.000397\n            }\n        }, \n        {\n            \"streams\": [\n                {\n                    \"bits_per_second\": 8675557.608141094, \n                    \"bytes\": 1084552, \n                    \"end\": 9.000504, \n                    \"omitted\": false, \n                    \"seconds\": 1.0000989437103271, \n                    \"sender\": false, \n                    \"socket\": 5, \n                    \"start\": 8.000405\n                }\n            ], \n            \"sum\": {\n                \"bits_per_second\": 8675557.608141094, \n                \"bytes\": 1084552, \n                \"end\": 9.000504, \n                \"omitted\": false, \n                \"seconds\": 1.0000989437103271, \n                \"sender\": false, \n                \"start\": 8.000405\n            }\n        }, \n        {\n            \"streams\": [\n                {\n                    \"bits_per_second\": 9905320.14283192, \n                    \"bytes\": 1238040, \n                    \"end\": 10.000403, \n                    \"omitted\": false, \n                    \"seconds\": 0.9998990297317505, \n                    \"sender\": false, \n                    \"socket\": 5, \n                    \"start\": 9.000504\n                }\n            ], \n            \"sum\": {\n                \"bits_per_second\": 9905320.14283192, \n                \"bytes\": 1238040, \n                \"end\": 10.000403, \n                \"omitted\": false, \n                \"seconds\": 0.9998990297317505, \n                \"sender\": false, \n                \"start\": 9.000504\n            }\n        }, \n        {\n            \"streams\": [\n                {\n                    \"bits_per_second\": 10152180.491193114, \n                    \"bytes\": 202720, \n                    \"end\": 10.160148, \n                    \"omitted\": false, \n                    \"seconds\": 0.159744992852211, \n                    \"sender\": false, \n                    \"socket\": 5, \n                    \"start\": 10.000403\n                }\n            ], \n            \"sum\": {\n                \"bits_per_second\": 10152180.491193114, \n                \"bytes\": 202720, \n                \"end\": 10.160148, \n                \"omitted\": false, \n                \"seconds\": 0.159744992852211, \n                \"sender\": false, \n                \"start\": 10.000403\n            }\n        }\n    ], \n    \"start\": {\n        \"accepted_connection\": {\n            \"host\": \"172.16.0.2\", \n            \"port\": 58113\n        }, \n        \"connected\": [\n            {\n                \"local_host\": \"172.16.0.1\", \n                \"local_port\": 5201, \n                \"remote_host\": \"172.16.0.2\", \n                \"remote_port\": 33077, \n                \"socket\": 5\n            }\n        ], \n        \"cookie\": \"ki5list7rlyy3ccxk26xssah3rcgkdquzacw\", \n        \"fq_rate\": 0, \n        \"rcvbuf_actual\": 87380, \n        \"sndbuf_actual\": 65536, \n        \"sock_bufsize\": 0, \n        \"system_info\": \"REDACTED\", \n        \"target_bitrate\": 0, \n        \"tcp_mss_default\": 0, \n        \"test_start\": {\n            \"bidir\": 0, \n            \"blksize\": 131072, \n            \"blocks\": 0, \n            \"bytes\": 0, \n            \"duration\": 10, \n            \"fqrate\": 0, \n            \"num_streams\": 1, \n            \"omit\": 0, \n            \"protocol\": \"TCP\", \n            \"reverse\": 0, \n            \"target_bitrate\": 0, \n            \"tos\": 0\n        }, \n        \"timestamp\": {\n            \"time\": \"Sat, 12 Oct 2024 02:26:18 GMT\", \n            \"timesecs\": 1728699978\n        }, \n        \"version\": \"iperf 3.14\"\n    }\n}\n","summary":{"streams":[{"end":10.000052,"rtt":225274,"start":0,"stream-id":5,"retransmits":287,"throughput-bits":13316845.952401048,"throughput-bytes":16646144}],"summary":{"end":10.000052,"start":0,"retransmits":287,"throughput-bits":13316845.952401048,"throughput-bytes":16646144,"receiver-throughput-bits":10013857.278456967}},"intervals":[{"streams":[{"end":1.00099,"rtt":312763,"start":0,"omitted":false,"stream-id":5,"retransmits":143,"tcp-window-size":321456,"throughput-bits":29093372.59669214,"throughput-bytes":3640272}],"summary":{"end":1.00099,"start":0,"omitted":false,"retransmits":143,"throughput-bits":29093372.59669214,"throughput-bytes":3640272}},{"streams":[{"end":2.000128,"rtt":98587,"start":1.00099,"omitted":false,"stream-id":5,"retransmits":133,"tcp-window-size":201272,"throughput-bits":20178289.733628258,"throughput-bytes":2520112}],"summary":{"end":2.000128,"start":1.00099,"omitted":false,"retransmits":133,"throughput-bits":20178289.733628258,"throughput-bytes":2520112}},{"streams":[{"end":3.000026,"rtt":177101,"start":2.000128,"omitted":false,"stream-id":5,"retransmits":0,"tcp-window-size":212856,"throughput-bits":10486829.48406978,"throughput-bytes":1310720}],"summary":{"end":3.000026,"start":2.000128,"omitted":false,"retransmits":0,"throughput-bits":10486829.48406978,"throughput-bytes":1310720}},{"streams":[{"end":4.000976,"rtt":183643,"start":3.000026,"omitted":false,"stream-id":5,"retransmits":0,"tcp-window-size":224440,"throughput-bits":10475808.20399551,"throughput-bytes":1310720}],"summary":{"end":4.000976,"start":3.000026,"omitted":false,"retransmits":0,"throughput-bits":10475808.20399551,"throughput-bytes":1310720}},{"streams":[{"end":5.000135,"rtt":153150,"start":4.000976,"omitted":false,"stream-id":5,"retransmits":0,"tcp-window-size":247608,"throughput-bits":10494586.173001591,"throughput-bytes":1310720}],"summary":{"end":5.000135,"start":4.000976,"omitted":false,"retransmits":0,"throughput-bits":10494586.173001591,"throughput-bytes":1310720}},{"streams":[{"end":6.00019,"rtt":175944,"start":5.000135,"omitted":false,"stream-id":5,"retransmits":0,"tcp-window-size":283808,"throughput-bits":10485183.781666357,"throughput-bytes":1310720}],"summary":{"end":6.00019,"start":5.000135,"omitted":false,"retransmits":0,"throughput-bits":10485183.781666357,"throughput-bytes":1310720}},{"streams":[{"end":7.000292,"rtt":202655,"start":6.00019,"omitted":false,"stream-id":5,"retransmits":0,"tcp-window-size":333040,"throughput-bits":10484690.109175032,"throughput-bytes":1310720}],"summary":{"end":7.000292,"start":6.00019,"omitted":false,"retransmits":0,"throughput-bits":10484690.109175032,"throughput-bytes":1310720}},{"streams":[{"end":8.000575,"rtt":458072,"start":7.000292,"omitted":false,"stream-id":5,"retransmits":0,"tcp-window-size":366344,"throughput-bits":10482793.339573367,"throughput-bytes":1310720}],"summary":{"end":8.000575,"start":7.000292,"omitted":false,"retransmits":0,"throughput-bits":10482793.339573367,"throughput-bytes":1310720}},{"streams":[{"end":9.0003,"rtt":335562,"start":8.000575,"omitted":false,"stream-id":5,"retransmits":2,"tcp-window-size":347520,"throughput-bits":10488644.54329507,"throughput-bytes":1310720}],"summary":{"end":9.0003,"start":8.000575,"omitted":false,"retransmits":2,"throughput-bits":10488644.54329507,"throughput-bytes":1310720}},{"streams":[{"end":10.000052,"rtt":155267,"start":9.0003,"omitted":false,"stream-id":5,"retransmits":9,"tcp-window-size":209960,"throughput-bits":10488361.270153828,"throughput-bytes":1310720}],"summary":{"end":10.000052,"start":9.0003,"omitted":false,"retransmits":9,"throughput-bits":10488361.270153828,"throughput-bytes":1310720}}],"succeeded":true}
