{"diags":"Participant 0:\n/usr/bin/iperf3 -p 5201 -B 10.0.0.1 -c 10.0.0.2 -t 60 --json --rsa-public-key-path /var/run/pscheduler-server/runner/tmp/tmpzo_j6j19/tmp5nw__kwt/public-key --username r4a7zkvChzfICtrWQXET\n\n{\n    \"end\": {\n        \"cpu_utilization_percent\": {\n            \"host_system\": 2.02320677731767, \n            \"host_total\": 2.050278678938529, \n            \"host_user\": 0.02707356809679799, \n            \"remote_system\": 5.25446255846583, \n            \"remote_total\": 5.749266124797368, \n            \"remote_user\": 0.4948068953941287\n        }, \n        \"receiver_tcp_congestion\": \"htcp\", \n        \"sender_tcp_congestion\": \"htcp\", \n        \"streams\": [\n            {\n                \"receiver\": {\n                    \"bits_per_second\": 865535626.139247, \n                    \"bytes\": 6499843216, \n                    \"end\": 60.076956, \n                    \"seconds\": 60.000072, \n                    \"sender\": true, \n                    \"socket\": 5, \n                    \"start\": 0\n                }, \n                \"sender\": {\n                    \"bits_per_second\": 867014025.1831697, \n                    \"bytes\": 6502612992, \n                    \"end\": 60.000072, \n                    \"max_rtt\": 77095, \n                    \"max_snd_cwnd\": 16698336, \n                    \"max_snd_wnd\": 0, \n                    \"mean_rtt\": 77087, \n                    \"min_rtt\": 77080, \n                    \"retransmits\": 0, \n                    \"seconds\": 60.000072, \n                    \"sender\": true, \n                    \"socket\": 5, \n                    \"start\": 0\n                }\n            }\n        ], \n        \"sum_received\": {\n            \"bits_per_second\": 865535626.139247, \n            \"bytes\": 6499843216, \n            \"end\": 60.076956, \n            \"seconds\": 60.076956, \n            \"sender\": true, \n            \"start\": 0\n        }, \n        \"sum_sent\": {\n            \"bits_per_second\": 867014025.1831697, \n            \"bytes\": 6502612992, \n            \"end\": 60.000072, \n            \"retransmits\": 0, \n            \"seconds\": 60.000072, \n            \"sender\": true, \n            \"start\": 0\n        }\n    }, \n    \"intervals\": [\n        {\n            \"streams\": [\n                {\n                    \"bits_per_second\": 955083661.555538, \n                    \"bytes\": 119406592, \n                    \"end\": 1.000177, \n                    \"omitted\": false, \n                    \"pmtu\": 1500, \n                    \"retransmits\": 0, \n                    \"rtt\": 77087, \n                    \"rttvar\": 8, \n                    \"seconds\": 1.000177025794983, \n                    \"sender\": true, \n                    \"snd_cwnd\": 16698336, \n                    \"snd_wnd\": -1, \n                    \"socket\": 5, \n                    \"start\": 0\n                }\n            ], \n            \"sum\": {\n                \"bits_per_second\": 955083661.555538, \n                \"bytes\": 119406592, \n                \"end\": 1.000177, \n                \"omitted\": false, \n                \"retransmits\": 0, \n                \"seconds\": 1.000177025794983, \n                \"sender\": true, \n                \"start\": 0\n            }\n        }, \n        {\n            \"streams\": [\n                {\n                    \"bits_per_second\": 870416446.1163948, \n                    \"bytes\": 108789760, \n                    \"end\": 2.000064, \n                    \"omitted\": false, \n                    \"pmtu\": 1500, \n                    \"retransmits\": 0, \n                    \"rtt\": 77086, \n                    \"rttvar\": 5, \n                    \"seconds\": 0.999886989593506, \n                    \"sender\": true, \n                    \"snd_cwnd\": 16698336, \n                    \"snd_wnd\": -1, \n                    \"socket\": 5, \n                    \"start\": 1.000177\n                }\n            ], \n            \"sum\": {\n                \"bits_per_second\": 870416446.1163948, \n                \"bytes\": 108789760, \n                \"end\": 2.000064, \n                \"omitted\": false, \n                \"retransmits\": 0, \n                \"seconds\": 0.999886989593506, \n                \"sender\": true, \n                \"start\": 1.000177\n            }\n        }, \n        {\n            \"streams\": [\n                {\n                    \"bits_per_second\": 859827195.030547, \n                    \"bytes\": 107479040, \n                    \"end\": 3.00007, \n                    \"omitted\": false, \n                    \"pmtu\": 1500, \n                    \"retransmits\": 0, \n                    \"rtt\": 77090, \n                    \"rttvar\": 8, \n                    \"seconds\": 1.0000059604644775, \n                    \"sender\": true, \n                    \"snd_cwnd\": 16698336, \n                    \"snd_wnd\": -1, \n                    \"socket\": 5, \n                    \"start\": 2.000064\n                }\n            ], \n            \"sum\": {\n                \"bits_per_second\": 859827195.030547, \n                \"bytes\": 107479040, \n                \"end\": 3.00007, \n                \"omitted\": false, \n                \"retransmits\": 0, \n                \"seconds\": 1.0000059604644775, \n                \"sender\": true, \n                \"start\": 2.000064\n            }\n        }, \n        {\n            \"streams\": [\n                {\n                    \"bits_per_second\": 870325031.30552, \n                    \"bytes\": 108789760, \n                    \"end\": 4.000062, \n                    \"omitted\": false, \n                    \"pmtu\": 1500, \n                    \"retransmits\": 0, \n                    \"rtt\": 77086, \n                    \"rttvar\": 6, \n                    \"seconds\": 0.9999920129776, \n                    \"sender\": true, \n                    \"snd_cwnd\": 16698336, \n                    \"snd_wnd\": -1, \n                    \"socket\": 5, \n                    \"start\": 3.00007\n                }\n            ], \n            \"sum\": {\n                \"bits_per_second\": 870325031.30552, \n                \"bytes\": 108789760, \n                \"end\": 4.000062, \n                \"omitted\": false, \n                \"retransmits\": 0, \n                \"seconds\": 0.9999920129776, \n                \"sender\": true, \n                \"start\": 3.00007\n            }\n        }, \n        {\n            \"streams\": [\n                {\n                    \"bits_per_second\": 859758423.8513664, \n                    \"bytes\": 107479040, \n                    \"end\": 5.000148, \n                    \"omitted\": false, \n                    \"pmtu\": 1500, \n                    \"retransmits\": 0, \n                    \"rtt\": 77089, \n                    \"rttvar\": 4, \n                    \"seconds\": 1.0000859498977661, \n                    \"sender\": true, \n                    \"snd_cwnd\": 16698336, \n                    \"snd_wnd\": -1, \n                    \"socket\": 5, \n                    \"start\": 4.000062\n                }\n            ], \n            \"sum\": {\n                \"bits_per_second\": 859758423.8513664, \n                \"bytes\": 107479040, \n                \"end\": 5.000148, \n                \"omitted\": false, \n                \"retransmits\": 0, \n                \"seconds\": 1.0000859498977661, \n                \"sender\": true, \n                \"start\": 4.000062\n            }\n        }, \n        {\n            \"streams\": [\n                {\n                    \"bits_per_second\": 870392060.038024, \n                    \"bytes\": 108789760, \n                    \"end\": 6.000063, \n                    \"omitted\": false, \n                    \"pmtu\": 1500, \n                    \"retransmits\": 0, \n                    \"rtt\": 77086, \n                    \"rttvar\": 6, \n                    \"seconds\": 0.9999150037765503, \n                    \"sender\": true, \n                    \"snd_cwnd\": 16698336, \n                    \"snd_wnd\": -1, \n                    \"socket\": 5, \n                    \"start\": 5.000148\n                }\n            ], \n            \"sum\": {\n                \"bits_per_second\": 870392060.038024, \n                \"bytes\": 108789760, \n                \"end\": 6.000063, \n                \"omitted\": false, \n                \"retransmits\": 0, \n                \"seconds\": 0.9999150037765503, \n                \"sender\": true, \n                \"start\": 5.000148\n            }\n        }, \n        {\n            \"streams\": [\n                {\n                    \"bits_per_second\": 870318961.8758936, \n                    \"bytes\": 108789760, \n                    \"end\": 7.000062, \n                    \"omitted\": false, \n                    \"pmtu\": 1500, \n                    \"retransmits\": 0, \n                    \"rtt\": 77087, \n                    \"rttvar\": 10, \n                    \"seconds\": 0.9999989867210388, \n                    \"sender\": true, \n                    \"snd_cwnd\": 16698336, \n                    \"snd_wnd\": -1, \n                    \"socket\": 5, \n                    \"start\": 6.000063\n                }\n            ], \n            \"sum\": {\n                \"bits_per_second\": 870318961.8758936, \n                \"bytes\": 108789760, \n                \"end\": 7.000062, \n                \"omitted\": false, \n                \"retransmits\": 0, \n                \"seconds\": 0.9999989867210388, \n                \"sender\": true, \n                \"start\": 6.000063\n            }\n        }, \n        {\n            \"streams\": [\n                {\n                    \"bits_per_second\": 859831500.000782, \n                    \"bytes\": 107479040, \n                    \"end\": 8.000063, \n                    \"omitted\": false, \n                    \"pmtu\": 1500, \n                    \"retransmits\": 0, \n                    \"rtt\": 77087, \n                    \"rttvar\": 5, \n                    \"seconds\": 1.0000009536743164, \n                    \"sender\": true, \n                    \"snd_cwnd\": 16698336, \n                    \"snd_wnd\": -1, \n                    \"socket\": 5, \n                    \"start\": 7.000062\n                }\n            ], \n            \"sum\": {\n                \"bits_per_second\": 859831500.000782, \n                \"bytes\": 107479040, \n                \"end\": 8.000063, \n                \"omitted\": false, \n                \"retransmits\": 0, \n                \"seconds\": 1.0000009536743164, \n                \"sender\": true, \n                \"start\": 7.000062\n            }\n        }, \n        {\n            \"streams\": [\n                {\n                    \"bits_per_second\": 870318080, \n                    \"bytes\": 108789760, \n                    \"end\": 9.000063, \n                    \"omitted\": false, \n                    \"pmtu\": 1500, \n                    \"retransmits\": 0, \n                    \"rtt\": 77086, \n                    \"rttvar\": 9, \n                    \"seconds\": 1, \n                    \"sender\": true, \n                    \"snd_cwnd\": 16698336, \n                    \"snd_wnd\": -1, \n                    \"socket\": 5, \n                    \"start\": 8.000063\n                }\n            ], \n            \"sum\": {\n                \"bits_per_second\": 870318080, \n                \"bytes\": 108789760, \n                \"end\": 9.000063, \n                \"omitted\": false, \n                \"retransmits\": 0, \n                \"seconds\": 1, \n                \"sender\": true, \n                \"start\": 8.000063\n            }\n        }, \n        {\n            \"streams\": [\n                {\n                    \"bits_per_second\": 859786709.9195297, \n                    \"bytes\": 107479040, \n                    \"end\": 10.000116, \n                    \"omitted\": false, \n                    \"pmtu\": 1500, \n                    \"retransmits\": 0, \n                    \"rtt\": 77084, \n                    \"rttvar\": 4, \n                    \"seconds\": 1.00005304813385, \n                    \"sender\": true, \n                    \"snd_cwnd\": 16698336, \n                    \"snd_wnd\": -1, \n                    \"socket\": 5, \n                    \"start\": 9.000063\n                }\n            ], \n            \"sum\": {\n                \"bits_per_second\": 859786709.9195297, \n                \"bytes\": 107479040, \n                \"end\": 10.000116, \n                \"omitted\": false, \n                \"retransmits\": 0, \n                \"seconds\": 1.00005304813385, \n                \"sender\": true, \n                \"start\": 9.000063\n            }\n        }, \n        {\n            \"streams\": [\n                {\n                    \"bits_per_second\": 870364199.318795, \n                    \"bytes\": 108789760, \n                    \"end\": 11.000063, \n                    \"omitted\": false, \n                    \"pmtu\": 1500, \n                    \"retransmits\": 0, \n                    \"rtt\": 77090, \n                    \"rttvar\": 5, \n                    \"seconds\": 0.9999470114707947, \n                    \"sender\": true, \n                    \"snd_cwnd\": 16698336, \n                    \"snd_wnd\": -1, \n                    \"socket\": 5, \n                    \"start\": 10.000116\n                }\n            ], \n            \"sum\": {\n                \"bits_per_second\": 870364199.318795, \n                \"bytes\": 108789760, \n                \"end\": 11.000063, \n                \"omitted\": false, \n                \"retransmits\": 0, \n                \"seconds\": 0.9999470114707947, \n                \"sender\": true, \n                \"start\": 10.000116\n            }\n        }, \n        {\n            \"streams\": [\n                {\n                    \"bits_per_second\": 859819405.1939852, \n                    \"bytes\": 107479040, \n                    \"end\": 12.000078, \n                    \"omitted\": false, \n                    \"pmtu\": 1500, \n                    \"retransmits\": 0, \n                    \"rtt\": 77095, \n                    \"rttvar\": 5, \n                    \"seconds\": 1.0000150203704834, \n                    \"sender\": true, \n                    \"snd_cwnd\": 16698336, \n                    \"snd_wnd\": -1, \n                    \"socket\": 5, \n                    \"start\": 11.000063\n                }\n            ], \n            \"sum\": {\n                \"bits_per_second\": 859819405.1939852, \n                \"bytes\": 107479040, \n                \"end\": 12.000078, \n                \"omitted\": false, \n                \"retransmits\": 0, \n                \"seconds\": 1.0000150203704834, \n                \"sender\": true, \n                \"start\": 11.000063\n            }\n        }, \n        {\n            \"streams\": [\n                {\n                    \"bits_per_second\": 870331982.7220827, \n                    \"bytes\": 108789760, \n                    \"end\": 13.000062, \n                    \"omitted\": false, \n                    \"pmtu\": 1500, \n                    \"retransmits\": 0, \n                    \"rtt\": 77086, \n                    \"rttvar\": 6, \n                    \"seconds\": 0.9999840259552002, \n                    \"sender\": true, \n                    \"snd_cwnd\": 16698336, \n                    \"snd_wnd\": -1, \n                    \"socket\": 5, \n                    \"start\": 12.000078\n                }\n            ], \n            \"sum\": {\n                \"bits_per_second\": 870331982.7220827, \n                \"bytes\": 108789760, \n                \"end\": 13.000062, \n                \"omitted\": false, \n                \"retransmits\": 0, \n                \"seconds\": 0.9999840259552002, \n                \"sender\": true, \n                \"start\": 12.000078\n            }\n        }, \n        {\n            \"streams\": [\n                {\n                    \"bits_per_second\": 859815100.3448608, \n                    \"bytes\": 107479040, \n                    \"end\": 14.000082, \n                    \"omitted\": false, \n                    \"pmtu\": 1500, \n                    \"retransmits\": 0, \n                    \"rtt\": 77092, \n                    \"rttvar\": 15, \n                    \"seconds\": 1.0000200271606445, \n                    \"sender\": true, \n                    \"snd_cwnd\": 16698336, \n                    \"snd_wnd\": -1, \n                    \"socket\": 5, \n                    \"start\": 13.000062\n                }\n            ], \n            \"sum\": {\n                \"bits_per_second\": 859815100.3448608, \n                \"bytes\": 107479040, \n                \"end\": 14.000082, \n                \"omitted\": false, \n                \"retransmits\": 0, \n                \"seconds\": 1.0000200271606445, \n                \"sender\": true, \n                \"start\": 13.000062\n            }\n        }, \n        {\n            \"streams\": [\n                {\n                    \"bits_per_second\": 870362487.2657287, \n                    \"bytes\": 108789760, \n                    \"end\": 15.000031, \n                    \"omitted\": false, \n                    \"pmtu\": 1500, \n                    \"retransmits\": 0, \n                    \"rtt\": 77084, \n                    \"rttvar\": 8, \n                    \"seconds\": 0.9999489784240723, \n                    \"sender\": true, \n                    \"snd_cwnd\": 16698336, \n                    \"snd_wnd\": -1, \n                    \"socket\": 5, \n                    \"start\": 14.000082\n                }\n            ], \n            \"sum\": {\n                \"bits_per_second\": 870362487.2657287, \n                \"bytes\": 108789760, \n                \"end\": 15.000031, \n                \"omitted\": false, \n                \"retransmits\": 0, \n                \"seconds\": 0.9999489784240723, \n                \"sender\": true, \n                \"start\": 14.000082\n            }\n        }, \n        {\n            \"streams\": [\n                {\n                    \"bits_per_second\": 859789374.6450644, \n                    \"bytes\": 107479040, \n                    \"end\": 16.000081, \n                    \"omitted\": false, \n                    \"pmtu\": 1500, \n                    \"retransmits\": 0, \n                    \"rtt\": 77091, \n                    \"rttvar\": 8, \n                    \"seconds\": 1.0000499486923218, \n                    \"sender\": true, \n                    \"snd_cwnd\": 16698336, \n                    \"snd_wnd\": -1, \n                    \"socket\": 5, \n                    \"start\": 15.000031\n                }\n            ], \n            \"sum\": {\n                \"bits_per_second\": 859789374.6450644, \n                \"bytes\": 107479040, \n                \"end\": 16.000081, \n                \"omitted\": false, \n                \"retransmits\": 0, \n                \"seconds\": 1.0000499486923218, \n                \"sender\": true, \n                \"start\": 15.000031\n            }\n        }, \n        {\n            \"streams\": [\n                {\n                    \"bits_per_second\": 870352889.5171968, \n                    \"bytes\": 108789760, \n                    \"end\": 17.000041, \n                    \"omitted\": false, \n                    \"pmtu\": 1500, \n                    \"retransmits\": 0, \n                    \"rtt\": 77092, \n                    \"rttvar\": 8, \n                    \"seconds\": 0.9999600052833557, \n                    \"sender\": true, \n                    \"snd_cwnd\": 16698336, \n                    \"snd_wnd\": -1, \n                    \"socket\": 5, \n                    \"start\": 16.000081\n                }\n            ], \n            \"sum\": {\n                \"bits_per_second\": 870352889.5171968, \n                \"bytes\": 108789760, \n                \"end\": 17.000041, \n                \"omitted\": false, \n                \"retransmits\": 0, \n                \"seconds\": 0.9999600052833557, \n                \"sender\": true, \n                \"start\": 16.000081\n            }\n        }, \n        {\n            \"streams\": [\n                {\n                    \"bits_per_second\": 870315486.25773, \n                    \"bytes\": 108789760, \n                    \"end\": 18.000044, \n                    \"omitted\": false, \n                    \"pmtu\": 1500, \n                    \"retransmits\": 0, \n                    \"rtt\": 77084, \n                    \"rttvar\": 5, \n                    \"seconds\": 1.0000029802322388, \n                    \"sender\": true, \n                    \"snd_cwnd\": 16698336, \n                    \"snd_wnd\": -1, \n                    \"socket\": 5, \n                    \"start\": 17.000041\n                }\n            ], \n            \"sum\": {\n                \"bits_per_second\": 870315486.25773, \n                \"bytes\": 108789760, \n                \"end\": 18.000044, \n                \"omitted\": false, \n                \"retransmits\": 0, \n                \"seconds\": 1.0000029802322388, \n                \"sender\": true, \n                \"start\": 17.000041\n            }\n        }, \n        {\n            \"streams\": [\n                {\n                    \"bits_per_second\": 859732599.0666947, \n                    \"bytes\": 107479040, \n                    \"end\": 19.00016, \n                    \"omitted\": false, \n                    \"pmtu\": 1500, \n                    \"retransmits\": 0, \n                    \"rtt\": 77086, \n                    \"rttvar\": 7, \n                    \"seconds\": 1.000115990638733, \n                    \"sender\": true, \n                    \"snd_cwnd\": 16698336, \n                    \"snd_wnd\": -1, \n                    \"socket\": 5, \n                    \"start\": 18.000044\n                }\n            ], \n            \"sum\": {\n                \"bits_per_second\": 859732599.0666947, \n                \"bytes\": 107479040, \n                \"end\": 19.00016, \n                \"omitted\": false, \n                \"retransmits\": 0, \n                \"seconds\": 1.000115990638733, \n                \"sender\": true, \n                \"start\": 18.000044\n            }\n        }, \n        {\n            \"streams\": [\n                {\n                    \"bits_per_second\": 870328506.999921, \n                    \"bytes\": 108789760, \n                    \"end\": 20.000148, \n                    \"omitted\": false, \n                    \"pmtu\": 1500, \n                    \"retransmits\": 0, \n                    \"rtt\": 77092, \n                    \"rttvar\": 7, \n                    \"seconds\": 0.9999880194664, \n                    \"sender\": true, \n                    \"snd_cwnd\": 16698336, \n                    \"snd_wnd\": -1, \n                    \"socket\": 5, \n                    \"start\": 19.00016\n                }\n            ], \n            \"sum\": {\n                \"bits_per_second\": 870328506.999921, \n                \"bytes\": 108789760, \n                \"end\": 20.000148, \n                \"omitted\": false, \n                \"retransmits\": 0, \n                \"seconds\": 0.9999880194664, \n                \"sender\": true, \n                \"start\": 19.00016\n            }\n        }, \n        {\n            \"streams\": [\n                {\n                    \"bits_per_second\": 859890800.227176, \n                    \"bytes\": 107479040, \n                    \"end\": 21.00008, \n                    \"omitted\": false, \n                    \"pmtu\": 1500, \n                    \"retransmits\": 0, \n                    \"rtt\": 77094, \n                    \"rttvar\": 14, \n                    \"seconds\": 0.9999319911003113, \n                    \"sender\": true, \n                    \"snd_cwnd\": 16698336, \n                    \"snd_wnd\": -1, \n                    \"socket\": 5, \n                    \"start\": 20.000148\n                }\n            ], \n            \"sum\": {\n                \"bits_per_second\": 859890800.227176, \n                \"bytes\": 107479040, \n                \"end\": 21.00008, \n                \"omitted\": false, \n                \"retransmits\": 0, \n                \"seconds\": 0.9999319911003113, \n                \"sender\": true, \n                \"start\": 20.000148\n            }\n        }, \n        {\n            \"streams\": [\n                {\n                    \"bits_per_second\": 870352007.5725455, \n                    \"bytes\": 108789760, \n                    \"end\": 22.000041, \n                    \"omitted\": false, \n                    \"pmtu\": 1500, \n                    \"retransmits\": 0, \n                    \"rtt\": 77092, \n                    \"rttvar\": 7, \n                    \"seconds\": 0.999961018562317, \n                    \"sender\": true, \n                    \"snd_cwnd\": 16698336, \n                    \"snd_wnd\": -1, \n                    \"socket\": 5, \n                    \"start\": 21.00008\n                }\n            ], \n            \"sum\": {\n                \"bits_per_second\": 870352007.5725455, \n                \"bytes\": 108789760, \n                \"end\": 22.000041, \n                \"omitted\": false, \n                \"retransmits\": 0, \n                \"seconds\": 0.999961018562317, \n                \"sender\": true, \n                \"start\": 21.00008\n            }\n        }, \n        {\n            \"streams\": [\n                {\n                    \"bits_per_second\": 859797881.3794156, \n                    \"bytes\": 107479040, \n                    \"end\": 23.000081, \n                    \"omitted\": false, \n                    \"pmtu\": 1500, \n                    \"retransmits\": 0, \n                    \"rtt\": 77086, \n                    \"rttvar\": 9, \n                    \"seconds\": 1.000040054321289, \n                    \"sender\": true, \n                    \"snd_cwnd\": 16698336, \n                    \"snd_wnd\": -1, \n                    \"socket\": 5, \n                    \"start\": 22.000041\n                }\n            ], \n            \"sum\": {\n                \"bits_per_second\": 859797881.3794156, \n                \"bytes\": 107479040, \n                \"end\": 23.000081, \n                \"omitted\": false, \n                \"retransmits\": 0, \n                \"seconds\": 1.000040054321289, \n                \"sender\": true, \n                \"start\": 22.000041\n            }\n        }, \n        {\n            \"streams\": [\n                {\n                    \"bits_per_second\": 870332864.6261512, \n                    \"bytes\": 108789760, \n                    \"end\": 24.000064, \n                    \"omitted\": false, \n                    \"pmtu\": 1500, \n                    \"retransmits\": 0, \n                    \"rtt\": 77091, \n                    \"rttvar\": 6, \n                    \"seconds\": 0.999983012676239, \n                    \"sender\": true, \n                    \"snd_cwnd\": 16698336, \n                    \"snd_wnd\": -1, \n                    \"socket\": 5, \n                    \"start\": 23.000081\n                }\n            ], \n            \"sum\": {\n                \"bits_per_second\": 870332864.6261512, \n                \"bytes\": 108789760, \n                \"end\": 24.000064, \n                \"omitted\": false, \n                \"retransmits\": 0, \n                \"seconds\": 0.999983012676239, \n                \"sender\": true, \n                \"start\": 23.000081\n            }\n        }, \n        {\n            \"streams\": [\n                {\n                    \"bits_per_second\": 859830577.5035312, \n                    \"bytes\": 107479040, \n                    \"end\": 25.000066, \n                    \"omitted\": false, \n                    \"pmtu\": 1500, \n                    \"retransmits\": 0, \n                    \"rtt\": 77088, \n                    \"rttvar\": 7, \n                    \"seconds\": 1.0000020265579224, \n                    \"sender\": true, \n                    \"snd_cwnd\": 16698336, \n                    \"snd_wnd\": -1, \n                    \"socket\": 5, \n                    \"start\": 24.000064\n                }\n            ], \n            \"sum\": {\n                \"bits_per_second\": 859830577.5035312, \n                \"bytes\": 107479040, \n                \"end\": 25.000066, \n                \"omitted\": false, \n                \"retransmits\": 0, \n                \"seconds\": 1.0000020265579224, \n                \"sender\": true, \n                \"start\": 24.000064\n            }\n        }, \n        {\n            \"streams\": [\n                {\n                    \"bits_per_second\": 870321555.63888, \n                    \"bytes\": 108789760, \n                    \"end\": 26.000062, \n                    \"omitted\": false, \n                    \"pmtu\": 1500, \n                    \"retransmits\": 0, \n                    \"rtt\": 77087, \n                    \"rttvar\": 9, \n                    \"seconds\": 0.9999960064888, \n                    \"sender\": true, \n                    \"snd_cwnd\": 16698336, \n                    \"snd_wnd\": -1, \n                    \"socket\": 5, \n                    \"start\": 25.000066\n                }\n            ], \n            \"sum\": {\n                \"bits_per_second\": 870321555.63888, \n                \"bytes\": 108789760, \n                \"end\": 26.000062, \n                \"omitted\": false, \n                \"retransmits\": 0, \n                \"seconds\": 0.9999960064888, \n                \"sender\": true, \n                \"start\": 25.000066\n            }\n        }, \n        {\n            \"streams\": [\n                {\n                    \"bits_per_second\": 859809155.6240784, \n                    \"bytes\": 107479040, \n                    \"end\": 27.000089, \n                    \"omitted\": false, \n                    \"pmtu\": 1500, \n                    \"retransmits\": 0, \n                    \"rtt\": 77085, \n                    \"rttvar\": 6, \n                    \"seconds\": 1.0000269412994385, \n                    \"sender\": true, \n                    \"snd_cwnd\": 16698336, \n                    \"snd_wnd\": -1, \n                    \"socket\": 5, \n                    \"start\": 26.000062\n                }\n            ], \n            \"sum\": {\n                \"bits_per_second\": 859809155.6240784, \n                \"bytes\": 107479040, \n                \"end\": 27.000089, \n                \"omitted\": false, \n                \"retransmits\": 0, \n                \"seconds\": 1.0000269412994385, \n                \"sender\": true, \n                \"start\": 26.000062\n            }\n        }, \n        {\n            \"streams\": [\n                {\n                    \"bits_per_second\": 870340698.0877904, \n                    \"bytes\": 108789760, \n                    \"end\": 28.000063, \n                    \"omitted\": false, \n                    \"pmtu\": 1500, \n                    \"retransmits\": 0, \n                    \"rtt\": 77088, \n                    \"rttvar\": 8, \n                    \"seconds\": 0.999974012374878, \n                    \"sender\": true, \n                    \"snd_cwnd\": 16698336, \n                    \"snd_wnd\": -1, \n                    \"socket\": 5, \n                    \"start\": 27.000089\n                }\n            ], \n            \"sum\": {\n                \"bits_per_second\": 870340698.0877904, \n                \"bytes\": 108789760, \n                \"end\": 28.000063, \n                \"omitted\": false, \n                \"retransmits\": 0, \n                \"seconds\": 0.999974012374878, \n                \"sender\": true, \n                \"start\": 27.000089\n            }\n        }, \n        {\n            \"streams\": [\n                {\n                    \"bits_per_second\": 870345055.8361002, \n                    \"bytes\": 108789760, \n                    \"end\": 29.000032, \n                    \"omitted\": false, \n                    \"pmtu\": 1500, \n                    \"retransmits\": 0, \n                    \"rtt\": 77091, \n                    \"rttvar\": 9, \n                    \"seconds\": 0.9999690055847168, \n                    \"sender\": true, \n                    \"snd_cwnd\": 16698336, \n                    \"snd_wnd\": -1, \n                    \"socket\": 5, \n                    \"start\": 28.000063\n                }\n            ], \n            \"sum\": {\n                \"bits_per_second\": 870345055.8361002, \n                \"bytes\": 108789760, \n                \"end\": 29.000032, \n                \"omitted\": false, \n                \"retransmits\": 0, \n                \"seconds\": 0.9999690055847168, \n                \"sender\": true, \n                \"start\": 28.000063\n            }\n        }, \n        {\n            \"streams\": [\n                {\n                    \"bits_per_second\": 859788452.2382023, \n                    \"bytes\": 107479040, \n                    \"end\": 30.000083, \n                    \"omitted\": false, \n                    \"pmtu\": 1500, \n                    \"retransmits\": 0, \n                    \"rtt\": 77087, \n                    \"rttvar\": 7, \n                    \"seconds\": 1.0000510215759277, \n                    \"sender\": true, \n                    \"snd_cwnd\": 16698336, \n                    \"snd_wnd\": -1, \n                    \"socket\": 5, \n                    \"start\": 29.000032\n                }\n            ], \n            \"sum\": {\n                \"bits_per_second\": 859788452.2382023, \n                \"bytes\": 107479040, \n                \"end\": 30.000083, \n                \"omitted\": false, \n                \"retransmits\": 0, \n                \"seconds\": 1.0000510215759277, \n                \"sender\": true, \n                \"start\": 29.000032\n            }\n        }, \n        {\n            \"streams\": [\n                {\n                    \"bits_per_second\": 870357247.3875915, \n                    \"bytes\": 108789760, \n                    \"end\": 31.000038, \n                    \"omitted\": false, \n                    \"pmtu\": 1500, \n                    \"retransmits\": 0, \n                    \"rtt\": 77086, \n                    \"rttvar\": 4, \n                    \"seconds\": 0.9999549984931946, \n                    \"sender\": true, \n                    \"snd_cwnd\": 16698336, \n                    \"snd_wnd\": -1, \n                    \"socket\": 5, \n                    \"start\": 30.000083\n                }\n            ], \n            \"sum\": {\n                \"bits_per_second\": 870357247.3875915, \n                \"bytes\": 108789760, \n                \"end\": 31.000038, \n                \"omitted\": false, \n                \"retransmits\": 0, \n                \"seconds\": 0.9999549984931946, \n                \"sender\": true, \n                \"start\": 30.000083\n            }\n        }, \n        {\n            \"streams\": [\n                {\n                    \"bits_per_second\": 859809975.5806783, \n                    \"bytes\": 107479040, \n                    \"end\": 32.000064, \n                    \"omitted\": false, \n                    \"pmtu\": 1500, \n                    \"retransmits\": 0, \n                    \"rtt\": 77086, \n                    \"rttvar\": 11, \n                    \"seconds\": 1.000025987625122, \n                    \"sender\": true, \n                    \"snd_cwnd\": 16698336, \n                    \"snd_wnd\": -1, \n                    \"socket\": 5, \n                    \"start\": 31.000038\n                }\n            ], \n            \"sum\": {\n                \"bits_per_second\": 859809975.5806783, \n                \"bytes\": 107479040, \n                \"end\": 32.000064, \n                \"omitted\": false, \n                \"retransmits\": 0, \n                \"seconds\": 1.000025987625122, \n                \"sender\": true, \n                \"start\": 31.000038\n            }\n        }, \n        {\n            \"streams\": [\n                {\n                    \"bits_per_second\": 870231976.0194473, \n                    \"bytes\": 108789760, \n                    \"end\": 33.000163, \n                    \"omitted\": false, \n                    \"pmtu\": 1500, \n                    \"retransmits\": 0, \n                    \"rtt\": 77083, \n                    \"rttvar\": 6, \n                    \"seconds\": 1.0000989437103271, \n                    \"sender\": true, \n                    \"snd_cwnd\": 16698336, \n                    \"snd_wnd\": -1, \n                    \"socket\": 5, \n                    \"start\": 32.000064\n                }\n            ], \n            \"sum\": {\n                \"bits_per_second\": 870231976.0194473, \n                \"bytes\": 108789760, \n                \"end\": 33.000163, \n                \"omitted\": false, \n                \"retransmits\": 0, \n                \"seconds\": 1.0000989437103271, \n                \"sender\": true, \n                \"start\": 32.000064\n            }\n        }, \n        {\n            \"streams\": [\n                {\n                    \"bits_per_second\": 859915711.83707, \n                    \"bytes\": 107479040, \n                    \"end\": 34.000066, \n                    \"omitted\": false, \n                    \"pmtu\": 1500, \n                    \"retransmits\": 0, \n                    \"rtt\": 77088, \n                    \"rttvar\": 5, \n                    \"seconds\": 0.9999030232429504, \n                    \"sender\": true, \n                    \"snd_cwnd\": 16698336, \n                    \"snd_wnd\": -1, \n                    \"socket\": 5, \n                    \"start\": 33.000163\n                }\n            ], \n            \"sum\": {\n                \"bits_per_second\": 859915711.83707, \n                \"bytes\": 107479040, \n                \"end\": 34.000066, \n                \"omitted\": false, \n                \"retransmits\": 0, \n                \"seconds\": 0.9999030232429504, \n                \"sender\": true, \n                \"start\": 33.000163\n            }\n        }, \n        {\n            \"streams\": [\n                {\n                    \"bits_per_second\": 870304177.7220756, \n                    \"bytes\": 108789760, \n                    \"end\": 35.000082, \n                    \"omitted\": false, \n                    \"pmtu\": 1500, \n                    \"retransmits\": 0, \n                    \"rtt\": 77091, \n                    \"rttvar\": 7, \n                    \"seconds\": 1.0000159740448, \n                    \"sender\": true, \n                    \"snd_cwnd\": 16698336, \n                    \"snd_wnd\": -1, \n                    \"socket\": 5, \n                    \"start\": 34.000066\n                }\n            ], \n            \"sum\": {\n                \"bits_per_second\": 870304177.7220756, \n                \"bytes\": 108789760, \n                \"end\": 35.000082, \n                \"omitted\": false, \n                \"retransmits\": 0, \n                \"seconds\": 1.0000159740448, \n                \"sender\": true, \n                \"start\": 34.000066\n            }\n        }, \n        {\n            \"streams\": [\n                {\n                    \"bits_per_second\": 859883060.4941255, \n                    \"bytes\": 107479040, \n                    \"end\": 36.000023, \n                    \"omitted\": false, \n                    \"pmtu\": 1500, \n                    \"retransmits\": 0, \n                    \"rtt\": 77085, \n                    \"rttvar\": 9, \n                    \"seconds\": 0.9999409914016724, \n                    \"sender\": true, \n                    \"snd_cwnd\": 16698336, \n                    \"snd_wnd\": -1, \n                    \"socket\": 5, \n                    \"start\": 35.000082\n                }\n            ], \n            \"sum\": {\n                \"bits_per_second\": 859883060.4941255, \n                \"bytes\": 107479040, \n                \"end\": 36.000023, \n                \"omitted\": false, \n                \"retransmits\": 0, \n                \"seconds\": 0.9999409914016724, \n                \"sender\": true, \n                \"start\": 35.000082\n            }\n        }, \n        {\n            \"streams\": [\n                {\n                    \"bits_per_second\": 870283221.3962377, \n                    \"bytes\": 108789760, \n                    \"end\": 37.000063, \n                    \"omitted\": false, \n                    \"pmtu\": 1500, \n                    \"retransmits\": 0, \n                    \"rtt\": 77083, \n                    \"rttvar\": 5, \n                    \"seconds\": 1.000040054321289, \n                    \"sender\": true, \n                    \"snd_cwnd\": 16698336, \n                    \"snd_wnd\": -1, \n                    \"socket\": 5, \n                    \"start\": 36.000023\n                }\n            ], \n            \"sum\": {\n                \"bits_per_second\": 870283221.3962377, \n                \"bytes\": 108789760, \n                \"end\": 37.000063, \n                \"omitted\": false, \n                \"retransmits\": 0, \n                \"seconds\": 1.000040054321289, \n                \"sender\": true, \n                \"start\": 36.000023\n            }\n        }, \n        {\n            \"streams\": [\n                {\n                    \"bits_per_second\": 859855536.8768767, \n                    \"bytes\": 107479040, \n                    \"end\": 38.000036, \n                    \"omitted\": false, \n                    \"pmtu\": 1500, \n                    \"retransmits\": 0, \n                    \"rtt\": 77087, \n                    \"rttvar\": 7, \n                    \"seconds\": 0.9999729990959167, \n                    \"sender\": true, \n                    \"snd_cwnd\": 16698336, \n                    \"snd_wnd\": -1, \n                    \"socket\": 5, \n                    \"start\": 37.000063\n                }\n            ], \n            \"sum\": {\n                \"bits_per_second\": 859855536.8768767, \n                \"bytes\": 107479040, \n                \"end\": 38.000036, \n                \"omitted\": false, \n                \"retransmits\": 0, \n                \"seconds\": 0.9999729990959167, \n                \"sender\": true, \n                \"start\": 37.000063\n            }\n        }, \n        {\n            \"streams\": [\n                {\n                    \"bits_per_second\": 870294633.131689, \n                    \"bytes\": 108789760, \n                    \"end\": 39.000063, \n                    \"omitted\": false, \n                    \"pmtu\": 1500, \n                    \"retransmits\": 0, \n                    \"rtt\": 77084, \n                    \"rttvar\": 9, \n                    \"seconds\": 1.0000269412994385, \n                    \"sender\": true, \n                    \"snd_cwnd\": 16698336, \n                    \"snd_wnd\": -1, \n                    \"socket\": 5, \n                    \"start\": 38.000036\n                }\n            ], \n            \"sum\": {\n                \"bits_per_second\": 870294633.131689, \n                \"bytes\": 108789760, \n                \"end\": 39.000063, \n                \"omitted\": false, \n                \"retransmits\": 0, \n                \"seconds\": 1.0000269412994385, \n                \"sender\": true, \n                \"start\": 38.000036\n            }\n        }, \n        {\n            \"streams\": [\n                {\n                    \"bits_per_second\": 870318080, \n                    \"bytes\": 108789760, \n                    \"end\": 40.000063, \n                    \"omitted\": false, \n                    \"pmtu\": 1500, \n                    \"retransmits\": 0, \n                    \"rtt\": 77087, \n                    \"rttvar\": 7, \n                    \"seconds\": 1, \n                    \"sender\": true, \n                    \"snd_cwnd\": 16698336, \n                    \"snd_wnd\": -1, \n                    \"socket\": 5, \n                    \"start\": 39.000063\n                }\n            ], \n            \"sum\": {\n                \"bits_per_second\": 870318080, \n                \"bytes\": 108789760, \n                \"end\": 40.000063, \n                \"omitted\": false, \n                \"retransmits\": 0, \n                \"seconds\": 1, \n                \"sender\": true, \n                \"start\": 39.000063\n            }\n        }, \n        {\n            \"streams\": [\n                {\n                    \"bits_per_second\": 859831500.000782, \n                    \"bytes\": 107479040, \n                    \"end\": 41.000064, \n                    \"omitted\": false, \n                    \"pmtu\": 1500, \n                    \"retransmits\": 0, \n                    \"rtt\": 77089, \n                    \"rttvar\": 5, \n                    \"seconds\": 1.0000009536743164, \n                    \"sender\": true, \n                    \"snd_cwnd\": 16698336, \n                    \"snd_wnd\": -1, \n                    \"socket\": 5, \n                    \"start\": 40.000063\n                }\n            ], \n            \"sum\": {\n                \"bits_per_second\": 859831500.000782, \n                \"bytes\": 107479040, \n                \"end\": 41.000064, \n                \"omitted\": false, \n                \"retransmits\": 0, \n                \"seconds\": 1.0000009536743164, \n                \"sender\": true, \n                \"start\": 40.000063\n            }\n        }, \n        {\n            \"streams\": [\n                {\n                    \"bits_per_second\": 870306771.396942, \n                    \"bytes\": 108789760, \n                    \"end\": 42.000077, \n                    \"omitted\": false, \n                    \"pmtu\": 1500, \n                    \"retransmits\": 0, \n                    \"rtt\": 77093, \n                    \"rttvar\": 12, \n                    \"seconds\": 1.000012993812561, \n                    \"sender\": true, \n                    \"snd_cwnd\": 16698336, \n                    \"snd_wnd\": -1, \n                    \"socket\": 5, \n                    \"start\": 41.000064\n                }\n            ], \n            \"sum\": {\n                \"bits_per_second\": 870306771.396942, \n                \"bytes\": 108789760, \n                \"end\": 42.000077, \n                \"omitted\": false, \n                \"retransmits\": 0, \n                \"seconds\": 1.000012993812561, \n                \"sender\": true, \n                \"start\": 41.000064\n            }\n        }, \n        {\n            \"streams\": [\n                {\n                    \"bits_per_second\": 859843492.6451752, \n                    \"bytes\": 107479040, \n                    \"end\": 43.000064, \n                    \"omitted\": false, \n                    \"pmtu\": 1500, \n                    \"retransmits\": 0, \n                    \"rtt\": 77086, \n                    \"rttvar\": 10, \n                    \"seconds\": 0.999987006187439, \n                    \"sender\": true, \n                    \"snd_cwnd\": 16698336, \n                    \"snd_wnd\": -1, \n                    \"socket\": 5, \n                    \"start\": 42.000077\n                }\n            ], \n            \"sum\": {\n                \"bits_per_second\": 859843492.6451752, \n                \"bytes\": 107479040, \n                \"end\": 43.000064, \n                \"omitted\": false, \n                \"retransmits\": 0, \n                \"seconds\": 0.999987006187439, \n                \"sender\": true, \n                \"start\": 42.000077\n            }\n        }, \n        {\n            \"streams\": [\n                {\n                    \"bits_per_second\": 870301584.0626686, \n                    \"bytes\": 108789760, \n                    \"end\": 44.000083, \n                    \"omitted\": false, \n                    \"pmtu\": 1500, \n                    \"retransmits\": 0, \n                    \"rtt\": 77087, \n                    \"rttvar\": 6, \n                    \"seconds\": 1.0000189542770386, \n                    \"sender\": true, \n                    \"snd_cwnd\": 16698336, \n                    \"snd_wnd\": -1, \n                    \"socket\": 5, \n                    \"start\": 43.000064\n                }\n            ], \n            \"sum\": {\n                \"bits_per_second\": 870301584.0626686, \n                \"bytes\": 108789760, \n                \"end\": 44.000083, \n                \"omitted\": false, \n                \"retransmits\": 0, \n                \"seconds\": 1.0000189542770386, \n                \"sender\": true, \n                \"start\": 43.000064\n            }\n        }, \n        {\n            \"streams\": [\n                {\n                    \"bits_per_second\": 859810795.5388423, \n                    \"bytes\": 107479040, \n                    \"end\": 45.000108, \n                    \"omitted\": false, \n                    \"pmtu\": 1500, \n                    \"retransmits\": 0, \n                    \"rtt\": 77084, \n                    \"rttvar\": 6, \n                    \"seconds\": 1.0000250339508057, \n                    \"sender\": true, \n                    \"snd_cwnd\": 16698336, \n                    \"snd_wnd\": -1, \n                    \"socket\": 5, \n                    \"start\": 44.000083\n                }\n            ], \n            \"sum\": {\n                \"bits_per_second\": 859810795.5388423, \n                \"bytes\": 107479040, \n                \"end\": 45.000108, \n                \"omitted\": false, \n                \"retransmits\": 0, \n                \"seconds\": 1.0000250339508057, \n                \"sender\": true, \n                \"start\": 44.000083\n            }\n        }, \n        {\n            \"streams\": [\n                {\n                    \"bits_per_second\": 870356365.4341084, \n                    \"bytes\": 108789760, \n                    \"end\": 46.000064, \n                    \"omitted\": false, \n                    \"pmtu\": 1500, \n                    \"retransmits\": 0, \n                    \"rtt\": 77086, \n                    \"rttvar\": 7, \n                    \"seconds\": 0.9999560117721558, \n                    \"sender\": true, \n                    \"snd_cwnd\": 16698336, \n                    \"snd_wnd\": -1, \n                    \"socket\": 5, \n                    \"start\": 45.000108\n                }\n            ], \n            \"sum\": {\n                \"bits_per_second\": 870356365.4341084, \n                \"bytes\": 108789760, \n                \"end\": 46.000064, \n                \"omitted\": false, \n                \"retransmits\": 0, \n                \"seconds\": 0.9999560117721558, \n                \"sender\": true, \n                \"start\": 45.000108\n            }\n        }, \n        {\n            \"streams\": [\n                {\n                    \"bits_per_second\": 859815100.3448608, \n                    \"bytes\": 107479040, \n                    \"end\": 47.000084, \n                    \"omitted\": false, \n                    \"pmtu\": 1500, \n                    \"retransmits\": 0, \n                    \"rtt\": 77084, \n                    \"rttvar\": 3, \n                    \"seconds\": 1.0000200271606445, \n                    \"sender\": true, \n                    \"snd_cwnd\": 16698336, \n                    \"snd_wnd\": -1, \n                    \"socket\": 5, \n                    \"start\": 46.000064\n                }\n            ], \n            \"sum\": {\n                \"bits_per_second\": 859815100.3448608, \n                \"bytes\": 107479040, \n                \"end\": 47.000084, \n                \"omitted\": false, \n                \"retransmits\": 0, \n                \"seconds\": 1.0000200271606445, \n                \"sender\": true, \n                \"start\": 46.000064\n            }\n        }, \n        {\n            \"streams\": [\n                {\n                    \"bits_per_second\": 870336340.383118, \n                    \"bytes\": 108789760, \n                    \"end\": 48.000063, \n                    \"omitted\": false, \n                    \"pmtu\": 1500, \n                    \"retransmits\": 0, \n                    \"rtt\": 77080, \n                    \"rttvar\": 4, \n                    \"seconds\": 0.999979019165039, \n                    \"sender\": true, \n                    \"snd_cwnd\": 16698336, \n                    \"snd_wnd\": -1, \n                    \"socket\": 5, \n                    \"start\": 47.000084\n                }\n            ], \n            \"sum\": {\n                \"bits_per_second\": 870336340.383118, \n                \"bytes\": 108789760, \n                \"end\": 48.000063, \n                \"omitted\": false, \n                \"retransmits\": 0, \n                \"seconds\": 0.999979019165039, \n                \"sender\": true, \n                \"start\": 47.000084\n            }\n        }, \n        {\n            \"streams\": [\n                {\n                    \"bits_per_second\": 859818585.2194, \n                    \"bytes\": 107479040, \n                    \"end\": 49.000079, \n                    \"omitted\": false, \n                    \"pmtu\": 1500, \n                    \"retransmits\": 0, \n                    \"rtt\": 77090, \n                    \"rttvar\": 7, \n                    \"seconds\": 1.0000159740448, \n                    \"sender\": true, \n                    \"snd_cwnd\": 16698336, \n                    \"snd_wnd\": -1, \n                    \"socket\": 5, \n                    \"start\": 48.000063\n                }\n            ], \n            \"sum\": {\n                \"bits_per_second\": 859818585.2194, \n                \"bytes\": 107479040, \n                \"end\": 49.000079, \n                \"omitted\": false, \n                \"retransmits\": 0, \n                \"seconds\": 1.0000159740448, \n                \"sender\": true, \n                \"start\": 48.000063\n            }\n        }, \n        {\n            \"streams\": [\n                {\n                    \"bits_per_second\": 870331982.7220827, \n                    \"bytes\": 108789760, \n                    \"end\": 50.000063, \n                    \"omitted\": false, \n                    \"pmtu\": 1500, \n                    \"retransmits\": 0, \n                    \"rtt\": 77090, \n                    \"rttvar\": 8, \n                    \"seconds\": 0.9999840259552002, \n                    \"sender\": true, \n                    \"snd_cwnd\": 16698336, \n                    \"snd_wnd\": -1, \n                    \"socket\": 5, \n                    \"start\": 49.000079\n                }\n            ], \n            \"sum\": {\n                \"bits_per_second\": 870331982.7220827, \n                \"bytes\": 108789760, \n                \"end\": 50.000063, \n                \"omitted\": false, \n                \"retransmits\": 0, \n                \"seconds\": 0.9999840259552002, \n                \"sender\": true, \n                \"start\": 49.000079\n            }\n        }, \n        {\n            \"streams\": [\n                {\n                    \"bits_per_second\": 870229279.0615276, \n                    \"bytes\": 108789760, \n                    \"end\": 51.000165, \n                    \"omitted\": false, \n                    \"pmtu\": 1500, \n                    \"retransmits\": 0, \n                    \"rtt\": 77086, \n                    \"rttvar\": 7, \n                    \"seconds\": 1.0001020431518555, \n                    \"sender\": true, \n                    \"snd_cwnd\": 16698336, \n                    \"snd_wnd\": -1, \n                    \"socket\": 5, \n                    \"start\": 50.000063\n                }\n            ], \n            \"sum\": {\n                \"bits_per_second\": 870229279.0615276, \n                \"bytes\": 108789760, \n                \"end\": 51.000165, \n                \"omitted\": false, \n                \"retransmits\": 0, \n                \"seconds\": 1.0001020431518555, \n                \"sender\": true, \n                \"start\": 50.000063\n            }\n        }, \n        {\n            \"streams\": [\n                {\n                    \"bits_per_second\": 859833191.250883, \n                    \"bytes\": 107479040, \n                    \"end\": 52.000164, \n                    \"omitted\": false, \n                    \"pmtu\": 1500, \n                    \"retransmits\": 0, \n                    \"rtt\": 77090, \n                    \"rttvar\": 7, \n                    \"seconds\": 0.9999989867210388, \n                    \"sender\": true, \n                    \"snd_cwnd\": 16698336, \n                    \"snd_wnd\": -1, \n                    \"socket\": 5, \n                    \"start\": 51.000165\n                }\n            ], \n            \"sum\": {\n                \"bits_per_second\": 859833191.250883, \n                \"bytes\": 107479040, \n                \"end\": 52.000164, \n                \"omitted\": false, \n                \"retransmits\": 0, \n                \"seconds\": 0.9999989867210388, \n                \"sender\": true, \n                \"start\": 51.000165\n            }\n        }, \n        {\n            \"streams\": [\n                {\n                    \"bits_per_second\": 870322437.5218172, \n                    \"bytes\": 108789760, \n                    \"end\": 53.000159, \n                    \"omitted\": false, \n                    \"pmtu\": 1500, \n                    \"retransmits\": 0, \n                    \"rtt\": 77086, \n                    \"rttvar\": 5, \n                    \"seconds\": 0.999994993209839, \n                    \"sender\": true, \n                    \"snd_cwnd\": 16698336, \n                    \"snd_wnd\": -1, \n                    \"socket\": 5, \n                    \"start\": 52.000164\n                }\n            ], \n            \"sum\": {\n                \"bits_per_second\": 870322437.5218172, \n                \"bytes\": 108789760, \n                \"end\": 53.000159, \n                \"omitted\": false, \n                \"retransmits\": 0, \n                \"seconds\": 0.999994993209839, \n                \"sender\": true, \n                \"start\": 52.000164\n            }\n        }, \n        {\n            \"streams\": [\n                {\n                    \"bits_per_second\": 859893363.0833955, \n                    \"bytes\": 107479040, \n                    \"end\": 54.000088, \n                    \"omitted\": false, \n                    \"pmtu\": 1500, \n                    \"retransmits\": 0, \n                    \"rtt\": 77090, \n                    \"rttvar\": 6, \n                    \"seconds\": 0.9999290108680725, \n                    \"sender\": true, \n                    \"snd_cwnd\": 16698336, \n                    \"snd_wnd\": -1, \n                    \"socket\": 5, \n                    \"start\": 53.000159\n                }\n            ], \n            \"sum\": {\n                \"bits_per_second\": 859893363.0833955, \n                \"bytes\": 107479040, \n                \"end\": 54.000088, \n                \"omitted\": false, \n                \"retransmits\": 0, \n                \"seconds\": 0.9999290108680725, \n                \"sender\": true, \n                \"start\": 53.000159\n            }\n        }, \n        {\n            \"streams\": [\n                {\n                    \"bits_per_second\": 870266726.7802815, \n                    \"bytes\": 108789760, \n                    \"end\": 55.000147, \n                    \"omitted\": false, \n                    \"pmtu\": 1500, \n                    \"retransmits\": 0, \n                    \"rtt\": 77084, \n                    \"rttvar\": 6, \n                    \"seconds\": 1.0000590085983276, \n                    \"sender\": true, \n                    \"snd_cwnd\": 16698336, \n                    \"snd_wnd\": -1, \n                    \"socket\": 5, \n                    \"start\": 54.000088\n                }\n            ], \n            \"sum\": {\n                \"bits_per_second\": 870266726.7802815, \n                \"bytes\": 108789760, \n                \"end\": 55.000147, \n                \"omitted\": false, \n                \"retransmits\": 0, \n                \"seconds\": 1.0000590085983276, \n                \"sender\": true, \n                \"start\": 54.000088\n            }\n        }, \n        {\n            \"streams\": [\n                {\n                    \"bits_per_second\": 859827195.030547, \n                    \"bytes\": 107479040, \n                    \"end\": 56.000153, \n                    \"omitted\": false, \n                    \"pmtu\": 1500, \n                    \"retransmits\": 0, \n                    \"rtt\": 77090, \n                    \"rttvar\": 9, \n                    \"seconds\": 1.0000059604644775, \n                    \"sender\": true, \n                    \"snd_cwnd\": 16698336, \n                    \"snd_wnd\": -1, \n                    \"socket\": 5, \n                    \"start\": 55.000147\n                }\n            ], \n            \"sum\": {\n                \"bits_per_second\": 859827195.030547, \n                \"bytes\": 107479040, \n                \"end\": 56.000153, \n                \"omitted\": false, \n                \"retransmits\": 0, \n                \"seconds\": 1.0000059604644775, \n                \"sender\": true, \n                \"start\": 55.000147\n            }\n        }, \n        {\n            \"streams\": [\n                {\n                    \"bits_per_second\": 870374679.3055774, \n                    \"bytes\": 108789760, \n                    \"end\": 57.000088, \n                    \"omitted\": false, \n                    \"pmtu\": 1500, \n                    \"retransmits\": 0, \n                    \"rtt\": 77085, \n                    \"rttvar\": 5, \n                    \"seconds\": 0.99993497133255, \n                    \"sender\": true, \n                    \"snd_cwnd\": 16698336, \n                    \"snd_wnd\": -1, \n                    \"socket\": 5, \n                    \"start\": 56.000153\n                }\n            ], \n            \"sum\": {\n                \"bits_per_second\": 870374679.3055774, \n                \"bytes\": 108789760, \n                \"end\": 57.000088, \n                \"omitted\": false, \n                \"retransmits\": 0, \n                \"seconds\": 0.99993497133255, \n                \"sender\": true, \n                \"start\": 56.000153\n            }\n        }, \n        {\n            \"streams\": [\n                {\n                    \"bits_per_second\": 859775538.7499443, \n                    \"bytes\": 107479040, \n                    \"end\": 58.000154, \n                    \"omitted\": false, \n                    \"pmtu\": 1500, \n                    \"retransmits\": 0, \n                    \"rtt\": 77087, \n                    \"rttvar\": 7, \n                    \"seconds\": 1.0000660419464111, \n                    \"sender\": true, \n                    \"snd_cwnd\": 16698336, \n                    \"snd_wnd\": -1, \n                    \"socket\": 5, \n                    \"start\": 57.000088\n                }\n            ], \n            \"sum\": {\n                \"bits_per_second\": 859775538.7499443, \n                \"bytes\": 107479040, \n                \"end\": 58.000154, \n                \"omitted\": false, \n                \"retransmits\": 0, \n                \"seconds\": 1.0000660419464111, \n                \"sender\": true, \n                \"start\": 57.000088\n            }\n        }, \n        {\n            \"streams\": [\n                {\n                    \"bits_per_second\": 870396418.300683, \n                    \"bytes\": 108789760, \n                    \"end\": 59.000064, \n                    \"omitted\": false, \n                    \"pmtu\": 1500, \n                    \"retransmits\": 0, \n                    \"rtt\": 77091, \n                    \"rttvar\": 8, \n                    \"seconds\": 0.999909996986389, \n                    \"sender\": true, \n                    \"snd_cwnd\": 16698336, \n                    \"snd_wnd\": -1, \n                    \"socket\": 5, \n                    \"start\": 58.000154\n                }\n            ], \n            \"sum\": {\n                \"bits_per_second\": 870396418.300683, \n                \"bytes\": 108789760, \n                \"end\": 59.000064, \n                \"omitted\": false, \n                \"retransmits\": 0, \n                \"seconds\": 0.999909996986389, \n                \"sender\": true, \n                \"start\": 58.000154\n            }\n        }, \n        {\n            \"streams\": [\n                {\n                    \"bits_per_second\": 859825452.5548505, \n                    \"bytes\": 107479040, \n                    \"end\": 60.000072, \n                    \"omitted\": false, \n                    \"pmtu\": 1500, \n                    \"retransmits\": 0, \n                    \"rtt\": 77085, \n                    \"rttvar\": 7, \n                    \"seconds\": 1.0000079870224, \n                    \"sender\": true, \n                    \"snd_cwnd\": 16698336, \n                    \"snd_wnd\": -1, \n                    \"socket\": 5, \n                    \"start\": 59.000064\n                }\n            ], \n            \"sum\": {\n                \"bits_per_second\": 859825452.5548505, \n                \"bytes\": 107479040, \n                \"end\": 60.000072, \n                \"omitted\": false, \n                \"retransmits\": 0, \n                \"seconds\": 1.0000079870224, \n                \"sender\": true, \n                \"start\": 59.000064\n            }\n        }\n    ], \n    \"start\": {\n        \"connected\": [\n            {\n                \"local_host\": \"10.0.0.1\", \n                \"local_port\": 57371, \n                \"remote_host\": \"10.0.0.2\", \n                \"remote_port\": 5201, \n                \"socket\": 5\n            }\n        ], \n        \"connecting_to\": {\n            \"host\": \"10.0.0.2\", \n            \"port\": 5201\n        }, \n        \"cookie\": \"jn2indy2ya5d43furt7jqyupgebwm6h3zpvk\", \n        \"fq_rate\": 0, \n        \"rcvbuf_actual\": 87380, \n        \"sndbuf_actual\": 87380, \n        \"sock_bufsize\": 0, \n        \"system_info\": \"REDACTED\", \n        \"target_bitrate\": 0, \n        \"tcp_mss_default\": 1448, \n        \"test_start\": {\n            \"bidir\": 0, \n            \"blksize\": 131072, \n            \"blocks\": 0, \n            \"bytes\": 0, \n            \"duration\": 60, \n            \"fqrate\": 0, \n            \"num_streams\": 1, \n            \"omit\": 0, \n            \"protocol\": \"TCP\", \n            \"reverse\": 0, \n            \"target_bitrate\": 0, \n            \"tos\": 0\n        }, \n        \"timestamp\": {\n            \"time\": \"Wed, 17 Apr 2024 01:24:34 GMT\", \n            \"timesecs\": 1713317074\n        }, \n        \"version\": \"iperf 3.14\"\n    }\n}\nParticipant 1:\n/usr/bin/iperf3 -s -1 --idle-timeout 60 --json -p 5201 -B 10.0.0.2 --authorized-users-path /var/run/pscheduler-server/runner/tmp/tmpk5qhke76/tmp6yn2t5o4/credentials --rsa-private-key-path /var/run/pscheduler-server/runner/tmp/tmpk5qhke76/tmp6yn2t5o4/private-key\n\n{\n    \"end\": {\n        \"cpu_utilization_percent\": {\n            \"host_system\": 5.25446255846583, \n            \"host_total\": 5.749266124797368, \n            \"host_user\": 0.4948068953941287, \n            \"remote_system\": 0, \n            \"remote_total\": 0, \n            \"remote_user\": 0\n        }, \n        \"receiver_tcp_congestion\": \"htcp\", \n        \"streams\": [\n            {\n                \"receiver\": {\n                    \"bits_per_second\": 865535626.139247, \n                    \"bytes\": 6499843216, \n                    \"end\": 60.076956, \n                    \"seconds\": 60.076956, \n                    \"sender\": false, \n                    \"socket\": 5, \n                    \"start\": 0\n                }, \n                \"sender\": {\n                    \"bits_per_second\": 0, \n                    \"bytes\": 0, \n                    \"end\": 60.076956, \n                    \"seconds\": 60.076956, \n                    \"sender\": false, \n                    \"socket\": 5, \n                    \"start\": 0\n                }\n            }\n        ], \n        \"sum_received\": {\n            \"bits_per_second\": 865535626.139247, \n            \"bytes\": 6499843216, \n            \"end\": 60.076956, \n            \"seconds\": 60.076956, \n            \"sender\": false, \n            \"start\": 0\n        }, \n        \"sum_sent\": {\n            \"bits_per_second\": 0, \n            \"bytes\": 0, \n            \"end\": 60.076956, \n            \"seconds\": 60.076956, \n            \"sender\": false, \n            \"start\": 0\n        }\n    }, \n    \"intervals\": [\n        {\n            \"streams\": [\n                {\n                    \"bits_per_second\": 865315990.3516215, \n                    \"bytes\": 108168496, \n                    \"end\": 1.000037, \n                    \"omitted\": false, \n                    \"seconds\": 1.0000369548797607, \n                    \"sender\": false, \n                    \"socket\": 5, \n                    \"start\": 0\n                }\n            ], \n            \"sum\": {\n                \"bits_per_second\": 865315990.3516215, \n                \"bytes\": 108168496, \n                \"end\": 1.000037, \n                \"omitted\": false, \n                \"seconds\": 1.0000369548797607, \n                \"sender\": false, \n                \"start\": 0\n            }\n        }, \n        {\n            \"streams\": [\n                {\n                    \"bits_per_second\": 865304066.391117, \n                    \"bytes\": 108165600, \n                    \"end\": 2.000061, \n                    \"omitted\": false, \n                    \"seconds\": 1.0000239610672, \n                    \"sender\": false, \n                    \"socket\": 5, \n                    \"start\": 1.000037\n                }\n            ], \n            \"sum\": {\n                \"bits_per_second\": 865304066.391117, \n                \"bytes\": 108165600, \n                \"end\": 2.000061, \n                \"omitted\": false, \n                \"seconds\": 1.0000239610672, \n                \"sender\": false, \n                \"start\": 1.000037\n            }\n        }, \n        {\n            \"streams\": [\n                {\n                    \"bits_per_second\": 865303138.0438102, \n                    \"bytes\": 108165600, \n                    \"end\": 3.000086, \n                    \"omitted\": false, \n                    \"seconds\": 1.0000250339508057, \n                    \"sender\": false, \n                    \"socket\": 5, \n                    \"start\": 2.000061\n                }\n            ], \n            \"sum\": {\n                \"bits_per_second\": 865303138.0438102, \n                \"bytes\": 108165600, \n                \"end\": 3.000086, \n                \"omitted\": false, \n                \"seconds\": 1.0000250339508057, \n                \"sender\": false, \n                \"start\": 2.000061\n            }\n        }, \n        {\n            \"streams\": [\n                {\n                    \"bits_per_second\": 865866001.3192767, \n                    \"bytes\": 108230760, \n                    \"end\": 4.000063, \n                    \"omitted\": false, \n                    \"seconds\": 0.9999769926071167, \n                    \"sender\": false, \n                    \"socket\": 5, \n                    \"start\": 3.000086\n                }\n            ], \n            \"sum\": {\n                \"bits_per_second\": 865866001.3192767, \n                \"bytes\": 108230760, \n                \"end\": 4.000063, \n                \"omitted\": false, \n                \"seconds\": 0.9999769926071167, \n                \"sender\": false, \n                \"start\": 3.000086\n            }\n        }, \n        {\n            \"streams\": [\n                {\n                    \"bits_per_second\": 865309223.9124285, \n                    \"bytes\": 108165600, \n                    \"end\": 5.000081, \n                    \"omitted\": false, \n                    \"seconds\": 1.0000180006027222, \n                    \"sender\": false, \n                    \"socket\": 5, \n                    \"start\": 4.000063\n                }\n            ], \n            \"sum\": {\n                \"bits_per_second\": 865309223.9124285, \n                \"bytes\": 108165600, \n                \"end\": 5.000081, \n                \"omitted\": false, \n                \"seconds\": 1.0000180006027222, \n                \"sender\": false, \n                \"start\": 4.000063\n            }\n        }, \n        {\n            \"streams\": [\n                {\n                    \"bits_per_second\": 865862543.4079545, \n                    \"bytes\": 108230760, \n                    \"end\": 6.000062, \n                    \"omitted\": false, \n                    \"seconds\": 0.9999809861183167, \n                    \"sender\": false, \n                    \"socket\": 5, \n                    \"start\": 5.000081\n                }\n            ], \n            \"sum\": {\n                \"bits_per_second\": 865862543.4079545, \n                \"bytes\": 108230760, \n                \"end\": 6.000062, \n                \"omitted\": false, \n                \"seconds\": 0.9999809861183167, \n                \"sender\": false, \n                \"start\": 5.000081\n            }\n        }, \n        {\n            \"streams\": [\n                {\n                    \"bits_per_second\": 865312731.0620387, \n                    \"bytes\": 108165600, \n                    \"end\": 7.000076, \n                    \"omitted\": false, \n                    \"seconds\": 1.0000139474868774, \n                    \"sender\": false, \n                    \"socket\": 5, \n                    \"start\": 6.000062\n                }\n            ], \n            \"sum\": {\n                \"bits_per_second\": 865312731.0620387, \n                \"bytes\": 108165600, \n                \"end\": 7.000076, \n                \"omitted\": false, \n                \"seconds\": 1.0000139474868774, \n                \"sender\": false, \n                \"start\": 6.000062\n            }\n        }, \n        {\n            \"streams\": [\n                {\n                    \"bits_per_second\": 865861666.0318626, \n                    \"bytes\": 108230760, \n                    \"end\": 8.000058, \n                    \"omitted\": false, \n                    \"seconds\": 0.9999819993972778, \n                    \"sender\": false, \n                    \"socket\": 5, \n                    \"start\": 7.000076\n                }\n            ], \n            \"sum\": {\n                \"bits_per_second\": 865861666.0318626, \n                \"bytes\": 108230760, \n                \"end\": 8.000058, \n                \"omitted\": false, \n                \"seconds\": 0.9999819993972778, \n                \"sender\": false, \n                \"start\": 7.000076\n            }\n        }, \n        {\n            \"streams\": [\n                {\n                    \"bits_per_second\": 865323046.372725, \n                    \"bytes\": 108165600, \n                    \"end\": 9.00006, \n                    \"omitted\": false, \n                    \"seconds\": 1.0000020265579224, \n                    \"sender\": false, \n                    \"socket\": 5, \n                    \"start\": 8.000058\n                }\n            ], \n            \"sum\": {\n                \"bits_per_second\": 865323046.372725, \n                \"bytes\": 108165600, \n                \"end\": 9.00006, \n                \"omitted\": false, \n                \"seconds\": 1.0000020265579224, \n                \"sender\": false, \n                \"start\": 8.000058\n            }\n        }, \n        {\n            \"streams\": [\n                {\n                    \"bits_per_second\": 865308398.704887, \n                    \"bytes\": 108165600, \n                    \"end\": 10.000079, \n                    \"omitted\": false, \n                    \"seconds\": 1.0000189542770386, \n                    \"sender\": false, \n                    \"socket\": 5, \n                    \"start\": 9.00006\n                }\n            ], \n            \"sum\": {\n                \"bits_per_second\": 865308398.704887, \n                \"bytes\": 108165600, \n                \"end\": 10.000079, \n                \"omitted\": false, \n                \"seconds\": 1.0000189542770386, \n                \"sender\": false, \n                \"start\": 9.00006\n            }\n        }, \n        {\n            \"streams\": [\n                {\n                    \"bits_per_second\": 865860788.657549, \n                    \"bytes\": 108230760, \n                    \"end\": 11.000062, \n                    \"omitted\": false, \n                    \"seconds\": 0.999983012676239, \n                    \"sender\": false, \n                    \"socket\": 5, \n                    \"start\": 10.000079\n                }\n            ], \n            \"sum\": {\n                \"bits_per_second\": 865860788.657549, \n                \"bytes\": 108230760, \n                \"end\": 11.000062, \n                \"omitted\": false, \n                \"seconds\": 0.999983012676239, \n                \"sender\": false, \n                \"start\": 10.000079\n            }\n        }, \n        {\n            \"streams\": [\n                {\n                    \"bits_per_second\": 865308398.704887, \n                    \"bytes\": 108165600, \n                    \"end\": 12.000081, \n                    \"omitted\": false, \n                    \"seconds\": 1.0000189542770386, \n                    \"sender\": false, \n                    \"socket\": 5, \n                    \"start\": 11.000062\n                }\n            ], \n            \"sum\": {\n                \"bits_per_second\": 865308398.704887, \n                \"bytes\": 108165600, \n                \"end\": 12.000081, \n                \"omitted\": false, \n                \"seconds\": 1.0000189542770386, \n                \"sender\": false, \n                \"start\": 11.000062\n            }\n        }, \n        {\n            \"streams\": [\n                {\n                    \"bits_per_second\": 865863420.7858243, \n                    \"bytes\": 108230760, \n                    \"end\": 13.000061, \n                    \"omitted\": false, \n                    \"seconds\": 0.9999799728393555, \n                    \"sender\": false, \n                    \"socket\": 5, \n                    \"start\": 12.000081\n                }\n            ], \n            \"sum\": {\n                \"bits_per_second\": 865863420.7858243, \n                \"bytes\": 108230760, \n                \"end\": 13.000061, \n                \"omitted\": false, \n                \"seconds\": 0.9999799728393555, \n                \"sender\": false, \n                \"start\": 12.000081\n            }\n        }, \n        {\n            \"streams\": [\n                {\n                    \"bits_per_second\": 865307470.3482844, \n                    \"bytes\": 108165600, \n                    \"end\": 14.000081, \n                    \"omitted\": false, \n                    \"seconds\": 1.0000200271606445, \n                    \"sender\": false, \n                    \"socket\": 5, \n                    \"start\": 13.000061\n                }\n            ], \n            \"sum\": {\n                \"bits_per_second\": 865307470.3482844, \n                \"bytes\": 108165600, \n                \"end\": 14.000081, \n                \"omitted\": false, \n                \"seconds\": 1.0000200271606445, \n                \"sender\": false, \n                \"start\": 13.000061\n            }\n        }, \n        {\n            \"streams\": [\n                {\n                    \"bits_per_second\": 865859911.2850132, \n                    \"bytes\": 108230760, \n                    \"end\": 15.000065, \n                    \"omitted\": false, \n                    \"seconds\": 0.9999840259552002, \n                    \"sender\": false, \n                    \"socket\": 5, \n                    \"start\": 14.000081\n                }\n            ], \n            \"sum\": {\n                \"bits_per_second\": 865859911.2850132, \n                \"bytes\": 108230760, \n                \"end\": 15.000065, \n                \"omitted\": false, \n                \"seconds\": 0.9999840259552002, \n                \"sender\": false, \n                \"start\": 14.000081\n            }\n        }, \n        {\n            \"streams\": [\n                {\n                    \"bits_per_second\": 865328255.6980808, \n                    \"bytes\": 108165600, \n                    \"end\": 16.000061, \n                    \"omitted\": false, \n                    \"seconds\": 0.9999960064888, \n                    \"sender\": false, \n                    \"socket\": 5, \n                    \"start\": 15.000065\n                }\n            ], \n            \"sum\": {\n                \"bits_per_second\": 865328255.6980808, \n                \"bytes\": 108165600, \n                \"end\": 16.000061, \n                \"omitted\": false, \n                \"seconds\": 0.9999960064888, \n                \"sender\": false, \n                \"start\": 15.000065\n            }\n        }, \n        {\n            \"streams\": [\n                {\n                    \"bits_per_second\": 865301487.6535165, \n                    \"bytes\": 108165600, \n                    \"end\": 17.000088, \n                    \"omitted\": false, \n                    \"seconds\": 1.0000269412994385, \n                    \"sender\": false, \n                    \"socket\": 5, \n                    \"start\": 16.000061\n                }\n            ], \n            \"sum\": {\n                \"bits_per_second\": 865301487.6535165, \n                \"bytes\": 108165600, \n                \"end\": 17.000088, \n                \"omitted\": false, \n                \"seconds\": 1.0000269412994385, \n                \"sender\": false, \n                \"start\": 16.000061\n            }\n        }, \n        {\n            \"streams\": [\n                {\n                    \"bits_per_second\": 865794165.0142238, \n                    \"bytes\": 108230760, \n                    \"end\": 18.000148, \n                    \"omitted\": false, \n                    \"seconds\": 1.000059962272644, \n                    \"sender\": false, \n                    \"socket\": 5, \n                    \"start\": 17.000088\n                }\n            ], \n            \"sum\": {\n                \"bits_per_second\": 865794165.0142238, \n                \"bytes\": 108230760, \n                \"end\": 18.000148, \n                \"omitted\": false, \n                \"seconds\": 1.000059962272644, \n                \"sender\": false, \n                \"start\": 17.000088\n            }\n        }, \n        {\n            \"streams\": [\n                {\n                    \"bits_per_second\": 865382776.8563024, \n                    \"bytes\": 108165600, \n                    \"end\": 19.000081, \n                    \"omitted\": false, \n                    \"seconds\": 0.9999330043792725, \n                    \"sender\": false, \n                    \"socket\": 5, \n                    \"start\": 18.000148\n                }\n            ], \n            \"sum\": {\n                \"bits_per_second\": 865382776.8563024, \n                \"bytes\": 108165600, \n                \"end\": 19.000081, \n                \"omitted\": false, \n                \"seconds\": 0.9999330043792725, \n                \"sender\": false, \n                \"start\": 18.000148\n            }\n        }, \n        {\n            \"streams\": [\n                {\n                    \"bits_per_second\": 865861666.0318626, \n                    \"bytes\": 108230760, \n                    \"end\": 20.000063, \n                    \"omitted\": false, \n                    \"seconds\": 0.9999819993972778, \n                    \"sender\": false, \n                    \"socket\": 5, \n                    \"start\": 19.000081\n                }\n            ], \n            \"sum\": {\n                \"bits_per_second\": 865861666.0318626, \n                \"bytes\": 108230760, \n                \"end\": 20.000063, \n                \"omitted\": false, \n                \"seconds\": 0.9999819993972778, \n                \"sender\": false, \n                \"start\": 19.000081\n            }\n        }, \n        {\n            \"streams\": [\n                {\n                    \"bits_per_second\": 865306645.1440877, \n                    \"bytes\": 108165600, \n                    \"end\": 21.000084, \n                    \"omitted\": false, \n                    \"seconds\": 1.000020980834961, \n                    \"sender\": false, \n                    \"socket\": 5, \n                    \"start\": 20.000063\n                }\n            ], \n            \"sum\": {\n                \"bits_per_second\": 865306645.1440877, \n                \"bytes\": 108165600, \n                \"end\": 21.000084, \n                \"omitted\": false, \n                \"seconds\": 1.000020980834961, \n                \"sender\": false, \n                \"start\": 20.000063\n            }\n        }, \n        {\n            \"streams\": [\n                {\n                    \"bits_per_second\": 865879007.4419992, \n                    \"bytes\": 108230760, \n                    \"end\": 22.000046, \n                    \"omitted\": false, \n                    \"seconds\": 0.9999619722366333, \n                    \"sender\": false, \n                    \"socket\": 5, \n                    \"start\": 21.000084\n                }\n            ], \n            \"sum\": {\n                \"bits_per_second\": 865879007.4419992, \n                \"bytes\": 108230760, \n                \"end\": 22.000046, \n                \"omitted\": false, \n                \"seconds\": 0.9999619722366333, \n                \"sender\": false, \n                \"start\": 21.000084\n            }\n        }, \n        {\n            \"streams\": [\n                {\n                    \"bits_per_second\": 865310977.48368, \n                    \"bytes\": 108165600, \n                    \"end\": 23.000062, \n                    \"omitted\": false, \n                    \"seconds\": 1.0000159740448, \n                    \"sender\": false, \n                    \"socket\": 5, \n                    \"start\": 22.000046\n                }\n            ], \n            \"sum\": {\n                \"bits_per_second\": 865310977.48368, \n                \"bytes\": 108165600, \n                \"end\": 23.000062, \n                \"omitted\": false, \n                \"seconds\": 1.0000159740448, \n                \"sender\": false, \n                \"start\": 22.000046\n            }\n        }, \n        {\n            \"streams\": [\n                {\n                    \"bits_per_second\": 865304891.5903953, \n                    \"bytes\": 108165600, \n                    \"end\": 24.000085, \n                    \"omitted\": false, \n                    \"seconds\": 1.0000230073928833, \n                    \"sender\": false, \n                    \"socket\": 5, \n                    \"start\": 23.000062\n                }\n            ], \n            \"sum\": {\n                \"bits_per_second\": 865304891.5903953, \n                \"bytes\": 108165600, \n                \"end\": 24.000085, \n                \"omitted\": false, \n                \"seconds\": 1.0000230073928833, \n                \"sender\": false, \n                \"start\": 23.000062\n            }\n        }, \n        {\n            \"streams\": [\n                {\n                    \"bits_per_second\": 865865123.936177, \n                    \"bytes\": 108230760, \n                    \"end\": 25.000063, \n                    \"omitted\": false, \n                    \"seconds\": 0.999978005886078, \n                    \"sender\": false, \n                    \"socket\": 5, \n                    \"start\": 24.000085\n                }\n            ], \n            \"sum\": {\n                \"bits_per_second\": 865865123.936177, \n                \"bytes\": 108230760, \n                \"end\": 25.000063, \n                \"omitted\": false, \n                \"seconds\": 0.999978005886078, \n                \"sender\": false, \n                \"start\": 24.000085\n            }\n        }, \n        {\n            \"streams\": [\n                {\n                    \"bits_per_second\": 865309223.9124285, \n                    \"bytes\": 108165600, \n                    \"end\": 26.000081, \n                    \"omitted\": false, \n                    \"seconds\": 1.0000180006027222, \n                    \"sender\": false, \n                    \"socket\": 5, \n                    \"start\": 25.000063\n                }\n            ], \n            \"sum\": {\n                \"bits_per_second\": 865309223.9124285, \n                \"bytes\": 108165600, \n                \"end\": 26.000081, \n                \"omitted\": false, \n                \"seconds\": 1.0000180006027222, \n                \"sender\": false, \n                \"start\": 25.000063\n            }\n        }, \n        {\n            \"streams\": [\n                {\n                    \"bits_per_second\": 865898878.6617607, \n                    \"bytes\": 108230760, \n                    \"end\": 27.00002, \n                    \"omitted\": false, \n                    \"seconds\": 0.9999390244483948, \n                    \"sender\": false, \n                    \"socket\": 5, \n                    \"start\": 26.000081\n                }\n            ], \n            \"sum\": {\n                \"bits_per_second\": 865898878.6617607, \n                \"bytes\": 108230760, \n                \"end\": 27.00002, \n                \"omitted\": false, \n                \"seconds\": 0.9999390244483948, \n                \"sender\": false, \n                \"start\": 26.000081\n            }\n        }, \n        {\n            \"streams\": [\n                {\n                    \"bits_per_second\": 865268584.3110026, \n                    \"bytes\": 108165600, \n                    \"end\": 28.000085, \n                    \"omitted\": false, \n                    \"seconds\": 1.0000649690628052, \n                    \"sender\": false, \n                    \"socket\": 5, \n                    \"start\": 27.00002\n                }\n            ], \n            \"sum\": {\n                \"bits_per_second\": 865268584.3110026, \n                \"bytes\": 108165600, \n                \"end\": 28.000085, \n                \"omitted\": false, \n                \"seconds\": 1.0000649690628052, \n                \"sender\": false, \n                \"start\": 27.00002\n            }\n        }, \n        {\n            \"streams\": [\n                {\n                    \"bits_per_second\": 865857330.787861, \n                    \"bytes\": 108230760, \n                    \"end\": 29.000072, \n                    \"omitted\": false, \n                    \"seconds\": 0.999987006187439, \n                    \"sender\": false, \n                    \"socket\": 5, \n                    \"start\": 28.000085\n                }\n            ], \n            \"sum\": {\n                \"bits_per_second\": 865857330.787861, \n                \"bytes\": 108230760, \n                \"end\": 29.000072, \n                \"omitted\": false, \n                \"seconds\": 0.999987006187439, \n                \"sender\": false, \n                \"start\": 28.000085\n            }\n        }, \n        {\n            \"streams\": [\n                {\n                    \"bits_per_second\": 865334341.9200215, \n                    \"bytes\": 108165600, \n                    \"end\": 30.000061, \n                    \"omitted\": false, \n                    \"seconds\": 0.9999889731407166, \n                    \"sender\": false, \n                    \"socket\": 5, \n                    \"start\": 29.000072\n                }\n            ], \n            \"sum\": {\n                \"bits_per_second\": 865334341.9200215, \n                \"bytes\": 108165600, \n                \"end\": 30.000061, \n                \"omitted\": false, \n                \"seconds\": 0.9999889731407166, \n                \"sender\": false, \n                \"start\": 29.000072\n            }\n        }, \n        {\n            \"streams\": [\n                {\n                    \"bits_per_second\": 865302312.8478764, \n                    \"bytes\": 108165600, \n                    \"end\": 31.000087, \n                    \"omitted\": false, \n                    \"seconds\": 1.000025987625122, \n                    \"sender\": false, \n                    \"socket\": 5, \n                    \"start\": 30.000061\n                }\n            ], \n            \"sum\": {\n                \"bits_per_second\": 865302312.8478764, \n                \"bytes\": 108165600, \n                \"end\": 31.000087, \n                \"omitted\": false, \n                \"seconds\": 1.000025987625122, \n                \"sender\": false, \n                \"start\": 30.000061\n            }\n        }, \n        {\n            \"streams\": [\n                {\n                    \"bits_per_second\": 865868581.8681105, \n                    \"bytes\": 108230760, \n                    \"end\": 32.000061, \n                    \"omitted\": false, \n                    \"seconds\": 0.999974012374878, \n                    \"sender\": false, \n                    \"socket\": 5, \n                    \"start\": 31.000087\n                }\n            ], \n            \"sum\": {\n                \"bits_per_second\": 865868581.8681105, \n                \"bytes\": 108230760, \n                \"end\": 32.000061, \n                \"omitted\": false, \n                \"seconds\": 0.999974012374878, \n                \"sender\": false, \n                \"start\": 31.000087\n            }\n        }, \n        {\n            \"streams\": [\n                {\n                    \"bits_per_second\": 865300559.311743, \n                    \"bytes\": 108165600, \n                    \"end\": 33.000089, \n                    \"omitted\": false, \n                    \"seconds\": 1.0000280141830444, \n                    \"sender\": false, \n                    \"socket\": 5, \n                    \"start\": 32.000061\n                }\n            ], \n            \"sum\": {\n                \"bits_per_second\": 865300559.311743, \n                \"bytes\": 108165600, \n                \"end\": 33.000089, \n                \"omitted\": false, \n                \"seconds\": 1.0000280141830444, \n                \"sender\": false, \n                \"start\": 32.000061\n            }\n        }, \n        {\n            \"streams\": [\n                {\n                    \"bits_per_second\": 865868581.8681105, \n                    \"bytes\": 108230760, \n                    \"end\": 34.000063, \n                    \"omitted\": false, \n                    \"seconds\": 0.999974012374878, \n                    \"sender\": false, \n                    \"socket\": 5, \n                    \"start\": 33.000089\n                }\n            ], \n            \"sum\": {\n                \"bits_per_second\": 865868581.8681105, \n                \"bytes\": 108230760, \n                \"end\": 34.000063, \n                \"omitted\": false, \n                \"seconds\": 0.999974012374878, \n                \"sender\": false, \n                \"start\": 33.000089\n            }\n        }, \n        {\n            \"streams\": [\n                {\n                    \"bits_per_second\": 865309223.9124285, \n                    \"bytes\": 108165600, \n                    \"end\": 35.000081, \n                    \"omitted\": false, \n                    \"seconds\": 1.0000180006027222, \n                    \"sender\": false, \n                    \"socket\": 5, \n                    \"start\": 34.000063\n                }\n            ], \n            \"sum\": {\n                \"bits_per_second\": 865309223.9124285, \n                \"bytes\": 108165600, \n                \"end\": 35.000081, \n                \"omitted\": false, \n                \"seconds\": 1.0000180006027222, \n                \"sender\": false, \n                \"start\": 34.000063\n            }\n        }, \n        {\n            \"streams\": [\n                {\n                    \"bits_per_second\": 865864246.5548556, \n                    \"bytes\": 108230760, \n                    \"end\": 36.00006, \n                    \"omitted\": false, \n                    \"seconds\": 0.999979019165039, \n                    \"sender\": false, \n                    \"socket\": 5, \n                    \"start\": 35.000081\n                }\n            ], \n            \"sum\": {\n                \"bits_per_second\": 865864246.5548556, \n                \"bytes\": 108230760, \n                \"end\": 36.00006, \n                \"omitted\": false, \n                \"seconds\": 0.999979019165039, \n                \"sender\": false, \n                \"start\": 35.000081\n            }\n        }, \n        {\n            \"streams\": [\n                {\n                    \"bits_per_second\": 865324800, \n                    \"bytes\": 108165600, \n                    \"end\": 37.00006, \n                    \"omitted\": false, \n                    \"seconds\": 1, \n                    \"sender\": false, \n                    \"socket\": 5, \n                    \"start\": 36.00006\n                }\n            ], \n            \"sum\": {\n                \"bits_per_second\": 865324800, \n                \"bytes\": 108165600, \n                \"end\": 37.00006, \n                \"omitted\": false, \n                \"seconds\": 1, \n                \"sender\": false, \n                \"start\": 36.00006\n            }\n        }, \n        {\n            \"streams\": [\n                {\n                    \"bits_per_second\": 865301487.6535165, \n                    \"bytes\": 108165600, \n                    \"end\": 38.000087, \n                    \"omitted\": false, \n                    \"seconds\": 1.0000269412994385, \n                    \"sender\": false, \n                    \"socket\": 5, \n                    \"start\": 37.00006\n                }\n            ], \n            \"sum\": {\n                \"bits_per_second\": 865301487.6535165, \n                \"bytes\": 108165600, \n                \"end\": 38.000087, \n                \"omitted\": false, \n                \"seconds\": 1.0000269412994385, \n                \"sender\": false, \n                \"start\": 37.00006\n            }\n        }, \n        {\n            \"streams\": [\n                {\n                    \"bits_per_second\": 865868581.8681105, \n                    \"bytes\": 108230760, \n                    \"end\": 39.000061, \n                    \"omitted\": false, \n                    \"seconds\": 0.999974012374878, \n                    \"sender\": false, \n                    \"socket\": 5, \n                    \"start\": 38.000087\n                }\n            ], \n            \"sum\": {\n                \"bits_per_second\": 865868581.8681105, \n                \"bytes\": 108230760, \n                \"end\": 39.000061, \n                \"omitted\": false, \n                \"seconds\": 0.999974012374878, \n                \"sender\": false, \n                \"start\": 38.000087\n            }\n        }, \n        {\n            \"streams\": [\n                {\n                    \"bits_per_second\": 865323046.372725, \n                    \"bytes\": 108165600, \n                    \"end\": 40.000063, \n                    \"omitted\": false, \n                    \"seconds\": 1.0000020265579224, \n                    \"sender\": false, \n                    \"socket\": 5, \n                    \"start\": 39.000061\n                }\n            ], \n            \"sum\": {\n                \"bits_per_second\": 865323046.372725, \n                \"bytes\": 108165600, \n                \"end\": 40.000063, \n                \"omitted\": false, \n                \"seconds\": 1.0000020265579224, \n                \"sender\": false, \n                \"start\": 39.000061\n            }\n        }, \n        {\n            \"streams\": [\n                {\n                    \"bits_per_second\": 865848660.4300917, \n                    \"bytes\": 108230760, \n                    \"end\": 41.00006, \n                    \"omitted\": false, \n                    \"seconds\": 0.9999970197677612, \n                    \"sender\": false, \n                    \"socket\": 5, \n                    \"start\": 40.000063\n                }\n            ], \n            \"sum\": {\n                \"bits_per_second\": 865848660.4300917, \n                \"bytes\": 108230760, \n                \"end\": 41.00006, \n                \"omitted\": false, \n                \"seconds\": 0.9999970197677612, \n                \"sender\": false, \n                \"start\": 40.000063\n            }\n        }, \n        {\n            \"streams\": [\n                {\n                    \"bits_per_second\": 865303138.0438102, \n                    \"bytes\": 108165600, \n                    \"end\": 42.000085, \n                    \"omitted\": false, \n                    \"seconds\": 1.0000250339508057, \n                    \"sender\": false, \n                    \"socket\": 5, \n                    \"start\": 41.00006\n                }\n            ], \n            \"sum\": {\n                \"bits_per_second\": 865303138.0438102, \n                \"bytes\": 108165600, \n                \"end\": 42.000085, \n                \"omitted\": false, \n                \"seconds\": 1.0000250339508057, \n                \"sender\": false, \n                \"start\": 41.00006\n            }\n        }, \n        {\n            \"streams\": [\n                {\n                    \"bits_per_second\": 865900633.566556, \n                    \"bytes\": 108230760, \n                    \"end\": 43.000022, \n                    \"omitted\": false, \n                    \"seconds\": 0.9999369978904724, \n                    \"sender\": false, \n                    \"socket\": 5, \n                    \"start\": 42.000085\n                }\n            ], \n            \"sum\": {\n                \"bits_per_second\": 865900633.566556, \n                \"bytes\": 108230760, \n                \"end\": 43.000022, \n                \"omitted\": false, \n                \"seconds\": 0.9999369978904724, \n                \"sender\": false, \n                \"start\": 42.000085\n            }\n        }, \n        {\n            \"streams\": [\n                {\n                    \"bits_per_second\": 865291069.7100884, \n                    \"bytes\": 108165600, \n                    \"end\": 44.000061, \n                    \"omitted\": false, \n                    \"seconds\": 1.000038981437683, \n                    \"sender\": false, \n                    \"socket\": 5, \n                    \"start\": 43.000022\n                }\n            ], \n            \"sum\": {\n                \"bits_per_second\": 865291069.7100884, \n                \"bytes\": 108165600, \n                \"end\": 44.000061, \n                \"omitted\": false, \n                \"seconds\": 1.000038981437683, \n                \"sender\": false, \n                \"start\": 43.000022\n            }\n        }, \n        {\n            \"streams\": [\n                {\n                    \"bits_per_second\": 865310049.121544, \n                    \"bytes\": 108165600, \n                    \"end\": 45.000078, \n                    \"omitted\": false, \n                    \"seconds\": 1.0000170469284058, \n                    \"sender\": false, \n                    \"socket\": 5, \n                    \"start\": 44.000061\n                }\n            ], \n            \"sum\": {\n                \"bits_per_second\": 865310049.121544, \n                \"bytes\": 108165600, \n                \"end\": 45.000078, \n                \"omitted\": false, \n                \"seconds\": 1.0000170469284058, \n                \"sender\": false, \n                \"start\": 44.000061\n            }\n        }, \n        {\n            \"streams\": [\n                {\n                    \"bits_per_second\": 865861666.0318626, \n                    \"bytes\": 108230760, \n                    \"end\": 46.00006, \n                    \"omitted\": false, \n                    \"seconds\": 0.9999819993972778, \n                    \"sender\": false, \n                    \"socket\": 5, \n                    \"start\": 45.000078\n                }\n            ], \n            \"sum\": {\n                \"bits_per_second\": 865861666.0318626, \n                \"bytes\": 108230760, \n                \"end\": 46.00006, \n                \"omitted\": false, \n                \"seconds\": 0.9999819993972778, \n                \"sender\": false, \n                \"start\": 45.000078\n            }\n        }, \n        {\n            \"streams\": [\n                {\n                    \"bits_per_second\": 865302312.8478764, \n                    \"bytes\": 108165600, \n                    \"end\": 47.000086, \n                    \"omitted\": false, \n                    \"seconds\": 1.000025987625122, \n                    \"sender\": false, \n                    \"socket\": 5, \n                    \"start\": 46.00006\n                }\n            ], \n            \"sum\": {\n                \"bits_per_second\": 865302312.8478764, \n                \"bytes\": 108165600, \n                \"end\": 47.000086, \n                \"omitted\": false, \n                \"seconds\": 1.000025987625122, \n                \"sender\": false, \n                \"start\": 46.00006\n            }\n        }, \n        {\n            \"streams\": [\n                {\n                    \"bits_per_second\": 865866001.3192767, \n                    \"bytes\": 108230760, \n                    \"end\": 48.000063, \n                    \"omitted\": false, \n                    \"seconds\": 0.9999769926071167, \n                    \"sender\": false, \n                    \"socket\": 5, \n                    \"start\": 47.000086\n                }\n            ], \n            \"sum\": {\n                \"bits_per_second\": 865866001.3192767, \n                \"bytes\": 108230760, \n                \"end\": 48.000063, \n                \"omitted\": false, \n                \"seconds\": 0.9999769926071167, \n                \"sender\": false, \n                \"start\": 47.000086\n            }\n        }, \n        {\n            \"streams\": [\n                {\n                    \"bits_per_second\": 865307470.3482844, \n                    \"bytes\": 108165600, \n                    \"end\": 49.000083, \n                    \"omitted\": false, \n                    \"seconds\": 1.0000200271606445, \n                    \"sender\": false, \n                    \"socket\": 5, \n                    \"start\": 48.000063\n                }\n            ], \n            \"sum\": {\n                \"bits_per_second\": 865307470.3482844, \n                \"bytes\": 108165600, \n                \"end\": 49.000083, \n                \"omitted\": false, \n                \"seconds\": 1.0000200271606445, \n                \"sender\": false, \n                \"start\": 48.000063\n            }\n        }, \n        {\n            \"streams\": [\n                {\n                    \"bits_per_second\": 865868581.8681105, \n                    \"bytes\": 108230760, \n                    \"end\": 50.000057, \n                    \"omitted\": false, \n                    \"seconds\": 0.999974012374878, \n                    \"sender\": false, \n                    \"socket\": 5, \n                    \"start\": 49.000083\n                }\n            ], \n            \"sum\": {\n                \"bits_per_second\": 865868581.8681105, \n                \"bytes\": 108230760, \n                \"end\": 50.000057, \n                \"omitted\": false, \n                \"seconds\": 0.999974012374878, \n                \"sender\": false, \n                \"start\": 49.000083\n            }\n        }, \n        {\n            \"streams\": [\n                {\n                    \"bits_per_second\": 865319642.2930104, \n                    \"bytes\": 108165600, \n                    \"end\": 51.000063, \n                    \"omitted\": false, \n                    \"seconds\": 1.0000059604644775, \n                    \"sender\": false, \n                    \"socket\": 5, \n                    \"start\": 50.000057\n                }\n            ], \n            \"sum\": {\n                \"bits_per_second\": 865319642.2930104, \n                \"bytes\": 108165600, \n                \"end\": 51.000063, \n                \"omitted\": false, \n                \"seconds\": 1.0000059604644775, \n                \"sender\": false, \n                \"start\": 50.000057\n            }\n        }, \n        {\n            \"streams\": [\n                {\n                    \"bits_per_second\": 865305716.7912476, \n                    \"bytes\": 108165600, \n                    \"end\": 52.000085, \n                    \"omitted\": false, \n                    \"seconds\": 1.000022053718567, \n                    \"sender\": false, \n                    \"socket\": 5, \n                    \"start\": 51.000063\n                }\n            ], \n            \"sum\": {\n                \"bits_per_second\": 865305716.7912476, \n                \"bytes\": 108165600, \n                \"end\": 52.000085, \n                \"omitted\": false, \n                \"seconds\": 1.000022053718567, \n                \"sender\": false, \n                \"start\": 51.000063\n            }\n        }, \n        {\n            \"streams\": [\n                {\n                    \"bits_per_second\": 865864246.5548556, \n                    \"bytes\": 108230760, \n                    \"end\": 53.000064, \n                    \"omitted\": false, \n                    \"seconds\": 0.999979019165039, \n                    \"sender\": false, \n                    \"socket\": 5, \n                    \"start\": 52.000085\n                }\n            ], \n            \"sum\": {\n                \"bits_per_second\": 865864246.5548556, \n                \"bytes\": 108230760, \n                \"end\": 53.000064, \n                \"omitted\": false, \n                \"seconds\": 0.999979019165039, \n                \"sender\": false, \n                \"start\": 52.000085\n            }\n        }, \n        {\n            \"streams\": [\n                {\n                    \"bits_per_second\": 865305716.7912476, \n                    \"bytes\": 108165600, \n                    \"end\": 54.000086, \n                    \"omitted\": false, \n                    \"seconds\": 1.000022053718567, \n                    \"sender\": false, \n                    \"socket\": 5, \n                    \"start\": 53.000064\n                }\n            ], \n            \"sum\": {\n                \"bits_per_second\": 865305716.7912476, \n                \"bytes\": 108165600, \n                \"end\": 54.000086, \n                \"omitted\": false, \n                \"seconds\": 1.000022053718567, \n                \"sender\": false, \n                \"start\": 53.000064\n            }\n        }, \n        {\n            \"streams\": [\n                {\n                    \"bits_per_second\": 865867704.4797813, \n                    \"bytes\": 108230760, \n                    \"end\": 55.000061, \n                    \"omitted\": false, \n                    \"seconds\": 0.999975025653839, \n                    \"sender\": false, \n                    \"socket\": 5, \n                    \"start\": 54.000086\n                }\n            ], \n            \"sum\": {\n                \"bits_per_second\": 865867704.4797813, \n                \"bytes\": 108230760, \n                \"end\": 55.000061, \n                \"omitted\": false, \n                \"seconds\": 0.999975025653839, \n                \"sender\": false, \n                \"start\": 54.000086\n            }\n        }, \n        {\n            \"streams\": [\n                {\n                    \"bits_per_second\": 865321292.7525575, \n                    \"bytes\": 108165600, \n                    \"end\": 56.000065, \n                    \"omitted\": false, \n                    \"seconds\": 1.0000040531158447, \n                    \"sender\": false, \n                    \"socket\": 5, \n                    \"start\": 55.000061\n                }\n            ], \n            \"sum\": {\n                \"bits_per_second\": 865321292.7525575, \n                \"bytes\": 108165600, \n                \"end\": 56.000065, \n                \"omitted\": false, \n                \"seconds\": 1.0000040531158447, \n                \"sender\": false, \n                \"start\": 55.000061\n            }\n        }, \n        {\n            \"streams\": [\n                {\n                    \"bits_per_second\": 865859911.2850132, \n                    \"bytes\": 108230760, \n                    \"end\": 57.000049, \n                    \"omitted\": false, \n                    \"seconds\": 0.9999840259552002, \n                    \"sender\": false, \n                    \"socket\": 5, \n                    \"start\": 56.000065\n                }\n            ], \n            \"sum\": {\n                \"bits_per_second\": 865859911.2850132, \n                \"bytes\": 108230760, \n                \"end\": 57.000049, \n                \"omitted\": false, \n                \"seconds\": 0.9999840259552002, \n                \"sender\": false, \n                \"start\": 56.000065\n            }\n        }, \n        {\n            \"streams\": [\n                {\n                    \"bits_per_second\": 865314381.4952217, \n                    \"bytes\": 108165600, \n                    \"end\": 58.000061, \n                    \"omitted\": false, \n                    \"seconds\": 1.0000120401382446, \n                    \"sender\": false, \n                    \"socket\": 5, \n                    \"start\": 57.000049\n                }\n            ], \n            \"sum\": {\n                \"bits_per_second\": 865314381.4952217, \n                \"bytes\": 108165600, \n                \"end\": 58.000061, \n                \"omitted\": false, \n                \"seconds\": 1.0000120401382446, \n                \"sender\": false, \n                \"start\": 57.000049\n            }\n        }, \n        {\n            \"streams\": [\n                {\n                    \"bits_per_second\": 865304891.5903953, \n                    \"bytes\": 108165600, \n                    \"end\": 59.000084, \n                    \"omitted\": false, \n                    \"seconds\": 1.0000230073928833, \n                    \"sender\": false, \n                    \"socket\": 5, \n                    \"start\": 58.000061\n                }\n            ], \n            \"sum\": {\n                \"bits_per_second\": 865304891.5903953, \n                \"bytes\": 108165600, \n                \"end\": 59.000084, \n                \"omitted\": false, \n                \"seconds\": 1.0000230073928833, \n                \"sender\": false, \n                \"start\": 58.000061\n            }\n        }, \n        {\n            \"streams\": [\n                {\n                    \"bits_per_second\": 865866001.3192767, \n                    \"bytes\": 108230760, \n                    \"end\": 60.000061, \n                    \"omitted\": false, \n                    \"seconds\": 0.9999769926071167, \n                    \"sender\": false, \n                    \"socket\": 5, \n                    \"start\": 59.000084\n                }\n            ], \n            \"sum\": {\n                \"bits_per_second\": 865866001.3192767, \n                \"bytes\": 108230760, \n                \"end\": 60.000061, \n                \"omitted\": false, \n                \"seconds\": 0.9999769926071167, \n                \"sender\": false, \n                \"start\": 59.000084\n            }\n        }, \n        {\n            \"streams\": [\n                {\n                    \"bits_per_second\": 860947542.077074, \n                    \"bytes\": 8275320, \n                    \"end\": 60.076956, \n                    \"omitted\": false, \n                    \"seconds\": 0.07689499855041504, \n                    \"sender\": false, \n                    \"socket\": 5, \n                    \"start\": 60.000061\n                }\n            ], \n            \"sum\": {\n                \"bits_per_second\": 860947542.077074, \n                \"bytes\": 8275320, \n                \"end\": 60.076956, \n                \"omitted\": false, \n                \"seconds\": 0.07689499855041504, \n                \"sender\": false, \n                \"start\": 60.000061\n            }\n        }\n    ], \n    \"start\": {\n        \"accepted_connection\": {\n            \"host\": \"10.0.0.1\", \n            \"port\": 53933\n        }, \n        \"connected\": [\n            {\n                \"local_host\": \"10.0.0.2\", \n                \"local_port\": 5201, \n                \"remote_host\": \"10.0.0.1\", \n                \"remote_port\": 57371, \n                \"socket\": 5\n            }\n        ], \n        \"cookie\": \"jn2indy2ya5d43furt7jqyupgebwm6h3zpvk\", \n        \"fq_rate\": 0, \n        \"rcvbuf_actual\": 87380, \n        \"sndbuf_actual\": 87380, \n        \"sock_bufsize\": 0, \n        \"system_info\": \"REDACTED\", \n        \"target_bitrate\": 0, \n        \"tcp_mss_default\": 0, \n        \"test_start\": {\n            \"bidir\": 0, \n            \"blksize\": 131072, \n            \"blocks\": 0, \n            \"bytes\": 0, \n            \"duration\": 60, \n            \"fqrate\": 0, \n            \"num_streams\": 1, \n            \"omit\": 0, \n            \"protocol\": \"TCP\", \n            \"reverse\": 0, \n            \"target_bitrate\": 0, \n            \"tos\": 0\n        }, \n        \"timestamp\": {\n            \"time\": \"Wed, 17 Apr 2024 01:24:34 GMT\", \n            \"timesecs\": 1713317074\n        }, \n        \"version\": \"iperf 3.14\"\n    }\n}\n","summary":{"streams":[{"end":60.000072,"rtt":77087,"start":0,"stream-id":5,"retransmits":0,"throughput-bits":867014025.1831697,"throughput-bytes":6502612992}],"summary":{"end":60.000072,"start":0,"retransmits":0,"throughput-bits":867014025.1831697,"throughput-bytes":6502612992,"receiver-throughput-bits":865535626.139247}},"intervals":[{"streams":[{"end":1.000177,"rtt":77087,"start":0,"omitted":false,"stream-id":5,"retransmits":0,"tcp-window-size":16698336,"throughput-bits":955083661.555538,"throughput-bytes":119406592}],"summary":{"end":1.000177,"start":0,"omitted":false,"retransmits":0,"throughput-bits":955083661.555538,"throughput-bytes":119406592}},{"streams":[{"end":2.000064,"rtt":77086,"start":1.000177,"omitted":false,"stream-id":5,"retransmits":0,"tcp-window-size":16698336,"throughput-bits":870416446.1163948,"throughput-bytes":108789760}],"summary":{"end":2.000064,"start":1.000177,"omitted":false,"retransmits":0,"throughput-bits":870416446.1163948,"throughput-bytes":108789760}},{"streams":[{"end":3.00007,"rtt":77090,"start":2.000064,"omitted":false,"stream-id":5,"retransmits":0,"tcp-window-size":16698336,"throughput-bits":859827195.030547,"throughput-bytes":107479040}],"summary":{"end":3.00007,"start":2.000064,"omitted":false,"retransmits":0,"throughput-bits":859827195.030547,"throughput-bytes":107479040}},{"streams":[{"end":4.000062,"rtt":77086,"start":3.00007,"omitted":false,"stream-id":5,"retransmits":0,"tcp-window-size":16698336,"throughput-bits":870325031.30552,"throughput-bytes":108789760}],"summary":{"end":4.000062,"start":3.00007,"omitted":false,"retransmits":0,"throughput-bits":870325031.30552,"throughput-bytes":108789760}},{"streams":[{"end":5.000148,"rtt":77089,"start":4.000062,"omitted":false,"stream-id":5,"retransmits":0,"tcp-window-size":16698336,"throughput-bits":859758423.8513664,"throughput-bytes":107479040}],"summary":{"end":5.000148,"start":4.000062,"omitted":false,"retransmits":0,"throughput-bits":859758423.8513664,"throughput-bytes":107479040}},{"streams":[{"end":6.000063,"rtt":77086,"start":5.000148,"omitted":false,"stream-id":5,"retransmits":0,"tcp-window-size":16698336,"throughput-bits":870392060.038024,"throughput-bytes":108789760}],"summary":{"end":6.000063,"start":5.000148,"omitted":false,"retransmits":0,"throughput-bits":870392060.038024,"throughput-bytes":108789760}},{"streams":[{"end":7.000062,"rtt":77087,"start":6.000063,"omitted":false,"stream-id":5,"retransmits":0,"tcp-window-size":16698336,"throughput-bits":870318961.8758936,"throughput-bytes":108789760}],"summary":{"end":7.000062,"start":6.000063,"omitted":false,"retransmits":0,"throughput-bits":870318961.8758936,"throughput-bytes":108789760}},{"streams":[{"end":8.000063,"rtt":77087,"start":7.000062,"omitted":false,"stream-id":5,"retransmits":0,"tcp-window-size":16698336,"throughput-bits":859831500.000782,"throughput-bytes":107479040}],"summary":{"end":8.000063,"start":7.000062,"omitted":false,"retransmits":0,"throughput-bits":859831500.000782,"throughput-bytes":107479040}},{"streams":[{"end":9.000063,"rtt":77086,"start":8.000063,"omitted":false,"stream-id":5,"retransmits":0,"tcp-window-size":16698336,"throughput-bits":870318080,"throughput-bytes":108789760}],"summary":{"end":9.000063,"start":8.000063,"omitted":false,"retransmits":0,"throughput-bits":870318080,"throughput-bytes":108789760}},{"streams":[{"end":10.000116,"rtt":77084,"start":9.000063,"omitted":false,"stream-id":5,"retransmits":0,"tcp-window-size":16698336,"throughput-bits":859786709.9195297,"throughput-bytes":107479040}],"summary":{"end":10.000116,"start":9.000063,"omitted":false,"retransmits":0,"throughput-bits":859786709.9195297,"throughput-bytes":107479040}},{"streams":[{"end":11.000063,"rtt":77090,"start":10.000116,"omitted":false,"stream-id":5,"retransmits":0,"tcp-window-size":16698336,"throughput-bits":870364199.318795,"throughput-bytes":108789760}],"summary":{"end":11.000063,"start":10.000116,"omitted":false,"retransmits":0,"throughput-bits":870364199.318795,"throughput-bytes":108789760}},{"streams":[{"end":12.000078,"rtt":77095,"start":11.000063,"omitted":false,"stream-id":5,"retransmits":0,"tcp-window-size":16698336,"throughput-bits":859819405.1939852,"throughput-bytes":107479040}],"summary":{"end":12.000078,"start":11.000063,"omitted":false,"retransmits":0,"throughput-bits":859819405.1939852,"throughput-bytes":107479040}},{"streams":[{"end":13.000062,"rtt":77086,"start":12.000078,"omitted":false,"stream-id":5,"retransmits":0,"tcp-window-size":16698336,"throughput-bits":870331982.7220827,"throughput-bytes":108789760}],"summary":{"end":13.000062,"start":12.000078,"omitted":false,"retransmits":0,"throughput-bits":870331982.7220827,"throughput-bytes":108789760}},{"streams":[{"end":14.000082,"rtt":77092,"start":13.000062,"omitted":false,"stream-id":5,"retransmits":0,"tcp-window-size":16698336,"throughput-bits":859815100.3448608,"throughput-bytes":107479040}],"summary":{"end":14.000082,"start":13.000062,"omitted":false,"retransmits":0,"throughput-bits":859815100.3448608,"throughput-bytes":107479040}},{"streams":[{"end":15.000031,"rtt":77084,"start":14.000082,"omitted":false,"stream-id":5,"retransmits":0,"tcp-window-size":16698336,"throughput-bits":870362487.2657287,"throughput-bytes":108789760}],"summary":{"end":15.000031,"start":14.000082,"omitted":false,"retransmits":0,"throughput-bits":870362487.2657287,"throughput-bytes":108789760}},{"streams":[{"end":16.000081,"rtt":77091,"start":15.000031,"omitted":false,"stream-id":5,"retransmits":0,"tcp-window-size":16698336,"throughput-bits":859789374.6450644,"throughput-bytes":107479040}],"summary":{"end":16.000081,"start":15.000031,"omitted":false,"retransmits":0,"throughput-bits":859789374.6450644,"throughput-bytes":107479040}},{"streams":[{"end":17.000041,"rtt":77092,"start":16.000081,"omitted":false,"stream-id":5,"retransmits":0,"tcp-window-size":16698336,"throughput-bits":870352889.5171968,"throughput-bytes":108789760}],"summary":{"end":17.000041,"start":16.000081,"omitted":false,"retransmits":0,"throughput-bits":870352889.5171968,"throughput-bytes":108789760}},{"streams":[{"end":18.000044,"rtt":77084,"start":17.000041,"omitted":false,"stream-id":5,"retransmits":0,"tcp-window-size":16698336,"throughput-bits":870315486.25773,"throughput-bytes":108789760}],"summary":{"end":18.000044,"start":17.000041,"omitted":false,"retransmits":0,"throughput-bits":870315486.25773,"throughput-bytes":108789760}},{"streams":[{"end":19.00016,"rtt":77086,"start":18.000044,"omitted":false,"stream-id":5,"retransmits":0,"tcp-window-size":16698336,"throughput-bits":859732599.0666947,"throughput-bytes":107479040}],"summary":{"end":19.00016,"start":18.000044,"omitted":false,"retransmits":0,"throughput-bits":859732599.0666947,"throughput-bytes":107479040}},{"streams":[{"end":20.000148,"rtt":77092,"start":19.00016,"omitted":false,"stream-id":5,"retransmits":0,"tcp-window-size":16698336,"throughput-bits":870328506.999921,"throughput-bytes":108789760}],"summary":{"end":20.000148,"start":19.00016,"omitted":false,"retransmits":0,"throughput-bits":870328506.999921,"throughput-bytes":108789760}},{"streams":[{"end":21.00008,"rtt":77094,"start":20.000148,"omitted":false,"stream-id":5,"retransmits":0,"tcp-window-size":16698336,"throughput-bits":859890800.227176,"throughput-bytes":107479040}],"summary":{"end":21.00008,"start":20.000148,"omitted":false,"retransmits":0,"throughput-bits":859890800.227176,"throughput-bytes":107479040}},{"streams":[{"end":22.000041,"rtt":77092,"start":21.00008,"omitted":false,"stream-id":5,"retransmits":0,"tcp-window-size":16698336,"throughput-bits":870352007.5725455,"throughput-bytes":108789760}],"summary":{"end":22.000041,"start":21.00008,"omitted":false,"retransmits":0,"throughput-bits":870352007.5725455,"throughput-bytes":108789760}},{"streams":[{"end":23.000081,"rtt":77086,"start":22.000041,"omitted":false,"stream-id":5,"retransmits":0,"tcp-window-size":16698336,"throughput-bits":859797881.3794156,"throughput-bytes":107479040}],"summary":{"end":23.000081,"start":22.000041,"omitted":false,"retransmits":0,"throughput-bits":859797881.3794156,"throughput-bytes":107479040}},{"streams":[{"end":24.000064,"rtt":77091,"start":23.000081,"omitted":false,"stream-id":5,"retransmits":0,"tcp-window-size":16698336,"throughput-bits":870332864.6261512,"throughput-bytes":108789760}],"summary":{"end":24.000064,"start":23.000081,"omitted":false,"retransmits":0,"throughput-bits":870332864.6261512,"throughput-bytes":108789760}},{"streams":[{"end":25.000066,"rtt":77088,"start":24.000064,"omitted":false,"stream-id":5,"retransmits":0,"tcp-window-size":16698336,"throughput-bits":859830577.5035312,"throughput-bytes":107479040}],"summary":{"end":25.000066,"start":24.000064,"omitted":false,"retransmits":0,"throughput-bits":859830577.5035312,"throughput-bytes":107479040}},{"streams":[{"end":26.000062,"rtt":77087,"start":25.000066,"omitted":false,"stream-id":5,"retransmits":0,"tcp-window-size":16698336,"throughput-bits":870321555.63888,"throughput-bytes":108789760}],"summary":{"end":26.000062,"start":25.000066,"omitted":false,"retransmits":0,"throughput-bits":870321555.63888,"throughput-bytes":108789760}},{"streams":[{"end":27.000089,"rtt":77085,"start":26.000062,"omitted":false,"stream-id":5,"retransmits":0,"tcp-window-size":16698336,"throughput-bits":859809155.6240784,"throughput-bytes":107479040}],"summary":{"end":27.000089,"start":26.000062,"omitted":false,"retransmits":0,"throughput-bits":859809155.6240784,"throughput-bytes":107479040}},{"streams":[{"end":28.000063,"rtt":77088,"start":27.000089,"omitted":false,"stream-id":5,"retransmits":0,"tcp-window-size":16698336,"throughput-bits":870340698.0877904,"throughput-bytes":108789760}],"summary":{"end":28.000063,"start":27.000089,"omitted":false,"retransmits":0,"throughput-bits":870340698.0877904,"throughput-bytes":108789760}},{"streams":[{"end":29.000032,"rtt":77091,"start":28.000063,"omitted":false,"stream-id":5,"retransmits":0,"tcp-window-size":16698336,"throughput-bits":870345055.8361002,"throughput-bytes":108789760}],"summary":{"end":29.000032,"start":28.000063,"omitted":false,"retransmits":0,"throughput-bits":870345055.8361002,"throughput-bytes":108789760}},{"streams":[{"end":30.000083,"rtt":77087,"start":29.000032,"omitted":false,"stream-id":5,"retransmits":0,"tcp-window-size":16698336,"throughput-bits":859788452.2382023,"throughput-bytes":107479040}],"summary":{"end":30.000083,"start":29.000032,"omitted":false,"retransmits":0,"throughput-bits":859788452.2382023,"throughput-bytes":107479040}},{"streams":[{"end":31.000038,"rtt":77086,"start":30.000083,"omitted":false,"stream-id":5,"retransmits":0,"tcp-window-size":16698336,"throughput-bits":870357247.3875915,"throughput-bytes":108789760}],"summary":{"end":31.000038,"start":30.000083,"omitted":false,"retransmits":0,"throughput-bits":870357247.3875915,"throughput-bytes":108789760}},{"streams":[{"end":32.000064,"rtt":77086,"start":31.000038,"omitted":false,"stream-id":5,"retransmits":0,"tcp-window-size":16698336,"throughput-bits":859809975.5806783,"throughput-bytes":107479040}],"summary":{"end":32.000064,"start":31.000038,"omitted":false,"retransmits":0,"throughput-bits":859809975.5806783,"throughput-bytes":107479040}},{"streams":[{"end":33.000163,"rtt":77083,"start":32.000064,"omitted":false,"stream-id":5,"retransmits":0,"tcp-window-size":16698336,"throughput-bits":870231976.0194473,"throughput-bytes":108789760}],"summary":{"end":33.000163,"start":32.000064,"omitted":false,"retransmits":0,"throughput-bits":870231976.0194473,"throughput-bytes":108789760}},{"streams":[{"end":34.000066,"rtt":77088,"start":33.000163,"omitted":false,"stream-id":5,"retransmits":0,"tcp-window-size":16698336,"throughput-bits":859915711.83707,"throughput-bytes":107479040}],"summary":{"end":34.000066,"start":33.000163,"omitted":false,"retransmits":0,"throughput-bits":859915711.83707,"throughput-bytes":107479040}},{"streams":[{"end":35.000082,"rtt":77091,"start":34.000066,"omitted":false,"stream-id":5,"retransmits":0,"tcp-window-size":16698336,"throughput-bits":870304177.7220756,"throughput-bytes":108789760}],"summary":{"end":35.000082,"start":34.000066,"omitted":false,"retransmits":0,"throughput-bits":870304177.7220756,"throughput-bytes":108789760}},{"streams":[{"end":36.000023,"rtt":77085,"start":35.000082,"omitted":false,"stream-id":5,"retransmits":0,"tcp-window-size":16698336,"throughput-bits":859883060.4941255,"throughput-bytes":107479040}],"summary":{"end":36.000023,"start":35.000082,"omitted":false,"retransmits":0,"throughput-bits":859883060.4941255,"throughput-bytes":107479040}},{"streams":[{"end":37.000063,"rtt":77083,"start":36.000023,"omitted":false,"stream-id":5,"retransmits":0,"tcp-window-size":16698336,"throughput-bits":870283221.3962377,"throughput-bytes":108789760}],"summary":{"end":37.000063,"start":36.000023,"omitted":false,"retransmits":0,"throughput-bits":870283221.3962377,"throughput-bytes":108789760}},{"streams":[{"end":38.000036,"rtt":77087,"start":37.000063,"omitted":false,"stream-id":5,"retransmits":0,"tcp-window-size":16698336,"throughput-bits":859855536.8768767,"throughput-bytes":107479040}],"summary":{"end":38.000036,"start":37.000063,"omitted":false,"retransmits":0,"throughput-bits":859855536.8768767,"throughput-bytes":107479040}},{"streams":[{"end":39.000063,"rtt":77084,"start":38.000036,"omitted":false,"stream-id":5,"retransmits":0,"tcp-window-size":16698336,"throughput-bits":870294633.131689,"throughput-bytes":108789760}],"summary":{"end":39.000063,"start":38.000036,"omitted":false,"retransmits":0,"throughput-bits":870294633.131689,"throughput-bytes":108789760}},{"streams":[{"end":40.000063,"rtt":77087,"start":39.000063,"omitted":false,"stream-id":5,"retransmits":0,"tcp-window-size":16698336,"throughput-bits":870318080,"throughput-bytes":108789760}],"summary":{"end":40.000063,"start":39.000063,"omitted":false,"retransmits":0,"throughput-bits":870318080,"throughput-bytes":108789760}},{"streams":[{"end":41.000064,"rtt":77089,"start":40.000063,"omitted":false,"stream-id":5,"retransmits":0,"tcp-window-size":16698336,"throughput-bits":859831500.000782,"throughput-bytes":107479040}],"summary":{"end":41.000064,"start":40.000063,"omitted":false,"retransmits":0,"throughput-bits":859831500.000782,"throughput-bytes":107479040}},{"streams":[{"end":42.000077,"rtt":77093,"start":41.000064,"omitted":false,"stream-id":5,"retransmits":0,"tcp-window-size":16698336,"throughput-bits":870306771.396942,"throughput-bytes":108789760}],"summary":{"end":42.000077,"start":41.000064,"omitted":false,"retransmits":0,"throughput-bits":870306771.396942,"throughput-bytes":108789760}},{"streams":[{"end":43.000064,"rtt":77086,"start":42.000077,"omitted":false,"stream-id":5,"retransmits":0,"tcp-window-size":16698336,"throughput-bits":859843492.6451752,"throughput-bytes":107479040}],"summary":{"end":43.000064,"start":42.000077,"omitted":false,"retransmits":0,"throughput-bits":859843492.6451752,"throughput-bytes":107479040}},{"streams":[{"end":44.000083,"rtt":77087,"start":43.000064,"omitted":false,"stream-id":5,"retransmits":0,"tcp-window-size":16698336,"throughput-bits":870301584.0626686,"throughput-bytes":108789760}],"summary":{"end":44.000083,"start":43.000064,"omitted":false,"retransmits":0,"throughput-bits":870301584.0626686,"throughput-bytes":108789760}},{"streams":[{"end":45.000108,"rtt":77084,"start":44.000083,"omitted":false,"stream-id":5,"retransmits":0,"tcp-window-size":16698336,"throughput-bits":859810795.5388423,"throughput-bytes":107479040}],"summary":{"end":45.000108,"start":44.000083,"omitted":false,"retransmits":0,"throughput-bits":859810795.5388423,"throughput-bytes":107479040}},{"streams":[{"end":46.000064,"rtt":77086,"start":45.000108,"omitted":false,"stream-id":5,"retransmits":0,"tcp-window-size":16698336,"throughput-bits":870356365.4341084,"throughput-bytes":108789760}],"summary":{"end":46.000064,"start":45.000108,"omitted":false,"retransmits":0,"throughput-bits":870356365.4341084,"throughput-bytes":108789760}},{"streams":[{"end":47.000084,"rtt":77084,"start":46.000064,"omitted":false,"stream-id":5,"retransmits":0,"tcp-window-size":16698336,"throughput-bits":859815100.3448608,"throughput-bytes":107479040}],"summary":{"end":47.000084,"start":46.000064,"omitted":false,"retransmits":0,"throughput-bits":859815100.3448608,"throughput-bytes":107479040}},{"streams":[{"end":48.000063,"rtt":77080,"start":47.000084,"omitted":false,"stream-id":5,"retransmits":0,"tcp-window-size":16698336,"throughput-bits":870336340.383118,"throughput-bytes":108789760}],"summary":{"end":48.000063,"start":47.000084,"omitted":false,"retransmits":0,"throughput-bits":870336340.383118,"throughput-bytes":108789760}},{"streams":[{"end":49.000079,"rtt":77090,"start":48.000063,"omitted":false,"stream-id":5,"retransmits":0,"tcp-window-size":16698336,"throughput-bits":859818585.2194,"throughput-bytes":107479040}],"summary":{"end":49.000079,"start":48.000063,"omitted":false,"retransmits":0,"throughput-bits":859818585.2194,"throughput-bytes":107479040}},{"streams":[{"end":50.000063,"rtt":77090,"start":49.000079,"omitted":false,"stream-id":5,"retransmits":0,"tcp-window-size":16698336,"throughput-bits":870331982.7220827,"throughput-bytes":108789760}],"summary":{"end":50.000063,"start":49.000079,"omitted":false,"retransmits":0,"throughput-bits":870331982.7220827,"throughput-bytes":108789760}},{"streams":[{"end":51.000165,"rtt":77086,"start":50.000063,"omitted":false,"stream-id":5,"retransmits":0,"tcp-window-size":16698336,"throughput-bits":870229279.0615276,"throughput-bytes":108789760}],"summary":{"end":51.000165,"start":50.000063,"omitted":false,"retransmits":0,"throughput-bits":870229279.0615276,"throughput-bytes":108789760}},{"streams":[{"end":52.000164,"rtt":77090,"start":51.000165,"omitted":false,"stream-id":5,"retransmits":0,"tcp-window-size":16698336,"throughput-bits":859833191.250883,"throughput-bytes":107479040}],"summary":{"end":52.000164,"start":51.000165,"omitted":false,"retransmits":0,"throughput-bits":859833191.250883,"throughput-bytes":107479040}},{"streams":[{"end":53.000159,"rtt":77086,"start":52.000164,"omitted":false,"stream-id":5,"retransmits":0,"tcp-window-size":16698336,"throughput-bits":870322437.5218172,"throughput-bytes":108789760}],"summary":{"end":53.000159,"start":52.000164,"omitted":false,"retransmits":0,"throughput-bits":870322437.5218172,"throughput-bytes":108789760}},{"streams":[{"end":54.000088,"rtt":77090,"start":53.000159,"omitted":false,"stream-id":5,"retransmits":0,"tcp-window-size":16698336,"throughput-bits":859893363.0833955,"throughput-bytes":107479040}],"summary":{"end":54.000088,"start":53.000159,"omitted":false,"retransmits":0,"throughput-bits":859893363.0833955,"throughput-bytes":107479040}},{"streams":[{"end":55.000147,"rtt":77084,"start":54.000088,"omitted":false,"stream-id":5,"retransmits":0,"tcp-window-size":16698336,"throughput-bits":870266726.7802815,"throughput-bytes":108789760}],"summary":{"end":55.000147,"start":54.000088,"omitted":false,"retransmits":0,"throughput-bits":870266726.7802815,"throughput-bytes":108789760}},{"streams":[{"end":56.000153,"rtt":77090,"start":55.000147,"omitted":false,"stream-id":5,"retransmits":0,"tcp-window-size":16698336,"throughput-bits":859827195.030547,"throughput-bytes":107479040}],"summary":{"end":56.000153,"start":55.000147,"omitted":false,"retransmits":0,"throughput-bits":859827195.030547,"throughput-bytes":107479040}},{"streams":[{"end":57.000088,"rtt":77085,"start":56.000153,"omitted":false,"stream-id":5,"retransmits":0,"tcp-window-size":16698336,"throughput-bits":870374679.3055774,"throughput-bytes":108789760}],"summary":{"end":57.000088,"start":56.000153,"omitted":false,"retransmits":0,"throughput-bits":870374679.3055774,"throughput-bytes":108789760}},{"streams":[{"end":58.000154,"rtt":77087,"start":57.000088,"omitted":false,"stream-id":5,"retransmits":0,"tcp-window-size":16698336,"throughput-bits":859775538.7499443,"throughput-bytes":107479040}],"summary":{"end":58.000154,"start":57.000088,"omitted":false,"retransmits":0,"throughput-bits":859775538.7499443,"throughput-bytes":107479040}},{"streams":[{"end":59.000064,"rtt":77091,"start":58.000154,"omitted":false,"stream-id":5,"retransmits":0,"tcp-window-size":16698336,"throughput-bits":870396418.300683,"throughput-bytes":108789760}],"summary":{"end":59.000064,"start":58.000154,"omitted":false,"retransmits":0,"throughput-bits":870396418.300683,"throughput-bytes":108789760}},{"streams":[{"end":60.000072,"rtt":77085,"start":59.000064,"omitted":false,"stream-id":5,"retransmits":0,"tcp-window-size":16698336,"throughput-bits":859825452.5548505,"throughput-bytes":107479040}],"summary":{"end":60.000072,"start":59.000064,"omitted":false,"retransmits":0,"throughput-bits":859825452.5548505,"throughput-bytes":107479040}}],"succeeded":true}
