{"diags":"Participant 0:\n/usr/bin/iperf3 -p 5201 -B 172.16.0.2 -c 172.16.0.1 -t 10 --json --rsa-public-key-path /var/run/pscheduler-server/runner/tmp/tmpsv7htc00/tmporzw_bw5/public-key --username 07H0KhQSv11Eyv2w7vwe\n\n{\n    \"end\": {\n        \"cpu_utilization_percent\": {\n            \"host_system\": 0.4118692480692282, \n            \"host_total\": 0.4118692480692282, \n            \"host_user\": 0, \n            \"remote_system\": 0.6438797811572455, \n            \"remote_total\": 0.7366766516716083, \n            \"remote_user\": 0.09283623709428188\n        }, \n        \"receiver_tcp_congestion\": \"htcp\", \n        \"sender_tcp_congestion\": \"htcp\", \n        \"streams\": [\n            {\n                \"receiver\": {\n                    \"bits_per_second\": 10383635.54248497, \n                    \"bytes\": 13188384, \n                    \"end\": 10.160899, \n                    \"seconds\": 10.000119, \n                    \"sender\": true, \n                    \"socket\": 5, \n                    \"start\": 0\n                }, \n                \"sender\": {\n                    \"bits_per_second\": 13316756.730594907, \n                    \"bytes\": 16646144, \n                    \"end\": 10.000119, \n                    \"max_rtt\": 420107, \n                    \"max_snd_cwnd\": 518384, \n                    \"max_snd_wnd\": 0, \n                    \"mean_rtt\": 229597, \n                    \"min_rtt\": 109668, \n                    \"retransmits\": 290, \n                    \"seconds\": 10.000119, \n                    \"sender\": true, \n                    \"socket\": 5, \n                    \"start\": 0\n                }\n            }\n        ], \n        \"sum_received\": {\n            \"bits_per_second\": 10383635.54248497, \n            \"bytes\": 13188384, \n            \"end\": 10.160899, \n            \"seconds\": 10.160899, \n            \"sender\": true, \n            \"start\": 0\n        }, \n        \"sum_sent\": {\n            \"bits_per_second\": 13316756.730594907, \n            \"bytes\": 16646144, \n            \"end\": 10.000119, \n            \"retransmits\": 290, \n            \"seconds\": 10.000119, \n            \"sender\": true, \n            \"start\": 0\n        }\n    }, \n    \"intervals\": [\n        {\n            \"streams\": [\n                {\n                    \"bits_per_second\": 38791337.42019524, \n                    \"bytes\": 4849664, \n                    \"end\": 1.000154, \n                    \"omitted\": false, \n                    \"pmtu\": 1500, \n                    \"retransmits\": 64, \n                    \"rtt\": 337937, \n                    \"rttvar\": 1759, \n                    \"seconds\": 1.0001540184020996, \n                    \"sender\": true, \n                    \"snd_cwnd\": 518384, \n                    \"snd_wnd\": -1, \n                    \"socket\": 5, \n                    \"start\": 0\n                }\n            ], \n            \"sum\": {\n                \"bits_per_second\": 38791337.42019524, \n                \"bytes\": 4849664, \n                \"end\": 1.000154, \n                \"omitted\": false, \n                \"retransmits\": 64, \n                \"seconds\": 1.0001540184020996, \n                \"sender\": true, \n                \"start\": 0\n            }\n        }, \n        {\n            \"streams\": [\n                {\n                    \"bits_per_second\": 10487018.275973173, \n                    \"bytes\": 1310720, \n                    \"end\": 2.000034, \n                    \"omitted\": false, \n                    \"pmtu\": 1500, \n                    \"retransmits\": 212, \n                    \"rtt\": 109668, \n                    \"rttvar\": 808, \n                    \"seconds\": 0.999880015850067, \n                    \"sender\": true, \n                    \"snd_cwnd\": 201272, \n                    \"snd_wnd\": -1, \n                    \"socket\": 5, \n                    \"start\": 1.000154\n                }\n            ], \n            \"sum\": {\n                \"bits_per_second\": 10487018.275973173, \n                \"bytes\": 1310720, \n                \"end\": 2.000034, \n                \"omitted\": false, \n                \"retransmits\": 212, \n                \"seconds\": 0.999880015850067, \n                \"sender\": true, \n                \"start\": 1.000154\n            }\n        }, \n        {\n            \"streams\": [\n                {\n                    \"bits_per_second\": 10485288.77117792, \n                    \"bytes\": 1310720, \n                    \"end\": 3.000079, \n                    \"omitted\": false, \n                    \"pmtu\": 1500, \n                    \"retransmits\": 0, \n                    \"rtt\": 157170, \n                    \"rttvar\": 1745, \n                    \"seconds\": 1.0000449419021606, \n                    \"sender\": true, \n                    \"snd_cwnd\": 212856, \n                    \"snd_wnd\": -1, \n                    \"socket\": 5, \n                    \"start\": 2.000034\n                }\n            ], \n            \"sum\": {\n                \"bits_per_second\": 10485288.77117792, \n                \"bytes\": 1310720, \n                \"end\": 3.000079, \n                \"omitted\": false, \n                \"retransmits\": 0, \n                \"seconds\": 1.0000449419021606, \n                \"sender\": true, \n                \"start\": 2.000034\n            }\n        }, \n        {\n            \"streams\": [\n                {\n                    \"bits_per_second\": 10478906.981751693, \n                    \"bytes\": 1310720, \n                    \"end\": 4.000733, \n                    \"omitted\": false, \n                    \"pmtu\": 1500, \n                    \"retransmits\": 0, \n                    \"rtt\": 174313, \n                    \"rttvar\": 2894, \n                    \"seconds\": 1.0006539821624756, \n                    \"sender\": true, \n                    \"snd_cwnd\": 227336, \n                    \"snd_wnd\": -1, \n                    \"socket\": 5, \n                    \"start\": 3.000079\n                }\n            ], \n            \"sum\": {\n                \"bits_per_second\": 10478906.981751693, \n                \"bytes\": 1310720, \n                \"end\": 4.000733, \n                \"omitted\": false, \n                \"retransmits\": 0, \n                \"seconds\": 1.0006539821624756, \n                \"sender\": true, \n                \"start\": 3.000079\n            }\n        }, \n        {\n            \"streams\": [\n                {\n                    \"bits_per_second\": 10487500.91398987, \n                    \"bytes\": 1310720, \n                    \"end\": 5.000567, \n                    \"omitted\": false, \n                    \"pmtu\": 1500, \n                    \"retransmits\": 0, \n                    \"rtt\": 217169, \n                    \"rttvar\": 3474, \n                    \"seconds\": 0.9998340010643005, \n                    \"sender\": true, \n                    \"snd_cwnd\": 264984, \n                    \"snd_wnd\": -1, \n                    \"socket\": 5, \n                    \"start\": 4.000733\n                }\n            ], \n            \"sum\": {\n                \"bits_per_second\": 10487500.91398987, \n                \"bytes\": 1310720, \n                \"end\": 5.000567, \n                \"omitted\": false, \n                \"retransmits\": 0, \n                \"seconds\": 0.9998340010643005, \n                \"sender\": true, \n                \"start\": 4.000733\n            }\n        }, \n        {\n            \"streams\": [\n                {\n                    \"bits_per_second\": 10490911.279396992, \n                    \"bytes\": 1310720, \n                    \"end\": 6.000076, \n                    \"omitted\": false, \n                    \"pmtu\": 1500, \n                    \"retransmits\": 0, \n                    \"rtt\": 297460, \n                    \"rttvar\": 2226, \n                    \"seconds\": 0.9995089769363403, \n                    \"sender\": true, \n                    \"snd_cwnd\": 304080, \n                    \"snd_wnd\": -1, \n                    \"socket\": 5, \n                    \"start\": 5.000567\n                }\n            ], \n            \"sum\": {\n                \"bits_per_second\": 10490911.279396992, \n                \"bytes\": 1310720, \n                \"end\": 6.000076, \n                \"omitted\": false, \n                \"retransmits\": 0, \n                \"seconds\": 0.9995089769363403, \n                \"sender\": true, \n                \"start\": 5.000567\n            }\n        }, \n        {\n            \"streams\": [\n                {\n                    \"bits_per_second\": 10486336.906738574, \n                    \"bytes\": 1310720, \n                    \"end\": 7.000021, \n                    \"omitted\": false, \n                    \"pmtu\": 1500, \n                    \"retransmits\": 0, \n                    \"rtt\": 213822, \n                    \"rttvar\": 895, \n                    \"seconds\": 0.9999449849128723, \n                    \"sender\": true, \n                    \"snd_cwnd\": 370688, \n                    \"snd_wnd\": -1, \n                    \"socket\": 5, \n                    \"start\": 6.000076\n                }\n            ], \n            \"sum\": {\n                \"bits_per_second\": 10486336.906738574, \n                \"bytes\": 1310720, \n                \"end\": 7.000021, \n                \"omitted\": false, \n                \"retransmits\": 0, \n                \"seconds\": 0.9999449849128723, \n                \"sender\": true, \n                \"start\": 6.000076\n            }\n        }, \n        {\n            \"streams\": [\n                {\n                    \"bits_per_second\": 10485760, \n                    \"bytes\": 1310720, \n                    \"end\": 8.000021, \n                    \"omitted\": false, \n                    \"pmtu\": 1500, \n                    \"retransmits\": 8, \n                    \"rtt\": 420107, \n                    \"rttvar\": 3162, \n                    \"seconds\": 1, \n                    \"sender\": true, \n                    \"snd_cwnd\": 293944, \n                    \"snd_wnd\": -1, \n                    \"socket\": 5, \n                    \"start\": 7.000021\n                }\n            ], \n            \"sum\": {\n                \"bits_per_second\": 10485760, \n                \"bytes\": 1310720, \n                \"end\": 8.000021, \n                \"omitted\": false, \n                \"retransmits\": 8, \n                \"seconds\": 1, \n                \"sender\": true, \n                \"start\": 7.000021\n            }\n        }, \n        {\n            \"streams\": [\n                {\n                    \"bits_per_second\": 10485392.512879517, \n                    \"bytes\": 1310720, \n                    \"end\": 9.000056, \n                    \"omitted\": false, \n                    \"pmtu\": 1500, \n                    \"retransmits\": 6, \n                    \"rtt\": 187107, \n                    \"rttvar\": 4641, \n                    \"seconds\": 1.000035047531128, \n                    \"sender\": true, \n                    \"snd_cwnd\": 212856, \n                    \"snd_wnd\": -1, \n                    \"socket\": 5, \n                    \"start\": 8.000021\n                }\n            ], \n            \"sum\": {\n                \"bits_per_second\": 10485392.512879517, \n                \"bytes\": 1310720, \n                \"end\": 9.000056, \n                \"omitted\": false, \n                \"retransmits\": 6, \n                \"seconds\": 1.000035047531128, \n                \"sender\": true, \n                \"start\": 8.000021\n            }\n        }, \n        {\n            \"streams\": [\n                {\n                    \"bits_per_second\": 10485100.041539438, \n                    \"bytes\": 1310720, \n                    \"end\": 10.000119, \n                    \"omitted\": false, \n                    \"pmtu\": 1500, \n                    \"retransmits\": 0, \n                    \"rtt\": 181220, \n                    \"rttvar\": 1141, \n                    \"seconds\": 1.0000629425048828, \n                    \"sender\": true, \n                    \"snd_cwnd\": 222992, \n                    \"snd_wnd\": -1, \n                    \"socket\": 5, \n                    \"start\": 9.000056\n                }\n            ], \n            \"sum\": {\n                \"bits_per_second\": 10485100.041539438, \n                \"bytes\": 1310720, \n                \"end\": 10.000119, \n                \"omitted\": false, \n                \"retransmits\": 0, \n                \"seconds\": 1.0000629425048828, \n                \"sender\": true, \n                \"start\": 9.000056\n            }\n        }\n    ], \n    \"start\": {\n        \"connected\": [\n            {\n                \"local_host\": \"172.16.0.2\", \n                \"local_port\": 53647, \n                \"remote_host\": \"172.16.0.1\", \n                \"remote_port\": 5201, \n                \"socket\": 5\n            }\n        ], \n        \"connecting_to\": {\n            \"host\": \"172.16.0.1\", \n            \"port\": 5201\n        }, \n        \"cookie\": \"tojbfrtdslqfbhe5fwch467rstmbch4v7pcm\", \n        \"fq_rate\": 0, \n        \"rcvbuf_actual\": 87380, \n        \"sndbuf_actual\": 65536, \n        \"sock_bufsize\": 0, \n        \"system_info\": \"REDACTED\", \n        \"target_bitrate\": 0, \n        \"tcp_mss_default\": 1448, \n        \"test_start\": {\n            \"bidir\": 0, \n            \"blksize\": 131072, \n            \"blocks\": 0, \n            \"bytes\": 0, \n            \"duration\": 10, \n            \"fqrate\": 0, \n            \"num_streams\": 1, \n            \"omit\": 0, \n            \"protocol\": \"TCP\", \n            \"reverse\": 0, \n            \"target_bitrate\": 0, \n            \"tos\": 0\n        }, \n        \"timestamp\": {\n            \"time\": \"Sat, 12 Oct 2024 02:38:18 GMT\", \n            \"timesecs\": 1728700698\n        }, \n        \"version\": \"iperf 3.14\"\n    }\n}\nParticipant 1:\n/usr/bin/iperf3 -s -1 --idle-timeout 10 --json -p 5201 -B 172.16.0.1 --authorized-users-path /var/run/pscheduler-server/runner/tmp/tmpitm_6ovt/tmpwk0qk4z7/credentials --rsa-private-key-path /var/run/pscheduler-server/runner/tmp/tmpitm_6ovt/tmpwk0qk4z7/private-key\n\n{\n    \"end\": {\n        \"cpu_utilization_percent\": {\n            \"host_system\": 0.6438797811572455, \n            \"host_total\": 0.7366766516716083, \n            \"host_user\": 0.09283623709428188, \n            \"remote_system\": 0, \n            \"remote_total\": 0, \n            \"remote_user\": 0\n        }, \n        \"receiver_tcp_congestion\": \"htcp\", \n        \"streams\": [\n            {\n                \"receiver\": {\n                    \"bits_per_second\": 10383635.54248497, \n                    \"bytes\": 13188384, \n                    \"end\": 10.160899, \n                    \"seconds\": 10.160899, \n                    \"sender\": false, \n                    \"socket\": 5, \n                    \"start\": 0\n                }, \n                \"sender\": {\n                    \"bits_per_second\": 0, \n                    \"bytes\": 0, \n                    \"end\": 10.160899, \n                    \"seconds\": 10.160899, \n                    \"sender\": false, \n                    \"socket\": 5, \n                    \"start\": 0\n                }\n            }\n        ], \n        \"sum_received\": {\n            \"bits_per_second\": 10383635.54248497, \n            \"bytes\": 13188384, \n            \"end\": 10.160899, \n            \"seconds\": 10.160899, \n            \"sender\": false, \n            \"start\": 0\n        }, \n        \"sum_sent\": {\n            \"bits_per_second\": 0, \n            \"bytes\": 0, \n            \"end\": 10.160899, \n            \"seconds\": 10.160899, \n            \"sender\": false, \n            \"start\": 0\n        }\n    }, \n    \"intervals\": [\n        {\n            \"streams\": [\n                {\n                    \"bits_per_second\": 6231276.095546506, \n                    \"bytes\": 779024, \n                    \"end\": 1.000147, \n                    \"omitted\": false, \n                    \"seconds\": 1.0001469850540161, \n                    \"sender\": false, \n                    \"socket\": 5, \n                    \"start\": 0\n                }\n            ], \n            \"sum\": {\n                \"bits_per_second\": 6231276.095546506, \n                \"bytes\": 779024, \n                \"end\": 1.000147, \n                \"omitted\": false, \n                \"seconds\": 1.0001469850540161, \n                \"sender\": false, \n                \"start\": 0\n            }\n        }, \n        {\n            \"streams\": [\n                {\n                    \"bits_per_second\": 13739832.781789895, \n                    \"bytes\": 1717328, \n                    \"end\": 2.000059, \n                    \"omitted\": false, \n                    \"seconds\": 0.9999120235443115, \n                    \"sender\": false, \n                    \"socket\": 5, \n                    \"start\": 1.000147\n                }\n            ], \n            \"sum\": {\n                \"bits_per_second\": 13739832.781789895, \n                \"bytes\": 1717328, \n                \"end\": 2.000059, \n                \"omitted\": false, \n                \"seconds\": 0.9999120235443115, \n                \"sender\": false, \n                \"start\": 1.000147\n            }\n        }, \n        {\n            \"streams\": [\n                {\n                    \"bits_per_second\": 12638092.776345922, \n                    \"bytes\": 1579768, \n                    \"end\": 3.000063, \n                    \"omitted\": false, \n                    \"seconds\": 1.0000040531158447, \n                    \"sender\": false, \n                    \"socket\": 5, \n                    \"start\": 2.000059\n                }\n            ], \n            \"sum\": {\n                \"bits_per_second\": 12638092.776345922, \n                \"bytes\": 1579768, \n                \"end\": 3.000063, \n                \"omitted\": false, \n                \"seconds\": 1.0000040531158447, \n                \"sender\": false, \n                \"start\": 2.000059\n            }\n        }, \n        {\n            \"streams\": [\n                {\n                    \"bits_per_second\": 9718743.1285428, \n                    \"bytes\": 1214872, \n                    \"end\": 4.000087, \n                    \"omitted\": false, \n                    \"seconds\": 1.0000239610672, \n                    \"sender\": false, \n                    \"socket\": 5, \n                    \"start\": 3.000063\n                }\n            ], \n            \"sum\": {\n                \"bits_per_second\": 9718743.1285428, \n                \"bytes\": 1214872, \n                \"end\": 4.000087, \n                \"omitted\": false, \n                \"seconds\": 1.0000239610672, \n                \"sender\": false, \n                \"start\": 3.000063\n            }\n        }, \n        {\n            \"streams\": [\n                {\n                    \"bits_per_second\": 11526356.870835956, \n                    \"bytes\": 1440760, \n                    \"end\": 5.000063, \n                    \"omitted\": false, \n                    \"seconds\": 0.9999759793281555, \n                    \"sender\": false, \n                    \"socket\": 5, \n                    \"start\": 4.000087\n                }\n            ], \n            \"sum\": {\n                \"bits_per_second\": 11526356.870835956, \n                \"bytes\": 1440760, \n                \"end\": 5.000063, \n                \"omitted\": false, \n                \"seconds\": 0.9999759793281555, \n                \"sender\": false, \n                \"start\": 4.000087\n            }\n        }, \n        {\n            \"streams\": [\n                {\n                    \"bits_per_second\": 8177543.62545063, \n                    \"bytes\": 1022288, \n                    \"end\": 6.000156, \n                    \"omitted\": false, \n                    \"seconds\": 1.0000929832458496, \n                    \"sender\": false, \n                    \"socket\": 5, \n                    \"start\": 5.000063\n                }\n            ], \n            \"sum\": {\n                \"bits_per_second\": 8177543.62545063, \n                \"bytes\": 1022288, \n                \"end\": 6.000156, \n                \"omitted\": false, \n                \"seconds\": 1.0000929832458496, \n                \"sender\": false, \n                \"start\": 5.000063\n            }\n        }, \n        {\n            \"streams\": [\n                {\n                    \"bits_per_second\": 12315516.311579222, \n                    \"bytes\": 1539224, \n                    \"end\": 7.000016, \n                    \"omitted\": false, \n                    \"seconds\": 0.9998599886894226, \n                    \"sender\": false, \n                    \"socket\": 5, \n                    \"start\": 6.000156\n                }\n            ], \n            \"sum\": {\n                \"bits_per_second\": 12315516.311579222, \n                \"bytes\": 1539224, \n                \"end\": 7.000016, \n                \"omitted\": false, \n                \"seconds\": 0.9998599886894226, \n                \"sender\": false, \n                \"start\": 6.000156\n            }\n        }, \n        {\n            \"streams\": [\n                {\n                    \"bits_per_second\": 7957690.99627388, \n                    \"bytes\": 994776, \n                    \"end\": 8.000081, \n                    \"omitted\": false, \n                    \"seconds\": 1.0000649690628052, \n                    \"sender\": false, \n                    \"socket\": 5, \n                    \"start\": 7.000016\n                }\n            ], \n            \"sum\": {\n                \"bits_per_second\": 7957690.99627388, \n                \"bytes\": 994776, \n                \"end\": 8.000081, \n                \"omitted\": false, \n                \"seconds\": 1.0000649690628052, \n                \"sender\": false, \n                \"start\": 7.000016\n            }\n        }, \n        {\n            \"streams\": [\n                {\n                    \"bits_per_second\": 9580150.15584157, \n                    \"bytes\": 1197496, \n                    \"end\": 9.000062, \n                    \"omitted\": false, \n                    \"seconds\": 0.9999809861183167, \n                    \"sender\": false, \n                    \"socket\": 5, \n                    \"start\": 8.000081\n                }\n            ], \n            \"sum\": {\n                \"bits_per_second\": 9580150.15584157, \n                \"bytes\": 1197496, \n                \"end\": 9.000062, \n                \"omitted\": false, \n                \"seconds\": 0.9999809861183167, \n                \"sender\": false, \n                \"start\": 8.000081\n            }\n        }, \n        {\n            \"streams\": [\n                {\n                    \"bits_per_second\": 11862016, \n                    \"bytes\": 1482752, \n                    \"end\": 10.000062, \n                    \"omitted\": false, \n                    \"seconds\": 1, \n                    \"sender\": false, \n                    \"socket\": 5, \n                    \"start\": 9.000062\n                }\n            ], \n            \"sum\": {\n                \"bits_per_second\": 11862016, \n                \"bytes\": 1482752, \n                \"end\": 10.000062, \n                \"omitted\": false, \n                \"seconds\": 1, \n                \"sender\": false, \n                \"start\": 9.000062\n            }\n        }, \n        {\n            \"streams\": [\n                {\n                    \"bits_per_second\": 10947531.094159978, \n                    \"bytes\": 220096, \n                    \"end\": 10.160899, \n                    \"omitted\": false, \n                    \"seconds\": 0.16083699464797974, \n                    \"sender\": false, \n                    \"socket\": 5, \n                    \"start\": 10.000062\n                }\n            ], \n            \"sum\": {\n                \"bits_per_second\": 10947531.094159978, \n                \"bytes\": 220096, \n                \"end\": 10.160899, \n                \"omitted\": false, \n                \"seconds\": 0.16083699464797974, \n                \"sender\": false, \n                \"start\": 10.000062\n            }\n        }\n    ], \n    \"start\": {\n        \"accepted_connection\": {\n            \"host\": \"172.16.0.2\", \n            \"port\": 54885\n        }, \n        \"connected\": [\n            {\n                \"local_host\": \"172.16.0.1\", \n                \"local_port\": 5201, \n                \"remote_host\": \"172.16.0.2\", \n                \"remote_port\": 53647, \n                \"socket\": 5\n            }\n        ], \n        \"cookie\": \"tojbfrtdslqfbhe5fwch467rstmbch4v7pcm\", \n        \"fq_rate\": 0, \n        \"rcvbuf_actual\": 87380, \n        \"sndbuf_actual\": 65536, \n        \"sock_bufsize\": 0, \n        \"system_info\": \"REDACTED\", \n        \"target_bitrate\": 0, \n        \"tcp_mss_default\": 0, \n        \"test_start\": {\n            \"bidir\": 0, \n            \"blksize\": 131072, \n            \"blocks\": 0, \n            \"bytes\": 0, \n            \"duration\": 10, \n            \"fqrate\": 0, \n            \"num_streams\": 1, \n            \"omit\": 0, \n            \"protocol\": \"TCP\", \n            \"reverse\": 0, \n            \"target_bitrate\": 0, \n            \"tos\": 0\n        }, \n        \"timestamp\": {\n            \"time\": \"Sat, 12 Oct 2024 02:38:18 GMT\", \n            \"timesecs\": 1728700698\n        }, \n        \"version\": \"iperf 3.14\"\n    }\n}\n","summary":{"streams":[{"end":10.000119,"rtt":229597,"start":0,"stream-id":5,"retransmits":290,"throughput-bits":13316756.730594907,"throughput-bytes":16646144}],"summary":{"end":10.000119,"start":0,"retransmits":290,"throughput-bits":13316756.730594907,"throughput-bytes":16646144,"receiver-throughput-bits":10383635.54248497}},"intervals":[{"streams":[{"end":1.000154,"rtt":337937,"start":0,"omitted":false,"stream-id":5,"retransmits":64,"tcp-window-size":518384,"throughput-bits":38791337.42019524,"throughput-bytes":4849664}],"summary":{"end":1.000154,"start":0,"omitted":false,"retransmits":64,"throughput-bits":38791337.42019524,"throughput-bytes":4849664}},{"streams":[{"end":2.000034,"rtt":109668,"start":1.000154,"omitted":false,"stream-id":5,"retransmits":212,"tcp-window-size":201272,"throughput-bits":10487018.275973173,"throughput-bytes":1310720}],"summary":{"end":2.000034,"start":1.000154,"omitted":false,"retransmits":212,"throughput-bits":10487018.275973173,"throughput-bytes":1310720}},{"streams":[{"end":3.000079,"rtt":157170,"start":2.000034,"omitted":false,"stream-id":5,"retransmits":0,"tcp-window-size":212856,"throughput-bits":10485288.77117792,"throughput-bytes":1310720}],"summary":{"end":3.000079,"start":2.000034,"omitted":false,"retransmits":0,"throughput-bits":10485288.77117792,"throughput-bytes":1310720}},{"streams":[{"end":4.000733,"rtt":174313,"start":3.000079,"omitted":false,"stream-id":5,"retransmits":0,"tcp-window-size":227336,"throughput-bits":10478906.981751693,"throughput-bytes":1310720}],"summary":{"end":4.000733,"start":3.000079,"omitted":false,"retransmits":0,"throughput-bits":10478906.981751693,"throughput-bytes":1310720}},{"streams":[{"end":5.000567,"rtt":217169,"start":4.000733,"omitted":false,"stream-id":5,"retransmits":0,"tcp-window-size":264984,"throughput-bits":10487500.91398987,"throughput-bytes":1310720}],"summary":{"end":5.000567,"start":4.000733,"omitted":false,"retransmits":0,"throughput-bits":10487500.91398987,"throughput-bytes":1310720}},{"streams":[{"end":6.000076,"rtt":297460,"start":5.000567,"omitted":false,"stream-id":5,"retransmits":0,"tcp-window-size":304080,"throughput-bits":10490911.279396992,"throughput-bytes":1310720}],"summary":{"end":6.000076,"start":5.000567,"omitted":false,"retransmits":0,"throughput-bits":10490911.279396992,"throughput-bytes":1310720}},{"streams":[{"end":7.000021,"rtt":213822,"start":6.000076,"omitted":false,"stream-id":5,"retransmits":0,"tcp-window-size":370688,"throughput-bits":10486336.906738574,"throughput-bytes":1310720}],"summary":{"end":7.000021,"start":6.000076,"omitted":false,"retransmits":0,"throughput-bits":10486336.906738574,"throughput-bytes":1310720}},{"streams":[{"end":8.000021,"rtt":420107,"start":7.000021,"omitted":false,"stream-id":5,"retransmits":8,"tcp-window-size":293944,"throughput-bits":10485760,"throughput-bytes":1310720}],"summary":{"end":8.000021,"start":7.000021,"omitted":false,"retransmits":8,"throughput-bits":10485760,"throughput-bytes":1310720}},{"streams":[{"end":9.000056,"rtt":187107,"start":8.000021,"omitted":false,"stream-id":5,"retransmits":6,"tcp-window-size":212856,"throughput-bits":10485392.512879517,"throughput-bytes":1310720}],"summary":{"end":9.000056,"start":8.000021,"omitted":false,"retransmits":6,"throughput-bits":10485392.512879517,"throughput-bytes":1310720}},{"streams":[{"end":10.000119,"rtt":181220,"start":9.000056,"omitted":false,"stream-id":5,"retransmits":0,"tcp-window-size":222992,"throughput-bits":10485100.041539438,"throughput-bytes":1310720}],"summary":{"end":10.000119,"start":9.000056,"omitted":false,"retransmits":0,"throughput-bits":10485100.041539438,"throughput-bytes":1310720}}],"succeeded":true}
