{"diags":"Participant 0:\n/usr/bin/iperf3 -p 5201 -B 10.0.0.1 -c 10.0.0.2 -t 60 --json --rsa-public-key-path /var/run/pscheduler-server/runner/tmp/tmpd6smnk16/tmpx58ml3rf/public-key --username Oki9irglhhTG3JXLZ2Dh\n\n{\n    \"end\": {\n        \"cpu_utilization_percent\": {\n            \"host_system\": 2.048816277276287, \n            \"host_total\": 2.0827024667742777, \n            \"host_user\": 0.03388452301871988, \n            \"remote_system\": 5.37580819647114, \n            \"remote_total\": 5.93489425965781, \n            \"remote_user\": 0.5590893922490373\n        }, \n        \"receiver_tcp_congestion\": \"htcp\", \n        \"sender_tcp_congestion\": \"htcp\", \n        \"streams\": [\n            {\n                \"receiver\": {\n                    \"bits_per_second\": 865535438.84679, \n                    \"bytes\": 6499843216, \n                    \"end\": 60.076969, \n                    \"seconds\": 60.000073, \n                    \"sender\": true, \n                    \"socket\": 5, \n                    \"start\": 0\n                }, \n                \"sender\": {\n                    \"bits_per_second\": 867014010.7329535, \n                    \"bytes\": 6502612992, \n                    \"end\": 60.000073, \n                    \"max_rtt\": 77093, \n                    \"max_snd_cwnd\": 16698336, \n                    \"max_snd_wnd\": 0, \n                    \"mean_rtt\": 77086, \n                    \"min_rtt\": 77078, \n                    \"retransmits\": 0, \n                    \"seconds\": 60.000073, \n                    \"sender\": true, \n                    \"socket\": 5, \n                    \"start\": 0\n                }\n            }\n        ], \n        \"sum_received\": {\n            \"bits_per_second\": 865535438.84679, \n            \"bytes\": 6499843216, \n            \"end\": 60.076969, \n            \"seconds\": 60.076969, \n            \"sender\": true, \n            \"start\": 0\n        }, \n        \"sum_sent\": {\n            \"bits_per_second\": 867014010.7329535, \n            \"bytes\": 6502612992, \n            \"end\": 60.000073, \n            \"retransmits\": 0, \n            \"seconds\": 60.000073, \n            \"sender\": true, \n            \"start\": 0\n        }\n    }, \n    \"intervals\": [\n        {\n            \"streams\": [\n                {\n                    \"bits_per_second\": 955201153.410553, \n                    \"bytes\": 119406592, \n                    \"end\": 1.000054, \n                    \"omitted\": false, \n                    \"pmtu\": 1500, \n                    \"retransmits\": 0, \n                    \"rtt\": 77090, \n                    \"rttvar\": 7, \n                    \"seconds\": 1.0000540018081665, \n                    \"sender\": true, \n                    \"snd_cwnd\": 16698336, \n                    \"snd_wnd\": -1, \n                    \"socket\": 5, \n                    \"start\": 0\n                }\n            ], \n            \"sum\": {\n                \"bits_per_second\": 955201153.410553, \n                \"bytes\": 119406592, \n                \"end\": 1.000054, \n                \"omitted\": false, \n                \"retransmits\": 0, \n                \"seconds\": 1.0000540018081665, \n                \"sender\": true, \n                \"start\": 0\n            }\n        }, \n        {\n            \"streams\": [\n                {\n                    \"bits_per_second\": 870291935.7853916, \n                    \"bytes\": 108789760, \n                    \"end\": 2.000084, \n                    \"omitted\": false, \n                    \"pmtu\": 1500, \n                    \"retransmits\": 0, \n                    \"rtt\": 77088, \n                    \"rttvar\": 6, \n                    \"seconds\": 1.0000300407409668, \n                    \"sender\": true, \n                    \"snd_cwnd\": 16698336, \n                    \"snd_wnd\": -1, \n                    \"socket\": 5, \n                    \"start\": 1.000054\n                }\n            ], \n            \"sum\": {\n                \"bits_per_second\": 870291935.7853916, \n                \"bytes\": 108789760, \n                \"end\": 2.000084, \n                \"omitted\": false, \n                \"retransmits\": 0, \n                \"seconds\": 1.0000300407409668, \n                \"sender\": true, \n                \"start\": 1.000054\n            }\n        }, \n        {\n            \"streams\": [\n                {\n                    \"bits_per_second\": 859840058.8196517, \n                    \"bytes\": 107479040, \n                    \"end\": 3.000075, \n                    \"omitted\": false, \n                    \"pmtu\": 1500, \n                    \"retransmits\": 0, \n                    \"rtt\": 77089, \n                    \"rttvar\": 8, \n                    \"seconds\": 0.999990999698639, \n                    \"sender\": true, \n                    \"snd_cwnd\": 16698336, \n                    \"snd_wnd\": -1, \n                    \"socket\": 5, \n                    \"start\": 2.000084\n                }\n            ], \n            \"sum\": {\n                \"bits_per_second\": 859840058.8196517, \n                \"bytes\": 107479040, \n                \"end\": 3.000075, \n                \"omitted\": false, \n                \"retransmits\": 0, \n                \"seconds\": 0.999990999698639, \n                \"sender\": true, \n                \"start\": 2.000084\n            }\n        }, \n        {\n            \"streams\": [\n                {\n                    \"bits_per_second\": 870328506.999921, \n                    \"bytes\": 108789760, \n                    \"end\": 4.000063, \n                    \"omitted\": false, \n                    \"pmtu\": 1500, \n                    \"retransmits\": 0, \n                    \"rtt\": 77084, \n                    \"rttvar\": 5, \n                    \"seconds\": 0.9999880194664, \n                    \"sender\": true, \n                    \"snd_cwnd\": 16698336, \n                    \"snd_wnd\": -1, \n                    \"socket\": 5, \n                    \"start\": 3.000075\n                }\n            ], \n            \"sum\": {\n                \"bits_per_second\": 870328506.999921, \n                \"bytes\": 108789760, \n                \"end\": 4.000063, \n                \"omitted\": false, \n                \"retransmits\": 0, \n                \"seconds\": 0.9999880194664, \n                \"sender\": true, \n                \"start\": 3.000075\n            }\n        }, \n        {\n            \"streams\": [\n                {\n                    \"bits_per_second\": 859751455.105839, \n                    \"bytes\": 107479040, \n                    \"end\": 5.000157, \n                    \"omitted\": false, \n                    \"pmtu\": 1500, \n                    \"retransmits\": 0, \n                    \"rtt\": 77083, \n                    \"rttvar\": 5, \n                    \"seconds\": 1.0000940561294556, \n                    \"sender\": true, \n                    \"snd_cwnd\": 16698336, \n                    \"snd_wnd\": -1, \n                    \"socket\": 5, \n                    \"start\": 4.000063\n                }\n            ], \n            \"sum\": {\n                \"bits_per_second\": 859751455.105839, \n                \"bytes\": 107479040, \n                \"end\": 5.000157, \n                \"omitted\": false, \n                \"retransmits\": 0, \n                \"seconds\": 1.0000940561294556, \n                \"sender\": true, \n                \"start\": 4.000063\n            }\n        }, \n        {\n            \"streams\": [\n                {\n                    \"bits_per_second\": 870311128.8055193, \n                    \"bytes\": 108789760, \n                    \"end\": 6.000165, \n                    \"omitted\": false, \n                    \"pmtu\": 1500, \n                    \"retransmits\": 0, \n                    \"rtt\": 77084, \n                    \"rttvar\": 5, \n                    \"seconds\": 1.0000079870224, \n                    \"sender\": true, \n                    \"snd_cwnd\": 16698336, \n                    \"snd_wnd\": -1, \n                    \"socket\": 5, \n                    \"start\": 5.000157\n                }\n            ], \n            \"sum\": {\n                \"bits_per_second\": 870311128.8055193, \n                \"bytes\": 108789760, \n                \"end\": 6.000165, \n                \"omitted\": false, \n                \"retransmits\": 0, \n                \"seconds\": 1.0000079870224, \n                \"sender\": true, \n                \"start\": 5.000157\n            }\n        }, \n        {\n            \"streams\": [\n                {\n                    \"bits_per_second\": 870406847.1777917, \n                    \"bytes\": 108789760, \n                    \"end\": 7.000063, \n                    \"omitted\": false, \n                    \"pmtu\": 1500, \n                    \"retransmits\": 0, \n                    \"rtt\": 77087, \n                    \"rttvar\": 9, \n                    \"seconds\": 0.9998980164527893, \n                    \"sender\": true, \n                    \"snd_cwnd\": 16698336, \n                    \"snd_wnd\": -1, \n                    \"socket\": 5, \n                    \"start\": 6.000165\n                }\n            ], \n            \"sum\": {\n                \"bits_per_second\": 870406847.1777917, \n                \"bytes\": 108789760, \n                \"end\": 7.000063, \n                \"omitted\": false, \n                \"retransmits\": 0, \n                \"seconds\": 0.9998980164527893, \n                \"sender\": true, \n                \"start\": 6.000165\n            }\n        }, \n        {\n            \"streams\": [\n                {\n                    \"bits_per_second\": 859780765.5913196, \n                    \"bytes\": 107479040, \n                    \"end\": 8.000123, \n                    \"omitted\": false, \n                    \"pmtu\": 1500, \n                    \"retransmits\": 0, \n                    \"rtt\": 77085, \n                    \"rttvar\": 5, \n                    \"seconds\": 1.000059962272644, \n                    \"sender\": true, \n                    \"snd_cwnd\": 16698336, \n                    \"snd_wnd\": -1, \n                    \"socket\": 5, \n                    \"start\": 7.000063\n                }\n            ], \n            \"sum\": {\n                \"bits_per_second\": 859780765.5913196, \n                \"bytes\": 107479040, \n                \"end\": 8.000123, \n                \"omitted\": false, \n                \"retransmits\": 0, \n                \"seconds\": 1.000059962272644, \n                \"sender\": true, \n                \"start\": 7.000063\n            }\n        }, \n        {\n            \"streams\": [\n                {\n                    \"bits_per_second\": 870353771.4636353, \n                    \"bytes\": 108789760, \n                    \"end\": 9.000082, \n                    \"omitted\": false, \n                    \"pmtu\": 1500, \n                    \"retransmits\": 0, \n                    \"rtt\": 77090, \n                    \"rttvar\": 7, \n                    \"seconds\": 0.9999589920043945, \n                    \"sender\": true, \n                    \"snd_cwnd\": 16698336, \n                    \"snd_wnd\": -1, \n                    \"socket\": 5, \n                    \"start\": 8.000123\n                }\n            ], \n            \"sum\": {\n                \"bits_per_second\": 870353771.4636353, \n                \"bytes\": 108789760, \n                \"end\": 9.000082, \n                \"omitted\": false, \n                \"retransmits\": 0, \n                \"seconds\": 0.9999589920043945, \n                \"sender\": true, \n                \"start\": 8.000123\n            }\n        }, \n        {\n            \"streams\": [\n                {\n                    \"bits_per_second\": 859793679.2365894, \n                    \"bytes\": 107479040, \n                    \"end\": 10.000127, \n                    \"omitted\": false, \n                    \"pmtu\": 1500, \n                    \"retransmits\": 0, \n                    \"rtt\": 77084, \n                    \"rttvar\": 9, \n                    \"seconds\": 1.0000449419021606, \n                    \"sender\": true, \n                    \"snd_cwnd\": 16698336, \n                    \"snd_wnd\": -1, \n                    \"socket\": 5, \n                    \"start\": 9.000082\n                }\n            ], \n            \"sum\": {\n                \"bits_per_second\": 859793679.2365894, \n                \"bytes\": 107479040, \n                \"end\": 10.000127, \n                \"omitted\": false, \n                \"retransmits\": 0, \n                \"seconds\": 1.0000449419021606, \n                \"sender\": true, \n                \"start\": 9.000082\n            }\n        }, \n        {\n            \"streams\": [\n                {\n                    \"bits_per_second\": 870373797.3167657, \n                    \"bytes\": 108789760, \n                    \"end\": 11.000063, \n                    \"omitted\": false, \n                    \"pmtu\": 1500, \n                    \"retransmits\": 0, \n                    \"rtt\": 77090, \n                    \"rttvar\": 5, \n                    \"seconds\": 0.9999359846115112, \n                    \"sender\": true, \n                    \"snd_cwnd\": 16698336, \n                    \"snd_wnd\": -1, \n                    \"socket\": 5, \n                    \"start\": 10.000127\n                }\n            ], \n            \"sum\": {\n                \"bits_per_second\": 870373797.3167657, \n                \"bytes\": 108789760, \n                \"end\": 11.000063, \n                \"omitted\": false, \n                \"retransmits\": 0, \n                \"seconds\": 0.9999359846115112, \n                \"sender\": true, \n                \"start\": 10.000127\n            }\n        }, \n        {\n            \"streams\": [\n                {\n                    \"bits_per_second\": 859818585.2194, \n                    \"bytes\": 107479040, \n                    \"end\": 12.000079, \n                    \"omitted\": false, \n                    \"pmtu\": 1500, \n                    \"retransmits\": 0, \n                    \"rtt\": 77089, \n                    \"rttvar\": 9, \n                    \"seconds\": 1.0000159740448, \n                    \"sender\": true, \n                    \"snd_cwnd\": 16698336, \n                    \"snd_wnd\": -1, \n                    \"socket\": 5, \n                    \"start\": 11.000063\n                }\n            ], \n            \"sum\": {\n                \"bits_per_second\": 859818585.2194, \n                \"bytes\": 107479040, \n                \"end\": 12.000079, \n                \"omitted\": false, \n                \"retransmits\": 0, \n                \"seconds\": 1.0000159740448, \n                \"sender\": true, \n                \"start\": 11.000063\n            }\n        }, \n        {\n            \"streams\": [\n                {\n                    \"bits_per_second\": 870332864.6261512, \n                    \"bytes\": 108789760, \n                    \"end\": 13.000062, \n                    \"omitted\": false, \n                    \"pmtu\": 1500, \n                    \"retransmits\": 0, \n                    \"rtt\": 77085, \n                    \"rttvar\": 9, \n                    \"seconds\": 0.999983012676239, \n                    \"sender\": true, \n                    \"snd_cwnd\": 16698336, \n                    \"snd_wnd\": -1, \n                    \"socket\": 5, \n                    \"start\": 12.000079\n                }\n            ], \n            \"sum\": {\n                \"bits_per_second\": 870332864.6261512, \n                \"bytes\": 108789760, \n                \"end\": 13.000062, \n                \"omitted\": false, \n                \"retransmits\": 0, \n                \"seconds\": 0.999983012676239, \n                \"sender\": true, \n                \"start\": 12.000079\n            }\n        }, \n        {\n            \"streams\": [\n                {\n                    \"bits_per_second\": 859818585.2194, \n                    \"bytes\": 107479040, \n                    \"end\": 14.000078, \n                    \"omitted\": false, \n                    \"pmtu\": 1500, \n                    \"retransmits\": 0, \n                    \"rtt\": 77087, \n                    \"rttvar\": 6, \n                    \"seconds\": 1.0000159740448, \n                    \"sender\": true, \n                    \"snd_cwnd\": 16698336, \n                    \"snd_wnd\": -1, \n                    \"socket\": 5, \n                    \"start\": 13.000062\n                }\n            ], \n            \"sum\": {\n                \"bits_per_second\": 859818585.2194, \n                \"bytes\": 107479040, \n                \"end\": 14.000078, \n                \"omitted\": false, \n                \"retransmits\": 0, \n                \"seconds\": 1.0000159740448, \n                \"sender\": true, \n                \"start\": 13.000062\n            }\n        }, \n        {\n            \"streams\": [\n                {\n                    \"bits_per_second\": 870345937.766663, \n                    \"bytes\": 108789760, \n                    \"end\": 15.000046, \n                    \"omitted\": false, \n                    \"pmtu\": 1500, \n                    \"retransmits\": 0, \n                    \"rtt\": 77085, \n                    \"rttvar\": 8, \n                    \"seconds\": 0.9999679923057556, \n                    \"sender\": true, \n                    \"snd_cwnd\": 16698336, \n                    \"snd_wnd\": -1, \n                    \"socket\": 5, \n                    \"start\": 14.000078\n                }\n            ], \n            \"sum\": {\n                \"bits_per_second\": 870345937.766663, \n                \"bytes\": 108789760, \n                \"end\": 15.000046, \n                \"omitted\": false, \n                \"retransmits\": 0, \n                \"seconds\": 0.9999679923057556, \n                \"sender\": true, \n                \"start\": 14.000078\n            }\n        }, \n        {\n            \"streams\": [\n                {\n                    \"bits_per_second\": 859812537.9551333, \n                    \"bytes\": 107479040, \n                    \"end\": 16.000069, \n                    \"omitted\": false, \n                    \"pmtu\": 1500, \n                    \"retransmits\": 0, \n                    \"rtt\": 77087, \n                    \"rttvar\": 7, \n                    \"seconds\": 1.0000230073928833, \n                    \"sender\": true, \n                    \"snd_cwnd\": 16698336, \n                    \"snd_wnd\": -1, \n                    \"socket\": 5, \n                    \"start\": 15.000046\n                }\n            ], \n            \"sum\": {\n                \"bits_per_second\": 859812537.9551333, \n                \"bytes\": 107479040, \n                \"end\": 16.000069, \n                \"omitted\": false, \n                \"retransmits\": 0, \n                \"seconds\": 1.0000230073928833, \n                \"sender\": true, \n                \"start\": 15.000046\n            }\n        }, \n        {\n            \"streams\": [\n                {\n                    \"bits_per_second\": 870316316.2535744, \n                    \"bytes\": 108789760, \n                    \"end\": 17.000071, \n                    \"omitted\": false, \n                    \"pmtu\": 1500, \n                    \"retransmits\": 0, \n                    \"rtt\": 77088, \n                    \"rttvar\": 9, \n                    \"seconds\": 1.0000020265579224, \n                    \"sender\": true, \n                    \"snd_cwnd\": 16698336, \n                    \"snd_wnd\": -1, \n                    \"socket\": 5, \n                    \"start\": 16.000069\n                }\n            ], \n            \"sum\": {\n                \"bits_per_second\": 870316316.2535744, \n                \"bytes\": 108789760, \n                \"end\": 17.000071, \n                \"omitted\": false, \n                \"retransmits\": 0, \n                \"seconds\": 1.0000020265579224, \n                \"sender\": true, \n                \"start\": 16.000069\n            }\n        }, \n        {\n            \"streams\": [\n                {\n                    \"bits_per_second\": 870192768.0455257, \n                    \"bytes\": 108789760, \n                    \"end\": 18.000215, \n                    \"omitted\": false, \n                    \"pmtu\": 1500, \n                    \"retransmits\": 0, \n                    \"rtt\": 77087, \n                    \"rttvar\": 9, \n                    \"seconds\": 1.0001440048217773, \n                    \"sender\": true, \n                    \"snd_cwnd\": 16698336, \n                    \"snd_wnd\": -1, \n                    \"socket\": 5, \n                    \"start\": 17.000071\n                }\n            ], \n            \"sum\": {\n                \"bits_per_second\": 870192768.0455257, \n                \"bytes\": 108789760, \n                \"end\": 18.000215, \n                \"omitted\": false, \n                \"retransmits\": 0, \n                \"seconds\": 1.0001440048217773, \n                \"sender\": true, \n                \"start\": 17.000071\n            }\n        }, \n        {\n            \"streams\": [\n                {\n                    \"bits_per_second\": 859883931.84784, \n                    \"bytes\": 107479040, \n                    \"end\": 19.000155, \n                    \"omitted\": false, \n                    \"pmtu\": 1500, \n                    \"retransmits\": 0, \n                    \"rtt\": 77081, \n                    \"rttvar\": 7, \n                    \"seconds\": 0.9999399781227112, \n                    \"sender\": true, \n                    \"snd_cwnd\": 16698336, \n                    \"snd_wnd\": -1, \n                    \"socket\": 5, \n                    \"start\": 18.000215\n                }\n            ], \n            \"sum\": {\n                \"bits_per_second\": 859883931.84784, \n                \"bytes\": 107479040, \n                \"end\": 19.000155, \n                \"omitted\": false, \n                \"retransmits\": 0, \n                \"seconds\": 0.9999399781227112, \n                \"sender\": true, \n                \"start\": 18.000215\n            }\n        }, \n        {\n            \"streams\": [\n                {\n                    \"bits_per_second\": 870393824.0914615, \n                    \"bytes\": 108789760, \n                    \"end\": 20.000068, \n                    \"omitted\": false, \n                    \"pmtu\": 1500, \n                    \"retransmits\": 0, \n                    \"rtt\": 77092, \n                    \"rttvar\": 7, \n                    \"seconds\": 0.999912977218628, \n                    \"sender\": true, \n                    \"snd_cwnd\": 16698336, \n                    \"snd_wnd\": -1, \n                    \"socket\": 5, \n                    \"start\": 19.000155\n                }\n            ], \n            \"sum\": {\n                \"bits_per_second\": 870393824.0914615, \n                \"bytes\": 108789760, \n                \"end\": 20.000068, \n                \"omitted\": false, \n                \"retransmits\": 0, \n                \"seconds\": 0.999912977218628, \n                \"sender\": true, \n                \"start\": 19.000155\n            }\n        }, \n        {\n            \"streams\": [\n                {\n                    \"bits_per_second\": 859817662.749861, \n                    \"bytes\": 107479040, \n                    \"end\": 21.000085, \n                    \"omitted\": false, \n                    \"pmtu\": 1500, \n                    \"retransmits\": 0, \n                    \"rtt\": 77090, \n                    \"rttvar\": 8, \n                    \"seconds\": 1.0000170469284058, \n                    \"sender\": true, \n                    \"snd_cwnd\": 16698336, \n                    \"snd_wnd\": -1, \n                    \"socket\": 5, \n                    \"start\": 20.000068\n                }\n            ], \n            \"sum\": {\n                \"bits_per_second\": 859817662.749861, \n                \"bytes\": 107479040, \n                \"end\": 21.000085, \n                \"omitted\": false, \n                \"retransmits\": 0, \n                \"seconds\": 1.0000170469284058, \n                \"sender\": true, \n                \"start\": 20.000068\n            }\n        }, \n        {\n            \"streams\": [\n                {\n                    \"bits_per_second\": 870360723.339311, \n                    \"bytes\": 108789760, \n                    \"end\": 22.000036, \n                    \"omitted\": false, \n                    \"pmtu\": 1500, \n                    \"retransmits\": 0, \n                    \"rtt\": 77087, \n                    \"rttvar\": 5, \n                    \"seconds\": 0.9999510049819946, \n                    \"sender\": true, \n                    \"snd_cwnd\": 16698336, \n                    \"snd_wnd\": -1, \n                    \"socket\": 5, \n                    \"start\": 21.000085\n                }\n            ], \n            \"sum\": {\n                \"bits_per_second\": 870360723.339311, \n                \"bytes\": 108789760, \n                \"end\": 22.000036, \n                \"omitted\": false, \n                \"retransmits\": 0, \n                \"seconds\": 0.9999510049819946, \n                \"sender\": true, \n                \"start\": 21.000085\n            }\n        }, \n        {\n            \"streams\": [\n                {\n                    \"bits_per_second\": 859808233.1747727, \n                    \"bytes\": 107479040, \n                    \"end\": 23.000064, \n                    \"omitted\": false, \n                    \"pmtu\": 1500, \n                    \"retransmits\": 0, \n                    \"rtt\": 77091, \n                    \"rttvar\": 6, \n                    \"seconds\": 1.0000280141830444, \n                    \"sender\": true, \n                    \"snd_cwnd\": 16698336, \n                    \"snd_wnd\": -1, \n                    \"socket\": 5, \n                    \"start\": 22.000036\n                }\n            ], \n            \"sum\": {\n                \"bits_per_second\": 859808233.1747727, \n                \"bytes\": 107479040, \n                \"end\": 23.000064, \n                \"omitted\": false, \n                \"retransmits\": 0, \n                \"seconds\": 1.0000280141830444, \n                \"sender\": true, \n                \"start\": 22.000036\n            }\n        }, \n        {\n            \"streams\": [\n                {\n                    \"bits_per_second\": 870237992.3704302, \n                    \"bytes\": 108789760, \n                    \"end\": 24.000156, \n                    \"omitted\": false, \n                    \"pmtu\": 1500, \n                    \"retransmits\": 0, \n                    \"rtt\": 77085, \n                    \"rttvar\": 9, \n                    \"seconds\": 1.0000920295715332, \n                    \"sender\": true, \n                    \"snd_cwnd\": 16698336, \n                    \"snd_wnd\": -1, \n                    \"socket\": 5, \n                    \"start\": 23.000064\n                }\n            ], \n            \"sum\": {\n                \"bits_per_second\": 870237992.3704302, \n                \"bytes\": 108789760, \n                \"end\": 24.000156, \n                \"omitted\": false, \n                \"retransmits\": 0, \n                \"seconds\": 1.0000920295715332, \n                \"sender\": true, \n                \"start\": 23.000064\n            }\n        }, \n        {\n            \"streams\": [\n                {\n                    \"bits_per_second\": 859911457.2829702, \n                    \"bytes\": 107479040, \n                    \"end\": 25.000064, \n                    \"omitted\": false, \n                    \"pmtu\": 1500, \n                    \"retransmits\": 0, \n                    \"rtt\": 77087, \n                    \"rttvar\": 7, \n                    \"seconds\": 0.9999079704284668, \n                    \"sender\": true, \n                    \"snd_cwnd\": 16698336, \n                    \"snd_wnd\": -1, \n                    \"socket\": 5, \n                    \"start\": 24.000156\n                }\n            ], \n            \"sum\": {\n                \"bits_per_second\": 859911457.2829702, \n                \"bytes\": 107479040, \n                \"end\": 25.000064, \n                \"omitted\": false, \n                \"retransmits\": 0, \n                \"seconds\": 0.9999079704284668, \n                \"sender\": true, \n                \"start\": 24.000156\n            }\n        }, \n        {\n            \"streams\": [\n                {\n                    \"bits_per_second\": 870303244.0029082, \n                    \"bytes\": 108789760, \n                    \"end\": 26.000081, \n                    \"omitted\": false, \n                    \"pmtu\": 1500, \n                    \"retransmits\": 0, \n                    \"rtt\": 77088, \n                    \"rttvar\": 9, \n                    \"seconds\": 1.0000170469284058, \n                    \"sender\": true, \n                    \"snd_cwnd\": 16698336, \n                    \"snd_wnd\": -1, \n                    \"socket\": 5, \n                    \"start\": 25.000064\n                }\n            ], \n            \"sum\": {\n                \"bits_per_second\": 870303244.0029082, \n                \"bytes\": 108789760, \n                \"end\": 26.000081, \n                \"omitted\": false, \n                \"retransmits\": 0, \n                \"seconds\": 1.0000170469284058, \n                \"sender\": true, \n                \"start\": 25.000064\n            }\n        }, \n        {\n            \"streams\": [\n                {\n                    \"bits_per_second\": 859847797.7786094, \n                    \"bytes\": 107479040, \n                    \"end\": 27.000063, \n                    \"omitted\": false, \n                    \"pmtu\": 1500, \n                    \"retransmits\": 0, \n                    \"rtt\": 77087, \n                    \"rttvar\": 6, \n                    \"seconds\": 0.9999819993972778, \n                    \"sender\": true, \n                    \"snd_cwnd\": 16698336, \n                    \"snd_wnd\": -1, \n                    \"socket\": 5, \n                    \"start\": 26.000081\n                }\n            ], \n            \"sum\": {\n                \"bits_per_second\": 859847797.7786094, \n                \"bytes\": 107479040, \n                \"end\": 27.000063, \n                \"omitted\": false, \n                \"retransmits\": 0, \n                \"seconds\": 0.9999819993972778, \n                \"sender\": true, \n                \"start\": 26.000081\n            }\n        }, \n        {\n            \"streams\": [\n                {\n                    \"bits_per_second\": 870317250.0007915, \n                    \"bytes\": 108789760, \n                    \"end\": 28.000064, \n                    \"omitted\": false, \n                    \"pmtu\": 1500, \n                    \"retransmits\": 0, \n                    \"rtt\": 77084, \n                    \"rttvar\": 4, \n                    \"seconds\": 1.0000009536743164, \n                    \"sender\": true, \n                    \"snd_cwnd\": 16698336, \n                    \"snd_wnd\": -1, \n                    \"socket\": 5, \n                    \"start\": 27.000063\n                }\n            ], \n            \"sum\": {\n                \"bits_per_second\": 870317250.0007915, \n                \"bytes\": 108789760, \n                \"end\": 28.000064, \n                \"omitted\": false, \n                \"retransmits\": 0, \n                \"seconds\": 1.0000009536743164, \n                \"sender\": true, \n                \"start\": 27.000063\n            }\n        }, \n        {\n            \"streams\": [\n                {\n                    \"bits_per_second\": 870335510.3490804, \n                    \"bytes\": 108789760, \n                    \"end\": 29.000044, \n                    \"omitted\": false, \n                    \"pmtu\": 1500, \n                    \"retransmits\": 0, \n                    \"rtt\": 77088, \n                    \"rttvar\": 8, \n                    \"seconds\": 0.9999799728393555, \n                    \"sender\": true, \n                    \"snd_cwnd\": 16698336, \n                    \"snd_wnd\": -1, \n                    \"socket\": 5, \n                    \"start\": 28.000064\n                }\n            ], \n            \"sum\": {\n                \"bits_per_second\": 870335510.3490804, \n                \"bytes\": 108789760, \n                \"end\": 29.000044, \n                \"omitted\": false, \n                \"retransmits\": 0, \n                \"seconds\": 0.9999799728393555, \n                \"sender\": true, \n                \"start\": 28.000064\n            }\n        }, \n        {\n            \"streams\": [\n                {\n                    \"bits_per_second\": 859802186.0561204, \n                    \"bytes\": 107479040, \n                    \"end\": 30.000079, \n                    \"omitted\": false, \n                    \"pmtu\": 1500, \n                    \"retransmits\": 0, \n                    \"rtt\": 77082, \n                    \"rttvar\": 8, \n                    \"seconds\": 1.000035047531128, \n                    \"sender\": true, \n                    \"snd_cwnd\": 16698336, \n                    \"snd_wnd\": -1, \n                    \"socket\": 5, \n                    \"start\": 29.000044\n                }\n            ], \n            \"sum\": {\n                \"bits_per_second\": 859802186.0561204, \n                \"bytes\": 107479040, \n                \"end\": 30.000079, \n                \"omitted\": false, \n                \"retransmits\": 0, \n                \"seconds\": 1.000035047531128, \n                \"sender\": true, \n                \"start\": 29.000044\n            }\n        }, \n        {\n            \"streams\": [\n                {\n                    \"bits_per_second\": 870325031.30552, \n                    \"bytes\": 108789760, \n                    \"end\": 31.000071, \n                    \"omitted\": false, \n                    \"pmtu\": 1500, \n                    \"retransmits\": 0, \n                    \"rtt\": 77085, \n                    \"rttvar\": 11, \n                    \"seconds\": 0.9999920129776, \n                    \"sender\": true, \n                    \"snd_cwnd\": 16698336, \n                    \"snd_wnd\": -1, \n                    \"socket\": 5, \n                    \"start\": 30.000079\n                }\n            ], \n            \"sum\": {\n                \"bits_per_second\": 870325031.30552, \n                \"bytes\": 108789760, \n                \"end\": 31.000071, \n                \"omitted\": false, \n                \"retransmits\": 0, \n                \"seconds\": 0.9999920129776, \n                \"sender\": true, \n                \"start\": 30.000079\n            }\n        }, \n        {\n            \"streams\": [\n                {\n                    \"bits_per_second\": 859837496.2811615, \n                    \"bytes\": 107479040, \n                    \"end\": 32.000065, \n                    \"omitted\": false, \n                    \"pmtu\": 1500, \n                    \"retransmits\": 0, \n                    \"rtt\": 77082, \n                    \"rttvar\": 6, \n                    \"seconds\": 0.9999939799308777, \n                    \"sender\": true, \n                    \"snd_cwnd\": 16698336, \n                    \"snd_wnd\": -1, \n                    \"socket\": 5, \n                    \"start\": 31.000071\n                }\n            ], \n            \"sum\": {\n                \"bits_per_second\": 859837496.2811615, \n                \"bytes\": 107479040, \n                \"end\": 32.000065, \n                \"omitted\": false, \n                \"retransmits\": 0, \n                \"seconds\": 0.9999939799308777, \n                \"sender\": true, \n                \"start\": 31.000071\n            }\n        }, \n        {\n            \"streams\": [\n                {\n                    \"bits_per_second\": 870301584.0626686, \n                    \"bytes\": 108789760, \n                    \"end\": 33.000084, \n                    \"omitted\": false, \n                    \"pmtu\": 1500, \n                    \"retransmits\": 0, \n                    \"rtt\": 77084, \n                    \"rttvar\": 6, \n                    \"seconds\": 1.0000189542770386, \n                    \"sender\": true, \n                    \"snd_cwnd\": 16698336, \n                    \"snd_wnd\": -1, \n                    \"socket\": 5, \n                    \"start\": 32.000065\n                }\n            ], \n            \"sum\": {\n                \"bits_per_second\": 870301584.0626686, \n                \"bytes\": 108789760, \n                \"end\": 33.000084, \n                \"omitted\": false, \n                \"retransmits\": 0, \n                \"seconds\": 1.0000189542770386, \n                \"sender\": true, \n                \"start\": 32.000065\n            }\n        }, \n        {\n            \"streams\": [\n                {\n                    \"bits_per_second\": 859841801.3545495, \n                    \"bytes\": 107479040, \n                    \"end\": 34.000073, \n                    \"omitted\": false, \n                    \"pmtu\": 1500, \n                    \"retransmits\": 0, \n                    \"rtt\": 77084, \n                    \"rttvar\": 8, \n                    \"seconds\": 0.9999889731407166, \n                    \"sender\": true, \n                    \"snd_cwnd\": 16698336, \n                    \"snd_wnd\": -1, \n                    \"socket\": 5, \n                    \"start\": 33.000084\n                }\n            ], \n            \"sum\": {\n                \"bits_per_second\": 859841801.3545495, \n                \"bytes\": 107479040, \n                \"end\": 34.000073, \n                \"omitted\": false, \n                \"retransmits\": 0, \n                \"seconds\": 0.9999889731407166, \n                \"sender\": true, \n                \"start\": 33.000084\n            }\n        }, \n        {\n            \"streams\": [\n                {\n                    \"bits_per_second\": 870310298.8195692, \n                    \"bytes\": 108789760, \n                    \"end\": 35.000082, \n                    \"omitted\": false, \n                    \"pmtu\": 1500, \n                    \"retransmits\": 0, \n                    \"rtt\": 77087, \n                    \"rttvar\": 9, \n                    \"seconds\": 1.0000089406967163, \n                    \"sender\": true, \n                    \"snd_cwnd\": 16698336, \n                    \"snd_wnd\": -1, \n                    \"socket\": 5, \n                    \"start\": 34.000073\n                }\n            ], \n            \"sum\": {\n                \"bits_per_second\": 870310298.8195692, \n                \"bytes\": 108789760, \n                \"end\": 35.000082, \n                \"omitted\": false, \n                \"retransmits\": 0, \n                \"seconds\": 1.0000089406967163, \n                \"sender\": true, \n                \"start\": 34.000073\n            }\n        }, \n        {\n            \"streams\": [\n                {\n                    \"bits_per_second\": 859846055.219407, \n                    \"bytes\": 107479040, \n                    \"end\": 36.000066, \n                    \"omitted\": false, \n                    \"pmtu\": 1500, \n                    \"retransmits\": 0, \n                    \"rtt\": 77085, \n                    \"rttvar\": 11, \n                    \"seconds\": 0.9999840259552002, \n                    \"sender\": true, \n                    \"snd_cwnd\": 16698336, \n                    \"snd_wnd\": -1, \n                    \"socket\": 5, \n                    \"start\": 35.000082\n                }\n            ], \n            \"sum\": {\n                \"bits_per_second\": 859846055.219407, \n                \"bytes\": 107479040, \n                \"end\": 36.000066, \n                \"omitted\": false, \n                \"retransmits\": 0, \n                \"seconds\": 0.9999840259552002, \n                \"sender\": true, \n                \"start\": 35.000082\n            }\n        }, \n        {\n            \"streams\": [\n                {\n                    \"bits_per_second\": 870305941.4193027, \n                    \"bytes\": 108789760, \n                    \"end\": 37.00008, \n                    \"omitted\": false, \n                    \"pmtu\": 1500, \n                    \"retransmits\": 0, \n                    \"rtt\": 77084, \n                    \"rttvar\": 11, \n                    \"seconds\": 1.0000139474868774, \n                    \"sender\": true, \n                    \"snd_cwnd\": 16698336, \n                    \"snd_wnd\": -1, \n                    \"socket\": 5, \n                    \"start\": 36.000066\n                }\n            ], \n            \"sum\": {\n                \"bits_per_second\": 870305941.4193027, \n                \"bytes\": 108789760, \n                \"end\": 37.00008, \n                \"omitted\": false, \n                \"retransmits\": 0, \n                \"seconds\": 1.0000139474868774, \n                \"sender\": true, \n                \"start\": 36.000066\n            }\n        }, \n        {\n            \"streams\": [\n                {\n                    \"bits_per_second\": 859846926.4981253, \n                    \"bytes\": 107479040, \n                    \"end\": 38.000063, \n                    \"omitted\": false, \n                    \"pmtu\": 1500, \n                    \"retransmits\": 0, \n                    \"rtt\": 77084, \n                    \"rttvar\": 11, \n                    \"seconds\": 0.999983012676239, \n                    \"sender\": true, \n                    \"snd_cwnd\": 16698336, \n                    \"snd_wnd\": -1, \n                    \"socket\": 5, \n                    \"start\": 37.00008\n                }\n            ], \n            \"sum\": {\n                \"bits_per_second\": 859846926.4981253, \n                \"bytes\": 107479040, \n                \"end\": 38.000063, \n                \"omitted\": false, \n                \"retransmits\": 0, \n                \"seconds\": 0.999983012676239, \n                \"sender\": true, \n                \"start\": 37.00008\n            }\n        }, \n        {\n            \"streams\": [\n                {\n                    \"bits_per_second\": 870318080, \n                    \"bytes\": 108789760, \n                    \"end\": 39.000063, \n                    \"omitted\": false, \n                    \"pmtu\": 1500, \n                    \"retransmits\": 0, \n                    \"rtt\": 77078, \n                    \"rttvar\": 8, \n                    \"seconds\": 1, \n                    \"sender\": true, \n                    \"snd_cwnd\": 16698336, \n                    \"snd_wnd\": -1, \n                    \"socket\": 5, \n                    \"start\": 38.000063\n                }\n            ], \n            \"sum\": {\n                \"bits_per_second\": 870318080, \n                \"bytes\": 108789760, \n                \"end\": 39.000063, \n                \"omitted\": false, \n                \"retransmits\": 0, \n                \"seconds\": 1, \n                \"sender\": true, \n                \"start\": 38.000063\n            }\n        }, \n        {\n            \"streams\": [\n                {\n                    \"bits_per_second\": 870318961.8758936, \n                    \"bytes\": 108789760, \n                    \"end\": 40.000062, \n                    \"omitted\": false, \n                    \"pmtu\": 1500, \n                    \"retransmits\": 0, \n                    \"rtt\": 77083, \n                    \"rttvar\": 5, \n                    \"seconds\": 0.9999989867210388, \n                    \"sender\": true, \n                    \"snd_cwnd\": 16698336, \n                    \"snd_wnd\": -1, \n                    \"socket\": 5, \n                    \"start\": 39.000063\n                }\n            ], \n            \"sum\": {\n                \"bits_per_second\": 870318961.8758936, \n                \"bytes\": 108789760, \n                \"end\": 40.000062, \n                \"omitted\": false, \n                \"retransmits\": 0, \n                \"seconds\": 0.9999989867210388, \n                \"sender\": true, \n                \"start\": 39.000063\n            }\n        }, \n        {\n            \"streams\": [\n                {\n                    \"bits_per_second\": 859832320, \n                    \"bytes\": 107479040, \n                    \"end\": 41.000062, \n                    \"omitted\": false, \n                    \"pmtu\": 1500, \n                    \"retransmits\": 0, \n                    \"rtt\": 77084, \n                    \"rttvar\": 7, \n                    \"seconds\": 1, \n                    \"sender\": true, \n                    \"snd_cwnd\": 16698336, \n                    \"snd_wnd\": -1, \n                    \"socket\": 5, \n                    \"start\": 40.000062\n                }\n            ], \n            \"sum\": {\n                \"bits_per_second\": 859832320, \n                \"bytes\": 107479040, \n                \"end\": 41.000062, \n                \"omitted\": false, \n                \"retransmits\": 0, \n                \"seconds\": 1, \n                \"sender\": true, \n                \"start\": 40.000062\n            }\n        }, \n        {\n            \"streams\": [\n                {\n                    \"bits_per_second\": 870191004.8069657, \n                    \"bytes\": 108789760, \n                    \"end\": 42.000208, \n                    \"omitted\": false, \n                    \"pmtu\": 1500, \n                    \"retransmits\": 0, \n                    \"rtt\": 77087, \n                    \"rttvar\": 11, \n                    \"seconds\": 1.0001460313797, \n                    \"sender\": true, \n                    \"snd_cwnd\": 16698336, \n                    \"snd_wnd\": -1, \n                    \"socket\": 5, \n                    \"start\": 41.000062\n                }\n            ], \n            \"sum\": {\n                \"bits_per_second\": 870191004.8069657, \n                \"bytes\": 108789760, \n                \"end\": 42.000208, \n                \"omitted\": false, \n                \"retransmits\": 0, \n                \"seconds\": 1.0001460313797, \n                \"sender\": true, \n                \"start\": 41.000062\n            }\n        }, \n        {\n            \"streams\": [\n                {\n                    \"bits_per_second\": 859939804.6846118, \n                    \"bytes\": 107479040, \n                    \"end\": 43.000083, \n                    \"omitted\": false, \n                    \"pmtu\": 1500, \n                    \"retransmits\": 0, \n                    \"rtt\": 77086, \n                    \"rttvar\": 9, \n                    \"seconds\": 0.999875009059906, \n                    \"sender\": true, \n                    \"snd_cwnd\": 16698336, \n                    \"snd_wnd\": -1, \n                    \"socket\": 5, \n                    \"start\": 42.000208\n                }\n            ], \n            \"sum\": {\n                \"bits_per_second\": 859939804.6846118, \n                \"bytes\": 107479040, \n                \"end\": 43.000083, \n                \"omitted\": false, \n                \"retransmits\": 0, \n                \"seconds\": 0.999875009059906, \n                \"sender\": true, \n                \"start\": 42.000208\n            }\n        }, \n        {\n            \"streams\": [\n                {\n                    \"bits_per_second\": 870256249.3929865, \n                    \"bytes\": 108789760, \n                    \"end\": 44.000154, \n                    \"omitted\": false, \n                    \"pmtu\": 1500, \n                    \"retransmits\": 0, \n                    \"rtt\": 77093, \n                    \"rttvar\": 9, \n                    \"seconds\": 1.0000710487365723, \n                    \"sender\": true, \n                    \"snd_cwnd\": 16698336, \n                    \"snd_wnd\": -1, \n                    \"socket\": 5, \n                    \"start\": 43.000083\n                }\n            ], \n            \"sum\": {\n                \"bits_per_second\": 870256249.3929865, \n                \"bytes\": 108789760, \n                \"end\": 44.000154, \n                \"omitted\": false, \n                \"retransmits\": 0, \n                \"seconds\": 1.0000710487365723, \n                \"sender\": true, \n                \"start\": 43.000083\n            }\n        }, \n        {\n            \"streams\": [\n                {\n                    \"bits_per_second\": 859825452.5548505, \n                    \"bytes\": 107479040, \n                    \"end\": 45.000162, \n                    \"omitted\": false, \n                    \"pmtu\": 1500, \n                    \"retransmits\": 0, \n                    \"rtt\": 77085, \n                    \"rttvar\": 4, \n                    \"seconds\": 1.0000079870224, \n                    \"sender\": true, \n                    \"snd_cwnd\": 16698336, \n                    \"snd_wnd\": -1, \n                    \"socket\": 5, \n                    \"start\": 44.000154\n                }\n            ], \n            \"sum\": {\n                \"bits_per_second\": 859825452.5548505, \n                \"bytes\": 107479040, \n                \"end\": 45.000162, \n                \"omitted\": false, \n                \"retransmits\": 0, \n                \"seconds\": 1.0000079870224, \n                \"sender\": true, \n                \"start\": 44.000154\n            }\n        }, \n        {\n            \"streams\": [\n                {\n                    \"bits_per_second\": 870375509.4143273, \n                    \"bytes\": 108789760, \n                    \"end\": 46.000096, \n                    \"omitted\": false, \n                    \"pmtu\": 1500, \n                    \"retransmits\": 0, \n                    \"rtt\": 77088, \n                    \"rttvar\": 8, \n                    \"seconds\": 0.9999340176582336, \n                    \"sender\": true, \n                    \"snd_cwnd\": 16698336, \n                    \"snd_wnd\": -1, \n                    \"socket\": 5, \n                    \"start\": 45.000162\n                }\n            ], \n            \"sum\": {\n                \"bits_per_second\": 870375509.4143273, \n                \"bytes\": 108789760, \n                \"end\": 46.000096, \n                \"omitted\": false, \n                \"retransmits\": 0, \n                \"seconds\": 0.9999340176582336, \n                \"sender\": true, \n                \"start\": 45.000162\n            }\n        }, \n        {\n            \"streams\": [\n                {\n                    \"bits_per_second\": 859768672.21178, \n                    \"bytes\": 107479040, \n                    \"end\": 47.00017, \n                    \"omitted\": false, \n                    \"pmtu\": 1500, \n                    \"retransmits\": 0, \n                    \"rtt\": 77091, \n                    \"rttvar\": 9, \n                    \"seconds\": 1.000074028968811, \n                    \"sender\": true, \n                    \"snd_cwnd\": 16698336, \n                    \"snd_wnd\": -1, \n                    \"socket\": 5, \n                    \"start\": 46.000096\n                }\n            ], \n            \"sum\": {\n                \"bits_per_second\": 859768672.21178, \n                \"bytes\": 107479040, \n                \"end\": 47.00017, \n                \"omitted\": false, \n                \"retransmits\": 0, \n                \"seconds\": 1.000074028968811, \n                \"sender\": true, \n                \"start\": 46.000096\n            }\n        }, \n        {\n            \"streams\": [\n                {\n                    \"bits_per_second\": 870330270.7957577, \n                    \"bytes\": 108789760, \n                    \"end\": 48.000156, \n                    \"omitted\": false, \n                    \"pmtu\": 1500, \n                    \"retransmits\": 0, \n                    \"rtt\": 77084, \n                    \"rttvar\": 6, \n                    \"seconds\": 0.9999859929084778, \n                    \"sender\": true, \n                    \"snd_cwnd\": 16698336, \n                    \"snd_wnd\": -1, \n                    \"socket\": 5, \n                    \"start\": 47.00017\n                }\n            ], \n            \"sum\": {\n                \"bits_per_second\": 870330270.7957577, \n                \"bytes\": 108789760, \n                \"end\": 48.000156, \n                \"omitted\": false, \n                \"retransmits\": 0, \n                \"seconds\": 0.9999859929084778, \n                \"sender\": true, \n                \"start\": 47.00017\n            }\n        }, \n        {\n            \"streams\": [\n                {\n                    \"bits_per_second\": 859895105.834351, \n                    \"bytes\": 107479040, \n                    \"end\": 49.000083, \n                    \"omitted\": false, \n                    \"pmtu\": 1500, \n                    \"retransmits\": 0, \n                    \"rtt\": 77084, \n                    \"rttvar\": 8, \n                    \"seconds\": 0.99992698431015, \n                    \"sender\": true, \n                    \"snd_cwnd\": 16698336, \n                    \"snd_wnd\": -1, \n                    \"socket\": 5, \n                    \"start\": 48.000156\n                }\n            ], \n            \"sum\": {\n                \"bits_per_second\": 859895105.834351, \n                \"bytes\": 107479040, \n                \"end\": 49.000083, \n                \"omitted\": false, \n                \"retransmits\": 0, \n                \"seconds\": 0.99992698431015, \n                \"sender\": true, \n                \"start\": 48.000156\n            }\n        }, \n        {\n            \"streams\": [\n                {\n                    \"bits_per_second\": 870347649.754622, \n                    \"bytes\": 108789760, \n                    \"end\": 50.000049, \n                    \"omitted\": false, \n                    \"pmtu\": 1500, \n                    \"retransmits\": 0, \n                    \"rtt\": 77089, \n                    \"rttvar\": 7, \n                    \"seconds\": 0.999966025352478, \n                    \"sender\": true, \n                    \"snd_cwnd\": 16698336, \n                    \"snd_wnd\": -1, \n                    \"socket\": 5, \n                    \"start\": 49.000083\n                }\n            ], \n            \"sum\": {\n                \"bits_per_second\": 870347649.754622, \n                \"bytes\": 108789760, \n                \"end\": 50.000049, \n                \"omitted\": false, \n                \"retransmits\": 0, \n                \"seconds\": 0.999966025352478, \n                \"sender\": true, \n                \"start\": 49.000083\n            }\n        }, \n        {\n            \"streams\": [\n                {\n                    \"bits_per_second\": 870356365.4341084, \n                    \"bytes\": 108789760, \n                    \"end\": 51.000005, \n                    \"omitted\": false, \n                    \"pmtu\": 1500, \n                    \"retransmits\": 0, \n                    \"rtt\": 77087, \n                    \"rttvar\": 7, \n                    \"seconds\": 0.9999560117721558, \n                    \"sender\": true, \n                    \"snd_cwnd\": 16698336, \n                    \"snd_wnd\": -1, \n                    \"socket\": 5, \n                    \"start\": 50.000049\n                }\n            ], \n            \"sum\": {\n                \"bits_per_second\": 870356365.4341084, \n                \"bytes\": 108789760, \n                \"end\": 51.000005, \n                \"omitted\": false, \n                \"retransmits\": 0, \n                \"seconds\": 0.9999560117721558, \n                \"sender\": true, \n                \"start\": 50.000049\n            }\n        }, \n        {\n            \"streams\": [\n                {\n                    \"bits_per_second\": 859787632.322653, \n                    \"bytes\": 107479040, \n                    \"end\": 52.000057, \n                    \"omitted\": false, \n                    \"pmtu\": 1500, \n                    \"retransmits\": 0, \n                    \"rtt\": 77085, \n                    \"rttvar\": 9, \n                    \"seconds\": 1.0000519752502441, \n                    \"sender\": true, \n                    \"snd_cwnd\": 16698336, \n                    \"snd_wnd\": -1, \n                    \"socket\": 5, \n                    \"start\": 51.000005\n                }\n            ], \n            \"sum\": {\n                \"bits_per_second\": 859787632.322653, \n                \"bytes\": 107479040, \n                \"end\": 52.000057, \n                \"omitted\": false, \n                \"retransmits\": 0, \n                \"seconds\": 1.0000519752502441, \n                \"sender\": true, \n                \"start\": 51.000005\n            }\n        }, \n        {\n            \"streams\": [\n                {\n                    \"bits_per_second\": 870312892.5309197, \n                    \"bytes\": 108789760, \n                    \"end\": 53.000063, \n                    \"omitted\": false, \n                    \"pmtu\": 1500, \n                    \"retransmits\": 0, \n                    \"rtt\": 77087, \n                    \"rttvar\": 12, \n                    \"seconds\": 1.0000059604644775, \n                    \"sender\": true, \n                    \"snd_cwnd\": 16698336, \n                    \"snd_wnd\": -1, \n                    \"socket\": 5, \n                    \"start\": 52.000057\n                }\n            ], \n            \"sum\": {\n                \"bits_per_second\": 870312892.5309197, \n                \"bytes\": 108789760, \n                \"end\": 53.000063, \n                \"omitted\": false, \n                \"retransmits\": 0, \n                \"seconds\": 1.0000059604644775, \n                \"sender\": true, \n                \"start\": 52.000057\n            }\n        }, \n        {\n            \"streams\": [\n                {\n                    \"bits_per_second\": 859817662.749861, \n                    \"bytes\": 107479040, \n                    \"end\": 54.00008, \n                    \"omitted\": false, \n                    \"pmtu\": 1500, \n                    \"retransmits\": 0, \n                    \"rtt\": 77089, \n                    \"rttvar\": 8, \n                    \"seconds\": 1.0000170469284058, \n                    \"sender\": true, \n                    \"snd_cwnd\": 16698336, \n                    \"snd_wnd\": -1, \n                    \"socket\": 5, \n                    \"start\": 53.000063\n                }\n            ], \n            \"sum\": {\n                \"bits_per_second\": 859817662.749861, \n                \"bytes\": 107479040, \n                \"end\": 54.00008, \n                \"omitted\": false, \n                \"retransmits\": 0, \n                \"seconds\": 1.0000170469284058, \n                \"sender\": true, \n                \"start\": 53.000063\n            }\n        }, \n        {\n            \"streams\": [\n                {\n                    \"bits_per_second\": 870333746.532007, \n                    \"bytes\": 108789760, \n                    \"end\": 55.000062, \n                    \"omitted\": false, \n                    \"pmtu\": 1500, \n                    \"retransmits\": 0, \n                    \"rtt\": 77088, \n                    \"rttvar\": 6, \n                    \"seconds\": 0.9999819993972778, \n                    \"sender\": true, \n                    \"snd_cwnd\": 16698336, \n                    \"snd_wnd\": -1, \n                    \"socket\": 5, \n                    \"start\": 54.00008\n                }\n            ], \n            \"sum\": {\n                \"bits_per_second\": 870333746.532007, \n                \"bytes\": 108789760, \n                \"end\": 55.000062, \n                \"omitted\": false, \n                \"retransmits\": 0, \n                \"seconds\": 0.9999819993972778, \n                \"sender\": true, \n                \"start\": 54.00008\n            }\n        }, \n        {\n            \"streams\": [\n                {\n                    \"bits_per_second\": 859816022.8089014, \n                    \"bytes\": 107479040, \n                    \"end\": 56.000081, \n                    \"omitted\": false, \n                    \"pmtu\": 1500, \n                    \"retransmits\": 0, \n                    \"rtt\": 77084, \n                    \"rttvar\": 6, \n                    \"seconds\": 1.0000189542770386, \n                    \"sender\": true, \n                    \"snd_cwnd\": 16698336, \n                    \"snd_wnd\": -1, \n                    \"socket\": 5, \n                    \"start\": 55.000062\n                }\n            ], \n            \"sum\": {\n                \"bits_per_second\": 859816022.8089014, \n                \"bytes\": 107479040, \n                \"end\": 56.000081, \n                \"omitted\": false, \n                \"retransmits\": 0, \n                \"seconds\": 1.0000189542770386, \n                \"sender\": true, \n                \"start\": 55.000062\n            }\n        }, \n        {\n            \"streams\": [\n                {\n                    \"bits_per_second\": 870359011.29992, \n                    \"bytes\": 108789760, \n                    \"end\": 57.000034, \n                    \"omitted\": false, \n                    \"pmtu\": 1500, \n                    \"retransmits\": 0, \n                    \"rtt\": 77088, \n                    \"rttvar\": 5, \n                    \"seconds\": 0.9999529719352722, \n                    \"sender\": true, \n                    \"snd_cwnd\": 16698336, \n                    \"snd_wnd\": -1, \n                    \"socket\": 5, \n                    \"start\": 56.000081\n                }\n            ], \n            \"sum\": {\n                \"bits_per_second\": 870359011.29992, \n                \"bytes\": 108789760, \n                \"end\": 57.000034, \n                \"omitted\": false, \n                \"retransmits\": 0, \n                \"seconds\": 0.9999529719352722, \n                \"sender\": true, \n                \"start\": 56.000081\n            }\n        }, \n        {\n            \"streams\": [\n                {\n                    \"bits_per_second\": 859785890.0073036, \n                    \"bytes\": 107479040, \n                    \"end\": 58.000088, \n                    \"omitted\": false, \n                    \"pmtu\": 1500, \n                    \"retransmits\": 0, \n                    \"rtt\": 77089, \n                    \"rttvar\": 12, \n                    \"seconds\": 1.0000540018081665, \n                    \"sender\": true, \n                    \"snd_cwnd\": 16698336, \n                    \"snd_wnd\": -1, \n                    \"socket\": 5, \n                    \"start\": 57.000034\n                }\n            ], \n            \"sum\": {\n                \"bits_per_second\": 859785890.0073036, \n                \"bytes\": 107479040, \n                \"end\": 58.000088, \n                \"omitted\": false, \n                \"retransmits\": 0, \n                \"seconds\": 1.0000540018081665, \n                \"sender\": true, \n                \"start\": 57.000034\n            }\n        }, \n        {\n            \"streams\": [\n                {\n                    \"bits_per_second\": 870345937.766663, \n                    \"bytes\": 108789760, \n                    \"end\": 59.000056, \n                    \"omitted\": false, \n                    \"pmtu\": 1500, \n                    \"retransmits\": 0, \n                    \"rtt\": 77089, \n                    \"rttvar\": 13, \n                    \"seconds\": 0.9999679923057556, \n                    \"sender\": true, \n                    \"snd_cwnd\": 16698336, \n                    \"snd_wnd\": -1, \n                    \"socket\": 5, \n                    \"start\": 58.000088\n                }\n            ], \n            \"sum\": {\n                \"bits_per_second\": 870345937.766663, \n                \"bytes\": 108789760, \n                \"end\": 59.000056, \n                \"omitted\": false, \n                \"retransmits\": 0, \n                \"seconds\": 0.9999679923057556, \n                \"sender\": true, \n                \"start\": 58.000088\n            }\n        }, \n        {\n            \"streams\": [\n                {\n                    \"bits_per_second\": 859817662.749861, \n                    \"bytes\": 107479040, \n                    \"end\": 60.000073, \n                    \"omitted\": false, \n                    \"pmtu\": 1500, \n                    \"retransmits\": 0, \n                    \"rtt\": 77086, \n                    \"rttvar\": 8, \n                    \"seconds\": 1.0000170469284058, \n                    \"sender\": true, \n                    \"snd_cwnd\": 16698336, \n                    \"snd_wnd\": -1, \n                    \"socket\": 5, \n                    \"start\": 59.000056\n                }\n            ], \n            \"sum\": {\n                \"bits_per_second\": 859817662.749861, \n                \"bytes\": 107479040, \n                \"end\": 60.000073, \n                \"omitted\": false, \n                \"retransmits\": 0, \n                \"seconds\": 1.0000170469284058, \n                \"sender\": true, \n                \"start\": 59.000056\n            }\n        }\n    ], \n    \"start\": {\n        \"connected\": [\n            {\n                \"local_host\": \"10.0.0.1\", \n                \"local_port\": 37311, \n                \"remote_host\": \"10.0.0.2\", \n                \"remote_port\": 5201, \n                \"socket\": 5\n            }\n        ], \n        \"connecting_to\": {\n            \"host\": \"10.0.0.2\", \n            \"port\": 5201\n        }, \n        \"cookie\": \"5jw7cglkzetned3jeeagnbygaprjsbpflmyr\", \n        \"fq_rate\": 0, \n        \"rcvbuf_actual\": 87380, \n        \"sndbuf_actual\": 87380, \n        \"sock_bufsize\": 0, \n        \"system_info\": \"REDACTED\", \n        \"target_bitrate\": 0, \n        \"tcp_mss_default\": 1448, \n        \"test_start\": {\n            \"bidir\": 0, \n            \"blksize\": 131072, \n            \"blocks\": 0, \n            \"bytes\": 0, \n            \"duration\": 60, \n            \"fqrate\": 0, \n            \"num_streams\": 1, \n            \"omit\": 0, \n            \"protocol\": \"TCP\", \n            \"reverse\": 0, \n            \"target_bitrate\": 0, \n            \"tos\": 0\n        }, \n        \"timestamp\": {\n            \"time\": \"Wed, 17 Apr 2024 01:28:34 GMT\", \n            \"timesecs\": 1713317314\n        }, \n        \"version\": \"iperf 3.14\"\n    }\n}\nParticipant 1:\n/usr/bin/iperf3 -s -1 --idle-timeout 60 --json -p 5201 -B 10.0.0.2 --authorized-users-path /var/run/pscheduler-server/runner/tmp/tmp8luim8_t/tmp19qtl_nu/credentials --rsa-private-key-path /var/run/pscheduler-server/runner/tmp/tmp8luim8_t/tmp19qtl_nu/private-key\n\n{\n    \"end\": {\n        \"cpu_utilization_percent\": {\n            \"host_system\": 5.37580819647114, \n            \"host_total\": 5.93489425965781, \n            \"host_user\": 0.5590893922490373, \n            \"remote_system\": 0, \n            \"remote_total\": 0, \n            \"remote_user\": 0\n        }, \n        \"receiver_tcp_congestion\": \"htcp\", \n        \"streams\": [\n            {\n                \"receiver\": {\n                    \"bits_per_second\": 865535438.84679, \n                    \"bytes\": 6499843216, \n                    \"end\": 60.076969, \n                    \"seconds\": 60.076969, \n                    \"sender\": false, \n                    \"socket\": 5, \n                    \"start\": 0\n                }, \n                \"sender\": {\n                    \"bits_per_second\": 0, \n                    \"bytes\": 0, \n                    \"end\": 60.076969, \n                    \"seconds\": 60.076969, \n                    \"sender\": false, \n                    \"socket\": 5, \n                    \"start\": 0\n                }\n            }\n        ], \n        \"sum_received\": {\n            \"bits_per_second\": 865535438.84679, \n            \"bytes\": 6499843216, \n            \"end\": 60.076969, \n            \"seconds\": 60.076969, \n            \"sender\": false, \n            \"start\": 0\n        }, \n        \"sum_sent\": {\n            \"bits_per_second\": 0, \n            \"bytes\": 0, \n            \"end\": 60.076969, \n            \"seconds\": 60.076969, \n            \"sender\": false, \n            \"start\": 0\n        }\n    }, \n    \"intervals\": [\n        {\n            \"streams\": [\n                {\n                    \"bits_per_second\": 865275248.062451, \n                    \"bytes\": 108168496, \n                    \"end\": 1.000084, \n                    \"omitted\": false, \n                    \"seconds\": 1.0000840425491333, \n                    \"sender\": false, \n                    \"socket\": 5, \n                    \"start\": 0\n                }\n            ], \n            \"sum\": {\n                \"bits_per_second\": 865275248.062451, \n                \"bytes\": 108168496, \n                \"end\": 1.000084, \n                \"omitted\": false, \n                \"seconds\": 1.0000840425491333, \n                \"sender\": false, \n                \"start\": 0\n            }\n        }, \n        {\n            \"streams\": [\n                {\n                    \"bits_per_second\": 865342955.6177365, \n                    \"bytes\": 108165600, \n                    \"end\": 2.000063, \n                    \"omitted\": false, \n                    \"seconds\": 0.999979019165039, \n                    \"sender\": false, \n                    \"socket\": 5, \n                    \"start\": 1.000084\n                }\n            ], \n            \"sum\": {\n                \"bits_per_second\": 865342955.6177365, \n                \"bytes\": 108165600, \n                \"end\": 2.000063, \n                \"omitted\": false, \n                \"seconds\": 0.999979019165039, \n                \"sender\": false, \n                \"start\": 1.000084\n            }\n        }, \n        {\n            \"streams\": [\n                {\n                    \"bits_per_second\": 865309223.9124285, \n                    \"bytes\": 108165600, \n                    \"end\": 3.000081, \n                    \"omitted\": false, \n                    \"seconds\": 1.0000180006027222, \n                    \"sender\": false, \n                    \"socket\": 5, \n                    \"start\": 2.000063\n                }\n            ], \n            \"sum\": {\n                \"bits_per_second\": 865309223.9124285, \n                \"bytes\": 108165600, \n                \"end\": 3.000081, \n                \"omitted\": false, \n                \"seconds\": 1.0000180006027222, \n                \"sender\": false, \n                \"start\": 2.000063\n            }\n        }, \n        {\n            \"streams\": [\n                {\n                    \"bits_per_second\": 865863420.7858243, \n                    \"bytes\": 108230760, \n                    \"end\": 4.000061, \n                    \"omitted\": false, \n                    \"seconds\": 0.9999799728393555, \n                    \"sender\": false, \n                    \"socket\": 5, \n                    \"start\": 3.000081\n                }\n            ], \n            \"sum\": {\n                \"bits_per_second\": 865863420.7858243, \n                \"bytes\": 108230760, \n                \"end\": 4.000061, \n                \"omitted\": false, \n                \"seconds\": 0.9999799728393555, \n                \"sender\": false, \n                \"start\": 3.000081\n            }\n        }, \n        {\n            \"streams\": [\n                {\n                    \"bits_per_second\": 865310977.48368, \n                    \"bytes\": 108165600, \n                    \"end\": 5.000077, \n                    \"omitted\": false, \n                    \"seconds\": 1.0000159740448, \n                    \"sender\": false, \n                    \"socket\": 5, \n                    \"start\": 4.000061\n                }\n            ], \n            \"sum\": {\n                \"bits_per_second\": 865310977.48368, \n                \"bytes\": 108165600, \n                \"end\": 5.000077, \n                \"omitted\": false, \n                \"seconds\": 1.0000159740448, \n                \"sender\": false, \n                \"start\": 4.000061\n            }\n        }, \n        {\n            \"streams\": [\n                {\n                    \"bits_per_second\": 865859085.524251, \n                    \"bytes\": 108230760, \n                    \"end\": 6.000062, \n                    \"omitted\": false, \n                    \"seconds\": 0.9999849796295166, \n                    \"sender\": false, \n                    \"socket\": 5, \n                    \"start\": 5.000077\n                }\n            ], \n            \"sum\": {\n                \"bits_per_second\": 865859085.524251, \n                \"bytes\": 108230760, \n                \"end\": 6.000062, \n                \"omitted\": false, \n                \"seconds\": 0.9999849796295166, \n                \"sender\": false, \n                \"start\": 5.000077\n            }\n        }, \n        {\n            \"streams\": [\n                {\n                    \"bits_per_second\": 865309223.9124285, \n                    \"bytes\": 108165600, \n                    \"end\": 7.00008, \n                    \"omitted\": false, \n                    \"seconds\": 1.0000180006027222, \n                    \"sender\": false, \n                    \"socket\": 5, \n                    \"start\": 6.000062\n                }\n            ], \n            \"sum\": {\n                \"bits_per_second\": 865309223.9124285, \n                \"bytes\": 108165600, \n                \"end\": 7.00008, \n                \"omitted\": false, \n                \"seconds\": 1.0000180006027222, \n                \"sender\": false, \n                \"start\": 6.000062\n            }\n        }, \n        {\n            \"streams\": [\n                {\n                    \"bits_per_second\": 865855627.668166, \n                    \"bytes\": 108230760, \n                    \"end\": 8.000069, \n                    \"omitted\": false, \n                    \"seconds\": 0.9999889731407166, \n                    \"sender\": false, \n                    \"socket\": 5, \n                    \"start\": 7.00008\n                }\n            ], \n            \"sum\": {\n                \"bits_per_second\": 865855627.668166, \n                \"bytes\": 108230760, \n                \"end\": 8.000069, \n                \"omitted\": false, \n                \"seconds\": 0.9999889731407166, \n                \"sender\": false, \n                \"start\": 7.00008\n            }\n        }, \n        {\n            \"streams\": [\n                {\n                    \"bits_per_second\": 865331711.4237624, \n                    \"bytes\": 108165600, \n                    \"end\": 9.000061, \n                    \"omitted\": false, \n                    \"seconds\": 0.9999920129776, \n                    \"sender\": false, \n                    \"socket\": 5, \n                    \"start\": 8.000069\n                }\n            ], \n            \"sum\": {\n                \"bits_per_second\": 865331711.4237624, \n                \"bytes\": 108165600, \n                \"end\": 9.000061, \n                \"omitted\": false, \n                \"seconds\": 0.9999920129776, \n                \"sender\": false, \n                \"start\": 8.000069\n            }\n        }, \n        {\n            \"streams\": [\n                {\n                    \"bits_per_second\": 865307470.3482844, \n                    \"bytes\": 108165600, \n                    \"end\": 10.000081, \n                    \"omitted\": false, \n                    \"seconds\": 1.0000200271606445, \n                    \"sender\": false, \n                    \"socket\": 5, \n                    \"start\": 9.000061\n                }\n            ], \n            \"sum\": {\n                \"bits_per_second\": 865307470.3482844, \n                \"bytes\": 108165600, \n                \"end\": 10.000081, \n                \"omitted\": false, \n                \"seconds\": 1.0000200271606445, \n                \"sender\": false, \n                \"start\": 9.000061\n            }\n        }, \n        {\n            \"streams\": [\n                {\n                    \"bits_per_second\": 865862543.4079545, \n                    \"bytes\": 108230760, \n                    \"end\": 11.000062, \n                    \"omitted\": false, \n                    \"seconds\": 0.9999809861183167, \n                    \"sender\": false, \n                    \"socket\": 5, \n                    \"start\": 10.000081\n                }\n            ], \n            \"sum\": {\n                \"bits_per_second\": 865862543.4079545, \n                \"bytes\": 108230760, \n                \"end\": 11.000062, \n                \"omitted\": false, \n                \"seconds\": 0.9999809861183167, \n                \"sender\": false, \n                \"start\": 10.000081\n            }\n        }, \n        {\n            \"streams\": [\n                {\n                    \"bits_per_second\": 865298805.7827166, \n                    \"bytes\": 108165600, \n                    \"end\": 12.000092, \n                    \"omitted\": false, \n                    \"seconds\": 1.0000300407409668, \n                    \"sender\": false, \n                    \"socket\": 5, \n                    \"start\": 11.000062\n                }\n            ], \n            \"sum\": {\n                \"bits_per_second\": 865298805.7827166, \n                \"bytes\": 108165600, \n                \"end\": 12.000092, \n                \"omitted\": false, \n                \"seconds\": 1.0000300407409668, \n                \"sender\": false, \n                \"start\": 11.000062\n            }\n        }, \n        {\n            \"streams\": [\n                {\n                    \"bits_per_second\": 865896297.9323368, \n                    \"bytes\": 108230760, \n                    \"end\": 13.000034, \n                    \"omitted\": false, \n                    \"seconds\": 0.9999420046806335, \n                    \"sender\": false, \n                    \"socket\": 5, \n                    \"start\": 12.000092\n                }\n            ], \n            \"sum\": {\n                \"bits_per_second\": 865896297.9323368, \n                \"bytes\": 108230760, \n                \"end\": 13.000034, \n                \"omitted\": false, \n                \"seconds\": 0.9999420046806335, \n                \"sender\": false, \n                \"start\": 12.000092\n            }\n        }, \n        {\n            \"streams\": [\n                {\n                    \"bits_per_second\": 865286737.5698372, \n                    \"bytes\": 108165600, \n                    \"end\": 14.000078, \n                    \"omitted\": false, \n                    \"seconds\": 1.0000439882278442, \n                    \"sender\": false, \n                    \"socket\": 5, \n                    \"start\": 13.000034\n                }\n            ], \n            \"sum\": {\n                \"bits_per_second\": 865286737.5698372, \n                \"bytes\": 108165600, \n                \"end\": 14.000078, \n                \"omitted\": false, \n                \"seconds\": 1.0000439882278442, \n                \"sender\": false, \n                \"start\": 13.000034\n            }\n        }, \n        {\n            \"streams\": [\n                {\n                    \"bits_per_second\": 865848660.4300917, \n                    \"bytes\": 108230760, \n                    \"end\": 15.000075, \n                    \"omitted\": false, \n                    \"seconds\": 0.9999970197677612, \n                    \"sender\": false, \n                    \"socket\": 5, \n                    \"start\": 14.000078\n                }\n            ], \n            \"sum\": {\n                \"bits_per_second\": 865848660.4300917, \n                \"bytes\": 108230760, \n                \"end\": 15.000075, \n                \"omitted\": false, \n                \"seconds\": 0.9999970197677612, \n                \"sender\": false, \n                \"start\": 14.000078\n            }\n        }, \n        {\n            \"streams\": [\n                {\n                    \"bits_per_second\": 865337797.6943146, \n                    \"bytes\": 108165600, \n                    \"end\": 16.00006, \n                    \"omitted\": false, \n                    \"seconds\": 0.9999849796295166, \n                    \"sender\": false, \n                    \"socket\": 5, \n                    \"start\": 15.000075\n                }\n            ], \n            \"sum\": {\n                \"bits_per_second\": 865337797.6943146, \n                \"bytes\": 108165600, \n                \"end\": 16.00006, \n                \"omitted\": false, \n                \"seconds\": 0.9999849796295166, \n                \"sender\": false, \n                \"start\": 15.000075\n            }\n        }, \n        {\n            \"streams\": [\n                {\n                    \"bits_per_second\": 865323046.372725, \n                    \"bytes\": 108165600, \n                    \"end\": 17.000062, \n                    \"omitted\": false, \n                    \"seconds\": 1.0000020265579224, \n                    \"sender\": false, \n                    \"socket\": 5, \n                    \"start\": 16.00006\n                }\n            ], \n            \"sum\": {\n                \"bits_per_second\": 865323046.372725, \n                \"bytes\": 108165600, \n                \"end\": 17.000062, \n                \"omitted\": false, \n                \"seconds\": 1.0000020265579224, \n                \"sender\": false, \n                \"start\": 16.00006\n            }\n        }, \n        {\n            \"streams\": [\n                {\n                    \"bits_per_second\": 865846080, \n                    \"bytes\": 108230760, \n                    \"end\": 18.000062, \n                    \"omitted\": false, \n                    \"seconds\": 1, \n                    \"sender\": false, \n                    \"socket\": 5, \n                    \"start\": 17.000062\n                }\n            ], \n            \"sum\": {\n                \"bits_per_second\": 865846080, \n                \"bytes\": 108230760, \n                \"end\": 18.000062, \n                \"omitted\": false, \n                \"seconds\": 1, \n                \"sender\": false, \n                \"start\": 17.000062\n            }\n        }, \n        {\n            \"streams\": [\n                {\n                    \"bits_per_second\": 865308398.704887, \n                    \"bytes\": 108165600, \n                    \"end\": 19.000081, \n                    \"omitted\": false, \n                    \"seconds\": 1.0000189542770386, \n                    \"sender\": false, \n                    \"socket\": 5, \n                    \"start\": 18.000062\n                }\n            ], \n            \"sum\": {\n                \"bits_per_second\": 865308398.704887, \n                \"bytes\": 108165600, \n                \"end\": 19.000081, \n                \"omitted\": false, \n                \"seconds\": 1.0000189542770386, \n                \"sender\": false, \n                \"start\": 18.000062\n            }\n        }, \n        {\n            \"streams\": [\n                {\n                    \"bits_per_second\": 865854750.3060896, \n                    \"bytes\": 108230760, \n                    \"end\": 20.000071, \n                    \"omitted\": false, \n                    \"seconds\": 0.9999899864196777, \n                    \"sender\": false, \n                    \"socket\": 5, \n                    \"start\": 19.000081\n                }\n            ], \n            \"sum\": {\n                \"bits_per_second\": 865854750.3060896, \n                \"bytes\": 108230760, \n                \"end\": 20.000071, \n                \"omitted\": false, \n                \"seconds\": 0.9999899864196777, \n                \"sender\": false, \n                \"start\": 19.000081\n            }\n        }, \n        {\n            \"streams\": [\n                {\n                    \"bits_per_second\": 865309223.9124285, \n                    \"bytes\": 108165600, \n                    \"end\": 21.000089, \n                    \"omitted\": false, \n                    \"seconds\": 1.0000180006027222, \n                    \"sender\": false, \n                    \"socket\": 5, \n                    \"start\": 20.000071\n                }\n            ], \n            \"sum\": {\n                \"bits_per_second\": 865309223.9124285, \n                \"bytes\": 108165600, \n                \"end\": 21.000089, \n                \"omitted\": false, \n                \"seconds\": 1.0000180006027222, \n                \"sender\": false, \n                \"start\": 20.000071\n            }\n        }, \n        {\n            \"streams\": [\n                {\n                    \"bits_per_second\": 865850415.1313396, \n                    \"bytes\": 108230760, \n                    \"end\": 22.000084, \n                    \"omitted\": false, \n                    \"seconds\": 0.999994993209839, \n                    \"sender\": false, \n                    \"socket\": 5, \n                    \"start\": 21.000089\n                }\n            ], \n            \"sum\": {\n                \"bits_per_second\": 865850415.1313396, \n                \"bytes\": 108230760, \n                \"end\": 22.000084, \n                \"omitted\": false, \n                \"seconds\": 0.999994993209839, \n                \"sender\": false, \n                \"start\": 21.000089\n            }\n        }, \n        {\n            \"streams\": [\n                {\n                    \"bits_per_second\": 865344709.325707, \n                    \"bytes\": 108165600, \n                    \"end\": 23.000061, \n                    \"omitted\": false, \n                    \"seconds\": 0.9999769926071167, \n                    \"sender\": false, \n                    \"socket\": 5, \n                    \"start\": 22.000084\n                }\n            ], \n            \"sum\": {\n                \"bits_per_second\": 865344709.325707, \n                \"bytes\": 108165600, \n                \"end\": 23.000061, \n                \"omitted\": false, \n                \"seconds\": 0.9999769926071167, \n                \"sender\": false, \n                \"start\": 22.000084\n            }\n        }, \n        {\n            \"streams\": [\n                {\n                    \"bits_per_second\": 865310977.48368, \n                    \"bytes\": 108165600, \n                    \"end\": 24.000077, \n                    \"omitted\": false, \n                    \"seconds\": 1.0000159740448, \n                    \"sender\": false, \n                    \"socket\": 5, \n                    \"start\": 23.000061\n                }\n            ], \n            \"sum\": {\n                \"bits_per_second\": 865310977.48368, \n                \"bytes\": 108165600, \n                \"end\": 24.000077, \n                \"omitted\": false, \n                \"seconds\": 1.0000159740448, \n                \"sender\": false, \n                \"start\": 23.000061\n            }\n        }, \n        {\n            \"streams\": [\n                {\n                    \"bits_per_second\": 865859911.2850132, \n                    \"bytes\": 108230760, \n                    \"end\": 25.000061, \n                    \"omitted\": false, \n                    \"seconds\": 0.9999840259552002, \n                    \"sender\": false, \n                    \"socket\": 5, \n                    \"start\": 24.000077\n                }\n            ], \n            \"sum\": {\n                \"bits_per_second\": 865859911.2850132, \n                \"bytes\": 108230760, \n                \"end\": 25.000061, \n                \"omitted\": false, \n                \"seconds\": 0.9999840259552002, \n                \"sender\": false, \n                \"start\": 24.000077\n            }\n        }, \n        {\n            \"streams\": [\n                {\n                    \"bits_per_second\": 865298805.7827166, \n                    \"bytes\": 108165600, \n                    \"end\": 26.000091, \n                    \"omitted\": false, \n                    \"seconds\": 1.0000300407409668, \n                    \"sender\": false, \n                    \"socket\": 5, \n                    \"start\": 25.000061\n                }\n            ], \n            \"sum\": {\n                \"bits_per_second\": 865298805.7827166, \n                \"bytes\": 108165600, \n                \"end\": 26.000091, \n                \"omitted\": false, \n                \"seconds\": 1.0000300407409668, \n                \"sender\": false, \n                \"start\": 25.000061\n            }\n        }, \n        {\n            \"streams\": [\n                {\n                    \"bits_per_second\": 865872039.8276635, \n                    \"bytes\": 108230760, \n                    \"end\": 27.000061, \n                    \"omitted\": false, \n                    \"seconds\": 0.999970018863678, \n                    \"sender\": false, \n                    \"socket\": 5, \n                    \"start\": 26.000091\n                }\n            ], \n            \"sum\": {\n                \"bits_per_second\": 865872039.8276635, \n                \"bytes\": 108230760, \n                \"end\": 27.000061, \n                \"omitted\": false, \n                \"seconds\": 0.999970018863678, \n                \"sender\": false, \n                \"start\": 26.000091\n            }\n        }, \n        {\n            \"streams\": [\n                {\n                    \"bits_per_second\": 865305716.7912476, \n                    \"bytes\": 108165600, \n                    \"end\": 28.000083, \n                    \"omitted\": false, \n                    \"seconds\": 1.000022053718567, \n                    \"sender\": false, \n                    \"socket\": 5, \n                    \"start\": 27.000061\n                }\n            ], \n            \"sum\": {\n                \"bits_per_second\": 865305716.7912476, \n                \"bytes\": 108165600, \n                \"end\": 28.000083, \n                \"omitted\": false, \n                \"seconds\": 1.000022053718567, \n                \"sender\": false, \n                \"start\": 27.000061\n            }\n        }, \n        {\n            \"streams\": [\n                {\n                    \"bits_per_second\": 865835655.219014, \n                    \"bytes\": 108230760, \n                    \"end\": 29.000095, \n                    \"omitted\": false, \n                    \"seconds\": 1.0000120401382446, \n                    \"sender\": false, \n                    \"socket\": 5, \n                    \"start\": 28.000083\n                }\n            ], \n            \"sum\": {\n                \"bits_per_second\": 865835655.219014, \n                \"bytes\": 108230760, \n                \"end\": 29.000095, \n                \"omitted\": false, \n                \"seconds\": 1.0000120401382446, \n                \"sender\": false, \n                \"start\": 28.000083\n            }\n        }, \n        {\n            \"streams\": [\n                {\n                    \"bits_per_second\": 865354200.1039302, \n                    \"bytes\": 108165600, \n                    \"end\": 30.000061, \n                    \"omitted\": false, \n                    \"seconds\": 0.999966025352478, \n                    \"sender\": false, \n                    \"socket\": 5, \n                    \"start\": 29.000095\n                }\n            ], \n            \"sum\": {\n                \"bits_per_second\": 865354200.1039302, \n                \"bytes\": 108165600, \n                \"end\": 30.000061, \n                \"omitted\": false, \n                \"seconds\": 0.999966025352478, \n                \"sender\": false, \n                \"start\": 29.000095\n            }\n        }, \n        {\n            \"streams\": [\n                {\n                    \"bits_per_second\": 865307470.3482844, \n                    \"bytes\": 108165600, \n                    \"end\": 31.000081, \n                    \"omitted\": false, \n                    \"seconds\": 1.0000200271606445, \n                    \"sender\": false, \n                    \"socket\": 5, \n                    \"start\": 30.000061\n                }\n            ], \n            \"sum\": {\n                \"bits_per_second\": 865307470.3482844, \n                \"bytes\": 108165600, \n                \"end\": 31.000081, \n                \"omitted\": false, \n                \"seconds\": 1.0000200271606445, \n                \"sender\": false, \n                \"start\": 30.000061\n            }\n        }, \n        {\n            \"streams\": [\n                {\n                    \"bits_per_second\": 865863420.7858243, \n                    \"bytes\": 108230760, \n                    \"end\": 32.000061, \n                    \"omitted\": false, \n                    \"seconds\": 0.9999799728393555, \n                    \"sender\": false, \n                    \"socket\": 5, \n                    \"start\": 31.000081\n                }\n            ], \n            \"sum\": {\n                \"bits_per_second\": 865863420.7858243, \n                \"bytes\": 108230760, \n                \"end\": 32.000061, \n                \"omitted\": false, \n                \"seconds\": 0.9999799728393555, \n                \"sender\": false, \n                \"start\": 31.000081\n            }\n        }, \n        {\n            \"streams\": [\n                {\n                    \"bits_per_second\": 865300559.311743, \n                    \"bytes\": 108165600, \n                    \"end\": 33.000089, \n                    \"omitted\": false, \n                    \"seconds\": 1.0000280141830444, \n                    \"sender\": false, \n                    \"socket\": 5, \n                    \"start\": 32.000061\n                }\n            ], \n            \"sum\": {\n                \"bits_per_second\": 865300559.311743, \n                \"bytes\": 108165600, \n                \"end\": 33.000089, \n                \"omitted\": false, \n                \"seconds\": 1.0000280141830444, \n                \"sender\": false, \n                \"start\": 32.000061\n            }\n        }, \n        {\n            \"streams\": [\n                {\n                    \"bits_per_second\": 865870336.6501037, \n                    \"bytes\": 108230760, \n                    \"end\": 34.000061, \n                    \"omitted\": false, \n                    \"seconds\": 0.9999719858169556, \n                    \"sender\": false, \n                    \"socket\": 5, \n                    \"start\": 33.000089\n                }\n            ], \n            \"sum\": {\n                \"bits_per_second\": 865870336.6501037, \n                \"bytes\": 108230760, \n                \"end\": 34.000061, \n                \"omitted\": false, \n                \"seconds\": 0.9999719858169556, \n                \"sender\": false, \n                \"start\": 33.000089\n            }\n        }, \n        {\n            \"streams\": [\n                {\n                    \"bits_per_second\": 865304066.391117, \n                    \"bytes\": 108165600, \n                    \"end\": 35.000085, \n                    \"omitted\": false, \n                    \"seconds\": 1.0000239610672, \n                    \"sender\": false, \n                    \"socket\": 5, \n                    \"start\": 34.000061\n                }\n            ], \n            \"sum\": {\n                \"bits_per_second\": 865304066.391117, \n                \"bytes\": 108165600, \n                \"end\": 35.000085, \n                \"omitted\": false, \n                \"seconds\": 1.0000239610672, \n                \"sender\": false, \n                \"start\": 34.000061\n            }\n        }, \n        {\n            \"streams\": [\n                {\n                    \"bits_per_second\": 865846080, \n                    \"bytes\": 108230760, \n                    \"end\": 36.000085, \n                    \"omitted\": false, \n                    \"seconds\": 1, \n                    \"sender\": false, \n                    \"socket\": 5, \n                    \"start\": 35.000085\n                }\n            ], \n            \"sum\": {\n                \"bits_per_second\": 865846080, \n                \"bytes\": 108230760, \n                \"end\": 36.000085, \n                \"omitted\": false, \n                \"seconds\": 1, \n                \"sender\": false, \n                \"start\": 35.000085\n            }\n        }, \n        {\n            \"streams\": [\n                {\n                    \"bits_per_second\": 865344709.325707, \n                    \"bytes\": 108165600, \n                    \"end\": 37.000062, \n                    \"omitted\": false, \n                    \"seconds\": 0.9999769926071167, \n                    \"sender\": false, \n                    \"socket\": 5, \n                    \"start\": 36.000085\n                }\n            ], \n            \"sum\": {\n                \"bits_per_second\": 865344709.325707, \n                \"bytes\": 108165600, \n                \"end\": 37.000062, \n                \"omitted\": false, \n                \"seconds\": 0.9999769926071167, \n                \"sender\": false, \n                \"start\": 36.000085\n            }\n        }, \n        {\n            \"streams\": [\n                {\n                    \"bits_per_second\": 865305716.7912476, \n                    \"bytes\": 108165600, \n                    \"end\": 38.000084, \n                    \"omitted\": false, \n                    \"seconds\": 1.000022053718567, \n                    \"sender\": false, \n                    \"socket\": 5, \n                    \"start\": 37.000062\n                }\n            ], \n            \"sum\": {\n                \"bits_per_second\": 865305716.7912476, \n                \"bytes\": 108165600, \n                \"end\": 38.000084, \n                \"omitted\": false, \n                \"seconds\": 1.000022053718567, \n                \"sender\": false, \n                \"start\": 37.000062\n            }\n        }, \n        {\n            \"streams\": [\n                {\n                    \"bits_per_second\": 865866878.7041544, \n                    \"bytes\": 108230760, \n                    \"end\": 39.00006, \n                    \"omitted\": false, \n                    \"seconds\": 0.9999759793281555, \n                    \"sender\": false, \n                    \"socket\": 5, \n                    \"start\": 38.000084\n                }\n            ], \n            \"sum\": {\n                \"bits_per_second\": 865866878.7041544, \n                \"bytes\": 108230760, \n                \"end\": 39.00006, \n                \"omitted\": false, \n                \"seconds\": 0.9999759793281555, \n                \"sender\": false, \n                \"start\": 38.000084\n            }\n        }, \n        {\n            \"streams\": [\n                {\n                    \"bits_per_second\": 865310977.48368, \n                    \"bytes\": 108165600, \n                    \"end\": 40.000076, \n                    \"omitted\": false, \n                    \"seconds\": 1.0000159740448, \n                    \"sender\": false, \n                    \"socket\": 5, \n                    \"start\": 39.00006\n                }\n            ], \n            \"sum\": {\n                \"bits_per_second\": 865310977.48368, \n                \"bytes\": 108165600, \n                \"end\": 40.000076, \n                \"omitted\": false, \n                \"seconds\": 1.0000159740448, \n                \"sender\": false, \n                \"start\": 39.00006\n            }\n        }, \n        {\n            \"streams\": [\n                {\n                    \"bits_per_second\": 865859085.524251, \n                    \"bytes\": 108230760, \n                    \"end\": 41.000061, \n                    \"omitted\": false, \n                    \"seconds\": 0.9999849796295166, \n                    \"sender\": false, \n                    \"socket\": 5, \n                    \"start\": 40.000076\n                }\n            ], \n            \"sum\": {\n                \"bits_per_second\": 865859085.524251, \n                \"bytes\": 108230760, \n                \"end\": 41.000061, \n                \"omitted\": false, \n                \"seconds\": 0.9999849796295166, \n                \"sender\": false, \n                \"start\": 40.000076\n            }\n        }, \n        {\n            \"streams\": [\n                {\n                    \"bits_per_second\": 865323974.76275, \n                    \"bytes\": 108165600, \n                    \"end\": 42.000062, \n                    \"omitted\": false, \n                    \"seconds\": 1.0000009536743164, \n                    \"sender\": false, \n                    \"socket\": 5, \n                    \"start\": 41.000061\n                }\n            ], \n            \"sum\": {\n                \"bits_per_second\": 865323974.76275, \n                \"bytes\": 108165600, \n                \"end\": 42.000062, \n                \"omitted\": false, \n                \"seconds\": 1.0000009536743164, \n                \"sender\": false, \n                \"start\": 41.000061\n            }\n        }, \n        {\n            \"streams\": [\n                {\n                    \"bits_per_second\": 865831320.2354724, \n                    \"bytes\": 108230760, \n                    \"end\": 43.000079, \n                    \"omitted\": false, \n                    \"seconds\": 1.0000170469284058, \n                    \"sender\": false, \n                    \"socket\": 5, \n                    \"start\": 42.000062\n                }\n            ], \n            \"sum\": {\n                \"bits_per_second\": 865831320.2354724, \n                \"bytes\": 108230760, \n                \"end\": 43.000079, \n                \"omitted\": false, \n                \"seconds\": 1.0000170469284058, \n                \"sender\": false, \n                \"start\": 42.000062\n            }\n        }, \n        {\n            \"streams\": [\n                {\n                    \"bits_per_second\": 865340376.6483395, \n                    \"bytes\": 108165600, \n                    \"end\": 44.000061, \n                    \"omitted\": false, \n                    \"seconds\": 0.9999819993972778, \n                    \"sender\": false, \n                    \"socket\": 5, \n                    \"start\": 43.000079\n                }\n            ], \n            \"sum\": {\n                \"bits_per_second\": 865340376.6483395, \n                \"bytes\": 108165600, \n                \"end\": 44.000061, \n                \"omitted\": false, \n                \"seconds\": 0.9999819993972778, \n                \"sender\": false, \n                \"start\": 43.000079\n            }\n        }, \n        {\n            \"streams\": [\n                {\n                    \"bits_per_second\": 865309223.9124285, \n                    \"bytes\": 108165600, \n                    \"end\": 45.000079, \n                    \"omitted\": false, \n                    \"seconds\": 1.0000180006027222, \n                    \"sender\": false, \n                    \"socket\": 5, \n                    \"start\": 44.000061\n                }\n            ], \n            \"sum\": {\n                \"bits_per_second\": 865309223.9124285, \n                \"bytes\": 108165600, \n                \"end\": 45.000079, \n                \"omitted\": false, \n                \"seconds\": 1.0000180006027222, \n                \"sender\": false, \n                \"start\": 44.000061\n            }\n        }, \n        {\n            \"streams\": [\n                {\n                    \"bits_per_second\": 865862543.4079545, \n                    \"bytes\": 108230760, \n                    \"end\": 46.00006, \n                    \"omitted\": false, \n                    \"seconds\": 0.9999809861183167, \n                    \"sender\": false, \n                    \"socket\": 5, \n                    \"start\": 45.000079\n                }\n            ], \n            \"sum\": {\n                \"bits_per_second\": 865862543.4079545, \n                \"bytes\": 108230760, \n                \"end\": 46.00006, \n                \"omitted\": false, \n                \"seconds\": 0.9999809861183167, \n                \"sender\": false, \n                \"start\": 45.000079\n            }\n        }, \n        {\n            \"streams\": [\n                {\n                    \"bits_per_second\": 865323974.76275, \n                    \"bytes\": 108165600, \n                    \"end\": 47.000061, \n                    \"omitted\": false, \n                    \"seconds\": 1.0000009536743164, \n                    \"sender\": false, \n                    \"socket\": 5, \n                    \"start\": 46.00006\n                }\n            ], \n            \"sum\": {\n                \"bits_per_second\": 865323974.76275, \n                \"bytes\": 108165600, \n                \"end\": 47.000061, \n                \"omitted\": false, \n                \"seconds\": 1.0000009536743164, \n                \"sender\": false, \n                \"start\": 46.00006\n            }\n        }, \n        {\n            \"streams\": [\n                {\n                    \"bits_per_second\": 865846080, \n                    \"bytes\": 108230760, \n                    \"end\": 48.000061, \n                    \"omitted\": false, \n                    \"seconds\": 1, \n                    \"sender\": false, \n                    \"socket\": 5, \n                    \"start\": 47.000061\n                }\n            ], \n            \"sum\": {\n                \"bits_per_second\": 865846080, \n                \"bytes\": 108230760, \n                \"end\": 48.000061, \n                \"omitted\": false, \n                \"seconds\": 1, \n                \"sender\": false, \n                \"start\": 47.000061\n            }\n        }, \n        {\n            \"streams\": [\n                {\n                    \"bits_per_second\": 865307470.3482844, \n                    \"bytes\": 108165600, \n                    \"end\": 49.000081, \n                    \"omitted\": false, \n                    \"seconds\": 1.0000200271606445, \n                    \"sender\": false, \n                    \"socket\": 5, \n                    \"start\": 48.000061\n                }\n            ], \n            \"sum\": {\n                \"bits_per_second\": 865307470.3482844, \n                \"bytes\": 108165600, \n                \"end\": 49.000081, \n                \"omitted\": false, \n                \"seconds\": 1.0000200271606445, \n                \"sender\": false, \n                \"start\": 48.000061\n            }\n        }, \n        {\n            \"streams\": [\n                {\n                    \"bits_per_second\": 865853872.945791, \n                    \"bytes\": 108230760, \n                    \"end\": 50.000072, \n                    \"omitted\": false, \n                    \"seconds\": 0.999990999698639, \n                    \"sender\": false, \n                    \"socket\": 5, \n                    \"start\": 49.000081\n                }\n            ], \n            \"sum\": {\n                \"bits_per_second\": 865853872.945791, \n                \"bytes\": 108230760, \n                \"end\": 50.000072, \n                \"omitted\": false, \n                \"seconds\": 0.999990999698639, \n                \"sender\": false, \n                \"start\": 49.000081\n            }\n        }, \n        {\n            \"streams\": [\n                {\n                    \"bits_per_second\": 865334341.9200215, \n                    \"bytes\": 108165600, \n                    \"end\": 51.000061, \n                    \"omitted\": false, \n                    \"seconds\": 0.9999889731407166, \n                    \"sender\": false, \n                    \"socket\": 5, \n                    \"start\": 50.000072\n                }\n            ], \n            \"sum\": {\n                \"bits_per_second\": 865334341.9200215, \n                \"bytes\": 108165600, \n                \"end\": 51.000061, \n                \"omitted\": false, \n                \"seconds\": 0.9999889731407166, \n                \"sender\": false, \n                \"start\": 50.000072\n            }\n        }, \n        {\n            \"streams\": [\n                {\n                    \"bits_per_second\": 865305716.7912476, \n                    \"bytes\": 108165600, \n                    \"end\": 52.000083, \n                    \"omitted\": false, \n                    \"seconds\": 1.000022053718567, \n                    \"sender\": false, \n                    \"socket\": 5, \n                    \"start\": 51.000061\n                }\n            ], \n            \"sum\": {\n                \"bits_per_second\": 865305716.7912476, \n                \"bytes\": 108165600, \n                \"end\": 52.000083, \n                \"omitted\": false, \n                \"seconds\": 1.000022053718567, \n                \"sender\": false, \n                \"start\": 51.000061\n            }\n        }, \n        {\n            \"streams\": [\n                {\n                    \"bits_per_second\": 865865123.936177, \n                    \"bytes\": 108230760, \n                    \"end\": 53.000061, \n                    \"omitted\": false, \n                    \"seconds\": 0.999978005886078, \n                    \"sender\": false, \n                    \"socket\": 5, \n                    \"start\": 52.000083\n                }\n            ], \n            \"sum\": {\n                \"bits_per_second\": 865865123.936177, \n                \"bytes\": 108230760, \n                \"end\": 53.000061, \n                \"omitted\": false, \n                \"seconds\": 0.999978005886078, \n                \"sender\": false, \n                \"start\": 52.000083\n            }\n        }, \n        {\n            \"streams\": [\n                {\n                    \"bits_per_second\": 865307470.3482844, \n                    \"bytes\": 108165600, \n                    \"end\": 54.000081, \n                    \"omitted\": false, \n                    \"seconds\": 1.0000200271606445, \n                    \"sender\": false, \n                    \"socket\": 5, \n                    \"start\": 53.000061\n                }\n            ], \n            \"sum\": {\n                \"bits_per_second\": 865307470.3482844, \n                \"bytes\": 108165600, \n                \"end\": 54.000081, \n                \"omitted\": false, \n                \"seconds\": 1.0000200271606445, \n                \"sender\": false, \n                \"start\": 53.000061\n            }\n        }, \n        {\n            \"streams\": [\n                {\n                    \"bits_per_second\": 865864246.5548556, \n                    \"bytes\": 108230760, \n                    \"end\": 55.00006, \n                    \"omitted\": false, \n                    \"seconds\": 0.999979019165039, \n                    \"sender\": false, \n                    \"socket\": 5, \n                    \"start\": 54.000081\n                }\n            ], \n            \"sum\": {\n                \"bits_per_second\": 865864246.5548556, \n                \"bytes\": 108230760, \n                \"end\": 55.00006, \n                \"omitted\": false, \n                \"seconds\": 0.999979019165039, \n                \"sender\": false, \n                \"start\": 54.000081\n            }\n        }, \n        {\n            \"streams\": [\n                {\n                    \"bits_per_second\": 865304066.391117, \n                    \"bytes\": 108165600, \n                    \"end\": 56.000084, \n                    \"omitted\": false, \n                    \"seconds\": 1.0000239610672, \n                    \"sender\": false, \n                    \"socket\": 5, \n                    \"start\": 55.00006\n                }\n            ], \n            \"sum\": {\n                \"bits_per_second\": 865304066.391117, \n                \"bytes\": 108165600, \n                \"end\": 56.000084, \n                \"omitted\": false, \n                \"seconds\": 1.0000239610672, \n                \"sender\": false, \n                \"start\": 55.00006\n            }\n        }, \n        {\n            \"streams\": [\n                {\n                    \"bits_per_second\": 865857330.787861, \n                    \"bytes\": 108230760, \n                    \"end\": 57.000071, \n                    \"omitted\": false, \n                    \"seconds\": 0.999987006187439, \n                    \"sender\": false, \n                    \"socket\": 5, \n                    \"start\": 56.000084\n                }\n            ], \n            \"sum\": {\n                \"bits_per_second\": 865857330.787861, \n                \"bytes\": 108230760, \n                \"end\": 57.000071, \n                \"omitted\": false, \n                \"seconds\": 0.999987006187439, \n                \"sender\": false, \n                \"start\": 56.000084\n            }\n        }, \n        {\n            \"streams\": [\n                {\n                    \"bits_per_second\": 865334341.9200215, \n                    \"bytes\": 108165600, \n                    \"end\": 58.00006, \n                    \"omitted\": false, \n                    \"seconds\": 0.9999889731407166, \n                    \"sender\": false, \n                    \"socket\": 5, \n                    \"start\": 57.000071\n                }\n            ], \n            \"sum\": {\n                \"bits_per_second\": 865334341.9200215, \n                \"bytes\": 108165600, \n                \"end\": 58.00006, \n                \"omitted\": false, \n                \"seconds\": 0.9999889731407166, \n                \"sender\": false, \n                \"start\": 57.000071\n            }\n        }, \n        {\n            \"streams\": [\n                {\n                    \"bits_per_second\": 865306645.1440877, \n                    \"bytes\": 108165600, \n                    \"end\": 59.000081, \n                    \"omitted\": false, \n                    \"seconds\": 1.000020980834961, \n                    \"sender\": false, \n                    \"socket\": 5, \n                    \"start\": 58.00006\n                }\n            ], \n            \"sum\": {\n                \"bits_per_second\": 865306645.1440877, \n                \"bytes\": 108165600, \n                \"end\": 59.000081, \n                \"omitted\": false, \n                \"seconds\": 1.000020980834961, \n                \"sender\": false, \n                \"start\": 58.00006\n            }\n        }, \n        {\n            \"streams\": [\n                {\n                    \"bits_per_second\": 865863420.7858243, \n                    \"bytes\": 108230760, \n                    \"end\": 60.000061, \n                    \"omitted\": false, \n                    \"seconds\": 0.9999799728393555, \n                    \"sender\": false, \n                    \"socket\": 5, \n                    \"start\": 59.000081\n                }\n            ], \n            \"sum\": {\n                \"bits_per_second\": 865863420.7858243, \n                \"bytes\": 108230760, \n                \"end\": 60.000061, \n                \"omitted\": false, \n                \"seconds\": 0.9999799728393555, \n                \"sender\": false, \n                \"start\": 59.000081\n            }\n        }, \n        {\n            \"streams\": [\n                {\n                    \"bits_per_second\": 860801999.2782388, \n                    \"bytes\": 8275320, \n                    \"end\": 60.076969, \n                    \"omitted\": false, \n                    \"seconds\": 0.07690799981355667, \n                    \"sender\": false, \n                    \"socket\": 5, \n                    \"start\": 60.000061\n                }\n            ], \n            \"sum\": {\n                \"bits_per_second\": 860801999.2782388, \n                \"bytes\": 8275320, \n                \"end\": 60.076969, \n                \"omitted\": false, \n                \"seconds\": 0.07690799981355667, \n                \"sender\": false, \n                \"start\": 60.000061\n            }\n        }\n    ], \n    \"start\": {\n        \"accepted_connection\": {\n            \"host\": \"10.0.0.1\", \n            \"port\": 53903\n        }, \n        \"connected\": [\n            {\n                \"local_host\": \"10.0.0.2\", \n                \"local_port\": 5201, \n                \"remote_host\": \"10.0.0.1\", \n                \"remote_port\": 37311, \n                \"socket\": 5\n            }\n        ], \n        \"cookie\": \"5jw7cglkzetned3jeeagnbygaprjsbpflmyr\", \n        \"fq_rate\": 0, \n        \"rcvbuf_actual\": 87380, \n        \"sndbuf_actual\": 87380, \n        \"sock_bufsize\": 0, \n        \"system_info\": \"REDACTED\", \n        \"target_bitrate\": 0, \n        \"tcp_mss_default\": 0, \n        \"test_start\": {\n            \"bidir\": 0, \n            \"blksize\": 131072, \n            \"blocks\": 0, \n            \"bytes\": 0, \n            \"duration\": 60, \n            \"fqrate\": 0, \n            \"num_streams\": 1, \n            \"omit\": 0, \n            \"protocol\": \"TCP\", \n            \"reverse\": 0, \n            \"target_bitrate\": 0, \n            \"tos\": 0\n        }, \n        \"timestamp\": {\n            \"time\": \"Wed, 17 Apr 2024 01:28:34 GMT\", \n            \"timesecs\": 1713317314\n        }, \n        \"version\": \"iperf 3.14\"\n    }\n}\n","summary":{"streams":[{"end":60.000073,"rtt":77086,"start":0,"stream-id":5,"retransmits":0,"throughput-bits":867014010.7329535,"throughput-bytes":6502612992}],"summary":{"end":60.000073,"start":0,"retransmits":0,"throughput-bits":867014010.7329535,"throughput-bytes":6502612992,"receiver-throughput-bits":865535438.84679}},"intervals":[{"streams":[{"end":1.000054,"rtt":77090,"start":0,"omitted":false,"stream-id":5,"retransmits":0,"tcp-window-size":16698336,"throughput-bits":955201153.410553,"throughput-bytes":119406592}],"summary":{"end":1.000054,"start":0,"omitted":false,"retransmits":0,"throughput-bits":955201153.410553,"throughput-bytes":119406592}},{"streams":[{"end":2.000084,"rtt":77088,"start":1.000054,"omitted":false,"stream-id":5,"retransmits":0,"tcp-window-size":16698336,"throughput-bits":870291935.7853916,"throughput-bytes":108789760}],"summary":{"end":2.000084,"start":1.000054,"omitted":false,"retransmits":0,"throughput-bits":870291935.7853916,"throughput-bytes":108789760}},{"streams":[{"end":3.000075,"rtt":77089,"start":2.000084,"omitted":false,"stream-id":5,"retransmits":0,"tcp-window-size":16698336,"throughput-bits":859840058.8196517,"throughput-bytes":107479040}],"summary":{"end":3.000075,"start":2.000084,"omitted":false,"retransmits":0,"throughput-bits":859840058.8196517,"throughput-bytes":107479040}},{"streams":[{"end":4.000063,"rtt":77084,"start":3.000075,"omitted":false,"stream-id":5,"retransmits":0,"tcp-window-size":16698336,"throughput-bits":870328506.999921,"throughput-bytes":108789760}],"summary":{"end":4.000063,"start":3.000075,"omitted":false,"retransmits":0,"throughput-bits":870328506.999921,"throughput-bytes":108789760}},{"streams":[{"end":5.000157,"rtt":77083,"start":4.000063,"omitted":false,"stream-id":5,"retransmits":0,"tcp-window-size":16698336,"throughput-bits":859751455.105839,"throughput-bytes":107479040}],"summary":{"end":5.000157,"start":4.000063,"omitted":false,"retransmits":0,"throughput-bits":859751455.105839,"throughput-bytes":107479040}},{"streams":[{"end":6.000165,"rtt":77084,"start":5.000157,"omitted":false,"stream-id":5,"retransmits":0,"tcp-window-size":16698336,"throughput-bits":870311128.8055193,"throughput-bytes":108789760}],"summary":{"end":6.000165,"start":5.000157,"omitted":false,"retransmits":0,"throughput-bits":870311128.8055193,"throughput-bytes":108789760}},{"streams":[{"end":7.000063,"rtt":77087,"start":6.000165,"omitted":false,"stream-id":5,"retransmits":0,"tcp-window-size":16698336,"throughput-bits":870406847.1777917,"throughput-bytes":108789760}],"summary":{"end":7.000063,"start":6.000165,"omitted":false,"retransmits":0,"throughput-bits":870406847.1777917,"throughput-bytes":108789760}},{"streams":[{"end":8.000123,"rtt":77085,"start":7.000063,"omitted":false,"stream-id":5,"retransmits":0,"tcp-window-size":16698336,"throughput-bits":859780765.5913196,"throughput-bytes":107479040}],"summary":{"end":8.000123,"start":7.000063,"omitted":false,"retransmits":0,"throughput-bits":859780765.5913196,"throughput-bytes":107479040}},{"streams":[{"end":9.000082,"rtt":77090,"start":8.000123,"omitted":false,"stream-id":5,"retransmits":0,"tcp-window-size":16698336,"throughput-bits":870353771.4636353,"throughput-bytes":108789760}],"summary":{"end":9.000082,"start":8.000123,"omitted":false,"retransmits":0,"throughput-bits":870353771.4636353,"throughput-bytes":108789760}},{"streams":[{"end":10.000127,"rtt":77084,"start":9.000082,"omitted":false,"stream-id":5,"retransmits":0,"tcp-window-size":16698336,"throughput-bits":859793679.2365894,"throughput-bytes":107479040}],"summary":{"end":10.000127,"start":9.000082,"omitted":false,"retransmits":0,"throughput-bits":859793679.2365894,"throughput-bytes":107479040}},{"streams":[{"end":11.000063,"rtt":77090,"start":10.000127,"omitted":false,"stream-id":5,"retransmits":0,"tcp-window-size":16698336,"throughput-bits":870373797.3167657,"throughput-bytes":108789760}],"summary":{"end":11.000063,"start":10.000127,"omitted":false,"retransmits":0,"throughput-bits":870373797.3167657,"throughput-bytes":108789760}},{"streams":[{"end":12.000079,"rtt":77089,"start":11.000063,"omitted":false,"stream-id":5,"retransmits":0,"tcp-window-size":16698336,"throughput-bits":859818585.2194,"throughput-bytes":107479040}],"summary":{"end":12.000079,"start":11.000063,"omitted":false,"retransmits":0,"throughput-bits":859818585.2194,"throughput-bytes":107479040}},{"streams":[{"end":13.000062,"rtt":77085,"start":12.000079,"omitted":false,"stream-id":5,"retransmits":0,"tcp-window-size":16698336,"throughput-bits":870332864.6261512,"throughput-bytes":108789760}],"summary":{"end":13.000062,"start":12.000079,"omitted":false,"retransmits":0,"throughput-bits":870332864.6261512,"throughput-bytes":108789760}},{"streams":[{"end":14.000078,"rtt":77087,"start":13.000062,"omitted":false,"stream-id":5,"retransmits":0,"tcp-window-size":16698336,"throughput-bits":859818585.2194,"throughput-bytes":107479040}],"summary":{"end":14.000078,"start":13.000062,"omitted":false,"retransmits":0,"throughput-bits":859818585.2194,"throughput-bytes":107479040}},{"streams":[{"end":15.000046,"rtt":77085,"start":14.000078,"omitted":false,"stream-id":5,"retransmits":0,"tcp-window-size":16698336,"throughput-bits":870345937.766663,"throughput-bytes":108789760}],"summary":{"end":15.000046,"start":14.000078,"omitted":false,"retransmits":0,"throughput-bits":870345937.766663,"throughput-bytes":108789760}},{"streams":[{"end":16.000069,"rtt":77087,"start":15.000046,"omitted":false,"stream-id":5,"retransmits":0,"tcp-window-size":16698336,"throughput-bits":859812537.9551333,"throughput-bytes":107479040}],"summary":{"end":16.000069,"start":15.000046,"omitted":false,"retransmits":0,"throughput-bits":859812537.9551333,"throughput-bytes":107479040}},{"streams":[{"end":17.000071,"rtt":77088,"start":16.000069,"omitted":false,"stream-id":5,"retransmits":0,"tcp-window-size":16698336,"throughput-bits":870316316.2535744,"throughput-bytes":108789760}],"summary":{"end":17.000071,"start":16.000069,"omitted":false,"retransmits":0,"throughput-bits":870316316.2535744,"throughput-bytes":108789760}},{"streams":[{"end":18.000215,"rtt":77087,"start":17.000071,"omitted":false,"stream-id":5,"retransmits":0,"tcp-window-size":16698336,"throughput-bits":870192768.0455257,"throughput-bytes":108789760}],"summary":{"end":18.000215,"start":17.000071,"omitted":false,"retransmits":0,"throughput-bits":870192768.0455257,"throughput-bytes":108789760}},{"streams":[{"end":19.000155,"rtt":77081,"start":18.000215,"omitted":false,"stream-id":5,"retransmits":0,"tcp-window-size":16698336,"throughput-bits":859883931.84784,"throughput-bytes":107479040}],"summary":{"end":19.000155,"start":18.000215,"omitted":false,"retransmits":0,"throughput-bits":859883931.84784,"throughput-bytes":107479040}},{"streams":[{"end":20.000068,"rtt":77092,"start":19.000155,"omitted":false,"stream-id":5,"retransmits":0,"tcp-window-size":16698336,"throughput-bits":870393824.0914615,"throughput-bytes":108789760}],"summary":{"end":20.000068,"start":19.000155,"omitted":false,"retransmits":0,"throughput-bits":870393824.0914615,"throughput-bytes":108789760}},{"streams":[{"end":21.000085,"rtt":77090,"start":20.000068,"omitted":false,"stream-id":5,"retransmits":0,"tcp-window-size":16698336,"throughput-bits":859817662.749861,"throughput-bytes":107479040}],"summary":{"end":21.000085,"start":20.000068,"omitted":false,"retransmits":0,"throughput-bits":859817662.749861,"throughput-bytes":107479040}},{"streams":[{"end":22.000036,"rtt":77087,"start":21.000085,"omitted":false,"stream-id":5,"retransmits":0,"tcp-window-size":16698336,"throughput-bits":870360723.339311,"throughput-bytes":108789760}],"summary":{"end":22.000036,"start":21.000085,"omitted":false,"retransmits":0,"throughput-bits":870360723.339311,"throughput-bytes":108789760}},{"streams":[{"end":23.000064,"rtt":77091,"start":22.000036,"omitted":false,"stream-id":5,"retransmits":0,"tcp-window-size":16698336,"throughput-bits":859808233.1747727,"throughput-bytes":107479040}],"summary":{"end":23.000064,"start":22.000036,"omitted":false,"retransmits":0,"throughput-bits":859808233.1747727,"throughput-bytes":107479040}},{"streams":[{"end":24.000156,"rtt":77085,"start":23.000064,"omitted":false,"stream-id":5,"retransmits":0,"tcp-window-size":16698336,"throughput-bits":870237992.3704302,"throughput-bytes":108789760}],"summary":{"end":24.000156,"start":23.000064,"omitted":false,"retransmits":0,"throughput-bits":870237992.3704302,"throughput-bytes":108789760}},{"streams":[{"end":25.000064,"rtt":77087,"start":24.000156,"omitted":false,"stream-id":5,"retransmits":0,"tcp-window-size":16698336,"throughput-bits":859911457.2829702,"throughput-bytes":107479040}],"summary":{"end":25.000064,"start":24.000156,"omitted":false,"retransmits":0,"throughput-bits":859911457.2829702,"throughput-bytes":107479040}},{"streams":[{"end":26.000081,"rtt":77088,"start":25.000064,"omitted":false,"stream-id":5,"retransmits":0,"tcp-window-size":16698336,"throughput-bits":870303244.0029082,"throughput-bytes":108789760}],"summary":{"end":26.000081,"start":25.000064,"omitted":false,"retransmits":0,"throughput-bits":870303244.0029082,"throughput-bytes":108789760}},{"streams":[{"end":27.000063,"rtt":77087,"start":26.000081,"omitted":false,"stream-id":5,"retransmits":0,"tcp-window-size":16698336,"throughput-bits":859847797.7786094,"throughput-bytes":107479040}],"summary":{"end":27.000063,"start":26.000081,"omitted":false,"retransmits":0,"throughput-bits":859847797.7786094,"throughput-bytes":107479040}},{"streams":[{"end":28.000064,"rtt":77084,"start":27.000063,"omitted":false,"stream-id":5,"retransmits":0,"tcp-window-size":16698336,"throughput-bits":870317250.0007915,"throughput-bytes":108789760}],"summary":{"end":28.000064,"start":27.000063,"omitted":false,"retransmits":0,"throughput-bits":870317250.0007915,"throughput-bytes":108789760}},{"streams":[{"end":29.000044,"rtt":77088,"start":28.000064,"omitted":false,"stream-id":5,"retransmits":0,"tcp-window-size":16698336,"throughput-bits":870335510.3490804,"throughput-bytes":108789760}],"summary":{"end":29.000044,"start":28.000064,"omitted":false,"retransmits":0,"throughput-bits":870335510.3490804,"throughput-bytes":108789760}},{"streams":[{"end":30.000079,"rtt":77082,"start":29.000044,"omitted":false,"stream-id":5,"retransmits":0,"tcp-window-size":16698336,"throughput-bits":859802186.0561204,"throughput-bytes":107479040}],"summary":{"end":30.000079,"start":29.000044,"omitted":false,"retransmits":0,"throughput-bits":859802186.0561204,"throughput-bytes":107479040}},{"streams":[{"end":31.000071,"rtt":77085,"start":30.000079,"omitted":false,"stream-id":5,"retransmits":0,"tcp-window-size":16698336,"throughput-bits":870325031.30552,"throughput-bytes":108789760}],"summary":{"end":31.000071,"start":30.000079,"omitted":false,"retransmits":0,"throughput-bits":870325031.30552,"throughput-bytes":108789760}},{"streams":[{"end":32.000065,"rtt":77082,"start":31.000071,"omitted":false,"stream-id":5,"retransmits":0,"tcp-window-size":16698336,"throughput-bits":859837496.2811615,"throughput-bytes":107479040}],"summary":{"end":32.000065,"start":31.000071,"omitted":false,"retransmits":0,"throughput-bits":859837496.2811615,"throughput-bytes":107479040}},{"streams":[{"end":33.000084,"rtt":77084,"start":32.000065,"omitted":false,"stream-id":5,"retransmits":0,"tcp-window-size":16698336,"throughput-bits":870301584.0626686,"throughput-bytes":108789760}],"summary":{"end":33.000084,"start":32.000065,"omitted":false,"retransmits":0,"throughput-bits":870301584.0626686,"throughput-bytes":108789760}},{"streams":[{"end":34.000073,"rtt":77084,"start":33.000084,"omitted":false,"stream-id":5,"retransmits":0,"tcp-window-size":16698336,"throughput-bits":859841801.3545495,"throughput-bytes":107479040}],"summary":{"end":34.000073,"start":33.000084,"omitted":false,"retransmits":0,"throughput-bits":859841801.3545495,"throughput-bytes":107479040}},{"streams":[{"end":35.000082,"rtt":77087,"start":34.000073,"omitted":false,"stream-id":5,"retransmits":0,"tcp-window-size":16698336,"throughput-bits":870310298.8195692,"throughput-bytes":108789760}],"summary":{"end":35.000082,"start":34.000073,"omitted":false,"retransmits":0,"throughput-bits":870310298.8195692,"throughput-bytes":108789760}},{"streams":[{"end":36.000066,"rtt":77085,"start":35.000082,"omitted":false,"stream-id":5,"retransmits":0,"tcp-window-size":16698336,"throughput-bits":859846055.219407,"throughput-bytes":107479040}],"summary":{"end":36.000066,"start":35.000082,"omitted":false,"retransmits":0,"throughput-bits":859846055.219407,"throughput-bytes":107479040}},{"streams":[{"end":37.00008,"rtt":77084,"start":36.000066,"omitted":false,"stream-id":5,"retransmits":0,"tcp-window-size":16698336,"throughput-bits":870305941.4193027,"throughput-bytes":108789760}],"summary":{"end":37.00008,"start":36.000066,"omitted":false,"retransmits":0,"throughput-bits":870305941.4193027,"throughput-bytes":108789760}},{"streams":[{"end":38.000063,"rtt":77084,"start":37.00008,"omitted":false,"stream-id":5,"retransmits":0,"tcp-window-size":16698336,"throughput-bits":859846926.4981253,"throughput-bytes":107479040}],"summary":{"end":38.000063,"start":37.00008,"omitted":false,"retransmits":0,"throughput-bits":859846926.4981253,"throughput-bytes":107479040}},{"streams":[{"end":39.000063,"rtt":77078,"start":38.000063,"omitted":false,"stream-id":5,"retransmits":0,"tcp-window-size":16698336,"throughput-bits":870318080,"throughput-bytes":108789760}],"summary":{"end":39.000063,"start":38.000063,"omitted":false,"retransmits":0,"throughput-bits":870318080,"throughput-bytes":108789760}},{"streams":[{"end":40.000062,"rtt":77083,"start":39.000063,"omitted":false,"stream-id":5,"retransmits":0,"tcp-window-size":16698336,"throughput-bits":870318961.8758936,"throughput-bytes":108789760}],"summary":{"end":40.000062,"start":39.000063,"omitted":false,"retransmits":0,"throughput-bits":870318961.8758936,"throughput-bytes":108789760}},{"streams":[{"end":41.000062,"rtt":77084,"start":40.000062,"omitted":false,"stream-id":5,"retransmits":0,"tcp-window-size":16698336,"throughput-bits":859832320,"throughput-bytes":107479040}],"summary":{"end":41.000062,"start":40.000062,"omitted":false,"retransmits":0,"throughput-bits":859832320,"throughput-bytes":107479040}},{"streams":[{"end":42.000208,"rtt":77087,"start":41.000062,"omitted":false,"stream-id":5,"retransmits":0,"tcp-window-size":16698336,"throughput-bits":870191004.8069657,"throughput-bytes":108789760}],"summary":{"end":42.000208,"start":41.000062,"omitted":false,"retransmits":0,"throughput-bits":870191004.8069657,"throughput-bytes":108789760}},{"streams":[{"end":43.000083,"rtt":77086,"start":42.000208,"omitted":false,"stream-id":5,"retransmits":0,"tcp-window-size":16698336,"throughput-bits":859939804.6846118,"throughput-bytes":107479040}],"summary":{"end":43.000083,"start":42.000208,"omitted":false,"retransmits":0,"throughput-bits":859939804.6846118,"throughput-bytes":107479040}},{"streams":[{"end":44.000154,"rtt":77093,"start":43.000083,"omitted":false,"stream-id":5,"retransmits":0,"tcp-window-size":16698336,"throughput-bits":870256249.3929865,"throughput-bytes":108789760}],"summary":{"end":44.000154,"start":43.000083,"omitted":false,"retransmits":0,"throughput-bits":870256249.3929865,"throughput-bytes":108789760}},{"streams":[{"end":45.000162,"rtt":77085,"start":44.000154,"omitted":false,"stream-id":5,"retransmits":0,"tcp-window-size":16698336,"throughput-bits":859825452.5548505,"throughput-bytes":107479040}],"summary":{"end":45.000162,"start":44.000154,"omitted":false,"retransmits":0,"throughput-bits":859825452.5548505,"throughput-bytes":107479040}},{"streams":[{"end":46.000096,"rtt":77088,"start":45.000162,"omitted":false,"stream-id":5,"retransmits":0,"tcp-window-size":16698336,"throughput-bits":870375509.4143273,"throughput-bytes":108789760}],"summary":{"end":46.000096,"start":45.000162,"omitted":false,"retransmits":0,"throughput-bits":870375509.4143273,"throughput-bytes":108789760}},{"streams":[{"end":47.00017,"rtt":77091,"start":46.000096,"omitted":false,"stream-id":5,"retransmits":0,"tcp-window-size":16698336,"throughput-bits":859768672.21178,"throughput-bytes":107479040}],"summary":{"end":47.00017,"start":46.000096,"omitted":false,"retransmits":0,"throughput-bits":859768672.21178,"throughput-bytes":107479040}},{"streams":[{"end":48.000156,"rtt":77084,"start":47.00017,"omitted":false,"stream-id":5,"retransmits":0,"tcp-window-size":16698336,"throughput-bits":870330270.7957577,"throughput-bytes":108789760}],"summary":{"end":48.000156,"start":47.00017,"omitted":false,"retransmits":0,"throughput-bits":870330270.7957577,"throughput-bytes":108789760}},{"streams":[{"end":49.000083,"rtt":77084,"start":48.000156,"omitted":false,"stream-id":5,"retransmits":0,"tcp-window-size":16698336,"throughput-bits":859895105.834351,"throughput-bytes":107479040}],"summary":{"end":49.000083,"start":48.000156,"omitted":false,"retransmits":0,"throughput-bits":859895105.834351,"throughput-bytes":107479040}},{"streams":[{"end":50.000049,"rtt":77089,"start":49.000083,"omitted":false,"stream-id":5,"retransmits":0,"tcp-window-size":16698336,"throughput-bits":870347649.754622,"throughput-bytes":108789760}],"summary":{"end":50.000049,"start":49.000083,"omitted":false,"retransmits":0,"throughput-bits":870347649.754622,"throughput-bytes":108789760}},{"streams":[{"end":51.000005,"rtt":77087,"start":50.000049,"omitted":false,"stream-id":5,"retransmits":0,"tcp-window-size":16698336,"throughput-bits":870356365.4341084,"throughput-bytes":108789760}],"summary":{"end":51.000005,"start":50.000049,"omitted":false,"retransmits":0,"throughput-bits":870356365.4341084,"throughput-bytes":108789760}},{"streams":[{"end":52.000057,"rtt":77085,"start":51.000005,"omitted":false,"stream-id":5,"retransmits":0,"tcp-window-size":16698336,"throughput-bits":859787632.322653,"throughput-bytes":107479040}],"summary":{"end":52.000057,"start":51.000005,"omitted":false,"retransmits":0,"throughput-bits":859787632.322653,"throughput-bytes":107479040}},{"streams":[{"end":53.000063,"rtt":77087,"start":52.000057,"omitted":false,"stream-id":5,"retransmits":0,"tcp-window-size":16698336,"throughput-bits":870312892.5309197,"throughput-bytes":108789760}],"summary":{"end":53.000063,"start":52.000057,"omitted":false,"retransmits":0,"throughput-bits":870312892.5309197,"throughput-bytes":108789760}},{"streams":[{"end":54.00008,"rtt":77089,"start":53.000063,"omitted":false,"stream-id":5,"retransmits":0,"tcp-window-size":16698336,"throughput-bits":859817662.749861,"throughput-bytes":107479040}],"summary":{"end":54.00008,"start":53.000063,"omitted":false,"retransmits":0,"throughput-bits":859817662.749861,"throughput-bytes":107479040}},{"streams":[{"end":55.000062,"rtt":77088,"start":54.00008,"omitted":false,"stream-id":5,"retransmits":0,"tcp-window-size":16698336,"throughput-bits":870333746.532007,"throughput-bytes":108789760}],"summary":{"end":55.000062,"start":54.00008,"omitted":false,"retransmits":0,"throughput-bits":870333746.532007,"throughput-bytes":108789760}},{"streams":[{"end":56.000081,"rtt":77084,"start":55.000062,"omitted":false,"stream-id":5,"retransmits":0,"tcp-window-size":16698336,"throughput-bits":859816022.8089014,"throughput-bytes":107479040}],"summary":{"end":56.000081,"start":55.000062,"omitted":false,"retransmits":0,"throughput-bits":859816022.8089014,"throughput-bytes":107479040}},{"streams":[{"end":57.000034,"rtt":77088,"start":56.000081,"omitted":false,"stream-id":5,"retransmits":0,"tcp-window-size":16698336,"throughput-bits":870359011.29992,"throughput-bytes":108789760}],"summary":{"end":57.000034,"start":56.000081,"omitted":false,"retransmits":0,"throughput-bits":870359011.29992,"throughput-bytes":108789760}},{"streams":[{"end":58.000088,"rtt":77089,"start":57.000034,"omitted":false,"stream-id":5,"retransmits":0,"tcp-window-size":16698336,"throughput-bits":859785890.0073036,"throughput-bytes":107479040}],"summary":{"end":58.000088,"start":57.000034,"omitted":false,"retransmits":0,"throughput-bits":859785890.0073036,"throughput-bytes":107479040}},{"streams":[{"end":59.000056,"rtt":77089,"start":58.000088,"omitted":false,"stream-id":5,"retransmits":0,"tcp-window-size":16698336,"throughput-bits":870345937.766663,"throughput-bytes":108789760}],"summary":{"end":59.000056,"start":58.000088,"omitted":false,"retransmits":0,"throughput-bits":870345937.766663,"throughput-bytes":108789760}},{"streams":[{"end":60.000073,"rtt":77086,"start":59.000056,"omitted":false,"stream-id":5,"retransmits":0,"tcp-window-size":16698336,"throughput-bits":859817662.749861,"throughput-bytes":107479040}],"summary":{"end":60.000073,"start":59.000056,"omitted":false,"retransmits":0,"throughput-bits":859817662.749861,"throughput-bytes":107479040}}],"succeeded":true}
