{"diags":"Participant 0:\n/usr/bin/iperf3 -p 5201 -B 10.0.0.1 -c 10.0.0.2 -t 60 --json --rsa-public-key-path /var/run/pscheduler-server/runner/tmp/tmp6ilelm0d/tmpzr9w1cbv/public-key --username rXMUAIkP8RVLCon2Jkpr\n\n{\n    \"end\": {\n        \"cpu_utilization_percent\": {\n            \"host_system\": 2.230430715728039, \n            \"host_total\": 2.2700369588837437, \n            \"host_user\": 0.0396062431557044, \n            \"remote_system\": 4.855504737877567, \n            \"remote_total\": 5.23795283581219, \n            \"remote_user\": 0.3824447689265594\n        }, \n        \"receiver_tcp_congestion\": \"htcp\", \n        \"sender_tcp_congestion\": \"htcp\", \n        \"streams\": [\n            {\n                \"receiver\": {\n                    \"bits_per_second\": 851136547.601172, \n                    \"bytes\": 6391816624, \n                    \"end\": 60.077943, \n                    \"seconds\": 60.000091, \n                    \"sender\": true, \n                    \"socket\": 5, \n                    \"start\": 0\n                }, \n                \"sender\": {\n                    \"bits_per_second\": 852753138.6577398, \n                    \"bytes\": 6395658240, \n                    \"end\": 60.000091, \n                    \"max_rtt\": 78394, \n                    \"max_snd_cwnd\": 16708472, \n                    \"max_snd_wnd\": 0, \n                    \"mean_rtt\": 78383, \n                    \"min_rtt\": 78362, \n                    \"retransmits\": 0, \n                    \"seconds\": 60.000091, \n                    \"sender\": true, \n                    \"socket\": 5, \n                    \"start\": 0\n                }\n            }\n        ], \n        \"sum_received\": {\n            \"bits_per_second\": 851136547.601172, \n            \"bytes\": 6391816624, \n            \"end\": 60.077943, \n            \"seconds\": 60.077943, \n            \"sender\": true, \n            \"start\": 0\n        }, \n        \"sum_sent\": {\n            \"bits_per_second\": 852753138.6577398, \n            \"bytes\": 6395658240, \n            \"end\": 60.000091, \n            \"retransmits\": 0, \n            \"seconds\": 60.000091, \n            \"sender\": true, \n            \"start\": 0\n        }\n    }, \n    \"intervals\": [\n        {\n            \"streams\": [\n                {\n                    \"bits_per_second\": 938327309.035264, \n                    \"bytes\": 117309440, \n                    \"end\": 1.000158, \n                    \"omitted\": false, \n                    \"pmtu\": 1500, \n                    \"retransmits\": 0, \n                    \"rtt\": 78380, \n                    \"rttvar\": 4, \n                    \"seconds\": 1.0001579523086548, \n                    \"sender\": true, \n                    \"snd_cwnd\": 16708472, \n                    \"snd_wnd\": -1, \n                    \"socket\": 5, \n                    \"start\": 0\n                }\n            ], \n            \"sum\": {\n                \"bits_per_second\": 938327309.035264, \n                \"bytes\": 117309440, \n                \"end\": 1.000158, \n                \"omitted\": false, \n                \"retransmits\": 0, \n                \"seconds\": 1.0001579523086548, \n                \"sender\": true, \n                \"start\": 0\n            }\n        }, \n        {\n            \"streams\": [\n                {\n                    \"bits_per_second\": 849349951.8885455, \n                    \"bytes\": 106168320, \n                    \"end\": 2.000154, \n                    \"omitted\": false, \n                    \"pmtu\": 1500, \n                    \"retransmits\": 0, \n                    \"rtt\": 78382, \n                    \"rttvar\": 8, \n                    \"seconds\": 0.9999960064888, \n                    \"sender\": true, \n                    \"snd_cwnd\": 16708472, \n                    \"snd_wnd\": -1, \n                    \"socket\": 5, \n                    \"start\": 1.000158\n                }\n            ], \n            \"sum\": {\n                \"bits_per_second\": 849349951.8885455, \n                \"bytes\": 106168320, \n                \"end\": 2.000154, \n                \"omitted\": false, \n                \"retransmits\": 0, \n                \"seconds\": 0.9999960064888, \n                \"sender\": true, \n                \"start\": 1.000158\n            }\n        }, \n        {\n            \"streams\": [\n                {\n                    \"bits_per_second\": 859609645.1820825, \n                    \"bytes\": 107479040, \n                    \"end\": 3.000413, \n                    \"omitted\": false, \n                    \"pmtu\": 1500, \n                    \"retransmits\": 0, \n                    \"rtt\": 78386, \n                    \"rttvar\": 4, \n                    \"seconds\": 1.0002590417861938, \n                    \"sender\": true, \n                    \"snd_cwnd\": 16708472, \n                    \"snd_wnd\": -1, \n                    \"socket\": 5, \n                    \"start\": 2.000154\n                }\n            ], \n            \"sum\": {\n                \"bits_per_second\": 859609645.1820825, \n                \"bytes\": 107479040, \n                \"end\": 3.000413, \n                \"omitted\": false, \n                \"retransmits\": 0, \n                \"seconds\": 1.0002590417861938, \n                \"sender\": true, \n                \"start\": 2.000154\n            }\n        }, \n        {\n            \"streams\": [\n                {\n                    \"bits_per_second\": 849629496.0958748, \n                    \"bytes\": 106168320, \n                    \"end\": 4.00008, \n                    \"omitted\": false, \n                    \"pmtu\": 1500, \n                    \"retransmits\": 0, \n                    \"rtt\": 78379, \n                    \"rttvar\": 12, \n                    \"seconds\": 0.99966698884964, \n                    \"sender\": true, \n                    \"snd_cwnd\": 16708472, \n                    \"snd_wnd\": -1, \n                    \"socket\": 5, \n                    \"start\": 3.000413\n                }\n            ], \n            \"sum\": {\n                \"bits_per_second\": 849629496.0958748, \n                \"bytes\": 106168320, \n                \"end\": 4.00008, \n                \"omitted\": false, \n                \"retransmits\": 0, \n                \"seconds\": 0.99966698884964, \n                \"sender\": true, \n                \"start\": 3.000413\n            }\n        }, \n        {\n            \"streams\": [\n                {\n                    \"bits_per_second\": 849283688.4043194, \n                    \"bytes\": 106168320, \n                    \"end\": 5.000154, \n                    \"omitted\": false, \n                    \"pmtu\": 1500, \n                    \"retransmits\": 0, \n                    \"rtt\": 78386, \n                    \"rttvar\": 6, \n                    \"seconds\": 1.000074028968811, \n                    \"sender\": true, \n                    \"snd_cwnd\": 16708472, \n                    \"snd_wnd\": -1, \n                    \"socket\": 5, \n                    \"start\": 4.00008\n                }\n            ], \n            \"sum\": {\n                \"bits_per_second\": 849283688.4043194, \n                \"bytes\": 106168320, \n                \"end\": 5.000154, \n                \"omitted\": false, \n                \"retransmits\": 0, \n                \"seconds\": 1.000074028968811, \n                \"sender\": true, \n                \"start\": 4.00008\n            }\n        }, \n        {\n            \"streams\": [\n                {\n                    \"bits_per_second\": 849340586.2920152, \n                    \"bytes\": 106168320, \n                    \"end\": 6.000161, \n                    \"omitted\": false, \n                    \"pmtu\": 1500, \n                    \"retransmits\": 0, \n                    \"rtt\": 78386, \n                    \"rttvar\": 8, \n                    \"seconds\": 1.0000070333480835, \n                    \"sender\": true, \n                    \"snd_cwnd\": 16708472, \n                    \"snd_wnd\": -1, \n                    \"socket\": 5, \n                    \"start\": 5.000154\n                }\n            ], \n            \"sum\": {\n                \"bits_per_second\": 849340586.2920152, \n                \"bytes\": 106168320, \n                \"end\": 6.000161, \n                \"omitted\": false, \n                \"retransmits\": 0, \n                \"seconds\": 1.0000070333480835, \n                \"sender\": true, \n                \"start\": 5.000154\n            }\n        }, \n        {\n            \"streams\": [\n                {\n                    \"bits_per_second\": 849405187.7966182, \n                    \"bytes\": 106168320, \n                    \"end\": 7.000092, \n                    \"omitted\": false, \n                    \"pmtu\": 1500, \n                    \"retransmits\": 0, \n                    \"rtt\": 78381, \n                    \"rttvar\": 10, \n                    \"seconds\": 0.99993097782135, \n                    \"sender\": true, \n                    \"snd_cwnd\": 16708472, \n                    \"snd_wnd\": -1, \n                    \"socket\": 5, \n                    \"start\": 6.000161\n                }\n            ], \n            \"sum\": {\n                \"bits_per_second\": 849405187.7966182, \n                \"bytes\": 106168320, \n                \"end\": 7.000092, \n                \"omitted\": false, \n                \"retransmits\": 0, \n                \"seconds\": 0.99993097782135, \n                \"sender\": true, \n                \"start\": 6.000161\n            }\n        }, \n        {\n            \"streams\": [\n                {\n                    \"bits_per_second\": 849358457.041643, \n                    \"bytes\": 106168320, \n                    \"end\": 8.000078, \n                    \"omitted\": false, \n                    \"pmtu\": 1500, \n                    \"retransmits\": 0, \n                    \"rtt\": 78381, \n                    \"rttvar\": 5, \n                    \"seconds\": 0.9999859929084778, \n                    \"sender\": true, \n                    \"snd_cwnd\": 16708472, \n                    \"snd_wnd\": -1, \n                    \"socket\": 5, \n                    \"start\": 7.000092\n                }\n            ], \n            \"sum\": {\n                \"bits_per_second\": 849358457.041643, \n                \"bytes\": 106168320, \n                \"end\": 8.000078, \n                \"omitted\": false, \n                \"retransmits\": 0, \n                \"seconds\": 0.9999859929084778, \n                \"sender\": true, \n                \"start\": 7.000092\n            }\n        }, \n        {\n            \"streams\": [\n                {\n                    \"bits_per_second\": 859829757.5076368, \n                    \"bytes\": 107479040, \n                    \"end\": 9.000081, \n                    \"omitted\": false, \n                    \"pmtu\": 1500, \n                    \"retransmits\": 0, \n                    \"rtt\": 78391, \n                    \"rttvar\": 9, \n                    \"seconds\": 1.0000029802322388, \n                    \"sender\": true, \n                    \"snd_cwnd\": 16708472, \n                    \"snd_wnd\": -1, \n                    \"socket\": 5, \n                    \"start\": 8.000078\n                }\n            ], \n            \"sum\": {\n                \"bits_per_second\": 859829757.5076368, \n                \"bytes\": 107479040, \n                \"end\": 9.000081, \n                \"omitted\": false, \n                \"retransmits\": 0, \n                \"seconds\": 1.0000029802322388, \n                \"sender\": true, \n                \"start\": 8.000078\n            }\n        }, \n        {\n            \"streams\": [\n                {\n                    \"bits_per_second\": 849341497.5301746, \n                    \"bytes\": 106168320, \n                    \"end\": 10.000087, \n                    \"omitted\": false, \n                    \"pmtu\": 1500, \n                    \"retransmits\": 0, \n                    \"rtt\": 78388, \n                    \"rttvar\": 4, \n                    \"seconds\": 1.0000059604644775, \n                    \"sender\": true, \n                    \"snd_cwnd\": 16708472, \n                    \"snd_wnd\": -1, \n                    \"socket\": 5, \n                    \"start\": 9.000081\n                }\n            ], \n            \"sum\": {\n                \"bits_per_second\": 849341497.5301746, \n                \"bytes\": 106168320, \n                \"end\": 10.000087, \n                \"omitted\": false, \n                \"retransmits\": 0, \n                \"seconds\": 1.0000059604644775, \n                \"sender\": true, \n                \"start\": 9.000081\n            }\n        }, \n        {\n            \"streams\": [\n                {\n                    \"bits_per_second\": 849366962.3650786, \n                    \"bytes\": 106168320, \n                    \"end\": 11.000063, \n                    \"omitted\": false, \n                    \"pmtu\": 1500, \n                    \"retransmits\": 0, \n                    \"rtt\": 78383, \n                    \"rttvar\": 6, \n                    \"seconds\": 0.9999759793281555, \n                    \"sender\": true, \n                    \"snd_cwnd\": 16708472, \n                    \"snd_wnd\": -1, \n                    \"socket\": 5, \n                    \"start\": 10.000087\n                }\n            ], \n            \"sum\": {\n                \"bits_per_second\": 849366962.3650786, \n                \"bytes\": 106168320, \n                \"end\": 11.000063, \n                \"omitted\": false, \n                \"retransmits\": 0, \n                \"seconds\": 0.9999759793281555, \n                \"sender\": true, \n                \"start\": 10.000087\n            }\n        }, \n        {\n            \"streams\": [\n                {\n                    \"bits_per_second\": 849325298.032271, \n                    \"bytes\": 106168320, \n                    \"end\": 12.000088, \n                    \"omitted\": false, \n                    \"pmtu\": 1500, \n                    \"retransmits\": 0, \n                    \"rtt\": 78382, \n                    \"rttvar\": 6, \n                    \"seconds\": 1.0000250339508057, \n                    \"sender\": true, \n                    \"snd_cwnd\": 16708472, \n                    \"snd_wnd\": -1, \n                    \"socket\": 5, \n                    \"start\": 11.000063\n                }\n            ], \n            \"sum\": {\n                \"bits_per_second\": 849325298.032271, \n                \"bytes\": 106168320, \n                \"end\": 12.000088, \n                \"omitted\": false, \n                \"retransmits\": 0, \n                \"seconds\": 1.0000250339508057, \n                \"sender\": true, \n                \"start\": 11.000063\n            }\n        }, \n        {\n            \"streams\": [\n                {\n                    \"bits_per_second\": 849276905.7127655, \n                    \"bytes\": 106168320, \n                    \"end\": 13.00017, \n                    \"omitted\": false, \n                    \"pmtu\": 1500, \n                    \"retransmits\": 0, \n                    \"rtt\": 78376, \n                    \"rttvar\": 10, \n                    \"seconds\": 1.000082015991211, \n                    \"sender\": true, \n                    \"snd_cwnd\": 16708472, \n                    \"snd_wnd\": -1, \n                    \"socket\": 5, \n                    \"start\": 12.000088\n                }\n            ], \n            \"sum\": {\n                \"bits_per_second\": 849276905.7127655, \n                \"bytes\": 106168320, \n                \"end\": 13.00017, \n                \"omitted\": false, \n                \"retransmits\": 0, \n                \"seconds\": 1.000082015991211, \n                \"sender\": true, \n                \"start\": 12.000088\n            }\n        }, \n        {\n            \"streams\": [\n                {\n                    \"bits_per_second\": 849414504.184817, \n                    \"bytes\": 106168320, \n                    \"end\": 14.00009, \n                    \"omitted\": false, \n                    \"pmtu\": 1500, \n                    \"retransmits\": 0, \n                    \"rtt\": 78383, \n                    \"rttvar\": 9, \n                    \"seconds\": 0.9999200105667114, \n                    \"sender\": true, \n                    \"snd_cwnd\": 16708472, \n                    \"snd_wnd\": -1, \n                    \"socket\": 5, \n                    \"start\": 13.00017\n                }\n            ], \n            \"sum\": {\n                \"bits_per_second\": 849414504.184817, \n                \"bytes\": 106168320, \n                \"end\": 14.00009, \n                \"omitted\": false, \n                \"retransmits\": 0, \n                \"seconds\": 0.9999200105667114, \n                \"sender\": true, \n                \"start\": 13.00017\n            }\n        }, \n        {\n            \"streams\": [\n                {\n                    \"bits_per_second\": 859835753.7637128, \n                    \"bytes\": 107479040, \n                    \"end\": 15.000086, \n                    \"omitted\": false, \n                    \"pmtu\": 1500, \n                    \"retransmits\": 0, \n                    \"rtt\": 78379, \n                    \"rttvar\": 12, \n                    \"seconds\": 0.9999960064888, \n                    \"sender\": true, \n                    \"snd_cwnd\": 16708472, \n                    \"snd_wnd\": -1, \n                    \"socket\": 5, \n                    \"start\": 14.00009\n                }\n            ], \n            \"sum\": {\n                \"bits_per_second\": 859835753.7637128, \n                \"bytes\": 107479040, \n                \"end\": 15.000086, \n                \"omitted\": false, \n                \"retransmits\": 0, \n                \"seconds\": 0.9999960064888, \n                \"sender\": true, \n                \"start\": 14.00009\n            }\n        }, \n        {\n            \"streams\": [\n                {\n                    \"bits_per_second\": 849349951.8885455, \n                    \"bytes\": 106168320, \n                    \"end\": 16.000082, \n                    \"omitted\": false, \n                    \"pmtu\": 1500, \n                    \"retransmits\": 0, \n                    \"rtt\": 78388, \n                    \"rttvar\": 13, \n                    \"seconds\": 0.9999960064888, \n                    \"sender\": true, \n                    \"snd_cwnd\": 16708472, \n                    \"snd_wnd\": -1, \n                    \"socket\": 5, \n                    \"start\": 15.000086\n                }\n            ], \n            \"sum\": {\n                \"bits_per_second\": 849349951.8885455, \n                \"bytes\": 106168320, \n                \"end\": 16.000082, \n                \"omitted\": false, \n                \"retransmits\": 0, \n                \"seconds\": 0.9999960064888, \n                \"sender\": true, \n                \"start\": 15.000086\n            }\n        }, \n        {\n            \"streams\": [\n                {\n                    \"bits_per_second\": 849344028.7575437, \n                    \"bytes\": 106168320, \n                    \"end\": 17.000085, \n                    \"omitted\": false, \n                    \"pmtu\": 1500, \n                    \"retransmits\": 0, \n                    \"rtt\": 78384, \n                    \"rttvar\": 12, \n                    \"seconds\": 1.0000029802322388, \n                    \"sender\": true, \n                    \"snd_cwnd\": 16708472, \n                    \"snd_wnd\": -1, \n                    \"socket\": 5, \n                    \"start\": 16.000082\n                }\n            ], \n            \"sum\": {\n                \"bits_per_second\": 849344028.7575437, \n                \"bytes\": 106168320, \n                \"end\": 17.000085, \n                \"omitted\": false, \n                \"retransmits\": 0, \n                \"seconds\": 1.0000029802322388, \n                \"sender\": true, \n                \"start\": 16.000082\n            }\n        }, \n        {\n            \"streams\": [\n                {\n                    \"bits_per_second\": 849349091.2575437, \n                    \"bytes\": 106168320, \n                    \"end\": 18.000082, \n                    \"omitted\": false, \n                    \"pmtu\": 1500, \n                    \"retransmits\": 0, \n                    \"rtt\": 78362, \n                    \"rttvar\": 12, \n                    \"seconds\": 0.9999970197677612, \n                    \"sender\": true, \n                    \"snd_cwnd\": 16708472, \n                    \"snd_wnd\": -1, \n                    \"socket\": 5, \n                    \"start\": 17.000085\n                }\n            ], \n            \"sum\": {\n                \"bits_per_second\": 849349091.2575437, \n                \"bytes\": 106168320, \n                \"end\": 18.000082, \n                \"omitted\": false, \n                \"retransmits\": 0, \n                \"seconds\": 0.9999970197677612, \n                \"sender\": true, \n                \"start\": 17.000085\n            }\n        }, \n        {\n            \"streams\": [\n                {\n                    \"bits_per_second\": 849281967.4126233, \n                    \"bytes\": 106168320, \n                    \"end\": 19.000158, \n                    \"omitted\": false, \n                    \"pmtu\": 1500, \n                    \"retransmits\": 0, \n                    \"rtt\": 78385, \n                    \"rttvar\": 8, \n                    \"seconds\": 1.0000760555267334, \n                    \"sender\": true, \n                    \"snd_cwnd\": 16708472, \n                    \"snd_wnd\": -1, \n                    \"socket\": 5, \n                    \"start\": 18.000082\n                }\n            ], \n            \"sum\": {\n                \"bits_per_second\": 849281967.4126233, \n                \"bytes\": 106168320, \n                \"end\": 19.000158, \n                \"omitted\": false, \n                \"retransmits\": 0, \n                \"seconds\": 1.0000760555267334, \n                \"sender\": true, \n                \"start\": 18.000082\n            }\n        }, \n        {\n            \"streams\": [\n                {\n                    \"bits_per_second\": 859914891.678787, \n                    \"bytes\": 107479040, \n                    \"end\": 20.000062, \n                    \"omitted\": false, \n                    \"pmtu\": 1500, \n                    \"retransmits\": 0, \n                    \"rtt\": 78386, \n                    \"rttvar\": 6, \n                    \"seconds\": 0.999903976917267, \n                    \"sender\": true, \n                    \"snd_cwnd\": 16708472, \n                    \"snd_wnd\": -1, \n                    \"socket\": 5, \n                    \"start\": 19.000158\n                }\n            ], \n            \"sum\": {\n                \"bits_per_second\": 859914891.678787, \n                \"bytes\": 107479040, \n                \"end\": 20.000062, \n                \"omitted\": false, \n                \"retransmits\": 0, \n                \"seconds\": 0.999903976917267, \n                \"sender\": true, \n                \"start\": 19.000158\n            }\n        }, \n        {\n            \"streams\": [\n                {\n                    \"bits_per_second\": 849334713.915223, \n                    \"bytes\": 106168320, \n                    \"end\": 21.000076, \n                    \"omitted\": false, \n                    \"pmtu\": 1500, \n                    \"retransmits\": 0, \n                    \"rtt\": 78376, \n                    \"rttvar\": 4, \n                    \"seconds\": 1.0000139474868774, \n                    \"sender\": true, \n                    \"snd_cwnd\": 16708472, \n                    \"snd_wnd\": -1, \n                    \"socket\": 5, \n                    \"start\": 20.000062\n                }\n            ], \n            \"sum\": {\n                \"bits_per_second\": 849334713.915223, \n                \"bytes\": 106168320, \n                \"end\": 21.000076, \n                \"omitted\": false, \n                \"retransmits\": 0, \n                \"seconds\": 1.0000139474868774, \n                \"sender\": true, \n                \"start\": 20.000062\n            }\n        }, \n        {\n            \"streams\": [\n                {\n                    \"bits_per_second\": 849285409.4029905, \n                    \"bytes\": 106168320, \n                    \"end\": 22.000148, \n                    \"omitted\": false, \n                    \"pmtu\": 1500, \n                    \"retransmits\": 0, \n                    \"rtt\": 78383, \n                    \"rttvar\": 6, \n                    \"seconds\": 1.0000720024108887, \n                    \"sender\": true, \n                    \"snd_cwnd\": 16708472, \n                    \"snd_wnd\": -1, \n                    \"socket\": 5, \n                    \"start\": 21.000076\n                }\n            ], \n            \"sum\": {\n                \"bits_per_second\": 849285409.4029905, \n                \"bytes\": 106168320, \n                \"end\": 22.000148, \n                \"omitted\": false, \n                \"retransmits\": 0, \n                \"seconds\": 1.0000720024108887, \n                \"sender\": true, \n                \"start\": 21.000076\n            }\n        }, \n        {\n            \"streams\": [\n                {\n                    \"bits_per_second\": 849347420.625872, \n                    \"bytes\": 106168320, \n                    \"end\": 23.000147, \n                    \"omitted\": false, \n                    \"pmtu\": 1500, \n                    \"retransmits\": 0, \n                    \"rtt\": 78387, \n                    \"rttvar\": 7, \n                    \"seconds\": 0.9999989867210388, \n                    \"sender\": true, \n                    \"snd_cwnd\": 16708472, \n                    \"snd_wnd\": -1, \n                    \"socket\": 5, \n                    \"start\": 22.000148\n                }\n            ], \n            \"sum\": {\n                \"bits_per_second\": 849347420.625872, \n                \"bytes\": 106168320, \n                \"end\": 23.000147, \n                \"omitted\": false, \n                \"retransmits\": 0, \n                \"seconds\": 0.9999989867210388, \n                \"sender\": true, \n                \"start\": 22.000148\n            }\n        }, \n        {\n            \"streams\": [\n                {\n                    \"bits_per_second\": 849401795.4668888, \n                    \"bytes\": 106168320, \n                    \"end\": 24.000082, \n                    \"omitted\": false, \n                    \"pmtu\": 1500, \n                    \"retransmits\": 0, \n                    \"rtt\": 78374, \n                    \"rttvar\": 9, \n                    \"seconds\": 0.99993497133255, \n                    \"sender\": true, \n                    \"snd_cwnd\": 16708472, \n                    \"snd_wnd\": -1, \n                    \"socket\": 5, \n                    \"start\": 23.000147\n                }\n            ], \n            \"sum\": {\n                \"bits_per_second\": 849401795.4668888, \n                \"bytes\": 106168320, \n                \"end\": 24.000082, \n                \"omitted\": false, \n                \"retransmits\": 0, \n                \"seconds\": 0.99993497133255, \n                \"sender\": true, \n                \"start\": 23.000147\n            }\n        }, \n        {\n            \"streams\": [\n                {\n                    \"bits_per_second\": 849366101.6996036, \n                    \"bytes\": 106168320, \n                    \"end\": 25.000059, \n                    \"omitted\": false, \n                    \"pmtu\": 1500, \n                    \"retransmits\": 0, \n                    \"rtt\": 78382, \n                    \"rttvar\": 5, \n                    \"seconds\": 0.9999769926071167, \n                    \"sender\": true, \n                    \"snd_cwnd\": 16708472, \n                    \"snd_wnd\": -1, \n                    \"socket\": 5, \n                    \"start\": 24.000082\n                }\n            ], \n            \"sum\": {\n                \"bits_per_second\": 849366101.6996036, \n                \"bytes\": 106168320, \n                \"end\": 25.000059, \n                \"omitted\": false, \n                \"retransmits\": 0, \n                \"seconds\": 0.9999769926071167, \n                \"sender\": true, \n                \"start\": 24.000082\n            }\n        }, \n        {\n            \"streams\": [\n                {\n                    \"bits_per_second\": 859809155.6240784, \n                    \"bytes\": 107479040, \n                    \"end\": 26.000086, \n                    \"omitted\": false, \n                    \"pmtu\": 1500, \n                    \"retransmits\": 0, \n                    \"rtt\": 78386, \n                    \"rttvar\": 6, \n                    \"seconds\": 1.0000269412994385, \n                    \"sender\": true, \n                    \"snd_cwnd\": 16708472, \n                    \"snd_wnd\": -1, \n                    \"socket\": 5, \n                    \"start\": 25.000059\n                }\n            ], \n            \"sum\": {\n                \"bits_per_second\": 859809155.6240784, \n                \"bytes\": 107479040, \n                \"end\": 26.000086, \n                \"omitted\": false, \n                \"retransmits\": 0, \n                \"seconds\": 1.0000269412994385, \n                \"sender\": true, \n                \"start\": 25.000059\n            }\n        }, \n        {\n            \"streams\": [\n                {\n                    \"bits_per_second\": 849276905.7127655, \n                    \"bytes\": 106168320, \n                    \"end\": 27.000168, \n                    \"omitted\": false, \n                    \"pmtu\": 1500, \n                    \"retransmits\": 0, \n                    \"rtt\": 78376, \n                    \"rttvar\": 10, \n                    \"seconds\": 1.000082015991211, \n                    \"sender\": true, \n                    \"snd_cwnd\": 16708472, \n                    \"snd_wnd\": -1, \n                    \"socket\": 5, \n                    \"start\": 26.000086\n                }\n            ], \n            \"sum\": {\n                \"bits_per_second\": 849276905.7127655, \n                \"bytes\": 106168320, \n                \"end\": 27.000168, \n                \"omitted\": false, \n                \"retransmits\": 0, \n                \"seconds\": 1.000082015991211, \n                \"sender\": true, \n                \"start\": 26.000086\n            }\n        }, \n        {\n            \"streams\": [\n                {\n                    \"bits_per_second\": 849411972.5373672, \n                    \"bytes\": 106168320, \n                    \"end\": 28.000091, \n                    \"omitted\": false, \n                    \"pmtu\": 1500, \n                    \"retransmits\": 0, \n                    \"rtt\": 78385, \n                    \"rttvar\": 6, \n                    \"seconds\": 0.9999229907989502, \n                    \"sender\": true, \n                    \"snd_cwnd\": 16708472, \n                    \"snd_wnd\": -1, \n                    \"socket\": 5, \n                    \"start\": 27.000168\n                }\n            ], \n            \"sum\": {\n                \"bits_per_second\": 849411972.5373672, \n                \"bytes\": 106168320, \n                \"end\": 28.000091, \n                \"omitted\": false, \n                \"retransmits\": 0, \n                \"seconds\": 0.9999229907989502, \n                \"sender\": true, \n                \"start\": 27.000168\n            }\n        }, \n        {\n            \"streams\": [\n                {\n                    \"bits_per_second\": 849338055.0851647, \n                    \"bytes\": 106168320, \n                    \"end\": 29.000101, \n                    \"omitted\": false, \n                    \"pmtu\": 1500, \n                    \"retransmits\": 0, \n                    \"rtt\": 78389, \n                    \"rttvar\": 11, \n                    \"seconds\": 1.0000100135803223, \n                    \"sender\": true, \n                    \"snd_cwnd\": 16708472, \n                    \"snd_wnd\": -1, \n                    \"socket\": 5, \n                    \"start\": 28.000091\n                }\n            ], \n            \"sum\": {\n                \"bits_per_second\": 849338055.0851647, \n                \"bytes\": 106168320, \n                \"end\": 29.000101, \n                \"omitted\": false, \n                \"retransmits\": 0, \n                \"seconds\": 1.0000100135803223, \n                \"sender\": true, \n                \"start\": 28.000091\n            }\n        }, \n        {\n            \"streams\": [\n                {\n                    \"bits_per_second\": 849352483.1663066, \n                    \"bytes\": 106168320, \n                    \"end\": 30.000094, \n                    \"omitted\": false, \n                    \"pmtu\": 1500, \n                    \"retransmits\": 0, \n                    \"rtt\": 78386, \n                    \"rttvar\": 16, \n                    \"seconds\": 0.9999930262565613, \n                    \"sender\": true, \n                    \"snd_cwnd\": 16708472, \n                    \"snd_wnd\": -1, \n                    \"socket\": 5, \n                    \"start\": 29.000101\n                }\n            ], \n            \"sum\": {\n                \"bits_per_second\": 849352483.1663066, \n                \"bytes\": 106168320, \n                \"end\": 30.000094, \n                \"omitted\": false, \n                \"retransmits\": 0, \n                \"seconds\": 0.9999930262565613, \n                \"sender\": true, \n                \"start\": 29.000101\n            }\n        }, \n        {\n            \"streams\": [\n                {\n                    \"bits_per_second\": 849272653.9315116, \n                    \"bytes\": 106168320, \n                    \"end\": 31.000181, \n                    \"omitted\": false, \n                    \"pmtu\": 1500, \n                    \"retransmits\": 0, \n                    \"rtt\": 78383, \n                    \"rttvar\": 8, \n                    \"seconds\": 1.000087022781372, \n                    \"sender\": true, \n                    \"snd_cwnd\": 16708472, \n                    \"snd_wnd\": -1, \n                    \"socket\": 5, \n                    \"start\": 30.000094\n                }\n            ], \n            \"sum\": {\n                \"bits_per_second\": 849272653.9315116, \n                \"bytes\": 106168320, \n                \"end\": 31.000181, \n                \"omitted\": false, \n                \"retransmits\": 0, \n                \"seconds\": 1.000087022781372, \n                \"sender\": true, \n                \"start\": 30.000094\n            }\n        }, \n        {\n            \"streams\": [\n                {\n                    \"bits_per_second\": 859933806.9772085, \n                    \"bytes\": 107479040, \n                    \"end\": 32.000063, \n                    \"omitted\": false, \n                    \"pmtu\": 1500, \n                    \"retransmits\": 0, \n                    \"rtt\": 78387, \n                    \"rttvar\": 9, \n                    \"seconds\": 0.9998819828033447, \n                    \"sender\": true, \n                    \"snd_cwnd\": 16708472, \n                    \"snd_wnd\": -1, \n                    \"socket\": 5, \n                    \"start\": 31.000181\n                }\n            ], \n            \"sum\": {\n                \"bits_per_second\": 859933806.9772085, \n                \"bytes\": 107479040, \n                \"end\": 32.000063, \n                \"omitted\": false, \n                \"retransmits\": 0, \n                \"seconds\": 0.9998819828033447, \n                \"sender\": true, \n                \"start\": 31.000181\n            }\n        }, \n        {\n            \"streams\": [\n                {\n                    \"bits_per_second\": 849344838.7534882, \n                    \"bytes\": 106168320, \n                    \"end\": 33.000065, \n                    \"omitted\": false, \n                    \"pmtu\": 1500, \n                    \"retransmits\": 0, \n                    \"rtt\": 78380, \n                    \"rttvar\": 11, \n                    \"seconds\": 1.0000020265579224, \n                    \"sender\": true, \n                    \"snd_cwnd\": 16708472, \n                    \"snd_wnd\": -1, \n                    \"socket\": 5, \n                    \"start\": 32.000063\n                }\n            ], \n            \"sum\": {\n                \"bits_per_second\": 849344838.7534882, \n                \"bytes\": 106168320, \n                \"end\": 33.000065, \n                \"omitted\": false, \n                \"retransmits\": 0, \n                \"seconds\": 1.0000020265579224, \n                \"sender\": true, \n                \"start\": 32.000063\n            }\n        }, \n        {\n            \"streams\": [\n                {\n                    \"bits_per_second\": 849347420.625872, \n                    \"bytes\": 106168320, \n                    \"end\": 34.000064, \n                    \"omitted\": false, \n                    \"pmtu\": 1500, \n                    \"retransmits\": 0, \n                    \"rtt\": 78383, \n                    \"rttvar\": 3, \n                    \"seconds\": 0.9999989867210388, \n                    \"sender\": true, \n                    \"snd_cwnd\": 16708472, \n                    \"snd_wnd\": -1, \n                    \"socket\": 5, \n                    \"start\": 33.000065\n                }\n            ], \n            \"sum\": {\n                \"bits_per_second\": 849347420.625872, \n                \"bytes\": 106168320, \n                \"end\": 34.000064, \n                \"omitted\": false, \n                \"retransmits\": 0, \n                \"seconds\": 0.9999989867210388, \n                \"sender\": true, \n                \"start\": 33.000065\n            }\n        }, \n        {\n            \"streams\": [\n                {\n                    \"bits_per_second\": 849319425.8668838, \n                    \"bytes\": 106168320, \n                    \"end\": 35.000096, \n                    \"omitted\": false, \n                    \"pmtu\": 1500, \n                    \"retransmits\": 0, \n                    \"rtt\": 78378, \n                    \"rttvar\": 11, \n                    \"seconds\": 1.0000319480895996, \n                    \"sender\": true, \n                    \"snd_cwnd\": 16708472, \n                    \"snd_wnd\": -1, \n                    \"socket\": 5, \n                    \"start\": 34.000064\n                }\n            ], \n            \"sum\": {\n                \"bits_per_second\": 849319425.8668838, \n                \"bytes\": 106168320, \n                \"end\": 35.000096, \n                \"omitted\": false, \n                \"retransmits\": 0, \n                \"seconds\": 1.0000319480895996, \n                \"sender\": true, \n                \"start\": 34.000064\n            }\n        }, \n        {\n            \"streams\": [\n                {\n                    \"bits_per_second\": 849368633.0736268, \n                    \"bytes\": 106168320, \n                    \"end\": 36.00007, \n                    \"omitted\": false, \n                    \"pmtu\": 1500, \n                    \"retransmits\": 0, \n                    \"rtt\": 78384, \n                    \"rttvar\": 5, \n                    \"seconds\": 0.999974012374878, \n                    \"sender\": true, \n                    \"snd_cwnd\": 16708472, \n                    \"snd_wnd\": -1, \n                    \"socket\": 5, \n                    \"start\": 35.000096\n                }\n            ], \n            \"sum\": {\n                \"bits_per_second\": 849368633.0736268, \n                \"bytes\": 106168320, \n                \"end\": 36.00007, \n                \"omitted\": false, \n                \"retransmits\": 0, \n                \"seconds\": 0.999974012374878, \n                \"sender\": true, \n                \"start\": 35.000096\n            }\n        }, \n        {\n            \"streams\": [\n                {\n                    \"bits_per_second\": 849334713.915223, \n                    \"bytes\": 106168320, \n                    \"end\": 37.000084, \n                    \"omitted\": false, \n                    \"pmtu\": 1500, \n                    \"retransmits\": 0, \n                    \"rtt\": 78389, \n                    \"rttvar\": 5, \n                    \"seconds\": 1.0000139474868774, \n                    \"sender\": true, \n                    \"snd_cwnd\": 16708472, \n                    \"snd_wnd\": -1, \n                    \"socket\": 5, \n                    \"start\": 36.00007\n                }\n            ], \n            \"sum\": {\n                \"bits_per_second\": 849334713.915223, \n                \"bytes\": 106168320, \n                \"end\": 37.000084, \n                \"omitted\": false, \n                \"retransmits\": 0, \n                \"seconds\": 1.0000139474868774, \n                \"sender\": true, \n                \"start\": 36.00007\n            }\n        }, \n        {\n            \"streams\": [\n                {\n                    \"bits_per_second\": 859828835.014125, \n                    \"bytes\": 107479040, \n                    \"end\": 38.000088, \n                    \"omitted\": false, \n                    \"pmtu\": 1500, \n                    \"retransmits\": 0, \n                    \"rtt\": 78386, \n                    \"rttvar\": 8, \n                    \"seconds\": 1.0000040531158447, \n                    \"sender\": true, \n                    \"snd_cwnd\": 16708472, \n                    \"snd_wnd\": -1, \n                    \"socket\": 5, \n                    \"start\": 37.000084\n                }\n            ], \n            \"sum\": {\n                \"bits_per_second\": 859828835.014125, \n                \"bytes\": 107479040, \n                \"end\": 38.000088, \n                \"omitted\": false, \n                \"retransmits\": 0, \n                \"seconds\": 1.0000040531158447, \n                \"sender\": true, \n                \"start\": 37.000084\n            }\n        }, \n        {\n            \"streams\": [\n                {\n                    \"bits_per_second\": 849344838.7534882, \n                    \"bytes\": 106168320, \n                    \"end\": 39.00009, \n                    \"omitted\": false, \n                    \"pmtu\": 1500, \n                    \"retransmits\": 0, \n                    \"rtt\": 78384, \n                    \"rttvar\": 12, \n                    \"seconds\": 1.0000020265579224, \n                    \"sender\": true, \n                    \"snd_cwnd\": 16708472, \n                    \"snd_wnd\": -1, \n                    \"socket\": 5, \n                    \"start\": 38.000088\n                }\n            ], \n            \"sum\": {\n                \"bits_per_second\": 849344838.7534882, \n                \"bytes\": 106168320, \n                \"end\": 39.00009, \n                \"omitted\": false, \n                \"retransmits\": 0, \n                \"seconds\": 1.0000020265579224, \n                \"sender\": true, \n                \"start\": 38.000088\n            }\n        }, \n        {\n            \"streams\": [\n                {\n                    \"bits_per_second\": 849293913.2635096, \n                    \"bytes\": 106168320, \n                    \"end\": 40.000152, \n                    \"omitted\": false, \n                    \"pmtu\": 1500, \n                    \"retransmits\": 0, \n                    \"rtt\": 78390, \n                    \"rttvar\": 15, \n                    \"seconds\": 1.0000619888305664, \n                    \"sender\": true, \n                    \"snd_cwnd\": 16708472, \n                    \"snd_wnd\": -1, \n                    \"socket\": 5, \n                    \"start\": 39.00009\n                }\n            ], \n            \"sum\": {\n                \"bits_per_second\": 849293913.2635096, \n                \"bytes\": 106168320, \n                \"end\": 40.000152, \n                \"omitted\": false, \n                \"retransmits\": 0, \n                \"seconds\": 1.0000619888305664, \n                \"sender\": true, \n                \"start\": 39.00009\n            }\n        }, \n        {\n            \"streams\": [\n                {\n                    \"bits_per_second\": 849405187.7966182, \n                    \"bytes\": 106168320, \n                    \"end\": 41.000083, \n                    \"omitted\": false, \n                    \"pmtu\": 1500, \n                    \"retransmits\": 0, \n                    \"rtt\": 78382, \n                    \"rttvar\": 6, \n                    \"seconds\": 0.99993097782135, \n                    \"sender\": true, \n                    \"snd_cwnd\": 16708472, \n                    \"snd_wnd\": -1, \n                    \"socket\": 5, \n                    \"start\": 40.000152\n                }\n            ], \n            \"sum\": {\n                \"bits_per_second\": 849405187.7966182, \n                \"bytes\": 106168320, \n                \"end\": 41.000083, \n                \"omitted\": false, \n                \"retransmits\": 0, \n                \"seconds\": 0.99993097782135, \n                \"sender\": true, \n                \"start\": 40.000152\n            }\n        }, \n        {\n            \"streams\": [\n                {\n                    \"bits_per_second\": 849268402.1928295, \n                    \"bytes\": 106168320, \n                    \"end\": 42.000175, \n                    \"omitted\": false, \n                    \"pmtu\": 1500, \n                    \"retransmits\": 0, \n                    \"rtt\": 78384, \n                    \"rttvar\": 6, \n                    \"seconds\": 1.0000920295715332, \n                    \"sender\": true, \n                    \"snd_cwnd\": 16708472, \n                    \"snd_wnd\": -1, \n                    \"socket\": 5, \n                    \"start\": 41.000083\n                }\n            ], \n            \"sum\": {\n                \"bits_per_second\": 849268402.1928295, \n                \"bytes\": 106168320, \n                \"end\": 42.000175, \n                \"omitted\": false, \n                \"retransmits\": 0, \n                \"seconds\": 1.0000920295715332, \n                \"sender\": true, \n                \"start\": 41.000083\n            }\n        }, \n        {\n            \"streams\": [\n                {\n                    \"bits_per_second\": 859928629.5363914, \n                    \"bytes\": 107479040, \n                    \"end\": 43.000063, \n                    \"omitted\": false, \n                    \"pmtu\": 1500, \n                    \"retransmits\": 0, \n                    \"rtt\": 78385, \n                    \"rttvar\": 6, \n                    \"seconds\": 0.999888002872467, \n                    \"sender\": true, \n                    \"snd_cwnd\": 16708472, \n                    \"snd_wnd\": -1, \n                    \"socket\": 5, \n                    \"start\": 42.000175\n                }\n            ], \n            \"sum\": {\n                \"bits_per_second\": 859928629.5363914, \n                \"bytes\": 107479040, \n                \"end\": 43.000063, \n                \"omitted\": false, \n                \"retransmits\": 0, \n                \"seconds\": 0.999888002872467, \n                \"sender\": true, \n                \"start\": 42.000175\n            }\n        }, \n        {\n            \"streams\": [\n                {\n                    \"bits_per_second\": 849345750.0007725, \n                    \"bytes\": 106168320, \n                    \"end\": 44.000064, \n                    \"omitted\": false, \n                    \"pmtu\": 1500, \n                    \"retransmits\": 0, \n                    \"rtt\": 78381, \n                    \"rttvar\": 7, \n                    \"seconds\": 1.0000009536743164, \n                    \"sender\": true, \n                    \"snd_cwnd\": 16708472, \n                    \"snd_wnd\": -1, \n                    \"socket\": 5, \n                    \"start\": 43.000063\n                }\n            ], \n            \"sum\": {\n                \"bits_per_second\": 849345750.0007725, \n                \"bytes\": 106168320, \n                \"end\": 44.000064, \n                \"omitted\": false, \n                \"retransmits\": 0, \n                \"seconds\": 1.0000009536743164, \n                \"sender\": true, \n                \"start\": 43.000063\n            }\n        }, \n        {\n            \"streams\": [\n                {\n                    \"bits_per_second\": 849271844.0732424, \n                    \"bytes\": 106168320, \n                    \"end\": 45.000152, \n                    \"omitted\": false, \n                    \"pmtu\": 1500, \n                    \"retransmits\": 0, \n                    \"rtt\": 78386, \n                    \"rttvar\": 7, \n                    \"seconds\": 1.0000879764556885, \n                    \"sender\": true, \n                    \"snd_cwnd\": 16708472, \n                    \"snd_wnd\": -1, \n                    \"socket\": 5, \n                    \"start\": 44.000064\n                }\n            ], \n            \"sum\": {\n                \"bits_per_second\": 849271844.0732424, \n                \"bytes\": 106168320, \n                \"end\": 45.000152, \n                \"omitted\": false, \n                \"retransmits\": 0, \n                \"seconds\": 1.0000879764556885, \n                \"sender\": true, \n                \"start\": 44.000064\n            }\n        }, \n        {\n            \"streams\": [\n                {\n                    \"bits_per_second\": 849340586.2920152, \n                    \"bytes\": 106168320, \n                    \"end\": 46.000159, \n                    \"omitted\": false, \n                    \"pmtu\": 1500, \n                    \"retransmits\": 0, \n                    \"rtt\": 78387, \n                    \"rttvar\": 8, \n                    \"seconds\": 1.0000070333480835, \n                    \"sender\": true, \n                    \"snd_cwnd\": 16708472, \n                    \"snd_wnd\": -1, \n                    \"socket\": 5, \n                    \"start\": 45.000152\n                }\n            ], \n            \"sum\": {\n                \"bits_per_second\": 849340586.2920152, \n                \"bytes\": 106168320, \n                \"end\": 46.000159, \n                \"omitted\": false, \n                \"retransmits\": 0, \n                \"seconds\": 1.0000070333480835, \n                \"sender\": true, \n                \"start\": 45.000152\n            }\n        }, \n        {\n            \"streams\": [\n                {\n                    \"bits_per_second\": 849422149.8517208, \n                    \"bytes\": 106168320, \n                    \"end\": 47.00007, \n                    \"omitted\": false, \n                    \"pmtu\": 1500, \n                    \"retransmits\": 0, \n                    \"rtt\": 78386, \n                    \"rttvar\": 10, \n                    \"seconds\": 0.9999110102653503, \n                    \"sender\": true, \n                    \"snd_cwnd\": 16708472, \n                    \"snd_wnd\": -1, \n                    \"socket\": 5, \n                    \"start\": 46.000159\n                }\n            ], \n            \"sum\": {\n                \"bits_per_second\": 849422149.8517208, \n                \"bytes\": 106168320, \n                \"end\": 47.00007, \n                \"omitted\": false, \n                \"retransmits\": 0, \n                \"seconds\": 0.9999110102653503, \n                \"sender\": true, \n                \"start\": 46.000159\n            }\n        }, \n        {\n            \"streams\": [\n                {\n                    \"bits_per_second\": 849265871.4162065, \n                    \"bytes\": 106168320, \n                    \"end\": 48.000165, \n                    \"omitted\": false, \n                    \"pmtu\": 1500, \n                    \"retransmits\": 0, \n                    \"rtt\": 78385, \n                    \"rttvar\": 7, \n                    \"seconds\": 1.000095009803772, \n                    \"sender\": true, \n                    \"snd_cwnd\": 16708472, \n                    \"snd_wnd\": -1, \n                    \"socket\": 5, \n                    \"start\": 47.00007\n                }\n            ], \n            \"sum\": {\n                \"bits_per_second\": 849265871.4162065, \n                \"bytes\": 106168320, \n                \"end\": 48.000165, \n                \"omitted\": false, \n                \"retransmits\": 0, \n                \"seconds\": 1.000095009803772, \n                \"sender\": true, \n                \"start\": 47.00007\n            }\n        }, \n        {\n            \"streams\": [\n                {\n                    \"bits_per_second\": 859902845.784242, \n                    \"bytes\": 107479040, \n                    \"end\": 49.000083, \n                    \"omitted\": false, \n                    \"pmtu\": 1500, \n                    \"retransmits\": 0, \n                    \"rtt\": 78387, \n                    \"rttvar\": 9, \n                    \"seconds\": 0.999917984008789, \n                    \"sender\": true, \n                    \"snd_cwnd\": 16708472, \n                    \"snd_wnd\": -1, \n                    \"socket\": 5, \n                    \"start\": 48.000165\n                }\n            ], \n            \"sum\": {\n                \"bits_per_second\": 859902845.784242, \n                \"bytes\": 107479040, \n                \"end\": 49.000083, \n                \"omitted\": false, \n                \"retransmits\": 0, \n                \"seconds\": 0.999917984008789, \n                \"sender\": true, \n                \"start\": 48.000165\n            }\n        }, \n        {\n            \"streams\": [\n                {\n                    \"bits_per_second\": 849285409.4029905, \n                    \"bytes\": 106168320, \n                    \"end\": 50.000155, \n                    \"omitted\": false, \n                    \"pmtu\": 1500, \n                    \"retransmits\": 0, \n                    \"rtt\": 78388, \n                    \"rttvar\": 5, \n                    \"seconds\": 1.0000720024108887, \n                    \"sender\": true, \n                    \"snd_cwnd\": 16708472, \n                    \"snd_wnd\": -1, \n                    \"socket\": 5, \n                    \"start\": 49.000083\n                }\n            ], \n            \"sum\": {\n                \"bits_per_second\": 849285409.4029905, \n                \"bytes\": 106168320, \n                \"end\": 50.000155, \n                \"omitted\": false, \n                \"retransmits\": 0, \n                \"seconds\": 1.0000720024108887, \n                \"sender\": true, \n                \"start\": 49.000083\n            }\n        }, \n        {\n            \"streams\": [\n                {\n                    \"bits_per_second\": 849349951.8885455, \n                    \"bytes\": 106168320, \n                    \"end\": 51.000151, \n                    \"omitted\": false, \n                    \"pmtu\": 1500, \n                    \"retransmits\": 0, \n                    \"rtt\": 78394, \n                    \"rttvar\": 7, \n                    \"seconds\": 0.9999960064888, \n                    \"sender\": true, \n                    \"snd_cwnd\": 16708472, \n                    \"snd_wnd\": -1, \n                    \"socket\": 5, \n                    \"start\": 50.000155\n                }\n            ], \n            \"sum\": {\n                \"bits_per_second\": 849349951.8885455, \n                \"bytes\": 106168320, \n                \"end\": 51.000151, \n                \"omitted\": false, \n                \"retransmits\": 0, \n                \"seconds\": 0.9999960064888, \n                \"sender\": true, \n                \"start\": 50.000155\n            }\n        }, \n        {\n            \"streams\": [\n                {\n                    \"bits_per_second\": 849397542.4350615, \n                    \"bytes\": 106168320, \n                    \"end\": 52.000091, \n                    \"omitted\": false, \n                    \"pmtu\": 1500, \n                    \"retransmits\": 0, \n                    \"rtt\": 78382, \n                    \"rttvar\": 9, \n                    \"seconds\": 0.9999399781227112, \n                    \"sender\": true, \n                    \"snd_cwnd\": 16708472, \n                    \"snd_wnd\": -1, \n                    \"socket\": 5, \n                    \"start\": 51.000151\n                }\n            ], \n            \"sum\": {\n                \"bits_per_second\": 849397542.4350615, \n                \"bytes\": 106168320, \n                \"end\": 52.000091, \n                \"omitted\": false, \n                \"retransmits\": 0, \n                \"seconds\": 0.9999399781227112, \n                \"sender\": true, \n                \"start\": 51.000151\n            }\n        }, \n        {\n            \"streams\": [\n                {\n                    \"bits_per_second\": 849277816.814287, \n                    \"bytes\": 106168320, \n                    \"end\": 53.000172, \n                    \"omitted\": false, \n                    \"pmtu\": 1500, \n                    \"retransmits\": 0, \n                    \"rtt\": 78394, \n                    \"rttvar\": 8, \n                    \"seconds\": 1.000080943107605, \n                    \"sender\": true, \n                    \"snd_cwnd\": 16708472, \n                    \"snd_wnd\": -1, \n                    \"socket\": 5, \n                    \"start\": 52.000091\n                }\n            ], \n            \"sum\": {\n                \"bits_per_second\": 849277816.814287, \n                \"bytes\": 106168320, \n                \"end\": 53.000172, \n                \"omitted\": false, \n                \"retransmits\": 0, \n                \"seconds\": 1.000080943107605, \n                \"sender\": true, \n                \"start\": 52.000091\n            }\n        }, \n        {\n            \"streams\": [\n                {\n                    \"bits_per_second\": 859809975.5806783, \n                    \"bytes\": 107479040, \n                    \"end\": 54.000198, \n                    \"omitted\": false, \n                    \"pmtu\": 1500, \n                    \"retransmits\": 0, \n                    \"rtt\": 78384, \n                    \"rttvar\": 8, \n                    \"seconds\": 1.000025987625122, \n                    \"sender\": true, \n                    \"snd_cwnd\": 16708472, \n                    \"snd_wnd\": -1, \n                    \"socket\": 5, \n                    \"start\": 53.000172\n                }\n            ], \n            \"sum\": {\n                \"bits_per_second\": 859809975.5806783, \n                \"bytes\": 107479040, \n                \"end\": 54.000198, \n                \"omitted\": false, \n                \"retransmits\": 0, \n                \"seconds\": 1.000025987625122, \n                \"sender\": true, \n                \"start\": 53.000172\n            }\n        }, \n        {\n            \"streams\": [\n                {\n                    \"bits_per_second\": 849438302.408512, \n                    \"bytes\": 106168320, \n                    \"end\": 55.00009, \n                    \"omitted\": false, \n                    \"pmtu\": 1500, \n                    \"retransmits\": 0, \n                    \"rtt\": 78383, \n                    \"rttvar\": 4, \n                    \"seconds\": 0.999891996383667, \n                    \"sender\": true, \n                    \"snd_cwnd\": 16708472, \n                    \"snd_wnd\": -1, \n                    \"socket\": 5, \n                    \"start\": 54.000198\n                }\n            ], \n            \"sum\": {\n                \"bits_per_second\": 849438302.408512, \n                \"bytes\": 106168320, \n                \"end\": 55.00009, \n                \"omitted\": false, \n                \"retransmits\": 0, \n                \"seconds\": 0.999891996383667, \n                \"sender\": true, \n                \"start\": 54.000198\n            }\n        }, \n        {\n            \"streams\": [\n                {\n                    \"bits_per_second\": 849358457.041643, \n                    \"bytes\": 106168320, \n                    \"end\": 56.000076, \n                    \"omitted\": false, \n                    \"pmtu\": 1500, \n                    \"retransmits\": 0, \n                    \"rtt\": 78383, \n                    \"rttvar\": 8, \n                    \"seconds\": 0.9999859929084778, \n                    \"sender\": true, \n                    \"snd_cwnd\": 16708472, \n                    \"snd_wnd\": -1, \n                    \"socket\": 5, \n                    \"start\": 55.00009\n                }\n            ], \n            \"sum\": {\n                \"bits_per_second\": 849358457.041643, \n                \"bytes\": 106168320, \n                \"end\": 56.000076, \n                \"omitted\": false, \n                \"retransmits\": 0, \n                \"seconds\": 0.9999859929084778, \n                \"sender\": true, \n                \"start\": 55.00009\n            }\n        }, \n        {\n            \"streams\": [\n                {\n                    \"bits_per_second\": 849260809.9082098, \n                    \"bytes\": 106168320, \n                    \"end\": 57.000177, \n                    \"omitted\": false, \n                    \"pmtu\": 1500, \n                    \"retransmits\": 0, \n                    \"rtt\": 78386, \n                    \"rttvar\": 6, \n                    \"seconds\": 1.0001009702682495, \n                    \"sender\": true, \n                    \"snd_cwnd\": 16708472, \n                    \"snd_wnd\": -1, \n                    \"socket\": 5, \n                    \"start\": 56.000076\n                }\n            ], \n            \"sum\": {\n                \"bits_per_second\": 849260809.9082098, \n                \"bytes\": 106168320, \n                \"end\": 57.000177, \n                \"omitted\": false, \n                \"retransmits\": 0, \n                \"seconds\": 1.0001009702682495, \n                \"sender\": true, \n                \"start\": 56.000076\n            }\n        }, \n        {\n            \"streams\": [\n                {\n                    \"bits_per_second\": 849444226.854477, \n                    \"bytes\": 106168320, \n                    \"end\": 58.000062, \n                    \"omitted\": false, \n                    \"pmtu\": 1500, \n                    \"retransmits\": 0, \n                    \"rtt\": 78384, \n                    \"rttvar\": 5, \n                    \"seconds\": 0.9998850226402283, \n                    \"sender\": true, \n                    \"snd_cwnd\": 16708472, \n                    \"snd_wnd\": -1, \n                    \"socket\": 5, \n                    \"start\": 57.000177\n                }\n            ], \n            \"sum\": {\n                \"bits_per_second\": 849444226.854477, \n                \"bytes\": 106168320, \n                \"end\": 58.000062, \n                \"omitted\": false, \n                \"retransmits\": 0, \n                \"seconds\": 0.9998850226402283, \n                \"sender\": true, \n                \"start\": 57.000177\n            }\n        }, \n        {\n            \"streams\": [\n                {\n                    \"bits_per_second\": 849320235.8159027, \n                    \"bytes\": 106168320, \n                    \"end\": 59.000093, \n                    \"omitted\": false, \n                    \"pmtu\": 1500, \n                    \"retransmits\": 0, \n                    \"rtt\": 78385, \n                    \"rttvar\": 6, \n                    \"seconds\": 1.0000309944152832, \n                    \"sender\": true, \n                    \"snd_cwnd\": 16708472, \n                    \"snd_wnd\": -1, \n                    \"socket\": 5, \n                    \"start\": 58.000062\n                }\n            ], \n            \"sum\": {\n                \"bits_per_second\": 849320235.8159027, \n                \"bytes\": 106168320, \n                \"end\": 59.000093, \n                \"omitted\": false, \n                \"retransmits\": 0, \n                \"seconds\": 1.0000309944152832, \n                \"sender\": true, \n                \"start\": 58.000062\n            }\n        }, \n        {\n            \"streams\": [\n                {\n                    \"bits_per_second\": 859834062.5035313, \n                    \"bytes\": 107479040, \n                    \"end\": 60.000091, \n                    \"omitted\": false, \n                    \"pmtu\": 1500, \n                    \"retransmits\": 0, \n                    \"rtt\": 78381, \n                    \"rttvar\": 8, \n                    \"seconds\": 0.9999979734420776, \n                    \"sender\": true, \n                    \"snd_cwnd\": 16708472, \n                    \"snd_wnd\": -1, \n                    \"socket\": 5, \n                    \"start\": 59.000093\n                }\n            ], \n            \"sum\": {\n                \"bits_per_second\": 859834062.5035313, \n                \"bytes\": 107479040, \n                \"end\": 60.000091, \n                \"omitted\": false, \n                \"retransmits\": 0, \n                \"seconds\": 0.9999979734420776, \n                \"sender\": true, \n                \"start\": 59.000093\n            }\n        }\n    ], \n    \"start\": {\n        \"connected\": [\n            {\n                \"local_host\": \"10.0.0.1\", \n                \"local_port\": 55685, \n                \"remote_host\": \"10.0.0.2\", \n                \"remote_port\": 5201, \n                \"socket\": 5\n            }\n        ], \n        \"connecting_to\": {\n            \"host\": \"10.0.0.2\", \n            \"port\": 5201\n        }, \n        \"cookie\": \"qcsonshflnxz3r2yxy3crkekqj4s5aocb32z\", \n        \"fq_rate\": 0, \n        \"rcvbuf_actual\": 87380, \n        \"sndbuf_actual\": 87380, \n        \"sock_bufsize\": 0, \n        \"system_info\": \"REDACTED\", \n        \"target_bitrate\": 0, \n        \"tcp_mss_default\": 1448, \n        \"test_start\": {\n            \"bidir\": 0, \n            \"blksize\": 131072, \n            \"blocks\": 0, \n            \"bytes\": 0, \n            \"duration\": 60, \n            \"fqrate\": 0, \n            \"num_streams\": 1, \n            \"omit\": 0, \n            \"protocol\": \"TCP\", \n            \"reverse\": 0, \n            \"target_bitrate\": 0, \n            \"tos\": 0\n        }, \n        \"timestamp\": {\n            \"time\": \"Tue, 16 Apr 2024 22:55:47 GMT\", \n            \"timesecs\": 1713308147\n        }, \n        \"version\": \"iperf 3.14\"\n    }\n}\nParticipant 1:\n/usr/bin/iperf3 -s -1 --idle-timeout 60 --json -p 5201 -B 10.0.0.2 --authorized-users-path /var/run/pscheduler-server/runner/tmp/tmp164afbgf/tmppxzrpxdd/credentials --rsa-private-key-path /var/run/pscheduler-server/runner/tmp/tmp164afbgf/tmppxzrpxdd/private-key\n\n{\n    \"end\": {\n        \"cpu_utilization_percent\": {\n            \"host_system\": 4.855504737877567, \n            \"host_total\": 5.23795283581219, \n            \"host_user\": 0.3824447689265594, \n            \"remote_system\": 0, \n            \"remote_total\": 0, \n            \"remote_user\": 0\n        }, \n        \"receiver_tcp_congestion\": \"htcp\", \n        \"streams\": [\n            {\n                \"receiver\": {\n                    \"bits_per_second\": 851136547.601172, \n                    \"bytes\": 6391816624, \n                    \"end\": 60.077943, \n                    \"seconds\": 60.077943, \n                    \"sender\": false, \n                    \"socket\": 5, \n                    \"start\": 0\n                }, \n                \"sender\": {\n                    \"bits_per_second\": 0, \n                    \"bytes\": 0, \n                    \"end\": 60.077943, \n                    \"seconds\": 60.077943, \n                    \"sender\": false, \n                    \"socket\": 5, \n                    \"start\": 0\n                }\n            }\n        ], \n        \"sum_received\": {\n            \"bits_per_second\": 851136547.601172, \n            \"bytes\": 6391816624, \n            \"end\": 60.077943, \n            \"seconds\": 60.077943, \n            \"sender\": false, \n            \"start\": 0\n        }, \n        \"sum_sent\": {\n            \"bits_per_second\": 0, \n            \"bytes\": 0, \n            \"end\": 60.077943, \n            \"seconds\": 60.077943, \n            \"sender\": false, \n            \"start\": 0\n        }\n    }, \n    \"intervals\": [\n        {\n            \"streams\": [\n                {\n                    \"bits_per_second\": 847120967.8393652, \n                    \"bytes\": 105896584, \n                    \"end\": 1.000061, \n                    \"omitted\": false, \n                    \"seconds\": 1.00006103515625, \n                    \"sender\": false, \n                    \"socket\": 5, \n                    \"start\": 0\n                }\n            ], \n            \"sum\": {\n                \"bits_per_second\": 847120967.8393652, \n                \"bytes\": 105896584, \n                \"end\": 1.000061, \n                \"omitted\": false, \n                \"seconds\": 1.00006103515625, \n                \"sender\": false, \n                \"start\": 0\n            }\n        }, \n        {\n            \"streams\": [\n                {\n                    \"bits_per_second\": 851273225.146701, \n                    \"bytes\": 106406280, \n                    \"end\": 2.000034, \n                    \"omitted\": false, \n                    \"seconds\": 0.9999729990959167, \n                    \"sender\": false, \n                    \"socket\": 5, \n                    \"start\": 1.000061\n                }\n            ], \n            \"sum\": {\n                \"bits_per_second\": 851273225.146701, \n                \"bytes\": 106406280, \n                \"end\": 2.000034, \n                \"omitted\": false, \n                \"seconds\": 0.9999729990959167, \n                \"sender\": false, \n                \"start\": 1.000061\n            }\n        }, \n        {\n            \"streams\": [\n                {\n                    \"bits_per_second\": 851202548.511996, \n                    \"bytes\": 106406280, \n                    \"end\": 3.00009, \n                    \"omitted\": false, \n                    \"seconds\": 1.0000560283660889, \n                    \"sender\": false, \n                    \"socket\": 5, \n                    \"start\": 2.000034\n                }\n            ], \n            \"sum\": {\n                \"bits_per_second\": 851202548.511996, \n                \"bytes\": 106406280, \n                \"end\": 3.00009, \n                \"omitted\": false, \n                \"seconds\": 1.0000560283660889, \n                \"sender\": false, \n                \"start\": 2.000034\n            }\n        }, \n        {\n            \"streams\": [\n                {\n                    \"bits_per_second\": 850733219.442713, \n                    \"bytes\": 106341120, \n                    \"end\": 4.000085, \n                    \"omitted\": false, \n                    \"seconds\": 0.999994993209839, \n                    \"sender\": false, \n                    \"socket\": 5, \n                    \"start\": 3.00009\n                }\n            ], \n            \"sum\": {\n                \"bits_per_second\": 850733219.442713, \n                \"bytes\": 106341120, \n                \"end\": 4.000085, \n                \"omitted\": false, \n                \"seconds\": 0.999994993209839, \n                \"sender\": false, \n                \"start\": 3.00009\n            }\n        }, \n        {\n            \"streams\": [\n                {\n                    \"bits_per_second\": 851251965.111414, \n                    \"bytes\": 106406280, \n                    \"end\": 5.000083, \n                    \"omitted\": false, \n                    \"seconds\": 0.9999979734420776, \n                    \"sender\": false, \n                    \"socket\": 5, \n                    \"start\": 4.000085\n                }\n            ], \n            \"sum\": {\n                \"bits_per_second\": 851251965.111414, \n                \"bytes\": 106406280, \n                \"end\": 5.000083, \n                \"omitted\": false, \n                \"seconds\": 0.9999979734420776, \n                \"sender\": false, \n                \"start\": 4.000085\n            }\n        }, \n        {\n            \"streams\": [\n                {\n                    \"bits_per_second\": 851251965.111414, \n                    \"bytes\": 106406280, \n                    \"end\": 6.000081, \n                    \"omitted\": false, \n                    \"seconds\": 0.9999979734420776, \n                    \"sender\": false, \n                    \"socket\": 5, \n                    \"start\": 5.000083\n                }\n            ], \n            \"sum\": {\n                \"bits_per_second\": 851251965.111414, \n                \"bytes\": 106406280, \n                \"end\": 6.000081, \n                \"omitted\": false, \n                \"seconds\": 0.9999979734420776, \n                \"sender\": false, \n                \"start\": 5.000083\n            }\n        }, \n        {\n            \"streams\": [\n                {\n                    \"bits_per_second\": 851248514.8955783, \n                    \"bytes\": 106406280, \n                    \"end\": 7.000083, \n                    \"omitted\": false, \n                    \"seconds\": 1.0000020265579224, \n                    \"sender\": false, \n                    \"socket\": 5, \n                    \"start\": 6.000081\n                }\n            ], \n            \"sum\": {\n                \"bits_per_second\": 851248514.8955783, \n                \"bytes\": 106406280, \n                \"end\": 7.000083, \n                \"omitted\": false, \n                \"seconds\": 1.0000020265579224, \n                \"sender\": false, \n                \"start\": 6.000081\n            }\n        }, \n        {\n            \"streams\": [\n                {\n                    \"bits_per_second\": 851251965.111414, \n                    \"bytes\": 106406280, \n                    \"end\": 8.000081, \n                    \"omitted\": false, \n                    \"seconds\": 0.9999979734420776, \n                    \"sender\": false, \n                    \"socket\": 5, \n                    \"start\": 7.000083\n                }\n            ], \n            \"sum\": {\n                \"bits_per_second\": 851251965.111414, \n                \"bytes\": 106406280, \n                \"end\": 8.000081, \n                \"omitted\": false, \n                \"seconds\": 0.9999979734420776, \n                \"sender\": false, \n                \"start\": 7.000083\n            }\n        }, \n        {\n            \"streams\": [\n                {\n                    \"bits_per_second\": 851265563.293216, \n                    \"bytes\": 106406280, \n                    \"end\": 9.000063, \n                    \"omitted\": false, \n                    \"seconds\": 0.9999819993972778, \n                    \"sender\": false, \n                    \"socket\": 5, \n                    \"start\": 8.000081\n                }\n            ], \n            \"sum\": {\n                \"bits_per_second\": 851265563.293216, \n                \"bytes\": 106406280, \n                \"end\": 9.000063, \n                \"omitted\": false, \n                \"seconds\": 0.9999819993972778, \n                \"sender\": false, \n                \"start\": 8.000081\n            }\n        }, \n        {\n            \"streams\": [\n                {\n                    \"bits_per_second\": 851251965.111414, \n                    \"bytes\": 106406280, \n                    \"end\": 10.000061, \n                    \"omitted\": false, \n                    \"seconds\": 0.9999979734420776, \n                    \"sender\": false, \n                    \"socket\": 5, \n                    \"start\": 9.000063\n                }\n            ], \n            \"sum\": {\n                \"bits_per_second\": 851251965.111414, \n                \"bytes\": 106406280, \n                \"end\": 10.000061, \n                \"omitted\": false, \n                \"seconds\": 0.9999979734420776, \n                \"sender\": false, \n                \"start\": 9.000063\n            }\n        }, \n        {\n            \"streams\": [\n                {\n                    \"bits_per_second\": 851250240, \n                    \"bytes\": 106406280, \n                    \"end\": 11.000061, \n                    \"omitted\": false, \n                    \"seconds\": 1, \n                    \"sender\": false, \n                    \"socket\": 5, \n                    \"start\": 10.000061\n                }\n            ], \n            \"sum\": {\n                \"bits_per_second\": 851250240, \n                \"bytes\": 106406280, \n                \"end\": 11.000061, \n                \"omitted\": false, \n                \"seconds\": 1, \n                \"sender\": false, \n                \"start\": 10.000061\n            }\n        }, \n        {\n            \"streams\": [\n                {\n                    \"bits_per_second\": 851250240, \n                    \"bytes\": 106406280, \n                    \"end\": 12.000061, \n                    \"omitted\": false, \n                    \"seconds\": 1, \n                    \"sender\": false, \n                    \"socket\": 5, \n                    \"start\": 11.000061\n                }\n            ], \n            \"sum\": {\n                \"bits_per_second\": 851250240, \n                \"bytes\": 106406280, \n                \"end\": 12.000061, \n                \"omitted\": false, \n                \"seconds\": 1, \n                \"sender\": false, \n                \"start\": 11.000061\n            }\n        }, \n        {\n            \"streams\": [\n                {\n                    \"bits_per_second\": 851269825.499325, \n                    \"bytes\": 106406280, \n                    \"end\": 13.000038, \n                    \"omitted\": false, \n                    \"seconds\": 0.9999769926071167, \n                    \"sender\": false, \n                    \"socket\": 5, \n                    \"start\": 12.000061\n                }\n            ], \n            \"sum\": {\n                \"bits_per_second\": 851269825.499325, \n                \"bytes\": 106406280, \n                \"end\": 13.000038, \n                \"omitted\": false, \n                \"seconds\": 0.9999769926071167, \n                \"sender\": false, \n                \"start\": 12.000061\n            }\n        }, \n        {\n            \"streams\": [\n                {\n                    \"bits_per_second\": 851209346.759221, \n                    \"bytes\": 106406280, \n                    \"end\": 14.000086, \n                    \"omitted\": false, \n                    \"seconds\": 1.000048041343689, \n                    \"sender\": false, \n                    \"socket\": 5, \n                    \"start\": 13.000038\n                }\n            ], \n            \"sum\": {\n                \"bits_per_second\": 851209346.759221, \n                \"bytes\": 106406280, \n                \"end\": 14.000086, \n                \"omitted\": false, \n                \"seconds\": 1.000048041343689, \n                \"sender\": false, \n                \"start\": 13.000038\n            }\n        }, \n        {\n            \"streams\": [\n                {\n                    \"bits_per_second\": 850736616.885931, \n                    \"bytes\": 106341120, \n                    \"end\": 15.000077, \n                    \"omitted\": false, \n                    \"seconds\": 0.999990999698639, \n                    \"sender\": false, \n                    \"socket\": 5, \n                    \"start\": 14.000086\n                }\n            ], \n            \"sum\": {\n                \"bits_per_second\": 850736616.885931, \n                \"bytes\": 106341120, \n                \"end\": 15.000077, \n                \"omitted\": false, \n                \"seconds\": 0.999990999698639, \n                \"sender\": false, \n                \"start\": 14.000086\n            }\n        }, \n        {\n            \"streams\": [\n                {\n                    \"bits_per_second\": 851246789.7981485, \n                    \"bytes\": 106406280, \n                    \"end\": 16.000081, \n                    \"omitted\": false, \n                    \"seconds\": 1.0000040531158447, \n                    \"sender\": false, \n                    \"socket\": 5, \n                    \"start\": 15.000077\n                }\n            ], \n            \"sum\": {\n                \"bits_per_second\": 851246789.7981485, \n                \"bytes\": 106406280, \n                \"end\": 16.000081, \n                \"omitted\": false, \n                \"seconds\": 1.0000040531158447, \n                \"sender\": false, \n                \"start\": 15.000077\n            }\n        }, \n        {\n            \"streams\": [\n                {\n                    \"bits_per_second\": 851242629.2978195, \n                    \"bytes\": 106406280, \n                    \"end\": 17.00009, \n                    \"omitted\": false, \n                    \"seconds\": 1.0000089406967163, \n                    \"sender\": false, \n                    \"socket\": 5, \n                    \"start\": 16.000081\n                }\n            ], \n            \"sum\": {\n                \"bits_per_second\": 851242629.2978195, \n                \"bytes\": 106406280, \n                \"end\": 17.00009, \n                \"omitted\": false, \n                \"seconds\": 1.0000089406967163, \n                \"sender\": false, \n                \"start\": 16.000081\n            }\n        }, \n        {\n            \"streams\": [\n                {\n                    \"bits_per_second\": 851262163.7070365, \n                    \"bytes\": 106406280, \n                    \"end\": 18.000076, \n                    \"omitted\": false, \n                    \"seconds\": 0.9999859929084778, \n                    \"sender\": false, \n                    \"socket\": 5, \n                    \"start\": 17.00009\n                }\n            ], \n            \"sum\": {\n                \"bits_per_second\": 851262163.7070365, \n                \"bytes\": 106406280, \n                \"end\": 18.000076, \n                \"omitted\": false, \n                \"seconds\": 0.9999859929084778, \n                \"sender\": false, \n                \"start\": 17.00009\n            }\n        }, \n        {\n            \"streams\": [\n                {\n                    \"bits_per_second\": 851245166.1834253, \n                    \"bytes\": 106406280, \n                    \"end\": 19.000082, \n                    \"omitted\": false, \n                    \"seconds\": 1.0000059604644775, \n                    \"sender\": false, \n                    \"socket\": 5, \n                    \"start\": 18.000076\n                }\n            ], \n            \"sum\": {\n                \"bits_per_second\": 851245166.1834253, \n                \"bytes\": 106406280, \n                \"end\": 19.000082, \n                \"omitted\": false, \n                \"seconds\": 1.0000059604644775, \n                \"sender\": false, \n                \"start\": 18.000076\n            }\n        }, \n        {\n            \"streams\": [\n                {\n                    \"bits_per_second\": 851268100.3155203, \n                    \"bytes\": 106406280, \n                    \"end\": 20.000061, \n                    \"omitted\": false, \n                    \"seconds\": 0.999979019165039, \n                    \"sender\": false, \n                    \"socket\": 5, \n                    \"start\": 19.000082\n                }\n            ], \n            \"sum\": {\n                \"bits_per_second\": 851268100.3155203, \n                \"bytes\": 106406280, \n                \"end\": 20.000061, \n                \"omitted\": false, \n                \"seconds\": 0.999979019165039, \n                \"sender\": false, \n                \"start\": 19.000082\n            }\n        }, \n        {\n            \"streams\": [\n                {\n                    \"bits_per_second\": 851246789.7981485, \n                    \"bytes\": 106406280, \n                    \"end\": 21.000065, \n                    \"omitted\": false, \n                    \"seconds\": 1.0000040531158447, \n                    \"sender\": false, \n                    \"socket\": 5, \n                    \"start\": 20.000061\n                }\n            ], \n            \"sum\": {\n                \"bits_per_second\": 851246789.7981485, \n                \"bytes\": 106406280, \n                \"end\": 21.000065, \n                \"omitted\": false, \n                \"seconds\": 1.0000040531158447, \n                \"sender\": false, \n                \"start\": 20.000061\n            }\n        }, \n        {\n            \"streams\": [\n                {\n                    \"bits_per_second\": 851253639.4909433, \n                    \"bytes\": 106406280, \n                    \"end\": 22.000061, \n                    \"omitted\": false, \n                    \"seconds\": 0.9999960064888, \n                    \"sender\": false, \n                    \"socket\": 5, \n                    \"start\": 21.000065\n                }\n            ], \n            \"sum\": {\n                \"bits_per_second\": 851253639.4909433, \n                \"bytes\": 106406280, \n                \"end\": 22.000061, \n                \"omitted\": false, \n                \"seconds\": 0.9999960064888, \n                \"sender\": false, \n                \"start\": 21.000065\n            }\n        }, \n        {\n            \"streams\": [\n                {\n                    \"bits_per_second\": 851251102.554833, \n                    \"bytes\": 106406280, \n                    \"end\": 23.00006, \n                    \"omitted\": false, \n                    \"seconds\": 0.9999989867210388, \n                    \"sender\": false, \n                    \"socket\": 5, \n                    \"start\": 22.000061\n                }\n            ], \n            \"sum\": {\n                \"bits_per_second\": 851251102.554833, \n                \"bytes\": 106406280, \n                \"end\": 23.00006, \n                \"omitted\": false, \n                \"seconds\": 0.9999989867210388, \n                \"sender\": false, \n                \"start\": 22.000061\n            }\n        }, \n        {\n            \"streams\": [\n                {\n                    \"bits_per_second\": 851270688.0938495, \n                    \"bytes\": 106406280, \n                    \"end\": 24.000036, \n                    \"omitted\": false, \n                    \"seconds\": 0.9999759793281555, \n                    \"sender\": false, \n                    \"socket\": 5, \n                    \"start\": 23.00006\n                }\n            ], \n            \"sum\": {\n                \"bits_per_second\": 851270688.0938495, \n                \"bytes\": 106406280, \n                \"end\": 24.000036, \n                \"omitted\": false, \n                \"seconds\": 0.9999759793281555, \n                \"sender\": false, \n                \"start\": 23.00006\n            }\n        }, \n        {\n            \"streams\": [\n                {\n                    \"bits_per_second\": 851200011.8804024, \n                    \"bytes\": 106406280, \n                    \"end\": 25.000095, \n                    \"omitted\": false, \n                    \"seconds\": 1.0000590085983276, \n                    \"sender\": false, \n                    \"socket\": 5, \n                    \"start\": 24.000036\n                }\n            ], \n            \"sum\": {\n                \"bits_per_second\": 851200011.8804024, \n                \"bytes\": 106406280, \n                \"end\": 25.000095, \n                \"omitted\": false, \n                \"seconds\": 1.0000590085983276, \n                \"sender\": false, \n                \"start\": 24.000036\n            }\n        }, \n        {\n            \"streams\": [\n                {\n                    \"bits_per_second\": 850745998.02677, \n                    \"bytes\": 106341120, \n                    \"end\": 26.000075, \n                    \"omitted\": false, \n                    \"seconds\": 0.9999799728393555, \n                    \"sender\": false, \n                    \"socket\": 5, \n                    \"start\": 25.000095\n                }\n            ], \n            \"sum\": {\n                \"bits_per_second\": 850745998.02677, \n                \"bytes\": 106341120, \n                \"end\": 26.000075, \n                \"omitted\": false, \n                \"seconds\": 0.9999799728393555, \n                \"sender\": false, \n                \"start\": 25.000095\n            }\n        }, \n        {\n            \"streams\": [\n                {\n                    \"bits_per_second\": 851250240, \n                    \"bytes\": 106406280, \n                    \"end\": 27.000075, \n                    \"omitted\": false, \n                    \"seconds\": 1, \n                    \"sender\": false, \n                    \"socket\": 5, \n                    \"start\": 26.000075\n                }\n            ], \n            \"sum\": {\n                \"bits_per_second\": 851250240, \n                \"bytes\": 106406280, \n                \"end\": 27.000075, \n                \"omitted\": false, \n                \"seconds\": 1, \n                \"sender\": false, \n                \"start\": 26.000075\n            }\n        }, \n        {\n            \"streams\": [\n                {\n                    \"bits_per_second\": 851245166.1834253, \n                    \"bytes\": 106406280, \n                    \"end\": 28.000081, \n                    \"omitted\": false, \n                    \"seconds\": 1.0000059604644775, \n                    \"sender\": false, \n                    \"socket\": 5, \n                    \"start\": 27.000075\n                }\n            ], \n            \"sum\": {\n                \"bits_per_second\": 851245166.1834253, \n                \"bytes\": 106406280, \n                \"end\": 28.000081, \n                \"omitted\": false, \n                \"seconds\": 1.0000059604644775, \n                \"sender\": false, \n                \"start\": 27.000075\n            }\n        }, \n        {\n            \"streams\": [\n                {\n                    \"bits_per_second\": 851249428.1852835, \n                    \"bytes\": 106406280, \n                    \"end\": 29.000082, \n                    \"omitted\": false, \n                    \"seconds\": 1.0000009536743164, \n                    \"sender\": false, \n                    \"socket\": 5, \n                    \"start\": 28.000081\n                }\n            ], \n            \"sum\": {\n                \"bits_per_second\": 851249428.1852835, \n                \"bytes\": 106406280, \n                \"end\": 29.000082, \n                \"omitted\": false, \n                \"seconds\": 1.0000009536743164, \n                \"sender\": false, \n                \"start\": 28.000081\n            }\n        }, \n        {\n            \"streams\": [\n                {\n                    \"bits_per_second\": 851250240, \n                    \"bytes\": 106406280, \n                    \"end\": 30.000082, \n                    \"omitted\": false, \n                    \"seconds\": 1, \n                    \"sender\": false, \n                    \"socket\": 5, \n                    \"start\": 29.000082\n                }\n            ], \n            \"sum\": {\n                \"bits_per_second\": 851250240, \n                \"bytes\": 106406280, \n                \"end\": 30.000082, \n                \"omitted\": false, \n                \"seconds\": 1, \n                \"sender\": false, \n                \"start\": 29.000082\n            }\n        }, \n        {\n            \"streams\": [\n                {\n                    \"bits_per_second\": 851268962.9065485, \n                    \"bytes\": 106406280, \n                    \"end\": 31.00006, \n                    \"omitted\": false, \n                    \"seconds\": 0.999978005886078, \n                    \"sender\": false, \n                    \"socket\": 5, \n                    \"start\": 30.000082\n                }\n            ], \n            \"sum\": {\n                \"bits_per_second\": 851268962.9065485, \n                \"bytes\": 106406280, \n                \"end\": 31.00006, \n                \"omitted\": false, \n                \"seconds\": 0.999978005886078, \n                \"sender\": false, \n                \"start\": 30.000082\n            }\n        }, \n        {\n            \"streams\": [\n                {\n                    \"bits_per_second\": 851248514.8955783, \n                    \"bytes\": 106406280, \n                    \"end\": 32.000062, \n                    \"omitted\": false, \n                    \"seconds\": 1.0000020265579224, \n                    \"sender\": false, \n                    \"socket\": 5, \n                    \"start\": 31.00006\n                }\n            ], \n            \"sum\": {\n                \"bits_per_second\": 851248514.8955783, \n                \"bytes\": 106406280, \n                \"end\": 32.000062, \n                \"omitted\": false, \n                \"seconds\": 1.0000020265579224, \n                \"sender\": false, \n                \"start\": 31.00006\n            }\n        }, \n        {\n            \"streams\": [\n                {\n                    \"bits_per_second\": 851250240, \n                    \"bytes\": 106406280, \n                    \"end\": 33.000062, \n                    \"omitted\": false, \n                    \"seconds\": 1, \n                    \"sender\": false, \n                    \"socket\": 5, \n                    \"start\": 32.000062\n                }\n            ], \n            \"sum\": {\n                \"bits_per_second\": 851250240, \n                \"bytes\": 106406280, \n                \"end\": 33.000062, \n                \"omitted\": false, \n                \"seconds\": 1, \n                \"sender\": false, \n                \"start\": 32.000062\n            }\n        }, \n        {\n            \"streams\": [\n                {\n                    \"bits_per_second\": 851251102.554833, \n                    \"bytes\": 106406280, \n                    \"end\": 34.000061, \n                    \"omitted\": false, \n                    \"seconds\": 0.9999989867210388, \n                    \"sender\": false, \n                    \"socket\": 5, \n                    \"start\": 33.000062\n                }\n            ], \n            \"sum\": {\n                \"bits_per_second\": 851251102.554833, \n                \"bytes\": 106406280, \n                \"end\": 34.000061, \n                \"omitted\": false, \n                \"seconds\": 0.9999989867210388, \n                \"sender\": false, \n                \"start\": 33.000062\n            }\n        }, \n        {\n            \"streams\": [\n                {\n                    \"bits_per_second\": 851271499.9491166, \n                    \"bytes\": 106406280, \n                    \"end\": 35.000036, \n                    \"omitted\": false, \n                    \"seconds\": 0.999975025653839, \n                    \"sender\": false, \n                    \"socket\": 5, \n                    \"start\": 34.000061\n                }\n            ], \n            \"sum\": {\n                \"bits_per_second\": 851271499.9491166, \n                \"bytes\": 106406280, \n                \"end\": 35.000036, \n                \"omitted\": false, \n                \"seconds\": 0.999975025653839, \n                \"sender\": false, \n                \"start\": 34.000061\n            }\n        }, \n        {\n            \"streams\": [\n                {\n                    \"bits_per_second\": 851204273.4301157, \n                    \"bytes\": 106406280, \n                    \"end\": 36.00009, \n                    \"omitted\": false, \n                    \"seconds\": 1.0000540018081665, \n                    \"sender\": false, \n                    \"socket\": 5, \n                    \"start\": 35.000036\n                }\n            ], \n            \"sum\": {\n                \"bits_per_second\": 851204273.4301157, \n                \"bytes\": 106406280, \n                \"end\": 36.00009, \n                \"omitted\": false, \n                \"seconds\": 1.0000540018081665, \n                \"sender\": false, \n                \"start\": 35.000036\n            }\n        }, \n        {\n            \"streams\": [\n                {\n                    \"bits_per_second\": 850740014.3562847, \n                    \"bytes\": 106341120, \n                    \"end\": 37.000077, \n                    \"omitted\": false, \n                    \"seconds\": 0.999987006187439, \n                    \"sender\": false, \n                    \"socket\": 5, \n                    \"start\": 36.00009\n                }\n            ], \n            \"sum\": {\n                \"bits_per_second\": 850740014.3562847, \n                \"bytes\": 106341120, \n                \"end\": 37.000077, \n                \"omitted\": false, \n                \"seconds\": 0.999987006187439, \n                \"sender\": false, \n                \"start\": 36.00009\n            }\n        }, \n        {\n            \"streams\": [\n                {\n                    \"bits_per_second\": 851248514.8955783, \n                    \"bytes\": 106406280, \n                    \"end\": 38.000079, \n                    \"omitted\": false, \n                    \"seconds\": 1.0000020265579224, \n                    \"sender\": false, \n                    \"socket\": 5, \n                    \"start\": 37.000077\n                }\n            ], \n            \"sum\": {\n                \"bits_per_second\": 851248514.8955783, \n                \"bytes\": 106406280, \n                \"end\": 38.000079, \n                \"omitted\": false, \n                \"seconds\": 1.0000020265579224, \n                \"sender\": false, \n                \"start\": 37.000077\n            }\n        }, \n        {\n            \"streams\": [\n                {\n                    \"bits_per_second\": 851248514.8955783, \n                    \"bytes\": 106406280, \n                    \"end\": 39.000081, \n                    \"omitted\": false, \n                    \"seconds\": 1.0000020265579224, \n                    \"sender\": false, \n                    \"socket\": 5, \n                    \"start\": 38.000079\n                }\n            ], \n            \"sum\": {\n                \"bits_per_second\": 851248514.8955783, \n                \"bytes\": 106406280, \n                \"end\": 39.000081, \n                \"omitted\": false, \n                \"seconds\": 1.0000020265579224, \n                \"sender\": false, \n                \"start\": 38.000079\n            }\n        }, \n        {\n            \"streams\": [\n                {\n                    \"bits_per_second\": 851251102.554833, \n                    \"bytes\": 106406280, \n                    \"end\": 40.00008, \n                    \"omitted\": false, \n                    \"seconds\": 0.9999989867210388, \n                    \"sender\": false, \n                    \"socket\": 5, \n                    \"start\": 39.000081\n                }\n            ], \n            \"sum\": {\n                \"bits_per_second\": 851251102.554833, \n                \"bytes\": 106406280, \n                \"end\": 40.00008, \n                \"omitted\": false, \n                \"seconds\": 0.9999989867210388, \n                \"sender\": false, \n                \"start\": 39.000081\n            }\n        }, \n        {\n            \"streams\": [\n                {\n                    \"bits_per_second\": 851266425.8791027, \n                    \"bytes\": 106406280, \n                    \"end\": 41.000061, \n                    \"omitted\": false, \n                    \"seconds\": 0.9999809861183167, \n                    \"sender\": false, \n                    \"socket\": 5, \n                    \"start\": 40.00008\n                }\n            ], \n            \"sum\": {\n                \"bits_per_second\": 851266425.8791027, \n                \"bytes\": 106406280, \n                \"end\": 41.000061, \n                \"omitted\": false, \n                \"seconds\": 0.9999809861183167, \n                \"sender\": false, \n                \"start\": 40.00008\n            }\n        }, \n        {\n            \"streams\": [\n                {\n                    \"bits_per_second\": 851250240, \n                    \"bytes\": 106406280, \n                    \"end\": 42.000061, \n                    \"omitted\": false, \n                    \"seconds\": 1, \n                    \"sender\": false, \n                    \"socket\": 5, \n                    \"start\": 41.000061\n                }\n            ], \n            \"sum\": {\n                \"bits_per_second\": 851250240, \n                \"bytes\": 106406280, \n                \"end\": 42.000061, \n                \"omitted\": false, \n                \"seconds\": 1, \n                \"sender\": false, \n                \"start\": 41.000061\n            }\n        }, \n        {\n            \"streams\": [\n                {\n                    \"bits_per_second\": 851250240, \n                    \"bytes\": 106406280, \n                    \"end\": 43.000061, \n                    \"omitted\": false, \n                    \"seconds\": 1, \n                    \"sender\": false, \n                    \"socket\": 5, \n                    \"start\": 42.000061\n                }\n            ], \n            \"sum\": {\n                \"bits_per_second\": 851250240, \n                \"bytes\": 106406280, \n                \"end\": 43.000061, \n                \"omitted\": false, \n                \"seconds\": 1, \n                \"sender\": false, \n                \"start\": 42.000061\n            }\n        }, \n        {\n            \"streams\": [\n                {\n                    \"bits_per_second\": 851250240, \n                    \"bytes\": 106406280, \n                    \"end\": 44.000061, \n                    \"omitted\": false, \n                    \"seconds\": 1, \n                    \"sender\": false, \n                    \"socket\": 5, \n                    \"start\": 43.000061\n                }\n            ], \n            \"sum\": {\n                \"bits_per_second\": 851250240, \n                \"bytes\": 106406280, \n                \"end\": 44.000061, \n                \"omitted\": false, \n                \"seconds\": 1, \n                \"sender\": false, \n                \"start\": 43.000061\n            }\n        }, \n        {\n            \"streams\": [\n                {\n                    \"bits_per_second\": 851250240, \n                    \"bytes\": 106406280, \n                    \"end\": 45.000061, \n                    \"omitted\": false, \n                    \"seconds\": 1, \n                    \"sender\": false, \n                    \"socket\": 5, \n                    \"start\": 44.000061\n                }\n            ], \n            \"sum\": {\n                \"bits_per_second\": 851250240, \n                \"bytes\": 106406280, \n                \"end\": 45.000061, \n                \"omitted\": false, \n                \"seconds\": 1, \n                \"sender\": false, \n                \"start\": 44.000061\n            }\n        }, \n        {\n            \"streams\": [\n                {\n                    \"bits_per_second\": 851278350.039587, \n                    \"bytes\": 106406280, \n                    \"end\": 46.000028, \n                    \"omitted\": false, \n                    \"seconds\": 0.9999669790267944, \n                    \"sender\": false, \n                    \"socket\": 5, \n                    \"start\": 45.000061\n                }\n            ], \n            \"sum\": {\n                \"bits_per_second\": 851278350.039587, \n                \"bytes\": 106406280, \n                \"end\": 46.000028, \n                \"omitted\": false, \n                \"seconds\": 0.9999669790267944, \n                \"sender\": false, \n                \"start\": 45.000061\n            }\n        }, \n        {\n            \"streams\": [\n                {\n                    \"bits_per_second\": 850684745.4474765, \n                    \"bytes\": 106341120, \n                    \"end\": 47.00008, \n                    \"omitted\": false, \n                    \"seconds\": 1.0000519752502441, \n                    \"sender\": false, \n                    \"socket\": 5, \n                    \"start\": 46.000028\n                }\n            ], \n            \"sum\": {\n                \"bits_per_second\": 850684745.4474765, \n                \"bytes\": 106341120, \n                \"end\": 47.00008, \n                \"omitted\": false, \n                \"seconds\": 1.0000519752502441, \n                \"sender\": false, \n                \"start\": 46.000028\n            }\n        }, \n        {\n            \"streams\": [\n                {\n                    \"bits_per_second\": 851244252.9028653, \n                    \"bytes\": 106406280, \n                    \"end\": 48.000087, \n                    \"omitted\": false, \n                    \"seconds\": 1.0000070333480835, \n                    \"sender\": false, \n                    \"socket\": 5, \n                    \"start\": 47.00008\n                }\n            ], \n            \"sum\": {\n                \"bits_per_second\": 851244252.9028653, \n                \"bytes\": 106406280, \n                \"end\": 48.000087, \n                \"omitted\": false, \n                \"seconds\": 1.0000070333480835, \n                \"sender\": false, \n                \"start\": 47.00008\n            }\n        }, \n        {\n            \"streams\": [\n                {\n                    \"bits_per_second\": 851259626.7201176, \n                    \"bytes\": 106406280, \n                    \"end\": 49.000076, \n                    \"omitted\": false, \n                    \"seconds\": 0.9999889731407166, \n                    \"sender\": false, \n                    \"socket\": 5, \n                    \"start\": 48.000087\n                }\n            ], \n            \"sum\": {\n                \"bits_per_second\": 851259626.7201176, \n                \"bytes\": 106406280, \n                \"end\": 49.000076, \n                \"omitted\": false, \n                \"seconds\": 0.9999889731407166, \n                \"sender\": false, \n                \"start\": 48.000087\n            }\n        }, \n        {\n            \"streams\": [\n                {\n                    \"bits_per_second\": 851245977.9900126, \n                    \"bytes\": 106406280, \n                    \"end\": 50.000081, \n                    \"omitted\": false, \n                    \"seconds\": 1.0000050067901611, \n                    \"sender\": false, \n                    \"socket\": 5, \n                    \"start\": 49.000076\n                }\n            ], \n            \"sum\": {\n                \"bits_per_second\": 851245977.9900126, \n                \"bytes\": 106406280, \n                \"end\": 50.000081, \n                \"omitted\": false, \n                \"seconds\": 1.0000050067901611, \n                \"sender\": false, \n                \"start\": 49.000076\n            }\n        }, \n        {\n            \"streams\": [\n                {\n                    \"bits_per_second\": 851249428.1852835, \n                    \"bytes\": 106406280, \n                    \"end\": 51.000082, \n                    \"omitted\": false, \n                    \"seconds\": 1.0000009536743164, \n                    \"sender\": false, \n                    \"socket\": 5, \n                    \"start\": 50.000081\n                }\n            ], \n            \"sum\": {\n                \"bits_per_second\": 851249428.1852835, \n                \"bytes\": 106406280, \n                \"end\": 51.000082, \n                \"omitted\": false, \n                \"seconds\": 1.0000009536743164, \n                \"sender\": false, \n                \"start\": 50.000081\n            }\n        }, \n        {\n            \"streams\": [\n                {\n                    \"bits_per_second\": 851251102.554833, \n                    \"bytes\": 106406280, \n                    \"end\": 52.000081, \n                    \"omitted\": false, \n                    \"seconds\": 0.9999989867210388, \n                    \"sender\": false, \n                    \"socket\": 5, \n                    \"start\": 51.000082\n                }\n            ], \n            \"sum\": {\n                \"bits_per_second\": 851251102.554833, \n                \"bytes\": 106406280, \n                \"end\": 52.000081, \n                \"omitted\": false, \n                \"seconds\": 0.9999989867210388, \n                \"sender\": false, \n                \"start\": 51.000082\n            }\n        }, \n        {\n            \"streams\": [\n                {\n                    \"bits_per_second\": 851268100.3155203, \n                    \"bytes\": 106406280, \n                    \"end\": 53.00006, \n                    \"omitted\": false, \n                    \"seconds\": 0.999979019165039, \n                    \"sender\": false, \n                    \"socket\": 5, \n                    \"start\": 52.000081\n                }\n            ], \n            \"sum\": {\n                \"bits_per_second\": 851268100.3155203, \n                \"bytes\": 106406280, \n                \"end\": 53.00006, \n                \"omitted\": false, \n                \"seconds\": 0.999979019165039, \n                \"sender\": false, \n                \"start\": 52.000081\n            }\n        }, \n        {\n            \"streams\": [\n                {\n                    \"bits_per_second\": 851250240, \n                    \"bytes\": 106406280, \n                    \"end\": 54.00006, \n                    \"omitted\": false, \n                    \"seconds\": 1, \n                    \"sender\": false, \n                    \"socket\": 5, \n                    \"start\": 53.00006\n                }\n            ], \n            \"sum\": {\n                \"bits_per_second\": 851250240, \n                \"bytes\": 106406280, \n                \"end\": 54.00006, \n                \"omitted\": false, \n                \"seconds\": 1, \n                \"sender\": false, \n                \"start\": 53.00006\n            }\n        }, \n        {\n            \"streams\": [\n                {\n                    \"bits_per_second\": 851248514.8955783, \n                    \"bytes\": 106406280, \n                    \"end\": 55.000062, \n                    \"omitted\": false, \n                    \"seconds\": 1.0000020265579224, \n                    \"sender\": false, \n                    \"socket\": 5, \n                    \"start\": 54.00006\n                }\n            ], \n            \"sum\": {\n                \"bits_per_second\": 851248514.8955783, \n                \"bytes\": 106406280, \n                \"end\": 55.000062, \n                \"omitted\": false, \n                \"seconds\": 1.0000020265579224, \n                \"sender\": false, \n                \"start\": 54.00006\n            }\n        }, \n        {\n            \"streams\": [\n                {\n                    \"bits_per_second\": 851250240, \n                    \"bytes\": 106406280, \n                    \"end\": 56.000062, \n                    \"omitted\": false, \n                    \"seconds\": 1, \n                    \"sender\": false, \n                    \"socket\": 5, \n                    \"start\": 55.000062\n                }\n            ], \n            \"sum\": {\n                \"bits_per_second\": 851250240, \n                \"bytes\": 106406280, \n                \"end\": 56.000062, \n                \"omitted\": false, \n                \"seconds\": 1, \n                \"sender\": false, \n                \"start\": 55.000062\n            }\n        }, \n        {\n            \"streams\": [\n                {\n                    \"bits_per_second\": 851258764.1480098, \n                    \"bytes\": 106406280, \n                    \"end\": 57.000052, \n                    \"omitted\": false, \n                    \"seconds\": 0.9999899864196777, \n                    \"sender\": false, \n                    \"socket\": 5, \n                    \"start\": 56.000062\n                }\n            ], \n            \"sum\": {\n                \"bits_per_second\": 851258764.1480098, \n                \"bytes\": 106406280, \n                \"end\": 57.000052, \n                \"omitted\": false, \n                \"seconds\": 0.9999899864196777, \n                \"sender\": false, \n                \"start\": 56.000062\n            }\n        }, \n        {\n            \"streams\": [\n                {\n                    \"bits_per_second\": 851217058.3352857, \n                    \"bytes\": 106406280, \n                    \"end\": 58.000091, \n                    \"omitted\": false, \n                    \"seconds\": 1.000038981437683, \n                    \"sender\": false, \n                    \"socket\": 5, \n                    \"start\": 57.000052\n                }\n            ], \n            \"sum\": {\n                \"bits_per_second\": 851217058.3352857, \n                \"bytes\": 106406280, \n                \"end\": 58.000091, \n                \"omitted\": false, \n                \"seconds\": 1.000038981437683, \n                \"sender\": false, \n                \"start\": 57.000052\n            }\n        }, \n        {\n            \"streams\": [\n                {\n                    \"bits_per_second\": 850741738.4560972, \n                    \"bytes\": 106341120, \n                    \"end\": 59.000076, \n                    \"omitted\": false, \n                    \"seconds\": 0.9999849796295166, \n                    \"sender\": false, \n                    \"socket\": 5, \n                    \"start\": 58.000091\n                }\n            ], \n            \"sum\": {\n                \"bits_per_second\": 850741738.4560972, \n                \"bytes\": 106341120, \n                \"end\": 59.000076, \n                \"omitted\": false, \n                \"seconds\": 0.9999849796295166, \n                \"sender\": false, \n                \"start\": 58.000091\n            }\n        }, \n        {\n            \"streams\": [\n                {\n                    \"bits_per_second\": 851262163.7070365, \n                    \"bytes\": 106406280, \n                    \"end\": 60.000062, \n                    \"omitted\": false, \n                    \"seconds\": 0.9999859929084778, \n                    \"sender\": false, \n                    \"socket\": 5, \n                    \"start\": 59.000076\n                }\n            ], \n            \"sum\": {\n                \"bits_per_second\": 851262163.7070365, \n                \"bytes\": 106406280, \n                \"end\": 60.000062, \n                \"omitted\": false, \n                \"seconds\": 0.9999859929084778, \n                \"sender\": false, \n                \"start\": 59.000076\n            }\n        }, \n        {\n            \"streams\": [\n                {\n                    \"bits_per_second\": 856740914.9608204, \n                    \"bytes\": 8340480, \n                    \"end\": 60.077943, \n                    \"omitted\": false, \n                    \"seconds\": 0.07788100093603134, \n                    \"sender\": false, \n                    \"socket\": 5, \n                    \"start\": 60.000062\n                }\n            ], \n            \"sum\": {\n                \"bits_per_second\": 856740914.9608204, \n                \"bytes\": 8340480, \n                \"end\": 60.077943, \n                \"omitted\": false, \n                \"seconds\": 0.07788100093603134, \n                \"sender\": false, \n                \"start\": 60.000062\n            }\n        }\n    ], \n    \"start\": {\n        \"accepted_connection\": {\n            \"host\": \"10.0.0.1\", \n            \"port\": 60265\n        }, \n        \"connected\": [\n            {\n                \"local_host\": \"10.0.0.2\", \n                \"local_port\": 5201, \n                \"remote_host\": \"10.0.0.1\", \n                \"remote_port\": 55685, \n                \"socket\": 5\n            }\n        ], \n        \"cookie\": \"qcsonshflnxz3r2yxy3crkekqj4s5aocb32z\", \n        \"fq_rate\": 0, \n        \"rcvbuf_actual\": 87380, \n        \"sndbuf_actual\": 87380, \n        \"sock_bufsize\": 0, \n        \"system_info\": \"REDACTED\", \n        \"target_bitrate\": 0, \n        \"tcp_mss_default\": 0, \n        \"test_start\": {\n            \"bidir\": 0, \n            \"blksize\": 131072, \n            \"blocks\": 0, \n            \"bytes\": 0, \n            \"duration\": 60, \n            \"fqrate\": 0, \n            \"num_streams\": 1, \n            \"omit\": 0, \n            \"protocol\": \"TCP\", \n            \"reverse\": 0, \n            \"target_bitrate\": 0, \n            \"tos\": 0\n        }, \n        \"timestamp\": {\n            \"time\": \"Tue, 16 Apr 2024 22:55:47 GMT\", \n            \"timesecs\": 1713308147\n        }, \n        \"version\": \"iperf 3.14\"\n    }\n}\n","summary":{"streams":[{"end":60.000091,"rtt":78383,"start":0,"stream-id":5,"retransmits":0,"throughput-bits":852753138.6577398,"throughput-bytes":6395658240}],"summary":{"end":60.000091,"start":0,"retransmits":0,"throughput-bits":852753138.6577398,"throughput-bytes":6395658240,"receiver-throughput-bits":851136547.601172}},"intervals":[{"streams":[{"end":1.000158,"rtt":78380,"start":0,"omitted":false,"stream-id":5,"retransmits":0,"tcp-window-size":16708472,"throughput-bits":938327309.035264,"throughput-bytes":117309440}],"summary":{"end":1.000158,"start":0,"omitted":false,"retransmits":0,"throughput-bits":938327309.035264,"throughput-bytes":117309440}},{"streams":[{"end":2.000154,"rtt":78382,"start":1.000158,"omitted":false,"stream-id":5,"retransmits":0,"tcp-window-size":16708472,"throughput-bits":849349951.8885455,"throughput-bytes":106168320}],"summary":{"end":2.000154,"start":1.000158,"omitted":false,"retransmits":0,"throughput-bits":849349951.8885455,"throughput-bytes":106168320}},{"streams":[{"end":3.000413,"rtt":78386,"start":2.000154,"omitted":false,"stream-id":5,"retransmits":0,"tcp-window-size":16708472,"throughput-bits":859609645.1820825,"throughput-bytes":107479040}],"summary":{"end":3.000413,"start":2.000154,"omitted":false,"retransmits":0,"throughput-bits":859609645.1820825,"throughput-bytes":107479040}},{"streams":[{"end":4.00008,"rtt":78379,"start":3.000413,"omitted":false,"stream-id":5,"retransmits":0,"tcp-window-size":16708472,"throughput-bits":849629496.0958748,"throughput-bytes":106168320}],"summary":{"end":4.00008,"start":3.000413,"omitted":false,"retransmits":0,"throughput-bits":849629496.0958748,"throughput-bytes":106168320}},{"streams":[{"end":5.000154,"rtt":78386,"start":4.00008,"omitted":false,"stream-id":5,"retransmits":0,"tcp-window-size":16708472,"throughput-bits":849283688.4043194,"throughput-bytes":106168320}],"summary":{"end":5.000154,"start":4.00008,"omitted":false,"retransmits":0,"throughput-bits":849283688.4043194,"throughput-bytes":106168320}},{"streams":[{"end":6.000161,"rtt":78386,"start":5.000154,"omitted":false,"stream-id":5,"retransmits":0,"tcp-window-size":16708472,"throughput-bits":849340586.2920152,"throughput-bytes":106168320}],"summary":{"end":6.000161,"start":5.000154,"omitted":false,"retransmits":0,"throughput-bits":849340586.2920152,"throughput-bytes":106168320}},{"streams":[{"end":7.000092,"rtt":78381,"start":6.000161,"omitted":false,"stream-id":5,"retransmits":0,"tcp-window-size":16708472,"throughput-bits":849405187.7966182,"throughput-bytes":106168320}],"summary":{"end":7.000092,"start":6.000161,"omitted":false,"retransmits":0,"throughput-bits":849405187.7966182,"throughput-bytes":106168320}},{"streams":[{"end":8.000078,"rtt":78381,"start":7.000092,"omitted":false,"stream-id":5,"retransmits":0,"tcp-window-size":16708472,"throughput-bits":849358457.041643,"throughput-bytes":106168320}],"summary":{"end":8.000078,"start":7.000092,"omitted":false,"retransmits":0,"throughput-bits":849358457.041643,"throughput-bytes":106168320}},{"streams":[{"end":9.000081,"rtt":78391,"start":8.000078,"omitted":false,"stream-id":5,"retransmits":0,"tcp-window-size":16708472,"throughput-bits":859829757.5076368,"throughput-bytes":107479040}],"summary":{"end":9.000081,"start":8.000078,"omitted":false,"retransmits":0,"throughput-bits":859829757.5076368,"throughput-bytes":107479040}},{"streams":[{"end":10.000087,"rtt":78388,"start":9.000081,"omitted":false,"stream-id":5,"retransmits":0,"tcp-window-size":16708472,"throughput-bits":849341497.5301746,"throughput-bytes":106168320}],"summary":{"end":10.000087,"start":9.000081,"omitted":false,"retransmits":0,"throughput-bits":849341497.5301746,"throughput-bytes":106168320}},{"streams":[{"end":11.000063,"rtt":78383,"start":10.000087,"omitted":false,"stream-id":5,"retransmits":0,"tcp-window-size":16708472,"throughput-bits":849366962.3650786,"throughput-bytes":106168320}],"summary":{"end":11.000063,"start":10.000087,"omitted":false,"retransmits":0,"throughput-bits":849366962.3650786,"throughput-bytes":106168320}},{"streams":[{"end":12.000088,"rtt":78382,"start":11.000063,"omitted":false,"stream-id":5,"retransmits":0,"tcp-window-size":16708472,"throughput-bits":849325298.032271,"throughput-bytes":106168320}],"summary":{"end":12.000088,"start":11.000063,"omitted":false,"retransmits":0,"throughput-bits":849325298.032271,"throughput-bytes":106168320}},{"streams":[{"end":13.00017,"rtt":78376,"start":12.000088,"omitted":false,"stream-id":5,"retransmits":0,"tcp-window-size":16708472,"throughput-bits":849276905.7127655,"throughput-bytes":106168320}],"summary":{"end":13.00017,"start":12.000088,"omitted":false,"retransmits":0,"throughput-bits":849276905.7127655,"throughput-bytes":106168320}},{"streams":[{"end":14.00009,"rtt":78383,"start":13.00017,"omitted":false,"stream-id":5,"retransmits":0,"tcp-window-size":16708472,"throughput-bits":849414504.184817,"throughput-bytes":106168320}],"summary":{"end":14.00009,"start":13.00017,"omitted":false,"retransmits":0,"throughput-bits":849414504.184817,"throughput-bytes":106168320}},{"streams":[{"end":15.000086,"rtt":78379,"start":14.00009,"omitted":false,"stream-id":5,"retransmits":0,"tcp-window-size":16708472,"throughput-bits":859835753.7637128,"throughput-bytes":107479040}],"summary":{"end":15.000086,"start":14.00009,"omitted":false,"retransmits":0,"throughput-bits":859835753.7637128,"throughput-bytes":107479040}},{"streams":[{"end":16.000082,"rtt":78388,"start":15.000086,"omitted":false,"stream-id":5,"retransmits":0,"tcp-window-size":16708472,"throughput-bits":849349951.8885455,"throughput-bytes":106168320}],"summary":{"end":16.000082,"start":15.000086,"omitted":false,"retransmits":0,"throughput-bits":849349951.8885455,"throughput-bytes":106168320}},{"streams":[{"end":17.000085,"rtt":78384,"start":16.000082,"omitted":false,"stream-id":5,"retransmits":0,"tcp-window-size":16708472,"throughput-bits":849344028.7575437,"throughput-bytes":106168320}],"summary":{"end":17.000085,"start":16.000082,"omitted":false,"retransmits":0,"throughput-bits":849344028.7575437,"throughput-bytes":106168320}},{"streams":[{"end":18.000082,"rtt":78362,"start":17.000085,"omitted":false,"stream-id":5,"retransmits":0,"tcp-window-size":16708472,"throughput-bits":849349091.2575437,"throughput-bytes":106168320}],"summary":{"end":18.000082,"start":17.000085,"omitted":false,"retransmits":0,"throughput-bits":849349091.2575437,"throughput-bytes":106168320}},{"streams":[{"end":19.000158,"rtt":78385,"start":18.000082,"omitted":false,"stream-id":5,"retransmits":0,"tcp-window-size":16708472,"throughput-bits":849281967.4126233,"throughput-bytes":106168320}],"summary":{"end":19.000158,"start":18.000082,"omitted":false,"retransmits":0,"throughput-bits":849281967.4126233,"throughput-bytes":106168320}},{"streams":[{"end":20.000062,"rtt":78386,"start":19.000158,"omitted":false,"stream-id":5,"retransmits":0,"tcp-window-size":16708472,"throughput-bits":859914891.678787,"throughput-bytes":107479040}],"summary":{"end":20.000062,"start":19.000158,"omitted":false,"retransmits":0,"throughput-bits":859914891.678787,"throughput-bytes":107479040}},{"streams":[{"end":21.000076,"rtt":78376,"start":20.000062,"omitted":false,"stream-id":5,"retransmits":0,"tcp-window-size":16708472,"throughput-bits":849334713.915223,"throughput-bytes":106168320}],"summary":{"end":21.000076,"start":20.000062,"omitted":false,"retransmits":0,"throughput-bits":849334713.915223,"throughput-bytes":106168320}},{"streams":[{"end":22.000148,"rtt":78383,"start":21.000076,"omitted":false,"stream-id":5,"retransmits":0,"tcp-window-size":16708472,"throughput-bits":849285409.4029905,"throughput-bytes":106168320}],"summary":{"end":22.000148,"start":21.000076,"omitted":false,"retransmits":0,"throughput-bits":849285409.4029905,"throughput-bytes":106168320}},{"streams":[{"end":23.000147,"rtt":78387,"start":22.000148,"omitted":false,"stream-id":5,"retransmits":0,"tcp-window-size":16708472,"throughput-bits":849347420.625872,"throughput-bytes":106168320}],"summary":{"end":23.000147,"start":22.000148,"omitted":false,"retransmits":0,"throughput-bits":849347420.625872,"throughput-bytes":106168320}},{"streams":[{"end":24.000082,"rtt":78374,"start":23.000147,"omitted":false,"stream-id":5,"retransmits":0,"tcp-window-size":16708472,"throughput-bits":849401795.4668888,"throughput-bytes":106168320}],"summary":{"end":24.000082,"start":23.000147,"omitted":false,"retransmits":0,"throughput-bits":849401795.4668888,"throughput-bytes":106168320}},{"streams":[{"end":25.000059,"rtt":78382,"start":24.000082,"omitted":false,"stream-id":5,"retransmits":0,"tcp-window-size":16708472,"throughput-bits":849366101.6996036,"throughput-bytes":106168320}],"summary":{"end":25.000059,"start":24.000082,"omitted":false,"retransmits":0,"throughput-bits":849366101.6996036,"throughput-bytes":106168320}},{"streams":[{"end":26.000086,"rtt":78386,"start":25.000059,"omitted":false,"stream-id":5,"retransmits":0,"tcp-window-size":16708472,"throughput-bits":859809155.6240784,"throughput-bytes":107479040}],"summary":{"end":26.000086,"start":25.000059,"omitted":false,"retransmits":0,"throughput-bits":859809155.6240784,"throughput-bytes":107479040}},{"streams":[{"end":27.000168,"rtt":78376,"start":26.000086,"omitted":false,"stream-id":5,"retransmits":0,"tcp-window-size":16708472,"throughput-bits":849276905.7127655,"throughput-bytes":106168320}],"summary":{"end":27.000168,"start":26.000086,"omitted":false,"retransmits":0,"throughput-bits":849276905.7127655,"throughput-bytes":106168320}},{"streams":[{"end":28.000091,"rtt":78385,"start":27.000168,"omitted":false,"stream-id":5,"retransmits":0,"tcp-window-size":16708472,"throughput-bits":849411972.5373672,"throughput-bytes":106168320}],"summary":{"end":28.000091,"start":27.000168,"omitted":false,"retransmits":0,"throughput-bits":849411972.5373672,"throughput-bytes":106168320}},{"streams":[{"end":29.000101,"rtt":78389,"start":28.000091,"omitted":false,"stream-id":5,"retransmits":0,"tcp-window-size":16708472,"throughput-bits":849338055.0851647,"throughput-bytes":106168320}],"summary":{"end":29.000101,"start":28.000091,"omitted":false,"retransmits":0,"throughput-bits":849338055.0851647,"throughput-bytes":106168320}},{"streams":[{"end":30.000094,"rtt":78386,"start":29.000101,"omitted":false,"stream-id":5,"retransmits":0,"tcp-window-size":16708472,"throughput-bits":849352483.1663066,"throughput-bytes":106168320}],"summary":{"end":30.000094,"start":29.000101,"omitted":false,"retransmits":0,"throughput-bits":849352483.1663066,"throughput-bytes":106168320}},{"streams":[{"end":31.000181,"rtt":78383,"start":30.000094,"omitted":false,"stream-id":5,"retransmits":0,"tcp-window-size":16708472,"throughput-bits":849272653.9315116,"throughput-bytes":106168320}],"summary":{"end":31.000181,"start":30.000094,"omitted":false,"retransmits":0,"throughput-bits":849272653.9315116,"throughput-bytes":106168320}},{"streams":[{"end":32.000063,"rtt":78387,"start":31.000181,"omitted":false,"stream-id":5,"retransmits":0,"tcp-window-size":16708472,"throughput-bits":859933806.9772085,"throughput-bytes":107479040}],"summary":{"end":32.000063,"start":31.000181,"omitted":false,"retransmits":0,"throughput-bits":859933806.9772085,"throughput-bytes":107479040}},{"streams":[{"end":33.000065,"rtt":78380,"start":32.000063,"omitted":false,"stream-id":5,"retransmits":0,"tcp-window-size":16708472,"throughput-bits":849344838.7534882,"throughput-bytes":106168320}],"summary":{"end":33.000065,"start":32.000063,"omitted":false,"retransmits":0,"throughput-bits":849344838.7534882,"throughput-bytes":106168320}},{"streams":[{"end":34.000064,"rtt":78383,"start":33.000065,"omitted":false,"stream-id":5,"retransmits":0,"tcp-window-size":16708472,"throughput-bits":849347420.625872,"throughput-bytes":106168320}],"summary":{"end":34.000064,"start":33.000065,"omitted":false,"retransmits":0,"throughput-bits":849347420.625872,"throughput-bytes":106168320}},{"streams":[{"end":35.000096,"rtt":78378,"start":34.000064,"omitted":false,"stream-id":5,"retransmits":0,"tcp-window-size":16708472,"throughput-bits":849319425.8668838,"throughput-bytes":106168320}],"summary":{"end":35.000096,"start":34.000064,"omitted":false,"retransmits":0,"throughput-bits":849319425.8668838,"throughput-bytes":106168320}},{"streams":[{"end":36.00007,"rtt":78384,"start":35.000096,"omitted":false,"stream-id":5,"retransmits":0,"tcp-window-size":16708472,"throughput-bits":849368633.0736268,"throughput-bytes":106168320}],"summary":{"end":36.00007,"start":35.000096,"omitted":false,"retransmits":0,"throughput-bits":849368633.0736268,"throughput-bytes":106168320}},{"streams":[{"end":37.000084,"rtt":78389,"start":36.00007,"omitted":false,"stream-id":5,"retransmits":0,"tcp-window-size":16708472,"throughput-bits":849334713.915223,"throughput-bytes":106168320}],"summary":{"end":37.000084,"start":36.00007,"omitted":false,"retransmits":0,"throughput-bits":849334713.915223,"throughput-bytes":106168320}},{"streams":[{"end":38.000088,"rtt":78386,"start":37.000084,"omitted":false,"stream-id":5,"retransmits":0,"tcp-window-size":16708472,"throughput-bits":859828835.014125,"throughput-bytes":107479040}],"summary":{"end":38.000088,"start":37.000084,"omitted":false,"retransmits":0,"throughput-bits":859828835.014125,"throughput-bytes":107479040}},{"streams":[{"end":39.00009,"rtt":78384,"start":38.000088,"omitted":false,"stream-id":5,"retransmits":0,"tcp-window-size":16708472,"throughput-bits":849344838.7534882,"throughput-bytes":106168320}],"summary":{"end":39.00009,"start":38.000088,"omitted":false,"retransmits":0,"throughput-bits":849344838.7534882,"throughput-bytes":106168320}},{"streams":[{"end":40.000152,"rtt":78390,"start":39.00009,"omitted":false,"stream-id":5,"retransmits":0,"tcp-window-size":16708472,"throughput-bits":849293913.2635096,"throughput-bytes":106168320}],"summary":{"end":40.000152,"start":39.00009,"omitted":false,"retransmits":0,"throughput-bits":849293913.2635096,"throughput-bytes":106168320}},{"streams":[{"end":41.000083,"rtt":78382,"start":40.000152,"omitted":false,"stream-id":5,"retransmits":0,"tcp-window-size":16708472,"throughput-bits":849405187.7966182,"throughput-bytes":106168320}],"summary":{"end":41.000083,"start":40.000152,"omitted":false,"retransmits":0,"throughput-bits":849405187.7966182,"throughput-bytes":106168320}},{"streams":[{"end":42.000175,"rtt":78384,"start":41.000083,"omitted":false,"stream-id":5,"retransmits":0,"tcp-window-size":16708472,"throughput-bits":849268402.1928295,"throughput-bytes":106168320}],"summary":{"end":42.000175,"start":41.000083,"omitted":false,"retransmits":0,"throughput-bits":849268402.1928295,"throughput-bytes":106168320}},{"streams":[{"end":43.000063,"rtt":78385,"start":42.000175,"omitted":false,"stream-id":5,"retransmits":0,"tcp-window-size":16708472,"throughput-bits":859928629.5363914,"throughput-bytes":107479040}],"summary":{"end":43.000063,"start":42.000175,"omitted":false,"retransmits":0,"throughput-bits":859928629.5363914,"throughput-bytes":107479040}},{"streams":[{"end":44.000064,"rtt":78381,"start":43.000063,"omitted":false,"stream-id":5,"retransmits":0,"tcp-window-size":16708472,"throughput-bits":849345750.0007725,"throughput-bytes":106168320}],"summary":{"end":44.000064,"start":43.000063,"omitted":false,"retransmits":0,"throughput-bits":849345750.0007725,"throughput-bytes":106168320}},{"streams":[{"end":45.000152,"rtt":78386,"start":44.000064,"omitted":false,"stream-id":5,"retransmits":0,"tcp-window-size":16708472,"throughput-bits":849271844.0732424,"throughput-bytes":106168320}],"summary":{"end":45.000152,"start":44.000064,"omitted":false,"retransmits":0,"throughput-bits":849271844.0732424,"throughput-bytes":106168320}},{"streams":[{"end":46.000159,"rtt":78387,"start":45.000152,"omitted":false,"stream-id":5,"retransmits":0,"tcp-window-size":16708472,"throughput-bits":849340586.2920152,"throughput-bytes":106168320}],"summary":{"end":46.000159,"start":45.000152,"omitted":false,"retransmits":0,"throughput-bits":849340586.2920152,"throughput-bytes":106168320}},{"streams":[{"end":47.00007,"rtt":78386,"start":46.000159,"omitted":false,"stream-id":5,"retransmits":0,"tcp-window-size":16708472,"throughput-bits":849422149.8517208,"throughput-bytes":106168320}],"summary":{"end":47.00007,"start":46.000159,"omitted":false,"retransmits":0,"throughput-bits":849422149.8517208,"throughput-bytes":106168320}},{"streams":[{"end":48.000165,"rtt":78385,"start":47.00007,"omitted":false,"stream-id":5,"retransmits":0,"tcp-window-size":16708472,"throughput-bits":849265871.4162065,"throughput-bytes":106168320}],"summary":{"end":48.000165,"start":47.00007,"omitted":false,"retransmits":0,"throughput-bits":849265871.4162065,"throughput-bytes":106168320}},{"streams":[{"end":49.000083,"rtt":78387,"start":48.000165,"omitted":false,"stream-id":5,"retransmits":0,"tcp-window-size":16708472,"throughput-bits":859902845.784242,"throughput-bytes":107479040}],"summary":{"end":49.000083,"start":48.000165,"omitted":false,"retransmits":0,"throughput-bits":859902845.784242,"throughput-bytes":107479040}},{"streams":[{"end":50.000155,"rtt":78388,"start":49.000083,"omitted":false,"stream-id":5,"retransmits":0,"tcp-window-size":16708472,"throughput-bits":849285409.4029905,"throughput-bytes":106168320}],"summary":{"end":50.000155,"start":49.000083,"omitted":false,"retransmits":0,"throughput-bits":849285409.4029905,"throughput-bytes":106168320}},{"streams":[{"end":51.000151,"rtt":78394,"start":50.000155,"omitted":false,"stream-id":5,"retransmits":0,"tcp-window-size":16708472,"throughput-bits":849349951.8885455,"throughput-bytes":106168320}],"summary":{"end":51.000151,"start":50.000155,"omitted":false,"retransmits":0,"throughput-bits":849349951.8885455,"throughput-bytes":106168320}},{"streams":[{"end":52.000091,"rtt":78382,"start":51.000151,"omitted":false,"stream-id":5,"retransmits":0,"tcp-window-size":16708472,"throughput-bits":849397542.4350615,"throughput-bytes":106168320}],"summary":{"end":52.000091,"start":51.000151,"omitted":false,"retransmits":0,"throughput-bits":849397542.4350615,"throughput-bytes":106168320}},{"streams":[{"end":53.000172,"rtt":78394,"start":52.000091,"omitted":false,"stream-id":5,"retransmits":0,"tcp-window-size":16708472,"throughput-bits":849277816.814287,"throughput-bytes":106168320}],"summary":{"end":53.000172,"start":52.000091,"omitted":false,"retransmits":0,"throughput-bits":849277816.814287,"throughput-bytes":106168320}},{"streams":[{"end":54.000198,"rtt":78384,"start":53.000172,"omitted":false,"stream-id":5,"retransmits":0,"tcp-window-size":16708472,"throughput-bits":859809975.5806783,"throughput-bytes":107479040}],"summary":{"end":54.000198,"start":53.000172,"omitted":false,"retransmits":0,"throughput-bits":859809975.5806783,"throughput-bytes":107479040}},{"streams":[{"end":55.00009,"rtt":78383,"start":54.000198,"omitted":false,"stream-id":5,"retransmits":0,"tcp-window-size":16708472,"throughput-bits":849438302.408512,"throughput-bytes":106168320}],"summary":{"end":55.00009,"start":54.000198,"omitted":false,"retransmits":0,"throughput-bits":849438302.408512,"throughput-bytes":106168320}},{"streams":[{"end":56.000076,"rtt":78383,"start":55.00009,"omitted":false,"stream-id":5,"retransmits":0,"tcp-window-size":16708472,"throughput-bits":849358457.041643,"throughput-bytes":106168320}],"summary":{"end":56.000076,"start":55.00009,"omitted":false,"retransmits":0,"throughput-bits":849358457.041643,"throughput-bytes":106168320}},{"streams":[{"end":57.000177,"rtt":78386,"start":56.000076,"omitted":false,"stream-id":5,"retransmits":0,"tcp-window-size":16708472,"throughput-bits":849260809.9082098,"throughput-bytes":106168320}],"summary":{"end":57.000177,"start":56.000076,"omitted":false,"retransmits":0,"throughput-bits":849260809.9082098,"throughput-bytes":106168320}},{"streams":[{"end":58.000062,"rtt":78384,"start":57.000177,"omitted":false,"stream-id":5,"retransmits":0,"tcp-window-size":16708472,"throughput-bits":849444226.854477,"throughput-bytes":106168320}],"summary":{"end":58.000062,"start":57.000177,"omitted":false,"retransmits":0,"throughput-bits":849444226.854477,"throughput-bytes":106168320}},{"streams":[{"end":59.000093,"rtt":78385,"start":58.000062,"omitted":false,"stream-id":5,"retransmits":0,"tcp-window-size":16708472,"throughput-bits":849320235.8159027,"throughput-bytes":106168320}],"summary":{"end":59.000093,"start":58.000062,"omitted":false,"retransmits":0,"throughput-bits":849320235.8159027,"throughput-bytes":106168320}},{"streams":[{"end":60.000091,"rtt":78381,"start":59.000093,"omitted":false,"stream-id":5,"retransmits":0,"tcp-window-size":16708472,"throughput-bits":859834062.5035313,"throughput-bytes":107479040}],"summary":{"end":60.000091,"start":59.000093,"omitted":false,"retransmits":0,"throughput-bits":859834062.5035313,"throughput-bytes":107479040}}],"succeeded":true}
