{"diags":"Participant 0:\n/usr/bin/iperf3 -p 5201 -B 172.16.0.2 -c 172.16.0.1 -t 10 --json --rsa-public-key-path /var/run/pscheduler-server/runner/tmp/tmpl8t620z3/tmp4s3iyn_h/public-key --username WA752SEpDOihjLNwWU4o\n\n{\n    \"end\": {\n        \"cpu_utilization_percent\": {\n            \"host_system\": 0.40604022849886556, \n            \"host_total\": 0.5250348830881455, \n            \"host_user\": 0.119004495364552, \n            \"remote_system\": 0.4907027460021065, \n            \"remote_total\": 0.8028483396043362, \n            \"remote_user\": 0.3121554271275299\n        }, \n        \"receiver_tcp_congestion\": \"htcp\", \n        \"sender_tcp_congestion\": \"htcp\", \n        \"streams\": [\n            {\n                \"receiver\": {\n                    \"bits_per_second\": 12333218.838185316, \n                    \"bytes\": 15677496, \n                    \"end\": 10.169281, \n                    \"seconds\": 10.000147, \n                    \"sender\": true, \n                    \"socket\": 5, \n                    \"start\": 0\n                }, \n                \"sender\": {\n                    \"bits_per_second\": 14889560.323463244, \n                    \"bytes\": 18612224, \n                    \"end\": 10.000147, \n                    \"max_rtt\": 222782, \n                    \"max_snd_cwnd\": 398200, \n                    \"max_snd_wnd\": 0, \n                    \"mean_rtt\": 168789, \n                    \"min_rtt\": 123237, \n                    \"retransmits\": 291, \n                    \"seconds\": 10.000147, \n                    \"sender\": true, \n                    \"socket\": 5, \n                    \"start\": 0\n                }\n            }\n        ], \n        \"sum_received\": {\n            \"bits_per_second\": 12333218.838185316, \n            \"bytes\": 15677496, \n            \"end\": 10.169281, \n            \"seconds\": 10.169281, \n            \"sender\": true, \n            \"start\": 0\n        }, \n        \"sum_sent\": {\n            \"bits_per_second\": 14889560.323463244, \n            \"bytes\": 18612224, \n            \"end\": 10.000147, \n            \"retransmits\": 291, \n            \"seconds\": 10.000147, \n            \"sender\": true, \n            \"start\": 0\n        }\n    }, \n    \"intervals\": [\n        {\n            \"streams\": [\n                {\n                    \"bits_per_second\": 44038165.59324467, \n                    \"bytes\": 5505024, \n                    \"end\": 1.000046, \n                    \"omitted\": false, \n                    \"pmtu\": 1500, \n                    \"retransmits\": 277, \n                    \"rtt\": 137028, \n                    \"rttvar\": 2567, \n                    \"seconds\": 1.0000460147857666, \n                    \"sender\": true, \n                    \"snd_cwnd\": 398200, \n                    \"snd_wnd\": -1, \n                    \"socket\": 5, \n                    \"start\": 0\n                }\n            ], \n            \"sum\": {\n                \"bits_per_second\": 44038165.59324467, \n                \"bytes\": 5505024, \n                \"end\": 1.000046, \n                \"omitted\": false, \n                \"retransmits\": 277, \n                \"seconds\": 1.0000460147857666, \n                \"sender\": true, \n                \"start\": 0\n            }\n        }, \n        {\n            \"streams\": [\n                {\n                    \"bits_per_second\": 10482929.51425674, \n                    \"bytes\": 1310720, \n                    \"end\": 2.000316, \n                    \"omitted\": false, \n                    \"pmtu\": 1500, \n                    \"retransmits\": 2, \n                    \"rtt\": 133629, \n                    \"rttvar\": 867, \n                    \"seconds\": 1.0002700090408325, \n                    \"sender\": true, \n                    \"snd_cwnd\": 204168, \n                    \"snd_wnd\": -1, \n                    \"socket\": 5, \n                    \"start\": 1.000046\n                }\n            ], \n            \"sum\": {\n                \"bits_per_second\": 10482929.51425674, \n                \"bytes\": 1310720, \n                \"end\": 2.000316, \n                \"omitted\": false, \n                \"retransmits\": 2, \n                \"seconds\": 1.0002700090408325, \n                \"sender\": true, \n                \"start\": 1.000046\n            }\n        }, \n        {\n            \"streams\": [\n                {\n                    \"bits_per_second\": 10484197.732795954, \n                    \"bytes\": 1310720, \n                    \"end\": 3.000465, \n                    \"omitted\": false, \n                    \"pmtu\": 1500, \n                    \"retransmits\": 0, \n                    \"rtt\": 161249, \n                    \"rttvar\": 1793, \n                    \"seconds\": 1.0001490116119385, \n                    \"sender\": true, \n                    \"snd_cwnd\": 212856, \n                    \"snd_wnd\": -1, \n                    \"socket\": 5, \n                    \"start\": 2.000316\n                }\n            ], \n            \"sum\": {\n                \"bits_per_second\": 10484197.732795954, \n                \"bytes\": 1310720, \n                \"end\": 3.000465, \n                \"omitted\": false, \n                \"retransmits\": 0, \n                \"seconds\": 1.0001490116119385, \n                \"sender\": true, \n                \"start\": 2.000316\n            }\n        }, \n        {\n            \"streams\": [\n                {\n                    \"bits_per_second\": 10488833.40055687, \n                    \"bytes\": 1310720, \n                    \"end\": 4.000172, \n                    \"omitted\": false, \n                    \"pmtu\": 1500, \n                    \"retransmits\": 0, \n                    \"rtt\": 153487, \n                    \"rttvar\": 1174, \n                    \"seconds\": 0.9997069835662842, \n                    \"sender\": true, \n                    \"snd_cwnd\": 231680, \n                    \"snd_wnd\": -1, \n                    \"socket\": 5, \n                    \"start\": 3.000465\n                }\n            ], \n            \"sum\": {\n                \"bits_per_second\": 10488833.40055687, \n                \"bytes\": 1310720, \n                \"end\": 4.000172, \n                \"omitted\": false, \n                \"retransmits\": 0, \n                \"seconds\": 0.9997069835662842, \n                \"sender\": true, \n                \"start\": 3.000465\n            }\n        }, \n        {\n            \"streams\": [\n                {\n                    \"bits_per_second\": 10484565.136171557, \n                    \"bytes\": 1310720, \n                    \"end\": 5.000286, \n                    \"omitted\": false, \n                    \"pmtu\": 1500, \n                    \"retransmits\": 0, \n                    \"rtt\": 219001, \n                    \"rttvar\": 3883, \n                    \"seconds\": 1.0001139640808105, \n                    \"sender\": true, \n                    \"snd_cwnd\": 264984, \n                    \"snd_wnd\": -1, \n                    \"socket\": 5, \n                    \"start\": 4.000172\n                }\n            ], \n            \"sum\": {\n                \"bits_per_second\": 10484565.136171557, \n                \"bytes\": 1310720, \n                \"end\": 5.000286, \n                \"omitted\": false, \n                \"retransmits\": 0, \n                \"seconds\": 1.0001139640808105, \n                \"sender\": true, \n                \"start\": 4.000172\n            }\n        }, \n        {\n            \"streams\": [\n                {\n                    \"bits_per_second\": 10488350.639892323, \n                    \"bytes\": 1310720, \n                    \"end\": 6.000039, \n                    \"omitted\": false, \n                    \"pmtu\": 1500, \n                    \"retransmits\": 0, \n                    \"rtt\": 158906, \n                    \"rttvar\": 514, \n                    \"seconds\": 0.9997529983520508, \n                    \"sender\": true, \n                    \"snd_cwnd\": 321456, \n                    \"snd_wnd\": -1, \n                    \"socket\": 5, \n                    \"start\": 5.000286\n                }\n            ], \n            \"sum\": {\n                \"bits_per_second\": 10488350.639892323, \n                \"bytes\": 1310720, \n                \"end\": 6.000039, \n                \"omitted\": false, \n                \"retransmits\": 0, \n                \"seconds\": 0.9997529983520508, \n                \"sender\": true, \n                \"start\": 5.000286\n            }\n        }, \n        {\n            \"streams\": [\n                {\n                    \"bits_per_second\": 20968605.40512295, \n                    \"bytes\": 2621440, \n                    \"end\": 7.000178, \n                    \"omitted\": false, \n                    \"pmtu\": 1500, \n                    \"retransmits\": 0, \n                    \"rtt\": 222782, \n                    \"rttvar\": 5974, \n                    \"seconds\": 1.0001389980316162, \n                    \"sender\": true, \n                    \"snd_cwnd\": 393856, \n                    \"snd_wnd\": -1, \n                    \"socket\": 5, \n                    \"start\": 6.000039\n                }\n            ], \n            \"sum\": {\n                \"bits_per_second\": 20968605.40512295, \n                \"bytes\": 2621440, \n                \"end\": 7.000178, \n                \"omitted\": false, \n                \"retransmits\": 0, \n                \"seconds\": 1.0001389980316162, \n                \"sender\": true, \n                \"start\": 6.000039\n            }\n        }, \n        {\n            \"streams\": [\n                {\n                    \"bits_per_second\": 10474939.926578546, \n                    \"bytes\": 1310720, \n                    \"end\": 8.001211, \n                    \"omitted\": false, \n                    \"pmtu\": 1500, \n                    \"retransmits\": 12, \n                    \"rtt\": 123237, \n                    \"rttvar\": 623, \n                    \"seconds\": 1.0010329484939575, \n                    \"sender\": true, \n                    \"snd_cwnd\": 214304, \n                    \"snd_wnd\": -1, \n                    \"socket\": 5, \n                    \"start\": 7.000178\n                }\n            ], \n            \"sum\": {\n                \"bits_per_second\": 10474939.926578546, \n                \"bytes\": 1310720, \n                \"end\": 8.001211, \n                \"omitted\": false, \n                \"retransmits\": 12, \n                \"seconds\": 1.0010329484939575, \n                \"sender\": true, \n                \"start\": 7.000178\n            }\n        }, \n        {\n            \"streams\": [\n                {\n                    \"bits_per_second\": 10497485.597387256, \n                    \"bytes\": 1310720, \n                    \"end\": 9.000094, \n                    \"omitted\": false, \n                    \"pmtu\": 1500, \n                    \"retransmits\": 0, \n                    \"rtt\": 209112, \n                    \"rttvar\": 2170, \n                    \"seconds\": 0.9988830089569092, \n                    \"sender\": true, \n                    \"snd_cwnd\": 224440, \n                    \"snd_wnd\": -1, \n                    \"socket\": 5, \n                    \"start\": 8.001211\n                }\n            ], \n            \"sum\": {\n                \"bits_per_second\": 10497485.597387256, \n                \"bytes\": 1310720, \n                \"end\": 9.000094, \n                \"omitted\": false, \n                \"retransmits\": 0, \n                \"seconds\": 0.9988830089569092, \n                \"sender\": true, \n                \"start\": 8.001211\n            }\n        }, \n        {\n            \"streams\": [\n                {\n                    \"bits_per_second\": 10485203.77950646, \n                    \"bytes\": 1310720, \n                    \"end\": 10.000147, \n                    \"omitted\": false, \n                    \"pmtu\": 1500, \n                    \"retransmits\": 0, \n                    \"rtt\": 169468, \n                    \"rttvar\": 5823, \n                    \"seconds\": 1.00005304813385, \n                    \"sender\": true, \n                    \"snd_cwnd\": 238920, \n                    \"snd_wnd\": -1, \n                    \"socket\": 5, \n                    \"start\": 9.000094\n                }\n            ], \n            \"sum\": {\n                \"bits_per_second\": 10485203.77950646, \n                \"bytes\": 1310720, \n                \"end\": 10.000147, \n                \"omitted\": false, \n                \"retransmits\": 0, \n                \"seconds\": 1.00005304813385, \n                \"sender\": true, \n                \"start\": 9.000094\n            }\n        }\n    ], \n    \"start\": {\n        \"connected\": [\n            {\n                \"local_host\": \"172.16.0.2\", \n                \"local_port\": 36809, \n                \"remote_host\": \"172.16.0.1\", \n                \"remote_port\": 5201, \n                \"socket\": 5\n            }\n        ], \n        \"connecting_to\": {\n            \"host\": \"172.16.0.1\", \n            \"port\": 5201\n        }, \n        \"cookie\": \"rsviqwdd6qqos2dvl5zyomn5pn5r2uz72cx5\", \n        \"fq_rate\": 0, \n        \"rcvbuf_actual\": 87380, \n        \"sndbuf_actual\": 65536, \n        \"sock_bufsize\": 0, \n        \"system_info\": \"REDACTED\", \n        \"target_bitrate\": 0, \n        \"tcp_mss_default\": 1448, \n        \"test_start\": {\n            \"bidir\": 0, \n            \"blksize\": 131072, \n            \"blocks\": 0, \n            \"bytes\": 0, \n            \"duration\": 10, \n            \"fqrate\": 0, \n            \"num_streams\": 1, \n            \"omit\": 0, \n            \"protocol\": \"TCP\", \n            \"reverse\": 0, \n            \"target_bitrate\": 0, \n            \"tos\": 0\n        }, \n        \"timestamp\": {\n            \"time\": \"Sat, 12 Oct 2024 02:22:18 GMT\", \n            \"timesecs\": 1728699738\n        }, \n        \"version\": \"iperf 3.14\"\n    }\n}\nParticipant 1:\n/usr/bin/iperf3 -s -1 --idle-timeout 10 --json -p 5201 -B 172.16.0.1 --authorized-users-path /var/run/pscheduler-server/runner/tmp/tmp3qtkj7nj/tmp4wfy6kar/credentials --rsa-private-key-path /var/run/pscheduler-server/runner/tmp/tmp3qtkj7nj/tmp4wfy6kar/private-key\n\n{\n    \"end\": {\n        \"cpu_utilization_percent\": {\n            \"host_system\": 0.4907027460021065, \n            \"host_total\": 0.8028483396043362, \n            \"host_user\": 0.3121554271275299, \n            \"remote_system\": 0, \n            \"remote_total\": 0, \n            \"remote_user\": 0\n        }, \n        \"receiver_tcp_congestion\": \"htcp\", \n        \"streams\": [\n            {\n                \"receiver\": {\n                    \"bits_per_second\": 12333218.838185316, \n                    \"bytes\": 15677496, \n                    \"end\": 10.169281, \n                    \"seconds\": 10.169281, \n                    \"sender\": false, \n                    \"socket\": 5, \n                    \"start\": 0\n                }, \n                \"sender\": {\n                    \"bits_per_second\": 0, \n                    \"bytes\": 0, \n                    \"end\": 10.169281, \n                    \"seconds\": 10.169281, \n                    \"sender\": false, \n                    \"socket\": 5, \n                    \"start\": 0\n                }\n            }\n        ], \n        \"sum_received\": {\n            \"bits_per_second\": 12333218.838185316, \n            \"bytes\": 15677496, \n            \"end\": 10.169281, \n            \"seconds\": 10.169281, \n            \"sender\": false, \n            \"start\": 0\n        }, \n        \"sum_sent\": {\n            \"bits_per_second\": 0, \n            \"bytes\": 0, \n            \"end\": 10.169281, \n            \"seconds\": 10.169281, \n            \"sender\": false, \n            \"start\": 0\n        }\n    }, \n    \"intervals\": [\n        {\n            \"streams\": [\n                {\n                    \"bits_per_second\": 11236177.282783281, \n                    \"bytes\": 1404560, \n                    \"end\": 1.000027, \n                    \"omitted\": false, \n                    \"seconds\": 1.0000269412994385, \n                    \"sender\": false, \n                    \"socket\": 5, \n                    \"start\": 0\n                }\n            ], \n            \"sum\": {\n                \"bits_per_second\": 11236177.282783281, \n                \"bytes\": 1404560, \n                \"end\": 1.000027, \n                \"omitted\": false, \n                \"seconds\": 1.0000269412994385, \n                \"sender\": false, \n                \"start\": 0\n            }\n        }, \n        {\n            \"streams\": [\n                {\n                    \"bits_per_second\": 13958175.890236365, \n                    \"bytes\": 1744840, \n                    \"end\": 2.000066, \n                    \"omitted\": false, \n                    \"seconds\": 1.000038981437683, \n                    \"sender\": false, \n                    \"socket\": 5, \n                    \"start\": 1.000027\n                }\n            ], \n            \"sum\": {\n                \"bits_per_second\": 13958175.890236365, \n                \"bytes\": 1744840, \n                \"end\": 2.000066, \n                \"omitted\": false, \n                \"seconds\": 1.000038981437683, \n                \"sender\": false, \n                \"start\": 1.000027\n            }\n        }, \n        {\n            \"streams\": [\n                {\n                    \"bits_per_second\": 10390722.894259892, \n                    \"bytes\": 1298856, \n                    \"end\": 3.000078, \n                    \"omitted\": false, \n                    \"seconds\": 1.0000120401382446, \n                    \"sender\": false, \n                    \"socket\": 5, \n                    \"start\": 2.000066\n                }\n            ], \n            \"sum\": {\n                \"bits_per_second\": 10390722.894259892, \n                \"bytes\": 1298856, \n                \"end\": 3.000078, \n                \"omitted\": false, \n                \"seconds\": 1.0000120401382446, \n                \"sender\": false, \n                \"start\": 2.000066\n            }\n        }, \n        {\n            \"streams\": [\n                {\n                    \"bits_per_second\": 10912477.28323633, \n                    \"bytes\": 1364016, \n                    \"end\": 4.000046, \n                    \"omitted\": false, \n                    \"seconds\": 0.9999679923057556, \n                    \"sender\": false, \n                    \"socket\": 5, \n                    \"start\": 3.000078\n                }\n            ], \n            \"sum\": {\n                \"bits_per_second\": 10912477.28323633, \n                \"bytes\": 1364016, \n                \"end\": 4.000046, \n                \"omitted\": false, \n                \"seconds\": 0.9999679923057556, \n                \"sender\": false, \n                \"start\": 3.000078\n            }\n        }, \n        {\n            \"streams\": [\n                {\n                    \"bits_per_second\": 10182152.715114119, \n                    \"bytes\": 1272792, \n                    \"end\": 5.000064, \n                    \"omitted\": false, \n                    \"seconds\": 1.0000180006027222, \n                    \"sender\": false, \n                    \"socket\": 5, \n                    \"start\": 4.000046\n                }\n            ], \n            \"sum\": {\n                \"bits_per_second\": 10182152.715114119, \n                \"bytes\": 1272792, \n                \"end\": 5.000064, \n                \"omitted\": false, \n                \"seconds\": 1.0000180006027222, \n                \"sender\": false, \n                \"start\": 4.000046\n            }\n        }, \n        {\n            \"streams\": [\n                {\n                    \"bits_per_second\": 13136282.621437617, \n                    \"bytes\": 1642032, \n                    \"end\": 6.000062, \n                    \"omitted\": false, \n                    \"seconds\": 0.9999979734420776, \n                    \"sender\": false, \n                    \"socket\": 5, \n                    \"start\": 5.000064\n                }\n            ], \n            \"sum\": {\n                \"bits_per_second\": 13136282.621437617, \n                \"bytes\": 1642032, \n                \"end\": 6.000062, \n                \"omitted\": false, \n                \"seconds\": 0.9999979734420776, \n                \"sender\": false, \n                \"start\": 5.000064\n            }\n        }, \n        {\n            \"streams\": [\n                {\n                    \"bits_per_second\": 15256051.61615087, \n                    \"bytes\": 1907016, \n                    \"end\": 7.000067, \n                    \"omitted\": false, \n                    \"seconds\": 1.0000050067901611, \n                    \"sender\": false, \n                    \"socket\": 5, \n                    \"start\": 6.000062\n                }\n            ], \n            \"sum\": {\n                \"bits_per_second\": 15256051.61615087, \n                \"bytes\": 1907016, \n                \"end\": 7.000067, \n                \"omitted\": false, \n                \"seconds\": 1.0000050067901611, \n                \"sender\": false, \n                \"start\": 6.000062\n            }\n        }, \n        {\n            \"streams\": [\n                {\n                    \"bits_per_second\": 17035549.5410302, \n                    \"bytes\": 2130008, \n                    \"end\": 8.000332, \n                    \"omitted\": false, \n                    \"seconds\": 1.0002650022506714, \n                    \"sender\": false, \n                    \"socket\": 5, \n                    \"start\": 7.000067\n                }\n            ], \n            \"sum\": {\n                \"bits_per_second\": 17035549.5410302, \n                \"bytes\": 2130008, \n                \"end\": 8.000332, \n                \"omitted\": false, \n                \"seconds\": 1.0002650022506714, \n                \"sender\": false, \n                \"start\": 7.000067\n            }\n        }, \n        {\n            \"streams\": [\n                {\n                    \"bits_per_second\": 11587105.141205482, \n                    \"bytes\": 1448000, \n                    \"end\": 9.000064, \n                    \"omitted\": false, \n                    \"seconds\": 0.99973201751709, \n                    \"sender\": false, \n                    \"socket\": 5, \n                    \"start\": 8.000332\n                }\n            ], \n            \"sum\": {\n                \"bits_per_second\": 11587105.141205482, \n                \"bytes\": 1448000, \n                \"end\": 9.000064, \n                \"omitted\": false, \n                \"seconds\": 0.99973201751709, \n                \"sender\": false, \n                \"start\": 8.000332\n            }\n        }, \n        {\n            \"streams\": [\n                {\n                    \"bits_per_second\": 9855174.98527553, \n                    \"bytes\": 1232248, \n                    \"end\": 10.000349, \n                    \"omitted\": false, \n                    \"seconds\": 1.000285029411316, \n                    \"sender\": false, \n                    \"socket\": 5, \n                    \"start\": 9.000064\n                }\n            ], \n            \"sum\": {\n                \"bits_per_second\": 9855174.98527553, \n                \"bytes\": 1232248, \n                \"end\": 10.000349, \n                \"omitted\": false, \n                \"seconds\": 1.000285029411316, \n                \"sender\": false, \n                \"start\": 9.000064\n            }\n        }, \n        {\n            \"streams\": [\n                {\n                    \"bits_per_second\": 11040086.75902366, \n                    \"bytes\": 233128, \n                    \"end\": 10.169281, \n                    \"omitted\": false, \n                    \"seconds\": 0.1689320057630539, \n                    \"sender\": false, \n                    \"socket\": 5, \n                    \"start\": 10.000349\n                }\n            ], \n            \"sum\": {\n                \"bits_per_second\": 11040086.75902366, \n                \"bytes\": 233128, \n                \"end\": 10.169281, \n                \"omitted\": false, \n                \"seconds\": 0.1689320057630539, \n                \"sender\": false, \n                \"start\": 10.000349\n            }\n        }\n    ], \n    \"start\": {\n        \"accepted_connection\": {\n            \"host\": \"172.16.0.2\", \n            \"port\": 56931\n        }, \n        \"connected\": [\n            {\n                \"local_host\": \"172.16.0.1\", \n                \"local_port\": 5201, \n                \"remote_host\": \"172.16.0.2\", \n                \"remote_port\": 36809, \n                \"socket\": 5\n            }\n        ], \n        \"cookie\": \"rsviqwdd6qqos2dvl5zyomn5pn5r2uz72cx5\", \n        \"fq_rate\": 0, \n        \"rcvbuf_actual\": 87380, \n        \"sndbuf_actual\": 65536, \n        \"sock_bufsize\": 0, \n        \"system_info\": \"REDACTED\", \n        \"target_bitrate\": 0, \n        \"tcp_mss_default\": 0, \n        \"test_start\": {\n            \"bidir\": 0, \n            \"blksize\": 131072, \n            \"blocks\": 0, \n            \"bytes\": 0, \n            \"duration\": 10, \n            \"fqrate\": 0, \n            \"num_streams\": 1, \n            \"omit\": 0, \n            \"protocol\": \"TCP\", \n            \"reverse\": 0, \n            \"target_bitrate\": 0, \n            \"tos\": 0\n        }, \n        \"timestamp\": {\n            \"time\": \"Sat, 12 Oct 2024 02:22:18 GMT\", \n            \"timesecs\": 1728699738\n        }, \n        \"version\": \"iperf 3.14\"\n    }\n}\n","summary":{"streams":[{"end":10.000147,"rtt":168789,"start":0,"stream-id":5,"retransmits":291,"throughput-bits":14889560.323463244,"throughput-bytes":18612224}],"summary":{"end":10.000147,"start":0,"retransmits":291,"throughput-bits":14889560.323463244,"throughput-bytes":18612224,"receiver-throughput-bits":12333218.838185316}},"intervals":[{"streams":[{"end":1.000046,"rtt":137028,"start":0,"omitted":false,"stream-id":5,"retransmits":277,"tcp-window-size":398200,"throughput-bits":44038165.59324467,"throughput-bytes":5505024}],"summary":{"end":1.000046,"start":0,"omitted":false,"retransmits":277,"throughput-bits":44038165.59324467,"throughput-bytes":5505024}},{"streams":[{"end":2.000316,"rtt":133629,"start":1.000046,"omitted":false,"stream-id":5,"retransmits":2,"tcp-window-size":204168,"throughput-bits":10482929.51425674,"throughput-bytes":1310720}],"summary":{"end":2.000316,"start":1.000046,"omitted":false,"retransmits":2,"throughput-bits":10482929.51425674,"throughput-bytes":1310720}},{"streams":[{"end":3.000465,"rtt":161249,"start":2.000316,"omitted":false,"stream-id":5,"retransmits":0,"tcp-window-size":212856,"throughput-bits":10484197.732795954,"throughput-bytes":1310720}],"summary":{"end":3.000465,"start":2.000316,"omitted":false,"retransmits":0,"throughput-bits":10484197.732795954,"throughput-bytes":1310720}},{"streams":[{"end":4.000172,"rtt":153487,"start":3.000465,"omitted":false,"stream-id":5,"retransmits":0,"tcp-window-size":231680,"throughput-bits":10488833.40055687,"throughput-bytes":1310720}],"summary":{"end":4.000172,"start":3.000465,"omitted":false,"retransmits":0,"throughput-bits":10488833.40055687,"throughput-bytes":1310720}},{"streams":[{"end":5.000286,"rtt":219001,"start":4.000172,"omitted":false,"stream-id":5,"retransmits":0,"tcp-window-size":264984,"throughput-bits":10484565.136171557,"throughput-bytes":1310720}],"summary":{"end":5.000286,"start":4.000172,"omitted":false,"retransmits":0,"throughput-bits":10484565.136171557,"throughput-bytes":1310720}},{"streams":[{"end":6.000039,"rtt":158906,"start":5.000286,"omitted":false,"stream-id":5,"retransmits":0,"tcp-window-size":321456,"throughput-bits":10488350.639892323,"throughput-bytes":1310720}],"summary":{"end":6.000039,"start":5.000286,"omitted":false,"retransmits":0,"throughput-bits":10488350.639892323,"throughput-bytes":1310720}},{"streams":[{"end":7.000178,"rtt":222782,"start":6.000039,"omitted":false,"stream-id":5,"retransmits":0,"tcp-window-size":393856,"throughput-bits":20968605.40512295,"throughput-bytes":2621440}],"summary":{"end":7.000178,"start":6.000039,"omitted":false,"retransmits":0,"throughput-bits":20968605.40512295,"throughput-bytes":2621440}},{"streams":[{"end":8.001211,"rtt":123237,"start":7.000178,"omitted":false,"stream-id":5,"retransmits":12,"tcp-window-size":214304,"throughput-bits":10474939.926578546,"throughput-bytes":1310720}],"summary":{"end":8.001211,"start":7.000178,"omitted":false,"retransmits":12,"throughput-bits":10474939.926578546,"throughput-bytes":1310720}},{"streams":[{"end":9.000094,"rtt":209112,"start":8.001211,"omitted":false,"stream-id":5,"retransmits":0,"tcp-window-size":224440,"throughput-bits":10497485.597387256,"throughput-bytes":1310720}],"summary":{"end":9.000094,"start":8.001211,"omitted":false,"retransmits":0,"throughput-bits":10497485.597387256,"throughput-bytes":1310720}},{"streams":[{"end":10.000147,"rtt":169468,"start":9.000094,"omitted":false,"stream-id":5,"retransmits":0,"tcp-window-size":238920,"throughput-bits":10485203.77950646,"throughput-bytes":1310720}],"summary":{"end":10.000147,"start":9.000094,"omitted":false,"retransmits":0,"throughput-bits":10485203.77950646,"throughput-bytes":1310720}}],"succeeded":true}
