{"diags":"Participant 0:\n/usr/bin/iperf3 -p 5201 -B 172.16.0.2 -c 172.16.0.1 -t 10 --json --rsa-public-key-path /var/run/pscheduler-server/runner/tmp/tmpeagdfhe9/tmpl6kptpgo/public-key --username fhswzmJn4qFU7rf8wIPA\n\n{\n    \"end\": {\n        \"cpu_utilization_percent\": {\n            \"host_system\": 0.21193507905584666, \n            \"host_total\": 0.2618277376891495, \n            \"host_user\": 0.04990254228200205, \n            \"remote_system\": 0.877826438706866, \n            \"remote_total\": 0.962365415703789, \n            \"remote_user\": 0.08454867405783113\n        }, \n        \"receiver_tcp_congestion\": \"htcp\", \n        \"sender_tcp_congestion\": \"htcp\", \n        \"streams\": [\n            {\n                \"receiver\": {\n                    \"bits_per_second\": 10123256.345713712, \n                    \"bytes\": 13049376, \n                    \"end\": 10.312394, \n                    \"seconds\": 10.000816, \n                    \"sender\": true, \n                    \"socket\": 5, \n                    \"start\": 0\n                }, \n                \"sender\": {\n                    \"bits_per_second\": 12791583.406794006, \n                    \"bytes\": 15990784, \n                    \"end\": 10.000816, \n                    \"max_rtt\": 294159, \n                    \"max_snd_cwnd\": 395304, \n                    \"max_snd_wnd\": 0, \n                    \"mean_rtt\": 220694, \n                    \"min_rtt\": 140920, \n                    \"retransmits\": 278, \n                    \"seconds\": 10.000816, \n                    \"sender\": true, \n                    \"socket\": 5, \n                    \"start\": 0\n                }\n            }\n        ], \n        \"sum_received\": {\n            \"bits_per_second\": 10123256.345713712, \n            \"bytes\": 13049376, \n            \"end\": 10.312394, \n            \"seconds\": 10.312394, \n            \"sender\": true, \n            \"start\": 0\n        }, \n        \"sum_sent\": {\n            \"bits_per_second\": 12791583.406794006, \n            \"bytes\": 15990784, \n            \"end\": 10.000816, \n            \"retransmits\": 278, \n            \"seconds\": 10.000816, \n            \"sender\": true, \n            \"start\": 0\n        }\n    }, \n    \"intervals\": [\n        {\n            \"streams\": [\n                {\n                    \"bits_per_second\": 44032444.363219246, \n                    \"bytes\": 5505024, \n                    \"end\": 1.000176, \n                    \"omitted\": false, \n                    \"pmtu\": 1500, \n                    \"retransmits\": 278, \n                    \"rtt\": 263150, \n                    \"rttvar\": 1467, \n                    \"seconds\": 1.000175952911377, \n                    \"sender\": true, \n                    \"snd_cwnd\": 395304, \n                    \"snd_wnd\": -1, \n                    \"socket\": 5, \n                    \"start\": 0\n                }\n            ], \n            \"sum\": {\n                \"bits_per_second\": 44032444.363219246, \n                \"bytes\": 5505024, \n                \"end\": 1.000176, \n                \"omitted\": false, \n                \"retransmits\": 278, \n                \"seconds\": 1.000175952911377, \n                \"sender\": true, \n                \"start\": 0\n            }\n        }, \n        {\n            \"streams\": [\n                {\n                    \"bits_per_second\": 10486053.7582294, \n                    \"bytes\": 1310720, \n                    \"end\": 2.000148, \n                    \"omitted\": false, \n                    \"pmtu\": 1500, \n                    \"retransmits\": 0, \n                    \"rtt\": 140920, \n                    \"rttvar\": 1395, \n                    \"seconds\": 0.9999719858169556, \n                    \"sender\": true, \n                    \"snd_cwnd\": 199824, \n                    \"snd_wnd\": -1, \n                    \"socket\": 5, \n                    \"start\": 1.000176\n                }\n            ], \n            \"sum\": {\n                \"bits_per_second\": 10486053.7582294, \n                \"bytes\": 1310720, \n                \"end\": 2.000148, \n                \"omitted\": false, \n                \"retransmits\": 0, \n                \"seconds\": 0.9999719858169556, \n                \"sender\": true, \n                \"start\": 1.000176\n            }\n        }, \n        {\n            \"streams\": [\n                {\n                    \"bits_per_second\": 10484952.562180141, \n                    \"bytes\": 1310720, \n                    \"end\": 3.000225, \n                    \"omitted\": false, \n                    \"pmtu\": 1500, \n                    \"retransmits\": 0, \n                    \"rtt\": 143938, \n                    \"rttvar\": 1495, \n                    \"seconds\": 1.00007700920105, \n                    \"sender\": true, \n                    \"snd_cwnd\": 209960, \n                    \"snd_wnd\": -1, \n                    \"socket\": 5, \n                    \"start\": 2.000148\n                }\n            ], \n            \"sum\": {\n                \"bits_per_second\": 10484952.562180141, \n                \"bytes\": 1310720, \n                \"end\": 3.000225, \n                \"omitted\": false, \n                \"retransmits\": 0, \n                \"seconds\": 1.00007700920105, \n                \"sender\": true, \n                \"start\": 2.000148\n            }\n        }, \n        {\n            \"streams\": [\n                {\n                    \"bits_per_second\": 10485320.01846236, \n                    \"bytes\": 1310720, \n                    \"end\": 4.000267, \n                    \"omitted\": false, \n                    \"pmtu\": 1500, \n                    \"retransmits\": 0, \n                    \"rtt\": 196838, \n                    \"rttvar\": 3266, \n                    \"seconds\": 1.0000419616699219, \n                    \"sender\": true, \n                    \"snd_cwnd\": 218648, \n                    \"snd_wnd\": -1, \n                    \"socket\": 5, \n                    \"start\": 3.000225\n                }\n            ], \n            \"sum\": {\n                \"bits_per_second\": 10485320.01846236, \n                \"bytes\": 1310720, \n                \"end\": 4.000267, \n                \"omitted\": false, \n                \"retransmits\": 0, \n                \"seconds\": 1.0000419616699219, \n                \"sender\": true, \n                \"start\": 3.000225\n            }\n        }, \n        {\n            \"streams\": [\n                {\n                    \"bits_per_second\": 0, \n                    \"bytes\": 0, \n                    \"end\": 5.001422, \n                    \"omitted\": false, \n                    \"pmtu\": 1500, \n                    \"retransmits\": 0, \n                    \"rtt\": 204153, \n                    \"rttvar\": 5247, \n                    \"seconds\": 1.0011550188064575, \n                    \"sender\": true, \n                    \"snd_cwnd\": 227336, \n                    \"snd_wnd\": -1, \n                    \"socket\": 5, \n                    \"start\": 4.000267\n                }\n            ], \n            \"sum\": {\n                \"bits_per_second\": 0, \n                \"bytes\": 0, \n                \"end\": 5.001422, \n                \"omitted\": false, \n                \"retransmits\": 0, \n                \"seconds\": 1.0011550188064575, \n                \"sender\": true, \n                \"start\": 4.000267\n            }\n        }, \n        {\n            \"streams\": [\n                {\n                    \"bits_per_second\": 10490637.893102413, \n                    \"bytes\": 1310720, \n                    \"end\": 6.000957, \n                    \"omitted\": false, \n                    \"pmtu\": 1500, \n                    \"retransmits\": 0, \n                    \"rtt\": 194226, \n                    \"rttvar\": 1682, \n                    \"seconds\": 0.9995350241661072, \n                    \"sender\": true, \n                    \"snd_cwnd\": 247608, \n                    \"snd_wnd\": -1, \n                    \"socket\": 5, \n                    \"start\": 5.001422\n                }\n            ], \n            \"sum\": {\n                \"bits_per_second\": 10490637.893102413, \n                \"bytes\": 1310720, \n                \"end\": 6.000957, \n                \"omitted\": false, \n                \"retransmits\": 0, \n                \"seconds\": 0.9995350241661072, \n                \"sender\": true, \n                \"start\": 5.001422\n            }\n        }, \n        {\n            \"streams\": [\n                {\n                    \"bits_per_second\": 10486420.666623391, \n                    \"bytes\": 1310720, \n                    \"end\": 7.000894, \n                    \"omitted\": false, \n                    \"pmtu\": 1500, \n                    \"retransmits\": 0, \n                    \"rtt\": 228580, \n                    \"rttvar\": 5642, \n                    \"seconds\": 0.9999369978904724, \n                    \"sender\": true, \n                    \"snd_cwnd\": 280912, \n                    \"snd_wnd\": -1, \n                    \"socket\": 5, \n                    \"start\": 6.000957\n                }\n            ], \n            \"sum\": {\n                \"bits_per_second\": 10486420.666623391, \n                \"bytes\": 1310720, \n                \"end\": 7.000894, \n                \"omitted\": false, \n                \"retransmits\": 0, \n                \"seconds\": 0.9999369978904724, \n                \"sender\": true, \n                \"start\": 6.000957\n            }\n        }, \n        {\n            \"streams\": [\n                {\n                    \"bits_per_second\": 10485550.00420562, \n                    \"bytes\": 1310720, \n                    \"end\": 8.000914, \n                    \"omitted\": false, \n                    \"pmtu\": 1500, \n                    \"retransmits\": 0, \n                    \"rtt\": 292483, \n                    \"rttvar\": 3109, \n                    \"seconds\": 1.0000200271606445, \n                    \"sender\": true, \n                    \"snd_cwnd\": 305528, \n                    \"snd_wnd\": -1, \n                    \"socket\": 5, \n                    \"start\": 7.000894\n                }\n            ], \n            \"sum\": {\n                \"bits_per_second\": 10485550.00420562, \n                \"bytes\": 1310720, \n                \"end\": 8.000914, \n                \"omitted\": false, \n                \"retransmits\": 0, \n                \"seconds\": 1.0000200271606445, \n                \"sender\": true, \n                \"start\": 7.000894\n            }\n        }, \n        {\n            \"streams\": [\n                {\n                    \"bits_per_second\": 10488161.800014714, \n                    \"bytes\": 1310720, \n                    \"end\": 9.000685, \n                    \"omitted\": false, \n                    \"pmtu\": 1500, \n                    \"retransmits\": 0, \n                    \"rtt\": 248500, \n                    \"rttvar\": 2328, \n                    \"seconds\": 0.999770998954773, \n                    \"sender\": true, \n                    \"snd_cwnd\": 350416, \n                    \"snd_wnd\": -1, \n                    \"socket\": 5, \n                    \"start\": 8.000914\n                }\n            ], \n            \"sum\": {\n                \"bits_per_second\": 10488161.800014714, \n                \"bytes\": 1310720, \n                \"end\": 9.000685, \n                \"omitted\": false, \n                \"retransmits\": 0, \n                \"seconds\": 0.999770998954773, \n                \"sender\": true, \n                \"start\": 8.000914\n            }\n        }, \n        {\n            \"streams\": [\n                {\n                    \"bits_per_second\": 10484386.4299528, \n                    \"bytes\": 1310720, \n                    \"end\": 10.000816, \n                    \"omitted\": false, \n                    \"pmtu\": 1500, \n                    \"retransmits\": 0, \n                    \"rtt\": 294159, \n                    \"rttvar\": 8852, \n                    \"seconds\": 1.0001310110092163, \n                    \"sender\": true, \n                    \"snd_cwnd\": 392408, \n                    \"snd_wnd\": -1, \n                    \"socket\": 5, \n                    \"start\": 9.000685\n                }\n            ], \n            \"sum\": {\n                \"bits_per_second\": 10484386.4299528, \n                \"bytes\": 1310720, \n                \"end\": 10.000816, \n                \"omitted\": false, \n                \"retransmits\": 0, \n                \"seconds\": 1.0001310110092163, \n                \"sender\": true, \n                \"start\": 9.000685\n            }\n        }\n    ], \n    \"start\": {\n        \"connected\": [\n            {\n                \"local_host\": \"172.16.0.2\", \n                \"local_port\": 44665, \n                \"remote_host\": \"172.16.0.1\", \n                \"remote_port\": 5201, \n                \"socket\": 5\n            }\n        ], \n        \"connecting_to\": {\n            \"host\": \"172.16.0.1\", \n            \"port\": 5201\n        }, \n        \"cookie\": \"zfhy7u3y7pzezoxtglrqxw4o47d3fjvjgh7c\", \n        \"fq_rate\": 0, \n        \"rcvbuf_actual\": 87380, \n        \"sndbuf_actual\": 65536, \n        \"sock_bufsize\": 0, \n        \"system_info\": \"REDACTED\", \n        \"target_bitrate\": 0, \n        \"tcp_mss_default\": 1448, \n        \"test_start\": {\n            \"bidir\": 0, \n            \"blksize\": 131072, \n            \"blocks\": 0, \n            \"bytes\": 0, \n            \"duration\": 10, \n            \"fqrate\": 0, \n            \"num_streams\": 1, \n            \"omit\": 0, \n            \"protocol\": \"TCP\", \n            \"reverse\": 0, \n            \"target_bitrate\": 0, \n            \"tos\": 0\n        }, \n        \"timestamp\": {\n            \"time\": \"Sat, 12 Oct 2024 02:34:18 GMT\", \n            \"timesecs\": 1728700458\n        }, \n        \"version\": \"iperf 3.14\"\n    }\n}\nParticipant 1:\n/usr/bin/iperf3 -s -1 --idle-timeout 10 --json -p 5201 -B 172.16.0.1 --authorized-users-path /var/run/pscheduler-server/runner/tmp/tmpd6bayphr/tmph6d5nd_5/credentials --rsa-private-key-path /var/run/pscheduler-server/runner/tmp/tmpd6bayphr/tmph6d5nd_5/private-key\n\n{\n    \"end\": {\n        \"cpu_utilization_percent\": {\n            \"host_system\": 0.877826438706866, \n            \"host_total\": 0.962365415703789, \n            \"host_user\": 0.08454867405783113, \n            \"remote_system\": 0, \n            \"remote_total\": 0, \n            \"remote_user\": 0\n        }, \n        \"receiver_tcp_congestion\": \"htcp\", \n        \"streams\": [\n            {\n                \"receiver\": {\n                    \"bits_per_second\": 10123256.345713712, \n                    \"bytes\": 13049376, \n                    \"end\": 10.312394, \n                    \"seconds\": 10.312394, \n                    \"sender\": false, \n                    \"socket\": 5, \n                    \"start\": 0\n                }, \n                \"sender\": {\n                    \"bits_per_second\": 0, \n                    \"bytes\": 0, \n                    \"end\": 10.312394, \n                    \"seconds\": 10.312394, \n                    \"sender\": false, \n                    \"socket\": 5, \n                    \"start\": 0\n                }\n            }\n        ], \n        \"sum_received\": {\n            \"bits_per_second\": 10123256.345713712, \n            \"bytes\": 13049376, \n            \"end\": 10.312394, \n            \"seconds\": 10.312394, \n            \"sender\": false, \n            \"start\": 0\n        }, \n        \"sum_sent\": {\n            \"bits_per_second\": 0, \n            \"bytes\": 0, \n            \"end\": 10.312394, \n            \"seconds\": 10.312394, \n            \"sender\": false, \n            \"start\": 0\n        }\n    }, \n    \"intervals\": [\n        {\n            \"streams\": [\n                {\n                    \"bits_per_second\": 12602989.35856675, \n                    \"bytes\": 1575424, \n                    \"end\": 1.000032, \n                    \"omitted\": false, \n                    \"seconds\": 1.0000319480895996, \n                    \"sender\": false, \n                    \"socket\": 5, \n                    \"start\": 0\n                }\n            ], \n            \"sum\": {\n                \"bits_per_second\": 12602989.35856675, \n                \"bytes\": 1575424, \n                \"end\": 1.000032, \n                \"omitted\": false, \n                \"seconds\": 1.0000319480895996, \n                \"sender\": false, \n                \"start\": 0\n            }\n        }, \n        {\n            \"streams\": [\n                {\n                    \"bits_per_second\": 8803593.374523757, \n                    \"bytes\": 1100480, \n                    \"end\": 2.00006, \n                    \"omitted\": false, \n                    \"seconds\": 1.0000280141830444, \n                    \"sender\": false, \n                    \"socket\": 5, \n                    \"start\": 1.000032\n                }\n            ], \n            \"sum\": {\n                \"bits_per_second\": 8803593.374523757, \n                \"bytes\": 1100480, \n                \"end\": 2.00006, \n                \"omitted\": false, \n                \"seconds\": 1.0000280141830444, \n                \"sender\": false, \n                \"start\": 1.000032\n            }\n        }, \n        {\n            \"streams\": [\n                {\n                    \"bits_per_second\": 11143752.2055711, \n                    \"bytes\": 1392976, \n                    \"end\": 3.000065, \n                    \"omitted\": false, \n                    \"seconds\": 1.0000050067901611, \n                    \"sender\": false, \n                    \"socket\": 5, \n                    \"start\": 2.00006\n                }\n            ], \n            \"sum\": {\n                \"bits_per_second\": 11143752.2055711, \n                \"bytes\": 1392976, \n                \"end\": 3.000065, \n                \"omitted\": false, \n                \"seconds\": 1.0000050067901611, \n                \"sender\": false, \n                \"start\": 2.00006\n            }\n        }, \n        {\n            \"streams\": [\n                {\n                    \"bits_per_second\": 10242324.900718773, \n                    \"bytes\": 1281480, \n                    \"end\": 4.000994, \n                    \"omitted\": false, \n                    \"seconds\": 1.0009289979934692, \n                    \"sender\": false, \n                    \"socket\": 5, \n                    \"start\": 3.000065\n                }\n            ], \n            \"sum\": {\n                \"bits_per_second\": 10242324.900718773, \n                \"bytes\": 1281480, \n                \"end\": 4.000994, \n                \"omitted\": false, \n                \"seconds\": 1.0009289979934692, \n                \"sender\": false, \n                \"start\": 3.000065\n            }\n        }, \n        {\n            \"streams\": [\n                {\n                    \"bits_per_second\": 7965472.595996818, \n                    \"bytes\": 994776, \n                    \"end\": 5.000082, \n                    \"omitted\": false, \n                    \"seconds\": 0.9990879893302917, \n                    \"sender\": false, \n                    \"socket\": 5, \n                    \"start\": 4.000994\n                }\n            ], \n            \"sum\": {\n                \"bits_per_second\": 7965472.595996818, \n                \"bytes\": 994776, \n                \"end\": 5.000082, \n                \"omitted\": false, \n                \"seconds\": 0.9990879893302917, \n                \"sender\": false, \n                \"start\": 4.000994\n            }\n        }, \n        {\n            \"streams\": [\n                {\n                    \"bits_per_second\": 8988096.46343727, \n                    \"bytes\": 1123648, \n                    \"end\": 6.000203, \n                    \"omitted\": false, \n                    \"seconds\": 1.000120997428894, \n                    \"sender\": false, \n                    \"socket\": 5, \n                    \"start\": 5.000082\n                }\n            ], \n            \"sum\": {\n                \"bits_per_second\": 8988096.46343727, \n                \"bytes\": 1123648, \n                \"end\": 6.000203, \n                \"omitted\": false, \n                \"seconds\": 1.000120997428894, \n                \"sender\": false, \n                \"start\": 5.000082\n            }\n        }, \n        {\n            \"streams\": [\n                {\n                    \"bits_per_second\": 11470178.895046536, \n                    \"bytes\": 1433520, \n                    \"end\": 7.000027, \n                    \"omitted\": false, \n                    \"seconds\": 0.9998239874839783, \n                    \"sender\": false, \n                    \"socket\": 5, \n                    \"start\": 6.000203\n                }\n            ], \n            \"sum\": {\n                \"bits_per_second\": 11470178.895046536, \n                \"bytes\": 1433520, \n                \"end\": 7.000027, \n                \"omitted\": false, \n                \"seconds\": 0.9998239874839783, \n                \"sender\": false, \n                \"start\": 6.000203\n            }\n        }, \n        {\n            \"streams\": [\n                {\n                    \"bits_per_second\": 7680115.094550616, \n                    \"bytes\": 960024, \n                    \"end\": 8.000037, \n                    \"omitted\": false, \n                    \"seconds\": 1.0000100135803223, \n                    \"sender\": false, \n                    \"socket\": 5, \n                    \"start\": 7.000027\n                }\n            ], \n            \"sum\": {\n                \"bits_per_second\": 7680115.094550616, \n                \"bytes\": 960024, \n                \"end\": 8.000037, \n                \"omitted\": false, \n                \"seconds\": 1.0000100135803223, \n                \"sender\": false, \n                \"start\": 7.000027\n            }\n        }, \n        {\n            \"streams\": [\n                {\n                    \"bits_per_second\": 11835569.045677405, \n                    \"bytes\": 1479856, \n                    \"end\": 9.000314, \n                    \"omitted\": false, \n                    \"seconds\": 1.000277042388916, \n                    \"sender\": false, \n                    \"socket\": 5, \n                    \"start\": 8.000037\n                }\n            ], \n            \"sum\": {\n                \"bits_per_second\": 11835569.045677405, \n                \"bytes\": 1479856, \n                \"end\": 9.000314, \n                \"omitted\": false, \n                \"seconds\": 1.000277042388916, \n                \"sender\": false, \n                \"start\": 8.000037\n            }\n        }, \n        {\n            \"streams\": [\n                {\n                    \"bits_per_second\": 10671574.317263953, \n                    \"bytes\": 1333608, \n                    \"end\": 10.00006, \n                    \"omitted\": false, \n                    \"seconds\": 0.999746024608612, \n                    \"sender\": false, \n                    \"socket\": 5, \n                    \"start\": 9.000314\n                }\n            ], \n            \"sum\": {\n                \"bits_per_second\": 10671574.317263953, \n                \"bytes\": 1333608, \n                \"end\": 10.00006, \n                \"omitted\": false, \n                \"seconds\": 0.999746024608612, \n                \"sender\": false, \n                \"start\": 9.000314\n            }\n        }, \n        {\n            \"streams\": [\n                {\n                    \"bits_per_second\": 9568833.33167662, \n                    \"bytes\": 373584, \n                    \"end\": 10.312394, \n                    \"omitted\": false, \n                    \"seconds\": 0.31233400106430054, \n                    \"sender\": false, \n                    \"socket\": 5, \n                    \"start\": 10.00006\n                }\n            ], \n            \"sum\": {\n                \"bits_per_second\": 9568833.33167662, \n                \"bytes\": 373584, \n                \"end\": 10.312394, \n                \"omitted\": false, \n                \"seconds\": 0.31233400106430054, \n                \"sender\": false, \n                \"start\": 10.00006\n            }\n        }\n    ], \n    \"start\": {\n        \"accepted_connection\": {\n            \"host\": \"172.16.0.2\", \n            \"port\": 56199\n        }, \n        \"connected\": [\n            {\n                \"local_host\": \"172.16.0.1\", \n                \"local_port\": 5201, \n                \"remote_host\": \"172.16.0.2\", \n                \"remote_port\": 44665, \n                \"socket\": 5\n            }\n        ], \n        \"cookie\": \"zfhy7u3y7pzezoxtglrqxw4o47d3fjvjgh7c\", \n        \"fq_rate\": 0, \n        \"rcvbuf_actual\": 87380, \n        \"sndbuf_actual\": 65536, \n        \"sock_bufsize\": 0, \n        \"system_info\": \"REDACTED\", \n        \"target_bitrate\": 0, \n        \"tcp_mss_default\": 0, \n        \"test_start\": {\n            \"bidir\": 0, \n            \"blksize\": 131072, \n            \"blocks\": 0, \n            \"bytes\": 0, \n            \"duration\": 10, \n            \"fqrate\": 0, \n            \"num_streams\": 1, \n            \"omit\": 0, \n            \"protocol\": \"TCP\", \n            \"reverse\": 0, \n            \"target_bitrate\": 0, \n            \"tos\": 0\n        }, \n        \"timestamp\": {\n            \"time\": \"Sat, 12 Oct 2024 02:34:18 GMT\", \n            \"timesecs\": 1728700458\n        }, \n        \"version\": \"iperf 3.14\"\n    }\n}\n","summary":{"streams":[{"end":10.000816,"rtt":220694,"start":0,"stream-id":5,"retransmits":278,"throughput-bits":12791583.406794006,"throughput-bytes":15990784}],"summary":{"end":10.000816,"start":0,"retransmits":278,"throughput-bits":12791583.406794006,"throughput-bytes":15990784,"receiver-throughput-bits":10123256.345713712}},"intervals":[{"streams":[{"end":1.000176,"rtt":263150,"start":0,"omitted":false,"stream-id":5,"retransmits":278,"tcp-window-size":395304,"throughput-bits":44032444.363219246,"throughput-bytes":5505024}],"summary":{"end":1.000176,"start":0,"omitted":false,"retransmits":278,"throughput-bits":44032444.363219246,"throughput-bytes":5505024}},{"streams":[{"end":2.000148,"rtt":140920,"start":1.000176,"omitted":false,"stream-id":5,"retransmits":0,"tcp-window-size":199824,"throughput-bits":10486053.7582294,"throughput-bytes":1310720}],"summary":{"end":2.000148,"start":1.000176,"omitted":false,"retransmits":0,"throughput-bits":10486053.7582294,"throughput-bytes":1310720}},{"streams":[{"end":3.000225,"rtt":143938,"start":2.000148,"omitted":false,"stream-id":5,"retransmits":0,"tcp-window-size":209960,"throughput-bits":10484952.562180141,"throughput-bytes":1310720}],"summary":{"end":3.000225,"start":2.000148,"omitted":false,"retransmits":0,"throughput-bits":10484952.562180141,"throughput-bytes":1310720}},{"streams":[{"end":4.000267,"rtt":196838,"start":3.000225,"omitted":false,"stream-id":5,"retransmits":0,"tcp-window-size":218648,"throughput-bits":10485320.01846236,"throughput-bytes":1310720}],"summary":{"end":4.000267,"start":3.000225,"omitted":false,"retransmits":0,"throughput-bits":10485320.01846236,"throughput-bytes":1310720}},{"streams":[{"end":5.001422,"rtt":204153,"start":4.000267,"omitted":false,"stream-id":5,"retransmits":0,"tcp-window-size":227336,"throughput-bits":0,"throughput-bytes":0}],"summary":{"end":5.001422,"start":4.000267,"omitted":false,"retransmits":0,"throughput-bits":0,"throughput-bytes":0}},{"streams":[{"end":6.000957,"rtt":194226,"start":5.001422,"omitted":false,"stream-id":5,"retransmits":0,"tcp-window-size":247608,"throughput-bits":10490637.893102413,"throughput-bytes":1310720}],"summary":{"end":6.000957,"start":5.001422,"omitted":false,"retransmits":0,"throughput-bits":10490637.893102413,"throughput-bytes":1310720}},{"streams":[{"end":7.000894,"rtt":228580,"start":6.000957,"omitted":false,"stream-id":5,"retransmits":0,"tcp-window-size":280912,"throughput-bits":10486420.666623391,"throughput-bytes":1310720}],"summary":{"end":7.000894,"start":6.000957,"omitted":false,"retransmits":0,"throughput-bits":10486420.666623391,"throughput-bytes":1310720}},{"streams":[{"end":8.000914,"rtt":292483,"start":7.000894,"omitted":false,"stream-id":5,"retransmits":0,"tcp-window-size":305528,"throughput-bits":10485550.00420562,"throughput-bytes":1310720}],"summary":{"end":8.000914,"start":7.000894,"omitted":false,"retransmits":0,"throughput-bits":10485550.00420562,"throughput-bytes":1310720}},{"streams":[{"end":9.000685,"rtt":248500,"start":8.000914,"omitted":false,"stream-id":5,"retransmits":0,"tcp-window-size":350416,"throughput-bits":10488161.800014714,"throughput-bytes":1310720}],"summary":{"end":9.000685,"start":8.000914,"omitted":false,"retransmits":0,"throughput-bits":10488161.800014714,"throughput-bytes":1310720}},{"streams":[{"end":10.000816,"rtt":294159,"start":9.000685,"omitted":false,"stream-id":5,"retransmits":0,"tcp-window-size":392408,"throughput-bits":10484386.4299528,"throughput-bytes":1310720}],"summary":{"end":10.000816,"start":9.000685,"omitted":false,"retransmits":0,"throughput-bits":10484386.4299528,"throughput-bytes":1310720}}],"succeeded":true}
