{"diags":"Participant 0:\n/usr/bin/iperf3 -p 5201 -c 172.16.0.1 -t 10 --json --rsa-public-key-path /var/run/pscheduler-server/runner/tmp/tmp7sc_kdpk/tmpl37anf76/public-key --username 5Qz4X45ovlYlkKHHFIG8\n\n{\n    \"end\": {\n        \"cpu_utilization_percent\": {\n            \"host_system\": 0.1958867834786206, \n            \"host_total\": 0.2402026410904632, \n            \"host_user\": 0.04430595683936452, \n            \"remote_system\": 3.900717475931976, \n            \"remote_total\": 4.393832950631287, \n            \"remote_user\": 0.4931055674107272\n        }, \n        \"receiver_tcp_congestion\": \"htcp\", \n        \"sender_tcp_congestion\": \"htcp\", \n        \"streams\": [\n            {\n                \"receiver\": {\n                    \"bits_per_second\": 18051609.81597645, \n                    \"bytes\": 22775592, \n                    \"end\": 10.093545, \n                    \"seconds\": 10.000324, \n                    \"sender\": true, \n                    \"socket\": 5, \n                    \"start\": 0\n                }, \n                \"sender\": {\n                    \"bits_per_second\": 19592542.801613227, \n                    \"bytes\": 24491472, \n                    \"end\": 10.000324, \n                    \"max_rtt\": 146848, \n                    \"max_snd_cwnd\": 351864, \n                    \"max_snd_wnd\": 0, \n                    \"mean_rtt\": 110969, \n                    \"min_rtt\": 78506, \n                    \"retransmits\": 65, \n                    \"seconds\": 10.000324, \n                    \"sender\": true, \n                    \"socket\": 5, \n                    \"start\": 0\n                }\n            }\n        ], \n        \"sum_received\": {\n            \"bits_per_second\": 18051609.81597645, \n            \"bytes\": 22775592, \n            \"end\": 10.093545, \n            \"seconds\": 10.093545, \n            \"sender\": true, \n            \"start\": 0\n        }, \n        \"sum_sent\": {\n            \"bits_per_second\": 19592542.801613227, \n            \"bytes\": 24491472, \n            \"end\": 10.000324, \n            \"retransmits\": 65, \n            \"seconds\": 10.000324, \n            \"sender\": true, \n            \"start\": 0\n        }\n    }, \n    \"intervals\": [\n        {\n            \"streams\": [\n                {\n                    \"bits_per_second\": 23889022.820295256, \n                    \"bytes\": 2988672, \n                    \"end\": 1.000852, \n                    \"omitted\": false, \n                    \"pmtu\": 1500, \n                    \"retransmits\": 60, \n                    \"rtt\": 116400, \n                    \"rttvar\": 576, \n                    \"seconds\": 1.0008519887924194, \n                    \"sender\": true, \n                    \"snd_cwnd\": 241816, \n                    \"snd_wnd\": -1, \n                    \"socket\": 5, \n                    \"start\": 0\n                }\n            ], \n            \"sum\": {\n                \"bits_per_second\": 23889022.820295256, \n                \"bytes\": 2988672, \n                \"end\": 1.000852, \n                \"omitted\": false, \n                \"retransmits\": 60, \n                \"seconds\": 1.0008519887924194, \n                \"sender\": true, \n                \"start\": 0\n            }\n        }, \n        {\n            \"streams\": [\n                {\n                    \"bits_per_second\": 15643718.628016366, \n                    \"bytes\": 1954800, \n                    \"end\": 2.000512, \n                    \"omitted\": false, \n                    \"pmtu\": 1500, \n                    \"retransmits\": 0, \n                    \"rtt\": 78506, \n                    \"rttvar\": 2598, \n                    \"seconds\": 0.9996600151062012, \n                    \"sender\": true, \n                    \"snd_cwnd\": 250504, \n                    \"snd_wnd\": -1, \n                    \"socket\": 5, \n                    \"start\": 1.000852\n                }\n            ], \n            \"sum\": {\n                \"bits_per_second\": 15643718.628016366, \n                \"bytes\": 1954800, \n                \"end\": 2.000512, \n                \"omitted\": false, \n                \"retransmits\": 0, \n                \"seconds\": 0.9996600151062012, \n                \"sender\": true, \n                \"start\": 1.000852\n            }\n        }, \n        {\n            \"streams\": [\n                {\n                    \"bits_per_second\": 15641012.240093753, \n                    \"bytes\": 1954800, \n                    \"end\": 3.000345, \n                    \"omitted\": false, \n                    \"pmtu\": 1500, \n                    \"retransmits\": 0, \n                    \"rtt\": 126331, \n                    \"rttvar\": 597, \n                    \"seconds\": 0.9998329877853394, \n                    \"sender\": true, \n                    \"snd_cwnd\": 262088, \n                    \"snd_wnd\": -1, \n                    \"socket\": 5, \n                    \"start\": 2.000512\n                }\n            ], \n            \"sum\": {\n                \"bits_per_second\": 15641012.240093753, \n                \"bytes\": 1954800, \n                \"end\": 3.000345, \n                \"omitted\": false, \n                \"retransmits\": 0, \n                \"seconds\": 0.9998329877853394, \n                \"sender\": true, \n                \"start\": 2.000512\n            }\n        }, \n        {\n            \"streams\": [\n                {\n                    \"bits_per_second\": 15637508.942833582, \n                    \"bytes\": 1954800, \n                    \"end\": 4.000402, \n                    \"omitted\": false, \n                    \"pmtu\": 1500, \n                    \"retransmits\": 0, \n                    \"rtt\": 133016, \n                    \"rttvar\": 939, \n                    \"seconds\": 1.0000569820404053, \n                    \"sender\": true, \n                    \"snd_cwnd\": 278016, \n                    \"snd_wnd\": -1, \n                    \"socket\": 5, \n                    \"start\": 3.000345\n                }\n            ], \n            \"sum\": {\n                \"bits_per_second\": 15637508.942833582, \n                \"bytes\": 1954800, \n                \"end\": 4.000402, \n                \"omitted\": false, \n                \"retransmits\": 0, \n                \"seconds\": 1.0000569820404053, \n                \"sender\": true, \n                \"start\": 3.000345\n            }\n        }, \n        {\n            \"streams\": [\n                {\n                    \"bits_per_second\": 23464920.367884964, \n                    \"bytes\": 2932200, \n                    \"end\": 5.00009, \n                    \"omitted\": false, \n                    \"pmtu\": 1500, \n                    \"retransmits\": 0, \n                    \"rtt\": 124379, \n                    \"rttvar\": 510, \n                    \"seconds\": 0.9996880292892456, \n                    \"sender\": true, \n                    \"snd_cwnd\": 308424, \n                    \"snd_wnd\": -1, \n                    \"socket\": 5, \n                    \"start\": 4.000402\n                }\n            ], \n            \"sum\": {\n                \"bits_per_second\": 23464920.367884964, \n                \"bytes\": 2932200, \n                \"end\": 5.00009, \n                \"omitted\": false, \n                \"retransmits\": 0, \n                \"seconds\": 0.9996880292892456, \n                \"sender\": true, \n                \"start\": 4.000402\n            }\n        }, \n        {\n            \"streams\": [\n                {\n                    \"bits_per_second\": 15635522.139193663, \n                    \"bytes\": 1954800, \n                    \"end\": 6.000274, \n                    \"omitted\": false, \n                    \"pmtu\": 1500, \n                    \"retransmits\": 0, \n                    \"rtt\": 127347, \n                    \"rttvar\": 526, \n                    \"seconds\": 1.0001840591430664, \n                    \"sender\": true, \n                    \"snd_cwnd\": 351864, \n                    \"snd_wnd\": -1, \n                    \"socket\": 5, \n                    \"start\": 5.00009\n                }\n            ], \n            \"sum\": {\n                \"bits_per_second\": 15635522.139193663, \n                \"bytes\": 1954800, \n                \"end\": 6.000274, \n                \"omitted\": false, \n                \"retransmits\": 0, \n                \"seconds\": 1.0001840591430664, \n                \"sender\": true, \n                \"start\": 5.00009\n            }\n        }, \n        {\n            \"streams\": [\n                {\n                    \"bits_per_second\": 23459968.759338755, \n                    \"bytes\": 2932200, \n                    \"end\": 7.000173, \n                    \"omitted\": false, \n                    \"pmtu\": 1500, \n                    \"retransmits\": 2, \n                    \"rtt\": 146848, \n                    \"rttvar\": 578, \n                    \"seconds\": 0.9998990297317505, \n                    \"sender\": true, \n                    \"snd_cwnd\": 335936, \n                    \"snd_wnd\": -1, \n                    \"socket\": 5, \n                    \"start\": 6.000274\n                }\n            ], \n            \"sum\": {\n                \"bits_per_second\": 23459968.759338755, \n                \"bytes\": 2932200, \n                \"end\": 7.000173, \n                \"omitted\": false, \n                \"retransmits\": 2, \n                \"seconds\": 0.9998990297317505, \n                \"sender\": true, \n                \"start\": 6.000274\n            }\n        }, \n        {\n            \"streams\": [\n                {\n                    \"bits_per_second\": 23458914.36464207, \n                    \"bytes\": 2932200, \n                    \"end\": 8.000117, \n                    \"omitted\": false, \n                    \"pmtu\": 1500, \n                    \"retransmits\": 3, \n                    \"rtt\": 79764, \n                    \"rttvar\": 919, \n                    \"seconds\": 0.999943971633911, \n                    \"sender\": true, \n                    \"snd_cwnd\": 217200, \n                    \"snd_wnd\": -1, \n                    \"socket\": 5, \n                    \"start\": 7.000173\n                }\n            ], \n            \"sum\": {\n                \"bits_per_second\": 23458914.36464207, \n                \"bytes\": 2932200, \n                \"end\": 8.000117, \n                \"omitted\": false, \n                \"retransmits\": 3, \n                \"seconds\": 0.999943971633911, \n                \"sender\": true, \n                \"start\": 7.000173\n            }\n        }, \n        {\n            \"streams\": [\n                {\n                    \"bits_per_second\": 23458703.21741334, \n                    \"bytes\": 2932200, \n                    \"end\": 9.00007, \n                    \"omitted\": false, \n                    \"pmtu\": 1500, \n                    \"retransmits\": 0, \n                    \"rtt\": 85301, \n                    \"rttvar\": 445, \n                    \"seconds\": 0.9999529719352722, \n                    \"sender\": true, \n                    \"snd_cwnd\": 234576, \n                    \"snd_wnd\": -1, \n                    \"socket\": 5, \n                    \"start\": 8.000117\n                }\n            ], \n            \"sum\": {\n                \"bits_per_second\": 23458703.21741334, \n                \"bytes\": 2932200, \n                \"end\": 9.00007, \n                \"omitted\": false, \n                \"retransmits\": 0, \n                \"seconds\": 0.9999529719352722, \n                \"sender\": true, \n                \"start\": 8.000117\n            }\n        }, \n        {\n            \"streams\": [\n                {\n                    \"bits_per_second\": 15634428.308066787, \n                    \"bytes\": 1954800, \n                    \"end\": 10.000324, \n                    \"omitted\": false, \n                    \"pmtu\": 1500, \n                    \"retransmits\": 0, \n                    \"rtt\": 91798, \n                    \"rttvar\": 625, \n                    \"seconds\": 1.0002540349960327, \n                    \"sender\": true, \n                    \"snd_cwnd\": 253400, \n                    \"snd_wnd\": -1, \n                    \"socket\": 5, \n                    \"start\": 9.00007\n                }\n            ], \n            \"sum\": {\n                \"bits_per_second\": 15634428.308066787, \n                \"bytes\": 1954800, \n                \"end\": 10.000324, \n                \"omitted\": false, \n                \"retransmits\": 0, \n                \"seconds\": 1.0002540349960327, \n                \"sender\": true, \n                \"start\": 9.00007\n            }\n        }\n    ], \n    \"start\": {\n        \"connected\": [\n            {\n                \"local_host\": \"172.16.0.2\", \n                \"local_port\": 51846, \n                \"remote_host\": \"172.16.0.1\", \n                \"remote_port\": 5201, \n                \"socket\": 5\n            }\n        ], \n        \"connecting_to\": {\n            \"host\": \"172.16.0.1\", \n            \"port\": 5201\n        }, \n        \"cookie\": \"lvrvvtywgf4w27n36ne2qtcxifgj53ylxdqh\", \n        \"fq_rate\": 0, \n        \"rcvbuf_actual\": 87380, \n        \"sndbuf_actual\": 65536, \n        \"sock_bufsize\": 0, \n        \"system_info\": \"REDACTED\", \n        \"target_bitrate\": 0, \n        \"tcp_mss_default\": 1448, \n        \"test_start\": {\n            \"bidir\": 0, \n            \"blksize\": 131072, \n            \"blocks\": 0, \n            \"bytes\": 0, \n            \"duration\": 10, \n            \"fqrate\": 0, \n            \"num_streams\": 1, \n            \"omit\": 0, \n            \"protocol\": \"TCP\", \n            \"reverse\": 0, \n            \"target_bitrate\": 0, \n            \"tos\": 0\n        }, \n        \"timestamp\": {\n            \"time\": \"Wed, 21 Aug 2024 16:06:49 GMT\", \n            \"timesecs\": 1724256409\n        }, \n        \"version\": \"iperf 3.14\"\n    }\n}\nParticipant 1:\n/usr/bin/iperf3 -s -1 --idle-timeout 10 --json -p 5201 --authorized-users-path /var/run/pscheduler-server/runner/tmp/tmpr0_q3n4j/tmpsxx04q5y/credentials --rsa-private-key-path /var/run/pscheduler-server/runner/tmp/tmpr0_q3n4j/tmpsxx04q5y/private-key\n\n{\n    \"end\": {\n        \"cpu_utilization_percent\": {\n            \"host_system\": 3.900717475931976, \n            \"host_total\": 4.393832950631287, \n            \"host_user\": 0.4931055674107272, \n            \"remote_system\": 0, \n            \"remote_total\": 0, \n            \"remote_user\": 0\n        }, \n        \"receiver_tcp_congestion\": \"htcp\", \n        \"streams\": [\n            {\n                \"receiver\": {\n                    \"bits_per_second\": 18051609.81597645, \n                    \"bytes\": 22775592, \n                    \"end\": 10.093545, \n                    \"seconds\": 10.093545, \n                    \"sender\": false, \n                    \"socket\": 5, \n                    \"start\": 0\n                }, \n                \"sender\": {\n                    \"bits_per_second\": 0, \n                    \"bytes\": 0, \n                    \"end\": 10.093545, \n                    \"seconds\": 10.093545, \n                    \"sender\": false, \n                    \"socket\": 5, \n                    \"start\": 0\n                }\n            }\n        ], \n        \"sum_received\": {\n            \"bits_per_second\": 18051609.81597645, \n            \"bytes\": 22775592, \n            \"end\": 10.093545, \n            \"seconds\": 10.093545, \n            \"sender\": false, \n            \"start\": 0\n        }, \n        \"sum_sent\": {\n            \"bits_per_second\": 0, \n            \"bytes\": 0, \n            \"end\": 10.093545, \n            \"seconds\": 10.093545, \n            \"sender\": false, \n            \"start\": 0\n        }\n    }, \n    \"intervals\": [\n        {\n            \"streams\": [\n                {\n                    \"bits_per_second\": 9208377.670740444, \n                    \"bytes\": 1151160, \n                    \"end\": 1.000098, \n                    \"omitted\": false, \n                    \"seconds\": 1.0000979900360107, \n                    \"sender\": false, \n                    \"socket\": 5, \n                    \"start\": 0\n                }\n            ], \n            \"sum\": {\n                \"bits_per_second\": 9208377.670740444, \n                \"bytes\": 1151160, \n                \"end\": 1.000098, \n                \"omitted\": false, \n                \"seconds\": 1.0000979900360107, \n                \"sender\": false, \n                \"start\": 0\n            }\n        }, \n        {\n            \"streams\": [\n                {\n                    \"bits_per_second\": 12857700.469416948, \n                    \"bytes\": 1607280, \n                    \"end\": 2.00014, \n                    \"omitted\": false, \n                    \"seconds\": 1.0000419616699219, \n                    \"sender\": false, \n                    \"socket\": 5, \n                    \"start\": 1.000098\n                }\n            ], \n            \"sum\": {\n                \"bits_per_second\": 12857700.469416948, \n                \"bytes\": 1607280, \n                \"end\": 2.00014, \n                \"omitted\": false, \n                \"seconds\": 1.0000419616699219, \n                \"sender\": false, \n                \"start\": 1.000098\n            }\n        }, \n        {\n            \"streams\": [\n                {\n                    \"bits_per_second\": 16531095.17358101, \n                    \"bytes\": 2066296, \n                    \"end\": 3.000096, \n                    \"omitted\": false, \n                    \"seconds\": 0.9999560117721558, \n                    \"sender\": false, \n                    \"socket\": 5, \n                    \"start\": 2.00014\n                }\n            ], \n            \"sum\": {\n                \"bits_per_second\": 16531095.17358101, \n                \"bytes\": 2066296, \n                \"end\": 3.000096, \n                \"omitted\": false, \n                \"seconds\": 0.9999560117721558, \n                \"sender\": false, \n                \"start\": 2.00014\n            }\n        }, \n        {\n            \"streams\": [\n                {\n                    \"bits_per_second\": 16530235.97263501, \n                    \"bytes\": 2066296, \n                    \"end\": 4.000104, \n                    \"omitted\": false, \n                    \"seconds\": 1.0000079870224, \n                    \"sender\": false, \n                    \"socket\": 5, \n                    \"start\": 3.000096\n                }\n            ], \n            \"sum\": {\n                \"bits_per_second\": 16530235.97263501, \n                \"bytes\": 2066296, \n                \"end\": 4.000104, \n                \"omitted\": false, \n                \"seconds\": 1.0000079870224, \n                \"sender\": false, \n                \"start\": 3.000096\n            }\n        }, \n        {\n            \"streams\": [\n                {\n                    \"bits_per_second\": 18511214.34633031, \n                    \"bytes\": 2313904, \n                    \"end\": 5.000105, \n                    \"omitted\": false, \n                    \"seconds\": 1.0000009536743164, \n                    \"sender\": false, \n                    \"socket\": 5, \n                    \"start\": 4.000104\n                }\n            ], \n            \"sum\": {\n                \"bits_per_second\": 18511214.34633031, \n                \"bytes\": 2313904, \n                \"end\": 5.000105, \n                \"omitted\": false, \n                \"seconds\": 1.0000009536743164, \n                \"sender\": false, \n                \"start\": 4.000104\n            }\n        }, \n        {\n            \"streams\": [\n                {\n                    \"bits_per_second\": 19808739.178200424, \n                    \"bytes\": 2476080, \n                    \"end\": 6.0001, \n                    \"omitted\": false, \n                    \"seconds\": 0.999994993209839, \n                    \"sender\": false, \n                    \"socket\": 5, \n                    \"start\": 5.000105\n                }\n            ], \n            \"sum\": {\n                \"bits_per_second\": 19808739.178200424, \n                \"bytes\": 2476080, \n                \"end\": 6.0001, \n                \"omitted\": false, \n                \"seconds\": 0.999994993209839, \n                \"sender\": false, \n                \"start\": 5.000105\n            }\n        }, \n        {\n            \"streams\": [\n                {\n                    \"bits_per_second\": 20619148.84289321, \n                    \"bytes\": 2577440, \n                    \"end\": 7.000118, \n                    \"omitted\": false, \n                    \"seconds\": 1.0000180006027222, \n                    \"sender\": false, \n                    \"socket\": 5, \n                    \"start\": 6.0001\n                }\n            ], \n            \"sum\": {\n                \"bits_per_second\": 20619148.84289321, \n                \"bytes\": 2577440, \n                \"end\": 7.000118, \n                \"omitted\": false, \n                \"seconds\": 1.0000180006027222, \n                \"sender\": false, \n                \"start\": 6.0001\n            }\n        }, \n        {\n            \"streams\": [\n                {\n                    \"bits_per_second\": 22739869.10144065, \n                    \"bytes\": 2842424, \n                    \"end\": 8.000097, \n                    \"omitted\": false, \n                    \"seconds\": 0.999979019165039, \n                    \"sender\": false, \n                    \"socket\": 5, \n                    \"start\": 7.000118\n                }\n            ], \n            \"sum\": {\n                \"bits_per_second\": 22739869.10144065, \n                \"bytes\": 2842424, \n                \"end\": 8.000097, \n                \"omitted\": false, \n                \"seconds\": 0.999979019165039, \n                \"sender\": false, \n                \"start\": 7.000118\n            }\n        }, \n        {\n            \"streams\": [\n                {\n                    \"bits_per_second\": 21685139.427057274, \n                    \"bytes\": 2710656, \n                    \"end\": 9.000102, \n                    \"omitted\": false, \n                    \"seconds\": 1.0000050067901611, \n                    \"sender\": false, \n                    \"socket\": 5, \n                    \"start\": 8.000097\n                }\n            ], \n            \"sum\": {\n                \"bits_per_second\": 21685139.427057274, \n                \"bytes\": 2710656, \n                \"end\": 9.000102, \n                \"omitted\": false, \n                \"seconds\": 1.0000050067901611, \n                \"sender\": false, \n                \"start\": 8.000097\n            }\n        }, \n        {\n            \"streams\": [\n                {\n                    \"bits_per_second\": 21673707.9230245, \n                    \"bytes\": 2709208, \n                    \"end\": 10.0001, \n                    \"omitted\": false, \n                    \"seconds\": 0.9999979734420776, \n                    \"sender\": false, \n                    \"socket\": 5, \n                    \"start\": 9.000102\n                }\n            ], \n            \"sum\": {\n                \"bits_per_second\": 21673707.9230245, \n                \"bytes\": 2709208, \n                \"end\": 10.0001, \n                \"omitted\": false, \n                \"seconds\": 0.9999979734420776, \n                \"sender\": false, \n                \"start\": 9.000102\n            }\n        }, \n        {\n            \"streams\": [\n                {\n                    \"bits_per_second\": 21818009.8863809, \n                    \"bytes\": 254848, \n                    \"end\": 10.093545, \n                    \"omitted\": false, \n                    \"seconds\": 0.09344500303268433, \n                    \"sender\": false, \n                    \"socket\": 5, \n                    \"start\": 10.0001\n                }\n            ], \n            \"sum\": {\n                \"bits_per_second\": 21818009.8863809, \n                \"bytes\": 254848, \n                \"end\": 10.093545, \n                \"omitted\": false, \n                \"seconds\": 0.09344500303268433, \n                \"sender\": false, \n                \"start\": 10.0001\n            }\n        }\n    ], \n    \"start\": {\n        \"accepted_connection\": {\n            \"host\": \"172.16.0.2\", \n            \"port\": 51836\n        }, \n        \"connected\": [\n            {\n                \"local_host\": \"172.16.0.1\", \n                \"local_port\": 5201, \n                \"remote_host\": \"172.16.0.2\", \n                \"remote_port\": 51846, \n                \"socket\": 5\n            }\n        ], \n        \"cookie\": \"lvrvvtywgf4w27n36ne2qtcxifgj53ylxdqh\", \n        \"fq_rate\": 0, \n        \"rcvbuf_actual\": 87380, \n        \"sndbuf_actual\": 65536, \n        \"sock_bufsize\": 0, \n        \"system_info\": \"REDACTED\", \n        \"target_bitrate\": 0, \n        \"tcp_mss_default\": 0, \n        \"test_start\": {\n            \"bidir\": 0, \n            \"blksize\": 131072, \n            \"blocks\": 0, \n            \"bytes\": 0, \n            \"duration\": 10, \n            \"fqrate\": 0, \n            \"num_streams\": 1, \n            \"omit\": 0, \n            \"protocol\": \"TCP\", \n            \"reverse\": 0, \n            \"target_bitrate\": 0, \n            \"tos\": 0\n        }, \n        \"timestamp\": {\n            \"time\": \"Wed, 21 Aug 2024 16:06:49 GMT\", \n            \"timesecs\": 1724256409\n        }, \n        \"version\": \"iperf 3.14\"\n    }\n}\n","summary":{"streams":[{"end":10.000324,"rtt":110969,"start":0,"stream-id":5,"retransmits":65,"throughput-bits":19592542.801613227,"throughput-bytes":24491472}],"summary":{"end":10.000324,"start":0,"retransmits":65,"throughput-bits":19592542.801613227,"throughput-bytes":24491472,"receiver-throughput-bits":18051609.81597645}},"intervals":[{"streams":[{"end":1.000852,"rtt":116400,"start":0,"omitted":false,"stream-id":5,"retransmits":60,"tcp-window-size":241816,"throughput-bits":23889022.820295256,"throughput-bytes":2988672}],"summary":{"end":1.000852,"start":0,"omitted":false,"retransmits":60,"throughput-bits":23889022.820295256,"throughput-bytes":2988672}},{"streams":[{"end":2.000512,"rtt":78506,"start":1.000852,"omitted":false,"stream-id":5,"retransmits":0,"tcp-window-size":250504,"throughput-bits":15643718.628016366,"throughput-bytes":1954800}],"summary":{"end":2.000512,"start":1.000852,"omitted":false,"retransmits":0,"throughput-bits":15643718.628016366,"throughput-bytes":1954800}},{"streams":[{"end":3.000345,"rtt":126331,"start":2.000512,"omitted":false,"stream-id":5,"retransmits":0,"tcp-window-size":262088,"throughput-bits":15641012.240093753,"throughput-bytes":1954800}],"summary":{"end":3.000345,"start":2.000512,"omitted":false,"retransmits":0,"throughput-bits":15641012.240093753,"throughput-bytes":1954800}},{"streams":[{"end":4.000402,"rtt":133016,"start":3.000345,"omitted":false,"stream-id":5,"retransmits":0,"tcp-window-size":278016,"throughput-bits":15637508.942833582,"throughput-bytes":1954800}],"summary":{"end":4.000402,"start":3.000345,"omitted":false,"retransmits":0,"throughput-bits":15637508.942833582,"throughput-bytes":1954800}},{"streams":[{"end":5.00009,"rtt":124379,"start":4.000402,"omitted":false,"stream-id":5,"retransmits":0,"tcp-window-size":308424,"throughput-bits":23464920.367884964,"throughput-bytes":2932200}],"summary":{"end":5.00009,"start":4.000402,"omitted":false,"retransmits":0,"throughput-bits":23464920.367884964,"throughput-bytes":2932200}},{"streams":[{"end":6.000274,"rtt":127347,"start":5.00009,"omitted":false,"stream-id":5,"retransmits":0,"tcp-window-size":351864,"throughput-bits":15635522.139193663,"throughput-bytes":1954800}],"summary":{"end":6.000274,"start":5.00009,"omitted":false,"retransmits":0,"throughput-bits":15635522.139193663,"throughput-bytes":1954800}},{"streams":[{"end":7.000173,"rtt":146848,"start":6.000274,"omitted":false,"stream-id":5,"retransmits":2,"tcp-window-size":335936,"throughput-bits":23459968.759338755,"throughput-bytes":2932200}],"summary":{"end":7.000173,"start":6.000274,"omitted":false,"retransmits":2,"throughput-bits":23459968.759338755,"throughput-bytes":2932200}},{"streams":[{"end":8.000117,"rtt":79764,"start":7.000173,"omitted":false,"stream-id":5,"retransmits":3,"tcp-window-size":217200,"throughput-bits":23458914.36464207,"throughput-bytes":2932200}],"summary":{"end":8.000117,"start":7.000173,"omitted":false,"retransmits":3,"throughput-bits":23458914.36464207,"throughput-bytes":2932200}},{"streams":[{"end":9.00007,"rtt":85301,"start":8.000117,"omitted":false,"stream-id":5,"retransmits":0,"tcp-window-size":234576,"throughput-bits":23458703.21741334,"throughput-bytes":2932200}],"summary":{"end":9.00007,"start":8.000117,"omitted":false,"retransmits":0,"throughput-bits":23458703.21741334,"throughput-bytes":2932200}},{"streams":[{"end":10.000324,"rtt":91798,"start":9.00007,"omitted":false,"stream-id":5,"retransmits":0,"tcp-window-size":253400,"throughput-bits":15634428.308066787,"throughput-bytes":1954800}],"summary":{"end":10.000324,"start":9.00007,"omitted":false,"retransmits":0,"throughput-bits":15634428.308066787,"throughput-bytes":1954800}}],"succeeded":true}
