{"diags":"Participant 0:\n/usr/bin/iperf3 -p 5201 -B 10.0.0.1 -c 10.0.0.2 -t 60 --json --rsa-public-key-path /var/run/pscheduler-server/runner/tmp/tmpfud_x3u_/tmpqx_6jsqp/public-key --username uv9QTMagl7Vq15bNFA8t\n\n{\n    \"end\": {\n        \"cpu_utilization_percent\": {\n            \"host_system\": 1.995137753809841, \n            \"host_total\": 2.0286206067795542, \n            \"host_user\": 0.033482852969713414, \n            \"remote_system\": 4.81051399247522, \n            \"remote_total\": 5.278140779705447, \n            \"remote_user\": 0.46762345816747186\n        }, \n        \"receiver_tcp_congestion\": \"htcp\", \n        \"sender_tcp_congestion\": \"htcp\", \n        \"streams\": [\n            {\n                \"receiver\": {\n                    \"bits_per_second\": 865534406.0676053, \n                    \"bytes\": 6499833080, \n                    \"end\": 60.076947, \n                    \"seconds\": 60.000166, \n                    \"sender\": true, \n                    \"socket\": 5, \n                    \"start\": 0\n                }, \n                \"sender\": {\n                    \"bits_per_second\": 867030143.0832708, \n                    \"bytes\": 6502744064, \n                    \"end\": 60.000166, \n                    \"max_rtt\": 77093, \n                    \"max_snd_cwnd\": 16708472, \n                    \"max_snd_wnd\": 0, \n                    \"mean_rtt\": 77087, \n                    \"min_rtt\": 77081, \n                    \"retransmits\": 0, \n                    \"seconds\": 60.000166, \n                    \"sender\": true, \n                    \"socket\": 5, \n                    \"start\": 0\n                }\n            }\n        ], \n        \"sum_received\": {\n            \"bits_per_second\": 865534406.0676053, \n            \"bytes\": 6499833080, \n            \"end\": 60.076947, \n            \"seconds\": 60.076947, \n            \"sender\": true, \n            \"start\": 0\n        }, \n        \"sum_sent\": {\n            \"bits_per_second\": 867030143.0832708, \n            \"bytes\": 6502744064, \n            \"end\": 60.000166, \n            \"retransmits\": 0, \n            \"seconds\": 60.000166, \n            \"sender\": true, \n            \"start\": 0\n        }\n    }, \n    \"intervals\": [\n        {\n            \"streams\": [\n                {\n                    \"bits_per_second\": 956241123.788397, \n                    \"bytes\": 119537664, \n                    \"end\": 1.000063, \n                    \"omitted\": false, \n                    \"pmtu\": 1500, \n                    \"retransmits\": 0, \n                    \"rtt\": 77081, \n                    \"rttvar\": 6, \n                    \"seconds\": 1.0000629425048828, \n                    \"sender\": true, \n                    \"snd_cwnd\": 16708472, \n                    \"snd_wnd\": -1, \n                    \"socket\": 5, \n                    \"start\": 0\n                }\n            ], \n            \"sum\": {\n                \"bits_per_second\": 956241123.788397, \n                \"bytes\": 119537664, \n                \"end\": 1.000063, \n                \"omitted\": false, \n                \"retransmits\": 0, \n                \"seconds\": 1.0000629425048828, \n                \"sender\": true, \n                \"start\": 0\n            }\n        }, \n        {\n            \"streams\": [\n                {\n                    \"bits_per_second\": 870305941.4193027, \n                    \"bytes\": 108789760, \n                    \"end\": 2.000077, \n                    \"omitted\": false, \n                    \"pmtu\": 1500, \n                    \"retransmits\": 0, \n                    \"rtt\": 77087, \n                    \"rttvar\": 7, \n                    \"seconds\": 1.0000139474868774, \n                    \"sender\": true, \n                    \"snd_cwnd\": 16708472, \n                    \"snd_wnd\": -1, \n                    \"socket\": 5, \n                    \"start\": 1.000063\n                }\n            ], \n            \"sum\": {\n                \"bits_per_second\": 870305941.4193027, \n                \"bytes\": 108789760, \n                \"end\": 2.000077, \n                \"omitted\": false, \n                \"retransmits\": 0, \n                \"seconds\": 1.0000139474868774, \n                \"sender\": true, \n                \"start\": 1.000063\n            }\n        }, \n        {\n            \"streams\": [\n                {\n                    \"bits_per_second\": 859843492.6451752, \n                    \"bytes\": 107479040, \n                    \"end\": 3.000064, \n                    \"omitted\": false, \n                    \"pmtu\": 1500, \n                    \"retransmits\": 0, \n                    \"rtt\": 77089, \n                    \"rttvar\": 11, \n                    \"seconds\": 0.999987006187439, \n                    \"sender\": true, \n                    \"snd_cwnd\": 16708472, \n                    \"snd_wnd\": -1, \n                    \"socket\": 5, \n                    \"start\": 2.000077\n                }\n            ], \n            \"sum\": {\n                \"bits_per_second\": 859843492.6451752, \n                \"bytes\": 107479040, \n                \"end\": 3.000064, \n                \"omitted\": false, \n                \"retransmits\": 0, \n                \"seconds\": 0.999987006187439, \n                \"sender\": true, \n                \"start\": 2.000077\n            }\n        }, \n        {\n            \"streams\": [\n                {\n                    \"bits_per_second\": 870301584.0626686, \n                    \"bytes\": 108789760, \n                    \"end\": 4.000083, \n                    \"omitted\": false, \n                    \"pmtu\": 1500, \n                    \"retransmits\": 0, \n                    \"rtt\": 77087, \n                    \"rttvar\": 9, \n                    \"seconds\": 1.0000189542770386, \n                    \"sender\": true, \n                    \"snd_cwnd\": 16708472, \n                    \"snd_wnd\": -1, \n                    \"socket\": 5, \n                    \"start\": 3.000064\n                }\n            ], \n            \"sum\": {\n                \"bits_per_second\": 870301584.0626686, \n                \"bytes\": 108789760, \n                \"end\": 4.000083, \n                \"omitted\": false, \n                \"retransmits\": 0, \n                \"seconds\": 1.0000189542770386, \n                \"sender\": true, \n                \"start\": 3.000064\n            }\n        }, \n        {\n            \"streams\": [\n                {\n                    \"bits_per_second\": 859848669.060859, \n                    \"bytes\": 107479040, \n                    \"end\": 5.000064, \n                    \"omitted\": false, \n                    \"pmtu\": 1500, \n                    \"retransmits\": 0, \n                    \"rtt\": 77089, \n                    \"rttvar\": 8, \n                    \"seconds\": 0.9999809861183167, \n                    \"sender\": true, \n                    \"snd_cwnd\": 16708472, \n                    \"snd_wnd\": -1, \n                    \"socket\": 5, \n                    \"start\": 4.000083\n                }\n            ], \n            \"sum\": {\n                \"bits_per_second\": 859848669.060859, \n                \"bytes\": 107479040, \n                \"end\": 5.000064, \n                \"omitted\": false, \n                \"retransmits\": 0, \n                \"seconds\": 0.9999809861183167, \n                \"sender\": true, \n                \"start\": 4.000083\n            }\n        }, \n        {\n            \"streams\": [\n                {\n                    \"bits_per_second\": 870319843.7535744, \n                    \"bytes\": 108789760, \n                    \"end\": 6.000062, \n                    \"omitted\": false, \n                    \"pmtu\": 1500, \n                    \"retransmits\": 0, \n                    \"rtt\": 77082, \n                    \"rttvar\": 5, \n                    \"seconds\": 0.9999979734420776, \n                    \"sender\": true, \n                    \"snd_cwnd\": 16708472, \n                    \"snd_wnd\": -1, \n                    \"socket\": 5, \n                    \"start\": 5.000064\n                }\n            ], \n            \"sum\": {\n                \"bits_per_second\": 870319843.7535744, \n                \"bytes\": 108789760, \n                \"end\": 6.000062, \n                \"omitted\": false, \n                \"retransmits\": 0, \n                \"seconds\": 0.9999979734420776, \n                \"sender\": true, \n                \"start\": 5.000064\n            }\n        }, \n        {\n            \"streams\": [\n                {\n                    \"bits_per_second\": 859830577.5035312, \n                    \"bytes\": 107479040, \n                    \"end\": 7.000064, \n                    \"omitted\": false, \n                    \"pmtu\": 1500, \n                    \"retransmits\": 0, \n                    \"rtt\": 77087, \n                    \"rttvar\": 11, \n                    \"seconds\": 1.0000020265579224, \n                    \"sender\": true, \n                    \"snd_cwnd\": 16708472, \n                    \"snd_wnd\": -1, \n                    \"socket\": 5, \n                    \"start\": 6.000062\n                }\n            ], \n            \"sum\": {\n                \"bits_per_second\": 859830577.5035312, \n                \"bytes\": 107479040, \n                \"end\": 7.000064, \n                \"omitted\": false, \n                \"retransmits\": 0, \n                \"seconds\": 1.0000020265579224, \n                \"sender\": true, \n                \"start\": 6.000062\n            }\n        }, \n        {\n            \"streams\": [\n                {\n                    \"bits_per_second\": 870318080, \n                    \"bytes\": 108789760, \n                    \"end\": 8.000064, \n                    \"omitted\": false, \n                    \"pmtu\": 1500, \n                    \"retransmits\": 0, \n                    \"rtt\": 77083, \n                    \"rttvar\": 4, \n                    \"seconds\": 1, \n                    \"sender\": true, \n                    \"snd_cwnd\": 16708472, \n                    \"snd_wnd\": -1, \n                    \"socket\": 5, \n                    \"start\": 7.000064\n                }\n            ], \n            \"sum\": {\n                \"bits_per_second\": 870318080, \n                \"bytes\": 108789760, \n                \"end\": 8.000064, \n                \"omitted\": false, \n                \"retransmits\": 0, \n                \"seconds\": 1, \n                \"sender\": true, \n                \"start\": 7.000064\n            }\n        }, \n        {\n            \"streams\": [\n                {\n                    \"bits_per_second\": 870318961.8758936, \n                    \"bytes\": 108789760, \n                    \"end\": 9.000063, \n                    \"omitted\": false, \n                    \"pmtu\": 1500, \n                    \"retransmits\": 0, \n                    \"rtt\": 77090, \n                    \"rttvar\": 8, \n                    \"seconds\": 0.9999989867210388, \n                    \"sender\": true, \n                    \"snd_cwnd\": 16708472, \n                    \"snd_wnd\": -1, \n                    \"socket\": 5, \n                    \"start\": 8.000064\n                }\n            ], \n            \"sum\": {\n                \"bits_per_second\": 870318961.8758936, \n                \"bytes\": 108789760, \n                \"end\": 9.000063, \n                \"omitted\": false, \n                \"retransmits\": 0, \n                \"seconds\": 0.9999989867210388, \n                \"sender\": true, \n                \"start\": 8.000064\n            }\n        }, \n        {\n            \"streams\": [\n                {\n                    \"bits_per_second\": 859831500.000782, \n                    \"bytes\": 107479040, \n                    \"end\": 10.000064, \n                    \"omitted\": false, \n                    \"pmtu\": 1500, \n                    \"retransmits\": 0, \n                    \"rtt\": 77088, \n                    \"rttvar\": 7, \n                    \"seconds\": 1.0000009536743164, \n                    \"sender\": true, \n                    \"snd_cwnd\": 16708472, \n                    \"snd_wnd\": -1, \n                    \"socket\": 5, \n                    \"start\": 9.000063\n                }\n            ], \n            \"sum\": {\n                \"bits_per_second\": 859831500.000782, \n                \"bytes\": 107479040, \n                \"end\": 10.000064, \n                \"omitted\": false, \n                \"retransmits\": 0, \n                \"seconds\": 1.0000009536743164, \n                \"sender\": true, \n                \"start\": 9.000063\n            }\n        }, \n        {\n            \"streams\": [\n                {\n                    \"bits_per_second\": 870300650.3490664, \n                    \"bytes\": 108789760, \n                    \"end\": 11.000084, \n                    \"omitted\": false, \n                    \"pmtu\": 1500, \n                    \"retransmits\": 0, \n                    \"rtt\": 77087, \n                    \"rttvar\": 9, \n                    \"seconds\": 1.0000200271606445, \n                    \"sender\": true, \n                    \"snd_cwnd\": 16708472, \n                    \"snd_wnd\": -1, \n                    \"socket\": 5, \n                    \"start\": 10.000064\n                }\n            ], \n            \"sum\": {\n                \"bits_per_second\": 870300650.3490664, \n                \"bytes\": 108789760, \n                \"end\": 11.000084, \n                \"omitted\": false, \n                \"retransmits\": 0, \n                \"seconds\": 1.0000200271606445, \n                \"sender\": true, \n                \"start\": 10.000064\n            }\n        }, \n        {\n            \"streams\": [\n                {\n                    \"bits_per_second\": 859847797.7786094, \n                    \"bytes\": 107479040, \n                    \"end\": 12.000066, \n                    \"omitted\": false, \n                    \"pmtu\": 1500, \n                    \"retransmits\": 0, \n                    \"rtt\": 77087, \n                    \"rttvar\": 10, \n                    \"seconds\": 0.9999819993972778, \n                    \"sender\": true, \n                    \"snd_cwnd\": 16708472, \n                    \"snd_wnd\": -1, \n                    \"socket\": 5, \n                    \"start\": 11.000084\n                }\n            ], \n            \"sum\": {\n                \"bits_per_second\": 859847797.7786094, \n                \"bytes\": 107479040, \n                \"end\": 12.000066, \n                \"omitted\": false, \n                \"retransmits\": 0, \n                \"seconds\": 0.9999819993972778, \n                \"sender\": true, \n                \"start\": 11.000084\n            }\n        }, \n        {\n            \"streams\": [\n                {\n                    \"bits_per_second\": 870321555.63888, \n                    \"bytes\": 108789760, \n                    \"end\": 13.000062, \n                    \"omitted\": false, \n                    \"pmtu\": 1500, \n                    \"retransmits\": 0, \n                    \"rtt\": 77085, \n                    \"rttvar\": 7, \n                    \"seconds\": 0.9999960064888, \n                    \"sender\": true, \n                    \"snd_cwnd\": 16708472, \n                    \"snd_wnd\": -1, \n                    \"socket\": 5, \n                    \"start\": 12.000066\n                }\n            ], \n            \"sum\": {\n                \"bits_per_second\": 870321555.63888, \n                \"bytes\": 108789760, \n                \"end\": 13.000062, \n                \"omitted\": false, \n                \"retransmits\": 0, \n                \"seconds\": 0.9999960064888, \n                \"sender\": true, \n                \"start\": 12.000066\n            }\n        }, \n        {\n            \"streams\": [\n                {\n                    \"bits_per_second\": 859813357.9181844, \n                    \"bytes\": 107479040, \n                    \"end\": 14.000084, \n                    \"omitted\": false, \n                    \"pmtu\": 1500, \n                    \"retransmits\": 0, \n                    \"rtt\": 77087, \n                    \"rttvar\": 10, \n                    \"seconds\": 1.000022053718567, \n                    \"sender\": true, \n                    \"snd_cwnd\": 16708472, \n                    \"snd_wnd\": -1, \n                    \"socket\": 5, \n                    \"start\": 13.000062\n                }\n            ], \n            \"sum\": {\n                \"bits_per_second\": 859813357.9181844, \n                \"bytes\": 107479040, \n                \"end\": 14.000084, \n                \"omitted\": false, \n                \"retransmits\": 0, \n                \"seconds\": 1.000022053718567, \n                \"sender\": true, \n                \"start\": 13.000062\n            }\n        }, \n        {\n            \"streams\": [\n                {\n                    \"bits_per_second\": 870335510.3490804, \n                    \"bytes\": 108789760, \n                    \"end\": 15.000064, \n                    \"omitted\": false, \n                    \"pmtu\": 1500, \n                    \"retransmits\": 0, \n                    \"rtt\": 77092, \n                    \"rttvar\": 9, \n                    \"seconds\": 0.9999799728393555, \n                    \"sender\": true, \n                    \"snd_cwnd\": 16708472, \n                    \"snd_wnd\": -1, \n                    \"socket\": 5, \n                    \"start\": 14.000084\n                }\n            ], \n            \"sum\": {\n                \"bits_per_second\": 870335510.3490804, \n                \"bytes\": 108789760, \n                \"end\": 15.000064, \n                \"omitted\": false, \n                \"retransmits\": 0, \n                \"seconds\": 0.9999799728393555, \n                \"sender\": true, \n                \"start\": 14.000084\n            }\n        }, \n        {\n            \"streams\": [\n                {\n                    \"bits_per_second\": 859816842.7785993, \n                    \"bytes\": 107479040, \n                    \"end\": 16.000082, \n                    \"omitted\": false, \n                    \"pmtu\": 1500, \n                    \"retransmits\": 0, \n                    \"rtt\": 77087, \n                    \"rttvar\": 10, \n                    \"seconds\": 1.0000180006027222, \n                    \"sender\": true, \n                    \"snd_cwnd\": 16708472, \n                    \"snd_wnd\": -1, \n                    \"socket\": 5, \n                    \"start\": 15.000064\n                }\n            ], \n            \"sum\": {\n                \"bits_per_second\": 859816842.7785993, \n                \"bytes\": 107479040, \n                \"end\": 16.000082, \n                \"omitted\": false, \n                \"retransmits\": 0, \n                \"seconds\": 1.0000180006027222, \n                \"sender\": true, \n                \"start\": 15.000064\n            }\n        }, \n        {\n            \"streams\": [\n                {\n                    \"bits_per_second\": 870333746.532007, \n                    \"bytes\": 108789760, \n                    \"end\": 17.000064, \n                    \"omitted\": false, \n                    \"pmtu\": 1500, \n                    \"retransmits\": 0, \n                    \"rtt\": 77084, \n                    \"rttvar\": 6, \n                    \"seconds\": 0.9999819993972778, \n                    \"sender\": true, \n                    \"snd_cwnd\": 16708472, \n                    \"snd_wnd\": -1, \n                    \"socket\": 5, \n                    \"start\": 16.000082\n                }\n            ], \n            \"sum\": {\n                \"bits_per_second\": 870333746.532007, \n                \"bytes\": 108789760, \n                \"end\": 17.000064, \n                \"omitted\": false, \n                \"retransmits\": 0, \n                \"seconds\": 0.9999819993972778, \n                \"sender\": true, \n                \"start\": 16.000082\n            }\n        }, \n        {\n            \"streams\": [\n                {\n                    \"bits_per_second\": 859815100.3448608, \n                    \"bytes\": 107479040, \n                    \"end\": 18.000084, \n                    \"omitted\": false, \n                    \"pmtu\": 1500, \n                    \"retransmits\": 0, \n                    \"rtt\": 77091, \n                    \"rttvar\": 9, \n                    \"seconds\": 1.0000200271606445, \n                    \"sender\": true, \n                    \"snd_cwnd\": 16708472, \n                    \"snd_wnd\": -1, \n                    \"socket\": 5, \n                    \"start\": 17.000064\n                }\n            ], \n            \"sum\": {\n                \"bits_per_second\": 859815100.3448608, \n                \"bytes\": 107479040, \n                \"end\": 18.000084, \n                \"omitted\": false, \n                \"retransmits\": 0, \n                \"seconds\": 1.0000200271606445, \n                \"sender\": true, \n                \"start\": 17.000064\n            }\n        }, \n        {\n            \"streams\": [\n                {\n                    \"bits_per_second\": 870334628.43965, \n                    \"bytes\": 108789760, \n                    \"end\": 19.000065, \n                    \"omitted\": false, \n                    \"pmtu\": 1500, \n                    \"retransmits\": 0, \n                    \"rtt\": 77088, \n                    \"rttvar\": 4, \n                    \"seconds\": 0.9999809861183167, \n                    \"sender\": true, \n                    \"snd_cwnd\": 16708472, \n                    \"snd_wnd\": -1, \n                    \"socket\": 5, \n                    \"start\": 18.000084\n                }\n            ], \n            \"sum\": {\n                \"bits_per_second\": 870334628.43965, \n                \"bytes\": 108789760, \n                \"end\": 19.000065, \n                \"omitted\": false, \n                \"retransmits\": 0, \n                \"seconds\": 0.9999809861183167, \n                \"sender\": true, \n                \"start\": 18.000084\n            }\n        }, \n        {\n            \"streams\": [\n                {\n                    \"bits_per_second\": 870284985.0085285, \n                    \"bytes\": 108789760, \n                    \"end\": 20.000103, \n                    \"omitted\": false, \n                    \"pmtu\": 1500, \n                    \"retransmits\": 0, \n                    \"rtt\": 77086, \n                    \"rttvar\": 7, \n                    \"seconds\": 1.0000380277633667, \n                    \"sender\": true, \n                    \"snd_cwnd\": 16708472, \n                    \"snd_wnd\": -1, \n                    \"socket\": 5, \n                    \"start\": 19.000065\n                }\n            ], \n            \"sum\": {\n                \"bits_per_second\": 870284985.0085285, \n                \"bytes\": 108789760, \n                \"end\": 20.000103, \n                \"omitted\": false, \n                \"retransmits\": 0, \n                \"seconds\": 1.0000380277633667, \n                \"sender\": true, \n                \"start\": 19.000065\n            }\n        }, \n        {\n            \"streams\": [\n                {\n                    \"bits_per_second\": 859831500.000782, \n                    \"bytes\": 107479040, \n                    \"end\": 21.000104, \n                    \"omitted\": false, \n                    \"pmtu\": 1500, \n                    \"retransmits\": 0, \n                    \"rtt\": 77085, \n                    \"rttvar\": 8, \n                    \"seconds\": 1.0000009536743164, \n                    \"sender\": true, \n                    \"snd_cwnd\": 16708472, \n                    \"snd_wnd\": -1, \n                    \"socket\": 5, \n                    \"start\": 20.000103\n                }\n            ], \n            \"sum\": {\n                \"bits_per_second\": 859831500.000782, \n                \"bytes\": 107479040, \n                \"end\": 21.000104, \n                \"omitted\": false, \n                \"retransmits\": 0, \n                \"seconds\": 1.0000009536743164, \n                \"sender\": true, \n                \"start\": 20.000103\n            }\n        }, \n        {\n            \"streams\": [\n                {\n                    \"bits_per_second\": 870353771.4636353, \n                    \"bytes\": 108789760, \n                    \"end\": 22.000063, \n                    \"omitted\": false, \n                    \"pmtu\": 1500, \n                    \"retransmits\": 0, \n                    \"rtt\": 77085, \n                    \"rttvar\": 4, \n                    \"seconds\": 0.9999589920043945, \n                    \"sender\": true, \n                    \"snd_cwnd\": 16708472, \n                    \"snd_wnd\": -1, \n                    \"socket\": 5, \n                    \"start\": 21.000104\n                }\n            ], \n            \"sum\": {\n                \"bits_per_second\": 870353771.4636353, \n                \"bytes\": 108789760, \n                \"end\": 22.000063, \n                \"omitted\": false, \n                \"retransmits\": 0, \n                \"seconds\": 0.9999589920043945, \n                \"sender\": true, \n                \"start\": 21.000104\n            }\n        }, \n        {\n            \"streams\": [\n                {\n                    \"bits_per_second\": 859832320, \n                    \"bytes\": 107479040, \n                    \"end\": 23.000063, \n                    \"omitted\": false, \n                    \"pmtu\": 1500, \n                    \"retransmits\": 0, \n                    \"rtt\": 77089, \n                    \"rttvar\": 4, \n                    \"seconds\": 1, \n                    \"sender\": true, \n                    \"snd_cwnd\": 16708472, \n                    \"snd_wnd\": -1, \n                    \"socket\": 5, \n                    \"start\": 22.000063\n                }\n            ], \n            \"sum\": {\n                \"bits_per_second\": 859832320, \n                \"bytes\": 107479040, \n                \"end\": 23.000063, \n                \"omitted\": false, \n                \"retransmits\": 0, \n                \"seconds\": 1, \n                \"sender\": true, \n                \"start\": 22.000063\n            }\n        }, \n        {\n            \"streams\": [\n                {\n                    \"bits_per_second\": 870318080, \n                    \"bytes\": 108789760, \n                    \"end\": 24.000063, \n                    \"omitted\": false, \n                    \"pmtu\": 1500, \n                    \"retransmits\": 0, \n                    \"rtt\": 77086, \n                    \"rttvar\": 8, \n                    \"seconds\": 1, \n                    \"sender\": true, \n                    \"snd_cwnd\": 16708472, \n                    \"snd_wnd\": -1, \n                    \"socket\": 5, \n                    \"start\": 23.000063\n                }\n            ], \n            \"sum\": {\n                \"bits_per_second\": 870318080, \n                \"bytes\": 108789760, \n                \"end\": 24.000063, \n                \"omitted\": false, \n                \"retransmits\": 0, \n                \"seconds\": 1, \n                \"sender\": true, \n                \"start\": 23.000063\n            }\n        }, \n        {\n            \"streams\": [\n                {\n                    \"bits_per_second\": 859814280.3784863, \n                    \"bytes\": 107479040, \n                    \"end\": 25.000084, \n                    \"omitted\": false, \n                    \"pmtu\": 1500, \n                    \"retransmits\": 0, \n                    \"rtt\": 77091, \n                    \"rttvar\": 10, \n                    \"seconds\": 1.000020980834961, \n                    \"sender\": true, \n                    \"snd_cwnd\": 16708472, \n                    \"snd_wnd\": -1, \n                    \"socket\": 5, \n                    \"start\": 24.000063\n                }\n            ], \n            \"sum\": {\n                \"bits_per_second\": 859814280.3784863, \n                \"bytes\": 107479040, \n                \"end\": 25.000084, \n                \"omitted\": false, \n                \"retransmits\": 0, \n                \"seconds\": 1.000020980834961, \n                \"sender\": true, \n                \"start\": 24.000063\n            }\n        }, \n        {\n            \"streams\": [\n                {\n                    \"bits_per_second\": 870329388.8969457, \n                    \"bytes\": 108789760, \n                    \"end\": 26.000071, \n                    \"omitted\": false, \n                    \"pmtu\": 1500, \n                    \"retransmits\": 0, \n                    \"rtt\": 77089, \n                    \"rttvar\": 6, \n                    \"seconds\": 0.999987006187439, \n                    \"sender\": true, \n                    \"snd_cwnd\": 16708472, \n                    \"snd_wnd\": -1, \n                    \"socket\": 5, \n                    \"start\": 25.000084\n                }\n            ], \n            \"sum\": {\n                \"bits_per_second\": 870329388.8969457, \n                \"bytes\": 108789760, \n                \"end\": 26.000071, \n                \"omitted\": false, \n                \"retransmits\": 0, \n                \"seconds\": 0.999987006187439, \n                \"sender\": true, \n                \"start\": 25.000084\n            }\n        }, \n        {\n            \"streams\": [\n                {\n                    \"bits_per_second\": 859818585.2194, \n                    \"bytes\": 107479040, \n                    \"end\": 27.000087, \n                    \"omitted\": false, \n                    \"pmtu\": 1500, \n                    \"retransmits\": 0, \n                    \"rtt\": 77083, \n                    \"rttvar\": 8, \n                    \"seconds\": 1.0000159740448, \n                    \"sender\": true, \n                    \"snd_cwnd\": 16708472, \n                    \"snd_wnd\": -1, \n                    \"socket\": 5, \n                    \"start\": 26.000071\n                }\n            ], \n            \"sum\": {\n                \"bits_per_second\": 859818585.2194, \n                \"bytes\": 107479040, \n                \"end\": 27.000087, \n                \"omitted\": false, \n                \"retransmits\": 0, \n                \"seconds\": 1.0000159740448, \n                \"sender\": true, \n                \"start\": 26.000071\n            }\n        }, \n        {\n            \"streams\": [\n                {\n                    \"bits_per_second\": 870319843.7535744, \n                    \"bytes\": 108789760, \n                    \"end\": 28.000085, \n                    \"omitted\": false, \n                    \"pmtu\": 1500, \n                    \"retransmits\": 0, \n                    \"rtt\": 77090, \n                    \"rttvar\": 11, \n                    \"seconds\": 0.9999979734420776, \n                    \"sender\": true, \n                    \"snd_cwnd\": 16708472, \n                    \"snd_wnd\": -1, \n                    \"socket\": 5, \n                    \"start\": 27.000087\n                }\n            ], \n            \"sum\": {\n                \"bits_per_second\": 870319843.7535744, \n                \"bytes\": 108789760, \n                \"end\": 28.000085, \n                \"omitted\": false, \n                \"retransmits\": 0, \n                \"seconds\": 0.9999979734420776, \n                \"sender\": true, \n                \"start\": 27.000087\n            }\n        }, \n        {\n            \"streams\": [\n                {\n                    \"bits_per_second\": 859850360.3785022, \n                    \"bytes\": 107479040, \n                    \"end\": 29.000064, \n                    \"omitted\": false, \n                    \"pmtu\": 1500, \n                    \"retransmits\": 0, \n                    \"rtt\": 77092, \n                    \"rttvar\": 11, \n                    \"seconds\": 0.999979019165039, \n                    \"sender\": true, \n                    \"snd_cwnd\": 16708472, \n                    \"snd_wnd\": -1, \n                    \"socket\": 5, \n                    \"start\": 28.000085\n                }\n            ], \n            \"sum\": {\n                \"bits_per_second\": 859850360.3785022, \n                \"bytes\": 107479040, \n                \"end\": 29.000064, \n                \"omitted\": false, \n                \"retransmits\": 0, \n                \"seconds\": 0.999979019165039, \n                \"sender\": true, \n                \"start\": 28.000085\n            }\n        }, \n        {\n            \"streams\": [\n                {\n                    \"bits_per_second\": 870318961.8758936, \n                    \"bytes\": 108789760, \n                    \"end\": 30.000063, \n                    \"omitted\": false, \n                    \"pmtu\": 1500, \n                    \"retransmits\": 0, \n                    \"rtt\": 77087, \n                    \"rttvar\": 7, \n                    \"seconds\": 0.9999989867210388, \n                    \"sender\": true, \n                    \"snd_cwnd\": 16708472, \n                    \"snd_wnd\": -1, \n                    \"socket\": 5, \n                    \"start\": 29.000064\n                }\n            ], \n            \"sum\": {\n                \"bits_per_second\": 870318961.8758936, \n                \"bytes\": 108789760, \n                \"end\": 30.000063, \n                \"omitted\": false, \n                \"retransmits\": 0, \n                \"seconds\": 0.9999989867210388, \n                \"sender\": true, \n                \"start\": 29.000064\n            }\n        }, \n        {\n            \"streams\": [\n                {\n                    \"bits_per_second\": 870184055.6422174, \n                    \"bytes\": 108789760, \n                    \"end\": 31.000217, \n                    \"omitted\": false, \n                    \"pmtu\": 1500, \n                    \"retransmits\": 0, \n                    \"rtt\": 77088, \n                    \"rttvar\": 7, \n                    \"seconds\": 1.0001540184020996, \n                    \"sender\": true, \n                    \"snd_cwnd\": 16708472, \n                    \"snd_wnd\": -1, \n                    \"socket\": 5, \n                    \"start\": 30.000063\n                }\n            ], \n            \"sum\": {\n                \"bits_per_second\": 870184055.6422174, \n                \"bytes\": 108789760, \n                \"end\": 31.000217, \n                \"omitted\": false, \n                \"retransmits\": 0, \n                \"seconds\": 1.0001540184020996, \n                \"sender\": true, \n                \"start\": 30.000063\n            }\n        }, \n        {\n            \"streams\": [\n                {\n                    \"bits_per_second\": 859950980.1232878, \n                    \"bytes\": 107479040, \n                    \"end\": 32.000079, \n                    \"omitted\": false, \n                    \"pmtu\": 1500, \n                    \"retransmits\": 0, \n                    \"rtt\": 77087, \n                    \"rttvar\": 10, \n                    \"seconds\": 0.999862015247345, \n                    \"sender\": true, \n                    \"snd_cwnd\": 16708472, \n                    \"snd_wnd\": -1, \n                    \"socket\": 5, \n                    \"start\": 31.000217\n                }\n            ], \n            \"sum\": {\n                \"bits_per_second\": 859950980.1232878, \n                \"bytes\": 107479040, \n                \"end\": 32.000079, \n                \"omitted\": false, \n                \"retransmits\": 0, \n                \"seconds\": 0.999862015247345, \n                \"sender\": true, \n                \"start\": 31.000217\n            }\n        }, \n        {\n            \"streams\": [\n                {\n                    \"bits_per_second\": 870331982.7220827, \n                    \"bytes\": 108789760, \n                    \"end\": 33.000063, \n                    \"omitted\": false, \n                    \"pmtu\": 1500, \n                    \"retransmits\": 0, \n                    \"rtt\": 77091, \n                    \"rttvar\": 11, \n                    \"seconds\": 0.9999840259552002, \n                    \"sender\": true, \n                    \"snd_cwnd\": 16708472, \n                    \"snd_wnd\": -1, \n                    \"socket\": 5, \n                    \"start\": 32.000079\n                }\n            ], \n            \"sum\": {\n                \"bits_per_second\": 870331982.7220827, \n                \"bytes\": 108789760, \n                \"end\": 33.000063, \n                \"omitted\": false, \n                \"retransmits\": 0, \n                \"seconds\": 0.9999840259552002, \n                \"sender\": true, \n                \"start\": 32.000079\n            }\n        }, \n        {\n            \"streams\": [\n                {\n                    \"bits_per_second\": 859831500.000782, \n                    \"bytes\": 107479040, \n                    \"end\": 34.000064, \n                    \"omitted\": false, \n                    \"pmtu\": 1500, \n                    \"retransmits\": 0, \n                    \"rtt\": 77093, \n                    \"rttvar\": 5, \n                    \"seconds\": 1.0000009536743164, \n                    \"sender\": true, \n                    \"snd_cwnd\": 16708472, \n                    \"snd_wnd\": -1, \n                    \"socket\": 5, \n                    \"start\": 33.000063\n                }\n            ], \n            \"sum\": {\n                \"bits_per_second\": 859831500.000782, \n                \"bytes\": 107479040, \n                \"end\": 34.000064, \n                \"omitted\": false, \n                \"retransmits\": 0, \n                \"seconds\": 1.0000009536743164, \n                \"sender\": true, \n                \"start\": 33.000063\n            }\n        }, \n        {\n            \"streams\": [\n                {\n                    \"bits_per_second\": 870317250.0007915, \n                    \"bytes\": 108789760, \n                    \"end\": 35.000065, \n                    \"omitted\": false, \n                    \"pmtu\": 1500, \n                    \"retransmits\": 0, \n                    \"rtt\": 77087, \n                    \"rttvar\": 6, \n                    \"seconds\": 1.0000009536743164, \n                    \"sender\": true, \n                    \"snd_cwnd\": 16708472, \n                    \"snd_wnd\": -1, \n                    \"socket\": 5, \n                    \"start\": 34.000064\n                }\n            ], \n            \"sum\": {\n                \"bits_per_second\": 870317250.0007915, \n                \"bytes\": 108789760, \n                \"end\": 35.000065, \n                \"omitted\": false, \n                \"retransmits\": 0, \n                \"seconds\": 1.0000009536743164, \n                \"sender\": true, \n                \"start\": 34.000064\n            }\n        }, \n        {\n            \"streams\": [\n                {\n                    \"bits_per_second\": 859749815.4174267, \n                    \"bytes\": 107479040, \n                    \"end\": 36.000161, \n                    \"omitted\": false, \n                    \"pmtu\": 1500, \n                    \"retransmits\": 0, \n                    \"rtt\": 77086, \n                    \"rttvar\": 9, \n                    \"seconds\": 1.0000959634780884, \n                    \"sender\": true, \n                    \"snd_cwnd\": 16708472, \n                    \"snd_wnd\": -1, \n                    \"socket\": 5, \n                    \"start\": 35.000065\n                }\n            ], \n            \"sum\": {\n                \"bits_per_second\": 859749815.4174267, \n                \"bytes\": 107479040, \n                \"end\": 36.000161, \n                \"omitted\": false, \n                \"retransmits\": 0, \n                \"seconds\": 1.0000959634780884, \n                \"sender\": true, \n                \"start\": 35.000065\n            }\n        }, \n        {\n            \"streams\": [\n                {\n                    \"bits_per_second\": 870387701.81901, \n                    \"bytes\": 108789760, \n                    \"end\": 37.000081, \n                    \"omitted\": false, \n                    \"pmtu\": 1500, \n                    \"retransmits\": 0, \n                    \"rtt\": 77092, \n                    \"rttvar\": 7, \n                    \"seconds\": 0.9999200105667114, \n                    \"sender\": true, \n                    \"snd_cwnd\": 16708472, \n                    \"snd_wnd\": -1, \n                    \"socket\": 5, \n                    \"start\": 36.000161\n                }\n            ], \n            \"sum\": {\n                \"bits_per_second\": 870387701.81901, \n                \"bytes\": 108789760, \n                \"end\": 37.000081, \n                \"omitted\": false, \n                \"retransmits\": 0, \n                \"seconds\": 0.9999200105667114, \n                \"sender\": true, \n                \"start\": 36.000161\n            }\n        }, \n        {\n            \"streams\": [\n                {\n                    \"bits_per_second\": 859847797.7786094, \n                    \"bytes\": 107479040, \n                    \"end\": 38.000063, \n                    \"omitted\": false, \n                    \"pmtu\": 1500, \n                    \"retransmits\": 0, \n                    \"rtt\": 77086, \n                    \"rttvar\": 9, \n                    \"seconds\": 0.9999819993972778, \n                    \"sender\": true, \n                    \"snd_cwnd\": 16708472, \n                    \"snd_wnd\": -1, \n                    \"socket\": 5, \n                    \"start\": 37.000081\n                }\n            ], \n            \"sum\": {\n                \"bits_per_second\": 859847797.7786094, \n                \"bytes\": 107479040, \n                \"end\": 38.000063, \n                \"omitted\": false, \n                \"retransmits\": 0, \n                \"seconds\": 0.9999819993972778, \n                \"sender\": true, \n                \"start\": 37.000081\n            }\n        }, \n        {\n            \"streams\": [\n                {\n                    \"bits_per_second\": 870317250.0007915, \n                    \"bytes\": 108789760, \n                    \"end\": 39.000064, \n                    \"omitted\": false, \n                    \"pmtu\": 1500, \n                    \"retransmits\": 0, \n                    \"rtt\": 77085, \n                    \"rttvar\": 6, \n                    \"seconds\": 1.0000009536743164, \n                    \"sender\": true, \n                    \"snd_cwnd\": 16708472, \n                    \"snd_wnd\": -1, \n                    \"socket\": 5, \n                    \"start\": 38.000063\n                }\n            ], \n            \"sum\": {\n                \"bits_per_second\": 870317250.0007915, \n                \"bytes\": 108789760, \n                \"end\": 39.000064, \n                \"omitted\": false, \n                \"retransmits\": 0, \n                \"seconds\": 1.0000009536743164, \n                \"sender\": true, \n                \"start\": 38.000063\n            }\n        }, \n        {\n            \"streams\": [\n                {\n                    \"bits_per_second\": 859830577.5035312, \n                    \"bytes\": 107479040, \n                    \"end\": 40.000066, \n                    \"omitted\": false, \n                    \"pmtu\": 1500, \n                    \"retransmits\": 0, \n                    \"rtt\": 77087, \n                    \"rttvar\": 5, \n                    \"seconds\": 1.0000020265579224, \n                    \"sender\": true, \n                    \"snd_cwnd\": 16708472, \n                    \"snd_wnd\": -1, \n                    \"socket\": 5, \n                    \"start\": 39.000064\n                }\n            ], \n            \"sum\": {\n                \"bits_per_second\": 859830577.5035312, \n                \"bytes\": 107479040, \n                \"end\": 40.000066, \n                \"omitted\": false, \n                \"retransmits\": 0, \n                \"seconds\": 1.0000020265579224, \n                \"sender\": true, \n                \"start\": 39.000064\n            }\n        }, \n        {\n            \"streams\": [\n                {\n                    \"bits_per_second\": 870320673.75773, \n                    \"bytes\": 108789760, \n                    \"end\": 41.000063, \n                    \"omitted\": false, \n                    \"pmtu\": 1500, \n                    \"retransmits\": 0, \n                    \"rtt\": 77088, \n                    \"rttvar\": 6, \n                    \"seconds\": 0.9999970197677612, \n                    \"sender\": true, \n                    \"snd_cwnd\": 16708472, \n                    \"snd_wnd\": -1, \n                    \"socket\": 5, \n                    \"start\": 40.000066\n                }\n            ], \n            \"sum\": {\n                \"bits_per_second\": 870320673.75773, \n                \"bytes\": 108789760, \n                \"end\": 41.000063, \n                \"omitted\": false, \n                \"retransmits\": 0, \n                \"seconds\": 0.9999970197677612, \n                \"sender\": true, \n                \"start\": 40.000066\n            }\n        }, \n        {\n            \"streams\": [\n                {\n                    \"bits_per_second\": 870318080, \n                    \"bytes\": 108789760, \n                    \"end\": 42.000063, \n                    \"omitted\": false, \n                    \"pmtu\": 1500, \n                    \"retransmits\": 0, \n                    \"rtt\": 77089, \n                    \"rttvar\": 8, \n                    \"seconds\": 1, \n                    \"sender\": true, \n                    \"snd_cwnd\": 16708472, \n                    \"snd_wnd\": -1, \n                    \"socket\": 5, \n                    \"start\": 41.000063\n                }\n            ], \n            \"sum\": {\n                \"bits_per_second\": 870318080, \n                \"bytes\": 108789760, \n                \"end\": 42.000063, \n                \"omitted\": false, \n                \"retransmits\": 0, \n                \"seconds\": 1, \n                \"sender\": true, \n                \"start\": 41.000063\n            }\n        }, \n        {\n            \"streams\": [\n                {\n                    \"bits_per_second\": 859755759.3176782, \n                    \"bytes\": 107479040, \n                    \"end\": 43.000152, \n                    \"omitted\": false, \n                    \"pmtu\": 1500, \n                    \"retransmits\": 0, \n                    \"rtt\": 77087, \n                    \"rttvar\": 5, \n                    \"seconds\": 1.0000890493392944, \n                    \"sender\": true, \n                    \"snd_cwnd\": 16708472, \n                    \"snd_wnd\": -1, \n                    \"socket\": 5, \n                    \"start\": 42.000063\n                }\n            ], \n            \"sum\": {\n                \"bits_per_second\": 859755759.3176782, \n                \"bytes\": 107479040, \n                \"end\": 43.000152, \n                \"omitted\": false, \n                \"retransmits\": 0, \n                \"seconds\": 1.0000890493392944, \n                \"sender\": true, \n                \"start\": 42.000063\n            }\n        }, \n        {\n            \"streams\": [\n                {\n                    \"bits_per_second\": 870385989.673481, \n                    \"bytes\": 108789760, \n                    \"end\": 44.000074, \n                    \"omitted\": false, \n                    \"pmtu\": 1500, \n                    \"retransmits\": 0, \n                    \"rtt\": 77087, \n                    \"rttvar\": 5, \n                    \"seconds\": 0.999921977519989, \n                    \"sender\": true, \n                    \"snd_cwnd\": 16708472, \n                    \"snd_wnd\": -1, \n                    \"socket\": 5, \n                    \"start\": 43.000152\n                }\n            ], \n            \"sum\": {\n                \"bits_per_second\": 870385989.673481, \n                \"bytes\": 108789760, \n                \"end\": 44.000074, \n                \"omitted\": false, \n                \"retransmits\": 0, \n                \"seconds\": 0.999921977519989, \n                \"sender\": true, \n                \"start\": 43.000152\n            }\n        }, \n        {\n            \"streams\": [\n                {\n                    \"bits_per_second\": 859840930.0862178, \n                    \"bytes\": 107479040, \n                    \"end\": 45.000064, \n                    \"omitted\": false, \n                    \"pmtu\": 1500, \n                    \"retransmits\": 0, \n                    \"rtt\": 77091, \n                    \"rttvar\": 6, \n                    \"seconds\": 0.9999899864196777, \n                    \"sender\": true, \n                    \"snd_cwnd\": 16708472, \n                    \"snd_wnd\": -1, \n                    \"socket\": 5, \n                    \"start\": 44.000074\n                }\n            ], \n            \"sum\": {\n                \"bits_per_second\": 859840930.0862178, \n                \"bytes\": 107479040, \n                \"end\": 45.000064, \n                \"omitted\": false, \n                \"retransmits\": 0, \n                \"seconds\": 0.9999899864196777, \n                \"sender\": true, \n                \"start\": 44.000074\n            }\n        }, \n        {\n            \"streams\": [\n                {\n                    \"bits_per_second\": 870304177.7220756, \n                    \"bytes\": 108789760, \n                    \"end\": 46.00008, \n                    \"omitted\": false, \n                    \"pmtu\": 1500, \n                    \"retransmits\": 0, \n                    \"rtt\": 77088, \n                    \"rttvar\": 6, \n                    \"seconds\": 1.0000159740448, \n                    \"sender\": true, \n                    \"snd_cwnd\": 16708472, \n                    \"snd_wnd\": -1, \n                    \"socket\": 5, \n                    \"start\": 45.000064\n                }\n            ], \n            \"sum\": {\n                \"bits_per_second\": 870304177.7220756, \n                \"bytes\": 108789760, \n                \"end\": 46.00008, \n                \"omitted\": false, \n                \"retransmits\": 0, \n                \"seconds\": 1.0000159740448, \n                \"sender\": true, \n                \"start\": 45.000064\n            }\n        }, \n        {\n            \"streams\": [\n                {\n                    \"bits_per_second\": 859846926.4981253, \n                    \"bytes\": 107479040, \n                    \"end\": 47.000063, \n                    \"omitted\": false, \n                    \"pmtu\": 1500, \n                    \"retransmits\": 0, \n                    \"rtt\": 77090, \n                    \"rttvar\": 10, \n                    \"seconds\": 0.999983012676239, \n                    \"sender\": true, \n                    \"snd_cwnd\": 16708472, \n                    \"snd_wnd\": -1, \n                    \"socket\": 5, \n                    \"start\": 46.00008\n                }\n            ], \n            \"sum\": {\n                \"bits_per_second\": 859846926.4981253, \n                \"bytes\": 107479040, \n                \"end\": 47.000063, \n                \"omitted\": false, \n                \"retransmits\": 0, \n                \"seconds\": 0.999983012676239, \n                \"sender\": true, \n                \"start\": 46.00008\n            }\n        }, \n        {\n            \"streams\": [\n                {\n                    \"bits_per_second\": 870317250.0007915, \n                    \"bytes\": 108789760, \n                    \"end\": 48.000064, \n                    \"omitted\": false, \n                    \"pmtu\": 1500, \n                    \"retransmits\": 0, \n                    \"rtt\": 77091, \n                    \"rttvar\": 8, \n                    \"seconds\": 1.0000009536743164, \n                    \"sender\": true, \n                    \"snd_cwnd\": 16708472, \n                    \"snd_wnd\": -1, \n                    \"socket\": 5, \n                    \"start\": 47.000063\n                }\n            ], \n            \"sum\": {\n                \"bits_per_second\": 870317250.0007915, \n                \"bytes\": 108789760, \n                \"end\": 48.000064, \n                \"omitted\": false, \n                \"retransmits\": 0, \n                \"seconds\": 1.0000009536743164, \n                \"sender\": true, \n                \"start\": 47.000063\n            }\n        }, \n        {\n            \"streams\": [\n                {\n                    \"bits_per_second\": 859790194.5639365, \n                    \"bytes\": 107479040, \n                    \"end\": 49.000113, \n                    \"omitted\": false, \n                    \"pmtu\": 1500, \n                    \"retransmits\": 0, \n                    \"rtt\": 77088, \n                    \"rttvar\": 8, \n                    \"seconds\": 1.0000489950180054, \n                    \"sender\": true, \n                    \"snd_cwnd\": 16708472, \n                    \"snd_wnd\": -1, \n                    \"socket\": 5, \n                    \"start\": 48.000064\n                }\n            ], \n            \"sum\": {\n                \"bits_per_second\": 859790194.5639365, \n                \"bytes\": 107479040, \n                \"end\": 49.000113, \n                \"omitted\": false, \n                \"retransmits\": 0, \n                \"seconds\": 1.0000489950180054, \n                \"sender\": true, \n                \"start\": 48.000064\n            }\n        }, \n        {\n            \"streams\": [\n                {\n                    \"bits_per_second\": 870286748.627967, \n                    \"bytes\": 108789760, \n                    \"end\": 50.000149, \n                    \"omitted\": false, \n                    \"pmtu\": 1500, \n                    \"retransmits\": 0, \n                    \"rtt\": 77085, \n                    \"rttvar\": 8, \n                    \"seconds\": 1.0000360012054443, \n                    \"sender\": true, \n                    \"snd_cwnd\": 16708472, \n                    \"snd_wnd\": -1, \n                    \"socket\": 5, \n                    \"start\": 49.000113\n                }\n            ], \n            \"sum\": {\n                \"bits_per_second\": 870286748.627967, \n                \"bytes\": 108789760, \n                \"end\": 50.000149, \n                \"omitted\": false, \n                \"retransmits\": 0, \n                \"seconds\": 1.0000360012054443, \n                \"sender\": true, \n                \"start\": 49.000113\n            }\n        }, \n        {\n            \"streams\": [\n                {\n                    \"bits_per_second\": 859809975.5806783, \n                    \"bytes\": 107479040, \n                    \"end\": 51.000175, \n                    \"omitted\": false, \n                    \"pmtu\": 1500, \n                    \"retransmits\": 0, \n                    \"rtt\": 77086, \n                    \"rttvar\": 9, \n                    \"seconds\": 1.000025987625122, \n                    \"sender\": true, \n                    \"snd_cwnd\": 16708472, \n                    \"snd_wnd\": -1, \n                    \"socket\": 5, \n                    \"start\": 50.000149\n                }\n            ], \n            \"sum\": {\n                \"bits_per_second\": 859809975.5806783, \n                \"bytes\": 107479040, \n                \"end\": 51.000175, \n                \"omitted\": false, \n                \"retransmits\": 0, \n                \"seconds\": 1.000025987625122, \n                \"sender\": true, \n                \"start\": 50.000149\n            }\n        }, \n        {\n            \"streams\": [\n                {\n                    \"bits_per_second\": 870405965.1237845, \n                    \"bytes\": 108789760, \n                    \"end\": 52.000074, \n                    \"omitted\": false, \n                    \"pmtu\": 1500, \n                    \"retransmits\": 0, \n                    \"rtt\": 77084, \n                    \"rttvar\": 6, \n                    \"seconds\": 0.9998990297317505, \n                    \"sender\": true, \n                    \"snd_cwnd\": 16708472, \n                    \"snd_wnd\": -1, \n                    \"socket\": 5, \n                    \"start\": 51.000175\n                }\n            ], \n            \"sum\": {\n                \"bits_per_second\": 870405965.1237845, \n                \"bytes\": 108789760, \n                \"end\": 52.000074, \n                \"omitted\": false, \n                \"retransmits\": 0, \n                \"seconds\": 0.9998990297317505, \n                \"sender\": true, \n                \"start\": 51.000175\n            }\n        }, \n        {\n            \"streams\": [\n                {\n                    \"bits_per_second\": 870328506.999921, \n                    \"bytes\": 108789760, \n                    \"end\": 53.000062, \n                    \"omitted\": false, \n                    \"pmtu\": 1500, \n                    \"retransmits\": 0, \n                    \"rtt\": 77085, \n                    \"rttvar\": 7, \n                    \"seconds\": 0.9999880194664, \n                    \"sender\": true, \n                    \"snd_cwnd\": 16708472, \n                    \"snd_wnd\": -1, \n                    \"socket\": 5, \n                    \"start\": 52.000074\n                }\n            ], \n            \"sum\": {\n                \"bits_per_second\": 870328506.999921, \n                \"bytes\": 108789760, \n                \"end\": 53.000062, \n                \"omitted\": false, \n                \"retransmits\": 0, \n                \"seconds\": 0.9999880194664, \n                \"sender\": true, \n                \"start\": 52.000074\n            }\n        }, \n        {\n            \"streams\": [\n                {\n                    \"bits_per_second\": 859748893.0954432, \n                    \"bytes\": 107479040, \n                    \"end\": 54.000159, \n                    \"omitted\": false, \n                    \"pmtu\": 1500, \n                    \"retransmits\": 0, \n                    \"rtt\": 77085, \n                    \"rttvar\": 9, \n                    \"seconds\": 1.0000970363616943, \n                    \"sender\": true, \n                    \"snd_cwnd\": 16708472, \n                    \"snd_wnd\": -1, \n                    \"socket\": 5, \n                    \"start\": 53.000062\n                }\n            ], \n            \"sum\": {\n                \"bits_per_second\": 859748893.0954432, \n                \"bytes\": 107479040, \n                \"end\": 54.000159, \n                \"omitted\": false, \n                \"retransmits\": 0, \n                \"seconds\": 1.0000970363616943, \n                \"sender\": true, \n                \"start\": 53.000062\n            }\n        }, \n        {\n            \"streams\": [\n                {\n                    \"bits_per_second\": 870327676.9808246, \n                    \"bytes\": 108789760, \n                    \"end\": 55.000148, \n                    \"omitted\": false, \n                    \"pmtu\": 1500, \n                    \"retransmits\": 0, \n                    \"rtt\": 77091, \n                    \"rttvar\": 9, \n                    \"seconds\": 0.9999889731407166, \n                    \"sender\": true, \n                    \"snd_cwnd\": 16708472, \n                    \"snd_wnd\": -1, \n                    \"socket\": 5, \n                    \"start\": 54.000159\n                }\n            ], \n            \"sum\": {\n                \"bits_per_second\": 870327676.9808246, \n                \"bytes\": 108789760, \n                \"end\": 55.000148, \n                \"omitted\": false, \n                \"retransmits\": 0, \n                \"seconds\": 0.9999889731407166, \n                \"sender\": true, \n                \"start\": 54.000159\n            }\n        }, \n        {\n            \"streams\": [\n                {\n                    \"bits_per_second\": 859825452.5548505, \n                    \"bytes\": 107479040, \n                    \"end\": 56.000156, \n                    \"omitted\": false, \n                    \"pmtu\": 1500, \n                    \"retransmits\": 0, \n                    \"rtt\": 77085, \n                    \"rttvar\": 12, \n                    \"seconds\": 1.0000079870224, \n                    \"sender\": true, \n                    \"snd_cwnd\": 16708472, \n                    \"snd_wnd\": -1, \n                    \"socket\": 5, \n                    \"start\": 55.000148\n                }\n            ], \n            \"sum\": {\n                \"bits_per_second\": 859825452.5548505, \n                \"bytes\": 107479040, \n                \"end\": 56.000156, \n                \"omitted\": false, \n                \"retransmits\": 0, \n                \"seconds\": 1.0000079870224, \n                \"sender\": true, \n                \"start\": 55.000148\n            }\n        }, \n        {\n            \"streams\": [\n                {\n                    \"bits_per_second\": 870320673.75773, \n                    \"bytes\": 108789760, \n                    \"end\": 57.000153, \n                    \"omitted\": false, \n                    \"pmtu\": 1500, \n                    \"retransmits\": 0, \n                    \"rtt\": 77086, \n                    \"rttvar\": 8, \n                    \"seconds\": 0.9999970197677612, \n                    \"sender\": true, \n                    \"snd_cwnd\": 16708472, \n                    \"snd_wnd\": -1, \n                    \"socket\": 5, \n                    \"start\": 56.000156\n                }\n            ], \n            \"sum\": {\n                \"bits_per_second\": 870320673.75773, \n                \"bytes\": 108789760, \n                \"end\": 57.000153, \n                \"omitted\": false, \n                \"retransmits\": 0, \n                \"seconds\": 0.9999970197677612, \n                \"sender\": true, \n                \"start\": 56.000156\n            }\n        }, \n        {\n            \"streams\": [\n                {\n                    \"bits_per_second\": 859823710.086216, \n                    \"bytes\": 107479040, \n                    \"end\": 58.000163, \n                    \"omitted\": false, \n                    \"pmtu\": 1500, \n                    \"retransmits\": 0, \n                    \"rtt\": 77086, \n                    \"rttvar\": 7, \n                    \"seconds\": 1.0000100135803223, \n                    \"sender\": true, \n                    \"snd_cwnd\": 16708472, \n                    \"snd_wnd\": -1, \n                    \"socket\": 5, \n                    \"start\": 57.000153\n                }\n            ], \n            \"sum\": {\n                \"bits_per_second\": 859823710.086216, \n                \"bytes\": 107479040, \n                \"end\": 58.000163, \n                \"omitted\": false, \n                \"retransmits\": 0, \n                \"seconds\": 1.0000100135803223, \n                \"sender\": true, \n                \"start\": 57.000153\n            }\n        }, \n        {\n            \"streams\": [\n                {\n                    \"bits_per_second\": 870324149.4173266, \n                    \"bytes\": 108789760, \n                    \"end\": 59.000156, \n                    \"omitted\": false, \n                    \"pmtu\": 1500, \n                    \"retransmits\": 0, \n                    \"rtt\": 77090, \n                    \"rttvar\": 5, \n                    \"seconds\": 0.9999930262565613, \n                    \"sender\": true, \n                    \"snd_cwnd\": 16708472, \n                    \"snd_wnd\": -1, \n                    \"socket\": 5, \n                    \"start\": 58.000163\n                }\n            ], \n            \"sum\": {\n                \"bits_per_second\": 870324149.4173266, \n                \"bytes\": 108789760, \n                \"end\": 59.000156, \n                \"omitted\": false, \n                \"retransmits\": 0, \n                \"seconds\": 0.9999930262565613, \n                \"sender\": true, \n                \"start\": 58.000163\n            }\n        }, \n        {\n            \"streams\": [\n                {\n                    \"bits_per_second\": 859823710.086216, \n                    \"bytes\": 107479040, \n                    \"end\": 60.000166, \n                    \"omitted\": false, \n                    \"pmtu\": 1500, \n                    \"retransmits\": 0, \n                    \"rtt\": 77088, \n                    \"rttvar\": 8, \n                    \"seconds\": 1.0000100135803223, \n                    \"sender\": true, \n                    \"snd_cwnd\": 16708472, \n                    \"snd_wnd\": -1, \n                    \"socket\": 5, \n                    \"start\": 59.000156\n                }\n            ], \n            \"sum\": {\n                \"bits_per_second\": 859823710.086216, \n                \"bytes\": 107479040, \n                \"end\": 60.000166, \n                \"omitted\": false, \n                \"retransmits\": 0, \n                \"seconds\": 1.0000100135803223, \n                \"sender\": true, \n                \"start\": 59.000156\n            }\n        }\n    ], \n    \"start\": {\n        \"connected\": [\n            {\n                \"local_host\": \"10.0.0.1\", \n                \"local_port\": 56875, \n                \"remote_host\": \"10.0.0.2\", \n                \"remote_port\": 5201, \n                \"socket\": 5\n            }\n        ], \n        \"connecting_to\": {\n            \"host\": \"10.0.0.2\", \n            \"port\": 5201\n        }, \n        \"cookie\": \"7z3nrbbxhssi64gdqpllh6jvm53y5fkymfpx\", \n        \"fq_rate\": 0, \n        \"rcvbuf_actual\": 87380, \n        \"sndbuf_actual\": 87380, \n        \"sock_bufsize\": 0, \n        \"system_info\": \"REDACTED\", \n        \"target_bitrate\": 0, \n        \"tcp_mss_default\": 1448, \n        \"test_start\": {\n            \"bidir\": 0, \n            \"blksize\": 131072, \n            \"blocks\": 0, \n            \"bytes\": 0, \n            \"duration\": 60, \n            \"fqrate\": 0, \n            \"num_streams\": 1, \n            \"omit\": 0, \n            \"protocol\": \"TCP\", \n            \"reverse\": 0, \n            \"target_bitrate\": 0, \n            \"tos\": 0\n        }, \n        \"timestamp\": {\n            \"time\": \"Wed, 17 Apr 2024 01:20:34 GMT\", \n            \"timesecs\": 1713316834\n        }, \n        \"version\": \"iperf 3.14\"\n    }\n}\nParticipant 1:\n/usr/bin/iperf3 -s -1 --idle-timeout 60 --json -p 5201 -B 10.0.0.2 --authorized-users-path /var/run/pscheduler-server/runner/tmp/tmpcfki2sup/tmpuizd6btl/credentials --rsa-private-key-path /var/run/pscheduler-server/runner/tmp/tmpcfki2sup/tmpuizd6btl/private-key\n\n{\n    \"end\": {\n        \"cpu_utilization_percent\": {\n            \"host_system\": 4.81051399247522, \n            \"host_total\": 5.278140779705447, \n            \"host_user\": 0.46762345816747186, \n            \"remote_system\": 0, \n            \"remote_total\": 0, \n            \"remote_user\": 0\n        }, \n        \"receiver_tcp_congestion\": \"htcp\", \n        \"streams\": [\n            {\n                \"receiver\": {\n                    \"bits_per_second\": 865534406.0676053, \n                    \"bytes\": 6499833080, \n                    \"end\": 60.076947, \n                    \"seconds\": 60.076947, \n                    \"sender\": false, \n                    \"socket\": 5, \n                    \"start\": 0\n                }, \n                \"sender\": {\n                    \"bits_per_second\": 0, \n                    \"bytes\": 0, \n                    \"end\": 60.076947, \n                    \"seconds\": 60.076947, \n                    \"sender\": false, \n                    \"socket\": 5, \n                    \"start\": 0\n                }\n            }\n        ], \n        \"sum_received\": {\n            \"bits_per_second\": 865534406.0676053, \n            \"bytes\": 6499833080, \n            \"end\": 60.076947, \n            \"seconds\": 60.076947, \n            \"sender\": false, \n            \"start\": 0\n        }, \n        \"sum_sent\": {\n            \"bits_per_second\": 0, \n            \"bytes\": 0, \n            \"end\": 60.076947, \n            \"seconds\": 60.076947, \n            \"sender\": false, \n            \"start\": 0\n        }\n    }, \n    \"intervals\": [\n        {\n            \"streams\": [\n                {\n                    \"bits_per_second\": 865214999.7422898, \n                    \"bytes\": 108158360, \n                    \"end\": 1.00006, \n                    \"omitted\": false, \n                    \"seconds\": 1.000059962272644, \n                    \"sender\": false, \n                    \"socket\": 5, \n                    \"start\": 0\n                }\n            ], \n            \"sum\": {\n                \"bits_per_second\": 865214999.7422898, \n                \"bytes\": 108158360, \n                \"end\": 1.00006, \n                \"omitted\": false, \n                \"seconds\": 1.000059962272644, \n                \"sender\": false, \n                \"start\": 0\n            }\n        }, \n        {\n            \"streams\": [\n                {\n                    \"bits_per_second\": 865307470.3482844, \n                    \"bytes\": 108165600, \n                    \"end\": 2.00008, \n                    \"omitted\": false, \n                    \"seconds\": 1.0000200271606445, \n                    \"sender\": false, \n                    \"socket\": 5, \n                    \"start\": 1.00006\n                }\n            ], \n            \"sum\": {\n                \"bits_per_second\": 865307470.3482844, \n                \"bytes\": 108165600, \n                \"end\": 2.00008, \n                \"omitted\": false, \n                \"seconds\": 1.0000200271606445, \n                \"sender\": false, \n                \"start\": 1.00006\n            }\n        }, \n        {\n            \"streams\": [\n                {\n                    \"bits_per_second\": 865866001.3192767, \n                    \"bytes\": 108230760, \n                    \"end\": 3.000057, \n                    \"omitted\": false, \n                    \"seconds\": 0.9999769926071167, \n                    \"sender\": false, \n                    \"socket\": 5, \n                    \"start\": 2.00008\n                }\n            ], \n            \"sum\": {\n                \"bits_per_second\": 865866001.3192767, \n                \"bytes\": 108230760, \n                \"end\": 3.000057, \n                \"omitted\": false, \n                \"seconds\": 0.9999769926071167, \n                \"sender\": false, \n                \"start\": 2.00008\n            }\n        }, \n        {\n            \"streams\": [\n                {\n                    \"bits_per_second\": 865321292.7525575, \n                    \"bytes\": 108165600, \n                    \"end\": 4.000061, \n                    \"omitted\": false, \n                    \"seconds\": 1.0000040531158447, \n                    \"sender\": false, \n                    \"socket\": 5, \n                    \"start\": 3.000057\n                }\n            ], \n            \"sum\": {\n                \"bits_per_second\": 865321292.7525575, \n                \"bytes\": 108165600, \n                \"end\": 4.000061, \n                \"omitted\": false, \n                \"seconds\": 1.0000040531158447, \n                \"sender\": false, \n                \"start\": 3.000057\n            }\n        }, \n        {\n            \"streams\": [\n                {\n                    \"bits_per_second\": 865301487.6535165, \n                    \"bytes\": 108165600, \n                    \"end\": 5.000088, \n                    \"omitted\": false, \n                    \"seconds\": 1.0000269412994385, \n                    \"sender\": false, \n                    \"socket\": 5, \n                    \"start\": 4.000061\n                }\n            ], \n            \"sum\": {\n                \"bits_per_second\": 865301487.6535165, \n                \"bytes\": 108165600, \n                \"end\": 5.000088, \n                \"omitted\": false, \n                \"seconds\": 1.0000269412994385, \n                \"sender\": false, \n                \"start\": 4.000061\n            }\n        }, \n        {\n            \"streams\": [\n                {\n                    \"bits_per_second\": 865870336.6501037, \n                    \"bytes\": 108230760, \n                    \"end\": 6.00006, \n                    \"omitted\": false, \n                    \"seconds\": 0.9999719858169556, \n                    \"sender\": false, \n                    \"socket\": 5, \n                    \"start\": 5.000088\n                }\n            ], \n            \"sum\": {\n                \"bits_per_second\": 865870336.6501037, \n                \"bytes\": 108230760, \n                \"end\": 6.00006, \n                \"omitted\": false, \n                \"seconds\": 0.9999719858169556, \n                \"sender\": false, \n                \"start\": 5.000088\n            }\n        }, \n        {\n            \"streams\": [\n                {\n                    \"bits_per_second\": 865305716.7912476, \n                    \"bytes\": 108165600, \n                    \"end\": 7.000082, \n                    \"omitted\": false, \n                    \"seconds\": 1.000022053718567, \n                    \"sender\": false, \n                    \"socket\": 5, \n                    \"start\": 6.00006\n                }\n            ], \n            \"sum\": {\n                \"bits_per_second\": 865305716.7912476, \n                \"bytes\": 108165600, \n                \"end\": 7.000082, \n                \"omitted\": false, \n                \"seconds\": 1.000022053718567, \n                \"sender\": false, \n                \"start\": 6.00006\n            }\n        }, \n        {\n            \"streams\": [\n                {\n                    \"bits_per_second\": 865864246.5548556, \n                    \"bytes\": 108230760, \n                    \"end\": 8.000061, \n                    \"omitted\": false, \n                    \"seconds\": 0.999979019165039, \n                    \"sender\": false, \n                    \"socket\": 5, \n                    \"start\": 7.000082\n                }\n            ], \n            \"sum\": {\n                \"bits_per_second\": 865864246.5548556, \n                \"bytes\": 108230760, \n                \"end\": 8.000061, \n                \"omitted\": false, \n                \"seconds\": 0.999979019165039, \n                \"sender\": false, \n                \"start\": 7.000082\n            }\n        }, \n        {\n            \"streams\": [\n                {\n                    \"bits_per_second\": 865310049.121544, \n                    \"bytes\": 108165600, \n                    \"end\": 9.000078, \n                    \"omitted\": false, \n                    \"seconds\": 1.0000170469284058, \n                    \"sender\": false, \n                    \"socket\": 5, \n                    \"start\": 8.000061\n                }\n            ], \n            \"sum\": {\n                \"bits_per_second\": 865310049.121544, \n                \"bytes\": 108165600, \n                \"end\": 9.000078, \n                \"omitted\": false, \n                \"seconds\": 1.0000170469284058, \n                \"sender\": false, \n                \"start\": 8.000061\n            }\n        }, \n        {\n            \"streams\": [\n                {\n                    \"bits_per_second\": 865872039.8276635, \n                    \"bytes\": 108230760, \n                    \"end\": 10.000048, \n                    \"omitted\": false, \n                    \"seconds\": 0.999970018863678, \n                    \"sender\": false, \n                    \"socket\": 5, \n                    \"start\": 9.000078\n                }\n            ], \n            \"sum\": {\n                \"bits_per_second\": 865872039.8276635, \n                \"bytes\": 108230760, \n                \"end\": 10.000048, \n                \"omitted\": false, \n                \"seconds\": 0.999970018863678, \n                \"sender\": false, \n                \"start\": 9.000078\n            }\n        }, \n        {\n            \"streams\": [\n                {\n                    \"bits_per_second\": 865309223.9124285, \n                    \"bytes\": 108165600, \n                    \"end\": 11.000066, \n                    \"omitted\": false, \n                    \"seconds\": 1.0000180006027222, \n                    \"sender\": false, \n                    \"socket\": 5, \n                    \"start\": 10.000048\n                }\n            ], \n            \"sum\": {\n                \"bits_per_second\": 865309223.9124285, \n                \"bytes\": 108165600, \n                \"end\": 11.000066, \n                \"omitted\": false, \n                \"seconds\": 1.0000180006027222, \n                \"sender\": false, \n                \"start\": 10.000048\n            }\n        }, \n        {\n            \"streams\": [\n                {\n                    \"bits_per_second\": 865311802.6961398, \n                    \"bytes\": 108165600, \n                    \"end\": 12.000081, \n                    \"omitted\": false, \n                    \"seconds\": 1.0000150203704834, \n                    \"sender\": false, \n                    \"socket\": 5, \n                    \"start\": 11.000066\n                }\n            ], \n            \"sum\": {\n                \"bits_per_second\": 865311802.6961398, \n                \"bytes\": 108165600, \n                \"end\": 12.000081, \n                \"omitted\": false, \n                \"seconds\": 1.0000150203704834, \n                \"sender\": false, \n                \"start\": 11.000066\n            }\n        }, \n        {\n            \"streams\": [\n                {\n                    \"bits_per_second\": 865864246.5548556, \n                    \"bytes\": 108230760, \n                    \"end\": 13.00006, \n                    \"omitted\": false, \n                    \"seconds\": 0.999979019165039, \n                    \"sender\": false, \n                    \"socket\": 5, \n                    \"start\": 12.000081\n                }\n            ], \n            \"sum\": {\n                \"bits_per_second\": 865864246.5548556, \n                \"bytes\": 108230760, \n                \"end\": 13.00006, \n                \"omitted\": false, \n                \"seconds\": 0.999979019165039, \n                \"sender\": false, \n                \"start\": 12.000081\n            }\n        }, \n        {\n            \"streams\": [\n                {\n                    \"bits_per_second\": 865305716.7912476, \n                    \"bytes\": 108165600, \n                    \"end\": 14.000082, \n                    \"omitted\": false, \n                    \"seconds\": 1.000022053718567, \n                    \"sender\": false, \n                    \"socket\": 5, \n                    \"start\": 13.00006\n                }\n            ], \n            \"sum\": {\n                \"bits_per_second\": 865305716.7912476, \n                \"bytes\": 108165600, \n                \"end\": 14.000082, \n                \"omitted\": false, \n                \"seconds\": 1.000022053718567, \n                \"sender\": false, \n                \"start\": 13.00006\n            }\n        }, \n        {\n            \"streams\": [\n                {\n                    \"bits_per_second\": 865863420.7858243, \n                    \"bytes\": 108230760, \n                    \"end\": 15.000062, \n                    \"omitted\": false, \n                    \"seconds\": 0.9999799728393555, \n                    \"sender\": false, \n                    \"socket\": 5, \n                    \"start\": 14.000082\n                }\n            ], \n            \"sum\": {\n                \"bits_per_second\": 865863420.7858243, \n                \"bytes\": 108230760, \n                \"end\": 15.000062, \n                \"omitted\": false, \n                \"seconds\": 0.9999799728393555, \n                \"sender\": false, \n                \"start\": 14.000082\n            }\n        }, \n        {\n            \"streams\": [\n                {\n                    \"bits_per_second\": 865312731.0620387, \n                    \"bytes\": 108165600, \n                    \"end\": 16.000076, \n                    \"omitted\": false, \n                    \"seconds\": 1.0000139474868774, \n                    \"sender\": false, \n                    \"socket\": 5, \n                    \"start\": 15.000062\n                }\n            ], \n            \"sum\": {\n                \"bits_per_second\": 865312731.0620387, \n                \"bytes\": 108165600, \n                \"end\": 16.000076, \n                \"omitted\": false, \n                \"seconds\": 1.0000139474868774, \n                \"sender\": false, \n                \"start\": 15.000062\n            }\n        }, \n        {\n            \"streams\": [\n                {\n                    \"bits_per_second\": 865868581.8681105, \n                    \"bytes\": 108230760, \n                    \"end\": 17.00005, \n                    \"omitted\": false, \n                    \"seconds\": 0.999974012374878, \n                    \"sender\": false, \n                    \"socket\": 5, \n                    \"start\": 16.000076\n                }\n            ], \n            \"sum\": {\n                \"bits_per_second\": 865868581.8681105, \n                \"bytes\": 108230760, \n                \"end\": 17.00005, \n                \"omitted\": false, \n                \"seconds\": 0.999974012374878, \n                \"sender\": false, \n                \"start\": 16.000076\n            }\n        }, \n        {\n            \"streams\": [\n                {\n                    \"bits_per_second\": 865312731.0620387, \n                    \"bytes\": 108165600, \n                    \"end\": 18.000064, \n                    \"omitted\": false, \n                    \"seconds\": 1.0000139474868774, \n                    \"sender\": false, \n                    \"socket\": 5, \n                    \"start\": 17.00005\n                }\n            ], \n            \"sum\": {\n                \"bits_per_second\": 865312731.0620387, \n                \"bytes\": 108165600, \n                \"end\": 18.000064, \n                \"omitted\": false, \n                \"seconds\": 1.0000139474868774, \n                \"sender\": false, \n                \"start\": 17.00005\n            }\n        }, \n        {\n            \"streams\": [\n                {\n                    \"bits_per_second\": 865309223.9124285, \n                    \"bytes\": 108165600, \n                    \"end\": 19.000082, \n                    \"omitted\": false, \n                    \"seconds\": 1.0000180006027222, \n                    \"sender\": false, \n                    \"socket\": 5, \n                    \"start\": 18.000064\n                }\n            ], \n            \"sum\": {\n                \"bits_per_second\": 865309223.9124285, \n                \"bytes\": 108165600, \n                \"end\": 19.000082, \n                \"omitted\": false, \n                \"seconds\": 1.0000180006027222, \n                \"sender\": false, \n                \"start\": 18.000064\n            }\n        }, \n        {\n            \"streams\": [\n                {\n                    \"bits_per_second\": 865864246.5548556, \n                    \"bytes\": 108230760, \n                    \"end\": 20.000061, \n                    \"omitted\": false, \n                    \"seconds\": 0.999979019165039, \n                    \"sender\": false, \n                    \"socket\": 5, \n                    \"start\": 19.000082\n                }\n            ], \n            \"sum\": {\n                \"bits_per_second\": 865864246.5548556, \n                \"bytes\": 108230760, \n                \"end\": 20.000061, \n                \"omitted\": false, \n                \"seconds\": 0.999979019165039, \n                \"sender\": false, \n                \"start\": 19.000082\n            }\n        }, \n        {\n            \"streams\": [\n                {\n                    \"bits_per_second\": 865323974.76275, \n                    \"bytes\": 108165600, \n                    \"end\": 21.000062, \n                    \"omitted\": false, \n                    \"seconds\": 1.0000009536743164, \n                    \"sender\": false, \n                    \"socket\": 5, \n                    \"start\": 20.000061\n                }\n            ], \n            \"sum\": {\n                \"bits_per_second\": 865323974.76275, \n                \"bytes\": 108165600, \n                \"end\": 21.000062, \n                \"omitted\": false, \n                \"seconds\": 1.0000009536743164, \n                \"sender\": false, \n                \"start\": 20.000061\n            }\n        }, \n        {\n            \"streams\": [\n                {\n                    \"bits_per_second\": 865847834.690789, \n                    \"bytes\": 108230760, \n                    \"end\": 22.00006, \n                    \"omitted\": false, \n                    \"seconds\": 0.9999979734420776, \n                    \"sender\": false, \n                    \"socket\": 5, \n                    \"start\": 21.000062\n                }\n            ], \n            \"sum\": {\n                \"bits_per_second\": 865847834.690789, \n                \"bytes\": 108230760, \n                \"end\": 22.00006, \n                \"omitted\": false, \n                \"seconds\": 0.9999979734420776, \n                \"sender\": false, \n                \"start\": 21.000062\n            }\n        }, \n        {\n            \"streams\": [\n                {\n                    \"bits_per_second\": 865305716.7912476, \n                    \"bytes\": 108165600, \n                    \"end\": 23.000082, \n                    \"omitted\": false, \n                    \"seconds\": 1.000022053718567, \n                    \"sender\": false, \n                    \"socket\": 5, \n                    \"start\": 22.00006\n                }\n            ], \n            \"sum\": {\n                \"bits_per_second\": 865305716.7912476, \n                \"bytes\": 108165600, \n                \"end\": 23.000082, \n                \"omitted\": false, \n                \"seconds\": 1.000022053718567, \n                \"sender\": false, \n                \"start\": 22.00006\n            }\n        }, \n        {\n            \"streams\": [\n                {\n                    \"bits_per_second\": 865879007.4419992, \n                    \"bytes\": 108230760, \n                    \"end\": 24.000044, \n                    \"omitted\": false, \n                    \"seconds\": 0.9999619722366333, \n                    \"sender\": false, \n                    \"socket\": 5, \n                    \"start\": 23.000082\n                }\n            ], \n            \"sum\": {\n                \"bits_per_second\": 865879007.4419992, \n                \"bytes\": 108230760, \n                \"end\": 24.000044, \n                \"omitted\": false, \n                \"seconds\": 0.9999619722366333, \n                \"sender\": false, \n                \"start\": 23.000082\n            }\n        }, \n        {\n            \"streams\": [\n                {\n                    \"bits_per_second\": 865309223.9124285, \n                    \"bytes\": 108165600, \n                    \"end\": 25.000062, \n                    \"omitted\": false, \n                    \"seconds\": 1.0000180006027222, \n                    \"sender\": false, \n                    \"socket\": 5, \n                    \"start\": 24.000044\n                }\n            ], \n            \"sum\": {\n                \"bits_per_second\": 865309223.9124285, \n                \"bytes\": 108165600, \n                \"end\": 25.000062, \n                \"omitted\": false, \n                \"seconds\": 1.0000180006027222, \n                \"sender\": false, \n                \"start\": 24.000044\n            }\n        }, \n        {\n            \"streams\": [\n                {\n                    \"bits_per_second\": 865312731.0620387, \n                    \"bytes\": 108165600, \n                    \"end\": 26.000076, \n                    \"omitted\": false, \n                    \"seconds\": 1.0000139474868774, \n                    \"sender\": false, \n                    \"socket\": 5, \n                    \"start\": 25.000062\n                }\n            ], \n            \"sum\": {\n                \"bits_per_second\": 865312731.0620387, \n                \"bytes\": 108165600, \n                \"end\": 26.000076, \n                \"omitted\": false, \n                \"seconds\": 1.0000139474868774, \n                \"sender\": false, \n                \"start\": 25.000062\n            }\n        }, \n        {\n            \"streams\": [\n                {\n                    \"bits_per_second\": 865853872.945791, \n                    \"bytes\": 108230760, \n                    \"end\": 27.000067, \n                    \"omitted\": false, \n                    \"seconds\": 0.999990999698639, \n                    \"sender\": false, \n                    \"socket\": 5, \n                    \"start\": 26.000076\n                }\n            ], \n            \"sum\": {\n                \"bits_per_second\": 865853872.945791, \n                \"bytes\": 108230760, \n                \"end\": 27.000067, \n                \"omitted\": false, \n                \"seconds\": 0.999990999698639, \n                \"sender\": false, \n                \"start\": 26.000076\n            }\n        }, \n        {\n            \"streams\": [\n                {\n                    \"bits_per_second\": 865312731.0620387, \n                    \"bytes\": 108165600, \n                    \"end\": 28.000081, \n                    \"omitted\": false, \n                    \"seconds\": 1.0000139474868774, \n                    \"sender\": false, \n                    \"socket\": 5, \n                    \"start\": 27.000067\n                }\n            ], \n            \"sum\": {\n                \"bits_per_second\": 865312731.0620387, \n                \"bytes\": 108165600, \n                \"end\": 28.000081, \n                \"omitted\": false, \n                \"seconds\": 1.0000139474868774, \n                \"sender\": false, \n                \"start\": 27.000067\n            }\n        }, \n        {\n            \"streams\": [\n                {\n                    \"bits_per_second\": 865862543.4079545, \n                    \"bytes\": 108230760, \n                    \"end\": 29.000062, \n                    \"omitted\": false, \n                    \"seconds\": 0.9999809861183167, \n                    \"sender\": false, \n                    \"socket\": 5, \n                    \"start\": 28.000081\n                }\n            ], \n            \"sum\": {\n                \"bits_per_second\": 865862543.4079545, \n                \"bytes\": 108230760, \n                \"end\": 29.000062, \n                \"omitted\": false, \n                \"seconds\": 0.9999809861183167, \n                \"sender\": false, \n                \"start\": 28.000081\n            }\n        }, \n        {\n            \"streams\": [\n                {\n                    \"bits_per_second\": 865305716.7912476, \n                    \"bytes\": 108165600, \n                    \"end\": 30.000084, \n                    \"omitted\": false, \n                    \"seconds\": 1.000022053718567, \n                    \"sender\": false, \n                    \"socket\": 5, \n                    \"start\": 29.000062\n                }\n            ], \n            \"sum\": {\n                \"bits_per_second\": 865305716.7912476, \n                \"bytes\": 108165600, \n                \"end\": 30.000084, \n                \"omitted\": false, \n                \"seconds\": 1.000022053718567, \n                \"sender\": false, \n                \"start\": 29.000062\n            }\n        }, \n        {\n            \"streams\": [\n                {\n                    \"bits_per_second\": 865894594.659344, \n                    \"bytes\": 108230760, \n                    \"end\": 31.000028, \n                    \"omitted\": false, \n                    \"seconds\": 0.999943971633911, \n                    \"sender\": false, \n                    \"socket\": 5, \n                    \"start\": 30.000084\n                }\n            ], \n            \"sum\": {\n                \"bits_per_second\": 865894594.659344, \n                \"bytes\": 108230760, \n                \"end\": 31.000028, \n                \"omitted\": false, \n                \"seconds\": 0.999943971633911, \n                \"sender\": false, \n                \"start\": 30.000084\n            }\n        }, \n        {\n            \"streams\": [\n                {\n                    \"bits_per_second\": 865290141.3906685, \n                    \"bytes\": 108165600, \n                    \"end\": 32.000068, \n                    \"omitted\": false, \n                    \"seconds\": 1.000040054321289, \n                    \"sender\": false, \n                    \"socket\": 5, \n                    \"start\": 31.000028\n                }\n            ], \n            \"sum\": {\n                \"bits_per_second\": 865290141.3906685, \n                \"bytes\": 108165600, \n                \"end\": 32.000068, \n                \"omitted\": false, \n                \"seconds\": 1.000040054321289, \n                \"sender\": false, \n                \"start\": 31.000028\n            }\n        }, \n        {\n            \"streams\": [\n                {\n                    \"bits_per_second\": 865313556.2778432, \n                    \"bytes\": 108165600, \n                    \"end\": 33.000081, \n                    \"omitted\": false, \n                    \"seconds\": 1.000012993812561, \n                    \"sender\": false, \n                    \"socket\": 5, \n                    \"start\": 32.000068\n                }\n            ], \n            \"sum\": {\n                \"bits_per_second\": 865313556.2778432, \n                \"bytes\": 108165600, \n                \"end\": 33.000081, \n                \"omitted\": false, \n                \"seconds\": 1.000012993812561, \n                \"sender\": false, \n                \"start\": 32.000068\n            }\n        }, \n        {\n            \"streams\": [\n                {\n                    \"bits_per_second\": 865863420.7858243, \n                    \"bytes\": 108230760, \n                    \"end\": 34.000061, \n                    \"omitted\": false, \n                    \"seconds\": 0.9999799728393555, \n                    \"sender\": false, \n                    \"socket\": 5, \n                    \"start\": 33.000081\n                }\n            ], \n            \"sum\": {\n                \"bits_per_second\": 865863420.7858243, \n                \"bytes\": 108230760, \n                \"end\": 34.000061, \n                \"omitted\": false, \n                \"seconds\": 0.9999799728393555, \n                \"sender\": false, \n                \"start\": 33.000081\n            }\n        }, \n        {\n            \"streams\": [\n                {\n                    \"bits_per_second\": 865309223.9124285, \n                    \"bytes\": 108165600, \n                    \"end\": 35.000079, \n                    \"omitted\": false, \n                    \"seconds\": 1.0000180006027222, \n                    \"sender\": false, \n                    \"socket\": 5, \n                    \"start\": 34.000061\n                }\n            ], \n            \"sum\": {\n                \"bits_per_second\": 865309223.9124285, \n                \"bytes\": 108165600, \n                \"end\": 35.000079, \n                \"omitted\": false, \n                \"seconds\": 1.0000180006027222, \n                \"sender\": false, \n                \"start\": 34.000061\n            }\n        }, \n        {\n            \"streams\": [\n                {\n                    \"bits_per_second\": 865859911.2850132, \n                    \"bytes\": 108230760, \n                    \"end\": 36.000063, \n                    \"omitted\": false, \n                    \"seconds\": 0.9999840259552002, \n                    \"sender\": false, \n                    \"socket\": 5, \n                    \"start\": 35.000079\n                }\n            ], \n            \"sum\": {\n                \"bits_per_second\": 865859911.2850132, \n                \"bytes\": 108230760, \n                \"end\": 36.000063, \n                \"omitted\": false, \n                \"seconds\": 0.9999840259552002, \n                \"sender\": false, \n                \"start\": 35.000079\n            }\n        }, \n        {\n            \"streams\": [\n                {\n                    \"bits_per_second\": 865314381.4952217, \n                    \"bytes\": 108165600, \n                    \"end\": 37.000075, \n                    \"omitted\": false, \n                    \"seconds\": 1.0000120401382446, \n                    \"sender\": false, \n                    \"socket\": 5, \n                    \"start\": 36.000063\n                }\n            ], \n            \"sum\": {\n                \"bits_per_second\": 865314381.4952217, \n                \"bytes\": 108165600, \n                \"end\": 37.000075, \n                \"omitted\": false, \n                \"seconds\": 1.0000120401382446, \n                \"sender\": false, \n                \"start\": 36.000063\n            }\n        }, \n        {\n            \"streams\": [\n                {\n                    \"bits_per_second\": 865872917.224779, \n                    \"bytes\": 108230760, \n                    \"end\": 38.000044, \n                    \"omitted\": false, \n                    \"seconds\": 0.9999690055847168, \n                    \"sender\": false, \n                    \"socket\": 5, \n                    \"start\": 37.000075\n                }\n            ], \n            \"sum\": {\n                \"bits_per_second\": 865872917.224779, \n                \"bytes\": 108230760, \n                \"end\": 38.000044, \n                \"omitted\": false, \n                \"seconds\": 0.9999690055847168, \n                \"sender\": false, \n                \"start\": 37.000075\n            }\n        }, \n        {\n            \"streams\": [\n                {\n                    \"bits_per_second\": 865295401.8937182, \n                    \"bytes\": 108165600, \n                    \"end\": 39.000078, \n                    \"omitted\": false, \n                    \"seconds\": 1.000033974647522, \n                    \"sender\": false, \n                    \"socket\": 5, \n                    \"start\": 38.000044\n                }\n            ], \n            \"sum\": {\n                \"bits_per_second\": 865295401.8937182, \n                \"bytes\": 108165600, \n                \"end\": 39.000078, \n                \"omitted\": false, \n                \"seconds\": 1.000033974647522, \n                \"sender\": false, \n                \"start\": 38.000044\n            }\n        }, \n        {\n            \"streams\": [\n                {\n                    \"bits_per_second\": 865320467.521997, \n                    \"bytes\": 108165600, \n                    \"end\": 40.000083, \n                    \"omitted\": false, \n                    \"seconds\": 1.0000050067901611, \n                    \"sender\": false, \n                    \"socket\": 5, \n                    \"start\": 39.000078\n                }\n            ], \n            \"sum\": {\n                \"bits_per_second\": 865320467.521997, \n                \"bytes\": 108165600, \n                \"end\": 40.000083, \n                \"omitted\": false, \n                \"seconds\": 1.0000050067901611, \n                \"sender\": false, \n                \"start\": 39.000078\n            }\n        }, \n        {\n            \"streams\": [\n                {\n                    \"bits_per_second\": 865864246.5548556, \n                    \"bytes\": 108230760, \n                    \"end\": 41.000062, \n                    \"omitted\": false, \n                    \"seconds\": 0.999979019165039, \n                    \"sender\": false, \n                    \"socket\": 5, \n                    \"start\": 40.000083\n                }\n            ], \n            \"sum\": {\n                \"bits_per_second\": 865864246.5548556, \n                \"bytes\": 108230760, \n                \"end\": 41.000062, \n                \"omitted\": false, \n                \"seconds\": 0.999979019165039, \n                \"sender\": false, \n                \"start\": 40.000083\n            }\n        }, \n        {\n            \"streams\": [\n                {\n                    \"bits_per_second\": 865310977.48368, \n                    \"bytes\": 108165600, \n                    \"end\": 42.000078, \n                    \"omitted\": false, \n                    \"seconds\": 1.0000159740448, \n                    \"sender\": false, \n                    \"socket\": 5, \n                    \"start\": 41.000062\n                }\n            ], \n            \"sum\": {\n                \"bits_per_second\": 865310977.48368, \n                \"bytes\": 108165600, \n                \"end\": 42.000078, \n                \"omitted\": false, \n                \"seconds\": 1.0000159740448, \n                \"sender\": false, \n                \"start\": 41.000062\n            }\n        }, \n        {\n            \"streams\": [\n                {\n                    \"bits_per_second\": 865860788.657549, \n                    \"bytes\": 108230760, \n                    \"end\": 43.000061, \n                    \"omitted\": false, \n                    \"seconds\": 0.999983012676239, \n                    \"sender\": false, \n                    \"socket\": 5, \n                    \"start\": 42.000078\n                }\n            ], \n            \"sum\": {\n                \"bits_per_second\": 865860788.657549, \n                \"bytes\": 108230760, \n                \"end\": 43.000061, \n                \"omitted\": false, \n                \"seconds\": 0.999983012676239, \n                \"sender\": false, \n                \"start\": 42.000078\n            }\n        }, \n        {\n            \"streams\": [\n                {\n                    \"bits_per_second\": 865322221.1388197, \n                    \"bytes\": 108165600, \n                    \"end\": 44.000064, \n                    \"omitted\": false, \n                    \"seconds\": 1.0000029802322388, \n                    \"sender\": false, \n                    \"socket\": 5, \n                    \"start\": 43.000061\n                }\n            ], \n            \"sum\": {\n                \"bits_per_second\": 865322221.1388197, \n                \"bytes\": 108165600, \n                \"end\": 44.000064, \n                \"omitted\": false, \n                \"seconds\": 1.0000029802322388, \n                \"sender\": false, \n                \"start\": 43.000061\n            }\n        }, \n        {\n            \"streams\": [\n                {\n                    \"bits_per_second\": 865877252.6248614, \n                    \"bytes\": 108230760, \n                    \"end\": 45.000028, \n                    \"omitted\": false, \n                    \"seconds\": 0.9999639987945557, \n                    \"sender\": false, \n                    \"socket\": 5, \n                    \"start\": 44.000064\n                }\n            ], \n            \"sum\": {\n                \"bits_per_second\": 865877252.6248614, \n                \"bytes\": 108230760, \n                \"end\": 45.000028, \n                \"omitted\": false, \n                \"seconds\": 0.9999639987945557, \n                \"sender\": false, \n                \"start\": 44.000064\n            }\n        }, \n        {\n            \"streams\": [\n                {\n                    \"bits_per_second\": 865288491.0499513, \n                    \"bytes\": 108165600, \n                    \"end\": 46.00007, \n                    \"omitted\": false, \n                    \"seconds\": 1.0000419616699219, \n                    \"sender\": false, \n                    \"socket\": 5, \n                    \"start\": 45.000028\n                }\n            ], \n            \"sum\": {\n                \"bits_per_second\": 865288491.0499513, \n                \"bytes\": 108165600, \n                \"end\": 46.00007, \n                \"omitted\": false, \n                \"seconds\": 1.0000419616699219, \n                \"sender\": false, \n                \"start\": 45.000028\n            }\n        }, \n        {\n            \"streams\": [\n                {\n                    \"bits_per_second\": 865313556.2778432, \n                    \"bytes\": 108165600, \n                    \"end\": 47.000083, \n                    \"omitted\": false, \n                    \"seconds\": 1.000012993812561, \n                    \"sender\": false, \n                    \"socket\": 5, \n                    \"start\": 46.00007\n                }\n            ], \n            \"sum\": {\n                \"bits_per_second\": 865313556.2778432, \n                \"bytes\": 108165600, \n                \"end\": 47.000083, \n                \"omitted\": false, \n                \"seconds\": 1.000012993812561, \n                \"sender\": false, \n                \"start\": 46.00007\n            }\n        }, \n        {\n            \"streams\": [\n                {\n                    \"bits_per_second\": 865865123.936177, \n                    \"bytes\": 108230760, \n                    \"end\": 48.000061, \n                    \"omitted\": false, \n                    \"seconds\": 0.999978005886078, \n                    \"sender\": false, \n                    \"socket\": 5, \n                    \"start\": 47.000083\n                }\n            ], \n            \"sum\": {\n                \"bits_per_second\": 865865123.936177, \n                \"bytes\": 108230760, \n                \"end\": 48.000061, \n                \"omitted\": false, \n                \"seconds\": 0.999978005886078, \n                \"sender\": false, \n                \"start\": 47.000083\n            }\n        }, \n        {\n            \"streams\": [\n                {\n                    \"bits_per_second\": 865311802.6961398, \n                    \"bytes\": 108165600, \n                    \"end\": 49.000076, \n                    \"omitted\": false, \n                    \"seconds\": 1.0000150203704834, \n                    \"sender\": false, \n                    \"socket\": 5, \n                    \"start\": 48.000061\n                }\n            ], \n            \"sum\": {\n                \"bits_per_second\": 865311802.6961398, \n                \"bytes\": 108165600, \n                \"end\": 49.000076, \n                \"omitted\": false, \n                \"seconds\": 1.0000150203704834, \n                \"sender\": false, \n                \"start\": 48.000061\n            }\n        }, \n        {\n            \"streams\": [\n                {\n                    \"bits_per_second\": 865859085.524251, \n                    \"bytes\": 108230760, \n                    \"end\": 50.000061, \n                    \"omitted\": false, \n                    \"seconds\": 0.9999849796295166, \n                    \"sender\": false, \n                    \"socket\": 5, \n                    \"start\": 49.000076\n                }\n            ], \n            \"sum\": {\n                \"bits_per_second\": 865859085.524251, \n                \"bytes\": 108230760, \n                \"end\": 50.000061, \n                \"omitted\": false, \n                \"seconds\": 0.9999849796295166, \n                \"sender\": false, \n                \"start\": 49.000076\n            }\n        }, \n        {\n            \"streams\": [\n                {\n                    \"bits_per_second\": 865321292.7525575, \n                    \"bytes\": 108165600, \n                    \"end\": 51.000065, \n                    \"omitted\": false, \n                    \"seconds\": 1.0000040531158447, \n                    \"sender\": false, \n                    \"socket\": 5, \n                    \"start\": 50.000061\n                }\n            ], \n            \"sum\": {\n                \"bits_per_second\": 865321292.7525575, \n                \"bytes\": 108165600, \n                \"end\": 51.000065, \n                \"omitted\": false, \n                \"seconds\": 1.0000040531158447, \n                \"sender\": false, \n                \"start\": 50.000061\n            }\n        }, \n        {\n            \"streams\": [\n                {\n                    \"bits_per_second\": 865874672.0243443, \n                    \"bytes\": 108230760, \n                    \"end\": 52.000032, \n                    \"omitted\": false, \n                    \"seconds\": 0.9999669790267944, \n                    \"sender\": false, \n                    \"socket\": 5, \n                    \"start\": 51.000065\n                }\n            ], \n            \"sum\": {\n                \"bits_per_second\": 865874672.0243443, \n                \"bytes\": 108230760, \n                \"end\": 52.000032, \n                \"omitted\": false, \n                \"seconds\": 0.9999669790267944, \n                \"sender\": false, \n                \"start\": 51.000065\n            }\n        }, \n        {\n            \"streams\": [\n                {\n                    \"bits_per_second\": 865298805.7827166, \n                    \"bytes\": 108165600, \n                    \"end\": 53.000062, \n                    \"omitted\": false, \n                    \"seconds\": 1.0000300407409668, \n                    \"sender\": false, \n                    \"socket\": 5, \n                    \"start\": 52.000032\n                }\n            ], \n            \"sum\": {\n                \"bits_per_second\": 865298805.7827166, \n                \"bytes\": 108165600, \n                \"end\": 53.000062, \n                \"omitted\": false, \n                \"seconds\": 1.0000300407409668, \n                \"sender\": false, \n                \"start\": 52.000032\n            }\n        }, \n        {\n            \"streams\": [\n                {\n                    \"bits_per_second\": 865306645.1440877, \n                    \"bytes\": 108165600, \n                    \"end\": 54.000083, \n                    \"omitted\": false, \n                    \"seconds\": 1.000020980834961, \n                    \"sender\": false, \n                    \"socket\": 5, \n                    \"start\": 53.000062\n                }\n            ], \n            \"sum\": {\n                \"bits_per_second\": 865306645.1440877, \n                \"bytes\": 108165600, \n                \"end\": 54.000083, \n                \"omitted\": false, \n                \"seconds\": 1.000020980834961, \n                \"sender\": false, \n                \"start\": 53.000062\n            }\n        }, \n        {\n            \"streams\": [\n                {\n                    \"bits_per_second\": 865865123.936177, \n                    \"bytes\": 108230760, \n                    \"end\": 55.000061, \n                    \"omitted\": false, \n                    \"seconds\": 0.999978005886078, \n                    \"sender\": false, \n                    \"socket\": 5, \n                    \"start\": 54.000083\n                }\n            ], \n            \"sum\": {\n                \"bits_per_second\": 865865123.936177, \n                \"bytes\": 108230760, \n                \"end\": 55.000061, \n                \"omitted\": false, \n                \"seconds\": 0.999978005886078, \n                \"sender\": false, \n                \"start\": 54.000083\n            }\n        }, \n        {\n            \"streams\": [\n                {\n                    \"bits_per_second\": 865306645.1440877, \n                    \"bytes\": 108165600, \n                    \"end\": 56.000082, \n                    \"omitted\": false, \n                    \"seconds\": 1.000020980834961, \n                    \"sender\": false, \n                    \"socket\": 5, \n                    \"start\": 55.000061\n                }\n            ], \n            \"sum\": {\n                \"bits_per_second\": 865306645.1440877, \n                \"bytes\": 108165600, \n                \"end\": 56.000082, \n                \"omitted\": false, \n                \"seconds\": 1.000020980834961, \n                \"sender\": false, \n                \"start\": 55.000061\n            }\n        }, \n        {\n            \"streams\": [\n                {\n                    \"bits_per_second\": 865864246.5548556, \n                    \"bytes\": 108230760, \n                    \"end\": 57.000061, \n                    \"omitted\": false, \n                    \"seconds\": 0.999979019165039, \n                    \"sender\": false, \n                    \"socket\": 5, \n                    \"start\": 56.000082\n                }\n            ], \n            \"sum\": {\n                \"bits_per_second\": 865864246.5548556, \n                \"bytes\": 108230760, \n                \"end\": 57.000061, \n                \"omitted\": false, \n                \"seconds\": 0.999979019165039, \n                \"sender\": false, \n                \"start\": 56.000082\n            }\n        }, \n        {\n            \"streams\": [\n                {\n                    \"bits_per_second\": 865303138.0438102, \n                    \"bytes\": 108165600, \n                    \"end\": 58.000086, \n                    \"omitted\": false, \n                    \"seconds\": 1.0000250339508057, \n                    \"sender\": false, \n                    \"socket\": 5, \n                    \"start\": 57.000061\n                }\n            ], \n            \"sum\": {\n                \"bits_per_second\": 865303138.0438102, \n                \"bytes\": 108165600, \n                \"end\": 58.000086, \n                \"omitted\": false, \n                \"seconds\": 1.0000250339508057, \n                \"sender\": false, \n                \"start\": 57.000061\n            }\n        }, \n        {\n            \"streams\": [\n                {\n                    \"bits_per_second\": 865889381.653338, \n                    \"bytes\": 108230760, \n                    \"end\": 59.000036, \n                    \"omitted\": false, \n                    \"seconds\": 0.9999499917030334, \n                    \"sender\": false, \n                    \"socket\": 5, \n                    \"start\": 58.000086\n                }\n            ], \n            \"sum\": {\n                \"bits_per_second\": 865889381.653338, \n                \"bytes\": 108230760, \n                \"end\": 59.000036, \n                \"omitted\": false, \n                \"seconds\": 0.9999499917030334, \n                \"sender\": false, \n                \"start\": 58.000086\n            }\n        }, \n        {\n            \"streams\": [\n                {\n                    \"bits_per_second\": 865286737.5698372, \n                    \"bytes\": 108165600, \n                    \"end\": 60.00008, \n                    \"omitted\": false, \n                    \"seconds\": 1.0000439882278442, \n                    \"sender\": false, \n                    \"socket\": 5, \n                    \"start\": 59.000036\n                }\n            ], \n            \"sum\": {\n                \"bits_per_second\": 865286737.5698372, \n                \"bytes\": 108165600, \n                \"end\": 60.00008, \n                \"omitted\": false, \n                \"seconds\": 1.0000439882278442, \n                \"sender\": false, \n                \"start\": 59.000036\n            }\n        }, \n        {\n            \"streams\": [\n                {\n                    \"bits_per_second\": 861261147.5663828, \n                    \"bytes\": 8275320, \n                    \"end\": 60.076947, \n                    \"omitted\": false, \n                    \"seconds\": 0.0768669992685318, \n                    \"sender\": false, \n                    \"socket\": 5, \n                    \"start\": 60.00008\n                }\n            ], \n            \"sum\": {\n                \"bits_per_second\": 861261147.5663828, \n                \"bytes\": 8275320, \n                \"end\": 60.076947, \n                \"omitted\": false, \n                \"seconds\": 0.0768669992685318, \n                \"sender\": false, \n                \"start\": 60.00008\n            }\n        }\n    ], \n    \"start\": {\n        \"accepted_connection\": {\n            \"host\": \"10.0.0.1\", \n            \"port\": 53113\n        }, \n        \"connected\": [\n            {\n                \"local_host\": \"10.0.0.2\", \n                \"local_port\": 5201, \n                \"remote_host\": \"10.0.0.1\", \n                \"remote_port\": 56875, \n                \"socket\": 5\n            }\n        ], \n        \"cookie\": \"7z3nrbbxhssi64gdqpllh6jvm53y5fkymfpx\", \n        \"fq_rate\": 0, \n        \"rcvbuf_actual\": 87380, \n        \"sndbuf_actual\": 87380, \n        \"sock_bufsize\": 0, \n        \"system_info\": \"REDACTED\", \n        \"target_bitrate\": 0, \n        \"tcp_mss_default\": 0, \n        \"test_start\": {\n            \"bidir\": 0, \n            \"blksize\": 131072, \n            \"blocks\": 0, \n            \"bytes\": 0, \n            \"duration\": 60, \n            \"fqrate\": 0, \n            \"num_streams\": 1, \n            \"omit\": 0, \n            \"protocol\": \"TCP\", \n            \"reverse\": 0, \n            \"target_bitrate\": 0, \n            \"tos\": 0\n        }, \n        \"timestamp\": {\n            \"time\": \"Wed, 17 Apr 2024 01:20:34 GMT\", \n            \"timesecs\": 1713316834\n        }, \n        \"version\": \"iperf 3.14\"\n    }\n}\n","summary":{"streams":[{"end":60.000166,"rtt":77087,"start":0,"stream-id":5,"retransmits":0,"throughput-bits":867030143.0832708,"throughput-bytes":6502744064}],"summary":{"end":60.000166,"start":0,"retransmits":0,"throughput-bits":867030143.0832708,"throughput-bytes":6502744064,"receiver-throughput-bits":865534406.0676053}},"intervals":[{"streams":[{"end":1.000063,"rtt":77081,"start":0,"omitted":false,"stream-id":5,"retransmits":0,"tcp-window-size":16708472,"throughput-bits":956241123.788397,"throughput-bytes":119537664}],"summary":{"end":1.000063,"start":0,"omitted":false,"retransmits":0,"throughput-bits":956241123.788397,"throughput-bytes":119537664}},{"streams":[{"end":2.000077,"rtt":77087,"start":1.000063,"omitted":false,"stream-id":5,"retransmits":0,"tcp-window-size":16708472,"throughput-bits":870305941.4193027,"throughput-bytes":108789760}],"summary":{"end":2.000077,"start":1.000063,"omitted":false,"retransmits":0,"throughput-bits":870305941.4193027,"throughput-bytes":108789760}},{"streams":[{"end":3.000064,"rtt":77089,"start":2.000077,"omitted":false,"stream-id":5,"retransmits":0,"tcp-window-size":16708472,"throughput-bits":859843492.6451752,"throughput-bytes":107479040}],"summary":{"end":3.000064,"start":2.000077,"omitted":false,"retransmits":0,"throughput-bits":859843492.6451752,"throughput-bytes":107479040}},{"streams":[{"end":4.000083,"rtt":77087,"start":3.000064,"omitted":false,"stream-id":5,"retransmits":0,"tcp-window-size":16708472,"throughput-bits":870301584.0626686,"throughput-bytes":108789760}],"summary":{"end":4.000083,"start":3.000064,"omitted":false,"retransmits":0,"throughput-bits":870301584.0626686,"throughput-bytes":108789760}},{"streams":[{"end":5.000064,"rtt":77089,"start":4.000083,"omitted":false,"stream-id":5,"retransmits":0,"tcp-window-size":16708472,"throughput-bits":859848669.060859,"throughput-bytes":107479040}],"summary":{"end":5.000064,"start":4.000083,"omitted":false,"retransmits":0,"throughput-bits":859848669.060859,"throughput-bytes":107479040}},{"streams":[{"end":6.000062,"rtt":77082,"start":5.000064,"omitted":false,"stream-id":5,"retransmits":0,"tcp-window-size":16708472,"throughput-bits":870319843.7535744,"throughput-bytes":108789760}],"summary":{"end":6.000062,"start":5.000064,"omitted":false,"retransmits":0,"throughput-bits":870319843.7535744,"throughput-bytes":108789760}},{"streams":[{"end":7.000064,"rtt":77087,"start":6.000062,"omitted":false,"stream-id":5,"retransmits":0,"tcp-window-size":16708472,"throughput-bits":859830577.5035312,"throughput-bytes":107479040}],"summary":{"end":7.000064,"start":6.000062,"omitted":false,"retransmits":0,"throughput-bits":859830577.5035312,"throughput-bytes":107479040}},{"streams":[{"end":8.000064,"rtt":77083,"start":7.000064,"omitted":false,"stream-id":5,"retransmits":0,"tcp-window-size":16708472,"throughput-bits":870318080,"throughput-bytes":108789760}],"summary":{"end":8.000064,"start":7.000064,"omitted":false,"retransmits":0,"throughput-bits":870318080,"throughput-bytes":108789760}},{"streams":[{"end":9.000063,"rtt":77090,"start":8.000064,"omitted":false,"stream-id":5,"retransmits":0,"tcp-window-size":16708472,"throughput-bits":870318961.8758936,"throughput-bytes":108789760}],"summary":{"end":9.000063,"start":8.000064,"omitted":false,"retransmits":0,"throughput-bits":870318961.8758936,"throughput-bytes":108789760}},{"streams":[{"end":10.000064,"rtt":77088,"start":9.000063,"omitted":false,"stream-id":5,"retransmits":0,"tcp-window-size":16708472,"throughput-bits":859831500.000782,"throughput-bytes":107479040}],"summary":{"end":10.000064,"start":9.000063,"omitted":false,"retransmits":0,"throughput-bits":859831500.000782,"throughput-bytes":107479040}},{"streams":[{"end":11.000084,"rtt":77087,"start":10.000064,"omitted":false,"stream-id":5,"retransmits":0,"tcp-window-size":16708472,"throughput-bits":870300650.3490664,"throughput-bytes":108789760}],"summary":{"end":11.000084,"start":10.000064,"omitted":false,"retransmits":0,"throughput-bits":870300650.3490664,"throughput-bytes":108789760}},{"streams":[{"end":12.000066,"rtt":77087,"start":11.000084,"omitted":false,"stream-id":5,"retransmits":0,"tcp-window-size":16708472,"throughput-bits":859847797.7786094,"throughput-bytes":107479040}],"summary":{"end":12.000066,"start":11.000084,"omitted":false,"retransmits":0,"throughput-bits":859847797.7786094,"throughput-bytes":107479040}},{"streams":[{"end":13.000062,"rtt":77085,"start":12.000066,"omitted":false,"stream-id":5,"retransmits":0,"tcp-window-size":16708472,"throughput-bits":870321555.63888,"throughput-bytes":108789760}],"summary":{"end":13.000062,"start":12.000066,"omitted":false,"retransmits":0,"throughput-bits":870321555.63888,"throughput-bytes":108789760}},{"streams":[{"end":14.000084,"rtt":77087,"start":13.000062,"omitted":false,"stream-id":5,"retransmits":0,"tcp-window-size":16708472,"throughput-bits":859813357.9181844,"throughput-bytes":107479040}],"summary":{"end":14.000084,"start":13.000062,"omitted":false,"retransmits":0,"throughput-bits":859813357.9181844,"throughput-bytes":107479040}},{"streams":[{"end":15.000064,"rtt":77092,"start":14.000084,"omitted":false,"stream-id":5,"retransmits":0,"tcp-window-size":16708472,"throughput-bits":870335510.3490804,"throughput-bytes":108789760}],"summary":{"end":15.000064,"start":14.000084,"omitted":false,"retransmits":0,"throughput-bits":870335510.3490804,"throughput-bytes":108789760}},{"streams":[{"end":16.000082,"rtt":77087,"start":15.000064,"omitted":false,"stream-id":5,"retransmits":0,"tcp-window-size":16708472,"throughput-bits":859816842.7785993,"throughput-bytes":107479040}],"summary":{"end":16.000082,"start":15.000064,"omitted":false,"retransmits":0,"throughput-bits":859816842.7785993,"throughput-bytes":107479040}},{"streams":[{"end":17.000064,"rtt":77084,"start":16.000082,"omitted":false,"stream-id":5,"retransmits":0,"tcp-window-size":16708472,"throughput-bits":870333746.532007,"throughput-bytes":108789760}],"summary":{"end":17.000064,"start":16.000082,"omitted":false,"retransmits":0,"throughput-bits":870333746.532007,"throughput-bytes":108789760}},{"streams":[{"end":18.000084,"rtt":77091,"start":17.000064,"omitted":false,"stream-id":5,"retransmits":0,"tcp-window-size":16708472,"throughput-bits":859815100.3448608,"throughput-bytes":107479040}],"summary":{"end":18.000084,"start":17.000064,"omitted":false,"retransmits":0,"throughput-bits":859815100.3448608,"throughput-bytes":107479040}},{"streams":[{"end":19.000065,"rtt":77088,"start":18.000084,"omitted":false,"stream-id":5,"retransmits":0,"tcp-window-size":16708472,"throughput-bits":870334628.43965,"throughput-bytes":108789760}],"summary":{"end":19.000065,"start":18.000084,"omitted":false,"retransmits":0,"throughput-bits":870334628.43965,"throughput-bytes":108789760}},{"streams":[{"end":20.000103,"rtt":77086,"start":19.000065,"omitted":false,"stream-id":5,"retransmits":0,"tcp-window-size":16708472,"throughput-bits":870284985.0085285,"throughput-bytes":108789760}],"summary":{"end":20.000103,"start":19.000065,"omitted":false,"retransmits":0,"throughput-bits":870284985.0085285,"throughput-bytes":108789760}},{"streams":[{"end":21.000104,"rtt":77085,"start":20.000103,"omitted":false,"stream-id":5,"retransmits":0,"tcp-window-size":16708472,"throughput-bits":859831500.000782,"throughput-bytes":107479040}],"summary":{"end":21.000104,"start":20.000103,"omitted":false,"retransmits":0,"throughput-bits":859831500.000782,"throughput-bytes":107479040}},{"streams":[{"end":22.000063,"rtt":77085,"start":21.000104,"omitted":false,"stream-id":5,"retransmits":0,"tcp-window-size":16708472,"throughput-bits":870353771.4636353,"throughput-bytes":108789760}],"summary":{"end":22.000063,"start":21.000104,"omitted":false,"retransmits":0,"throughput-bits":870353771.4636353,"throughput-bytes":108789760}},{"streams":[{"end":23.000063,"rtt":77089,"start":22.000063,"omitted":false,"stream-id":5,"retransmits":0,"tcp-window-size":16708472,"throughput-bits":859832320,"throughput-bytes":107479040}],"summary":{"end":23.000063,"start":22.000063,"omitted":false,"retransmits":0,"throughput-bits":859832320,"throughput-bytes":107479040}},{"streams":[{"end":24.000063,"rtt":77086,"start":23.000063,"omitted":false,"stream-id":5,"retransmits":0,"tcp-window-size":16708472,"throughput-bits":870318080,"throughput-bytes":108789760}],"summary":{"end":24.000063,"start":23.000063,"omitted":false,"retransmits":0,"throughput-bits":870318080,"throughput-bytes":108789760}},{"streams":[{"end":25.000084,"rtt":77091,"start":24.000063,"omitted":false,"stream-id":5,"retransmits":0,"tcp-window-size":16708472,"throughput-bits":859814280.3784863,"throughput-bytes":107479040}],"summary":{"end":25.000084,"start":24.000063,"omitted":false,"retransmits":0,"throughput-bits":859814280.3784863,"throughput-bytes":107479040}},{"streams":[{"end":26.000071,"rtt":77089,"start":25.000084,"omitted":false,"stream-id":5,"retransmits":0,"tcp-window-size":16708472,"throughput-bits":870329388.8969457,"throughput-bytes":108789760}],"summary":{"end":26.000071,"start":25.000084,"omitted":false,"retransmits":0,"throughput-bits":870329388.8969457,"throughput-bytes":108789760}},{"streams":[{"end":27.000087,"rtt":77083,"start":26.000071,"omitted":false,"stream-id":5,"retransmits":0,"tcp-window-size":16708472,"throughput-bits":859818585.2194,"throughput-bytes":107479040}],"summary":{"end":27.000087,"start":26.000071,"omitted":false,"retransmits":0,"throughput-bits":859818585.2194,"throughput-bytes":107479040}},{"streams":[{"end":28.000085,"rtt":77090,"start":27.000087,"omitted":false,"stream-id":5,"retransmits":0,"tcp-window-size":16708472,"throughput-bits":870319843.7535744,"throughput-bytes":108789760}],"summary":{"end":28.000085,"start":27.000087,"omitted":false,"retransmits":0,"throughput-bits":870319843.7535744,"throughput-bytes":108789760}},{"streams":[{"end":29.000064,"rtt":77092,"start":28.000085,"omitted":false,"stream-id":5,"retransmits":0,"tcp-window-size":16708472,"throughput-bits":859850360.3785022,"throughput-bytes":107479040}],"summary":{"end":29.000064,"start":28.000085,"omitted":false,"retransmits":0,"throughput-bits":859850360.3785022,"throughput-bytes":107479040}},{"streams":[{"end":30.000063,"rtt":77087,"start":29.000064,"omitted":false,"stream-id":5,"retransmits":0,"tcp-window-size":16708472,"throughput-bits":870318961.8758936,"throughput-bytes":108789760}],"summary":{"end":30.000063,"start":29.000064,"omitted":false,"retransmits":0,"throughput-bits":870318961.8758936,"throughput-bytes":108789760}},{"streams":[{"end":31.000217,"rtt":77088,"start":30.000063,"omitted":false,"stream-id":5,"retransmits":0,"tcp-window-size":16708472,"throughput-bits":870184055.6422174,"throughput-bytes":108789760}],"summary":{"end":31.000217,"start":30.000063,"omitted":false,"retransmits":0,"throughput-bits":870184055.6422174,"throughput-bytes":108789760}},{"streams":[{"end":32.000079,"rtt":77087,"start":31.000217,"omitted":false,"stream-id":5,"retransmits":0,"tcp-window-size":16708472,"throughput-bits":859950980.1232878,"throughput-bytes":107479040}],"summary":{"end":32.000079,"start":31.000217,"omitted":false,"retransmits":0,"throughput-bits":859950980.1232878,"throughput-bytes":107479040}},{"streams":[{"end":33.000063,"rtt":77091,"start":32.000079,"omitted":false,"stream-id":5,"retransmits":0,"tcp-window-size":16708472,"throughput-bits":870331982.7220827,"throughput-bytes":108789760}],"summary":{"end":33.000063,"start":32.000079,"omitted":false,"retransmits":0,"throughput-bits":870331982.7220827,"throughput-bytes":108789760}},{"streams":[{"end":34.000064,"rtt":77093,"start":33.000063,"omitted":false,"stream-id":5,"retransmits":0,"tcp-window-size":16708472,"throughput-bits":859831500.000782,"throughput-bytes":107479040}],"summary":{"end":34.000064,"start":33.000063,"omitted":false,"retransmits":0,"throughput-bits":859831500.000782,"throughput-bytes":107479040}},{"streams":[{"end":35.000065,"rtt":77087,"start":34.000064,"omitted":false,"stream-id":5,"retransmits":0,"tcp-window-size":16708472,"throughput-bits":870317250.0007915,"throughput-bytes":108789760}],"summary":{"end":35.000065,"start":34.000064,"omitted":false,"retransmits":0,"throughput-bits":870317250.0007915,"throughput-bytes":108789760}},{"streams":[{"end":36.000161,"rtt":77086,"start":35.000065,"omitted":false,"stream-id":5,"retransmits":0,"tcp-window-size":16708472,"throughput-bits":859749815.4174267,"throughput-bytes":107479040}],"summary":{"end":36.000161,"start":35.000065,"omitted":false,"retransmits":0,"throughput-bits":859749815.4174267,"throughput-bytes":107479040}},{"streams":[{"end":37.000081,"rtt":77092,"start":36.000161,"omitted":false,"stream-id":5,"retransmits":0,"tcp-window-size":16708472,"throughput-bits":870387701.81901,"throughput-bytes":108789760}],"summary":{"end":37.000081,"start":36.000161,"omitted":false,"retransmits":0,"throughput-bits":870387701.81901,"throughput-bytes":108789760}},{"streams":[{"end":38.000063,"rtt":77086,"start":37.000081,"omitted":false,"stream-id":5,"retransmits":0,"tcp-window-size":16708472,"throughput-bits":859847797.7786094,"throughput-bytes":107479040}],"summary":{"end":38.000063,"start":37.000081,"omitted":false,"retransmits":0,"throughput-bits":859847797.7786094,"throughput-bytes":107479040}},{"streams":[{"end":39.000064,"rtt":77085,"start":38.000063,"omitted":false,"stream-id":5,"retransmits":0,"tcp-window-size":16708472,"throughput-bits":870317250.0007915,"throughput-bytes":108789760}],"summary":{"end":39.000064,"start":38.000063,"omitted":false,"retransmits":0,"throughput-bits":870317250.0007915,"throughput-bytes":108789760}},{"streams":[{"end":40.000066,"rtt":77087,"start":39.000064,"omitted":false,"stream-id":5,"retransmits":0,"tcp-window-size":16708472,"throughput-bits":859830577.5035312,"throughput-bytes":107479040}],"summary":{"end":40.000066,"start":39.000064,"omitted":false,"retransmits":0,"throughput-bits":859830577.5035312,"throughput-bytes":107479040}},{"streams":[{"end":41.000063,"rtt":77088,"start":40.000066,"omitted":false,"stream-id":5,"retransmits":0,"tcp-window-size":16708472,"throughput-bits":870320673.75773,"throughput-bytes":108789760}],"summary":{"end":41.000063,"start":40.000066,"omitted":false,"retransmits":0,"throughput-bits":870320673.75773,"throughput-bytes":108789760}},{"streams":[{"end":42.000063,"rtt":77089,"start":41.000063,"omitted":false,"stream-id":5,"retransmits":0,"tcp-window-size":16708472,"throughput-bits":870318080,"throughput-bytes":108789760}],"summary":{"end":42.000063,"start":41.000063,"omitted":false,"retransmits":0,"throughput-bits":870318080,"throughput-bytes":108789760}},{"streams":[{"end":43.000152,"rtt":77087,"start":42.000063,"omitted":false,"stream-id":5,"retransmits":0,"tcp-window-size":16708472,"throughput-bits":859755759.3176782,"throughput-bytes":107479040}],"summary":{"end":43.000152,"start":42.000063,"omitted":false,"retransmits":0,"throughput-bits":859755759.3176782,"throughput-bytes":107479040}},{"streams":[{"end":44.000074,"rtt":77087,"start":43.000152,"omitted":false,"stream-id":5,"retransmits":0,"tcp-window-size":16708472,"throughput-bits":870385989.673481,"throughput-bytes":108789760}],"summary":{"end":44.000074,"start":43.000152,"omitted":false,"retransmits":0,"throughput-bits":870385989.673481,"throughput-bytes":108789760}},{"streams":[{"end":45.000064,"rtt":77091,"start":44.000074,"omitted":false,"stream-id":5,"retransmits":0,"tcp-window-size":16708472,"throughput-bits":859840930.0862178,"throughput-bytes":107479040}],"summary":{"end":45.000064,"start":44.000074,"omitted":false,"retransmits":0,"throughput-bits":859840930.0862178,"throughput-bytes":107479040}},{"streams":[{"end":46.00008,"rtt":77088,"start":45.000064,"omitted":false,"stream-id":5,"retransmits":0,"tcp-window-size":16708472,"throughput-bits":870304177.7220756,"throughput-bytes":108789760}],"summary":{"end":46.00008,"start":45.000064,"omitted":false,"retransmits":0,"throughput-bits":870304177.7220756,"throughput-bytes":108789760}},{"streams":[{"end":47.000063,"rtt":77090,"start":46.00008,"omitted":false,"stream-id":5,"retransmits":0,"tcp-window-size":16708472,"throughput-bits":859846926.4981253,"throughput-bytes":107479040}],"summary":{"end":47.000063,"start":46.00008,"omitted":false,"retransmits":0,"throughput-bits":859846926.4981253,"throughput-bytes":107479040}},{"streams":[{"end":48.000064,"rtt":77091,"start":47.000063,"omitted":false,"stream-id":5,"retransmits":0,"tcp-window-size":16708472,"throughput-bits":870317250.0007915,"throughput-bytes":108789760}],"summary":{"end":48.000064,"start":47.000063,"omitted":false,"retransmits":0,"throughput-bits":870317250.0007915,"throughput-bytes":108789760}},{"streams":[{"end":49.000113,"rtt":77088,"start":48.000064,"omitted":false,"stream-id":5,"retransmits":0,"tcp-window-size":16708472,"throughput-bits":859790194.5639365,"throughput-bytes":107479040}],"summary":{"end":49.000113,"start":48.000064,"omitted":false,"retransmits":0,"throughput-bits":859790194.5639365,"throughput-bytes":107479040}},{"streams":[{"end":50.000149,"rtt":77085,"start":49.000113,"omitted":false,"stream-id":5,"retransmits":0,"tcp-window-size":16708472,"throughput-bits":870286748.627967,"throughput-bytes":108789760}],"summary":{"end":50.000149,"start":49.000113,"omitted":false,"retransmits":0,"throughput-bits":870286748.627967,"throughput-bytes":108789760}},{"streams":[{"end":51.000175,"rtt":77086,"start":50.000149,"omitted":false,"stream-id":5,"retransmits":0,"tcp-window-size":16708472,"throughput-bits":859809975.5806783,"throughput-bytes":107479040}],"summary":{"end":51.000175,"start":50.000149,"omitted":false,"retransmits":0,"throughput-bits":859809975.5806783,"throughput-bytes":107479040}},{"streams":[{"end":52.000074,"rtt":77084,"start":51.000175,"omitted":false,"stream-id":5,"retransmits":0,"tcp-window-size":16708472,"throughput-bits":870405965.1237845,"throughput-bytes":108789760}],"summary":{"end":52.000074,"start":51.000175,"omitted":false,"retransmits":0,"throughput-bits":870405965.1237845,"throughput-bytes":108789760}},{"streams":[{"end":53.000062,"rtt":77085,"start":52.000074,"omitted":false,"stream-id":5,"retransmits":0,"tcp-window-size":16708472,"throughput-bits":870328506.999921,"throughput-bytes":108789760}],"summary":{"end":53.000062,"start":52.000074,"omitted":false,"retransmits":0,"throughput-bits":870328506.999921,"throughput-bytes":108789760}},{"streams":[{"end":54.000159,"rtt":77085,"start":53.000062,"omitted":false,"stream-id":5,"retransmits":0,"tcp-window-size":16708472,"throughput-bits":859748893.0954432,"throughput-bytes":107479040}],"summary":{"end":54.000159,"start":53.000062,"omitted":false,"retransmits":0,"throughput-bits":859748893.0954432,"throughput-bytes":107479040}},{"streams":[{"end":55.000148,"rtt":77091,"start":54.000159,"omitted":false,"stream-id":5,"retransmits":0,"tcp-window-size":16708472,"throughput-bits":870327676.9808246,"throughput-bytes":108789760}],"summary":{"end":55.000148,"start":54.000159,"omitted":false,"retransmits":0,"throughput-bits":870327676.9808246,"throughput-bytes":108789760}},{"streams":[{"end":56.000156,"rtt":77085,"start":55.000148,"omitted":false,"stream-id":5,"retransmits":0,"tcp-window-size":16708472,"throughput-bits":859825452.5548505,"throughput-bytes":107479040}],"summary":{"end":56.000156,"start":55.000148,"omitted":false,"retransmits":0,"throughput-bits":859825452.5548505,"throughput-bytes":107479040}},{"streams":[{"end":57.000153,"rtt":77086,"start":56.000156,"omitted":false,"stream-id":5,"retransmits":0,"tcp-window-size":16708472,"throughput-bits":870320673.75773,"throughput-bytes":108789760}],"summary":{"end":57.000153,"start":56.000156,"omitted":false,"retransmits":0,"throughput-bits":870320673.75773,"throughput-bytes":108789760}},{"streams":[{"end":58.000163,"rtt":77086,"start":57.000153,"omitted":false,"stream-id":5,"retransmits":0,"tcp-window-size":16708472,"throughput-bits":859823710.086216,"throughput-bytes":107479040}],"summary":{"end":58.000163,"start":57.000153,"omitted":false,"retransmits":0,"throughput-bits":859823710.086216,"throughput-bytes":107479040}},{"streams":[{"end":59.000156,"rtt":77090,"start":58.000163,"omitted":false,"stream-id":5,"retransmits":0,"tcp-window-size":16708472,"throughput-bits":870324149.4173266,"throughput-bytes":108789760}],"summary":{"end":59.000156,"start":58.000163,"omitted":false,"retransmits":0,"throughput-bits":870324149.4173266,"throughput-bytes":108789760}},{"streams":[{"end":60.000166,"rtt":77088,"start":59.000156,"omitted":false,"stream-id":5,"retransmits":0,"tcp-window-size":16708472,"throughput-bits":859823710.086216,"throughput-bytes":107479040}],"summary":{"end":60.000166,"start":59.000156,"omitted":false,"retransmits":0,"throughput-bits":859823710.086216,"throughput-bytes":107479040}}],"succeeded":true}
