{"diags":"Participant 0:\n/usr/bin/iperf3 -p 5201 -B 10.0.0.1 -c 10.0.0.2 -t 60 --json --rsa-public-key-path /var/run/pscheduler-server/runner/tmp/tmp19nc16j9/tmp7yf4mzz1/public-key --username 2Qu6gD4yfFEzh00uCMla\n\n{\n    \"end\": {\n        \"cpu_utilization_percent\": {\n            \"host_system\": 2.10292508807312, \n            \"host_total\": 2.144434584666075, \n            \"host_user\": 0.04151116297178267, \n            \"remote_system\": 4.849106379257348, \n            \"remote_total\": 5.2662093435132, \n            \"remote_user\": 0.4171012997655349\n        }, \n        \"receiver_tcp_congestion\": \"htcp\", \n        \"sender_tcp_congestion\": \"htcp\", \n        \"streams\": [\n            {\n                \"receiver\": {\n                    \"bits_per_second\": 851119043.423738, \n                    \"bytes\": 6391736984, \n                    \"end\": 60.07843, \n                    \"seconds\": 60.000072, \n                    \"sender\": true, \n                    \"socket\": 5, \n                    \"start\": 0\n                }, \n                \"sender\": {\n                    \"bits_per_second\": 852735932.4502144, \n                    \"bytes\": 6395527168, \n                    \"end\": 60.000072, \n                    \"max_rtt\": 78446, \n                    \"max_snd_cwnd\": 16685304, \n                    \"max_snd_wnd\": 0, \n                    \"mean_rtt\": 78385, \n                    \"min_rtt\": 78377, \n                    \"retransmits\": 0, \n                    \"seconds\": 60.000072, \n                    \"sender\": true, \n                    \"socket\": 5, \n                    \"start\": 0\n                }\n            }\n        ], \n        \"sum_received\": {\n            \"bits_per_second\": 851119043.423738, \n            \"bytes\": 6391736984, \n            \"end\": 60.07843, \n            \"seconds\": 60.07843, \n            \"sender\": true, \n            \"start\": 0\n        }, \n        \"sum_sent\": {\n            \"bits_per_second\": 852735932.4502144, \n            \"bytes\": 6395527168, \n            \"end\": 60.000072, \n            \"retransmits\": 0, \n            \"seconds\": 60.000072, \n            \"sender\": true, \n            \"start\": 0\n        }\n    }, \n    \"intervals\": [\n        {\n            \"streams\": [\n                {\n                    \"bits_per_second\": 937358557.9891757, \n                    \"bytes\": 117178368, \n                    \"end\": 1.000073, \n                    \"omitted\": false, \n                    \"pmtu\": 1500, \n                    \"retransmits\": 0, \n                    \"rtt\": 78381, \n                    \"rttvar\": 15, \n                    \"seconds\": 1.000072956085205, \n                    \"sender\": true, \n                    \"snd_cwnd\": 16685304, \n                    \"snd_wnd\": -1, \n                    \"socket\": 5, \n                    \"start\": 0\n                }\n            ], \n            \"sum\": {\n                \"bits_per_second\": 937358557.9891757, \n                \"bytes\": 117178368, \n                \"end\": 1.000073, \n                \"omitted\": false, \n                \"retransmits\": 0, \n                \"seconds\": 1.000072956085205, \n                \"sender\": true, \n                \"start\": 0\n            }\n        }, \n        {\n            \"streams\": [\n                {\n                    \"bits_per_second\": 849343117.513953, \n                    \"bytes\": 106168320, \n                    \"end\": 2.000077, \n                    \"omitted\": false, \n                    \"pmtu\": 1500, \n                    \"retransmits\": 0, \n                    \"rtt\": 78383, \n                    \"rttvar\": 9, \n                    \"seconds\": 1.0000040531158447, \n                    \"sender\": true, \n                    \"snd_cwnd\": 16685304, \n                    \"snd_wnd\": -1, \n                    \"socket\": 5, \n                    \"start\": 1.000073\n                }\n            ], \n            \"sum\": {\n                \"bits_per_second\": 849343117.513953, \n                \"bytes\": 106168320, \n                \"end\": 2.000077, \n                \"omitted\": false, \n                \"retransmits\": 0, \n                \"seconds\": 1.0000040531158447, \n                \"sender\": true, \n                \"start\": 1.000073\n            }\n        }, \n        {\n            \"streams\": [\n                {\n                    \"bits_per_second\": 859830577.5035312, \n                    \"bytes\": 107479040, \n                    \"end\": 3.000079, \n                    \"omitted\": false, \n                    \"pmtu\": 1500, \n                    \"retransmits\": 0, \n                    \"rtt\": 78384, \n                    \"rttvar\": 18, \n                    \"seconds\": 1.0000020265579224, \n                    \"sender\": true, \n                    \"snd_cwnd\": 16685304, \n                    \"snd_wnd\": -1, \n                    \"socket\": 5, \n                    \"start\": 2.000077\n                }\n            ], \n            \"sum\": {\n                \"bits_per_second\": 859830577.5035312, \n                \"bytes\": 107479040, \n                \"end\": 3.000079, \n                \"omitted\": false, \n                \"retransmits\": 0, \n                \"seconds\": 1.0000020265579224, \n                \"sender\": true, \n                \"start\": 2.000077\n            }\n        }, \n        {\n            \"streams\": [\n                {\n                    \"bits_per_second\": 849360127.7167313, \n                    \"bytes\": 106168320, \n                    \"end\": 4.000063, \n                    \"omitted\": false, \n                    \"pmtu\": 1500, \n                    \"retransmits\": 0, \n                    \"rtt\": 78388, \n                    \"rttvar\": 7, \n                    \"seconds\": 0.9999840259552002, \n                    \"sender\": true, \n                    \"snd_cwnd\": 16685304, \n                    \"snd_wnd\": -1, \n                    \"socket\": 5, \n                    \"start\": 3.000079\n                }\n            ], \n            \"sum\": {\n                \"bits_per_second\": 849360127.7167313, \n                \"bytes\": 106168320, \n                \"end\": 4.000063, \n                \"omitted\": false, \n                \"retransmits\": 0, \n                \"seconds\": 0.9999840259552002, \n                \"sender\": true, \n                \"start\": 3.000079\n            }\n        }, \n        {\n            \"streams\": [\n                {\n                    \"bits_per_second\": 849269313.276106, \n                    \"bytes\": 106168320, \n                    \"end\": 5.000154, \n                    \"omitted\": false, \n                    \"pmtu\": 1500, \n                    \"retransmits\": 0, \n                    \"rtt\": 78383, \n                    \"rttvar\": 8, \n                    \"seconds\": 1.0000909566879272, \n                    \"sender\": true, \n                    \"snd_cwnd\": 16685304, \n                    \"snd_wnd\": -1, \n                    \"socket\": 5, \n                    \"start\": 4.000063\n                }\n            ], \n            \"sum\": {\n                \"bits_per_second\": 849269313.276106, \n                \"bytes\": 106168320, \n                \"end\": 5.000154, \n                \"omitted\": false, \n                \"retransmits\": 0, \n                \"seconds\": 1.0000909566879272, \n                \"sender\": true, \n                \"start\": 4.000063\n            }\n        }, \n        {\n            \"streams\": [\n                {\n                    \"bits_per_second\": 849344838.7534882, \n                    \"bytes\": 106168320, \n                    \"end\": 6.000156, \n                    \"omitted\": false, \n                    \"pmtu\": 1500, \n                    \"retransmits\": 0, \n                    \"rtt\": 78390, \n                    \"rttvar\": 11, \n                    \"seconds\": 1.0000020265579224, \n                    \"sender\": true, \n                    \"snd_cwnd\": 16685304, \n                    \"snd_wnd\": -1, \n                    \"socket\": 5, \n                    \"start\": 5.000154\n                }\n            ], \n            \"sum\": {\n                \"bits_per_second\": 849344838.7534882, \n                \"bytes\": 106168320, \n                \"end\": 6.000156, \n                \"omitted\": false, \n                \"retransmits\": 0, \n                \"seconds\": 1.0000020265579224, \n                \"sender\": true, \n                \"start\": 5.000154\n            }\n        }, \n        {\n            \"streams\": [\n                {\n                    \"bits_per_second\": 849332992.7167244, \n                    \"bytes\": 106168320, \n                    \"end\": 7.000172, \n                    \"omitted\": false, \n                    \"pmtu\": 1500, \n                    \"retransmits\": 0, \n                    \"rtt\": 78390, \n                    \"rttvar\": 4, \n                    \"seconds\": 1.0000159740448, \n                    \"sender\": true, \n                    \"snd_cwnd\": 16685304, \n                    \"snd_wnd\": -1, \n                    \"socket\": 5, \n                    \"start\": 6.000156\n                }\n            ], \n            \"sum\": {\n                \"bits_per_second\": 849332992.7167244, \n                \"bytes\": 106168320, \n                \"end\": 7.000172, \n                \"omitted\": false, \n                \"retransmits\": 0, \n                \"seconds\": 1.0000159740448, \n                \"sender\": true, \n                \"start\": 6.000156\n            }\n        }, \n        {\n            \"streams\": [\n                {\n                    \"bits_per_second\": 849344028.7575437, \n                    \"bytes\": 106168320, \n                    \"end\": 8.000175, \n                    \"omitted\": false, \n                    \"pmtu\": 1500, \n                    \"retransmits\": 0, \n                    \"rtt\": 78383, \n                    \"rttvar\": 6, \n                    \"seconds\": 1.0000029802322388, \n                    \"sender\": true, \n                    \"snd_cwnd\": 16685304, \n                    \"snd_wnd\": -1, \n                    \"socket\": 5, \n                    \"start\": 7.000172\n                }\n            ], \n            \"sum\": {\n                \"bits_per_second\": 849344028.7575437, \n                \"bytes\": 106168320, \n                \"end\": 8.000175, \n                \"omitted\": false, \n                \"retransmits\": 0, \n                \"seconds\": 1.0000029802322388, \n                \"sender\": true, \n                \"start\": 7.000172\n            }\n        }, \n        {\n            \"streams\": [\n                {\n                    \"bits_per_second\": 859912277.4347018, \n                    \"bytes\": 107479040, \n                    \"end\": 9.000082, \n                    \"omitted\": false, \n                    \"pmtu\": 1500, \n                    \"retransmits\": 0, \n                    \"rtt\": 78384, \n                    \"rttvar\": 5, \n                    \"seconds\": 0.9999070167541504, \n                    \"sender\": true, \n                    \"snd_cwnd\": 16685304, \n                    \"snd_wnd\": -1, \n                    \"socket\": 5, \n                    \"start\": 8.000175\n                }\n            ], \n            \"sum\": {\n                \"bits_per_second\": 859912277.4347018, \n                \"bytes\": 107479040, \n                \"end\": 9.000082, \n                \"omitted\": false, \n                \"retransmits\": 0, \n                \"seconds\": 0.9999070167541504, \n                \"sender\": true, \n                \"start\": 8.000175\n            }\n        }, \n        {\n            \"streams\": [\n                {\n                    \"bits_per_second\": 849282878.5250053, \n                    \"bytes\": 106168320, \n                    \"end\": 10.000157, \n                    \"omitted\": false, \n                    \"pmtu\": 1500, \n                    \"retransmits\": 0, \n                    \"rtt\": 78381, \n                    \"rttvar\": 5, \n                    \"seconds\": 1.0000749826431274, \n                    \"sender\": true, \n                    \"snd_cwnd\": 16685304, \n                    \"snd_wnd\": -1, \n                    \"socket\": 5, \n                    \"start\": 9.000082\n                }\n            ], \n            \"sum\": {\n                \"bits_per_second\": 849282878.5250053, \n                \"bytes\": 106168320, \n                \"end\": 10.000157, \n                \"omitted\": false, \n                \"retransmits\": 0, \n                \"seconds\": 1.0000749826431274, \n                \"sender\": true, \n                \"start\": 9.000082\n            }\n        }, \n        {\n            \"streams\": [\n                {\n                    \"bits_per_second\": 849407719.4036245, \n                    \"bytes\": 106168320, \n                    \"end\": 11.000085, \n                    \"omitted\": false, \n                    \"pmtu\": 1500, \n                    \"retransmits\": 0, \n                    \"rtt\": 78381, \n                    \"rttvar\": 8, \n                    \"seconds\": 0.9999279975891113, \n                    \"sender\": true, \n                    \"snd_cwnd\": 16685304, \n                    \"snd_wnd\": -1, \n                    \"socket\": 5, \n                    \"start\": 10.000157\n                }\n            ], \n            \"sum\": {\n                \"bits_per_second\": 849407719.4036245, \n                \"bytes\": 106168320, \n                \"end\": 11.000085, \n                \"omitted\": false, \n                \"retransmits\": 0, \n                \"seconds\": 0.9999279975891113, \n                \"sender\": true, \n                \"start\": 10.000157\n            }\n        }, \n        {\n            \"streams\": [\n                {\n                    \"bits_per_second\": 849284599.520394, \n                    \"bytes\": 106168320, \n                    \"end\": 12.000158, \n                    \"omitted\": false, \n                    \"pmtu\": 1500, \n                    \"retransmits\": 0, \n                    \"rtt\": 78386, \n                    \"rttvar\": 9, \n                    \"seconds\": 1.000072956085205, \n                    \"sender\": true, \n                    \"snd_cwnd\": 16685304, \n                    \"snd_wnd\": -1, \n                    \"socket\": 5, \n                    \"start\": 11.000085\n                }\n            ], \n            \"sum\": {\n                \"bits_per_second\": 849284599.520394, \n                \"bytes\": 106168320, \n                \"end\": 12.000158, \n                \"omitted\": false, \n                \"retransmits\": 0, \n                \"seconds\": 1.000072956085205, \n                \"sender\": true, \n                \"start\": 11.000085\n            }\n        }, \n        {\n            \"streams\": [\n                {\n                    \"bits_per_second\": 849352483.1663066, \n                    \"bytes\": 106168320, \n                    \"end\": 13.000151, \n                    \"omitted\": false, \n                    \"pmtu\": 1500, \n                    \"retransmits\": 0, \n                    \"rtt\": 78387, \n                    \"rttvar\": 5, \n                    \"seconds\": 0.9999930262565613, \n                    \"sender\": true, \n                    \"snd_cwnd\": 16685304, \n                    \"snd_wnd\": -1, \n                    \"socket\": 5, \n                    \"start\": 12.000158\n                }\n            ], \n            \"sum\": {\n                \"bits_per_second\": 849352483.1663066, \n                \"bytes\": 106168320, \n                \"end\": 13.000151, \n                \"omitted\": false, \n                \"retransmits\": 0, \n                \"seconds\": 0.9999930262565613, \n                \"sender\": true, \n                \"start\": 12.000158\n            }\n        }, \n        {\n            \"streams\": [\n                {\n                    \"bits_per_second\": 859910585.8734696, \n                    \"bytes\": 107479040, \n                    \"end\": 14.00006, \n                    \"omitted\": false, \n                    \"pmtu\": 1500, \n                    \"retransmits\": 0, \n                    \"rtt\": 78384, \n                    \"rttvar\": 6, \n                    \"seconds\": 0.999908983707428, \n                    \"sender\": true, \n                    \"snd_cwnd\": 16685304, \n                    \"snd_wnd\": -1, \n                    \"socket\": 5, \n                    \"start\": 13.000151\n                }\n            ], \n            \"sum\": {\n                \"bits_per_second\": 859910585.8734696, \n                \"bytes\": 107479040, \n                \"end\": 14.00006, \n                \"omitted\": false, \n                \"retransmits\": 0, \n                \"seconds\": 0.999908983707428, \n                \"sender\": true, \n                \"start\": 13.000151\n            }\n        }, \n        {\n            \"streams\": [\n                {\n                    \"bits_per_second\": 849265871.4162065, \n                    \"bytes\": 106168320, \n                    \"end\": 15.000155, \n                    \"omitted\": false, \n                    \"pmtu\": 1500, \n                    \"retransmits\": 0, \n                    \"rtt\": 78387, \n                    \"rttvar\": 6, \n                    \"seconds\": 1.000095009803772, \n                    \"sender\": true, \n                    \"snd_cwnd\": 16685304, \n                    \"snd_wnd\": -1, \n                    \"socket\": 5, \n                    \"start\": 14.00006\n                }\n            ], \n            \"sum\": {\n                \"bits_per_second\": 849265871.4162065, \n                \"bytes\": 106168320, \n                \"end\": 15.000155, \n                \"omitted\": false, \n                \"retransmits\": 0, \n                \"seconds\": 1.000095009803772, \n                \"sender\": true, \n                \"start\": 14.00006\n            }\n        }, \n        {\n            \"streams\": [\n                {\n                    \"bits_per_second\": 849332992.7167244, \n                    \"bytes\": 106168320, \n                    \"end\": 16.000171, \n                    \"omitted\": false, \n                    \"pmtu\": 1500, \n                    \"retransmits\": 0, \n                    \"rtt\": 78377, \n                    \"rttvar\": 8, \n                    \"seconds\": 1.0000159740448, \n                    \"sender\": true, \n                    \"snd_cwnd\": 16685304, \n                    \"snd_wnd\": -1, \n                    \"socket\": 5, \n                    \"start\": 15.000155\n                }\n            ], \n            \"sum\": {\n                \"bits_per_second\": 849332992.7167244, \n                \"bytes\": 106168320, \n                \"end\": 16.000171, \n                \"omitted\": false, \n                \"retransmits\": 0, \n                \"seconds\": 1.0000159740448, \n                \"sender\": true, \n                \"start\": 15.000155\n            }\n        }, \n        {\n            \"streams\": [\n                {\n                    \"bits_per_second\": 849360127.7167313, \n                    \"bytes\": 106168320, \n                    \"end\": 17.000155, \n                    \"omitted\": false, \n                    \"pmtu\": 1500, \n                    \"retransmits\": 0, \n                    \"rtt\": 78383, \n                    \"rttvar\": 5, \n                    \"seconds\": 0.9999840259552002, \n                    \"sender\": true, \n                    \"snd_cwnd\": 16685304, \n                    \"snd_wnd\": -1, \n                    \"socket\": 5, \n                    \"start\": 16.000171\n                }\n            ], \n            \"sum\": {\n                \"bits_per_second\": 849360127.7167313, \n                \"bytes\": 106168320, \n                \"end\": 17.000155, \n                \"omitted\": false, \n                \"retransmits\": 0, \n                \"seconds\": 0.9999840259552002, \n                \"sender\": true, \n                \"start\": 16.000171\n            }\n        }, \n        {\n            \"streams\": [\n                {\n                    \"bits_per_second\": 849350812.5212915, \n                    \"bytes\": 106168320, \n                    \"end\": 18.00015, \n                    \"omitted\": false, \n                    \"pmtu\": 1500, \n                    \"retransmits\": 0, \n                    \"rtt\": 78384, \n                    \"rttvar\": 7, \n                    \"seconds\": 0.999994993209839, \n                    \"sender\": true, \n                    \"snd_cwnd\": 16685304, \n                    \"snd_wnd\": -1, \n                    \"socket\": 5, \n                    \"start\": 17.000155\n                }\n            ], \n            \"sum\": {\n                \"bits_per_second\": 849350812.5212915, \n                \"bytes\": 106168320, \n                \"end\": 18.00015, \n                \"omitted\": false, \n                \"retransmits\": 0, \n                \"seconds\": 0.999994993209839, \n                \"sender\": true, \n                \"start\": 17.000155\n            }\n        }, \n        {\n            \"streams\": [\n                {\n                    \"bits_per_second\": 849387315.0804996, \n                    \"bytes\": 106168320, \n                    \"end\": 19.000102, \n                    \"omitted\": false, \n                    \"pmtu\": 1500, \n                    \"retransmits\": 0, \n                    \"rtt\": 78386, \n                    \"rttvar\": 5, \n                    \"seconds\": 0.9999520182609558, \n                    \"sender\": true, \n                    \"snd_cwnd\": 16685304, \n                    \"snd_wnd\": -1, \n                    \"socket\": 5, \n                    \"start\": 18.00015\n                }\n            ], \n            \"sum\": {\n                \"bits_per_second\": 849387315.0804996, \n                \"bytes\": 106168320, \n                \"end\": 19.000102, \n                \"omitted\": false, \n                \"retransmits\": 0, \n                \"seconds\": 0.9999520182609558, \n                \"sender\": true, \n                \"start\": 18.00015\n            }\n        }, \n        {\n            \"streams\": [\n                {\n                    \"bits_per_second\": 859849540.3448746, \n                    \"bytes\": 107479040, \n                    \"end\": 20.000082, \n                    \"omitted\": false, \n                    \"pmtu\": 1500, \n                    \"retransmits\": 0, \n                    \"rtt\": 78386, \n                    \"rttvar\": 8, \n                    \"seconds\": 0.9999799728393555, \n                    \"sender\": true, \n                    \"snd_cwnd\": 16685304, \n                    \"snd_wnd\": -1, \n                    \"socket\": 5, \n                    \"start\": 19.000102\n                }\n            ], \n            \"sum\": {\n                \"bits_per_second\": 859849540.3448746, \n                \"bytes\": 107479040, \n                \"end\": 20.000082, \n                \"omitted\": false, \n                \"retransmits\": 0, \n                \"seconds\": 0.9999799728393555, \n                \"sender\": true, \n                \"start\": 19.000102\n            }\n        }, \n        {\n            \"streams\": [\n                {\n                    \"bits_per_second\": 849283688.4043194, \n                    \"bytes\": 106168320, \n                    \"end\": 21.000156, \n                    \"omitted\": false, \n                    \"pmtu\": 1500, \n                    \"retransmits\": 0, \n                    \"rtt\": 78385, \n                    \"rttvar\": 6, \n                    \"seconds\": 1.000074028968811, \n                    \"sender\": true, \n                    \"snd_cwnd\": 16685304, \n                    \"snd_wnd\": -1, \n                    \"socket\": 5, \n                    \"start\": 20.000082\n                }\n            ], \n            \"sum\": {\n                \"bits_per_second\": 849283688.4043194, \n                \"bytes\": 106168320, \n                \"end\": 21.000156, \n                \"omitted\": false, \n                \"retransmits\": 0, \n                \"seconds\": 1.000074028968811, \n                \"sender\": true, \n                \"start\": 20.000082\n            }\n        }, \n        {\n            \"streams\": [\n                {\n                    \"bits_per_second\": 849337245.102159, \n                    \"bytes\": 106168320, \n                    \"end\": 22.000167, \n                    \"omitted\": false, \n                    \"pmtu\": 1500, \n                    \"retransmits\": 0, \n                    \"rtt\": 78382, \n                    \"rttvar\": 3, \n                    \"seconds\": 1.0000109672546387, \n                    \"sender\": true, \n                    \"snd_cwnd\": 16685304, \n                    \"snd_wnd\": -1, \n                    \"socket\": 5, \n                    \"start\": 21.000156\n                }\n            ], \n            \"sum\": {\n                \"bits_per_second\": 849337245.102159, \n                \"bytes\": 106168320, \n                \"end\": 22.000167, \n                \"omitted\": false, \n                \"retransmits\": 0, \n                \"seconds\": 1.0000109672546387, \n                \"sender\": true, \n                \"start\": 21.000156\n            }\n        }, \n        {\n            \"streams\": [\n                {\n                    \"bits_per_second\": 849342307.5212913, \n                    \"bytes\": 106168320, \n                    \"end\": 23.000172, \n                    \"omitted\": false, \n                    \"pmtu\": 1500, \n                    \"retransmits\": 0, \n                    \"rtt\": 78387, \n                    \"rttvar\": 12, \n                    \"seconds\": 1.0000050067901611, \n                    \"sender\": true, \n                    \"snd_cwnd\": 16685304, \n                    \"snd_wnd\": -1, \n                    \"socket\": 5, \n                    \"start\": 22.000167\n                }\n            ], \n            \"sum\": {\n                \"bits_per_second\": 849342307.5212913, \n                \"bytes\": 106168320, \n                \"end\": 23.000172, \n                \"omitted\": false, \n                \"retransmits\": 0, \n                \"seconds\": 1.0000050067901611, \n                \"sender\": true, \n                \"start\": 22.000167\n            }\n        }, \n        {\n            \"streams\": [\n                {\n                    \"bits_per_second\": 849423010.630787, \n                    \"bytes\": 106168320, \n                    \"end\": 24.000082, \n                    \"omitted\": false, \n                    \"pmtu\": 1500, \n                    \"retransmits\": 0, \n                    \"rtt\": 78387, \n                    \"rttvar\": 7, \n                    \"seconds\": 0.999909996986389, \n                    \"sender\": true, \n                    \"snd_cwnd\": 16685304, \n                    \"snd_wnd\": -1, \n                    \"socket\": 5, \n                    \"start\": 23.000172\n                }\n            ], \n            \"sum\": {\n                \"bits_per_second\": 849423010.630787, \n                \"bytes\": 106168320, \n                \"end\": 24.000082, \n                \"omitted\": false, \n                \"retransmits\": 0, \n                \"seconds\": 0.999909996986389, \n                \"sender\": true, \n                \"start\": 23.000172\n            }\n        }, \n        {\n            \"streams\": [\n                {\n                    \"bits_per_second\": 849282878.5250053, \n                    \"bytes\": 106168320, \n                    \"end\": 25.000157, \n                    \"omitted\": false, \n                    \"pmtu\": 1500, \n                    \"retransmits\": 0, \n                    \"rtt\": 78386, \n                    \"rttvar\": 14, \n                    \"seconds\": 1.0000749826431274, \n                    \"sender\": true, \n                    \"snd_cwnd\": 16685304, \n                    \"snd_wnd\": -1, \n                    \"socket\": 5, \n                    \"start\": 24.000082\n                }\n            ], \n            \"sum\": {\n                \"bits_per_second\": 849282878.5250053, \n                \"bytes\": 106168320, \n                \"end\": 25.000157, \n                \"omitted\": false, \n                \"retransmits\": 0, \n                \"seconds\": 1.0000749826431274, \n                \"sender\": true, \n                \"start\": 24.000082\n            }\n        }, \n        {\n            \"streams\": [\n                {\n                    \"bits_per_second\": 859897668.716236, \n                    \"bytes\": 107479040, \n                    \"end\": 26.000081, \n                    \"omitted\": false, \n                    \"pmtu\": 1500, \n                    \"retransmits\": 0, \n                    \"rtt\": 78387, \n                    \"rttvar\": 9, \n                    \"seconds\": 0.9999240040779114, \n                    \"sender\": true, \n                    \"snd_cwnd\": 16685304, \n                    \"snd_wnd\": -1, \n                    \"socket\": 5, \n                    \"start\": 25.000157\n                }\n            ], \n            \"sum\": {\n                \"bits_per_second\": 859897668.716236, \n                \"bytes\": 107479040, \n                \"end\": 26.000081, \n                \"omitted\": false, \n                \"retransmits\": 0, \n                \"seconds\": 0.9999240040779114, \n                \"sender\": true, \n                \"start\": 25.000157\n            }\n        }, \n        {\n            \"streams\": [\n                {\n                    \"bits_per_second\": 849276905.7127655, \n                    \"bytes\": 106168320, \n                    \"end\": 27.000163, \n                    \"omitted\": false, \n                    \"pmtu\": 1500, \n                    \"retransmits\": 0, \n                    \"rtt\": 78386, \n                    \"rttvar\": 6, \n                    \"seconds\": 1.000082015991211, \n                    \"sender\": true, \n                    \"snd_cwnd\": 16685304, \n                    \"snd_wnd\": -1, \n                    \"socket\": 5, \n                    \"start\": 26.000081\n                }\n            ], \n            \"sum\": {\n                \"bits_per_second\": 849276905.7127655, \n                \"bytes\": 106168320, \n                \"end\": 27.000163, \n                \"omitted\": false, \n                \"retransmits\": 0, \n                \"seconds\": 1.000082015991211, \n                \"sender\": true, \n                \"start\": 26.000081\n            }\n        }, \n        {\n            \"streams\": [\n                {\n                    \"bits_per_second\": 849338966.3178928, \n                    \"bytes\": 106168320, \n                    \"end\": 28.000172, \n                    \"omitted\": false, \n                    \"pmtu\": 1500, \n                    \"retransmits\": 0, \n                    \"rtt\": 78381, \n                    \"rttvar\": 6, \n                    \"seconds\": 1.0000089406967163, \n                    \"sender\": true, \n                    \"snd_cwnd\": 16685304, \n                    \"snd_wnd\": -1, \n                    \"socket\": 5, \n                    \"start\": 27.000163\n                }\n            ], \n            \"sum\": {\n                \"bits_per_second\": 849338966.3178928, \n                \"bytes\": 106168320, \n                \"end\": 28.000172, \n                \"omitted\": false, \n                \"retransmits\": 0, \n                \"seconds\": 1.0000089406967163, \n                \"sender\": true, \n                \"start\": 27.000163\n            }\n        }, \n        {\n            \"streams\": [\n                {\n                    \"bits_per_second\": 849389036.4991773, \n                    \"bytes\": 106168320, \n                    \"end\": 29.000122, \n                    \"omitted\": false, \n                    \"pmtu\": 1500, \n                    \"retransmits\": 0, \n                    \"rtt\": 78387, \n                    \"rttvar\": 7, \n                    \"seconds\": 0.9999499917030334, \n                    \"sender\": true, \n                    \"snd_cwnd\": 16685304, \n                    \"snd_wnd\": -1, \n                    \"socket\": 5, \n                    \"start\": 28.000172\n                }\n            ], \n            \"sum\": {\n                \"bits_per_second\": 849389036.4991773, \n                \"bytes\": 106168320, \n                \"end\": 29.000122, \n                \"omitted\": false, \n                \"retransmits\": 0, \n                \"seconds\": 0.9999499917030334, \n                \"sender\": true, \n                \"start\": 28.000172\n            }\n        }, \n        {\n            \"streams\": [\n                {\n                    \"bits_per_second\": 849316793.5432408, \n                    \"bytes\": 106168320, \n                    \"end\": 30.000157, \n                    \"omitted\": false, \n                    \"pmtu\": 1500, \n                    \"retransmits\": 0, \n                    \"rtt\": 78382, \n                    \"rttvar\": 7, \n                    \"seconds\": 1.000035047531128, \n                    \"sender\": true, \n                    \"snd_cwnd\": 16685304, \n                    \"snd_wnd\": -1, \n                    \"socket\": 5, \n                    \"start\": 29.000122\n                }\n            ], \n            \"sum\": {\n                \"bits_per_second\": 849316793.5432408, \n                \"bytes\": 106168320, \n                \"end\": 30.000157, \n                \"omitted\": false, \n                \"retransmits\": 0, \n                \"seconds\": 1.000035047531128, \n                \"sender\": true, \n                \"start\": 29.000122\n            }\n        }, \n        {\n            \"streams\": [\n                {\n                    \"bits_per_second\": 859584751.3021724, \n                    \"bytes\": 107479040, \n                    \"end\": 31.000445, \n                    \"omitted\": false, \n                    \"pmtu\": 1500, \n                    \"retransmits\": 0, \n                    \"rtt\": 78379, \n                    \"rttvar\": 5, \n                    \"seconds\": 1.0002880096435547, \n                    \"sender\": true, \n                    \"snd_cwnd\": 16685304, \n                    \"snd_wnd\": -1, \n                    \"socket\": 5, \n                    \"start\": 30.000157\n                }\n            ], \n            \"sum\": {\n                \"bits_per_second\": 859584751.3021724, \n                \"bytes\": 107479040, \n                \"end\": 31.000445, \n                \"omitted\": false, \n                \"retransmits\": 0, \n                \"seconds\": 1.0002880096435547, \n                \"sender\": true, \n                \"start\": 30.000157\n            }\n        }, \n        {\n            \"streams\": [\n                {\n                    \"bits_per_second\": 849594644.316403, \n                    \"bytes\": 106168320, \n                    \"end\": 32.000153, \n                    \"omitted\": false, \n                    \"pmtu\": 1500, \n                    \"retransmits\": 0, \n                    \"rtt\": 78382, \n                    \"rttvar\": 6, \n                    \"seconds\": 0.9997079968452454, \n                    \"sender\": true, \n                    \"snd_cwnd\": 16685304, \n                    \"snd_wnd\": -1, \n                    \"socket\": 5, \n                    \"start\": 31.000445\n                }\n            ], \n            \"sum\": {\n                \"bits_per_second\": 849594644.316403, \n                \"bytes\": 106168320, \n                \"end\": 32.000153, \n                \"omitted\": false, \n                \"retransmits\": 0, \n                \"seconds\": 0.9997079968452454, \n                \"sender\": true, \n                \"start\": 31.000445\n            }\n        }, \n        {\n            \"streams\": [\n                {\n                    \"bits_per_second\": 849328740.3738706, \n                    \"bytes\": 106168320, \n                    \"end\": 33.000174, \n                    \"omitted\": false, \n                    \"pmtu\": 1500, \n                    \"retransmits\": 0, \n                    \"rtt\": 78384, \n                    \"rttvar\": 9, \n                    \"seconds\": 1.000020980834961, \n                    \"sender\": true, \n                    \"snd_cwnd\": 16685304, \n                    \"snd_wnd\": -1, \n                    \"socket\": 5, \n                    \"start\": 32.000153\n                }\n            ], \n            \"sum\": {\n                \"bits_per_second\": 849328740.3738706, \n                \"bytes\": 106168320, \n                \"end\": 33.000174, \n                \"omitted\": false, \n                \"retransmits\": 0, \n                \"seconds\": 1.000020980834961, \n                \"sender\": true, \n                \"start\": 32.000153\n            }\n        }, \n        {\n            \"streams\": [\n                {\n                    \"bits_per_second\": 849359317.6916252, \n                    \"bytes\": 106168320, \n                    \"end\": 34.000159, \n                    \"omitted\": false, \n                    \"pmtu\": 1500, \n                    \"retransmits\": 0, \n                    \"rtt\": 78383, \n                    \"rttvar\": 6, \n                    \"seconds\": 0.9999849796295166, \n                    \"sender\": true, \n                    \"snd_cwnd\": 16685304, \n                    \"snd_wnd\": -1, \n                    \"socket\": 5, \n                    \"start\": 33.000174\n                }\n            ], \n            \"sum\": {\n                \"bits_per_second\": 849359317.6916252, \n                \"bytes\": 106168320, \n                \"end\": 34.000159, \n                \"omitted\": false, \n                \"retransmits\": 0, \n                \"seconds\": 0.9999849796295166, \n                \"sender\": true, \n                \"start\": 33.000174\n            }\n        }, \n        {\n            \"streams\": [\n                {\n                    \"bits_per_second\": 849412833.295807, \n                    \"bytes\": 106168320, \n                    \"end\": 35.000081, \n                    \"omitted\": false, \n                    \"pmtu\": 1500, \n                    \"retransmits\": 0, \n                    \"rtt\": 78383, \n                    \"rttvar\": 5, \n                    \"seconds\": 0.999921977519989, \n                    \"sender\": true, \n                    \"snd_cwnd\": 16685304, \n                    \"snd_wnd\": -1, \n                    \"socket\": 5, \n                    \"start\": 34.000159\n                }\n            ], \n            \"sum\": {\n                \"bits_per_second\": 849412833.295807, \n                \"bytes\": 106168320, \n                \"end\": 35.000081, \n                \"omitted\": false, \n                \"retransmits\": 0, \n                \"seconds\": 0.999921977519989, \n                \"sender\": true, \n                \"start\": 34.000159\n            }\n        }, \n        {\n            \"streams\": [\n                {\n                    \"bits_per_second\": 849361849.0252117, \n                    \"bytes\": 106168320, \n                    \"end\": 36.000063, \n                    \"omitted\": false, \n                    \"pmtu\": 1500, \n                    \"retransmits\": 0, \n                    \"rtt\": 78388, \n                    \"rttvar\": 12, \n                    \"seconds\": 0.9999819993972778, \n                    \"sender\": true, \n                    \"snd_cwnd\": 16685304, \n                    \"snd_wnd\": -1, \n                    \"socket\": 5, \n                    \"start\": 35.000081\n                }\n            ], \n            \"sum\": {\n                \"bits_per_second\": 849361849.0252117, \n                \"bytes\": 106168320, \n                \"end\": 36.000063, \n                \"omitted\": false, \n                \"retransmits\": 0, \n                \"seconds\": 0.9999819993972778, \n                \"sender\": true, \n                \"start\": 35.000081\n            }\n        }, \n        {\n            \"streams\": [\n                {\n                    \"bits_per_second\": 859815100.3448608, \n                    \"bytes\": 107479040, \n                    \"end\": 37.000083, \n                    \"omitted\": false, \n                    \"pmtu\": 1500, \n                    \"retransmits\": 0, \n                    \"rtt\": 78382, \n                    \"rttvar\": 6, \n                    \"seconds\": 1.0000200271606445, \n                    \"sender\": true, \n                    \"snd_cwnd\": 16685304, \n                    \"snd_wnd\": -1, \n                    \"socket\": 5, \n                    \"start\": 36.000063\n                }\n            ], \n            \"sum\": {\n                \"bits_per_second\": 859815100.3448608, \n                \"bytes\": 107479040, \n                \"end\": 37.000083, \n                \"omitted\": false, \n                \"retransmits\": 0, \n                \"seconds\": 1.0000200271606445, \n                \"sender\": true, \n                \"start\": 36.000063\n            }\n        }, \n        {\n            \"streams\": [\n                {\n                    \"bits_per_second\": 849284599.520394, \n                    \"bytes\": 106168320, \n                    \"end\": 38.000156, \n                    \"omitted\": false, \n                    \"pmtu\": 1500, \n                    \"retransmits\": 0, \n                    \"rtt\": 78387, \n                    \"rttvar\": 7, \n                    \"seconds\": 1.000072956085205, \n                    \"sender\": true, \n                    \"snd_cwnd\": 16685304, \n                    \"snd_wnd\": -1, \n                    \"socket\": 5, \n                    \"start\": 37.000083\n                }\n            ], \n            \"sum\": {\n                \"bits_per_second\": 849284599.520394, \n                \"bytes\": 106168320, \n                \"end\": 38.000156, \n                \"omitted\": false, \n                \"retransmits\": 0, \n                \"seconds\": 1.000072956085205, \n                \"sender\": true, \n                \"start\": 37.000083\n            }\n        }, \n        {\n            \"streams\": [\n                {\n                    \"bits_per_second\": 849344028.7575437, \n                    \"bytes\": 106168320, \n                    \"end\": 39.000159, \n                    \"omitted\": false, \n                    \"pmtu\": 1500, \n                    \"retransmits\": 0, \n                    \"rtt\": 78389, \n                    \"rttvar\": 7, \n                    \"seconds\": 1.0000029802322388, \n                    \"sender\": true, \n                    \"snd_cwnd\": 16685304, \n                    \"snd_wnd\": -1, \n                    \"socket\": 5, \n                    \"start\": 38.000156\n                }\n            ], \n            \"sum\": {\n                \"bits_per_second\": 849344028.7575437, \n                \"bytes\": 106168320, \n                \"end\": 39.000159, \n                \"omitted\": false, \n                \"retransmits\": 0, \n                \"seconds\": 1.0000029802322388, \n                \"sender\": true, \n                \"start\": 38.000156\n            }\n        }, \n        {\n            \"streams\": [\n                {\n                    \"bits_per_second\": 849347420.625872, \n                    \"bytes\": 106168320, \n                    \"end\": 40.000158, \n                    \"omitted\": false, \n                    \"pmtu\": 1500, \n                    \"retransmits\": 0, \n                    \"rtt\": 78389, \n                    \"rttvar\": 6, \n                    \"seconds\": 0.9999989867210388, \n                    \"sender\": true, \n                    \"snd_cwnd\": 16685304, \n                    \"snd_wnd\": -1, \n                    \"socket\": 5, \n                    \"start\": 39.000159\n                }\n            ], \n            \"sum\": {\n                \"bits_per_second\": 849347420.625872, \n                \"bytes\": 106168320, \n                \"end\": 40.000158, \n                \"omitted\": false, \n                \"retransmits\": 0, \n                \"seconds\": 0.9999989867210388, \n                \"sender\": true, \n                \"start\": 39.000159\n            }\n        }, \n        {\n            \"streams\": [\n                {\n                    \"bits_per_second\": 849331271.5252018, \n                    \"bytes\": 106168320, \n                    \"end\": 41.000176, \n                    \"omitted\": false, \n                    \"pmtu\": 1500, \n                    \"retransmits\": 0, \n                    \"rtt\": 78377, \n                    \"rttvar\": 5, \n                    \"seconds\": 1.0000180006027222, \n                    \"sender\": true, \n                    \"snd_cwnd\": 16685304, \n                    \"snd_wnd\": -1, \n                    \"socket\": 5, \n                    \"start\": 40.000158\n                }\n            ], \n            \"sum\": {\n                \"bits_per_second\": 849331271.5252018, \n                \"bytes\": 106168320, \n                \"end\": 41.000176, \n                \"omitted\": false, \n                \"retransmits\": 0, \n                \"seconds\": 1.0000180006027222, \n                \"sender\": true, \n                \"start\": 40.000158\n            }\n        }, \n        {\n            \"streams\": [\n                {\n                    \"bits_per_second\": 849423010.630787, \n                    \"bytes\": 106168320, \n                    \"end\": 42.000086, \n                    \"omitted\": false, \n                    \"pmtu\": 1500, \n                    \"retransmits\": 0, \n                    \"rtt\": 78446, \n                    \"rttvar\": 103, \n                    \"seconds\": 0.999909996986389, \n                    \"sender\": true, \n                    \"snd_cwnd\": 16685304, \n                    \"snd_wnd\": -1, \n                    \"socket\": 5, \n                    \"start\": 41.000176\n                }\n            ], \n            \"sum\": {\n                \"bits_per_second\": 849423010.630787, \n                \"bytes\": 106168320, \n                \"end\": 42.000086, \n                \"omitted\": false, \n                \"retransmits\": 0, \n                \"seconds\": 0.999909996986389, \n                \"sender\": true, \n                \"start\": 41.000176\n            }\n        }, \n        {\n            \"streams\": [\n                {\n                    \"bits_per_second\": 859835753.7637128, \n                    \"bytes\": 107479040, \n                    \"end\": 43.000082, \n                    \"omitted\": false, \n                    \"pmtu\": 1500, \n                    \"retransmits\": 0, \n                    \"rtt\": 78385, \n                    \"rttvar\": 5, \n                    \"seconds\": 0.9999960064888, \n                    \"sender\": true, \n                    \"snd_cwnd\": 16685304, \n                    \"snd_wnd\": -1, \n                    \"socket\": 5, \n                    \"start\": 42.000086\n                }\n            ], \n            \"sum\": {\n                \"bits_per_second\": 859835753.7637128, \n                \"bytes\": 107479040, \n                \"end\": 43.000082, \n                \"omitted\": false, \n                \"retransmits\": 0, \n                \"seconds\": 0.9999960064888, \n                \"sender\": true, \n                \"start\": 42.000086\n            }\n        }, \n        {\n            \"streams\": [\n                {\n                    \"bits_per_second\": 849352483.1663066, \n                    \"bytes\": 106168320, \n                    \"end\": 44.000075, \n                    \"omitted\": false, \n                    \"pmtu\": 1500, \n                    \"retransmits\": 0, \n                    \"rtt\": 78377, \n                    \"rttvar\": 8, \n                    \"seconds\": 0.9999930262565613, \n                    \"sender\": true, \n                    \"snd_cwnd\": 16685304, \n                    \"snd_wnd\": -1, \n                    \"socket\": 5, \n                    \"start\": 43.000082\n                }\n            ], \n            \"sum\": {\n                \"bits_per_second\": 849352483.1663066, \n                \"bytes\": 106168320, \n                \"end\": 44.000075, \n                \"omitted\": false, \n                \"retransmits\": 0, \n                \"seconds\": 0.9999930262565613, \n                \"sender\": true, \n                \"start\": 43.000082\n            }\n        }, \n        {\n            \"streams\": [\n                {\n                    \"bits_per_second\": 849276095.8463873, \n                    \"bytes\": 106168320, \n                    \"end\": 45.000158, \n                    \"omitted\": false, \n                    \"pmtu\": 1500, \n                    \"retransmits\": 0, \n                    \"rtt\": 78382, \n                    \"rttvar\": 8, \n                    \"seconds\": 1.0000829696655273, \n                    \"sender\": true, \n                    \"snd_cwnd\": 16685304, \n                    \"snd_wnd\": -1, \n                    \"socket\": 5, \n                    \"start\": 44.000075\n                }\n            ], \n            \"sum\": {\n                \"bits_per_second\": 849276095.8463873, \n                \"bytes\": 106168320, \n                \"end\": 45.000158, \n                \"omitted\": false, \n                \"retransmits\": 0, \n                \"seconds\": 1.0000829696655273, \n                \"sender\": true, \n                \"start\": 44.000075\n            }\n        }, \n        {\n            \"streams\": [\n                {\n                    \"bits_per_second\": 849348281.2534882, \n                    \"bytes\": 106168320, \n                    \"end\": 46.000156, \n                    \"omitted\": false, \n                    \"pmtu\": 1500, \n                    \"retransmits\": 0, \n                    \"rtt\": 78388, \n                    \"rttvar\": 5, \n                    \"seconds\": 0.9999979734420776, \n                    \"sender\": true, \n                    \"snd_cwnd\": 16685304, \n                    \"snd_wnd\": -1, \n                    \"socket\": 5, \n                    \"start\": 45.000158\n                }\n            ], \n            \"sum\": {\n                \"bits_per_second\": 849348281.2534882, \n                \"bytes\": 106168320, \n                \"end\": 46.000156, \n                \"omitted\": false, \n                \"retransmits\": 0, \n                \"seconds\": 0.9999979734420776, \n                \"sender\": true, \n                \"start\": 45.000158\n            }\n        }, \n        {\n            \"streams\": [\n                {\n                    \"bits_per_second\": 849424732.1941535, \n                    \"bytes\": 106168320, \n                    \"end\": 47.000064, \n                    \"omitted\": false, \n                    \"pmtu\": 1500, \n                    \"retransmits\": 0, \n                    \"rtt\": 78388, \n                    \"rttvar\": 9, \n                    \"seconds\": 0.9999079704284668, \n                    \"sender\": true, \n                    \"snd_cwnd\": 16685304, \n                    \"snd_wnd\": -1, \n                    \"socket\": 5, \n                    \"start\": 46.000156\n                }\n            ], \n            \"sum\": {\n                \"bits_per_second\": 849424732.1941535, \n                \"bytes\": 106168320, \n                \"end\": 47.000064, \n                \"omitted\": false, \n                \"retransmits\": 0, \n                \"seconds\": 0.9999079704284668, \n                \"sender\": true, \n                \"start\": 46.000156\n            }\n        }, \n        {\n            \"streams\": [\n                {\n                    \"bits_per_second\": 859748073.2553415, \n                    \"bytes\": 107479040, \n                    \"end\": 48.000162, \n                    \"omitted\": false, \n                    \"pmtu\": 1500, \n                    \"retransmits\": 0, \n                    \"rtt\": 78384, \n                    \"rttvar\": 9, \n                    \"seconds\": 1.0000979900360107, \n                    \"sender\": true, \n                    \"snd_cwnd\": 16685304, \n                    \"snd_wnd\": -1, \n                    \"socket\": 5, \n                    \"start\": 47.000064\n                }\n            ], \n            \"sum\": {\n                \"bits_per_second\": 859748073.2553415, \n                \"bytes\": 107479040, \n                \"end\": 48.000162, \n                \"omitted\": false, \n                \"retransmits\": 0, \n                \"seconds\": 1.0000979900360107, \n                \"sender\": true, \n                \"start\": 47.000064\n            }\n        }, \n        {\n            \"streams\": [\n                {\n                    \"bits_per_second\": 849428124.7070947, \n                    \"bytes\": 106168320, \n                    \"end\": 49.000066, \n                    \"omitted\": false, \n                    \"pmtu\": 1500, \n                    \"retransmits\": 0, \n                    \"rtt\": 78381, \n                    \"rttvar\": 9, \n                    \"seconds\": 0.999903976917267, \n                    \"sender\": true, \n                    \"snd_cwnd\": 16685304, \n                    \"snd_wnd\": -1, \n                    \"socket\": 5, \n                    \"start\": 48.000162\n                }\n            ], \n            \"sum\": {\n                \"bits_per_second\": 849428124.7070947, \n                \"bytes\": 106168320, \n                \"end\": 49.000066, \n                \"omitted\": false, \n                \"retransmits\": 0, \n                \"seconds\": 0.999903976917267, \n                \"sender\": true, \n                \"start\": 48.000162\n            }\n        }, \n        {\n            \"streams\": [\n                {\n                    \"bits_per_second\": 849349091.2575437, \n                    \"bytes\": 106168320, \n                    \"end\": 50.000063, \n                    \"omitted\": false, \n                    \"pmtu\": 1500, \n                    \"retransmits\": 0, \n                    \"rtt\": 78388, \n                    \"rttvar\": 4, \n                    \"seconds\": 0.9999970197677612, \n                    \"sender\": true, \n                    \"snd_cwnd\": 16685304, \n                    \"snd_wnd\": -1, \n                    \"socket\": 5, \n                    \"start\": 49.000066\n                }\n            ], \n            \"sum\": {\n                \"bits_per_second\": 849349091.2575437, \n                \"bytes\": 106168320, \n                \"end\": 50.000063, \n                \"omitted\": false, \n                \"retransmits\": 0, \n                \"seconds\": 0.9999970197677612, \n                \"sender\": true, \n                \"start\": 49.000066\n            }\n        }, \n        {\n            \"streams\": [\n                {\n                    \"bits_per_second\": 849353343.8041824, \n                    \"bytes\": 106168320, \n                    \"end\": 51.000055, \n                    \"omitted\": false, \n                    \"pmtu\": 1500, \n                    \"retransmits\": 0, \n                    \"rtt\": 78384, \n                    \"rttvar\": 6, \n                    \"seconds\": 0.9999920129776, \n                    \"sender\": true, \n                    \"snd_cwnd\": 16685304, \n                    \"snd_wnd\": -1, \n                    \"socket\": 5, \n                    \"start\": 50.000063\n                }\n            ], \n            \"sum\": {\n                \"bits_per_second\": 849353343.8041824, \n                \"bytes\": 106168320, \n                \"end\": 51.000055, \n                \"omitted\": false, \n                \"retransmits\": 0, \n                \"seconds\": 0.9999920129776, \n                \"sender\": true, \n                \"start\": 50.000063\n            }\n        }, \n        {\n            \"streams\": [\n                {\n                    \"bits_per_second\": 849309200.393383, \n                    \"bytes\": 106168320, \n                    \"end\": 52.000099, \n                    \"omitted\": false, \n                    \"pmtu\": 1500, \n                    \"retransmits\": 0, \n                    \"rtt\": 78383, \n                    \"rttvar\": 4, \n                    \"seconds\": 1.0000439882278442, \n                    \"sender\": true, \n                    \"snd_cwnd\": 16685304, \n                    \"snd_wnd\": -1, \n                    \"socket\": 5, \n                    \"start\": 51.000055\n                }\n            ], \n            \"sum\": {\n                \"bits_per_second\": 849309200.393383, \n                \"bytes\": 106168320, \n                \"end\": 52.000099, \n                \"omitted\": false, \n                \"retransmits\": 0, \n                \"seconds\": 1.0000439882278442, \n                \"sender\": true, \n                \"start\": 51.000055\n            }\n        }, \n        {\n            \"streams\": [\n                {\n                    \"bits_per_second\": 849297254.1124495, \n                    \"bytes\": 106168320, \n                    \"end\": 53.000157, \n                    \"omitted\": false, \n                    \"pmtu\": 1500, \n                    \"retransmits\": 0, \n                    \"rtt\": 78382, \n                    \"rttvar\": 6, \n                    \"seconds\": 1.0000580549240112, \n                    \"sender\": true, \n                    \"snd_cwnd\": 16685304, \n                    \"snd_wnd\": -1, \n                    \"socket\": 5, \n                    \"start\": 52.000099\n                }\n            ], \n            \"sum\": {\n                \"bits_per_second\": 849297254.1124495, \n                \"bytes\": 106168320, \n                \"end\": 53.000157, \n                \"omitted\": false, \n                \"retransmits\": 0, \n                \"seconds\": 1.0000580549240112, \n                \"sender\": true, \n                \"start\": 52.000099\n            }\n        }, \n        {\n            \"streams\": [\n                {\n                    \"bits_per_second\": 859896797.334681, \n                    \"bytes\": 107479040, \n                    \"end\": 54.000082, \n                    \"omitted\": false, \n                    \"pmtu\": 1500, \n                    \"retransmits\": 0, \n                    \"rtt\": 78385, \n                    \"rttvar\": 8, \n                    \"seconds\": 0.9999250173568726, \n                    \"sender\": true, \n                    \"snd_cwnd\": 16685304, \n                    \"snd_wnd\": -1, \n                    \"socket\": 5, \n                    \"start\": 53.000157\n                }\n            ], \n            \"sum\": {\n                \"bits_per_second\": 859896797.334681, \n                \"bytes\": 107479040, \n                \"end\": 54.000082, \n                \"omitted\": false, \n                \"retransmits\": 0, \n                \"seconds\": 0.9999250173568726, \n                \"sender\": true, \n                \"start\": 53.000157\n            }\n        }, \n        {\n            \"streams\": [\n                {\n                    \"bits_per_second\": 849282878.5250053, \n                    \"bytes\": 106168320, \n                    \"end\": 55.000157, \n                    \"omitted\": false, \n                    \"pmtu\": 1500, \n                    \"retransmits\": 0, \n                    \"rtt\": 78389, \n                    \"rttvar\": 12, \n                    \"seconds\": 1.0000749826431274, \n                    \"sender\": true, \n                    \"snd_cwnd\": 16685304, \n                    \"snd_wnd\": -1, \n                    \"socket\": 5, \n                    \"start\": 54.000082\n                }\n            ], \n            \"sum\": {\n                \"bits_per_second\": 849282878.5250053, \n                \"bytes\": 106168320, \n                \"end\": 55.000157, \n                \"omitted\": false, \n                \"retransmits\": 0, \n                \"seconds\": 1.0000749826431274, \n                \"sender\": true, \n                \"start\": 54.000082\n            }\n        }, \n        {\n            \"streams\": [\n                {\n                    \"bits_per_second\": 849404327.0536737, \n                    \"bytes\": 106168320, \n                    \"end\": 56.000089, \n                    \"omitted\": false, \n                    \"pmtu\": 1500, \n                    \"retransmits\": 0, \n                    \"rtt\": 78389, \n                    \"rttvar\": 15, \n                    \"seconds\": 0.9999319911003113, \n                    \"sender\": true, \n                    \"snd_cwnd\": 16685304, \n                    \"snd_wnd\": -1, \n                    \"socket\": 5, \n                    \"start\": 55.000157\n                }\n            ], \n            \"sum\": {\n                \"bits_per_second\": 849404327.0536737, \n                \"bytes\": 106168320, \n                \"end\": 56.000089, \n                \"omitted\": false, \n                \"retransmits\": 0, \n                \"seconds\": 0.9999319911003113, \n                \"sender\": true, \n                \"start\": 55.000157\n            }\n        }, \n        {\n            \"streams\": [\n                {\n                    \"bits_per_second\": 849293913.2635096, \n                    \"bytes\": 106168320, \n                    \"end\": 57.000151, \n                    \"omitted\": false, \n                    \"pmtu\": 1500, \n                    \"retransmits\": 0, \n                    \"rtt\": 78382, \n                    \"rttvar\": 6, \n                    \"seconds\": 1.0000619888305664, \n                    \"sender\": true, \n                    \"snd_cwnd\": 16685304, \n                    \"snd_wnd\": -1, \n                    \"socket\": 5, \n                    \"start\": 56.000089\n                }\n            ], \n            \"sum\": {\n                \"bits_per_second\": 849293913.2635096, \n                \"bytes\": 106168320, \n                \"end\": 57.000151, \n                \"omitted\": false, \n                \"retransmits\": 0, \n                \"seconds\": 1.0000619888305664, \n                \"sender\": true, \n                \"start\": 56.000089\n            }\n        }, \n        {\n            \"streams\": [\n                {\n                    \"bits_per_second\": 849341497.5301746, \n                    \"bytes\": 106168320, \n                    \"end\": 58.000157, \n                    \"omitted\": false, \n                    \"pmtu\": 1500, \n                    \"retransmits\": 0, \n                    \"rtt\": 78383, \n                    \"rttvar\": 5, \n                    \"seconds\": 1.0000059604644775, \n                    \"sender\": true, \n                    \"snd_cwnd\": 16685304, \n                    \"snd_wnd\": -1, \n                    \"socket\": 5, \n                    \"start\": 57.000151\n                }\n            ], \n            \"sum\": {\n                \"bits_per_second\": 849341497.5301746, \n                \"bytes\": 106168320, \n                \"end\": 58.000157, \n                \"omitted\": false, \n                \"retransmits\": 0, \n                \"seconds\": 1.0000059604644775, \n                \"sender\": true, \n                \"start\": 57.000151\n            }\n        }, \n        {\n            \"streams\": [\n                {\n                    \"bits_per_second\": 849365241.0358728, \n                    \"bytes\": 106168320, \n                    \"end\": 59.000135, \n                    \"omitted\": false, \n                    \"pmtu\": 1500, \n                    \"retransmits\": 0, \n                    \"rtt\": 78387, \n                    \"rttvar\": 8, \n                    \"seconds\": 0.999978005886078, \n                    \"sender\": true, \n                    \"snd_cwnd\": 16685304, \n                    \"snd_wnd\": -1, \n                    \"socket\": 5, \n                    \"start\": 58.000157\n                }\n            ], \n            \"sum\": {\n                \"bits_per_second\": 849365241.0358728, \n                \"bytes\": 106168320, \n                \"end\": 59.000135, \n                \"omitted\": false, \n                \"retransmits\": 0, \n                \"seconds\": 0.999978005886078, \n                \"sender\": true, \n                \"start\": 58.000157\n            }\n        }, \n        {\n            \"streams\": [\n                {\n                    \"bits_per_second\": 859886494.663118, \n                    \"bytes\": 107479040, \n                    \"end\": 60.000072, \n                    \"omitted\": false, \n                    \"pmtu\": 1500, \n                    \"retransmits\": 0, \n                    \"rtt\": 78384, \n                    \"rttvar\": 7, \n                    \"seconds\": 0.9999369978904724, \n                    \"sender\": true, \n                    \"snd_cwnd\": 16685304, \n                    \"snd_wnd\": -1, \n                    \"socket\": 5, \n                    \"start\": 59.000135\n                }\n            ], \n            \"sum\": {\n                \"bits_per_second\": 859886494.663118, \n                \"bytes\": 107479040, \n                \"end\": 60.000072, \n                \"omitted\": false, \n                \"retransmits\": 0, \n                \"seconds\": 0.9999369978904724, \n                \"sender\": true, \n                \"start\": 59.000135\n            }\n        }\n    ], \n    \"start\": {\n        \"connected\": [\n            {\n                \"local_host\": \"10.0.0.1\", \n                \"local_port\": 49379, \n                \"remote_host\": \"10.0.0.2\", \n                \"remote_port\": 5201, \n                \"socket\": 5\n            }\n        ], \n        \"connecting_to\": {\n            \"host\": \"10.0.0.2\", \n            \"port\": 5201\n        }, \n        \"cookie\": \"f4bzt52sxwhf4md6frn7x4xopvhivsb2xwf2\", \n        \"fq_rate\": 0, \n        \"rcvbuf_actual\": 87380, \n        \"sndbuf_actual\": 87380, \n        \"sock_bufsize\": 0, \n        \"system_info\": \"REDACTED\", \n        \"target_bitrate\": 0, \n        \"tcp_mss_default\": 1448, \n        \"test_start\": {\n            \"bidir\": 0, \n            \"blksize\": 131072, \n            \"blocks\": 0, \n            \"bytes\": 0, \n            \"duration\": 60, \n            \"fqrate\": 0, \n            \"num_streams\": 1, \n            \"omit\": 0, \n            \"protocol\": \"TCP\", \n            \"reverse\": 0, \n            \"target_bitrate\": 0, \n            \"tos\": 0\n        }, \n        \"timestamp\": {\n            \"time\": \"Tue, 16 Apr 2024 23:01:47 GMT\", \n            \"timesecs\": 1713308507\n        }, \n        \"version\": \"iperf 3.14\"\n    }\n}\nParticipant 1:\n/usr/bin/iperf3 -s -1 --idle-timeout 60 --json -p 5201 -B 10.0.0.2 --authorized-users-path /var/run/pscheduler-server/runner/tmp/tmp503ebe54/tmpqbnmskvs/credentials --rsa-private-key-path /var/run/pscheduler-server/runner/tmp/tmp503ebe54/tmpqbnmskvs/private-key\n\n{\n    \"end\": {\n        \"cpu_utilization_percent\": {\n            \"host_system\": 4.849106379257348, \n            \"host_total\": 5.2662093435132, \n            \"host_user\": 0.4171012997655349, \n            \"remote_system\": 0, \n            \"remote_total\": 0, \n            \"remote_user\": 0\n        }, \n        \"receiver_tcp_congestion\": \"htcp\", \n        \"streams\": [\n            {\n                \"receiver\": {\n                    \"bits_per_second\": 851119043.423738, \n                    \"bytes\": 6391736984, \n                    \"end\": 60.07843, \n                    \"seconds\": 60.07843, \n                    \"sender\": false, \n                    \"socket\": 5, \n                    \"start\": 0\n                }, \n                \"sender\": {\n                    \"bits_per_second\": 0, \n                    \"bytes\": 0, \n                    \"end\": 60.07843, \n                    \"seconds\": 60.07843, \n                    \"sender\": false, \n                    \"socket\": 5, \n                    \"start\": 0\n                }\n            }\n        ], \n        \"sum_received\": {\n            \"bits_per_second\": 851119043.423738, \n            \"bytes\": 6391736984, \n            \"end\": 60.07843, \n            \"seconds\": 60.07843, \n            \"sender\": false, \n            \"start\": 0\n        }, \n        \"sum_sent\": {\n            \"bits_per_second\": 0, \n            \"bytes\": 0, \n            \"end\": 60.07843, \n            \"seconds\": 60.07843, \n            \"sender\": false, \n            \"start\": 0\n        }\n    }, \n    \"intervals\": [\n        {\n            \"streams\": [\n                {\n                    \"bits_per_second\": 846472081.2860116, \n                    \"bytes\": 105816944, \n                    \"end\": 1.000075, \n                    \"omitted\": false, \n                    \"seconds\": 1.0000749826431274, \n                    \"sender\": false, \n                    \"socket\": 5, \n                    \"start\": 0\n                }\n            ], \n            \"sum\": {\n                \"bits_per_second\": 846472081.2860116, \n                \"bytes\": 105816944, \n                \"end\": 1.000075, \n                \"omitted\": false, \n                \"seconds\": 1.0000749826431274, \n                \"sender\": false, \n                \"start\": 0\n            }\n        }, \n        {\n            \"streams\": [\n                {\n                    \"bits_per_second\": 851258764.1480098, \n                    \"bytes\": 106406280, \n                    \"end\": 2.000065, \n                    \"omitted\": false, \n                    \"seconds\": 0.9999899864196777, \n                    \"sender\": false, \n                    \"socket\": 5, \n                    \"start\": 1.000075\n                }\n            ], \n            \"sum\": {\n                \"bits_per_second\": 851258764.1480098, \n                \"bytes\": 106406280, \n                \"end\": 2.000065, \n                \"omitted\": false, \n                \"seconds\": 0.9999899864196777, \n                \"sender\": false, \n                \"start\": 1.000075\n            }\n        }, \n        {\n            \"streams\": [\n                {\n                    \"bits_per_second\": 851256176.442175, \n                    \"bytes\": 106406280, \n                    \"end\": 3.000058, \n                    \"omitted\": false, \n                    \"seconds\": 0.9999930262565613, \n                    \"sender\": false, \n                    \"socket\": 5, \n                    \"start\": 2.000065\n                }\n            ], \n            \"sum\": {\n                \"bits_per_second\": 851256176.442175, \n                \"bytes\": 106406280, \n                \"end\": 3.000058, \n                \"omitted\": false, \n                \"seconds\": 0.9999930262565613, \n                \"sender\": false, \n                \"start\": 2.000065\n            }\n        }, \n        {\n            \"streams\": [\n                {\n                    \"bits_per_second\": 851247703.084152, \n                    \"bytes\": 106406280, \n                    \"end\": 4.000061, \n                    \"omitted\": false, \n                    \"seconds\": 1.0000029802322388, \n                    \"sender\": false, \n                    \"socket\": 5, \n                    \"start\": 3.000058\n                }\n            ], \n            \"sum\": {\n                \"bits_per_second\": 851247703.084152, \n                \"bytes\": 106406280, \n                \"end\": 4.000061, \n                \"omitted\": false, \n                \"seconds\": 1.0000029802322388, \n                \"sender\": false, \n                \"start\": 3.000058\n            }\n        }, \n        {\n            \"streams\": [\n                {\n                    \"bits_per_second\": 851251102.554833, \n                    \"bytes\": 106406280, \n                    \"end\": 5.00006, \n                    \"omitted\": false, \n                    \"seconds\": 0.9999989867210388, \n                    \"sender\": false, \n                    \"socket\": 5, \n                    \"start\": 4.000061\n                }\n            ], \n            \"sum\": {\n                \"bits_per_second\": 851251102.554833, \n                \"bytes\": 106406280, \n                \"end\": 5.00006, \n                \"omitted\": false, \n                \"seconds\": 0.9999989867210388, \n                \"sender\": false, \n                \"start\": 4.000061\n            }\n        }, \n        {\n            \"streams\": [\n                {\n                    \"bits_per_second\": 851269825.499325, \n                    \"bytes\": 106406280, \n                    \"end\": 6.000037, \n                    \"omitted\": false, \n                    \"seconds\": 0.9999769926071167, \n                    \"sender\": false, \n                    \"socket\": 5, \n                    \"start\": 5.00006\n                }\n            ], \n            \"sum\": {\n                \"bits_per_second\": 851269825.499325, \n                \"bytes\": 106406280, \n                \"end\": 6.000037, \n                \"omitted\": false, \n                \"seconds\": 0.9999769926071167, \n                \"sender\": false, \n                \"start\": 5.00006\n            }\n        }, \n        {\n            \"streams\": [\n                {\n                    \"bits_per_second\": 851205085.1587086, \n                    \"bytes\": 106406280, \n                    \"end\": 7.00009, \n                    \"omitted\": false, \n                    \"seconds\": 1.00005304813385, \n                    \"sender\": false, \n                    \"socket\": 5, \n                    \"start\": 6.000037\n                }\n            ], \n            \"sum\": {\n                \"bits_per_second\": 851205085.1587086, \n                \"bytes\": 106406280, \n                \"end\": 7.00009, \n                \"omitted\": false, \n                \"seconds\": 1.00005304813385, \n                \"sender\": false, \n                \"start\": 6.000037\n            }\n        }, \n        {\n            \"streams\": [\n                {\n                    \"bits_per_second\": 850735754.8455304, \n                    \"bytes\": 106341120, \n                    \"end\": 8.000082, \n                    \"omitted\": false, \n                    \"seconds\": 0.9999920129776, \n                    \"sender\": false, \n                    \"socket\": 5, \n                    \"start\": 7.00009\n                }\n            ], \n            \"sum\": {\n                \"bits_per_second\": 850735754.8455304, \n                \"bytes\": 106341120, \n                \"end\": 8.000082, \n                \"omitted\": false, \n                \"seconds\": 0.9999920129776, \n                \"sender\": false, \n                \"start\": 7.00009\n            }\n        }, \n        {\n            \"streams\": [\n                {\n                    \"bits_per_second\": 851251102.554833, \n                    \"bytes\": 106406280, \n                    \"end\": 9.000081, \n                    \"omitted\": false, \n                    \"seconds\": 0.9999989867210388, \n                    \"sender\": false, \n                    \"socket\": 5, \n                    \"start\": 8.000082\n                }\n            ], \n            \"sum\": {\n                \"bits_per_second\": 851251102.554833, \n                \"bytes\": 106406280, \n                \"end\": 9.000081, \n                \"omitted\": false, \n                \"seconds\": 0.9999989867210388, \n                \"sender\": false, \n                \"start\": 8.000082\n            }\n        }, \n        {\n            \"streams\": [\n                {\n                    \"bits_per_second\": 851250240, \n                    \"bytes\": 106406280, \n                    \"end\": 10.000081, \n                    \"omitted\": false, \n                    \"seconds\": 1, \n                    \"sender\": false, \n                    \"socket\": 5, \n                    \"start\": 9.000081\n                }\n            ], \n            \"sum\": {\n                \"bits_per_second\": 851250240, \n                \"bytes\": 106406280, \n                \"end\": 10.000081, \n                \"omitted\": false, \n                \"seconds\": 1, \n                \"sender\": false, \n                \"start\": 9.000081\n            }\n        }, \n        {\n            \"streams\": [\n                {\n                    \"bits_per_second\": 851249428.1852835, \n                    \"bytes\": 106406280, \n                    \"end\": 11.000082, \n                    \"omitted\": false, \n                    \"seconds\": 1.0000009536743164, \n                    \"sender\": false, \n                    \"socket\": 5, \n                    \"start\": 10.000081\n                }\n            ], \n            \"sum\": {\n                \"bits_per_second\": 851249428.1852835, \n                \"bytes\": 106406280, \n                \"end\": 11.000082, \n                \"omitted\": false, \n                \"seconds\": 1.0000009536743164, \n                \"sender\": false, \n                \"start\": 10.000081\n            }\n        }, \n        {\n            \"streams\": [\n                {\n                    \"bits_per_second\": 851251102.554833, \n                    \"bytes\": 106406280, \n                    \"end\": 12.000081, \n                    \"omitted\": false, \n                    \"seconds\": 0.9999989867210388, \n                    \"sender\": false, \n                    \"socket\": 5, \n                    \"start\": 11.000082\n                }\n            ], \n            \"sum\": {\n                \"bits_per_second\": 851251102.554833, \n                \"bytes\": 106406280, \n                \"end\": 12.000081, \n                \"omitted\": false, \n                \"seconds\": 0.9999989867210388, \n                \"sender\": false, \n                \"start\": 11.000082\n            }\n        }, \n        {\n            \"streams\": [\n                {\n                    \"bits_per_second\": 851267288.4667375, \n                    \"bytes\": 106406280, \n                    \"end\": 13.000061, \n                    \"omitted\": false, \n                    \"seconds\": 0.9999799728393555, \n                    \"sender\": false, \n                    \"socket\": 5, \n                    \"start\": 12.000081\n                }\n            ], \n            \"sum\": {\n                \"bits_per_second\": 851267288.4667375, \n                \"bytes\": 106406280, \n                \"end\": 13.000061, \n                \"omitted\": false, \n                \"seconds\": 0.9999799728393555, \n                \"sender\": false, \n                \"start\": 12.000081\n            }\n        }, \n        {\n            \"streams\": [\n                {\n                    \"bits_per_second\": 851242629.2978195, \n                    \"bytes\": 106406280, \n                    \"end\": 14.00007, \n                    \"omitted\": false, \n                    \"seconds\": 1.0000089406967163, \n                    \"sender\": false, \n                    \"socket\": 5, \n                    \"start\": 13.000061\n                }\n            ], \n            \"sum\": {\n                \"bits_per_second\": 851242629.2978195, \n                \"bytes\": 106406280, \n                \"end\": 14.00007, \n                \"omitted\": false, \n                \"seconds\": 1.0000089406967163, \n                \"sender\": false, \n                \"start\": 13.000061\n            }\n        }, \n        {\n            \"streams\": [\n                {\n                    \"bits_per_second\": 851257901.5776502, \n                    \"bytes\": 106406280, \n                    \"end\": 15.000061, \n                    \"omitted\": false, \n                    \"seconds\": 0.999990999698639, \n                    \"sender\": false, \n                    \"socket\": 5, \n                    \"start\": 14.00007\n                }\n            ], \n            \"sum\": {\n                \"bits_per_second\": 851257901.5776502, \n                \"bytes\": 106406280, \n                \"end\": 15.000061, \n                \"omitted\": false, \n                \"seconds\": 0.999990999698639, \n                \"sender\": false, \n                \"start\": 14.00007\n            }\n        }, \n        {\n            \"streams\": [\n                {\n                    \"bits_per_second\": 851250240, \n                    \"bytes\": 106406280, \n                    \"end\": 16.000061, \n                    \"omitted\": false, \n                    \"seconds\": 1, \n                    \"sender\": false, \n                    \"socket\": 5, \n                    \"start\": 15.000061\n                }\n            ], \n            \"sum\": {\n                \"bits_per_second\": 851250240, \n                \"bytes\": 106406280, \n                \"end\": 16.000061, \n                \"omitted\": false, \n                \"seconds\": 1, \n                \"sender\": false, \n                \"start\": 15.000061\n            }\n        }, \n        {\n            \"streams\": [\n                {\n                    \"bits_per_second\": 851278350.039587, \n                    \"bytes\": 106406280, \n                    \"end\": 17.000028, \n                    \"omitted\": false, \n                    \"seconds\": 0.9999669790267944, \n                    \"sender\": false, \n                    \"socket\": 5, \n                    \"start\": 16.000061\n                }\n            ], \n            \"sum\": {\n                \"bits_per_second\": 851278350.039587, \n                \"bytes\": 106406280, \n                \"end\": 17.000028, \n                \"omitted\": false, \n                \"seconds\": 0.9999669790267944, \n                \"sender\": false, \n                \"start\": 16.000061\n            }\n        }, \n        {\n            \"streams\": [\n                {\n                    \"bits_per_second\": 851203461.703071, \n                    \"bytes\": 106406280, \n                    \"end\": 18.000083, \n                    \"omitted\": false, \n                    \"seconds\": 1.000054955482483, \n                    \"sender\": false, \n                    \"socket\": 5, \n                    \"start\": 17.000028\n                }\n            ], \n            \"sum\": {\n                \"bits_per_second\": 851203461.703071, \n                \"bytes\": 106406280, \n                \"end\": 18.000083, \n                \"omitted\": false, \n                \"seconds\": 1.000054955482483, \n                \"sender\": false, \n                \"start\": 17.000028\n            }\n        }, \n        {\n            \"streams\": [\n                {\n                    \"bits_per_second\": 850730684.0550076, \n                    \"bytes\": 106341120, \n                    \"end\": 19.000081, \n                    \"omitted\": false, \n                    \"seconds\": 0.9999979734420776, \n                    \"sender\": false, \n                    \"socket\": 5, \n                    \"start\": 18.000083\n                }\n            ], \n            \"sum\": {\n                \"bits_per_second\": 850730684.0550076, \n                \"bytes\": 106341120, \n                \"end\": 19.000081, \n                \"omitted\": false, \n                \"seconds\": 0.9999979734420776, \n                \"sender\": false, \n                \"start\": 18.000083\n            }\n        }, \n        {\n            \"streams\": [\n                {\n                    \"bits_per_second\": 851254502.0526655, \n                    \"bytes\": 106406280, \n                    \"end\": 20.000076, \n                    \"omitted\": false, \n                    \"seconds\": 0.999994993209839, \n                    \"sender\": false, \n                    \"socket\": 5, \n                    \"start\": 19.000081\n                }\n            ], \n            \"sum\": {\n                \"bits_per_second\": 851254502.0526655, \n                \"bytes\": 106406280, \n                \"end\": 20.000076, \n                \"omitted\": false, \n                \"seconds\": 0.999994993209839, \n                \"sender\": false, \n                \"start\": 19.000081\n            }\n        }, \n        {\n            \"streams\": [\n                {\n                    \"bits_per_second\": 851263026.2860336, \n                    \"bytes\": 106406280, \n                    \"end\": 21.000061, \n                    \"omitted\": false, \n                    \"seconds\": 0.9999849796295166, \n                    \"sender\": false, \n                    \"socket\": 5, \n                    \"start\": 20.000076\n                }\n            ], \n            \"sum\": {\n                \"bits_per_second\": 851263026.2860336, \n                \"bytes\": 106406280, \n                \"end\": 21.000061, \n                \"omitted\": false, \n                \"seconds\": 0.9999849796295166, \n                \"sender\": false, \n                \"start\": 20.000076\n            }\n        }, \n        {\n            \"streams\": [\n                {\n                    \"bits_per_second\": 851234105.4729402, \n                    \"bytes\": 106406280, \n                    \"end\": 22.00008, \n                    \"omitted\": false, \n                    \"seconds\": 1.0000189542770386, \n                    \"sender\": false, \n                    \"socket\": 5, \n                    \"start\": 21.000061\n                }\n            ], \n            \"sum\": {\n                \"bits_per_second\": 851234105.4729402, \n                \"bytes\": 106406280, \n                \"end\": 22.00008, \n                \"omitted\": false, \n                \"seconds\": 1.0000189542770386, \n                \"sender\": false, \n                \"start\": 21.000061\n            }\n        }, \n        {\n            \"streams\": [\n                {\n                    \"bits_per_second\": 851263026.2860336, \n                    \"bytes\": 106406280, \n                    \"end\": 23.000065, \n                    \"omitted\": false, \n                    \"seconds\": 0.9999849796295166, \n                    \"sender\": false, \n                    \"socket\": 5, \n                    \"start\": 22.00008\n                }\n            ], \n            \"sum\": {\n                \"bits_per_second\": 851263026.2860336, \n                \"bytes\": 106406280, \n                \"end\": 23.000065, \n                \"omitted\": false, \n                \"seconds\": 0.9999849796295166, \n                \"sender\": false, \n                \"start\": 22.00008\n            }\n        }, \n        {\n            \"streams\": [\n                {\n                    \"bits_per_second\": 851253639.4909433, \n                    \"bytes\": 106406280, \n                    \"end\": 24.000061, \n                    \"omitted\": false, \n                    \"seconds\": 0.9999960064888, \n                    \"sender\": false, \n                    \"socket\": 5, \n                    \"start\": 23.000065\n                }\n            ], \n            \"sum\": {\n                \"bits_per_second\": 851253639.4909433, \n                \"bytes\": 106406280, \n                \"end\": 24.000061, \n                \"omitted\": false, \n                \"seconds\": 0.9999960064888, \n                \"sender\": false, \n                \"start\": 23.000065\n            }\n        }, \n        {\n            \"streams\": [\n                {\n                    \"bits_per_second\": 851249428.1852835, \n                    \"bytes\": 106406280, \n                    \"end\": 25.000062, \n                    \"omitted\": false, \n                    \"seconds\": 1.0000009536743164, \n                    \"sender\": false, \n                    \"socket\": 5, \n                    \"start\": 24.000061\n                }\n            ], \n            \"sum\": {\n                \"bits_per_second\": 851249428.1852835, \n                \"bytes\": 106406280, \n                \"end\": 25.000062, \n                \"omitted\": false, \n                \"seconds\": 1.0000009536743164, \n                \"sender\": false, \n                \"start\": 24.000061\n            }\n        }, \n        {\n            \"streams\": [\n                {\n                    \"bits_per_second\": 851250240, \n                    \"bytes\": 106406280, \n                    \"end\": 26.000062, \n                    \"omitted\": false, \n                    \"seconds\": 1, \n                    \"sender\": false, \n                    \"socket\": 5, \n                    \"start\": 25.000062\n                }\n            ], \n            \"sum\": {\n                \"bits_per_second\": 851250240, \n                \"bytes\": 106406280, \n                \"end\": 26.000062, \n                \"omitted\": false, \n                \"seconds\": 1, \n                \"sender\": false, \n                \"start\": 25.000062\n            }\n        }, \n        {\n            \"streams\": [\n                {\n                    \"bits_per_second\": 851251965.111414, \n                    \"bytes\": 106406280, \n                    \"end\": 27.00006, \n                    \"omitted\": false, \n                    \"seconds\": 0.9999979734420776, \n                    \"sender\": false, \n                    \"socket\": 5, \n                    \"start\": 26.000062\n                }\n            ], \n            \"sum\": {\n                \"bits_per_second\": 851251965.111414, \n                \"bytes\": 106406280, \n                \"end\": 27.00006, \n                \"omitted\": false, \n                \"seconds\": 0.9999979734420776, \n                \"sender\": false, \n                \"start\": 26.000062\n            }\n        }, \n        {\n            \"streams\": [\n                {\n                    \"bits_per_second\": 851259626.7201176, \n                    \"bytes\": 106406280, \n                    \"end\": 28.000049, \n                    \"omitted\": false, \n                    \"seconds\": 0.9999889731407166, \n                    \"sender\": false, \n                    \"socket\": 5, \n                    \"start\": 27.00006\n                }\n            ], \n            \"sum\": {\n                \"bits_per_second\": 851259626.7201176, \n                \"bytes\": 106406280, \n                \"end\": 28.000049, \n                \"omitted\": false, \n                \"seconds\": 0.9999889731407166, \n                \"sender\": false, \n                \"start\": 27.00006\n            }\n        }, \n        {\n            \"streams\": [\n                {\n                    \"bits_per_second\": 851213608.4024056, \n                    \"bytes\": 106406280, \n                    \"end\": 29.000092, \n                    \"omitted\": false, \n                    \"seconds\": 1.0000430345535278, \n                    \"sender\": false, \n                    \"socket\": 5, \n                    \"start\": 28.000049\n                }\n            ], \n            \"sum\": {\n                \"bits_per_second\": 851213608.4024056, \n                \"bytes\": 106406280, \n                \"end\": 29.000092, \n                \"omitted\": false, \n                \"seconds\": 1.0000430345535278, \n                \"sender\": false, \n                \"start\": 28.000049\n            }\n        }, \n        {\n            \"streams\": [\n                {\n                    \"bits_per_second\": 850742549.7996036, \n                    \"bytes\": 106341120, \n                    \"end\": 30.000076, \n                    \"omitted\": false, \n                    \"seconds\": 0.9999840259552002, \n                    \"sender\": false, \n                    \"socket\": 5, \n                    \"start\": 29.000092\n                }\n            ], \n            \"sum\": {\n                \"bits_per_second\": 850742549.7996036, \n                \"bytes\": 106341120, \n                \"end\": 30.000076, \n                \"omitted\": false, \n                \"seconds\": 0.9999840259552002, \n                \"sender\": false, \n                \"start\": 29.000092\n            }\n        }, \n        {\n            \"streams\": [\n                {\n                    \"bits_per_second\": 851263026.2860336, \n                    \"bytes\": 106406280, \n                    \"end\": 31.000061, \n                    \"omitted\": false, \n                    \"seconds\": 0.9999849796295166, \n                    \"sender\": false, \n                    \"socket\": 5, \n                    \"start\": 30.000076\n                }\n            ], \n            \"sum\": {\n                \"bits_per_second\": 851263026.2860336, \n                \"bytes\": 106406280, \n                \"end\": 31.000061, \n                \"omitted\": false, \n                \"seconds\": 0.9999849796295166, \n                \"sender\": false, \n                \"start\": 30.000076\n            }\n        }, \n        {\n            \"streams\": [\n                {\n                    \"bits_per_second\": 851231467.1807876, \n                    \"bytes\": 106406280, \n                    \"end\": 32.000083, \n                    \"omitted\": false, \n                    \"seconds\": 1.000022053718567, \n                    \"sender\": false, \n                    \"socket\": 5, \n                    \"start\": 31.000061\n                }\n            ], \n            \"sum\": {\n                \"bits_per_second\": 851231467.1807876, \n                \"bytes\": 106406280, \n                \"end\": 32.000083, \n                \"omitted\": false, \n                \"seconds\": 1.000022053718567, \n                \"sender\": false, \n                \"start\": 31.000061\n            }\n        }, \n        {\n            \"streams\": [\n                {\n                    \"bits_per_second\": 851265563.293216, \n                    \"bytes\": 106406280, \n                    \"end\": 33.000065, \n                    \"omitted\": false, \n                    \"seconds\": 0.9999819993972778, \n                    \"sender\": false, \n                    \"socket\": 5, \n                    \"start\": 32.000083\n                }\n            ], \n            \"sum\": {\n                \"bits_per_second\": 851265563.293216, \n                \"bytes\": 106406280, \n                \"end\": 33.000065, \n                \"omitted\": false, \n                \"seconds\": 0.9999819993972778, \n                \"sender\": false, \n                \"start\": 32.000083\n            }\n        }, \n        {\n            \"streams\": [\n                {\n                    \"bits_per_second\": 851251102.554833, \n                    \"bytes\": 106406280, \n                    \"end\": 34.000064, \n                    \"omitted\": false, \n                    \"seconds\": 0.9999989867210388, \n                    \"sender\": false, \n                    \"socket\": 5, \n                    \"start\": 33.000065\n                }\n            ], \n            \"sum\": {\n                \"bits_per_second\": 851251102.554833, \n                \"bytes\": 106406280, \n                \"end\": 34.000064, \n                \"omitted\": false, \n                \"seconds\": 0.9999989867210388, \n                \"sender\": false, \n                \"start\": 33.000065\n            }\n        }, \n        {\n            \"streams\": [\n                {\n                    \"bits_per_second\": 851252776.930969, \n                    \"bytes\": 106406280, \n                    \"end\": 35.000061, \n                    \"omitted\": false, \n                    \"seconds\": 0.9999970197677612, \n                    \"sender\": false, \n                    \"socket\": 5, \n                    \"start\": 34.000064\n                }\n            ], \n            \"sum\": {\n                \"bits_per_second\": 851252776.930969, \n                \"bytes\": 106406280, \n                \"end\": 35.000061, \n                \"omitted\": false, \n                \"seconds\": 0.9999970197677612, \n                \"sender\": false, \n                \"start\": 34.000064\n            }\n        }, \n        {\n            \"streams\": [\n                {\n                    \"bits_per_second\": 851250240, \n                    \"bytes\": 106406280, \n                    \"end\": 36.000061, \n                    \"omitted\": false, \n                    \"seconds\": 1, \n                    \"sender\": false, \n                    \"socket\": 5, \n                    \"start\": 35.000061\n                }\n            ], \n            \"sum\": {\n                \"bits_per_second\": 851250240, \n                \"bytes\": 106406280, \n                \"end\": 36.000061, \n                \"omitted\": false, \n                \"seconds\": 1, \n                \"sender\": false, \n                \"start\": 35.000061\n            }\n        }, \n        {\n            \"streams\": [\n                {\n                    \"bits_per_second\": 851251102.554833, \n                    \"bytes\": 106406280, \n                    \"end\": 37.00006, \n                    \"omitted\": false, \n                    \"seconds\": 0.9999989867210388, \n                    \"sender\": false, \n                    \"socket\": 5, \n                    \"start\": 36.000061\n                }\n            ], \n            \"sum\": {\n                \"bits_per_second\": 851251102.554833, \n                \"bytes\": 106406280, \n                \"end\": 37.00006, \n                \"omitted\": false, \n                \"seconds\": 0.9999989867210388, \n                \"sender\": false, \n                \"start\": 36.000061\n            }\n        }, \n        {\n            \"streams\": [\n                {\n                    \"bits_per_second\": 851249428.1852835, \n                    \"bytes\": 106406280, \n                    \"end\": 38.000061, \n                    \"omitted\": false, \n                    \"seconds\": 1.0000009536743164, \n                    \"sender\": false, \n                    \"socket\": 5, \n                    \"start\": 37.00006\n                }\n            ], \n            \"sum\": {\n                \"bits_per_second\": 851249428.1852835, \n                \"bytes\": 106406280, \n                \"end\": 38.000061, \n                \"omitted\": false, \n                \"seconds\": 1.0000009536743164, \n                \"sender\": false, \n                \"start\": 37.00006\n            }\n        }, \n        {\n            \"streams\": [\n                {\n                    \"bits_per_second\": 851274087.7481152, \n                    \"bytes\": 106406280, \n                    \"end\": 39.000033, \n                    \"omitted\": false, \n                    \"seconds\": 0.9999719858169556, \n                    \"sender\": false, \n                    \"socket\": 5, \n                    \"start\": 38.000061\n                }\n            ], \n            \"sum\": {\n                \"bits_per_second\": 851274087.7481152, \n                \"bytes\": 106406280, \n                \"end\": 39.000033, \n                \"omitted\": false, \n                \"seconds\": 0.9999719858169556, \n                \"sender\": false, \n                \"start\": 38.000061\n            }\n        }, \n        {\n            \"streams\": [\n                {\n                    \"bits_per_second\": 850686469.3232815, \n                    \"bytes\": 106341120, \n                    \"end\": 40.000083, \n                    \"omitted\": false, \n                    \"seconds\": 1.0000499486923218, \n                    \"sender\": false, \n                    \"socket\": 5, \n                    \"start\": 39.000033\n                }\n            ], \n            \"sum\": {\n                \"bits_per_second\": 850686469.3232815, \n                \"bytes\": 106341120, \n                \"end\": 40.000083, \n                \"omitted\": false, \n                \"seconds\": 1.0000499486923218, \n                \"sender\": false, \n                \"start\": 39.000033\n            }\n        }, \n        {\n            \"streams\": [\n                {\n                    \"bits_per_second\": 851268100.3155203, \n                    \"bytes\": 106406280, \n                    \"end\": 41.000062, \n                    \"omitted\": false, \n                    \"seconds\": 0.999979019165039, \n                    \"sender\": false, \n                    \"socket\": 5, \n                    \"start\": 40.000083\n                }\n            ], \n            \"sum\": {\n                \"bits_per_second\": 851268100.3155203, \n                \"bytes\": 106406280, \n                \"end\": 41.000062, \n                \"omitted\": false, \n                \"seconds\": 0.999979019165039, \n                \"sender\": false, \n                \"start\": 40.000083\n            }\n        }, \n        {\n            \"streams\": [\n                {\n                    \"bits_per_second\": 851236642.3077406, \n                    \"bytes\": 106406280, \n                    \"end\": 42.000078, \n                    \"omitted\": false, \n                    \"seconds\": 1.0000159740448, \n                    \"sender\": false, \n                    \"socket\": 5, \n                    \"start\": 41.000062\n                }\n            ], \n            \"sum\": {\n                \"bits_per_second\": 851236642.3077406, \n                \"bytes\": 106406280, \n                \"end\": 42.000078, \n                \"omitted\": false, \n                \"seconds\": 1.0000159740448, \n                \"sender\": false, \n                \"start\": 41.000062\n            }\n        }, \n        {\n            \"streams\": [\n                {\n                    \"bits_per_second\": 851246789.7981485, \n                    \"bytes\": 106406280, \n                    \"end\": 43.000082, \n                    \"omitted\": false, \n                    \"seconds\": 1.0000040531158447, \n                    \"sender\": false, \n                    \"socket\": 5, \n                    \"start\": 42.000078\n                }\n            ], \n            \"sum\": {\n                \"bits_per_second\": 851246789.7981485, \n                \"bytes\": 106406280, \n                \"end\": 43.000082, \n                \"omitted\": false, \n                \"seconds\": 1.0000040531158447, \n                \"sender\": false, \n                \"start\": 42.000078\n            }\n        }, \n        {\n            \"streams\": [\n                {\n                    \"bits_per_second\": 851256176.442175, \n                    \"bytes\": 106406280, \n                    \"end\": 44.000075, \n                    \"omitted\": false, \n                    \"seconds\": 0.9999930262565613, \n                    \"sender\": false, \n                    \"socket\": 5, \n                    \"start\": 43.000082\n                }\n            ], \n            \"sum\": {\n                \"bits_per_second\": 851256176.442175, \n                \"bytes\": 106406280, \n                \"end\": 44.000075, \n                \"omitted\": false, \n                \"seconds\": 0.9999930262565613, \n                \"sender\": false, \n                \"start\": 43.000082\n            }\n        }, \n        {\n            \"streams\": [\n                {\n                    \"bits_per_second\": 851243441.099568, \n                    \"bytes\": 106406280, \n                    \"end\": 45.000083, \n                    \"omitted\": false, \n                    \"seconds\": 1.0000079870224, \n                    \"sender\": false, \n                    \"socket\": 5, \n                    \"start\": 44.000075\n                }\n            ], \n            \"sum\": {\n                \"bits_per_second\": 851243441.099568, \n                \"bytes\": 106406280, \n                \"end\": 45.000083, \n                \"omitted\": false, \n                \"seconds\": 1.0000079870224, \n                \"sender\": false, \n                \"start\": 44.000075\n            }\n        }, \n        {\n            \"streams\": [\n                {\n                    \"bits_per_second\": 851268100.3155203, \n                    \"bytes\": 106406280, \n                    \"end\": 46.000062, \n                    \"omitted\": false, \n                    \"seconds\": 0.999979019165039, \n                    \"sender\": false, \n                    \"socket\": 5, \n                    \"start\": 45.000083\n                }\n            ], \n            \"sum\": {\n                \"bits_per_second\": 851268100.3155203, \n                \"bytes\": 106406280, \n                \"end\": 46.000062, \n                \"omitted\": false, \n                \"seconds\": 0.999979019165039, \n                \"sender\": false, \n                \"start\": 45.000083\n            }\n        }, \n        {\n            \"streams\": [\n                {\n                    \"bits_per_second\": 851249428.1852835, \n                    \"bytes\": 106406280, \n                    \"end\": 47.000063, \n                    \"omitted\": false, \n                    \"seconds\": 1.0000009536743164, \n                    \"sender\": false, \n                    \"socket\": 5, \n                    \"start\": 46.000062\n                }\n            ], \n            \"sum\": {\n                \"bits_per_second\": 851249428.1852835, \n                \"bytes\": 106406280, \n                \"end\": 47.000063, \n                \"omitted\": false, \n                \"seconds\": 1.0000009536743164, \n                \"sender\": false, \n                \"start\": 46.000062\n            }\n        }, \n        {\n            \"streams\": [\n                {\n                    \"bits_per_second\": 851251965.111414, \n                    \"bytes\": 106406280, \n                    \"end\": 48.000061, \n                    \"omitted\": false, \n                    \"seconds\": 0.9999979734420776, \n                    \"sender\": false, \n                    \"socket\": 5, \n                    \"start\": 47.000063\n                }\n            ], \n            \"sum\": {\n                \"bits_per_second\": 851251965.111414, \n                \"bytes\": 106406280, \n                \"end\": 48.000061, \n                \"omitted\": false, \n                \"seconds\": 0.9999979734420776, \n                \"sender\": false, \n                \"start\": 47.000063\n            }\n        }, \n        {\n            \"streams\": [\n                {\n                    \"bits_per_second\": 851250240, \n                    \"bytes\": 106406280, \n                    \"end\": 49.000061, \n                    \"omitted\": false, \n                    \"seconds\": 1, \n                    \"sender\": false, \n                    \"socket\": 5, \n                    \"start\": 48.000061\n                }\n            ], \n            \"sum\": {\n                \"bits_per_second\": 851250240, \n                \"bytes\": 106406280, \n                \"end\": 49.000061, \n                \"omitted\": false, \n                \"seconds\": 1, \n                \"sender\": false, \n                \"start\": 48.000061\n            }\n        }, \n        {\n            \"streams\": [\n                {\n                    \"bits_per_second\": 851263838.1266867, \n                    \"bytes\": 106406280, \n                    \"end\": 50.000045, \n                    \"omitted\": false, \n                    \"seconds\": 0.9999840259552002, \n                    \"sender\": false, \n                    \"socket\": 5, \n                    \"start\": 49.000061\n                }\n            ], \n            \"sum\": {\n                \"bits_per_second\": 851263838.1266867, \n                \"bytes\": 106406280, \n                \"end\": 50.000045, \n                \"omitted\": false, \n                \"seconds\": 0.9999840259552002, \n                \"sender\": false, \n                \"start\": 49.000061\n            }\n        }, \n        {\n            \"streams\": [\n                {\n                    \"bits_per_second\": 851207723.2873276, \n                    \"bytes\": 106406280, \n                    \"end\": 51.000095, \n                    \"omitted\": false, \n                    \"seconds\": 1.0000499486923218, \n                    \"sender\": false, \n                    \"socket\": 5, \n                    \"start\": 50.000045\n                }\n            ], \n            \"sum\": {\n                \"bits_per_second\": 851207723.2873276, \n                \"bytes\": 106406280, \n                \"end\": 51.000095, \n                \"omitted\": false, \n                \"seconds\": 1.0000499486923218, \n                \"sender\": false, \n                \"start\": 50.000045\n            }\n        }, \n        {\n            \"streams\": [\n                {\n                    \"bits_per_second\": 850740876.4053175, \n                    \"bytes\": 106341120, \n                    \"end\": 52.000081, \n                    \"omitted\": false, \n                    \"seconds\": 0.9999859929084778, \n                    \"sender\": false, \n                    \"socket\": 5, \n                    \"start\": 51.000095\n                }\n            ], \n            \"sum\": {\n                \"bits_per_second\": 850740876.4053175, \n                \"bytes\": 106341120, \n                \"end\": 52.000081, \n                \"omitted\": false, \n                \"seconds\": 0.9999859929084778, \n                \"sender\": false, \n                \"start\": 51.000095\n            }\n        }, \n        {\n            \"streams\": [\n                {\n                    \"bits_per_second\": 851247703.084152, \n                    \"bytes\": 106406280, \n                    \"end\": 53.000084, \n                    \"omitted\": false, \n                    \"seconds\": 1.0000029802322388, \n                    \"sender\": false, \n                    \"socket\": 5, \n                    \"start\": 52.000081\n                }\n            ], \n            \"sum\": {\n                \"bits_per_second\": 851247703.084152, \n                \"bytes\": 106406280, \n                \"end\": 53.000084, \n                \"omitted\": false, \n                \"seconds\": 1.0000029802322388, \n                \"sender\": false, \n                \"start\": 52.000081\n            }\n        }, \n        {\n            \"streams\": [\n                {\n                    \"bits_per_second\": 851256176.442175, \n                    \"bytes\": 106406280, \n                    \"end\": 54.000077, \n                    \"omitted\": false, \n                    \"seconds\": 0.9999930262565613, \n                    \"sender\": false, \n                    \"socket\": 5, \n                    \"start\": 53.000084\n                }\n            ], \n            \"sum\": {\n                \"bits_per_second\": 851256176.442175, \n                \"bytes\": 106406280, \n                \"end\": 54.000077, \n                \"omitted\": false, \n                \"seconds\": 0.9999930262565613, \n                \"sender\": false, \n                \"start\": 53.000084\n            }\n        }, \n        {\n            \"streams\": [\n                {\n                    \"bits_per_second\": 851261301.1297873, \n                    \"bytes\": 106406280, \n                    \"end\": 55.000064, \n                    \"omitted\": false, \n                    \"seconds\": 0.999987006187439, \n                    \"sender\": false, \n                    \"socket\": 5, \n                    \"start\": 54.000077\n                }\n            ], \n            \"sum\": {\n                \"bits_per_second\": 851261301.1297873, \n                \"bytes\": 106406280, \n                \"end\": 55.000064, \n                \"omitted\": false, \n                \"seconds\": 0.999987006187439, \n                \"sender\": false, \n                \"start\": 54.000077\n            }\n        }, \n        {\n            \"streams\": [\n                {\n                    \"bits_per_second\": 851249428.1852835, \n                    \"bytes\": 106406280, \n                    \"end\": 56.000065, \n                    \"omitted\": false, \n                    \"seconds\": 1.0000009536743164, \n                    \"sender\": false, \n                    \"socket\": 5, \n                    \"start\": 55.000064\n                }\n            ], \n            \"sum\": {\n                \"bits_per_second\": 851249428.1852835, \n                \"bytes\": 106406280, \n                \"end\": 56.000065, \n                \"omitted\": false, \n                \"seconds\": 1.0000009536743164, \n                \"sender\": false, \n                \"start\": 55.000064\n            }\n        }, \n        {\n            \"streams\": [\n                {\n                    \"bits_per_second\": 851253639.4909433, \n                    \"bytes\": 106406280, \n                    \"end\": 57.000061, \n                    \"omitted\": false, \n                    \"seconds\": 0.9999960064888, \n                    \"sender\": false, \n                    \"socket\": 5, \n                    \"start\": 56.000065\n                }\n            ], \n            \"sum\": {\n                \"bits_per_second\": 851253639.4909433, \n                \"bytes\": 106406280, \n                \"end\": 57.000061, \n                \"omitted\": false, \n                \"seconds\": 0.9999960064888, \n                \"sender\": false, \n                \"start\": 56.000065\n            }\n        }, \n        {\n            \"streams\": [\n                {\n                    \"bits_per_second\": 851249428.1852835, \n                    \"bytes\": 106406280, \n                    \"end\": 58.000062, \n                    \"omitted\": false, \n                    \"seconds\": 1.0000009536743164, \n                    \"sender\": false, \n                    \"socket\": 5, \n                    \"start\": 57.000061\n                }\n            ], \n            \"sum\": {\n                \"bits_per_second\": 851249428.1852835, \n                \"bytes\": 106406280, \n                \"end\": 58.000062, \n                \"omitted\": false, \n                \"seconds\": 1.0000009536743164, \n                \"sender\": false, \n                \"start\": 57.000061\n            }\n        }, \n        {\n            \"streams\": [\n                {\n                    \"bits_per_second\": 851251102.554833, \n                    \"bytes\": 106406280, \n                    \"end\": 59.000061, \n                    \"omitted\": false, \n                    \"seconds\": 0.9999989867210388, \n                    \"sender\": false, \n                    \"socket\": 5, \n                    \"start\": 58.000062\n                }\n            ], \n            \"sum\": {\n                \"bits_per_second\": 851251102.554833, \n                \"bytes\": 106406280, \n                \"end\": 59.000061, \n                \"omitted\": false, \n                \"seconds\": 0.9999989867210388, \n                \"sender\": false, \n                \"start\": 58.000062\n            }\n        }, \n        {\n            \"streams\": [\n                {\n                    \"bits_per_second\": 851250240, \n                    \"bytes\": 106406280, \n                    \"end\": 60.000061, \n                    \"omitted\": false, \n                    \"seconds\": 1, \n                    \"sender\": false, \n                    \"socket\": 5, \n                    \"start\": 59.000061\n                }\n            ], \n            \"sum\": {\n                \"bits_per_second\": 851250240, \n                \"bytes\": 106406280, \n                \"end\": 60.000061, \n                \"omitted\": false, \n                \"seconds\": 1, \n                \"sender\": false, \n                \"start\": 59.000061\n            }\n        }, \n        {\n            \"streams\": [\n                {\n                    \"bits_per_second\": 844754441.0508828, \n                    \"bytes\": 8275320, \n                    \"end\": 60.07843, \n                    \"omitted\": false, \n                    \"seconds\": 0.07836899906396866, \n                    \"sender\": false, \n                    \"socket\": 5, \n                    \"start\": 60.000061\n                }\n            ], \n            \"sum\": {\n                \"bits_per_second\": 844754441.0508828, \n                \"bytes\": 8275320, \n                \"end\": 60.07843, \n                \"omitted\": false, \n                \"seconds\": 0.07836899906396866, \n                \"sender\": false, \n                \"start\": 60.000061\n            }\n        }\n    ], \n    \"start\": {\n        \"accepted_connection\": {\n            \"host\": \"10.0.0.1\", \n            \"port\": 44779\n        }, \n        \"connected\": [\n            {\n                \"local_host\": \"10.0.0.2\", \n                \"local_port\": 5201, \n                \"remote_host\": \"10.0.0.1\", \n                \"remote_port\": 49379, \n                \"socket\": 5\n            }\n        ], \n        \"cookie\": \"f4bzt52sxwhf4md6frn7x4xopvhivsb2xwf2\", \n        \"fq_rate\": 0, \n        \"rcvbuf_actual\": 87380, \n        \"sndbuf_actual\": 87380, \n        \"sock_bufsize\": 0, \n        \"system_info\": \"REDACTED\", \n        \"target_bitrate\": 0, \n        \"tcp_mss_default\": 0, \n        \"test_start\": {\n            \"bidir\": 0, \n            \"blksize\": 131072, \n            \"blocks\": 0, \n            \"bytes\": 0, \n            \"duration\": 60, \n            \"fqrate\": 0, \n            \"num_streams\": 1, \n            \"omit\": 0, \n            \"protocol\": \"TCP\", \n            \"reverse\": 0, \n            \"target_bitrate\": 0, \n            \"tos\": 0\n        }, \n        \"timestamp\": {\n            \"time\": \"Tue, 16 Apr 2024 23:01:47 GMT\", \n            \"timesecs\": 1713308507\n        }, \n        \"version\": \"iperf 3.14\"\n    }\n}\n","summary":{"streams":[{"end":60.000072,"rtt":78385,"start":0,"stream-id":5,"retransmits":0,"throughput-bits":852735932.4502144,"throughput-bytes":6395527168}],"summary":{"end":60.000072,"start":0,"retransmits":0,"throughput-bits":852735932.4502144,"throughput-bytes":6395527168,"receiver-throughput-bits":851119043.423738}},"intervals":[{"streams":[{"end":1.000073,"rtt":78381,"start":0,"omitted":false,"stream-id":5,"retransmits":0,"tcp-window-size":16685304,"throughput-bits":937358557.9891757,"throughput-bytes":117178368}],"summary":{"end":1.000073,"start":0,"omitted":false,"retransmits":0,"throughput-bits":937358557.9891757,"throughput-bytes":117178368}},{"streams":[{"end":2.000077,"rtt":78383,"start":1.000073,"omitted":false,"stream-id":5,"retransmits":0,"tcp-window-size":16685304,"throughput-bits":849343117.513953,"throughput-bytes":106168320}],"summary":{"end":2.000077,"start":1.000073,"omitted":false,"retransmits":0,"throughput-bits":849343117.513953,"throughput-bytes":106168320}},{"streams":[{"end":3.000079,"rtt":78384,"start":2.000077,"omitted":false,"stream-id":5,"retransmits":0,"tcp-window-size":16685304,"throughput-bits":859830577.5035312,"throughput-bytes":107479040}],"summary":{"end":3.000079,"start":2.000077,"omitted":false,"retransmits":0,"throughput-bits":859830577.5035312,"throughput-bytes":107479040}},{"streams":[{"end":4.000063,"rtt":78388,"start":3.000079,"omitted":false,"stream-id":5,"retransmits":0,"tcp-window-size":16685304,"throughput-bits":849360127.7167313,"throughput-bytes":106168320}],"summary":{"end":4.000063,"start":3.000079,"omitted":false,"retransmits":0,"throughput-bits":849360127.7167313,"throughput-bytes":106168320}},{"streams":[{"end":5.000154,"rtt":78383,"start":4.000063,"omitted":false,"stream-id":5,"retransmits":0,"tcp-window-size":16685304,"throughput-bits":849269313.276106,"throughput-bytes":106168320}],"summary":{"end":5.000154,"start":4.000063,"omitted":false,"retransmits":0,"throughput-bits":849269313.276106,"throughput-bytes":106168320}},{"streams":[{"end":6.000156,"rtt":78390,"start":5.000154,"omitted":false,"stream-id":5,"retransmits":0,"tcp-window-size":16685304,"throughput-bits":849344838.7534882,"throughput-bytes":106168320}],"summary":{"end":6.000156,"start":5.000154,"omitted":false,"retransmits":0,"throughput-bits":849344838.7534882,"throughput-bytes":106168320}},{"streams":[{"end":7.000172,"rtt":78390,"start":6.000156,"omitted":false,"stream-id":5,"retransmits":0,"tcp-window-size":16685304,"throughput-bits":849332992.7167244,"throughput-bytes":106168320}],"summary":{"end":7.000172,"start":6.000156,"omitted":false,"retransmits":0,"throughput-bits":849332992.7167244,"throughput-bytes":106168320}},{"streams":[{"end":8.000175,"rtt":78383,"start":7.000172,"omitted":false,"stream-id":5,"retransmits":0,"tcp-window-size":16685304,"throughput-bits":849344028.7575437,"throughput-bytes":106168320}],"summary":{"end":8.000175,"start":7.000172,"omitted":false,"retransmits":0,"throughput-bits":849344028.7575437,"throughput-bytes":106168320}},{"streams":[{"end":9.000082,"rtt":78384,"start":8.000175,"omitted":false,"stream-id":5,"retransmits":0,"tcp-window-size":16685304,"throughput-bits":859912277.4347018,"throughput-bytes":107479040}],"summary":{"end":9.000082,"start":8.000175,"omitted":false,"retransmits":0,"throughput-bits":859912277.4347018,"throughput-bytes":107479040}},{"streams":[{"end":10.000157,"rtt":78381,"start":9.000082,"omitted":false,"stream-id":5,"retransmits":0,"tcp-window-size":16685304,"throughput-bits":849282878.5250053,"throughput-bytes":106168320}],"summary":{"end":10.000157,"start":9.000082,"omitted":false,"retransmits":0,"throughput-bits":849282878.5250053,"throughput-bytes":106168320}},{"streams":[{"end":11.000085,"rtt":78381,"start":10.000157,"omitted":false,"stream-id":5,"retransmits":0,"tcp-window-size":16685304,"throughput-bits":849407719.4036245,"throughput-bytes":106168320}],"summary":{"end":11.000085,"start":10.000157,"omitted":false,"retransmits":0,"throughput-bits":849407719.4036245,"throughput-bytes":106168320}},{"streams":[{"end":12.000158,"rtt":78386,"start":11.000085,"omitted":false,"stream-id":5,"retransmits":0,"tcp-window-size":16685304,"throughput-bits":849284599.520394,"throughput-bytes":106168320}],"summary":{"end":12.000158,"start":11.000085,"omitted":false,"retransmits":0,"throughput-bits":849284599.520394,"throughput-bytes":106168320}},{"streams":[{"end":13.000151,"rtt":78387,"start":12.000158,"omitted":false,"stream-id":5,"retransmits":0,"tcp-window-size":16685304,"throughput-bits":849352483.1663066,"throughput-bytes":106168320}],"summary":{"end":13.000151,"start":12.000158,"omitted":false,"retransmits":0,"throughput-bits":849352483.1663066,"throughput-bytes":106168320}},{"streams":[{"end":14.00006,"rtt":78384,"start":13.000151,"omitted":false,"stream-id":5,"retransmits":0,"tcp-window-size":16685304,"throughput-bits":859910585.8734696,"throughput-bytes":107479040}],"summary":{"end":14.00006,"start":13.000151,"omitted":false,"retransmits":0,"throughput-bits":859910585.8734696,"throughput-bytes":107479040}},{"streams":[{"end":15.000155,"rtt":78387,"start":14.00006,"omitted":false,"stream-id":5,"retransmits":0,"tcp-window-size":16685304,"throughput-bits":849265871.4162065,"throughput-bytes":106168320}],"summary":{"end":15.000155,"start":14.00006,"omitted":false,"retransmits":0,"throughput-bits":849265871.4162065,"throughput-bytes":106168320}},{"streams":[{"end":16.000171,"rtt":78377,"start":15.000155,"omitted":false,"stream-id":5,"retransmits":0,"tcp-window-size":16685304,"throughput-bits":849332992.7167244,"throughput-bytes":106168320}],"summary":{"end":16.000171,"start":15.000155,"omitted":false,"retransmits":0,"throughput-bits":849332992.7167244,"throughput-bytes":106168320}},{"streams":[{"end":17.000155,"rtt":78383,"start":16.000171,"omitted":false,"stream-id":5,"retransmits":0,"tcp-window-size":16685304,"throughput-bits":849360127.7167313,"throughput-bytes":106168320}],"summary":{"end":17.000155,"start":16.000171,"omitted":false,"retransmits":0,"throughput-bits":849360127.7167313,"throughput-bytes":106168320}},{"streams":[{"end":18.00015,"rtt":78384,"start":17.000155,"omitted":false,"stream-id":5,"retransmits":0,"tcp-window-size":16685304,"throughput-bits":849350812.5212915,"throughput-bytes":106168320}],"summary":{"end":18.00015,"start":17.000155,"omitted":false,"retransmits":0,"throughput-bits":849350812.5212915,"throughput-bytes":106168320}},{"streams":[{"end":19.000102,"rtt":78386,"start":18.00015,"omitted":false,"stream-id":5,"retransmits":0,"tcp-window-size":16685304,"throughput-bits":849387315.0804996,"throughput-bytes":106168320}],"summary":{"end":19.000102,"start":18.00015,"omitted":false,"retransmits":0,"throughput-bits":849387315.0804996,"throughput-bytes":106168320}},{"streams":[{"end":20.000082,"rtt":78386,"start":19.000102,"omitted":false,"stream-id":5,"retransmits":0,"tcp-window-size":16685304,"throughput-bits":859849540.3448746,"throughput-bytes":107479040}],"summary":{"end":20.000082,"start":19.000102,"omitted":false,"retransmits":0,"throughput-bits":859849540.3448746,"throughput-bytes":107479040}},{"streams":[{"end":21.000156,"rtt":78385,"start":20.000082,"omitted":false,"stream-id":5,"retransmits":0,"tcp-window-size":16685304,"throughput-bits":849283688.4043194,"throughput-bytes":106168320}],"summary":{"end":21.000156,"start":20.000082,"omitted":false,"retransmits":0,"throughput-bits":849283688.4043194,"throughput-bytes":106168320}},{"streams":[{"end":22.000167,"rtt":78382,"start":21.000156,"omitted":false,"stream-id":5,"retransmits":0,"tcp-window-size":16685304,"throughput-bits":849337245.102159,"throughput-bytes":106168320}],"summary":{"end":22.000167,"start":21.000156,"omitted":false,"retransmits":0,"throughput-bits":849337245.102159,"throughput-bytes":106168320}},{"streams":[{"end":23.000172,"rtt":78387,"start":22.000167,"omitted":false,"stream-id":5,"retransmits":0,"tcp-window-size":16685304,"throughput-bits":849342307.5212913,"throughput-bytes":106168320}],"summary":{"end":23.000172,"start":22.000167,"omitted":false,"retransmits":0,"throughput-bits":849342307.5212913,"throughput-bytes":106168320}},{"streams":[{"end":24.000082,"rtt":78387,"start":23.000172,"omitted":false,"stream-id":5,"retransmits":0,"tcp-window-size":16685304,"throughput-bits":849423010.630787,"throughput-bytes":106168320}],"summary":{"end":24.000082,"start":23.000172,"omitted":false,"retransmits":0,"throughput-bits":849423010.630787,"throughput-bytes":106168320}},{"streams":[{"end":25.000157,"rtt":78386,"start":24.000082,"omitted":false,"stream-id":5,"retransmits":0,"tcp-window-size":16685304,"throughput-bits":849282878.5250053,"throughput-bytes":106168320}],"summary":{"end":25.000157,"start":24.000082,"omitted":false,"retransmits":0,"throughput-bits":849282878.5250053,"throughput-bytes":106168320}},{"streams":[{"end":26.000081,"rtt":78387,"start":25.000157,"omitted":false,"stream-id":5,"retransmits":0,"tcp-window-size":16685304,"throughput-bits":859897668.716236,"throughput-bytes":107479040}],"summary":{"end":26.000081,"start":25.000157,"omitted":false,"retransmits":0,"throughput-bits":859897668.716236,"throughput-bytes":107479040}},{"streams":[{"end":27.000163,"rtt":78386,"start":26.000081,"omitted":false,"stream-id":5,"retransmits":0,"tcp-window-size":16685304,"throughput-bits":849276905.7127655,"throughput-bytes":106168320}],"summary":{"end":27.000163,"start":26.000081,"omitted":false,"retransmits":0,"throughput-bits":849276905.7127655,"throughput-bytes":106168320}},{"streams":[{"end":28.000172,"rtt":78381,"start":27.000163,"omitted":false,"stream-id":5,"retransmits":0,"tcp-window-size":16685304,"throughput-bits":849338966.3178928,"throughput-bytes":106168320}],"summary":{"end":28.000172,"start":27.000163,"omitted":false,"retransmits":0,"throughput-bits":849338966.3178928,"throughput-bytes":106168320}},{"streams":[{"end":29.000122,"rtt":78387,"start":28.000172,"omitted":false,"stream-id":5,"retransmits":0,"tcp-window-size":16685304,"throughput-bits":849389036.4991773,"throughput-bytes":106168320}],"summary":{"end":29.000122,"start":28.000172,"omitted":false,"retransmits":0,"throughput-bits":849389036.4991773,"throughput-bytes":106168320}},{"streams":[{"end":30.000157,"rtt":78382,"start":29.000122,"omitted":false,"stream-id":5,"retransmits":0,"tcp-window-size":16685304,"throughput-bits":849316793.5432408,"throughput-bytes":106168320}],"summary":{"end":30.000157,"start":29.000122,"omitted":false,"retransmits":0,"throughput-bits":849316793.5432408,"throughput-bytes":106168320}},{"streams":[{"end":31.000445,"rtt":78379,"start":30.000157,"omitted":false,"stream-id":5,"retransmits":0,"tcp-window-size":16685304,"throughput-bits":859584751.3021724,"throughput-bytes":107479040}],"summary":{"end":31.000445,"start":30.000157,"omitted":false,"retransmits":0,"throughput-bits":859584751.3021724,"throughput-bytes":107479040}},{"streams":[{"end":32.000153,"rtt":78382,"start":31.000445,"omitted":false,"stream-id":5,"retransmits":0,"tcp-window-size":16685304,"throughput-bits":849594644.316403,"throughput-bytes":106168320}],"summary":{"end":32.000153,"start":31.000445,"omitted":false,"retransmits":0,"throughput-bits":849594644.316403,"throughput-bytes":106168320}},{"streams":[{"end":33.000174,"rtt":78384,"start":32.000153,"omitted":false,"stream-id":5,"retransmits":0,"tcp-window-size":16685304,"throughput-bits":849328740.3738706,"throughput-bytes":106168320}],"summary":{"end":33.000174,"start":32.000153,"omitted":false,"retransmits":0,"throughput-bits":849328740.3738706,"throughput-bytes":106168320}},{"streams":[{"end":34.000159,"rtt":78383,"start":33.000174,"omitted":false,"stream-id":5,"retransmits":0,"tcp-window-size":16685304,"throughput-bits":849359317.6916252,"throughput-bytes":106168320}],"summary":{"end":34.000159,"start":33.000174,"omitted":false,"retransmits":0,"throughput-bits":849359317.6916252,"throughput-bytes":106168320}},{"streams":[{"end":35.000081,"rtt":78383,"start":34.000159,"omitted":false,"stream-id":5,"retransmits":0,"tcp-window-size":16685304,"throughput-bits":849412833.295807,"throughput-bytes":106168320}],"summary":{"end":35.000081,"start":34.000159,"omitted":false,"retransmits":0,"throughput-bits":849412833.295807,"throughput-bytes":106168320}},{"streams":[{"end":36.000063,"rtt":78388,"start":35.000081,"omitted":false,"stream-id":5,"retransmits":0,"tcp-window-size":16685304,"throughput-bits":849361849.0252117,"throughput-bytes":106168320}],"summary":{"end":36.000063,"start":35.000081,"omitted":false,"retransmits":0,"throughput-bits":849361849.0252117,"throughput-bytes":106168320}},{"streams":[{"end":37.000083,"rtt":78382,"start":36.000063,"omitted":false,"stream-id":5,"retransmits":0,"tcp-window-size":16685304,"throughput-bits":859815100.3448608,"throughput-bytes":107479040}],"summary":{"end":37.000083,"start":36.000063,"omitted":false,"retransmits":0,"throughput-bits":859815100.3448608,"throughput-bytes":107479040}},{"streams":[{"end":38.000156,"rtt":78387,"start":37.000083,"omitted":false,"stream-id":5,"retransmits":0,"tcp-window-size":16685304,"throughput-bits":849284599.520394,"throughput-bytes":106168320}],"summary":{"end":38.000156,"start":37.000083,"omitted":false,"retransmits":0,"throughput-bits":849284599.520394,"throughput-bytes":106168320}},{"streams":[{"end":39.000159,"rtt":78389,"start":38.000156,"omitted":false,"stream-id":5,"retransmits":0,"tcp-window-size":16685304,"throughput-bits":849344028.7575437,"throughput-bytes":106168320}],"summary":{"end":39.000159,"start":38.000156,"omitted":false,"retransmits":0,"throughput-bits":849344028.7575437,"throughput-bytes":106168320}},{"streams":[{"end":40.000158,"rtt":78389,"start":39.000159,"omitted":false,"stream-id":5,"retransmits":0,"tcp-window-size":16685304,"throughput-bits":849347420.625872,"throughput-bytes":106168320}],"summary":{"end":40.000158,"start":39.000159,"omitted":false,"retransmits":0,"throughput-bits":849347420.625872,"throughput-bytes":106168320}},{"streams":[{"end":41.000176,"rtt":78377,"start":40.000158,"omitted":false,"stream-id":5,"retransmits":0,"tcp-window-size":16685304,"throughput-bits":849331271.5252018,"throughput-bytes":106168320}],"summary":{"end":41.000176,"start":40.000158,"omitted":false,"retransmits":0,"throughput-bits":849331271.5252018,"throughput-bytes":106168320}},{"streams":[{"end":42.000086,"rtt":78446,"start":41.000176,"omitted":false,"stream-id":5,"retransmits":0,"tcp-window-size":16685304,"throughput-bits":849423010.630787,"throughput-bytes":106168320}],"summary":{"end":42.000086,"start":41.000176,"omitted":false,"retransmits":0,"throughput-bits":849423010.630787,"throughput-bytes":106168320}},{"streams":[{"end":43.000082,"rtt":78385,"start":42.000086,"omitted":false,"stream-id":5,"retransmits":0,"tcp-window-size":16685304,"throughput-bits":859835753.7637128,"throughput-bytes":107479040}],"summary":{"end":43.000082,"start":42.000086,"omitted":false,"retransmits":0,"throughput-bits":859835753.7637128,"throughput-bytes":107479040}},{"streams":[{"end":44.000075,"rtt":78377,"start":43.000082,"omitted":false,"stream-id":5,"retransmits":0,"tcp-window-size":16685304,"throughput-bits":849352483.1663066,"throughput-bytes":106168320}],"summary":{"end":44.000075,"start":43.000082,"omitted":false,"retransmits":0,"throughput-bits":849352483.1663066,"throughput-bytes":106168320}},{"streams":[{"end":45.000158,"rtt":78382,"start":44.000075,"omitted":false,"stream-id":5,"retransmits":0,"tcp-window-size":16685304,"throughput-bits":849276095.8463873,"throughput-bytes":106168320}],"summary":{"end":45.000158,"start":44.000075,"omitted":false,"retransmits":0,"throughput-bits":849276095.8463873,"throughput-bytes":106168320}},{"streams":[{"end":46.000156,"rtt":78388,"start":45.000158,"omitted":false,"stream-id":5,"retransmits":0,"tcp-window-size":16685304,"throughput-bits":849348281.2534882,"throughput-bytes":106168320}],"summary":{"end":46.000156,"start":45.000158,"omitted":false,"retransmits":0,"throughput-bits":849348281.2534882,"throughput-bytes":106168320}},{"streams":[{"end":47.000064,"rtt":78388,"start":46.000156,"omitted":false,"stream-id":5,"retransmits":0,"tcp-window-size":16685304,"throughput-bits":849424732.1941535,"throughput-bytes":106168320}],"summary":{"end":47.000064,"start":46.000156,"omitted":false,"retransmits":0,"throughput-bits":849424732.1941535,"throughput-bytes":106168320}},{"streams":[{"end":48.000162,"rtt":78384,"start":47.000064,"omitted":false,"stream-id":5,"retransmits":0,"tcp-window-size":16685304,"throughput-bits":859748073.2553415,"throughput-bytes":107479040}],"summary":{"end":48.000162,"start":47.000064,"omitted":false,"retransmits":0,"throughput-bits":859748073.2553415,"throughput-bytes":107479040}},{"streams":[{"end":49.000066,"rtt":78381,"start":48.000162,"omitted":false,"stream-id":5,"retransmits":0,"tcp-window-size":16685304,"throughput-bits":849428124.7070947,"throughput-bytes":106168320}],"summary":{"end":49.000066,"start":48.000162,"omitted":false,"retransmits":0,"throughput-bits":849428124.7070947,"throughput-bytes":106168320}},{"streams":[{"end":50.000063,"rtt":78388,"start":49.000066,"omitted":false,"stream-id":5,"retransmits":0,"tcp-window-size":16685304,"throughput-bits":849349091.2575437,"throughput-bytes":106168320}],"summary":{"end":50.000063,"start":49.000066,"omitted":false,"retransmits":0,"throughput-bits":849349091.2575437,"throughput-bytes":106168320}},{"streams":[{"end":51.000055,"rtt":78384,"start":50.000063,"omitted":false,"stream-id":5,"retransmits":0,"tcp-window-size":16685304,"throughput-bits":849353343.8041824,"throughput-bytes":106168320}],"summary":{"end":51.000055,"start":50.000063,"omitted":false,"retransmits":0,"throughput-bits":849353343.8041824,"throughput-bytes":106168320}},{"streams":[{"end":52.000099,"rtt":78383,"start":51.000055,"omitted":false,"stream-id":5,"retransmits":0,"tcp-window-size":16685304,"throughput-bits":849309200.393383,"throughput-bytes":106168320}],"summary":{"end":52.000099,"start":51.000055,"omitted":false,"retransmits":0,"throughput-bits":849309200.393383,"throughput-bytes":106168320}},{"streams":[{"end":53.000157,"rtt":78382,"start":52.000099,"omitted":false,"stream-id":5,"retransmits":0,"tcp-window-size":16685304,"throughput-bits":849297254.1124495,"throughput-bytes":106168320}],"summary":{"end":53.000157,"start":52.000099,"omitted":false,"retransmits":0,"throughput-bits":849297254.1124495,"throughput-bytes":106168320}},{"streams":[{"end":54.000082,"rtt":78385,"start":53.000157,"omitted":false,"stream-id":5,"retransmits":0,"tcp-window-size":16685304,"throughput-bits":859896797.334681,"throughput-bytes":107479040}],"summary":{"end":54.000082,"start":53.000157,"omitted":false,"retransmits":0,"throughput-bits":859896797.334681,"throughput-bytes":107479040}},{"streams":[{"end":55.000157,"rtt":78389,"start":54.000082,"omitted":false,"stream-id":5,"retransmits":0,"tcp-window-size":16685304,"throughput-bits":849282878.5250053,"throughput-bytes":106168320}],"summary":{"end":55.000157,"start":54.000082,"omitted":false,"retransmits":0,"throughput-bits":849282878.5250053,"throughput-bytes":106168320}},{"streams":[{"end":56.000089,"rtt":78389,"start":55.000157,"omitted":false,"stream-id":5,"retransmits":0,"tcp-window-size":16685304,"throughput-bits":849404327.0536737,"throughput-bytes":106168320}],"summary":{"end":56.000089,"start":55.000157,"omitted":false,"retransmits":0,"throughput-bits":849404327.0536737,"throughput-bytes":106168320}},{"streams":[{"end":57.000151,"rtt":78382,"start":56.000089,"omitted":false,"stream-id":5,"retransmits":0,"tcp-window-size":16685304,"throughput-bits":849293913.2635096,"throughput-bytes":106168320}],"summary":{"end":57.000151,"start":56.000089,"omitted":false,"retransmits":0,"throughput-bits":849293913.2635096,"throughput-bytes":106168320}},{"streams":[{"end":58.000157,"rtt":78383,"start":57.000151,"omitted":false,"stream-id":5,"retransmits":0,"tcp-window-size":16685304,"throughput-bits":849341497.5301746,"throughput-bytes":106168320}],"summary":{"end":58.000157,"start":57.000151,"omitted":false,"retransmits":0,"throughput-bits":849341497.5301746,"throughput-bytes":106168320}},{"streams":[{"end":59.000135,"rtt":78387,"start":58.000157,"omitted":false,"stream-id":5,"retransmits":0,"tcp-window-size":16685304,"throughput-bits":849365241.0358728,"throughput-bytes":106168320}],"summary":{"end":59.000135,"start":58.000157,"omitted":false,"retransmits":0,"throughput-bits":849365241.0358728,"throughput-bytes":106168320}},{"streams":[{"end":60.000072,"rtt":78384,"start":59.000135,"omitted":false,"stream-id":5,"retransmits":0,"tcp-window-size":16685304,"throughput-bits":859886494.663118,"throughput-bytes":107479040}],"summary":{"end":60.000072,"start":59.000135,"omitted":false,"retransmits":0,"throughput-bits":859886494.663118,"throughput-bytes":107479040}}],"succeeded":true}
