{"diags":"Participant 0:\n/usr/bin/iperf3 -p 5201 -c 172.16.0.1 -t 10 --json --rsa-public-key-path /var/run/pscheduler-server/runner/tmp/tmpze5s92ag/tmpgn0fxish/public-key --username kBqHJ1gdnWsbhrNpXG8Z\n\n{\n    \"end\": {\n        \"cpu_utilization_percent\": {\n            \"host_system\": 0.20421908464461472, \n            \"host_total\": 0.2604408625575216, \n            \"host_user\": 0.05621189363408954, \n            \"remote_system\": 3.2432975984196193, \n            \"remote_total\": 3.7456767887518736, \n            \"remote_user\": 0.5023692832311416\n        }, \n        \"receiver_tcp_congestion\": \"htcp\", \n        \"sender_tcp_congestion\": \"htcp\", \n        \"streams\": [\n            {\n                \"receiver\": {\n                    \"bits_per_second\": 21020219.272626113, \n                    \"bytes\": 26521568, \n                    \"end\": 10.093736, \n                    \"seconds\": 10.000147, \n                    \"sender\": true, \n                    \"socket\": 5, \n                    \"start\": 0\n                }, \n                \"sender\": {\n                    \"bits_per_second\": 24221749.540281758, \n                    \"bytes\": 30277632, \n                    \"end\": 10.000147, \n                    \"max_rtt\": 127473, \n                    \"max_snd_cwnd\": 353312, \n                    \"max_snd_wnd\": 0, \n                    \"mean_rtt\": 89774, \n                    \"min_rtt\": 70013, \n                    \"retransmits\": 293, \n                    \"seconds\": 10.000147, \n                    \"sender\": true, \n                    \"socket\": 5, \n                    \"start\": 0\n                }\n            }\n        ], \n        \"sum_received\": {\n            \"bits_per_second\": 21020219.272626113, \n            \"bytes\": 26521568, \n            \"end\": 10.093736, \n            \"seconds\": 10.093736, \n            \"sender\": true, \n            \"start\": 0\n        }, \n        \"sum_sent\": {\n            \"bits_per_second\": 24221749.540281758, \n            \"bytes\": 30277632, \n            \"end\": 10.000147, \n            \"retransmits\": 293, \n            \"seconds\": 10.000147, \n            \"sender\": true, \n            \"start\": 0\n        }\n    }, \n    \"intervals\": [\n        {\n            \"streams\": [\n                {\n                    \"bits_per_second\": 53472027.90989776, \n                    \"bytes\": 6684672, \n                    \"end\": 1.0001, \n                    \"omitted\": false, \n                    \"pmtu\": 1500, \n                    \"retransmits\": 277, \n                    \"rtt\": 74249, \n                    \"rttvar\": 420, \n                    \"seconds\": 1.000100016593933, \n                    \"sender\": true, \n                    \"snd_cwnd\": 202720, \n                    \"snd_wnd\": -1, \n                    \"socket\": 5, \n                    \"start\": 0\n                }\n            ], \n            \"sum\": {\n                \"bits_per_second\": 53472027.90989776, \n                \"bytes\": 6684672, \n                \"end\": 1.0001, \n                \"omitted\": false, \n                \"retransmits\": 277, \n                \"seconds\": 1.000100016593933, \n                \"sender\": true, \n                \"start\": 0\n            }\n        }, \n        {\n            \"streams\": [\n                {\n                    \"bits_per_second\": 20970912.517597463, \n                    \"bytes\": 2621440, \n                    \"end\": 2.000129, \n                    \"omitted\": false, \n                    \"pmtu\": 1500, \n                    \"retransmits\": 0, \n                    \"rtt\": 81218, \n                    \"rttvar\": 1021, \n                    \"seconds\": 1.0000289678573608, \n                    \"sender\": true, \n                    \"snd_cwnd\": 221544, \n                    \"snd_wnd\": -1, \n                    \"socket\": 5, \n                    \"start\": 1.0001\n                }\n            ], \n            \"sum\": {\n                \"bits_per_second\": 20970912.517597463, \n                \"bytes\": 2621440, \n                \"end\": 2.000129, \n                \"omitted\": false, \n                \"retransmits\": 0, \n                \"seconds\": 1.0000289678573608, \n                \"sender\": true, \n                \"start\": 1.0001\n            }\n        }, \n        {\n            \"streams\": [\n                {\n                    \"bits_per_second\": 20970890.0189251, \n                    \"bytes\": 2621440, \n                    \"end\": 3.000159, \n                    \"omitted\": false, \n                    \"pmtu\": 1500, \n                    \"retransmits\": 0, \n                    \"rtt\": 86042, \n                    \"rttvar\": 973, \n                    \"seconds\": 1.0000300407409668, \n                    \"sender\": true, \n                    \"snd_cwnd\": 237472, \n                    \"snd_wnd\": -1, \n                    \"socket\": 5, \n                    \"start\": 2.000129\n                }\n            ], \n            \"sum\": {\n                \"bits_per_second\": 20970890.0189251, \n                \"bytes\": 2621440, \n                \"end\": 3.000159, \n                \"omitted\": false, \n                \"retransmits\": 0, \n                \"seconds\": 1.0000300407409668, \n                \"sender\": true, \n                \"start\": 2.000129\n            }\n        }, \n        {\n            \"streams\": [\n                {\n                    \"bits_per_second\": 20970430.05665008, \n                    \"bytes\": 2621440, \n                    \"end\": 4.000211, \n                    \"omitted\": false, \n                    \"pmtu\": 1500, \n                    \"retransmits\": 0, \n                    \"rtt\": 94965, \n                    \"rttvar\": 951, \n                    \"seconds\": 1.0000519752502441, \n                    \"sender\": true, \n                    \"snd_cwnd\": 262088, \n                    \"snd_wnd\": -1, \n                    \"socket\": 5, \n                    \"start\": 3.000159\n                }\n            ], \n            \"sum\": {\n                \"bits_per_second\": 20970430.05665008, \n                \"bytes\": 2621440, \n                \"end\": 4.000211, \n                \"omitted\": false, \n                \"retransmits\": 0, \n                \"seconds\": 1.0000519752502441, \n                \"sender\": true, \n                \"start\": 3.000159\n            }\n        }, \n        {\n            \"streams\": [\n                {\n                    \"bits_per_second\": 20971057.51019962, \n                    \"bytes\": 2621440, \n                    \"end\": 5.000233, \n                    \"omitted\": false, \n                    \"pmtu\": 1500, \n                    \"retransmits\": 0, \n                    \"rtt\": 109889, \n                    \"rttvar\": 479, \n                    \"seconds\": 1.000022053718567, \n                    \"sender\": true, \n                    \"snd_cwnd\": 304080, \n                    \"snd_wnd\": -1, \n                    \"socket\": 5, \n                    \"start\": 4.000211\n                }\n            ], \n            \"sum\": {\n                \"bits_per_second\": 20971057.51019962, \n                \"bytes\": 2621440, \n                \"end\": 5.000233, \n                \"omitted\": false, \n                \"retransmits\": 0, \n                \"seconds\": 1.000022053718567, \n                \"sender\": true, \n                \"start\": 4.000211\n            }\n        }, \n        {\n            \"streams\": [\n                {\n                    \"bits_per_second\": 20971310.00210283, \n                    \"bytes\": 2621440, \n                    \"end\": 6.000243, \n                    \"omitted\": false, \n                    \"pmtu\": 1500, \n                    \"retransmits\": 0, \n                    \"rtt\": 127473, \n                    \"rttvar\": 642, \n                    \"seconds\": 1.0000100135803223, \n                    \"sender\": true, \n                    \"snd_cwnd\": 353312, \n                    \"snd_wnd\": -1, \n                    \"socket\": 5, \n                    \"start\": 5.000233\n                }\n            ], \n            \"sum\": {\n                \"bits_per_second\": 20971310.00210283, \n                \"bytes\": 2621440, \n                \"end\": 6.000243, \n                \"omitted\": false, \n                \"retransmits\": 0, \n                \"seconds\": 1.0000100135803223, \n                \"sender\": true, \n                \"start\": 5.000233\n            }\n        }, \n        {\n            \"streams\": [\n                {\n                    \"bits_per_second\": 20975253.164426625, \n                    \"bytes\": 2621440, \n                    \"end\": 7.000065, \n                    \"omitted\": false, \n                    \"pmtu\": 1500, \n                    \"retransmits\": 16, \n                    \"rtt\": 70013, \n                    \"rttvar\": 541, \n                    \"seconds\": 0.9998220205307007, \n                    \"sender\": true, \n                    \"snd_cwnd\": 192584, \n                    \"snd_wnd\": -1, \n                    \"socket\": 5, \n                    \"start\": 6.000243\n                }\n            ], \n            \"sum\": {\n                \"bits_per_second\": 20975253.164426625, \n                \"bytes\": 2621440, \n                \"end\": 7.000065, \n                \"omitted\": false, \n                \"retransmits\": 16, \n                \"seconds\": 0.9998220205307007, \n                \"sender\": true, \n                \"start\": 6.000243\n            }\n        }, \n        {\n            \"streams\": [\n                {\n                    \"bits_per_second\": 20971227.504079584, \n                    \"bytes\": 2621440, \n                    \"end\": 8.000079, \n                    \"omitted\": false, \n                    \"pmtu\": 1500, \n                    \"retransmits\": 0, \n                    \"rtt\": 77114, \n                    \"rttvar\": 744, \n                    \"seconds\": 1.0000139474868774, \n                    \"sender\": true, \n                    \"snd_cwnd\": 211408, \n                    \"snd_wnd\": -1, \n                    \"socket\": 5, \n                    \"start\": 7.000065\n                }\n            ], \n            \"sum\": {\n                \"bits_per_second\": 20971227.504079584, \n                \"bytes\": 2621440, \n                \"end\": 8.000079, \n                \"omitted\": false, \n                \"retransmits\": 0, \n                \"seconds\": 1.0000139474868774, \n                \"sender\": true, \n                \"start\": 7.000065\n            }\n        }, \n        {\n            \"streams\": [\n                {\n                    \"bits_per_second\": 20970765.02717993, \n                    \"bytes\": 2621440, \n                    \"end\": 9.000115, \n                    \"omitted\": false, \n                    \"pmtu\": 1500, \n                    \"retransmits\": 0, \n                    \"rtt\": 83861, \n                    \"rttvar\": 502, \n                    \"seconds\": 1.0000360012054443, \n                    \"sender\": true, \n                    \"snd_cwnd\": 228784, \n                    \"snd_wnd\": -1, \n                    \"socket\": 5, \n                    \"start\": 8.000079\n                }\n            ], \n            \"sum\": {\n                \"bits_per_second\": 20970765.02717993, \n                \"bytes\": 2621440, \n                \"end\": 9.000115, \n                \"omitted\": false, \n                \"retransmits\": 0, \n                \"seconds\": 1.0000360012054443, \n                \"sender\": true, \n                \"start\": 8.000079\n            }\n        }, \n        {\n            \"streams\": [\n                {\n                    \"bits_per_second\": 20970850.021404535, \n                    \"bytes\": 2621440, \n                    \"end\": 10.000147, \n                    \"omitted\": false, \n                    \"pmtu\": 1500, \n                    \"retransmits\": 0, \n                    \"rtt\": 92919, \n                    \"rttvar\": 1078, \n                    \"seconds\": 1.0000319480895996, \n                    \"sender\": true, \n                    \"snd_cwnd\": 254848, \n                    \"snd_wnd\": -1, \n                    \"socket\": 5, \n                    \"start\": 9.000115\n                }\n            ], \n            \"sum\": {\n                \"bits_per_second\": 20970850.021404535, \n                \"bytes\": 2621440, \n                \"end\": 10.000147, \n                \"omitted\": false, \n                \"retransmits\": 0, \n                \"seconds\": 1.0000319480895996, \n                \"sender\": true, \n                \"start\": 9.000115\n            }\n        }\n    ], \n    \"start\": {\n        \"connected\": [\n            {\n                \"local_host\": \"172.16.0.2\", \n                \"local_port\": 39650, \n                \"remote_host\": \"172.16.0.1\", \n                \"remote_port\": 5201, \n                \"socket\": 5\n            }\n        ], \n        \"connecting_to\": {\n            \"host\": \"172.16.0.1\", \n            \"port\": 5201\n        }, \n        \"cookie\": \"mbtk6s3cizai2qdqusxhlsppu72mnf23myeq\", \n        \"fq_rate\": 0, \n        \"rcvbuf_actual\": 87380, \n        \"sndbuf_actual\": 65536, \n        \"sock_bufsize\": 0, \n        \"system_info\": \"REDACTED\", \n        \"target_bitrate\": 0, \n        \"tcp_mss_default\": 1448, \n        \"test_start\": {\n            \"bidir\": 0, \n            \"blksize\": 131072, \n            \"blocks\": 0, \n            \"bytes\": 0, \n            \"duration\": 10, \n            \"fqrate\": 0, \n            \"num_streams\": 1, \n            \"omit\": 0, \n            \"protocol\": \"TCP\", \n            \"reverse\": 0, \n            \"target_bitrate\": 0, \n            \"tos\": 0\n        }, \n        \"timestamp\": {\n            \"time\": \"Wed, 04 Sep 2024 22:27:32 GMT\", \n            \"timesecs\": 1725488852\n        }, \n        \"version\": \"iperf 3.14\"\n    }\n}\nParticipant 1:\n/usr/bin/iperf3 -s -1 --idle-timeout 10 --json -p 5201 --authorized-users-path /var/run/pscheduler-server/runner/tmp/tmpk7g3zbaj/tmptftxpopl/credentials --rsa-private-key-path /var/run/pscheduler-server/runner/tmp/tmpk7g3zbaj/tmptftxpopl/private-key\n\n{\n    \"end\": {\n        \"cpu_utilization_percent\": {\n            \"host_system\": 3.2432975984196193, \n            \"host_total\": 3.7456767887518736, \n            \"host_user\": 0.5023692832311416, \n            \"remote_system\": 0, \n            \"remote_total\": 0, \n            \"remote_user\": 0\n        }, \n        \"receiver_tcp_congestion\": \"htcp\", \n        \"streams\": [\n            {\n                \"receiver\": {\n                    \"bits_per_second\": 21020219.272626113, \n                    \"bytes\": 26521568, \n                    \"end\": 10.093736, \n                    \"seconds\": 10.093736, \n                    \"sender\": false, \n                    \"socket\": 5, \n                    \"start\": 0\n                }, \n                \"sender\": {\n                    \"bits_per_second\": 0, \n                    \"bytes\": 0, \n                    \"end\": 10.093736, \n                    \"seconds\": 10.093736, \n                    \"sender\": false, \n                    \"socket\": 5, \n                    \"start\": 0\n                }\n            }\n        ], \n        \"sum_received\": {\n            \"bits_per_second\": 21020219.272626113, \n            \"bytes\": 26521568, \n            \"end\": 10.093736, \n            \"seconds\": 10.093736, \n            \"sender\": false, \n            \"start\": 0\n        }, \n        \"sum_sent\": {\n            \"bits_per_second\": 0, \n            \"bytes\": 0, \n            \"end\": 10.093736, \n            \"seconds\": 10.093736, \n            \"sender\": false, \n            \"start\": 0\n        }\n    }, \n    \"intervals\": [\n        {\n            \"streams\": [\n                {\n                    \"bits_per_second\": 20316548.622060407, \n                    \"bytes\": 2539792, \n                    \"end\": 1.000088, \n                    \"omitted\": false, \n                    \"seconds\": 1.0000879764556885, \n                    \"sender\": false, \n                    \"socket\": 5, \n                    \"start\": 0\n                }\n            ], \n            \"sum\": {\n                \"bits_per_second\": 20316548.622060407, \n                \"bytes\": 2539792, \n                \"end\": 1.000088, \n                \"omitted\": false, \n                \"seconds\": 1.0000879764556885, \n                \"sender\": false, \n                \"start\": 0\n            }\n        }, \n        {\n            \"streams\": [\n                {\n                    \"bits_per_second\": 21673620.077153526, \n                    \"bytes\": 2709208, \n                    \"end\": 2.00009, \n                    \"omitted\": false, \n                    \"seconds\": 1.0000020265579224, \n                    \"sender\": false, \n                    \"socket\": 5, \n                    \"start\": 1.000088\n                }\n            ], \n            \"sum\": {\n                \"bits_per_second\": 21673620.077153526, \n                \"bytes\": 2709208, \n                \"end\": 2.00009, \n                \"omitted\": false, \n                \"seconds\": 1.0000020265579224, \n                \"sender\": false, \n                \"start\": 1.000088\n            }\n        }, \n        {\n            \"streams\": [\n                {\n                    \"bits_per_second\": 21685487.122815, \n                    \"bytes\": 2710656, \n                    \"end\": 3.000079, \n                    \"omitted\": false, \n                    \"seconds\": 0.9999889731407166, \n                    \"sender\": false, \n                    \"socket\": 5, \n                    \"start\": 2.00009\n                }\n            ], \n            \"sum\": {\n                \"bits_per_second\": 21685487.122815, \n                \"bytes\": 2710656, \n                \"end\": 3.000079, \n                \"omitted\": false, \n                \"seconds\": 0.9999889731407166, \n                \"sender\": false, \n                \"start\": 2.00009\n            }\n        }, \n        {\n            \"streams\": [\n                {\n                    \"bits_per_second\": 21673534.81566563, \n                    \"bytes\": 2709208, \n                    \"end\": 4.000085, \n                    \"omitted\": false, \n                    \"seconds\": 1.0000059604644775, \n                    \"sender\": false, \n                    \"socket\": 5, \n                    \"start\": 3.000079\n                }\n            ], \n            \"sum\": {\n                \"bits_per_second\": 21673534.81566563, \n                \"bytes\": 2709208, \n                \"end\": 4.000085, \n                \"omitted\": false, \n                \"seconds\": 1.0000059604644775, \n                \"sender\": false, \n                \"start\": 3.000079\n            }\n        }, \n        {\n            \"streams\": [\n                {\n                    \"bits_per_second\": 21685399.228410587, \n                    \"bytes\": 2710656, \n                    \"end\": 5.000078, \n                    \"omitted\": false, \n                    \"seconds\": 0.9999930262565613, \n                    \"sender\": false, \n                    \"socket\": 5, \n                    \"start\": 4.000085\n                }\n            ], \n            \"sum\": {\n                \"bits_per_second\": 21685399.228410587, \n                \"bytes\": 2710656, \n                \"end\": 5.000078, \n                \"omitted\": false, \n                \"seconds\": 0.9999930262565613, \n                \"sender\": false, \n                \"start\": 4.000085\n            }\n        }, \n        {\n            \"streams\": [\n                {\n                    \"bits_per_second\": 21673707.9230245, \n                    \"bytes\": 2709208, \n                    \"end\": 6.000076, \n                    \"omitted\": false, \n                    \"seconds\": 0.9999979734420776, \n                    \"sender\": false, \n                    \"socket\": 5, \n                    \"start\": 5.000078\n                }\n            ], \n            \"sum\": {\n                \"bits_per_second\": 21673707.9230245, \n                \"bytes\": 2709208, \n                \"end\": 6.000076, \n                \"omitted\": false, \n                \"seconds\": 0.9999979734420776, \n                \"sender\": false, \n                \"start\": 5.000078\n            }\n        }, \n        {\n            \"streams\": [\n                {\n                    \"bits_per_second\": 16392310.677292883, \n                    \"bytes\": 2048920, \n                    \"end\": 7.000018, \n                    \"omitted\": false, \n                    \"seconds\": 0.9999420046806335, \n                    \"sender\": false, \n                    \"socket\": 5, \n                    \"start\": 6.000076\n                }\n            ], \n            \"sum\": {\n                \"bits_per_second\": 16392310.677292883, \n                \"bytes\": 2048920, \n                \"end\": 7.000018, \n                \"omitted\": false, \n                \"seconds\": 0.9999420046806335, \n                \"sender\": false, \n                \"start\": 6.000076\n            }\n        }, \n        {\n            \"streams\": [\n                {\n                    \"bits_per_second\": 21671821.97697668, \n                    \"bytes\": 2709208, \n                    \"end\": 8.000103, \n                    \"omitted\": false, \n                    \"seconds\": 1.00008499622345, \n                    \"sender\": false, \n                    \"socket\": 5, \n                    \"start\": 7.000018\n                }\n            ], \n            \"sum\": {\n                \"bits_per_second\": 21671821.97697668, \n                \"bytes\": 2709208, \n                \"end\": 8.000103, \n                \"omitted\": false, \n                \"seconds\": 1.00008499622345, \n                \"sender\": false, \n                \"start\": 7.000018\n            }\n        }, \n        {\n            \"streams\": [\n                {\n                    \"bits_per_second\": 21685529.77770922, \n                    \"bytes\": 2710656, \n                    \"end\": 9.00009, \n                    \"omitted\": false, \n                    \"seconds\": 0.999987006187439, \n                    \"sender\": false, \n                    \"socket\": 5, \n                    \"start\": 8.000103\n                }\n            ], \n            \"sum\": {\n                \"bits_per_second\": 21685529.77770922, \n                \"bytes\": 2710656, \n                \"end\": 9.00009, \n                \"omitted\": false, \n                \"seconds\": 0.999987006187439, \n                \"sender\": false, \n                \"start\": 8.000103\n            }\n        }, \n        {\n            \"streams\": [\n                {\n                    \"bits_per_second\": 21674032.18380191, \n                    \"bytes\": 2709208, \n                    \"end\": 10.000073, \n                    \"omitted\": false, \n                    \"seconds\": 0.999983012676239, \n                    \"sender\": false, \n                    \"socket\": 5, \n                    \"start\": 9.00009\n                }\n            ], \n            \"sum\": {\n                \"bits_per_second\": 21674032.18380191, \n                \"bytes\": 2709208, \n                \"end\": 10.000073, \n                \"omitted\": false, \n                \"seconds\": 0.999983012676239, \n                \"sender\": false, \n                \"start\": 9.00009\n            }\n        }, \n        {\n            \"streams\": [\n                {\n                    \"bits_per_second\": 21767229.421990123, \n                    \"bytes\": 254848, \n                    \"end\": 10.093736, \n                    \"omitted\": false, \n                    \"seconds\": 0.0936629995703697, \n                    \"sender\": false, \n                    \"socket\": 5, \n                    \"start\": 10.000073\n                }\n            ], \n            \"sum\": {\n                \"bits_per_second\": 21767229.421990123, \n                \"bytes\": 254848, \n                \"end\": 10.093736, \n                \"omitted\": false, \n                \"seconds\": 0.0936629995703697, \n                \"sender\": false, \n                \"start\": 10.000073\n            }\n        }\n    ], \n    \"start\": {\n        \"accepted_connection\": {\n            \"host\": \"172.16.0.2\", \n            \"port\": 39646\n        }, \n        \"connected\": [\n            {\n                \"local_host\": \"172.16.0.1\", \n                \"local_port\": 5201, \n                \"remote_host\": \"172.16.0.2\", \n                \"remote_port\": 39650, \n                \"socket\": 5\n            }\n        ], \n        \"cookie\": \"mbtk6s3cizai2qdqusxhlsppu72mnf23myeq\", \n        \"fq_rate\": 0, \n        \"rcvbuf_actual\": 87380, \n        \"sndbuf_actual\": 65536, \n        \"sock_bufsize\": 0, \n        \"system_info\": \"REDACTED\", \n        \"target_bitrate\": 0, \n        \"tcp_mss_default\": 0, \n        \"test_start\": {\n            \"bidir\": 0, \n            \"blksize\": 131072, \n            \"blocks\": 0, \n            \"bytes\": 0, \n            \"duration\": 10, \n            \"fqrate\": 0, \n            \"num_streams\": 1, \n            \"omit\": 0, \n            \"protocol\": \"TCP\", \n            \"reverse\": 0, \n            \"target_bitrate\": 0, \n            \"tos\": 0\n        }, \n        \"timestamp\": {\n            \"time\": \"Wed, 04 Sep 2024 22:27:32 GMT\", \n            \"timesecs\": 1725488852\n        }, \n        \"version\": \"iperf 3.14\"\n    }\n}\n","summary":{"streams":[{"end":10.000147,"rtt":89774,"start":0,"stream-id":5,"retransmits":293,"throughput-bits":24221749.540281758,"throughput-bytes":30277632}],"summary":{"end":10.000147,"start":0,"retransmits":293,"throughput-bits":24221749.540281758,"throughput-bytes":30277632,"receiver-throughput-bits":21020219.272626113}},"intervals":[{"streams":[{"end":1.0001,"rtt":74249,"start":0,"omitted":false,"stream-id":5,"retransmits":277,"tcp-window-size":202720,"throughput-bits":53472027.90989776,"throughput-bytes":6684672}],"summary":{"end":1.0001,"start":0,"omitted":false,"retransmits":277,"throughput-bits":53472027.90989776,"throughput-bytes":6684672}},{"streams":[{"end":2.000129,"rtt":81218,"start":1.0001,"omitted":false,"stream-id":5,"retransmits":0,"tcp-window-size":221544,"throughput-bits":20970912.517597463,"throughput-bytes":2621440}],"summary":{"end":2.000129,"start":1.0001,"omitted":false,"retransmits":0,"throughput-bits":20970912.517597463,"throughput-bytes":2621440}},{"streams":[{"end":3.000159,"rtt":86042,"start":2.000129,"omitted":false,"stream-id":5,"retransmits":0,"tcp-window-size":237472,"throughput-bits":20970890.0189251,"throughput-bytes":2621440}],"summary":{"end":3.000159,"start":2.000129,"omitted":false,"retransmits":0,"throughput-bits":20970890.0189251,"throughput-bytes":2621440}},{"streams":[{"end":4.000211,"rtt":94965,"start":3.000159,"omitted":false,"stream-id":5,"retransmits":0,"tcp-window-size":262088,"throughput-bits":20970430.05665008,"throughput-bytes":2621440}],"summary":{"end":4.000211,"start":3.000159,"omitted":false,"retransmits":0,"throughput-bits":20970430.05665008,"throughput-bytes":2621440}},{"streams":[{"end":5.000233,"rtt":109889,"start":4.000211,"omitted":false,"stream-id":5,"retransmits":0,"tcp-window-size":304080,"throughput-bits":20971057.51019962,"throughput-bytes":2621440}],"summary":{"end":5.000233,"start":4.000211,"omitted":false,"retransmits":0,"throughput-bits":20971057.51019962,"throughput-bytes":2621440}},{"streams":[{"end":6.000243,"rtt":127473,"start":5.000233,"omitted":false,"stream-id":5,"retransmits":0,"tcp-window-size":353312,"throughput-bits":20971310.00210283,"throughput-bytes":2621440}],"summary":{"end":6.000243,"start":5.000233,"omitted":false,"retransmits":0,"throughput-bits":20971310.00210283,"throughput-bytes":2621440}},{"streams":[{"end":7.000065,"rtt":70013,"start":6.000243,"omitted":false,"stream-id":5,"retransmits":16,"tcp-window-size":192584,"throughput-bits":20975253.164426625,"throughput-bytes":2621440}],"summary":{"end":7.000065,"start":6.000243,"omitted":false,"retransmits":16,"throughput-bits":20975253.164426625,"throughput-bytes":2621440}},{"streams":[{"end":8.000079,"rtt":77114,"start":7.000065,"omitted":false,"stream-id":5,"retransmits":0,"tcp-window-size":211408,"throughput-bits":20971227.504079584,"throughput-bytes":2621440}],"summary":{"end":8.000079,"start":7.000065,"omitted":false,"retransmits":0,"throughput-bits":20971227.504079584,"throughput-bytes":2621440}},{"streams":[{"end":9.000115,"rtt":83861,"start":8.000079,"omitted":false,"stream-id":5,"retransmits":0,"tcp-window-size":228784,"throughput-bits":20970765.02717993,"throughput-bytes":2621440}],"summary":{"end":9.000115,"start":8.000079,"omitted":false,"retransmits":0,"throughput-bits":20970765.02717993,"throughput-bytes":2621440}},{"streams":[{"end":10.000147,"rtt":92919,"start":9.000115,"omitted":false,"stream-id":5,"retransmits":0,"tcp-window-size":254848,"throughput-bits":20970850.021404535,"throughput-bytes":2621440}],"summary":{"end":10.000147,"start":9.000115,"omitted":false,"retransmits":0,"throughput-bits":20970850.021404535,"throughput-bytes":2621440}}],"succeeded":true}
