{"diags":"Participant 0:\n/usr/bin/iperf3 -p 5201 -B 10.0.0.1 -c 10.0.0.2 -t 60 --json --rsa-public-key-path /var/run/pscheduler-server/runner/tmp/tmpdu7jhrg0/tmpb2uxy_r9/public-key --username dp0fduBLz0FcfN6F1uy4\n\n{\n    \"end\": {\n        \"cpu_utilization_percent\": {\n            \"host_system\": 1.9946864865233294, \n            \"host_total\": 2.037471763741812, \n            \"host_user\": 0.04278361073576828, \n            \"remote_system\": 5.193361916660924, \n            \"remote_total\": 5.600417997043127, \n            \"remote_user\": 0.40705275132005636\n        }, \n        \"receiver_tcp_congestion\": \"htcp\", \n        \"sender_tcp_congestion\": \"htcp\", \n        \"streams\": [\n            {\n                \"receiver\": {\n                    \"bits_per_second\": 865535640.5463626, \n                    \"bytes\": 6499843216, \n                    \"end\": 60.076955, \n                    \"seconds\": 60.000071, \n                    \"sender\": true, \n                    \"socket\": 5, \n                    \"start\": 0\n                }, \n                \"sender\": {\n                    \"bits_per_second\": 867014039.6333865, \n                    \"bytes\": 6502612992, \n                    \"end\": 60.000071, \n                    \"max_rtt\": 77094, \n                    \"max_snd_cwnd\": 16698336, \n                    \"max_snd_wnd\": 0, \n                    \"mean_rtt\": 77088, \n                    \"min_rtt\": 77082, \n                    \"retransmits\": 0, \n                    \"seconds\": 60.000071, \n                    \"sender\": true, \n                    \"socket\": 5, \n                    \"start\": 0\n                }\n            }\n        ], \n        \"sum_received\": {\n            \"bits_per_second\": 865535640.5463626, \n            \"bytes\": 6499843216, \n            \"end\": 60.076955, \n            \"seconds\": 60.076955, \n            \"sender\": true, \n            \"start\": 0\n        }, \n        \"sum_sent\": {\n            \"bits_per_second\": 867014039.6333865, \n            \"bytes\": 6502612992, \n            \"end\": 60.000071, \n            \"retransmits\": 0, \n            \"seconds\": 60.000071, \n            \"sender\": true, \n            \"start\": 0\n        }\n    }, \n    \"intervals\": [\n        {\n            \"streams\": [\n                {\n                    \"bits_per_second\": 955176331.9865137, \n                    \"bytes\": 119406592, \n                    \"end\": 1.00008, \n                    \"omitted\": false, \n                    \"pmtu\": 1500, \n                    \"retransmits\": 0, \n                    \"rtt\": 77088, \n                    \"rttvar\": 11, \n                    \"seconds\": 1.0000799894332886, \n                    \"sender\": true, \n                    \"snd_cwnd\": 16698336, \n                    \"snd_wnd\": -1, \n                    \"socket\": 5, \n                    \"start\": 0\n                }\n            ], \n            \"sum\": {\n                \"bits_per_second\": 955176331.9865137, \n                \"bytes\": 119406592, \n                \"end\": 1.00008, \n                \"omitted\": false, \n                \"retransmits\": 0, \n                \"seconds\": 1.0000799894332886, \n                \"sender\": true, \n                \"start\": 0\n            }\n        }, \n        {\n            \"streams\": [\n                {\n                    \"bits_per_second\": 870330270.7957577, \n                    \"bytes\": 108789760, \n                    \"end\": 2.000066, \n                    \"omitted\": false, \n                    \"pmtu\": 1500, \n                    \"retransmits\": 0, \n                    \"rtt\": 77090, \n                    \"rttvar\": 6, \n                    \"seconds\": 0.9999859929084778, \n                    \"sender\": true, \n                    \"snd_cwnd\": 16698336, \n                    \"snd_wnd\": -1, \n                    \"socket\": 5, \n                    \"start\": 1.00008\n                }\n            ], \n            \"sum\": {\n                \"bits_per_second\": 870330270.7957577, \n                \"bytes\": 108789760, \n                \"end\": 2.000066, \n                \"omitted\": false, \n                \"retransmits\": 0, \n                \"seconds\": 0.9999859929084778, \n                \"sender\": true, \n                \"start\": 1.00008\n            }\n        }, \n        {\n            \"streams\": [\n                {\n                    \"bits_per_second\": 859850360.3785022, \n                    \"bytes\": 107479040, \n                    \"end\": 3.000045, \n                    \"omitted\": false, \n                    \"pmtu\": 1500, \n                    \"retransmits\": 0, \n                    \"rtt\": 77089, \n                    \"rttvar\": 7, \n                    \"seconds\": 0.999979019165039, \n                    \"sender\": true, \n                    \"snd_cwnd\": 16698336, \n                    \"snd_wnd\": -1, \n                    \"socket\": 5, \n                    \"start\": 2.000066\n                }\n            ], \n            \"sum\": {\n                \"bits_per_second\": 859850360.3785022, \n                \"bytes\": 107479040, \n                \"end\": 3.000045, \n                \"omitted\": false, \n                \"retransmits\": 0, \n                \"seconds\": 0.999979019165039, \n                \"sender\": true, \n                \"start\": 2.000066\n            }\n        }, \n        {\n            \"streams\": [\n                {\n                    \"bits_per_second\": 870301584.0626686, \n                    \"bytes\": 108789760, \n                    \"end\": 4.000064, \n                    \"omitted\": false, \n                    \"pmtu\": 1500, \n                    \"retransmits\": 0, \n                    \"rtt\": 77085, \n                    \"rttvar\": 8, \n                    \"seconds\": 1.0000189542770386, \n                    \"sender\": true, \n                    \"snd_cwnd\": 16698336, \n                    \"snd_wnd\": -1, \n                    \"socket\": 5, \n                    \"start\": 3.000045\n                }\n            ], \n            \"sum\": {\n                \"bits_per_second\": 870301584.0626686, \n                \"bytes\": 108789760, \n                \"end\": 4.000064, \n                \"omitted\": false, \n                \"retransmits\": 0, \n                \"seconds\": 1.0000189542770386, \n                \"sender\": true, \n                \"start\": 3.000045\n            }\n        }, \n        {\n            \"streams\": [\n                {\n                    \"bits_per_second\": 859833191.250883, \n                    \"bytes\": 107479040, \n                    \"end\": 5.000063, \n                    \"omitted\": false, \n                    \"pmtu\": 1500, \n                    \"retransmits\": 0, \n                    \"rtt\": 77085, \n                    \"rttvar\": 4, \n                    \"seconds\": 0.9999989867210388, \n                    \"sender\": true, \n                    \"snd_cwnd\": 16698336, \n                    \"snd_wnd\": -1, \n                    \"socket\": 5, \n                    \"start\": 4.000064\n                }\n            ], \n            \"sum\": {\n                \"bits_per_second\": 859833191.250883, \n                \"bytes\": 107479040, \n                \"end\": 5.000063, \n                \"omitted\": false, \n                \"retransmits\": 0, \n                \"seconds\": 0.9999989867210388, \n                \"sender\": true, \n                \"start\": 4.000064\n            }\n        }, \n        {\n            \"streams\": [\n                {\n                    \"bits_per_second\": 870318961.8758936, \n                    \"bytes\": 108789760, \n                    \"end\": 6.000062, \n                    \"omitted\": false, \n                    \"pmtu\": 1500, \n                    \"retransmits\": 0, \n                    \"rtt\": 77087, \n                    \"rttvar\": 7, \n                    \"seconds\": 0.9999989867210388, \n                    \"sender\": true, \n                    \"snd_cwnd\": 16698336, \n                    \"snd_wnd\": -1, \n                    \"socket\": 5, \n                    \"start\": 5.000063\n                }\n            ], \n            \"sum\": {\n                \"bits_per_second\": 870318961.8758936, \n                \"bytes\": 108789760, \n                \"end\": 6.000062, \n                \"omitted\": false, \n                \"retransmits\": 0, \n                \"seconds\": 0.9999989867210388, \n                \"sender\": true, \n                \"start\": 5.000063\n            }\n        }, \n        {\n            \"streams\": [\n                {\n                    \"bits_per_second\": 870318961.8758936, \n                    \"bytes\": 108789760, \n                    \"end\": 7.000061, \n                    \"omitted\": false, \n                    \"pmtu\": 1500, \n                    \"retransmits\": 0, \n                    \"rtt\": 77085, \n                    \"rttvar\": 9, \n                    \"seconds\": 0.9999989867210388, \n                    \"sender\": true, \n                    \"snd_cwnd\": 16698336, \n                    \"snd_wnd\": -1, \n                    \"socket\": 5, \n                    \"start\": 6.000062\n                }\n            ], \n            \"sum\": {\n                \"bits_per_second\": 870318961.8758936, \n                \"bytes\": 108789760, \n                \"end\": 7.000061, \n                \"omitted\": false, \n                \"retransmits\": 0, \n                \"seconds\": 0.9999989867210388, \n                \"sender\": true, \n                \"start\": 6.000062\n            }\n        }, \n        {\n            \"streams\": [\n                {\n                    \"bits_per_second\": 859841801.3545495, \n                    \"bytes\": 107479040, \n                    \"end\": 8.00005, \n                    \"omitted\": false, \n                    \"pmtu\": 1500, \n                    \"retransmits\": 0, \n                    \"rtt\": 77090, \n                    \"rttvar\": 9, \n                    \"seconds\": 0.9999889731407166, \n                    \"sender\": true, \n                    \"snd_cwnd\": 16698336, \n                    \"snd_wnd\": -1, \n                    \"socket\": 5, \n                    \"start\": 7.000061\n                }\n            ], \n            \"sum\": {\n                \"bits_per_second\": 859841801.3545495, \n                \"bytes\": 107479040, \n                \"end\": 8.00005, \n                \"omitted\": false, \n                \"retransmits\": 0, \n                \"seconds\": 0.9999889731407166, \n                \"sender\": true, \n                \"start\": 7.000061\n            }\n        }, \n        {\n            \"streams\": [\n                {\n                    \"bits_per_second\": 870307601.376164, \n                    \"bytes\": 108789760, \n                    \"end\": 9.000062, \n                    \"omitted\": false, \n                    \"pmtu\": 1500, \n                    \"retransmits\": 0, \n                    \"rtt\": 77087, \n                    \"rttvar\": 5, \n                    \"seconds\": 1.0000120401382446, \n                    \"sender\": true, \n                    \"snd_cwnd\": 16698336, \n                    \"snd_wnd\": -1, \n                    \"socket\": 5, \n                    \"start\": 8.00005\n                }\n            ], \n            \"sum\": {\n                \"bits_per_second\": 870307601.376164, \n                \"bytes\": 108789760, \n                \"end\": 9.000062, \n                \"omitted\": false, \n                \"retransmits\": 0, \n                \"seconds\": 1.0000120401382446, \n                \"sender\": true, \n                \"start\": 8.00005\n            }\n        }, \n        {\n            \"streams\": [\n                {\n                    \"bits_per_second\": 859848669.060859, \n                    \"bytes\": 107479040, \n                    \"end\": 10.000043, \n                    \"omitted\": false, \n                    \"pmtu\": 1500, \n                    \"retransmits\": 0, \n                    \"rtt\": 77091, \n                    \"rttvar\": 7, \n                    \"seconds\": 0.9999809861183167, \n                    \"sender\": true, \n                    \"snd_cwnd\": 16698336, \n                    \"snd_wnd\": -1, \n                    \"socket\": 5, \n                    \"start\": 9.000062\n                }\n            ], \n            \"sum\": {\n                \"bits_per_second\": 859848669.060859, \n                \"bytes\": 107479040, \n                \"end\": 10.000043, \n                \"omitted\": false, \n                \"retransmits\": 0, \n                \"seconds\": 0.9999809861183167, \n                \"sender\": true, \n                \"start\": 9.000062\n            }\n        }, \n        {\n            \"streams\": [\n                {\n                    \"bits_per_second\": 870302414.031997, \n                    \"bytes\": 108789760, \n                    \"end\": 11.000061, \n                    \"omitted\": false, \n                    \"pmtu\": 1500, \n                    \"retransmits\": 0, \n                    \"rtt\": 77089, \n                    \"rttvar\": 6, \n                    \"seconds\": 1.0000180006027222, \n                    \"sender\": true, \n                    \"snd_cwnd\": 16698336, \n                    \"snd_wnd\": -1, \n                    \"socket\": 5, \n                    \"start\": 10.000043\n                }\n            ], \n            \"sum\": {\n                \"bits_per_second\": 870302414.031997, \n                \"bytes\": 108789760, \n                \"end\": 11.000061, \n                \"omitted\": false, \n                \"retransmits\": 0, \n                \"seconds\": 1.0000180006027222, \n                \"sender\": true, \n                \"start\": 10.000043\n            }\n        }, \n        {\n            \"streams\": [\n                {\n                    \"bits_per_second\": 859828835.014125, \n                    \"bytes\": 107479040, \n                    \"end\": 12.000065, \n                    \"omitted\": false, \n                    \"pmtu\": 1500, \n                    \"retransmits\": 0, \n                    \"rtt\": 77087, \n                    \"rttvar\": 6, \n                    \"seconds\": 1.0000040531158447, \n                    \"sender\": true, \n                    \"snd_cwnd\": 16698336, \n                    \"snd_wnd\": -1, \n                    \"socket\": 5, \n                    \"start\": 11.000061\n                }\n            ], \n            \"sum\": {\n                \"bits_per_second\": 859828835.014125, \n                \"bytes\": 107479040, \n                \"end\": 12.000065, \n                \"omitted\": false, \n                \"retransmits\": 0, \n                \"seconds\": 1.0000040531158447, \n                \"sender\": true, \n                \"start\": 11.000061\n            }\n        }, \n        {\n            \"streams\": [\n                {\n                    \"bits_per_second\": 870319843.7535744, \n                    \"bytes\": 108789760, \n                    \"end\": 13.000063, \n                    \"omitted\": false, \n                    \"pmtu\": 1500, \n                    \"retransmits\": 0, \n                    \"rtt\": 77088, \n                    \"rttvar\": 8, \n                    \"seconds\": 0.9999979734420776, \n                    \"sender\": true, \n                    \"snd_cwnd\": 16698336, \n                    \"snd_wnd\": -1, \n                    \"socket\": 5, \n                    \"start\": 12.000065\n                }\n            ], \n            \"sum\": {\n                \"bits_per_second\": 870319843.7535744, \n                \"bytes\": 108789760, \n                \"end\": 13.000063, \n                \"omitted\": false, \n                \"retransmits\": 0, \n                \"seconds\": 0.9999979734420776, \n                \"sender\": true, \n                \"start\": 12.000065\n            }\n        }, \n        {\n            \"streams\": [\n                {\n                    \"bits_per_second\": 859840058.8196517, \n                    \"bytes\": 107479040, \n                    \"end\": 14.000054, \n                    \"omitted\": false, \n                    \"pmtu\": 1500, \n                    \"retransmits\": 0, \n                    \"rtt\": 77085, \n                    \"rttvar\": 10, \n                    \"seconds\": 0.999990999698639, \n                    \"sender\": true, \n                    \"snd_cwnd\": 16698336, \n                    \"snd_wnd\": -1, \n                    \"socket\": 5, \n                    \"start\": 13.000063\n                }\n            ], \n            \"sum\": {\n                \"bits_per_second\": 859840058.8196517, \n                \"bytes\": 107479040, \n                \"end\": 14.000054, \n                \"omitted\": false, \n                \"retransmits\": 0, \n                \"seconds\": 0.999990999698639, \n                \"sender\": true, \n                \"start\": 13.000063\n            }\n        }, \n        {\n            \"streams\": [\n                {\n                    \"bits_per_second\": 870337222.296018, \n                    \"bytes\": 108789760, \n                    \"end\": 15.000032, \n                    \"omitted\": false, \n                    \"pmtu\": 1500, \n                    \"retransmits\": 0, \n                    \"rtt\": 77088, \n                    \"rttvar\": 7, \n                    \"seconds\": 0.999978005886078, \n                    \"sender\": true, \n                    \"snd_cwnd\": 16698336, \n                    \"snd_wnd\": -1, \n                    \"socket\": 5, \n                    \"start\": 14.000054\n                }\n            ], \n            \"sum\": {\n                \"bits_per_second\": 870337222.296018, \n                \"bytes\": 108789760, \n                \"end\": 15.000032, \n                \"omitted\": false, \n                \"retransmits\": 0, \n                \"seconds\": 0.999978005886078, \n                \"sender\": true, \n                \"start\": 14.000054\n            }\n        }, \n        {\n            \"streams\": [\n                {\n                    \"bits_per_second\": 859806490.775929, \n                    \"bytes\": 107479040, \n                    \"end\": 16.000062, \n                    \"omitted\": false, \n                    \"pmtu\": 1500, \n                    \"retransmits\": 0, \n                    \"rtt\": 77091, \n                    \"rttvar\": 8, \n                    \"seconds\": 1.0000300407409668, \n                    \"sender\": true, \n                    \"snd_cwnd\": 16698336, \n                    \"snd_wnd\": -1, \n                    \"socket\": 5, \n                    \"start\": 15.000032\n                }\n            ], \n            \"sum\": {\n                \"bits_per_second\": 859806490.775929, \n                \"bytes\": 107479040, \n                \"end\": 16.000062, \n                \"omitted\": false, \n                \"retransmits\": 0, \n                \"seconds\": 1.0000300407409668, \n                \"sender\": true, \n                \"start\": 15.000032\n            }\n        }, \n        {\n            \"streams\": [\n                {\n                    \"bits_per_second\": 870335510.3490804, \n                    \"bytes\": 108789760, \n                    \"end\": 17.000042, \n                    \"omitted\": false, \n                    \"pmtu\": 1500, \n                    \"retransmits\": 0, \n                    \"rtt\": 77085, \n                    \"rttvar\": 6, \n                    \"seconds\": 0.9999799728393555, \n                    \"sender\": true, \n                    \"snd_cwnd\": 16698336, \n                    \"snd_wnd\": -1, \n                    \"socket\": 5, \n                    \"start\": 16.000062\n                }\n            ], \n            \"sum\": {\n                \"bits_per_second\": 870335510.3490804, \n                \"bytes\": 108789760, \n                \"end\": 17.000042, \n                \"omitted\": false, \n                \"retransmits\": 0, \n                \"seconds\": 0.9999799728393555, \n                \"sender\": true, \n                \"start\": 16.000062\n            }\n        }, \n        {\n            \"streams\": [\n                {\n                    \"bits_per_second\": 870251892.5339226, \n                    \"bytes\": 108789760, \n                    \"end\": 18.000118, \n                    \"omitted\": false, \n                    \"pmtu\": 1500, \n                    \"retransmits\": 0, \n                    \"rtt\": 77092, \n                    \"rttvar\": 6, \n                    \"seconds\": 1.0000760555267334, \n                    \"sender\": true, \n                    \"snd_cwnd\": 16698336, \n                    \"snd_wnd\": -1, \n                    \"socket\": 5, \n                    \"start\": 17.000042\n                }\n            ], \n            \"sum\": {\n                \"bits_per_second\": 870251892.5339226, \n                \"bytes\": 108789760, \n                \"end\": 18.000118, \n                \"omitted\": false, \n                \"retransmits\": 0, \n                \"seconds\": 1.0000760555267334, \n                \"sender\": true, \n                \"start\": 17.000042\n            }\n        }, \n        {\n            \"streams\": [\n                {\n                    \"bits_per_second\": 859878755.0075743, \n                    \"bytes\": 107479040, \n                    \"end\": 19.000064, \n                    \"omitted\": false, \n                    \"pmtu\": 1500, \n                    \"retransmits\": 0, \n                    \"rtt\": 77089, \n                    \"rttvar\": 7, \n                    \"seconds\": 0.9999459981918335, \n                    \"sender\": true, \n                    \"snd_cwnd\": 16698336, \n                    \"snd_wnd\": -1, \n                    \"socket\": 5, \n                    \"start\": 18.000118\n                }\n            ], \n            \"sum\": {\n                \"bits_per_second\": 859878755.0075743, \n                \"bytes\": 107479040, \n                \"end\": 19.000064, \n                \"omitted\": false, \n                \"retransmits\": 0, \n                \"seconds\": 0.9999459981918335, \n                \"sender\": true, \n                \"start\": 18.000118\n            }\n        }, \n        {\n            \"streams\": [\n                {\n                    \"bits_per_second\": 870319843.7535744, \n                    \"bytes\": 108789760, \n                    \"end\": 20.000062, \n                    \"omitted\": false, \n                    \"pmtu\": 1500, \n                    \"retransmits\": 0, \n                    \"rtt\": 77090, \n                    \"rttvar\": 10, \n                    \"seconds\": 0.9999979734420776, \n                    \"sender\": true, \n                    \"snd_cwnd\": 16698336, \n                    \"snd_wnd\": -1, \n                    \"socket\": 5, \n                    \"start\": 19.000064\n                }\n            ], \n            \"sum\": {\n                \"bits_per_second\": 870319843.7535744, \n                \"bytes\": 108789760, \n                \"end\": 20.000062, \n                \"omitted\": false, \n                \"retransmits\": 0, \n                \"seconds\": 0.9999979734420776, \n                \"sender\": true, \n                \"start\": 19.000064\n            }\n        }, \n        {\n            \"streams\": [\n                {\n                    \"bits_per_second\": 859807413.221496, \n                    \"bytes\": 107479040, \n                    \"end\": 21.000091, \n                    \"omitted\": false, \n                    \"pmtu\": 1500, \n                    \"retransmits\": 0, \n                    \"rtt\": 77093, \n                    \"rttvar\": 9, \n                    \"seconds\": 1.0000289678573608, \n                    \"sender\": true, \n                    \"snd_cwnd\": 16698336, \n                    \"snd_wnd\": -1, \n                    \"socket\": 5, \n                    \"start\": 20.000062\n                }\n            ], \n            \"sum\": {\n                \"bits_per_second\": 859807413.221496, \n                \"bytes\": 107479040, \n                \"end\": 21.000091, \n                \"omitted\": false, \n                \"retransmits\": 0, \n                \"seconds\": 1.0000289678573608, \n                \"sender\": true, \n                \"start\": 20.000062\n            }\n        }, \n        {\n            \"streams\": [\n                {\n                    \"bits_per_second\": 870337222.296018, \n                    \"bytes\": 108789760, \n                    \"end\": 22.000069, \n                    \"omitted\": false, \n                    \"pmtu\": 1500, \n                    \"retransmits\": 0, \n                    \"rtt\": 77093, \n                    \"rttvar\": 6, \n                    \"seconds\": 0.999978005886078, \n                    \"sender\": true, \n                    \"snd_cwnd\": 16698336, \n                    \"snd_wnd\": -1, \n                    \"socket\": 5, \n                    \"start\": 21.000091\n                }\n            ], \n            \"sum\": {\n                \"bits_per_second\": 870337222.296018, \n                \"bytes\": 108789760, \n                \"end\": 22.000069, \n                \"omitted\": false, \n                \"retransmits\": 0, \n                \"seconds\": 0.999978005886078, \n                \"sender\": true, \n                \"start\": 21.000091\n            }\n        }, \n        {\n            \"streams\": [\n                {\n                    \"bits_per_second\": 859822890.10342, \n                    \"bytes\": 107479040, \n                    \"end\": 23.00008, \n                    \"omitted\": false, \n                    \"pmtu\": 1500, \n                    \"retransmits\": 0, \n                    \"rtt\": 77092, \n                    \"rttvar\": 11, \n                    \"seconds\": 1.0000109672546387, \n                    \"sender\": true, \n                    \"snd_cwnd\": 16698336, \n                    \"snd_wnd\": -1, \n                    \"socket\": 5, \n                    \"start\": 22.000069\n                }\n            ], \n            \"sum\": {\n                \"bits_per_second\": 859822890.10342, \n                \"bytes\": 107479040, \n                \"end\": 23.00008, \n                \"omitted\": false, \n                \"retransmits\": 0, \n                \"seconds\": 1.0000109672546387, \n                \"sender\": true, \n                \"start\": 22.000069\n            }\n        }, \n        {\n            \"streams\": [\n                {\n                    \"bits_per_second\": 870352007.5725455, \n                    \"bytes\": 108789760, \n                    \"end\": 24.000041, \n                    \"omitted\": false, \n                    \"pmtu\": 1500, \n                    \"retransmits\": 0, \n                    \"rtt\": 77088, \n                    \"rttvar\": 8, \n                    \"seconds\": 0.999961018562317, \n                    \"sender\": true, \n                    \"snd_cwnd\": 16698336, \n                    \"snd_wnd\": -1, \n                    \"socket\": 5, \n                    \"start\": 23.00008\n                }\n            ], \n            \"sum\": {\n                \"bits_per_second\": 870352007.5725455, \n                \"bytes\": 108789760, \n                \"end\": 24.000041, \n                \"omitted\": false, \n                \"retransmits\": 0, \n                \"seconds\": 0.999961018562317, \n                \"sender\": true, \n                \"start\": 23.00008\n            }\n        }, \n        {\n            \"streams\": [\n                {\n                    \"bits_per_second\": 859810795.5388423, \n                    \"bytes\": 107479040, \n                    \"end\": 25.000066, \n                    \"omitted\": false, \n                    \"pmtu\": 1500, \n                    \"retransmits\": 0, \n                    \"rtt\": 77090, \n                    \"rttvar\": 8, \n                    \"seconds\": 1.0000250339508057, \n                    \"sender\": true, \n                    \"snd_cwnd\": 16698336, \n                    \"snd_wnd\": -1, \n                    \"socket\": 5, \n                    \"start\": 24.000041\n                }\n            ], \n            \"sum\": {\n                \"bits_per_second\": 859810795.5388423, \n                \"bytes\": 107479040, \n                \"end\": 25.000066, \n                \"omitted\": false, \n                \"retransmits\": 0, \n                \"seconds\": 1.0000250339508057, \n                \"sender\": true, \n                \"start\": 24.000041\n            }\n        }, \n        {\n            \"streams\": [\n                {\n                    \"bits_per_second\": 870321555.63888, \n                    \"bytes\": 108789760, \n                    \"end\": 26.000062, \n                    \"omitted\": false, \n                    \"pmtu\": 1500, \n                    \"retransmits\": 0, \n                    \"rtt\": 77094, \n                    \"rttvar\": 9, \n                    \"seconds\": 0.9999960064888, \n                    \"sender\": true, \n                    \"snd_cwnd\": 16698336, \n                    \"snd_wnd\": -1, \n                    \"socket\": 5, \n                    \"start\": 25.000066\n                }\n            ], \n            \"sum\": {\n                \"bits_per_second\": 870321555.63888, \n                \"bytes\": 108789760, \n                \"end\": 26.000062, \n                \"omitted\": false, \n                \"retransmits\": 0, \n                \"seconds\": 0.9999960064888, \n                \"sender\": true, \n                \"start\": 25.000066\n            }\n        }, \n        {\n            \"streams\": [\n                {\n                    \"bits_per_second\": 859830577.5035312, \n                    \"bytes\": 107479040, \n                    \"end\": 27.000064, \n                    \"omitted\": false, \n                    \"pmtu\": 1500, \n                    \"retransmits\": 0, \n                    \"rtt\": 77089, \n                    \"rttvar\": 8, \n                    \"seconds\": 1.0000020265579224, \n                    \"sender\": true, \n                    \"snd_cwnd\": 16698336, \n                    \"snd_wnd\": -1, \n                    \"socket\": 5, \n                    \"start\": 26.000062\n                }\n            ], \n            \"sum\": {\n                \"bits_per_second\": 859830577.5035312, \n                \"bytes\": 107479040, \n                \"end\": 27.000064, \n                \"omitted\": false, \n                \"retransmits\": 0, \n                \"seconds\": 1.0000020265579224, \n                \"sender\": true, \n                \"start\": 26.000062\n            }\n        }, \n        {\n            \"streams\": [\n                {\n                    \"bits_per_second\": 870318961.8758936, \n                    \"bytes\": 108789760, \n                    \"end\": 28.000063, \n                    \"omitted\": false, \n                    \"pmtu\": 1500, \n                    \"retransmits\": 0, \n                    \"rtt\": 77087, \n                    \"rttvar\": 11, \n                    \"seconds\": 0.9999989867210388, \n                    \"sender\": true, \n                    \"snd_cwnd\": 16698336, \n                    \"snd_wnd\": -1, \n                    \"socket\": 5, \n                    \"start\": 27.000064\n                }\n            ], \n            \"sum\": {\n                \"bits_per_second\": 870318961.8758936, \n                \"bytes\": 108789760, \n                \"end\": 28.000063, \n                \"omitted\": false, \n                \"retransmits\": 0, \n                \"seconds\": 0.9999989867210388, \n                \"sender\": true, \n                \"start\": 27.000064\n            }\n        }, \n        {\n            \"streams\": [\n                {\n                    \"bits_per_second\": 870318080, \n                    \"bytes\": 108789760, \n                    \"end\": 29.000063, \n                    \"omitted\": false, \n                    \"pmtu\": 1500, \n                    \"retransmits\": 0, \n                    \"rtt\": 77089, \n                    \"rttvar\": 16, \n                    \"seconds\": 1, \n                    \"sender\": true, \n                    \"snd_cwnd\": 16698336, \n                    \"snd_wnd\": -1, \n                    \"socket\": 5, \n                    \"start\": 28.000063\n                }\n            ], \n            \"sum\": {\n                \"bits_per_second\": 870318080, \n                \"bytes\": 108789760, \n                \"end\": 29.000063, \n                \"omitted\": false, \n                \"retransmits\": 0, \n                \"seconds\": 1, \n                \"sender\": true, \n                \"start\": 28.000063\n            }\n        }, \n        {\n            \"streams\": [\n                {\n                    \"bits_per_second\": 859744588.9523526, \n                    \"bytes\": 107479040, \n                    \"end\": 30.000165, \n                    \"omitted\": false, \n                    \"pmtu\": 1500, \n                    \"retransmits\": 0, \n                    \"rtt\": 77087, \n                    \"rttvar\": 9, \n                    \"seconds\": 1.0001020431518555, \n                    \"sender\": true, \n                    \"snd_cwnd\": 16698336, \n                    \"snd_wnd\": -1, \n                    \"socket\": 5, \n                    \"start\": 29.000063\n                }\n            ], \n            \"sum\": {\n                \"bits_per_second\": 859744588.9523526, \n                \"bytes\": 107479040, \n                \"end\": 30.000165, \n                \"omitted\": false, \n                \"retransmits\": 0, \n                \"seconds\": 1.0001020431518555, \n                \"sender\": true, \n                \"start\": 29.000063\n            }\n        }, \n        {\n            \"streams\": [\n                {\n                    \"bits_per_second\": 870426875.4734485, \n                    \"bytes\": 108789760, \n                    \"end\": 31.00004, \n                    \"omitted\": false, \n                    \"pmtu\": 1500, \n                    \"retransmits\": 0, \n                    \"rtt\": 77087, \n                    \"rttvar\": 13, \n                    \"seconds\": 0.999875009059906, \n                    \"sender\": true, \n                    \"snd_cwnd\": 16698336, \n                    \"snd_wnd\": -1, \n                    \"socket\": 5, \n                    \"start\": 30.000165\n                }\n            ], \n            \"sum\": {\n                \"bits_per_second\": 870426875.4734485, \n                \"bytes\": 108789760, \n                \"end\": 31.00004, \n                \"omitted\": false, \n                \"retransmits\": 0, \n                \"seconds\": 0.999875009059906, \n                \"sender\": true, \n                \"start\": 30.000165\n            }\n        }, \n        {\n            \"streams\": [\n                {\n                    \"bits_per_second\": 859809155.6240784, \n                    \"bytes\": 107479040, \n                    \"end\": 32.000067, \n                    \"omitted\": false, \n                    \"pmtu\": 1500, \n                    \"retransmits\": 0, \n                    \"rtt\": 77089, \n                    \"rttvar\": 3, \n                    \"seconds\": 1.0000269412994385, \n                    \"sender\": true, \n                    \"snd_cwnd\": 16698336, \n                    \"snd_wnd\": -1, \n                    \"socket\": 5, \n                    \"start\": 31.00004\n                }\n            ], \n            \"sum\": {\n                \"bits_per_second\": 859809155.6240784, \n                \"bytes\": 107479040, \n                \"end\": 32.000067, \n                \"omitted\": false, \n                \"retransmits\": 0, \n                \"seconds\": 1.0000269412994385, \n                \"sender\": true, \n                \"start\": 31.00004\n            }\n        }, \n        {\n            \"streams\": [\n                {\n                    \"bits_per_second\": 870311128.8055193, \n                    \"bytes\": 108789760, \n                    \"end\": 33.000075, \n                    \"omitted\": false, \n                    \"pmtu\": 1500, \n                    \"retransmits\": 0, \n                    \"rtt\": 77088, \n                    \"rttvar\": 6, \n                    \"seconds\": 1.0000079870224, \n                    \"sender\": true, \n                    \"snd_cwnd\": 16698336, \n                    \"snd_wnd\": -1, \n                    \"socket\": 5, \n                    \"start\": 32.000067\n                }\n            ], \n            \"sum\": {\n                \"bits_per_second\": 870311128.8055193, \n                \"bytes\": 108789760, \n                \"end\": 33.000075, \n                \"omitted\": false, \n                \"retransmits\": 0, \n                \"seconds\": 1.0000079870224, \n                \"sender\": true, \n                \"start\": 32.000067\n            }\n        }, \n        {\n            \"streams\": [\n                {\n                    \"bits_per_second\": 859843492.6451752, \n                    \"bytes\": 107479040, \n                    \"end\": 34.000062, \n                    \"omitted\": false, \n                    \"pmtu\": 1500, \n                    \"retransmits\": 0, \n                    \"rtt\": 77086, \n                    \"rttvar\": 7, \n                    \"seconds\": 0.999987006187439, \n                    \"sender\": true, \n                    \"snd_cwnd\": 16698336, \n                    \"snd_wnd\": -1, \n                    \"socket\": 5, \n                    \"start\": 33.000075\n                }\n            ], \n            \"sum\": {\n                \"bits_per_second\": 859843492.6451752, \n                \"bytes\": 107479040, \n                \"end\": 34.000062, \n                \"omitted\": false, \n                \"retransmits\": 0, \n                \"seconds\": 0.999987006187439, \n                \"sender\": true, \n                \"start\": 33.000075\n            }\n        }, \n        {\n            \"streams\": [\n                {\n                    \"bits_per_second\": 870318080, \n                    \"bytes\": 108789760, \n                    \"end\": 35.000062, \n                    \"omitted\": false, \n                    \"pmtu\": 1500, \n                    \"retransmits\": 0, \n                    \"rtt\": 77089, \n                    \"rttvar\": 5, \n                    \"seconds\": 1, \n                    \"sender\": true, \n                    \"snd_cwnd\": 16698336, \n                    \"snd_wnd\": -1, \n                    \"socket\": 5, \n                    \"start\": 34.000062\n                }\n            ], \n            \"sum\": {\n                \"bits_per_second\": 870318080, \n                \"bytes\": 108789760, \n                \"end\": 35.000062, \n                \"omitted\": false, \n                \"retransmits\": 0, \n                \"seconds\": 1, \n                \"sender\": true, \n                \"start\": 34.000062\n            }\n        }, \n        {\n            \"streams\": [\n                {\n                    \"bits_per_second\": 859764367.870648, \n                    \"bytes\": 107479040, \n                    \"end\": 36.000141, \n                    \"omitted\": false, \n                    \"pmtu\": 1500, \n                    \"retransmits\": 0, \n                    \"rtt\": 77089, \n                    \"rttvar\": 9, \n                    \"seconds\": 1.0000790357589722, \n                    \"sender\": true, \n                    \"snd_cwnd\": 16698336, \n                    \"snd_wnd\": -1, \n                    \"socket\": 5, \n                    \"start\": 35.000062\n                }\n            ], \n            \"sum\": {\n                \"bits_per_second\": 859764367.870648, \n                \"bytes\": 107479040, \n                \"end\": 36.000141, \n                \"omitted\": false, \n                \"retransmits\": 0, \n                \"seconds\": 1.0000790357589722, \n                \"sender\": true, \n                \"start\": 35.000062\n            }\n        }, \n        {\n            \"streams\": [\n                {\n                    \"bits_per_second\": 870384225.6517998, \n                    \"bytes\": 108789760, \n                    \"end\": 37.000065, \n                    \"omitted\": false, \n                    \"pmtu\": 1500, \n                    \"retransmits\": 0, \n                    \"rtt\": 77082, \n                    \"rttvar\": 12, \n                    \"seconds\": 0.9999240040779114, \n                    \"sender\": true, \n                    \"snd_cwnd\": 16698336, \n                    \"snd_wnd\": -1, \n                    \"socket\": 5, \n                    \"start\": 36.000141\n                }\n            ], \n            \"sum\": {\n                \"bits_per_second\": 870384225.6517998, \n                \"bytes\": 108789760, \n                \"end\": 37.000065, \n                \"omitted\": false, \n                \"retransmits\": 0, \n                \"seconds\": 0.9999240040779114, \n                \"sender\": true, \n                \"start\": 36.000141\n            }\n        }, \n        {\n            \"streams\": [\n                {\n                    \"bits_per_second\": 859830577.5035312, \n                    \"bytes\": 107479040, \n                    \"end\": 38.000067, \n                    \"omitted\": false, \n                    \"pmtu\": 1500, \n                    \"retransmits\": 0, \n                    \"rtt\": 77086, \n                    \"rttvar\": 8, \n                    \"seconds\": 1.0000020265579224, \n                    \"sender\": true, \n                    \"snd_cwnd\": 16698336, \n                    \"snd_wnd\": -1, \n                    \"socket\": 5, \n                    \"start\": 37.000065\n                }\n            ], \n            \"sum\": {\n                \"bits_per_second\": 859830577.5035312, \n                \"bytes\": 107479040, \n                \"end\": 38.000067, \n                \"omitted\": false, \n                \"retransmits\": 0, \n                \"seconds\": 1.0000020265579224, \n                \"sender\": true, \n                \"start\": 37.000065\n            }\n        }, \n        {\n            \"streams\": [\n                {\n                    \"bits_per_second\": 870321555.63888, \n                    \"bytes\": 108789760, \n                    \"end\": 39.000063, \n                    \"omitted\": false, \n                    \"pmtu\": 1500, \n                    \"retransmits\": 0, \n                    \"rtt\": 77087, \n                    \"rttvar\": 4, \n                    \"seconds\": 0.9999960064888, \n                    \"sender\": true, \n                    \"snd_cwnd\": 16698336, \n                    \"snd_wnd\": -1, \n                    \"socket\": 5, \n                    \"start\": 38.000067\n                }\n            ], \n            \"sum\": {\n                \"bits_per_second\": 870321555.63888, \n                \"bytes\": 108789760, \n                \"end\": 39.000063, \n                \"omitted\": false, \n                \"retransmits\": 0, \n                \"seconds\": 0.9999960064888, \n                \"sender\": true, \n                \"start\": 38.000067\n            }\n        }, \n        {\n            \"streams\": [\n                {\n                    \"bits_per_second\": 870319843.7535744, \n                    \"bytes\": 108789760, \n                    \"end\": 40.000061, \n                    \"omitted\": false, \n                    \"pmtu\": 1500, \n                    \"retransmits\": 0, \n                    \"rtt\": 77086, \n                    \"rttvar\": 13, \n                    \"seconds\": 0.9999979734420776, \n                    \"sender\": true, \n                    \"snd_cwnd\": 16698336, \n                    \"snd_wnd\": -1, \n                    \"socket\": 5, \n                    \"start\": 39.000063\n                }\n            ], \n            \"sum\": {\n                \"bits_per_second\": 870319843.7535744, \n                \"bytes\": 108789760, \n                \"end\": 40.000061, \n                \"omitted\": false, \n                \"retransmits\": 0, \n                \"seconds\": 0.9999979734420776, \n                \"sender\": true, \n                \"start\": 39.000063\n            }\n        }, \n        {\n            \"streams\": [\n                {\n                    \"bits_per_second\": 859741207.155871, \n                    \"bytes\": 107479040, \n                    \"end\": 41.000167, \n                    \"omitted\": false, \n                    \"pmtu\": 1500, \n                    \"retransmits\": 0, \n                    \"rtt\": 77090, \n                    \"rttvar\": 5, \n                    \"seconds\": 1.0001059770584106, \n                    \"sender\": true, \n                    \"snd_cwnd\": 16698336, \n                    \"snd_wnd\": -1, \n                    \"socket\": 5, \n                    \"start\": 40.000061\n                }\n            ], \n            \"sum\": {\n                \"bits_per_second\": 859741207.155871, \n                \"bytes\": 107479040, \n                \"end\": 41.000167, \n                \"omitted\": false, \n                \"retransmits\": 0, \n                \"seconds\": 1.0001059770584106, \n                \"sender\": true, \n                \"start\": 40.000061\n            }\n        }, \n        {\n            \"streams\": [\n                {\n                    \"bits_per_second\": 870401658.6504797, \n                    \"bytes\": 108789760, \n                    \"end\": 42.000071, \n                    \"omitted\": false, \n                    \"pmtu\": 1500, \n                    \"retransmits\": 0, \n                    \"rtt\": 77085, \n                    \"rttvar\": 7, \n                    \"seconds\": 0.999903976917267, \n                    \"sender\": true, \n                    \"snd_cwnd\": 16698336, \n                    \"snd_wnd\": -1, \n                    \"socket\": 5, \n                    \"start\": 41.000167\n                }\n            ], \n            \"sum\": {\n                \"bits_per_second\": 870401658.6504797, \n                \"bytes\": 108789760, \n                \"end\": 42.000071, \n                \"omitted\": false, \n                \"retransmits\": 0, \n                \"seconds\": 0.999903976917267, \n                \"sender\": true, \n                \"start\": 41.000167\n            }\n        }, \n        {\n            \"streams\": [\n                {\n                    \"bits_per_second\": 859851231.6659453, \n                    \"bytes\": 107479040, \n                    \"end\": 43.000049, \n                    \"omitted\": false, \n                    \"pmtu\": 1500, \n                    \"retransmits\": 0, \n                    \"rtt\": 77090, \n                    \"rttvar\": 15, \n                    \"seconds\": 0.999978005886078, \n                    \"sender\": true, \n                    \"snd_cwnd\": 16698336, \n                    \"snd_wnd\": -1, \n                    \"socket\": 5, \n                    \"start\": 42.000071\n                }\n            ], \n            \"sum\": {\n                \"bits_per_second\": 859851231.6659453, \n                \"bytes\": 107479040, \n                \"end\": 43.000049, \n                \"omitted\": false, \n                \"retransmits\": 0, \n                \"seconds\": 0.999978005886078, \n                \"sender\": true, \n                \"start\": 42.000071\n            }\n        }, \n        {\n            \"streams\": [\n                {\n                    \"bits_per_second\": 870306771.396942, \n                    \"bytes\": 108789760, \n                    \"end\": 44.000062, \n                    \"omitted\": false, \n                    \"pmtu\": 1500, \n                    \"retransmits\": 0, \n                    \"rtt\": 77089, \n                    \"rttvar\": 8, \n                    \"seconds\": 1.000012993812561, \n                    \"sender\": true, \n                    \"snd_cwnd\": 16698336, \n                    \"snd_wnd\": -1, \n                    \"socket\": 5, \n                    \"start\": 43.000049\n                }\n            ], \n            \"sum\": {\n                \"bits_per_second\": 870306771.396942, \n                \"bytes\": 108789760, \n                \"end\": 44.000062, \n                \"omitted\": false, \n                \"retransmits\": 0, \n                \"seconds\": 1.000012993812561, \n                \"sender\": true, \n                \"start\": 43.000049\n            }\n        }, \n        {\n            \"streams\": [\n                {\n                    \"bits_per_second\": 859827195.030547, \n                    \"bytes\": 107479040, \n                    \"end\": 45.000068, \n                    \"omitted\": false, \n                    \"pmtu\": 1500, \n                    \"retransmits\": 0, \n                    \"rtt\": 77089, \n                    \"rttvar\": 13, \n                    \"seconds\": 1.0000059604644775, \n                    \"sender\": true, \n                    \"snd_cwnd\": 16698336, \n                    \"snd_wnd\": -1, \n                    \"socket\": 5, \n                    \"start\": 44.000062\n                }\n            ], \n            \"sum\": {\n                \"bits_per_second\": 859827195.030547, \n                \"bytes\": 107479040, \n                \"end\": 45.000068, \n                \"omitted\": false, \n                \"retransmits\": 0, \n                \"seconds\": 1.0000059604644775, \n                \"sender\": true, \n                \"start\": 44.000062\n            }\n        }, \n        {\n            \"streams\": [\n                {\n                    \"bits_per_second\": 870322437.5218172, \n                    \"bytes\": 108789760, \n                    \"end\": 46.000063, \n                    \"omitted\": false, \n                    \"pmtu\": 1500, \n                    \"retransmits\": 0, \n                    \"rtt\": 77088, \n                    \"rttvar\": 7, \n                    \"seconds\": 0.999994993209839, \n                    \"sender\": true, \n                    \"snd_cwnd\": 16698336, \n                    \"snd_wnd\": -1, \n                    \"socket\": 5, \n                    \"start\": 45.000068\n                }\n            ], \n            \"sum\": {\n                \"bits_per_second\": 870322437.5218172, \n                \"bytes\": 108789760, \n                \"end\": 46.000063, \n                \"omitted\": false, \n                \"retransmits\": 0, \n                \"seconds\": 0.999994993209839, \n                \"sender\": true, \n                \"start\": 45.000068\n            }\n        }, \n        {\n            \"streams\": [\n                {\n                    \"bits_per_second\": 859831500.000782, \n                    \"bytes\": 107479040, \n                    \"end\": 47.000064, \n                    \"omitted\": false, \n                    \"pmtu\": 1500, \n                    \"retransmits\": 0, \n                    \"rtt\": 77084, \n                    \"rttvar\": 8, \n                    \"seconds\": 1.0000009536743164, \n                    \"sender\": true, \n                    \"snd_cwnd\": 16698336, \n                    \"snd_wnd\": -1, \n                    \"socket\": 5, \n                    \"start\": 46.000063\n                }\n            ], \n            \"sum\": {\n                \"bits_per_second\": 859831500.000782, \n                \"bytes\": 107479040, \n                \"end\": 47.000064, \n                \"omitted\": false, \n                \"retransmits\": 0, \n                \"seconds\": 1.0000009536743164, \n                \"sender\": true, \n                \"start\": 46.000063\n            }\n        }, \n        {\n            \"streams\": [\n                {\n                    \"bits_per_second\": 870319843.7535744, \n                    \"bytes\": 108789760, \n                    \"end\": 48.000062, \n                    \"omitted\": false, \n                    \"pmtu\": 1500, \n                    \"retransmits\": 0, \n                    \"rtt\": 77088, \n                    \"rttvar\": 5, \n                    \"seconds\": 0.9999979734420776, \n                    \"sender\": true, \n                    \"snd_cwnd\": 16698336, \n                    \"snd_wnd\": -1, \n                    \"socket\": 5, \n                    \"start\": 47.000064\n                }\n            ], \n            \"sum\": {\n                \"bits_per_second\": 870319843.7535744, \n                \"bytes\": 108789760, \n                \"end\": 48.000062, \n                \"omitted\": false, \n                \"retransmits\": 0, \n                \"seconds\": 0.9999979734420776, \n                \"sender\": true, \n                \"start\": 47.000064\n            }\n        }, \n        {\n            \"streams\": [\n                {\n                    \"bits_per_second\": 859831500.000782, \n                    \"bytes\": 107479040, \n                    \"end\": 49.000063, \n                    \"omitted\": false, \n                    \"pmtu\": 1500, \n                    \"retransmits\": 0, \n                    \"rtt\": 77091, \n                    \"rttvar\": 5, \n                    \"seconds\": 1.0000009536743164, \n                    \"sender\": true, \n                    \"snd_cwnd\": 16698336, \n                    \"snd_wnd\": -1, \n                    \"socket\": 5, \n                    \"start\": 48.000062\n                }\n            ], \n            \"sum\": {\n                \"bits_per_second\": 859831500.000782, \n                \"bytes\": 107479040, \n                \"end\": 49.000063, \n                \"omitted\": false, \n                \"retransmits\": 0, \n                \"seconds\": 1.0000009536743164, \n                \"sender\": true, \n                \"start\": 48.000062\n            }\n        }, \n        {\n            \"streams\": [\n                {\n                    \"bits_per_second\": 870317250.0007915, \n                    \"bytes\": 108789760, \n                    \"end\": 50.000064, \n                    \"omitted\": false, \n                    \"pmtu\": 1500, \n                    \"retransmits\": 0, \n                    \"rtt\": 77090, \n                    \"rttvar\": 7, \n                    \"seconds\": 1.0000009536743164, \n                    \"sender\": true, \n                    \"snd_cwnd\": 16698336, \n                    \"snd_wnd\": -1, \n                    \"socket\": 5, \n                    \"start\": 49.000063\n                }\n            ], \n            \"sum\": {\n                \"bits_per_second\": 870317250.0007915, \n                \"bytes\": 108789760, \n                \"end\": 50.000064, \n                \"omitted\": false, \n                \"retransmits\": 0, \n                \"seconds\": 1.0000009536743164, \n                \"sender\": true, \n                \"start\": 49.000063\n            }\n        }, \n        {\n            \"streams\": [\n                {\n                    \"bits_per_second\": 870320673.75773, \n                    \"bytes\": 108789760, \n                    \"end\": 51.000061, \n                    \"omitted\": false, \n                    \"pmtu\": 1500, \n                    \"retransmits\": 0, \n                    \"rtt\": 77088, \n                    \"rttvar\": 8, \n                    \"seconds\": 0.9999970197677612, \n                    \"sender\": true, \n                    \"snd_cwnd\": 16698336, \n                    \"snd_wnd\": -1, \n                    \"socket\": 5, \n                    \"start\": 50.000064\n                }\n            ], \n            \"sum\": {\n                \"bits_per_second\": 870320673.75773, \n                \"bytes\": 108789760, \n                \"end\": 51.000061, \n                \"omitted\": false, \n                \"retransmits\": 0, \n                \"seconds\": 0.9999970197677612, \n                \"sender\": true, \n                \"start\": 50.000064\n            }\n        }, \n        {\n            \"streams\": [\n                {\n                    \"bits_per_second\": 859856408.1748105, \n                    \"bytes\": 107479040, \n                    \"end\": 52.000033, \n                    \"omitted\": false, \n                    \"pmtu\": 1500, \n                    \"retransmits\": 0, \n                    \"rtt\": 77086, \n                    \"rttvar\": 9, \n                    \"seconds\": 0.9999719858169556, \n                    \"sender\": true, \n                    \"snd_cwnd\": 16698336, \n                    \"snd_wnd\": -1, \n                    \"socket\": 5, \n                    \"start\": 51.000061\n                }\n            ], \n            \"sum\": {\n                \"bits_per_second\": 859856408.1748105, \n                \"bytes\": 107479040, \n                \"end\": 52.000033, \n                \"omitted\": false, \n                \"retransmits\": 0, \n                \"seconds\": 0.9999719858169556, \n                \"sender\": true, \n                \"start\": 51.000061\n            }\n        }, \n        {\n            \"streams\": [\n                {\n                    \"bits_per_second\": 870293699.4330016, \n                    \"bytes\": 108789760, \n                    \"end\": 53.000061, \n                    \"omitted\": false, \n                    \"pmtu\": 1500, \n                    \"retransmits\": 0, \n                    \"rtt\": 77090, \n                    \"rttvar\": 9, \n                    \"seconds\": 1.0000280141830444, \n                    \"sender\": true, \n                    \"snd_cwnd\": 16698336, \n                    \"snd_wnd\": -1, \n                    \"socket\": 5, \n                    \"start\": 52.000033\n                }\n            ], \n            \"sum\": {\n                \"bits_per_second\": 870293699.4330016, \n                \"bytes\": 108789760, \n                \"end\": 53.000061, \n                \"omitted\": false, \n                \"retransmits\": 0, \n                \"seconds\": 1.0000280141830444, \n                \"sender\": true, \n                \"start\": 52.000033\n            }\n        }, \n        {\n            \"streams\": [\n                {\n                    \"bits_per_second\": 859830577.5035312, \n                    \"bytes\": 107479040, \n                    \"end\": 54.000063, \n                    \"omitted\": false, \n                    \"pmtu\": 1500, \n                    \"retransmits\": 0, \n                    \"rtt\": 77085, \n                    \"rttvar\": 6, \n                    \"seconds\": 1.0000020265579224, \n                    \"sender\": true, \n                    \"snd_cwnd\": 16698336, \n                    \"snd_wnd\": -1, \n                    \"socket\": 5, \n                    \"start\": 53.000061\n                }\n            ], \n            \"sum\": {\n                \"bits_per_second\": 859830577.5035312, \n                \"bytes\": 107479040, \n                \"end\": 54.000063, \n                \"omitted\": false, \n                \"retransmits\": 0, \n                \"seconds\": 1.0000020265579224, \n                \"sender\": true, \n                \"start\": 53.000061\n            }\n        }, \n        {\n            \"streams\": [\n                {\n                    \"bits_per_second\": 870318961.8758936, \n                    \"bytes\": 108789760, \n                    \"end\": 55.000062, \n                    \"omitted\": false, \n                    \"pmtu\": 1500, \n                    \"retransmits\": 0, \n                    \"rtt\": 77092, \n                    \"rttvar\": 10, \n                    \"seconds\": 0.9999989867210388, \n                    \"sender\": true, \n                    \"snd_cwnd\": 16698336, \n                    \"snd_wnd\": -1, \n                    \"socket\": 5, \n                    \"start\": 54.000063\n                }\n            ], \n            \"sum\": {\n                \"bits_per_second\": 870318961.8758936, \n                \"bytes\": 108789760, \n                \"end\": 55.000062, \n                \"omitted\": false, \n                \"retransmits\": 0, \n                \"seconds\": 0.9999989867210388, \n                \"sender\": true, \n                \"start\": 54.000063\n            }\n        }, \n        {\n            \"streams\": [\n                {\n                    \"bits_per_second\": 859836625.0215544, \n                    \"bytes\": 107479040, \n                    \"end\": 56.000057, \n                    \"omitted\": false, \n                    \"pmtu\": 1500, \n                    \"retransmits\": 0, \n                    \"rtt\": 77087, \n                    \"rttvar\": 9, \n                    \"seconds\": 0.999994993209839, \n                    \"sender\": true, \n                    \"snd_cwnd\": 16698336, \n                    \"snd_wnd\": -1, \n                    \"socket\": 5, \n                    \"start\": 55.000062\n                }\n            ], \n            \"sum\": {\n                \"bits_per_second\": 859836625.0215544, \n                \"bytes\": 107479040, \n                \"end\": 56.000057, \n                \"omitted\": false, \n                \"retransmits\": 0, \n                \"seconds\": 0.999994993209839, \n                \"sender\": true, \n                \"start\": 55.000062\n            }\n        }, \n        {\n            \"streams\": [\n                {\n                    \"bits_per_second\": 870302414.031997, \n                    \"bytes\": 108789760, \n                    \"end\": 57.000075, \n                    \"omitted\": false, \n                    \"pmtu\": 1500, \n                    \"retransmits\": 0, \n                    \"rtt\": 77086, \n                    \"rttvar\": 10, \n                    \"seconds\": 1.0000180006027222, \n                    \"sender\": true, \n                    \"snd_cwnd\": 16698336, \n                    \"snd_wnd\": -1, \n                    \"socket\": 5, \n                    \"start\": 56.000057\n                }\n            ], \n            \"sum\": {\n                \"bits_per_second\": 870302414.031997, \n                \"bytes\": 108789760, \n                \"end\": 57.000075, \n                \"omitted\": false, \n                \"retransmits\": 0, \n                \"seconds\": 1.0000180006027222, \n                \"sender\": true, \n                \"start\": 56.000057\n            }\n        }, \n        {\n            \"streams\": [\n                {\n                    \"bits_per_second\": 859852974.246129, \n                    \"bytes\": 107479040, \n                    \"end\": 58.000051, \n                    \"omitted\": false, \n                    \"pmtu\": 1500, \n                    \"retransmits\": 0, \n                    \"rtt\": 77085, \n                    \"rttvar\": 8, \n                    \"seconds\": 0.9999759793281555, \n                    \"sender\": true, \n                    \"snd_cwnd\": 16698336, \n                    \"snd_wnd\": -1, \n                    \"socket\": 5, \n                    \"start\": 57.000075\n                }\n            ], \n            \"sum\": {\n                \"bits_per_second\": 859852974.246129, \n                \"bytes\": 107479040, \n                \"end\": 58.000051, \n                \"omitted\": false, \n                \"retransmits\": 0, \n                \"seconds\": 0.9999759793281555, \n                \"sender\": true, \n                \"start\": 57.000075\n            }\n        }, \n        {\n            \"streams\": [\n                {\n                    \"bits_per_second\": 870344173.907325, \n                    \"bytes\": 108789760, \n                    \"end\": 59.000021, \n                    \"omitted\": false, \n                    \"pmtu\": 1500, \n                    \"retransmits\": 0, \n                    \"rtt\": 77085, \n                    \"rttvar\": 7, \n                    \"seconds\": 0.999970018863678, \n                    \"sender\": true, \n                    \"snd_cwnd\": 16698336, \n                    \"snd_wnd\": -1, \n                    \"socket\": 5, \n                    \"start\": 58.000051\n                }\n            ], \n            \"sum\": {\n                \"bits_per_second\": 870344173.907325, \n                \"bytes\": 108789760, \n                \"end\": 59.000021, \n                \"omitted\": false, \n                \"retransmits\": 0, \n                \"seconds\": 0.999970018863678, \n                \"sender\": true, \n                \"start\": 58.000051\n            }\n        }, \n        {\n            \"streams\": [\n                {\n                    \"bits_per_second\": 859789374.6450644, \n                    \"bytes\": 107479040, \n                    \"end\": 60.000071, \n                    \"omitted\": false, \n                    \"pmtu\": 1500, \n                    \"retransmits\": 0, \n                    \"rtt\": 77088, \n                    \"rttvar\": 8, \n                    \"seconds\": 1.0000499486923218, \n                    \"sender\": true, \n                    \"snd_cwnd\": 16698336, \n                    \"snd_wnd\": -1, \n                    \"socket\": 5, \n                    \"start\": 59.000021\n                }\n            ], \n            \"sum\": {\n                \"bits_per_second\": 859789374.6450644, \n                \"bytes\": 107479040, \n                \"end\": 60.000071, \n                \"omitted\": false, \n                \"retransmits\": 0, \n                \"seconds\": 1.0000499486923218, \n                \"sender\": true, \n                \"start\": 59.000021\n            }\n        }\n    ], \n    \"start\": {\n        \"connected\": [\n            {\n                \"local_host\": \"10.0.0.1\", \n                \"local_port\": 54817, \n                \"remote_host\": \"10.0.0.2\", \n                \"remote_port\": 5201, \n                \"socket\": 5\n            }\n        ], \n        \"connecting_to\": {\n            \"host\": \"10.0.0.2\", \n            \"port\": 5201\n        }, \n        \"cookie\": \"2xth5gkq32pk7wfrgrfxkr4dfuwz4dd3vupa\", \n        \"fq_rate\": 0, \n        \"rcvbuf_actual\": 87380, \n        \"sndbuf_actual\": 87380, \n        \"sock_bufsize\": 0, \n        \"system_info\": \"REDACTED\", \n        \"target_bitrate\": 0, \n        \"tcp_mss_default\": 1448, \n        \"test_start\": {\n            \"bidir\": 0, \n            \"blksize\": 131072, \n            \"blocks\": 0, \n            \"bytes\": 0, \n            \"duration\": 60, \n            \"fqrate\": 0, \n            \"num_streams\": 1, \n            \"omit\": 0, \n            \"protocol\": \"TCP\", \n            \"reverse\": 0, \n            \"target_bitrate\": 0, \n            \"tos\": 0\n        }, \n        \"timestamp\": {\n            \"time\": \"Wed, 17 Apr 2024 01:12:34 GMT\", \n            \"timesecs\": 1713316354\n        }, \n        \"version\": \"iperf 3.14\"\n    }\n}\nParticipant 1:\n/usr/bin/iperf3 -s -1 --idle-timeout 60 --json -p 5201 -B 10.0.0.2 --authorized-users-path /var/run/pscheduler-server/runner/tmp/tmp404r_3sv/tmpo2s47c0h/credentials --rsa-private-key-path /var/run/pscheduler-server/runner/tmp/tmp404r_3sv/tmpo2s47c0h/private-key\n\n{\n    \"end\": {\n        \"cpu_utilization_percent\": {\n            \"host_system\": 5.193361916660924, \n            \"host_total\": 5.600417997043127, \n            \"host_user\": 0.40705275132005636, \n            \"remote_system\": 0, \n            \"remote_total\": 0, \n            \"remote_user\": 0\n        }, \n        \"receiver_tcp_congestion\": \"htcp\", \n        \"streams\": [\n            {\n                \"receiver\": {\n                    \"bits_per_second\": 865535640.5463626, \n                    \"bytes\": 6499843216, \n                    \"end\": 60.076955, \n                    \"seconds\": 60.076955, \n                    \"sender\": false, \n                    \"socket\": 5, \n                    \"start\": 0\n                }, \n                \"sender\": {\n                    \"bits_per_second\": 0, \n                    \"bytes\": 0, \n                    \"end\": 60.076955, \n                    \"seconds\": 60.076955, \n                    \"sender\": false, \n                    \"socket\": 5, \n                    \"start\": 0\n                }\n            }\n        ], \n        \"sum_received\": {\n            \"bits_per_second\": 865535640.5463626, \n            \"bytes\": 6499843216, \n            \"end\": 60.076955, \n            \"seconds\": 60.076955, \n            \"sender\": false, \n            \"start\": 0\n        }, \n        \"sum_sent\": {\n            \"bits_per_second\": 0, \n            \"bytes\": 0, \n            \"end\": 60.076955, \n            \"seconds\": 60.076955, \n            \"sender\": false, \n            \"start\": 0\n        }\n    }, \n    \"intervals\": [\n        {\n            \"streams\": [\n                {\n                    \"bits_per_second\": 864791224.64526, \n                    \"bytes\": 108103336, \n                    \"end\": 1.000041, \n                    \"omitted\": false, \n                    \"seconds\": 1.0000410079956055, \n                    \"sender\": false, \n                    \"socket\": 5, \n                    \"start\": 0\n                }\n            ], \n            \"sum\": {\n                \"bits_per_second\": 864791224.64526, \n                \"bytes\": 108103336, \n                \"end\": 1.000041, \n                \"omitted\": false, \n                \"seconds\": 1.0000410079956055, \n                \"sender\": false, \n                \"start\": 0\n            }\n        }, \n        {\n            \"streams\": [\n                {\n                    \"bits_per_second\": 865856453.422333, \n                    \"bytes\": 108230760, \n                    \"end\": 2.000029, \n                    \"omitted\": false, \n                    \"seconds\": 0.9999880194664, \n                    \"sender\": false, \n                    \"socket\": 5, \n                    \"start\": 1.000041\n                }\n            ], \n            \"sum\": {\n                \"bits_per_second\": 865856453.422333, \n                \"bytes\": 108230760, \n                \"end\": 2.000029, \n                \"omitted\": false, \n                \"seconds\": 0.9999880194664, \n                \"sender\": false, \n                \"start\": 1.000041\n            }\n        }, \n        {\n            \"streams\": [\n                {\n                    \"bits_per_second\": 865303138.0438102, \n                    \"bytes\": 108165600, \n                    \"end\": 3.000054, \n                    \"omitted\": false, \n                    \"seconds\": 1.0000250339508057, \n                    \"sender\": false, \n                    \"socket\": 5, \n                    \"start\": 2.000029\n                }\n            ], \n            \"sum\": {\n                \"bits_per_second\": 865303138.0438102, \n                \"bytes\": 108165600, \n                \"end\": 3.000054, \n                \"omitted\": false, \n                \"seconds\": 1.0000250339508057, \n                \"sender\": false, \n                \"start\": 2.000029\n            }\n        }, \n        {\n            \"streams\": [\n                {\n                    \"bits_per_second\": 865869459.258218, \n                    \"bytes\": 108230760, \n                    \"end\": 4.000027, \n                    \"omitted\": false, \n                    \"seconds\": 0.9999729990959167, \n                    \"sender\": false, \n                    \"socket\": 5, \n                    \"start\": 3.000054\n                }\n            ], \n            \"sum\": {\n                \"bits_per_second\": 865869459.258218, \n                \"bytes\": 108230760, \n                \"end\": 4.000027, \n                \"omitted\": false, \n                \"seconds\": 0.9999729990959167, \n                \"sender\": false, \n                \"start\": 3.000054\n            }\n        }, \n        {\n            \"streams\": [\n                {\n                    \"bits_per_second\": 865292823.2077606, \n                    \"bytes\": 108165600, \n                    \"end\": 5.000064, \n                    \"omitted\": false, \n                    \"seconds\": 1.0000369548797607, \n                    \"sender\": false, \n                    \"socket\": 5, \n                    \"start\": 4.000027\n                }\n            ], \n            \"sum\": {\n                \"bits_per_second\": 865292823.2077606, \n                \"bytes\": 108165600, \n                \"end\": 5.000064, \n                \"omitted\": false, \n                \"seconds\": 1.0000369548797607, \n                \"sender\": false, \n                \"start\": 4.000027\n            }\n        }, \n        {\n            \"streams\": [\n                {\n                    \"bits_per_second\": 865879007.4419992, \n                    \"bytes\": 108230760, \n                    \"end\": 6.000026, \n                    \"omitted\": false, \n                    \"seconds\": 0.9999619722366333, \n                    \"sender\": false, \n                    \"socket\": 5, \n                    \"start\": 5.000064\n                }\n            ], \n            \"sum\": {\n                \"bits_per_second\": 865879007.4419992, \n                \"bytes\": 108230760, \n                \"end\": 6.000026, \n                \"omitted\": false, \n                \"seconds\": 0.9999619722366333, \n                \"sender\": false, \n                \"start\": 5.000064\n            }\n        }, \n        {\n            \"streams\": [\n                {\n                    \"bits_per_second\": 865297980.5950457, \n                    \"bytes\": 108165600, \n                    \"end\": 7.000057, \n                    \"omitted\": false, \n                    \"seconds\": 1.0000309944152832, \n                    \"sender\": false, \n                    \"socket\": 5, \n                    \"start\": 6.000026\n                }\n            ], \n            \"sum\": {\n                \"bits_per_second\": 865297980.5950457, \n                \"bytes\": 108165600, \n                \"end\": 7.000057, \n                \"omitted\": false, \n                \"seconds\": 1.0000309944152832, \n                \"sender\": false, \n                \"start\": 6.000026\n            }\n        }, \n        {\n            \"streams\": [\n                {\n                    \"bits_per_second\": 865836584.149706, \n                    \"bytes\": 108230760, \n                    \"end\": 8.000068, \n                    \"omitted\": false, \n                    \"seconds\": 1.0000109672546387, \n                    \"sender\": false, \n                    \"socket\": 5, \n                    \"start\": 7.000057\n                }\n            ], \n            \"sum\": {\n                \"bits_per_second\": 865836584.149706, \n                \"bytes\": 108230760, \n                \"end\": 8.000068, \n                \"omitted\": false, \n                \"seconds\": 1.0000109672546387, \n                \"sender\": false, \n                \"start\": 7.000057\n            }\n        }, \n        {\n            \"streams\": [\n                {\n                    \"bits_per_second\": 865367198.6814806, \n                    \"bytes\": 108165600, \n                    \"end\": 9.000019, \n                    \"omitted\": false, \n                    \"seconds\": 0.9999510049819946, \n                    \"sender\": false, \n                    \"socket\": 5, \n                    \"start\": 8.000068\n                }\n            ], \n            \"sum\": {\n                \"bits_per_second\": 865367198.6814806, \n                \"bytes\": 108165600, \n                \"end\": 9.000019, \n                \"omitted\": false, \n                \"seconds\": 0.9999510049819946, \n                \"sender\": false, \n                \"start\": 8.000068\n            }\n        }, \n        {\n            \"streams\": [\n                {\n                    \"bits_per_second\": 865289316.219523, \n                    \"bytes\": 108165600, \n                    \"end\": 10.00006, \n                    \"omitted\": false, \n                    \"seconds\": 1.0000410079956055, \n                    \"sender\": false, \n                    \"socket\": 5, \n                    \"start\": 9.000019\n                }\n            ], \n            \"sum\": {\n                \"bits_per_second\": 865289316.219523, \n                \"bytes\": 108165600, \n                \"end\": 10.00006, \n                \"omitted\": false, \n                \"seconds\": 1.0000410079956055, \n                \"sender\": false, \n                \"start\": 9.000019\n            }\n        }, \n        {\n            \"streams\": [\n                {\n                    \"bits_per_second\": 865875497.814836, \n                    \"bytes\": 108230760, \n                    \"end\": 11.000026, \n                    \"omitted\": false, \n                    \"seconds\": 0.999966025352478, \n                    \"sender\": false, \n                    \"socket\": 5, \n                    \"start\": 10.00006\n                }\n            ], \n            \"sum\": {\n                \"bits_per_second\": 865875497.814836, \n                \"bytes\": 108230760, \n                \"end\": 11.000026, \n                \"omitted\": false, \n                \"seconds\": 0.999966025352478, \n                \"sender\": false, \n                \"start\": 10.00006\n            }\n        }, \n        {\n            \"streams\": [\n                {\n                    \"bits_per_second\": 865310977.48368, \n                    \"bytes\": 108165600, \n                    \"end\": 12.000042, \n                    \"omitted\": false, \n                    \"seconds\": 1.0000159740448, \n                    \"sender\": false, \n                    \"socket\": 5, \n                    \"start\": 11.000026\n                }\n            ], \n            \"sum\": {\n                \"bits_per_second\": 865310977.48368, \n                \"bytes\": 108165600, \n                \"end\": 12.000042, \n                \"omitted\": false, \n                \"seconds\": 1.0000159740448, \n                \"sender\": false, \n                \"start\": 11.000026\n            }\n        }, \n        {\n            \"streams\": [\n                {\n                    \"bits_per_second\": 865859911.2850132, \n                    \"bytes\": 108230760, \n                    \"end\": 13.000026, \n                    \"omitted\": false, \n                    \"seconds\": 0.9999840259552002, \n                    \"sender\": false, \n                    \"socket\": 5, \n                    \"start\": 12.000042\n                }\n            ], \n            \"sum\": {\n                \"bits_per_second\": 865859911.2850132, \n                \"bytes\": 108230760, \n                \"end\": 13.000026, \n                \"omitted\": false, \n                \"seconds\": 0.9999840259552002, \n                \"sender\": false, \n                \"start\": 12.000042\n            }\n        }, \n        {\n            \"streams\": [\n                {\n                    \"bits_per_second\": 865328255.6980808, \n                    \"bytes\": 108165600, \n                    \"end\": 14.000022, \n                    \"omitted\": false, \n                    \"seconds\": 0.9999960064888, \n                    \"sender\": false, \n                    \"socket\": 5, \n                    \"start\": 13.000026\n                }\n            ], \n            \"sum\": {\n                \"bits_per_second\": 865328255.6980808, \n                \"bytes\": 108165600, \n                \"end\": 14.000022, \n                \"omitted\": false, \n                \"seconds\": 0.9999960064888, \n                \"sender\": false, \n                \"start\": 13.000026\n            }\n        }, \n        {\n            \"streams\": [\n                {\n                    \"bits_per_second\": 865814083.9446326, \n                    \"bytes\": 108230760, \n                    \"end\": 15.000059, \n                    \"omitted\": false, \n                    \"seconds\": 1.0000369548797607, \n                    \"sender\": false, \n                    \"socket\": 5, \n                    \"start\": 14.000022\n                }\n            ], \n            \"sum\": {\n                \"bits_per_second\": 865814083.9446326, \n                \"bytes\": 108230760, \n                \"end\": 15.000059, \n                \"omitted\": false, \n                \"seconds\": 1.0000369548797607, \n                \"sender\": false, \n                \"start\": 14.000022\n            }\n        }, \n        {\n            \"streams\": [\n                {\n                    \"bits_per_second\": 865355076.9798152, \n                    \"bytes\": 108165600, \n                    \"end\": 16.000024, \n                    \"omitted\": false, \n                    \"seconds\": 0.999965012073517, \n                    \"sender\": false, \n                    \"socket\": 5, \n                    \"start\": 15.000059\n                }\n            ], \n            \"sum\": {\n                \"bits_per_second\": 865355076.9798152, \n                \"bytes\": 108165600, \n                \"end\": 16.000024, \n                \"omitted\": false, \n                \"seconds\": 0.999965012073517, \n                \"sender\": false, \n                \"start\": 15.000059\n            }\n        }, \n        {\n            \"streams\": [\n                {\n                    \"bits_per_second\": 865302312.8478764, \n                    \"bytes\": 108165600, \n                    \"end\": 17.00005, \n                    \"omitted\": false, \n                    \"seconds\": 1.000025987625122, \n                    \"sender\": false, \n                    \"socket\": 5, \n                    \"start\": 16.000024\n                }\n            ], \n            \"sum\": {\n                \"bits_per_second\": 865302312.8478764, \n                \"bytes\": 108165600, \n                \"end\": 17.00005, \n                \"omitted\": false, \n                \"seconds\": 1.000025987625122, \n                \"sender\": false, \n                \"start\": 16.000024\n            }\n        }, \n        {\n            \"streams\": [\n                {\n                    \"bits_per_second\": 865864246.5548556, \n                    \"bytes\": 108230760, \n                    \"end\": 18.000029, \n                    \"omitted\": false, \n                    \"seconds\": 0.999979019165039, \n                    \"sender\": false, \n                    \"socket\": 5, \n                    \"start\": 17.00005\n                }\n            ], \n            \"sum\": {\n                \"bits_per_second\": 865864246.5548556, \n                \"bytes\": 108230760, \n                \"end\": 18.000029, \n                \"omitted\": false, \n                \"seconds\": 0.999979019165039, \n                \"sender\": false, \n                \"start\": 17.00005\n            }\n        }, \n        {\n            \"streams\": [\n                {\n                    \"bits_per_second\": 865304066.391117, \n                    \"bytes\": 108165600, \n                    \"end\": 19.000053, \n                    \"omitted\": false, \n                    \"seconds\": 1.0000239610672, \n                    \"sender\": false, \n                    \"socket\": 5, \n                    \"start\": 18.000029\n                }\n            ], \n            \"sum\": {\n                \"bits_per_second\": 865304066.391117, \n                \"bytes\": 108165600, \n                \"end\": 19.000053, \n                \"omitted\": false, \n                \"seconds\": 1.0000239610672, \n                \"sender\": false, \n                \"start\": 18.000029\n            }\n        }, \n        {\n            \"streams\": [\n                {\n                    \"bits_per_second\": 865869459.258218, \n                    \"bytes\": 108230760, \n                    \"end\": 20.000026, \n                    \"omitted\": false, \n                    \"seconds\": 0.9999729990959167, \n                    \"sender\": false, \n                    \"socket\": 5, \n                    \"start\": 19.000053\n                }\n            ], \n            \"sum\": {\n                \"bits_per_second\": 865869459.258218, \n                \"bytes\": 108230760, \n                \"end\": 20.000026, \n                \"omitted\": false, \n                \"seconds\": 0.9999729990959167, \n                \"sender\": false, \n                \"start\": 19.000053\n            }\n        }, \n        {\n            \"streams\": [\n                {\n                    \"bits_per_second\": 865319642.2930104, \n                    \"bytes\": 108165600, \n                    \"end\": 21.000032, \n                    \"omitted\": false, \n                    \"seconds\": 1.0000059604644775, \n                    \"sender\": false, \n                    \"socket\": 5, \n                    \"start\": 20.000026\n                }\n            ], \n            \"sum\": {\n                \"bits_per_second\": 865319642.2930104, \n                \"bytes\": 108165600, \n                \"end\": 21.000032, \n                \"omitted\": false, \n                \"seconds\": 1.0000059604644775, \n                \"sender\": false, \n                \"start\": 20.000026\n            }\n        }, \n        {\n            \"streams\": [\n                {\n                    \"bits_per_second\": 865807994.6406624, \n                    \"bytes\": 108230760, \n                    \"end\": 22.000076, \n                    \"omitted\": false, \n                    \"seconds\": 1.0000439882278442, \n                    \"sender\": false, \n                    \"socket\": 5, \n                    \"start\": 21.000032\n                }\n            ], \n            \"sum\": {\n                \"bits_per_second\": 865807994.6406624, \n                \"bytes\": 108230760, \n                \"end\": 22.000076, \n                \"omitted\": false, \n                \"seconds\": 1.0000439882278442, \n                \"sender\": false, \n                \"start\": 21.000032\n            }\n        }, \n        {\n            \"streams\": [\n                {\n                    \"bits_per_second\": 865366321.7810293, \n                    \"bytes\": 108165600, \n                    \"end\": 23.000028, \n                    \"omitted\": false, \n                    \"seconds\": 0.9999520182609558, \n                    \"sender\": false, \n                    \"socket\": 5, \n                    \"start\": 22.000076\n                }\n            ], \n            \"sum\": {\n                \"bits_per_second\": 865366321.7810293, \n                \"bytes\": 108165600, \n                \"end\": 23.000028, \n                \"omitted\": false, \n                \"seconds\": 0.9999520182609558, \n                \"sender\": false, \n                \"start\": 22.000076\n            }\n        }, \n        {\n            \"streams\": [\n                {\n                    \"bits_per_second\": 865295401.8937182, \n                    \"bytes\": 108165600, \n                    \"end\": 24.000062, \n                    \"omitted\": false, \n                    \"seconds\": 1.000033974647522, \n                    \"sender\": false, \n                    \"socket\": 5, \n                    \"start\": 23.000028\n                }\n            ], \n            \"sum\": {\n                \"bits_per_second\": 865295401.8937182, \n                \"bytes\": 108165600, \n                \"end\": 24.000062, \n                \"omitted\": false, \n                \"seconds\": 1.000033974647522, \n                \"sender\": false, \n                \"start\": 23.000028\n            }\n        }, \n        {\n            \"streams\": [\n                {\n                    \"bits_per_second\": 865873794.6236725, \n                    \"bytes\": 108230760, \n                    \"end\": 25.00003, \n                    \"omitted\": false, \n                    \"seconds\": 0.9999679923057556, \n                    \"sender\": false, \n                    \"socket\": 5, \n                    \"start\": 24.000062\n                }\n            ], \n            \"sum\": {\n                \"bits_per_second\": 865873794.6236725, \n                \"bytes\": 108230760, \n                \"end\": 25.00003, \n                \"omitted\": false, \n                \"seconds\": 0.9999679923057556, \n                \"sender\": false, \n                \"start\": 24.000062\n            }\n        }, \n        {\n            \"streams\": [\n                {\n                    \"bits_per_second\": 865306645.1440877, \n                    \"bytes\": 108165600, \n                    \"end\": 26.000051, \n                    \"omitted\": false, \n                    \"seconds\": 1.000020980834961, \n                    \"sender\": false, \n                    \"socket\": 5, \n                    \"start\": 25.00003\n                }\n            ], \n            \"sum\": {\n                \"bits_per_second\": 865306645.1440877, \n                \"bytes\": 108165600, \n                \"end\": 26.000051, \n                \"omitted\": false, \n                \"seconds\": 1.000020980834961, \n                \"sender\": false, \n                \"start\": 25.00003\n            }\n        }, \n        {\n            \"streams\": [\n                {\n                    \"bits_per_second\": 865857330.787861, \n                    \"bytes\": 108230760, \n                    \"end\": 27.000038, \n                    \"omitted\": false, \n                    \"seconds\": 0.999987006187439, \n                    \"sender\": false, \n                    \"socket\": 5, \n                    \"start\": 26.000051\n                }\n            ], \n            \"sum\": {\n                \"bits_per_second\": 865857330.787861, \n                \"bytes\": 108230760, \n                \"end\": 27.000038, \n                \"omitted\": false, \n                \"seconds\": 0.999987006187439, \n                \"sender\": false, \n                \"start\": 26.000051\n            }\n        }, \n        {\n            \"streams\": [\n                {\n                    \"bits_per_second\": 865337797.6943146, \n                    \"bytes\": 108165600, \n                    \"end\": 28.000023, \n                    \"omitted\": false, \n                    \"seconds\": 0.9999849796295166, \n                    \"sender\": false, \n                    \"socket\": 5, \n                    \"start\": 27.000038\n                }\n            ], \n            \"sum\": {\n                \"bits_per_second\": 865337797.6943146, \n                \"bytes\": 108165600, \n                \"end\": 28.000023, \n                \"omitted\": false, \n                \"seconds\": 0.9999849796295166, \n                \"sender\": false, \n                \"start\": 27.000038\n            }\n        }, \n        {\n            \"streams\": [\n                {\n                    \"bits_per_second\": 865300559.311743, \n                    \"bytes\": 108165600, \n                    \"end\": 29.000051, \n                    \"omitted\": false, \n                    \"seconds\": 1.0000280141830444, \n                    \"sender\": false, \n                    \"socket\": 5, \n                    \"start\": 28.000023\n                }\n            ], \n            \"sum\": {\n                \"bits_per_second\": 865300559.311743, \n                \"bytes\": 108165600, \n                \"end\": 29.000051, \n                \"omitted\": false, \n                \"seconds\": 1.0000280141830444, \n                \"sender\": false, \n                \"start\": 28.000023\n            }\n        }, \n        {\n            \"streams\": [\n                {\n                    \"bits_per_second\": 865869459.258218, \n                    \"bytes\": 108230760, \n                    \"end\": 30.000024, \n                    \"omitted\": false, \n                    \"seconds\": 0.9999729990959167, \n                    \"sender\": false, \n                    \"socket\": 5, \n                    \"start\": 29.000051\n                }\n            ], \n            \"sum\": {\n                \"bits_per_second\": 865869459.258218, \n                \"bytes\": 108230760, \n                \"end\": 30.000024, \n                \"omitted\": false, \n                \"seconds\": 0.9999729990959167, \n                \"sender\": false, \n                \"start\": 29.000051\n            }\n        }, \n        {\n            \"streams\": [\n                {\n                    \"bits_per_second\": 865324800, \n                    \"bytes\": 108165600, \n                    \"end\": 31.000024, \n                    \"omitted\": false, \n                    \"seconds\": 1, \n                    \"sender\": false, \n                    \"socket\": 5, \n                    \"start\": 30.000024\n                }\n            ], \n            \"sum\": {\n                \"bits_per_second\": 865324800, \n                \"bytes\": 108165600, \n                \"end\": 31.000024, \n                \"omitted\": false, \n                \"seconds\": 1, \n                \"sender\": false, \n                \"start\": 30.000024\n            }\n        }, \n        {\n            \"streams\": [\n                {\n                    \"bits_per_second\": 865841744.9120705, \n                    \"bytes\": 108230760, \n                    \"end\": 32.000029, \n                    \"omitted\": false, \n                    \"seconds\": 1.0000050067901611, \n                    \"sender\": false, \n                    \"socket\": 5, \n                    \"start\": 31.000024\n                }\n            ], \n            \"sum\": {\n                \"bits_per_second\": 865841744.9120705, \n                \"bytes\": 108230760, \n                \"end\": 32.000029, \n                \"omitted\": false, \n                \"seconds\": 1.0000050067901611, \n                \"sender\": false, \n                \"start\": 31.000024\n            }\n        }, \n        {\n            \"streams\": [\n                {\n                    \"bits_per_second\": 865311802.6961398, \n                    \"bytes\": 108165600, \n                    \"end\": 33.000044, \n                    \"omitted\": false, \n                    \"seconds\": 1.0000150203704834, \n                    \"sender\": false, \n                    \"socket\": 5, \n                    \"start\": 32.000029\n                }\n            ], \n            \"sum\": {\n                \"bits_per_second\": 865311802.6961398, \n                \"bytes\": 108165600, \n                \"end\": 33.000044, \n                \"omitted\": false, \n                \"seconds\": 1.0000150203704834, \n                \"sender\": false, \n                \"start\": 32.000029\n            }\n        }, \n        {\n            \"streams\": [\n                {\n                    \"bits_per_second\": 865865123.936177, \n                    \"bytes\": 108230760, \n                    \"end\": 34.000022, \n                    \"omitted\": false, \n                    \"seconds\": 0.999978005886078, \n                    \"sender\": false, \n                    \"socket\": 5, \n                    \"start\": 33.000044\n                }\n            ], \n            \"sum\": {\n                \"bits_per_second\": 865865123.936177, \n                \"bytes\": 108230760, \n                \"end\": 34.000022, \n                \"omitted\": false, \n                \"seconds\": 0.999978005886078, \n                \"sender\": false, \n                \"start\": 33.000044\n            }\n        }, \n        {\n            \"streams\": [\n                {\n                    \"bits_per_second\": 865322221.1388197, \n                    \"bytes\": 108165600, \n                    \"end\": 35.000025, \n                    \"omitted\": false, \n                    \"seconds\": 1.0000029802322388, \n                    \"sender\": false, \n                    \"socket\": 5, \n                    \"start\": 34.000022\n                }\n            ], \n            \"sum\": {\n                \"bits_per_second\": 865322221.1388197, \n                \"bytes\": 108165600, \n                \"end\": 35.000025, \n                \"omitted\": false, \n                \"seconds\": 1.0000029802322388, \n                \"sender\": false, \n                \"start\": 34.000022\n            }\n        }, \n        {\n            \"streams\": [\n                {\n                    \"bits_per_second\": 865812329.3906366, \n                    \"bytes\": 108230760, \n                    \"end\": 36.000064, \n                    \"omitted\": false, \n                    \"seconds\": 1.000038981437683, \n                    \"sender\": false, \n                    \"socket\": 5, \n                    \"start\": 35.000025\n                }\n            ], \n            \"sum\": {\n                \"bits_per_second\": 865812329.3906366, \n                \"bytes\": 108230760, \n                \"end\": 36.000064, \n                \"omitted\": false, \n                \"seconds\": 1.000038981437683, \n                \"sender\": false, \n                \"start\": 35.000025\n            }\n        }, \n        {\n            \"streams\": [\n                {\n                    \"bits_per_second\": 865360286.6908338, \n                    \"bytes\": 108165600, \n                    \"end\": 37.000023, \n                    \"omitted\": false, \n                    \"seconds\": 0.9999589920043945, \n                    \"sender\": false, \n                    \"socket\": 5, \n                    \"start\": 36.000064\n                }\n            ], \n            \"sum\": {\n                \"bits_per_second\": 865360286.6908338, \n                \"bytes\": 108165600, \n                \"end\": 37.000023, \n                \"omitted\": false, \n                \"seconds\": 0.9999589920043945, \n                \"sender\": false, \n                \"start\": 36.000064\n            }\n        }, \n        {\n            \"streams\": [\n                {\n                    \"bits_per_second\": 865294473.565003, \n                    \"bytes\": 108165600, \n                    \"end\": 38.000058, \n                    \"omitted\": false, \n                    \"seconds\": 1.000035047531128, \n                    \"sender\": false, \n                    \"socket\": 5, \n                    \"start\": 37.000023\n                }\n            ], \n            \"sum\": {\n                \"bits_per_second\": 865294473.565003, \n                \"bytes\": 108165600, \n                \"end\": 38.000058, \n                \"omitted\": false, \n                \"seconds\": 1.000035047531128, \n                \"sender\": false, \n                \"start\": 37.000023\n            }\n        }, \n        {\n            \"streams\": [\n                {\n                    \"bits_per_second\": 865878130.032541, \n                    \"bytes\": 108230760, \n                    \"end\": 39.000021, \n                    \"omitted\": false, \n                    \"seconds\": 0.9999629855155945, \n                    \"sender\": false, \n                    \"socket\": 5, \n                    \"start\": 38.000058\n                }\n            ], \n            \"sum\": {\n                \"bits_per_second\": 865878130.032541, \n                \"bytes\": 108230760, \n                \"end\": 39.000021, \n                \"omitted\": false, \n                \"seconds\": 0.9999629855155945, \n                \"sender\": false, \n                \"start\": 38.000058\n            }\n        }, \n        {\n            \"streams\": [\n                {\n                    \"bits_per_second\": 865308398.704887, \n                    \"bytes\": 108165600, \n                    \"end\": 40.00004, \n                    \"omitted\": false, \n                    \"seconds\": 1.0000189542770386, \n                    \"sender\": false, \n                    \"socket\": 5, \n                    \"start\": 39.000021\n                }\n            ], \n            \"sum\": {\n                \"bits_per_second\": 865308398.704887, \n                \"bytes\": 108165600, \n                \"end\": 40.00004, \n                \"omitted\": false, \n                \"seconds\": 1.0000189542770386, \n                \"sender\": false, \n                \"start\": 39.000021\n            }\n        }, \n        {\n            \"streams\": [\n                {\n                    \"bits_per_second\": 865854750.3060896, \n                    \"bytes\": 108230760, \n                    \"end\": 41.00003, \n                    \"omitted\": false, \n                    \"seconds\": 0.9999899864196777, \n                    \"sender\": false, \n                    \"socket\": 5, \n                    \"start\": 40.00004\n                }\n            ], \n            \"sum\": {\n                \"bits_per_second\": 865854750.3060896, \n                \"bytes\": 108230760, \n                \"end\": 41.00003, \n                \"omitted\": false, \n                \"seconds\": 0.9999899864196777, \n                \"sender\": false, \n                \"start\": 40.00004\n            }\n        }, \n        {\n            \"streams\": [\n                {\n                    \"bits_per_second\": 865324800, \n                    \"bytes\": 108165600, \n                    \"end\": 42.00003, \n                    \"omitted\": false, \n                    \"seconds\": 1, \n                    \"sender\": false, \n                    \"socket\": 5, \n                    \"start\": 41.00003\n                }\n            ], \n            \"sum\": {\n                \"bits_per_second\": 865324800, \n                \"bytes\": 108165600, \n                \"end\": 42.00003, \n                \"omitted\": false, \n                \"seconds\": 1, \n                \"sender\": false, \n                \"start\": 41.00003\n            }\n        }, \n        {\n            \"streams\": [\n                {\n                    \"bits_per_second\": 865819244.4387777, \n                    \"bytes\": 108230760, \n                    \"end\": 43.000061, \n                    \"omitted\": false, \n                    \"seconds\": 1.0000309944152832, \n                    \"sender\": false, \n                    \"socket\": 5, \n                    \"start\": 42.00003\n                }\n            ], \n            \"sum\": {\n                \"bits_per_second\": 865819244.4387777, \n                \"bytes\": 108230760, \n                \"end\": 43.000061, \n                \"omitted\": false, \n                \"seconds\": 1.0000309944152832, \n                \"sender\": false, \n                \"start\": 42.00003\n            }\n        }, \n        {\n            \"streams\": [\n                {\n                    \"bits_per_second\": 865357707.618133, \n                    \"bytes\": 108165600, \n                    \"end\": 44.000023, \n                    \"omitted\": false, \n                    \"seconds\": 0.9999619722366333, \n                    \"sender\": false, \n                    \"socket\": 5, \n                    \"start\": 43.000061\n                }\n            ], \n            \"sum\": {\n                \"bits_per_second\": 865357707.618133, \n                \"bytes\": 108165600, \n                \"end\": 44.000023, \n                \"omitted\": false, \n                \"seconds\": 0.9999619722366333, \n                \"sender\": false, \n                \"start\": 43.000061\n            }\n        }, \n        {\n            \"streams\": [\n                {\n                    \"bits_per_second\": 865298805.7827166, \n                    \"bytes\": 108165600, \n                    \"end\": 45.000053, \n                    \"omitted\": false, \n                    \"seconds\": 1.0000300407409668, \n                    \"sender\": false, \n                    \"socket\": 5, \n                    \"start\": 44.000023\n                }\n            ], \n            \"sum\": {\n                \"bits_per_second\": 865298805.7827166, \n                \"bytes\": 108165600, \n                \"end\": 45.000053, \n                \"omitted\": false, \n                \"seconds\": 1.0000300407409668, \n                \"sender\": false, \n                \"start\": 44.000023\n            }\n        }, \n        {\n            \"streams\": [\n                {\n                    \"bits_per_second\": 865870336.6501037, \n                    \"bytes\": 108230760, \n                    \"end\": 46.000025, \n                    \"omitted\": false, \n                    \"seconds\": 0.9999719858169556, \n                    \"sender\": false, \n                    \"socket\": 5, \n                    \"start\": 45.000053\n                }\n            ], \n            \"sum\": {\n                \"bits_per_second\": 865870336.6501037, \n                \"bytes\": 108230760, \n                \"end\": 46.000025, \n                \"omitted\": false, \n                \"seconds\": 0.9999719858169556, \n                \"sender\": false, \n                \"start\": 45.000053\n            }\n        }, \n        {\n            \"streams\": [\n                {\n                    \"bits_per_second\": 865301487.6535165, \n                    \"bytes\": 108165600, \n                    \"end\": 47.000052, \n                    \"omitted\": false, \n                    \"seconds\": 1.0000269412994385, \n                    \"sender\": false, \n                    \"socket\": 5, \n                    \"start\": 46.000025\n                }\n            ], \n            \"sum\": {\n                \"bits_per_second\": 865301487.6535165, \n                \"bytes\": 108165600, \n                \"end\": 47.000052, \n                \"omitted\": false, \n                \"seconds\": 1.0000269412994385, \n                \"sender\": false, \n                \"start\": 46.000025\n            }\n        }, \n        {\n            \"streams\": [\n                {\n                    \"bits_per_second\": 865871214.0437675, \n                    \"bytes\": 108230760, \n                    \"end\": 48.000023, \n                    \"omitted\": false, \n                    \"seconds\": 0.9999709725379944, \n                    \"sender\": false, \n                    \"socket\": 5, \n                    \"start\": 47.000052\n                }\n            ], \n            \"sum\": {\n                \"bits_per_second\": 865871214.0437675, \n                \"bytes\": 108230760, \n                \"end\": 48.000023, \n                \"omitted\": false, \n                \"seconds\": 0.9999709725379944, \n                \"sender\": false, \n                \"start\": 47.000052\n            }\n        }, \n        {\n            \"streams\": [\n                {\n                    \"bits_per_second\": 865325676.816303, \n                    \"bytes\": 108165600, \n                    \"end\": 49.000022, \n                    \"omitted\": false, \n                    \"seconds\": 0.9999989867210388, \n                    \"sender\": false, \n                    \"socket\": 5, \n                    \"start\": 48.000023\n                }\n            ], \n            \"sum\": {\n                \"bits_per_second\": 865325676.816303, \n                \"bytes\": 108165600, \n                \"end\": 49.000022, \n                \"omitted\": false, \n                \"seconds\": 0.9999989867210388, \n                \"sender\": false, \n                \"start\": 48.000023\n            }\n        }, \n        {\n            \"streams\": [\n                {\n                    \"bits_per_second\": 865806240.111346, \n                    \"bytes\": 108230760, \n                    \"end\": 50.000068, \n                    \"omitted\": false, \n                    \"seconds\": 1.0000460147857666, \n                    \"sender\": false, \n                    \"socket\": 5, \n                    \"start\": 49.000022\n                }\n            ], \n            \"sum\": {\n                \"bits_per_second\": 865806240.111346, \n                \"bytes\": 108230760, \n                \"end\": 50.000068, \n                \"omitted\": false, \n                \"seconds\": 1.0000460147857666, \n                \"sender\": false, \n                \"start\": 49.000022\n            }\n        }, \n        {\n            \"streams\": [\n                {\n                    \"bits_per_second\": 865273741.4093497, \n                    \"bytes\": 108165600, \n                    \"end\": 51.000127, \n                    \"omitted\": false, \n                    \"seconds\": 1.0000590085983276, \n                    \"sender\": false, \n                    \"socket\": 5, \n                    \"start\": 50.000068\n                }\n            ], \n            \"sum\": {\n                \"bits_per_second\": 865273741.4093497, \n                \"bytes\": 108165600, \n                \"end\": 51.000127, \n                \"omitted\": false, \n                \"seconds\": 1.0000590085983276, \n                \"sender\": false, \n                \"start\": 50.000068\n            }\n        }, \n        {\n            \"streams\": [\n                {\n                    \"bits_per_second\": 865394022.3774213, \n                    \"bytes\": 108165600, \n                    \"end\": 52.000047, \n                    \"omitted\": false, \n                    \"seconds\": 0.9999200105667114, \n                    \"sender\": false, \n                    \"socket\": 5, \n                    \"start\": 51.000127\n                }\n            ], \n            \"sum\": {\n                \"bits_per_second\": 865394022.3774213, \n                \"bytes\": 108165600, \n                \"end\": 52.000047, \n                \"omitted\": false, \n                \"seconds\": 0.9999200105667114, \n                \"sender\": false, \n                \"start\": 51.000127\n            }\n        }, \n        {\n            \"streams\": [\n                {\n                    \"bits_per_second\": 865871214.0437675, \n                    \"bytes\": 108230760, \n                    \"end\": 53.000018, \n                    \"omitted\": false, \n                    \"seconds\": 0.9999709725379944, \n                    \"sender\": false, \n                    \"socket\": 5, \n                    \"start\": 52.000047\n                }\n            ], \n            \"sum\": {\n                \"bits_per_second\": 865871214.0437675, \n                \"bytes\": 108230760, \n                \"end\": 53.000018, \n                \"omitted\": false, \n                \"seconds\": 0.9999709725379944, \n                \"sender\": false, \n                \"start\": 52.000047\n            }\n        }, \n        {\n            \"streams\": [\n                {\n                    \"bits_per_second\": 865298805.7827166, \n                    \"bytes\": 108165600, \n                    \"end\": 54.000048, \n                    \"omitted\": false, \n                    \"seconds\": 1.0000300407409668, \n                    \"sender\": false, \n                    \"socket\": 5, \n                    \"start\": 53.000018\n                }\n            ], \n            \"sum\": {\n                \"bits_per_second\": 865298805.7827166, \n                \"bytes\": 108165600, \n                \"end\": 54.000048, \n                \"omitted\": false, \n                \"seconds\": 1.0000300407409668, \n                \"sender\": false, \n                \"start\": 53.000018\n            }\n        }, \n        {\n            \"streams\": [\n                {\n                    \"bits_per_second\": 865858208.155167, \n                    \"bytes\": 108230760, \n                    \"end\": 55.000034, \n                    \"omitted\": false, \n                    \"seconds\": 0.9999859929084778, \n                    \"sender\": false, \n                    \"socket\": 5, \n                    \"start\": 54.000048\n                }\n            ], \n            \"sum\": {\n                \"bits_per_second\": 865858208.155167, \n                \"bytes\": 108230760, \n                \"end\": 55.000034, \n                \"omitted\": false, \n                \"seconds\": 0.9999859929084778, \n                \"sender\": false, \n                \"start\": 54.000048\n            }\n        }, \n        {\n            \"streams\": [\n                {\n                    \"bits_per_second\": 865315309.866654, \n                    \"bytes\": 108165600, \n                    \"end\": 56.000045, \n                    \"omitted\": false, \n                    \"seconds\": 1.0000109672546387, \n                    \"sender\": false, \n                    \"socket\": 5, \n                    \"start\": 55.000034\n                }\n            ], \n            \"sum\": {\n                \"bits_per_second\": 865315309.866654, \n                \"bytes\": 108165600, \n                \"end\": 56.000045, \n                \"omitted\": false, \n                \"seconds\": 1.0000109672546387, \n                \"sender\": false, \n                \"start\": 55.000034\n            }\n        }, \n        {\n            \"streams\": [\n                {\n                    \"bits_per_second\": 865830494.5292432, \n                    \"bytes\": 108230760, \n                    \"end\": 57.000063, \n                    \"omitted\": false, \n                    \"seconds\": 1.0000180006027222, \n                    \"sender\": false, \n                    \"socket\": 5, \n                    \"start\": 56.000045\n                }\n            ], \n            \"sum\": {\n                \"bits_per_second\": 865830494.5292432, \n                \"bytes\": 108230760, \n                \"end\": 57.000063, \n                \"omitted\": false, \n                \"seconds\": 1.0000180006027222, \n                \"sender\": false, \n                \"start\": 56.000045\n            }\n        }, \n        {\n            \"streams\": [\n                {\n                    \"bits_per_second\": 865354200.1039302, \n                    \"bytes\": 108165600, \n                    \"end\": 58.000029, \n                    \"omitted\": false, \n                    \"seconds\": 0.999966025352478, \n                    \"sender\": false, \n                    \"socket\": 5, \n                    \"start\": 57.000063\n                }\n            ], \n            \"sum\": {\n                \"bits_per_second\": 865354200.1039302, \n                \"bytes\": 108165600, \n                \"end\": 58.000029, \n                \"omitted\": false, \n                \"seconds\": 0.999966025352478, \n                \"sender\": false, \n                \"start\": 57.000063\n            }\n        }, \n        {\n            \"streams\": [\n                {\n                    \"bits_per_second\": 865285912.4051837, \n                    \"bytes\": 108165600, \n                    \"end\": 59.000074, \n                    \"omitted\": false, \n                    \"seconds\": 1.0000449419021606, \n                    \"sender\": false, \n                    \"socket\": 5, \n                    \"start\": 58.000029\n                }\n            ], \n            \"sum\": {\n                \"bits_per_second\": 865285912.4051837, \n                \"bytes\": 108165600, \n                \"end\": 59.000074, \n                \"omitted\": false, \n                \"seconds\": 1.0000449419021606, \n                \"sender\": false, \n                \"start\": 58.000029\n            }\n        }, \n        {\n            \"streams\": [\n                {\n                    \"bits_per_second\": 865885046.1317962, \n                    \"bytes\": 108230760, \n                    \"end\": 60.000029, \n                    \"omitted\": false, \n                    \"seconds\": 0.9999549984931946, \n                    \"sender\": false, \n                    \"socket\": 5, \n                    \"start\": 59.000074\n                }\n            ], \n            \"sum\": {\n                \"bits_per_second\": 865885046.1317962, \n                \"bytes\": 108230760, \n                \"end\": 60.000029, \n                \"omitted\": false, \n                \"seconds\": 0.9999549984931946, \n                \"sender\": false, \n                \"start\": 59.000074\n            }\n        }, \n        {\n            \"streams\": [\n                {\n                    \"bits_per_second\": 860600572.5209967, \n                    \"bytes\": 8275320, \n                    \"end\": 60.076955, \n                    \"omitted\": false, \n                    \"seconds\": 0.07692600041627884, \n                    \"sender\": false, \n                    \"socket\": 5, \n                    \"start\": 60.000029\n                }\n            ], \n            \"sum\": {\n                \"bits_per_second\": 860600572.5209967, \n                \"bytes\": 8275320, \n                \"end\": 60.076955, \n                \"omitted\": false, \n                \"seconds\": 0.07692600041627884, \n                \"sender\": false, \n                \"start\": 60.000029\n            }\n        }\n    ], \n    \"start\": {\n        \"accepted_connection\": {\n            \"host\": \"10.0.0.1\", \n            \"port\": 59609\n        }, \n        \"connected\": [\n            {\n                \"local_host\": \"10.0.0.2\", \n                \"local_port\": 5201, \n                \"remote_host\": \"10.0.0.1\", \n                \"remote_port\": 54817, \n                \"socket\": 5\n            }\n        ], \n        \"cookie\": \"2xth5gkq32pk7wfrgrfxkr4dfuwz4dd3vupa\", \n        \"fq_rate\": 0, \n        \"rcvbuf_actual\": 87380, \n        \"sndbuf_actual\": 87380, \n        \"sock_bufsize\": 0, \n        \"system_info\": \"REDACTED\", \n        \"target_bitrate\": 0, \n        \"tcp_mss_default\": 0, \n        \"test_start\": {\n            \"bidir\": 0, \n            \"blksize\": 131072, \n            \"blocks\": 0, \n            \"bytes\": 0, \n            \"duration\": 60, \n            \"fqrate\": 0, \n            \"num_streams\": 1, \n            \"omit\": 0, \n            \"protocol\": \"TCP\", \n            \"reverse\": 0, \n            \"target_bitrate\": 0, \n            \"tos\": 0\n        }, \n        \"timestamp\": {\n            \"time\": \"Wed, 17 Apr 2024 01:12:34 GMT\", \n            \"timesecs\": 1713316354\n        }, \n        \"version\": \"iperf 3.14\"\n    }\n}\n","summary":{"streams":[{"end":60.000071,"rtt":77088,"start":0,"stream-id":5,"retransmits":0,"throughput-bits":867014039.6333865,"throughput-bytes":6502612992}],"summary":{"end":60.000071,"start":0,"retransmits":0,"throughput-bits":867014039.6333865,"throughput-bytes":6502612992,"receiver-throughput-bits":865535640.5463626}},"intervals":[{"streams":[{"end":1.00008,"rtt":77088,"start":0,"omitted":false,"stream-id":5,"retransmits":0,"tcp-window-size":16698336,"throughput-bits":955176331.9865137,"throughput-bytes":119406592}],"summary":{"end":1.00008,"start":0,"omitted":false,"retransmits":0,"throughput-bits":955176331.9865137,"throughput-bytes":119406592}},{"streams":[{"end":2.000066,"rtt":77090,"start":1.00008,"omitted":false,"stream-id":5,"retransmits":0,"tcp-window-size":16698336,"throughput-bits":870330270.7957577,"throughput-bytes":108789760}],"summary":{"end":2.000066,"start":1.00008,"omitted":false,"retransmits":0,"throughput-bits":870330270.7957577,"throughput-bytes":108789760}},{"streams":[{"end":3.000045,"rtt":77089,"start":2.000066,"omitted":false,"stream-id":5,"retransmits":0,"tcp-window-size":16698336,"throughput-bits":859850360.3785022,"throughput-bytes":107479040}],"summary":{"end":3.000045,"start":2.000066,"omitted":false,"retransmits":0,"throughput-bits":859850360.3785022,"throughput-bytes":107479040}},{"streams":[{"end":4.000064,"rtt":77085,"start":3.000045,"omitted":false,"stream-id":5,"retransmits":0,"tcp-window-size":16698336,"throughput-bits":870301584.0626686,"throughput-bytes":108789760}],"summary":{"end":4.000064,"start":3.000045,"omitted":false,"retransmits":0,"throughput-bits":870301584.0626686,"throughput-bytes":108789760}},{"streams":[{"end":5.000063,"rtt":77085,"start":4.000064,"omitted":false,"stream-id":5,"retransmits":0,"tcp-window-size":16698336,"throughput-bits":859833191.250883,"throughput-bytes":107479040}],"summary":{"end":5.000063,"start":4.000064,"omitted":false,"retransmits":0,"throughput-bits":859833191.250883,"throughput-bytes":107479040}},{"streams":[{"end":6.000062,"rtt":77087,"start":5.000063,"omitted":false,"stream-id":5,"retransmits":0,"tcp-window-size":16698336,"throughput-bits":870318961.8758936,"throughput-bytes":108789760}],"summary":{"end":6.000062,"start":5.000063,"omitted":false,"retransmits":0,"throughput-bits":870318961.8758936,"throughput-bytes":108789760}},{"streams":[{"end":7.000061,"rtt":77085,"start":6.000062,"omitted":false,"stream-id":5,"retransmits":0,"tcp-window-size":16698336,"throughput-bits":870318961.8758936,"throughput-bytes":108789760}],"summary":{"end":7.000061,"start":6.000062,"omitted":false,"retransmits":0,"throughput-bits":870318961.8758936,"throughput-bytes":108789760}},{"streams":[{"end":8.00005,"rtt":77090,"start":7.000061,"omitted":false,"stream-id":5,"retransmits":0,"tcp-window-size":16698336,"throughput-bits":859841801.3545495,"throughput-bytes":107479040}],"summary":{"end":8.00005,"start":7.000061,"omitted":false,"retransmits":0,"throughput-bits":859841801.3545495,"throughput-bytes":107479040}},{"streams":[{"end":9.000062,"rtt":77087,"start":8.00005,"omitted":false,"stream-id":5,"retransmits":0,"tcp-window-size":16698336,"throughput-bits":870307601.376164,"throughput-bytes":108789760}],"summary":{"end":9.000062,"start":8.00005,"omitted":false,"retransmits":0,"throughput-bits":870307601.376164,"throughput-bytes":108789760}},{"streams":[{"end":10.000043,"rtt":77091,"start":9.000062,"omitted":false,"stream-id":5,"retransmits":0,"tcp-window-size":16698336,"throughput-bits":859848669.060859,"throughput-bytes":107479040}],"summary":{"end":10.000043,"start":9.000062,"omitted":false,"retransmits":0,"throughput-bits":859848669.060859,"throughput-bytes":107479040}},{"streams":[{"end":11.000061,"rtt":77089,"start":10.000043,"omitted":false,"stream-id":5,"retransmits":0,"tcp-window-size":16698336,"throughput-bits":870302414.031997,"throughput-bytes":108789760}],"summary":{"end":11.000061,"start":10.000043,"omitted":false,"retransmits":0,"throughput-bits":870302414.031997,"throughput-bytes":108789760}},{"streams":[{"end":12.000065,"rtt":77087,"start":11.000061,"omitted":false,"stream-id":5,"retransmits":0,"tcp-window-size":16698336,"throughput-bits":859828835.014125,"throughput-bytes":107479040}],"summary":{"end":12.000065,"start":11.000061,"omitted":false,"retransmits":0,"throughput-bits":859828835.014125,"throughput-bytes":107479040}},{"streams":[{"end":13.000063,"rtt":77088,"start":12.000065,"omitted":false,"stream-id":5,"retransmits":0,"tcp-window-size":16698336,"throughput-bits":870319843.7535744,"throughput-bytes":108789760}],"summary":{"end":13.000063,"start":12.000065,"omitted":false,"retransmits":0,"throughput-bits":870319843.7535744,"throughput-bytes":108789760}},{"streams":[{"end":14.000054,"rtt":77085,"start":13.000063,"omitted":false,"stream-id":5,"retransmits":0,"tcp-window-size":16698336,"throughput-bits":859840058.8196517,"throughput-bytes":107479040}],"summary":{"end":14.000054,"start":13.000063,"omitted":false,"retransmits":0,"throughput-bits":859840058.8196517,"throughput-bytes":107479040}},{"streams":[{"end":15.000032,"rtt":77088,"start":14.000054,"omitted":false,"stream-id":5,"retransmits":0,"tcp-window-size":16698336,"throughput-bits":870337222.296018,"throughput-bytes":108789760}],"summary":{"end":15.000032,"start":14.000054,"omitted":false,"retransmits":0,"throughput-bits":870337222.296018,"throughput-bytes":108789760}},{"streams":[{"end":16.000062,"rtt":77091,"start":15.000032,"omitted":false,"stream-id":5,"retransmits":0,"tcp-window-size":16698336,"throughput-bits":859806490.775929,"throughput-bytes":107479040}],"summary":{"end":16.000062,"start":15.000032,"omitted":false,"retransmits":0,"throughput-bits":859806490.775929,"throughput-bytes":107479040}},{"streams":[{"end":17.000042,"rtt":77085,"start":16.000062,"omitted":false,"stream-id":5,"retransmits":0,"tcp-window-size":16698336,"throughput-bits":870335510.3490804,"throughput-bytes":108789760}],"summary":{"end":17.000042,"start":16.000062,"omitted":false,"retransmits":0,"throughput-bits":870335510.3490804,"throughput-bytes":108789760}},{"streams":[{"end":18.000118,"rtt":77092,"start":17.000042,"omitted":false,"stream-id":5,"retransmits":0,"tcp-window-size":16698336,"throughput-bits":870251892.5339226,"throughput-bytes":108789760}],"summary":{"end":18.000118,"start":17.000042,"omitted":false,"retransmits":0,"throughput-bits":870251892.5339226,"throughput-bytes":108789760}},{"streams":[{"end":19.000064,"rtt":77089,"start":18.000118,"omitted":false,"stream-id":5,"retransmits":0,"tcp-window-size":16698336,"throughput-bits":859878755.0075743,"throughput-bytes":107479040}],"summary":{"end":19.000064,"start":18.000118,"omitted":false,"retransmits":0,"throughput-bits":859878755.0075743,"throughput-bytes":107479040}},{"streams":[{"end":20.000062,"rtt":77090,"start":19.000064,"omitted":false,"stream-id":5,"retransmits":0,"tcp-window-size":16698336,"throughput-bits":870319843.7535744,"throughput-bytes":108789760}],"summary":{"end":20.000062,"start":19.000064,"omitted":false,"retransmits":0,"throughput-bits":870319843.7535744,"throughput-bytes":108789760}},{"streams":[{"end":21.000091,"rtt":77093,"start":20.000062,"omitted":false,"stream-id":5,"retransmits":0,"tcp-window-size":16698336,"throughput-bits":859807413.221496,"throughput-bytes":107479040}],"summary":{"end":21.000091,"start":20.000062,"omitted":false,"retransmits":0,"throughput-bits":859807413.221496,"throughput-bytes":107479040}},{"streams":[{"end":22.000069,"rtt":77093,"start":21.000091,"omitted":false,"stream-id":5,"retransmits":0,"tcp-window-size":16698336,"throughput-bits":870337222.296018,"throughput-bytes":108789760}],"summary":{"end":22.000069,"start":21.000091,"omitted":false,"retransmits":0,"throughput-bits":870337222.296018,"throughput-bytes":108789760}},{"streams":[{"end":23.00008,"rtt":77092,"start":22.000069,"omitted":false,"stream-id":5,"retransmits":0,"tcp-window-size":16698336,"throughput-bits":859822890.10342,"throughput-bytes":107479040}],"summary":{"end":23.00008,"start":22.000069,"omitted":false,"retransmits":0,"throughput-bits":859822890.10342,"throughput-bytes":107479040}},{"streams":[{"end":24.000041,"rtt":77088,"start":23.00008,"omitted":false,"stream-id":5,"retransmits":0,"tcp-window-size":16698336,"throughput-bits":870352007.5725455,"throughput-bytes":108789760}],"summary":{"end":24.000041,"start":23.00008,"omitted":false,"retransmits":0,"throughput-bits":870352007.5725455,"throughput-bytes":108789760}},{"streams":[{"end":25.000066,"rtt":77090,"start":24.000041,"omitted":false,"stream-id":5,"retransmits":0,"tcp-window-size":16698336,"throughput-bits":859810795.5388423,"throughput-bytes":107479040}],"summary":{"end":25.000066,"start":24.000041,"omitted":false,"retransmits":0,"throughput-bits":859810795.5388423,"throughput-bytes":107479040}},{"streams":[{"end":26.000062,"rtt":77094,"start":25.000066,"omitted":false,"stream-id":5,"retransmits":0,"tcp-window-size":16698336,"throughput-bits":870321555.63888,"throughput-bytes":108789760}],"summary":{"end":26.000062,"start":25.000066,"omitted":false,"retransmits":0,"throughput-bits":870321555.63888,"throughput-bytes":108789760}},{"streams":[{"end":27.000064,"rtt":77089,"start":26.000062,"omitted":false,"stream-id":5,"retransmits":0,"tcp-window-size":16698336,"throughput-bits":859830577.5035312,"throughput-bytes":107479040}],"summary":{"end":27.000064,"start":26.000062,"omitted":false,"retransmits":0,"throughput-bits":859830577.5035312,"throughput-bytes":107479040}},{"streams":[{"end":28.000063,"rtt":77087,"start":27.000064,"omitted":false,"stream-id":5,"retransmits":0,"tcp-window-size":16698336,"throughput-bits":870318961.8758936,"throughput-bytes":108789760}],"summary":{"end":28.000063,"start":27.000064,"omitted":false,"retransmits":0,"throughput-bits":870318961.8758936,"throughput-bytes":108789760}},{"streams":[{"end":29.000063,"rtt":77089,"start":28.000063,"omitted":false,"stream-id":5,"retransmits":0,"tcp-window-size":16698336,"throughput-bits":870318080,"throughput-bytes":108789760}],"summary":{"end":29.000063,"start":28.000063,"omitted":false,"retransmits":0,"throughput-bits":870318080,"throughput-bytes":108789760}},{"streams":[{"end":30.000165,"rtt":77087,"start":29.000063,"omitted":false,"stream-id":5,"retransmits":0,"tcp-window-size":16698336,"throughput-bits":859744588.9523526,"throughput-bytes":107479040}],"summary":{"end":30.000165,"start":29.000063,"omitted":false,"retransmits":0,"throughput-bits":859744588.9523526,"throughput-bytes":107479040}},{"streams":[{"end":31.00004,"rtt":77087,"start":30.000165,"omitted":false,"stream-id":5,"retransmits":0,"tcp-window-size":16698336,"throughput-bits":870426875.4734485,"throughput-bytes":108789760}],"summary":{"end":31.00004,"start":30.000165,"omitted":false,"retransmits":0,"throughput-bits":870426875.4734485,"throughput-bytes":108789760}},{"streams":[{"end":32.000067,"rtt":77089,"start":31.00004,"omitted":false,"stream-id":5,"retransmits":0,"tcp-window-size":16698336,"throughput-bits":859809155.6240784,"throughput-bytes":107479040}],"summary":{"end":32.000067,"start":31.00004,"omitted":false,"retransmits":0,"throughput-bits":859809155.6240784,"throughput-bytes":107479040}},{"streams":[{"end":33.000075,"rtt":77088,"start":32.000067,"omitted":false,"stream-id":5,"retransmits":0,"tcp-window-size":16698336,"throughput-bits":870311128.8055193,"throughput-bytes":108789760}],"summary":{"end":33.000075,"start":32.000067,"omitted":false,"retransmits":0,"throughput-bits":870311128.8055193,"throughput-bytes":108789760}},{"streams":[{"end":34.000062,"rtt":77086,"start":33.000075,"omitted":false,"stream-id":5,"retransmits":0,"tcp-window-size":16698336,"throughput-bits":859843492.6451752,"throughput-bytes":107479040}],"summary":{"end":34.000062,"start":33.000075,"omitted":false,"retransmits":0,"throughput-bits":859843492.6451752,"throughput-bytes":107479040}},{"streams":[{"end":35.000062,"rtt":77089,"start":34.000062,"omitted":false,"stream-id":5,"retransmits":0,"tcp-window-size":16698336,"throughput-bits":870318080,"throughput-bytes":108789760}],"summary":{"end":35.000062,"start":34.000062,"omitted":false,"retransmits":0,"throughput-bits":870318080,"throughput-bytes":108789760}},{"streams":[{"end":36.000141,"rtt":77089,"start":35.000062,"omitted":false,"stream-id":5,"retransmits":0,"tcp-window-size":16698336,"throughput-bits":859764367.870648,"throughput-bytes":107479040}],"summary":{"end":36.000141,"start":35.000062,"omitted":false,"retransmits":0,"throughput-bits":859764367.870648,"throughput-bytes":107479040}},{"streams":[{"end":37.000065,"rtt":77082,"start":36.000141,"omitted":false,"stream-id":5,"retransmits":0,"tcp-window-size":16698336,"throughput-bits":870384225.6517998,"throughput-bytes":108789760}],"summary":{"end":37.000065,"start":36.000141,"omitted":false,"retransmits":0,"throughput-bits":870384225.6517998,"throughput-bytes":108789760}},{"streams":[{"end":38.000067,"rtt":77086,"start":37.000065,"omitted":false,"stream-id":5,"retransmits":0,"tcp-window-size":16698336,"throughput-bits":859830577.5035312,"throughput-bytes":107479040}],"summary":{"end":38.000067,"start":37.000065,"omitted":false,"retransmits":0,"throughput-bits":859830577.5035312,"throughput-bytes":107479040}},{"streams":[{"end":39.000063,"rtt":77087,"start":38.000067,"omitted":false,"stream-id":5,"retransmits":0,"tcp-window-size":16698336,"throughput-bits":870321555.63888,"throughput-bytes":108789760}],"summary":{"end":39.000063,"start":38.000067,"omitted":false,"retransmits":0,"throughput-bits":870321555.63888,"throughput-bytes":108789760}},{"streams":[{"end":40.000061,"rtt":77086,"start":39.000063,"omitted":false,"stream-id":5,"retransmits":0,"tcp-window-size":16698336,"throughput-bits":870319843.7535744,"throughput-bytes":108789760}],"summary":{"end":40.000061,"start":39.000063,"omitted":false,"retransmits":0,"throughput-bits":870319843.7535744,"throughput-bytes":108789760}},{"streams":[{"end":41.000167,"rtt":77090,"start":40.000061,"omitted":false,"stream-id":5,"retransmits":0,"tcp-window-size":16698336,"throughput-bits":859741207.155871,"throughput-bytes":107479040}],"summary":{"end":41.000167,"start":40.000061,"omitted":false,"retransmits":0,"throughput-bits":859741207.155871,"throughput-bytes":107479040}},{"streams":[{"end":42.000071,"rtt":77085,"start":41.000167,"omitted":false,"stream-id":5,"retransmits":0,"tcp-window-size":16698336,"throughput-bits":870401658.6504797,"throughput-bytes":108789760}],"summary":{"end":42.000071,"start":41.000167,"omitted":false,"retransmits":0,"throughput-bits":870401658.6504797,"throughput-bytes":108789760}},{"streams":[{"end":43.000049,"rtt":77090,"start":42.000071,"omitted":false,"stream-id":5,"retransmits":0,"tcp-window-size":16698336,"throughput-bits":859851231.6659453,"throughput-bytes":107479040}],"summary":{"end":43.000049,"start":42.000071,"omitted":false,"retransmits":0,"throughput-bits":859851231.6659453,"throughput-bytes":107479040}},{"streams":[{"end":44.000062,"rtt":77089,"start":43.000049,"omitted":false,"stream-id":5,"retransmits":0,"tcp-window-size":16698336,"throughput-bits":870306771.396942,"throughput-bytes":108789760}],"summary":{"end":44.000062,"start":43.000049,"omitted":false,"retransmits":0,"throughput-bits":870306771.396942,"throughput-bytes":108789760}},{"streams":[{"end":45.000068,"rtt":77089,"start":44.000062,"omitted":false,"stream-id":5,"retransmits":0,"tcp-window-size":16698336,"throughput-bits":859827195.030547,"throughput-bytes":107479040}],"summary":{"end":45.000068,"start":44.000062,"omitted":false,"retransmits":0,"throughput-bits":859827195.030547,"throughput-bytes":107479040}},{"streams":[{"end":46.000063,"rtt":77088,"start":45.000068,"omitted":false,"stream-id":5,"retransmits":0,"tcp-window-size":16698336,"throughput-bits":870322437.5218172,"throughput-bytes":108789760}],"summary":{"end":46.000063,"start":45.000068,"omitted":false,"retransmits":0,"throughput-bits":870322437.5218172,"throughput-bytes":108789760}},{"streams":[{"end":47.000064,"rtt":77084,"start":46.000063,"omitted":false,"stream-id":5,"retransmits":0,"tcp-window-size":16698336,"throughput-bits":859831500.000782,"throughput-bytes":107479040}],"summary":{"end":47.000064,"start":46.000063,"omitted":false,"retransmits":0,"throughput-bits":859831500.000782,"throughput-bytes":107479040}},{"streams":[{"end":48.000062,"rtt":77088,"start":47.000064,"omitted":false,"stream-id":5,"retransmits":0,"tcp-window-size":16698336,"throughput-bits":870319843.7535744,"throughput-bytes":108789760}],"summary":{"end":48.000062,"start":47.000064,"omitted":false,"retransmits":0,"throughput-bits":870319843.7535744,"throughput-bytes":108789760}},{"streams":[{"end":49.000063,"rtt":77091,"start":48.000062,"omitted":false,"stream-id":5,"retransmits":0,"tcp-window-size":16698336,"throughput-bits":859831500.000782,"throughput-bytes":107479040}],"summary":{"end":49.000063,"start":48.000062,"omitted":false,"retransmits":0,"throughput-bits":859831500.000782,"throughput-bytes":107479040}},{"streams":[{"end":50.000064,"rtt":77090,"start":49.000063,"omitted":false,"stream-id":5,"retransmits":0,"tcp-window-size":16698336,"throughput-bits":870317250.0007915,"throughput-bytes":108789760}],"summary":{"end":50.000064,"start":49.000063,"omitted":false,"retransmits":0,"throughput-bits":870317250.0007915,"throughput-bytes":108789760}},{"streams":[{"end":51.000061,"rtt":77088,"start":50.000064,"omitted":false,"stream-id":5,"retransmits":0,"tcp-window-size":16698336,"throughput-bits":870320673.75773,"throughput-bytes":108789760}],"summary":{"end":51.000061,"start":50.000064,"omitted":false,"retransmits":0,"throughput-bits":870320673.75773,"throughput-bytes":108789760}},{"streams":[{"end":52.000033,"rtt":77086,"start":51.000061,"omitted":false,"stream-id":5,"retransmits":0,"tcp-window-size":16698336,"throughput-bits":859856408.1748105,"throughput-bytes":107479040}],"summary":{"end":52.000033,"start":51.000061,"omitted":false,"retransmits":0,"throughput-bits":859856408.1748105,"throughput-bytes":107479040}},{"streams":[{"end":53.000061,"rtt":77090,"start":52.000033,"omitted":false,"stream-id":5,"retransmits":0,"tcp-window-size":16698336,"throughput-bits":870293699.4330016,"throughput-bytes":108789760}],"summary":{"end":53.000061,"start":52.000033,"omitted":false,"retransmits":0,"throughput-bits":870293699.4330016,"throughput-bytes":108789760}},{"streams":[{"end":54.000063,"rtt":77085,"start":53.000061,"omitted":false,"stream-id":5,"retransmits":0,"tcp-window-size":16698336,"throughput-bits":859830577.5035312,"throughput-bytes":107479040}],"summary":{"end":54.000063,"start":53.000061,"omitted":false,"retransmits":0,"throughput-bits":859830577.5035312,"throughput-bytes":107479040}},{"streams":[{"end":55.000062,"rtt":77092,"start":54.000063,"omitted":false,"stream-id":5,"retransmits":0,"tcp-window-size":16698336,"throughput-bits":870318961.8758936,"throughput-bytes":108789760}],"summary":{"end":55.000062,"start":54.000063,"omitted":false,"retransmits":0,"throughput-bits":870318961.8758936,"throughput-bytes":108789760}},{"streams":[{"end":56.000057,"rtt":77087,"start":55.000062,"omitted":false,"stream-id":5,"retransmits":0,"tcp-window-size":16698336,"throughput-bits":859836625.0215544,"throughput-bytes":107479040}],"summary":{"end":56.000057,"start":55.000062,"omitted":false,"retransmits":0,"throughput-bits":859836625.0215544,"throughput-bytes":107479040}},{"streams":[{"end":57.000075,"rtt":77086,"start":56.000057,"omitted":false,"stream-id":5,"retransmits":0,"tcp-window-size":16698336,"throughput-bits":870302414.031997,"throughput-bytes":108789760}],"summary":{"end":57.000075,"start":56.000057,"omitted":false,"retransmits":0,"throughput-bits":870302414.031997,"throughput-bytes":108789760}},{"streams":[{"end":58.000051,"rtt":77085,"start":57.000075,"omitted":false,"stream-id":5,"retransmits":0,"tcp-window-size":16698336,"throughput-bits":859852974.246129,"throughput-bytes":107479040}],"summary":{"end":58.000051,"start":57.000075,"omitted":false,"retransmits":0,"throughput-bits":859852974.246129,"throughput-bytes":107479040}},{"streams":[{"end":59.000021,"rtt":77085,"start":58.000051,"omitted":false,"stream-id":5,"retransmits":0,"tcp-window-size":16698336,"throughput-bits":870344173.907325,"throughput-bytes":108789760}],"summary":{"end":59.000021,"start":58.000051,"omitted":false,"retransmits":0,"throughput-bits":870344173.907325,"throughput-bytes":108789760}},{"streams":[{"end":60.000071,"rtt":77088,"start":59.000021,"omitted":false,"stream-id":5,"retransmits":0,"tcp-window-size":16698336,"throughput-bits":859789374.6450644,"throughput-bytes":107479040}],"summary":{"end":60.000071,"start":59.000021,"omitted":false,"retransmits":0,"throughput-bits":859789374.6450644,"throughput-bytes":107479040}}],"succeeded":true}
