{"diags":"Participant 0:\n/usr/bin/iperf3 -p 5201 -B 172.16.0.2 -c 172.16.0.1 -t 60 --json --rsa-public-key-path /var/run/pscheduler-server/runner/tmp/tmpmi4msko2/tmpeum68bvv/public-key --username d6ct62ImL34QBtZxPzFl\n\n{\n    \"end\": {\n        \"cpu_utilization_percent\": {\n            \"host_system\": 0.060077668705599274, \n            \"host_total\": 0.06026900945837273, \n            \"host_user\": 0.00019134075277345508, \n            \"remote_system\": 1.544647386239829, \n            \"remote_total\": 1.7740456058661682, \n            \"remote_user\": 0.22939821962633944\n        }, \n        \"receiver_tcp_congestion\": \"htcp\", \n        \"sender_tcp_congestion\": \"htcp\", \n        \"streams\": [\n            {\n                \"receiver\": {\n                    \"bits_per_second\": 8600919.8651786, \n                    \"bytes\": 64645620, \n                    \"end\": 60.129029, \n                    \"seconds\": 60.000387, \n                    \"sender\": true, \n                    \"socket\": 5, \n                    \"start\": 0\n                }, \n                \"sender\": {\n                    \"bits_per_second\": 9017695.43586444, \n                    \"bytes\": 67633152, \n                    \"end\": 60.000387, \n                    \"max_rtt\": 133126, \n                    \"max_snd_cwnd\": 371108, \n                    \"max_snd_wnd\": 0, \n                    \"mean_rtt\": 80487, \n                    \"min_rtt\": 23464, \n                    \"retransmits\": 2203, \n                    \"seconds\": 60.000387, \n                    \"sender\": true, \n                    \"socket\": 5, \n                    \"start\": 0\n                }\n            }\n        ], \n        \"sum_received\": {\n            \"bits_per_second\": 8600919.8651786, \n            \"bytes\": 64645620, \n            \"end\": 60.129029, \n            \"seconds\": 60.129029, \n            \"sender\": true, \n            \"start\": 0\n        }, \n        \"sum_sent\": {\n            \"bits_per_second\": 9017695.43586444, \n            \"bytes\": 67633152, \n            \"end\": 60.000387, \n            \"retransmits\": 2203, \n            \"seconds\": 60.000387, \n            \"sender\": true, \n            \"start\": 0\n        }\n    }, \n    \"intervals\": [\n        {\n            \"streams\": [\n                {\n                    \"bits_per_second\": 48224705.73755466, \n                    \"bytes\": 6029312, \n                    \"end\": 1.000203, \n                    \"omitted\": false, \n                    \"pmtu\": 1500, \n                    \"retransmits\": 288, \n                    \"rtt\": 92608, \n                    \"rttvar\": 3571, \n                    \"seconds\": 1.000203013420105, \n                    \"sender\": true, \n                    \"snd_cwnd\": 201272, \n                    \"snd_wnd\": -1, \n                    \"socket\": 5, \n                    \"start\": 0\n                }\n            ], \n            \"sum\": {\n                \"bits_per_second\": 48224705.73755466, \n                \"bytes\": 6029312, \n                \"end\": 1.000203, \n                \"omitted\": false, \n                \"retransmits\": 288, \n                \"seconds\": 1.000203013420105, \n                \"sender\": true, \n                \"start\": 0\n            }\n        }, \n        {\n            \"streams\": [\n                {\n                    \"bits_per_second\": 0, \n                    \"bytes\": 0, \n                    \"end\": 2.001015, \n                    \"omitted\": false, \n                    \"pmtu\": 1500, \n                    \"retransmits\": 1, \n                    \"rtt\": 74346, \n                    \"rttvar\": 500, \n                    \"seconds\": 1.00081205368042, \n                    \"sender\": true, \n                    \"snd_cwnd\": 1448, \n                    \"snd_wnd\": -1, \n                    \"socket\": 5, \n                    \"start\": 1.000203\n                }\n            ], \n            \"sum\": {\n                \"bits_per_second\": 0, \n                \"bytes\": 0, \n                \"end\": 2.001015, \n                \"omitted\": false, \n                \"retransmits\": 1, \n                \"seconds\": 1.00081205368042, \n                \"sender\": true, \n                \"start\": 1.000203\n            }\n        }, \n        {\n            \"streams\": [\n                {\n                    \"bits_per_second\": 0, \n                    \"bytes\": 0, \n                    \"end\": 3.001019, \n                    \"omitted\": false, \n                    \"pmtu\": 1500, \n                    \"retransmits\": 1, \n                    \"rtt\": 74346, \n                    \"rttvar\": 500, \n                    \"seconds\": 1.0000040531158447, \n                    \"sender\": true, \n                    \"snd_cwnd\": 1448, \n                    \"snd_wnd\": -1, \n                    \"socket\": 5, \n                    \"start\": 2.001015\n                }\n            ], \n            \"sum\": {\n                \"bits_per_second\": 0, \n                \"bytes\": 0, \n                \"end\": 3.001019, \n                \"omitted\": false, \n                \"retransmits\": 1, \n                \"seconds\": 1.0000040531158447, \n                \"sender\": true, \n                \"start\": 2.001015\n            }\n        }, \n        {\n            \"streams\": [\n                {\n                    \"bits_per_second\": 0, \n                    \"bytes\": 0, \n                    \"end\": 4.000031, \n                    \"omitted\": false, \n                    \"pmtu\": 1500, \n                    \"retransmits\": 1, \n                    \"rtt\": 74346, \n                    \"rttvar\": 500, \n                    \"seconds\": 0.999011993408203, \n                    \"sender\": true, \n                    \"snd_cwnd\": 1448, \n                    \"snd_wnd\": -1, \n                    \"socket\": 5, \n                    \"start\": 3.001019\n                }\n            ], \n            \"sum\": {\n                \"bits_per_second\": 0, \n                \"bytes\": 0, \n                \"end\": 4.000031, \n                \"omitted\": false, \n                \"retransmits\": 1, \n                \"seconds\": 0.999011993408203, \n                \"sender\": true, \n                \"start\": 3.001019\n            }\n        }, \n        {\n            \"streams\": [\n                {\n                    \"bits_per_second\": 0, \n                    \"bytes\": 0, \n                    \"end\": 5.000022, \n                    \"omitted\": false, \n                    \"pmtu\": 1500, \n                    \"retransmits\": 0, \n                    \"rtt\": 74346, \n                    \"rttvar\": 500, \n                    \"seconds\": 0.999990999698639, \n                    \"sender\": true, \n                    \"snd_cwnd\": 1448, \n                    \"snd_wnd\": -1, \n                    \"socket\": 5, \n                    \"start\": 4.000031\n                }\n            ], \n            \"sum\": {\n                \"bits_per_second\": 0, \n                \"bytes\": 0, \n                \"end\": 5.000022, \n                \"omitted\": false, \n                \"retransmits\": 0, \n                \"seconds\": 0.999990999698639, \n                \"sender\": true, \n                \"start\": 4.000031\n            }\n        }, \n        {\n            \"streams\": [\n                {\n                    \"bits_per_second\": 0, \n                    \"bytes\": 0, \n                    \"end\": 6.00011, \n                    \"omitted\": false, \n                    \"pmtu\": 1500, \n                    \"retransmits\": 1, \n                    \"rtt\": 74346, \n                    \"rttvar\": 500, \n                    \"seconds\": 1.0000879764556885, \n                    \"sender\": true, \n                    \"snd_cwnd\": 1024, \n                    \"snd_wnd\": -1, \n                    \"socket\": 5, \n                    \"start\": 5.000022\n                }\n            ], \n            \"sum\": {\n                \"bits_per_second\": 0, \n                \"bytes\": 0, \n                \"end\": 6.00011, \n                \"omitted\": false, \n                \"retransmits\": 1, \n                \"seconds\": 1.0000879764556885, \n                \"sender\": true, \n                \"start\": 5.000022\n            }\n        }, \n        {\n            \"streams\": [\n                {\n                    \"bits_per_second\": 0, \n                    \"bytes\": 0, \n                    \"end\": 7.001016, \n                    \"omitted\": false, \n                    \"pmtu\": 1500, \n                    \"retransmits\": 0, \n                    \"rtt\": 74346, \n                    \"rttvar\": 500, \n                    \"seconds\": 1.000905990600586, \n                    \"sender\": true, \n                    \"snd_cwnd\": 1024, \n                    \"snd_wnd\": -1, \n                    \"socket\": 5, \n                    \"start\": 6.00011\n                }\n            ], \n            \"sum\": {\n                \"bits_per_second\": 0, \n                \"bytes\": 0, \n                \"end\": 7.001016, \n                \"omitted\": false, \n                \"retransmits\": 0, \n                \"seconds\": 1.000905990600586, \n                \"sender\": true, \n                \"start\": 6.00011\n            }\n        }, \n        {\n            \"streams\": [\n                {\n                    \"bits_per_second\": 0, \n                    \"bytes\": 0, \n                    \"end\": 8.001013, \n                    \"omitted\": false, \n                    \"pmtu\": 1500, \n                    \"retransmits\": 0, \n                    \"rtt\": 74346, \n                    \"rttvar\": 500, \n                    \"seconds\": 0.9999970197677612, \n                    \"sender\": true, \n                    \"snd_cwnd\": 1024, \n                    \"snd_wnd\": -1, \n                    \"socket\": 5, \n                    \"start\": 7.001016\n                }\n            ], \n            \"sum\": {\n                \"bits_per_second\": 0, \n                \"bytes\": 0, \n                \"end\": 8.001013, \n                \"omitted\": false, \n                \"retransmits\": 0, \n                \"seconds\": 0.9999970197677612, \n                \"sender\": true, \n                \"start\": 7.001016\n            }\n        }, \n        {\n            \"streams\": [\n                {\n                    \"bits_per_second\": 0, \n                    \"bytes\": 0, \n                    \"end\": 9.001014, \n                    \"omitted\": false, \n                    \"pmtu\": 1500, \n                    \"retransmits\": 0, \n                    \"rtt\": 74346, \n                    \"rttvar\": 500, \n                    \"seconds\": 1.0000009536743164, \n                    \"sender\": true, \n                    \"snd_cwnd\": 1024, \n                    \"snd_wnd\": -1, \n                    \"socket\": 5, \n                    \"start\": 8.001013\n                }\n            ], \n            \"sum\": {\n                \"bits_per_second\": 0, \n                \"bytes\": 0, \n                \"end\": 9.001014, \n                \"omitted\": false, \n                \"retransmits\": 0, \n                \"seconds\": 1.0000009536743164, \n                \"sender\": true, \n                \"start\": 8.001013\n            }\n        }, \n        {\n            \"streams\": [\n                {\n                    \"bits_per_second\": 0, \n                    \"bytes\": 0, \n                    \"end\": 10.001013, \n                    \"omitted\": false, \n                    \"pmtu\": 1500, \n                    \"retransmits\": 0, \n                    \"rtt\": 74346, \n                    \"rttvar\": 500, \n                    \"seconds\": 0.9999989867210388, \n                    \"sender\": true, \n                    \"snd_cwnd\": 1024, \n                    \"snd_wnd\": -1, \n                    \"socket\": 5, \n                    \"start\": 9.001014\n                }\n            ], \n            \"sum\": {\n                \"bits_per_second\": 0, \n                \"bytes\": 0, \n                \"end\": 10.001013, \n                \"omitted\": false, \n                \"retransmits\": 0, \n                \"seconds\": 0.9999989867210388, \n                \"sender\": true, \n                \"start\": 9.001014\n            }\n        }, \n        {\n            \"streams\": [\n                {\n                    \"bits_per_second\": 10493483.184249349, \n                    \"bytes\": 1310720, \n                    \"end\": 11.000277, \n                    \"omitted\": false, \n                    \"pmtu\": 1500, \n                    \"retransmits\": 426, \n                    \"rtt\": 36824, \n                    \"rttvar\": 361, \n                    \"seconds\": 0.9992640018463135, \n                    \"sender\": true, \n                    \"snd_cwnd\": 100800, \n                    \"snd_wnd\": -1, \n                    \"socket\": 5, \n                    \"start\": 10.001013\n                }\n            ], \n            \"sum\": {\n                \"bits_per_second\": 10493483.184249349, \n                \"bytes\": 1310720, \n                \"end\": 11.000277, \n                \"omitted\": false, \n                \"retransmits\": 426, \n                \"seconds\": 0.9992640018463135, \n                \"sender\": true, \n                \"start\": 10.001013\n            }\n        }, \n        {\n            \"streams\": [\n                {\n                    \"bits_per_second\": 20970995.0131425, \n                    \"bytes\": 2621440, \n                    \"end\": 12.000302, \n                    \"omitted\": false, \n                    \"pmtu\": 1500, \n                    \"retransmits\": 0, \n                    \"rtt\": 47084, \n                    \"rttvar\": 549, \n                    \"seconds\": 1.0000250339508057, \n                    \"sender\": true, \n                    \"snd_cwnd\": 132848, \n                    \"snd_wnd\": -1, \n                    \"socket\": 5, \n                    \"start\": 11.000277\n                }\n            ], \n            \"sum\": {\n                \"bits_per_second\": 20970995.0131425, \n                \"bytes\": 2621440, \n                \"end\": 12.000302, \n                \"omitted\": false, \n                \"retransmits\": 0, \n                \"seconds\": 1.0000250339508057, \n                \"sender\": true, \n                \"start\": 11.000277\n            }\n        }, \n        {\n            \"streams\": [\n                {\n                    \"bits_per_second\": 20972862.58594616, \n                    \"bytes\": 2621440, \n                    \"end\": 13.000238, \n                    \"omitted\": false, \n                    \"pmtu\": 1500, \n                    \"retransmits\": 0, \n                    \"rtt\": 57815, \n                    \"rttvar\": 260, \n                    \"seconds\": 0.9999359846115112, \n                    \"sender\": true, \n                    \"snd_cwnd\": 158840, \n                    \"snd_wnd\": -1, \n                    \"socket\": 5, \n                    \"start\": 12.000302\n                }\n            ], \n            \"sum\": {\n                \"bits_per_second\": 20972862.58594616, \n                \"bytes\": 2621440, \n                \"end\": 13.000238, \n                \"omitted\": false, \n                \"retransmits\": 0, \n                \"seconds\": 0.9999359846115112, \n                \"sender\": true, \n                \"start\": 12.000302\n            }\n        }, \n        {\n            \"streams\": [\n                {\n                    \"bits_per_second\": 20969025.29679701, \n                    \"bytes\": 2621440, \n                    \"end\": 14.000357, \n                    \"omitted\": false, \n                    \"pmtu\": 1500, \n                    \"retransmits\": 0, \n                    \"rtt\": 70653, \n                    \"rttvar\": 849, \n                    \"seconds\": 1.0001189708709717, \n                    \"sender\": true, \n                    \"snd_cwnd\": 193496, \n                    \"snd_wnd\": -1, \n                    \"socket\": 5, \n                    \"start\": 13.000238\n                }\n            ], \n            \"sum\": {\n                \"bits_per_second\": 20969025.29679701, \n                \"bytes\": 2621440, \n                \"end\": 14.000357, \n                \"omitted\": false, \n                \"retransmits\": 0, \n                \"seconds\": 1.0001189708709717, \n                \"sender\": true, \n                \"start\": 13.000238\n            }\n        }, \n        {\n            \"streams\": [\n                {\n                    \"bits_per_second\": 20971017.51204015, \n                    \"bytes\": 2621440, \n                    \"end\": 15.000381, \n                    \"omitted\": false, \n                    \"pmtu\": 1500, \n                    \"retransmits\": 0, \n                    \"rtt\": 89065, \n                    \"rttvar\": 671, \n                    \"seconds\": 1.0000239610672, \n                    \"sender\": true, \n                    \"snd_cwnd\": 246924, \n                    \"snd_wnd\": -1, \n                    \"socket\": 5, \n                    \"start\": 14.000357\n                }\n            ], \n            \"sum\": {\n                \"bits_per_second\": 20971017.51204015, \n                \"bytes\": 2621440, \n                \"end\": 15.000381, \n                \"omitted\": false, \n                \"retransmits\": 0, \n                \"seconds\": 1.0000239610672, \n                \"sender\": true, \n                \"start\": 14.000357\n            }\n        }, \n        {\n            \"streams\": [\n                {\n                    \"bits_per_second\": 20971017.51204015, \n                    \"bytes\": 2621440, \n                    \"end\": 16.000405, \n                    \"omitted\": false, \n                    \"pmtu\": 1500, \n                    \"retransmits\": 0, \n                    \"rtt\": 110281, \n                    \"rttvar\": 691, \n                    \"seconds\": 1.0000239610672, \n                    \"sender\": true, \n                    \"snd_cwnd\": 306128, \n                    \"snd_wnd\": -1, \n                    \"socket\": 5, \n                    \"start\": 15.000381\n                }\n            ], \n            \"sum\": {\n                \"bits_per_second\": 20971017.51204015, \n                \"bytes\": 2621440, \n                \"end\": 16.000405, \n                \"omitted\": false, \n                \"retransmits\": 0, \n                \"seconds\": 1.0000239610672, \n                \"sender\": true, \n                \"start\": 15.000381\n            }\n        }, \n        {\n            \"streams\": [\n                {\n                    \"bits_per_second\": 20972506.29638361, \n                    \"bytes\": 2621440, \n                    \"end\": 17.000358, \n                    \"omitted\": false, \n                    \"pmtu\": 1500, \n                    \"retransmits\": 0, \n                    \"rtt\": 133126, \n                    \"rttvar\": 718, \n                    \"seconds\": 0.9999529719352722, \n                    \"sender\": true, \n                    \"snd_cwnd\": 371108, \n                    \"snd_wnd\": -1, \n                    \"socket\": 5, \n                    \"start\": 16.000405\n                }\n            ], \n            \"sum\": {\n                \"bits_per_second\": 20972506.29638361, \n                \"bytes\": 2621440, \n                \"end\": 17.000358, \n                \"omitted\": false, \n                \"retransmits\": 0, \n                \"seconds\": 0.9999529719352722, \n                \"sender\": true, \n                \"start\": 16.000405\n            }\n        }, \n        {\n            \"streams\": [\n                {\n                    \"bits_per_second\": 20971897.50679535, \n                    \"bytes\": 2621440, \n                    \"end\": 18.00034, \n                    \"omitted\": false, \n                    \"pmtu\": 1500, \n                    \"retransmits\": 8, \n                    \"rtt\": 75792, \n                    \"rttvar\": 576, \n                    \"seconds\": 0.9999819993972778, \n                    \"sender\": true, \n                    \"snd_cwnd\": 207936, \n                    \"snd_wnd\": -1, \n                    \"socket\": 5, \n                    \"start\": 17.000358\n                }\n            ], \n            \"sum\": {\n                \"bits_per_second\": 20971897.50679535, \n                \"bytes\": 2621440, \n                \"end\": 18.00034, \n                \"omitted\": false, \n                \"retransmits\": 8, \n                \"seconds\": 0.9999819993972778, \n                \"sender\": true, \n                \"start\": 17.000358\n            }\n        }, \n        {\n            \"streams\": [\n                {\n                    \"bits_per_second\": 31466091.217340175, \n                    \"bytes\": 3932160, \n                    \"end\": 19.00006, \n                    \"omitted\": false, \n                    \"pmtu\": 1500, \n                    \"retransmits\": 0, \n                    \"rtt\": 82525, \n                    \"rttvar\": 940, \n                    \"seconds\": 0.9997199773788452, \n                    \"sender\": true, \n                    \"snd_cwnd\": 225264, \n                    \"snd_wnd\": -1, \n                    \"socket\": 5, \n                    \"start\": 18.00034\n                }\n            ], \n            \"sum\": {\n                \"bits_per_second\": 31466091.217340175, \n                \"bytes\": 3932160, \n                \"end\": 19.00006, \n                \"omitted\": false, \n                \"retransmits\": 0, \n                \"seconds\": 0.9997199773788452, \n                \"sender\": true, \n                \"start\": 18.00034\n            }\n        }, \n        {\n            \"streams\": [\n                {\n                    \"bits_per_second\": 20971477.50008613, \n                    \"bytes\": 2621440, \n                    \"end\": 20.000062, \n                    \"omitted\": false, \n                    \"pmtu\": 1500, \n                    \"retransmits\": 0, \n                    \"rtt\": 88229, \n                    \"rttvar\": 738, \n                    \"seconds\": 1.0000020265579224, \n                    \"sender\": true, \n                    \"snd_cwnd\": 242592, \n                    \"snd_wnd\": -1, \n                    \"socket\": 5, \n                    \"start\": 19.00006\n                }\n            ], \n            \"sum\": {\n                \"bits_per_second\": 20971477.50008613, \n                \"bytes\": 2621440, \n                \"end\": 20.000062, \n                \"omitted\": false, \n                \"retransmits\": 0, \n                \"seconds\": 1.0000020265579224, \n                \"sender\": true, \n                \"start\": 19.00006\n            }\n        }, \n        {\n            \"streams\": [\n                {\n                    \"bits_per_second\": 20970932.51645787, \n                    \"bytes\": 2621440, \n                    \"end\": 21.00009, \n                    \"omitted\": false, \n                    \"pmtu\": 1500, \n                    \"retransmits\": 0, \n                    \"rtt\": 96966, \n                    \"rttvar\": 976, \n                    \"seconds\": 1.0000280141830444, \n                    \"sender\": true, \n                    \"snd_cwnd\": 265696, \n                    \"snd_wnd\": -1, \n                    \"socket\": 5, \n                    \"start\": 20.000062\n                }\n            ], \n            \"sum\": {\n                \"bits_per_second\": 20970932.51645787, \n                \"bytes\": 2621440, \n                \"end\": 21.00009, \n                \"omitted\": false, \n                \"retransmits\": 0, \n                \"seconds\": 1.0000280141830444, \n                \"sender\": true, \n                \"start\": 20.000062\n            }\n        }, \n        {\n            \"streams\": [\n                {\n                    \"bits_per_second\": 20971080.009231374, \n                    \"bytes\": 2621440, \n                    \"end\": 22.000111, \n                    \"omitted\": false, \n                    \"pmtu\": 1500, \n                    \"retransmits\": 0, \n                    \"rtt\": 110830, \n                    \"rttvar\": 980, \n                    \"seconds\": 1.000020980834961, \n                    \"sender\": true, \n                    \"snd_cwnd\": 307572, \n                    \"snd_wnd\": -1, \n                    \"socket\": 5, \n                    \"start\": 21.00009\n                }\n            ], \n            \"sum\": {\n                \"bits_per_second\": 20971080.009231374, \n                \"bytes\": 2621440, \n                \"end\": 22.000111, \n                \"omitted\": false, \n                \"retransmits\": 0, \n                \"seconds\": 1.000020980834961, \n                \"sender\": true, \n                \"start\": 21.00009\n            }\n        }, \n        {\n            \"streams\": [\n                {\n                    \"bits_per_second\": 20970955.015221424, \n                    \"bytes\": 2621440, \n                    \"end\": 23.000138, \n                    \"omitted\": false, \n                    \"pmtu\": 1500, \n                    \"retransmits\": 0, \n                    \"rtt\": 128996, \n                    \"rttvar\": 690, \n                    \"seconds\": 1.0000269412994385, \n                    \"sender\": true, \n                    \"snd_cwnd\": 358112, \n                    \"snd_wnd\": -1, \n                    \"socket\": 5, \n                    \"start\": 22.000111\n                }\n            ], \n            \"sum\": {\n                \"bits_per_second\": 20970955.015221424, \n                \"bytes\": 2621440, \n                \"end\": 23.000138, \n                \"omitted\": false, \n                \"retransmits\": 0, \n                \"seconds\": 1.0000269412994385, \n                \"sender\": true, \n                \"start\": 22.000111\n            }\n        }, \n        {\n            \"streams\": [\n                {\n                    \"bits_per_second\": 20972841.333246782, \n                    \"bytes\": 2621440, \n                    \"end\": 24.000075, \n                    \"omitted\": false, \n                    \"pmtu\": 1500, \n                    \"retransmits\": 6, \n                    \"rtt\": 131868, \n                    \"rttvar\": 3233, \n                    \"seconds\": 0.9999369978904724, \n                    \"sender\": true, \n                    \"snd_cwnd\": 202160, \n                    \"snd_wnd\": -1, \n                    \"socket\": 5, \n                    \"start\": 23.000138\n                }\n            ], \n            \"sum\": {\n                \"bits_per_second\": 20972841.333246782, \n                \"bytes\": 2621440, \n                \"end\": 24.000075, \n                \"omitted\": false, \n                \"retransmits\": 6, \n                \"seconds\": 0.9999369978904724, \n                \"sender\": true, \n                \"start\": 23.000138\n            }\n        }, \n        {\n            \"streams\": [\n                {\n                    \"bits_per_second\": 20968270.503581207, \n                    \"bytes\": 2621440, \n                    \"end\": 25.00023, \n                    \"omitted\": false, \n                    \"pmtu\": 1500, \n                    \"retransmits\": 0, \n                    \"rtt\": 80383, \n                    \"rttvar\": 614, \n                    \"seconds\": 1.000154972076416, \n                    \"sender\": true, \n                    \"snd_cwnd\": 219488, \n                    \"snd_wnd\": -1, \n                    \"socket\": 5, \n                    \"start\": 24.000075\n                }\n            ], \n            \"sum\": {\n                \"bits_per_second\": 20968270.503581207, \n                \"bytes\": 2621440, \n                \"end\": 25.00023, \n                \"omitted\": false, \n                \"retransmits\": 0, \n                \"seconds\": 1.000154972076416, \n                \"sender\": true, \n                \"start\": 24.000075\n            }\n        }, \n        {\n            \"streams\": [\n                {\n                    \"bits_per_second\": 20970890.0189251, \n                    \"bytes\": 2621440, \n                    \"end\": 26.00026, \n                    \"omitted\": false, \n                    \"pmtu\": 1500, \n                    \"retransmits\": 0, \n                    \"rtt\": 86215, \n                    \"rttvar\": 399, \n                    \"seconds\": 1.0000300407409668, \n                    \"sender\": true, \n                    \"snd_cwnd\": 236816, \n                    \"snd_wnd\": -1, \n                    \"socket\": 5, \n                    \"start\": 25.00023\n                }\n            ], \n            \"sum\": {\n                \"bits_per_second\": 20970890.0189251, \n                \"bytes\": 2621440, \n                \"end\": 26.00026, \n                \"omitted\": false, \n                \"retransmits\": 0, \n                \"seconds\": 1.0000300407409668, \n                \"sender\": true, \n                \"start\": 25.00023\n            }\n        }, \n        {\n            \"streams\": [\n                {\n                    \"bits_per_second\": 20971017.51204015, \n                    \"bytes\": 2621440, \n                    \"end\": 27.000284, \n                    \"omitted\": false, \n                    \"pmtu\": 1500, \n                    \"retransmits\": 0, \n                    \"rtt\": 93681, \n                    \"rttvar\": 293, \n                    \"seconds\": 1.0000239610672, \n                    \"sender\": true, \n                    \"snd_cwnd\": 257032, \n                    \"snd_wnd\": -1, \n                    \"socket\": 5, \n                    \"start\": 26.00026\n                }\n            ], \n            \"sum\": {\n                \"bits_per_second\": 20971017.51204015, \n                \"bytes\": 2621440, \n                \"end\": 27.000284, \n                \"omitted\": false, \n                \"retransmits\": 0, \n                \"seconds\": 1.0000239610672, \n                \"sender\": true, \n                \"start\": 26.00026\n            }\n        }, \n        {\n            \"streams\": [\n                {\n                    \"bits_per_second\": 0, \n                    \"bytes\": 0, \n                    \"end\": 28.000271, \n                    \"omitted\": false, \n                    \"pmtu\": 1500, \n                    \"retransmits\": 1, \n                    \"rtt\": 95899, \n                    \"rttvar\": 534, \n                    \"seconds\": 0.999987006187439, \n                    \"sender\": true, \n                    \"snd_cwnd\": 1444, \n                    \"snd_wnd\": -1, \n                    \"socket\": 5, \n                    \"start\": 27.000284\n                }\n            ], \n            \"sum\": {\n                \"bits_per_second\": 0, \n                \"bytes\": 0, \n                \"end\": 28.000271, \n                \"omitted\": false, \n                \"retransmits\": 1, \n                \"seconds\": 0.999987006187439, \n                \"sender\": true, \n                \"start\": 27.000284\n            }\n        }, \n        {\n            \"streams\": [\n                {\n                    \"bits_per_second\": 0, \n                    \"bytes\": 0, \n                    \"end\": 29.001015, \n                    \"omitted\": false, \n                    \"pmtu\": 1500, \n                    \"retransmits\": 1, \n                    \"rtt\": 95899, \n                    \"rttvar\": 534, \n                    \"seconds\": 1.0007439851760864, \n                    \"sender\": true, \n                    \"snd_cwnd\": 1444, \n                    \"snd_wnd\": -1, \n                    \"socket\": 5, \n                    \"start\": 28.000271\n                }\n            ], \n            \"sum\": {\n                \"bits_per_second\": 0, \n                \"bytes\": 0, \n                \"end\": 29.001015, \n                \"omitted\": false, \n                \"retransmits\": 1, \n                \"seconds\": 1.0007439851760864, \n                \"sender\": true, \n                \"start\": 28.000271\n            }\n        }, \n        {\n            \"streams\": [\n                {\n                    \"bits_per_second\": 0, \n                    \"bytes\": 0, \n                    \"end\": 30.001014, \n                    \"omitted\": false, \n                    \"pmtu\": 1500, \n                    \"retransmits\": 1, \n                    \"rtt\": 95899, \n                    \"rttvar\": 534, \n                    \"seconds\": 0.9999989867210388, \n                    \"sender\": true, \n                    \"snd_cwnd\": 1444, \n                    \"snd_wnd\": -1, \n                    \"socket\": 5, \n                    \"start\": 29.001015\n                }\n            ], \n            \"sum\": {\n                \"bits_per_second\": 0, \n                \"bytes\": 0, \n                \"end\": 30.001014, \n                \"omitted\": false, \n                \"retransmits\": 1, \n                \"seconds\": 0.9999989867210388, \n                \"sender\": true, \n                \"start\": 29.001015\n            }\n        }, \n        {\n            \"streams\": [\n                {\n                    \"bits_per_second\": 0, \n                    \"bytes\": 0, \n                    \"end\": 31.001014, \n                    \"omitted\": false, \n                    \"pmtu\": 1500, \n                    \"retransmits\": 0, \n                    \"rtt\": 95899, \n                    \"rttvar\": 534, \n                    \"seconds\": 1, \n                    \"sender\": true, \n                    \"snd_cwnd\": 1444, \n                    \"snd_wnd\": -1, \n                    \"socket\": 5, \n                    \"start\": 30.001014\n                }\n            ], \n            \"sum\": {\n                \"bits_per_second\": 0, \n                \"bytes\": 0, \n                \"end\": 31.001014, \n                \"omitted\": false, \n                \"retransmits\": 0, \n                \"seconds\": 1, \n                \"sender\": true, \n                \"start\": 30.001014\n            }\n        }, \n        {\n            \"streams\": [\n                {\n                    \"bits_per_second\": 0, \n                    \"bytes\": 0, \n                    \"end\": 32.001014, \n                    \"omitted\": false, \n                    \"pmtu\": 1500, \n                    \"retransmits\": 1, \n                    \"rtt\": 95899, \n                    \"rttvar\": 534, \n                    \"seconds\": 1, \n                    \"sender\": true, \n                    \"snd_cwnd\": 722, \n                    \"snd_wnd\": -1, \n                    \"socket\": 5, \n                    \"start\": 31.001014\n                }\n            ], \n            \"sum\": {\n                \"bits_per_second\": 0, \n                \"bytes\": 0, \n                \"end\": 32.001014, \n                \"omitted\": false, \n                \"retransmits\": 1, \n                \"seconds\": 1, \n                \"sender\": true, \n                \"start\": 31.001014\n            }\n        }, \n        {\n            \"streams\": [\n                {\n                    \"bits_per_second\": 0, \n                    \"bytes\": 0, \n                    \"end\": 33.001015, \n                    \"omitted\": false, \n                    \"pmtu\": 1500, \n                    \"retransmits\": 0, \n                    \"rtt\": 95899, \n                    \"rttvar\": 534, \n                    \"seconds\": 1.0000009536743164, \n                    \"sender\": true, \n                    \"snd_cwnd\": 722, \n                    \"snd_wnd\": -1, \n                    \"socket\": 5, \n                    \"start\": 32.001014\n                }\n            ], \n            \"sum\": {\n                \"bits_per_second\": 0, \n                \"bytes\": 0, \n                \"end\": 33.001015, \n                \"omitted\": false, \n                \"retransmits\": 0, \n                \"seconds\": 1.0000009536743164, \n                \"sender\": true, \n                \"start\": 32.001014\n            }\n        }, \n        {\n            \"streams\": [\n                {\n                    \"bits_per_second\": 0, \n                    \"bytes\": 0, \n                    \"end\": 34.001015, \n                    \"omitted\": false, \n                    \"pmtu\": 1500, \n                    \"retransmits\": 0, \n                    \"rtt\": 95899, \n                    \"rttvar\": 534, \n                    \"seconds\": 1, \n                    \"sender\": true, \n                    \"snd_cwnd\": 722, \n                    \"snd_wnd\": -1, \n                    \"socket\": 5, \n                    \"start\": 33.001015\n                }\n            ], \n            \"sum\": {\n                \"bits_per_second\": 0, \n                \"bytes\": 0, \n                \"end\": 34.001015, \n                \"omitted\": false, \n                \"retransmits\": 0, \n                \"seconds\": 1, \n                \"sender\": true, \n                \"start\": 33.001015\n            }\n        }, \n        {\n            \"streams\": [\n                {\n                    \"bits_per_second\": 0, \n                    \"bytes\": 0, \n                    \"end\": 35.00102, \n                    \"omitted\": false, \n                    \"pmtu\": 1500, \n                    \"retransmits\": 0, \n                    \"rtt\": 95899, \n                    \"rttvar\": 534, \n                    \"seconds\": 1.0000050067901611, \n                    \"sender\": true, \n                    \"snd_cwnd\": 722, \n                    \"snd_wnd\": -1, \n                    \"socket\": 5, \n                    \"start\": 34.001015\n                }\n            ], \n            \"sum\": {\n                \"bits_per_second\": 0, \n                \"bytes\": 0, \n                \"end\": 35.00102, \n                \"omitted\": false, \n                \"retransmits\": 0, \n                \"seconds\": 1.0000050067901611, \n                \"sender\": true, \n                \"start\": 34.001015\n            }\n        }, \n        {\n            \"streams\": [\n                {\n                    \"bits_per_second\": 0, \n                    \"bytes\": 0, \n                    \"end\": 36.000233, \n                    \"omitted\": false, \n                    \"pmtu\": 1500, \n                    \"retransmits\": 0, \n                    \"rtt\": 95899, \n                    \"rttvar\": 534, \n                    \"seconds\": 0.9992129802703857, \n                    \"sender\": true, \n                    \"snd_cwnd\": 722, \n                    \"snd_wnd\": -1, \n                    \"socket\": 5, \n                    \"start\": 35.00102\n                }\n            ], \n            \"sum\": {\n                \"bits_per_second\": 0, \n                \"bytes\": 0, \n                \"end\": 36.000233, \n                \"omitted\": false, \n                \"retransmits\": 0, \n                \"seconds\": 0.9992129802703857, \n                \"sender\": true, \n                \"start\": 35.00102\n            }\n        }, \n        {\n            \"streams\": [\n                {\n                    \"bits_per_second\": 0, \n                    \"bytes\": 0, \n                    \"end\": 37.001016, \n                    \"omitted\": false, \n                    \"pmtu\": 1500, \n                    \"retransmits\": 1, \n                    \"rtt\": 95899, \n                    \"rttvar\": 534, \n                    \"seconds\": 1.0007829666137695, \n                    \"sender\": true, \n                    \"snd_cwnd\": 361, \n                    \"snd_wnd\": -1, \n                    \"socket\": 5, \n                    \"start\": 36.000233\n                }\n            ], \n            \"sum\": {\n                \"bits_per_second\": 0, \n                \"bytes\": 0, \n                \"end\": 37.001016, \n                \"omitted\": false, \n                \"retransmits\": 1, \n                \"seconds\": 1.0007829666137695, \n                \"sender\": true, \n                \"start\": 36.000233\n            }\n        }, \n        {\n            \"streams\": [\n                {\n                    \"bits_per_second\": 0, \n                    \"bytes\": 0, \n                    \"end\": 38.001015, \n                    \"omitted\": false, \n                    \"pmtu\": 1500, \n                    \"retransmits\": 0, \n                    \"rtt\": 95899, \n                    \"rttvar\": 534, \n                    \"seconds\": 0.9999989867210388, \n                    \"sender\": true, \n                    \"snd_cwnd\": 361, \n                    \"snd_wnd\": -1, \n                    \"socket\": 5, \n                    \"start\": 37.001016\n                }\n            ], \n            \"sum\": {\n                \"bits_per_second\": 0, \n                \"bytes\": 0, \n                \"end\": 38.001015, \n                \"omitted\": false, \n                \"retransmits\": 0, \n                \"seconds\": 0.9999989867210388, \n                \"sender\": true, \n                \"start\": 37.001016\n            }\n        }, \n        {\n            \"streams\": [\n                {\n                    \"bits_per_second\": 0, \n                    \"bytes\": 0, \n                    \"end\": 39.001014, \n                    \"omitted\": false, \n                    \"pmtu\": 1500, \n                    \"retransmits\": 0, \n                    \"rtt\": 95899, \n                    \"rttvar\": 534, \n                    \"seconds\": 0.9999989867210388, \n                    \"sender\": true, \n                    \"snd_cwnd\": 361, \n                    \"snd_wnd\": -1, \n                    \"socket\": 5, \n                    \"start\": 38.001015\n                }\n            ], \n            \"sum\": {\n                \"bits_per_second\": 0, \n                \"bytes\": 0, \n                \"end\": 39.001014, \n                \"omitted\": false, \n                \"retransmits\": 0, \n                \"seconds\": 0.9999989867210388, \n                \"sender\": true, \n                \"start\": 38.001015\n            }\n        }, \n        {\n            \"streams\": [\n                {\n                    \"bits_per_second\": 0, \n                    \"bytes\": 0, \n                    \"end\": 40.000574, \n                    \"omitted\": false, \n                    \"pmtu\": 1500, \n                    \"retransmits\": 0, \n                    \"rtt\": 95899, \n                    \"rttvar\": 534, \n                    \"seconds\": 0.999559998512268, \n                    \"sender\": true, \n                    \"snd_cwnd\": 361, \n                    \"snd_wnd\": -1, \n                    \"socket\": 5, \n                    \"start\": 39.001014\n                }\n            ], \n            \"sum\": {\n                \"bits_per_second\": 0, \n                \"bytes\": 0, \n                \"end\": 40.000574, \n                \"omitted\": false, \n                \"retransmits\": 0, \n                \"seconds\": 0.999559998512268, \n                \"sender\": true, \n                \"start\": 39.001014\n            }\n        }, \n        {\n            \"streams\": [\n                {\n                    \"bits_per_second\": 0, \n                    \"bytes\": 0, \n                    \"end\": 41.001016, \n                    \"omitted\": false, \n                    \"pmtu\": 1500, \n                    \"retransmits\": 0, \n                    \"rtt\": 95899, \n                    \"rttvar\": 534, \n                    \"seconds\": 1.0004420280456543, \n                    \"sender\": true, \n                    \"snd_cwnd\": 361, \n                    \"snd_wnd\": -1, \n                    \"socket\": 5, \n                    \"start\": 40.000574\n                }\n            ], \n            \"sum\": {\n                \"bits_per_second\": 0, \n                \"bytes\": 0, \n                \"end\": 41.001016, \n                \"omitted\": false, \n                \"retransmits\": 0, \n                \"seconds\": 1.0004420280456543, \n                \"sender\": true, \n                \"start\": 40.000574\n            }\n        }, \n        {\n            \"streams\": [\n                {\n                    \"bits_per_second\": 0, \n                    \"bytes\": 0, \n                    \"end\": 42.001013, \n                    \"omitted\": false, \n                    \"pmtu\": 1500, \n                    \"retransmits\": 0, \n                    \"rtt\": 95899, \n                    \"rttvar\": 534, \n                    \"seconds\": 0.9999970197677612, \n                    \"sender\": true, \n                    \"snd_cwnd\": 361, \n                    \"snd_wnd\": -1, \n                    \"socket\": 5, \n                    \"start\": 41.001016\n                }\n            ], \n            \"sum\": {\n                \"bits_per_second\": 0, \n                \"bytes\": 0, \n                \"end\": 42.001013, \n                \"omitted\": false, \n                \"retransmits\": 0, \n                \"seconds\": 0.9999970197677612, \n                \"sender\": true, \n                \"start\": 41.001016\n            }\n        }, \n        {\n            \"streams\": [\n                {\n                    \"bits_per_second\": 0, \n                    \"bytes\": 0, \n                    \"end\": 43.001014, \n                    \"omitted\": false, \n                    \"pmtu\": 1500, \n                    \"retransmits\": 0, \n                    \"rtt\": 95899, \n                    \"rttvar\": 534, \n                    \"seconds\": 1.0000009536743164, \n                    \"sender\": true, \n                    \"snd_cwnd\": 361, \n                    \"snd_wnd\": -1, \n                    \"socket\": 5, \n                    \"start\": 42.001013\n                }\n            ], \n            \"sum\": {\n                \"bits_per_second\": 0, \n                \"bytes\": 0, \n                \"end\": 43.001014, \n                \"omitted\": false, \n                \"retransmits\": 0, \n                \"seconds\": 1.0000009536743164, \n                \"sender\": true, \n                \"start\": 42.001013\n            }\n        }, \n        {\n            \"streams\": [\n                {\n                    \"bits_per_second\": 0, \n                    \"bytes\": 0, \n                    \"end\": 44.00104, \n                    \"omitted\": false, \n                    \"pmtu\": 1500, \n                    \"retransmits\": 0, \n                    \"rtt\": 95899, \n                    \"rttvar\": 534, \n                    \"seconds\": 1.000025987625122, \n                    \"sender\": true, \n                    \"snd_cwnd\": 361, \n                    \"snd_wnd\": -1, \n                    \"socket\": 5, \n                    \"start\": 43.001014\n                }\n            ], \n            \"sum\": {\n                \"bits_per_second\": 0, \n                \"bytes\": 0, \n                \"end\": 44.00104, \n                \"omitted\": false, \n                \"retransmits\": 0, \n                \"seconds\": 1.000025987625122, \n                \"sender\": true, \n                \"start\": 43.001014\n            }\n        }, \n        {\n            \"streams\": [\n                {\n                    \"bits_per_second\": 0, \n                    \"bytes\": 0, \n                    \"end\": 45.001022, \n                    \"omitted\": false, \n                    \"pmtu\": 1500, \n                    \"retransmits\": 0, \n                    \"rtt\": 95899, \n                    \"rttvar\": 534, \n                    \"seconds\": 0.9999819993972778, \n                    \"sender\": true, \n                    \"snd_cwnd\": 361, \n                    \"snd_wnd\": -1, \n                    \"socket\": 5, \n                    \"start\": 44.00104\n                }\n            ], \n            \"sum\": {\n                \"bits_per_second\": 0, \n                \"bytes\": 0, \n                \"end\": 45.001022, \n                \"omitted\": false, \n                \"retransmits\": 0, \n                \"seconds\": 0.9999819993972778, \n                \"sender\": true, \n                \"start\": 44.00104\n            }\n        }, \n        {\n            \"streams\": [\n                {\n                    \"bits_per_second\": 0, \n                    \"bytes\": 0, \n                    \"end\": 46.001026, \n                    \"omitted\": false, \n                    \"pmtu\": 1500, \n                    \"retransmits\": 0, \n                    \"rtt\": 95899, \n                    \"rttvar\": 534, \n                    \"seconds\": 1.0000040531158447, \n                    \"sender\": true, \n                    \"snd_cwnd\": 361, \n                    \"snd_wnd\": -1, \n                    \"socket\": 5, \n                    \"start\": 45.001022\n                }\n            ], \n            \"sum\": {\n                \"bits_per_second\": 0, \n                \"bytes\": 0, \n                \"end\": 46.001026, \n                \"omitted\": false, \n                \"retransmits\": 0, \n                \"seconds\": 1.0000040531158447, \n                \"sender\": true, \n                \"start\": 45.001022\n            }\n        }, \n        {\n            \"streams\": [\n                {\n                    \"bits_per_second\": 10492055.026892465, \n                    \"bytes\": 1310720, \n                    \"end\": 47.000426, \n                    \"omitted\": false, \n                    \"pmtu\": 1500, \n                    \"retransmits\": 1381, \n                    \"rtt\": 24052, \n                    \"rttvar\": 1773, \n                    \"seconds\": 0.999400019645691, \n                    \"sender\": true, \n                    \"snd_cwnd\": 16200, \n                    \"snd_wnd\": -1, \n                    \"socket\": 5, \n                    \"start\": 46.001026\n                }\n            ], \n            \"sum\": {\n                \"bits_per_second\": 10492055.026892465, \n                \"bytes\": 1310720, \n                \"end\": 47.000426, \n                \"omitted\": false, \n                \"retransmits\": 1381, \n                \"seconds\": 0.999400019645691, \n                \"sender\": true, \n                \"start\": 46.001026\n            }\n        }, \n        {\n            \"streams\": [\n                {\n                    \"bits_per_second\": 0, \n                    \"bytes\": 0, \n                    \"end\": 48.000163, \n                    \"omitted\": false, \n                    \"pmtu\": 1500, \n                    \"retransmits\": 0, \n                    \"rtt\": 37043, \n                    \"rttvar\": 6876, \n                    \"seconds\": 0.999737024307251, \n                    \"sender\": true, \n                    \"snd_cwnd\": 109565, \n                    \"snd_wnd\": -1, \n                    \"socket\": 5, \n                    \"start\": 47.000426\n                }\n            ], \n            \"sum\": {\n                \"bits_per_second\": 0, \n                \"bytes\": 0, \n                \"end\": 48.000163, \n                \"omitted\": false, \n                \"retransmits\": 0, \n                \"seconds\": 0.999737024307251, \n                \"sender\": true, \n                \"start\": 47.000426\n            }\n        }, \n        {\n            \"streams\": [\n                {\n                    \"bits_per_second\": 0, \n                    \"bytes\": 0, \n                    \"end\": 49.000486, \n                    \"omitted\": false, \n                    \"pmtu\": 1500, \n                    \"retransmits\": 0, \n                    \"rtt\": 37043, \n                    \"rttvar\": 6876, \n                    \"seconds\": 1.0003230571746826, \n                    \"sender\": true, \n                    \"snd_cwnd\": 109565, \n                    \"snd_wnd\": -1, \n                    \"socket\": 5, \n                    \"start\": 48.000163\n                }\n            ], \n            \"sum\": {\n                \"bits_per_second\": 0, \n                \"bytes\": 0, \n                \"end\": 49.000486, \n                \"omitted\": false, \n                \"retransmits\": 0, \n                \"seconds\": 1.0003230571746826, \n                \"sender\": true, \n                \"start\": 48.000163\n            }\n        }, \n        {\n            \"streams\": [\n                {\n                    \"bits_per_second\": 0, \n                    \"bytes\": 0, \n                    \"end\": 50.000892, \n                    \"omitted\": false, \n                    \"pmtu\": 1500, \n                    \"retransmits\": 0, \n                    \"rtt\": 37043, \n                    \"rttvar\": 6876, \n                    \"seconds\": 1.00040602684021, \n                    \"sender\": true, \n                    \"snd_cwnd\": 109565, \n                    \"snd_wnd\": -1, \n                    \"socket\": 5, \n                    \"start\": 49.000486\n                }\n            ], \n            \"sum\": {\n                \"bits_per_second\": 0, \n                \"bytes\": 0, \n                \"end\": 50.000892, \n                \"omitted\": false, \n                \"retransmits\": 0, \n                \"seconds\": 1.00040602684021, \n                \"sender\": true, \n                \"start\": 49.000486\n            }\n        }, \n        {\n            \"streams\": [\n                {\n                    \"bits_per_second\": 0, \n                    \"bytes\": 0, \n                    \"end\": 51.001021, \n                    \"omitted\": false, \n                    \"pmtu\": 1500, \n                    \"retransmits\": 0, \n                    \"rtt\": 37043, \n                    \"rttvar\": 6876, \n                    \"seconds\": 1.000128984451294, \n                    \"sender\": true, \n                    \"snd_cwnd\": 109565, \n                    \"snd_wnd\": -1, \n                    \"socket\": 5, \n                    \"start\": 50.000892\n                }\n            ], \n            \"sum\": {\n                \"bits_per_second\": 0, \n                \"bytes\": 0, \n                \"end\": 51.001021, \n                \"omitted\": false, \n                \"retransmits\": 0, \n                \"seconds\": 1.000128984451294, \n                \"sender\": true, \n                \"start\": 50.000892\n            }\n        }, \n        {\n            \"streams\": [\n                {\n                    \"bits_per_second\": 0, \n                    \"bytes\": 0, \n                    \"end\": 52.001021, \n                    \"omitted\": false, \n                    \"pmtu\": 1500, \n                    \"retransmits\": 0, \n                    \"rtt\": 37043, \n                    \"rttvar\": 6876, \n                    \"seconds\": 1, \n                    \"sender\": true, \n                    \"snd_cwnd\": 109565, \n                    \"snd_wnd\": -1, \n                    \"socket\": 5, \n                    \"start\": 51.001021\n                }\n            ], \n            \"sum\": {\n                \"bits_per_second\": 0, \n                \"bytes\": 0, \n                \"end\": 52.001021, \n                \"omitted\": false, \n                \"retransmits\": 0, \n                \"seconds\": 1, \n                \"sender\": true, \n                \"start\": 51.001021\n            }\n        }, \n        {\n            \"streams\": [\n                {\n                    \"bits_per_second\": 0, \n                    \"bytes\": 0, \n                    \"end\": 53.001018, \n                    \"omitted\": false, \n                    \"pmtu\": 1500, \n                    \"retransmits\": 0, \n                    \"rtt\": 37043, \n                    \"rttvar\": 6876, \n                    \"seconds\": 0.9999970197677612, \n                    \"sender\": true, \n                    \"snd_cwnd\": 109565, \n                    \"snd_wnd\": -1, \n                    \"socket\": 5, \n                    \"start\": 52.001021\n                }\n            ], \n            \"sum\": {\n                \"bits_per_second\": 0, \n                \"bytes\": 0, \n                \"end\": 53.001018, \n                \"omitted\": false, \n                \"retransmits\": 0, \n                \"seconds\": 0.9999970197677612, \n                \"sender\": true, \n                \"start\": 52.001021\n            }\n        }, \n        {\n            \"streams\": [\n                {\n                    \"bits_per_second\": 0, \n                    \"bytes\": 0, \n                    \"end\": 54.001022, \n                    \"omitted\": false, \n                    \"pmtu\": 1500, \n                    \"retransmits\": 85, \n                    \"rtt\": 23464, \n                    \"rttvar\": 4658, \n                    \"seconds\": 1.0000040531158447, \n                    \"sender\": true, \n                    \"snd_cwnd\": 57456, \n                    \"snd_wnd\": -1, \n                    \"socket\": 5, \n                    \"start\": 53.001018\n                }\n            ], \n            \"sum\": {\n                \"bits_per_second\": 0, \n                \"bytes\": 0, \n                \"end\": 54.001022, \n                \"omitted\": false, \n                \"retransmits\": 85, \n                \"seconds\": 1.0000040531158447, \n                \"sender\": true, \n                \"start\": 53.001018\n            }\n        }, \n        {\n            \"streams\": [\n                {\n                    \"bits_per_second\": 20987512.185818166, \n                    \"bytes\": 2621440, \n                    \"end\": 55.00026, \n                    \"omitted\": false, \n                    \"pmtu\": 1500, \n                    \"retransmits\": 0, \n                    \"rtt\": 36410, \n                    \"rttvar\": 766, \n                    \"seconds\": 0.9992380142211914, \n                    \"sender\": true, \n                    \"snd_cwnd\": 102453, \n                    \"snd_wnd\": -1, \n                    \"socket\": 5, \n                    \"start\": 54.001022\n                }\n            ], \n            \"sum\": {\n                \"bits_per_second\": 20987512.185818166, \n                \"bytes\": 2621440, \n                \"end\": 55.00026, \n                \"omitted\": false, \n                \"retransmits\": 0, \n                \"seconds\": 0.9992380142211914, \n                \"sender\": true, \n                \"start\": 54.001022\n            }\n        }, \n        {\n            \"streams\": [\n                {\n                    \"bits_per_second\": 20971017.51204015, \n                    \"bytes\": 2621440, \n                    \"end\": 56.000284, \n                    \"omitted\": false, \n                    \"pmtu\": 1500, \n                    \"retransmits\": 0, \n                    \"rtt\": 48796, \n                    \"rttvar\": 385, \n                    \"seconds\": 1.0000239610672, \n                    \"sender\": true, \n                    \"snd_cwnd\": 134199, \n                    \"snd_wnd\": -1, \n                    \"socket\": 5, \n                    \"start\": 55.00026\n                }\n            ], \n            \"sum\": {\n                \"bits_per_second\": 20971017.51204015, \n                \"bytes\": 2621440, \n                \"end\": 56.000284, \n                \"omitted\": false, \n                \"retransmits\": 0, \n                \"seconds\": 1.0000239610672, \n                \"sender\": true, \n                \"start\": 55.00026\n            }\n        }, \n        {\n            \"streams\": [\n                {\n                    \"bits_per_second\": 20970932.51645787, \n                    \"bytes\": 2621440, \n                    \"end\": 57.000312, \n                    \"omitted\": false, \n                    \"pmtu\": 1500, \n                    \"retransmits\": 0, \n                    \"rtt\": 61724, \n                    \"rttvar\": 467, \n                    \"seconds\": 1.0000280141830444, \n                    \"sender\": true, \n                    \"snd_cwnd\": 170274, \n                    \"snd_wnd\": -1, \n                    \"socket\": 5, \n                    \"start\": 56.000284\n                }\n            ], \n            \"sum\": {\n                \"bits_per_second\": 20970932.51645787, \n                \"bytes\": 2621440, \n                \"end\": 57.000312, \n                \"omitted\": false, \n                \"retransmits\": 0, \n                \"seconds\": 1.0000280141830444, \n                \"sender\": true, \n                \"start\": 56.000284\n            }\n        }, \n        {\n            \"streams\": [\n                {\n                    \"bits_per_second\": 20970995.0131425, \n                    \"bytes\": 2621440, \n                    \"end\": 58.000337, \n                    \"omitted\": false, \n                    \"pmtu\": 1500, \n                    \"retransmits\": 0, \n                    \"rtt\": 80655, \n                    \"rttvar\": 784, \n                    \"seconds\": 1.0000250339508057, \n                    \"sender\": true, \n                    \"snd_cwnd\": 222222, \n                    \"snd_wnd\": -1, \n                    \"socket\": 5, \n                    \"start\": 57.000312\n                }\n            ], \n            \"sum\": {\n                \"bits_per_second\": 20970995.0131425, \n                \"bytes\": 2621440, \n                \"end\": 58.000337, \n                \"omitted\": false, \n                \"retransmits\": 0, \n                \"seconds\": 1.0000250339508057, \n                \"sender\": true, \n                \"start\": 57.000312\n            }\n        }, \n        {\n            \"streams\": [\n                {\n                    \"bits_per_second\": 20971057.51019962, \n                    \"bytes\": 2621440, \n                    \"end\": 59.000359, \n                    \"omitted\": false, \n                    \"pmtu\": 1500, \n                    \"retransmits\": 0, \n                    \"rtt\": 101844, \n                    \"rttvar\": 781, \n                    \"seconds\": 1.000022053718567, \n                    \"sender\": true, \n                    \"snd_cwnd\": 284271, \n                    \"snd_wnd\": -1, \n                    \"socket\": 5, \n                    \"start\": 58.000337\n                }\n            ], \n            \"sum\": {\n                \"bits_per_second\": 20971057.51019962, \n                \"bytes\": 2621440, \n                \"end\": 59.000359, \n                \"omitted\": false, \n                \"retransmits\": 0, \n                \"seconds\": 1.000022053718567, \n                \"sender\": true, \n                \"start\": 58.000337\n            }\n        }, \n        {\n            \"streams\": [\n                {\n                    \"bits_per_second\": 20970932.51645787, \n                    \"bytes\": 2621440, \n                    \"end\": 60.000387, \n                    \"omitted\": false, \n                    \"pmtu\": 1500, \n                    \"retransmits\": 0, \n                    \"rtt\": 125886, \n                    \"rttvar\": 440, \n                    \"seconds\": 1.0000280141830444, \n                    \"sender\": true, \n                    \"snd_cwnd\": 347763, \n                    \"snd_wnd\": -1, \n                    \"socket\": 5, \n                    \"start\": 59.000359\n                }\n            ], \n            \"sum\": {\n                \"bits_per_second\": 20970932.51645787, \n                \"bytes\": 2621440, \n                \"end\": 60.000387, \n                \"omitted\": false, \n                \"retransmits\": 0, \n                \"seconds\": 1.0000280141830444, \n                \"sender\": true, \n                \"start\": 59.000359\n            }\n        }\n    ], \n    \"start\": {\n        \"connected\": [\n            {\n                \"local_host\": \"172.16.0.2\", \n                \"local_port\": 55387, \n                \"remote_host\": \"172.16.0.1\", \n                \"remote_port\": 5201, \n                \"socket\": 5\n            }\n        ], \n        \"connecting_to\": {\n            \"host\": \"172.16.0.1\", \n            \"port\": 5201\n        }, \n        \"cookie\": \"jm2rsmdbojoyaih6b5oi5xef5l2krlevq2mf\", \n        \"fq_rate\": 0, \n        \"rcvbuf_actual\": 87380, \n        \"sndbuf_actual\": 65536, \n        \"sock_bufsize\": 0, \n        \"system_info\": \"REDACTED\", \n        \"target_bitrate\": 0, \n        \"tcp_mss_default\": 1448, \n        \"test_start\": {\n            \"bidir\": 0, \n            \"blksize\": 131072, \n            \"blocks\": 0, \n            \"bytes\": 0, \n            \"duration\": 60, \n            \"fqrate\": 0, \n            \"num_streams\": 1, \n            \"omit\": 0, \n            \"protocol\": \"TCP\", \n            \"reverse\": 0, \n            \"target_bitrate\": 0, \n            \"tos\": 0\n        }, \n        \"timestamp\": {\n            \"time\": \"Thu, 09 May 2024 01:35:57 GMT\", \n            \"timesecs\": 1715218557\n        }, \n        \"version\": \"iperf 3.14\"\n    }\n}\nParticipant 1:\n/usr/bin/iperf3 -s -1 --idle-timeout 60 --json -p 5201 -B 172.16.0.1 --authorized-users-path /var/run/pscheduler-server/runner/tmp/tmpy8y7y89n/tmpdsmav4h6/credentials --rsa-private-key-path /var/run/pscheduler-server/runner/tmp/tmpy8y7y89n/tmpdsmav4h6/private-key\n","summary":{"streams":[{"end":60.000387,"rtt":80487,"start":0,"stream-id":5,"retransmits":2203,"throughput-bits":9017695.43586444,"throughput-bytes":67633152}],"summary":{"end":60.000387,"start":0,"retransmits":2203,"throughput-bits":9017695.43586444,"throughput-bytes":67633152,"receiver-throughput-bits":8600919.8651786}},"intervals":[{"streams":[{"end":1.000203,"rtt":92608,"start":0,"omitted":false,"stream-id":5,"retransmits":288,"tcp-window-size":201272,"throughput-bits":48224705.73755466,"throughput-bytes":6029312}],"summary":{"end":1.000203,"start":0,"omitted":false,"retransmits":288,"throughput-bits":48224705.73755466,"throughput-bytes":6029312}},{"streams":[{"end":2.001015,"rtt":74346,"start":1.000203,"omitted":false,"stream-id":5,"retransmits":1,"tcp-window-size":1448,"throughput-bits":0,"throughput-bytes":0}],"summary":{"end":2.001015,"start":1.000203,"omitted":false,"retransmits":1,"throughput-bits":0,"throughput-bytes":0}},{"streams":[{"end":3.001019,"rtt":74346,"start":2.001015,"omitted":false,"stream-id":5,"retransmits":1,"tcp-window-size":1448,"throughput-bits":0,"throughput-bytes":0}],"summary":{"end":3.001019,"start":2.001015,"omitted":false,"retransmits":1,"throughput-bits":0,"throughput-bytes":0}},{"streams":[{"end":4.000031,"rtt":74346,"start":3.001019,"omitted":false,"stream-id":5,"retransmits":1,"tcp-window-size":1448,"throughput-bits":0,"throughput-bytes":0}],"summary":{"end":4.000031,"start":3.001019,"omitted":false,"retransmits":1,"throughput-bits":0,"throughput-bytes":0}},{"streams":[{"end":5.000022,"rtt":74346,"start":4.000031,"omitted":false,"stream-id":5,"retransmits":0,"tcp-window-size":1448,"throughput-bits":0,"throughput-bytes":0}],"summary":{"end":5.000022,"start":4.000031,"omitted":false,"retransmits":0,"throughput-bits":0,"throughput-bytes":0}},{"streams":[{"end":6.00011,"rtt":74346,"start":5.000022,"omitted":false,"stream-id":5,"retransmits":1,"tcp-window-size":1024,"throughput-bits":0,"throughput-bytes":0}],"summary":{"end":6.00011,"start":5.000022,"omitted":false,"retransmits":1,"throughput-bits":0,"throughput-bytes":0}},{"streams":[{"end":7.001016,"rtt":74346,"start":6.00011,"omitted":false,"stream-id":5,"retransmits":0,"tcp-window-size":1024,"throughput-bits":0,"throughput-bytes":0}],"summary":{"end":7.001016,"start":6.00011,"omitted":false,"retransmits":0,"throughput-bits":0,"throughput-bytes":0}},{"streams":[{"end":8.001013,"rtt":74346,"start":7.001016,"omitted":false,"stream-id":5,"retransmits":0,"tcp-window-size":1024,"throughput-bits":0,"throughput-bytes":0}],"summary":{"end":8.001013,"start":7.001016,"omitted":false,"retransmits":0,"throughput-bits":0,"throughput-bytes":0}},{"streams":[{"end":9.001014,"rtt":74346,"start":8.001013,"omitted":false,"stream-id":5,"retransmits":0,"tcp-window-size":1024,"throughput-bits":0,"throughput-bytes":0}],"summary":{"end":9.001014,"start":8.001013,"omitted":false,"retransmits":0,"throughput-bits":0,"throughput-bytes":0}},{"streams":[{"end":10.001013,"rtt":74346,"start":9.001014,"omitted":false,"stream-id":5,"retransmits":0,"tcp-window-size":1024,"throughput-bits":0,"throughput-bytes":0}],"summary":{"end":10.001013,"start":9.001014,"omitted":false,"retransmits":0,"throughput-bits":0,"throughput-bytes":0}},{"streams":[{"end":11.000277,"rtt":36824,"start":10.001013,"omitted":false,"stream-id":5,"retransmits":426,"tcp-window-size":100800,"throughput-bits":10493483.184249349,"throughput-bytes":1310720}],"summary":{"end":11.000277,"start":10.001013,"omitted":false,"retransmits":426,"throughput-bits":10493483.184249349,"throughput-bytes":1310720}},{"streams":[{"end":12.000302,"rtt":47084,"start":11.000277,"omitted":false,"stream-id":5,"retransmits":0,"tcp-window-size":132848,"throughput-bits":20970995.0131425,"throughput-bytes":2621440}],"summary":{"end":12.000302,"start":11.000277,"omitted":false,"retransmits":0,"throughput-bits":20970995.0131425,"throughput-bytes":2621440}},{"streams":[{"end":13.000238,"rtt":57815,"start":12.000302,"omitted":false,"stream-id":5,"retransmits":0,"tcp-window-size":158840,"throughput-bits":20972862.58594616,"throughput-bytes":2621440}],"summary":{"end":13.000238,"start":12.000302,"omitted":false,"retransmits":0,"throughput-bits":20972862.58594616,"throughput-bytes":2621440}},{"streams":[{"end":14.000357,"rtt":70653,"start":13.000238,"omitted":false,"stream-id":5,"retransmits":0,"tcp-window-size":193496,"throughput-bits":20969025.29679701,"throughput-bytes":2621440}],"summary":{"end":14.000357,"start":13.000238,"omitted":false,"retransmits":0,"throughput-bits":20969025.29679701,"throughput-bytes":2621440}},{"streams":[{"end":15.000381,"rtt":89065,"start":14.000357,"omitted":false,"stream-id":5,"retransmits":0,"tcp-window-size":246924,"throughput-bits":20971017.51204015,"throughput-bytes":2621440}],"summary":{"end":15.000381,"start":14.000357,"omitted":false,"retransmits":0,"throughput-bits":20971017.51204015,"throughput-bytes":2621440}},{"streams":[{"end":16.000405,"rtt":110281,"start":15.000381,"omitted":false,"stream-id":5,"retransmits":0,"tcp-window-size":306128,"throughput-bits":20971017.51204015,"throughput-bytes":2621440}],"summary":{"end":16.000405,"start":15.000381,"omitted":false,"retransmits":0,"throughput-bits":20971017.51204015,"throughput-bytes":2621440}},{"streams":[{"end":17.000358,"rtt":133126,"start":16.000405,"omitted":false,"stream-id":5,"retransmits":0,"tcp-window-size":371108,"throughput-bits":20972506.29638361,"throughput-bytes":2621440}],"summary":{"end":17.000358,"start":16.000405,"omitted":false,"retransmits":0,"throughput-bits":20972506.29638361,"throughput-bytes":2621440}},{"streams":[{"end":18.00034,"rtt":75792,"start":17.000358,"omitted":false,"stream-id":5,"retransmits":8,"tcp-window-size":207936,"throughput-bits":20971897.50679535,"throughput-bytes":2621440}],"summary":{"end":18.00034,"start":17.000358,"omitted":false,"retransmits":8,"throughput-bits":20971897.50679535,"throughput-bytes":2621440}},{"streams":[{"end":19.00006,"rtt":82525,"start":18.00034,"omitted":false,"stream-id":5,"retransmits":0,"tcp-window-size":225264,"throughput-bits":31466091.217340175,"throughput-bytes":3932160}],"summary":{"end":19.00006,"start":18.00034,"omitted":false,"retransmits":0,"throughput-bits":31466091.217340175,"throughput-bytes":3932160}},{"streams":[{"end":20.000062,"rtt":88229,"start":19.00006,"omitted":false,"stream-id":5,"retransmits":0,"tcp-window-size":242592,"throughput-bits":20971477.50008613,"throughput-bytes":2621440}],"summary":{"end":20.000062,"start":19.00006,"omitted":false,"retransmits":0,"throughput-bits":20971477.50008613,"throughput-bytes":2621440}},{"streams":[{"end":21.00009,"rtt":96966,"start":20.000062,"omitted":false,"stream-id":5,"retransmits":0,"tcp-window-size":265696,"throughput-bits":20970932.51645787,"throughput-bytes":2621440}],"summary":{"end":21.00009,"start":20.000062,"omitted":false,"retransmits":0,"throughput-bits":20970932.51645787,"throughput-bytes":2621440}},{"streams":[{"end":22.000111,"rtt":110830,"start":21.00009,"omitted":false,"stream-id":5,"retransmits":0,"tcp-window-size":307572,"throughput-bits":20971080.009231374,"throughput-bytes":2621440}],"summary":{"end":22.000111,"start":21.00009,"omitted":false,"retransmits":0,"throughput-bits":20971080.009231374,"throughput-bytes":2621440}},{"streams":[{"end":23.000138,"rtt":128996,"start":22.000111,"omitted":false,"stream-id":5,"retransmits":0,"tcp-window-size":358112,"throughput-bits":20970955.015221424,"throughput-bytes":2621440}],"summary":{"end":23.000138,"start":22.000111,"omitted":false,"retransmits":0,"throughput-bits":20970955.015221424,"throughput-bytes":2621440}},{"streams":[{"end":24.000075,"rtt":131868,"start":23.000138,"omitted":false,"stream-id":5,"retransmits":6,"tcp-window-size":202160,"throughput-bits":20972841.333246782,"throughput-bytes":2621440}],"summary":{"end":24.000075,"start":23.000138,"omitted":false,"retransmits":6,"throughput-bits":20972841.333246782,"throughput-bytes":2621440}},{"streams":[{"end":25.00023,"rtt":80383,"start":24.000075,"omitted":false,"stream-id":5,"retransmits":0,"tcp-window-size":219488,"throughput-bits":20968270.503581207,"throughput-bytes":2621440}],"summary":{"end":25.00023,"start":24.000075,"omitted":false,"retransmits":0,"throughput-bits":20968270.503581207,"throughput-bytes":2621440}},{"streams":[{"end":26.00026,"rtt":86215,"start":25.00023,"omitted":false,"stream-id":5,"retransmits":0,"tcp-window-size":236816,"throughput-bits":20970890.0189251,"throughput-bytes":2621440}],"summary":{"end":26.00026,"start":25.00023,"omitted":false,"retransmits":0,"throughput-bits":20970890.0189251,"throughput-bytes":2621440}},{"streams":[{"end":27.000284,"rtt":93681,"start":26.00026,"omitted":false,"stream-id":5,"retransmits":0,"tcp-window-size":257032,"throughput-bits":20971017.51204015,"throughput-bytes":2621440}],"summary":{"end":27.000284,"start":26.00026,"omitted":false,"retransmits":0,"throughput-bits":20971017.51204015,"throughput-bytes":2621440}},{"streams":[{"end":28.000271,"rtt":95899,"start":27.000284,"omitted":false,"stream-id":5,"retransmits":1,"tcp-window-size":1444,"throughput-bits":0,"throughput-bytes":0}],"summary":{"end":28.000271,"start":27.000284,"omitted":false,"retransmits":1,"throughput-bits":0,"throughput-bytes":0}},{"streams":[{"end":29.001015,"rtt":95899,"start":28.000271,"omitted":false,"stream-id":5,"retransmits":1,"tcp-window-size":1444,"throughput-bits":0,"throughput-bytes":0}],"summary":{"end":29.001015,"start":28.000271,"omitted":false,"retransmits":1,"throughput-bits":0,"throughput-bytes":0}},{"streams":[{"end":30.001014,"rtt":95899,"start":29.001015,"omitted":false,"stream-id":5,"retransmits":1,"tcp-window-size":1444,"throughput-bits":0,"throughput-bytes":0}],"summary":{"end":30.001014,"start":29.001015,"omitted":false,"retransmits":1,"throughput-bits":0,"throughput-bytes":0}},{"streams":[{"end":31.001014,"rtt":95899,"start":30.001014,"omitted":false,"stream-id":5,"retransmits":0,"tcp-window-size":1444,"throughput-bits":0,"throughput-bytes":0}],"summary":{"end":31.001014,"start":30.001014,"omitted":false,"retransmits":0,"throughput-bits":0,"throughput-bytes":0}},{"streams":[{"end":32.001014,"rtt":95899,"start":31.001014,"omitted":false,"stream-id":5,"retransmits":1,"tcp-window-size":722,"throughput-bits":0,"throughput-bytes":0}],"summary":{"end":32.001014,"start":31.001014,"omitted":false,"retransmits":1,"throughput-bits":0,"throughput-bytes":0}},{"streams":[{"end":33.001015,"rtt":95899,"start":32.001014,"omitted":false,"stream-id":5,"retransmits":0,"tcp-window-size":722,"throughput-bits":0,"throughput-bytes":0}],"summary":{"end":33.001015,"start":32.001014,"omitted":false,"retransmits":0,"throughput-bits":0,"throughput-bytes":0}},{"streams":[{"end":34.001015,"rtt":95899,"start":33.001015,"omitted":false,"stream-id":5,"retransmits":0,"tcp-window-size":722,"throughput-bits":0,"throughput-bytes":0}],"summary":{"end":34.001015,"start":33.001015,"omitted":false,"retransmits":0,"throughput-bits":0,"throughput-bytes":0}},{"streams":[{"end":35.00102,"rtt":95899,"start":34.001015,"omitted":false,"stream-id":5,"retransmits":0,"tcp-window-size":722,"throughput-bits":0,"throughput-bytes":0}],"summary":{"end":35.00102,"start":34.001015,"omitted":false,"retransmits":0,"throughput-bits":0,"throughput-bytes":0}},{"streams":[{"end":36.000233,"rtt":95899,"start":35.00102,"omitted":false,"stream-id":5,"retransmits":0,"tcp-window-size":722,"throughput-bits":0,"throughput-bytes":0}],"summary":{"end":36.000233,"start":35.00102,"omitted":false,"retransmits":0,"throughput-bits":0,"throughput-bytes":0}},{"streams":[{"end":37.001016,"rtt":95899,"start":36.000233,"omitted":false,"stream-id":5,"retransmits":1,"tcp-window-size":361,"throughput-bits":0,"throughput-bytes":0}],"summary":{"end":37.001016,"start":36.000233,"omitted":false,"retransmits":1,"throughput-bits":0,"throughput-bytes":0}},{"streams":[{"end":38.001015,"rtt":95899,"start":37.001016,"omitted":false,"stream-id":5,"retransmits":0,"tcp-window-size":361,"throughput-bits":0,"throughput-bytes":0}],"summary":{"end":38.001015,"start":37.001016,"omitted":false,"retransmits":0,"throughput-bits":0,"throughput-bytes":0}},{"streams":[{"end":39.001014,"rtt":95899,"start":38.001015,"omitted":false,"stream-id":5,"retransmits":0,"tcp-window-size":361,"throughput-bits":0,"throughput-bytes":0}],"summary":{"end":39.001014,"start":38.001015,"omitted":false,"retransmits":0,"throughput-bits":0,"throughput-bytes":0}},{"streams":[{"end":40.000574,"rtt":95899,"start":39.001014,"omitted":false,"stream-id":5,"retransmits":0,"tcp-window-size":361,"throughput-bits":0,"throughput-bytes":0}],"summary":{"end":40.000574,"start":39.001014,"omitted":false,"retransmits":0,"throughput-bits":0,"throughput-bytes":0}},{"streams":[{"end":41.001016,"rtt":95899,"start":40.000574,"omitted":false,"stream-id":5,"retransmits":0,"tcp-window-size":361,"throughput-bits":0,"throughput-bytes":0}],"summary":{"end":41.001016,"start":40.000574,"omitted":false,"retransmits":0,"throughput-bits":0,"throughput-bytes":0}},{"streams":[{"end":42.001013,"rtt":95899,"start":41.001016,"omitted":false,"stream-id":5,"retransmits":0,"tcp-window-size":361,"throughput-bits":0,"throughput-bytes":0}],"summary":{"end":42.001013,"start":41.001016,"omitted":false,"retransmits":0,"throughput-bits":0,"throughput-bytes":0}},{"streams":[{"end":43.001014,"rtt":95899,"start":42.001013,"omitted":false,"stream-id":5,"retransmits":0,"tcp-window-size":361,"throughput-bits":0,"throughput-bytes":0}],"summary":{"end":43.001014,"start":42.001013,"omitted":false,"retransmits":0,"throughput-bits":0,"throughput-bytes":0}},{"streams":[{"end":44.00104,"rtt":95899,"start":43.001014,"omitted":false,"stream-id":5,"retransmits":0,"tcp-window-size":361,"throughput-bits":0,"throughput-bytes":0}],"summary":{"end":44.00104,"start":43.001014,"omitted":false,"retransmits":0,"throughput-bits":0,"throughput-bytes":0}},{"streams":[{"end":45.001022,"rtt":95899,"start":44.00104,"omitted":false,"stream-id":5,"retransmits":0,"tcp-window-size":361,"throughput-bits":0,"throughput-bytes":0}],"summary":{"end":45.001022,"start":44.00104,"omitted":false,"retransmits":0,"throughput-bits":0,"throughput-bytes":0}},{"streams":[{"end":46.001026,"rtt":95899,"start":45.001022,"omitted":false,"stream-id":5,"retransmits":0,"tcp-window-size":361,"throughput-bits":0,"throughput-bytes":0}],"summary":{"end":46.001026,"start":45.001022,"omitted":false,"retransmits":0,"throughput-bits":0,"throughput-bytes":0}},{"streams":[{"end":47.000426,"rtt":24052,"start":46.001026,"omitted":false,"stream-id":5,"retransmits":1381,"tcp-window-size":16200,"throughput-bits":10492055.026892465,"throughput-bytes":1310720}],"summary":{"end":47.000426,"start":46.001026,"omitted":false,"retransmits":1381,"throughput-bits":10492055.026892465,"throughput-bytes":1310720}},{"streams":[{"end":48.000163,"rtt":37043,"start":47.000426,"omitted":false,"stream-id":5,"retransmits":0,"tcp-window-size":109565,"throughput-bits":0,"throughput-bytes":0}],"summary":{"end":48.000163,"start":47.000426,"omitted":false,"retransmits":0,"throughput-bits":0,"throughput-bytes":0}},{"streams":[{"end":49.000486,"rtt":37043,"start":48.000163,"omitted":false,"stream-id":5,"retransmits":0,"tcp-window-size":109565,"throughput-bits":0,"throughput-bytes":0}],"summary":{"end":49.000486,"start":48.000163,"omitted":false,"retransmits":0,"throughput-bits":0,"throughput-bytes":0}},{"streams":[{"end":50.000892,"rtt":37043,"start":49.000486,"omitted":false,"stream-id":5,"retransmits":0,"tcp-window-size":109565,"throughput-bits":0,"throughput-bytes":0}],"summary":{"end":50.000892,"start":49.000486,"omitted":false,"retransmits":0,"throughput-bits":0,"throughput-bytes":0}},{"streams":[{"end":51.001021,"rtt":37043,"start":50.000892,"omitted":false,"stream-id":5,"retransmits":0,"tcp-window-size":109565,"throughput-bits":0,"throughput-bytes":0}],"summary":{"end":51.001021,"start":50.000892,"omitted":false,"retransmits":0,"throughput-bits":0,"throughput-bytes":0}},{"streams":[{"end":52.001021,"rtt":37043,"start":51.001021,"omitted":false,"stream-id":5,"retransmits":0,"tcp-window-size":109565,"throughput-bits":0,"throughput-bytes":0}],"summary":{"end":52.001021,"start":51.001021,"omitted":false,"retransmits":0,"throughput-bits":0,"throughput-bytes":0}},{"streams":[{"end":53.001018,"rtt":37043,"start":52.001021,"omitted":false,"stream-id":5,"retransmits":0,"tcp-window-size":109565,"throughput-bits":0,"throughput-bytes":0}],"summary":{"end":53.001018,"start":52.001021,"omitted":false,"retransmits":0,"throughput-bits":0,"throughput-bytes":0}},{"streams":[{"end":54.001022,"rtt":23464,"start":53.001018,"omitted":false,"stream-id":5,"retransmits":85,"tcp-window-size":57456,"throughput-bits":0,"throughput-bytes":0}],"summary":{"end":54.001022,"start":53.001018,"omitted":false,"retransmits":85,"throughput-bits":0,"throughput-bytes":0}},{"streams":[{"end":55.00026,"rtt":36410,"start":54.001022,"omitted":false,"stream-id":5,"retransmits":0,"tcp-window-size":102453,"throughput-bits":20987512.185818166,"throughput-bytes":2621440}],"summary":{"end":55.00026,"start":54.001022,"omitted":false,"retransmits":0,"throughput-bits":20987512.185818166,"throughput-bytes":2621440}},{"streams":[{"end":56.000284,"rtt":48796,"start":55.00026,"omitted":false,"stream-id":5,"retransmits":0,"tcp-window-size":134199,"throughput-bits":20971017.51204015,"throughput-bytes":2621440}],"summary":{"end":56.000284,"start":55.00026,"omitted":false,"retransmits":0,"throughput-bits":20971017.51204015,"throughput-bytes":2621440}},{"streams":[{"end":57.000312,"rtt":61724,"start":56.000284,"omitted":false,"stream-id":5,"retransmits":0,"tcp-window-size":170274,"throughput-bits":20970932.51645787,"throughput-bytes":2621440}],"summary":{"end":57.000312,"start":56.000284,"omitted":false,"retransmits":0,"throughput-bits":20970932.51645787,"throughput-bytes":2621440}},{"streams":[{"end":58.000337,"rtt":80655,"start":57.000312,"omitted":false,"stream-id":5,"retransmits":0,"tcp-window-size":222222,"throughput-bits":20970995.0131425,"throughput-bytes":2621440}],"summary":{"end":58.000337,"start":57.000312,"omitted":false,"retransmits":0,"throughput-bits":20970995.0131425,"throughput-bytes":2621440}},{"streams":[{"end":59.000359,"rtt":101844,"start":58.000337,"omitted":false,"stream-id":5,"retransmits":0,"tcp-window-size":284271,"throughput-bits":20971057.51019962,"throughput-bytes":2621440}],"summary":{"end":59.000359,"start":58.000337,"omitted":false,"retransmits":0,"throughput-bits":20971057.51019962,"throughput-bytes":2621440}},{"streams":[{"end":60.000387,"rtt":125886,"start":59.000359,"omitted":false,"stream-id":5,"retransmits":0,"tcp-window-size":347763,"throughput-bits":20970932.51645787,"throughput-bytes":2621440}],"summary":{"end":60.000387,"start":59.000359,"omitted":false,"retransmits":0,"throughput-bits":20970932.51645787,"throughput-bytes":2621440}}],"succeeded":true}
