{"diags":"Participant 0:\n/usr/bin/iperf3 -p 5201 -B 10.0.0.1 -c 10.0.0.2 -t 60 --json --rsa-public-key-path /var/run/pscheduler-server/runner/tmp/tmpk313700_/tmp633bi505/public-key --username NARnuxJyM22j3psFbbL9\n\n{\n    \"end\": {\n        \"cpu_utilization_percent\": {\n            \"host_system\": 2.047728900458616, \n            \"host_total\": 2.0880215000511573, \n            \"host_user\": 0.040295932313765034, \n            \"remote_system\": 5.00471091713538, \n            \"remote_total\": 5.411155581606642, \n            \"remote_user\": 0.4064429999832719\n        }, \n        \"receiver_tcp_congestion\": \"htcp\", \n        \"sender_tcp_congestion\": \"htcp\", \n        \"streams\": [\n            {\n                \"receiver\": {\n                    \"bits_per_second\": 851127244.650076, \n                    \"bytes\": 6391807936, \n                    \"end\": 60.078518, \n                    \"seconds\": 60.000175, \n                    \"sender\": true, \n                    \"socket\": 5, \n                    \"start\": 0\n                }, \n                \"sender\": {\n                    \"bits_per_second\": 852682039.9440502, \n                    \"bytes\": 6395133952, \n                    \"end\": 60.000175, \n                    \"max_rtt\": 78394, \n                    \"max_snd_cwnd\": 16698336, \n                    \"max_snd_wnd\": 0, \n                    \"mean_rtt\": 78384, \n                    \"min_rtt\": 78374, \n                    \"retransmits\": 0, \n                    \"seconds\": 60.000175, \n                    \"sender\": true, \n                    \"socket\": 5, \n                    \"start\": 0\n                }\n            }\n        ], \n        \"sum_received\": {\n            \"bits_per_second\": 851127244.650076, \n            \"bytes\": 6391807936, \n            \"end\": 60.078518, \n            \"seconds\": 60.078518, \n            \"sender\": true, \n            \"start\": 0\n        }, \n        \"sum_sent\": {\n            \"bits_per_second\": 852682039.9440502, \n            \"bytes\": 6395133952, \n            \"end\": 60.000175, \n            \"retransmits\": 0, \n            \"seconds\": 60.000175, \n            \"sender\": true, \n            \"start\": 0\n        }\n    }, \n    \"intervals\": [\n        {\n            \"streams\": [\n                {\n                    \"bits_per_second\": 944689496.35457, \n                    \"bytes\": 118095872, \n                    \"end\": 1.000082, \n                    \"omitted\": false, \n                    \"pmtu\": 1500, \n                    \"retransmits\": 0, \n                    \"rtt\": 78389, \n                    \"rttvar\": 7, \n                    \"seconds\": 1.000082015991211, \n                    \"sender\": true, \n                    \"snd_cwnd\": 16698336, \n                    \"snd_wnd\": -1, \n                    \"socket\": 5, \n                    \"start\": 0\n                }\n            ], \n            \"sum\": {\n                \"bits_per_second\": 944689496.35457, \n                \"bytes\": 118095872, \n                \"end\": 1.000082, \n                \"omitted\": false, \n                \"retransmits\": 0, \n                \"seconds\": 1.000082015991211, \n                \"sender\": true, \n                \"start\": 0\n            }\n        }, \n        {\n            \"streams\": [\n                {\n                    \"bits_per_second\": 849288851.4212573, \n                    \"bytes\": 106168320, \n                    \"end\": 2.00015, \n                    \"omitted\": false, \n                    \"pmtu\": 1500, \n                    \"retransmits\": 0, \n                    \"rtt\": 78383, \n                    \"rttvar\": 7, \n                    \"seconds\": 1.000067949295044, \n                    \"sender\": true, \n                    \"snd_cwnd\": 16698336, \n                    \"snd_wnd\": -1, \n                    \"socket\": 5, \n                    \"start\": 1.000082\n                }\n            ], \n            \"sum\": {\n                \"bits_per_second\": 849288851.4212573, \n                \"bytes\": 106168320, \n                \"end\": 2.00015, \n                \"omitted\": false, \n                \"retransmits\": 0, \n                \"seconds\": 1.000067949295044, \n                \"sender\": true, \n                \"start\": 1.000082\n            }\n        }, \n        {\n            \"streams\": [\n                {\n                    \"bits_per_second\": 849348281.2534882, \n                    \"bytes\": 106168320, \n                    \"end\": 3.000148, \n                    \"omitted\": false, \n                    \"pmtu\": 1500, \n                    \"retransmits\": 0, \n                    \"rtt\": 78385, \n                    \"rttvar\": 8, \n                    \"seconds\": 0.9999979734420776, \n                    \"sender\": true, \n                    \"snd_cwnd\": 16698336, \n                    \"snd_wnd\": -1, \n                    \"socket\": 5, \n                    \"start\": 2.00015\n                }\n            ], \n            \"sum\": {\n                \"bits_per_second\": 849348281.2534882, \n                \"bytes\": 106168320, \n                \"end\": 3.000148, \n                \"omitted\": false, \n                \"retransmits\": 0, \n                \"seconds\": 0.9999979734420776, \n                \"sender\": true, \n                \"start\": 2.00015\n            }\n        }, \n        {\n            \"streams\": [\n                {\n                    \"bits_per_second\": 849344028.7575437, \n                    \"bytes\": 106168320, \n                    \"end\": 4.000151, \n                    \"omitted\": false, \n                    \"pmtu\": 1500, \n                    \"retransmits\": 0, \n                    \"rtt\": 78378, \n                    \"rttvar\": 5, \n                    \"seconds\": 1.0000029802322388, \n                    \"sender\": true, \n                    \"snd_cwnd\": 16698336, \n                    \"snd_wnd\": -1, \n                    \"socket\": 5, \n                    \"start\": 3.000148\n                }\n            ], \n            \"sum\": {\n                \"bits_per_second\": 849344028.7575437, \n                \"bytes\": 106168320, \n                \"end\": 4.000151, \n                \"omitted\": false, \n                \"retransmits\": 0, \n                \"seconds\": 1.0000029802322388, \n                \"sender\": true, \n                \"start\": 3.000148\n            }\n        }, \n        {\n            \"streams\": [\n                {\n                    \"bits_per_second\": 849405997.9092184, \n                    \"bytes\": 106168320, \n                    \"end\": 5.000081, \n                    \"omitted\": false, \n                    \"pmtu\": 1500, \n                    \"retransmits\": 0, \n                    \"rtt\": 78383, \n                    \"rttvar\": 7, \n                    \"seconds\": 0.9999300241470337, \n                    \"sender\": true, \n                    \"snd_cwnd\": 16698336, \n                    \"snd_wnd\": -1, \n                    \"socket\": 5, \n                    \"start\": 4.000151\n                }\n            ], \n            \"sum\": {\n                \"bits_per_second\": 849405997.9092184, \n                \"bytes\": 106168320, \n                \"end\": 5.000081, \n                \"omitted\": false, \n                \"retransmits\": 0, \n                \"seconds\": 0.9999300241470337, \n                \"sender\": true, \n                \"start\": 4.000151\n            }\n        }, \n        {\n            \"streams\": [\n                {\n                    \"bits_per_second\": 849349091.2575437, \n                    \"bytes\": 106168320, \n                    \"end\": 6.000078, \n                    \"omitted\": false, \n                    \"pmtu\": 1500, \n                    \"retransmits\": 0, \n                    \"rtt\": 78389, \n                    \"rttvar\": 9, \n                    \"seconds\": 0.9999970197677612, \n                    \"sender\": true, \n                    \"snd_cwnd\": 16698336, \n                    \"snd_wnd\": -1, \n                    \"socket\": 5, \n                    \"start\": 5.000081\n                }\n            ], \n            \"sum\": {\n                \"bits_per_second\": 849349091.2575437, \n                \"bytes\": 106168320, \n                \"end\": 6.000078, \n                \"omitted\": false, \n                \"retransmits\": 0, \n                \"seconds\": 0.9999970197677612, \n                \"sender\": true, \n                \"start\": 5.000081\n            }\n        }, \n        {\n            \"streams\": [\n                {\n                    \"bits_per_second\": 859829757.5076368, \n                    \"bytes\": 107479040, \n                    \"end\": 7.000081, \n                    \"omitted\": false, \n                    \"pmtu\": 1500, \n                    \"retransmits\": 0, \n                    \"rtt\": 78387, \n                    \"rttvar\": 6, \n                    \"seconds\": 1.0000029802322388, \n                    \"sender\": true, \n                    \"snd_cwnd\": 16698336, \n                    \"snd_wnd\": -1, \n                    \"socket\": 5, \n                    \"start\": 6.000078\n                }\n            ], \n            \"sum\": {\n                \"bits_per_second\": 859829757.5076368, \n                \"bytes\": 107479040, \n                \"end\": 7.000081, \n                \"omitted\": false, \n                \"retransmits\": 0, \n                \"seconds\": 1.0000029802322388, \n                \"sender\": true, \n                \"start\": 6.000078\n            }\n        }, \n        {\n            \"streams\": [\n                {\n                    \"bits_per_second\": 849362709.682068, \n                    \"bytes\": 106168320, \n                    \"end\": 8.000062, \n                    \"omitted\": false, \n                    \"pmtu\": 1500, \n                    \"retransmits\": 0, \n                    \"rtt\": 78391, \n                    \"rttvar\": 16, \n                    \"seconds\": 0.9999809861183167, \n                    \"sender\": true, \n                    \"snd_cwnd\": 16698336, \n                    \"snd_wnd\": -1, \n                    \"socket\": 5, \n                    \"start\": 7.000081\n                }\n            ], \n            \"sum\": {\n                \"bits_per_second\": 849362709.682068, \n                \"bytes\": 106168320, \n                \"end\": 8.000062, \n                \"omitted\": false, \n                \"retransmits\": 0, \n                \"seconds\": 0.9999809861183167, \n                \"sender\": true, \n                \"start\": 7.000081\n            }\n        }, \n        {\n            \"streams\": [\n                {\n                    \"bits_per_second\": 849267592.342669, \n                    \"bytes\": 106168320, \n                    \"end\": 9.000155, \n                    \"omitted\": false, \n                    \"pmtu\": 1500, \n                    \"retransmits\": 0, \n                    \"rtt\": 78386, \n                    \"rttvar\": 5, \n                    \"seconds\": 1.0000929832458496, \n                    \"sender\": true, \n                    \"snd_cwnd\": 16698336, \n                    \"snd_wnd\": -1, \n                    \"socket\": 5, \n                    \"start\": 8.000062\n                }\n            ], \n            \"sum\": {\n                \"bits_per_second\": 849267592.342669, \n                \"bytes\": 106168320, \n                \"end\": 9.000155, \n                \"omitted\": false, \n                \"retransmits\": 0, \n                \"seconds\": 1.0000929832458496, \n                \"sender\": true, \n                \"start\": 8.000062\n            }\n        }, \n        {\n            \"streams\": [\n                {\n                    \"bits_per_second\": 849345750.0007725, \n                    \"bytes\": 106168320, \n                    \"end\": 10.000156, \n                    \"omitted\": false, \n                    \"pmtu\": 1500, \n                    \"retransmits\": 0, \n                    \"rtt\": 78386, \n                    \"rttvar\": 9, \n                    \"seconds\": 1.0000009536743164, \n                    \"sender\": true, \n                    \"snd_cwnd\": 16698336, \n                    \"snd_wnd\": -1, \n                    \"socket\": 5, \n                    \"start\": 9.000155\n                }\n            ], \n            \"sum\": {\n                \"bits_per_second\": 849345750.0007725, \n                \"bytes\": 106168320, \n                \"end\": 10.000156, \n                \"omitted\": false, \n                \"retransmits\": 0, \n                \"seconds\": 1.0000009536743164, \n                \"sender\": true, \n                \"start\": 9.000155\n            }\n        }, \n        {\n            \"streams\": [\n                {\n                    \"bits_per_second\": 849408580.1534443, \n                    \"bytes\": 106168320, \n                    \"end\": 11.000083, \n                    \"omitted\": false, \n                    \"pmtu\": 1500, \n                    \"retransmits\": 0, \n                    \"rtt\": 78374, \n                    \"rttvar\": 17, \n                    \"seconds\": 0.99992698431015, \n                    \"sender\": true, \n                    \"snd_cwnd\": 16698336, \n                    \"snd_wnd\": -1, \n                    \"socket\": 5, \n                    \"start\": 10.000156\n                }\n            ], \n            \"sum\": {\n                \"bits_per_second\": 849408580.1534443, \n                \"bytes\": 106168320, \n                \"end\": 11.000083, \n                \"omitted\": false, \n                \"retransmits\": 0, \n                \"seconds\": 0.99992698431015, \n                \"sender\": true, \n                \"start\": 10.000156\n            }\n        }, \n        {\n            \"streams\": [\n                {\n                    \"bits_per_second\": 859665584.8388704, \n                    \"bytes\": 107479040, \n                    \"end\": 12.000277, \n                    \"omitted\": false, \n                    \"pmtu\": 1500, \n                    \"retransmits\": 0, \n                    \"rtt\": 78380, \n                    \"rttvar\": 4, \n                    \"seconds\": 1.0001939535140991, \n                    \"sender\": true, \n                    \"snd_cwnd\": 16698336, \n                    \"snd_wnd\": -1, \n                    \"socket\": 5, \n                    \"start\": 11.000083\n                }\n            ], \n            \"sum\": {\n                \"bits_per_second\": 859665584.8388704, \n                \"bytes\": 107479040, \n                \"end\": 12.000277, \n                \"omitted\": false, \n                \"retransmits\": 0, \n                \"seconds\": 1.0001939535140991, \n                \"sender\": true, \n                \"start\": 11.000083\n            }\n        }, \n        {\n            \"streams\": [\n                {\n                    \"bits_per_second\": 849514769.5566075, \n                    \"bytes\": 106168320, \n                    \"end\": 13.000079, \n                    \"omitted\": false, \n                    \"pmtu\": 1500, \n                    \"retransmits\": 0, \n                    \"rtt\": 78381, \n                    \"rttvar\": 10, \n                    \"seconds\": 0.999801993370056, \n                    \"sender\": true, \n                    \"snd_cwnd\": 16698336, \n                    \"snd_wnd\": -1, \n                    \"socket\": 5, \n                    \"start\": 12.000277\n                }\n            ], \n            \"sum\": {\n                \"bits_per_second\": 849514769.5566075, \n                \"bytes\": 106168320, \n                \"end\": 13.000079, \n                \"omitted\": false, \n                \"retransmits\": 0, \n                \"seconds\": 0.999801993370056, \n                \"sender\": true, \n                \"start\": 12.000277\n            }\n        }, \n        {\n            \"streams\": [\n                {\n                    \"bits_per_second\": 849281157.5365914, \n                    \"bytes\": 106168320, \n                    \"end\": 14.000156, \n                    \"omitted\": false, \n                    \"pmtu\": 1500, \n                    \"retransmits\": 0, \n                    \"rtt\": 78383, \n                    \"rttvar\": 4, \n                    \"seconds\": 1.00007700920105, \n                    \"sender\": true, \n                    \"snd_cwnd\": 16698336, \n                    \"snd_wnd\": -1, \n                    \"socket\": 5, \n                    \"start\": 13.000079\n                }\n            ], \n            \"sum\": {\n                \"bits_per_second\": 849281157.5365914, \n                \"bytes\": 106168320, \n                \"end\": 14.000156, \n                \"omitted\": false, \n                \"retransmits\": 0, \n                \"seconds\": 1.00007700920105, \n                \"sender\": true, \n                \"start\": 13.000079\n            }\n        }, \n        {\n            \"streams\": [\n                {\n                    \"bits_per_second\": 849403466.3124738, \n                    \"bytes\": 106168320, \n                    \"end\": 15.000089, \n                    \"omitted\": false, \n                    \"pmtu\": 1500, \n                    \"retransmits\": 0, \n                    \"rtt\": 78390, \n                    \"rttvar\": 8, \n                    \"seconds\": 0.9999330043792725, \n                    \"sender\": true, \n                    \"snd_cwnd\": 16698336, \n                    \"snd_wnd\": -1, \n                    \"socket\": 5, \n                    \"start\": 14.000156\n                }\n            ], \n            \"sum\": {\n                \"bits_per_second\": 849403466.3124738, \n                \"bytes\": 106168320, \n                \"end\": 15.000089, \n                \"omitted\": false, \n                \"retransmits\": 0, \n                \"seconds\": 0.9999330043792725, \n                \"sender\": true, \n                \"start\": 14.000156\n            }\n        }, \n        {\n            \"streams\": [\n                {\n                    \"bits_per_second\": 849351673.1557815, \n                    \"bytes\": 106168320, \n                    \"end\": 16.000083, \n                    \"omitted\": false, \n                    \"pmtu\": 1500, \n                    \"retransmits\": 0, \n                    \"rtt\": 78382, \n                    \"rttvar\": 12, \n                    \"seconds\": 0.9999939799308777, \n                    \"sender\": true, \n                    \"snd_cwnd\": 16698336, \n                    \"snd_wnd\": -1, \n                    \"socket\": 5, \n                    \"start\": 15.000089\n                }\n            ], \n            \"sum\": {\n                \"bits_per_second\": 849351673.1557815, \n                \"bytes\": 106168320, \n                \"end\": 16.000083, \n                \"omitted\": false, \n                \"retransmits\": 0, \n                \"seconds\": 0.9999939799308777, \n                \"sender\": true, \n                \"start\": 15.000089\n            }\n        }, \n        {\n            \"streams\": [\n                {\n                    \"bits_per_second\": 849363570.3406688, \n                    \"bytes\": 106168320, \n                    \"end\": 17.000063, \n                    \"omitted\": false, \n                    \"pmtu\": 1500, \n                    \"retransmits\": 0, \n                    \"rtt\": 78386, \n                    \"rttvar\": 9, \n                    \"seconds\": 0.9999799728393555, \n                    \"sender\": true, \n                    \"snd_cwnd\": 16698336, \n                    \"snd_wnd\": -1, \n                    \"socket\": 5, \n                    \"start\": 16.000083\n                }\n            ], \n            \"sum\": {\n                \"bits_per_second\": 849363570.3406688, \n                \"bytes\": 106168320, \n                \"end\": 17.000063, \n                \"omitted\": false, \n                \"retransmits\": 0, \n                \"seconds\": 0.9999799728393555, \n                \"sender\": true, \n                \"start\": 16.000083\n            }\n        }, \n        {\n            \"streams\": [\n                {\n                    \"bits_per_second\": 859830577.5035312, \n                    \"bytes\": 107479040, \n                    \"end\": 18.000065, \n                    \"omitted\": false, \n                    \"pmtu\": 1500, \n                    \"retransmits\": 0, \n                    \"rtt\": 78385, \n                    \"rttvar\": 7, \n                    \"seconds\": 1.0000020265579224, \n                    \"sender\": true, \n                    \"snd_cwnd\": 16698336, \n                    \"snd_wnd\": -1, \n                    \"socket\": 5, \n                    \"start\": 17.000063\n                }\n            ], \n            \"sum\": {\n                \"bits_per_second\": 859830577.5035312, \n                \"bytes\": 107479040, \n                \"end\": 18.000065, \n                \"omitted\": false, \n                \"retransmits\": 0, \n                \"seconds\": 1.0000020265579224, \n                \"sender\": true, \n                \"start\": 17.000063\n            }\n        }, \n        {\n            \"streams\": [\n                {\n                    \"bits_per_second\": 849269313.276106, \n                    \"bytes\": 106168320, \n                    \"end\": 19.000156, \n                    \"omitted\": false, \n                    \"pmtu\": 1500, \n                    \"retransmits\": 0, \n                    \"rtt\": 78379, \n                    \"rttvar\": 4, \n                    \"seconds\": 1.0000909566879272, \n                    \"sender\": true, \n                    \"snd_cwnd\": 16698336, \n                    \"snd_wnd\": -1, \n                    \"socket\": 5, \n                    \"start\": 18.000065\n                }\n            ], \n            \"sum\": {\n                \"bits_per_second\": 849269313.276106, \n                \"bytes\": 106168320, \n                \"end\": 19.000156, \n                \"omitted\": false, \n                \"retransmits\": 0, \n                \"seconds\": 1.0000909566879272, \n                \"sender\": true, \n                \"start\": 18.000065\n            }\n        }, \n        {\n            \"streams\": [\n                {\n                    \"bits_per_second\": 849425542.3440347, \n                    \"bytes\": 106168320, \n                    \"end\": 20.000063, \n                    \"omitted\": false, \n                    \"pmtu\": 1500, \n                    \"retransmits\": 0, \n                    \"rtt\": 78386, \n                    \"rttvar\": 10, \n                    \"seconds\": 0.9999070167541504, \n                    \"sender\": true, \n                    \"snd_cwnd\": 16698336, \n                    \"snd_wnd\": -1, \n                    \"socket\": 5, \n                    \"start\": 19.000156\n                }\n            ], \n            \"sum\": {\n                \"bits_per_second\": 849425542.3440347, \n                \"bytes\": 106168320, \n                \"end\": 20.000063, \n                \"omitted\": false, \n                \"retransmits\": 0, \n                \"seconds\": 0.9999070167541504, \n                \"sender\": true, \n                \"start\": 19.000156\n            }\n        }, \n        {\n            \"streams\": [\n                {\n                    \"bits_per_second\": 849345750.0007725, \n                    \"bytes\": 106168320, \n                    \"end\": 21.000064, \n                    \"omitted\": false, \n                    \"pmtu\": 1500, \n                    \"retransmits\": 0, \n                    \"rtt\": 78383, \n                    \"rttvar\": 8, \n                    \"seconds\": 1.0000009536743164, \n                    \"sender\": true, \n                    \"snd_cwnd\": 16698336, \n                    \"snd_wnd\": -1, \n                    \"socket\": 5, \n                    \"start\": 20.000063\n                }\n            ], \n            \"sum\": {\n                \"bits_per_second\": 849345750.0007725, \n                \"bytes\": 106168320, \n                \"end\": 21.000064, \n                \"omitted\": false, \n                \"retransmits\": 0, \n                \"seconds\": 1.0000009536743164, \n                \"sender\": true, \n                \"start\": 20.000063\n            }\n        }, \n        {\n            \"streams\": [\n                {\n                    \"bits_per_second\": 849331271.5252018, \n                    \"bytes\": 106168320, \n                    \"end\": 22.000082, \n                    \"omitted\": false, \n                    \"pmtu\": 1500, \n                    \"retransmits\": 0, \n                    \"rtt\": 78386, \n                    \"rttvar\": 11, \n                    \"seconds\": 1.0000180006027222, \n                    \"sender\": true, \n                    \"snd_cwnd\": 16698336, \n                    \"snd_wnd\": -1, \n                    \"socket\": 5, \n                    \"start\": 21.000064\n                }\n            ], \n            \"sum\": {\n                \"bits_per_second\": 849331271.5252018, \n                \"bytes\": 106168320, \n                \"end\": 22.000082, \n                \"omitted\": false, \n                \"retransmits\": 0, \n                \"seconds\": 1.0000180006027222, \n                \"sender\": true, \n                \"start\": 21.000064\n            }\n        }, \n        {\n            \"streams\": [\n                {\n                    \"bits_per_second\": 849362709.682068, \n                    \"bytes\": 106168320, \n                    \"end\": 23.000063, \n                    \"omitted\": false, \n                    \"pmtu\": 1500, \n                    \"retransmits\": 0, \n                    \"rtt\": 78385, \n                    \"rttvar\": 6, \n                    \"seconds\": 0.9999809861183167, \n                    \"sender\": true, \n                    \"snd_cwnd\": 16698336, \n                    \"snd_wnd\": -1, \n                    \"socket\": 5, \n                    \"start\": 22.000082\n                }\n            ], \n            \"sum\": {\n                \"bits_per_second\": 849362709.682068, \n                \"bytes\": 106168320, \n                \"end\": 23.000063, \n                \"omitted\": false, \n                \"retransmits\": 0, \n                \"seconds\": 0.9999809861183167, \n                \"sender\": true, \n                \"start\": 22.000082\n            }\n        }, \n        {\n            \"streams\": [\n                {\n                    \"bits_per_second\": 859834062.5035313, \n                    \"bytes\": 107479040, \n                    \"end\": 24.000061, \n                    \"omitted\": false, \n                    \"pmtu\": 1500, \n                    \"retransmits\": 0, \n                    \"rtt\": 78379, \n                    \"rttvar\": 6, \n                    \"seconds\": 0.9999979734420776, \n                    \"sender\": true, \n                    \"snd_cwnd\": 16698336, \n                    \"snd_wnd\": -1, \n                    \"socket\": 5, \n                    \"start\": 23.000063\n                }\n            ], \n            \"sum\": {\n                \"bits_per_second\": 859834062.5035313, \n                \"bytes\": 107479040, \n                \"end\": 24.000061, \n                \"omitted\": false, \n                \"retransmits\": 0, \n                \"seconds\": 0.9999979734420776, \n                \"sender\": true, \n                \"start\": 23.000063\n            }\n        }, \n        {\n            \"streams\": [\n                {\n                    \"bits_per_second\": 849270932.9845358, \n                    \"bytes\": 106168320, \n                    \"end\": 25.00015, \n                    \"omitted\": false, \n                    \"pmtu\": 1500, \n                    \"retransmits\": 0, \n                    \"rtt\": 78380, \n                    \"rttvar\": 6, \n                    \"seconds\": 1.0000890493392944, \n                    \"sender\": true, \n                    \"snd_cwnd\": 16698336, \n                    \"snd_wnd\": -1, \n                    \"socket\": 5, \n                    \"start\": 24.000061\n                }\n            ], \n            \"sum\": {\n                \"bits_per_second\": 849270932.9845358, \n                \"bytes\": 106168320, \n                \"end\": 25.00015, \n                \"omitted\": false, \n                \"retransmits\": 0, \n                \"seconds\": 1.0000890493392944, \n                \"sender\": true, \n                \"start\": 24.000061\n            }\n        }, \n        {\n            \"streams\": [\n                {\n                    \"bits_per_second\": 849332992.7167244, \n                    \"bytes\": 106168320, \n                    \"end\": 26.000166, \n                    \"omitted\": false, \n                    \"pmtu\": 1500, \n                    \"retransmits\": 0, \n                    \"rtt\": 78386, \n                    \"rttvar\": 8, \n                    \"seconds\": 1.0000159740448, \n                    \"sender\": true, \n                    \"snd_cwnd\": 16698336, \n                    \"snd_wnd\": -1, \n                    \"socket\": 5, \n                    \"start\": 25.00015\n                }\n            ], \n            \"sum\": {\n                \"bits_per_second\": 849332992.7167244, \n                \"bytes\": 106168320, \n                \"end\": 26.000166, \n                \"omitted\": false, \n                \"retransmits\": 0, \n                \"seconds\": 1.0000159740448, \n                \"sender\": true, \n                \"start\": 25.00015\n            }\n        }, \n        {\n            \"streams\": [\n                {\n                    \"bits_per_second\": 849417086.4807622, \n                    \"bytes\": 106168320, \n                    \"end\": 27.000083, \n                    \"omitted\": false, \n                    \"pmtu\": 1500, \n                    \"retransmits\": 0, \n                    \"rtt\": 78385, \n                    \"rttvar\": 5, \n                    \"seconds\": 0.999916970729828, \n                    \"sender\": true, \n                    \"snd_cwnd\": 16698336, \n                    \"snd_wnd\": -1, \n                    \"socket\": 5, \n                    \"start\": 26.000166\n                }\n            ], \n            \"sum\": {\n                \"bits_per_second\": 849417086.4807622, \n                \"bytes\": 106168320, \n                \"end\": 27.000083, \n                \"omitted\": false, \n                \"retransmits\": 0, \n                \"seconds\": 0.999916970729828, \n                \"sender\": true, \n                \"start\": 26.000166\n            }\n        }, \n        {\n            \"streams\": [\n                {\n                    \"bits_per_second\": 849344028.7575437, \n                    \"bytes\": 106168320, \n                    \"end\": 28.000086, \n                    \"omitted\": false, \n                    \"pmtu\": 1500, \n                    \"retransmits\": 0, \n                    \"rtt\": 78386, \n                    \"rttvar\": 7, \n                    \"seconds\": 1.0000029802322388, \n                    \"sender\": true, \n                    \"snd_cwnd\": 16698336, \n                    \"snd_wnd\": -1, \n                    \"socket\": 5, \n                    \"start\": 27.000083\n                }\n            ], \n            \"sum\": {\n                \"bits_per_second\": 849344028.7575437, \n                \"bytes\": 106168320, \n                \"end\": 28.000086, \n                \"omitted\": false, \n                \"retransmits\": 0, \n                \"seconds\": 1.0000029802322388, \n                \"sender\": true, \n                \"start\": 27.000083\n            }\n        }, \n        {\n            \"streams\": [\n                {\n                    \"bits_per_second\": 849362709.682068, \n                    \"bytes\": 106168320, \n                    \"end\": 29.000067, \n                    \"omitted\": false, \n                    \"pmtu\": 1500, \n                    \"retransmits\": 0, \n                    \"rtt\": 78384, \n                    \"rttvar\": 7, \n                    \"seconds\": 0.9999809861183167, \n                    \"sender\": true, \n                    \"snd_cwnd\": 16698336, \n                    \"snd_wnd\": -1, \n                    \"socket\": 5, \n                    \"start\": 28.000086\n                }\n            ], \n            \"sum\": {\n                \"bits_per_second\": 849362709.682068, \n                \"bytes\": 106168320, \n                \"end\": 29.000067, \n                \"omitted\": false, \n                \"retransmits\": 0, \n                \"seconds\": 0.9999809861183167, \n                \"sender\": true, \n                \"start\": 28.000086\n            }\n        }, \n        {\n            \"streams\": [\n                {\n                    \"bits_per_second\": 859813357.9181844, \n                    \"bytes\": 107479040, \n                    \"end\": 30.000089, \n                    \"omitted\": false, \n                    \"pmtu\": 1500, \n                    \"retransmits\": 0, \n                    \"rtt\": 78387, \n                    \"rttvar\": 9, \n                    \"seconds\": 1.000022053718567, \n                    \"sender\": true, \n                    \"snd_cwnd\": 16698336, \n                    \"snd_wnd\": -1, \n                    \"socket\": 5, \n                    \"start\": 29.000067\n                }\n            ], \n            \"sum\": {\n                \"bits_per_second\": 859813357.9181844, \n                \"bytes\": 107479040, \n                \"end\": 30.000089, \n                \"omitted\": false, \n                \"retransmits\": 0, \n                \"seconds\": 1.000022053718567, \n                \"sender\": true, \n                \"start\": 29.000067\n            }\n        }, \n        {\n            \"streams\": [\n                {\n                    \"bits_per_second\": 849355925.7282746, \n                    \"bytes\": 106168320, \n                    \"end\": 31.000078, \n                    \"omitted\": false, \n                    \"pmtu\": 1500, \n                    \"retransmits\": 0, \n                    \"rtt\": 78384, \n                    \"rttvar\": 7, \n                    \"seconds\": 0.9999889731407166, \n                    \"sender\": true, \n                    \"snd_cwnd\": 16698336, \n                    \"snd_wnd\": -1, \n                    \"socket\": 5, \n                    \"start\": 30.000089\n                }\n            ], \n            \"sum\": {\n                \"bits_per_second\": 849355925.7282746, \n                \"bytes\": 106168320, \n                \"end\": 31.000078, \n                \"omitted\": false, \n                \"retransmits\": 0, \n                \"seconds\": 0.9999889731407166, \n                \"sender\": true, \n                \"start\": 30.000089\n            }\n        }, \n        {\n            \"streams\": [\n                {\n                    \"bits_per_second\": 849340586.2920152, \n                    \"bytes\": 106168320, \n                    \"end\": 32.000085, \n                    \"omitted\": false, \n                    \"pmtu\": 1500, \n                    \"retransmits\": 0, \n                    \"rtt\": 78385, \n                    \"rttvar\": 6, \n                    \"seconds\": 1.0000070333480835, \n                    \"sender\": true, \n                    \"snd_cwnd\": 16698336, \n                    \"snd_wnd\": -1, \n                    \"socket\": 5, \n                    \"start\": 31.000078\n                }\n            ], \n            \"sum\": {\n                \"bits_per_second\": 849340586.2920152, \n                \"bytes\": 106168320, \n                \"end\": 32.000085, \n                \"omitted\": false, \n                \"retransmits\": 0, \n                \"seconds\": 1.0000070333480835, \n                \"sender\": true, \n                \"start\": 31.000078\n            }\n        }, \n        {\n            \"streams\": [\n                {\n                    \"bits_per_second\": 849290471.2042133, \n                    \"bytes\": 106168320, \n                    \"end\": 33.000151, \n                    \"omitted\": false, \n                    \"pmtu\": 1500, \n                    \"retransmits\": 0, \n                    \"rtt\": 78384, \n                    \"rttvar\": 6, \n                    \"seconds\": 1.0000660419464111, \n                    \"sender\": true, \n                    \"snd_cwnd\": 16698336, \n                    \"snd_wnd\": -1, \n                    \"socket\": 5, \n                    \"start\": 32.000085\n                }\n            ], \n            \"sum\": {\n                \"bits_per_second\": 849290471.2042133, \n                \"bytes\": 106168320, \n                \"end\": 33.000151, \n                \"omitted\": false, \n                \"retransmits\": 0, \n                \"seconds\": 1.0000660419464111, \n                \"sender\": true, \n                \"start\": 32.000085\n            }\n        }, \n        {\n            \"streams\": [\n                {\n                    \"bits_per_second\": 849421289.074399, \n                    \"bytes\": 106168320, \n                    \"end\": 34.000063, \n                    \"omitted\": false, \n                    \"pmtu\": 1500, \n                    \"retransmits\": 0, \n                    \"rtt\": 78380, \n                    \"rttvar\": 11, \n                    \"seconds\": 0.9999120235443115, \n                    \"sender\": true, \n                    \"snd_cwnd\": 16698336, \n                    \"snd_wnd\": -1, \n                    \"socket\": 5, \n                    \"start\": 33.000151\n                }\n            ], \n            \"sum\": {\n                \"bits_per_second\": 849421289.074399, \n                \"bytes\": 106168320, \n                \"end\": 34.000063, \n                \"omitted\": false, \n                \"retransmits\": 0, \n                \"seconds\": 0.9999120235443115, \n                \"sender\": true, \n                \"start\": 33.000151\n            }\n        }, \n        {\n            \"streams\": [\n                {\n                    \"bits_per_second\": 859816842.7785993, \n                    \"bytes\": 107479040, \n                    \"end\": 35.000081, \n                    \"omitted\": false, \n                    \"pmtu\": 1500, \n                    \"retransmits\": 0, \n                    \"rtt\": 78385, \n                    \"rttvar\": 3, \n                    \"seconds\": 1.0000180006027222, \n                    \"sender\": true, \n                    \"snd_cwnd\": 16698336, \n                    \"snd_wnd\": -1, \n                    \"socket\": 5, \n                    \"start\": 34.000063\n                }\n            ], \n            \"sum\": {\n                \"bits_per_second\": 859816842.7785993, \n                \"bytes\": 107479040, \n                \"end\": 35.000081, \n                \"omitted\": false, \n                \"retransmits\": 0, \n                \"seconds\": 1.0000180006027222, \n                \"sender\": true, \n                \"start\": 34.000063\n            }\n        }, \n        {\n            \"streams\": [\n                {\n                    \"bits_per_second\": 849281967.4126233, \n                    \"bytes\": 106168320, \n                    \"end\": 36.000157, \n                    \"omitted\": false, \n                    \"pmtu\": 1500, \n                    \"retransmits\": 0, \n                    \"rtt\": 78380, \n                    \"rttvar\": 6, \n                    \"seconds\": 1.0000760555267334, \n                    \"sender\": true, \n                    \"snd_cwnd\": 16698336, \n                    \"snd_wnd\": -1, \n                    \"socket\": 5, \n                    \"start\": 35.000081\n                }\n            ], \n            \"sum\": {\n                \"bits_per_second\": 849281967.4126233, \n                \"bytes\": 106168320, \n                \"end\": 36.000157, \n                \"omitted\": false, \n                \"retransmits\": 0, \n                \"seconds\": 1.0000760555267334, \n                \"sender\": true, \n                \"start\": 35.000081\n            }\n        }, \n        {\n            \"streams\": [\n                {\n                    \"bits_per_second\": 849396681.7076117, \n                    \"bytes\": 106168320, \n                    \"end\": 37.000098, \n                    \"omitted\": false, \n                    \"pmtu\": 1500, \n                    \"retransmits\": 0, \n                    \"rtt\": 78381, \n                    \"rttvar\": 9, \n                    \"seconds\": 0.9999409914016724, \n                    \"sender\": true, \n                    \"snd_cwnd\": 16698336, \n                    \"snd_wnd\": -1, \n                    \"socket\": 5, \n                    \"start\": 36.000157\n                }\n            ], \n            \"sum\": {\n                \"bits_per_second\": 849396681.7076117, \n                \"bytes\": 106168320, \n                \"end\": 37.000098, \n                \"omitted\": false, \n                \"retransmits\": 0, \n                \"seconds\": 0.9999409914016724, \n                \"sender\": true, \n                \"start\": 36.000157\n            }\n        }, \n        {\n            \"streams\": [\n                {\n                    \"bits_per_second\": 849358457.041643, \n                    \"bytes\": 106168320, \n                    \"end\": 38.000084, \n                    \"omitted\": false, \n                    \"pmtu\": 1500, \n                    \"retransmits\": 0, \n                    \"rtt\": 78380, \n                    \"rttvar\": 7, \n                    \"seconds\": 0.9999859929084778, \n                    \"sender\": true, \n                    \"snd_cwnd\": 16698336, \n                    \"snd_wnd\": -1, \n                    \"socket\": 5, \n                    \"start\": 37.000098\n                }\n            ], \n            \"sum\": {\n                \"bits_per_second\": 849358457.041643, \n                \"bytes\": 106168320, \n                \"end\": 38.000084, \n                \"omitted\": false, \n                \"retransmits\": 0, \n                \"seconds\": 0.9999859929084778, \n                \"sender\": true, \n                \"start\": 37.000098\n            }\n        }, \n        {\n            \"streams\": [\n                {\n                    \"bits_per_second\": 849363570.3406688, \n                    \"bytes\": 106168320, \n                    \"end\": 39.000064, \n                    \"omitted\": false, \n                    \"pmtu\": 1500, \n                    \"retransmits\": 0, \n                    \"rtt\": 78391, \n                    \"rttvar\": 12, \n                    \"seconds\": 0.9999799728393555, \n                    \"sender\": true, \n                    \"snd_cwnd\": 16698336, \n                    \"snd_wnd\": -1, \n                    \"socket\": 5, \n                    \"start\": 38.000084\n                }\n            ], \n            \"sum\": {\n                \"bits_per_second\": 849363570.3406688, \n                \"bytes\": 106168320, \n                \"end\": 39.000064, \n                \"omitted\": false, \n                \"retransmits\": 0, \n                \"seconds\": 0.9999799728393555, \n                \"sender\": true, \n                \"start\": 38.000084\n            }\n        }, \n        {\n            \"streams\": [\n                {\n                    \"bits_per_second\": 849347420.625872, \n                    \"bytes\": 106168320, \n                    \"end\": 40.000063, \n                    \"omitted\": false, \n                    \"pmtu\": 1500, \n                    \"retransmits\": 0, \n                    \"rtt\": 78385, \n                    \"rttvar\": 6, \n                    \"seconds\": 0.9999989867210388, \n                    \"sender\": true, \n                    \"snd_cwnd\": 16698336, \n                    \"snd_wnd\": -1, \n                    \"socket\": 5, \n                    \"start\": 39.000064\n                }\n            ], \n            \"sum\": {\n                \"bits_per_second\": 849347420.625872, \n                \"bytes\": 106168320, \n                \"end\": 40.000063, \n                \"omitted\": false, \n                \"retransmits\": 0, \n                \"seconds\": 0.9999989867210388, \n                \"sender\": true, \n                \"start\": 39.000064\n            }\n        }, \n        {\n            \"streams\": [\n                {\n                    \"bits_per_second\": 859733418.877285, \n                    \"bytes\": 107479040, \n                    \"end\": 41.000178, \n                    \"omitted\": false, \n                    \"pmtu\": 1500, \n                    \"retransmits\": 0, \n                    \"rtt\": 78382, \n                    \"rttvar\": 7, \n                    \"seconds\": 1.0001150369644165, \n                    \"sender\": true, \n                    \"snd_cwnd\": 16698336, \n                    \"snd_wnd\": -1, \n                    \"socket\": 5, \n                    \"start\": 40.000063\n                }\n            ], \n            \"sum\": {\n                \"bits_per_second\": 859733418.877285, \n                \"bytes\": 107479040, \n                \"end\": 41.000178, \n                \"omitted\": false, \n                \"retransmits\": 0, \n                \"seconds\": 1.0001150369644165, \n                \"sender\": true, \n                \"start\": 40.000063\n            }\n        }, \n        {\n            \"streams\": [\n                {\n                    \"bits_per_second\": 849366101.6996036, \n                    \"bytes\": 106168320, \n                    \"end\": 42.000155, \n                    \"omitted\": false, \n                    \"pmtu\": 1500, \n                    \"retransmits\": 0, \n                    \"rtt\": 78385, \n                    \"rttvar\": 7, \n                    \"seconds\": 0.9999769926071167, \n                    \"sender\": true, \n                    \"snd_cwnd\": 16698336, \n                    \"snd_wnd\": -1, \n                    \"socket\": 5, \n                    \"start\": 41.000178\n                }\n            ], \n            \"sum\": {\n                \"bits_per_second\": 849366101.6996036, \n                \"bytes\": 106168320, \n                \"end\": 42.000155, \n                \"omitted\": false, \n                \"retransmits\": 0, \n                \"seconds\": 0.9999769926071167, \n                \"sender\": true, \n                \"start\": 41.000178\n            }\n        }, \n        {\n            \"streams\": [\n                {\n                    \"bits_per_second\": 849349091.2575437, \n                    \"bytes\": 106168320, \n                    \"end\": 43.000152, \n                    \"omitted\": false, \n                    \"pmtu\": 1500, \n                    \"retransmits\": 0, \n                    \"rtt\": 78387, \n                    \"rttvar\": 4, \n                    \"seconds\": 0.9999970197677612, \n                    \"sender\": true, \n                    \"snd_cwnd\": 16698336, \n                    \"snd_wnd\": -1, \n                    \"socket\": 5, \n                    \"start\": 42.000155\n                }\n            ], \n            \"sum\": {\n                \"bits_per_second\": 849349091.2575437, \n                \"bytes\": 106168320, \n                \"end\": 43.000152, \n                \"omitted\": false, \n                \"retransmits\": 0, \n                \"seconds\": 0.9999970197677612, \n                \"sender\": true, \n                \"start\": 42.000155\n            }\n        }, \n        {\n            \"streams\": [\n                {\n                    \"bits_per_second\": 849417896.616059, \n                    \"bytes\": 106168320, \n                    \"end\": 44.000068, \n                    \"omitted\": false, \n                    \"pmtu\": 1500, \n                    \"retransmits\": 0, \n                    \"rtt\": 78386, \n                    \"rttvar\": 6, \n                    \"seconds\": 0.9999160170555115, \n                    \"sender\": true, \n                    \"snd_cwnd\": 16698336, \n                    \"snd_wnd\": -1, \n                    \"socket\": 5, \n                    \"start\": 43.000152\n                }\n            ], \n            \"sum\": {\n                \"bits_per_second\": 849417896.616059, \n                \"bytes\": 106168320, \n                \"end\": 44.000068, \n                \"omitted\": false, \n                \"retransmits\": 0, \n                \"seconds\": 0.9999160170555115, \n                \"sender\": true, \n                \"start\": 43.000152\n            }\n        }, \n        {\n            \"streams\": [\n                {\n                    \"bits_per_second\": 849341497.5301746, \n                    \"bytes\": 106168320, \n                    \"end\": 45.000074, \n                    \"omitted\": false, \n                    \"pmtu\": 1500, \n                    \"retransmits\": 0, \n                    \"rtt\": 78382, \n                    \"rttvar\": 6, \n                    \"seconds\": 1.0000059604644775, \n                    \"sender\": true, \n                    \"snd_cwnd\": 16698336, \n                    \"snd_wnd\": -1, \n                    \"socket\": 5, \n                    \"start\": 44.000068\n                }\n            ], \n            \"sum\": {\n                \"bits_per_second\": 849341497.5301746, \n                \"bytes\": 106168320, \n                \"end\": 45.000074, \n                \"omitted\": false, \n                \"retransmits\": 0, \n                \"seconds\": 1.0000059604644775, \n                \"sender\": true, \n                \"start\": 44.000068\n            }\n        }, \n        {\n            \"streams\": [\n                {\n                    \"bits_per_second\": 859591614.9028722, \n                    \"bytes\": 107479040, \n                    \"end\": 46.000354, \n                    \"omitted\": false, \n                    \"pmtu\": 1500, \n                    \"retransmits\": 0, \n                    \"rtt\": 78386, \n                    \"rttvar\": 4, \n                    \"seconds\": 1.0002800226211548, \n                    \"sender\": true, \n                    \"snd_cwnd\": 16698336, \n                    \"snd_wnd\": -1, \n                    \"socket\": 5, \n                    \"start\": 45.000074\n                }\n            ], \n            \"sum\": {\n                \"bits_per_second\": 859591614.9028722, \n                \"bytes\": 107479040, \n                \"end\": 46.000354, \n                \"omitted\": false, \n                \"retransmits\": 0, \n                \"seconds\": 1.0002800226211548, \n                \"sender\": true, \n                \"start\": 45.000074\n            }\n        }, \n        {\n            \"streams\": [\n                {\n                    \"bits_per_second\": 849616730.2866602, \n                    \"bytes\": 106168320, \n                    \"end\": 47.000036, \n                    \"omitted\": false, \n                    \"pmtu\": 1500, \n                    \"retransmits\": 0, \n                    \"rtt\": 78386, \n                    \"rttvar\": 10, \n                    \"seconds\": 0.9996820092201233, \n                    \"sender\": true, \n                    \"snd_cwnd\": 16698336, \n                    \"snd_wnd\": -1, \n                    \"socket\": 5, \n                    \"start\": 46.000354\n                }\n            ], \n            \"sum\": {\n                \"bits_per_second\": 849616730.2866602, \n                \"bytes\": 106168320, \n                \"end\": 47.000036, \n                \"omitted\": false, \n                \"retransmits\": 0, \n                \"seconds\": 0.9996820092201233, \n                \"sender\": true, \n                \"start\": 46.000354\n            }\n        }, \n        {\n            \"streams\": [\n                {\n                    \"bits_per_second\": 849298975.1661005, \n                    \"bytes\": 106168320, \n                    \"end\": 48.000092, \n                    \"omitted\": false, \n                    \"pmtu\": 1500, \n                    \"retransmits\": 0, \n                    \"rtt\": 78385, \n                    \"rttvar\": 6, \n                    \"seconds\": 1.0000560283660889, \n                    \"sender\": true, \n                    \"snd_cwnd\": 16698336, \n                    \"snd_wnd\": -1, \n                    \"socket\": 5, \n                    \"start\": 47.000036\n                }\n            ], \n            \"sum\": {\n                \"bits_per_second\": 849298975.1661005, \n                \"bytes\": 106168320, \n                \"end\": 48.000092, \n                \"omitted\": false, \n                \"retransmits\": 0, \n                \"seconds\": 1.0000560283660889, \n                \"sender\": true, \n                \"start\": 47.000036\n            }\n        }, \n        {\n            \"streams\": [\n                {\n                    \"bits_per_second\": 849355925.7282746, \n                    \"bytes\": 106168320, \n                    \"end\": 49.000081, \n                    \"omitted\": false, \n                    \"pmtu\": 1500, \n                    \"retransmits\": 0, \n                    \"rtt\": 78386, \n                    \"rttvar\": 9, \n                    \"seconds\": 0.9999889731407166, \n                    \"sender\": true, \n                    \"snd_cwnd\": 16698336, \n                    \"snd_wnd\": -1, \n                    \"socket\": 5, \n                    \"start\": 48.000092\n                }\n            ], \n            \"sum\": {\n                \"bits_per_second\": 849355925.7282746, \n                \"bytes\": 106168320, \n                \"end\": 49.000081, \n                \"omitted\": false, \n                \"retransmits\": 0, \n                \"seconds\": 0.9999889731407166, \n                \"sender\": true, \n                \"start\": 48.000092\n            }\n        }, \n        {\n            \"streams\": [\n                {\n                    \"bits_per_second\": 849346560, \n                    \"bytes\": 106168320, \n                    \"end\": 50.000081, \n                    \"omitted\": false, \n                    \"pmtu\": 1500, \n                    \"retransmits\": 0, \n                    \"rtt\": 78388, \n                    \"rttvar\": 8, \n                    \"seconds\": 1, \n                    \"sender\": true, \n                    \"snd_cwnd\": 16698336, \n                    \"snd_wnd\": -1, \n                    \"socket\": 5, \n                    \"start\": 49.000081\n                }\n            ], \n            \"sum\": {\n                \"bits_per_second\": 849346560, \n                \"bytes\": 106168320, \n                \"end\": 50.000081, \n                \"omitted\": false, \n                \"retransmits\": 0, \n                \"seconds\": 1, \n                \"sender\": true, \n                \"start\": 49.000081\n            }\n        }, \n        {\n            \"streams\": [\n                {\n                    \"bits_per_second\": 849279436.5551524, \n                    \"bytes\": 106168320, \n                    \"end\": 51.00016, \n                    \"omitted\": false, \n                    \"pmtu\": 1500, \n                    \"retransmits\": 0, \n                    \"rtt\": 78391, \n                    \"rttvar\": 17, \n                    \"seconds\": 1.0000790357589722, \n                    \"sender\": true, \n                    \"snd_cwnd\": 16698336, \n                    \"snd_wnd\": -1, \n                    \"socket\": 5, \n                    \"start\": 50.000081\n                }\n            ], \n            \"sum\": {\n                \"bits_per_second\": 849279436.5551524, \n                \"bytes\": 106168320, \n                \"end\": 51.00016, \n                \"omitted\": false, \n                \"retransmits\": 0, \n                \"seconds\": 1.0000790357589722, \n                \"sender\": true, \n                \"start\": 50.000081\n            }\n        }, \n        {\n            \"streams\": [\n                {\n                    \"bits_per_second\": 859895105.834351, \n                    \"bytes\": 107479040, \n                    \"end\": 52.000087, \n                    \"omitted\": false, \n                    \"pmtu\": 1500, \n                    \"retransmits\": 0, \n                    \"rtt\": 78394, \n                    \"rttvar\": 15, \n                    \"seconds\": 0.99992698431015, \n                    \"sender\": true, \n                    \"snd_cwnd\": 16698336, \n                    \"snd_wnd\": -1, \n                    \"socket\": 5, \n                    \"start\": 51.00016\n                }\n            ], \n            \"sum\": {\n                \"bits_per_second\": 859895105.834351, \n                \"bytes\": 107479040, \n                \"end\": 52.000087, \n                \"omitted\": false, \n                \"retransmits\": 0, \n                \"seconds\": 0.99992698431015, \n                \"sender\": true, \n                \"start\": 51.00016\n            }\n        }, \n        {\n            \"streams\": [\n                {\n                    \"bits_per_second\": 849342307.5212913, \n                    \"bytes\": 106168320, \n                    \"end\": 53.000092, \n                    \"omitted\": false, \n                    \"pmtu\": 1500, \n                    \"retransmits\": 0, \n                    \"rtt\": 78381, \n                    \"rttvar\": 4, \n                    \"seconds\": 1.0000050067901611, \n                    \"sender\": true, \n                    \"snd_cwnd\": 16698336, \n                    \"snd_wnd\": -1, \n                    \"socket\": 5, \n                    \"start\": 52.000087\n                }\n            ], \n            \"sum\": {\n                \"bits_per_second\": 849342307.5212913, \n                \"bytes\": 106168320, \n                \"end\": 53.000092, \n                \"omitted\": false, \n                \"retransmits\": 0, \n                \"seconds\": 1.0000050067901611, \n                \"sender\": true, \n                \"start\": 52.000087\n            }\n        }, \n        {\n            \"streams\": [\n                {\n                    \"bits_per_second\": 849372885.8159533, \n                    \"bytes\": 106168320, \n                    \"end\": 54.000061, \n                    \"omitted\": false, \n                    \"pmtu\": 1500, \n                    \"retransmits\": 0, \n                    \"rtt\": 78386, \n                    \"rttvar\": 6, \n                    \"seconds\": 0.9999690055847168, \n                    \"sender\": true, \n                    \"snd_cwnd\": 16698336, \n                    \"snd_wnd\": -1, \n                    \"socket\": 5, \n                    \"start\": 53.000092\n                }\n            ], \n            \"sum\": {\n                \"bits_per_second\": 849372885.8159533, \n                \"bytes\": 106168320, \n                \"end\": 54.000061, \n                \"omitted\": false, \n                \"retransmits\": 0, \n                \"seconds\": 0.9999690055847168, \n                \"sender\": true, \n                \"start\": 53.000092\n            }\n        }, \n        {\n            \"streams\": [\n                {\n                    \"bits_per_second\": 849265871.4162065, \n                    \"bytes\": 106168320, \n                    \"end\": 55.000156, \n                    \"omitted\": false, \n                    \"pmtu\": 1500, \n                    \"retransmits\": 0, \n                    \"rtt\": 78389, \n                    \"rttvar\": 7, \n                    \"seconds\": 1.000095009803772, \n                    \"sender\": true, \n                    \"snd_cwnd\": 16698336, \n                    \"snd_wnd\": -1, \n                    \"socket\": 5, \n                    \"start\": 54.000061\n                }\n            ], \n            \"sum\": {\n                \"bits_per_second\": 849265871.4162065, \n                \"bytes\": 106168320, \n                \"end\": 55.000156, \n                \"omitted\": false, \n                \"retransmits\": 0, \n                \"seconds\": 1.000095009803772, \n                \"sender\": true, \n                \"start\": 54.000061\n            }\n        }, \n        {\n            \"streams\": [\n                {\n                    \"bits_per_second\": 849425542.3440347, \n                    \"bytes\": 106168320, \n                    \"end\": 56.000063, \n                    \"omitted\": false, \n                    \"pmtu\": 1500, \n                    \"retransmits\": 0, \n                    \"rtt\": 78385, \n                    \"rttvar\": 4, \n                    \"seconds\": 0.9999070167541504, \n                    \"sender\": true, \n                    \"snd_cwnd\": 16698336, \n                    \"snd_wnd\": -1, \n                    \"socket\": 5, \n                    \"start\": 55.000156\n                }\n            ], \n            \"sum\": {\n                \"bits_per_second\": 849425542.3440347, \n                \"bytes\": 106168320, \n                \"end\": 56.000063, \n                \"omitted\": false, \n                \"retransmits\": 0, \n                \"seconds\": 0.9999070167541504, \n                \"sender\": true, \n                \"start\": 55.000156\n            }\n        }, \n        {\n            \"streams\": [\n                {\n                    \"bits_per_second\": 849347420.625872, \n                    \"bytes\": 106168320, \n                    \"end\": 57.000062, \n                    \"omitted\": false, \n                    \"pmtu\": 1500, \n                    \"retransmits\": 0, \n                    \"rtt\": 78378, \n                    \"rttvar\": 11, \n                    \"seconds\": 0.9999989867210388, \n                    \"sender\": true, \n                    \"snd_cwnd\": 16698336, \n                    \"snd_wnd\": -1, \n                    \"socket\": 5, \n                    \"start\": 56.000063\n                }\n            ], \n            \"sum\": {\n                \"bits_per_second\": 849347420.625872, \n                \"bytes\": 106168320, \n                \"end\": 57.000062, \n                \"omitted\": false, \n                \"retransmits\": 0, \n                \"seconds\": 0.9999989867210388, \n                \"sender\": true, \n                \"start\": 56.000063\n            }\n        }, \n        {\n            \"streams\": [\n                {\n                    \"bits_per_second\": 859853794.2863063, \n                    \"bytes\": 107479040, \n                    \"end\": 58.000037, \n                    \"omitted\": false, \n                    \"pmtu\": 1500, \n                    \"retransmits\": 0, \n                    \"rtt\": 78386, \n                    \"rttvar\": 3, \n                    \"seconds\": 0.999975025653839, \n                    \"sender\": true, \n                    \"snd_cwnd\": 16698336, \n                    \"snd_wnd\": -1, \n                    \"socket\": 5, \n                    \"start\": 57.000062\n                }\n            ], \n            \"sum\": {\n                \"bits_per_second\": 859853794.2863063, \n                \"bytes\": 107479040, \n                \"end\": 58.000037, \n                \"omitted\": false, \n                \"retransmits\": 0, \n                \"seconds\": 0.999975025653839, \n                \"sender\": true, \n                \"start\": 57.000062\n            }\n        }, \n        {\n            \"streams\": [\n                {\n                    \"bits_per_second\": 849291382.3348413, \n                    \"bytes\": 106168320, \n                    \"end\": 59.000102, \n                    \"omitted\": false, \n                    \"pmtu\": 1500, \n                    \"retransmits\": 0, \n                    \"rtt\": 78383, \n                    \"rttvar\": 7, \n                    \"seconds\": 1.0000649690628052, \n                    \"sender\": true, \n                    \"snd_cwnd\": 16698336, \n                    \"snd_wnd\": -1, \n                    \"socket\": 5, \n                    \"start\": 58.000037\n                }\n            ], \n            \"sum\": {\n                \"bits_per_second\": 849291382.3348413, \n                \"bytes\": 106168320, \n                \"end\": 59.000102, \n                \"omitted\": false, \n                \"retransmits\": 0, \n                \"seconds\": 1.0000649690628052, \n                \"sender\": true, \n                \"start\": 58.000037\n            }\n        }, \n        {\n            \"streams\": [\n                {\n                    \"bits_per_second\": 849284599.520394, \n                    \"bytes\": 106168320, \n                    \"end\": 60.000175, \n                    \"omitted\": false, \n                    \"pmtu\": 1500, \n                    \"retransmits\": 0, \n                    \"rtt\": 78388, \n                    \"rttvar\": 9, \n                    \"seconds\": 1.000072956085205, \n                    \"sender\": true, \n                    \"snd_cwnd\": 16698336, \n                    \"snd_wnd\": -1, \n                    \"socket\": 5, \n                    \"start\": 59.000102\n                }\n            ], \n            \"sum\": {\n                \"bits_per_second\": 849284599.520394, \n                \"bytes\": 106168320, \n                \"end\": 60.000175, \n                \"omitted\": false, \n                \"retransmits\": 0, \n                \"seconds\": 1.000072956085205, \n                \"sender\": true, \n                \"start\": 59.000102\n            }\n        }\n    ], \n    \"start\": {\n        \"connected\": [\n            {\n                \"local_host\": \"10.0.0.1\", \n                \"local_port\": 49789, \n                \"remote_host\": \"10.0.0.2\", \n                \"remote_port\": 5201, \n                \"socket\": 5\n            }\n        ], \n        \"connecting_to\": {\n            \"host\": \"10.0.0.2\", \n            \"port\": 5201\n        }, \n        \"cookie\": \"ldbki7qirkd2yh3s44meju6htwatad62sw5w\", \n        \"fq_rate\": 0, \n        \"rcvbuf_actual\": 87380, \n        \"sndbuf_actual\": 87380, \n        \"sock_bufsize\": 0, \n        \"system_info\": \"REDACTED\", \n        \"target_bitrate\": 0, \n        \"tcp_mss_default\": 1448, \n        \"test_start\": {\n            \"bidir\": 0, \n            \"blksize\": 131072, \n            \"blocks\": 0, \n            \"bytes\": 0, \n            \"duration\": 60, \n            \"fqrate\": 0, \n            \"num_streams\": 1, \n            \"omit\": 0, \n            \"protocol\": \"TCP\", \n            \"reverse\": 0, \n            \"target_bitrate\": 0, \n            \"tos\": 0\n        }, \n        \"timestamp\": {\n            \"time\": \"Tue, 16 Apr 2024 23:05:47 GMT\", \n            \"timesecs\": 1713308747\n        }, \n        \"version\": \"iperf 3.14\"\n    }\n}\nParticipant 1:\n/usr/bin/iperf3 -s -1 --idle-timeout 60 --json -p 5201 -B 10.0.0.2 --authorized-users-path /var/run/pscheduler-server/runner/tmp/tmpsaj269_g/tmpwvq9xekz/credentials --rsa-private-key-path /var/run/pscheduler-server/runner/tmp/tmpsaj269_g/tmpwvq9xekz/private-key\n\n{\n    \"end\": {\n        \"cpu_utilization_percent\": {\n            \"host_system\": 5.00471091713538, \n            \"host_total\": 5.411155581606642, \n            \"host_user\": 0.4064429999832719, \n            \"remote_system\": 0, \n            \"remote_total\": 0, \n            \"remote_user\": 0\n        }, \n        \"receiver_tcp_congestion\": \"htcp\", \n        \"streams\": [\n            {\n                \"receiver\": {\n                    \"bits_per_second\": 851127244.650076, \n                    \"bytes\": 6391807936, \n                    \"end\": 60.078518, \n                    \"seconds\": 60.078518, \n                    \"sender\": false, \n                    \"socket\": 5, \n                    \"start\": 0\n                }, \n                \"sender\": {\n                    \"bits_per_second\": 0, \n                    \"bytes\": 0, \n                    \"end\": 60.078518, \n                    \"seconds\": 60.078518, \n                    \"sender\": false, \n                    \"socket\": 5, \n                    \"start\": 0\n                }\n            }\n        ], \n        \"sum_received\": {\n            \"bits_per_second\": 851127244.650076, \n            \"bytes\": 6391807936, \n            \"end\": 60.078518, \n            \"seconds\": 60.078518, \n            \"sender\": false, \n            \"start\": 0\n        }, \n        \"sum_sent\": {\n            \"bits_per_second\": 0, \n            \"bytes\": 0, \n            \"end\": 60.078518, \n            \"seconds\": 60.078518, \n            \"sender\": false, \n            \"start\": 0\n        }\n    }, \n    \"intervals\": [\n        {\n            \"streams\": [\n                {\n                    \"bits_per_second\": 847050660.3201363, \n                    \"bytes\": 105887896, \n                    \"end\": 1.000062, \n                    \"omitted\": false, \n                    \"seconds\": 1.0000619888305664, \n                    \"sender\": false, \n                    \"socket\": 5, \n                    \"start\": 0\n                }\n            ], \n            \"sum\": {\n                \"bits_per_second\": 847050660.3201363, \n                \"bytes\": 105887896, \n                \"end\": 1.000062, \n                \"omitted\": false, \n                \"seconds\": 1.0000619888305664, \n                \"sender\": false, \n                \"start\": 0\n            }\n        }, \n        {\n            \"streams\": [\n                {\n                    \"bits_per_second\": 851281749.755051, \n                    \"bytes\": 106406280, \n                    \"end\": 2.000025, \n                    \"omitted\": false, \n                    \"seconds\": 0.9999629855155945, \n                    \"sender\": false, \n                    \"socket\": 5, \n                    \"start\": 1.000062\n                }\n            ], \n            \"sum\": {\n                \"bits_per_second\": 851281749.755051, \n                \"bytes\": 106406280, \n                \"end\": 2.000025, \n                \"omitted\": false, \n                \"seconds\": 0.9999629855155945, \n                \"sender\": false, \n                \"start\": 1.000062\n            }\n        }, \n        {\n            \"streams\": [\n                {\n                    \"bits_per_second\": 851235729.0454705, \n                    \"bytes\": 106406280, \n                    \"end\": 3.000042, \n                    \"omitted\": false, \n                    \"seconds\": 1.0000170469284058, \n                    \"sender\": false, \n                    \"socket\": 5, \n                    \"start\": 2.000025\n                }\n            ], \n            \"sum\": {\n                \"bits_per_second\": 851235729.0454705, \n                \"bytes\": 106406280, \n                \"end\": 3.000042, \n                \"omitted\": false, \n                \"seconds\": 1.0000170469284058, \n                \"sender\": false, \n                \"start\": 2.000025\n            }\n        }, \n        {\n            \"streams\": [\n                {\n                    \"bits_per_second\": 850689004.4474516, \n                    \"bytes\": 106341120, \n                    \"end\": 4.000089, \n                    \"omitted\": false, \n                    \"seconds\": 1.000046968460083, \n                    \"sender\": false, \n                    \"socket\": 5, \n                    \"start\": 3.000042\n                }\n            ], \n            \"sum\": {\n                \"bits_per_second\": 850689004.4474516, \n                \"bytes\": 106341120, \n                \"end\": 4.000089, \n                \"omitted\": false, \n                \"seconds\": 1.000046968460083, \n                \"sender\": false, \n                \"start\": 3.000042\n            }\n        }, \n        {\n            \"streams\": [\n                {\n                    \"bits_per_second\": 851255364.6161357, \n                    \"bytes\": 106406280, \n                    \"end\": 5.000083, \n                    \"omitted\": false, \n                    \"seconds\": 0.9999939799308777, \n                    \"sender\": false, \n                    \"socket\": 5, \n                    \"start\": 4.000089\n                }\n            ], \n            \"sum\": {\n                \"bits_per_second\": 851255364.6161357, \n                \"bytes\": 106406280, \n                \"end\": 5.000083, \n                \"omitted\": false, \n                \"seconds\": 0.9999939799308777, \n                \"sender\": false, \n                \"start\": 4.000089\n            }\n        }, \n        {\n            \"streams\": [\n                {\n                    \"bits_per_second\": 851251965.111414, \n                    \"bytes\": 106406280, \n                    \"end\": 6.000081, \n                    \"omitted\": false, \n                    \"seconds\": 0.9999979734420776, \n                    \"sender\": false, \n                    \"socket\": 5, \n                    \"start\": 5.000083\n                }\n            ], \n            \"sum\": {\n                \"bits_per_second\": 851251965.111414, \n                \"bytes\": 106406280, \n                \"end\": 6.000081, \n                \"omitted\": false, \n                \"seconds\": 0.9999979734420776, \n                \"sender\": false, \n                \"start\": 5.000083\n            }\n        }, \n        {\n            \"streams\": [\n                {\n                    \"bits_per_second\": 851241716.022703, \n                    \"bytes\": 106406280, \n                    \"end\": 7.000091, \n                    \"omitted\": false, \n                    \"seconds\": 1.0000100135803223, \n                    \"sender\": false, \n                    \"socket\": 5, \n                    \"start\": 6.000081\n                }\n            ], \n            \"sum\": {\n                \"bits_per_second\": 851241716.022703, \n                \"bytes\": 106406280, \n                \"end\": 7.000091, \n                \"omitted\": false, \n                \"seconds\": 1.0000100135803223, \n                \"sender\": false, \n                \"start\": 6.000081\n            }\n        }, \n        {\n            \"streams\": [\n                {\n                    \"bits_per_second\": 851253639.4909433, \n                    \"bytes\": 106406280, \n                    \"end\": 8.000087, \n                    \"omitted\": false, \n                    \"seconds\": 0.9999960064888, \n                    \"sender\": false, \n                    \"socket\": 5, \n                    \"start\": 7.000091\n                }\n            ], \n            \"sum\": {\n                \"bits_per_second\": 851253639.4909433, \n                \"bytes\": 106406280, \n                \"end\": 8.000087, \n                \"omitted\": false, \n                \"seconds\": 0.9999960064888, \n                \"sender\": false, \n                \"start\": 7.000091\n            }\n        }, \n        {\n            \"streams\": [\n                {\n                    \"bits_per_second\": 851270688.0938495, \n                    \"bytes\": 106406280, \n                    \"end\": 9.000063, \n                    \"omitted\": false, \n                    \"seconds\": 0.9999759793281555, \n                    \"sender\": false, \n                    \"socket\": 5, \n                    \"start\": 8.000087\n                }\n            ], \n            \"sum\": {\n                \"bits_per_second\": 851270688.0938495, \n                \"bytes\": 106406280, \n                \"end\": 9.000063, \n                \"omitted\": false, \n                \"seconds\": 0.9999759793281555, \n                \"sender\": false, \n                \"start\": 8.000087\n            }\n        }, \n        {\n            \"streams\": [\n                {\n                    \"bits_per_second\": 851249428.1852835, \n                    \"bytes\": 106406280, \n                    \"end\": 10.000064, \n                    \"omitted\": false, \n                    \"seconds\": 1.0000009536743164, \n                    \"sender\": false, \n                    \"socket\": 5, \n                    \"start\": 9.000063\n                }\n            ], \n            \"sum\": {\n                \"bits_per_second\": 851249428.1852835, \n                \"bytes\": 106406280, \n                \"end\": 10.000064, \n                \"omitted\": false, \n                \"seconds\": 1.0000009536743164, \n                \"sender\": false, \n                \"start\": 9.000063\n            }\n        }, \n        {\n            \"streams\": [\n                {\n                    \"bits_per_second\": 851247703.084152, \n                    \"bytes\": 106406280, \n                    \"end\": 11.000067, \n                    \"omitted\": false, \n                    \"seconds\": 1.0000029802322388, \n                    \"sender\": false, \n                    \"socket\": 5, \n                    \"start\": 10.000064\n                }\n            ], \n            \"sum\": {\n                \"bits_per_second\": 851247703.084152, \n                \"bytes\": 106406280, \n                \"end\": 11.000067, \n                \"omitted\": false, \n                \"seconds\": 1.0000029802322388, \n                \"sender\": false, \n                \"start\": 10.000064\n            }\n        }, \n        {\n            \"streams\": [\n                {\n                    \"bits_per_second\": 851253639.4909433, \n                    \"bytes\": 106406280, \n                    \"end\": 12.000063, \n                    \"omitted\": false, \n                    \"seconds\": 0.9999960064888, \n                    \"sender\": false, \n                    \"socket\": 5, \n                    \"start\": 11.000067\n                }\n            ], \n            \"sum\": {\n                \"bits_per_second\": 851253639.4909433, \n                \"bytes\": 106406280, \n                \"end\": 12.000063, \n                \"omitted\": false, \n                \"seconds\": 0.9999960064888, \n                \"sender\": false, \n                \"start\": 11.000067\n            }\n        }, \n        {\n            \"streams\": [\n                {\n                    \"bits_per_second\": 851250240, \n                    \"bytes\": 106406280, \n                    \"end\": 13.000063, \n                    \"omitted\": false, \n                    \"seconds\": 1, \n                    \"sender\": false, \n                    \"socket\": 5, \n                    \"start\": 12.000063\n                }\n            ], \n            \"sum\": {\n                \"bits_per_second\": 851250240, \n                \"bytes\": 106406280, \n                \"end\": 13.000063, \n                \"omitted\": false, \n                \"seconds\": 1, \n                \"sender\": false, \n                \"start\": 12.000063\n            }\n        }, \n        {\n            \"streams\": [\n                {\n                    \"bits_per_second\": 851247703.084152, \n                    \"bytes\": 106406280, \n                    \"end\": 14.000066, \n                    \"omitted\": false, \n                    \"seconds\": 1.0000029802322388, \n                    \"sender\": false, \n                    \"socket\": 5, \n                    \"start\": 13.000063\n                }\n            ], \n            \"sum\": {\n                \"bits_per_second\": 851247703.084152, \n                \"bytes\": 106406280, \n                \"end\": 14.000066, \n                \"omitted\": false, \n                \"seconds\": 1.0000029802322388, \n                \"sender\": false, \n                \"start\": 13.000063\n            }\n        }, \n        {\n            \"streams\": [\n                {\n                    \"bits_per_second\": 851223856.814283, \n                    \"bytes\": 106406280, \n                    \"end\": 15.000097, \n                    \"omitted\": false, \n                    \"seconds\": 1.0000309944152832, \n                    \"sender\": false, \n                    \"socket\": 5, \n                    \"start\": 14.000066\n                }\n            ], \n            \"sum\": {\n                \"bits_per_second\": 851223856.814283, \n                \"bytes\": 106406280, \n                \"end\": 15.000097, \n                \"omitted\": false, \n                \"seconds\": 1.0000309944152832, \n                \"sender\": false, \n                \"start\": 14.000066\n            }\n        }, \n        {\n            \"streams\": [\n                {\n                    \"bits_per_second\": 850741738.4560972, \n                    \"bytes\": 106341120, \n                    \"end\": 16.000082, \n                    \"omitted\": false, \n                    \"seconds\": 0.9999849796295166, \n                    \"sender\": false, \n                    \"socket\": 5, \n                    \"start\": 15.000097\n                }\n            ], \n            \"sum\": {\n                \"bits_per_second\": 850741738.4560972, \n                \"bytes\": 106341120, \n                \"end\": 16.000082, \n                \"omitted\": false, \n                \"seconds\": 0.9999849796295166, \n                \"sender\": false, \n                \"start\": 15.000097\n            }\n        }, \n        {\n            \"streams\": [\n                {\n                    \"bits_per_second\": 851247703.084152, \n                    \"bytes\": 106406280, \n                    \"end\": 17.000085, \n                    \"omitted\": false, \n                    \"seconds\": 1.0000029802322388, \n                    \"sender\": false, \n                    \"socket\": 5, \n                    \"start\": 16.000082\n                }\n            ], \n            \"sum\": {\n                \"bits_per_second\": 851247703.084152, \n                \"bytes\": 106406280, \n                \"end\": 17.000085, \n                \"omitted\": false, \n                \"seconds\": 1.0000029802322388, \n                \"sender\": false, \n                \"start\": 16.000082\n            }\n        }, \n        {\n            \"streams\": [\n                {\n                    \"bits_per_second\": 851251102.554833, \n                    \"bytes\": 106406280, \n                    \"end\": 18.000084, \n                    \"omitted\": false, \n                    \"seconds\": 0.9999989867210388, \n                    \"sender\": false, \n                    \"socket\": 5, \n                    \"start\": 17.000085\n                }\n            ], \n            \"sum\": {\n                \"bits_per_second\": 851251102.554833, \n                \"bytes\": 106406280, \n                \"end\": 18.000084, \n                \"omitted\": false, \n                \"seconds\": 0.9999989867210388, \n                \"sender\": false, \n                \"start\": 17.000085\n            }\n        }, \n        {\n            \"streams\": [\n                {\n                    \"bits_per_second\": 851251102.554833, \n                    \"bytes\": 106406280, \n                    \"end\": 19.000083, \n                    \"omitted\": false, \n                    \"seconds\": 0.9999989867210388, \n                    \"sender\": false, \n                    \"socket\": 5, \n                    \"start\": 18.000084\n                }\n            ], \n            \"sum\": {\n                \"bits_per_second\": 851251102.554833, \n                \"bytes\": 106406280, \n                \"end\": 19.000083, \n                \"omitted\": false, \n                \"seconds\": 0.9999989867210388, \n                \"sender\": false, \n                \"start\": 18.000084\n            }\n        }, \n        {\n            \"streams\": [\n                {\n                    \"bits_per_second\": 851245166.1834253, \n                    \"bytes\": 106406280, \n                    \"end\": 20.000089, \n                    \"omitted\": false, \n                    \"seconds\": 1.0000059604644775, \n                    \"sender\": false, \n                    \"socket\": 5, \n                    \"start\": 19.000083\n                }\n            ], \n            \"sum\": {\n                \"bits_per_second\": 851245166.1834253, \n                \"bytes\": 106406280, \n                \"end\": 20.000089, \n                \"omitted\": false, \n                \"seconds\": 1.0000059604644775, \n                \"sender\": false, \n                \"start\": 19.000083\n            }\n        }, \n        {\n            \"streams\": [\n                {\n                    \"bits_per_second\": 851273225.146701, \n                    \"bytes\": 106406280, \n                    \"end\": 21.000062, \n                    \"omitted\": false, \n                    \"seconds\": 0.9999729990959167, \n                    \"sender\": false, \n                    \"socket\": 5, \n                    \"start\": 20.000089\n                }\n            ], \n            \"sum\": {\n                \"bits_per_second\": 851273225.146701, \n                \"bytes\": 106406280, \n                \"end\": 21.000062, \n                \"omitted\": false, \n                \"seconds\": 0.9999729990959167, \n                \"sender\": false, \n                \"start\": 20.000089\n            }\n        }, \n        {\n            \"streams\": [\n                {\n                    \"bits_per_second\": 851249428.1852835, \n                    \"bytes\": 106406280, \n                    \"end\": 22.000063, \n                    \"omitted\": false, \n                    \"seconds\": 1.0000009536743164, \n                    \"sender\": false, \n                    \"socket\": 5, \n                    \"start\": 21.000062\n                }\n            ], \n            \"sum\": {\n                \"bits_per_second\": 851249428.1852835, \n                \"bytes\": 106406280, \n                \"end\": 22.000063, \n                \"omitted\": false, \n                \"seconds\": 1.0000009536743164, \n                \"sender\": false, \n                \"start\": 21.000062\n            }\n        }, \n        {\n            \"streams\": [\n                {\n                    \"bits_per_second\": 851249428.1852835, \n                    \"bytes\": 106406280, \n                    \"end\": 23.000064, \n                    \"omitted\": false, \n                    \"seconds\": 1.0000009536743164, \n                    \"sender\": false, \n                    \"socket\": 5, \n                    \"start\": 22.000063\n                }\n            ], \n            \"sum\": {\n                \"bits_per_second\": 851249428.1852835, \n                \"bytes\": 106406280, \n                \"end\": 23.000064, \n                \"omitted\": false, \n                \"seconds\": 1.0000009536743164, \n                \"sender\": false, \n                \"start\": 22.000063\n            }\n        }, \n        {\n            \"streams\": [\n                {\n                    \"bits_per_second\": 851285149.4976696, \n                    \"bytes\": 106406280, \n                    \"end\": 24.000023, \n                    \"omitted\": false, \n                    \"seconds\": 0.9999589920043945, \n                    \"sender\": false, \n                    \"socket\": 5, \n                    \"start\": 23.000064\n                }\n            ], \n            \"sum\": {\n                \"bits_per_second\": 851285149.4976696, \n                \"bytes\": 106406280, \n                \"end\": 24.000023, \n                \"omitted\": false, \n                \"seconds\": 0.9999589920043945, \n                \"sender\": false, \n                \"start\": 23.000064\n            }\n        }, \n        {\n            \"streams\": [\n                {\n                    \"bits_per_second\": 851194938.6625706, \n                    \"bytes\": 106406280, \n                    \"end\": 25.000088, \n                    \"omitted\": false, \n                    \"seconds\": 1.0000649690628052, \n                    \"sender\": false, \n                    \"socket\": 5, \n                    \"start\": 24.000023\n                }\n            ], \n            \"sum\": {\n                \"bits_per_second\": 851194938.6625706, \n                \"bytes\": 106406280, \n                \"end\": 25.000088, \n                \"omitted\": false, \n                \"seconds\": 1.0000649690628052, \n                \"sender\": false, \n                \"start\": 24.000023\n            }\n        }, \n        {\n            \"streams\": [\n                {\n                    \"bits_per_second\": 851224668.5802267, \n                    \"bytes\": 106406280, \n                    \"end\": 26.000118, \n                    \"omitted\": false, \n                    \"seconds\": 1.0000300407409668, \n                    \"sender\": false, \n                    \"socket\": 5, \n                    \"start\": 25.000088\n                }\n            ], \n            \"sum\": {\n                \"bits_per_second\": 851224668.5802267, \n                \"bytes\": 106406280, \n                \"end\": 26.000118, \n                \"omitted\": false, \n                \"seconds\": 1.0000300407409668, \n                \"sender\": false, \n                \"start\": 25.000088\n            }\n        }, \n        {\n            \"streams\": [\n                {\n                    \"bits_per_second\": 850757052.825846, \n                    \"bytes\": 106341120, \n                    \"end\": 27.000085, \n                    \"omitted\": false, \n                    \"seconds\": 0.9999669790267944, \n                    \"sender\": false, \n                    \"socket\": 5, \n                    \"start\": 26.000118\n                }\n            ], \n            \"sum\": {\n                \"bits_per_second\": 850757052.825846, \n                \"bytes\": 106341120, \n                \"end\": 27.000085, \n                \"omitted\": false, \n                \"seconds\": 0.9999669790267944, \n                \"sender\": false, \n                \"start\": 26.000118\n            }\n        }, \n        {\n            \"streams\": [\n                {\n                    \"bits_per_second\": 851251102.554833, \n                    \"bytes\": 106406280, \n                    \"end\": 28.000084, \n                    \"omitted\": false, \n                    \"seconds\": 0.9999989867210388, \n                    \"sender\": false, \n                    \"socket\": 5, \n                    \"start\": 27.000085\n                }\n            ], \n            \"sum\": {\n                \"bits_per_second\": 851251102.554833, \n                \"bytes\": 106406280, \n                \"end\": 28.000084, \n                \"omitted\": false, \n                \"seconds\": 0.9999989867210388, \n                \"sender\": false, \n                \"start\": 27.000085\n            }\n        }, \n        {\n            \"streams\": [\n                {\n                    \"bits_per_second\": 851253639.4909433, \n                    \"bytes\": 106406280, \n                    \"end\": 29.00008, \n                    \"omitted\": false, \n                    \"seconds\": 0.9999960064888, \n                    \"sender\": false, \n                    \"socket\": 5, \n                    \"start\": 28.000084\n                }\n            ], \n            \"sum\": {\n                \"bits_per_second\": 851253639.4909433, \n                \"bytes\": 106406280, \n                \"end\": 29.00008, \n                \"omitted\": false, \n                \"seconds\": 0.9999960064888, \n                \"sender\": false, \n                \"start\": 28.000084\n            }\n        }, \n        {\n            \"streams\": [\n                {\n                    \"bits_per_second\": 851247703.084152, \n                    \"bytes\": 106406280, \n                    \"end\": 30.000083, \n                    \"omitted\": false, \n                    \"seconds\": 1.0000029802322388, \n                    \"sender\": false, \n                    \"socket\": 5, \n                    \"start\": 29.00008\n                }\n            ], \n            \"sum\": {\n                \"bits_per_second\": 851247703.084152, \n                \"bytes\": 106406280, \n                \"end\": 30.000083, \n                \"omitted\": false, \n                \"seconds\": 1.0000029802322388, \n                \"sender\": false, \n                \"start\": 29.00008\n            }\n        }, \n        {\n            \"streams\": [\n                {\n                    \"bits_per_second\": 851267288.4667375, \n                    \"bytes\": 106406280, \n                    \"end\": 31.000063, \n                    \"omitted\": false, \n                    \"seconds\": 0.9999799728393555, \n                    \"sender\": false, \n                    \"socket\": 5, \n                    \"start\": 30.000083\n                }\n            ], \n            \"sum\": {\n                \"bits_per_second\": 851267288.4667375, \n                \"bytes\": 106406280, \n                \"end\": 31.000063, \n                \"omitted\": false, \n                \"seconds\": 0.9999799728393555, \n                \"sender\": false, \n                \"start\": 30.000083\n            }\n        }, \n        {\n            \"streams\": [\n                {\n                    \"bits_per_second\": 851251102.554833, \n                    \"bytes\": 106406280, \n                    \"end\": 32.000062, \n                    \"omitted\": false, \n                    \"seconds\": 0.9999989867210388, \n                    \"sender\": false, \n                    \"socket\": 5, \n                    \"start\": 31.000063\n                }\n            ], \n            \"sum\": {\n                \"bits_per_second\": 851251102.554833, \n                \"bytes\": 106406280, \n                \"end\": 32.000062, \n                \"omitted\": false, \n                \"seconds\": 0.9999989867210388, \n                \"sender\": false, \n                \"start\": 31.000063\n            }\n        }, \n        {\n            \"streams\": [\n                {\n                    \"bits_per_second\": 851249428.1852835, \n                    \"bytes\": 106406280, \n                    \"end\": 33.000063, \n                    \"omitted\": false, \n                    \"seconds\": 1.0000009536743164, \n                    \"sender\": false, \n                    \"socket\": 5, \n                    \"start\": 32.000062\n                }\n            ], \n            \"sum\": {\n                \"bits_per_second\": 851249428.1852835, \n                \"bytes\": 106406280, \n                \"end\": 33.000063, \n                \"omitted\": false, \n                \"seconds\": 1.0000009536743164, \n                \"sender\": false, \n                \"start\": 32.000062\n            }\n        }, \n        {\n            \"streams\": [\n                {\n                    \"bits_per_second\": 851249428.1852835, \n                    \"bytes\": 106406280, \n                    \"end\": 34.000064, \n                    \"omitted\": false, \n                    \"seconds\": 1.0000009536743164, \n                    \"sender\": false, \n                    \"socket\": 5, \n                    \"start\": 33.000063\n                }\n            ], \n            \"sum\": {\n                \"bits_per_second\": 851249428.1852835, \n                \"bytes\": 106406280, \n                \"end\": 34.000064, \n                \"omitted\": false, \n                \"seconds\": 1.0000009536743164, \n                \"sender\": false, \n                \"start\": 33.000063\n            }\n        }, \n        {\n            \"streams\": [\n                {\n                    \"bits_per_second\": 851251102.554833, \n                    \"bytes\": 106406280, \n                    \"end\": 35.000063, \n                    \"omitted\": false, \n                    \"seconds\": 0.9999989867210388, \n                    \"sender\": false, \n                    \"socket\": 5, \n                    \"start\": 34.000064\n                }\n            ], \n            \"sum\": {\n                \"bits_per_second\": 851251102.554833, \n                \"bytes\": 106406280, \n                \"end\": 35.000063, \n                \"omitted\": false, \n                \"seconds\": 0.9999989867210388, \n                \"sender\": false, \n                \"start\": 34.000064\n            }\n        }, \n        {\n            \"streams\": [\n                {\n                    \"bits_per_second\": 851238367.3640416, \n                    \"bytes\": 106406280, \n                    \"end\": 36.000077, \n                    \"omitted\": false, \n                    \"seconds\": 1.0000139474868774, \n                    \"sender\": false, \n                    \"socket\": 5, \n                    \"start\": 35.000063\n                }\n            ], \n            \"sum\": {\n                \"bits_per_second\": 851238367.3640416, \n                \"bytes\": 106406280, \n                \"end\": 36.000077, \n                \"omitted\": false, \n                \"seconds\": 1.0000139474868774, \n                \"sender\": false, \n                \"start\": 35.000063\n            }\n        }, \n        {\n            \"streams\": [\n                {\n                    \"bits_per_second\": 850720441.24253, \n                    \"bytes\": 106341120, \n                    \"end\": 37.000087, \n                    \"omitted\": false, \n                    \"seconds\": 1.0000100135803223, \n                    \"sender\": false, \n                    \"socket\": 5, \n                    \"start\": 36.000077\n                }\n            ], \n            \"sum\": {\n                \"bits_per_second\": 850720441.24253, \n                \"bytes\": 106341120, \n                \"end\": 37.000087, \n                \"omitted\": false, \n                \"seconds\": 1.0000100135803223, \n                \"sender\": false, \n                \"start\": 36.000077\n            }\n        }, \n        {\n            \"streams\": [\n                {\n                    \"bits_per_second\": 851254502.0526655, \n                    \"bytes\": 106406280, \n                    \"end\": 38.000082, \n                    \"omitted\": false, \n                    \"seconds\": 0.999994993209839, \n                    \"sender\": false, \n                    \"socket\": 5, \n                    \"start\": 37.000087\n                }\n            ], \n            \"sum\": {\n                \"bits_per_second\": 851254502.0526655, \n                \"bytes\": 106406280, \n                \"end\": 38.000082, \n                \"omitted\": false, \n                \"seconds\": 0.999994993209839, \n                \"sender\": false, \n                \"start\": 37.000087\n            }\n        }, \n        {\n            \"streams\": [\n                {\n                    \"bits_per_second\": 851248514.8955783, \n                    \"bytes\": 106406280, \n                    \"end\": 39.000084, \n                    \"omitted\": false, \n                    \"seconds\": 1.0000020265579224, \n                    \"sender\": false, \n                    \"socket\": 5, \n                    \"start\": 38.000082\n                }\n            ], \n            \"sum\": {\n                \"bits_per_second\": 851248514.8955783, \n                \"bytes\": 106406280, \n                \"end\": 39.000084, \n                \"omitted\": false, \n                \"seconds\": 1.0000020265579224, \n                \"sender\": false, \n                \"start\": 38.000082\n            }\n        }, \n        {\n            \"streams\": [\n                {\n                    \"bits_per_second\": 851251102.554833, \n                    \"bytes\": 106406280, \n                    \"end\": 40.000083, \n                    \"omitted\": false, \n                    \"seconds\": 0.9999989867210388, \n                    \"sender\": false, \n                    \"socket\": 5, \n                    \"start\": 39.000084\n                }\n            ], \n            \"sum\": {\n                \"bits_per_second\": 851251102.554833, \n                \"bytes\": 106406280, \n                \"end\": 40.000083, \n                \"omitted\": false, \n                \"seconds\": 0.9999989867210388, \n                \"sender\": false, \n                \"start\": 39.000084\n            }\n        }, \n        {\n            \"streams\": [\n                {\n                    \"bits_per_second\": 851249428.1852835, \n                    \"bytes\": 106406280, \n                    \"end\": 41.000084, \n                    \"omitted\": false, \n                    \"seconds\": 1.0000009536743164, \n                    \"sender\": false, \n                    \"socket\": 5, \n                    \"start\": 40.000083\n                }\n            ], \n            \"sum\": {\n                \"bits_per_second\": 851249428.1852835, \n                \"bytes\": 106406280, \n                \"end\": 41.000084, \n                \"omitted\": false, \n                \"seconds\": 1.0000009536743164, \n                \"sender\": false, \n                \"start\": 40.000083\n            }\n        }, \n        {\n            \"streams\": [\n                {\n                    \"bits_per_second\": 851268962.9065485, \n                    \"bytes\": 106406280, \n                    \"end\": 42.000062, \n                    \"omitted\": false, \n                    \"seconds\": 0.999978005886078, \n                    \"sender\": false, \n                    \"socket\": 5, \n                    \"start\": 41.000084\n                }\n            ], \n            \"sum\": {\n                \"bits_per_second\": 851268962.9065485, \n                \"bytes\": 106406280, \n                \"end\": 42.000062, \n                \"omitted\": false, \n                \"seconds\": 0.999978005886078, \n                \"sender\": false, \n                \"start\": 41.000084\n            }\n        }, \n        {\n            \"streams\": [\n                {\n                    \"bits_per_second\": 851249428.1852835, \n                    \"bytes\": 106406280, \n                    \"end\": 43.000063, \n                    \"omitted\": false, \n                    \"seconds\": 1.0000009536743164, \n                    \"sender\": false, \n                    \"socket\": 5, \n                    \"start\": 42.000062\n                }\n            ], \n            \"sum\": {\n                \"bits_per_second\": 851249428.1852835, \n                \"bytes\": 106406280, \n                \"end\": 43.000063, \n                \"omitted\": false, \n                \"seconds\": 1.0000009536743164, \n                \"sender\": false, \n                \"start\": 42.000062\n            }\n        }, \n        {\n            \"streams\": [\n                {\n                    \"bits_per_second\": 851250240, \n                    \"bytes\": 106406280, \n                    \"end\": 44.000063, \n                    \"omitted\": false, \n                    \"seconds\": 1, \n                    \"sender\": false, \n                    \"socket\": 5, \n                    \"start\": 43.000063\n                }\n            ], \n            \"sum\": {\n                \"bits_per_second\": 851250240, \n                \"bytes\": 106406280, \n                \"end\": 44.000063, \n                \"omitted\": false, \n                \"seconds\": 1, \n                \"sender\": false, \n                \"start\": 43.000063\n            }\n        }, \n        {\n            \"streams\": [\n                {\n                    \"bits_per_second\": 851249428.1852835, \n                    \"bytes\": 106406280, \n                    \"end\": 45.000064, \n                    \"omitted\": false, \n                    \"seconds\": 1.0000009536743164, \n                    \"sender\": false, \n                    \"socket\": 5, \n                    \"start\": 44.000063\n                }\n            ], \n            \"sum\": {\n                \"bits_per_second\": 851249428.1852835, \n                \"bytes\": 106406280, \n                \"end\": 45.000064, \n                \"omitted\": false, \n                \"seconds\": 1.0000009536743164, \n                \"sender\": false, \n                \"start\": 44.000063\n            }\n        }, \n        {\n            \"streams\": [\n                {\n                    \"bits_per_second\": 851291086.4267596, \n                    \"bytes\": 106406280, \n                    \"end\": 46.000016, \n                    \"omitted\": false, \n                    \"seconds\": 0.9999520182609558, \n                    \"sender\": false, \n                    \"socket\": 5, \n                    \"start\": 45.000064\n                }\n            ], \n            \"sum\": {\n                \"bits_per_second\": 851291086.4267596, \n                \"bytes\": 106406280, \n                \"end\": 46.000016, \n                \"omitted\": false, \n                \"seconds\": 0.9999520182609558, \n                \"sender\": false, \n                \"start\": 45.000064\n            }\n        }, \n        {\n            \"streams\": [\n                {\n                    \"bits_per_second\": 851190677.2063255, \n                    \"bytes\": 106406280, \n                    \"end\": 47.000086, \n                    \"omitted\": false, \n                    \"seconds\": 1.0000699758529663, \n                    \"sender\": false, \n                    \"socket\": 5, \n                    \"start\": 46.000016\n                }\n            ], \n            \"sum\": {\n                \"bits_per_second\": 851190677.2063255, \n                \"bytes\": 106406280, \n                \"end\": 47.000086, \n                \"omitted\": false, \n                \"seconds\": 1.0000699758529663, \n                \"sender\": false, \n                \"start\": 46.000016\n            }\n        }, \n        {\n            \"streams\": [\n                {\n                    \"bits_per_second\": 850731495.377429, \n                    \"bytes\": 106341120, \n                    \"end\": 48.000083, \n                    \"omitted\": false, \n                    \"seconds\": 0.9999970197677612, \n                    \"sender\": false, \n                    \"socket\": 5, \n                    \"start\": 47.000086\n                }\n            ], \n            \"sum\": {\n                \"bits_per_second\": 850731495.377429, \n                \"bytes\": 106341120, \n                \"end\": 48.000083, \n                \"omitted\": false, \n                \"seconds\": 0.9999970197677612, \n                \"sender\": false, \n                \"start\": 47.000086\n            }\n        }, \n        {\n            \"streams\": [\n                {\n                    \"bits_per_second\": 851248514.8955783, \n                    \"bytes\": 106406280, \n                    \"end\": 49.000085, \n                    \"omitted\": false, \n                    \"seconds\": 1.0000020265579224, \n                    \"sender\": false, \n                    \"socket\": 5, \n                    \"start\": 48.000083\n                }\n            ], \n            \"sum\": {\n                \"bits_per_second\": 851248514.8955783, \n                \"bytes\": 106406280, \n                \"end\": 49.000085, \n                \"omitted\": false, \n                \"seconds\": 1.0000020265579224, \n                \"sender\": false, \n                \"start\": 48.000083\n            }\n        }, \n        {\n            \"streams\": [\n                {\n                    \"bits_per_second\": 851251965.111414, \n                    \"bytes\": 106406280, \n                    \"end\": 50.000083, \n                    \"omitted\": false, \n                    \"seconds\": 0.9999979734420776, \n                    \"sender\": false, \n                    \"socket\": 5, \n                    \"start\": 49.000085\n                }\n            ], \n            \"sum\": {\n                \"bits_per_second\": 851251965.111414, \n                \"bytes\": 106406280, \n                \"end\": 50.000083, \n                \"omitted\": false, \n                \"seconds\": 0.9999979734420776, \n                \"sender\": false, \n                \"start\": 49.000085\n            }\n        }, \n        {\n            \"streams\": [\n                {\n                    \"bits_per_second\": 851265563.293216, \n                    \"bytes\": 106406280, \n                    \"end\": 51.000065, \n                    \"omitted\": false, \n                    \"seconds\": 0.9999819993972778, \n                    \"sender\": false, \n                    \"socket\": 5, \n                    \"start\": 50.000083\n                }\n            ], \n            \"sum\": {\n                \"bits_per_second\": 851265563.293216, \n                \"bytes\": 106406280, \n                \"end\": 51.000065, \n                \"omitted\": false, \n                \"seconds\": 0.9999819993972778, \n                \"sender\": false, \n                \"start\": 50.000083\n            }\n        }, \n        {\n            \"streams\": [\n                {\n                    \"bits_per_second\": 851237454.09807, \n                    \"bytes\": 106406280, \n                    \"end\": 52.00008, \n                    \"omitted\": false, \n                    \"seconds\": 1.0000150203704834, \n                    \"sender\": false, \n                    \"socket\": 5, \n                    \"start\": 51.000065\n                }\n            ], \n            \"sum\": {\n                \"bits_per_second\": 851237454.09807, \n                \"bytes\": 106406280, \n                \"end\": 52.00008, \n                \"omitted\": false, \n                \"seconds\": 1.0000150203704834, \n                \"sender\": false, \n                \"start\": 51.000065\n            }\n        }, \n        {\n            \"streams\": [\n                {\n                    \"bits_per_second\": 851247703.084152, \n                    \"bytes\": 106406280, \n                    \"end\": 53.000083, \n                    \"omitted\": false, \n                    \"seconds\": 1.0000029802322388, \n                    \"sender\": false, \n                    \"socket\": 5, \n                    \"start\": 52.00008\n                }\n            ], \n            \"sum\": {\n                \"bits_per_second\": 851247703.084152, \n                \"bytes\": 106406280, \n                \"end\": 53.000083, \n                \"omitted\": false, \n                \"seconds\": 1.0000029802322388, \n                \"sender\": false, \n                \"start\": 52.00008\n            }\n        }, \n        {\n            \"streams\": [\n                {\n                    \"bits_per_second\": 851266425.8791027, \n                    \"bytes\": 106406280, \n                    \"end\": 54.000064, \n                    \"omitted\": false, \n                    \"seconds\": 0.9999809861183167, \n                    \"sender\": false, \n                    \"socket\": 5, \n                    \"start\": 53.000083\n                }\n            ], \n            \"sum\": {\n                \"bits_per_second\": 851266425.8791027, \n                \"bytes\": 106406280, \n                \"end\": 54.000064, \n                \"omitted\": false, \n                \"seconds\": 0.9999809861183167, \n                \"sender\": false, \n                \"start\": 53.000083\n            }\n        }, \n        {\n            \"streams\": [\n                {\n                    \"bits_per_second\": 851251102.554833, \n                    \"bytes\": 106406280, \n                    \"end\": 55.000063, \n                    \"omitted\": false, \n                    \"seconds\": 0.9999989867210388, \n                    \"sender\": false, \n                    \"socket\": 5, \n                    \"start\": 54.000064\n                }\n            ], \n            \"sum\": {\n                \"bits_per_second\": 851251102.554833, \n                \"bytes\": 106406280, \n                \"end\": 55.000063, \n                \"omitted\": false, \n                \"seconds\": 0.9999989867210388, \n                \"sender\": false, \n                \"start\": 54.000064\n            }\n        }, \n        {\n            \"streams\": [\n                {\n                    \"bits_per_second\": 851250240, \n                    \"bytes\": 106406280, \n                    \"end\": 56.000063, \n                    \"omitted\": false, \n                    \"seconds\": 1, \n                    \"sender\": false, \n                    \"socket\": 5, \n                    \"start\": 55.000063\n                }\n            ], \n            \"sum\": {\n                \"bits_per_second\": 851250240, \n                \"bytes\": 106406280, \n                \"end\": 56.000063, \n                \"omitted\": false, \n                \"seconds\": 1, \n                \"sender\": false, \n                \"start\": 55.000063\n            }\n        }, \n        {\n            \"streams\": [\n                {\n                    \"bits_per_second\": 851295348.888457, \n                    \"bytes\": 106406280, \n                    \"end\": 57.00001, \n                    \"omitted\": false, \n                    \"seconds\": 0.9999470114707947, \n                    \"sender\": false, \n                    \"socket\": 5, \n                    \"start\": 56.000063\n                }\n            ], \n            \"sum\": {\n                \"bits_per_second\": 851295348.888457, \n                \"bytes\": 106406280, \n                \"end\": 57.00001, \n                \"omitted\": false, \n                \"seconds\": 0.9999470114707947, \n                \"sender\": false, \n                \"start\": 56.000063\n            }\n        }, \n        {\n            \"streams\": [\n                {\n                    \"bits_per_second\": 851201736.7882413, \n                    \"bytes\": 106406280, \n                    \"end\": 58.000067, \n                    \"omitted\": false, \n                    \"seconds\": 1.0000569820404053, \n                    \"sender\": false, \n                    \"socket\": 5, \n                    \"start\": 57.00001\n                }\n            ], \n            \"sum\": {\n                \"bits_per_second\": 851201736.7882413, \n                \"bytes\": 106406280, \n                \"end\": 58.000067, \n                \"omitted\": false, \n                \"seconds\": 1.0000569820404053, \n                \"sender\": false, \n                \"start\": 57.00001\n            }\n        }, \n        {\n            \"streams\": [\n                {\n                    \"bits_per_second\": 850714457.931542, \n                    \"bytes\": 106341120, \n                    \"end\": 59.000084, \n                    \"omitted\": false, \n                    \"seconds\": 1.0000170469284058, \n                    \"sender\": false, \n                    \"socket\": 5, \n                    \"start\": 58.000067\n                }\n            ], \n            \"sum\": {\n                \"bits_per_second\": 850714457.931542, \n                \"bytes\": 106341120, \n                \"end\": 59.000084, \n                \"omitted\": false, \n                \"seconds\": 1.0000170469284058, \n                \"sender\": false, \n                \"start\": 58.000067\n            }\n        }, \n        {\n            \"streams\": [\n                {\n                    \"bits_per_second\": 851248514.8955783, \n                    \"bytes\": 106406280, \n                    \"end\": 60.000086, \n                    \"omitted\": false, \n                    \"seconds\": 1.0000020265579224, \n                    \"sender\": false, \n                    \"socket\": 5, \n                    \"start\": 59.000084\n                }\n            ], \n            \"sum\": {\n                \"bits_per_second\": 851248514.8955783, \n                \"bytes\": 106406280, \n                \"end\": 60.000086, \n                \"omitted\": false, \n                \"seconds\": 1.0000020265579224, \n                \"sender\": false, \n                \"start\": 59.000084\n            }\n        }, \n        {\n            \"streams\": [\n                {\n                    \"bits_per_second\": 850722141.4942977, \n                    \"bytes\": 8340480, \n                    \"end\": 60.078518, \n                    \"omitted\": false, \n                    \"seconds\": 0.07843200117349625, \n                    \"sender\": false, \n                    \"socket\": 5, \n                    \"start\": 60.000086\n                }\n            ], \n            \"sum\": {\n                \"bits_per_second\": 850722141.4942977, \n                \"bytes\": 8340480, \n                \"end\": 60.078518, \n                \"omitted\": false, \n                \"seconds\": 0.07843200117349625, \n                \"sender\": false, \n                \"start\": 60.000086\n            }\n        }\n    ], \n    \"start\": {\n        \"accepted_connection\": {\n            \"host\": \"10.0.0.1\", \n            \"port\": 54387\n        }, \n        \"connected\": [\n            {\n                \"local_host\": \"10.0.0.2\", \n                \"local_port\": 5201, \n                \"remote_host\": \"10.0.0.1\", \n                \"remote_port\": 49789, \n                \"socket\": 5\n            }\n        ], \n        \"cookie\": \"ldbki7qirkd2yh3s44meju6htwatad62sw5w\", \n        \"fq_rate\": 0, \n        \"rcvbuf_actual\": 87380, \n        \"sndbuf_actual\": 87380, \n        \"sock_bufsize\": 0, \n        \"system_info\": \"REDACTED\", \n        \"target_bitrate\": 0, \n        \"tcp_mss_default\": 0, \n        \"test_start\": {\n            \"bidir\": 0, \n            \"blksize\": 131072, \n            \"blocks\": 0, \n            \"bytes\": 0, \n            \"duration\": 60, \n            \"fqrate\": 0, \n            \"num_streams\": 1, \n            \"omit\": 0, \n            \"protocol\": \"TCP\", \n            \"reverse\": 0, \n            \"target_bitrate\": 0, \n            \"tos\": 0\n        }, \n        \"timestamp\": {\n            \"time\": \"Tue, 16 Apr 2024 23:05:47 GMT\", \n            \"timesecs\": 1713308747\n        }, \n        \"version\": \"iperf 3.14\"\n    }\n}\n","summary":{"streams":[{"end":60.000175,"rtt":78384,"start":0,"stream-id":5,"retransmits":0,"throughput-bits":852682039.9440502,"throughput-bytes":6395133952}],"summary":{"end":60.000175,"start":0,"retransmits":0,"throughput-bits":852682039.9440502,"throughput-bytes":6395133952,"receiver-throughput-bits":851127244.650076}},"intervals":[{"streams":[{"end":1.000082,"rtt":78389,"start":0,"omitted":false,"stream-id":5,"retransmits":0,"tcp-window-size":16698336,"throughput-bits":944689496.35457,"throughput-bytes":118095872}],"summary":{"end":1.000082,"start":0,"omitted":false,"retransmits":0,"throughput-bits":944689496.35457,"throughput-bytes":118095872}},{"streams":[{"end":2.00015,"rtt":78383,"start":1.000082,"omitted":false,"stream-id":5,"retransmits":0,"tcp-window-size":16698336,"throughput-bits":849288851.4212573,"throughput-bytes":106168320}],"summary":{"end":2.00015,"start":1.000082,"omitted":false,"retransmits":0,"throughput-bits":849288851.4212573,"throughput-bytes":106168320}},{"streams":[{"end":3.000148,"rtt":78385,"start":2.00015,"omitted":false,"stream-id":5,"retransmits":0,"tcp-window-size":16698336,"throughput-bits":849348281.2534882,"throughput-bytes":106168320}],"summary":{"end":3.000148,"start":2.00015,"omitted":false,"retransmits":0,"throughput-bits":849348281.2534882,"throughput-bytes":106168320}},{"streams":[{"end":4.000151,"rtt":78378,"start":3.000148,"omitted":false,"stream-id":5,"retransmits":0,"tcp-window-size":16698336,"throughput-bits":849344028.7575437,"throughput-bytes":106168320}],"summary":{"end":4.000151,"start":3.000148,"omitted":false,"retransmits":0,"throughput-bits":849344028.7575437,"throughput-bytes":106168320}},{"streams":[{"end":5.000081,"rtt":78383,"start":4.000151,"omitted":false,"stream-id":5,"retransmits":0,"tcp-window-size":16698336,"throughput-bits":849405997.9092184,"throughput-bytes":106168320}],"summary":{"end":5.000081,"start":4.000151,"omitted":false,"retransmits":0,"throughput-bits":849405997.9092184,"throughput-bytes":106168320}},{"streams":[{"end":6.000078,"rtt":78389,"start":5.000081,"omitted":false,"stream-id":5,"retransmits":0,"tcp-window-size":16698336,"throughput-bits":849349091.2575437,"throughput-bytes":106168320}],"summary":{"end":6.000078,"start":5.000081,"omitted":false,"retransmits":0,"throughput-bits":849349091.2575437,"throughput-bytes":106168320}},{"streams":[{"end":7.000081,"rtt":78387,"start":6.000078,"omitted":false,"stream-id":5,"retransmits":0,"tcp-window-size":16698336,"throughput-bits":859829757.5076368,"throughput-bytes":107479040}],"summary":{"end":7.000081,"start":6.000078,"omitted":false,"retransmits":0,"throughput-bits":859829757.5076368,"throughput-bytes":107479040}},{"streams":[{"end":8.000062,"rtt":78391,"start":7.000081,"omitted":false,"stream-id":5,"retransmits":0,"tcp-window-size":16698336,"throughput-bits":849362709.682068,"throughput-bytes":106168320}],"summary":{"end":8.000062,"start":7.000081,"omitted":false,"retransmits":0,"throughput-bits":849362709.682068,"throughput-bytes":106168320}},{"streams":[{"end":9.000155,"rtt":78386,"start":8.000062,"omitted":false,"stream-id":5,"retransmits":0,"tcp-window-size":16698336,"throughput-bits":849267592.342669,"throughput-bytes":106168320}],"summary":{"end":9.000155,"start":8.000062,"omitted":false,"retransmits":0,"throughput-bits":849267592.342669,"throughput-bytes":106168320}},{"streams":[{"end":10.000156,"rtt":78386,"start":9.000155,"omitted":false,"stream-id":5,"retransmits":0,"tcp-window-size":16698336,"throughput-bits":849345750.0007725,"throughput-bytes":106168320}],"summary":{"end":10.000156,"start":9.000155,"omitted":false,"retransmits":0,"throughput-bits":849345750.0007725,"throughput-bytes":106168320}},{"streams":[{"end":11.000083,"rtt":78374,"start":10.000156,"omitted":false,"stream-id":5,"retransmits":0,"tcp-window-size":16698336,"throughput-bits":849408580.1534443,"throughput-bytes":106168320}],"summary":{"end":11.000083,"start":10.000156,"omitted":false,"retransmits":0,"throughput-bits":849408580.1534443,"throughput-bytes":106168320}},{"streams":[{"end":12.000277,"rtt":78380,"start":11.000083,"omitted":false,"stream-id":5,"retransmits":0,"tcp-window-size":16698336,"throughput-bits":859665584.8388704,"throughput-bytes":107479040}],"summary":{"end":12.000277,"start":11.000083,"omitted":false,"retransmits":0,"throughput-bits":859665584.8388704,"throughput-bytes":107479040}},{"streams":[{"end":13.000079,"rtt":78381,"start":12.000277,"omitted":false,"stream-id":5,"retransmits":0,"tcp-window-size":16698336,"throughput-bits":849514769.5566075,"throughput-bytes":106168320}],"summary":{"end":13.000079,"start":12.000277,"omitted":false,"retransmits":0,"throughput-bits":849514769.5566075,"throughput-bytes":106168320}},{"streams":[{"end":14.000156,"rtt":78383,"start":13.000079,"omitted":false,"stream-id":5,"retransmits":0,"tcp-window-size":16698336,"throughput-bits":849281157.5365914,"throughput-bytes":106168320}],"summary":{"end":14.000156,"start":13.000079,"omitted":false,"retransmits":0,"throughput-bits":849281157.5365914,"throughput-bytes":106168320}},{"streams":[{"end":15.000089,"rtt":78390,"start":14.000156,"omitted":false,"stream-id":5,"retransmits":0,"tcp-window-size":16698336,"throughput-bits":849403466.3124738,"throughput-bytes":106168320}],"summary":{"end":15.000089,"start":14.000156,"omitted":false,"retransmits":0,"throughput-bits":849403466.3124738,"throughput-bytes":106168320}},{"streams":[{"end":16.000083,"rtt":78382,"start":15.000089,"omitted":false,"stream-id":5,"retransmits":0,"tcp-window-size":16698336,"throughput-bits":849351673.1557815,"throughput-bytes":106168320}],"summary":{"end":16.000083,"start":15.000089,"omitted":false,"retransmits":0,"throughput-bits":849351673.1557815,"throughput-bytes":106168320}},{"streams":[{"end":17.000063,"rtt":78386,"start":16.000083,"omitted":false,"stream-id":5,"retransmits":0,"tcp-window-size":16698336,"throughput-bits":849363570.3406688,"throughput-bytes":106168320}],"summary":{"end":17.000063,"start":16.000083,"omitted":false,"retransmits":0,"throughput-bits":849363570.3406688,"throughput-bytes":106168320}},{"streams":[{"end":18.000065,"rtt":78385,"start":17.000063,"omitted":false,"stream-id":5,"retransmits":0,"tcp-window-size":16698336,"throughput-bits":859830577.5035312,"throughput-bytes":107479040}],"summary":{"end":18.000065,"start":17.000063,"omitted":false,"retransmits":0,"throughput-bits":859830577.5035312,"throughput-bytes":107479040}},{"streams":[{"end":19.000156,"rtt":78379,"start":18.000065,"omitted":false,"stream-id":5,"retransmits":0,"tcp-window-size":16698336,"throughput-bits":849269313.276106,"throughput-bytes":106168320}],"summary":{"end":19.000156,"start":18.000065,"omitted":false,"retransmits":0,"throughput-bits":849269313.276106,"throughput-bytes":106168320}},{"streams":[{"end":20.000063,"rtt":78386,"start":19.000156,"omitted":false,"stream-id":5,"retransmits":0,"tcp-window-size":16698336,"throughput-bits":849425542.3440347,"throughput-bytes":106168320}],"summary":{"end":20.000063,"start":19.000156,"omitted":false,"retransmits":0,"throughput-bits":849425542.3440347,"throughput-bytes":106168320}},{"streams":[{"end":21.000064,"rtt":78383,"start":20.000063,"omitted":false,"stream-id":5,"retransmits":0,"tcp-window-size":16698336,"throughput-bits":849345750.0007725,"throughput-bytes":106168320}],"summary":{"end":21.000064,"start":20.000063,"omitted":false,"retransmits":0,"throughput-bits":849345750.0007725,"throughput-bytes":106168320}},{"streams":[{"end":22.000082,"rtt":78386,"start":21.000064,"omitted":false,"stream-id":5,"retransmits":0,"tcp-window-size":16698336,"throughput-bits":849331271.5252018,"throughput-bytes":106168320}],"summary":{"end":22.000082,"start":21.000064,"omitted":false,"retransmits":0,"throughput-bits":849331271.5252018,"throughput-bytes":106168320}},{"streams":[{"end":23.000063,"rtt":78385,"start":22.000082,"omitted":false,"stream-id":5,"retransmits":0,"tcp-window-size":16698336,"throughput-bits":849362709.682068,"throughput-bytes":106168320}],"summary":{"end":23.000063,"start":22.000082,"omitted":false,"retransmits":0,"throughput-bits":849362709.682068,"throughput-bytes":106168320}},{"streams":[{"end":24.000061,"rtt":78379,"start":23.000063,"omitted":false,"stream-id":5,"retransmits":0,"tcp-window-size":16698336,"throughput-bits":859834062.5035313,"throughput-bytes":107479040}],"summary":{"end":24.000061,"start":23.000063,"omitted":false,"retransmits":0,"throughput-bits":859834062.5035313,"throughput-bytes":107479040}},{"streams":[{"end":25.00015,"rtt":78380,"start":24.000061,"omitted":false,"stream-id":5,"retransmits":0,"tcp-window-size":16698336,"throughput-bits":849270932.9845358,"throughput-bytes":106168320}],"summary":{"end":25.00015,"start":24.000061,"omitted":false,"retransmits":0,"throughput-bits":849270932.9845358,"throughput-bytes":106168320}},{"streams":[{"end":26.000166,"rtt":78386,"start":25.00015,"omitted":false,"stream-id":5,"retransmits":0,"tcp-window-size":16698336,"throughput-bits":849332992.7167244,"throughput-bytes":106168320}],"summary":{"end":26.000166,"start":25.00015,"omitted":false,"retransmits":0,"throughput-bits":849332992.7167244,"throughput-bytes":106168320}},{"streams":[{"end":27.000083,"rtt":78385,"start":26.000166,"omitted":false,"stream-id":5,"retransmits":0,"tcp-window-size":16698336,"throughput-bits":849417086.4807622,"throughput-bytes":106168320}],"summary":{"end":27.000083,"start":26.000166,"omitted":false,"retransmits":0,"throughput-bits":849417086.4807622,"throughput-bytes":106168320}},{"streams":[{"end":28.000086,"rtt":78386,"start":27.000083,"omitted":false,"stream-id":5,"retransmits":0,"tcp-window-size":16698336,"throughput-bits":849344028.7575437,"throughput-bytes":106168320}],"summary":{"end":28.000086,"start":27.000083,"omitted":false,"retransmits":0,"throughput-bits":849344028.7575437,"throughput-bytes":106168320}},{"streams":[{"end":29.000067,"rtt":78384,"start":28.000086,"omitted":false,"stream-id":5,"retransmits":0,"tcp-window-size":16698336,"throughput-bits":849362709.682068,"throughput-bytes":106168320}],"summary":{"end":29.000067,"start":28.000086,"omitted":false,"retransmits":0,"throughput-bits":849362709.682068,"throughput-bytes":106168320}},{"streams":[{"end":30.000089,"rtt":78387,"start":29.000067,"omitted":false,"stream-id":5,"retransmits":0,"tcp-window-size":16698336,"throughput-bits":859813357.9181844,"throughput-bytes":107479040}],"summary":{"end":30.000089,"start":29.000067,"omitted":false,"retransmits":0,"throughput-bits":859813357.9181844,"throughput-bytes":107479040}},{"streams":[{"end":31.000078,"rtt":78384,"start":30.000089,"omitted":false,"stream-id":5,"retransmits":0,"tcp-window-size":16698336,"throughput-bits":849355925.7282746,"throughput-bytes":106168320}],"summary":{"end":31.000078,"start":30.000089,"omitted":false,"retransmits":0,"throughput-bits":849355925.7282746,"throughput-bytes":106168320}},{"streams":[{"end":32.000085,"rtt":78385,"start":31.000078,"omitted":false,"stream-id":5,"retransmits":0,"tcp-window-size":16698336,"throughput-bits":849340586.2920152,"throughput-bytes":106168320}],"summary":{"end":32.000085,"start":31.000078,"omitted":false,"retransmits":0,"throughput-bits":849340586.2920152,"throughput-bytes":106168320}},{"streams":[{"end":33.000151,"rtt":78384,"start":32.000085,"omitted":false,"stream-id":5,"retransmits":0,"tcp-window-size":16698336,"throughput-bits":849290471.2042133,"throughput-bytes":106168320}],"summary":{"end":33.000151,"start":32.000085,"omitted":false,"retransmits":0,"throughput-bits":849290471.2042133,"throughput-bytes":106168320}},{"streams":[{"end":34.000063,"rtt":78380,"start":33.000151,"omitted":false,"stream-id":5,"retransmits":0,"tcp-window-size":16698336,"throughput-bits":849421289.074399,"throughput-bytes":106168320}],"summary":{"end":34.000063,"start":33.000151,"omitted":false,"retransmits":0,"throughput-bits":849421289.074399,"throughput-bytes":106168320}},{"streams":[{"end":35.000081,"rtt":78385,"start":34.000063,"omitted":false,"stream-id":5,"retransmits":0,"tcp-window-size":16698336,"throughput-bits":859816842.7785993,"throughput-bytes":107479040}],"summary":{"end":35.000081,"start":34.000063,"omitted":false,"retransmits":0,"throughput-bits":859816842.7785993,"throughput-bytes":107479040}},{"streams":[{"end":36.000157,"rtt":78380,"start":35.000081,"omitted":false,"stream-id":5,"retransmits":0,"tcp-window-size":16698336,"throughput-bits":849281967.4126233,"throughput-bytes":106168320}],"summary":{"end":36.000157,"start":35.000081,"omitted":false,"retransmits":0,"throughput-bits":849281967.4126233,"throughput-bytes":106168320}},{"streams":[{"end":37.000098,"rtt":78381,"start":36.000157,"omitted":false,"stream-id":5,"retransmits":0,"tcp-window-size":16698336,"throughput-bits":849396681.7076117,"throughput-bytes":106168320}],"summary":{"end":37.000098,"start":36.000157,"omitted":false,"retransmits":0,"throughput-bits":849396681.7076117,"throughput-bytes":106168320}},{"streams":[{"end":38.000084,"rtt":78380,"start":37.000098,"omitted":false,"stream-id":5,"retransmits":0,"tcp-window-size":16698336,"throughput-bits":849358457.041643,"throughput-bytes":106168320}],"summary":{"end":38.000084,"start":37.000098,"omitted":false,"retransmits":0,"throughput-bits":849358457.041643,"throughput-bytes":106168320}},{"streams":[{"end":39.000064,"rtt":78391,"start":38.000084,"omitted":false,"stream-id":5,"retransmits":0,"tcp-window-size":16698336,"throughput-bits":849363570.3406688,"throughput-bytes":106168320}],"summary":{"end":39.000064,"start":38.000084,"omitted":false,"retransmits":0,"throughput-bits":849363570.3406688,"throughput-bytes":106168320}},{"streams":[{"end":40.000063,"rtt":78385,"start":39.000064,"omitted":false,"stream-id":5,"retransmits":0,"tcp-window-size":16698336,"throughput-bits":849347420.625872,"throughput-bytes":106168320}],"summary":{"end":40.000063,"start":39.000064,"omitted":false,"retransmits":0,"throughput-bits":849347420.625872,"throughput-bytes":106168320}},{"streams":[{"end":41.000178,"rtt":78382,"start":40.000063,"omitted":false,"stream-id":5,"retransmits":0,"tcp-window-size":16698336,"throughput-bits":859733418.877285,"throughput-bytes":107479040}],"summary":{"end":41.000178,"start":40.000063,"omitted":false,"retransmits":0,"throughput-bits":859733418.877285,"throughput-bytes":107479040}},{"streams":[{"end":42.000155,"rtt":78385,"start":41.000178,"omitted":false,"stream-id":5,"retransmits":0,"tcp-window-size":16698336,"throughput-bits":849366101.6996036,"throughput-bytes":106168320}],"summary":{"end":42.000155,"start":41.000178,"omitted":false,"retransmits":0,"throughput-bits":849366101.6996036,"throughput-bytes":106168320}},{"streams":[{"end":43.000152,"rtt":78387,"start":42.000155,"omitted":false,"stream-id":5,"retransmits":0,"tcp-window-size":16698336,"throughput-bits":849349091.2575437,"throughput-bytes":106168320}],"summary":{"end":43.000152,"start":42.000155,"omitted":false,"retransmits":0,"throughput-bits":849349091.2575437,"throughput-bytes":106168320}},{"streams":[{"end":44.000068,"rtt":78386,"start":43.000152,"omitted":false,"stream-id":5,"retransmits":0,"tcp-window-size":16698336,"throughput-bits":849417896.616059,"throughput-bytes":106168320}],"summary":{"end":44.000068,"start":43.000152,"omitted":false,"retransmits":0,"throughput-bits":849417896.616059,"throughput-bytes":106168320}},{"streams":[{"end":45.000074,"rtt":78382,"start":44.000068,"omitted":false,"stream-id":5,"retransmits":0,"tcp-window-size":16698336,"throughput-bits":849341497.5301746,"throughput-bytes":106168320}],"summary":{"end":45.000074,"start":44.000068,"omitted":false,"retransmits":0,"throughput-bits":849341497.5301746,"throughput-bytes":106168320}},{"streams":[{"end":46.000354,"rtt":78386,"start":45.000074,"omitted":false,"stream-id":5,"retransmits":0,"tcp-window-size":16698336,"throughput-bits":859591614.9028722,"throughput-bytes":107479040}],"summary":{"end":46.000354,"start":45.000074,"omitted":false,"retransmits":0,"throughput-bits":859591614.9028722,"throughput-bytes":107479040}},{"streams":[{"end":47.000036,"rtt":78386,"start":46.000354,"omitted":false,"stream-id":5,"retransmits":0,"tcp-window-size":16698336,"throughput-bits":849616730.2866602,"throughput-bytes":106168320}],"summary":{"end":47.000036,"start":46.000354,"omitted":false,"retransmits":0,"throughput-bits":849616730.2866602,"throughput-bytes":106168320}},{"streams":[{"end":48.000092,"rtt":78385,"start":47.000036,"omitted":false,"stream-id":5,"retransmits":0,"tcp-window-size":16698336,"throughput-bits":849298975.1661005,"throughput-bytes":106168320}],"summary":{"end":48.000092,"start":47.000036,"omitted":false,"retransmits":0,"throughput-bits":849298975.1661005,"throughput-bytes":106168320}},{"streams":[{"end":49.000081,"rtt":78386,"start":48.000092,"omitted":false,"stream-id":5,"retransmits":0,"tcp-window-size":16698336,"throughput-bits":849355925.7282746,"throughput-bytes":106168320}],"summary":{"end":49.000081,"start":48.000092,"omitted":false,"retransmits":0,"throughput-bits":849355925.7282746,"throughput-bytes":106168320}},{"streams":[{"end":50.000081,"rtt":78388,"start":49.000081,"omitted":false,"stream-id":5,"retransmits":0,"tcp-window-size":16698336,"throughput-bits":849346560,"throughput-bytes":106168320}],"summary":{"end":50.000081,"start":49.000081,"omitted":false,"retransmits":0,"throughput-bits":849346560,"throughput-bytes":106168320}},{"streams":[{"end":51.00016,"rtt":78391,"start":50.000081,"omitted":false,"stream-id":5,"retransmits":0,"tcp-window-size":16698336,"throughput-bits":849279436.5551524,"throughput-bytes":106168320}],"summary":{"end":51.00016,"start":50.000081,"omitted":false,"retransmits":0,"throughput-bits":849279436.5551524,"throughput-bytes":106168320}},{"streams":[{"end":52.000087,"rtt":78394,"start":51.00016,"omitted":false,"stream-id":5,"retransmits":0,"tcp-window-size":16698336,"throughput-bits":859895105.834351,"throughput-bytes":107479040}],"summary":{"end":52.000087,"start":51.00016,"omitted":false,"retransmits":0,"throughput-bits":859895105.834351,"throughput-bytes":107479040}},{"streams":[{"end":53.000092,"rtt":78381,"start":52.000087,"omitted":false,"stream-id":5,"retransmits":0,"tcp-window-size":16698336,"throughput-bits":849342307.5212913,"throughput-bytes":106168320}],"summary":{"end":53.000092,"start":52.000087,"omitted":false,"retransmits":0,"throughput-bits":849342307.5212913,"throughput-bytes":106168320}},{"streams":[{"end":54.000061,"rtt":78386,"start":53.000092,"omitted":false,"stream-id":5,"retransmits":0,"tcp-window-size":16698336,"throughput-bits":849372885.8159533,"throughput-bytes":106168320}],"summary":{"end":54.000061,"start":53.000092,"omitted":false,"retransmits":0,"throughput-bits":849372885.8159533,"throughput-bytes":106168320}},{"streams":[{"end":55.000156,"rtt":78389,"start":54.000061,"omitted":false,"stream-id":5,"retransmits":0,"tcp-window-size":16698336,"throughput-bits":849265871.4162065,"throughput-bytes":106168320}],"summary":{"end":55.000156,"start":54.000061,"omitted":false,"retransmits":0,"throughput-bits":849265871.4162065,"throughput-bytes":106168320}},{"streams":[{"end":56.000063,"rtt":78385,"start":55.000156,"omitted":false,"stream-id":5,"retransmits":0,"tcp-window-size":16698336,"throughput-bits":849425542.3440347,"throughput-bytes":106168320}],"summary":{"end":56.000063,"start":55.000156,"omitted":false,"retransmits":0,"throughput-bits":849425542.3440347,"throughput-bytes":106168320}},{"streams":[{"end":57.000062,"rtt":78378,"start":56.000063,"omitted":false,"stream-id":5,"retransmits":0,"tcp-window-size":16698336,"throughput-bits":849347420.625872,"throughput-bytes":106168320}],"summary":{"end":57.000062,"start":56.000063,"omitted":false,"retransmits":0,"throughput-bits":849347420.625872,"throughput-bytes":106168320}},{"streams":[{"end":58.000037,"rtt":78386,"start":57.000062,"omitted":false,"stream-id":5,"retransmits":0,"tcp-window-size":16698336,"throughput-bits":859853794.2863063,"throughput-bytes":107479040}],"summary":{"end":58.000037,"start":57.000062,"omitted":false,"retransmits":0,"throughput-bits":859853794.2863063,"throughput-bytes":107479040}},{"streams":[{"end":59.000102,"rtt":78383,"start":58.000037,"omitted":false,"stream-id":5,"retransmits":0,"tcp-window-size":16698336,"throughput-bits":849291382.3348413,"throughput-bytes":106168320}],"summary":{"end":59.000102,"start":58.000037,"omitted":false,"retransmits":0,"throughput-bits":849291382.3348413,"throughput-bytes":106168320}},{"streams":[{"end":60.000175,"rtt":78388,"start":59.000102,"omitted":false,"stream-id":5,"retransmits":0,"tcp-window-size":16698336,"throughput-bits":849284599.520394,"throughput-bytes":106168320}],"summary":{"end":60.000175,"start":59.000102,"omitted":false,"retransmits":0,"throughput-bits":849284599.520394,"throughput-bytes":106168320}}],"succeeded":true}
