{"diags":"Participant 0:\n/usr/bin/iperf3 -p 5201 -B 172.16.0.2 -c 172.16.0.1 -t 60 --json --rsa-public-key-path /var/run/pscheduler-server/runner/tmp/tmp87j9wo3r/tmp7rn5yr10/public-key --username 5Q5UJ5YkDRSEE7LyP7xY\n\n{\n    \"end\": {\n        \"cpu_utilization_percent\": {\n            \"host_system\": 0.047373028943320065, \n            \"host_total\": 0.064459065548369, \n            \"host_user\": 0.017084372758851166, \n            \"remote_system\": 1.2682929820150872, \n            \"remote_total\": 1.4113074372265142, \n            \"remote_user\": 0.14301945356138848\n        }, \n        \"receiver_tcp_congestion\": \"htcp\", \n        \"sender_tcp_congestion\": \"htcp\", \n        \"streams\": [\n            {\n                \"receiver\": {\n                    \"bits_per_second\": 6072353.230326443, \n                    \"bytes\": 45557632, \n                    \"end\": 60.019739, \n                    \"seconds\": 60.000695, \n                    \"sender\": true, \n                    \"socket\": 5, \n                    \"start\": 0\n                }, \n                \"sender\": {\n                    \"bits_per_second\": 6588476.2168171555, \n                    \"bytes\": 49414144, \n                    \"end\": 60.000695, \n                    \"max_rtt\": 249721, \n                    \"max_snd_cwnd\": 353312, \n                    \"max_snd_wnd\": 0, \n                    \"mean_rtt\": 108251, \n                    \"min_rtt\": 16376, \n                    \"retransmits\": 909, \n                    \"seconds\": 60.000695, \n                    \"sender\": true, \n                    \"socket\": 5, \n                    \"start\": 0\n                }\n            }\n        ], \n        \"sum_received\": {\n            \"bits_per_second\": 6072353.230326443, \n            \"bytes\": 45557632, \n            \"end\": 60.019739, \n            \"seconds\": 60.019739, \n            \"sender\": true, \n            \"start\": 0\n        }, \n        \"sum_sent\": {\n            \"bits_per_second\": 6588476.2168171555, \n            \"bytes\": 49414144, \n            \"end\": 60.000695, \n            \"retransmits\": 909, \n            \"seconds\": 60.000695, \n            \"sender\": true, \n            \"start\": 0\n        }\n    }, \n    \"intervals\": [\n        {\n            \"streams\": [\n                {\n                    \"bits_per_second\": 49272428.7990084, \n                    \"bytes\": 6160384, \n                    \"end\": 1.000216, \n                    \"omitted\": false, \n                    \"pmtu\": 1500, \n                    \"retransmits\": 281, \n                    \"rtt\": 73948, \n                    \"rttvar\": 485, \n                    \"seconds\": 1.000216007232666, \n                    \"sender\": true, \n                    \"snd_cwnd\": 202720, \n                    \"snd_wnd\": -1, \n                    \"socket\": 5, \n                    \"start\": 0\n                }\n            ], \n            \"sum\": {\n                \"bits_per_second\": 49272428.7990084, \n                \"bytes\": 6160384, \n                \"end\": 1.000216, \n                \"omitted\": false, \n                \"retransmits\": 281, \n                \"seconds\": 1.000216007232666, \n                \"sender\": true, \n                \"start\": 0\n            }\n        }, \n        {\n            \"streams\": [\n                {\n                    \"bits_per_second\": 20968792.85468525, \n                    \"bytes\": 2621440, \n                    \"end\": 2.000346, \n                    \"omitted\": false, \n                    \"pmtu\": 1500, \n                    \"retransmits\": 0, \n                    \"rtt\": 80229, \n                    \"rttvar\": 497, \n                    \"seconds\": 1.0001300573349, \n                    \"sender\": true, \n                    \"snd_cwnd\": 221544, \n                    \"snd_wnd\": -1, \n                    \"socket\": 5, \n                    \"start\": 1.000216\n                }\n            ], \n            \"sum\": {\n                \"bits_per_second\": 20968792.85468525, \n                \"bytes\": 2621440, \n                \"end\": 2.000346, \n                \"omitted\": false, \n                \"retransmits\": 0, \n                \"seconds\": 1.0001300573349, \n                \"sender\": true, \n                \"start\": 1.000216\n            }\n        }, \n        {\n            \"streams\": [\n                {\n                    \"bits_per_second\": 20970912.517597463, \n                    \"bytes\": 2621440, \n                    \"end\": 3.000375, \n                    \"omitted\": false, \n                    \"pmtu\": 1500, \n                    \"retransmits\": 0, \n                    \"rtt\": 86812, \n                    \"rttvar\": 561, \n                    \"seconds\": 1.0000289678573608, \n                    \"sender\": true, \n                    \"snd_cwnd\": 237472, \n                    \"snd_wnd\": -1, \n                    \"socket\": 5, \n                    \"start\": 2.000346\n                }\n            ], \n            \"sum\": {\n                \"bits_per_second\": 20970912.517597463, \n                \"bytes\": 2621440, \n                \"end\": 3.000375, \n                \"omitted\": false, \n                \"retransmits\": 0, \n                \"seconds\": 1.0000289678573608, \n                \"sender\": true, \n                \"start\": 2.000346\n            }\n        }, \n        {\n            \"streams\": [\n                {\n                    \"bits_per_second\": 20970807.524206113, \n                    \"bytes\": 2621440, \n                    \"end\": 4.000409, \n                    \"omitted\": false, \n                    \"pmtu\": 1500, \n                    \"retransmits\": 0, \n                    \"rtt\": 95376, \n                    \"rttvar\": 381, \n                    \"seconds\": 1.000033974647522, \n                    \"sender\": true, \n                    \"snd_cwnd\": 262088, \n                    \"snd_wnd\": -1, \n                    \"socket\": 5, \n                    \"start\": 3.000375\n                }\n            ], \n            \"sum\": {\n                \"bits_per_second\": 20970807.524206113, \n                \"bytes\": 2621440, \n                \"end\": 4.000409, \n                \"omitted\": false, \n                \"retransmits\": 0, \n                \"seconds\": 1.000033974647522, \n                \"sender\": true, \n                \"start\": 3.000375\n            }\n        }, \n        {\n            \"streams\": [\n                {\n                    \"bits_per_second\": 20970745.028638974, \n                    \"bytes\": 2621440, \n                    \"end\": 5.000446, \n                    \"omitted\": false, \n                    \"pmtu\": 1500, \n                    \"retransmits\": 0, \n                    \"rtt\": 109616, \n                    \"rttvar\": 406, \n                    \"seconds\": 1.0000369548797607, \n                    \"sender\": true, \n                    \"snd_cwnd\": 304080, \n                    \"snd_wnd\": -1, \n                    \"socket\": 5, \n                    \"start\": 4.000409\n                }\n            ], \n            \"sum\": {\n                \"bits_per_second\": 20970745.028638974, \n                \"bytes\": 2621440, \n                \"end\": 5.000446, \n                \"omitted\": false, \n                \"retransmits\": 0, \n                \"seconds\": 1.0000369548797607, \n                \"sender\": true, \n                \"start\": 4.000409\n            }\n        }, \n        {\n            \"streams\": [\n                {\n                    \"bits_per_second\": 20971227.504079584, \n                    \"bytes\": 2621440, \n                    \"end\": 6.00046, \n                    \"omitted\": false, \n                    \"pmtu\": 1500, \n                    \"retransmits\": 0, \n                    \"rtt\": 127532, \n                    \"rttvar\": 1038, \n                    \"seconds\": 1.0000139474868774, \n                    \"sender\": true, \n                    \"snd_cwnd\": 353312, \n                    \"snd_wnd\": -1, \n                    \"socket\": 5, \n                    \"start\": 5.000446\n                }\n            ], \n            \"sum\": {\n                \"bits_per_second\": 20971227.504079584, \n                \"bytes\": 2621440, \n                \"end\": 6.00046, \n                \"omitted\": false, \n                \"retransmits\": 0, \n                \"seconds\": 1.0000139474868774, \n                \"sender\": true, \n                \"start\": 5.000446\n            }\n        }, \n        {\n            \"streams\": [\n                {\n                    \"bits_per_second\": 20971037.51110081, \n                    \"bytes\": 2621440, \n                    \"end\": 7.000483, \n                    \"omitted\": false, \n                    \"pmtu\": 1500, \n                    \"retransmits\": 3, \n                    \"rtt\": 147179, \n                    \"rttvar\": 392, \n                    \"seconds\": 1.0000230073928833, \n                    \"sender\": true, \n                    \"snd_cwnd\": 276568, \n                    \"snd_wnd\": -1, \n                    \"socket\": 5, \n                    \"start\": 6.00046\n                }\n            ], \n            \"sum\": {\n                \"bits_per_second\": 20971037.51110081, \n                \"bytes\": 2621440, \n                \"end\": 7.000483, \n                \"omitted\": false, \n                \"retransmits\": 3, \n                \"seconds\": 1.0000230073928833, \n                \"sender\": true, \n                \"start\": 6.00046\n            }\n        }, \n        {\n            \"streams\": [\n                {\n                    \"bits_per_second\": 31470402.972201914, \n                    \"bytes\": 3932160, \n                    \"end\": 8.000066, \n                    \"omitted\": false, \n                    \"pmtu\": 1500, \n                    \"retransmits\": 2, \n                    \"rtt\": 79984, \n                    \"rttvar\": 722, \n                    \"seconds\": 0.9995830059051514, \n                    \"sender\": true, \n                    \"snd_cwnd\": 220096, \n                    \"snd_wnd\": -1, \n                    \"socket\": 5, \n                    \"start\": 7.000483\n                }\n            ], \n            \"sum\": {\n                \"bits_per_second\": 31470402.972201914, \n                \"bytes\": 3932160, \n                \"end\": 8.000066, \n                \"omitted\": false, \n                \"retransmits\": 2, \n                \"seconds\": 0.9995830059051514, \n                \"sender\": true, \n                \"start\": 7.000483\n            }\n        }, \n        {\n            \"streams\": [\n                {\n                    \"bits_per_second\": 10480436.454099307, \n                    \"bytes\": 1310720, \n                    \"end\": 9.000574, \n                    \"omitted\": false, \n                    \"pmtu\": 1500, \n                    \"retransmits\": 0, \n                    \"rtt\": 85695, \n                    \"rttvar\": 337, \n                    \"seconds\": 1.0005079507827759, \n                    \"sender\": true, \n                    \"snd_cwnd\": 234576, \n                    \"snd_wnd\": -1, \n                    \"socket\": 5, \n                    \"start\": 8.000066\n                }\n            ], \n            \"sum\": {\n                \"bits_per_second\": 10480436.454099307, \n                \"bytes\": 1310720, \n                \"end\": 9.000574, \n                \"omitted\": false, \n                \"retransmits\": 0, \n                \"seconds\": 1.0005079507827759, \n                \"sender\": true, \n                \"start\": 8.000066\n            }\n        }, \n        {\n            \"streams\": [\n                {\n                    \"bits_per_second\": 0, \n                    \"bytes\": 0, \n                    \"end\": 10.00103, \n                    \"omitted\": false, \n                    \"pmtu\": 1500, \n                    \"retransmits\": 2, \n                    \"rtt\": 85695, \n                    \"rttvar\": 337, \n                    \"seconds\": 1.0004559755325317, \n                    \"sender\": true, \n                    \"snd_cwnd\": 1448, \n                    \"snd_wnd\": -1, \n                    \"socket\": 5, \n                    \"start\": 9.000574\n                }\n            ], \n            \"sum\": {\n                \"bits_per_second\": 0, \n                \"bytes\": 0, \n                \"end\": 10.00103, \n                \"omitted\": false, \n                \"retransmits\": 2, \n                \"seconds\": 1.0004559755325317, \n                \"sender\": true, \n                \"start\": 9.000574\n            }\n        }, \n        {\n            \"streams\": [\n                {\n                    \"bits_per_second\": 0, \n                    \"bytes\": 0, \n                    \"end\": 11.001017, \n                    \"omitted\": false, \n                    \"pmtu\": 1500, \n                    \"retransmits\": 0, \n                    \"rtt\": 85695, \n                    \"rttvar\": 337, \n                    \"seconds\": 0.999987006187439, \n                    \"sender\": true, \n                    \"snd_cwnd\": 1448, \n                    \"snd_wnd\": -1, \n                    \"socket\": 5, \n                    \"start\": 10.00103\n                }\n            ], \n            \"sum\": {\n                \"bits_per_second\": 0, \n                \"bytes\": 0, \n                \"end\": 11.001017, \n                \"omitted\": false, \n                \"retransmits\": 0, \n                \"seconds\": 0.999987006187439, \n                \"sender\": true, \n                \"start\": 10.00103\n            }\n        }, \n        {\n            \"streams\": [\n                {\n                    \"bits_per_second\": 0, \n                    \"bytes\": 0, \n                    \"end\": 12.001018, \n                    \"omitted\": false, \n                    \"pmtu\": 1500, \n                    \"retransmits\": 1, \n                    \"rtt\": 85695, \n                    \"rttvar\": 337, \n                    \"seconds\": 1.0000009536743164, \n                    \"sender\": true, \n                    \"snd_cwnd\": 1448, \n                    \"snd_wnd\": -1, \n                    \"socket\": 5, \n                    \"start\": 11.001017\n                }\n            ], \n            \"sum\": {\n                \"bits_per_second\": 0, \n                \"bytes\": 0, \n                \"end\": 12.001018, \n                \"omitted\": false, \n                \"retransmits\": 1, \n                \"seconds\": 1.0000009536743164, \n                \"sender\": true, \n                \"start\": 11.001017\n            }\n        }, \n        {\n            \"streams\": [\n                {\n                    \"bits_per_second\": 0, \n                    \"bytes\": 0, \n                    \"end\": 13.001018, \n                    \"omitted\": false, \n                    \"pmtu\": 1500, \n                    \"retransmits\": 0, \n                    \"rtt\": 85695, \n                    \"rttvar\": 337, \n                    \"seconds\": 1, \n                    \"sender\": true, \n                    \"snd_cwnd\": 1448, \n                    \"snd_wnd\": -1, \n                    \"socket\": 5, \n                    \"start\": 12.001018\n                }\n            ], \n            \"sum\": {\n                \"bits_per_second\": 0, \n                \"bytes\": 0, \n                \"end\": 13.001018, \n                \"omitted\": false, \n                \"retransmits\": 0, \n                \"seconds\": 1, \n                \"sender\": true, \n                \"start\": 12.001018\n            }\n        }, \n        {\n            \"streams\": [\n                {\n                    \"bits_per_second\": 10494733.2974262, \n                    \"bytes\": 1310720, \n                    \"end\": 14.000163, \n                    \"omitted\": false, \n                    \"pmtu\": 1500, \n                    \"retransmits\": 163, \n                    \"rtt\": 43791, \n                    \"rttvar\": 244, \n                    \"seconds\": 0.999144971370697, \n                    \"sender\": true, \n                    \"snd_cwnd\": 121632, \n                    \"snd_wnd\": -1, \n                    \"socket\": 5, \n                    \"start\": 13.001018\n                }\n            ], \n            \"sum\": {\n                \"bits_per_second\": 10494733.2974262, \n                \"bytes\": 1310720, \n                \"end\": 14.000163, \n                \"omitted\": false, \n                \"retransmits\": 163, \n                \"seconds\": 0.999144971370697, \n                \"sender\": true, \n                \"start\": 13.001018\n            }\n        }, \n        {\n            \"streams\": [\n                {\n                    \"bits_per_second\": 10482196.21163421, \n                    \"bytes\": 1310720, \n                    \"end\": 15.000503, \n                    \"omitted\": false, \n                    \"pmtu\": 1500, \n                    \"retransmits\": 33, \n                    \"rtt\": 33356, \n                    \"rttvar\": 548, \n                    \"seconds\": 1.0003399848937988, \n                    \"sender\": true, \n                    \"snd_cwnd\": 92672, \n                    \"snd_wnd\": -1, \n                    \"socket\": 5, \n                    \"start\": 14.000163\n                }\n            ], \n            \"sum\": {\n                \"bits_per_second\": 10482196.21163421, \n                \"bytes\": 1310720, \n                \"end\": 15.000503, \n                \"omitted\": false, \n                \"retransmits\": 33, \n                \"seconds\": 1.0003399848937988, \n                \"sender\": true, \n                \"start\": 14.000163\n            }\n        }, \n        {\n            \"streams\": [\n                {\n                    \"bits_per_second\": 10484082.768321622, \n                    \"bytes\": 1310720, \n                    \"end\": 16.000663, \n                    \"omitted\": false, \n                    \"pmtu\": 1500, \n                    \"retransmits\": 47, \n                    \"rtt\": 28922, \n                    \"rttvar\": 11246, \n                    \"seconds\": 1.0001599788665771, \n                    \"sender\": true, \n                    \"snd_cwnd\": 1448, \n                    \"snd_wnd\": -1, \n                    \"socket\": 5, \n                    \"start\": 15.000503\n                }\n            ], \n            \"sum\": {\n                \"bits_per_second\": 10484082.768321622, \n                \"bytes\": 1310720, \n                \"end\": 16.000663, \n                \"omitted\": false, \n                \"retransmits\": 47, \n                \"seconds\": 1.0001599788665771, \n                \"sender\": true, \n                \"start\": 15.000503\n            }\n        }, \n        {\n            \"streams\": [\n                {\n                    \"bits_per_second\": 0, \n                    \"bytes\": 0, \n                    \"end\": 17.001019, \n                    \"omitted\": false, \n                    \"pmtu\": 1500, \n                    \"retransmits\": 56, \n                    \"rtt\": 39034, \n                    \"rttvar\": 3032, \n                    \"seconds\": 1.0003559589385986, \n                    \"sender\": true, \n                    \"snd_cwnd\": 11584, \n                    \"snd_wnd\": -1, \n                    \"socket\": 5, \n                    \"start\": 16.000663\n                }\n            ], \n            \"sum\": {\n                \"bits_per_second\": 0, \n                \"bytes\": 0, \n                \"end\": 17.001019, \n                \"omitted\": false, \n                \"retransmits\": 56, \n                \"seconds\": 1.0003559589385986, \n                \"sender\": true, \n                \"start\": 16.000663\n            }\n        }, \n        {\n            \"streams\": [\n                {\n                    \"bits_per_second\": 10495752.012449672, \n                    \"bytes\": 1310720, \n                    \"end\": 18.000067, \n                    \"omitted\": false, \n                    \"pmtu\": 1500, \n                    \"retransmits\": 32, \n                    \"rtt\": 16376, \n                    \"rttvar\": 1781, \n                    \"seconds\": 0.9990479946136475, \n                    \"sender\": true, \n                    \"snd_cwnd\": 28960, \n                    \"snd_wnd\": -1, \n                    \"socket\": 5, \n                    \"start\": 17.001019\n                }\n            ], \n            \"sum\": {\n                \"bits_per_second\": 10495752.012449672, \n                \"bytes\": 1310720, \n                \"end\": 18.000067, \n                \"omitted\": false, \n                \"retransmits\": 32, \n                \"seconds\": 0.9990479946136475, \n                \"sender\": true, \n                \"start\": 17.001019\n            }\n        }, \n        {\n            \"streams\": [\n                {\n                    \"bits_per_second\": 10482458.539798005, \n                    \"bytes\": 1310720, \n                    \"end\": 19.000382, \n                    \"omitted\": false, \n                    \"pmtu\": 1500, \n                    \"retransmits\": 0, \n                    \"rtt\": 40851, \n                    \"rttvar\": 10926, \n                    \"seconds\": 1.0003149509429932, \n                    \"sender\": true, \n                    \"snd_cwnd\": 75296, \n                    \"snd_wnd\": -1, \n                    \"socket\": 5, \n                    \"start\": 18.000067\n                }\n            ], \n            \"sum\": {\n                \"bits_per_second\": 10482458.539798005, \n                \"bytes\": 1310720, \n                \"end\": 19.000382, \n                \"omitted\": false, \n                \"retransmits\": 0, \n                \"seconds\": 1.0003149509429932, \n                \"sender\": true, \n                \"start\": 18.000067\n            }\n        }, \n        {\n            \"streams\": [\n                {\n                    \"bits_per_second\": 10485676.250668908, \n                    \"bytes\": 1310720, \n                    \"end\": 20.00039, \n                    \"omitted\": false, \n                    \"pmtu\": 1500, \n                    \"retransmits\": 46, \n                    \"rtt\": 33796, \n                    \"rttvar\": 544, \n                    \"seconds\": 1.0000079870224, \n                    \"sender\": true, \n                    \"snd_cwnd\": 72400, \n                    \"snd_wnd\": -1, \n                    \"socket\": 5, \n                    \"start\": 19.000382\n                }\n            ], \n            \"sum\": {\n                \"bits_per_second\": 10485676.250668908, \n                \"bytes\": 1310720, \n                \"end\": 20.00039, \n                \"omitted\": false, \n                \"retransmits\": 46, \n                \"seconds\": 1.0000079870224, \n                \"sender\": true, \n                \"start\": 19.000382\n            }\n        }, \n        {\n            \"streams\": [\n                {\n                    \"bits_per_second\": 10482048.813951321, \n                    \"bytes\": 1310720, \n                    \"end\": 21.000744, \n                    \"omitted\": false, \n                    \"pmtu\": 1500, \n                    \"retransmits\": 17, \n                    \"rtt\": 249721, \n                    \"rttvar\": 267786, \n                    \"seconds\": 1.0003540515899658, \n                    \"sender\": true, \n                    \"snd_cwnd\": 23168, \n                    \"snd_wnd\": -1, \n                    \"socket\": 5, \n                    \"start\": 20.00039\n                }\n            ], \n            \"sum\": {\n                \"bits_per_second\": 10482048.813951321, \n                \"bytes\": 1310720, \n                \"end\": 21.000744, \n                \"omitted\": false, \n                \"retransmits\": 17, \n                \"seconds\": 1.0003540515899658, \n                \"sender\": true, \n                \"start\": 20.00039\n            }\n        }, \n        {\n            \"streams\": [\n                {\n                    \"bits_per_second\": 0, \n                    \"bytes\": 0, \n                    \"end\": 22.001019, \n                    \"omitted\": false, \n                    \"pmtu\": 1500, \n                    \"retransmits\": 36, \n                    \"rtt\": 186018, \n                    \"rttvar\": 193748, \n                    \"seconds\": 1.0002750158309937, \n                    \"sender\": true, \n                    \"snd_cwnd\": 5792, \n                    \"snd_wnd\": -1, \n                    \"socket\": 5, \n                    \"start\": 21.000744\n                }\n            ], \n            \"sum\": {\n                \"bits_per_second\": 0, \n                \"bytes\": 0, \n                \"end\": 22.001019, \n                \"omitted\": false, \n                \"retransmits\": 36, \n                \"seconds\": 1.0002750158309937, \n                \"sender\": true, \n                \"start\": 21.000744\n            }\n        }, \n        {\n            \"streams\": [\n                {\n                    \"bits_per_second\": 0, \n                    \"bytes\": 0, \n                    \"end\": 23.001042, \n                    \"omitted\": false, \n                    \"pmtu\": 1500, \n                    \"retransmits\": 0, \n                    \"rtt\": 186018, \n                    \"rttvar\": 193748, \n                    \"seconds\": 1.0000230073928833, \n                    \"sender\": true, \n                    \"snd_cwnd\": 5792, \n                    \"snd_wnd\": -1, \n                    \"socket\": 5, \n                    \"start\": 22.001019\n                }\n            ], \n            \"sum\": {\n                \"bits_per_second\": 0, \n                \"bytes\": 0, \n                \"end\": 23.001042, \n                \"omitted\": false, \n                \"retransmits\": 0, \n                \"seconds\": 1.0000230073928833, \n                \"sender\": true, \n                \"start\": 22.001019\n            }\n        }, \n        {\n            \"streams\": [\n                {\n                    \"bits_per_second\": 0, \n                    \"bytes\": 0, \n                    \"end\": 24.001021, \n                    \"omitted\": false, \n                    \"pmtu\": 1500, \n                    \"retransmits\": 1, \n                    \"rtt\": 186018, \n                    \"rttvar\": 193748, \n                    \"seconds\": 0.999979019165039, \n                    \"sender\": true, \n                    \"snd_cwnd\": 1448, \n                    \"snd_wnd\": -1, \n                    \"socket\": 5, \n                    \"start\": 23.001042\n                }\n            ], \n            \"sum\": {\n                \"bits_per_second\": 0, \n                \"bytes\": 0, \n                \"end\": 24.001021, \n                \"omitted\": false, \n                \"retransmits\": 1, \n                \"seconds\": 0.999979019165039, \n                \"sender\": true, \n                \"start\": 23.001042\n            }\n        }, \n        {\n            \"streams\": [\n                {\n                    \"bits_per_second\": 0, \n                    \"bytes\": 0, \n                    \"end\": 25.001018, \n                    \"omitted\": false, \n                    \"pmtu\": 1500, \n                    \"retransmits\": 0, \n                    \"rtt\": 186018, \n                    \"rttvar\": 193748, \n                    \"seconds\": 0.9999970197677612, \n                    \"sender\": true, \n                    \"snd_cwnd\": 1448, \n                    \"snd_wnd\": -1, \n                    \"socket\": 5, \n                    \"start\": 24.001021\n                }\n            ], \n            \"sum\": {\n                \"bits_per_second\": 0, \n                \"bytes\": 0, \n                \"end\": 25.001018, \n                \"omitted\": false, \n                \"retransmits\": 0, \n                \"seconds\": 0.9999970197677612, \n                \"sender\": true, \n                \"start\": 24.001021\n            }\n        }, \n        {\n            \"streams\": [\n                {\n                    \"bits_per_second\": 0, \n                    \"bytes\": 0, \n                    \"end\": 26.001019, \n                    \"omitted\": false, \n                    \"pmtu\": 1500, \n                    \"retransmits\": 0, \n                    \"rtt\": 186018, \n                    \"rttvar\": 193748, \n                    \"seconds\": 1.0000009536743164, \n                    \"sender\": true, \n                    \"snd_cwnd\": 1448, \n                    \"snd_wnd\": -1, \n                    \"socket\": 5, \n                    \"start\": 25.001018\n                }\n            ], \n            \"sum\": {\n                \"bits_per_second\": 0, \n                \"bytes\": 0, \n                \"end\": 26.001019, \n                \"omitted\": false, \n                \"retransmits\": 0, \n                \"seconds\": 1.0000009536743164, \n                \"sender\": true, \n                \"start\": 25.001018\n            }\n        }, \n        {\n            \"streams\": [\n                {\n                    \"bits_per_second\": 0, \n                    \"bytes\": 0, \n                    \"end\": 27.001018, \n                    \"omitted\": false, \n                    \"pmtu\": 1500, \n                    \"retransmits\": 1, \n                    \"rtt\": 186018, \n                    \"rttvar\": 193748, \n                    \"seconds\": 0.9999989867210388, \n                    \"sender\": true, \n                    \"snd_cwnd\": 1448, \n                    \"snd_wnd\": -1, \n                    \"socket\": 5, \n                    \"start\": 26.001019\n                }\n            ], \n            \"sum\": {\n                \"bits_per_second\": 0, \n                \"bytes\": 0, \n                \"end\": 27.001018, \n                \"omitted\": false, \n                \"retransmits\": 1, \n                \"seconds\": 0.9999989867210388, \n                \"sender\": true, \n                \"start\": 26.001019\n            }\n        }, \n        {\n            \"streams\": [\n                {\n                    \"bits_per_second\": 0, \n                    \"bytes\": 0, \n                    \"end\": 28.001019, \n                    \"omitted\": false, \n                    \"pmtu\": 1500, \n                    \"retransmits\": 0, \n                    \"rtt\": 186018, \n                    \"rttvar\": 193748, \n                    \"seconds\": 1.0000009536743164, \n                    \"sender\": true, \n                    \"snd_cwnd\": 1448, \n                    \"snd_wnd\": -1, \n                    \"socket\": 5, \n                    \"start\": 27.001018\n                }\n            ], \n            \"sum\": {\n                \"bits_per_second\": 0, \n                \"bytes\": 0, \n                \"end\": 28.001019, \n                \"omitted\": false, \n                \"retransmits\": 0, \n                \"seconds\": 1.0000009536743164, \n                \"sender\": true, \n                \"start\": 27.001018\n            }\n        }, \n        {\n            \"streams\": [\n                {\n                    \"bits_per_second\": 0, \n                    \"bytes\": 0, \n                    \"end\": 29.001027, \n                    \"omitted\": false, \n                    \"pmtu\": 1500, \n                    \"retransmits\": 0, \n                    \"rtt\": 186018, \n                    \"rttvar\": 193748, \n                    \"seconds\": 1.0000079870224, \n                    \"sender\": true, \n                    \"snd_cwnd\": 1448, \n                    \"snd_wnd\": -1, \n                    \"socket\": 5, \n                    \"start\": 28.001019\n                }\n            ], \n            \"sum\": {\n                \"bits_per_second\": 0, \n                \"bytes\": 0, \n                \"end\": 29.001027, \n                \"omitted\": false, \n                \"retransmits\": 0, \n                \"seconds\": 1.0000079870224, \n                \"sender\": true, \n                \"start\": 28.001019\n            }\n        }, \n        {\n            \"streams\": [\n                {\n                    \"bits_per_second\": 0, \n                    \"bytes\": 0, \n                    \"end\": 30.001019, \n                    \"omitted\": false, \n                    \"pmtu\": 1500, \n                    \"retransmits\": 0, \n                    \"rtt\": 186018, \n                    \"rttvar\": 193748, \n                    \"seconds\": 0.9999920129776, \n                    \"sender\": true, \n                    \"snd_cwnd\": 1448, \n                    \"snd_wnd\": -1, \n                    \"socket\": 5, \n                    \"start\": 29.001027\n                }\n            ], \n            \"sum\": {\n                \"bits_per_second\": 0, \n                \"bytes\": 0, \n                \"end\": 30.001019, \n                \"omitted\": false, \n                \"retransmits\": 0, \n                \"seconds\": 0.9999920129776, \n                \"sender\": true, \n                \"start\": 29.001027\n            }\n        }, \n        {\n            \"streams\": [\n                {\n                    \"bits_per_second\": 0, \n                    \"bytes\": 0, \n                    \"end\": 31.001027, \n                    \"omitted\": false, \n                    \"pmtu\": 1500, \n                    \"retransmits\": 0, \n                    \"rtt\": 186018, \n                    \"rttvar\": 193748, \n                    \"seconds\": 1.0000079870224, \n                    \"sender\": true, \n                    \"snd_cwnd\": 1448, \n                    \"snd_wnd\": -1, \n                    \"socket\": 5, \n                    \"start\": 30.001019\n                }\n            ], \n            \"sum\": {\n                \"bits_per_second\": 0, \n                \"bytes\": 0, \n                \"end\": 31.001027, \n                \"omitted\": false, \n                \"retransmits\": 0, \n                \"seconds\": 1.0000079870224, \n                \"sender\": true, \n                \"start\": 30.001019\n            }\n        }, \n        {\n            \"streams\": [\n                {\n                    \"bits_per_second\": 0, \n                    \"bytes\": 0, \n                    \"end\": 32.001025, \n                    \"omitted\": false, \n                    \"pmtu\": 1500, \n                    \"retransmits\": 0, \n                    \"rtt\": 186018, \n                    \"rttvar\": 193748, \n                    \"seconds\": 0.9999979734420776, \n                    \"sender\": true, \n                    \"snd_cwnd\": 1448, \n                    \"snd_wnd\": -1, \n                    \"socket\": 5, \n                    \"start\": 31.001027\n                }\n            ], \n            \"sum\": {\n                \"bits_per_second\": 0, \n                \"bytes\": 0, \n                \"end\": 32.001025, \n                \"omitted\": false, \n                \"retransmits\": 0, \n                \"seconds\": 0.9999979734420776, \n                \"sender\": true, \n                \"start\": 31.001027\n            }\n        }, \n        {\n            \"streams\": [\n                {\n                    \"bits_per_second\": 0, \n                    \"bytes\": 0, \n                    \"end\": 33.001018, \n                    \"omitted\": false, \n                    \"pmtu\": 1500, \n                    \"retransmits\": 1, \n                    \"rtt\": 186018, \n                    \"rttvar\": 193748, \n                    \"seconds\": 0.9999930262565613, \n                    \"sender\": true, \n                    \"snd_cwnd\": 1448, \n                    \"snd_wnd\": -1, \n                    \"socket\": 5, \n                    \"start\": 32.001025\n                }\n            ], \n            \"sum\": {\n                \"bits_per_second\": 0, \n                \"bytes\": 0, \n                \"end\": 33.001018, \n                \"omitted\": false, \n                \"retransmits\": 1, \n                \"seconds\": 0.9999930262565613, \n                \"sender\": true, \n                \"start\": 32.001025\n            }\n        }, \n        {\n            \"streams\": [\n                {\n                    \"bits_per_second\": 0, \n                    \"bytes\": 0, \n                    \"end\": 34.001018, \n                    \"omitted\": false, \n                    \"pmtu\": 1500, \n                    \"retransmits\": 0, \n                    \"rtt\": 186018, \n                    \"rttvar\": 193748, \n                    \"seconds\": 1, \n                    \"sender\": true, \n                    \"snd_cwnd\": 1448, \n                    \"snd_wnd\": -1, \n                    \"socket\": 5, \n                    \"start\": 33.001018\n                }\n            ], \n            \"sum\": {\n                \"bits_per_second\": 0, \n                \"bytes\": 0, \n                \"end\": 34.001018, \n                \"omitted\": false, \n                \"retransmits\": 0, \n                \"seconds\": 1, \n                \"sender\": true, \n                \"start\": 33.001018\n            }\n        }, \n        {\n            \"streams\": [\n                {\n                    \"bits_per_second\": 0, \n                    \"bytes\": 0, \n                    \"end\": 35.001019, \n                    \"omitted\": false, \n                    \"pmtu\": 1500, \n                    \"retransmits\": 0, \n                    \"rtt\": 186018, \n                    \"rttvar\": 193748, \n                    \"seconds\": 1.0000009536743164, \n                    \"sender\": true, \n                    \"snd_cwnd\": 1448, \n                    \"snd_wnd\": -1, \n                    \"socket\": 5, \n                    \"start\": 34.001018\n                }\n            ], \n            \"sum\": {\n                \"bits_per_second\": 0, \n                \"bytes\": 0, \n                \"end\": 35.001019, \n                \"omitted\": false, \n                \"retransmits\": 0, \n                \"seconds\": 1.0000009536743164, \n                \"sender\": true, \n                \"start\": 34.001018\n            }\n        }, \n        {\n            \"streams\": [\n                {\n                    \"bits_per_second\": 0, \n                    \"bytes\": 0, \n                    \"end\": 36.001024, \n                    \"omitted\": false, \n                    \"pmtu\": 1500, \n                    \"retransmits\": 0, \n                    \"rtt\": 186018, \n                    \"rttvar\": 193748, \n                    \"seconds\": 1.0000050067901611, \n                    \"sender\": true, \n                    \"snd_cwnd\": 1448, \n                    \"snd_wnd\": -1, \n                    \"socket\": 5, \n                    \"start\": 35.001019\n                }\n            ], \n            \"sum\": {\n                \"bits_per_second\": 0, \n                \"bytes\": 0, \n                \"end\": 36.001024, \n                \"omitted\": false, \n                \"retransmits\": 0, \n                \"seconds\": 1.0000050067901611, \n                \"sender\": true, \n                \"start\": 35.001019\n            }\n        }, \n        {\n            \"streams\": [\n                {\n                    \"bits_per_second\": 0, \n                    \"bytes\": 0, \n                    \"end\": 37.001019, \n                    \"omitted\": false, \n                    \"pmtu\": 1500, \n                    \"retransmits\": 0, \n                    \"rtt\": 186018, \n                    \"rttvar\": 193748, \n                    \"seconds\": 0.999994993209839, \n                    \"sender\": true, \n                    \"snd_cwnd\": 1448, \n                    \"snd_wnd\": -1, \n                    \"socket\": 5, \n                    \"start\": 36.001024\n                }\n            ], \n            \"sum\": {\n                \"bits_per_second\": 0, \n                \"bytes\": 0, \n                \"end\": 37.001019, \n                \"omitted\": false, \n                \"retransmits\": 0, \n                \"seconds\": 0.999994993209839, \n                \"sender\": true, \n                \"start\": 36.001024\n            }\n        }, \n        {\n            \"streams\": [\n                {\n                    \"bits_per_second\": 0, \n                    \"bytes\": 0, \n                    \"end\": 38.001022, \n                    \"omitted\": false, \n                    \"pmtu\": 1500, \n                    \"retransmits\": 0, \n                    \"rtt\": 186018, \n                    \"rttvar\": 193748, \n                    \"seconds\": 1.0000029802322388, \n                    \"sender\": true, \n                    \"snd_cwnd\": 1448, \n                    \"snd_wnd\": -1, \n                    \"socket\": 5, \n                    \"start\": 37.001019\n                }\n            ], \n            \"sum\": {\n                \"bits_per_second\": 0, \n                \"bytes\": 0, \n                \"end\": 38.001022, \n                \"omitted\": false, \n                \"retransmits\": 0, \n                \"seconds\": 1.0000029802322388, \n                \"sender\": true, \n                \"start\": 37.001019\n            }\n        }, \n        {\n            \"streams\": [\n                {\n                    \"bits_per_second\": 0, \n                    \"bytes\": 0, \n                    \"end\": 39.001017, \n                    \"omitted\": false, \n                    \"pmtu\": 1500, \n                    \"retransmits\": 0, \n                    \"rtt\": 186018, \n                    \"rttvar\": 193748, \n                    \"seconds\": 0.999994993209839, \n                    \"sender\": true, \n                    \"snd_cwnd\": 1448, \n                    \"snd_wnd\": -1, \n                    \"socket\": 5, \n                    \"start\": 38.001022\n                }\n            ], \n            \"sum\": {\n                \"bits_per_second\": 0, \n                \"bytes\": 0, \n                \"end\": 39.001017, \n                \"omitted\": false, \n                \"retransmits\": 0, \n                \"seconds\": 0.999994993209839, \n                \"sender\": true, \n                \"start\": 38.001022\n            }\n        }, \n        {\n            \"streams\": [\n                {\n                    \"bits_per_second\": 0, \n                    \"bytes\": 0, \n                    \"end\": 40.00102, \n                    \"omitted\": false, \n                    \"pmtu\": 1500, \n                    \"retransmits\": 0, \n                    \"rtt\": 186018, \n                    \"rttvar\": 193748, \n                    \"seconds\": 1.0000029802322388, \n                    \"sender\": true, \n                    \"snd_cwnd\": 1448, \n                    \"snd_wnd\": -1, \n                    \"socket\": 5, \n                    \"start\": 39.001017\n                }\n            ], \n            \"sum\": {\n                \"bits_per_second\": 0, \n                \"bytes\": 0, \n                \"end\": 40.00102, \n                \"omitted\": false, \n                \"retransmits\": 0, \n                \"seconds\": 1.0000029802322388, \n                \"sender\": true, \n                \"start\": 39.001017\n            }\n        }, \n        {\n            \"streams\": [\n                {\n                    \"bits_per_second\": 0, \n                    \"bytes\": 0, \n                    \"end\": 41.001019, \n                    \"omitted\": false, \n                    \"pmtu\": 1500, \n                    \"retransmits\": 0, \n                    \"rtt\": 186018, \n                    \"rttvar\": 193748, \n                    \"seconds\": 0.9999989867210388, \n                    \"sender\": true, \n                    \"snd_cwnd\": 1448, \n                    \"snd_wnd\": -1, \n                    \"socket\": 5, \n                    \"start\": 40.00102\n                }\n            ], \n            \"sum\": {\n                \"bits_per_second\": 0, \n                \"bytes\": 0, \n                \"end\": 41.001019, \n                \"omitted\": false, \n                \"retransmits\": 0, \n                \"seconds\": 0.9999989867210388, \n                \"sender\": true, \n                \"start\": 40.00102\n            }\n        }, \n        {\n            \"streams\": [\n                {\n                    \"bits_per_second\": 0, \n                    \"bytes\": 0, \n                    \"end\": 42.001019, \n                    \"omitted\": false, \n                    \"pmtu\": 1500, \n                    \"retransmits\": 0, \n                    \"rtt\": 186018, \n                    \"rttvar\": 193748, \n                    \"seconds\": 1, \n                    \"sender\": true, \n                    \"snd_cwnd\": 1448, \n                    \"snd_wnd\": -1, \n                    \"socket\": 5, \n                    \"start\": 41.001019\n                }\n            ], \n            \"sum\": {\n                \"bits_per_second\": 0, \n                \"bytes\": 0, \n                \"end\": 42.001019, \n                \"omitted\": false, \n                \"retransmits\": 0, \n                \"seconds\": 1, \n                \"sender\": true, \n                \"start\": 41.001019\n            }\n        }, \n        {\n            \"streams\": [\n                {\n                    \"bits_per_second\": 0, \n                    \"bytes\": 0, \n                    \"end\": 43.001019, \n                    \"omitted\": false, \n                    \"pmtu\": 1500, \n                    \"retransmits\": 0, \n                    \"rtt\": 186018, \n                    \"rttvar\": 193748, \n                    \"seconds\": 1, \n                    \"sender\": true, \n                    \"snd_cwnd\": 1448, \n                    \"snd_wnd\": -1, \n                    \"socket\": 5, \n                    \"start\": 42.001019\n                }\n            ], \n            \"sum\": {\n                \"bits_per_second\": 0, \n                \"bytes\": 0, \n                \"end\": 43.001019, \n                \"omitted\": false, \n                \"retransmits\": 0, \n                \"seconds\": 1, \n                \"sender\": true, \n                \"start\": 42.001019\n            }\n        }, \n        {\n            \"streams\": [\n                {\n                    \"bits_per_second\": 0, \n                    \"bytes\": 0, \n                    \"end\": 44.001018, \n                    \"omitted\": false, \n                    \"pmtu\": 1500, \n                    \"retransmits\": 1, \n                    \"rtt\": 173016, \n                    \"rttvar\": 171315, \n                    \"seconds\": 0.9999989867210388, \n                    \"sender\": true, \n                    \"snd_cwnd\": 2896, \n                    \"snd_wnd\": -1, \n                    \"socket\": 5, \n                    \"start\": 43.001019\n                }\n            ], \n            \"sum\": {\n                \"bits_per_second\": 0, \n                \"bytes\": 0, \n                \"end\": 44.001018, \n                \"omitted\": false, \n                \"retransmits\": 1, \n                \"seconds\": 0.9999989867210388, \n                \"sender\": true, \n                \"start\": 43.001019\n            }\n        }, \n        {\n            \"streams\": [\n                {\n                    \"bits_per_second\": 0, \n                    \"bytes\": 0, \n                    \"end\": 45.001018, \n                    \"omitted\": false, \n                    \"pmtu\": 1500, \n                    \"retransmits\": 25, \n                    \"rtt\": 24076, \n                    \"rttvar\": 1510, \n                    \"seconds\": 1, \n                    \"sender\": true, \n                    \"snd_cwnd\": 44888, \n                    \"snd_wnd\": -1, \n                    \"socket\": 5, \n                    \"start\": 44.001018\n                }\n            ], \n            \"sum\": {\n                \"bits_per_second\": 0, \n                \"bytes\": 0, \n                \"end\": 45.001018, \n                \"omitted\": false, \n                \"retransmits\": 25, \n                \"seconds\": 1, \n                \"sender\": true, \n                \"start\": 44.001018\n            }\n        }, \n        {\n            \"streams\": [\n                {\n                    \"bits_per_second\": 0, \n                    \"bytes\": 0, \n                    \"end\": 46.001017, \n                    \"omitted\": false, \n                    \"pmtu\": 1500, \n                    \"retransmits\": 1, \n                    \"rtt\": 24076, \n                    \"rttvar\": 1510, \n                    \"seconds\": 0.9999989867210388, \n                    \"sender\": true, \n                    \"snd_cwnd\": 1448, \n                    \"snd_wnd\": -1, \n                    \"socket\": 5, \n                    \"start\": 45.001018\n                }\n            ], \n            \"sum\": {\n                \"bits_per_second\": 0, \n                \"bytes\": 0, \n                \"end\": 46.001017, \n                \"omitted\": false, \n                \"retransmits\": 1, \n                \"seconds\": 0.9999989867210388, \n                \"sender\": true, \n                \"start\": 45.001018\n            }\n        }, \n        {\n            \"streams\": [\n                {\n                    \"bits_per_second\": 0, \n                    \"bytes\": 0, \n                    \"end\": 47.001025, \n                    \"omitted\": false, \n                    \"pmtu\": 1500, \n                    \"retransmits\": 1, \n                    \"rtt\": 24076, \n                    \"rttvar\": 1510, \n                    \"seconds\": 1.0000079870224, \n                    \"sender\": true, \n                    \"snd_cwnd\": 1448, \n                    \"snd_wnd\": -1, \n                    \"socket\": 5, \n                    \"start\": 46.001017\n                }\n            ], \n            \"sum\": {\n                \"bits_per_second\": 0, \n                \"bytes\": 0, \n                \"end\": 47.001025, \n                \"omitted\": false, \n                \"retransmits\": 1, \n                \"seconds\": 1.0000079870224, \n                \"sender\": true, \n                \"start\": 46.001017\n            }\n        }, \n        {\n            \"streams\": [\n                {\n                    \"bits_per_second\": 0, \n                    \"bytes\": 0, \n                    \"end\": 48.001029, \n                    \"omitted\": false, \n                    \"pmtu\": 1500, \n                    \"retransmits\": 0, \n                    \"rtt\": 24076, \n                    \"rttvar\": 1510, \n                    \"seconds\": 1.0000040531158447, \n                    \"sender\": true, \n                    \"snd_cwnd\": 1448, \n                    \"snd_wnd\": -1, \n                    \"socket\": 5, \n                    \"start\": 47.001025\n                }\n            ], \n            \"sum\": {\n                \"bits_per_second\": 0, \n                \"bytes\": 0, \n                \"end\": 48.001029, \n                \"omitted\": false, \n                \"retransmits\": 0, \n                \"seconds\": 1.0000040531158447, \n                \"sender\": true, \n                \"start\": 47.001025\n            }\n        }, \n        {\n            \"streams\": [\n                {\n                    \"bits_per_second\": 0, \n                    \"bytes\": 0, \n                    \"end\": 49.001025, \n                    \"omitted\": false, \n                    \"pmtu\": 1500, \n                    \"retransmits\": 0, \n                    \"rtt\": 24076, \n                    \"rttvar\": 1510, \n                    \"seconds\": 0.9999960064888, \n                    \"sender\": true, \n                    \"snd_cwnd\": 1448, \n                    \"snd_wnd\": -1, \n                    \"socket\": 5, \n                    \"start\": 48.001029\n                }\n            ], \n            \"sum\": {\n                \"bits_per_second\": 0, \n                \"bytes\": 0, \n                \"end\": 49.001025, \n                \"omitted\": false, \n                \"retransmits\": 0, \n                \"seconds\": 0.9999960064888, \n                \"sender\": true, \n                \"start\": 48.001029\n            }\n        }, \n        {\n            \"streams\": [\n                {\n                    \"bits_per_second\": 0, \n                    \"bytes\": 0, \n                    \"end\": 50.001018, \n                    \"omitted\": false, \n                    \"pmtu\": 1500, \n                    \"retransmits\": 0, \n                    \"rtt\": 24076, \n                    \"rttvar\": 1510, \n                    \"seconds\": 0.9999930262565613, \n                    \"sender\": true, \n                    \"snd_cwnd\": 1448, \n                    \"snd_wnd\": -1, \n                    \"socket\": 5, \n                    \"start\": 49.001025\n                }\n            ], \n            \"sum\": {\n                \"bits_per_second\": 0, \n                \"bytes\": 0, \n                \"end\": 50.001018, \n                \"omitted\": false, \n                \"retransmits\": 0, \n                \"seconds\": 0.9999930262565613, \n                \"sender\": true, \n                \"start\": 49.001025\n            }\n        }, \n        {\n            \"streams\": [\n                {\n                    \"bits_per_second\": 0, \n                    \"bytes\": 0, \n                    \"end\": 51.00102, \n                    \"omitted\": false, \n                    \"pmtu\": 1500, \n                    \"retransmits\": 41, \n                    \"rtt\": 30795, \n                    \"rttvar\": 11388, \n                    \"seconds\": 1.0000020265579224, \n                    \"sender\": true, \n                    \"snd_cwnd\": 20272, \n                    \"snd_wnd\": -1, \n                    \"socket\": 5, \n                    \"start\": 50.001018\n                }\n            ], \n            \"sum\": {\n                \"bits_per_second\": 0, \n                \"bytes\": 0, \n                \"end\": 51.00102, \n                \"omitted\": false, \n                \"retransmits\": 41, \n                \"seconds\": 1.0000020265579224, \n                \"sender\": true, \n                \"start\": 50.001018\n            }\n        }, \n        {\n            \"streams\": [\n                {\n                    \"bits_per_second\": 20989675.70436846, \n                    \"bytes\": 2621440, \n                    \"end\": 52.000155, \n                    \"omitted\": false, \n                    \"pmtu\": 1500, \n                    \"retransmits\": 0, \n                    \"rtt\": 33010, \n                    \"rttvar\": 9882, \n                    \"seconds\": 0.9991350173950195, \n                    \"sender\": true, \n                    \"snd_cwnd\": 78192, \n                    \"snd_wnd\": -1, \n                    \"socket\": 5, \n                    \"start\": 51.00102\n                }\n            ], \n            \"sum\": {\n                \"bits_per_second\": 20989675.70436846, \n                \"bytes\": 2621440, \n                \"end\": 52.000155, \n                \"omitted\": false, \n                \"retransmits\": 0, \n                \"seconds\": 0.9991350173950195, \n                \"sender\": true, \n                \"start\": 51.00102\n            }\n        }, \n        {\n            \"streams\": [\n                {\n                    \"bits_per_second\": 10484030.2853781, \n                    \"bytes\": 1310720, \n                    \"end\": 53.00032, \n                    \"omitted\": false, \n                    \"pmtu\": 1500, \n                    \"retransmits\": 52, \n                    \"rtt\": 28484, \n                    \"rttvar\": 559, \n                    \"seconds\": 1.0001649856567383, \n                    \"sender\": true, \n                    \"snd_cwnd\": 79640, \n                    \"snd_wnd\": -1, \n                    \"socket\": 5, \n                    \"start\": 52.000155\n                }\n            ], \n            \"sum\": {\n                \"bits_per_second\": 10484030.2853781, \n                \"bytes\": 1310720, \n                \"end\": 53.00032, \n                \"omitted\": false, \n                \"retransmits\": 52, \n                \"seconds\": 1.0001649856567383, \n                \"sender\": true, \n                \"start\": 52.000155\n            }\n        }, \n        {\n            \"streams\": [\n                {\n                    \"bits_per_second\": 20977330.359369516, \n                    \"bytes\": 2621440, \n                    \"end\": 54.000043, \n                    \"omitted\": false, \n                    \"pmtu\": 1500, \n                    \"retransmits\": 0, \n                    \"rtt\": 42371, \n                    \"rttvar\": 458, \n                    \"seconds\": 0.9997230172157288, \n                    \"sender\": true, \n                    \"snd_cwnd\": 117288, \n                    \"snd_wnd\": -1, \n                    \"socket\": 5, \n                    \"start\": 53.00032\n                }\n            ], \n            \"sum\": {\n                \"bits_per_second\": 20977330.359369516, \n                \"bytes\": 2621440, \n                \"end\": 54.000043, \n                \"omitted\": false, \n                \"retransmits\": 0, \n                \"seconds\": 0.9997230172157288, \n                \"sender\": true, \n                \"start\": 53.00032\n            }\n        }, \n        {\n            \"streams\": [\n                {\n                    \"bits_per_second\": 20964684.728554178, \n                    \"bytes\": 2621440, \n                    \"end\": 55.000369, \n                    \"omitted\": false, \n                    \"pmtu\": 1500, \n                    \"retransmits\": 0, \n                    \"rtt\": 52670, \n                    \"rttvar\": 623, \n                    \"seconds\": 1.0003260374069214, \n                    \"sender\": true, \n                    \"snd_cwnd\": 146248, \n                    \"snd_wnd\": -1, \n                    \"socket\": 5, \n                    \"start\": 54.000043\n                }\n            ], \n            \"sum\": {\n                \"bits_per_second\": 20964684.728554178, \n                \"bytes\": 2621440, \n                \"end\": 55.000369, \n                \"omitted\": false, \n                \"retransmits\": 0, \n                \"seconds\": 1.0003260374069214, \n                \"sender\": true, \n                \"start\": 54.000043\n            }\n        }, \n        {\n            \"streams\": [\n                {\n                    \"bits_per_second\": 20975924.674925193, \n                    \"bytes\": 2621440, \n                    \"end\": 56.000159, \n                    \"omitted\": false, \n                    \"pmtu\": 1500, \n                    \"retransmits\": 60, \n                    \"rtt\": 38818, \n                    \"rttvar\": 564, \n                    \"seconds\": 0.9997900128364563, \n                    \"sender\": true, \n                    \"snd_cwnd\": 105704, \n                    \"snd_wnd\": -1, \n                    \"socket\": 5, \n                    \"start\": 55.000369\n                }\n            ], \n            \"sum\": {\n                \"bits_per_second\": 20975924.674925193, \n                \"bytes\": 2621440, \n                \"end\": 56.000159, \n                \"omitted\": false, \n                \"retransmits\": 60, \n                \"seconds\": 0.9997900128364563, \n                \"sender\": true, \n                \"start\": 55.000369\n            }\n        }, \n        {\n            \"streams\": [\n                {\n                    \"bits_per_second\": 10483328.064163582, \n                    \"bytes\": 1310720, \n                    \"end\": 57.000391, \n                    \"omitted\": false, \n                    \"pmtu\": 1500, \n                    \"retransmits\": 3, \n                    \"rtt\": 36019, \n                    \"rttvar\": 12094, \n                    \"seconds\": 1.0002319812774658, \n                    \"sender\": true, \n                    \"snd_cwnd\": 81088, \n                    \"snd_wnd\": -1, \n                    \"socket\": 5, \n                    \"start\": 56.000159\n                }\n            ], \n            \"sum\": {\n                \"bits_per_second\": 10483328.064163582, \n                \"bytes\": 1310720, \n                \"end\": 57.000391, \n                \"omitted\": false, \n                \"retransmits\": 3, \n                \"seconds\": 1.0002319812774658, \n                \"sender\": true, \n                \"start\": 56.000159\n            }\n        }, \n        {\n            \"streams\": [\n                {\n                    \"bits_per_second\": 0, \n                    \"bytes\": 0, \n                    \"end\": 58.000112, \n                    \"omitted\": false, \n                    \"pmtu\": 1500, \n                    \"retransmits\": 2, \n                    \"rtt\": 36019, \n                    \"rttvar\": 12094, \n                    \"seconds\": 0.9997209906578064, \n                    \"sender\": true, \n                    \"snd_cwnd\": 1448, \n                    \"snd_wnd\": -1, \n                    \"socket\": 5, \n                    \"start\": 57.000391\n                }\n            ], \n            \"sum\": {\n                \"bits_per_second\": 0, \n                \"bytes\": 0, \n                \"end\": 58.000112, \n                \"omitted\": false, \n                \"retransmits\": 2, \n                \"seconds\": 0.9997209906578064, \n                \"sender\": true, \n                \"start\": 57.000391\n            }\n        }, \n        {\n            \"streams\": [\n                {\n                    \"bits_per_second\": 0, \n                    \"bytes\": 0, \n                    \"end\": 59.00043, \n                    \"omitted\": false, \n                    \"pmtu\": 1500, \n                    \"retransmits\": 1, \n                    \"rtt\": 36019, \n                    \"rttvar\": 12094, \n                    \"seconds\": 1.0003180503845215, \n                    \"sender\": true, \n                    \"snd_cwnd\": 1448, \n                    \"snd_wnd\": -1, \n                    \"socket\": 5, \n                    \"start\": 58.000112\n                }\n            ], \n            \"sum\": {\n                \"bits_per_second\": 0, \n                \"bytes\": 0, \n                \"end\": 59.00043, \n                \"omitted\": false, \n                \"retransmits\": 1, \n                \"seconds\": 1.0003180503845215, \n                \"sender\": true, \n                \"start\": 58.000112\n            }\n        }, \n        {\n            \"streams\": [\n                {\n                    \"bits_per_second\": 0, \n                    \"bytes\": 0, \n                    \"end\": 60.000695, \n                    \"omitted\": false, \n                    \"pmtu\": 1500, \n                    \"retransmits\": 0, \n                    \"rtt\": 36019, \n                    \"rttvar\": 12094, \n                    \"seconds\": 1.0002650022506714, \n                    \"sender\": true, \n                    \"snd_cwnd\": 1448, \n                    \"snd_wnd\": -1, \n                    \"socket\": 5, \n                    \"start\": 59.00043\n                }\n            ], \n            \"sum\": {\n                \"bits_per_second\": 0, \n                \"bytes\": 0, \n                \"end\": 60.000695, \n                \"omitted\": false, \n                \"retransmits\": 0, \n                \"seconds\": 1.0002650022506714, \n                \"sender\": true, \n                \"start\": 59.00043\n            }\n        }\n    ], \n    \"start\": {\n        \"connected\": [\n            {\n                \"local_host\": \"172.16.0.2\", \n                \"local_port\": 58621, \n                \"remote_host\": \"172.16.0.1\", \n                \"remote_port\": 5201, \n                \"socket\": 5\n            }\n        ], \n        \"connecting_to\": {\n            \"host\": \"172.16.0.1\", \n            \"port\": 5201\n        }, \n        \"cookie\": \"r6efeya7vefuyv6b3ozp6b6ya7ee55heeohw\", \n        \"fq_rate\": 0, \n        \"rcvbuf_actual\": 87380, \n        \"sndbuf_actual\": 65536, \n        \"sock_bufsize\": 0, \n        \"system_info\": \"REDACTED\", \n        \"target_bitrate\": 0, \n        \"tcp_mss_default\": 1448, \n        \"test_start\": {\n            \"bidir\": 0, \n            \"blksize\": 131072, \n            \"blocks\": 0, \n            \"bytes\": 0, \n            \"duration\": 60, \n            \"fqrate\": 0, \n            \"num_streams\": 1, \n            \"omit\": 0, \n            \"protocol\": \"TCP\", \n            \"reverse\": 0, \n            \"target_bitrate\": 0, \n            \"tos\": 0\n        }, \n        \"timestamp\": {\n            \"time\": \"Wed, 16 Oct 2024 02:43:09 GMT\", \n            \"timesecs\": 1729046589\n        }, \n        \"version\": \"iperf 3.14\"\n    }\n}\nParticipant 1:\n/usr/bin/iperf3 --use-pkcs1-padding -s -1 --idle-timeout 60 --json -p 5201 -B 172.16.0.1 --authorized-users-path /var/pscheduler-server/runner/tmp/tmpp6ztja4y/tmpc7ecruna/credentials --rsa-private-key-path /var/pscheduler-server/runner/tmp/tmpp6ztja4y/tmpc7ecruna/private-key\n\n{\n    \"end\": {\n        \"cpu_utilization_percent\": {\n            \"host_system\": 1.2682929820150872, \n            \"host_total\": 1.4113074372265142, \n            \"host_user\": 0.14301945356138848, \n            \"remote_system\": 0, \n            \"remote_total\": 0, \n            \"remote_user\": 0\n        }, \n        \"receiver_tcp_congestion\": \"htcp\", \n        \"streams\": [\n            {\n                \"receiver\": {\n                    \"bits_per_second\": 6072353.230326443, \n                    \"bytes\": 45557632, \n                    \"end\": 60.019739, \n                    \"seconds\": 60.019739, \n                    \"sender\": false, \n                    \"socket\": 5, \n                    \"start\": 0\n                }, \n                \"sender\": {\n                    \"bits_per_second\": 0, \n                    \"bytes\": 0, \n                    \"end\": 60.019739, \n                    \"seconds\": 60.019739, \n                    \"sender\": false, \n                    \"socket\": 5, \n                    \"start\": 0\n                }\n            }\n        ], \n        \"sum_received\": {\n            \"bits_per_second\": 6072353.230326443, \n            \"bytes\": 45557632, \n            \"end\": 60.019739, \n            \"seconds\": 60.019739, \n            \"sender\": false, \n            \"start\": 0\n        }, \n        \"sum_sent\": {\n            \"bits_per_second\": 0, \n            \"bytes\": 0, \n            \"end\": 60.019739, \n            \"seconds\": 60.019739, \n            \"sender\": false, \n            \"start\": 0\n        }\n    }, \n    \"intervals\": [\n        {\n            \"streams\": [\n                {\n                    \"bits_per_second\": 19901888.15171784, \n                    \"bytes\": 2490368, \n                    \"end\": 1.001058, \n                    \"omitted\": false, \n                    \"seconds\": 1.0010579824447632, \n                    \"sender\": false, \n                    \"socket\": 5, \n                    \"start\": 0\n                }\n            ], \n            \"sum\": {\n                \"bits_per_second\": 19901888.15171784, \n                \"bytes\": 2490368, \n                \"end\": 1.001058, \n                \"omitted\": false, \n                \"seconds\": 1.0010579824447632, \n                \"sender\": false, \n                \"start\": 0\n            }\n        }, \n        {\n            \"streams\": [\n                {\n                    \"bits_per_second\": 22018796.701669775, \n                    \"bytes\": 2752512, \n                    \"end\": 2.001117, \n                    \"omitted\": false, \n                    \"seconds\": 1.0000590085983276, \n                    \"sender\": false, \n                    \"socket\": 5, \n                    \"start\": 1.001058\n                }\n            ], \n            \"sum\": {\n                \"bits_per_second\": 22018796.701669775, \n                \"bytes\": 2752512, \n                \"end\": 2.001117, \n                \"omitted\": false, \n                \"seconds\": 1.0000590085983276, \n                \"sender\": false, \n                \"start\": 1.001058\n            }\n        }, \n        {\n            \"streams\": [\n                {\n                    \"bits_per_second\": 22020580.32315226, \n                    \"bytes\": 2752512, \n                    \"end\": 3.001095, \n                    \"omitted\": false, \n                    \"seconds\": 0.999978005886078, \n                    \"sender\": false, \n                    \"socket\": 5, \n                    \"start\": 2.001117\n                }\n            ], \n            \"sum\": {\n                \"bits_per_second\": 22020580.32315226, \n                \"bytes\": 2752512, \n                \"end\": 3.001095, \n                \"omitted\": false, \n                \"seconds\": 0.999978005886078, \n                \"sender\": false, \n                \"start\": 2.001117\n            }\n        }, \n        {\n            \"streams\": [\n                {\n                    \"bits_per_second\": 20990768.901578832, \n                    \"bytes\": 2621440, \n                    \"end\": 4.000178, \n                    \"omitted\": false, \n                    \"seconds\": 0.9990829825401306, \n                    \"sender\": false, \n                    \"socket\": 5, \n                    \"start\": 3.001095\n                }\n            ], \n            \"sum\": {\n                \"bits_per_second\": 20990768.901578832, \n                \"bytes\": 2621440, \n                \"end\": 4.000178, \n                \"omitted\": false, \n                \"seconds\": 0.9990829825401306, \n                \"sender\": false, \n                \"start\": 3.001095\n            }\n        }, \n        {\n            \"streams\": [\n                {\n                    \"bits_per_second\": 22020624.95020574, \n                    \"bytes\": 2752512, \n                    \"end\": 5.000154, \n                    \"omitted\": false, \n                    \"seconds\": 0.9999759793281555, \n                    \"sender\": false, \n                    \"socket\": 5, \n                    \"start\": 4.000178\n                }\n            ], \n            \"sum\": {\n                \"bits_per_second\": 22020624.95020574, \n                \"bytes\": 2752512, \n                \"end\": 5.000154, \n                \"omitted\": false, \n                \"seconds\": 0.9999759793281555, \n                \"sender\": false, \n                \"start\": 4.000178\n            }\n        }, \n        {\n            \"streams\": [\n                {\n                    \"bits_per_second\": 22021924.46431606, \n                    \"bytes\": 2752512, \n                    \"end\": 6.000071, \n                    \"omitted\": false, \n                    \"seconds\": 0.999916970729828, \n                    \"sender\": false, \n                    \"socket\": 5, \n                    \"start\": 5.000154\n                }\n            ], \n            \"sum\": {\n                \"bits_per_second\": 22021924.46431606, \n                \"bytes\": 2752512, \n                \"end\": 6.000071, \n                \"omitted\": false, \n                \"seconds\": 0.999916970729828, \n                \"sender\": false, \n                \"start\": 5.000154\n            }\n        }, \n        {\n            \"streams\": [\n                {\n                    \"bits_per_second\": 18873859.513699282, \n                    \"bytes\": 2359296, \n                    \"end\": 7.000098, \n                    \"omitted\": false, \n                    \"seconds\": 1.0000269412994385, \n                    \"sender\": false, \n                    \"socket\": 5, \n                    \"start\": 6.000071\n                }\n            ], \n            \"sum\": {\n                \"bits_per_second\": 18873859.513699282, \n                \"bytes\": 2359296, \n                \"end\": 7.000098, \n                \"omitted\": false, \n                \"seconds\": 1.0000269412994385, \n                \"sender\": false, \n                \"start\": 6.000071\n            }\n        }, \n        {\n            \"streams\": [\n                {\n                    \"bits_per_second\": 24115632.35824092, \n                    \"bytes\": 3014656, \n                    \"end\": 8.000165, \n                    \"omitted\": false, \n                    \"seconds\": 1.0000669956207275, \n                    \"sender\": false, \n                    \"socket\": 5, \n                    \"start\": 7.000098\n                }\n            ], \n            \"sum\": {\n                \"bits_per_second\": 24115632.35824092, \n                \"bytes\": 3014656, \n                \"end\": 8.000165, \n                \"omitted\": false, \n                \"seconds\": 1.0000669956207275, \n                \"sender\": false, \n                \"start\": 7.000098\n            }\n        }, \n        {\n            \"streams\": [\n                {\n                    \"bits_per_second\": 18855305.0229364, \n                    \"bytes\": 2359296, \n                    \"end\": 9.001176, \n                    \"omitted\": false, \n                    \"seconds\": 1.00101101398468, \n                    \"sender\": false, \n                    \"socket\": 5, \n                    \"start\": 8.000165\n                }\n            ], \n            \"sum\": {\n                \"bits_per_second\": 18855305.0229364, \n                \"bytes\": 2359296, \n                \"end\": 9.001176, \n                \"omitted\": false, \n                \"seconds\": 1.00101101398468, \n                \"sender\": false, \n                \"start\": 8.000165\n            }\n        }, \n        {\n            \"streams\": [\n                {\n                    \"bits_per_second\": 0, \n                    \"bytes\": 0, \n                    \"end\": 10.001081, \n                    \"omitted\": false, \n                    \"seconds\": 0.999904990196228, \n                    \"sender\": false, \n                    \"socket\": 5, \n                    \"start\": 9.001176\n                }\n            ], \n            \"sum\": {\n                \"bits_per_second\": 0, \n                \"bytes\": 0, \n                \"end\": 10.001081, \n                \"omitted\": false, \n                \"seconds\": 0.999904990196228, \n                \"sender\": false, \n                \"start\": 9.001176\n            }\n        }, \n        {\n            \"streams\": [\n                {\n                    \"bits_per_second\": 0, \n                    \"bytes\": 0, \n                    \"end\": 11.001103, \n                    \"omitted\": false, \n                    \"seconds\": 1.000022053718567, \n                    \"sender\": false, \n                    \"socket\": 5, \n                    \"start\": 10.001081\n                }\n            ], \n            \"sum\": {\n                \"bits_per_second\": 0, \n                \"bytes\": 0, \n                \"end\": 11.001103, \n                \"omitted\": false, \n                \"seconds\": 1.000022053718567, \n                \"sender\": false, \n                \"start\": 10.001081\n            }\n        }, \n        {\n            \"streams\": [\n                {\n                    \"bits_per_second\": 0, \n                    \"bytes\": 0, \n                    \"end\": 12.001104, \n                    \"omitted\": false, \n                    \"seconds\": 1.0000009536743164, \n                    \"sender\": false, \n                    \"socket\": 5, \n                    \"start\": 11.001103\n                }\n            ], \n            \"sum\": {\n                \"bits_per_second\": 0, \n                \"bytes\": 0, \n                \"end\": 12.001104, \n                \"omitted\": false, \n                \"seconds\": 1.0000009536743164, \n                \"sender\": false, \n                \"start\": 11.001103\n            }\n        }, \n        {\n            \"streams\": [\n                {\n                    \"bits_per_second\": 0, \n                    \"bytes\": 0, \n                    \"end\": 13.001125, \n                    \"omitted\": false, \n                    \"seconds\": 1.000020980834961, \n                    \"sender\": false, \n                    \"socket\": 5, \n                    \"start\": 12.001104\n                }\n            ], \n            \"sum\": {\n                \"bits_per_second\": 0, \n                \"bytes\": 0, \n                \"end\": 13.001125, \n                \"omitted\": false, \n                \"seconds\": 1.000020980834961, \n                \"sender\": false, \n                \"start\": 12.001104\n            }\n        }, \n        {\n            \"streams\": [\n                {\n                    \"bits_per_second\": 4194555.765111415, \n                    \"bytes\": 524288, \n                    \"end\": 14.001065, \n                    \"omitted\": false, \n                    \"seconds\": 0.9999399781227112, \n                    \"sender\": false, \n                    \"socket\": 5, \n                    \"start\": 13.001125\n                }\n            ], \n            \"sum\": {\n                \"bits_per_second\": 4194555.765111415, \n                \"bytes\": 524288, \n                \"end\": 14.001065, \n                \"omitted\": false, \n                \"seconds\": 0.9999399781227112, \n                \"sender\": false, \n                \"start\": 13.001125\n            }\n        }, \n        {\n            \"streams\": [\n                {\n                    \"bits_per_second\": 16776528.028212344, \n                    \"bytes\": 2097152, \n                    \"end\": 15.001106, \n                    \"omitted\": false, \n                    \"seconds\": 1.0000410079956055, \n                    \"sender\": false, \n                    \"socket\": 5, \n                    \"start\": 14.001065\n                }\n            ], \n            \"sum\": {\n                \"bits_per_second\": 16776528.028212344, \n                \"bytes\": 2097152, \n                \"end\": 15.001106, \n                \"omitted\": false, \n                \"seconds\": 1.0000410079956055, \n                \"sender\": false, \n                \"start\": 14.001065\n            }\n        }, \n        {\n            \"streams\": [\n                {\n                    \"bits_per_second\": 5243126.574095903, \n                    \"bytes\": 655360, \n                    \"end\": 16.001059, \n                    \"omitted\": false, \n                    \"seconds\": 0.9999529719352722, \n                    \"sender\": false, \n                    \"socket\": 5, \n                    \"start\": 15.001106\n                }\n            ], \n            \"sum\": {\n                \"bits_per_second\": 5243126.574095903, \n                \"bytes\": 655360, \n                \"end\": 16.001059, \n                \"omitted\": false, \n                \"seconds\": 0.9999529719352722, \n                \"sender\": false, \n                \"start\": 15.001106\n            }\n        }, \n        {\n            \"streams\": [\n                {\n                    \"bits_per_second\": 3145470.02115839, \n                    \"bytes\": 393216, \n                    \"end\": 17.001141, \n                    \"omitted\": false, \n                    \"seconds\": 1.000082015991211, \n                    \"sender\": false, \n                    \"socket\": 5, \n                    \"start\": 16.001059\n                }\n            ], \n            \"sum\": {\n                \"bits_per_second\": 3145470.02115839, \n                \"bytes\": 393216, \n                \"end\": 17.001141, \n                \"omitted\": false, \n                \"seconds\": 1.000082015991211, \n                \"sender\": false, \n                \"start\": 16.001059\n            }\n        }, \n        {\n            \"streams\": [\n                {\n                    \"bits_per_second\": 3145951.328353886, \n                    \"bytes\": 393216, \n                    \"end\": 18.00107, \n                    \"omitted\": false, \n                    \"seconds\": 0.9999290108680725, \n                    \"sender\": false, \n                    \"socket\": 5, \n                    \"start\": 17.001141\n                }\n            ], \n            \"sum\": {\n                \"bits_per_second\": 3145951.328353886, \n                \"bytes\": 393216, \n                \"end\": 18.00107, \n                \"omitted\": false, \n                \"seconds\": 0.9999290108680725, \n                \"sender\": false, \n                \"start\": 17.001141\n            }\n        }, \n        {\n            \"streams\": [\n                {\n                    \"bits_per_second\": 14679595.014983175, \n                    \"bytes\": 1835008, \n                    \"end\": 19.001102, \n                    \"omitted\": false, \n                    \"seconds\": 1.0000319480895996, \n                    \"sender\": false, \n                    \"socket\": 5, \n                    \"start\": 18.00107\n                }\n            ], \n            \"sum\": {\n                \"bits_per_second\": 14679595.014983175, \n                \"bytes\": 1835008, \n                \"end\": 19.001102, \n                \"omitted\": false, \n                \"seconds\": 1.0000319480895996, \n                \"sender\": false, \n                \"start\": 18.00107\n            }\n        }, \n        {\n            \"streams\": [\n                {\n                    \"bits_per_second\": 11534151.752943171, \n                    \"bytes\": 1441792, \n                    \"end\": 20.001118, \n                    \"omitted\": false, \n                    \"seconds\": 1.0000159740448, \n                    \"sender\": false, \n                    \"socket\": 5, \n                    \"start\": 19.001102\n                }\n            ], \n            \"sum\": {\n                \"bits_per_second\": 11534151.752943171, \n                \"bytes\": 1441792, \n                \"end\": 20.001118, \n                \"omitted\": false, \n                \"seconds\": 1.0000159740448, \n                \"sender\": false, \n                \"start\": 19.001102\n            }\n        }, \n        {\n            \"streams\": [\n                {\n                    \"bits_per_second\": 8388759.00271814, \n                    \"bytes\": 1048576, \n                    \"end\": 21.0011, \n                    \"omitted\": false, \n                    \"seconds\": 0.9999819993972778, \n                    \"sender\": false, \n                    \"socket\": 5, \n                    \"start\": 20.001118\n                }\n            ], \n            \"sum\": {\n                \"bits_per_second\": 8388759.00271814, \n                \"bytes\": 1048576, \n                \"end\": 21.0011, \n                \"omitted\": false, \n                \"seconds\": 0.9999819993972778, \n                \"sender\": false, \n                \"start\": 20.001118\n            }\n        }, \n        {\n            \"streams\": [\n                {\n                    \"bits_per_second\": 0, \n                    \"bytes\": 0, \n                    \"end\": 22.001113, \n                    \"omitted\": false, \n                    \"seconds\": 1.000012993812561, \n                    \"sender\": false, \n                    \"socket\": 5, \n                    \"start\": 21.0011\n                }\n            ], \n            \"sum\": {\n                \"bits_per_second\": 0, \n                \"bytes\": 0, \n                \"end\": 22.001113, \n                \"omitted\": false, \n                \"seconds\": 1.000012993812561, \n                \"sender\": false, \n                \"start\": 21.0011\n            }\n        }, \n        {\n            \"streams\": [\n                {\n                    \"bits_per_second\": 0, \n                    \"bytes\": 0, \n                    \"end\": 23.001109, \n                    \"omitted\": false, \n                    \"seconds\": 0.9999960064888, \n                    \"sender\": false, \n                    \"socket\": 5, \n                    \"start\": 22.001113\n                }\n            ], \n            \"sum\": {\n                \"bits_per_second\": 0, \n                \"bytes\": 0, \n                \"end\": 23.001109, \n                \"omitted\": false, \n                \"seconds\": 0.9999960064888, \n                \"sender\": false, \n                \"start\": 22.001113\n            }\n        }, \n        {\n            \"streams\": [\n                {\n                    \"bits_per_second\": 0, \n                    \"bytes\": 0, \n                    \"end\": 24.001186, \n                    \"omitted\": false, \n                    \"seconds\": 1.00007700920105, \n                    \"sender\": false, \n                    \"socket\": 5, \n                    \"start\": 23.001109\n                }\n            ], \n            \"sum\": {\n                \"bits_per_second\": 0, \n                \"bytes\": 0, \n                \"end\": 24.001186, \n                \"omitted\": false, \n                \"seconds\": 1.00007700920105, \n                \"sender\": false, \n                \"start\": 23.001109\n            }\n        }, \n        {\n            \"streams\": [\n                {\n                    \"bits_per_second\": 0, \n                    \"bytes\": 0, \n                    \"end\": 25.001201, \n                    \"omitted\": false, \n                    \"seconds\": 1.0000150203704834, \n                    \"sender\": false, \n                    \"socket\": 5, \n                    \"start\": 24.001186\n                }\n            ], \n            \"sum\": {\n                \"bits_per_second\": 0, \n                \"bytes\": 0, \n                \"end\": 25.001201, \n                \"omitted\": false, \n                \"seconds\": 1.0000150203704834, \n                \"sender\": false, \n                \"start\": 24.001186\n            }\n        }, \n        {\n            \"streams\": [\n                {\n                    \"bits_per_second\": 0, \n                    \"bytes\": 0, \n                    \"end\": 26.001063, \n                    \"omitted\": false, \n                    \"seconds\": 0.999862015247345, \n                    \"sender\": false, \n                    \"socket\": 5, \n                    \"start\": 25.001201\n                }\n            ], \n            \"sum\": {\n                \"bits_per_second\": 0, \n                \"bytes\": 0, \n                \"end\": 26.001063, \n                \"omitted\": false, \n                \"seconds\": 0.999862015247345, \n                \"sender\": false, \n                \"start\": 25.001201\n            }\n        }, \n        {\n            \"streams\": [\n                {\n                    \"bits_per_second\": 0, \n                    \"bytes\": 0, \n                    \"end\": 27.001096, \n                    \"omitted\": false, \n                    \"seconds\": 1.0000330209732056, \n                    \"sender\": false, \n                    \"socket\": 5, \n                    \"start\": 26.001063\n                }\n            ], \n            \"sum\": {\n                \"bits_per_second\": 0, \n                \"bytes\": 0, \n                \"end\": 27.001096, \n                \"omitted\": false, \n                \"seconds\": 1.0000330209732056, \n                \"sender\": false, \n                \"start\": 26.001063\n            }\n        }, \n        {\n            \"streams\": [\n                {\n                    \"bits_per_second\": 0, \n                    \"bytes\": 0, \n                    \"end\": 28.001118, \n                    \"omitted\": false, \n                    \"seconds\": 1.000022053718567, \n                    \"sender\": false, \n                    \"socket\": 5, \n                    \"start\": 27.001096\n                }\n            ], \n            \"sum\": {\n                \"bits_per_second\": 0, \n                \"bytes\": 0, \n                \"end\": 28.001118, \n                \"omitted\": false, \n                \"seconds\": 1.000022053718567, \n                \"sender\": false, \n                \"start\": 27.001096\n            }\n        }, \n        {\n            \"streams\": [\n                {\n                    \"bits_per_second\": 0, \n                    \"bytes\": 0, \n                    \"end\": 29.00109, \n                    \"omitted\": false, \n                    \"seconds\": 0.9999719858169556, \n                    \"sender\": false, \n                    \"socket\": 5, \n                    \"start\": 28.001118\n                }\n            ], \n            \"sum\": {\n                \"bits_per_second\": 0, \n                \"bytes\": 0, \n                \"end\": 29.00109, \n                \"omitted\": false, \n                \"seconds\": 0.9999719858169556, \n                \"sender\": false, \n                \"start\": 28.001118\n            }\n        }, \n        {\n            \"streams\": [\n                {\n                    \"bits_per_second\": 0, \n                    \"bytes\": 0, \n                    \"end\": 30.001118, \n                    \"omitted\": false, \n                    \"seconds\": 1.0000280141830444, \n                    \"sender\": false, \n                    \"socket\": 5, \n                    \"start\": 29.00109\n                }\n            ], \n            \"sum\": {\n                \"bits_per_second\": 0, \n                \"bytes\": 0, \n                \"end\": 30.001118, \n                \"omitted\": false, \n                \"seconds\": 1.0000280141830444, \n                \"sender\": false, \n                \"start\": 29.00109\n            }\n        }, \n        {\n            \"streams\": [\n                {\n                    \"bits_per_second\": 605186.4168187337, \n                    \"bytes\": 75648, \n                    \"end\": 31.001114, \n                    \"omitted\": false, \n                    \"seconds\": 0.9999960064888, \n                    \"sender\": false, \n                    \"socket\": 5, \n                    \"start\": 30.001118\n                }\n            ], \n            \"sum\": {\n                \"bits_per_second\": 605186.4168187337, \n                \"bytes\": 75648, \n                \"end\": 31.001114, \n                \"omitted\": false, \n                \"seconds\": 0.9999960064888, \n                \"sender\": false, \n                \"start\": 30.001118\n            }\n        }, \n        {\n            \"streams\": [\n                {\n                    \"bits_per_second\": 0, \n                    \"bytes\": 0, \n                    \"end\": 32.00112, \n                    \"omitted\": false, \n                    \"seconds\": 1.0000059604644775, \n                    \"sender\": false, \n                    \"socket\": 5, \n                    \"start\": 31.001114\n                }\n            ], \n            \"sum\": {\n                \"bits_per_second\": 0, \n                \"bytes\": 0, \n                \"end\": 32.00112, \n                \"omitted\": false, \n                \"seconds\": 1.0000059604644775, \n                \"sender\": false, \n                \"start\": 31.001114\n            }\n        }, \n        {\n            \"streams\": [\n                {\n                    \"bits_per_second\": 0, \n                    \"bytes\": 0, \n                    \"end\": 33.00019, \n                    \"omitted\": false, \n                    \"seconds\": 0.9990699887275696, \n                    \"sender\": false, \n                    \"socket\": 5, \n                    \"start\": 32.00112\n                }\n            ], \n            \"sum\": {\n                \"bits_per_second\": 0, \n                \"bytes\": 0, \n                \"end\": 33.00019, \n                \"omitted\": false, \n                \"seconds\": 0.9990699887275696, \n                \"sender\": false, \n                \"start\": 32.00112\n            }\n        }, \n        {\n            \"streams\": [\n                {\n                    \"bits_per_second\": 0, \n                    \"bytes\": 0, \n                    \"end\": 34.000054, \n                    \"omitted\": false, \n                    \"seconds\": 0.9998639822006226, \n                    \"sender\": false, \n                    \"socket\": 5, \n                    \"start\": 33.00019\n                }\n            ], \n            \"sum\": {\n                \"bits_per_second\": 0, \n                \"bytes\": 0, \n                \"end\": 34.000054, \n                \"omitted\": false, \n                \"seconds\": 0.9998639822006226, \n                \"sender\": false, \n                \"start\": 33.00019\n            }\n        }, \n        {\n            \"streams\": [\n                {\n                    \"bits_per_second\": 0, \n                    \"bytes\": 0, \n                    \"end\": 35.000133, \n                    \"omitted\": false, \n                    \"seconds\": 1.0000790357589722, \n                    \"sender\": false, \n                    \"socket\": 5, \n                    \"start\": 34.000054\n                }\n            ], \n            \"sum\": {\n                \"bits_per_second\": 0, \n                \"bytes\": 0, \n                \"end\": 35.000133, \n                \"omitted\": false, \n                \"seconds\": 1.0000790357589722, \n                \"sender\": false, \n                \"start\": 34.000054\n            }\n        }, \n        {\n            \"streams\": [\n                {\n                    \"bits_per_second\": 0, \n                    \"bytes\": 0, \n                    \"end\": 36.000137, \n                    \"omitted\": false, \n                    \"seconds\": 1.0000040531158447, \n                    \"sender\": false, \n                    \"socket\": 5, \n                    \"start\": 35.000133\n                }\n            ], \n            \"sum\": {\n                \"bits_per_second\": 0, \n                \"bytes\": 0, \n                \"end\": 36.000137, \n                \"omitted\": false, \n                \"seconds\": 1.0000040531158447, \n                \"sender\": false, \n                \"start\": 35.000133\n            }\n        }, \n        {\n            \"streams\": [\n                {\n                    \"bits_per_second\": 0, \n                    \"bytes\": 0, \n                    \"end\": 37.001147, \n                    \"omitted\": false, \n                    \"seconds\": 1.0010099411010742, \n                    \"sender\": false, \n                    \"socket\": 5, \n                    \"start\": 36.000137\n                }\n            ], \n            \"sum\": {\n                \"bits_per_second\": 0, \n                \"bytes\": 0, \n                \"end\": 37.001147, \n                \"omitted\": false, \n                \"seconds\": 1.0010099411010742, \n                \"sender\": false, \n                \"start\": 36.000137\n            }\n        }, \n        {\n            \"streams\": [\n                {\n                    \"bits_per_second\": 0, \n                    \"bytes\": 0, \n                    \"end\": 38.00017, \n                    \"omitted\": false, \n                    \"seconds\": 0.9990230202674866, \n                    \"sender\": false, \n                    \"socket\": 5, \n                    \"start\": 37.001147\n                }\n            ], \n            \"sum\": {\n                \"bits_per_second\": 0, \n                \"bytes\": 0, \n                \"end\": 38.00017, \n                \"omitted\": false, \n                \"seconds\": 0.9990230202674866, \n                \"sender\": false, \n                \"start\": 37.001147\n            }\n        }, \n        {\n            \"streams\": [\n                {\n                    \"bits_per_second\": 0, \n                    \"bytes\": 0, \n                    \"end\": 39.000078, \n                    \"omitted\": false, \n                    \"seconds\": 0.9999079704284668, \n                    \"sender\": false, \n                    \"socket\": 5, \n                    \"start\": 38.00017\n                }\n            ], \n            \"sum\": {\n                \"bits_per_second\": 0, \n                \"bytes\": 0, \n                \"end\": 39.000078, \n                \"omitted\": false, \n                \"seconds\": 0.9999079704284668, \n                \"sender\": false, \n                \"start\": 38.00017\n            }\n        }, \n        {\n            \"streams\": [\n                {\n                    \"bits_per_second\": 0, \n                    \"bytes\": 0, \n                    \"end\": 40.001118, \n                    \"omitted\": false, \n                    \"seconds\": 1.001039981842041, \n                    \"sender\": false, \n                    \"socket\": 5, \n                    \"start\": 39.000078\n                }\n            ], \n            \"sum\": {\n                \"bits_per_second\": 0, \n                \"bytes\": 0, \n                \"end\": 40.001118, \n                \"omitted\": false, \n                \"seconds\": 1.001039981842041, \n                \"sender\": false, \n                \"start\": 39.000078\n            }\n        }, \n        {\n            \"streams\": [\n                {\n                    \"bits_per_second\": 0, \n                    \"bytes\": 0, \n                    \"end\": 41.001126, \n                    \"omitted\": false, \n                    \"seconds\": 1.0000079870224, \n                    \"sender\": false, \n                    \"socket\": 5, \n                    \"start\": 40.001118\n                }\n            ], \n            \"sum\": {\n                \"bits_per_second\": 0, \n                \"bytes\": 0, \n                \"end\": 41.001126, \n                \"omitted\": false, \n                \"seconds\": 1.0000079870224, \n                \"sender\": false, \n                \"start\": 40.001118\n            }\n        }, \n        {\n            \"streams\": [\n                {\n                    \"bits_per_second\": 0, \n                    \"bytes\": 0, \n                    \"end\": 42.000063, \n                    \"omitted\": false, \n                    \"seconds\": 0.9989370107650757, \n                    \"sender\": false, \n                    \"socket\": 5, \n                    \"start\": 41.001126\n                }\n            ], \n            \"sum\": {\n                \"bits_per_second\": 0, \n                \"bytes\": 0, \n                \"end\": 42.000063, \n                \"omitted\": false, \n                \"seconds\": 0.9989370107650757, \n                \"sender\": false, \n                \"start\": 41.001126\n            }\n        }, \n        {\n            \"streams\": [\n                {\n                    \"bits_per_second\": 0, \n                    \"bytes\": 0, \n                    \"end\": 43.000063, \n                    \"omitted\": false, \n                    \"seconds\": 1, \n                    \"sender\": false, \n                    \"socket\": 5, \n                    \"start\": 42.000063\n                }\n            ], \n            \"sum\": {\n                \"bits_per_second\": 0, \n                \"bytes\": 0, \n                \"end\": 43.000063, \n                \"omitted\": false, \n                \"seconds\": 1, \n                \"sender\": false, \n                \"start\": 42.000063\n            }\n        }, \n        {\n            \"streams\": [\n                {\n                    \"bits_per_second\": 0, \n                    \"bytes\": 0, \n                    \"end\": 44.00019, \n                    \"omitted\": false, \n                    \"seconds\": 1.0001269578933716, \n                    \"sender\": false, \n                    \"socket\": 5, \n                    \"start\": 43.000063\n                }\n            ], \n            \"sum\": {\n                \"bits_per_second\": 0, \n                \"bytes\": 0, \n                \"end\": 44.00019, \n                \"omitted\": false, \n                \"seconds\": 1.0001269578933716, \n                \"sender\": false, \n                \"start\": 43.000063\n            }\n        }, \n        {\n            \"streams\": [\n                {\n                    \"bits_per_second\": 1048600.1255550662, \n                    \"bytes\": 131072, \n                    \"end\": 45.000167, \n                    \"omitted\": false, \n                    \"seconds\": 0.9999769926071167, \n                    \"sender\": false, \n                    \"socket\": 5, \n                    \"start\": 44.00019\n                }\n            ], \n            \"sum\": {\n                \"bits_per_second\": 1048600.1255550662, \n                \"bytes\": 131072, \n                \"end\": 45.000167, \n                \"omitted\": false, \n                \"seconds\": 0.9999769926071167, \n                \"sender\": false, \n                \"start\": 44.00019\n            }\n        }, \n        {\n            \"streams\": [\n                {\n                    \"bits_per_second\": 0, \n                    \"bytes\": 0, \n                    \"end\": 46.000039, \n                    \"omitted\": false, \n                    \"seconds\": 0.9998720288276672, \n                    \"sender\": false, \n                    \"socket\": 5, \n                    \"start\": 45.000167\n                }\n            ], \n            \"sum\": {\n                \"bits_per_second\": 0, \n                \"bytes\": 0, \n                \"end\": 46.000039, \n                \"omitted\": false, \n                \"seconds\": 0.9998720288276672, \n                \"sender\": false, \n                \"start\": 45.000167\n            }\n        }, \n        {\n            \"streams\": [\n                {\n                    \"bits_per_second\": 0, \n                    \"bytes\": 0, \n                    \"end\": 47.001078, \n                    \"omitted\": false, \n                    \"seconds\": 1.0010390281677246, \n                    \"sender\": false, \n                    \"socket\": 5, \n                    \"start\": 46.000039\n                }\n            ], \n            \"sum\": {\n                \"bits_per_second\": 0, \n                \"bytes\": 0, \n                \"end\": 47.001078, \n                \"omitted\": false, \n                \"seconds\": 1.0010390281677246, \n                \"sender\": false, \n                \"start\": 46.000039\n            }\n        }, \n        {\n            \"streams\": [\n                {\n                    \"bits_per_second\": 0, \n                    \"bytes\": 0, \n                    \"end\": 48.001104, \n                    \"omitted\": false, \n                    \"seconds\": 1.000025987625122, \n                    \"sender\": false, \n                    \"socket\": 5, \n                    \"start\": 47.001078\n                }\n            ], \n            \"sum\": {\n                \"bits_per_second\": 0, \n                \"bytes\": 0, \n                \"end\": 48.001104, \n                \"omitted\": false, \n                \"seconds\": 1.000025987625122, \n                \"sender\": false, \n                \"start\": 47.001078\n            }\n        }, \n        {\n            \"streams\": [\n                {\n                    \"bits_per_second\": 0, \n                    \"bytes\": 0, \n                    \"end\": 49.001095, \n                    \"omitted\": false, \n                    \"seconds\": 0.999990999698639, \n                    \"sender\": false, \n                    \"socket\": 5, \n                    \"start\": 48.001104\n                }\n            ], \n            \"sum\": {\n                \"bits_per_second\": 0, \n                \"bytes\": 0, \n                \"end\": 49.001095, \n                \"omitted\": false, \n                \"seconds\": 0.999990999698639, \n                \"sender\": false, \n                \"start\": 48.001104\n            }\n        }, \n        {\n            \"streams\": [\n                {\n                    \"bits_per_second\": 0, \n                    \"bytes\": 0, \n                    \"end\": 50.001114, \n                    \"omitted\": false, \n                    \"seconds\": 1.0000189542770386, \n                    \"sender\": false, \n                    \"socket\": 5, \n                    \"start\": 49.001095\n                }\n            ], \n            \"sum\": {\n                \"bits_per_second\": 0, \n                \"bytes\": 0, \n                \"end\": 50.001114, \n                \"omitted\": false, \n                \"seconds\": 1.0000189542770386, \n                \"sender\": false, \n                \"start\": 49.001095\n            }\n        }, \n        {\n            \"streams\": [\n                {\n                    \"bits_per_second\": 1048578.1250043064, \n                    \"bytes\": 131072, \n                    \"end\": 51.001112, \n                    \"omitted\": false, \n                    \"seconds\": 0.9999979734420776, \n                    \"sender\": false, \n                    \"socket\": 5, \n                    \"start\": 50.001114\n                }\n            ], \n            \"sum\": {\n                \"bits_per_second\": 1048578.1250043064, \n                \"bytes\": 131072, \n                \"end\": 51.001112, \n                \"omitted\": false, \n                \"seconds\": 0.9999979734420776, \n                \"sender\": false, \n                \"start\": 50.001114\n            }\n        }, \n        {\n            \"streams\": [\n                {\n                    \"bits_per_second\": 16777434.00283269, \n                    \"bytes\": 2097152, \n                    \"end\": 52.001099, \n                    \"omitted\": false, \n                    \"seconds\": 0.999987006187439, \n                    \"sender\": false, \n                    \"socket\": 5, \n                    \"start\": 51.001112\n                }\n            ], \n            \"sum\": {\n                \"bits_per_second\": 16777434.00283269, \n                \"bytes\": 2097152, \n                \"end\": 52.001099, \n                \"omitted\": false, \n                \"seconds\": 0.999987006187439, \n                \"sender\": false, \n                \"start\": 51.001112\n            }\n        }, \n        {\n            \"streams\": [\n                {\n                    \"bits_per_second\": 14680768.40879876, \n                    \"bytes\": 1835008, \n                    \"end\": 53.001051, \n                    \"omitted\": false, \n                    \"seconds\": 0.9999520182609558, \n                    \"sender\": false, \n                    \"socket\": 5, \n                    \"start\": 52.001099\n                }\n            ], \n            \"sum\": {\n                \"bits_per_second\": 14680768.40879876, \n                \"bytes\": 1835008, \n                \"end\": 53.001051, \n                \"omitted\": false, \n                \"seconds\": 0.9999520182609558, \n                \"sender\": false, \n                \"start\": 52.001099\n            }\n        }, \n        {\n            \"streams\": [\n                {\n                    \"bits_per_second\": 22019875.502207972, \n                    \"bytes\": 2752512, \n                    \"end\": 54.001061, \n                    \"omitted\": false, \n                    \"seconds\": 1.0000100135803223, \n                    \"sender\": false, \n                    \"socket\": 5, \n                    \"start\": 53.001051\n                }\n            ], \n            \"sum\": {\n                \"bits_per_second\": 22019875.502207972, \n                \"bytes\": 2752512, \n                \"end\": 54.001061, \n                \"omitted\": false, \n                \"seconds\": 1.0000100135803223, \n                \"sender\": false, \n                \"start\": 53.001051\n            }\n        }, \n        {\n            \"streams\": [\n                {\n                    \"bits_per_second\": 19920851.84472523, \n                    \"bytes\": 2490368, \n                    \"end\": 55.001166, \n                    \"omitted\": false, \n                    \"seconds\": 1.0001050233840942, \n                    \"sender\": false, \n                    \"socket\": 5, \n                    \"start\": 54.001061\n                }\n            ], \n            \"sum\": {\n                \"bits_per_second\": 19920851.84472523, \n                \"bytes\": 2490368, \n                \"end\": 55.001166, \n                \"omitted\": false, \n                \"seconds\": 1.0001050233840942, \n                \"sender\": false, \n                \"start\": 54.001061\n            }\n        }, \n        {\n            \"streams\": [\n                {\n                    \"bits_per_second\": 17827254.119917214, \n                    \"bytes\": 2228224, \n                    \"end\": 56.001084, \n                    \"omitted\": false, \n                    \"seconds\": 0.999917984008789, \n                    \"sender\": false, \n                    \"socket\": 5, \n                    \"start\": 55.001166\n                }\n            ], \n            \"sum\": {\n                \"bits_per_second\": 17827254.119917214, \n                \"bytes\": 2228224, \n                \"end\": 56.001084, \n                \"omitted\": false, \n                \"seconds\": 0.999917984008789, \n                \"sender\": false, \n                \"start\": 55.001166\n            }\n        }, \n        {\n            \"streams\": [\n                {\n                    \"bits_per_second\": 12582799.501005819, \n                    \"bytes\": 1572864, \n                    \"end\": 57.001093, \n                    \"omitted\": false, \n                    \"seconds\": 1.0000089406967163, \n                    \"sender\": false, \n                    \"socket\": 5, \n                    \"start\": 56.001084\n                }\n            ], \n            \"sum\": {\n                \"bits_per_second\": 12582799.501005819, \n                \"bytes\": 1572864, \n                \"end\": 57.001093, \n                \"omitted\": false, \n                \"seconds\": 1.0000089406967163, \n                \"sender\": false, \n                \"start\": 56.001084\n            }\n        }, \n        {\n            \"streams\": [\n                {\n                    \"bits_per_second\": 0, \n                    \"bytes\": 0, \n                    \"end\": 58.001127, \n                    \"omitted\": false, \n                    \"seconds\": 1.000033974647522, \n                    \"sender\": false, \n                    \"socket\": 5, \n                    \"start\": 57.001093\n                }\n            ], \n            \"sum\": {\n                \"bits_per_second\": 0, \n                \"bytes\": 0, \n                \"end\": 58.001127, \n                \"omitted\": false, \n                \"seconds\": 1.000033974647522, \n                \"sender\": false, \n                \"start\": 57.001093\n            }\n        }, \n        {\n            \"streams\": [\n                {\n                    \"bits_per_second\": 0, \n                    \"bytes\": 0, \n                    \"end\": 59.001117, \n                    \"omitted\": false, \n                    \"seconds\": 0.9999899864196777, \n                    \"sender\": false, \n                    \"socket\": 5, \n                    \"start\": 58.001127\n                }\n            ], \n            \"sum\": {\n                \"bits_per_second\": 0, \n                \"bytes\": 0, \n                \"end\": 59.001117, \n                \"omitted\": false, \n                \"seconds\": 0.9999899864196777, \n                \"sender\": false, \n                \"start\": 58.001127\n            }\n        }, \n        {\n            \"streams\": [\n                {\n                    \"bits_per_second\": 0, \n                    \"bytes\": 0, \n                    \"end\": 60.001133, \n                    \"omitted\": false, \n                    \"seconds\": 1.0000159740448, \n                    \"sender\": false, \n                    \"socket\": 5, \n                    \"start\": 59.001117\n                }\n            ], \n            \"sum\": {\n                \"bits_per_second\": 0, \n                \"bytes\": 0, \n                \"end\": 60.001133, \n                \"omitted\": false, \n                \"seconds\": 1.0000159740448, \n                \"sender\": false, \n                \"start\": 59.001117\n            }\n        }\n    ], \n    \"start\": {\n        \"accepted_connection\": {\n            \"host\": \"172.16.0.2\", \n            \"port\": 38229\n        }, \n        \"connected\": [\n            {\n                \"local_host\": \"172.16.0.1\", \n                \"local_port\": 5201, \n                \"remote_host\": \"172.16.0.2\", \n                \"remote_port\": 58621, \n                \"socket\": 5\n            }\n        ], \n        \"cookie\": \"r6efeya7vefuyv6b3ozp6b6ya7ee55heeohw\", \n        \"fq_rate\": 0, \n        \"rcvbuf_actual\": 87380, \n        \"sndbuf_actual\": 65536, \n        \"sock_bufsize\": 0, \n        \"system_info\": \"REDACTED\", \n        \"target_bitrate\": 0, \n        \"tcp_mss_default\": 0, \n        \"test_start\": {\n            \"bidir\": 0, \n            \"blksize\": 131072, \n            \"blocks\": 0, \n            \"bytes\": 0, \n            \"duration\": 60, \n            \"fqrate\": 0, \n            \"interval\": 1, \n            \"num_streams\": 1, \n            \"omit\": 0, \n            \"protocol\": \"TCP\", \n            \"reverse\": 0, \n            \"target_bitrate\": 0, \n            \"tos\": 0\n        }, \n        \"timestamp\": {\n            \"time\": \"Wed, 16 Oct 2024 02:43:09 GMT\", \n            \"timesecs\": 1729046589\n        }, \n        \"version\": \"iperf 3.17.1\"\n    }\n}\n","summary":{"streams":[{"end":60.000695,"rtt":108251,"start":0,"stream-id":5,"retransmits":909,"throughput-bits":6588476.2168171555,"throughput-bytes":49414144}],"summary":{"end":60.000695,"start":0,"retransmits":909,"throughput-bits":6588476.2168171555,"throughput-bytes":49414144,"receiver-throughput-bits":6072353.230326443}},"intervals":[{"streams":[{"end":1.000216,"rtt":73948,"start":0,"omitted":false,"stream-id":5,"retransmits":281,"tcp-window-size":202720,"throughput-bits":49272428.7990084,"throughput-bytes":6160384}],"summary":{"end":1.000216,"start":0,"omitted":false,"retransmits":281,"throughput-bits":49272428.7990084,"throughput-bytes":6160384}},{"streams":[{"end":2.000346,"rtt":80229,"start":1.000216,"omitted":false,"stream-id":5,"retransmits":0,"tcp-window-size":221544,"throughput-bits":20968792.85468525,"throughput-bytes":2621440}],"summary":{"end":2.000346,"start":1.000216,"omitted":false,"retransmits":0,"throughput-bits":20968792.85468525,"throughput-bytes":2621440}},{"streams":[{"end":3.000375,"rtt":86812,"start":2.000346,"omitted":false,"stream-id":5,"retransmits":0,"tcp-window-size":237472,"throughput-bits":20970912.517597463,"throughput-bytes":2621440}],"summary":{"end":3.000375,"start":2.000346,"omitted":false,"retransmits":0,"throughput-bits":20970912.517597463,"throughput-bytes":2621440}},{"streams":[{"end":4.000409,"rtt":95376,"start":3.000375,"omitted":false,"stream-id":5,"retransmits":0,"tcp-window-size":262088,"throughput-bits":20970807.524206113,"throughput-bytes":2621440}],"summary":{"end":4.000409,"start":3.000375,"omitted":false,"retransmits":0,"throughput-bits":20970807.524206113,"throughput-bytes":2621440}},{"streams":[{"end":5.000446,"rtt":109616,"start":4.000409,"omitted":false,"stream-id":5,"retransmits":0,"tcp-window-size":304080,"throughput-bits":20970745.028638974,"throughput-bytes":2621440}],"summary":{"end":5.000446,"start":4.000409,"omitted":false,"retransmits":0,"throughput-bits":20970745.028638974,"throughput-bytes":2621440}},{"streams":[{"end":6.00046,"rtt":127532,"start":5.000446,"omitted":false,"stream-id":5,"retransmits":0,"tcp-window-size":353312,"throughput-bits":20971227.504079584,"throughput-bytes":2621440}],"summary":{"end":6.00046,"start":5.000446,"omitted":false,"retransmits":0,"throughput-bits":20971227.504079584,"throughput-bytes":2621440}},{"streams":[{"end":7.000483,"rtt":147179,"start":6.00046,"omitted":false,"stream-id":5,"retransmits":3,"tcp-window-size":276568,"throughput-bits":20971037.51110081,"throughput-bytes":2621440}],"summary":{"end":7.000483,"start":6.00046,"omitted":false,"retransmits":3,"throughput-bits":20971037.51110081,"throughput-bytes":2621440}},{"streams":[{"end":8.000066,"rtt":79984,"start":7.000483,"omitted":false,"stream-id":5,"retransmits":2,"tcp-window-size":220096,"throughput-bits":31470402.972201914,"throughput-bytes":3932160}],"summary":{"end":8.000066,"start":7.000483,"omitted":false,"retransmits":2,"throughput-bits":31470402.972201914,"throughput-bytes":3932160}},{"streams":[{"end":9.000574,"rtt":85695,"start":8.000066,"omitted":false,"stream-id":5,"retransmits":0,"tcp-window-size":234576,"throughput-bits":10480436.454099307,"throughput-bytes":1310720}],"summary":{"end":9.000574,"start":8.000066,"omitted":false,"retransmits":0,"throughput-bits":10480436.454099307,"throughput-bytes":1310720}},{"streams":[{"end":10.00103,"rtt":85695,"start":9.000574,"omitted":false,"stream-id":5,"retransmits":2,"tcp-window-size":1448,"throughput-bits":0,"throughput-bytes":0}],"summary":{"end":10.00103,"start":9.000574,"omitted":false,"retransmits":2,"throughput-bits":0,"throughput-bytes":0}},{"streams":[{"end":11.001017,"rtt":85695,"start":10.00103,"omitted":false,"stream-id":5,"retransmits":0,"tcp-window-size":1448,"throughput-bits":0,"throughput-bytes":0}],"summary":{"end":11.001017,"start":10.00103,"omitted":false,"retransmits":0,"throughput-bits":0,"throughput-bytes":0}},{"streams":[{"end":12.001018,"rtt":85695,"start":11.001017,"omitted":false,"stream-id":5,"retransmits":1,"tcp-window-size":1448,"throughput-bits":0,"throughput-bytes":0}],"summary":{"end":12.001018,"start":11.001017,"omitted":false,"retransmits":1,"throughput-bits":0,"throughput-bytes":0}},{"streams":[{"end":13.001018,"rtt":85695,"start":12.001018,"omitted":false,"stream-id":5,"retransmits":0,"tcp-window-size":1448,"throughput-bits":0,"throughput-bytes":0}],"summary":{"end":13.001018,"start":12.001018,"omitted":false,"retransmits":0,"throughput-bits":0,"throughput-bytes":0}},{"streams":[{"end":14.000163,"rtt":43791,"start":13.001018,"omitted":false,"stream-id":5,"retransmits":163,"tcp-window-size":121632,"throughput-bits":10494733.2974262,"throughput-bytes":1310720}],"summary":{"end":14.000163,"start":13.001018,"omitted":false,"retransmits":163,"throughput-bits":10494733.2974262,"throughput-bytes":1310720}},{"streams":[{"end":15.000503,"rtt":33356,"start":14.000163,"omitted":false,"stream-id":5,"retransmits":33,"tcp-window-size":92672,"throughput-bits":10482196.21163421,"throughput-bytes":1310720}],"summary":{"end":15.000503,"start":14.000163,"omitted":false,"retransmits":33,"throughput-bits":10482196.21163421,"throughput-bytes":1310720}},{"streams":[{"end":16.000663,"rtt":28922,"start":15.000503,"omitted":false,"stream-id":5,"retransmits":47,"tcp-window-size":1448,"throughput-bits":10484082.768321622,"throughput-bytes":1310720}],"summary":{"end":16.000663,"start":15.000503,"omitted":false,"retransmits":47,"throughput-bits":10484082.768321622,"throughput-bytes":1310720}},{"streams":[{"end":17.001019,"rtt":39034,"start":16.000663,"omitted":false,"stream-id":5,"retransmits":56,"tcp-window-size":11584,"throughput-bits":0,"throughput-bytes":0}],"summary":{"end":17.001019,"start":16.000663,"omitted":false,"retransmits":56,"throughput-bits":0,"throughput-bytes":0}},{"streams":[{"end":18.000067,"rtt":16376,"start":17.001019,"omitted":false,"stream-id":5,"retransmits":32,"tcp-window-size":28960,"throughput-bits":10495752.012449672,"throughput-bytes":1310720}],"summary":{"end":18.000067,"start":17.001019,"omitted":false,"retransmits":32,"throughput-bits":10495752.012449672,"throughput-bytes":1310720}},{"streams":[{"end":19.000382,"rtt":40851,"start":18.000067,"omitted":false,"stream-id":5,"retransmits":0,"tcp-window-size":75296,"throughput-bits":10482458.539798005,"throughput-bytes":1310720}],"summary":{"end":19.000382,"start":18.000067,"omitted":false,"retransmits":0,"throughput-bits":10482458.539798005,"throughput-bytes":1310720}},{"streams":[{"end":20.00039,"rtt":33796,"start":19.000382,"omitted":false,"stream-id":5,"retransmits":46,"tcp-window-size":72400,"throughput-bits":10485676.250668908,"throughput-bytes":1310720}],"summary":{"end":20.00039,"start":19.000382,"omitted":false,"retransmits":46,"throughput-bits":10485676.250668908,"throughput-bytes":1310720}},{"streams":[{"end":21.000744,"rtt":249721,"start":20.00039,"omitted":false,"stream-id":5,"retransmits":17,"tcp-window-size":23168,"throughput-bits":10482048.813951321,"throughput-bytes":1310720}],"summary":{"end":21.000744,"start":20.00039,"omitted":false,"retransmits":17,"throughput-bits":10482048.813951321,"throughput-bytes":1310720}},{"streams":[{"end":22.001019,"rtt":186018,"start":21.000744,"omitted":false,"stream-id":5,"retransmits":36,"tcp-window-size":5792,"throughput-bits":0,"throughput-bytes":0}],"summary":{"end":22.001019,"start":21.000744,"omitted":false,"retransmits":36,"throughput-bits":0,"throughput-bytes":0}},{"streams":[{"end":23.001042,"rtt":186018,"start":22.001019,"omitted":false,"stream-id":5,"retransmits":0,"tcp-window-size":5792,"throughput-bits":0,"throughput-bytes":0}],"summary":{"end":23.001042,"start":22.001019,"omitted":false,"retransmits":0,"throughput-bits":0,"throughput-bytes":0}},{"streams":[{"end":24.001021,"rtt":186018,"start":23.001042,"omitted":false,"stream-id":5,"retransmits":1,"tcp-window-size":1448,"throughput-bits":0,"throughput-bytes":0}],"summary":{"end":24.001021,"start":23.001042,"omitted":false,"retransmits":1,"throughput-bits":0,"throughput-bytes":0}},{"streams":[{"end":25.001018,"rtt":186018,"start":24.001021,"omitted":false,"stream-id":5,"retransmits":0,"tcp-window-size":1448,"throughput-bits":0,"throughput-bytes":0}],"summary":{"end":25.001018,"start":24.001021,"omitted":false,"retransmits":0,"throughput-bits":0,"throughput-bytes":0}},{"streams":[{"end":26.001019,"rtt":186018,"start":25.001018,"omitted":false,"stream-id":5,"retransmits":0,"tcp-window-size":1448,"throughput-bits":0,"throughput-bytes":0}],"summary":{"end":26.001019,"start":25.001018,"omitted":false,"retransmits":0,"throughput-bits":0,"throughput-bytes":0}},{"streams":[{"end":27.001018,"rtt":186018,"start":26.001019,"omitted":false,"stream-id":5,"retransmits":1,"tcp-window-size":1448,"throughput-bits":0,"throughput-bytes":0}],"summary":{"end":27.001018,"start":26.001019,"omitted":false,"retransmits":1,"throughput-bits":0,"throughput-bytes":0}},{"streams":[{"end":28.001019,"rtt":186018,"start":27.001018,"omitted":false,"stream-id":5,"retransmits":0,"tcp-window-size":1448,"throughput-bits":0,"throughput-bytes":0}],"summary":{"end":28.001019,"start":27.001018,"omitted":false,"retransmits":0,"throughput-bits":0,"throughput-bytes":0}},{"streams":[{"end":29.001027,"rtt":186018,"start":28.001019,"omitted":false,"stream-id":5,"retransmits":0,"tcp-window-size":1448,"throughput-bits":0,"throughput-bytes":0}],"summary":{"end":29.001027,"start":28.001019,"omitted":false,"retransmits":0,"throughput-bits":0,"throughput-bytes":0}},{"streams":[{"end":30.001019,"rtt":186018,"start":29.001027,"omitted":false,"stream-id":5,"retransmits":0,"tcp-window-size":1448,"throughput-bits":0,"throughput-bytes":0}],"summary":{"end":30.001019,"start":29.001027,"omitted":false,"retransmits":0,"throughput-bits":0,"throughput-bytes":0}},{"streams":[{"end":31.001027,"rtt":186018,"start":30.001019,"omitted":false,"stream-id":5,"retransmits":0,"tcp-window-size":1448,"throughput-bits":0,"throughput-bytes":0}],"summary":{"end":31.001027,"start":30.001019,"omitted":false,"retransmits":0,"throughput-bits":0,"throughput-bytes":0}},{"streams":[{"end":32.001025,"rtt":186018,"start":31.001027,"omitted":false,"stream-id":5,"retransmits":0,"tcp-window-size":1448,"throughput-bits":0,"throughput-bytes":0}],"summary":{"end":32.001025,"start":31.001027,"omitted":false,"retransmits":0,"throughput-bits":0,"throughput-bytes":0}},{"streams":[{"end":33.001018,"rtt":186018,"start":32.001025,"omitted":false,"stream-id":5,"retransmits":1,"tcp-window-size":1448,"throughput-bits":0,"throughput-bytes":0}],"summary":{"end":33.001018,"start":32.001025,"omitted":false,"retransmits":1,"throughput-bits":0,"throughput-bytes":0}},{"streams":[{"end":34.001018,"rtt":186018,"start":33.001018,"omitted":false,"stream-id":5,"retransmits":0,"tcp-window-size":1448,"throughput-bits":0,"throughput-bytes":0}],"summary":{"end":34.001018,"start":33.001018,"omitted":false,"retransmits":0,"throughput-bits":0,"throughput-bytes":0}},{"streams":[{"end":35.001019,"rtt":186018,"start":34.001018,"omitted":false,"stream-id":5,"retransmits":0,"tcp-window-size":1448,"throughput-bits":0,"throughput-bytes":0}],"summary":{"end":35.001019,"start":34.001018,"omitted":false,"retransmits":0,"throughput-bits":0,"throughput-bytes":0}},{"streams":[{"end":36.001024,"rtt":186018,"start":35.001019,"omitted":false,"stream-id":5,"retransmits":0,"tcp-window-size":1448,"throughput-bits":0,"throughput-bytes":0}],"summary":{"end":36.001024,"start":35.001019,"omitted":false,"retransmits":0,"throughput-bits":0,"throughput-bytes":0}},{"streams":[{"end":37.001019,"rtt":186018,"start":36.001024,"omitted":false,"stream-id":5,"retransmits":0,"tcp-window-size":1448,"throughput-bits":0,"throughput-bytes":0}],"summary":{"end":37.001019,"start":36.001024,"omitted":false,"retransmits":0,"throughput-bits":0,"throughput-bytes":0}},{"streams":[{"end":38.001022,"rtt":186018,"start":37.001019,"omitted":false,"stream-id":5,"retransmits":0,"tcp-window-size":1448,"throughput-bits":0,"throughput-bytes":0}],"summary":{"end":38.001022,"start":37.001019,"omitted":false,"retransmits":0,"throughput-bits":0,"throughput-bytes":0}},{"streams":[{"end":39.001017,"rtt":186018,"start":38.001022,"omitted":false,"stream-id":5,"retransmits":0,"tcp-window-size":1448,"throughput-bits":0,"throughput-bytes":0}],"summary":{"end":39.001017,"start":38.001022,"omitted":false,"retransmits":0,"throughput-bits":0,"throughput-bytes":0}},{"streams":[{"end":40.00102,"rtt":186018,"start":39.001017,"omitted":false,"stream-id":5,"retransmits":0,"tcp-window-size":1448,"throughput-bits":0,"throughput-bytes":0}],"summary":{"end":40.00102,"start":39.001017,"omitted":false,"retransmits":0,"throughput-bits":0,"throughput-bytes":0}},{"streams":[{"end":41.001019,"rtt":186018,"start":40.00102,"omitted":false,"stream-id":5,"retransmits":0,"tcp-window-size":1448,"throughput-bits":0,"throughput-bytes":0}],"summary":{"end":41.001019,"start":40.00102,"omitted":false,"retransmits":0,"throughput-bits":0,"throughput-bytes":0}},{"streams":[{"end":42.001019,"rtt":186018,"start":41.001019,"omitted":false,"stream-id":5,"retransmits":0,"tcp-window-size":1448,"throughput-bits":0,"throughput-bytes":0}],"summary":{"end":42.001019,"start":41.001019,"omitted":false,"retransmits":0,"throughput-bits":0,"throughput-bytes":0}},{"streams":[{"end":43.001019,"rtt":186018,"start":42.001019,"omitted":false,"stream-id":5,"retransmits":0,"tcp-window-size":1448,"throughput-bits":0,"throughput-bytes":0}],"summary":{"end":43.001019,"start":42.001019,"omitted":false,"retransmits":0,"throughput-bits":0,"throughput-bytes":0}},{"streams":[{"end":44.001018,"rtt":173016,"start":43.001019,"omitted":false,"stream-id":5,"retransmits":1,"tcp-window-size":2896,"throughput-bits":0,"throughput-bytes":0}],"summary":{"end":44.001018,"start":43.001019,"omitted":false,"retransmits":1,"throughput-bits":0,"throughput-bytes":0}},{"streams":[{"end":45.001018,"rtt":24076,"start":44.001018,"omitted":false,"stream-id":5,"retransmits":25,"tcp-window-size":44888,"throughput-bits":0,"throughput-bytes":0}],"summary":{"end":45.001018,"start":44.001018,"omitted":false,"retransmits":25,"throughput-bits":0,"throughput-bytes":0}},{"streams":[{"end":46.001017,"rtt":24076,"start":45.001018,"omitted":false,"stream-id":5,"retransmits":1,"tcp-window-size":1448,"throughput-bits":0,"throughput-bytes":0}],"summary":{"end":46.001017,"start":45.001018,"omitted":false,"retransmits":1,"throughput-bits":0,"throughput-bytes":0}},{"streams":[{"end":47.001025,"rtt":24076,"start":46.001017,"omitted":false,"stream-id":5,"retransmits":1,"tcp-window-size":1448,"throughput-bits":0,"throughput-bytes":0}],"summary":{"end":47.001025,"start":46.001017,"omitted":false,"retransmits":1,"throughput-bits":0,"throughput-bytes":0}},{"streams":[{"end":48.001029,"rtt":24076,"start":47.001025,"omitted":false,"stream-id":5,"retransmits":0,"tcp-window-size":1448,"throughput-bits":0,"throughput-bytes":0}],"summary":{"end":48.001029,"start":47.001025,"omitted":false,"retransmits":0,"throughput-bits":0,"throughput-bytes":0}},{"streams":[{"end":49.001025,"rtt":24076,"start":48.001029,"omitted":false,"stream-id":5,"retransmits":0,"tcp-window-size":1448,"throughput-bits":0,"throughput-bytes":0}],"summary":{"end":49.001025,"start":48.001029,"omitted":false,"retransmits":0,"throughput-bits":0,"throughput-bytes":0}},{"streams":[{"end":50.001018,"rtt":24076,"start":49.001025,"omitted":false,"stream-id":5,"retransmits":0,"tcp-window-size":1448,"throughput-bits":0,"throughput-bytes":0}],"summary":{"end":50.001018,"start":49.001025,"omitted":false,"retransmits":0,"throughput-bits":0,"throughput-bytes":0}},{"streams":[{"end":51.00102,"rtt":30795,"start":50.001018,"omitted":false,"stream-id":5,"retransmits":41,"tcp-window-size":20272,"throughput-bits":0,"throughput-bytes":0}],"summary":{"end":51.00102,"start":50.001018,"omitted":false,"retransmits":41,"throughput-bits":0,"throughput-bytes":0}},{"streams":[{"end":52.000155,"rtt":33010,"start":51.00102,"omitted":false,"stream-id":5,"retransmits":0,"tcp-window-size":78192,"throughput-bits":20989675.70436846,"throughput-bytes":2621440}],"summary":{"end":52.000155,"start":51.00102,"omitted":false,"retransmits":0,"throughput-bits":20989675.70436846,"throughput-bytes":2621440}},{"streams":[{"end":53.00032,"rtt":28484,"start":52.000155,"omitted":false,"stream-id":5,"retransmits":52,"tcp-window-size":79640,"throughput-bits":10484030.2853781,"throughput-bytes":1310720}],"summary":{"end":53.00032,"start":52.000155,"omitted":false,"retransmits":52,"throughput-bits":10484030.2853781,"throughput-bytes":1310720}},{"streams":[{"end":54.000043,"rtt":42371,"start":53.00032,"omitted":false,"stream-id":5,"retransmits":0,"tcp-window-size":117288,"throughput-bits":20977330.359369516,"throughput-bytes":2621440}],"summary":{"end":54.000043,"start":53.00032,"omitted":false,"retransmits":0,"throughput-bits":20977330.359369516,"throughput-bytes":2621440}},{"streams":[{"end":55.000369,"rtt":52670,"start":54.000043,"omitted":false,"stream-id":5,"retransmits":0,"tcp-window-size":146248,"throughput-bits":20964684.728554178,"throughput-bytes":2621440}],"summary":{"end":55.000369,"start":54.000043,"omitted":false,"retransmits":0,"throughput-bits":20964684.728554178,"throughput-bytes":2621440}},{"streams":[{"end":56.000159,"rtt":38818,"start":55.000369,"omitted":false,"stream-id":5,"retransmits":60,"tcp-window-size":105704,"throughput-bits":20975924.674925193,"throughput-bytes":2621440}],"summary":{"end":56.000159,"start":55.000369,"omitted":false,"retransmits":60,"throughput-bits":20975924.674925193,"throughput-bytes":2621440}},{"streams":[{"end":57.000391,"rtt":36019,"start":56.000159,"omitted":false,"stream-id":5,"retransmits":3,"tcp-window-size":81088,"throughput-bits":10483328.064163582,"throughput-bytes":1310720}],"summary":{"end":57.000391,"start":56.000159,"omitted":false,"retransmits":3,"throughput-bits":10483328.064163582,"throughput-bytes":1310720}},{"streams":[{"end":58.000112,"rtt":36019,"start":57.000391,"omitted":false,"stream-id":5,"retransmits":2,"tcp-window-size":1448,"throughput-bits":0,"throughput-bytes":0}],"summary":{"end":58.000112,"start":57.000391,"omitted":false,"retransmits":2,"throughput-bits":0,"throughput-bytes":0}},{"streams":[{"end":59.00043,"rtt":36019,"start":58.000112,"omitted":false,"stream-id":5,"retransmits":1,"tcp-window-size":1448,"throughput-bits":0,"throughput-bytes":0}],"summary":{"end":59.00043,"start":58.000112,"omitted":false,"retransmits":1,"throughput-bits":0,"throughput-bytes":0}},{"streams":[{"end":60.000695,"rtt":36019,"start":59.00043,"omitted":false,"stream-id":5,"retransmits":0,"tcp-window-size":1448,"throughput-bits":0,"throughput-bytes":0}],"summary":{"end":60.000695,"start":59.00043,"omitted":false,"retransmits":0,"throughput-bits":0,"throughput-bytes":0}}],"succeeded":true}
