{"diags":"Participant 0:\n/usr/bin/iperf3 -p 5201 -B 10.0.0.1 -c 10.0.0.2 -t 60 --json --rsa-public-key-path /var/run/pscheduler-server/runner/tmp/tmplmsp1qxw/tmp9cgwy4ch/public-key --username uuusSGp4RGsLVz91Ym44\n\n{\n    \"end\": {\n        \"cpu_utilization_percent\": {\n            \"host_system\": 2.01050489197682, \n            \"host_total\": 2.0598628625666486, \n            \"host_user\": 0.04935797058982875, \n            \"remote_system\": 5.32159871924289, \n            \"remote_total\": 5.819117194085953, \n            \"remote_user\": 0.4975184748430618\n        }, \n        \"receiver_tcp_congestion\": \"htcp\", \n        \"sender_tcp_congestion\": \"htcp\", \n        \"streams\": [\n            {\n                \"receiver\": {\n                    \"bits_per_second\": 865535784.6175433, \n                    \"bytes\": 6499843216, \n                    \"end\": 60.076945, \n                    \"seconds\": 60.000073, \n                    \"sender\": true, \n                    \"socket\": 5, \n                    \"start\": 0\n                }, \n                \"sender\": {\n                    \"bits_per_second\": 867014010.7329535, \n                    \"bytes\": 6502612992, \n                    \"end\": 60.000073, \n                    \"max_rtt\": 77093, \n                    \"max_snd_cwnd\": 16698336, \n                    \"max_snd_wnd\": 0, \n                    \"mean_rtt\": 77086, \n                    \"min_rtt\": 77068, \n                    \"retransmits\": 0, \n                    \"seconds\": 60.000073, \n                    \"sender\": true, \n                    \"socket\": 5, \n                    \"start\": 0\n                }\n            }\n        ], \n        \"sum_received\": {\n            \"bits_per_second\": 865535784.6175433, \n            \"bytes\": 6499843216, \n            \"end\": 60.076945, \n            \"seconds\": 60.076945, \n            \"sender\": true, \n            \"start\": 0\n        }, \n        \"sum_sent\": {\n            \"bits_per_second\": 867014010.7329535, \n            \"bytes\": 6502612992, \n            \"end\": 60.000073, \n            \"retransmits\": 0, \n            \"seconds\": 60.000073, \n            \"sender\": true, \n            \"start\": 0\n        }\n    }, \n    \"intervals\": [\n        {\n            \"streams\": [\n                {\n                    \"bits_per_second\": 955203089.080411, \n                    \"bytes\": 119406592, \n                    \"end\": 1.000052, \n                    \"omitted\": false, \n                    \"pmtu\": 1500, \n                    \"retransmits\": 0, \n                    \"rtt\": 77091, \n                    \"rttvar\": 9, \n                    \"seconds\": 1.0000519752502441, \n                    \"sender\": true, \n                    \"snd_cwnd\": 16698336, \n                    \"snd_wnd\": -1, \n                    \"socket\": 5, \n                    \"start\": 0\n                }\n            ], \n            \"sum\": {\n                \"bits_per_second\": 955203089.080411, \n                \"bytes\": 119406592, \n                \"end\": 1.000052, \n                \"omitted\": false, \n                \"retransmits\": 0, \n                \"seconds\": 1.0000519752502441, \n                \"sender\": true, \n                \"start\": 0\n            }\n        }, \n        {\n            \"streams\": [\n                {\n                    \"bits_per_second\": 870310298.8195692, \n                    \"bytes\": 108789760, \n                    \"end\": 2.000061, \n                    \"omitted\": false, \n                    \"pmtu\": 1500, \n                    \"retransmits\": 0, \n                    \"rtt\": 77084, \n                    \"rttvar\": 9, \n                    \"seconds\": 1.0000089406967163, \n                    \"sender\": true, \n                    \"snd_cwnd\": 16698336, \n                    \"snd_wnd\": -1, \n                    \"socket\": 5, \n                    \"start\": 1.000052\n                }\n            ], \n            \"sum\": {\n                \"bits_per_second\": 870310298.8195692, \n                \"bytes\": 108789760, \n                \"end\": 2.000061, \n                \"omitted\": false, \n                \"retransmits\": 0, \n                \"seconds\": 1.0000089406967163, \n                \"sender\": true, \n                \"start\": 1.000052\n            }\n        }, \n        {\n            \"streams\": [\n                {\n                    \"bits_per_second\": 859810795.5388423, \n                    \"bytes\": 107479040, \n                    \"end\": 3.000086, \n                    \"omitted\": false, \n                    \"pmtu\": 1500, \n                    \"retransmits\": 0, \n                    \"rtt\": 77090, \n                    \"rttvar\": 8, \n                    \"seconds\": 1.0000250339508057, \n                    \"sender\": true, \n                    \"snd_cwnd\": 16698336, \n                    \"snd_wnd\": -1, \n                    \"socket\": 5, \n                    \"start\": 2.000061\n                }\n            ], \n            \"sum\": {\n                \"bits_per_second\": 859810795.5388423, \n                \"bytes\": 107479040, \n                \"end\": 3.000086, \n                \"omitted\": false, \n                \"retransmits\": 0, \n                \"seconds\": 1.0000250339508057, \n                \"sender\": true, \n                \"start\": 2.000061\n            }\n        }, \n        {\n            \"streams\": [\n                {\n                    \"bits_per_second\": 870316316.2535744, \n                    \"bytes\": 108789760, \n                    \"end\": 4.000088, \n                    \"omitted\": false, \n                    \"pmtu\": 1500, \n                    \"retransmits\": 0, \n                    \"rtt\": 77089, \n                    \"rttvar\": 6, \n                    \"seconds\": 1.0000020265579224, \n                    \"sender\": true, \n                    \"snd_cwnd\": 16698336, \n                    \"snd_wnd\": -1, \n                    \"socket\": 5, \n                    \"start\": 3.000086\n                }\n            ], \n            \"sum\": {\n                \"bits_per_second\": 870316316.2535744, \n                \"bytes\": 108789760, \n                \"end\": 4.000088, \n                \"omitted\": false, \n                \"retransmits\": 0, \n                \"seconds\": 1.0000020265579224, \n                \"sender\": true, \n                \"start\": 3.000086\n            }\n        }, \n        {\n            \"streams\": [\n                {\n                    \"bits_per_second\": 859841801.3545495, \n                    \"bytes\": 107479040, \n                    \"end\": 5.000077, \n                    \"omitted\": false, \n                    \"pmtu\": 1500, \n                    \"retransmits\": 0, \n                    \"rtt\": 77086, \n                    \"rttvar\": 2, \n                    \"seconds\": 0.9999889731407166, \n                    \"sender\": true, \n                    \"snd_cwnd\": 16698336, \n                    \"snd_wnd\": -1, \n                    \"socket\": 5, \n                    \"start\": 4.000088\n                }\n            ], \n            \"sum\": {\n                \"bits_per_second\": 859841801.3545495, \n                \"bytes\": 107479040, \n                \"end\": 5.000077, \n                \"omitted\": false, \n                \"retransmits\": 0, \n                \"seconds\": 0.9999889731407166, \n                \"sender\": true, \n                \"start\": 4.000088\n            }\n        }, \n        {\n            \"streams\": [\n                {\n                    \"bits_per_second\": 870237992.3704302, \n                    \"bytes\": 108789760, \n                    \"end\": 6.000169, \n                    \"omitted\": false, \n                    \"pmtu\": 1500, \n                    \"retransmits\": 0, \n                    \"rtt\": 77087, \n                    \"rttvar\": 9, \n                    \"seconds\": 1.0000920295715332, \n                    \"sender\": true, \n                    \"snd_cwnd\": 16698336, \n                    \"snd_wnd\": -1, \n                    \"socket\": 5, \n                    \"start\": 5.000077\n                }\n            ], \n            \"sum\": {\n                \"bits_per_second\": 870237992.3704302, \n                \"bytes\": 108789760, \n                \"end\": 6.000169, \n                \"omitted\": false, \n                \"retransmits\": 0, \n                \"seconds\": 1.0000920295715332, \n                \"sender\": true, \n                \"start\": 5.000077\n            }\n        }, \n        {\n            \"streams\": [\n                {\n                    \"bits_per_second\": 870412087.6531665, \n                    \"bytes\": 108789760, \n                    \"end\": 7.000061, \n                    \"omitted\": false, \n                    \"pmtu\": 1500, \n                    \"retransmits\": 0, \n                    \"rtt\": 77089, \n                    \"rttvar\": 14, \n                    \"seconds\": 0.999891996383667, \n                    \"sender\": true, \n                    \"snd_cwnd\": 16698336, \n                    \"snd_wnd\": -1, \n                    \"socket\": 5, \n                    \"start\": 6.000169\n                }\n            ], \n            \"sum\": {\n                \"bits_per_second\": 870412087.6531665, \n                \"bytes\": 108789760, \n                \"end\": 7.000061, \n                \"omitted\": false, \n                \"retransmits\": 0, \n                \"seconds\": 0.999891996383667, \n                \"sender\": true, \n                \"start\": 6.000169\n            }\n        }, \n        {\n            \"streams\": [\n                {\n                    \"bits_per_second\": 859850360.3785022, \n                    \"bytes\": 107479040, \n                    \"end\": 8.00004, \n                    \"omitted\": false, \n                    \"pmtu\": 1500, \n                    \"retransmits\": 0, \n                    \"rtt\": 77090, \n                    \"rttvar\": 8, \n                    \"seconds\": 0.999979019165039, \n                    \"sender\": true, \n                    \"snd_cwnd\": 16698336, \n                    \"snd_wnd\": -1, \n                    \"socket\": 5, \n                    \"start\": 7.000061\n                }\n            ], \n            \"sum\": {\n                \"bits_per_second\": 859850360.3785022, \n                \"bytes\": 107479040, \n                \"end\": 8.00004, \n                \"omitted\": false, \n                \"retransmits\": 0, \n                \"seconds\": 0.999979019165039, \n                \"sender\": true, \n                \"start\": 7.000061\n            }\n        }, \n        {\n            \"streams\": [\n                {\n                    \"bits_per_second\": 870298886.673284, \n                    \"bytes\": 108789760, \n                    \"end\": 9.000062, \n                    \"omitted\": false, \n                    \"pmtu\": 1500, \n                    \"retransmits\": 0, \n                    \"rtt\": 77087, \n                    \"rttvar\": 10, \n                    \"seconds\": 1.000022053718567, \n                    \"sender\": true, \n                    \"snd_cwnd\": 16698336, \n                    \"snd_wnd\": -1, \n                    \"socket\": 5, \n                    \"start\": 8.00004\n                }\n            ], \n            \"sum\": {\n                \"bits_per_second\": 870298886.673284, \n                \"bytes\": 108789760, \n                \"end\": 9.000062, \n                \"omitted\": false, \n                \"retransmits\": 0, \n                \"seconds\": 1.000022053718567, \n                \"sender\": true, \n                \"start\": 8.00004\n            }\n        }, \n        {\n            \"streams\": [\n                {\n                    \"bits_per_second\": 859837496.2811615, \n                    \"bytes\": 107479040, \n                    \"end\": 10.000056, \n                    \"omitted\": false, \n                    \"pmtu\": 1500, \n                    \"retransmits\": 0, \n                    \"rtt\": 77086, \n                    \"rttvar\": 14, \n                    \"seconds\": 0.9999939799308777, \n                    \"sender\": true, \n                    \"snd_cwnd\": 16698336, \n                    \"snd_wnd\": -1, \n                    \"socket\": 5, \n                    \"start\": 9.000062\n                }\n            ], \n            \"sum\": {\n                \"bits_per_second\": 859837496.2811615, \n                \"bytes\": 107479040, \n                \"end\": 10.000056, \n                \"omitted\": false, \n                \"retransmits\": 0, \n                \"seconds\": 0.9999939799308777, \n                \"sender\": true, \n                \"start\": 9.000062\n            }\n        }, \n        {\n            \"streams\": [\n                {\n                    \"bits_per_second\": 870312892.5309197, \n                    \"bytes\": 108789760, \n                    \"end\": 11.000062, \n                    \"omitted\": false, \n                    \"pmtu\": 1500, \n                    \"retransmits\": 0, \n                    \"rtt\": 77091, \n                    \"rttvar\": 8, \n                    \"seconds\": 1.0000059604644775, \n                    \"sender\": true, \n                    \"snd_cwnd\": 16698336, \n                    \"snd_wnd\": -1, \n                    \"socket\": 5, \n                    \"start\": 10.000056\n                }\n            ], \n            \"sum\": {\n                \"bits_per_second\": 870312892.5309197, \n                \"bytes\": 108789760, \n                \"end\": 11.000062, \n                \"omitted\": false, \n                \"retransmits\": 0, \n                \"seconds\": 1.0000059604644775, \n                \"sender\": true, \n                \"start\": 10.000056\n            }\n        }, \n        {\n            \"streams\": [\n                {\n                    \"bits_per_second\": 859830577.5035312, \n                    \"bytes\": 107479040, \n                    \"end\": 12.000064, \n                    \"omitted\": false, \n                    \"pmtu\": 1500, \n                    \"retransmits\": 0, \n                    \"rtt\": 77085, \n                    \"rttvar\": 5, \n                    \"seconds\": 1.0000020265579224, \n                    \"sender\": true, \n                    \"snd_cwnd\": 16698336, \n                    \"snd_wnd\": -1, \n                    \"socket\": 5, \n                    \"start\": 11.000062\n                }\n            ], \n            \"sum\": {\n                \"bits_per_second\": 859830577.5035312, \n                \"bytes\": 107479040, \n                \"end\": 12.000064, \n                \"omitted\": false, \n                \"retransmits\": 0, \n                \"seconds\": 1.0000020265579224, \n                \"sender\": true, \n                \"start\": 11.000062\n            }\n        }, \n        {\n            \"streams\": [\n                {\n                    \"bits_per_second\": 870320673.75773, \n                    \"bytes\": 108789760, \n                    \"end\": 13.000061, \n                    \"omitted\": false, \n                    \"pmtu\": 1500, \n                    \"retransmits\": 0, \n                    \"rtt\": 77089, \n                    \"rttvar\": 12, \n                    \"seconds\": 0.9999970197677612, \n                    \"sender\": true, \n                    \"snd_cwnd\": 16698336, \n                    \"snd_wnd\": -1, \n                    \"socket\": 5, \n                    \"start\": 12.000064\n                }\n            ], \n            \"sum\": {\n                \"bits_per_second\": 870320673.75773, \n                \"bytes\": 108789760, \n                \"end\": 13.000061, \n                \"omitted\": false, \n                \"retransmits\": 0, \n                \"seconds\": 0.9999970197677612, \n                \"sender\": true, \n                \"start\": 12.000064\n            }\n        }, \n        {\n            \"streams\": [\n                {\n                    \"bits_per_second\": 859813357.9181844, \n                    \"bytes\": 107479040, \n                    \"end\": 14.000083, \n                    \"omitted\": false, \n                    \"pmtu\": 1500, \n                    \"retransmits\": 0, \n                    \"rtt\": 77086, \n                    \"rttvar\": 5, \n                    \"seconds\": 1.000022053718567, \n                    \"sender\": true, \n                    \"snd_cwnd\": 16698336, \n                    \"snd_wnd\": -1, \n                    \"socket\": 5, \n                    \"start\": 13.000061\n                }\n            ], \n            \"sum\": {\n                \"bits_per_second\": 859813357.9181844, \n                \"bytes\": 107479040, \n                \"end\": 14.000083, \n                \"omitted\": false, \n                \"retransmits\": 0, \n                \"seconds\": 1.000022053718567, \n                \"sender\": true, \n                \"start\": 13.000061\n            }\n        }, \n        {\n            \"streams\": [\n                {\n                    \"bits_per_second\": 870364199.318795, \n                    \"bytes\": 108789760, \n                    \"end\": 15.00003, \n                    \"omitted\": false, \n                    \"pmtu\": 1500, \n                    \"retransmits\": 0, \n                    \"rtt\": 77085, \n                    \"rttvar\": 8, \n                    \"seconds\": 0.9999470114707947, \n                    \"sender\": true, \n                    \"snd_cwnd\": 16698336, \n                    \"snd_wnd\": -1, \n                    \"socket\": 5, \n                    \"start\": 14.000083\n                }\n            ], \n            \"sum\": {\n                \"bits_per_second\": 870364199.318795, \n                \"bytes\": 108789760, \n                \"end\": 15.00003, \n                \"omitted\": false, \n                \"retransmits\": 0, \n                \"seconds\": 0.9999470114707947, \n                \"sender\": true, \n                \"start\": 14.000083\n            }\n        }, \n        {\n            \"streams\": [\n                {\n                    \"bits_per_second\": 859719687.2561295, \n                    \"bytes\": 107479040, \n                    \"end\": 16.000161, \n                    \"omitted\": false, \n                    \"pmtu\": 1500, \n                    \"retransmits\": 0, \n                    \"rtt\": 77083, \n                    \"rttvar\": 7, \n                    \"seconds\": 1.0001310110092163, \n                    \"sender\": true, \n                    \"snd_cwnd\": 16698336, \n                    \"snd_wnd\": -1, \n                    \"socket\": 5, \n                    \"start\": 15.00003\n                }\n            ], \n            \"sum\": {\n                \"bits_per_second\": 859719687.2561295, \n                \"bytes\": 107479040, \n                \"end\": 16.000161, \n                \"omitted\": false, \n                \"retransmits\": 0, \n                \"seconds\": 1.0001310110092163, \n                \"sender\": true, \n                \"start\": 15.00003\n            }\n        }, \n        {\n            \"streams\": [\n                {\n                    \"bits_per_second\": 870402488.8106927, \n                    \"bytes\": 108789760, \n                    \"end\": 17.000064, \n                    \"omitted\": false, \n                    \"pmtu\": 1500, \n                    \"retransmits\": 0, \n                    \"rtt\": 77089, \n                    \"rttvar\": 5, \n                    \"seconds\": 0.9999030232429504, \n                    \"sender\": true, \n                    \"snd_cwnd\": 16698336, \n                    \"snd_wnd\": -1, \n                    \"socket\": 5, \n                    \"start\": 16.000161\n                }\n            ], \n            \"sum\": {\n                \"bits_per_second\": 870402488.8106927, \n                \"bytes\": 108789760, \n                \"end\": 17.000064, \n                \"omitted\": false, \n                \"retransmits\": 0, \n                \"seconds\": 0.9999030232429504, \n                \"sender\": true, \n                \"start\": 16.000161\n            }\n        }, \n        {\n            \"streams\": [\n                {\n                    \"bits_per_second\": 870295463.08776, \n                    \"bytes\": 108789760, \n                    \"end\": 18.00009, \n                    \"omitted\": false, \n                    \"pmtu\": 1500, \n                    \"retransmits\": 0, \n                    \"rtt\": 77085, \n                    \"rttvar\": 7, \n                    \"seconds\": 1.000025987625122, \n                    \"sender\": true, \n                    \"snd_cwnd\": 16698336, \n                    \"snd_wnd\": -1, \n                    \"socket\": 5, \n                    \"start\": 17.000064\n                }\n            ], \n            \"sum\": {\n                \"bits_per_second\": 870295463.08776, \n                \"bytes\": 108789760, \n                \"end\": 18.00009, \n                \"omitted\": false, \n                \"retransmits\": 0, \n                \"seconds\": 1.000025987625122, \n                \"sender\": true, \n                \"start\": 17.000064\n            }\n        }, \n        {\n            \"streams\": [\n                {\n                    \"bits_per_second\": 859839187.5548513, \n                    \"bytes\": 107479040, \n                    \"end\": 19.000082, \n                    \"omitted\": false, \n                    \"pmtu\": 1500, \n                    \"retransmits\": 0, \n                    \"rtt\": 77086, \n                    \"rttvar\": 9, \n                    \"seconds\": 0.9999920129776, \n                    \"sender\": true, \n                    \"snd_cwnd\": 16698336, \n                    \"snd_wnd\": -1, \n                    \"socket\": 5, \n                    \"start\": 18.00009\n                }\n            ], \n            \"sum\": {\n                \"bits_per_second\": 859839187.5548513, \n                \"bytes\": 107479040, \n                \"end\": 19.000082, \n                \"omitted\": false, \n                \"retransmits\": 0, \n                \"seconds\": 0.9999920129776, \n                \"sender\": true, \n                \"start\": 18.00009\n            }\n        }, \n        {\n            \"streams\": [\n                {\n                    \"bits_per_second\": 870335510.3490804, \n                    \"bytes\": 108789760, \n                    \"end\": 20.000062, \n                    \"omitted\": false, \n                    \"pmtu\": 1500, \n                    \"retransmits\": 0, \n                    \"rtt\": 77090, \n                    \"rttvar\": 12, \n                    \"seconds\": 0.9999799728393555, \n                    \"sender\": true, \n                    \"snd_cwnd\": 16698336, \n                    \"snd_wnd\": -1, \n                    \"socket\": 5, \n                    \"start\": 19.000082\n                }\n            ], \n            \"sum\": {\n                \"bits_per_second\": 870335510.3490804, \n                \"bytes\": 108789760, \n                \"end\": 20.000062, \n                \"omitted\": false, \n                \"retransmits\": 0, \n                \"seconds\": 0.9999799728393555, \n                \"sender\": true, \n                \"start\": 19.000082\n            }\n        }, \n        {\n            \"streams\": [\n                {\n                    \"bits_per_second\": 859815100.3448608, \n                    \"bytes\": 107479040, \n                    \"end\": 21.000082, \n                    \"omitted\": false, \n                    \"pmtu\": 1500, \n                    \"retransmits\": 0, \n                    \"rtt\": 77087, \n                    \"rttvar\": 6, \n                    \"seconds\": 1.0000200271606445, \n                    \"sender\": true, \n                    \"snd_cwnd\": 16698336, \n                    \"snd_wnd\": -1, \n                    \"socket\": 5, \n                    \"start\": 20.000062\n                }\n            ], \n            \"sum\": {\n                \"bits_per_second\": 859815100.3448608, \n                \"bytes\": 107479040, \n                \"end\": 21.000082, \n                \"omitted\": false, \n                \"retransmits\": 0, \n                \"seconds\": 1.0000200271606445, \n                \"sender\": true, \n                \"start\": 20.000062\n            }\n        }, \n        {\n            \"streams\": [\n                {\n                    \"bits_per_second\": 870312892.5309197, \n                    \"bytes\": 108789760, \n                    \"end\": 22.000088, \n                    \"omitted\": false, \n                    \"pmtu\": 1500, \n                    \"retransmits\": 0, \n                    \"rtt\": 77089, \n                    \"rttvar\": 11, \n                    \"seconds\": 1.0000059604644775, \n                    \"sender\": true, \n                    \"snd_cwnd\": 16698336, \n                    \"snd_wnd\": -1, \n                    \"socket\": 5, \n                    \"start\": 21.000082\n                }\n            ], \n            \"sum\": {\n                \"bits_per_second\": 870312892.5309197, \n                \"bytes\": 108789760, \n                \"end\": 22.000088, \n                \"omitted\": false, \n                \"retransmits\": 0, \n                \"seconds\": 1.0000059604644775, \n                \"sender\": true, \n                \"start\": 21.000082\n            }\n        }, \n        {\n            \"streams\": [\n                {\n                    \"bits_per_second\": 859825452.5548505, \n                    \"bytes\": 107479040, \n                    \"end\": 23.000096, \n                    \"omitted\": false, \n                    \"pmtu\": 1500, \n                    \"retransmits\": 0, \n                    \"rtt\": 77089, \n                    \"rttvar\": 7, \n                    \"seconds\": 1.0000079870224, \n                    \"sender\": true, \n                    \"snd_cwnd\": 16698336, \n                    \"snd_wnd\": -1, \n                    \"socket\": 5, \n                    \"start\": 22.000088\n                }\n            ], \n            \"sum\": {\n                \"bits_per_second\": 859825452.5548505, \n                \"bytes\": 107479040, \n                \"end\": 23.000096, \n                \"omitted\": false, \n                \"retransmits\": 0, \n                \"seconds\": 1.0000079870224, \n                \"sender\": true, \n                \"start\": 22.000088\n            }\n        }, \n        {\n            \"streams\": [\n                {\n                    \"bits_per_second\": 870302414.031997, \n                    \"bytes\": 108789760, \n                    \"end\": 24.000114, \n                    \"omitted\": false, \n                    \"pmtu\": 1500, \n                    \"retransmits\": 0, \n                    \"rtt\": 77089, \n                    \"rttvar\": 9, \n                    \"seconds\": 1.0000180006027222, \n                    \"sender\": true, \n                    \"snd_cwnd\": 16698336, \n                    \"snd_wnd\": -1, \n                    \"socket\": 5, \n                    \"start\": 23.000096\n                }\n            ], \n            \"sum\": {\n                \"bits_per_second\": 870302414.031997, \n                \"bytes\": 108789760, \n                \"end\": 24.000114, \n                \"omitted\": false, \n                \"retransmits\": 0, \n                \"seconds\": 1.0000180006027222, \n                \"sender\": true, \n                \"start\": 23.000096\n            }\n        }, \n        {\n            \"streams\": [\n                {\n                    \"bits_per_second\": 859876192.2384307, \n                    \"bytes\": 107479040, \n                    \"end\": 25.000063, \n                    \"omitted\": false, \n                    \"pmtu\": 1500, \n                    \"retransmits\": 0, \n                    \"rtt\": 77085, \n                    \"rttvar\": 6, \n                    \"seconds\": 0.9999489784240723, \n                    \"sender\": true, \n                    \"snd_cwnd\": 16698336, \n                    \"snd_wnd\": -1, \n                    \"socket\": 5, \n                    \"start\": 24.000114\n                }\n            ], \n            \"sum\": {\n                \"bits_per_second\": 859876192.2384307, \n                \"bytes\": 107479040, \n                \"end\": 25.000063, \n                \"omitted\": false, \n                \"retransmits\": 0, \n                \"seconds\": 0.9999489784240723, \n                \"sender\": true, \n                \"start\": 24.000114\n            }\n        }, \n        {\n            \"streams\": [\n                {\n                    \"bits_per_second\": 870306771.396942, \n                    \"bytes\": 108789760, \n                    \"end\": 26.000076, \n                    \"omitted\": false, \n                    \"pmtu\": 1500, \n                    \"retransmits\": 0, \n                    \"rtt\": 77085, \n                    \"rttvar\": 6, \n                    \"seconds\": 1.000012993812561, \n                    \"sender\": true, \n                    \"snd_cwnd\": 16698336, \n                    \"snd_wnd\": -1, \n                    \"socket\": 5, \n                    \"start\": 25.000063\n                }\n            ], \n            \"sum\": {\n                \"bits_per_second\": 870306771.396942, \n                \"bytes\": 108789760, \n                \"end\": 26.000076, \n                \"omitted\": false, \n                \"retransmits\": 0, \n                \"seconds\": 1.000012993812561, \n                \"sender\": true, \n                \"start\": 25.000063\n            }\n        }, \n        {\n            \"streams\": [\n                {\n                    \"bits_per_second\": 859843492.6451752, \n                    \"bytes\": 107479040, \n                    \"end\": 27.000063, \n                    \"omitted\": false, \n                    \"pmtu\": 1500, \n                    \"retransmits\": 0, \n                    \"rtt\": 77089, \n                    \"rttvar\": 7, \n                    \"seconds\": 0.999987006187439, \n                    \"sender\": true, \n                    \"snd_cwnd\": 16698336, \n                    \"snd_wnd\": -1, \n                    \"socket\": 5, \n                    \"start\": 26.000076\n                }\n            ], \n            \"sum\": {\n                \"bits_per_second\": 859843492.6451752, \n                \"bytes\": 107479040, \n                \"end\": 27.000063, \n                \"omitted\": false, \n                \"retransmits\": 0, \n                \"seconds\": 0.999987006187439, \n                \"sender\": true, \n                \"start\": 26.000076\n            }\n        }, \n        {\n            \"streams\": [\n                {\n                    \"bits_per_second\": 870302414.031997, \n                    \"bytes\": 108789760, \n                    \"end\": 28.000081, \n                    \"omitted\": false, \n                    \"pmtu\": 1500, \n                    \"retransmits\": 0, \n                    \"rtt\": 77089, \n                    \"rttvar\": 8, \n                    \"seconds\": 1.0000180006027222, \n                    \"sender\": true, \n                    \"snd_cwnd\": 16698336, \n                    \"snd_wnd\": -1, \n                    \"socket\": 5, \n                    \"start\": 27.000063\n                }\n            ], \n            \"sum\": {\n                \"bits_per_second\": 870302414.031997, \n                \"bytes\": 108789760, \n                \"end\": 28.000081, \n                \"omitted\": false, \n                \"retransmits\": 0, \n                \"seconds\": 1.0000180006027222, \n                \"sender\": true, \n                \"start\": 27.000063\n            }\n        }, \n        {\n            \"streams\": [\n                {\n                    \"bits_per_second\": 870334628.43965, \n                    \"bytes\": 108789760, \n                    \"end\": 29.000062, \n                    \"omitted\": false, \n                    \"pmtu\": 1500, \n                    \"retransmits\": 0, \n                    \"rtt\": 77090, \n                    \"rttvar\": 7, \n                    \"seconds\": 0.9999809861183167, \n                    \"sender\": true, \n                    \"snd_cwnd\": 16698336, \n                    \"snd_wnd\": -1, \n                    \"socket\": 5, \n                    \"start\": 28.000081\n                }\n            ], \n            \"sum\": {\n                \"bits_per_second\": 870334628.43965, \n                \"bytes\": 108789760, \n                \"end\": 29.000062, \n                \"omitted\": false, \n                \"retransmits\": 0, \n                \"seconds\": 0.9999809861183167, \n                \"sender\": true, \n                \"start\": 28.000081\n            }\n        }, \n        {\n            \"streams\": [\n                {\n                    \"bits_per_second\": 859820327.667263, \n                    \"bytes\": 107479040, \n                    \"end\": 30.000076, \n                    \"omitted\": false, \n                    \"pmtu\": 1500, \n                    \"retransmits\": 0, \n                    \"rtt\": 77080, \n                    \"rttvar\": 13, \n                    \"seconds\": 1.0000139474868774, \n                    \"sender\": true, \n                    \"snd_cwnd\": 16698336, \n                    \"snd_wnd\": -1, \n                    \"socket\": 5, \n                    \"start\": 29.000062\n                }\n            ], \n            \"sum\": {\n                \"bits_per_second\": 859820327.667263, \n                \"bytes\": 107479040, \n                \"end\": 30.000076, \n                \"omitted\": false, \n                \"retransmits\": 0, \n                \"seconds\": 1.0000139474868774, \n                \"sender\": true, \n                \"start\": 29.000062\n            }\n        }, \n        {\n            \"streams\": [\n                {\n                    \"bits_per_second\": 870314552.5142974, \n                    \"bytes\": 108789760, \n                    \"end\": 31.00008, \n                    \"omitted\": false, \n                    \"pmtu\": 1500, \n                    \"retransmits\": 0, \n                    \"rtt\": 77088, \n                    \"rttvar\": 8, \n                    \"seconds\": 1.0000040531158447, \n                    \"sender\": true, \n                    \"snd_cwnd\": 16698336, \n                    \"snd_wnd\": -1, \n                    \"socket\": 5, \n                    \"start\": 30.000076\n                }\n            ], \n            \"sum\": {\n                \"bits_per_second\": 870314552.5142974, \n                \"bytes\": 108789760, \n                \"end\": 31.00008, \n                \"omitted\": false, \n                \"retransmits\": 0, \n                \"seconds\": 1.0000040531158447, \n                \"sender\": true, \n                \"start\": 30.000076\n            }\n        }, \n        {\n            \"streams\": [\n                {\n                    \"bits_per_second\": 859766929.973273, \n                    \"bytes\": 107479040, \n                    \"end\": 32.000156, \n                    \"omitted\": false, \n                    \"pmtu\": 1500, \n                    \"retransmits\": 0, \n                    \"rtt\": 77090, \n                    \"rttvar\": 9, \n                    \"seconds\": 1.0000760555267334, \n                    \"sender\": true, \n                    \"snd_cwnd\": 16698336, \n                    \"snd_wnd\": -1, \n                    \"socket\": 5, \n                    \"start\": 31.00008\n                }\n            ], \n            \"sum\": {\n                \"bits_per_second\": 859766929.973273, \n                \"bytes\": 107479040, \n                \"end\": 32.000156, \n                \"omitted\": false, \n                \"retransmits\": 0, \n                \"seconds\": 1.0000760555267334, \n                \"sender\": true, \n                \"start\": 31.00008\n            }\n        }, \n        {\n            \"streams\": [\n                {\n                    \"bits_per_second\": 870399894.565285, \n                    \"bytes\": 108789760, \n                    \"end\": 33.000062, \n                    \"omitted\": false, \n                    \"pmtu\": 1500, \n                    \"retransmits\": 0, \n                    \"rtt\": 77088, \n                    \"rttvar\": 11, \n                    \"seconds\": 0.9999060034751892, \n                    \"sender\": true, \n                    \"snd_cwnd\": 16698336, \n                    \"snd_wnd\": -1, \n                    \"socket\": 5, \n                    \"start\": 32.000156\n                }\n            ], \n            \"sum\": {\n                \"bits_per_second\": 870399894.565285, \n                \"bytes\": 108789760, \n                \"end\": 33.000062, \n                \"omitted\": false, \n                \"retransmits\": 0, \n                \"seconds\": 0.9999060034751892, \n                \"sender\": true, \n                \"start\": 32.000156\n            }\n        }, \n        {\n            \"streams\": [\n                {\n                    \"bits_per_second\": 859830577.5035312, \n                    \"bytes\": 107479040, \n                    \"end\": 34.000064, \n                    \"omitted\": false, \n                    \"pmtu\": 1500, \n                    \"retransmits\": 0, \n                    \"rtt\": 77086, \n                    \"rttvar\": 5, \n                    \"seconds\": 1.0000020265579224, \n                    \"sender\": true, \n                    \"snd_cwnd\": 16698336, \n                    \"snd_wnd\": -1, \n                    \"socket\": 5, \n                    \"start\": 33.000062\n                }\n            ], \n            \"sum\": {\n                \"bits_per_second\": 859830577.5035312, \n                \"bytes\": 107479040, \n                \"end\": 34.000064, \n                \"omitted\": false, \n                \"retransmits\": 0, \n                \"seconds\": 1.0000020265579224, \n                \"sender\": true, \n                \"start\": 33.000062\n            }\n        }, \n        {\n            \"streams\": [\n                {\n                    \"bits_per_second\": 870319843.7535744, \n                    \"bytes\": 108789760, \n                    \"end\": 35.000062, \n                    \"omitted\": false, \n                    \"pmtu\": 1500, \n                    \"retransmits\": 0, \n                    \"rtt\": 77078, \n                    \"rttvar\": 8, \n                    \"seconds\": 0.9999979734420776, \n                    \"sender\": true, \n                    \"snd_cwnd\": 16698336, \n                    \"snd_wnd\": -1, \n                    \"socket\": 5, \n                    \"start\": 34.000064\n                }\n            ], \n            \"sum\": {\n                \"bits_per_second\": 870319843.7535744, \n                \"bytes\": 108789760, \n                \"end\": 35.000062, \n                \"omitted\": false, \n                \"retransmits\": 0, \n                \"seconds\": 0.9999979734420776, \n                \"sender\": true, \n                \"start\": 34.000064\n            }\n        }, \n        {\n            \"streams\": [\n                {\n                    \"bits_per_second\": 859828835.014125, \n                    \"bytes\": 107479040, \n                    \"end\": 36.000066, \n                    \"omitted\": false, \n                    \"pmtu\": 1500, \n                    \"retransmits\": 0, \n                    \"rtt\": 77086, \n                    \"rttvar\": 11, \n                    \"seconds\": 1.0000040531158447, \n                    \"sender\": true, \n                    \"snd_cwnd\": 16698336, \n                    \"snd_wnd\": -1, \n                    \"socket\": 5, \n                    \"start\": 35.000062\n                }\n            ], \n            \"sum\": {\n                \"bits_per_second\": 859828835.014125, \n                \"bytes\": 107479040, \n                \"end\": 36.000066, \n                \"omitted\": false, \n                \"retransmits\": 0, \n                \"seconds\": 1.0000040531158447, \n                \"sender\": true, \n                \"start\": 35.000062\n            }\n        }, \n        {\n            \"streams\": [\n                {\n                    \"bits_per_second\": 870321555.63888, \n                    \"bytes\": 108789760, \n                    \"end\": 37.000062, \n                    \"omitted\": false, \n                    \"pmtu\": 1500, \n                    \"retransmits\": 0, \n                    \"rtt\": 77090, \n                    \"rttvar\": 11, \n                    \"seconds\": 0.9999960064888, \n                    \"sender\": true, \n                    \"snd_cwnd\": 16698336, \n                    \"snd_wnd\": -1, \n                    \"socket\": 5, \n                    \"start\": 36.000066\n                }\n            ], \n            \"sum\": {\n                \"bits_per_second\": 870321555.63888, \n                \"bytes\": 108789760, \n                \"end\": 37.000062, \n                \"omitted\": false, \n                \"retransmits\": 0, \n                \"seconds\": 0.9999960064888, \n                \"sender\": true, \n                \"start\": 36.000066\n            }\n        }, \n        {\n            \"streams\": [\n                {\n                    \"bits_per_second\": 859846926.4981253, \n                    \"bytes\": 107479040, \n                    \"end\": 38.000045, \n                    \"omitted\": false, \n                    \"pmtu\": 1500, \n                    \"retransmits\": 0, \n                    \"rtt\": 77090, \n                    \"rttvar\": 12, \n                    \"seconds\": 0.999983012676239, \n                    \"sender\": true, \n                    \"snd_cwnd\": 16698336, \n                    \"snd_wnd\": -1, \n                    \"socket\": 5, \n                    \"start\": 37.000062\n                }\n            ], \n            \"sum\": {\n                \"bits_per_second\": 859846926.4981253, \n                \"bytes\": 107479040, \n                \"end\": 38.000045, \n                \"omitted\": false, \n                \"retransmits\": 0, \n                \"seconds\": 0.999983012676239, \n                \"sender\": true, \n                \"start\": 37.000062\n            }\n        }, \n        {\n            \"streams\": [\n                {\n                    \"bits_per_second\": 870302414.031997, \n                    \"bytes\": 108789760, \n                    \"end\": 39.000063, \n                    \"omitted\": false, \n                    \"pmtu\": 1500, \n                    \"retransmits\": 0, \n                    \"rtt\": 77088, \n                    \"rttvar\": 11, \n                    \"seconds\": 1.0000180006027222, \n                    \"sender\": true, \n                    \"snd_cwnd\": 16698336, \n                    \"snd_wnd\": -1, \n                    \"socket\": 5, \n                    \"start\": 38.000045\n                }\n            ], \n            \"sum\": {\n                \"bits_per_second\": 870302414.031997, \n                \"bytes\": 108789760, \n                \"end\": 39.000063, \n                \"omitted\": false, \n                \"retransmits\": 0, \n                \"seconds\": 1.0000180006027222, \n                \"sender\": true, \n                \"start\": 38.000045\n            }\n        }, \n        {\n            \"streams\": [\n                {\n                    \"bits_per_second\": 870319843.7535744, \n                    \"bytes\": 108789760, \n                    \"end\": 40.000061, \n                    \"omitted\": false, \n                    \"pmtu\": 1500, \n                    \"retransmits\": 0, \n                    \"rtt\": 77068, \n                    \"rttvar\": 10, \n                    \"seconds\": 0.9999979734420776, \n                    \"sender\": true, \n                    \"snd_cwnd\": 16698336, \n                    \"snd_wnd\": -1, \n                    \"socket\": 5, \n                    \"start\": 39.000063\n                }\n            ], \n            \"sum\": {\n                \"bits_per_second\": 870319843.7535744, \n                \"bytes\": 108789760, \n                \"end\": 40.000061, \n                \"omitted\": false, \n                \"retransmits\": 0, \n                \"seconds\": 0.9999979734420776, \n                \"sender\": true, \n                \"start\": 39.000063\n            }\n        }, \n        {\n            \"streams\": [\n                {\n                    \"bits_per_second\": 859830577.5035312, \n                    \"bytes\": 107479040, \n                    \"end\": 41.000063, \n                    \"omitted\": false, \n                    \"pmtu\": 1500, \n                    \"retransmits\": 0, \n                    \"rtt\": 77087, \n                    \"rttvar\": 10, \n                    \"seconds\": 1.0000020265579224, \n                    \"sender\": true, \n                    \"snd_cwnd\": 16698336, \n                    \"snd_wnd\": -1, \n                    \"socket\": 5, \n                    \"start\": 40.000061\n                }\n            ], \n            \"sum\": {\n                \"bits_per_second\": 859830577.5035312, \n                \"bytes\": 107479040, \n                \"end\": 41.000063, \n                \"omitted\": false, \n                \"retransmits\": 0, \n                \"seconds\": 1.0000020265579224, \n                \"sender\": true, \n                \"start\": 40.000061\n            }\n        }, \n        {\n            \"streams\": [\n                {\n                    \"bits_per_second\": 870309365.0872675, \n                    \"bytes\": 108789760, \n                    \"end\": 42.000073, \n                    \"omitted\": false, \n                    \"pmtu\": 1500, \n                    \"retransmits\": 0, \n                    \"rtt\": 77085, \n                    \"rttvar\": 6, \n                    \"seconds\": 1.0000100135803223, \n                    \"sender\": true, \n                    \"snd_cwnd\": 16698336, \n                    \"snd_wnd\": -1, \n                    \"socket\": 5, \n                    \"start\": 41.000063\n                }\n            ], \n            \"sum\": {\n                \"bits_per_second\": 870309365.0872675, \n                \"bytes\": 108789760, \n                \"end\": 42.000073, \n                \"omitted\": false, \n                \"retransmits\": 0, \n                \"seconds\": 1.0000100135803223, \n                \"sender\": true, \n                \"start\": 41.000063\n            }\n        }, \n        {\n            \"streams\": [\n                {\n                    \"bits_per_second\": 859866710.1254233, \n                    \"bytes\": 107479040, \n                    \"end\": 43.000033, \n                    \"omitted\": false, \n                    \"pmtu\": 1500, \n                    \"retransmits\": 0, \n                    \"rtt\": 77092, \n                    \"rttvar\": 7, \n                    \"seconds\": 0.9999600052833557, \n                    \"sender\": true, \n                    \"snd_cwnd\": 16698336, \n                    \"snd_wnd\": -1, \n                    \"socket\": 5, \n                    \"start\": 42.000073\n                }\n            ], \n            \"sum\": {\n                \"bits_per_second\": 859866710.1254233, \n                \"bytes\": 107479040, \n                \"end\": 43.000033, \n                \"omitted\": false, \n                \"retransmits\": 0, \n                \"seconds\": 0.9999600052833557, \n                \"sender\": true, \n                \"start\": 42.000073\n            }\n        }, \n        {\n            \"streams\": [\n                {\n                    \"bits_per_second\": 870291105.8360485, \n                    \"bytes\": 108789760, \n                    \"end\": 44.000064, \n                    \"omitted\": false, \n                    \"pmtu\": 1500, \n                    \"retransmits\": 0, \n                    \"rtt\": 77084, \n                    \"rttvar\": 9, \n                    \"seconds\": 1.0000309944152832, \n                    \"sender\": true, \n                    \"snd_cwnd\": 16698336, \n                    \"snd_wnd\": -1, \n                    \"socket\": 5, \n                    \"start\": 43.000033\n                }\n            ], \n            \"sum\": {\n                \"bits_per_second\": 870291105.8360485, \n                \"bytes\": 108789760, \n                \"end\": 44.000064, \n                \"omitted\": false, \n                \"retransmits\": 0, \n                \"seconds\": 1.0000309944152832, \n                \"sender\": true, \n                \"start\": 43.000033\n            }\n        }, \n        {\n            \"streams\": [\n                {\n                    \"bits_per_second\": 859863276.1144575, \n                    \"bytes\": 107479040, \n                    \"end\": 45.000028, \n                    \"omitted\": false, \n                    \"pmtu\": 1500, \n                    \"retransmits\": 0, \n                    \"rtt\": 77089, \n                    \"rttvar\": 15, \n                    \"seconds\": 0.9999639987945557, \n                    \"sender\": true, \n                    \"snd_cwnd\": 16698336, \n                    \"snd_wnd\": -1, \n                    \"socket\": 5, \n                    \"start\": 44.000064\n                }\n            ], \n            \"sum\": {\n                \"bits_per_second\": 859863276.1144575, \n                \"bytes\": 107479040, \n                \"end\": 45.000028, \n                \"omitted\": false, \n                \"retransmits\": 0, \n                \"seconds\": 0.9999639987945557, \n                \"sender\": true, \n                \"start\": 44.000064\n            }\n        }, \n        {\n            \"streams\": [\n                {\n                    \"bits_per_second\": 870286748.627967, \n                    \"bytes\": 108789760, \n                    \"end\": 46.000064, \n                    \"omitted\": false, \n                    \"pmtu\": 1500, \n                    \"retransmits\": 0, \n                    \"rtt\": 77084, \n                    \"rttvar\": 9, \n                    \"seconds\": 1.0000360012054443, \n                    \"sender\": true, \n                    \"snd_cwnd\": 16698336, \n                    \"snd_wnd\": -1, \n                    \"socket\": 5, \n                    \"start\": 45.000028\n                }\n            ], \n            \"sum\": {\n                \"bits_per_second\": 870286748.627967, \n                \"bytes\": 108789760, \n                \"end\": 46.000064, \n                \"omitted\": false, \n                \"retransmits\": 0, \n                \"seconds\": 1.0000360012054443, \n                \"sender\": true, \n                \"start\": 45.000028\n            }\n        }, \n        {\n            \"streams\": [\n                {\n                    \"bits_per_second\": 859816842.7785993, \n                    \"bytes\": 107479040, \n                    \"end\": 47.000082, \n                    \"omitted\": false, \n                    \"pmtu\": 1500, \n                    \"retransmits\": 0, \n                    \"rtt\": 77084, \n                    \"rttvar\": 9, \n                    \"seconds\": 1.0000180006027222, \n                    \"sender\": true, \n                    \"snd_cwnd\": 16698336, \n                    \"snd_wnd\": -1, \n                    \"socket\": 5, \n                    \"start\": 46.000064\n                }\n            ], \n            \"sum\": {\n                \"bits_per_second\": 859816842.7785993, \n                \"bytes\": 107479040, \n                \"end\": 47.000082, \n                \"omitted\": false, \n                \"retransmits\": 0, \n                \"seconds\": 1.0000180006027222, \n                \"sender\": true, \n                \"start\": 46.000064\n            }\n        }, \n        {\n            \"streams\": [\n                {\n                    \"bits_per_second\": 870318961.8758936, \n                    \"bytes\": 108789760, \n                    \"end\": 48.000081, \n                    \"omitted\": false, \n                    \"pmtu\": 1500, \n                    \"retransmits\": 0, \n                    \"rtt\": 77086, \n                    \"rttvar\": 12, \n                    \"seconds\": 0.9999989867210388, \n                    \"sender\": true, \n                    \"snd_cwnd\": 16698336, \n                    \"snd_wnd\": -1, \n                    \"socket\": 5, \n                    \"start\": 47.000082\n                }\n            ], \n            \"sum\": {\n                \"bits_per_second\": 870318961.8758936, \n                \"bytes\": 108789760, \n                \"end\": 48.000081, \n                \"omitted\": false, \n                \"retransmits\": 0, \n                \"seconds\": 0.9999989867210388, \n                \"sender\": true, \n                \"start\": 47.000082\n            }\n        }, \n        {\n            \"streams\": [\n                {\n                    \"bits_per_second\": 859768672.21178, \n                    \"bytes\": 107479040, \n                    \"end\": 49.000155, \n                    \"omitted\": false, \n                    \"pmtu\": 1500, \n                    \"retransmits\": 0, \n                    \"rtt\": 77084, \n                    \"rttvar\": 5, \n                    \"seconds\": 1.000074028968811, \n                    \"sender\": true, \n                    \"snd_cwnd\": 16698336, \n                    \"snd_wnd\": -1, \n                    \"socket\": 5, \n                    \"start\": 48.000081\n                }\n            ], \n            \"sum\": {\n                \"bits_per_second\": 859768672.21178, \n                \"bytes\": 107479040, \n                \"end\": 49.000155, \n                \"omitted\": false, \n                \"retransmits\": 0, \n                \"seconds\": 1.000074028968811, \n                \"sender\": true, \n                \"start\": 48.000081\n            }\n        }, \n        {\n            \"streams\": [\n                {\n                    \"bits_per_second\": 870371151.3610555, \n                    \"bytes\": 108789760, \n                    \"end\": 50.000094, \n                    \"omitted\": false, \n                    \"pmtu\": 1500, \n                    \"retransmits\": 0, \n                    \"rtt\": 77089, \n                    \"rttvar\": 8, \n                    \"seconds\": 0.9999390244483948, \n                    \"sender\": true, \n                    \"snd_cwnd\": 16698336, \n                    \"snd_wnd\": -1, \n                    \"socket\": 5, \n                    \"start\": 49.000155\n                }\n            ], \n            \"sum\": {\n                \"bits_per_second\": 870371151.3610555, \n                \"bytes\": 108789760, \n                \"end\": 50.000094, \n                \"omitted\": false, \n                \"retransmits\": 0, \n                \"seconds\": 0.9999390244483948, \n                \"sender\": true, \n                \"start\": 49.000155\n            }\n        }, \n        {\n            \"streams\": [\n                {\n                    \"bits_per_second\": 870346819.699013, \n                    \"bytes\": 108789760, \n                    \"end\": 51.000061, \n                    \"omitted\": false, \n                    \"pmtu\": 1500, \n                    \"retransmits\": 0, \n                    \"rtt\": 77085, \n                    \"rttvar\": 7, \n                    \"seconds\": 0.9999669790267944, \n                    \"sender\": true, \n                    \"snd_cwnd\": 16698336, \n                    \"snd_wnd\": -1, \n                    \"socket\": 5, \n                    \"start\": 50.000094\n                }\n            ], \n            \"sum\": {\n                \"bits_per_second\": 870346819.699013, \n                \"bytes\": 108789760, \n                \"end\": 51.000061, \n                \"omitted\": false, \n                \"retransmits\": 0, \n                \"seconds\": 0.9999669790267944, \n                \"sender\": true, \n                \"start\": 50.000094\n            }\n        }, \n        {\n            \"streams\": [\n                {\n                    \"bits_per_second\": 859782405.3977884, \n                    \"bytes\": 107479040, \n                    \"end\": 52.000119, \n                    \"omitted\": false, \n                    \"pmtu\": 1500, \n                    \"retransmits\": 0, \n                    \"rtt\": 77089, \n                    \"rttvar\": 6, \n                    \"seconds\": 1.0000580549240112, \n                    \"sender\": true, \n                    \"snd_cwnd\": 16698336, \n                    \"snd_wnd\": -1, \n                    \"socket\": 5, \n                    \"start\": 51.000061\n                }\n            ], \n            \"sum\": {\n                \"bits_per_second\": 859782405.3977884, \n                \"bytes\": 107479040, \n                \"end\": 52.000119, \n                \"omitted\": false, \n                \"retransmits\": 0, \n                \"seconds\": 1.0000580549240112, \n                \"sender\": true, \n                \"start\": 51.000061\n            }\n        }, \n        {\n            \"streams\": [\n                {\n                    \"bits_per_second\": 870367675.326043, \n                    \"bytes\": 108789760, \n                    \"end\": 53.000062, \n                    \"omitted\": false, \n                    \"pmtu\": 1500, \n                    \"retransmits\": 0, \n                    \"rtt\": 77092, \n                    \"rttvar\": 6, \n                    \"seconds\": 0.9999430179595947, \n                    \"sender\": true, \n                    \"snd_cwnd\": 16698336, \n                    \"snd_wnd\": -1, \n                    \"socket\": 5, \n                    \"start\": 52.000119\n                }\n            ], \n            \"sum\": {\n                \"bits_per_second\": 870367675.326043, \n                \"bytes\": 108789760, \n                \"end\": 53.000062, \n                \"omitted\": false, \n                \"retransmits\": 0, \n                \"seconds\": 0.9999430179595947, \n                \"sender\": true, \n                \"start\": 52.000119\n            }\n        }, \n        {\n            \"streams\": [\n                {\n                    \"bits_per_second\": 859826272.542534, \n                    \"bytes\": 107479040, \n                    \"end\": 54.000069, \n                    \"omitted\": false, \n                    \"pmtu\": 1500, \n                    \"retransmits\": 0, \n                    \"rtt\": 77078, \n                    \"rttvar\": 8, \n                    \"seconds\": 1.0000070333480835, \n                    \"sender\": true, \n                    \"snd_cwnd\": 16698336, \n                    \"snd_wnd\": -1, \n                    \"socket\": 5, \n                    \"start\": 53.000062\n                }\n            ], \n            \"sum\": {\n                \"bits_per_second\": 859826272.542534, \n                \"bytes\": 107479040, \n                \"end\": 54.000069, \n                \"omitted\": false, \n                \"retransmits\": 0, \n                \"seconds\": 1.0000070333480835, \n                \"sender\": true, \n                \"start\": 53.000062\n            }\n        }, \n        {\n            \"streams\": [\n                {\n                    \"bits_per_second\": 870324149.4173266, \n                    \"bytes\": 108789760, \n                    \"end\": 55.000062, \n                    \"omitted\": false, \n                    \"pmtu\": 1500, \n                    \"retransmits\": 0, \n                    \"rtt\": 77091, \n                    \"rttvar\": 8, \n                    \"seconds\": 0.9999930262565613, \n                    \"sender\": true, \n                    \"snd_cwnd\": 16698336, \n                    \"snd_wnd\": -1, \n                    \"socket\": 5, \n                    \"start\": 54.000069\n                }\n            ], \n            \"sum\": {\n                \"bits_per_second\": 870324149.4173266, \n                \"bytes\": 108789760, \n                \"end\": 55.000062, \n                \"omitted\": false, \n                \"retransmits\": 0, \n                \"seconds\": 0.9999930262565613, \n                \"sender\": true, \n                \"start\": 54.000069\n            }\n        }, \n        {\n            \"streams\": [\n                {\n                    \"bits_per_second\": 859816842.7785993, \n                    \"bytes\": 107479040, \n                    \"end\": 56.00008, \n                    \"omitted\": false, \n                    \"pmtu\": 1500, \n                    \"retransmits\": 0, \n                    \"rtt\": 77086, \n                    \"rttvar\": 11, \n                    \"seconds\": 1.0000180006027222, \n                    \"sender\": true, \n                    \"snd_cwnd\": 16698336, \n                    \"snd_wnd\": -1, \n                    \"socket\": 5, \n                    \"start\": 55.000062\n                }\n            ], \n            \"sum\": {\n                \"bits_per_second\": 859816842.7785993, \n                \"bytes\": 107479040, \n                \"end\": 56.00008, \n                \"omitted\": false, \n                \"retransmits\": 0, \n                \"seconds\": 1.0000180006027222, \n                \"sender\": true, \n                \"start\": 55.000062\n            }\n        }, \n        {\n            \"streams\": [\n                {\n                    \"bits_per_second\": 870330270.7957577, \n                    \"bytes\": 108789760, \n                    \"end\": 57.000066, \n                    \"omitted\": false, \n                    \"pmtu\": 1500, \n                    \"retransmits\": 0, \n                    \"rtt\": 77086, \n                    \"rttvar\": 4, \n                    \"seconds\": 0.9999859929084778, \n                    \"sender\": true, \n                    \"snd_cwnd\": 16698336, \n                    \"snd_wnd\": -1, \n                    \"socket\": 5, \n                    \"start\": 56.00008\n                }\n            ], \n            \"sum\": {\n                \"bits_per_second\": 870330270.7957577, \n                \"bytes\": 108789760, \n                \"end\": 57.000066, \n                \"omitted\": false, \n                \"retransmits\": 0, \n                \"seconds\": 0.9999859929084778, \n                \"sender\": true, \n                \"start\": 56.00008\n            }\n        }, \n        {\n            \"streams\": [\n                {\n                    \"bits_per_second\": 859832320, \n                    \"bytes\": 107479040, \n                    \"end\": 58.000066, \n                    \"omitted\": false, \n                    \"pmtu\": 1500, \n                    \"retransmits\": 0, \n                    \"rtt\": 77088, \n                    \"rttvar\": 6, \n                    \"seconds\": 1, \n                    \"sender\": true, \n                    \"snd_cwnd\": 16698336, \n                    \"snd_wnd\": -1, \n                    \"socket\": 5, \n                    \"start\": 57.000066\n                }\n            ], \n            \"sum\": {\n                \"bits_per_second\": 859832320, \n                \"bytes\": 107479040, \n                \"end\": 58.000066, \n                \"omitted\": false, \n                \"retransmits\": 0, \n                \"seconds\": 1, \n                \"sender\": true, \n                \"start\": 57.000066\n            }\n        }, \n        {\n            \"streams\": [\n                {\n                    \"bits_per_second\": 870341580.0095215, \n                    \"bytes\": 108789760, \n                    \"end\": 59.000039, \n                    \"omitted\": false, \n                    \"pmtu\": 1500, \n                    \"retransmits\": 0, \n                    \"rtt\": 77092, \n                    \"rttvar\": 11, \n                    \"seconds\": 0.9999729990959167, \n                    \"sender\": true, \n                    \"snd_cwnd\": 16698336, \n                    \"snd_wnd\": -1, \n                    \"socket\": 5, \n                    \"start\": 58.000066\n                }\n            ], \n            \"sum\": {\n                \"bits_per_second\": 870341580.0095215, \n                \"bytes\": 108789760, \n                \"end\": 59.000039, \n                \"omitted\": false, \n                \"retransmits\": 0, \n                \"seconds\": 0.9999729990959167, \n                \"sender\": true, \n                \"start\": 58.000066\n            }\n        }, \n        {\n            \"streams\": [\n                {\n                    \"bits_per_second\": 859803108.4924507, \n                    \"bytes\": 107479040, \n                    \"end\": 60.000073, \n                    \"omitted\": false, \n                    \"pmtu\": 1500, \n                    \"retransmits\": 0, \n                    \"rtt\": 77093, \n                    \"rttvar\": 8, \n                    \"seconds\": 1.000033974647522, \n                    \"sender\": true, \n                    \"snd_cwnd\": 16698336, \n                    \"snd_wnd\": -1, \n                    \"socket\": 5, \n                    \"start\": 59.000039\n                }\n            ], \n            \"sum\": {\n                \"bits_per_second\": 859803108.4924507, \n                \"bytes\": 107479040, \n                \"end\": 60.000073, \n                \"omitted\": false, \n                \"retransmits\": 0, \n                \"seconds\": 1.000033974647522, \n                \"sender\": true, \n                \"start\": 59.000039\n            }\n        }\n    ], \n    \"start\": {\n        \"connected\": [\n            {\n                \"local_host\": \"10.0.0.1\", \n                \"local_port\": 52235, \n                \"remote_host\": \"10.0.0.2\", \n                \"remote_port\": 5201, \n                \"socket\": 5\n            }\n        ], \n        \"connecting_to\": {\n            \"host\": \"10.0.0.2\", \n            \"port\": 5201\n        }, \n        \"cookie\": \"cw7u6d6oxnzvwfsxvtrobrxw77i6lj6d37dt\", \n        \"fq_rate\": 0, \n        \"rcvbuf_actual\": 87380, \n        \"sndbuf_actual\": 87380, \n        \"sock_bufsize\": 0, \n        \"system_info\": \"REDACTED\", \n        \"target_bitrate\": 0, \n        \"tcp_mss_default\": 1448, \n        \"test_start\": {\n            \"bidir\": 0, \n            \"blksize\": 131072, \n            \"blocks\": 0, \n            \"bytes\": 0, \n            \"duration\": 60, \n            \"fqrate\": 0, \n            \"num_streams\": 1, \n            \"omit\": 0, \n            \"protocol\": \"TCP\", \n            \"reverse\": 0, \n            \"target_bitrate\": 0, \n            \"tos\": 0\n        }, \n        \"timestamp\": {\n            \"time\": \"Wed, 17 Apr 2024 01:18:34 GMT\", \n            \"timesecs\": 1713316714\n        }, \n        \"version\": \"iperf 3.14\"\n    }\n}\nParticipant 1:\n/usr/bin/iperf3 -s -1 --idle-timeout 60 --json -p 5201 -B 10.0.0.2 --authorized-users-path /var/run/pscheduler-server/runner/tmp/tmpbpy5odp7/tmp41gwwjcr/credentials --rsa-private-key-path /var/run/pscheduler-server/runner/tmp/tmpbpy5odp7/tmp41gwwjcr/private-key\n\n{\n    \"end\": {\n        \"cpu_utilization_percent\": {\n            \"host_system\": 5.32159871924289, \n            \"host_total\": 5.819117194085953, \n            \"host_user\": 0.4975184748430618, \n            \"remote_system\": 0, \n            \"remote_total\": 0, \n            \"remote_user\": 0\n        }, \n        \"receiver_tcp_congestion\": \"htcp\", \n        \"streams\": [\n            {\n                \"receiver\": {\n                    \"bits_per_second\": 865535784.6175433, \n                    \"bytes\": 6499843216, \n                    \"end\": 60.076945, \n                    \"seconds\": 60.076945, \n                    \"sender\": false, \n                    \"socket\": 5, \n                    \"start\": 0\n                }, \n                \"sender\": {\n                    \"bits_per_second\": 0, \n                    \"bytes\": 0, \n                    \"end\": 60.076945, \n                    \"seconds\": 60.076945, \n                    \"sender\": false, \n                    \"socket\": 5, \n                    \"start\": 0\n                }\n            }\n        ], \n        \"sum_received\": {\n            \"bits_per_second\": 865535784.6175433, \n            \"bytes\": 6499843216, \n            \"end\": 60.076945, \n            \"seconds\": 60.076945, \n            \"sender\": false, \n            \"start\": 0\n        }, \n        \"sum_sent\": {\n            \"bits_per_second\": 0, \n            \"bytes\": 0, \n            \"end\": 60.076945, \n            \"seconds\": 60.076945, \n            \"sender\": false, \n            \"start\": 0\n        }\n    }, \n    \"intervals\": [\n        {\n            \"streams\": [\n                {\n                    \"bits_per_second\": 865295154.5750382, \n                    \"bytes\": 108168496, \n                    \"end\": 1.000061, \n                    \"omitted\": false, \n                    \"seconds\": 1.00006103515625, \n                    \"sender\": false, \n                    \"socket\": 5, \n                    \"start\": 0\n                }\n            ], \n            \"sum\": {\n                \"bits_per_second\": 865295154.5750382, \n                \"bytes\": 108168496, \n                \"end\": 1.000061, \n                \"omitted\": false, \n                \"seconds\": 1.00006103515625, \n                \"sender\": false, \n                \"start\": 0\n            }\n        }, \n        {\n            \"streams\": [\n                {\n                    \"bits_per_second\": 865324800, \n                    \"bytes\": 108165600, \n                    \"end\": 2.000061, \n                    \"omitted\": false, \n                    \"seconds\": 1, \n                    \"sender\": false, \n                    \"socket\": 5, \n                    \"start\": 1.000061\n                }\n            ], \n            \"sum\": {\n                \"bits_per_second\": 865324800, \n                \"bytes\": 108165600, \n                \"end\": 2.000061, \n                \"omitted\": false, \n                \"seconds\": 1, \n                \"sender\": false, \n                \"start\": 1.000061\n            }\n        }, \n        {\n            \"streams\": [\n                {\n                    \"bits_per_second\": 865306645.1440877, \n                    \"bytes\": 108165600, \n                    \"end\": 3.000082, \n                    \"omitted\": false, \n                    \"seconds\": 1.000020980834961, \n                    \"sender\": false, \n                    \"socket\": 5, \n                    \"start\": 2.000061\n                }\n            ], \n            \"sum\": {\n                \"bits_per_second\": 865306645.1440877, \n                \"bytes\": 108165600, \n                \"end\": 3.000082, \n                \"omitted\": false, \n                \"seconds\": 1.000020980834961, \n                \"sender\": false, \n                \"start\": 2.000061\n            }\n        }, \n        {\n            \"streams\": [\n                {\n                    \"bits_per_second\": 865864246.5548556, \n                    \"bytes\": 108230760, \n                    \"end\": 4.000061, \n                    \"omitted\": false, \n                    \"seconds\": 0.999979019165039, \n                    \"sender\": false, \n                    \"socket\": 5, \n                    \"start\": 3.000082\n                }\n            ], \n            \"sum\": {\n                \"bits_per_second\": 865864246.5548556, \n                \"bytes\": 108230760, \n                \"end\": 4.000061, \n                \"omitted\": false, \n                \"seconds\": 0.999979019165039, \n                \"sender\": false, \n                \"start\": 3.000082\n            }\n        }, \n        {\n            \"streams\": [\n                {\n                    \"bits_per_second\": 865305716.7912476, \n                    \"bytes\": 108165600, \n                    \"end\": 5.000083, \n                    \"omitted\": false, \n                    \"seconds\": 1.000022053718567, \n                    \"sender\": false, \n                    \"socket\": 5, \n                    \"start\": 4.000061\n                }\n            ], \n            \"sum\": {\n                \"bits_per_second\": 865305716.7912476, \n                \"bytes\": 108165600, \n                \"end\": 5.000083, \n                \"omitted\": false, \n                \"seconds\": 1.000022053718567, \n                \"sender\": false, \n                \"start\": 4.000061\n            }\n        }, \n        {\n            \"streams\": [\n                {\n                    \"bits_per_second\": 865864246.5548556, \n                    \"bytes\": 108230760, \n                    \"end\": 6.000062, \n                    \"omitted\": false, \n                    \"seconds\": 0.999979019165039, \n                    \"sender\": false, \n                    \"socket\": 5, \n                    \"start\": 5.000083\n                }\n            ], \n            \"sum\": {\n                \"bits_per_second\": 865864246.5548556, \n                \"bytes\": 108230760, \n                \"end\": 6.000062, \n                \"omitted\": false, \n                \"seconds\": 0.999979019165039, \n                \"sender\": false, \n                \"start\": 5.000083\n            }\n        }, \n        {\n            \"streams\": [\n                {\n                    \"bits_per_second\": 865309223.9124285, \n                    \"bytes\": 108165600, \n                    \"end\": 7.00008, \n                    \"omitted\": false, \n                    \"seconds\": 1.0000180006027222, \n                    \"sender\": false, \n                    \"socket\": 5, \n                    \"start\": 6.000062\n                }\n            ], \n            \"sum\": {\n                \"bits_per_second\": 865309223.9124285, \n                \"bytes\": 108165600, \n                \"end\": 7.00008, \n                \"omitted\": false, \n                \"seconds\": 1.0000180006027222, \n                \"sender\": false, \n                \"start\": 6.000062\n            }\n        }, \n        {\n            \"streams\": [\n                {\n                    \"bits_per_second\": 865846957.3445054, \n                    \"bytes\": 108230760, \n                    \"end\": 8.000079, \n                    \"omitted\": false, \n                    \"seconds\": 0.9999989867210388, \n                    \"sender\": false, \n                    \"socket\": 5, \n                    \"start\": 7.00008\n                }\n            ], \n            \"sum\": {\n                \"bits_per_second\": 865846957.3445054, \n                \"bytes\": 108230760, \n                \"end\": 8.000079, \n                \"omitted\": false, \n                \"seconds\": 0.9999989867210388, \n                \"sender\": false, \n                \"start\": 7.00008\n            }\n        }, \n        {\n            \"streams\": [\n                {\n                    \"bits_per_second\": 865339499.8022463, \n                    \"bytes\": 108165600, \n                    \"end\": 9.000062, \n                    \"omitted\": false, \n                    \"seconds\": 0.999983012676239, \n                    \"sender\": false, \n                    \"socket\": 5, \n                    \"start\": 8.000079\n                }\n            ], \n            \"sum\": {\n                \"bits_per_second\": 865339499.8022463, \n                \"bytes\": 108165600, \n                \"end\": 9.000062, \n                \"omitted\": false, \n                \"seconds\": 0.999983012676239, \n                \"sender\": false, \n                \"start\": 8.000079\n            }\n        }, \n        {\n            \"streams\": [\n                {\n                    \"bits_per_second\": 865305716.7912476, \n                    \"bytes\": 108165600, \n                    \"end\": 10.000084, \n                    \"omitted\": false, \n                    \"seconds\": 1.000022053718567, \n                    \"sender\": false, \n                    \"socket\": 5, \n                    \"start\": 9.000062\n                }\n            ], \n            \"sum\": {\n                \"bits_per_second\": 865305716.7912476, \n                \"bytes\": 108165600, \n                \"end\": 10.000084, \n                \"omitted\": false, \n                \"seconds\": 1.000022053718567, \n                \"sender\": false, \n                \"start\": 9.000062\n            }\n        }, \n        {\n            \"streams\": [\n                {\n                    \"bits_per_second\": 865865123.936177, \n                    \"bytes\": 108230760, \n                    \"end\": 11.000062, \n                    \"omitted\": false, \n                    \"seconds\": 0.999978005886078, \n                    \"sender\": false, \n                    \"socket\": 5, \n                    \"start\": 10.000084\n                }\n            ], \n            \"sum\": {\n                \"bits_per_second\": 865865123.936177, \n                \"bytes\": 108230760, \n                \"end\": 11.000062, \n                \"omitted\": false, \n                \"seconds\": 0.999978005886078, \n                \"sender\": false, \n                \"start\": 10.000084\n            }\n        }, \n        {\n            \"streams\": [\n                {\n                    \"bits_per_second\": 865310977.48368, \n                    \"bytes\": 108165600, \n                    \"end\": 12.000078, \n                    \"omitted\": false, \n                    \"seconds\": 1.0000159740448, \n                    \"sender\": false, \n                    \"socket\": 5, \n                    \"start\": 11.000062\n                }\n            ], \n            \"sum\": {\n                \"bits_per_second\": 865310977.48368, \n                \"bytes\": 108165600, \n                \"end\": 12.000078, \n                \"omitted\": false, \n                \"seconds\": 1.0000159740448, \n                \"sender\": false, \n                \"start\": 11.000062\n            }\n        }, \n        {\n            \"streams\": [\n                {\n                    \"bits_per_second\": 865859911.2850132, \n                    \"bytes\": 108230760, \n                    \"end\": 13.000062, \n                    \"omitted\": false, \n                    \"seconds\": 0.9999840259552002, \n                    \"sender\": false, \n                    \"socket\": 5, \n                    \"start\": 12.000078\n                }\n            ], \n            \"sum\": {\n                \"bits_per_second\": 865859911.2850132, \n                \"bytes\": 108230760, \n                \"end\": 13.000062, \n                \"omitted\": false, \n                \"seconds\": 0.9999840259552002, \n                \"sender\": false, \n                \"start\": 12.000078\n            }\n        }, \n        {\n            \"streams\": [\n                {\n                    \"bits_per_second\": 865307470.3482844, \n                    \"bytes\": 108165600, \n                    \"end\": 14.000082, \n                    \"omitted\": false, \n                    \"seconds\": 1.0000200271606445, \n                    \"sender\": false, \n                    \"socket\": 5, \n                    \"start\": 13.000062\n                }\n            ], \n            \"sum\": {\n                \"bits_per_second\": 865307470.3482844, \n                \"bytes\": 108165600, \n                \"end\": 14.000082, \n                \"omitted\": false, \n                \"seconds\": 1.0000200271606445, \n                \"sender\": false, \n                \"start\": 13.000062\n            }\n        }, \n        {\n            \"streams\": [\n                {\n                    \"bits_per_second\": 865857330.787861, \n                    \"bytes\": 108230760, \n                    \"end\": 15.000069, \n                    \"omitted\": false, \n                    \"seconds\": 0.999987006187439, \n                    \"sender\": false, \n                    \"socket\": 5, \n                    \"start\": 14.000082\n                }\n            ], \n            \"sum\": {\n                \"bits_per_second\": 865857330.787861, \n                \"bytes\": 108230760, \n                \"end\": 15.000069, \n                \"omitted\": false, \n                \"seconds\": 0.999987006187439, \n                \"sender\": false, \n                \"start\": 14.000082\n            }\n        }, \n        {\n            \"streams\": [\n                {\n                    \"bits_per_second\": 865328255.6980808, \n                    \"bytes\": 108165600, \n                    \"end\": 16.000065, \n                    \"omitted\": false, \n                    \"seconds\": 0.9999960064888, \n                    \"sender\": false, \n                    \"socket\": 5, \n                    \"start\": 15.000069\n                }\n            ], \n            \"sum\": {\n                \"bits_per_second\": 865328255.6980808, \n                \"bytes\": 108165600, \n                \"end\": 16.000065, \n                \"omitted\": false, \n                \"seconds\": 0.9999960064888, \n                \"sender\": false, \n                \"start\": 15.000069\n            }\n        }, \n        {\n            \"streams\": [\n                {\n                    \"bits_per_second\": 865308398.704887, \n                    \"bytes\": 108165600, \n                    \"end\": 17.000084, \n                    \"omitted\": false, \n                    \"seconds\": 1.0000189542770386, \n                    \"sender\": false, \n                    \"socket\": 5, \n                    \"start\": 16.000065\n                }\n            ], \n            \"sum\": {\n                \"bits_per_second\": 865308398.704887, \n                \"bytes\": 108165600, \n                \"end\": 17.000084, \n                \"omitted\": false, \n                \"seconds\": 1.0000189542770386, \n                \"sender\": false, \n                \"start\": 16.000065\n            }\n        }, \n        {\n            \"streams\": [\n                {\n                    \"bits_per_second\": 865865123.936177, \n                    \"bytes\": 108230760, \n                    \"end\": 18.000062, \n                    \"omitted\": false, \n                    \"seconds\": 0.999978005886078, \n                    \"sender\": false, \n                    \"socket\": 5, \n                    \"start\": 17.000084\n                }\n            ], \n            \"sum\": {\n                \"bits_per_second\": 865865123.936177, \n                \"bytes\": 108230760, \n                \"end\": 18.000062, \n                \"omitted\": false, \n                \"seconds\": 0.999978005886078, \n                \"sender\": false, \n                \"start\": 17.000084\n            }\n        }, \n        {\n            \"streams\": [\n                {\n                    \"bits_per_second\": 865307470.3482844, \n                    \"bytes\": 108165600, \n                    \"end\": 19.000082, \n                    \"omitted\": false, \n                    \"seconds\": 1.0000200271606445, \n                    \"sender\": false, \n                    \"socket\": 5, \n                    \"start\": 18.000062\n                }\n            ], \n            \"sum\": {\n                \"bits_per_second\": 865307470.3482844, \n                \"bytes\": 108165600, \n                \"end\": 19.000082, \n                \"omitted\": false, \n                \"seconds\": 1.0000200271606445, \n                \"sender\": false, \n                \"start\": 18.000062\n            }\n        }, \n        {\n            \"streams\": [\n                {\n                    \"bits_per_second\": 865863420.7858243, \n                    \"bytes\": 108230760, \n                    \"end\": 20.000062, \n                    \"omitted\": false, \n                    \"seconds\": 0.9999799728393555, \n                    \"sender\": false, \n                    \"socket\": 5, \n                    \"start\": 19.000082\n                }\n            ], \n            \"sum\": {\n                \"bits_per_second\": 865863420.7858243, \n                \"bytes\": 108230760, \n                \"end\": 20.000062, \n                \"omitted\": false, \n                \"seconds\": 0.9999799728393555, \n                \"sender\": false, \n                \"start\": 19.000082\n            }\n        }, \n        {\n            \"streams\": [\n                {\n                    \"bits_per_second\": 865305716.7912476, \n                    \"bytes\": 108165600, \n                    \"end\": 21.000084, \n                    \"omitted\": false, \n                    \"seconds\": 1.000022053718567, \n                    \"sender\": false, \n                    \"socket\": 5, \n                    \"start\": 20.000062\n                }\n            ], \n            \"sum\": {\n                \"bits_per_second\": 865305716.7912476, \n                \"bytes\": 108165600, \n                \"end\": 21.000084, \n                \"omitted\": false, \n                \"seconds\": 1.000022053718567, \n                \"sender\": false, \n                \"start\": 20.000062\n            }\n        }, \n        {\n            \"streams\": [\n                {\n                    \"bits_per_second\": 865862543.4079545, \n                    \"bytes\": 108230760, \n                    \"end\": 22.000065, \n                    \"omitted\": false, \n                    \"seconds\": 0.9999809861183167, \n                    \"sender\": false, \n                    \"socket\": 5, \n                    \"start\": 21.000084\n                }\n            ], \n            \"sum\": {\n                \"bits_per_second\": 865862543.4079545, \n                \"bytes\": 108230760, \n                \"end\": 22.000065, \n                \"omitted\": false, \n                \"seconds\": 0.9999809861183167, \n                \"sender\": false, \n                \"start\": 21.000084\n            }\n        }, \n        {\n            \"streams\": [\n                {\n                    \"bits_per_second\": 865321292.7525575, \n                    \"bytes\": 108165600, \n                    \"end\": 23.000069, \n                    \"omitted\": false, \n                    \"seconds\": 1.0000040531158447, \n                    \"sender\": false, \n                    \"socket\": 5, \n                    \"start\": 22.000065\n                }\n            ], \n            \"sum\": {\n                \"bits_per_second\": 865321292.7525575, \n                \"bytes\": 108165600, \n                \"end\": 23.000069, \n                \"omitted\": false, \n                \"seconds\": 1.0000040531158447, \n                \"sender\": false, \n                \"start\": 22.000065\n            }\n        }, \n        {\n            \"streams\": [\n                {\n                    \"bits_per_second\": 865308398.704887, \n                    \"bytes\": 108165600, \n                    \"end\": 24.000088, \n                    \"omitted\": false, \n                    \"seconds\": 1.0000189542770386, \n                    \"sender\": false, \n                    \"socket\": 5, \n                    \"start\": 23.000069\n                }\n            ], \n            \"sum\": {\n                \"bits_per_second\": 865308398.704887, \n                \"bytes\": 108165600, \n                \"end\": 24.000088, \n                \"omitted\": false, \n                \"seconds\": 1.0000189542770386, \n                \"sender\": false, \n                \"start\": 23.000069\n            }\n        }, \n        {\n            \"streams\": [\n                {\n                    \"bits_per_second\": 865866878.7041544, \n                    \"bytes\": 108230760, \n                    \"end\": 25.000064, \n                    \"omitted\": false, \n                    \"seconds\": 0.9999759793281555, \n                    \"sender\": false, \n                    \"socket\": 5, \n                    \"start\": 24.000088\n                }\n            ], \n            \"sum\": {\n                \"bits_per_second\": 865866878.7041544, \n                \"bytes\": 108230760, \n                \"end\": 25.000064, \n                \"omitted\": false, \n                \"seconds\": 0.9999759793281555, \n                \"sender\": false, \n                \"start\": 24.000088\n            }\n        }, \n        {\n            \"streams\": [\n                {\n                    \"bits_per_second\": 865309223.9124285, \n                    \"bytes\": 108165600, \n                    \"end\": 26.000082, \n                    \"omitted\": false, \n                    \"seconds\": 1.0000180006027222, \n                    \"sender\": false, \n                    \"socket\": 5, \n                    \"start\": 25.000064\n                }\n            ], \n            \"sum\": {\n                \"bits_per_second\": 865309223.9124285, \n                \"bytes\": 108165600, \n                \"end\": 26.000082, \n                \"omitted\": false, \n                \"seconds\": 1.0000180006027222, \n                \"sender\": false, \n                \"start\": 25.000064\n            }\n        }, \n        {\n            \"streams\": [\n                {\n                    \"bits_per_second\": 865863420.7858243, \n                    \"bytes\": 108230760, \n                    \"end\": 27.000062, \n                    \"omitted\": false, \n                    \"seconds\": 0.9999799728393555, \n                    \"sender\": false, \n                    \"socket\": 5, \n                    \"start\": 26.000082\n                }\n            ], \n            \"sum\": {\n                \"bits_per_second\": 865863420.7858243, \n                \"bytes\": 108230760, \n                \"end\": 27.000062, \n                \"omitted\": false, \n                \"seconds\": 0.9999799728393555, \n                \"sender\": false, \n                \"start\": 26.000082\n            }\n        }, \n        {\n            \"streams\": [\n                {\n                    \"bits_per_second\": 865306645.1440877, \n                    \"bytes\": 108165600, \n                    \"end\": 28.000083, \n                    \"omitted\": false, \n                    \"seconds\": 1.000020980834961, \n                    \"sender\": false, \n                    \"socket\": 5, \n                    \"start\": 27.000062\n                }\n            ], \n            \"sum\": {\n                \"bits_per_second\": 865306645.1440877, \n                \"bytes\": 108165600, \n                \"end\": 28.000083, \n                \"omitted\": false, \n                \"seconds\": 1.000020980834961, \n                \"sender\": false, \n                \"start\": 27.000062\n            }\n        }, \n        {\n            \"streams\": [\n                {\n                    \"bits_per_second\": 865881588.0683584, \n                    \"bytes\": 108230760, \n                    \"end\": 29.000042, \n                    \"omitted\": false, \n                    \"seconds\": 0.9999589920043945, \n                    \"sender\": false, \n                    \"socket\": 5, \n                    \"start\": 28.000083\n                }\n            ], \n            \"sum\": {\n                \"bits_per_second\": 865881588.0683584, \n                \"bytes\": 108230760, \n                \"end\": 29.000042, \n                \"omitted\": false, \n                \"seconds\": 0.9999589920043945, \n                \"sender\": false, \n                \"start\": 28.000083\n            }\n        }, \n        {\n            \"streams\": [\n                {\n                    \"bits_per_second\": 865295401.8937182, \n                    \"bytes\": 108165600, \n                    \"end\": 30.000076, \n                    \"omitted\": false, \n                    \"seconds\": 1.000033974647522, \n                    \"sender\": false, \n                    \"socket\": 5, \n                    \"start\": 29.000042\n                }\n            ], \n            \"sum\": {\n                \"bits_per_second\": 865295401.8937182, \n                \"bytes\": 108165600, \n                \"end\": 30.000076, \n                \"omitted\": false, \n                \"seconds\": 1.000033974647522, \n                \"sender\": false, \n                \"start\": 29.000042\n            }\n        }, \n        {\n            \"streams\": [\n                {\n                    \"bits_per_second\": 865318713.912282, \n                    \"bytes\": 108165600, \n                    \"end\": 31.000083, \n                    \"omitted\": false, \n                    \"seconds\": 1.0000070333480835, \n                    \"sender\": false, \n                    \"socket\": 5, \n                    \"start\": 30.000076\n                }\n            ], \n            \"sum\": {\n                \"bits_per_second\": 865318713.912282, \n                \"bytes\": 108165600, \n                \"end\": 31.000083, \n                \"omitted\": false, \n                \"seconds\": 1.0000070333480835, \n                \"sender\": false, \n                \"start\": 30.000076\n            }\n        }, \n        {\n            \"streams\": [\n                {\n                    \"bits_per_second\": 865863420.7858243, \n                    \"bytes\": 108230760, \n                    \"end\": 32.000063, \n                    \"omitted\": false, \n                    \"seconds\": 0.9999799728393555, \n                    \"sender\": false, \n                    \"socket\": 5, \n                    \"start\": 31.000083\n                }\n            ], \n            \"sum\": {\n                \"bits_per_second\": 865863420.7858243, \n                \"bytes\": 108230760, \n                \"end\": 32.000063, \n                \"omitted\": false, \n                \"seconds\": 0.9999799728393555, \n                \"sender\": false, \n                \"start\": 31.000083\n            }\n        }, \n        {\n            \"streams\": [\n                {\n                    \"bits_per_second\": 865308398.704887, \n                    \"bytes\": 108165600, \n                    \"end\": 33.000082, \n                    \"omitted\": false, \n                    \"seconds\": 1.0000189542770386, \n                    \"sender\": false, \n                    \"socket\": 5, \n                    \"start\": 32.000063\n                }\n            ], \n            \"sum\": {\n                \"bits_per_second\": 865308398.704887, \n                \"bytes\": 108165600, \n                \"end\": 33.000082, \n                \"omitted\": false, \n                \"seconds\": 1.0000189542770386, \n                \"sender\": false, \n                \"start\": 32.000063\n            }\n        }, \n        {\n            \"streams\": [\n                {\n                    \"bits_per_second\": 865863420.7858243, \n                    \"bytes\": 108230760, \n                    \"end\": 34.000062, \n                    \"omitted\": false, \n                    \"seconds\": 0.9999799728393555, \n                    \"sender\": false, \n                    \"socket\": 5, \n                    \"start\": 33.000082\n                }\n            ], \n            \"sum\": {\n                \"bits_per_second\": 865863420.7858243, \n                \"bytes\": 108230760, \n                \"end\": 34.000062, \n                \"omitted\": false, \n                \"seconds\": 0.9999799728393555, \n                \"sender\": false, \n                \"start\": 33.000082\n            }\n        }, \n        {\n            \"streams\": [\n                {\n                    \"bits_per_second\": 865308398.704887, \n                    \"bytes\": 108165600, \n                    \"end\": 35.000081, \n                    \"omitted\": false, \n                    \"seconds\": 1.0000189542770386, \n                    \"sender\": false, \n                    \"socket\": 5, \n                    \"start\": 34.000062\n                }\n            ], \n            \"sum\": {\n                \"bits_per_second\": 865308398.704887, \n                \"bytes\": 108165600, \n                \"end\": 35.000081, \n                \"omitted\": false, \n                \"seconds\": 1.0000189542770386, \n                \"sender\": false, \n                \"start\": 34.000062\n            }\n        }, \n        {\n            \"streams\": [\n                {\n                    \"bits_per_second\": 865857330.787861, \n                    \"bytes\": 108230760, \n                    \"end\": 36.000068, \n                    \"omitted\": false, \n                    \"seconds\": 0.999987006187439, \n                    \"sender\": false, \n                    \"socket\": 5, \n                    \"start\": 35.000081\n                }\n            ], \n            \"sum\": {\n                \"bits_per_second\": 865857330.787861, \n                \"bytes\": 108230760, \n                \"end\": 36.000068, \n                \"omitted\": false, \n                \"seconds\": 0.999987006187439, \n                \"sender\": false, \n                \"start\": 35.000081\n            }\n        }, \n        {\n            \"streams\": [\n                {\n                    \"bits_per_second\": 865330009.34647, \n                    \"bytes\": 108165600, \n                    \"end\": 37.000062, \n                    \"omitted\": false, \n                    \"seconds\": 0.9999939799308777, \n                    \"sender\": false, \n                    \"socket\": 5, \n                    \"start\": 36.000068\n                }\n            ], \n            \"sum\": {\n                \"bits_per_second\": 865330009.34647, \n                \"bytes\": 108165600, \n                \"end\": 37.000062, \n                \"omitted\": false, \n                \"seconds\": 0.9999939799308777, \n                \"sender\": false, \n                \"start\": 36.000068\n            }\n        }, \n        {\n            \"streams\": [\n                {\n                    \"bits_per_second\": 865306645.1440877, \n                    \"bytes\": 108165600, \n                    \"end\": 38.000083, \n                    \"omitted\": false, \n                    \"seconds\": 1.000020980834961, \n                    \"sender\": false, \n                    \"socket\": 5, \n                    \"start\": 37.000062\n                }\n            ], \n            \"sum\": {\n                \"bits_per_second\": 865306645.1440877, \n                \"bytes\": 108165600, \n                \"end\": 38.000083, \n                \"omitted\": false, \n                \"seconds\": 1.000020980834961, \n                \"sender\": false, \n                \"start\": 37.000062\n            }\n        }, \n        {\n            \"streams\": [\n                {\n                    \"bits_per_second\": 865863420.7858243, \n                    \"bytes\": 108230760, \n                    \"end\": 39.000063, \n                    \"omitted\": false, \n                    \"seconds\": 0.9999799728393555, \n                    \"sender\": false, \n                    \"socket\": 5, \n                    \"start\": 38.000083\n                }\n            ], \n            \"sum\": {\n                \"bits_per_second\": 865863420.7858243, \n                \"bytes\": 108230760, \n                \"end\": 39.000063, \n                \"omitted\": false, \n                \"seconds\": 0.9999799728393555, \n                \"sender\": false, \n                \"start\": 38.000083\n            }\n        }, \n        {\n            \"streams\": [\n                {\n                    \"bits_per_second\": 865312731.0620387, \n                    \"bytes\": 108165600, \n                    \"end\": 40.000077, \n                    \"omitted\": false, \n                    \"seconds\": 1.0000139474868774, \n                    \"sender\": false, \n                    \"socket\": 5, \n                    \"start\": 39.000063\n                }\n            ], \n            \"sum\": {\n                \"bits_per_second\": 865312731.0620387, \n                \"bytes\": 108165600, \n                \"end\": 40.000077, \n                \"omitted\": false, \n                \"seconds\": 1.0000139474868774, \n                \"sender\": false, \n                \"start\": 39.000063\n            }\n        }, \n        {\n            \"streams\": [\n                {\n                    \"bits_per_second\": 865859085.524251, \n                    \"bytes\": 108230760, \n                    \"end\": 41.000062, \n                    \"omitted\": false, \n                    \"seconds\": 0.9999849796295166, \n                    \"sender\": false, \n                    \"socket\": 5, \n                    \"start\": 40.000077\n                }\n            ], \n            \"sum\": {\n                \"bits_per_second\": 865859085.524251, \n                \"bytes\": 108230760, \n                \"end\": 41.000062, \n                \"omitted\": false, \n                \"seconds\": 0.9999849796295166, \n                \"sender\": false, \n                \"start\": 40.000077\n            }\n        }, \n        {\n            \"streams\": [\n                {\n                    \"bits_per_second\": 865307470.3482844, \n                    \"bytes\": 108165600, \n                    \"end\": 42.000082, \n                    \"omitted\": false, \n                    \"seconds\": 1.0000200271606445, \n                    \"sender\": false, \n                    \"socket\": 5, \n                    \"start\": 41.000062\n                }\n            ], \n            \"sum\": {\n                \"bits_per_second\": 865307470.3482844, \n                \"bytes\": 108165600, \n                \"end\": 42.000082, \n                \"omitted\": false, \n                \"seconds\": 1.0000200271606445, \n                \"sender\": false, \n                \"start\": 41.000062\n            }\n        }, \n        {\n            \"streams\": [\n                {\n                    \"bits_per_second\": 865874672.0243443, \n                    \"bytes\": 108230760, \n                    \"end\": 43.000049, \n                    \"omitted\": false, \n                    \"seconds\": 0.9999669790267944, \n                    \"sender\": false, \n                    \"socket\": 5, \n                    \"start\": 42.000082\n                }\n            ], \n            \"sum\": {\n                \"bits_per_second\": 865874672.0243443, \n                \"bytes\": 108230760, \n                \"end\": 43.000049, \n                \"omitted\": false, \n                \"seconds\": 0.9999669790267944, \n                \"sender\": false, \n                \"start\": 42.000082\n            }\n        }, \n        {\n            \"streams\": [\n                {\n                    \"bits_per_second\": 865313556.2778432, \n                    \"bytes\": 108165600, \n                    \"end\": 44.000062, \n                    \"omitted\": false, \n                    \"seconds\": 1.000012993812561, \n                    \"sender\": false, \n                    \"socket\": 5, \n                    \"start\": 43.000049\n                }\n            ], \n            \"sum\": {\n                \"bits_per_second\": 865313556.2778432, \n                \"bytes\": 108165600, \n                \"end\": 44.000062, \n                \"omitted\": false, \n                \"seconds\": 1.000012993812561, \n                \"sender\": false, \n                \"start\": 43.000049\n            }\n        }, \n        {\n            \"streams\": [\n                {\n                    \"bits_per_second\": 865311802.6961398, \n                    \"bytes\": 108165600, \n                    \"end\": 45.000077, \n                    \"omitted\": false, \n                    \"seconds\": 1.0000150203704834, \n                    \"sender\": false, \n                    \"socket\": 5, \n                    \"start\": 44.000062\n                }\n            ], \n            \"sum\": {\n                \"bits_per_second\": 865311802.6961398, \n                \"bytes\": 108165600, \n                \"end\": 45.000077, \n                \"omitted\": false, \n                \"seconds\": 1.0000150203704834, \n                \"sender\": false, \n                \"start\": 44.000062\n            }\n        }, \n        {\n            \"streams\": [\n                {\n                    \"bits_per_second\": 865859911.2850132, \n                    \"bytes\": 108230760, \n                    \"end\": 46.000061, \n                    \"omitted\": false, \n                    \"seconds\": 0.9999840259552002, \n                    \"sender\": false, \n                    \"socket\": 5, \n                    \"start\": 45.000077\n                }\n            ], \n            \"sum\": {\n                \"bits_per_second\": 865859911.2850132, \n                \"bytes\": 108230760, \n                \"end\": 46.000061, \n                \"omitted\": false, \n                \"seconds\": 0.9999840259552002, \n                \"sender\": false, \n                \"start\": 45.000077\n            }\n        }, \n        {\n            \"streams\": [\n                {\n                    \"bits_per_second\": 865302312.8478764, \n                    \"bytes\": 108165600, \n                    \"end\": 47.000087, \n                    \"omitted\": false, \n                    \"seconds\": 1.000025987625122, \n                    \"sender\": false, \n                    \"socket\": 5, \n                    \"start\": 46.000061\n                }\n            ], \n            \"sum\": {\n                \"bits_per_second\": 865302312.8478764, \n                \"bytes\": 108165600, \n                \"end\": 47.000087, \n                \"omitted\": false, \n                \"seconds\": 1.000025987625122, \n                \"sender\": false, \n                \"start\": 46.000061\n            }\n        }, \n        {\n            \"streams\": [\n                {\n                    \"bits_per_second\": 865868581.8681105, \n                    \"bytes\": 108230760, \n                    \"end\": 48.000061, \n                    \"omitted\": false, \n                    \"seconds\": 0.999974012374878, \n                    \"sender\": false, \n                    \"socket\": 5, \n                    \"start\": 47.000087\n                }\n            ], \n            \"sum\": {\n                \"bits_per_second\": 865868581.8681105, \n                \"bytes\": 108230760, \n                \"end\": 48.000061, \n                \"omitted\": false, \n                \"seconds\": 0.999974012374878, \n                \"sender\": false, \n                \"start\": 47.000087\n            }\n        }, \n        {\n            \"streams\": [\n                {\n                    \"bits_per_second\": 865306645.1440877, \n                    \"bytes\": 108165600, \n                    \"end\": 49.000082, \n                    \"omitted\": false, \n                    \"seconds\": 1.000020980834961, \n                    \"sender\": false, \n                    \"socket\": 5, \n                    \"start\": 48.000061\n                }\n            ], \n            \"sum\": {\n                \"bits_per_second\": 865306645.1440877, \n                \"bytes\": 108165600, \n                \"end\": 49.000082, \n                \"omitted\": false, \n                \"seconds\": 1.000020980834961, \n                \"sender\": false, \n                \"start\": 48.000061\n            }\n        }, \n        {\n            \"streams\": [\n                {\n                    \"bits_per_second\": 865859085.524251, \n                    \"bytes\": 108230760, \n                    \"end\": 50.000067, \n                    \"omitted\": false, \n                    \"seconds\": 0.9999849796295166, \n                    \"sender\": false, \n                    \"socket\": 5, \n                    \"start\": 49.000082\n                }\n            ], \n            \"sum\": {\n                \"bits_per_second\": 865859085.524251, \n                \"bytes\": 108230760, \n                \"end\": 50.000067, \n                \"omitted\": false, \n                \"seconds\": 0.9999849796295166, \n                \"sender\": false, \n                \"start\": 49.000082\n            }\n        }, \n        {\n            \"streams\": [\n                {\n                    \"bits_per_second\": 865328255.6980808, \n                    \"bytes\": 108165600, \n                    \"end\": 51.000063, \n                    \"omitted\": false, \n                    \"seconds\": 0.9999960064888, \n                    \"sender\": false, \n                    \"socket\": 5, \n                    \"start\": 50.000067\n                }\n            ], \n            \"sum\": {\n                \"bits_per_second\": 865328255.6980808, \n                \"bytes\": 108165600, \n                \"end\": 51.000063, \n                \"omitted\": false, \n                \"seconds\": 0.9999960064888, \n                \"sender\": false, \n                \"start\": 50.000067\n            }\n        }, \n        {\n            \"streams\": [\n                {\n                    \"bits_per_second\": 865312731.0620387, \n                    \"bytes\": 108165600, \n                    \"end\": 52.000077, \n                    \"omitted\": false, \n                    \"seconds\": 1.0000139474868774, \n                    \"sender\": false, \n                    \"socket\": 5, \n                    \"start\": 51.000063\n                }\n            ], \n            \"sum\": {\n                \"bits_per_second\": 865312731.0620387, \n                \"bytes\": 108165600, \n                \"end\": 52.000077, \n                \"omitted\": false, \n                \"seconds\": 1.0000139474868774, \n                \"sender\": false, \n                \"start\": 51.000063\n            }\n        }, \n        {\n            \"streams\": [\n                {\n                    \"bits_per_second\": 865859085.524251, \n                    \"bytes\": 108230760, \n                    \"end\": 53.000062, \n                    \"omitted\": false, \n                    \"seconds\": 0.9999849796295166, \n                    \"sender\": false, \n                    \"socket\": 5, \n                    \"start\": 52.000077\n                }\n            ], \n            \"sum\": {\n                \"bits_per_second\": 865859085.524251, \n                \"bytes\": 108230760, \n                \"end\": 53.000062, \n                \"omitted\": false, \n                \"seconds\": 0.9999849796295166, \n                \"sender\": false, \n                \"start\": 52.000077\n            }\n        }, \n        {\n            \"streams\": [\n                {\n                    \"bits_per_second\": 865307470.3482844, \n                    \"bytes\": 108165600, \n                    \"end\": 54.000082, \n                    \"omitted\": false, \n                    \"seconds\": 1.0000200271606445, \n                    \"sender\": false, \n                    \"socket\": 5, \n                    \"start\": 53.000062\n                }\n            ], \n            \"sum\": {\n                \"bits_per_second\": 865307470.3482844, \n                \"bytes\": 108165600, \n                \"end\": 54.000082, \n                \"omitted\": false, \n                \"seconds\": 1.0000200271606445, \n                \"sender\": false, \n                \"start\": 53.000062\n            }\n        }, \n        {\n            \"streams\": [\n                {\n                    \"bits_per_second\": 865862543.4079545, \n                    \"bytes\": 108230760, \n                    \"end\": 55.000063, \n                    \"omitted\": false, \n                    \"seconds\": 0.9999809861183167, \n                    \"sender\": false, \n                    \"socket\": 5, \n                    \"start\": 54.000082\n                }\n            ], \n            \"sum\": {\n                \"bits_per_second\": 865862543.4079545, \n                \"bytes\": 108230760, \n                \"end\": 55.000063, \n                \"omitted\": false, \n                \"seconds\": 0.9999809861183167, \n                \"sender\": false, \n                \"start\": 54.000082\n            }\n        }, \n        {\n            \"streams\": [\n                {\n                    \"bits_per_second\": 865308398.704887, \n                    \"bytes\": 108165600, \n                    \"end\": 56.000082, \n                    \"omitted\": false, \n                    \"seconds\": 1.0000189542770386, \n                    \"sender\": false, \n                    \"socket\": 5, \n                    \"start\": 55.000063\n                }\n            ], \n            \"sum\": {\n                \"bits_per_second\": 865308398.704887, \n                \"bytes\": 108165600, \n                \"end\": 56.000082, \n                \"omitted\": false, \n                \"seconds\": 1.0000189542770386, \n                \"sender\": false, \n                \"start\": 55.000063\n            }\n        }, \n        {\n            \"streams\": [\n                {\n                    \"bits_per_second\": 865870336.6501037, \n                    \"bytes\": 108230760, \n                    \"end\": 57.000054, \n                    \"omitted\": false, \n                    \"seconds\": 0.9999719858169556, \n                    \"sender\": false, \n                    \"socket\": 5, \n                    \"start\": 56.000082\n                }\n            ], \n            \"sum\": {\n                \"bits_per_second\": 865870336.6501037, \n                \"bytes\": 108230760, \n                \"end\": 57.000054, \n                \"omitted\": false, \n                \"seconds\": 0.9999719858169556, \n                \"sender\": false, \n                \"start\": 56.000082\n            }\n        }, \n        {\n            \"streams\": [\n                {\n                    \"bits_per_second\": 865304066.391117, \n                    \"bytes\": 108165600, \n                    \"end\": 58.000078, \n                    \"omitted\": false, \n                    \"seconds\": 1.0000239610672, \n                    \"sender\": false, \n                    \"socket\": 5, \n                    \"start\": 57.000054\n                }\n            ], \n            \"sum\": {\n                \"bits_per_second\": 865304066.391117, \n                \"bytes\": 108165600, \n                \"end\": 58.000078, \n                \"omitted\": false, \n                \"seconds\": 1.0000239610672, \n                \"sender\": false, \n                \"start\": 57.000054\n            }\n        }, \n        {\n            \"streams\": [\n                {\n                    \"bits_per_second\": 865325676.816303, \n                    \"bytes\": 108165600, \n                    \"end\": 59.000077, \n                    \"omitted\": false, \n                    \"seconds\": 0.9999989867210388, \n                    \"sender\": false, \n                    \"socket\": 5, \n                    \"start\": 58.000078\n                }\n            ], \n            \"sum\": {\n                \"bits_per_second\": 865325676.816303, \n                \"bytes\": 108165600, \n                \"end\": 59.000077, \n                \"omitted\": false, \n                \"seconds\": 0.9999989867210388, \n                \"sender\": false, \n                \"start\": 58.000078\n            }\n        }, \n        {\n            \"streams\": [\n                {\n                    \"bits_per_second\": 865859085.524251, \n                    \"bytes\": 108230760, \n                    \"end\": 60.000062, \n                    \"omitted\": false, \n                    \"seconds\": 0.9999849796295166, \n                    \"sender\": false, \n                    \"socket\": 5, \n                    \"start\": 59.000077\n                }\n            ], \n            \"sum\": {\n                \"bits_per_second\": 865859085.524251, \n                \"bytes\": 108230760, \n                \"end\": 60.000062, \n                \"omitted\": false, \n                \"seconds\": 0.9999849796295166, \n                \"sender\": false, \n                \"start\": 59.000077\n            }\n        }, \n        {\n            \"streams\": [\n                {\n                    \"bits_per_second\": 861081868.7768016, \n                    \"bytes\": 8275320, \n                    \"end\": 60.076945, \n                    \"omitted\": false, \n                    \"seconds\": 0.076883003115654, \n                    \"sender\": false, \n                    \"socket\": 5, \n                    \"start\": 60.000062\n                }\n            ], \n            \"sum\": {\n                \"bits_per_second\": 861081868.7768016, \n                \"bytes\": 8275320, \n                \"end\": 60.076945, \n                \"omitted\": false, \n                \"seconds\": 0.076883003115654, \n                \"sender\": false, \n                \"start\": 60.000062\n            }\n        }\n    ], \n    \"start\": {\n        \"accepted_connection\": {\n            \"host\": \"10.0.0.1\", \n            \"port\": 58579\n        }, \n        \"connected\": [\n            {\n                \"local_host\": \"10.0.0.2\", \n                \"local_port\": 5201, \n                \"remote_host\": \"10.0.0.1\", \n                \"remote_port\": 52235, \n                \"socket\": 5\n            }\n        ], \n        \"cookie\": \"cw7u6d6oxnzvwfsxvtrobrxw77i6lj6d37dt\", \n        \"fq_rate\": 0, \n        \"rcvbuf_actual\": 87380, \n        \"sndbuf_actual\": 87380, \n        \"sock_bufsize\": 0, \n        \"system_info\": \"REDACTED\", \n        \"target_bitrate\": 0, \n        \"tcp_mss_default\": 0, \n        \"test_start\": {\n            \"bidir\": 0, \n            \"blksize\": 131072, \n            \"blocks\": 0, \n            \"bytes\": 0, \n            \"duration\": 60, \n            \"fqrate\": 0, \n            \"num_streams\": 1, \n            \"omit\": 0, \n            \"protocol\": \"TCP\", \n            \"reverse\": 0, \n            \"target_bitrate\": 0, \n            \"tos\": 0\n        }, \n        \"timestamp\": {\n            \"time\": \"Wed, 17 Apr 2024 01:18:34 GMT\", \n            \"timesecs\": 1713316714\n        }, \n        \"version\": \"iperf 3.14\"\n    }\n}\n","summary":{"streams":[{"end":60.000073,"rtt":77086,"start":0,"stream-id":5,"retransmits":0,"throughput-bits":867014010.7329535,"throughput-bytes":6502612992}],"summary":{"end":60.000073,"start":0,"retransmits":0,"throughput-bits":867014010.7329535,"throughput-bytes":6502612992,"receiver-throughput-bits":865535784.6175433}},"intervals":[{"streams":[{"end":1.000052,"rtt":77091,"start":0,"omitted":false,"stream-id":5,"retransmits":0,"tcp-window-size":16698336,"throughput-bits":955203089.080411,"throughput-bytes":119406592}],"summary":{"end":1.000052,"start":0,"omitted":false,"retransmits":0,"throughput-bits":955203089.080411,"throughput-bytes":119406592}},{"streams":[{"end":2.000061,"rtt":77084,"start":1.000052,"omitted":false,"stream-id":5,"retransmits":0,"tcp-window-size":16698336,"throughput-bits":870310298.8195692,"throughput-bytes":108789760}],"summary":{"end":2.000061,"start":1.000052,"omitted":false,"retransmits":0,"throughput-bits":870310298.8195692,"throughput-bytes":108789760}},{"streams":[{"end":3.000086,"rtt":77090,"start":2.000061,"omitted":false,"stream-id":5,"retransmits":0,"tcp-window-size":16698336,"throughput-bits":859810795.5388423,"throughput-bytes":107479040}],"summary":{"end":3.000086,"start":2.000061,"omitted":false,"retransmits":0,"throughput-bits":859810795.5388423,"throughput-bytes":107479040}},{"streams":[{"end":4.000088,"rtt":77089,"start":3.000086,"omitted":false,"stream-id":5,"retransmits":0,"tcp-window-size":16698336,"throughput-bits":870316316.2535744,"throughput-bytes":108789760}],"summary":{"end":4.000088,"start":3.000086,"omitted":false,"retransmits":0,"throughput-bits":870316316.2535744,"throughput-bytes":108789760}},{"streams":[{"end":5.000077,"rtt":77086,"start":4.000088,"omitted":false,"stream-id":5,"retransmits":0,"tcp-window-size":16698336,"throughput-bits":859841801.3545495,"throughput-bytes":107479040}],"summary":{"end":5.000077,"start":4.000088,"omitted":false,"retransmits":0,"throughput-bits":859841801.3545495,"throughput-bytes":107479040}},{"streams":[{"end":6.000169,"rtt":77087,"start":5.000077,"omitted":false,"stream-id":5,"retransmits":0,"tcp-window-size":16698336,"throughput-bits":870237992.3704302,"throughput-bytes":108789760}],"summary":{"end":6.000169,"start":5.000077,"omitted":false,"retransmits":0,"throughput-bits":870237992.3704302,"throughput-bytes":108789760}},{"streams":[{"end":7.000061,"rtt":77089,"start":6.000169,"omitted":false,"stream-id":5,"retransmits":0,"tcp-window-size":16698336,"throughput-bits":870412087.6531665,"throughput-bytes":108789760}],"summary":{"end":7.000061,"start":6.000169,"omitted":false,"retransmits":0,"throughput-bits":870412087.6531665,"throughput-bytes":108789760}},{"streams":[{"end":8.00004,"rtt":77090,"start":7.000061,"omitted":false,"stream-id":5,"retransmits":0,"tcp-window-size":16698336,"throughput-bits":859850360.3785022,"throughput-bytes":107479040}],"summary":{"end":8.00004,"start":7.000061,"omitted":false,"retransmits":0,"throughput-bits":859850360.3785022,"throughput-bytes":107479040}},{"streams":[{"end":9.000062,"rtt":77087,"start":8.00004,"omitted":false,"stream-id":5,"retransmits":0,"tcp-window-size":16698336,"throughput-bits":870298886.673284,"throughput-bytes":108789760}],"summary":{"end":9.000062,"start":8.00004,"omitted":false,"retransmits":0,"throughput-bits":870298886.673284,"throughput-bytes":108789760}},{"streams":[{"end":10.000056,"rtt":77086,"start":9.000062,"omitted":false,"stream-id":5,"retransmits":0,"tcp-window-size":16698336,"throughput-bits":859837496.2811615,"throughput-bytes":107479040}],"summary":{"end":10.000056,"start":9.000062,"omitted":false,"retransmits":0,"throughput-bits":859837496.2811615,"throughput-bytes":107479040}},{"streams":[{"end":11.000062,"rtt":77091,"start":10.000056,"omitted":false,"stream-id":5,"retransmits":0,"tcp-window-size":16698336,"throughput-bits":870312892.5309197,"throughput-bytes":108789760}],"summary":{"end":11.000062,"start":10.000056,"omitted":false,"retransmits":0,"throughput-bits":870312892.5309197,"throughput-bytes":108789760}},{"streams":[{"end":12.000064,"rtt":77085,"start":11.000062,"omitted":false,"stream-id":5,"retransmits":0,"tcp-window-size":16698336,"throughput-bits":859830577.5035312,"throughput-bytes":107479040}],"summary":{"end":12.000064,"start":11.000062,"omitted":false,"retransmits":0,"throughput-bits":859830577.5035312,"throughput-bytes":107479040}},{"streams":[{"end":13.000061,"rtt":77089,"start":12.000064,"omitted":false,"stream-id":5,"retransmits":0,"tcp-window-size":16698336,"throughput-bits":870320673.75773,"throughput-bytes":108789760}],"summary":{"end":13.000061,"start":12.000064,"omitted":false,"retransmits":0,"throughput-bits":870320673.75773,"throughput-bytes":108789760}},{"streams":[{"end":14.000083,"rtt":77086,"start":13.000061,"omitted":false,"stream-id":5,"retransmits":0,"tcp-window-size":16698336,"throughput-bits":859813357.9181844,"throughput-bytes":107479040}],"summary":{"end":14.000083,"start":13.000061,"omitted":false,"retransmits":0,"throughput-bits":859813357.9181844,"throughput-bytes":107479040}},{"streams":[{"end":15.00003,"rtt":77085,"start":14.000083,"omitted":false,"stream-id":5,"retransmits":0,"tcp-window-size":16698336,"throughput-bits":870364199.318795,"throughput-bytes":108789760}],"summary":{"end":15.00003,"start":14.000083,"omitted":false,"retransmits":0,"throughput-bits":870364199.318795,"throughput-bytes":108789760}},{"streams":[{"end":16.000161,"rtt":77083,"start":15.00003,"omitted":false,"stream-id":5,"retransmits":0,"tcp-window-size":16698336,"throughput-bits":859719687.2561295,"throughput-bytes":107479040}],"summary":{"end":16.000161,"start":15.00003,"omitted":false,"retransmits":0,"throughput-bits":859719687.2561295,"throughput-bytes":107479040}},{"streams":[{"end":17.000064,"rtt":77089,"start":16.000161,"omitted":false,"stream-id":5,"retransmits":0,"tcp-window-size":16698336,"throughput-bits":870402488.8106927,"throughput-bytes":108789760}],"summary":{"end":17.000064,"start":16.000161,"omitted":false,"retransmits":0,"throughput-bits":870402488.8106927,"throughput-bytes":108789760}},{"streams":[{"end":18.00009,"rtt":77085,"start":17.000064,"omitted":false,"stream-id":5,"retransmits":0,"tcp-window-size":16698336,"throughput-bits":870295463.08776,"throughput-bytes":108789760}],"summary":{"end":18.00009,"start":17.000064,"omitted":false,"retransmits":0,"throughput-bits":870295463.08776,"throughput-bytes":108789760}},{"streams":[{"end":19.000082,"rtt":77086,"start":18.00009,"omitted":false,"stream-id":5,"retransmits":0,"tcp-window-size":16698336,"throughput-bits":859839187.5548513,"throughput-bytes":107479040}],"summary":{"end":19.000082,"start":18.00009,"omitted":false,"retransmits":0,"throughput-bits":859839187.5548513,"throughput-bytes":107479040}},{"streams":[{"end":20.000062,"rtt":77090,"start":19.000082,"omitted":false,"stream-id":5,"retransmits":0,"tcp-window-size":16698336,"throughput-bits":870335510.3490804,"throughput-bytes":108789760}],"summary":{"end":20.000062,"start":19.000082,"omitted":false,"retransmits":0,"throughput-bits":870335510.3490804,"throughput-bytes":108789760}},{"streams":[{"end":21.000082,"rtt":77087,"start":20.000062,"omitted":false,"stream-id":5,"retransmits":0,"tcp-window-size":16698336,"throughput-bits":859815100.3448608,"throughput-bytes":107479040}],"summary":{"end":21.000082,"start":20.000062,"omitted":false,"retransmits":0,"throughput-bits":859815100.3448608,"throughput-bytes":107479040}},{"streams":[{"end":22.000088,"rtt":77089,"start":21.000082,"omitted":false,"stream-id":5,"retransmits":0,"tcp-window-size":16698336,"throughput-bits":870312892.5309197,"throughput-bytes":108789760}],"summary":{"end":22.000088,"start":21.000082,"omitted":false,"retransmits":0,"throughput-bits":870312892.5309197,"throughput-bytes":108789760}},{"streams":[{"end":23.000096,"rtt":77089,"start":22.000088,"omitted":false,"stream-id":5,"retransmits":0,"tcp-window-size":16698336,"throughput-bits":859825452.5548505,"throughput-bytes":107479040}],"summary":{"end":23.000096,"start":22.000088,"omitted":false,"retransmits":0,"throughput-bits":859825452.5548505,"throughput-bytes":107479040}},{"streams":[{"end":24.000114,"rtt":77089,"start":23.000096,"omitted":false,"stream-id":5,"retransmits":0,"tcp-window-size":16698336,"throughput-bits":870302414.031997,"throughput-bytes":108789760}],"summary":{"end":24.000114,"start":23.000096,"omitted":false,"retransmits":0,"throughput-bits":870302414.031997,"throughput-bytes":108789760}},{"streams":[{"end":25.000063,"rtt":77085,"start":24.000114,"omitted":false,"stream-id":5,"retransmits":0,"tcp-window-size":16698336,"throughput-bits":859876192.2384307,"throughput-bytes":107479040}],"summary":{"end":25.000063,"start":24.000114,"omitted":false,"retransmits":0,"throughput-bits":859876192.2384307,"throughput-bytes":107479040}},{"streams":[{"end":26.000076,"rtt":77085,"start":25.000063,"omitted":false,"stream-id":5,"retransmits":0,"tcp-window-size":16698336,"throughput-bits":870306771.396942,"throughput-bytes":108789760}],"summary":{"end":26.000076,"start":25.000063,"omitted":false,"retransmits":0,"throughput-bits":870306771.396942,"throughput-bytes":108789760}},{"streams":[{"end":27.000063,"rtt":77089,"start":26.000076,"omitted":false,"stream-id":5,"retransmits":0,"tcp-window-size":16698336,"throughput-bits":859843492.6451752,"throughput-bytes":107479040}],"summary":{"end":27.000063,"start":26.000076,"omitted":false,"retransmits":0,"throughput-bits":859843492.6451752,"throughput-bytes":107479040}},{"streams":[{"end":28.000081,"rtt":77089,"start":27.000063,"omitted":false,"stream-id":5,"retransmits":0,"tcp-window-size":16698336,"throughput-bits":870302414.031997,"throughput-bytes":108789760}],"summary":{"end":28.000081,"start":27.000063,"omitted":false,"retransmits":0,"throughput-bits":870302414.031997,"throughput-bytes":108789760}},{"streams":[{"end":29.000062,"rtt":77090,"start":28.000081,"omitted":false,"stream-id":5,"retransmits":0,"tcp-window-size":16698336,"throughput-bits":870334628.43965,"throughput-bytes":108789760}],"summary":{"end":29.000062,"start":28.000081,"omitted":false,"retransmits":0,"throughput-bits":870334628.43965,"throughput-bytes":108789760}},{"streams":[{"end":30.000076,"rtt":77080,"start":29.000062,"omitted":false,"stream-id":5,"retransmits":0,"tcp-window-size":16698336,"throughput-bits":859820327.667263,"throughput-bytes":107479040}],"summary":{"end":30.000076,"start":29.000062,"omitted":false,"retransmits":0,"throughput-bits":859820327.667263,"throughput-bytes":107479040}},{"streams":[{"end":31.00008,"rtt":77088,"start":30.000076,"omitted":false,"stream-id":5,"retransmits":0,"tcp-window-size":16698336,"throughput-bits":870314552.5142974,"throughput-bytes":108789760}],"summary":{"end":31.00008,"start":30.000076,"omitted":false,"retransmits":0,"throughput-bits":870314552.5142974,"throughput-bytes":108789760}},{"streams":[{"end":32.000156,"rtt":77090,"start":31.00008,"omitted":false,"stream-id":5,"retransmits":0,"tcp-window-size":16698336,"throughput-bits":859766929.973273,"throughput-bytes":107479040}],"summary":{"end":32.000156,"start":31.00008,"omitted":false,"retransmits":0,"throughput-bits":859766929.973273,"throughput-bytes":107479040}},{"streams":[{"end":33.000062,"rtt":77088,"start":32.000156,"omitted":false,"stream-id":5,"retransmits":0,"tcp-window-size":16698336,"throughput-bits":870399894.565285,"throughput-bytes":108789760}],"summary":{"end":33.000062,"start":32.000156,"omitted":false,"retransmits":0,"throughput-bits":870399894.565285,"throughput-bytes":108789760}},{"streams":[{"end":34.000064,"rtt":77086,"start":33.000062,"omitted":false,"stream-id":5,"retransmits":0,"tcp-window-size":16698336,"throughput-bits":859830577.5035312,"throughput-bytes":107479040}],"summary":{"end":34.000064,"start":33.000062,"omitted":false,"retransmits":0,"throughput-bits":859830577.5035312,"throughput-bytes":107479040}},{"streams":[{"end":35.000062,"rtt":77078,"start":34.000064,"omitted":false,"stream-id":5,"retransmits":0,"tcp-window-size":16698336,"throughput-bits":870319843.7535744,"throughput-bytes":108789760}],"summary":{"end":35.000062,"start":34.000064,"omitted":false,"retransmits":0,"throughput-bits":870319843.7535744,"throughput-bytes":108789760}},{"streams":[{"end":36.000066,"rtt":77086,"start":35.000062,"omitted":false,"stream-id":5,"retransmits":0,"tcp-window-size":16698336,"throughput-bits":859828835.014125,"throughput-bytes":107479040}],"summary":{"end":36.000066,"start":35.000062,"omitted":false,"retransmits":0,"throughput-bits":859828835.014125,"throughput-bytes":107479040}},{"streams":[{"end":37.000062,"rtt":77090,"start":36.000066,"omitted":false,"stream-id":5,"retransmits":0,"tcp-window-size":16698336,"throughput-bits":870321555.63888,"throughput-bytes":108789760}],"summary":{"end":37.000062,"start":36.000066,"omitted":false,"retransmits":0,"throughput-bits":870321555.63888,"throughput-bytes":108789760}},{"streams":[{"end":38.000045,"rtt":77090,"start":37.000062,"omitted":false,"stream-id":5,"retransmits":0,"tcp-window-size":16698336,"throughput-bits":859846926.4981253,"throughput-bytes":107479040}],"summary":{"end":38.000045,"start":37.000062,"omitted":false,"retransmits":0,"throughput-bits":859846926.4981253,"throughput-bytes":107479040}},{"streams":[{"end":39.000063,"rtt":77088,"start":38.000045,"omitted":false,"stream-id":5,"retransmits":0,"tcp-window-size":16698336,"throughput-bits":870302414.031997,"throughput-bytes":108789760}],"summary":{"end":39.000063,"start":38.000045,"omitted":false,"retransmits":0,"throughput-bits":870302414.031997,"throughput-bytes":108789760}},{"streams":[{"end":40.000061,"rtt":77068,"start":39.000063,"omitted":false,"stream-id":5,"retransmits":0,"tcp-window-size":16698336,"throughput-bits":870319843.7535744,"throughput-bytes":108789760}],"summary":{"end":40.000061,"start":39.000063,"omitted":false,"retransmits":0,"throughput-bits":870319843.7535744,"throughput-bytes":108789760}},{"streams":[{"end":41.000063,"rtt":77087,"start":40.000061,"omitted":false,"stream-id":5,"retransmits":0,"tcp-window-size":16698336,"throughput-bits":859830577.5035312,"throughput-bytes":107479040}],"summary":{"end":41.000063,"start":40.000061,"omitted":false,"retransmits":0,"throughput-bits":859830577.5035312,"throughput-bytes":107479040}},{"streams":[{"end":42.000073,"rtt":77085,"start":41.000063,"omitted":false,"stream-id":5,"retransmits":0,"tcp-window-size":16698336,"throughput-bits":870309365.0872675,"throughput-bytes":108789760}],"summary":{"end":42.000073,"start":41.000063,"omitted":false,"retransmits":0,"throughput-bits":870309365.0872675,"throughput-bytes":108789760}},{"streams":[{"end":43.000033,"rtt":77092,"start":42.000073,"omitted":false,"stream-id":5,"retransmits":0,"tcp-window-size":16698336,"throughput-bits":859866710.1254233,"throughput-bytes":107479040}],"summary":{"end":43.000033,"start":42.000073,"omitted":false,"retransmits":0,"throughput-bits":859866710.1254233,"throughput-bytes":107479040}},{"streams":[{"end":44.000064,"rtt":77084,"start":43.000033,"omitted":false,"stream-id":5,"retransmits":0,"tcp-window-size":16698336,"throughput-bits":870291105.8360485,"throughput-bytes":108789760}],"summary":{"end":44.000064,"start":43.000033,"omitted":false,"retransmits":0,"throughput-bits":870291105.8360485,"throughput-bytes":108789760}},{"streams":[{"end":45.000028,"rtt":77089,"start":44.000064,"omitted":false,"stream-id":5,"retransmits":0,"tcp-window-size":16698336,"throughput-bits":859863276.1144575,"throughput-bytes":107479040}],"summary":{"end":45.000028,"start":44.000064,"omitted":false,"retransmits":0,"throughput-bits":859863276.1144575,"throughput-bytes":107479040}},{"streams":[{"end":46.000064,"rtt":77084,"start":45.000028,"omitted":false,"stream-id":5,"retransmits":0,"tcp-window-size":16698336,"throughput-bits":870286748.627967,"throughput-bytes":108789760}],"summary":{"end":46.000064,"start":45.000028,"omitted":false,"retransmits":0,"throughput-bits":870286748.627967,"throughput-bytes":108789760}},{"streams":[{"end":47.000082,"rtt":77084,"start":46.000064,"omitted":false,"stream-id":5,"retransmits":0,"tcp-window-size":16698336,"throughput-bits":859816842.7785993,"throughput-bytes":107479040}],"summary":{"end":47.000082,"start":46.000064,"omitted":false,"retransmits":0,"throughput-bits":859816842.7785993,"throughput-bytes":107479040}},{"streams":[{"end":48.000081,"rtt":77086,"start":47.000082,"omitted":false,"stream-id":5,"retransmits":0,"tcp-window-size":16698336,"throughput-bits":870318961.8758936,"throughput-bytes":108789760}],"summary":{"end":48.000081,"start":47.000082,"omitted":false,"retransmits":0,"throughput-bits":870318961.8758936,"throughput-bytes":108789760}},{"streams":[{"end":49.000155,"rtt":77084,"start":48.000081,"omitted":false,"stream-id":5,"retransmits":0,"tcp-window-size":16698336,"throughput-bits":859768672.21178,"throughput-bytes":107479040}],"summary":{"end":49.000155,"start":48.000081,"omitted":false,"retransmits":0,"throughput-bits":859768672.21178,"throughput-bytes":107479040}},{"streams":[{"end":50.000094,"rtt":77089,"start":49.000155,"omitted":false,"stream-id":5,"retransmits":0,"tcp-window-size":16698336,"throughput-bits":870371151.3610555,"throughput-bytes":108789760}],"summary":{"end":50.000094,"start":49.000155,"omitted":false,"retransmits":0,"throughput-bits":870371151.3610555,"throughput-bytes":108789760}},{"streams":[{"end":51.000061,"rtt":77085,"start":50.000094,"omitted":false,"stream-id":5,"retransmits":0,"tcp-window-size":16698336,"throughput-bits":870346819.699013,"throughput-bytes":108789760}],"summary":{"end":51.000061,"start":50.000094,"omitted":false,"retransmits":0,"throughput-bits":870346819.699013,"throughput-bytes":108789760}},{"streams":[{"end":52.000119,"rtt":77089,"start":51.000061,"omitted":false,"stream-id":5,"retransmits":0,"tcp-window-size":16698336,"throughput-bits":859782405.3977884,"throughput-bytes":107479040}],"summary":{"end":52.000119,"start":51.000061,"omitted":false,"retransmits":0,"throughput-bits":859782405.3977884,"throughput-bytes":107479040}},{"streams":[{"end":53.000062,"rtt":77092,"start":52.000119,"omitted":false,"stream-id":5,"retransmits":0,"tcp-window-size":16698336,"throughput-bits":870367675.326043,"throughput-bytes":108789760}],"summary":{"end":53.000062,"start":52.000119,"omitted":false,"retransmits":0,"throughput-bits":870367675.326043,"throughput-bytes":108789760}},{"streams":[{"end":54.000069,"rtt":77078,"start":53.000062,"omitted":false,"stream-id":5,"retransmits":0,"tcp-window-size":16698336,"throughput-bits":859826272.542534,"throughput-bytes":107479040}],"summary":{"end":54.000069,"start":53.000062,"omitted":false,"retransmits":0,"throughput-bits":859826272.542534,"throughput-bytes":107479040}},{"streams":[{"end":55.000062,"rtt":77091,"start":54.000069,"omitted":false,"stream-id":5,"retransmits":0,"tcp-window-size":16698336,"throughput-bits":870324149.4173266,"throughput-bytes":108789760}],"summary":{"end":55.000062,"start":54.000069,"omitted":false,"retransmits":0,"throughput-bits":870324149.4173266,"throughput-bytes":108789760}},{"streams":[{"end":56.00008,"rtt":77086,"start":55.000062,"omitted":false,"stream-id":5,"retransmits":0,"tcp-window-size":16698336,"throughput-bits":859816842.7785993,"throughput-bytes":107479040}],"summary":{"end":56.00008,"start":55.000062,"omitted":false,"retransmits":0,"throughput-bits":859816842.7785993,"throughput-bytes":107479040}},{"streams":[{"end":57.000066,"rtt":77086,"start":56.00008,"omitted":false,"stream-id":5,"retransmits":0,"tcp-window-size":16698336,"throughput-bits":870330270.7957577,"throughput-bytes":108789760}],"summary":{"end":57.000066,"start":56.00008,"omitted":false,"retransmits":0,"throughput-bits":870330270.7957577,"throughput-bytes":108789760}},{"streams":[{"end":58.000066,"rtt":77088,"start":57.000066,"omitted":false,"stream-id":5,"retransmits":0,"tcp-window-size":16698336,"throughput-bits":859832320,"throughput-bytes":107479040}],"summary":{"end":58.000066,"start":57.000066,"omitted":false,"retransmits":0,"throughput-bits":859832320,"throughput-bytes":107479040}},{"streams":[{"end":59.000039,"rtt":77092,"start":58.000066,"omitted":false,"stream-id":5,"retransmits":0,"tcp-window-size":16698336,"throughput-bits":870341580.0095215,"throughput-bytes":108789760}],"summary":{"end":59.000039,"start":58.000066,"omitted":false,"retransmits":0,"throughput-bits":870341580.0095215,"throughput-bytes":108789760}},{"streams":[{"end":60.000073,"rtt":77093,"start":59.000039,"omitted":false,"stream-id":5,"retransmits":0,"tcp-window-size":16698336,"throughput-bits":859803108.4924507,"throughput-bytes":107479040}],"summary":{"end":60.000073,"start":59.000039,"omitted":false,"retransmits":0,"throughput-bits":859803108.4924507,"throughput-bytes":107479040}}],"succeeded":true}
