{"diags":"Participant 0:\n/usr/bin/iperf3 -p 5201 -B 172.16.0.2 -c 172.16.0.1 -t 60 --json --rsa-public-key-path /var/run/pscheduler-server/runner/tmp/tmplugxlvip/tmpkogqsb5s/public-key --username 0im6czhwTaQmfOrWYBdl\n\n{\n    \"end\": {\n        \"cpu_utilization_percent\": {\n            \"host_system\": 0.04134961812582773, \n            \"host_total\": 0.05850874462396314, \n            \"host_user\": 0.0171574626635094, \n            \"remote_system\": 0.855582203928019, \n            \"remote_total\": 0.9919912633447325, \n            \"remote_user\": 0.1364090594167137\n        }, \n        \"receiver_tcp_congestion\": \"htcp\", \n        \"sender_tcp_congestion\": \"htcp\", \n        \"streams\": [\n            {\n                \"receiver\": {\n                    \"bits_per_second\": 4013481.258756496, \n                    \"bytes\": 30741944, \n                    \"end\": 61.277364, \n                    \"seconds\": 60.001027, \n                    \"sender\": true, \n                    \"socket\": 5, \n                    \"start\": 0\n                }, \n                \"sender\": {\n                    \"bits_per_second\": 4578703.494525186, \n                    \"bytes\": 34340864, \n                    \"end\": 60.001027, \n                    \"max_rtt\": 399613, \n                    \"max_snd_cwnd\": 296840, \n                    \"max_snd_wnd\": 0, \n                    \"mean_rtt\": 130391, \n                    \"min_rtt\": 18886, \n                    \"retransmits\": 1046, \n                    \"seconds\": 60.001027, \n                    \"sender\": true, \n                    \"socket\": 5, \n                    \"start\": 0\n                }\n            }\n        ], \n        \"sum_received\": {\n            \"bits_per_second\": 4013481.258756496, \n            \"bytes\": 30741944, \n            \"end\": 61.277364, \n            \"seconds\": 61.277364, \n            \"sender\": true, \n            \"start\": 0\n        }, \n        \"sum_sent\": {\n            \"bits_per_second\": 4578703.494525186, \n            \"bytes\": 34340864, \n            \"end\": 60.001027, \n            \"retransmits\": 1046, \n            \"seconds\": 60.001027, \n            \"sender\": true, \n            \"start\": 0\n        }\n    }, \n    \"intervals\": [\n        {\n            \"streams\": [\n                {\n                    \"bits_per_second\": 33528983.315692544, \n                    \"bytes\": 4194304, \n                    \"end\": 1.000759, \n                    \"omitted\": false, \n                    \"pmtu\": 1500, \n                    \"retransmits\": 95, \n                    \"rtt\": 374399, \n                    \"rttvar\": 1716, \n                    \"seconds\": 1.00075900554657, \n                    \"sender\": true, \n                    \"snd_cwnd\": 296840, \n                    \"snd_wnd\": -1, \n                    \"socket\": 5, \n                    \"start\": 0\n                }\n            ], \n            \"sum\": {\n                \"bits_per_second\": 33528983.315692544, \n                \"bytes\": 4194304, \n                \"end\": 1.000759, \n                \"omitted\": false, \n                \"retransmits\": 95, \n                \"seconds\": 1.00075900554657, \n                \"sender\": true, \n                \"start\": 0\n            }\n        }, \n        {\n            \"streams\": [\n                {\n                    \"bits_per_second\": 10490312.60074413, \n                    \"bytes\": 1310720, \n                    \"end\": 2.000325, \n                    \"omitted\": false, \n                    \"pmtu\": 1500, \n                    \"retransmits\": 217, \n                    \"rtt\": 399613, \n                    \"rttvar\": 15490, \n                    \"seconds\": 0.9995660185813904, \n                    \"sender\": true, \n                    \"snd_cwnd\": 260640, \n                    \"snd_wnd\": -1, \n                    \"socket\": 5, \n                    \"start\": 1.000759\n                }\n            ], \n            \"sum\": {\n                \"bits_per_second\": 10490312.60074413, \n                \"bytes\": 1310720, \n                \"end\": 2.000325, \n                \"omitted\": false, \n                \"retransmits\": 217, \n                \"seconds\": 0.9995660185813904, \n                \"sender\": true, \n                \"start\": 1.000759\n            }\n        }, \n        {\n            \"streams\": [\n                {\n                    \"bits_per_second\": 0, \n                    \"bytes\": 0, \n                    \"end\": 3.001018, \n                    \"omitted\": false, \n                    \"pmtu\": 1500, \n                    \"retransmits\": 0, \n                    \"rtt\": 399613, \n                    \"rttvar\": 15490, \n                    \"seconds\": 1.0006929636001587, \n                    \"sender\": true, \n                    \"snd_cwnd\": 260640, \n                    \"snd_wnd\": -1, \n                    \"socket\": 5, \n                    \"start\": 2.000325\n                }\n            ], \n            \"sum\": {\n                \"bits_per_second\": 0, \n                \"bytes\": 0, \n                \"end\": 3.001018, \n                \"omitted\": false, \n                \"retransmits\": 0, \n                \"seconds\": 1.0006929636001587, \n                \"sender\": true, \n                \"start\": 2.000325\n            }\n        }, \n        {\n            \"streams\": [\n                {\n                    \"bits_per_second\": 0, \n                    \"bytes\": 0, \n                    \"end\": 4.000168, \n                    \"omitted\": false, \n                    \"pmtu\": 1500, \n                    \"retransmits\": 1, \n                    \"rtt\": 399613, \n                    \"rttvar\": 15490, \n                    \"seconds\": 0.999149978160858, \n                    \"sender\": true, \n                    \"snd_cwnd\": 1448, \n                    \"snd_wnd\": -1, \n                    \"socket\": 5, \n                    \"start\": 3.001018\n                }\n            ], \n            \"sum\": {\n                \"bits_per_second\": 0, \n                \"bytes\": 0, \n                \"end\": 4.000168, \n                \"omitted\": false, \n                \"retransmits\": 1, \n                \"seconds\": 0.999149978160858, \n                \"sender\": true, \n                \"start\": 3.001018\n            }\n        }, \n        {\n            \"streams\": [\n                {\n                    \"bits_per_second\": 0, \n                    \"bytes\": 0, \n                    \"end\": 5.000492, \n                    \"omitted\": false, \n                    \"pmtu\": 1500, \n                    \"retransmits\": 0, \n                    \"rtt\": 399613, \n                    \"rttvar\": 15490, \n                    \"seconds\": 1.000324010848999, \n                    \"sender\": true, \n                    \"snd_cwnd\": 1448, \n                    \"snd_wnd\": -1, \n                    \"socket\": 5, \n                    \"start\": 4.000168\n                }\n            ], \n            \"sum\": {\n                \"bits_per_second\": 0, \n                \"bytes\": 0, \n                \"end\": 5.000492, \n                \"omitted\": false, \n                \"retransmits\": 0, \n                \"seconds\": 1.000324010848999, \n                \"sender\": true, \n                \"start\": 4.000168\n            }\n        }, \n        {\n            \"streams\": [\n                {\n                    \"bits_per_second\": 0, \n                    \"bytes\": 0, \n                    \"end\": 6.000839, \n                    \"omitted\": false, \n                    \"pmtu\": 1500, \n                    \"retransmits\": 145, \n                    \"rtt\": 36958, \n                    \"rttvar\": 1960, \n                    \"seconds\": 1.0003470182418823, \n                    \"sender\": true, \n                    \"snd_cwnd\": 105704, \n                    \"snd_wnd\": -1, \n                    \"socket\": 5, \n                    \"start\": 5.000492\n                }\n            ], \n            \"sum\": {\n                \"bits_per_second\": 0, \n                \"bytes\": 0, \n                \"end\": 6.000839, \n                \"omitted\": false, \n                \"retransmits\": 145, \n                \"seconds\": 1.0003470182418823, \n                \"sender\": true, \n                \"start\": 5.000492\n            }\n        }, \n        {\n            \"streams\": [\n                {\n                    \"bits_per_second\": 20986231.56295609, \n                    \"bytes\": 2621440, \n                    \"end\": 7.000138, \n                    \"omitted\": false, \n                    \"pmtu\": 1500, \n                    \"retransmits\": 66, \n                    \"rtt\": 69034, \n                    \"rttvar\": 244, \n                    \"seconds\": 0.9992989897727966, \n                    \"sender\": true, \n                    \"snd_cwnd\": 189688, \n                    \"snd_wnd\": -1, \n                    \"socket\": 5, \n                    \"start\": 6.000839\n                }\n            ], \n            \"sum\": {\n                \"bits_per_second\": 20986231.56295609, \n                \"bytes\": 2621440, \n                \"end\": 7.000138, \n                \"omitted\": false, \n                \"retransmits\": 66, \n                \"seconds\": 0.9992989897727966, \n                \"sender\": true, \n                \"start\": 6.000839\n            }\n        }, \n        {\n            \"streams\": [\n                {\n                    \"bits_per_second\": 10480341.551395845, \n                    \"bytes\": 1310720, \n                    \"end\": 8.000655, \n                    \"omitted\": false, \n                    \"pmtu\": 1500, \n                    \"retransmits\": 61, \n                    \"rtt\": 223865, \n                    \"rttvar\": 103662, \n                    \"seconds\": 1.0005170106887817, \n                    \"sender\": true, \n                    \"snd_cwnd\": 101360, \n                    \"snd_wnd\": -1, \n                    \"socket\": 5, \n                    \"start\": 7.000138\n                }\n            ], \n            \"sum\": {\n                \"bits_per_second\": 10480341.551395845, \n                \"bytes\": 1310720, \n                \"end\": 8.000655, \n                \"omitted\": false, \n                \"retransmits\": 61, \n                \"seconds\": 1.0005170106887817, \n                \"sender\": true, \n                \"start\": 7.000138\n            }\n        }, \n        {\n            \"streams\": [\n                {\n                    \"bits_per_second\": 10482971.991487382, \n                    \"bytes\": 1310720, \n                    \"end\": 9.000921, \n                    \"omitted\": false, \n                    \"pmtu\": 1500, \n                    \"retransmits\": 54, \n                    \"rtt\": 23219, \n                    \"rttvar\": 710, \n                    \"seconds\": 1.0002659559249878, \n                    \"sender\": true, \n                    \"snd_cwnd\": 59368, \n                    \"snd_wnd\": -1, \n                    \"socket\": 5, \n                    \"start\": 8.000655\n                }\n            ], \n            \"sum\": {\n                \"bits_per_second\": 10482971.991487382, \n                \"bytes\": 1310720, \n                \"end\": 9.000921, \n                \"omitted\": false, \n                \"retransmits\": 54, \n                \"seconds\": 1.0002659559249878, \n                \"sender\": true, \n                \"start\": 8.000655\n            }\n        }, \n        {\n            \"streams\": [\n                {\n                    \"bits_per_second\": 0, \n                    \"bytes\": 0, \n                    \"end\": 10.001015, \n                    \"omitted\": false, \n                    \"pmtu\": 1500, \n                    \"retransmits\": 2, \n                    \"rtt\": 23219, \n                    \"rttvar\": 710, \n                    \"seconds\": 1.0000940561294556, \n                    \"sender\": true, \n                    \"snd_cwnd\": 1448, \n                    \"snd_wnd\": -1, \n                    \"socket\": 5, \n                    \"start\": 9.000921\n                }\n            ], \n            \"sum\": {\n                \"bits_per_second\": 0, \n                \"bytes\": 0, \n                \"end\": 10.001015, \n                \"omitted\": false, \n                \"retransmits\": 2, \n                \"seconds\": 1.0000940561294556, \n                \"sender\": true, \n                \"start\": 9.000921\n            }\n        }, \n        {\n            \"streams\": [\n                {\n                    \"bits_per_second\": 0, \n                    \"bytes\": 0, \n                    \"end\": 11.002554, \n                    \"omitted\": false, \n                    \"pmtu\": 1500, \n                    \"retransmits\": 0, \n                    \"rtt\": 23219, \n                    \"rttvar\": 710, \n                    \"seconds\": 1.0015389919281006, \n                    \"sender\": true, \n                    \"snd_cwnd\": 1448, \n                    \"snd_wnd\": -1, \n                    \"socket\": 5, \n                    \"start\": 10.001015\n                }\n            ], \n            \"sum\": {\n                \"bits_per_second\": 0, \n                \"bytes\": 0, \n                \"end\": 11.002554, \n                \"omitted\": false, \n                \"retransmits\": 0, \n                \"seconds\": 1.0015389919281006, \n                \"sender\": true, \n                \"start\": 10.001015\n            }\n        }, \n        {\n            \"streams\": [\n                {\n                    \"bits_per_second\": 0, \n                    \"bytes\": 0, \n                    \"end\": 12.001024, \n                    \"omitted\": false, \n                    \"pmtu\": 1500, \n                    \"retransmits\": 1, \n                    \"rtt\": 210317, \n                    \"rttvar\": 374728, \n                    \"seconds\": 0.9984700083732605, \n                    \"sender\": true, \n                    \"snd_cwnd\": 2896, \n                    \"snd_wnd\": -1, \n                    \"socket\": 5, \n                    \"start\": 11.002554\n                }\n            ], \n            \"sum\": {\n                \"bits_per_second\": 0, \n                \"bytes\": 0, \n                \"end\": 12.001024, \n                \"omitted\": false, \n                \"retransmits\": 1, \n                \"seconds\": 0.9984700083732605, \n                \"sender\": true, \n                \"start\": 11.002554\n            }\n        }, \n        {\n            \"streams\": [\n                {\n                    \"bits_per_second\": 0, \n                    \"bytes\": 0, \n                    \"end\": 13.00104, \n                    \"omitted\": false, \n                    \"pmtu\": 1500, \n                    \"retransmits\": 0, \n                    \"rtt\": 210317, \n                    \"rttvar\": 374728, \n                    \"seconds\": 1.0000159740448, \n                    \"sender\": true, \n                    \"snd_cwnd\": 2896, \n                    \"snd_wnd\": -1, \n                    \"socket\": 5, \n                    \"start\": 12.001024\n                }\n            ], \n            \"sum\": {\n                \"bits_per_second\": 0, \n                \"bytes\": 0, \n                \"end\": 13.00104, \n                \"omitted\": false, \n                \"retransmits\": 0, \n                \"seconds\": 1.0000159740448, \n                \"sender\": true, \n                \"start\": 12.001024\n            }\n        }, \n        {\n            \"streams\": [\n                {\n                    \"bits_per_second\": 0, \n                    \"bytes\": 0, \n                    \"end\": 14.001016, \n                    \"omitted\": false, \n                    \"pmtu\": 1500, \n                    \"retransmits\": 42, \n                    \"rtt\": 23670, \n                    \"rttvar\": 6650, \n                    \"seconds\": 0.9999759793281555, \n                    \"sender\": true, \n                    \"snd_cwnd\": 28960, \n                    \"snd_wnd\": -1, \n                    \"socket\": 5, \n                    \"start\": 13.00104\n                }\n            ], \n            \"sum\": {\n                \"bits_per_second\": 0, \n                \"bytes\": 0, \n                \"end\": 14.001016, \n                \"omitted\": false, \n                \"retransmits\": 42, \n                \"seconds\": 0.9999759793281555, \n                \"sender\": true, \n                \"start\": 13.00104\n            }\n        }, \n        {\n            \"streams\": [\n                {\n                    \"bits_per_second\": 20987701.22549962, \n                    \"bytes\": 2621440, \n                    \"end\": 15.000245, \n                    \"omitted\": false, \n                    \"pmtu\": 1500, \n                    \"retransmits\": 0, \n                    \"rtt\": 30179, \n                    \"rttvar\": 329, \n                    \"seconds\": 0.9992290139198303, \n                    \"sender\": true, \n                    \"snd_cwnd\": 83984, \n                    \"snd_wnd\": -1, \n                    \"socket\": 5, \n                    \"start\": 14.001016\n                }\n            ], \n            \"sum\": {\n                \"bits_per_second\": 20987701.22549962, \n                \"bytes\": 2621440, \n                \"end\": 15.000245, \n                \"omitted\": false, \n                \"retransmits\": 0, \n                \"seconds\": 0.9992290139198303, \n                \"sender\": true, \n                \"start\": 14.001016\n            }\n        }, \n        {\n            \"streams\": [\n                {\n                    \"bits_per_second\": 20970765.02717993, \n                    \"bytes\": 2621440, \n                    \"end\": 16.000281, \n                    \"omitted\": false, \n                    \"pmtu\": 1500, \n                    \"retransmits\": 0, \n                    \"rtt\": 43650, \n                    \"rttvar\": 729, \n                    \"seconds\": 1.0000360012054443, \n                    \"sender\": true, \n                    \"snd_cwnd\": 121632, \n                    \"snd_wnd\": -1, \n                    \"socket\": 5, \n                    \"start\": 15.000245\n                }\n            ], \n            \"sum\": {\n                \"bits_per_second\": 20970765.02717993, \n                \"bytes\": 2621440, \n                \"end\": 16.000281, \n                \"omitted\": false, \n                \"retransmits\": 0, \n                \"seconds\": 1.0000360012054443, \n                \"sender\": true, \n                \"start\": 15.000245\n            }\n        }, \n        {\n            \"streams\": [\n                {\n                    \"bits_per_second\": 20971017.51204015, \n                    \"bytes\": 2621440, \n                    \"end\": 17.000305, \n                    \"omitted\": false, \n                    \"pmtu\": 1500, \n                    \"retransmits\": 0, \n                    \"rtt\": 62290, \n                    \"rttvar\": 524, \n                    \"seconds\": 1.0000239610672, \n                    \"sender\": true, \n                    \"snd_cwnd\": 173760, \n                    \"snd_wnd\": -1, \n                    \"socket\": 5, \n                    \"start\": 16.000281\n                }\n            ], \n            \"sum\": {\n                \"bits_per_second\": 20971017.51204015, \n                \"bytes\": 2621440, \n                \"end\": 17.000305, \n                \"omitted\": false, \n                \"retransmits\": 0, \n                \"seconds\": 1.0000239610672, \n                \"sender\": true, \n                \"start\": 16.000281\n            }\n        }, \n        {\n            \"streams\": [\n                {\n                    \"bits_per_second\": 10480456.433834836, \n                    \"bytes\": 1310720, \n                    \"end\": 18.000811, \n                    \"omitted\": false, \n                    \"pmtu\": 1500, \n                    \"retransmits\": 68, \n                    \"rtt\": 95856, \n                    \"rttvar\": 75785, \n                    \"seconds\": 1.000506043434143, \n                    \"sender\": true, \n                    \"snd_cwnd\": 11584, \n                    \"snd_wnd\": -1, \n                    \"socket\": 5, \n                    \"start\": 17.000305\n                }\n            ], \n            \"sum\": {\n                \"bits_per_second\": 10480456.433834836, \n                \"bytes\": 1310720, \n                \"end\": 18.000811, \n                \"omitted\": false, \n                \"retransmits\": 68, \n                \"seconds\": 1.000506043434143, \n                \"sender\": true, \n                \"start\": 17.000305\n            }\n        }, \n        {\n            \"streams\": [\n                {\n                    \"bits_per_second\": 20981485.983736776, \n                    \"bytes\": 2621440, \n                    \"end\": 19.000336, \n                    \"omitted\": false, \n                    \"pmtu\": 1500, \n                    \"retransmits\": 53, \n                    \"rtt\": 38391, \n                    \"rttvar\": 10689, \n                    \"seconds\": 0.999525010585785, \n                    \"sender\": true, \n                    \"snd_cwnd\": 89776, \n                    \"snd_wnd\": -1, \n                    \"socket\": 5, \n                    \"start\": 18.000811\n                }\n            ], \n            \"sum\": {\n                \"bits_per_second\": 20981485.983736776, \n                \"bytes\": 2621440, \n                \"end\": 19.000336, \n                \"omitted\": false, \n                \"retransmits\": 53, \n                \"seconds\": 0.999525010585785, \n                \"sender\": true, \n                \"start\": 18.000811\n            }\n        }, \n        {\n            \"streams\": [\n                {\n                    \"bits_per_second\": 0, \n                    \"bytes\": 0, \n                    \"end\": 20.001019, \n                    \"omitted\": false, \n                    \"pmtu\": 1500, \n                    \"retransmits\": 64, \n                    \"rtt\": 18886, \n                    \"rttvar\": 876, \n                    \"seconds\": 1.0006829500198364, \n                    \"sender\": true, \n                    \"snd_cwnd\": 47784, \n                    \"snd_wnd\": -1, \n                    \"socket\": 5, \n                    \"start\": 19.000336\n                }\n            ], \n            \"sum\": {\n                \"bits_per_second\": 0, \n                \"bytes\": 0, \n                \"end\": 20.001019, \n                \"omitted\": false, \n                \"retransmits\": 64, \n                \"seconds\": 1.0006829500198364, \n                \"sender\": true, \n                \"start\": 19.000336\n            }\n        }, \n        {\n            \"streams\": [\n                {\n                    \"bits_per_second\": 0, \n                    \"bytes\": 0, \n                    \"end\": 21.001016, \n                    \"omitted\": false, \n                    \"pmtu\": 1500, \n                    \"retransmits\": 2, \n                    \"rtt\": 28352, \n                    \"rttvar\": 11182, \n                    \"seconds\": 0.9999970197677612, \n                    \"sender\": true, \n                    \"snd_cwnd\": 1448, \n                    \"snd_wnd\": -1, \n                    \"socket\": 5, \n                    \"start\": 20.001019\n                }\n            ], \n            \"sum\": {\n                \"bits_per_second\": 0, \n                \"bytes\": 0, \n                \"end\": 21.001016, \n                \"omitted\": false, \n                \"retransmits\": 2, \n                \"seconds\": 0.9999970197677612, \n                \"sender\": true, \n                \"start\": 20.001019\n            }\n        }, \n        {\n            \"streams\": [\n                {\n                    \"bits_per_second\": 0, \n                    \"bytes\": 0, \n                    \"end\": 22.001017, \n                    \"omitted\": false, \n                    \"pmtu\": 1500, \n                    \"retransmits\": 2, \n                    \"rtt\": 33933, \n                    \"rttvar\": 19548, \n                    \"seconds\": 1.0000009536743164, \n                    \"sender\": true, \n                    \"snd_cwnd\": 1448, \n                    \"snd_wnd\": -1, \n                    \"socket\": 5, \n                    \"start\": 21.001016\n                }\n            ], \n            \"sum\": {\n                \"bits_per_second\": 0, \n                \"bytes\": 0, \n                \"end\": 22.001017, \n                \"omitted\": false, \n                \"retransmits\": 2, \n                \"seconds\": 1.0000009536743164, \n                \"sender\": true, \n                \"start\": 21.001016\n            }\n        }, \n        {\n            \"streams\": [\n                {\n                    \"bits_per_second\": 0, \n                    \"bytes\": 0, \n                    \"end\": 23.001016, \n                    \"omitted\": false, \n                    \"pmtu\": 1500, \n                    \"retransmits\": 5, \n                    \"rtt\": 144672, \n                    \"rttvar\": 233005, \n                    \"seconds\": 0.9999989867210388, \n                    \"sender\": true, \n                    \"snd_cwnd\": 2896, \n                    \"snd_wnd\": -1, \n                    \"socket\": 5, \n                    \"start\": 22.001017\n                }\n            ], \n            \"sum\": {\n                \"bits_per_second\": 0, \n                \"bytes\": 0, \n                \"end\": 23.001016, \n                \"omitted\": false, \n                \"retransmits\": 5, \n                \"seconds\": 0.9999989867210388, \n                \"sender\": true, \n                \"start\": 22.001017\n            }\n        }, \n        {\n            \"streams\": [\n                {\n                    \"bits_per_second\": 0, \n                    \"bytes\": 0, \n                    \"end\": 24.001032, \n                    \"omitted\": false, \n                    \"pmtu\": 1500, \n                    \"retransmits\": 0, \n                    \"rtt\": 144672, \n                    \"rttvar\": 233005, \n                    \"seconds\": 1.0000159740448, \n                    \"sender\": true, \n                    \"snd_cwnd\": 2896, \n                    \"snd_wnd\": -1, \n                    \"socket\": 5, \n                    \"start\": 23.001016\n                }\n            ], \n            \"sum\": {\n                \"bits_per_second\": 0, \n                \"bytes\": 0, \n                \"end\": 24.001032, \n                \"omitted\": false, \n                \"retransmits\": 0, \n                \"seconds\": 1.0000159740448, \n                \"sender\": true, \n                \"start\": 23.001016\n            }\n        }, \n        {\n            \"streams\": [\n                {\n                    \"bits_per_second\": 0, \n                    \"bytes\": 0, \n                    \"end\": 25.001017, \n                    \"omitted\": false, \n                    \"pmtu\": 1500, \n                    \"retransmits\": 5, \n                    \"rtt\": 152101, \n                    \"rttvar\": 135354, \n                    \"seconds\": 0.9999849796295166, \n                    \"sender\": true, \n                    \"snd_cwnd\": 2896, \n                    \"snd_wnd\": -1, \n                    \"socket\": 5, \n                    \"start\": 24.001032\n                }\n            ], \n            \"sum\": {\n                \"bits_per_second\": 0, \n                \"bytes\": 0, \n                \"end\": 25.001017, \n                \"omitted\": false, \n                \"retransmits\": 5, \n                \"seconds\": 0.9999849796295166, \n                \"sender\": true, \n                \"start\": 24.001032\n            }\n        }, \n        {\n            \"streams\": [\n                {\n                    \"bits_per_second\": 0, \n                    \"bytes\": 0, \n                    \"end\": 26.001033, \n                    \"omitted\": false, \n                    \"pmtu\": 1500, \n                    \"retransmits\": 3, \n                    \"rtt\": 125827, \n                    \"rttvar\": 121677, \n                    \"seconds\": 1.0000159740448, \n                    \"sender\": true, \n                    \"snd_cwnd\": 4344, \n                    \"snd_wnd\": -1, \n                    \"socket\": 5, \n                    \"start\": 25.001017\n                }\n            ], \n            \"sum\": {\n                \"bits_per_second\": 0, \n                \"bytes\": 0, \n                \"end\": 26.001033, \n                \"omitted\": false, \n                \"retransmits\": 3, \n                \"seconds\": 1.0000159740448, \n                \"sender\": true, \n                \"start\": 25.001017\n            }\n        }, \n        {\n            \"streams\": [\n                {\n                    \"bits_per_second\": 0, \n                    \"bytes\": 0, \n                    \"end\": 27.001017, \n                    \"omitted\": false, \n                    \"pmtu\": 1500, \n                    \"retransmits\": 13, \n                    \"rtt\": 226380, \n                    \"rttvar\": 334814, \n                    \"seconds\": 0.9999840259552002, \n                    \"sender\": true, \n                    \"snd_cwnd\": 7240, \n                    \"snd_wnd\": -1, \n                    \"socket\": 5, \n                    \"start\": 26.001033\n                }\n            ], \n            \"sum\": {\n                \"bits_per_second\": 0, \n                \"bytes\": 0, \n                \"end\": 27.001017, \n                \"omitted\": false, \n                \"retransmits\": 13, \n                \"seconds\": 0.9999840259552002, \n                \"sender\": true, \n                \"start\": 26.001033\n            }\n        }, \n        {\n            \"streams\": [\n                {\n                    \"bits_per_second\": 0, \n                    \"bytes\": 0, \n                    \"end\": 28.001017, \n                    \"omitted\": false, \n                    \"pmtu\": 1500, \n                    \"retransmits\": 0, \n                    \"rtt\": 226380, \n                    \"rttvar\": 334814, \n                    \"seconds\": 1, \n                    \"sender\": true, \n                    \"snd_cwnd\": 7240, \n                    \"snd_wnd\": -1, \n                    \"socket\": 5, \n                    \"start\": 27.001017\n                }\n            ], \n            \"sum\": {\n                \"bits_per_second\": 0, \n                \"bytes\": 0, \n                \"end\": 28.001017, \n                \"omitted\": false, \n                \"retransmits\": 0, \n                \"seconds\": 1, \n                \"sender\": true, \n                \"start\": 27.001017\n            }\n        }, \n        {\n            \"streams\": [\n                {\n                    \"bits_per_second\": 0, \n                    \"bytes\": 0, \n                    \"end\": 29.001018, \n                    \"omitted\": false, \n                    \"pmtu\": 1500, \n                    \"retransmits\": 0, \n                    \"rtt\": 226380, \n                    \"rttvar\": 334814, \n                    \"seconds\": 1.0000009536743164, \n                    \"sender\": true, \n                    \"snd_cwnd\": 7240, \n                    \"snd_wnd\": -1, \n                    \"socket\": 5, \n                    \"start\": 28.001017\n                }\n            ], \n            \"sum\": {\n                \"bits_per_second\": 0, \n                \"bytes\": 0, \n                \"end\": 29.001018, \n                \"omitted\": false, \n                \"retransmits\": 0, \n                \"seconds\": 1.0000009536743164, \n                \"sender\": true, \n                \"start\": 28.001017\n            }\n        }, \n        {\n            \"streams\": [\n                {\n                    \"bits_per_second\": 0, \n                    \"bytes\": 0, \n                    \"end\": 30.001017, \n                    \"omitted\": false, \n                    \"pmtu\": 1500, \n                    \"retransmits\": 3, \n                    \"rtt\": 206582, \n                    \"rttvar\": 290706, \n                    \"seconds\": 0.9999989867210388, \n                    \"sender\": true, \n                    \"snd_cwnd\": 2896, \n                    \"snd_wnd\": -1, \n                    \"socket\": 5, \n                    \"start\": 29.001018\n                }\n            ], \n            \"sum\": {\n                \"bits_per_second\": 0, \n                \"bytes\": 0, \n                \"end\": 30.001017, \n                \"omitted\": false, \n                \"retransmits\": 3, \n                \"seconds\": 0.9999989867210388, \n                \"sender\": true, \n                \"start\": 29.001018\n            }\n        }, \n        {\n            \"streams\": [\n                {\n                    \"bits_per_second\": 0, \n                    \"bytes\": 0, \n                    \"end\": 31.001022, \n                    \"omitted\": false, \n                    \"pmtu\": 1500, \n                    \"retransmits\": 0, \n                    \"rtt\": 206582, \n                    \"rttvar\": 290706, \n                    \"seconds\": 1.0000050067901611, \n                    \"sender\": true, \n                    \"snd_cwnd\": 2896, \n                    \"snd_wnd\": -1, \n                    \"socket\": 5, \n                    \"start\": 30.001017\n                }\n            ], \n            \"sum\": {\n                \"bits_per_second\": 0, \n                \"bytes\": 0, \n                \"end\": 31.001022, \n                \"omitted\": false, \n                \"retransmits\": 0, \n                \"seconds\": 1.0000050067901611, \n                \"sender\": true, \n                \"start\": 30.001017\n            }\n        }, \n        {\n            \"streams\": [\n                {\n                    \"bits_per_second\": 0, \n                    \"bytes\": 0, \n                    \"end\": 32.001015, \n                    \"omitted\": false, \n                    \"pmtu\": 1500, \n                    \"retransmits\": 0, \n                    \"rtt\": 206582, \n                    \"rttvar\": 290706, \n                    \"seconds\": 0.9999930262565613, \n                    \"sender\": true, \n                    \"snd_cwnd\": 2896, \n                    \"snd_wnd\": -1, \n                    \"socket\": 5, \n                    \"start\": 31.001022\n                }\n            ], \n            \"sum\": {\n                \"bits_per_second\": 0, \n                \"bytes\": 0, \n                \"end\": 32.001015, \n                \"omitted\": false, \n                \"retransmits\": 0, \n                \"seconds\": 0.9999930262565613, \n                \"sender\": true, \n                \"start\": 31.001022\n            }\n        }, \n        {\n            \"streams\": [\n                {\n                    \"bits_per_second\": 0, \n                    \"bytes\": 0, \n                    \"end\": 33.001018, \n                    \"omitted\": false, \n                    \"pmtu\": 1500, \n                    \"retransmits\": 0, \n                    \"rtt\": 206582, \n                    \"rttvar\": 290706, \n                    \"seconds\": 1.0000029802322388, \n                    \"sender\": true, \n                    \"snd_cwnd\": 2896, \n                    \"snd_wnd\": -1, \n                    \"socket\": 5, \n                    \"start\": 32.001015\n                }\n            ], \n            \"sum\": {\n                \"bits_per_second\": 0, \n                \"bytes\": 0, \n                \"end\": 33.001018, \n                \"omitted\": false, \n                \"retransmits\": 0, \n                \"seconds\": 1.0000029802322388, \n                \"sender\": true, \n                \"start\": 32.001015\n            }\n        }, \n        {\n            \"streams\": [\n                {\n                    \"bits_per_second\": 0, \n                    \"bytes\": 0, \n                    \"end\": 34.001023, \n                    \"omitted\": false, \n                    \"pmtu\": 1500, \n                    \"retransmits\": 1, \n                    \"rtt\": 206582, \n                    \"rttvar\": 290706, \n                    \"seconds\": 1.0000050067901611, \n                    \"sender\": true, \n                    \"snd_cwnd\": 1448, \n                    \"snd_wnd\": -1, \n                    \"socket\": 5, \n                    \"start\": 33.001018\n                }\n            ], \n            \"sum\": {\n                \"bits_per_second\": 0, \n                \"bytes\": 0, \n                \"end\": 34.001023, \n                \"omitted\": false, \n                \"retransmits\": 1, \n                \"seconds\": 1.0000050067901611, \n                \"sender\": true, \n                \"start\": 33.001018\n            }\n        }, \n        {\n            \"streams\": [\n                {\n                    \"bits_per_second\": 0, \n                    \"bytes\": 0, \n                    \"end\": 35.001031, \n                    \"omitted\": false, \n                    \"pmtu\": 1500, \n                    \"retransmits\": 0, \n                    \"rtt\": 206582, \n                    \"rttvar\": 290706, \n                    \"seconds\": 1.0000079870224, \n                    \"sender\": true, \n                    \"snd_cwnd\": 1448, \n                    \"snd_wnd\": -1, \n                    \"socket\": 5, \n                    \"start\": 34.001023\n                }\n            ], \n            \"sum\": {\n                \"bits_per_second\": 0, \n                \"bytes\": 0, \n                \"end\": 35.001031, \n                \"omitted\": false, \n                \"retransmits\": 0, \n                \"seconds\": 1.0000079870224, \n                \"sender\": true, \n                \"start\": 34.001023\n            }\n        }, \n        {\n            \"streams\": [\n                {\n                    \"bits_per_second\": 0, \n                    \"bytes\": 0, \n                    \"end\": 36.001015, \n                    \"omitted\": false, \n                    \"pmtu\": 1500, \n                    \"retransmits\": 0, \n                    \"rtt\": 206582, \n                    \"rttvar\": 290706, \n                    \"seconds\": 0.9999840259552002, \n                    \"sender\": true, \n                    \"snd_cwnd\": 1448, \n                    \"snd_wnd\": -1, \n                    \"socket\": 5, \n                    \"start\": 35.001031\n                }\n            ], \n            \"sum\": {\n                \"bits_per_second\": 0, \n                \"bytes\": 0, \n                \"end\": 36.001015, \n                \"omitted\": false, \n                \"retransmits\": 0, \n                \"seconds\": 0.9999840259552002, \n                \"sender\": true, \n                \"start\": 35.001031\n            }\n        }, \n        {\n            \"streams\": [\n                {\n                    \"bits_per_second\": 0, \n                    \"bytes\": 0, \n                    \"end\": 37.001027, \n                    \"omitted\": false, \n                    \"pmtu\": 1500, \n                    \"retransmits\": 0, \n                    \"rtt\": 206582, \n                    \"rttvar\": 290706, \n                    \"seconds\": 1.0000120401382446, \n                    \"sender\": true, \n                    \"snd_cwnd\": 1448, \n                    \"snd_wnd\": -1, \n                    \"socket\": 5, \n                    \"start\": 36.001015\n                }\n            ], \n            \"sum\": {\n                \"bits_per_second\": 0, \n                \"bytes\": 0, \n                \"end\": 37.001027, \n                \"omitted\": false, \n                \"retransmits\": 0, \n                \"seconds\": 1.0000120401382446, \n                \"sender\": true, \n                \"start\": 36.001015\n            }\n        }, \n        {\n            \"streams\": [\n                {\n                    \"bits_per_second\": 0, \n                    \"bytes\": 0, \n                    \"end\": 38.001022, \n                    \"omitted\": false, \n                    \"pmtu\": 1500, \n                    \"retransmits\": 0, \n                    \"rtt\": 206582, \n                    \"rttvar\": 290706, \n                    \"seconds\": 0.999994993209839, \n                    \"sender\": true, \n                    \"snd_cwnd\": 1448, \n                    \"snd_wnd\": -1, \n                    \"socket\": 5, \n                    \"start\": 37.001027\n                }\n            ], \n            \"sum\": {\n                \"bits_per_second\": 0, \n                \"bytes\": 0, \n                \"end\": 38.001022, \n                \"omitted\": false, \n                \"retransmits\": 0, \n                \"seconds\": 0.999994993209839, \n                \"sender\": true, \n                \"start\": 37.001027\n            }\n        }, \n        {\n            \"streams\": [\n                {\n                    \"bits_per_second\": 0, \n                    \"bytes\": 0, \n                    \"end\": 39.001027, \n                    \"omitted\": false, \n                    \"pmtu\": 1500, \n                    \"retransmits\": 0, \n                    \"rtt\": 206582, \n                    \"rttvar\": 290706, \n                    \"seconds\": 1.0000050067901611, \n                    \"sender\": true, \n                    \"snd_cwnd\": 1448, \n                    \"snd_wnd\": -1, \n                    \"socket\": 5, \n                    \"start\": 38.001022\n                }\n            ], \n            \"sum\": {\n                \"bits_per_second\": 0, \n                \"bytes\": 0, \n                \"end\": 39.001027, \n                \"omitted\": false, \n                \"retransmits\": 0, \n                \"seconds\": 1.0000050067901611, \n                \"sender\": true, \n                \"start\": 38.001022\n            }\n        }, \n        {\n            \"streams\": [\n                {\n                    \"bits_per_second\": 0, \n                    \"bytes\": 0, \n                    \"end\": 40.001363, \n                    \"omitted\": false, \n                    \"pmtu\": 1500, \n                    \"retransmits\": 9, \n                    \"rtt\": 117692, \n                    \"rttvar\": 117626, \n                    \"seconds\": 1.0003360509872437, \n                    \"sender\": true, \n                    \"snd_cwnd\": 4344, \n                    \"snd_wnd\": -1, \n                    \"socket\": 5, \n                    \"start\": 39.001027\n                }\n            ], \n            \"sum\": {\n                \"bits_per_second\": 0, \n                \"bytes\": 0, \n                \"end\": 40.001363, \n                \"omitted\": false, \n                \"retransmits\": 9, \n                \"seconds\": 1.0003360509872437, \n                \"sender\": true, \n                \"start\": 39.001027\n            }\n        }, \n        {\n            \"streams\": [\n                {\n                    \"bits_per_second\": 0, \n                    \"bytes\": 0, \n                    \"end\": 41.001018, \n                    \"omitted\": false, \n                    \"pmtu\": 1500, \n                    \"retransmits\": 3, \n                    \"rtt\": 99717, \n                    \"rttvar\": 97321, \n                    \"seconds\": 0.99965500831604, \n                    \"sender\": true, \n                    \"snd_cwnd\": 5792, \n                    \"snd_wnd\": -1, \n                    \"socket\": 5, \n                    \"start\": 40.001363\n                }\n            ], \n            \"sum\": {\n                \"bits_per_second\": 0, \n                \"bytes\": 0, \n                \"end\": 41.001018, \n                \"omitted\": false, \n                \"retransmits\": 3, \n                \"seconds\": 0.99965500831604, \n                \"sender\": true, \n                \"start\": 40.001363\n            }\n        }, \n        {\n            \"streams\": [\n                {\n                    \"bits_per_second\": 0, \n                    \"bytes\": 0, \n                    \"end\": 42.001017, \n                    \"omitted\": false, \n                    \"pmtu\": 1500, \n                    \"retransmits\": 0, \n                    \"rtt\": 99717, \n                    \"rttvar\": 97321, \n                    \"seconds\": 0.9999989867210388, \n                    \"sender\": true, \n                    \"snd_cwnd\": 5792, \n                    \"snd_wnd\": -1, \n                    \"socket\": 5, \n                    \"start\": 41.001018\n                }\n            ], \n            \"sum\": {\n                \"bits_per_second\": 0, \n                \"bytes\": 0, \n                \"end\": 42.001017, \n                \"omitted\": false, \n                \"retransmits\": 0, \n                \"seconds\": 0.9999989867210388, \n                \"sender\": true, \n                \"start\": 41.001018\n            }\n        }, \n        {\n            \"streams\": [\n                {\n                    \"bits_per_second\": 0, \n                    \"bytes\": 0, \n                    \"end\": 43.001017, \n                    \"omitted\": false, \n                    \"pmtu\": 1500, \n                    \"retransmits\": 0, \n                    \"rtt\": 99717, \n                    \"rttvar\": 97321, \n                    \"seconds\": 1, \n                    \"sender\": true, \n                    \"snd_cwnd\": 5792, \n                    \"snd_wnd\": -1, \n                    \"socket\": 5, \n                    \"start\": 42.001017\n                }\n            ], \n            \"sum\": {\n                \"bits_per_second\": 0, \n                \"bytes\": 0, \n                \"end\": 43.001017, \n                \"omitted\": false, \n                \"retransmits\": 0, \n                \"seconds\": 1, \n                \"sender\": true, \n                \"start\": 42.001017\n            }\n        }, \n        {\n            \"streams\": [\n                {\n                    \"bits_per_second\": 0, \n                    \"bytes\": 0, \n                    \"end\": 44.001015, \n                    \"omitted\": false, \n                    \"pmtu\": 1500, \n                    \"retransmits\": 1, \n                    \"rtt\": 99717, \n                    \"rttvar\": 97321, \n                    \"seconds\": 0.9999979734420776, \n                    \"sender\": true, \n                    \"snd_cwnd\": 1448, \n                    \"snd_wnd\": -1, \n                    \"socket\": 5, \n                    \"start\": 43.001017\n                }\n            ], \n            \"sum\": {\n                \"bits_per_second\": 0, \n                \"bytes\": 0, \n                \"end\": 44.001015, \n                \"omitted\": false, \n                \"retransmits\": 1, \n                \"seconds\": 0.9999979734420776, \n                \"sender\": true, \n                \"start\": 43.001017\n            }\n        }, \n        {\n            \"streams\": [\n                {\n                    \"bits_per_second\": 0, \n                    \"bytes\": 0, \n                    \"end\": 45.001022, \n                    \"omitted\": false, \n                    \"pmtu\": 1500, \n                    \"retransmits\": 0, \n                    \"rtt\": 99717, \n                    \"rttvar\": 97321, \n                    \"seconds\": 1.0000070333480835, \n                    \"sender\": true, \n                    \"snd_cwnd\": 1448, \n                    \"snd_wnd\": -1, \n                    \"socket\": 5, \n                    \"start\": 44.001015\n                }\n            ], \n            \"sum\": {\n                \"bits_per_second\": 0, \n                \"bytes\": 0, \n                \"end\": 45.001022, \n                \"omitted\": false, \n                \"retransmits\": 0, \n                \"seconds\": 1.0000070333480835, \n                \"sender\": true, \n                \"start\": 44.001015\n            }\n        }, \n        {\n            \"streams\": [\n                {\n                    \"bits_per_second\": 0, \n                    \"bytes\": 0, \n                    \"end\": 46.00104, \n                    \"omitted\": false, \n                    \"pmtu\": 1500, \n                    \"retransmits\": 0, \n                    \"rtt\": 99717, \n                    \"rttvar\": 97321, \n                    \"seconds\": 1.0000180006027222, \n                    \"sender\": true, \n                    \"snd_cwnd\": 1448, \n                    \"snd_wnd\": -1, \n                    \"socket\": 5, \n                    \"start\": 45.001022\n                }\n            ], \n            \"sum\": {\n                \"bits_per_second\": 0, \n                \"bytes\": 0, \n                \"end\": 46.00104, \n                \"omitted\": false, \n                \"retransmits\": 0, \n                \"seconds\": 1.0000180006027222, \n                \"sender\": true, \n                \"start\": 45.001022\n            }\n        }, \n        {\n            \"streams\": [\n                {\n                    \"bits_per_second\": 0, \n                    \"bytes\": 0, \n                    \"end\": 47.001014, \n                    \"omitted\": false, \n                    \"pmtu\": 1500, \n                    \"retransmits\": 0, \n                    \"rtt\": 99717, \n                    \"rttvar\": 97321, \n                    \"seconds\": 0.999974012374878, \n                    \"sender\": true, \n                    \"snd_cwnd\": 1448, \n                    \"snd_wnd\": -1, \n                    \"socket\": 5, \n                    \"start\": 46.00104\n                }\n            ], \n            \"sum\": {\n                \"bits_per_second\": 0, \n                \"bytes\": 0, \n                \"end\": 47.001014, \n                \"omitted\": false, \n                \"retransmits\": 0, \n                \"seconds\": 0.999974012374878, \n                \"sender\": true, \n                \"start\": 46.00104\n            }\n        }, \n        {\n            \"streams\": [\n                {\n                    \"bits_per_second\": 0, \n                    \"bytes\": 0, \n                    \"end\": 48.001021, \n                    \"omitted\": false, \n                    \"pmtu\": 1500, \n                    \"retransmits\": 0, \n                    \"rtt\": 99717, \n                    \"rttvar\": 97321, \n                    \"seconds\": 1.0000070333480835, \n                    \"sender\": true, \n                    \"snd_cwnd\": 1448, \n                    \"snd_wnd\": -1, \n                    \"socket\": 5, \n                    \"start\": 47.001014\n                }\n            ], \n            \"sum\": {\n                \"bits_per_second\": 0, \n                \"bytes\": 0, \n                \"end\": 48.001021, \n                \"omitted\": false, \n                \"retransmits\": 0, \n                \"seconds\": 1.0000070333480835, \n                \"sender\": true, \n                \"start\": 47.001014\n            }\n        }, \n        {\n            \"streams\": [\n                {\n                    \"bits_per_second\": 0, \n                    \"bytes\": 0, \n                    \"end\": 49.001016, \n                    \"omitted\": false, \n                    \"pmtu\": 1500, \n                    \"retransmits\": 0, \n                    \"rtt\": 99717, \n                    \"rttvar\": 97321, \n                    \"seconds\": 0.999994993209839, \n                    \"sender\": true, \n                    \"snd_cwnd\": 1448, \n                    \"snd_wnd\": -1, \n                    \"socket\": 5, \n                    \"start\": 48.001021\n                }\n            ], \n            \"sum\": {\n                \"bits_per_second\": 0, \n                \"bytes\": 0, \n                \"end\": 49.001016, \n                \"omitted\": false, \n                \"retransmits\": 0, \n                \"seconds\": 0.999994993209839, \n                \"sender\": true, \n                \"start\": 48.001021\n            }\n        }, \n        {\n            \"streams\": [\n                {\n                    \"bits_per_second\": 10494291.936527146, \n                    \"bytes\": 1310720, \n                    \"end\": 50.000203, \n                    \"omitted\": false, \n                    \"pmtu\": 1500, \n                    \"retransmits\": 14, \n                    \"rtt\": 20929, \n                    \"rttvar\": 6051, \n                    \"seconds\": 0.9991869926452637, \n                    \"sender\": true, \n                    \"snd_cwnd\": 27512, \n                    \"snd_wnd\": -1, \n                    \"socket\": 5, \n                    \"start\": 49.001016\n                }\n            ], \n            \"sum\": {\n                \"bits_per_second\": 10494291.936527146, \n                \"bytes\": 1310720, \n                \"end\": 50.000203, \n                \"omitted\": false, \n                \"retransmits\": 14, \n                \"seconds\": 0.9991869926452637, \n                \"sender\": true, \n                \"start\": 49.001016\n            }\n        }, \n        {\n            \"streams\": [\n                {\n                    \"bits_per_second\": 0, \n                    \"bytes\": 0, \n                    \"end\": 51.001016, \n                    \"omitted\": false, \n                    \"pmtu\": 1500, \n                    \"retransmits\": 2, \n                    \"rtt\": 21070, \n                    \"rttvar\": 6599, \n                    \"seconds\": 1.0008130073547363, \n                    \"sender\": true, \n                    \"snd_cwnd\": 1448, \n                    \"snd_wnd\": -1, \n                    \"socket\": 5, \n                    \"start\": 50.000203\n                }\n            ], \n            \"sum\": {\n                \"bits_per_second\": 0, \n                \"bytes\": 0, \n                \"end\": 51.001016, \n                \"omitted\": false, \n                \"retransmits\": 2, \n                \"seconds\": 1.0008130073547363, \n                \"sender\": true, \n                \"start\": 50.000203\n            }\n        }, \n        {\n            \"streams\": [\n                {\n                    \"bits_per_second\": 0, \n                    \"bytes\": 0, \n                    \"end\": 52.00102, \n                    \"omitted\": false, \n                    \"pmtu\": 1500, \n                    \"retransmits\": 1, \n                    \"rtt\": 21070, \n                    \"rttvar\": 6599, \n                    \"seconds\": 1.0000040531158447, \n                    \"sender\": true, \n                    \"snd_cwnd\": 1448, \n                    \"snd_wnd\": -1, \n                    \"socket\": 5, \n                    \"start\": 51.001016\n                }\n            ], \n            \"sum\": {\n                \"bits_per_second\": 0, \n                \"bytes\": 0, \n                \"end\": 52.00102, \n                \"omitted\": false, \n                \"retransmits\": 1, \n                \"seconds\": 1.0000040531158447, \n                \"sender\": true, \n                \"start\": 51.001016\n            }\n        }, \n        {\n            \"streams\": [\n                {\n                    \"bits_per_second\": 0, \n                    \"bytes\": 0, \n                    \"end\": 53.001017, \n                    \"omitted\": false, \n                    \"pmtu\": 1500, \n                    \"retransmits\": 0, \n                    \"rtt\": 21070, \n                    \"rttvar\": 6599, \n                    \"seconds\": 0.9999970197677612, \n                    \"sender\": true, \n                    \"snd_cwnd\": 1448, \n                    \"snd_wnd\": -1, \n                    \"socket\": 5, \n                    \"start\": 52.00102\n                }\n            ], \n            \"sum\": {\n                \"bits_per_second\": 0, \n                \"bytes\": 0, \n                \"end\": 53.001017, \n                \"omitted\": false, \n                \"retransmits\": 0, \n                \"seconds\": 0.9999970197677612, \n                \"sender\": true, \n                \"start\": 52.00102\n            }\n        }, \n        {\n            \"streams\": [\n                {\n                    \"bits_per_second\": 0, \n                    \"bytes\": 0, \n                    \"end\": 54.001018, \n                    \"omitted\": false, \n                    \"pmtu\": 1500, \n                    \"retransmits\": 22, \n                    \"rtt\": 29594, \n                    \"rttvar\": 15236, \n                    \"seconds\": 1.0000009536743164, \n                    \"sender\": true, \n                    \"snd_cwnd\": 26064, \n                    \"snd_wnd\": -1, \n                    \"socket\": 5, \n                    \"start\": 53.001017\n                }\n            ], \n            \"sum\": {\n                \"bits_per_second\": 0, \n                \"bytes\": 0, \n                \"end\": 54.001018, \n                \"omitted\": false, \n                \"retransmits\": 22, \n                \"seconds\": 1.0000009536743164, \n                \"sender\": true, \n                \"start\": 53.001017\n            }\n        }, \n        {\n            \"streams\": [\n                {\n                    \"bits_per_second\": 10491194.690299833, \n                    \"bytes\": 1310720, \n                    \"end\": 55.0005, \n                    \"omitted\": false, \n                    \"pmtu\": 1500, \n                    \"retransmits\": 0, \n                    \"rtt\": 29348, \n                    \"rttvar\": 857, \n                    \"seconds\": 0.999481976032257, \n                    \"sender\": true, \n                    \"snd_cwnd\": 81088, \n                    \"snd_wnd\": -1, \n                    \"socket\": 5, \n                    \"start\": 54.001018\n                }\n            ], \n            \"sum\": {\n                \"bits_per_second\": 10491194.690299833, \n                \"bytes\": 1310720, \n                \"end\": 55.0005, \n                \"omitted\": false, \n                \"retransmits\": 0, \n                \"seconds\": 0.999481976032257, \n                \"sender\": true, \n                \"start\": 54.001018\n            }\n        }, \n        {\n            \"streams\": [\n                {\n                    \"bits_per_second\": 20978107.068321463, \n                    \"bytes\": 2621440, \n                    \"end\": 56.000186, \n                    \"omitted\": false, \n                    \"pmtu\": 1500, \n                    \"retransmits\": 61, \n                    \"rtt\": 22729, \n                    \"rttvar\": 992, \n                    \"seconds\": 0.9996860027313232, \n                    \"sender\": true, \n                    \"snd_cwnd\": 63712, \n                    \"snd_wnd\": -1, \n                    \"socket\": 5, \n                    \"start\": 55.0005\n                }\n            ], \n            \"sum\": {\n                \"bits_per_second\": 20978107.068321463, \n                \"bytes\": 2621440, \n                \"end\": 56.000186, \n                \"omitted\": false, \n                \"retransmits\": 61, \n                \"seconds\": 0.9996860027313232, \n                \"sender\": true, \n                \"start\": 55.0005\n            }\n        }, \n        {\n            \"streams\": [\n                {\n                    \"bits_per_second\": 20970975.014162887, \n                    \"bytes\": 2621440, \n                    \"end\": 57.000212, \n                    \"omitted\": false, \n                    \"pmtu\": 1500, \n                    \"retransmits\": 0, \n                    \"rtt\": 38803, \n                    \"rttvar\": 999, \n                    \"seconds\": 1.000025987625122, \n                    \"sender\": true, \n                    \"snd_cwnd\": 107152, \n                    \"snd_wnd\": -1, \n                    \"socket\": 5, \n                    \"start\": 56.000186\n                }\n            ], \n            \"sum\": {\n                \"bits_per_second\": 20970975.014162887, \n                \"bytes\": 2621440, \n                \"end\": 57.000212, \n                \"omitted\": false, \n                \"retransmits\": 0, \n                \"seconds\": 1.000025987625122, \n                \"sender\": true, \n                \"start\": 56.000186\n            }\n        }, \n        {\n            \"streams\": [\n                {\n                    \"bits_per_second\": 20970660.03526543, \n                    \"bytes\": 2621440, \n                    \"end\": 58.000253, \n                    \"omitted\": false, \n                    \"pmtu\": 1500, \n                    \"retransmits\": 0, \n                    \"rtt\": 50156, \n                    \"rttvar\": 890, \n                    \"seconds\": 1.0000410079956055, \n                    \"sender\": true, \n                    \"snd_cwnd\": 139008, \n                    \"snd_wnd\": -1, \n                    \"socket\": 5, \n                    \"start\": 57.000212\n                }\n            ], \n            \"sum\": {\n                \"bits_per_second\": 20970660.03526543, \n                \"bytes\": 2621440, \n                \"end\": 58.000253, \n                \"omitted\": false, \n                \"retransmits\": 0, \n                \"seconds\": 1.0000410079956055, \n                \"sender\": true, \n                \"start\": 57.000212\n            }\n        }, \n        {\n            \"streams\": [\n                {\n                    \"bits_per_second\": 10482991.980891505, \n                    \"bytes\": 1310720, \n                    \"end\": 59.000517, \n                    \"omitted\": false, \n                    \"pmtu\": 1500, \n                    \"retransmits\": 28, \n                    \"rtt\": 36561, \n                    \"rttvar\": 10804, \n                    \"seconds\": 1.000264048576355, \n                    \"sender\": true, \n                    \"snd_cwnd\": 78192, \n                    \"snd_wnd\": -1, \n                    \"socket\": 5, \n                    \"start\": 58.000253\n                }\n            ], \n            \"sum\": {\n                \"bits_per_second\": 10482991.980891505, \n                \"bytes\": 1310720, \n                \"end\": 59.000517, \n                \"omitted\": false, \n                \"retransmits\": 28, \n                \"seconds\": 1.000264048576355, \n                \"sender\": true, \n                \"start\": 58.000253\n            }\n        }, \n        {\n            \"streams\": [\n                {\n                    \"bits_per_second\": 0, \n                    \"bytes\": 0, \n                    \"end\": 60.001027, \n                    \"omitted\": false, \n                    \"pmtu\": 1500, \n                    \"retransmits\": 2, \n                    \"rtt\": 36561, \n                    \"rttvar\": 10804, \n                    \"seconds\": 1.0005099773406982, \n                    \"sender\": true, \n                    \"snd_cwnd\": 1448, \n                    \"snd_wnd\": -1, \n                    \"socket\": 5, \n                    \"start\": 59.000517\n                }\n            ], \n            \"sum\": {\n                \"bits_per_second\": 0, \n                \"bytes\": 0, \n                \"end\": 60.001027, \n                \"omitted\": false, \n                \"retransmits\": 2, \n                \"seconds\": 1.0005099773406982, \n                \"sender\": true, \n                \"start\": 59.000517\n            }\n        }\n    ], \n    \"start\": {\n        \"connected\": [\n            {\n                \"local_host\": \"172.16.0.2\", \n                \"local_port\": 48627, \n                \"remote_host\": \"172.16.0.1\", \n                \"remote_port\": 5201, \n                \"socket\": 5\n            }\n        ], \n        \"connecting_to\": {\n            \"host\": \"172.16.0.1\", \n            \"port\": 5201\n        }, \n        \"cookie\": \"bjbim23kxzpjfkse5vg2iszpvmergwp3t4oc\", \n        \"fq_rate\": 0, \n        \"rcvbuf_actual\": 87380, \n        \"sndbuf_actual\": 65536, \n        \"sock_bufsize\": 0, \n        \"system_info\": \"REDACTED\", \n        \"target_bitrate\": 0, \n        \"tcp_mss_default\": 1448, \n        \"test_start\": {\n            \"bidir\": 0, \n            \"blksize\": 131072, \n            \"blocks\": 0, \n            \"bytes\": 0, \n            \"duration\": 60, \n            \"fqrate\": 0, \n            \"num_streams\": 1, \n            \"omit\": 0, \n            \"protocol\": \"TCP\", \n            \"reverse\": 0, \n            \"target_bitrate\": 0, \n            \"tos\": 0\n        }, \n        \"timestamp\": {\n            \"time\": \"Wed, 16 Oct 2024 02:47:09 GMT\", \n            \"timesecs\": 1729046829\n        }, \n        \"version\": \"iperf 3.14\"\n    }\n}\nParticipant 1:\n/usr/bin/iperf3 --use-pkcs1-padding -s -1 --idle-timeout 60 --json -p 5201 -B 172.16.0.1 --authorized-users-path /var/pscheduler-server/runner/tmp/tmp272mioce/tmpy26uwtzu/credentials --rsa-private-key-path /var/pscheduler-server/runner/tmp/tmp272mioce/tmpy26uwtzu/private-key\n\n{\n    \"end\": {\n        \"cpu_utilization_percent\": {\n            \"host_system\": 0.855582203928019, \n            \"host_total\": 0.9919912633447325, \n            \"host_user\": 0.1364090594167137, \n            \"remote_system\": 0, \n            \"remote_total\": 0, \n            \"remote_user\": 0\n        }, \n        \"receiver_tcp_congestion\": \"htcp\", \n        \"streams\": [\n            {\n                \"receiver\": {\n                    \"bits_per_second\": 4013481.258756496, \n                    \"bytes\": 30741944, \n                    \"end\": 61.277364, \n                    \"seconds\": 61.277364, \n                    \"sender\": false, \n                    \"socket\": 5, \n                    \"start\": 0\n                }, \n                \"sender\": {\n                    \"bits_per_second\": 0, \n                    \"bytes\": 0, \n                    \"end\": 61.277364, \n                    \"seconds\": 61.277364, \n                    \"sender\": false, \n                    \"socket\": 5, \n                    \"start\": 0\n                }\n            }\n        ], \n        \"sum_received\": {\n            \"bits_per_second\": 4013481.258756496, \n            \"bytes\": 30741944, \n            \"end\": 61.277364, \n            \"seconds\": 61.277364, \n            \"sender\": false, \n            \"start\": 0\n        }, \n        \"sum_sent\": {\n            \"bits_per_second\": 0, \n            \"bytes\": 0, \n            \"end\": 61.277364, \n            \"seconds\": 61.277364, \n            \"sender\": false, \n            \"start\": 0\n        }\n    }, \n    \"intervals\": [\n        {\n            \"streams\": [\n                {\n                    \"bits_per_second\": 5236810.783934425, \n                    \"bytes\": 655360, \n                    \"end\": 1.001159, \n                    \"omitted\": false, \n                    \"seconds\": 1.0011589527130127, \n                    \"sender\": false, \n                    \"socket\": 5, \n                    \"start\": 0\n                }\n            ], \n            \"sum\": {\n                \"bits_per_second\": 5236810.783934425, \n                \"bytes\": 655360, \n                \"end\": 1.001159, \n                \"omitted\": false, \n                \"seconds\": 1.0011589527130127, \n                \"sender\": false, \n                \"start\": 0\n            }\n        }, \n        {\n            \"streams\": [\n                {\n                    \"bits_per_second\": 8389430.080555703, \n                    \"bytes\": 1048576, \n                    \"end\": 2.001061, \n                    \"omitted\": false, \n                    \"seconds\": 0.9999020099639893, \n                    \"sender\": false, \n                    \"socket\": 5, \n                    \"start\": 1.001159\n                }\n            ], \n            \"sum\": {\n                \"bits_per_second\": 8389430.080555703, \n                \"bytes\": 1048576, \n                \"end\": 2.001061, \n                \"omitted\": false, \n                \"seconds\": 0.9999020099639893, \n                \"sender\": false, \n                \"start\": 1.001159\n            }\n        }, \n        {\n            \"streams\": [\n                {\n                    \"bits_per_second\": 0, \n                    \"bytes\": 0, \n                    \"end\": 3.001156, \n                    \"omitted\": false, \n                    \"seconds\": 1.000095009803772, \n                    \"sender\": false, \n                    \"socket\": 5, \n                    \"start\": 2.001061\n                }\n            ], \n            \"sum\": {\n                \"bits_per_second\": 0, \n                \"bytes\": 0, \n                \"end\": 3.001156, \n                \"omitted\": false, \n                \"seconds\": 1.000095009803772, \n                \"sender\": false, \n                \"start\": 2.001061\n            }\n        }, \n        {\n            \"streams\": [\n                {\n                    \"bits_per_second\": 0, \n                    \"bytes\": 0, \n                    \"end\": 4.001109, \n                    \"omitted\": false, \n                    \"seconds\": 0.9999529719352722, \n                    \"sender\": false, \n                    \"socket\": 5, \n                    \"start\": 3.001156\n                }\n            ], \n            \"sum\": {\n                \"bits_per_second\": 0, \n                \"bytes\": 0, \n                \"end\": 4.001109, \n                \"omitted\": false, \n                \"seconds\": 0.9999529719352722, \n                \"sender\": false, \n                \"start\": 3.001156\n            }\n        }, \n        {\n            \"streams\": [\n                {\n                    \"bits_per_second\": 0, \n                    \"bytes\": 0, \n                    \"end\": 5.001147, \n                    \"omitted\": false, \n                    \"seconds\": 1.0000380277633667, \n                    \"sender\": false, \n                    \"socket\": 5, \n                    \"start\": 4.001109\n                }\n            ], \n            \"sum\": {\n                \"bits_per_second\": 0, \n                \"bytes\": 0, \n                \"end\": 5.001147, \n                \"omitted\": false, \n                \"seconds\": 1.0000380277633667, \n                \"sender\": false, \n                \"start\": 4.001109\n            }\n        }, \n        {\n            \"streams\": [\n                {\n                    \"bits_per_second\": 1048652.568090672, \n                    \"bytes\": 131072, \n                    \"end\": 6.001074, \n                    \"omitted\": false, \n                    \"seconds\": 0.99992698431015, \n                    \"sender\": false, \n                    \"socket\": 5, \n                    \"start\": 5.001147\n                }\n            ], \n            \"sum\": {\n                \"bits_per_second\": 1048652.568090672, \n                \"bytes\": 131072, \n                \"end\": 6.001074, \n                \"omitted\": false, \n                \"seconds\": 0.99992698431015, \n                \"sender\": false, \n                \"start\": 5.001147\n            }\n        }, \n        {\n            \"streams\": [\n                {\n                    \"bits_per_second\": 20970262.575398035, \n                    \"bytes\": 2621440, \n                    \"end\": 7.001134, \n                    \"omitted\": false, \n                    \"seconds\": 1.000059962272644, \n                    \"sender\": false, \n                    \"socket\": 5, \n                    \"start\": 6.001074\n                }\n            ], \n            \"sum\": {\n                \"bits_per_second\": 20970262.575398035, \n                \"bytes\": 2621440, \n                \"end\": 7.001134, \n                \"omitted\": false, \n                \"seconds\": 1.000059962272644, \n                \"sender\": false, \n                \"start\": 6.001074\n            }\n        }, \n        {\n            \"streams\": [\n                {\n                    \"bits_per_second\": 15728608.125064597, \n                    \"bytes\": 1966080, \n                    \"end\": 8.001136, \n                    \"omitted\": false, \n                    \"seconds\": 1.0000020265579224, \n                    \"sender\": false, \n                    \"socket\": 5, \n                    \"start\": 7.001134\n                }\n            ], \n            \"sum\": {\n                \"bits_per_second\": 15728608.125064597, \n                \"bytes\": 1966080, \n                \"end\": 8.001136, \n                \"omitted\": false, \n                \"seconds\": 1.0000020265579224, \n                \"sender\": false, \n                \"start\": 7.001134\n            }\n        }, \n        {\n            \"streams\": [\n                {\n                    \"bits_per_second\": 6291393.00063085, \n                    \"bytes\": 786432, \n                    \"end\": 9.001146, \n                    \"omitted\": false, \n                    \"seconds\": 1.0000100135803223, \n                    \"sender\": false, \n                    \"socket\": 5, \n                    \"start\": 8.001136\n                }\n            ], \n            \"sum\": {\n                \"bits_per_second\": 6291393.00063085, \n                \"bytes\": 786432, \n                \"end\": 9.001146, \n                \"omitted\": false, \n                \"seconds\": 1.0000100135803223, \n                \"sender\": false, \n                \"start\": 8.001136\n            }\n        }, \n        {\n            \"streams\": [\n                {\n                    \"bits_per_second\": 0, \n                    \"bytes\": 0, \n                    \"end\": 10.001147, \n                    \"omitted\": false, \n                    \"seconds\": 1.0000009536743164, \n                    \"sender\": false, \n                    \"socket\": 5, \n                    \"start\": 9.001146\n                }\n            ], \n            \"sum\": {\n                \"bits_per_second\": 0, \n                \"bytes\": 0, \n                \"end\": 10.001147, \n                \"omitted\": false, \n                \"seconds\": 1.0000009536743164, \n                \"sender\": false, \n                \"start\": 9.001146\n            }\n        }, \n        {\n            \"streams\": [\n                {\n                    \"bits_per_second\": 0, \n                    \"bytes\": 0, \n                    \"end\": 11.001103, \n                    \"omitted\": false, \n                    \"seconds\": 0.9999560117721558, \n                    \"sender\": false, \n                    \"socket\": 5, \n                    \"start\": 10.001147\n                }\n            ], \n            \"sum\": {\n                \"bits_per_second\": 0, \n                \"bytes\": 0, \n                \"end\": 11.001103, \n                \"omitted\": false, \n                \"seconds\": 0.9999560117721558, \n                \"sender\": false, \n                \"start\": 10.001147\n            }\n        }, \n        {\n            \"streams\": [\n                {\n                    \"bits_per_second\": 0, \n                    \"bytes\": 0, \n                    \"end\": 12.001091, \n                    \"omitted\": false, \n                    \"seconds\": 0.9999880194664, \n                    \"sender\": false, \n                    \"socket\": 5, \n                    \"start\": 11.001103\n                }\n            ], \n            \"sum\": {\n                \"bits_per_second\": 0, \n                \"bytes\": 0, \n                \"end\": 12.001091, \n                \"omitted\": false, \n                \"seconds\": 0.9999880194664, \n                \"sender\": false, \n                \"start\": 11.001103\n            }\n        }, \n        {\n            \"streams\": [\n                {\n                    \"bits_per_second\": 0, \n                    \"bytes\": 0, \n                    \"end\": 13.001202, \n                    \"omitted\": false, \n                    \"seconds\": 1.0001109838485718, \n                    \"sender\": false, \n                    \"socket\": 5, \n                    \"start\": 12.001091\n                }\n            ], \n            \"sum\": {\n                \"bits_per_second\": 0, \n                \"bytes\": 0, \n                \"end\": 13.001202, \n                \"omitted\": false, \n                \"seconds\": 1.0001109838485718, \n                \"sender\": false, \n                \"start\": 12.001091\n            }\n        }, \n        {\n            \"streams\": [\n                {\n                    \"bits_per_second\": 3146096.105569794, \n                    \"bytes\": 393216, \n                    \"end\": 14.001085, \n                    \"omitted\": false, \n                    \"seconds\": 0.999882996082306, \n                    \"sender\": false, \n                    \"socket\": 5, \n                    \"start\": 13.001202\n                }\n            ], \n            \"sum\": {\n                \"bits_per_second\": 3146096.105569794, \n                \"bytes\": 393216, \n                \"end\": 14.001085, \n                \"omitted\": false, \n                \"seconds\": 0.999882996082306, \n                \"sender\": false, \n                \"start\": 13.001202\n            }\n        }, \n        {\n            \"streams\": [\n                {\n                    \"bits_per_second\": 18872273.48245762, \n                    \"bytes\": 2359296, \n                    \"end\": 15.001196, \n                    \"omitted\": false, \n                    \"seconds\": 1.0001109838485718, \n                    \"sender\": false, \n                    \"socket\": 5, \n                    \"start\": 14.001085\n                }\n            ], \n            \"sum\": {\n                \"bits_per_second\": 18872273.48245762, \n                \"bytes\": 2359296, \n                \"end\": 15.001196, \n                \"omitted\": false, \n                \"seconds\": 1.0001109838485718, \n                \"sender\": false, \n                \"start\": 14.001085\n            }\n        }, \n        {\n            \"streams\": [\n                {\n                    \"bits_per_second\": 22021814.196557958, \n                    \"bytes\": 2752512, \n                    \"end\": 16.001118, \n                    \"omitted\": false, \n                    \"seconds\": 0.999921977519989, \n                    \"sender\": false, \n                    \"socket\": 5, \n                    \"start\": 15.001196\n                }\n            ], \n            \"sum\": {\n                \"bits_per_second\": 22021814.196557958, \n                \"bytes\": 2752512, \n                \"end\": 16.001118, \n                \"omitted\": false, \n                \"seconds\": 0.999921977519989, \n                \"sender\": false, \n                \"start\": 15.001196\n            }\n        }, \n        {\n            \"streams\": [\n                {\n                    \"bits_per_second\": 20971267.5030401, \n                    \"bytes\": 2621440, \n                    \"end\": 17.00113, \n                    \"omitted\": false, \n                    \"seconds\": 1.0000120401382446, \n                    \"sender\": false, \n                    \"socket\": 5, \n                    \"start\": 16.001118\n                }\n            ], \n            \"sum\": {\n                \"bits_per_second\": 20971267.5030401, \n                \"bytes\": 2621440, \n                \"end\": 17.00113, \n                \"omitted\": false, \n                \"seconds\": 1.0000120401382446, \n                \"sender\": false, \n                \"start\": 16.001118\n            }\n        }, \n        {\n            \"streams\": [\n                {\n                    \"bits_per_second\": 12582823.500622448, \n                    \"bytes\": 1572864, \n                    \"end\": 18.001137, \n                    \"omitted\": false, \n                    \"seconds\": 1.0000070333480835, \n                    \"sender\": false, \n                    \"socket\": 5, \n                    \"start\": 17.00113\n                }\n            ], \n            \"sum\": {\n                \"bits_per_second\": 12582823.500622448, \n                \"bytes\": 1572864, \n                \"end\": 18.001137, \n                \"omitted\": false, \n                \"seconds\": 1.0000070333480835, \n                \"sender\": false, \n                \"start\": 17.00113\n            }\n        }, \n        {\n            \"streams\": [\n                {\n                    \"bits_per_second\": 16776846.008159695, \n                    \"bytes\": 2097152, \n                    \"end\": 19.001159, \n                    \"omitted\": false, \n                    \"seconds\": 1.000022053718567, \n                    \"sender\": false, \n                    \"socket\": 5, \n                    \"start\": 18.001137\n                }\n            ], \n            \"sum\": {\n                \"bits_per_second\": 16776846.008159695, \n                \"bytes\": 2097152, \n                \"end\": 19.001159, \n                \"omitted\": false, \n                \"seconds\": 1.000022053718567, \n                \"sender\": false, \n                \"start\": 18.001137\n            }\n        }, \n        {\n            \"streams\": [\n                {\n                    \"bits_per_second\": 2097288.3838688615, \n                    \"bytes\": 262144, \n                    \"end\": 20.001094, \n                    \"omitted\": false, \n                    \"seconds\": 0.99993497133255, \n                    \"sender\": false, \n                    \"socket\": 5, \n                    \"start\": 19.001159\n                }\n            ], \n            \"sum\": {\n                \"bits_per_second\": 2097288.3838688615, \n                \"bytes\": 262144, \n                \"end\": 20.001094, \n                \"omitted\": false, \n                \"seconds\": 0.99993497133255, \n                \"sender\": false, \n                \"start\": 19.001159\n            }\n        }, \n        {\n            \"streams\": [\n                {\n                    \"bits_per_second\": 3145605.3797799125, \n                    \"bytes\": 393216, \n                    \"end\": 21.001133, \n                    \"omitted\": false, \n                    \"seconds\": 1.000038981437683, \n                    \"sender\": false, \n                    \"socket\": 5, \n                    \"start\": 20.001094\n                }\n            ], \n            \"sum\": {\n                \"bits_per_second\": 3145605.3797799125, \n                \"bytes\": 393216, \n                \"end\": 21.001133, \n                \"omitted\": false, \n                \"seconds\": 1.000038981437683, \n                \"sender\": false, \n                \"start\": 20.001094\n            }\n        }, \n        {\n            \"streams\": [\n                {\n                    \"bits_per_second\": 0, \n                    \"bytes\": 0, \n                    \"end\": 22.001127, \n                    \"omitted\": false, \n                    \"seconds\": 0.9999939799308777, \n                    \"sender\": false, \n                    \"socket\": 5, \n                    \"start\": 21.001133\n                }\n            ], \n            \"sum\": {\n                \"bits_per_second\": 0, \n                \"bytes\": 0, \n                \"end\": 22.001127, \n                \"omitted\": false, \n                \"seconds\": 0.9999939799308777, \n                \"sender\": false, \n                \"start\": 21.001133\n            }\n        }, \n        {\n            \"streams\": [\n                {\n                    \"bits_per_second\": 0, \n                    \"bytes\": 0, \n                    \"end\": 23.000171, \n                    \"omitted\": false, \n                    \"seconds\": 0.9990440011024475, \n                    \"sender\": false, \n                    \"socket\": 5, \n                    \"start\": 22.001127\n                }\n            ], \n            \"sum\": {\n                \"bits_per_second\": 0, \n                \"bytes\": 0, \n                \"end\": 23.000171, \n                \"omitted\": false, \n                \"seconds\": 0.9990440011024475, \n                \"sender\": false, \n                \"start\": 22.001127\n            }\n        }, \n        {\n            \"streams\": [\n                {\n                    \"bits_per_second\": 0, \n                    \"bytes\": 0, \n                    \"end\": 24.00008, \n                    \"omitted\": false, \n                    \"seconds\": 0.999908983707428, \n                    \"sender\": false, \n                    \"socket\": 5, \n                    \"start\": 23.000171\n                }\n            ], \n            \"sum\": {\n                \"bits_per_second\": 0, \n                \"bytes\": 0, \n                \"end\": 24.00008, \n                \"omitted\": false, \n                \"seconds\": 0.999908983707428, \n                \"sender\": false, \n                \"start\": 23.000171\n            }\n        }, \n        {\n            \"streams\": [\n                {\n                    \"bits_per_second\": 0, \n                    \"bytes\": 0, \n                    \"end\": 25.000057, \n                    \"omitted\": false, \n                    \"seconds\": 0.9999769926071167, \n                    \"sender\": false, \n                    \"socket\": 5, \n                    \"start\": 24.00008\n                }\n            ], \n            \"sum\": {\n                \"bits_per_second\": 0, \n                \"bytes\": 0, \n                \"end\": 25.000057, \n                \"omitted\": false, \n                \"seconds\": 0.9999769926071167, \n                \"sender\": false, \n                \"start\": 24.00008\n            }\n        }, \n        {\n            \"streams\": [\n                {\n                    \"bits_per_second\": 0, \n                    \"bytes\": 0, \n                    \"end\": 26.00112, \n                    \"omitted\": false, \n                    \"seconds\": 1.0010629892349243, \n                    \"sender\": false, \n                    \"socket\": 5, \n                    \"start\": 25.000057\n                }\n            ], \n            \"sum\": {\n                \"bits_per_second\": 0, \n                \"bytes\": 0, \n                \"end\": 26.00112, \n                \"omitted\": false, \n                \"seconds\": 1.0010629892349243, \n                \"sender\": false, \n                \"start\": 25.000057\n            }\n        }, \n        {\n            \"streams\": [\n                {\n                    \"bits_per_second\": 0, \n                    \"bytes\": 0, \n                    \"end\": 27.000059, \n                    \"omitted\": false, \n                    \"seconds\": 0.9989389777183533, \n                    \"sender\": false, \n                    \"socket\": 5, \n                    \"start\": 26.00112\n                }\n            ], \n            \"sum\": {\n                \"bits_per_second\": 0, \n                \"bytes\": 0, \n                \"end\": 27.000059, \n                \"omitted\": false, \n                \"seconds\": 0.9989389777183533, \n                \"sender\": false, \n                \"start\": 26.00112\n            }\n        }, \n        {\n            \"streams\": [\n                {\n                    \"bits_per_second\": 0, \n                    \"bytes\": 0, \n                    \"end\": 28.000298, \n                    \"omitted\": false, \n                    \"seconds\": 1.0002390146255493, \n                    \"sender\": false, \n                    \"socket\": 5, \n                    \"start\": 27.000059\n                }\n            ], \n            \"sum\": {\n                \"bits_per_second\": 0, \n                \"bytes\": 0, \n                \"end\": 28.000298, \n                \"omitted\": false, \n                \"seconds\": 1.0002390146255493, \n                \"sender\": false, \n                \"start\": 27.000059\n            }\n        }, \n        {\n            \"streams\": [\n                {\n                    \"bits_per_second\": 0, \n                    \"bytes\": 0, \n                    \"end\": 29.000771, \n                    \"omitted\": false, \n                    \"seconds\": 1.0004730224609375, \n                    \"sender\": false, \n                    \"socket\": 5, \n                    \"start\": 28.000298\n                }\n            ], \n            \"sum\": {\n                \"bits_per_second\": 0, \n                \"bytes\": 0, \n                \"end\": 29.000771, \n                \"omitted\": false, \n                \"seconds\": 1.0004730224609375, \n                \"sender\": false, \n                \"start\": 28.000298\n            }\n        }, \n        {\n            \"streams\": [\n                {\n                    \"bits_per_second\": 0, \n                    \"bytes\": 0, \n                    \"end\": 30.001112, \n                    \"omitted\": false, \n                    \"seconds\": 1.0003410577774048, \n                    \"sender\": false, \n                    \"socket\": 5, \n                    \"start\": 29.000771\n                }\n            ], \n            \"sum\": {\n                \"bits_per_second\": 0, \n                \"bytes\": 0, \n                \"end\": 30.001112, \n                \"omitted\": false, \n                \"seconds\": 1.0003410577774048, \n                \"sender\": false, \n                \"start\": 29.000771\n            }\n        }, \n        {\n            \"streams\": [\n                {\n                    \"bits_per_second\": 476043.16689725145, \n                    \"bytes\": 59512, \n                    \"end\": 31.001223, \n                    \"omitted\": false, \n                    \"seconds\": 1.0001109838485718, \n                    \"sender\": false, \n                    \"socket\": 5, \n                    \"start\": 30.001112\n                }\n            ], \n            \"sum\": {\n                \"bits_per_second\": 476043.16689725145, \n                \"bytes\": 59512, \n                \"end\": 31.001223, \n                \"omitted\": false, \n                \"seconds\": 1.0001109838485718, \n                \"sender\": false, \n                \"start\": 30.001112\n            }\n        }, \n        {\n            \"streams\": [\n                {\n                    \"bits_per_second\": 0, \n                    \"bytes\": 0, \n                    \"end\": 32.001131, \n                    \"omitted\": false, \n                    \"seconds\": 0.9999079704284668, \n                    \"sender\": false, \n                    \"socket\": 5, \n                    \"start\": 31.001223\n                }\n            ], \n            \"sum\": {\n                \"bits_per_second\": 0, \n                \"bytes\": 0, \n                \"end\": 32.001131, \n                \"omitted\": false, \n                \"seconds\": 0.9999079704284668, \n                \"sender\": false, \n                \"start\": 31.001223\n            }\n        }, \n        {\n            \"streams\": [\n                {\n                    \"bits_per_second\": 0, \n                    \"bytes\": 0, \n                    \"end\": 33.00106, \n                    \"omitted\": false, \n                    \"seconds\": 0.9999290108680725, \n                    \"sender\": false, \n                    \"socket\": 5, \n                    \"start\": 32.001131\n                }\n            ], \n            \"sum\": {\n                \"bits_per_second\": 0, \n                \"bytes\": 0, \n                \"end\": 33.00106, \n                \"omitted\": false, \n                \"seconds\": 0.9999290108680725, \n                \"sender\": false, \n                \"start\": 32.001131\n            }\n        }, \n        {\n            \"streams\": [\n                {\n                    \"bits_per_second\": 0, \n                    \"bytes\": 0, \n                    \"end\": 34.001151, \n                    \"omitted\": false, \n                    \"seconds\": 1.0000909566879272, \n                    \"sender\": false, \n                    \"socket\": 5, \n                    \"start\": 33.00106\n                }\n            ], \n            \"sum\": {\n                \"bits_per_second\": 0, \n                \"bytes\": 0, \n                \"end\": 34.001151, \n                \"omitted\": false, \n                \"seconds\": 1.0000909566879272, \n                \"sender\": false, \n                \"start\": 33.00106\n            }\n        }, \n        {\n            \"streams\": [\n                {\n                    \"bits_per_second\": 0, \n                    \"bytes\": 0, \n                    \"end\": 35.001159, \n                    \"omitted\": false, \n                    \"seconds\": 1.0000079870224, \n                    \"sender\": false, \n                    \"socket\": 5, \n                    \"start\": 34.001151\n                }\n            ], \n            \"sum\": {\n                \"bits_per_second\": 0, \n                \"bytes\": 0, \n                \"end\": 35.001159, \n                \"omitted\": false, \n                \"seconds\": 1.0000079870224, \n                \"sender\": false, \n                \"start\": 34.001151\n            }\n        }, \n        {\n            \"streams\": [\n                {\n                    \"bits_per_second\": 0, \n                    \"bytes\": 0, \n                    \"end\": 36.001158, \n                    \"omitted\": false, \n                    \"seconds\": 0.9999989867210388, \n                    \"sender\": false, \n                    \"socket\": 5, \n                    \"start\": 35.001159\n                }\n            ], \n            \"sum\": {\n                \"bits_per_second\": 0, \n                \"bytes\": 0, \n                \"end\": 36.001158, \n                \"omitted\": false, \n                \"seconds\": 0.9999989867210388, \n                \"sender\": false, \n                \"start\": 35.001159\n            }\n        }, \n        {\n            \"streams\": [\n                {\n                    \"bits_per_second\": 0, \n                    \"bytes\": 0, \n                    \"end\": 37.001159, \n                    \"omitted\": false, \n                    \"seconds\": 1.0000009536743164, \n                    \"sender\": false, \n                    \"socket\": 5, \n                    \"start\": 36.001158\n                }\n            ], \n            \"sum\": {\n                \"bits_per_second\": 0, \n                \"bytes\": 0, \n                \"end\": 37.001159, \n                \"omitted\": false, \n                \"seconds\": 1.0000009536743164, \n                \"sender\": false, \n                \"start\": 36.001158\n            }\n        }, \n        {\n            \"streams\": [\n                {\n                    \"bits_per_second\": 0, \n                    \"bytes\": 0, \n                    \"end\": 38.001104, \n                    \"omitted\": false, \n                    \"seconds\": 0.9999449849128723, \n                    \"sender\": false, \n                    \"socket\": 5, \n                    \"start\": 37.001159\n                }\n            ], \n            \"sum\": {\n                \"bits_per_second\": 0, \n                \"bytes\": 0, \n                \"end\": 38.001104, \n                \"omitted\": false, \n                \"seconds\": 0.9999449849128723, \n                \"sender\": false, \n                \"start\": 37.001159\n            }\n        }, \n        {\n            \"streams\": [\n                {\n                    \"bits_per_second\": 0, \n                    \"bytes\": 0, \n                    \"end\": 39.001152, \n                    \"omitted\": false, \n                    \"seconds\": 1.000048041343689, \n                    \"sender\": false, \n                    \"socket\": 5, \n                    \"start\": 38.001104\n                }\n            ], \n            \"sum\": {\n                \"bits_per_second\": 0, \n                \"bytes\": 0, \n                \"end\": 39.001152, \n                \"omitted\": false, \n                \"seconds\": 1.000048041343689, \n                \"sender\": false, \n                \"start\": 38.001104\n            }\n        }, \n        {\n            \"streams\": [\n                {\n                    \"bits_per_second\": 0, \n                    \"bytes\": 0, \n                    \"end\": 40.000107, \n                    \"omitted\": false, \n                    \"seconds\": 0.998955011367798, \n                    \"sender\": false, \n                    \"socket\": 5, \n                    \"start\": 39.001152\n                }\n            ], \n            \"sum\": {\n                \"bits_per_second\": 0, \n                \"bytes\": 0, \n                \"end\": 40.000107, \n                \"omitted\": false, \n                \"seconds\": 0.998955011367798, \n                \"sender\": false, \n                \"start\": 39.001152\n            }\n        }, \n        {\n            \"streams\": [\n                {\n                    \"bits_per_second\": 92676.72851274055, \n                    \"bytes\": 11584, \n                    \"end\": 41.000056, \n                    \"omitted\": false, \n                    \"seconds\": 0.9999489784240723, \n                    \"sender\": false, \n                    \"socket\": 5, \n                    \"start\": 40.000107\n                }\n            ], \n            \"sum\": {\n                \"bits_per_second\": 92676.72851274055, \n                \"bytes\": 11584, \n                \"end\": 41.000056, \n                \"omitted\": false, \n                \"seconds\": 0.9999489784240723, \n                \"sender\": false, \n                \"start\": 40.000107\n            }\n        }, \n        {\n            \"streams\": [\n                {\n                    \"bits_per_second\": 0, \n                    \"bytes\": 0, \n                    \"end\": 42.001144, \n                    \"omitted\": false, \n                    \"seconds\": 1.00108802318573, \n                    \"sender\": false, \n                    \"socket\": 5, \n                    \"start\": 41.000056\n                }\n            ], \n            \"sum\": {\n                \"bits_per_second\": 0, \n                \"bytes\": 0, \n                \"end\": 42.001144, \n                \"omitted\": false, \n                \"seconds\": 1.00108802318573, \n                \"sender\": false, \n                \"start\": 41.000056\n            }\n        }, \n        {\n            \"streams\": [\n                {\n                    \"bits_per_second\": 0, \n                    \"bytes\": 0, \n                    \"end\": 43.001096, \n                    \"omitted\": false, \n                    \"seconds\": 0.9999520182609558, \n                    \"sender\": false, \n                    \"socket\": 5, \n                    \"start\": 42.001144\n                }\n            ], \n            \"sum\": {\n                \"bits_per_second\": 0, \n                \"bytes\": 0, \n                \"end\": 43.001096, \n                \"omitted\": false, \n                \"seconds\": 0.9999520182609558, \n                \"sender\": false, \n                \"start\": 42.001144\n            }\n        }, \n        {\n            \"streams\": [\n                {\n                    \"bits_per_second\": 0, \n                    \"bytes\": 0, \n                    \"end\": 44.000188, \n                    \"omitted\": false, \n                    \"seconds\": 0.9990919828414917, \n                    \"sender\": false, \n                    \"socket\": 5, \n                    \"start\": 43.001096\n                }\n            ], \n            \"sum\": {\n                \"bits_per_second\": 0, \n                \"bytes\": 0, \n                \"end\": 44.000188, \n                \"omitted\": false, \n                \"seconds\": 0.9990919828414917, \n                \"sender\": false, \n                \"start\": 43.001096\n            }\n        }, \n        {\n            \"streams\": [\n                {\n                    \"bits_per_second\": 0, \n                    \"bytes\": 0, \n                    \"end\": 45.001154, \n                    \"omitted\": false, \n                    \"seconds\": 1.00096595287323, \n                    \"sender\": false, \n                    \"socket\": 5, \n                    \"start\": 44.000188\n                }\n            ], \n            \"sum\": {\n                \"bits_per_second\": 0, \n                \"bytes\": 0, \n                \"end\": 45.001154, \n                \"omitted\": false, \n                \"seconds\": 1.00096595287323, \n                \"sender\": false, \n                \"start\": 44.000188\n            }\n        }, \n        {\n            \"streams\": [\n                {\n                    \"bits_per_second\": 0, \n                    \"bytes\": 0, \n                    \"end\": 46.001132, \n                    \"omitted\": false, \n                    \"seconds\": 0.999978005886078, \n                    \"sender\": false, \n                    \"socket\": 5, \n                    \"start\": 45.001154\n                }\n            ], \n            \"sum\": {\n                \"bits_per_second\": 0, \n                \"bytes\": 0, \n                \"end\": 46.001132, \n                \"omitted\": false, \n                \"seconds\": 0.999978005886078, \n                \"sender\": false, \n                \"start\": 45.001154\n            }\n        }, \n        {\n            \"streams\": [\n                {\n                    \"bits_per_second\": 0, \n                    \"bytes\": 0, \n                    \"end\": 47.001158, \n                    \"omitted\": false, \n                    \"seconds\": 1.000025987625122, \n                    \"sender\": false, \n                    \"socket\": 5, \n                    \"start\": 46.001132\n                }\n            ], \n            \"sum\": {\n                \"bits_per_second\": 0, \n                \"bytes\": 0, \n                \"end\": 47.001158, \n                \"omitted\": false, \n                \"seconds\": 1.000025987625122, \n                \"sender\": false, \n                \"start\": 46.001132\n            }\n        }, \n        {\n            \"streams\": [\n                {\n                    \"bits_per_second\": 0, \n                    \"bytes\": 0, \n                    \"end\": 48.001136, \n                    \"omitted\": false, \n                    \"seconds\": 0.999978005886078, \n                    \"sender\": false, \n                    \"socket\": 5, \n                    \"start\": 47.001158\n                }\n            ], \n            \"sum\": {\n                \"bits_per_second\": 0, \n                \"bytes\": 0, \n                \"end\": 48.001136, \n                \"omitted\": false, \n                \"seconds\": 0.999978005886078, \n                \"sender\": false, \n                \"start\": 47.001158\n            }\n        }, \n        {\n            \"streams\": [\n                {\n                    \"bits_per_second\": 0, \n                    \"bytes\": 0, \n                    \"end\": 49.001094, \n                    \"omitted\": false, \n                    \"seconds\": 0.9999579787254333, \n                    \"sender\": false, \n                    \"socket\": 5, \n                    \"start\": 48.001136\n                }\n            ], \n            \"sum\": {\n                \"bits_per_second\": 0, \n                \"bytes\": 0, \n                \"end\": 49.001094, \n                \"omitted\": false, \n                \"seconds\": 0.9999579787254333, \n                \"sender\": false, \n                \"start\": 48.001136\n            }\n        }, \n        {\n            \"streams\": [\n                {\n                    \"bits_per_second\": 2097093.2516457872, \n                    \"bytes\": 262144, \n                    \"end\": 50.001122, \n                    \"omitted\": false, \n                    \"seconds\": 1.0000280141830444, \n                    \"sender\": false, \n                    \"socket\": 5, \n                    \"start\": 49.001094\n                }\n            ], \n            \"sum\": {\n                \"bits_per_second\": 2097093.2516457872, \n                \"bytes\": 262144, \n                \"end\": 50.001122, \n                \"omitted\": false, \n                \"seconds\": 1.0000280141830444, \n                \"sender\": false, \n                \"start\": 49.001094\n            }\n        }, \n        {\n            \"streams\": [\n                {\n                    \"bits_per_second\": 1048580.1875167228, \n                    \"bytes\": 131072, \n                    \"end\": 51.001118, \n                    \"omitted\": false, \n                    \"seconds\": 0.9999960064888, \n                    \"sender\": false, \n                    \"socket\": 5, \n                    \"start\": 50.001122\n                }\n            ], \n            \"sum\": {\n                \"bits_per_second\": 1048580.1875167228, \n                \"bytes\": 131072, \n                \"end\": 51.001118, \n                \"omitted\": false, \n                \"seconds\": 0.9999960064888, \n                \"sender\": false, \n                \"start\": 50.001122\n            }\n        }, \n        {\n            \"streams\": [\n                {\n                    \"bits_per_second\": 0, \n                    \"bytes\": 0, \n                    \"end\": 52.001114, \n                    \"omitted\": false, \n                    \"seconds\": 0.9999960064888, \n                    \"sender\": false, \n                    \"socket\": 5, \n                    \"start\": 51.001118\n                }\n            ], \n            \"sum\": {\n                \"bits_per_second\": 0, \n                \"bytes\": 0, \n                \"end\": 52.001114, \n                \"omitted\": false, \n                \"seconds\": 0.9999960064888, \n                \"sender\": false, \n                \"start\": 51.001118\n            }\n        }, \n        {\n            \"streams\": [\n                {\n                    \"bits_per_second\": 0, \n                    \"bytes\": 0, \n                    \"end\": 53.001114, \n                    \"omitted\": false, \n                    \"seconds\": 1, \n                    \"sender\": false, \n                    \"socket\": 5, \n                    \"start\": 52.001114\n                }\n            ], \n            \"sum\": {\n                \"bits_per_second\": 0, \n                \"bytes\": 0, \n                \"end\": 53.001114, \n                \"omitted\": false, \n                \"seconds\": 1, \n                \"sender\": false, \n                \"start\": 52.001114\n            }\n        }, \n        {\n            \"streams\": [\n                {\n                    \"bits_per_second\": 1049552.095279613, \n                    \"bytes\": 131072, \n                    \"end\": 54.000184, \n                    \"omitted\": false, \n                    \"seconds\": 0.9990699887275696, \n                    \"sender\": false, \n                    \"socket\": 5, \n                    \"start\": 53.001114\n                }\n            ], \n            \"sum\": {\n                \"bits_per_second\": 1049552.095279613, \n                \"bytes\": 131072, \n                \"end\": 54.000184, \n                \"omitted\": false, \n                \"seconds\": 0.9990699887275696, \n                \"sender\": false, \n                \"start\": 53.001114\n            }\n        }, \n        {\n            \"streams\": [\n                {\n                    \"bits_per_second\": 17826504.966014873, \n                    \"bytes\": 2228224, \n                    \"end\": 55.000144, \n                    \"omitted\": false, \n                    \"seconds\": 0.9999600052833557, \n                    \"sender\": false, \n                    \"socket\": 5, \n                    \"start\": 54.000184\n                }\n            ], \n            \"sum\": {\n                \"bits_per_second\": 17826504.966014873, \n                \"bytes\": 2228224, \n                \"end\": 55.000144, \n                \"omitted\": false, \n                \"seconds\": 0.9999600052833557, \n                \"sender\": false, \n                \"start\": 54.000184\n            }\n        }, \n        {\n            \"streams\": [\n                {\n                    \"bits_per_second\": 13631542.437717397, \n                    \"bytes\": 1703936, \n                    \"end\": 56.00014, \n                    \"omitted\": false, \n                    \"seconds\": 0.9999960064888, \n                    \"sender\": false, \n                    \"socket\": 5, \n                    \"start\": 55.000144\n                }\n            ], \n            \"sum\": {\n                \"bits_per_second\": 13631542.437717397, \n                \"bytes\": 1703936, \n                \"end\": 56.00014, \n                \"omitted\": false, \n                \"seconds\": 0.9999960064888, \n                \"sender\": false, \n                \"start\": 55.000144\n            }\n        }, \n        {\n            \"streams\": [\n                {\n                    \"bits_per_second\": 22021152.61319814, \n                    \"bytes\": 2752512, \n                    \"end\": 57.000092, \n                    \"omitted\": false, \n                    \"seconds\": 0.9999520182609558, \n                    \"sender\": false, \n                    \"socket\": 5, \n                    \"start\": 56.00014\n                }\n            ], \n            \"sum\": {\n                \"bits_per_second\": 22021152.61319814, \n                \"bytes\": 2752512, \n                \"end\": 57.000092, \n                \"omitted\": false, \n                \"seconds\": 0.9999520182609558, \n                \"sender\": false, \n                \"start\": 56.00014\n            }\n        }, \n        {\n            \"streams\": [\n                {\n                    \"bits_per_second\": 22021174.92786209, \n                    \"bytes\": 2752512, \n                    \"end\": 58.000043, \n                    \"omitted\": false, \n                    \"seconds\": 0.9999510049819946, \n                    \"sender\": false, \n                    \"socket\": 5, \n                    \"start\": 57.000092\n                }\n            ], \n            \"sum\": {\n                \"bits_per_second\": 22021174.92786209, \n                \"bytes\": 2752512, \n                \"end\": 58.000043, \n                \"omitted\": false, \n                \"seconds\": 0.9999510049819946, \n                \"sender\": false, \n                \"start\": 57.000092\n            }\n        }, \n        {\n            \"streams\": [\n                {\n                    \"bits_per_second\": 8379717.43256023, \n                    \"bytes\": 1048576, \n                    \"end\": 59.001104, \n                    \"omitted\": false, \n                    \"seconds\": 1.001060962677002, \n                    \"sender\": false, \n                    \"socket\": 5, \n                    \"start\": 58.000043\n                }\n            ], \n            \"sum\": {\n                \"bits_per_second\": 8379717.43256023, \n                \"bytes\": 1048576, \n                \"end\": 59.001104, \n                \"omitted\": false, \n                \"seconds\": 1.001060962677002, \n                \"sender\": false, \n                \"start\": 58.000043\n            }\n        }, \n        {\n            \"streams\": [\n                {\n                    \"bits_per_second\": 0, \n                    \"bytes\": 0, \n                    \"end\": 60.001137, \n                    \"omitted\": false, \n                    \"seconds\": 1.0000330209732056, \n                    \"sender\": false, \n                    \"socket\": 5, \n                    \"start\": 59.001104\n                }\n            ], \n            \"sum\": {\n                \"bits_per_second\": 0, \n                \"bytes\": 0, \n                \"end\": 60.001137, \n                \"omitted\": false, \n                \"seconds\": 1.0000330209732056, \n                \"sender\": false, \n                \"start\": 59.001104\n            }\n        }, \n        {\n            \"streams\": [\n                {\n                    \"bits_per_second\": 0, \n                    \"bytes\": 0, \n                    \"end\": 61.001115, \n                    \"omitted\": false, \n                    \"seconds\": 0.999978005886078, \n                    \"sender\": false, \n                    \"socket\": 5, \n                    \"start\": 60.001137\n                }\n            ], \n            \"sum\": {\n                \"bits_per_second\": 0, \n                \"bytes\": 0, \n                \"end\": 61.001115, \n                \"omitted\": false, \n                \"seconds\": 0.999978005886078, \n                \"sender\": false, \n                \"start\": 60.001137\n            }\n        }, \n        {\n            \"streams\": [\n                {\n                    \"bits_per_second\": 0, \n                    \"bytes\": 0, \n                    \"end\": 61.277364, \n                    \"omitted\": false, \n                    \"seconds\": 0.2762489914894104, \n                    \"sender\": false, \n                    \"socket\": 5, \n                    \"start\": 61.001115\n                }\n            ], \n            \"sum\": {\n                \"bits_per_second\": 0, \n                \"bytes\": 0, \n                \"end\": 61.277364, \n                \"omitted\": false, \n                \"seconds\": 0.2762489914894104, \n                \"sender\": false, \n                \"start\": 61.001115\n            }\n        }\n    ], \n    \"start\": {\n        \"accepted_connection\": {\n            \"host\": \"172.16.0.2\", \n            \"port\": 34971\n        }, \n        \"connected\": [\n            {\n                \"local_host\": \"172.16.0.1\", \n                \"local_port\": 5201, \n                \"remote_host\": \"172.16.0.2\", \n                \"remote_port\": 48627, \n                \"socket\": 5\n            }\n        ], \n        \"cookie\": \"bjbim23kxzpjfkse5vg2iszpvmergwp3t4oc\", \n        \"fq_rate\": 0, \n        \"rcvbuf_actual\": 87380, \n        \"sndbuf_actual\": 65536, \n        \"sock_bufsize\": 0, \n        \"system_info\": \"REDACTED\", \n        \"target_bitrate\": 0, \n        \"tcp_mss_default\": 0, \n        \"test_start\": {\n            \"bidir\": 0, \n            \"blksize\": 131072, \n            \"blocks\": 0, \n            \"bytes\": 0, \n            \"duration\": 60, \n            \"fqrate\": 0, \n            \"interval\": 1, \n            \"num_streams\": 1, \n            \"omit\": 0, \n            \"protocol\": \"TCP\", \n            \"reverse\": 0, \n            \"target_bitrate\": 0, \n            \"tos\": 0\n        }, \n        \"timestamp\": {\n            \"time\": \"Wed, 16 Oct 2024 02:47:09 GMT\", \n            \"timesecs\": 1729046829\n        }, \n        \"version\": \"iperf 3.17.1\"\n    }\n}\n","summary":{"streams":[{"end":60.001027,"rtt":130391,"start":0,"stream-id":5,"retransmits":1046,"throughput-bits":4578703.494525186,"throughput-bytes":34340864}],"summary":{"end":60.001027,"start":0,"retransmits":1046,"throughput-bits":4578703.494525186,"throughput-bytes":34340864,"receiver-throughput-bits":4013481.258756496}},"intervals":[{"streams":[{"end":1.000759,"rtt":374399,"start":0,"omitted":false,"stream-id":5,"retransmits":95,"tcp-window-size":296840,"throughput-bits":33528983.315692544,"throughput-bytes":4194304}],"summary":{"end":1.000759,"start":0,"omitted":false,"retransmits":95,"throughput-bits":33528983.315692544,"throughput-bytes":4194304}},{"streams":[{"end":2.000325,"rtt":399613,"start":1.000759,"omitted":false,"stream-id":5,"retransmits":217,"tcp-window-size":260640,"throughput-bits":10490312.60074413,"throughput-bytes":1310720}],"summary":{"end":2.000325,"start":1.000759,"omitted":false,"retransmits":217,"throughput-bits":10490312.60074413,"throughput-bytes":1310720}},{"streams":[{"end":3.001018,"rtt":399613,"start":2.000325,"omitted":false,"stream-id":5,"retransmits":0,"tcp-window-size":260640,"throughput-bits":0,"throughput-bytes":0}],"summary":{"end":3.001018,"start":2.000325,"omitted":false,"retransmits":0,"throughput-bits":0,"throughput-bytes":0}},{"streams":[{"end":4.000168,"rtt":399613,"start":3.001018,"omitted":false,"stream-id":5,"retransmits":1,"tcp-window-size":1448,"throughput-bits":0,"throughput-bytes":0}],"summary":{"end":4.000168,"start":3.001018,"omitted":false,"retransmits":1,"throughput-bits":0,"throughput-bytes":0}},{"streams":[{"end":5.000492,"rtt":399613,"start":4.000168,"omitted":false,"stream-id":5,"retransmits":0,"tcp-window-size":1448,"throughput-bits":0,"throughput-bytes":0}],"summary":{"end":5.000492,"start":4.000168,"omitted":false,"retransmits":0,"throughput-bits":0,"throughput-bytes":0}},{"streams":[{"end":6.000839,"rtt":36958,"start":5.000492,"omitted":false,"stream-id":5,"retransmits":145,"tcp-window-size":105704,"throughput-bits":0,"throughput-bytes":0}],"summary":{"end":6.000839,"start":5.000492,"omitted":false,"retransmits":145,"throughput-bits":0,"throughput-bytes":0}},{"streams":[{"end":7.000138,"rtt":69034,"start":6.000839,"omitted":false,"stream-id":5,"retransmits":66,"tcp-window-size":189688,"throughput-bits":20986231.56295609,"throughput-bytes":2621440}],"summary":{"end":7.000138,"start":6.000839,"omitted":false,"retransmits":66,"throughput-bits":20986231.56295609,"throughput-bytes":2621440}},{"streams":[{"end":8.000655,"rtt":223865,"start":7.000138,"omitted":false,"stream-id":5,"retransmits":61,"tcp-window-size":101360,"throughput-bits":10480341.551395845,"throughput-bytes":1310720}],"summary":{"end":8.000655,"start":7.000138,"omitted":false,"retransmits":61,"throughput-bits":10480341.551395845,"throughput-bytes":1310720}},{"streams":[{"end":9.000921,"rtt":23219,"start":8.000655,"omitted":false,"stream-id":5,"retransmits":54,"tcp-window-size":59368,"throughput-bits":10482971.991487382,"throughput-bytes":1310720}],"summary":{"end":9.000921,"start":8.000655,"omitted":false,"retransmits":54,"throughput-bits":10482971.991487382,"throughput-bytes":1310720}},{"streams":[{"end":10.001015,"rtt":23219,"start":9.000921,"omitted":false,"stream-id":5,"retransmits":2,"tcp-window-size":1448,"throughput-bits":0,"throughput-bytes":0}],"summary":{"end":10.001015,"start":9.000921,"omitted":false,"retransmits":2,"throughput-bits":0,"throughput-bytes":0}},{"streams":[{"end":11.002554,"rtt":23219,"start":10.001015,"omitted":false,"stream-id":5,"retransmits":0,"tcp-window-size":1448,"throughput-bits":0,"throughput-bytes":0}],"summary":{"end":11.002554,"start":10.001015,"omitted":false,"retransmits":0,"throughput-bits":0,"throughput-bytes":0}},{"streams":[{"end":12.001024,"rtt":210317,"start":11.002554,"omitted":false,"stream-id":5,"retransmits":1,"tcp-window-size":2896,"throughput-bits":0,"throughput-bytes":0}],"summary":{"end":12.001024,"start":11.002554,"omitted":false,"retransmits":1,"throughput-bits":0,"throughput-bytes":0}},{"streams":[{"end":13.00104,"rtt":210317,"start":12.001024,"omitted":false,"stream-id":5,"retransmits":0,"tcp-window-size":2896,"throughput-bits":0,"throughput-bytes":0}],"summary":{"end":13.00104,"start":12.001024,"omitted":false,"retransmits":0,"throughput-bits":0,"throughput-bytes":0}},{"streams":[{"end":14.001016,"rtt":23670,"start":13.00104,"omitted":false,"stream-id":5,"retransmits":42,"tcp-window-size":28960,"throughput-bits":0,"throughput-bytes":0}],"summary":{"end":14.001016,"start":13.00104,"omitted":false,"retransmits":42,"throughput-bits":0,"throughput-bytes":0}},{"streams":[{"end":15.000245,"rtt":30179,"start":14.001016,"omitted":false,"stream-id":5,"retransmits":0,"tcp-window-size":83984,"throughput-bits":20987701.22549962,"throughput-bytes":2621440}],"summary":{"end":15.000245,"start":14.001016,"omitted":false,"retransmits":0,"throughput-bits":20987701.22549962,"throughput-bytes":2621440}},{"streams":[{"end":16.000281,"rtt":43650,"start":15.000245,"omitted":false,"stream-id":5,"retransmits":0,"tcp-window-size":121632,"throughput-bits":20970765.02717993,"throughput-bytes":2621440}],"summary":{"end":16.000281,"start":15.000245,"omitted":false,"retransmits":0,"throughput-bits":20970765.02717993,"throughput-bytes":2621440}},{"streams":[{"end":17.000305,"rtt":62290,"start":16.000281,"omitted":false,"stream-id":5,"retransmits":0,"tcp-window-size":173760,"throughput-bits":20971017.51204015,"throughput-bytes":2621440}],"summary":{"end":17.000305,"start":16.000281,"omitted":false,"retransmits":0,"throughput-bits":20971017.51204015,"throughput-bytes":2621440}},{"streams":[{"end":18.000811,"rtt":95856,"start":17.000305,"omitted":false,"stream-id":5,"retransmits":68,"tcp-window-size":11584,"throughput-bits":10480456.433834836,"throughput-bytes":1310720}],"summary":{"end":18.000811,"start":17.000305,"omitted":false,"retransmits":68,"throughput-bits":10480456.433834836,"throughput-bytes":1310720}},{"streams":[{"end":19.000336,"rtt":38391,"start":18.000811,"omitted":false,"stream-id":5,"retransmits":53,"tcp-window-size":89776,"throughput-bits":20981485.983736776,"throughput-bytes":2621440}],"summary":{"end":19.000336,"start":18.000811,"omitted":false,"retransmits":53,"throughput-bits":20981485.983736776,"throughput-bytes":2621440}},{"streams":[{"end":20.001019,"rtt":18886,"start":19.000336,"omitted":false,"stream-id":5,"retransmits":64,"tcp-window-size":47784,"throughput-bits":0,"throughput-bytes":0}],"summary":{"end":20.001019,"start":19.000336,"omitted":false,"retransmits":64,"throughput-bits":0,"throughput-bytes":0}},{"streams":[{"end":21.001016,"rtt":28352,"start":20.001019,"omitted":false,"stream-id":5,"retransmits":2,"tcp-window-size":1448,"throughput-bits":0,"throughput-bytes":0}],"summary":{"end":21.001016,"start":20.001019,"omitted":false,"retransmits":2,"throughput-bits":0,"throughput-bytes":0}},{"streams":[{"end":22.001017,"rtt":33933,"start":21.001016,"omitted":false,"stream-id":5,"retransmits":2,"tcp-window-size":1448,"throughput-bits":0,"throughput-bytes":0}],"summary":{"end":22.001017,"start":21.001016,"omitted":false,"retransmits":2,"throughput-bits":0,"throughput-bytes":0}},{"streams":[{"end":23.001016,"rtt":144672,"start":22.001017,"omitted":false,"stream-id":5,"retransmits":5,"tcp-window-size":2896,"throughput-bits":0,"throughput-bytes":0}],"summary":{"end":23.001016,"start":22.001017,"omitted":false,"retransmits":5,"throughput-bits":0,"throughput-bytes":0}},{"streams":[{"end":24.001032,"rtt":144672,"start":23.001016,"omitted":false,"stream-id":5,"retransmits":0,"tcp-window-size":2896,"throughput-bits":0,"throughput-bytes":0}],"summary":{"end":24.001032,"start":23.001016,"omitted":false,"retransmits":0,"throughput-bits":0,"throughput-bytes":0}},{"streams":[{"end":25.001017,"rtt":152101,"start":24.001032,"omitted":false,"stream-id":5,"retransmits":5,"tcp-window-size":2896,"throughput-bits":0,"throughput-bytes":0}],"summary":{"end":25.001017,"start":24.001032,"omitted":false,"retransmits":5,"throughput-bits":0,"throughput-bytes":0}},{"streams":[{"end":26.001033,"rtt":125827,"start":25.001017,"omitted":false,"stream-id":5,"retransmits":3,"tcp-window-size":4344,"throughput-bits":0,"throughput-bytes":0}],"summary":{"end":26.001033,"start":25.001017,"omitted":false,"retransmits":3,"throughput-bits":0,"throughput-bytes":0}},{"streams":[{"end":27.001017,"rtt":226380,"start":26.001033,"omitted":false,"stream-id":5,"retransmits":13,"tcp-window-size":7240,"throughput-bits":0,"throughput-bytes":0}],"summary":{"end":27.001017,"start":26.001033,"omitted":false,"retransmits":13,"throughput-bits":0,"throughput-bytes":0}},{"streams":[{"end":28.001017,"rtt":226380,"start":27.001017,"omitted":false,"stream-id":5,"retransmits":0,"tcp-window-size":7240,"throughput-bits":0,"throughput-bytes":0}],"summary":{"end":28.001017,"start":27.001017,"omitted":false,"retransmits":0,"throughput-bits":0,"throughput-bytes":0}},{"streams":[{"end":29.001018,"rtt":226380,"start":28.001017,"omitted":false,"stream-id":5,"retransmits":0,"tcp-window-size":7240,"throughput-bits":0,"throughput-bytes":0}],"summary":{"end":29.001018,"start":28.001017,"omitted":false,"retransmits":0,"throughput-bits":0,"throughput-bytes":0}},{"streams":[{"end":30.001017,"rtt":206582,"start":29.001018,"omitted":false,"stream-id":5,"retransmits":3,"tcp-window-size":2896,"throughput-bits":0,"throughput-bytes":0}],"summary":{"end":30.001017,"start":29.001018,"omitted":false,"retransmits":3,"throughput-bits":0,"throughput-bytes":0}},{"streams":[{"end":31.001022,"rtt":206582,"start":30.001017,"omitted":false,"stream-id":5,"retransmits":0,"tcp-window-size":2896,"throughput-bits":0,"throughput-bytes":0}],"summary":{"end":31.001022,"start":30.001017,"omitted":false,"retransmits":0,"throughput-bits":0,"throughput-bytes":0}},{"streams":[{"end":32.001015,"rtt":206582,"start":31.001022,"omitted":false,"stream-id":5,"retransmits":0,"tcp-window-size":2896,"throughput-bits":0,"throughput-bytes":0}],"summary":{"end":32.001015,"start":31.001022,"omitted":false,"retransmits":0,"throughput-bits":0,"throughput-bytes":0}},{"streams":[{"end":33.001018,"rtt":206582,"start":32.001015,"omitted":false,"stream-id":5,"retransmits":0,"tcp-window-size":2896,"throughput-bits":0,"throughput-bytes":0}],"summary":{"end":33.001018,"start":32.001015,"omitted":false,"retransmits":0,"throughput-bits":0,"throughput-bytes":0}},{"streams":[{"end":34.001023,"rtt":206582,"start":33.001018,"omitted":false,"stream-id":5,"retransmits":1,"tcp-window-size":1448,"throughput-bits":0,"throughput-bytes":0}],"summary":{"end":34.001023,"start":33.001018,"omitted":false,"retransmits":1,"throughput-bits":0,"throughput-bytes":0}},{"streams":[{"end":35.001031,"rtt":206582,"start":34.001023,"omitted":false,"stream-id":5,"retransmits":0,"tcp-window-size":1448,"throughput-bits":0,"throughput-bytes":0}],"summary":{"end":35.001031,"start":34.001023,"omitted":false,"retransmits":0,"throughput-bits":0,"throughput-bytes":0}},{"streams":[{"end":36.001015,"rtt":206582,"start":35.001031,"omitted":false,"stream-id":5,"retransmits":0,"tcp-window-size":1448,"throughput-bits":0,"throughput-bytes":0}],"summary":{"end":36.001015,"start":35.001031,"omitted":false,"retransmits":0,"throughput-bits":0,"throughput-bytes":0}},{"streams":[{"end":37.001027,"rtt":206582,"start":36.001015,"omitted":false,"stream-id":5,"retransmits":0,"tcp-window-size":1448,"throughput-bits":0,"throughput-bytes":0}],"summary":{"end":37.001027,"start":36.001015,"omitted":false,"retransmits":0,"throughput-bits":0,"throughput-bytes":0}},{"streams":[{"end":38.001022,"rtt":206582,"start":37.001027,"omitted":false,"stream-id":5,"retransmits":0,"tcp-window-size":1448,"throughput-bits":0,"throughput-bytes":0}],"summary":{"end":38.001022,"start":37.001027,"omitted":false,"retransmits":0,"throughput-bits":0,"throughput-bytes":0}},{"streams":[{"end":39.001027,"rtt":206582,"start":38.001022,"omitted":false,"stream-id":5,"retransmits":0,"tcp-window-size":1448,"throughput-bits":0,"throughput-bytes":0}],"summary":{"end":39.001027,"start":38.001022,"omitted":false,"retransmits":0,"throughput-bits":0,"throughput-bytes":0}},{"streams":[{"end":40.001363,"rtt":117692,"start":39.001027,"omitted":false,"stream-id":5,"retransmits":9,"tcp-window-size":4344,"throughput-bits":0,"throughput-bytes":0}],"summary":{"end":40.001363,"start":39.001027,"omitted":false,"retransmits":9,"throughput-bits":0,"throughput-bytes":0}},{"streams":[{"end":41.001018,"rtt":99717,"start":40.001363,"omitted":false,"stream-id":5,"retransmits":3,"tcp-window-size":5792,"throughput-bits":0,"throughput-bytes":0}],"summary":{"end":41.001018,"start":40.001363,"omitted":false,"retransmits":3,"throughput-bits":0,"throughput-bytes":0}},{"streams":[{"end":42.001017,"rtt":99717,"start":41.001018,"omitted":false,"stream-id":5,"retransmits":0,"tcp-window-size":5792,"throughput-bits":0,"throughput-bytes":0}],"summary":{"end":42.001017,"start":41.001018,"omitted":false,"retransmits":0,"throughput-bits":0,"throughput-bytes":0}},{"streams":[{"end":43.001017,"rtt":99717,"start":42.001017,"omitted":false,"stream-id":5,"retransmits":0,"tcp-window-size":5792,"throughput-bits":0,"throughput-bytes":0}],"summary":{"end":43.001017,"start":42.001017,"omitted":false,"retransmits":0,"throughput-bits":0,"throughput-bytes":0}},{"streams":[{"end":44.001015,"rtt":99717,"start":43.001017,"omitted":false,"stream-id":5,"retransmits":1,"tcp-window-size":1448,"throughput-bits":0,"throughput-bytes":0}],"summary":{"end":44.001015,"start":43.001017,"omitted":false,"retransmits":1,"throughput-bits":0,"throughput-bytes":0}},{"streams":[{"end":45.001022,"rtt":99717,"start":44.001015,"omitted":false,"stream-id":5,"retransmits":0,"tcp-window-size":1448,"throughput-bits":0,"throughput-bytes":0}],"summary":{"end":45.001022,"start":44.001015,"omitted":false,"retransmits":0,"throughput-bits":0,"throughput-bytes":0}},{"streams":[{"end":46.00104,"rtt":99717,"start":45.001022,"omitted":false,"stream-id":5,"retransmits":0,"tcp-window-size":1448,"throughput-bits":0,"throughput-bytes":0}],"summary":{"end":46.00104,"start":45.001022,"omitted":false,"retransmits":0,"throughput-bits":0,"throughput-bytes":0}},{"streams":[{"end":47.001014,"rtt":99717,"start":46.00104,"omitted":false,"stream-id":5,"retransmits":0,"tcp-window-size":1448,"throughput-bits":0,"throughput-bytes":0}],"summary":{"end":47.001014,"start":46.00104,"omitted":false,"retransmits":0,"throughput-bits":0,"throughput-bytes":0}},{"streams":[{"end":48.001021,"rtt":99717,"start":47.001014,"omitted":false,"stream-id":5,"retransmits":0,"tcp-window-size":1448,"throughput-bits":0,"throughput-bytes":0}],"summary":{"end":48.001021,"start":47.001014,"omitted":false,"retransmits":0,"throughput-bits":0,"throughput-bytes":0}},{"streams":[{"end":49.001016,"rtt":99717,"start":48.001021,"omitted":false,"stream-id":5,"retransmits":0,"tcp-window-size":1448,"throughput-bits":0,"throughput-bytes":0}],"summary":{"end":49.001016,"start":48.001021,"omitted":false,"retransmits":0,"throughput-bits":0,"throughput-bytes":0}},{"streams":[{"end":50.000203,"rtt":20929,"start":49.001016,"omitted":false,"stream-id":5,"retransmits":14,"tcp-window-size":27512,"throughput-bits":10494291.936527146,"throughput-bytes":1310720}],"summary":{"end":50.000203,"start":49.001016,"omitted":false,"retransmits":14,"throughput-bits":10494291.936527146,"throughput-bytes":1310720}},{"streams":[{"end":51.001016,"rtt":21070,"start":50.000203,"omitted":false,"stream-id":5,"retransmits":2,"tcp-window-size":1448,"throughput-bits":0,"throughput-bytes":0}],"summary":{"end":51.001016,"start":50.000203,"omitted":false,"retransmits":2,"throughput-bits":0,"throughput-bytes":0}},{"streams":[{"end":52.00102,"rtt":21070,"start":51.001016,"omitted":false,"stream-id":5,"retransmits":1,"tcp-window-size":1448,"throughput-bits":0,"throughput-bytes":0}],"summary":{"end":52.00102,"start":51.001016,"omitted":false,"retransmits":1,"throughput-bits":0,"throughput-bytes":0}},{"streams":[{"end":53.001017,"rtt":21070,"start":52.00102,"omitted":false,"stream-id":5,"retransmits":0,"tcp-window-size":1448,"throughput-bits":0,"throughput-bytes":0}],"summary":{"end":53.001017,"start":52.00102,"omitted":false,"retransmits":0,"throughput-bits":0,"throughput-bytes":0}},{"streams":[{"end":54.001018,"rtt":29594,"start":53.001017,"omitted":false,"stream-id":5,"retransmits":22,"tcp-window-size":26064,"throughput-bits":0,"throughput-bytes":0}],"summary":{"end":54.001018,"start":53.001017,"omitted":false,"retransmits":22,"throughput-bits":0,"throughput-bytes":0}},{"streams":[{"end":55.0005,"rtt":29348,"start":54.001018,"omitted":false,"stream-id":5,"retransmits":0,"tcp-window-size":81088,"throughput-bits":10491194.690299833,"throughput-bytes":1310720}],"summary":{"end":55.0005,"start":54.001018,"omitted":false,"retransmits":0,"throughput-bits":10491194.690299833,"throughput-bytes":1310720}},{"streams":[{"end":56.000186,"rtt":22729,"start":55.0005,"omitted":false,"stream-id":5,"retransmits":61,"tcp-window-size":63712,"throughput-bits":20978107.068321463,"throughput-bytes":2621440}],"summary":{"end":56.000186,"start":55.0005,"omitted":false,"retransmits":61,"throughput-bits":20978107.068321463,"throughput-bytes":2621440}},{"streams":[{"end":57.000212,"rtt":38803,"start":56.000186,"omitted":false,"stream-id":5,"retransmits":0,"tcp-window-size":107152,"throughput-bits":20970975.014162887,"throughput-bytes":2621440}],"summary":{"end":57.000212,"start":56.000186,"omitted":false,"retransmits":0,"throughput-bits":20970975.014162887,"throughput-bytes":2621440}},{"streams":[{"end":58.000253,"rtt":50156,"start":57.000212,"omitted":false,"stream-id":5,"retransmits":0,"tcp-window-size":139008,"throughput-bits":20970660.03526543,"throughput-bytes":2621440}],"summary":{"end":58.000253,"start":57.000212,"omitted":false,"retransmits":0,"throughput-bits":20970660.03526543,"throughput-bytes":2621440}},{"streams":[{"end":59.000517,"rtt":36561,"start":58.000253,"omitted":false,"stream-id":5,"retransmits":28,"tcp-window-size":78192,"throughput-bits":10482991.980891505,"throughput-bytes":1310720}],"summary":{"end":59.000517,"start":58.000253,"omitted":false,"retransmits":28,"throughput-bits":10482991.980891505,"throughput-bytes":1310720}},{"streams":[{"end":60.001027,"rtt":36561,"start":59.000517,"omitted":false,"stream-id":5,"retransmits":2,"tcp-window-size":1448,"throughput-bits":0,"throughput-bytes":0}],"summary":{"end":60.001027,"start":59.000517,"omitted":false,"retransmits":2,"throughput-bits":0,"throughput-bytes":0}}],"succeeded":true}
