{"diags":"Participant 0:\n/usr/bin/iperf3 -p 5201 -B 172.16.0.2 -c 172.16.0.1 -t 60 --json --rsa-public-key-path /var/run/pscheduler-server/runner/tmp/tmpm0y_xudx/tmpqlayxlyb/public-key --username pRysZIAq2IDzQ1saYEXu\n\n{\n    \"end\": {\n        \"cpu_utilization_percent\": {\n            \"host_system\": 0.04516575958558182, \n            \"host_total\": 0.0568893897951972, \n            \"host_user\": 0.01172196633930462, \n            \"remote_system\": 1.2073772614081335, \n            \"remote_total\": 1.37201007280692, \n            \"remote_user\": 0.164651138922295\n        }, \n        \"receiver_tcp_congestion\": \"htcp\", \n        \"sender_tcp_congestion\": \"htcp\", \n        \"streams\": [\n            {\n                \"receiver\": {\n                    \"bits_per_second\": 6114758.114302792, \n                    \"bytes\": 45875200, \n                    \"end\": 60.018989, \n                    \"seconds\": 60.001028, \n                    \"sender\": true, \n                    \"socket\": 5, \n                    \"start\": 0\n                }, \n                \"sender\": {\n                    \"bits_per_second\": 6521873.325237027, \n                    \"bytes\": 48914888, \n                    \"end\": 60.001028, \n                    \"max_rtt\": 144273, \n                    \"max_snd_cwnd\": 402544, \n                    \"max_snd_wnd\": 0, \n                    \"mean_rtt\": 50231, \n                    \"min_rtt\": 18899, \n                    \"retransmits\": 879, \n                    \"seconds\": 60.001028, \n                    \"sender\": true, \n                    \"socket\": 5, \n                    \"start\": 0\n                }\n            }\n        ], \n        \"sum_received\": {\n            \"bits_per_second\": 6114758.114302792, \n            \"bytes\": 45875200, \n            \"end\": 60.018989, \n            \"seconds\": 60.018989, \n            \"sender\": true, \n            \"start\": 0\n        }, \n        \"sum_sent\": {\n            \"bits_per_second\": 6521873.325237027, \n            \"bytes\": 48914888, \n            \"end\": 60.001028, \n            \"retransmits\": 879, \n            \"seconds\": 60.001028, \n            \"sender\": true, \n            \"start\": 0\n        }\n    }, \n    \"intervals\": [\n        {\n            \"streams\": [\n                {\n                    \"bits_per_second\": 23796095.2610922, \n                    \"bytes\": 2977088, \n                    \"end\": 1.000866, \n                    \"omitted\": false, \n                    \"pmtu\": 1500, \n                    \"retransmits\": 1, \n                    \"rtt\": 93673, \n                    \"rttvar\": 2208, \n                    \"seconds\": 1.0008660554885864, \n                    \"sender\": true, \n                    \"snd_cwnd\": 1448, \n                    \"snd_wnd\": -1, \n                    \"socket\": 5, \n                    \"start\": 0\n                }\n            ], \n            \"sum\": {\n                \"bits_per_second\": 23796095.2610922, \n                \"bytes\": 2977088, \n                \"end\": 1.000866, \n                \"omitted\": false, \n                \"retransmits\": 1, \n                \"seconds\": 1.0008660554885864, \n                \"sender\": true, \n                \"start\": 0\n            }\n        }, \n        {\n            \"streams\": [\n                {\n                    \"bits_per_second\": 0, \n                    \"bytes\": 0, \n                    \"end\": 2.001057, \n                    \"omitted\": false, \n                    \"pmtu\": 1500, \n                    \"retransmits\": 1, \n                    \"rtt\": 93673, \n                    \"rttvar\": 2208, \n                    \"seconds\": 1.0001909732818604, \n                    \"sender\": true, \n                    \"snd_cwnd\": 1448, \n                    \"snd_wnd\": -1, \n                    \"socket\": 5, \n                    \"start\": 1.000866\n                }\n            ], \n            \"sum\": {\n                \"bits_per_second\": 0, \n                \"bytes\": 0, \n                \"end\": 2.001057, \n                \"omitted\": false, \n                \"retransmits\": 1, \n                \"seconds\": 1.0001909732818604, \n                \"sender\": true, \n                \"start\": 1.000866\n            }\n        }, \n        {\n            \"streams\": [\n                {\n                    \"bits_per_second\": 0, \n                    \"bytes\": 0, \n                    \"end\": 3.001053, \n                    \"omitted\": false, \n                    \"pmtu\": 1500, \n                    \"retransmits\": 1, \n                    \"rtt\": 93673, \n                    \"rttvar\": 2208, \n                    \"seconds\": 0.9999960064888, \n                    \"sender\": true, \n                    \"snd_cwnd\": 1448, \n                    \"snd_wnd\": -1, \n                    \"socket\": 5, \n                    \"start\": 2.001057\n                }\n            ], \n            \"sum\": {\n                \"bits_per_second\": 0, \n                \"bytes\": 0, \n                \"end\": 3.001053, \n                \"omitted\": false, \n                \"retransmits\": 1, \n                \"seconds\": 0.9999960064888, \n                \"sender\": true, \n                \"start\": 2.001057\n            }\n        }, \n        {\n            \"streams\": [\n                {\n                    \"bits_per_second\": 0, \n                    \"bytes\": 0, \n                    \"end\": 4.001052, \n                    \"omitted\": false, \n                    \"pmtu\": 1500, \n                    \"retransmits\": 0, \n                    \"rtt\": 93673, \n                    \"rttvar\": 2208, \n                    \"seconds\": 0.9999989867210388, \n                    \"sender\": true, \n                    \"snd_cwnd\": 1448, \n                    \"snd_wnd\": -1, \n                    \"socket\": 5, \n                    \"start\": 3.001053\n                }\n            ], \n            \"sum\": {\n                \"bits_per_second\": 0, \n                \"bytes\": 0, \n                \"end\": 4.001052, \n                \"omitted\": false, \n                \"retransmits\": 0, \n                \"seconds\": 0.9999989867210388, \n                \"sender\": true, \n                \"start\": 3.001053\n            }\n        }, \n        {\n            \"streams\": [\n                {\n                    \"bits_per_second\": 0, \n                    \"bytes\": 0, \n                    \"end\": 5.00105, \n                    \"omitted\": false, \n                    \"pmtu\": 1500, \n                    \"retransmits\": 0, \n                    \"rtt\": 93673, \n                    \"rttvar\": 2208, \n                    \"seconds\": 0.9999979734420776, \n                    \"sender\": true, \n                    \"snd_cwnd\": 1448, \n                    \"snd_wnd\": -1, \n                    \"socket\": 5, \n                    \"start\": 4.001052\n                }\n            ], \n            \"sum\": {\n                \"bits_per_second\": 0, \n                \"bytes\": 0, \n                \"end\": 5.00105, \n                \"omitted\": false, \n                \"retransmits\": 0, \n                \"seconds\": 0.9999979734420776, \n                \"sender\": true, \n                \"start\": 4.001052\n            }\n        }, \n        {\n            \"streams\": [\n                {\n                    \"bits_per_second\": 0, \n                    \"bytes\": 0, \n                    \"end\": 6.001061, \n                    \"omitted\": false, \n                    \"pmtu\": 1500, \n                    \"retransmits\": 34, \n                    \"rtt\": 31905, \n                    \"rttvar\": 11001, \n                    \"seconds\": 1.0000109672546387, \n                    \"sender\": true, \n                    \"snd_cwnd\": 1448, \n                    \"snd_wnd\": -1, \n                    \"socket\": 5, \n                    \"start\": 5.00105\n                }\n            ], \n            \"sum\": {\n                \"bits_per_second\": 0, \n                \"bytes\": 0, \n                \"end\": 6.001061, \n                \"omitted\": false, \n                \"retransmits\": 34, \n                \"seconds\": 1.0000109672546387, \n                \"sender\": true, \n                \"start\": 5.00105\n            }\n        }, \n        {\n            \"streams\": [\n                {\n                    \"bits_per_second\": 0, \n                    \"bytes\": 0, \n                    \"end\": 7.001053, \n                    \"omitted\": false, \n                    \"pmtu\": 1500, \n                    \"retransmits\": 1, \n                    \"rtt\": 31905, \n                    \"rttvar\": 11001, \n                    \"seconds\": 0.9999920129776, \n                    \"sender\": true, \n                    \"snd_cwnd\": 1448, \n                    \"snd_wnd\": -1, \n                    \"socket\": 5, \n                    \"start\": 6.001061\n                }\n            ], \n            \"sum\": {\n                \"bits_per_second\": 0, \n                \"bytes\": 0, \n                \"end\": 7.001053, \n                \"omitted\": false, \n                \"retransmits\": 1, \n                \"seconds\": 0.9999920129776, \n                \"sender\": true, \n                \"start\": 6.001061\n            }\n        }, \n        {\n            \"streams\": [\n                {\n                    \"bits_per_second\": 0, \n                    \"bytes\": 0, \n                    \"end\": 8.001021, \n                    \"omitted\": false, \n                    \"pmtu\": 1500, \n                    \"retransmits\": 1, \n                    \"rtt\": 31905, \n                    \"rttvar\": 11001, \n                    \"seconds\": 0.9999679923057556, \n                    \"sender\": true, \n                    \"snd_cwnd\": 1448, \n                    \"snd_wnd\": -1, \n                    \"socket\": 5, \n                    \"start\": 7.001053\n                }\n            ], \n            \"sum\": {\n                \"bits_per_second\": 0, \n                \"bytes\": 0, \n                \"end\": 8.001021, \n                \"omitted\": false, \n                \"retransmits\": 1, \n                \"seconds\": 0.9999679923057556, \n                \"sender\": true, \n                \"start\": 7.001053\n            }\n        }, \n        {\n            \"streams\": [\n                {\n                    \"bits_per_second\": 0, \n                    \"bytes\": 0, \n                    \"end\": 9.001024, \n                    \"omitted\": false, \n                    \"pmtu\": 1500, \n                    \"retransmits\": 3, \n                    \"rtt\": 31167, \n                    \"rttvar\": 9171, \n                    \"seconds\": 1.0000029802322388, \n                    \"sender\": true, \n                    \"snd_cwnd\": 2896, \n                    \"snd_wnd\": -1, \n                    \"socket\": 5, \n                    \"start\": 8.001021\n                }\n            ], \n            \"sum\": {\n                \"bits_per_second\": 0, \n                \"bytes\": 0, \n                \"end\": 9.001024, \n                \"omitted\": false, \n                \"retransmits\": 3, \n                \"seconds\": 1.0000029802322388, \n                \"sender\": true, \n                \"start\": 8.001021\n            }\n        }, \n        {\n            \"streams\": [\n                {\n                    \"bits_per_second\": 16695919.159899449, \n                    \"bytes\": 2085120, \n                    \"end\": 10.000128, \n                    \"omitted\": false, \n                    \"pmtu\": 1500, \n                    \"retransmits\": 343, \n                    \"rtt\": 24091, \n                    \"rttvar\": 442, \n                    \"seconds\": 0.9991040229797363, \n                    \"sender\": true, \n                    \"snd_cwnd\": 68056, \n                    \"snd_wnd\": -1, \n                    \"socket\": 5, \n                    \"start\": 9.001024\n                }\n            ], \n            \"sum\": {\n                \"bits_per_second\": 16695919.159899449, \n                \"bytes\": 2085120, \n                \"end\": 10.000128, \n                \"omitted\": false, \n                \"retransmits\": 343, \n                \"seconds\": 0.9991040229797363, \n                \"sender\": true, \n                \"start\": 9.001024\n            }\n        }, \n        {\n            \"streams\": [\n                {\n                    \"bits_per_second\": 0, \n                    \"bytes\": 0, \n                    \"end\": 11.001022, \n                    \"omitted\": false, \n                    \"pmtu\": 1500, \n                    \"retransmits\": 48, \n                    \"rtt\": 22926, \n                    \"rttvar\": 12420, \n                    \"seconds\": 1.0008939504623413, \n                    \"sender\": true, \n                    \"snd_cwnd\": 1448, \n                    \"snd_wnd\": -1, \n                    \"socket\": 5, \n                    \"start\": 10.000128\n                }\n            ], \n            \"sum\": {\n                \"bits_per_second\": 0, \n                \"bytes\": 0, \n                \"end\": 11.001022, \n                \"omitted\": false, \n                \"retransmits\": 48, \n                \"seconds\": 1.0008939504623413, \n                \"sender\": true, \n                \"start\": 10.000128\n            }\n        }, \n        {\n            \"streams\": [\n                {\n                    \"bits_per_second\": 0, \n                    \"bytes\": 0, \n                    \"end\": 12.001061, \n                    \"omitted\": false, \n                    \"pmtu\": 1500, \n                    \"retransmits\": 1, \n                    \"rtt\": 22926, \n                    \"rttvar\": 12420, \n                    \"seconds\": 1.000038981437683, \n                    \"sender\": true, \n                    \"snd_cwnd\": 1448, \n                    \"snd_wnd\": -1, \n                    \"socket\": 5, \n                    \"start\": 11.001022\n                }\n            ], \n            \"sum\": {\n                \"bits_per_second\": 0, \n                \"bytes\": 0, \n                \"end\": 12.001061, \n                \"omitted\": false, \n                \"retransmits\": 1, \n                \"seconds\": 1.000038981437683, \n                \"sender\": true, \n                \"start\": 11.001022\n            }\n        }, \n        {\n            \"streams\": [\n                {\n                    \"bits_per_second\": 0, \n                    \"bytes\": 0, \n                    \"end\": 13.00102, \n                    \"omitted\": false, \n                    \"pmtu\": 1500, \n                    \"retransmits\": 24, \n                    \"rtt\": 23568, \n                    \"rttvar\": 13142, \n                    \"seconds\": 0.9999589920043945, \n                    \"sender\": true, \n                    \"snd_cwnd\": 18824, \n                    \"snd_wnd\": -1, \n                    \"socket\": 5, \n                    \"start\": 12.001061\n                }\n            ], \n            \"sum\": {\n                \"bits_per_second\": 0, \n                \"bytes\": 0, \n                \"end\": 13.00102, \n                \"omitted\": false, \n                \"retransmits\": 24, \n                \"seconds\": 0.9999589920043945, \n                \"sender\": true, \n                \"start\": 12.001061\n            }\n        }, \n        {\n            \"streams\": [\n                {\n                    \"bits_per_second\": 0, \n                    \"bytes\": 0, \n                    \"end\": 14.001062, \n                    \"omitted\": false, \n                    \"pmtu\": 1500, \n                    \"retransmits\": 5, \n                    \"rtt\": 29868, \n                    \"rttvar\": 11692, \n                    \"seconds\": 1.0000419616699219, \n                    \"sender\": true, \n                    \"snd_cwnd\": 1448, \n                    \"snd_wnd\": -1, \n                    \"socket\": 5, \n                    \"start\": 13.00102\n                }\n            ], \n            \"sum\": {\n                \"bits_per_second\": 0, \n                \"bytes\": 0, \n                \"end\": 14.001062, \n                \"omitted\": false, \n                \"retransmits\": 5, \n                \"seconds\": 1.0000419616699219, \n                \"sender\": true, \n                \"start\": 13.00102\n            }\n        }, \n        {\n            \"streams\": [\n                {\n                    \"bits_per_second\": 0, \n                    \"bytes\": 0, \n                    \"end\": 15.001036, \n                    \"omitted\": false, \n                    \"pmtu\": 1500, \n                    \"retransmits\": 1, \n                    \"rtt\": 29868, \n                    \"rttvar\": 11692, \n                    \"seconds\": 0.999974012374878, \n                    \"sender\": true, \n                    \"snd_cwnd\": 1448, \n                    \"snd_wnd\": -1, \n                    \"socket\": 5, \n                    \"start\": 14.001062\n                }\n            ], \n            \"sum\": {\n                \"bits_per_second\": 0, \n                \"bytes\": 0, \n                \"end\": 15.001036, \n                \"omitted\": false, \n                \"retransmits\": 1, \n                \"seconds\": 0.999974012374878, \n                \"sender\": true, \n                \"start\": 14.001062\n            }\n        }, \n        {\n            \"streams\": [\n                {\n                    \"bits_per_second\": 8347851.012264233, \n                    \"bytes\": 1042560, \n                    \"end\": 16.000153, \n                    \"omitted\": false, \n                    \"pmtu\": 1500, \n                    \"retransmits\": 22, \n                    \"rtt\": 20185, \n                    \"rttvar\": 3979, \n                    \"seconds\": 0.9991170167922974, \n                    \"sender\": true, \n                    \"snd_cwnd\": 36200, \n                    \"snd_wnd\": -1, \n                    \"socket\": 5, \n                    \"start\": 15.001036\n                }\n            ], \n            \"sum\": {\n                \"bits_per_second\": 8347851.012264233, \n                \"bytes\": 1042560, \n                \"end\": 16.000153, \n                \"omitted\": false, \n                \"retransmits\": 22, \n                \"seconds\": 0.9991170167922974, \n                \"sender\": true, \n                \"start\": 15.001036\n            }\n        }, \n        {\n            \"streams\": [\n                {\n                    \"bits_per_second\": 0, \n                    \"bytes\": 0, \n                    \"end\": 17.001034, \n                    \"omitted\": false, \n                    \"pmtu\": 1500, \n                    \"retransmits\": 1, \n                    \"rtt\": 23151, \n                    \"rttvar\": 1130, \n                    \"seconds\": 1.00088095664978, \n                    \"sender\": true, \n                    \"snd_cwnd\": 1448, \n                    \"snd_wnd\": -1, \n                    \"socket\": 5, \n                    \"start\": 16.000153\n                }\n            ], \n            \"sum\": {\n                \"bits_per_second\": 0, \n                \"bytes\": 0, \n                \"end\": 17.001034, \n                \"omitted\": false, \n                \"retransmits\": 1, \n                \"seconds\": 1.00088095664978, \n                \"sender\": true, \n                \"start\": 16.000153\n            }\n        }, \n        {\n            \"streams\": [\n                {\n                    \"bits_per_second\": 0, \n                    \"bytes\": 0, \n                    \"end\": 18.001024, \n                    \"omitted\": false, \n                    \"pmtu\": 1500, \n                    \"retransmits\": 1, \n                    \"rtt\": 23151, \n                    \"rttvar\": 1130, \n                    \"seconds\": 0.9999899864196777, \n                    \"sender\": true, \n                    \"snd_cwnd\": 1448, \n                    \"snd_wnd\": -1, \n                    \"socket\": 5, \n                    \"start\": 17.001034\n                }\n            ], \n            \"sum\": {\n                \"bits_per_second\": 0, \n                \"bytes\": 0, \n                \"end\": 18.001024, \n                \"omitted\": false, \n                \"retransmits\": 1, \n                \"seconds\": 0.9999899864196777, \n                \"sender\": true, \n                \"start\": 17.001034\n            }\n        }, \n        {\n            \"streams\": [\n                {\n                    \"bits_per_second\": 0, \n                    \"bytes\": 0, \n                    \"end\": 19.001022, \n                    \"omitted\": false, \n                    \"pmtu\": 1500, \n                    \"retransmits\": 1, \n                    \"rtt\": 23151, \n                    \"rttvar\": 1130, \n                    \"seconds\": 0.9999979734420776, \n                    \"sender\": true, \n                    \"snd_cwnd\": 1448, \n                    \"snd_wnd\": -1, \n                    \"socket\": 5, \n                    \"start\": 18.001024\n                }\n            ], \n            \"sum\": {\n                \"bits_per_second\": 0, \n                \"bytes\": 0, \n                \"end\": 19.001022, \n                \"omitted\": false, \n                \"retransmits\": 1, \n                \"seconds\": 0.9999979734420776, \n                \"sender\": true, \n                \"start\": 18.001024\n            }\n        }, \n        {\n            \"streams\": [\n                {\n                    \"bits_per_second\": 0, \n                    \"bytes\": 0, \n                    \"end\": 20.001022, \n                    \"omitted\": false, \n                    \"pmtu\": 1500, \n                    \"retransmits\": 15, \n                    \"rtt\": 32991, \n                    \"rttvar\": 8957, \n                    \"seconds\": 1, \n                    \"sender\": true, \n                    \"snd_cwnd\": 11584, \n                    \"snd_wnd\": -1, \n                    \"socket\": 5, \n                    \"start\": 19.001022\n                }\n            ], \n            \"sum\": {\n                \"bits_per_second\": 0, \n                \"bytes\": 0, \n                \"end\": 20.001022, \n                \"omitted\": false, \n                \"retransmits\": 15, \n                \"seconds\": 1, \n                \"sender\": true, \n                \"start\": 19.001022\n            }\n        }, \n        {\n            \"streams\": [\n                {\n                    \"bits_per_second\": 25045332.554493826, \n                    \"bytes\": 3127680, \n                    \"end\": 21.000068, \n                    \"omitted\": false, \n                    \"pmtu\": 1500, \n                    \"retransmits\": 25, \n                    \"rtt\": 29765, \n                    \"rttvar\": 579, \n                    \"seconds\": 0.99904602766037, \n                    \"sender\": true, \n                    \"snd_cwnd\": 82536, \n                    \"snd_wnd\": -1, \n                    \"socket\": 5, \n                    \"start\": 20.001022\n                }\n            ], \n            \"sum\": {\n                \"bits_per_second\": 25045332.554493826, \n                \"bytes\": 3127680, \n                \"end\": 21.000068, \n                \"omitted\": false, \n                \"retransmits\": 25, \n                \"seconds\": 0.99904602766037, \n                \"sender\": true, \n                \"start\": 20.001022\n            }\n        }, \n        {\n            \"streams\": [\n                {\n                    \"bits_per_second\": 0, \n                    \"bytes\": 0, \n                    \"end\": 22.001022, \n                    \"omitted\": false, \n                    \"pmtu\": 1500, \n                    \"retransmits\": 2, \n                    \"rtt\": 29765, \n                    \"rttvar\": 579, \n                    \"seconds\": 1.000954031944275, \n                    \"sender\": true, \n                    \"snd_cwnd\": 1448, \n                    \"snd_wnd\": -1, \n                    \"socket\": 5, \n                    \"start\": 21.000068\n                }\n            ], \n            \"sum\": {\n                \"bits_per_second\": 0, \n                \"bytes\": 0, \n                \"end\": 22.001022, \n                \"omitted\": false, \n                \"retransmits\": 2, \n                \"seconds\": 1.000954031944275, \n                \"sender\": true, \n                \"start\": 21.000068\n            }\n        }, \n        {\n            \"streams\": [\n                {\n                    \"bits_per_second\": 0, \n                    \"bytes\": 0, \n                    \"end\": 23.00102, \n                    \"omitted\": false, \n                    \"pmtu\": 1500, \n                    \"retransmits\": 1, \n                    \"rtt\": 29765, \n                    \"rttvar\": 579, \n                    \"seconds\": 0.9999979734420776, \n                    \"sender\": true, \n                    \"snd_cwnd\": 1448, \n                    \"snd_wnd\": -1, \n                    \"socket\": 5, \n                    \"start\": 22.001022\n                }\n            ], \n            \"sum\": {\n                \"bits_per_second\": 0, \n                \"bytes\": 0, \n                \"end\": 23.00102, \n                \"omitted\": false, \n                \"retransmits\": 1, \n                \"seconds\": 0.9999979734420776, \n                \"sender\": true, \n                \"start\": 22.001022\n            }\n        }, \n        {\n            \"streams\": [\n                {\n                    \"bits_per_second\": 0, \n                    \"bytes\": 0, \n                    \"end\": 24.001023, \n                    \"omitted\": false, \n                    \"pmtu\": 1500, \n                    \"retransmits\": 0, \n                    \"rtt\": 29765, \n                    \"rttvar\": 579, \n                    \"seconds\": 1.0000029802322388, \n                    \"sender\": true, \n                    \"snd_cwnd\": 1448, \n                    \"snd_wnd\": -1, \n                    \"socket\": 5, \n                    \"start\": 23.00102\n                }\n            ], \n            \"sum\": {\n                \"bits_per_second\": 0, \n                \"bytes\": 0, \n                \"end\": 24.001023, \n                \"omitted\": false, \n                \"retransmits\": 0, \n                \"seconds\": 1.0000029802322388, \n                \"sender\": true, \n                \"start\": 23.00102\n            }\n        }, \n        {\n            \"streams\": [\n                {\n                    \"bits_per_second\": 0, \n                    \"bytes\": 0, \n                    \"end\": 25.001023, \n                    \"omitted\": false, \n                    \"pmtu\": 1500, \n                    \"retransmits\": 57, \n                    \"rtt\": 18899, \n                    \"rttvar\": 704, \n                    \"seconds\": 1, \n                    \"sender\": true, \n                    \"snd_cwnd\": 52128, \n                    \"snd_wnd\": -1, \n                    \"socket\": 5, \n                    \"start\": 24.001023\n                }\n            ], \n            \"sum\": {\n                \"bits_per_second\": 0, \n                \"bytes\": 0, \n                \"end\": 25.001023, \n                \"omitted\": false, \n                \"retransmits\": 57, \n                \"seconds\": 1, \n                \"sender\": true, \n                \"start\": 24.001023\n            }\n        }, \n        {\n            \"streams\": [\n                {\n                    \"bits_per_second\": 0, \n                    \"bytes\": 0, \n                    \"end\": 26.001025, \n                    \"omitted\": false, \n                    \"pmtu\": 1500, \n                    \"retransmits\": 2, \n                    \"rtt\": 20138, \n                    \"rttvar\": 555, \n                    \"seconds\": 1.0000020265579224, \n                    \"sender\": true, \n                    \"snd_cwnd\": 1448, \n                    \"snd_wnd\": -1, \n                    \"socket\": 5, \n                    \"start\": 25.001023\n                }\n            ], \n            \"sum\": {\n                \"bits_per_second\": 0, \n                \"bytes\": 0, \n                \"end\": 26.001025, \n                \"omitted\": false, \n                \"retransmits\": 2, \n                \"seconds\": 1.0000020265579224, \n                \"sender\": true, \n                \"start\": 25.001023\n            }\n        }, \n        {\n            \"streams\": [\n                {\n                    \"bits_per_second\": 0, \n                    \"bytes\": 0, \n                    \"end\": 27.001023, \n                    \"omitted\": false, \n                    \"pmtu\": 1500, \n                    \"retransmits\": 1, \n                    \"rtt\": 20138, \n                    \"rttvar\": 555, \n                    \"seconds\": 0.9999979734420776, \n                    \"sender\": true, \n                    \"snd_cwnd\": 1448, \n                    \"snd_wnd\": -1, \n                    \"socket\": 5, \n                    \"start\": 26.001025\n                }\n            ], \n            \"sum\": {\n                \"bits_per_second\": 0, \n                \"bytes\": 0, \n                \"end\": 27.001023, \n                \"omitted\": false, \n                \"retransmits\": 1, \n                \"seconds\": 0.9999979734420776, \n                \"sender\": true, \n                \"start\": 26.001025\n            }\n        }, \n        {\n            \"streams\": [\n                {\n                    \"bits_per_second\": 0, \n                    \"bytes\": 0, \n                    \"end\": 28.001032, \n                    \"omitted\": false, \n                    \"pmtu\": 1500, \n                    \"retransmits\": 0, \n                    \"rtt\": 20138, \n                    \"rttvar\": 555, \n                    \"seconds\": 1.0000089406967163, \n                    \"sender\": true, \n                    \"snd_cwnd\": 1448, \n                    \"snd_wnd\": -1, \n                    \"socket\": 5, \n                    \"start\": 27.001023\n                }\n            ], \n            \"sum\": {\n                \"bits_per_second\": 0, \n                \"bytes\": 0, \n                \"end\": 28.001032, \n                \"omitted\": false, \n                \"retransmits\": 0, \n                \"seconds\": 1.0000089406967163, \n                \"sender\": true, \n                \"start\": 27.001023\n            }\n        }, \n        {\n            \"streams\": [\n                {\n                    \"bits_per_second\": 0, \n                    \"bytes\": 0, \n                    \"end\": 29.001022, \n                    \"omitted\": false, \n                    \"pmtu\": 1500, \n                    \"retransmits\": 39, \n                    \"rtt\": 24383, \n                    \"rttvar\": 12797, \n                    \"seconds\": 0.9999899864196777, \n                    \"sender\": true, \n                    \"snd_cwnd\": 37648, \n                    \"snd_wnd\": -1, \n                    \"socket\": 5, \n                    \"start\": 28.001032\n                }\n            ], \n            \"sum\": {\n                \"bits_per_second\": 0, \n                \"bytes\": 0, \n                \"end\": 29.001022, \n                \"omitted\": false, \n                \"retransmits\": 39, \n                \"seconds\": 0.9999899864196777, \n                \"sender\": true, \n                \"start\": 28.001032\n            }\n        }, \n        {\n            \"streams\": [\n                {\n                    \"bits_per_second\": 0, \n                    \"bytes\": 0, \n                    \"end\": 30.001026, \n                    \"omitted\": false, \n                    \"pmtu\": 1500, \n                    \"retransmits\": 2, \n                    \"rtt\": 24383, \n                    \"rttvar\": 12797, \n                    \"seconds\": 1.0000040531158447, \n                    \"sender\": true, \n                    \"snd_cwnd\": 1448, \n                    \"snd_wnd\": -1, \n                    \"socket\": 5, \n                    \"start\": 29.001022\n                }\n            ], \n            \"sum\": {\n                \"bits_per_second\": 0, \n                \"bytes\": 0, \n                \"end\": 30.001026, \n                \"omitted\": false, \n                \"retransmits\": 2, \n                \"seconds\": 1.0000040531158447, \n                \"sender\": true, \n                \"start\": 29.001022\n            }\n        }, \n        {\n            \"streams\": [\n                {\n                    \"bits_per_second\": 0, \n                    \"bytes\": 0, \n                    \"end\": 31.001023, \n                    \"omitted\": false, \n                    \"pmtu\": 1500, \n                    \"retransmits\": 1, \n                    \"rtt\": 24383, \n                    \"rttvar\": 12797, \n                    \"seconds\": 0.9999970197677612, \n                    \"sender\": true, \n                    \"snd_cwnd\": 1448, \n                    \"snd_wnd\": -1, \n                    \"socket\": 5, \n                    \"start\": 30.001026\n                }\n            ], \n            \"sum\": {\n                \"bits_per_second\": 0, \n                \"bytes\": 0, \n                \"end\": 31.001023, \n                \"omitted\": false, \n                \"retransmits\": 1, \n                \"seconds\": 0.9999970197677612, \n                \"sender\": true, \n                \"start\": 30.001026\n            }\n        }, \n        {\n            \"streams\": [\n                {\n                    \"bits_per_second\": 0, \n                    \"bytes\": 0, \n                    \"end\": 32.001021, \n                    \"omitted\": false, \n                    \"pmtu\": 1500, \n                    \"retransmits\": 0, \n                    \"rtt\": 24383, \n                    \"rttvar\": 12797, \n                    \"seconds\": 0.9999979734420776, \n                    \"sender\": true, \n                    \"snd_cwnd\": 1448, \n                    \"snd_wnd\": -1, \n                    \"socket\": 5, \n                    \"start\": 31.001023\n                }\n            ], \n            \"sum\": {\n                \"bits_per_second\": 0, \n                \"bytes\": 0, \n                \"end\": 32.001021, \n                \"omitted\": false, \n                \"retransmits\": 0, \n                \"seconds\": 0.9999979734420776, \n                \"sender\": true, \n                \"start\": 31.001023\n            }\n        }, \n        {\n            \"streams\": [\n                {\n                    \"bits_per_second\": 8346464.28361819, \n                    \"bytes\": 1042560, \n                    \"end\": 33.000304, \n                    \"omitted\": false, \n                    \"pmtu\": 1500, \n                    \"retransmits\": 27, \n                    \"rtt\": 19454, \n                    \"rttvar\": 6031, \n                    \"seconds\": 0.9992830157279968, \n                    \"sender\": true, \n                    \"snd_cwnd\": 34752, \n                    \"snd_wnd\": -1, \n                    \"socket\": 5, \n                    \"start\": 32.001021\n                }\n            ], \n            \"sum\": {\n                \"bits_per_second\": 8346464.28361819, \n                \"bytes\": 1042560, \n                \"end\": 33.000304, \n                \"omitted\": false, \n                \"retransmits\": 27, \n                \"seconds\": 0.9992830157279968, \n                \"sender\": true, \n                \"start\": 32.001021\n            }\n        }, \n        {\n            \"streams\": [\n                {\n                    \"bits_per_second\": 8337336.332442818, \n                    \"bytes\": 1042560, \n                    \"end\": 34.000681, \n                    \"omitted\": false, \n                    \"pmtu\": 1500, \n                    \"retransmits\": 1, \n                    \"rtt\": 27508, \n                    \"rttvar\": 9794, \n                    \"seconds\": 1.0003770589828491, \n                    \"sender\": true, \n                    \"snd_cwnd\": 1448, \n                    \"snd_wnd\": -1, \n                    \"socket\": 5, \n                    \"start\": 33.000304\n                }\n            ], \n            \"sum\": {\n                \"bits_per_second\": 8337336.332442818, \n                \"bytes\": 1042560, \n                \"end\": 34.000681, \n                \"omitted\": false, \n                \"retransmits\": 1, \n                \"seconds\": 1.0003770589828491, \n                \"sender\": true, \n                \"start\": 33.000304\n            }\n        }, \n        {\n            \"streams\": [\n                {\n                    \"bits_per_second\": 0, \n                    \"bytes\": 0, \n                    \"end\": 35.001028, \n                    \"omitted\": false, \n                    \"pmtu\": 1500, \n                    \"retransmits\": 1, \n                    \"rtt\": 27508, \n                    \"rttvar\": 9794, \n                    \"seconds\": 1.0003470182418823, \n                    \"sender\": true, \n                    \"snd_cwnd\": 1448, \n                    \"snd_wnd\": -1, \n                    \"socket\": 5, \n                    \"start\": 34.000681\n                }\n            ], \n            \"sum\": {\n                \"bits_per_second\": 0, \n                \"bytes\": 0, \n                \"end\": 35.001028, \n                \"omitted\": false, \n                \"retransmits\": 1, \n                \"seconds\": 1.0003470182418823, \n                \"sender\": true, \n                \"start\": 34.000681\n            }\n        }, \n        {\n            \"streams\": [\n                {\n                    \"bits_per_second\": 0, \n                    \"bytes\": 0, \n                    \"end\": 36.001025, \n                    \"omitted\": false, \n                    \"pmtu\": 1500, \n                    \"retransmits\": 1, \n                    \"rtt\": 27508, \n                    \"rttvar\": 9794, \n                    \"seconds\": 0.9999970197677612, \n                    \"sender\": true, \n                    \"snd_cwnd\": 1448, \n                    \"snd_wnd\": -1, \n                    \"socket\": 5, \n                    \"start\": 35.001028\n                }\n            ], \n            \"sum\": {\n                \"bits_per_second\": 0, \n                \"bytes\": 0, \n                \"end\": 36.001025, \n                \"omitted\": false, \n                \"retransmits\": 1, \n                \"seconds\": 0.9999970197677612, \n                \"sender\": true, \n                \"start\": 35.001028\n            }\n        }, \n        {\n            \"streams\": [\n                {\n                    \"bits_per_second\": 0, \n                    \"bytes\": 0, \n                    \"end\": 37.001025, \n                    \"omitted\": false, \n                    \"pmtu\": 1500, \n                    \"retransmits\": 0, \n                    \"rtt\": 27508, \n                    \"rttvar\": 9794, \n                    \"seconds\": 1, \n                    \"sender\": true, \n                    \"snd_cwnd\": 1448, \n                    \"snd_wnd\": -1, \n                    \"socket\": 5, \n                    \"start\": 36.001025\n                }\n            ], \n            \"sum\": {\n                \"bits_per_second\": 0, \n                \"bytes\": 0, \n                \"end\": 37.001025, \n                \"omitted\": false, \n                \"retransmits\": 0, \n                \"seconds\": 1, \n                \"sender\": true, \n                \"start\": 36.001025\n            }\n        }, \n        {\n            \"streams\": [\n                {\n                    \"bits_per_second\": 0, \n                    \"bytes\": 0, \n                    \"end\": 38.001022, \n                    \"omitted\": false, \n                    \"pmtu\": 1500, \n                    \"retransmits\": 48, \n                    \"rtt\": 32065, \n                    \"rttvar\": 17260, \n                    \"seconds\": 0.9999970197677612, \n                    \"sender\": true, \n                    \"snd_cwnd\": 2896, \n                    \"snd_wnd\": -1, \n                    \"socket\": 5, \n                    \"start\": 37.001025\n                }\n            ], \n            \"sum\": {\n                \"bits_per_second\": 0, \n                \"bytes\": 0, \n                \"end\": 38.001022, \n                \"omitted\": false, \n                \"retransmits\": 48, \n                \"seconds\": 0.9999970197677612, \n                \"sender\": true, \n                \"start\": 37.001025\n            }\n        }, \n        {\n            \"streams\": [\n                {\n                    \"bits_per_second\": 16692243.560646849, \n                    \"bytes\": 2085120, \n                    \"end\": 39.000346, \n                    \"omitted\": false, \n                    \"pmtu\": 1500, \n                    \"retransmits\": 32, \n                    \"rtt\": 30268, \n                    \"rttvar\": 473, \n                    \"seconds\": 0.9993240237236023, \n                    \"sender\": true, \n                    \"snd_cwnd\": 75296, \n                    \"snd_wnd\": -1, \n                    \"socket\": 5, \n                    \"start\": 38.001022\n                }\n            ], \n            \"sum\": {\n                \"bits_per_second\": 16692243.560646849, \n                \"bytes\": 2085120, \n                \"end\": 39.000346, \n                \"omitted\": false, \n                \"retransmits\": 32, \n                \"seconds\": 0.9993240237236023, \n                \"sender\": true, \n                \"start\": 38.001022\n            }\n        }, \n        {\n            \"streams\": [\n                {\n                    \"bits_per_second\": 25027421.919878643, \n                    \"bytes\": 3127680, \n                    \"end\": 40.000107, \n                    \"omitted\": false, \n                    \"pmtu\": 1500, \n                    \"retransmits\": 0, \n                    \"rtt\": 41641, \n                    \"rttvar\": 577, \n                    \"seconds\": 0.9997609853744507, \n                    \"sender\": true, \n                    \"snd_cwnd\": 114392, \n                    \"snd_wnd\": -1, \n                    \"socket\": 5, \n                    \"start\": 39.000346\n                }\n            ], \n            \"sum\": {\n                \"bits_per_second\": 25027421.919878643, \n                \"bytes\": 3127680, \n                \"end\": 40.000107, \n                \"omitted\": false, \n                \"retransmits\": 0, \n                \"seconds\": 0.9997609853744507, \n                \"sender\": true, \n                \"start\": 39.000346\n            }\n        }, \n        {\n            \"streams\": [\n                {\n                    \"bits_per_second\": 16677041.537143027, \n                    \"bytes\": 2085120, \n                    \"end\": 41.000342, \n                    \"omitted\": false, \n                    \"pmtu\": 1500, \n                    \"retransmits\": 0, \n                    \"rtt\": 54772, \n                    \"rttvar\": 638, \n                    \"seconds\": 1.0002349615097046, \n                    \"sender\": true, \n                    \"snd_cwnd\": 152040, \n                    \"snd_wnd\": -1, \n                    \"socket\": 5, \n                    \"start\": 40.000107\n                }\n            ], \n            \"sum\": {\n                \"bits_per_second\": 16677041.537143027, \n                \"bytes\": 2085120, \n                \"end\": 41.000342, \n                \"omitted\": false, \n                \"retransmits\": 0, \n                \"seconds\": 1.0002349615097046, \n                \"sender\": true, \n                \"start\": 40.000107\n            }\n        }, \n        {\n            \"streams\": [\n                {\n                    \"bits_per_second\": 25025694.178988844, \n                    \"bytes\": 3127680, \n                    \"end\": 42.000172, \n                    \"omitted\": false, \n                    \"pmtu\": 1500, \n                    \"retransmits\": 0, \n                    \"rtt\": 74099, \n                    \"rttvar\": 987, \n                    \"seconds\": 0.9998300075531006, \n                    \"sender\": true, \n                    \"snd_cwnd\": 205616, \n                    \"snd_wnd\": -1, \n                    \"socket\": 5, \n                    \"start\": 41.000342\n                }\n            ], \n            \"sum\": {\n                \"bits_per_second\": 25025694.178988844, \n                \"bytes\": 3127680, \n                \"end\": 42.000172, \n                \"omitted\": false, \n                \"retransmits\": 0, \n                \"seconds\": 0.9998300075531006, \n                \"sender\": true, \n                \"start\": 41.000342\n            }\n        }, \n        {\n            \"streams\": [\n                {\n                    \"bits_per_second\": 16677224.397544505, \n                    \"bytes\": 2085120, \n                    \"end\": 43.000396, \n                    \"omitted\": false, \n                    \"pmtu\": 1500, \n                    \"retransmits\": 0, \n                    \"rtt\": 95761, \n                    \"rttvar\": 543, \n                    \"seconds\": 1.000223994255066, \n                    \"sender\": true, \n                    \"snd_cwnd\": 266432, \n                    \"snd_wnd\": -1, \n                    \"socket\": 5, \n                    \"start\": 42.000172\n                }\n            ], \n            \"sum\": {\n                \"bits_per_second\": 16677224.397544505, \n                \"bytes\": 2085120, \n                \"end\": 43.000396, \n                \"omitted\": false, \n                \"retransmits\": 0, \n                \"seconds\": 1.000223994255066, \n                \"sender\": true, \n                \"start\": 42.000172\n            }\n        }, \n        {\n            \"streams\": [\n                {\n                    \"bits_per_second\": 25025519.62776315, \n                    \"bytes\": 3127680, \n                    \"end\": 44.000233, \n                    \"omitted\": false, \n                    \"pmtu\": 1500, \n                    \"retransmits\": 0, \n                    \"rtt\": 119202, \n                    \"rttvar\": 670, \n                    \"seconds\": 0.9998369812965393, \n                    \"sender\": true, \n                    \"snd_cwnd\": 333040, \n                    \"snd_wnd\": -1, \n                    \"socket\": 5, \n                    \"start\": 43.000396\n                }\n            ], \n            \"sum\": {\n                \"bits_per_second\": 25025519.62776315, \n                \"bytes\": 3127680, \n                \"end\": 44.000233, \n                \"omitted\": false, \n                \"retransmits\": 0, \n                \"seconds\": 0.9998369812965393, \n                \"sender\": true, \n                \"start\": 43.000396\n            }\n        }, \n        {\n            \"streams\": [\n                {\n                    \"bits_per_second\": 25025543.49787251, \n                    \"bytes\": 3127680, \n                    \"end\": 45.000069, \n                    \"omitted\": false, \n                    \"pmtu\": 1500, \n                    \"retransmits\": 0, \n                    \"rtt\": 144273, \n                    \"rttvar\": 470, \n                    \"seconds\": 0.999836027622223, \n                    \"sender\": true, \n                    \"snd_cwnd\": 402544, \n                    \"snd_wnd\": -1, \n                    \"socket\": 5, \n                    \"start\": 44.000233\n                }\n            ], \n            \"sum\": {\n                \"bits_per_second\": 25025543.49787251, \n                \"bytes\": 3127680, \n                \"end\": 45.000069, \n                \"omitted\": false, \n                \"retransmits\": 0, \n                \"seconds\": 0.999836027622223, \n                \"sender\": true, \n                \"start\": 44.000233\n            }\n        }, \n        {\n            \"streams\": [\n                {\n                    \"bits_per_second\": 16679641.711857919, \n                    \"bytes\": 2085120, \n                    \"end\": 46.000148, \n                    \"omitted\": false, \n                    \"pmtu\": 1500, \n                    \"retransmits\": 68, \n                    \"rtt\": 78334, \n                    \"rttvar\": 498, \n                    \"seconds\": 1.0000790357589722, \n                    \"sender\": true, \n                    \"snd_cwnd\": 214304, \n                    \"snd_wnd\": -1, \n                    \"socket\": 5, \n                    \"start\": 45.000069\n                }\n            ], \n            \"sum\": {\n                \"bits_per_second\": 16679641.711857919, \n                \"bytes\": 2085120, \n                \"end\": 46.000148, \n                \"omitted\": false, \n                \"retransmits\": 68, \n                \"seconds\": 1.0000790357589722, \n                \"sender\": true, \n                \"start\": 45.000069\n            }\n        }, \n        {\n            \"streams\": [\n                {\n                    \"bits_per_second\": 16677156.818233337, \n                    \"bytes\": 2085120, \n                    \"end\": 47.000376, \n                    \"omitted\": false, \n                    \"pmtu\": 1500, \n                    \"retransmits\": 0, \n                    \"rtt\": 84819, \n                    \"rttvar\": 651, \n                    \"seconds\": 1.0002280473709106, \n                    \"sender\": true, \n                    \"snd_cwnd\": 231680, \n                    \"snd_wnd\": -1, \n                    \"socket\": 5, \n                    \"start\": 46.000148\n                }\n            ], \n            \"sum\": {\n                \"bits_per_second\": 16677156.818233337, \n                \"bytes\": 2085120, \n                \"end\": 47.000376, \n                \"omitted\": false, \n                \"retransmits\": 0, \n                \"seconds\": 1.0002280473709106, \n                \"sender\": true, \n                \"start\": 46.000148\n            }\n        }, \n        {\n            \"streams\": [\n                {\n                    \"bits_per_second\": 25025318.22552838, \n                    \"bytes\": 3127680, \n                    \"end\": 48.000221, \n                    \"omitted\": false, \n                    \"pmtu\": 1500, \n                    \"retransmits\": 0, \n                    \"rtt\": 90984, \n                    \"rttvar\": 589, \n                    \"seconds\": 0.999845027923584, \n                    \"sender\": true, \n                    \"snd_cwnd\": 247608, \n                    \"snd_wnd\": -1, \n                    \"socket\": 5, \n                    \"start\": 47.000376\n                }\n            ], \n            \"sum\": {\n                \"bits_per_second\": 25025318.22552838, \n                \"bytes\": 3127680, \n                \"end\": 48.000221, \n                \"omitted\": false, \n                \"retransmits\": 0, \n                \"seconds\": 0.999845027923584, \n                \"sender\": true, \n                \"start\": 47.000376\n            }\n        }, \n        {\n            \"streams\": [\n                {\n                    \"bits_per_second\": 25025243.632930756, \n                    \"bytes\": 3127680, \n                    \"end\": 49.000069, \n                    \"omitted\": false, \n                    \"pmtu\": 1500, \n                    \"retransmits\": 0, \n                    \"rtt\": 101884, \n                    \"rttvar\": 181, \n                    \"seconds\": 0.9998480081558228, \n                    \"sender\": true, \n                    \"snd_cwnd\": 280912, \n                    \"snd_wnd\": -1, \n                    \"socket\": 5, \n                    \"start\": 48.000221\n                }\n            ], \n            \"sum\": {\n                \"bits_per_second\": 25025243.632930756, \n                \"bytes\": 3127680, \n                \"end\": 49.000069, \n                \"omitted\": false, \n                \"retransmits\": 0, \n                \"seconds\": 0.9998480081558228, \n                \"sender\": true, \n                \"start\": 48.000221\n            }\n        }, \n        {\n            \"streams\": [\n                {\n                    \"bits_per_second\": 16677341.668825475, \n                    \"bytes\": 2085120, \n                    \"end\": 50.000286, \n                    \"omitted\": false, \n                    \"pmtu\": 1500, \n                    \"retransmits\": 0, \n                    \"rtt\": 117381, \n                    \"rttvar\": 659, \n                    \"seconds\": 1.0002169609069824, \n                    \"sender\": true, \n                    \"snd_cwnd\": 324352, \n                    \"snd_wnd\": -1, \n                    \"socket\": 5, \n                    \"start\": 49.000069\n                }\n            ], \n            \"sum\": {\n                \"bits_per_second\": 16677341.668825475, \n                \"bytes\": 2085120, \n                \"end\": 50.000286, \n                \"omitted\": false, \n                \"retransmits\": 0, \n                \"seconds\": 1.0002169609069824, \n                \"sender\": true, \n                \"start\": 49.000069\n            }\n        }, \n        {\n            \"streams\": [\n                {\n                    \"bits_per_second\": 25025543.49787251, \n                    \"bytes\": 3127680, \n                    \"end\": 51.000122, \n                    \"omitted\": false, \n                    \"pmtu\": 1500, \n                    \"retransmits\": 0, \n                    \"rtt\": 135842, \n                    \"rttvar\": 765, \n                    \"seconds\": 0.999836027622223, \n                    \"sender\": true, \n                    \"snd_cwnd\": 376480, \n                    \"snd_wnd\": -1, \n                    \"socket\": 5, \n                    \"start\": 50.000286\n                }\n            ], \n            \"sum\": {\n                \"bits_per_second\": 25025543.49787251, \n                \"bytes\": 3127680, \n                \"end\": 51.000122, \n                \"omitted\": false, \n                \"retransmits\": 0, \n                \"seconds\": 0.999836027622223, \n                \"sender\": true, \n                \"start\": 50.000286\n            }\n        }, \n        {\n            \"streams\": [\n                {\n                    \"bits_per_second\": 17199023.1054625, \n                    \"bytes\": 2150280, \n                    \"end\": 52.000309, \n                    \"omitted\": false, \n                    \"pmtu\": 1500, \n                    \"retransmits\": 7, \n                    \"rtt\": 76383, \n                    \"rttvar\": 641, \n                    \"seconds\": 1.0001870393753052, \n                    \"sender\": true, \n                    \"snd_cwnd\": 208512, \n                    \"snd_wnd\": -1, \n                    \"socket\": 5, \n                    \"start\": 51.000122\n                }\n            ], \n            \"sum\": {\n                \"bits_per_second\": 17199023.1054625, \n                \"bytes\": 2150280, \n                \"end\": 52.000309, \n                \"omitted\": false, \n                \"retransmits\": 7, \n                \"seconds\": 1.0001870393753052, \n                \"sender\": true, \n                \"start\": 51.000122\n            }\n        }, \n        {\n            \"streams\": [\n                {\n                    \"bits_per_second\": 8334953.575140842, \n                    \"bytes\": 1042560, \n                    \"end\": 53.000972, \n                    \"omitted\": false, \n                    \"pmtu\": 1500, \n                    \"retransmits\": 1, \n                    \"rtt\": 76453, \n                    \"rttvar\": 998, \n                    \"seconds\": 1.0006630420684814, \n                    \"sender\": true, \n                    \"snd_cwnd\": 1448, \n                    \"snd_wnd\": -1, \n                    \"socket\": 5, \n                    \"start\": 52.000309\n                }\n            ], \n            \"sum\": {\n                \"bits_per_second\": 8334953.575140842, \n                \"bytes\": 1042560, \n                \"end\": 53.000972, \n                \"omitted\": false, \n                \"retransmits\": 1, \n                \"seconds\": 1.0006630420684814, \n                \"sender\": true, \n                \"start\": 52.000309\n            }\n        }, \n        {\n            \"streams\": [\n                {\n                    \"bits_per_second\": 0, \n                    \"bytes\": 0, \n                    \"end\": 54.00103, \n                    \"omitted\": false, \n                    \"pmtu\": 1500, \n                    \"retransmits\": 1, \n                    \"rtt\": 76453, \n                    \"rttvar\": 998, \n                    \"seconds\": 1.0000580549240112, \n                    \"sender\": true, \n                    \"snd_cwnd\": 1448, \n                    \"snd_wnd\": -1, \n                    \"socket\": 5, \n                    \"start\": 53.000972\n                }\n            ], \n            \"sum\": {\n                \"bits_per_second\": 0, \n                \"bytes\": 0, \n                \"end\": 54.00103, \n                \"omitted\": false, \n                \"retransmits\": 1, \n                \"seconds\": 1.0000580549240112, \n                \"sender\": true, \n                \"start\": 53.000972\n            }\n        }, \n        {\n            \"streams\": [\n                {\n                    \"bits_per_second\": 0, \n                    \"bytes\": 0, \n                    \"end\": 55.001022, \n                    \"omitted\": false, \n                    \"pmtu\": 1500, \n                    \"retransmits\": 1, \n                    \"rtt\": 76453, \n                    \"rttvar\": 998, \n                    \"seconds\": 0.9999920129776, \n                    \"sender\": true, \n                    \"snd_cwnd\": 1448, \n                    \"snd_wnd\": -1, \n                    \"socket\": 5, \n                    \"start\": 54.00103\n                }\n            ], \n            \"sum\": {\n                \"bits_per_second\": 0, \n                \"bytes\": 0, \n                \"end\": 55.001022, \n                \"omitted\": false, \n                \"retransmits\": 1, \n                \"seconds\": 0.9999920129776, \n                \"sender\": true, \n                \"start\": 54.00103\n            }\n        }, \n        {\n            \"streams\": [\n                {\n                    \"bits_per_second\": 0, \n                    \"bytes\": 0, \n                    \"end\": 56.001027, \n                    \"omitted\": false, \n                    \"pmtu\": 1500, \n                    \"retransmits\": 0, \n                    \"rtt\": 76453, \n                    \"rttvar\": 998, \n                    \"seconds\": 1.0000050067901611, \n                    \"sender\": true, \n                    \"snd_cwnd\": 1448, \n                    \"snd_wnd\": -1, \n                    \"socket\": 5, \n                    \"start\": 55.001022\n                }\n            ], \n            \"sum\": {\n                \"bits_per_second\": 0, \n                \"bytes\": 0, \n                \"end\": 56.001027, \n                \"omitted\": false, \n                \"retransmits\": 0, \n                \"seconds\": 1.0000050067901611, \n                \"sender\": true, \n                \"start\": 55.001022\n            }\n        }, \n        {\n            \"streams\": [\n                {\n                    \"bits_per_second\": 0, \n                    \"bytes\": 0, \n                    \"end\": 57.001022, \n                    \"omitted\": false, \n                    \"pmtu\": 1500, \n                    \"retransmits\": 54, \n                    \"rtt\": 33470, \n                    \"rttvar\": 3023, \n                    \"seconds\": 0.999994993209839, \n                    \"sender\": true, \n                    \"snd_cwnd\": 40544, \n                    \"snd_wnd\": -1, \n                    \"socket\": 5, \n                    \"start\": 56.001027\n                }\n            ], \n            \"sum\": {\n                \"bits_per_second\": 0, \n                \"bytes\": 0, \n                \"end\": 57.001022, \n                \"omitted\": false, \n                \"retransmits\": 54, \n                \"seconds\": 0.999994993209839, \n                \"sender\": true, \n                \"start\": 56.001027\n            }\n        }, \n        {\n            \"streams\": [\n                {\n                    \"bits_per_second\": 0, \n                    \"bytes\": 0, \n                    \"end\": 58.001023, \n                    \"omitted\": false, \n                    \"pmtu\": 1500, \n                    \"retransmits\": 2, \n                    \"rtt\": 33470, \n                    \"rttvar\": 3023, \n                    \"seconds\": 1.0000009536743164, \n                    \"sender\": true, \n                    \"snd_cwnd\": 1448, \n                    \"snd_wnd\": -1, \n                    \"socket\": 5, \n                    \"start\": 57.001022\n                }\n            ], \n            \"sum\": {\n                \"bits_per_second\": 0, \n                \"bytes\": 0, \n                \"end\": 58.001023, \n                \"omitted\": false, \n                \"retransmits\": 2, \n                \"seconds\": 1.0000009536743164, \n                \"sender\": true, \n                \"start\": 57.001022\n            }\n        }, \n        {\n            \"streams\": [\n                {\n                    \"bits_per_second\": 0, \n                    \"bytes\": 0, \n                    \"end\": 59.001022, \n                    \"omitted\": false, \n                    \"pmtu\": 1500, \n                    \"retransmits\": 1, \n                    \"rtt\": 33470, \n                    \"rttvar\": 3023, \n                    \"seconds\": 0.9999989867210388, \n                    \"sender\": true, \n                    \"snd_cwnd\": 1448, \n                    \"snd_wnd\": -1, \n                    \"socket\": 5, \n                    \"start\": 58.001023\n                }\n            ], \n            \"sum\": {\n                \"bits_per_second\": 0, \n                \"bytes\": 0, \n                \"end\": 59.001022, \n                \"omitted\": false, \n                \"retransmits\": 1, \n                \"seconds\": 0.9999989867210388, \n                \"sender\": true, \n                \"start\": 58.001023\n            }\n        }, \n        {\n            \"streams\": [\n                {\n                    \"bits_per_second\": 0, \n                    \"bytes\": 0, \n                    \"end\": 60.001028, \n                    \"omitted\": false, \n                    \"pmtu\": 1500, \n                    \"retransmits\": 0, \n                    \"rtt\": 33470, \n                    \"rttvar\": 3023, \n                    \"seconds\": 1.0000059604644775, \n                    \"sender\": true, \n                    \"snd_cwnd\": 1448, \n                    \"snd_wnd\": -1, \n                    \"socket\": 5, \n                    \"start\": 59.001022\n                }\n            ], \n            \"sum\": {\n                \"bits_per_second\": 0, \n                \"bytes\": 0, \n                \"end\": 60.001028, \n                \"omitted\": false, \n                \"retransmits\": 0, \n                \"seconds\": 1.0000059604644775, \n                \"sender\": true, \n                \"start\": 59.001022\n            }\n        }\n    ], \n    \"start\": {\n        \"connected\": [\n            {\n                \"local_host\": \"172.16.0.2\", \n                \"local_port\": 49269, \n                \"remote_host\": \"172.16.0.1\", \n                \"remote_port\": 5201, \n                \"socket\": 5\n            }\n        ], \n        \"connecting_to\": {\n            \"host\": \"172.16.0.1\", \n            \"port\": 5201\n        }, \n        \"cookie\": \"h3mvjqjtfbnishq2cil4feo6hmncfnmt7id6\", \n        \"fq_rate\": 0, \n        \"rcvbuf_actual\": 87380, \n        \"sndbuf_actual\": 65536, \n        \"sock_bufsize\": 0, \n        \"system_info\": \"REDACTED\", \n        \"target_bitrate\": 0, \n        \"tcp_mss_default\": 1448, \n        \"test_start\": {\n            \"bidir\": 0, \n            \"blksize\": 131072, \n            \"blocks\": 0, \n            \"bytes\": 0, \n            \"duration\": 60, \n            \"fqrate\": 0, \n            \"num_streams\": 1, \n            \"omit\": 0, \n            \"protocol\": \"TCP\", \n            \"reverse\": 0, \n            \"target_bitrate\": 0, \n            \"tos\": 0\n        }, \n        \"timestamp\": {\n            \"time\": \"Sun, 20 Oct 2024 17:40:26 GMT\", \n            \"timesecs\": 1729446026\n        }, \n        \"version\": \"iperf 3.14\"\n    }\n}\nParticipant 1:\n/usr/bin/iperf3 --use-pkcs1-padding -s -1 --idle-timeout 60 --json -p 5201 -B 172.16.0.1 --authorized-users-path /var/pscheduler-server/runner/tmp/tmpdze9l1sh/tmpgdkald9j/credentials --rsa-private-key-path /var/pscheduler-server/runner/tmp/tmpdze9l1sh/tmpgdkald9j/private-key\n\n{\n    \"end\": {\n        \"cpu_utilization_percent\": {\n            \"host_system\": 1.2073772614081335, \n            \"host_total\": 1.37201007280692, \n            \"host_user\": 0.164651138922295, \n            \"remote_system\": 0, \n            \"remote_total\": 0, \n            \"remote_user\": 0\n        }, \n        \"receiver_tcp_congestion\": \"htcp\", \n        \"streams\": [\n            {\n                \"receiver\": {\n                    \"bits_per_second\": 6114758.114302792, \n                    \"bytes\": 45875200, \n                    \"end\": 60.018989, \n                    \"seconds\": 60.018989, \n                    \"sender\": false, \n                    \"socket\": 5, \n                    \"start\": 0\n                }, \n                \"sender\": {\n                    \"bits_per_second\": 0, \n                    \"bytes\": 0, \n                    \"end\": 60.018989, \n                    \"seconds\": 60.018989, \n                    \"sender\": false, \n                    \"socket\": 5, \n                    \"start\": 0\n                }\n            }\n        ], \n        \"sum_received\": {\n            \"bits_per_second\": 6114758.114302792, \n            \"bytes\": 45875200, \n            \"end\": 60.018989, \n            \"seconds\": 60.018989, \n            \"sender\": false, \n            \"start\": 0\n        }, \n        \"sum_sent\": {\n            \"bits_per_second\": 0, \n            \"bytes\": 0, \n            \"end\": 60.018989, \n            \"seconds\": 60.018989, \n            \"sender\": false, \n            \"start\": 0\n        }\n    }, \n    \"intervals\": [\n        {\n            \"streams\": [\n                {\n                    \"bits_per_second\": 3142183.7477687136, \n                    \"bytes\": 393216, \n                    \"end\": 1.001128, \n                    \"omitted\": false, \n                    \"seconds\": 1.0011279582977295, \n                    \"sender\": false, \n                    \"socket\": 5, \n                    \"start\": 0\n                }\n            ], \n            \"sum\": {\n                \"bits_per_second\": 3142183.7477687136, \n                \"bytes\": 393216, \n                \"end\": 1.001128, \n                \"omitted\": false, \n                \"seconds\": 1.0011279582977295, \n                \"sender\": false, \n                \"start\": 0\n            }\n        }, \n        {\n            \"streams\": [\n                {\n                    \"bits_per_second\": 0, \n                    \"bytes\": 0, \n                    \"end\": 2.001108, \n                    \"omitted\": false, \n                    \"seconds\": 0.9999799728393555, \n                    \"sender\": false, \n                    \"socket\": 5, \n                    \"start\": 1.001128\n                }\n            ], \n            \"sum\": {\n                \"bits_per_second\": 0, \n                \"bytes\": 0, \n                \"end\": 2.001108, \n                \"omitted\": false, \n                \"seconds\": 0.9999799728393555, \n                \"sender\": false, \n                \"start\": 1.001128\n            }\n        }, \n        {\n            \"streams\": [\n                {\n                    \"bits_per_second\": 0, \n                    \"bytes\": 0, \n                    \"end\": 3.001118, \n                    \"omitted\": false, \n                    \"seconds\": 1.0000100135803223, \n                    \"sender\": false, \n                    \"socket\": 5, \n                    \"start\": 2.001108\n                }\n            ], \n            \"sum\": {\n                \"bits_per_second\": 0, \n                \"bytes\": 0, \n                \"end\": 3.001118, \n                \"omitted\": false, \n                \"seconds\": 1.0000100135803223, \n                \"sender\": false, \n                \"start\": 2.001108\n            }\n        }, \n        {\n            \"streams\": [\n                {\n                    \"bits_per_second\": 0, \n                    \"bytes\": 0, \n                    \"end\": 4.001118, \n                    \"omitted\": false, \n                    \"seconds\": 1, \n                    \"sender\": false, \n                    \"socket\": 5, \n                    \"start\": 3.001118\n                }\n            ], \n            \"sum\": {\n                \"bits_per_second\": 0, \n                \"bytes\": 0, \n                \"end\": 4.001118, \n                \"omitted\": false, \n                \"seconds\": 1, \n                \"sender\": false, \n                \"start\": 3.001118\n            }\n        }, \n        {\n            \"streams\": [\n                {\n                    \"bits_per_second\": 0, \n                    \"bytes\": 0, \n                    \"end\": 5.001108, \n                    \"omitted\": false, \n                    \"seconds\": 0.9999899864196777, \n                    \"sender\": false, \n                    \"socket\": 5, \n                    \"start\": 4.001118\n                }\n            ], \n            \"sum\": {\n                \"bits_per_second\": 0, \n                \"bytes\": 0, \n                \"end\": 5.001108, \n                \"omitted\": false, \n                \"seconds\": 0.9999899864196777, \n                \"sender\": false, \n                \"start\": 4.001118\n            }\n        }, \n        {\n            \"streams\": [\n                {\n                    \"bits_per_second\": 1048552.875509981, \n                    \"bytes\": 131072, \n                    \"end\": 6.00113, \n                    \"omitted\": false, \n                    \"seconds\": 1.000022053718567, \n                    \"sender\": false, \n                    \"socket\": 5, \n                    \"start\": 5.001108\n                }\n            ], \n            \"sum\": {\n                \"bits_per_second\": 1048552.875509981, \n                \"bytes\": 131072, \n                \"end\": 6.00113, \n                \"omitted\": false, \n                \"seconds\": 1.000022053718567, \n                \"sender\": false, \n                \"start\": 5.001108\n            }\n        }, \n        {\n            \"streams\": [\n                {\n                    \"bits_per_second\": 0, \n                    \"bytes\": 0, \n                    \"end\": 7.001098, \n                    \"omitted\": false, \n                    \"seconds\": 0.9999679923057556, \n                    \"sender\": false, \n                    \"socket\": 5, \n                    \"start\": 6.00113\n                }\n            ], \n            \"sum\": {\n                \"bits_per_second\": 0, \n                \"bytes\": 0, \n                \"end\": 7.001098, \n                \"omitted\": false, \n                \"seconds\": 0.9999679923057556, \n                \"sender\": false, \n                \"start\": 6.00113\n            }\n        }, \n        {\n            \"streams\": [\n                {\n                    \"bits_per_second\": 0, \n                    \"bytes\": 0, \n                    \"end\": 8.001114, \n                    \"omitted\": false, \n                    \"seconds\": 1.0000159740448, \n                    \"sender\": false, \n                    \"socket\": 5, \n                    \"start\": 7.001098\n                }\n            ], \n            \"sum\": {\n                \"bits_per_second\": 0, \n                \"bytes\": 0, \n                \"end\": 8.001114, \n                \"omitted\": false, \n                \"seconds\": 1.0000159740448, \n                \"sender\": false, \n                \"start\": 7.001098\n            }\n        }, \n        {\n            \"streams\": [\n                {\n                    \"bits_per_second\": 0, \n                    \"bytes\": 0, \n                    \"end\": 9.000041, \n                    \"omitted\": false, \n                    \"seconds\": 0.9989269971847534, \n                    \"sender\": false, \n                    \"socket\": 5, \n                    \"start\": 8.001114\n                }\n            ], \n            \"sum\": {\n                \"bits_per_second\": 0, \n                \"bytes\": 0, \n                \"end\": 9.000041, \n                \"omitted\": false, \n                \"seconds\": 0.9989269971847534, \n                \"sender\": false, \n                \"start\": 8.001114\n            }\n        }, \n        {\n            \"streams\": [\n                {\n                    \"bits_per_second\": 12569650.990394475, \n                    \"bytes\": 1572864, \n                    \"end\": 10.001096, \n                    \"omitted\": false, \n                    \"seconds\": 1.0010550022125244, \n                    \"sender\": false, \n                    \"socket\": 5, \n                    \"start\": 9.000041\n                }\n            ], \n            \"sum\": {\n                \"bits_per_second\": 12569650.990394475, \n                \"bytes\": 1572864, \n                \"end\": 10.001096, \n                \"omitted\": false, \n                \"seconds\": 1.0010550022125244, \n                \"sender\": false, \n                \"start\": 9.000041\n            }\n        }, \n        {\n            \"streams\": [\n                {\n                    \"bits_per_second\": 1048450.1401086939, \n                    \"bytes\": 131072, \n                    \"end\": 11.001216, \n                    \"omitted\": false, \n                    \"seconds\": 1.0001200437545776, \n                    \"sender\": false, \n                    \"socket\": 5, \n                    \"start\": 10.001096\n                }\n            ], \n            \"sum\": {\n                \"bits_per_second\": 1048450.1401086939, \n                \"bytes\": 131072, \n                \"end\": 11.001216, \n                \"omitted\": false, \n                \"seconds\": 1.0001200437545776, \n                \"sender\": false, \n                \"start\": 10.001096\n            }\n        }, \n        {\n            \"streams\": [\n                {\n                    \"bits_per_second\": 0, \n                    \"bytes\": 0, \n                    \"end\": 12.001129, \n                    \"omitted\": false, \n                    \"seconds\": 0.999912977218628, \n                    \"sender\": false, \n                    \"socket\": 5, \n                    \"start\": 11.001216\n                }\n            ], \n            \"sum\": {\n                \"bits_per_second\": 0, \n                \"bytes\": 0, \n                \"end\": 12.001129, \n                \"omitted\": false, \n                \"seconds\": 0.999912977218628, \n                \"sender\": false, \n                \"start\": 11.001216\n            }\n        }, \n        {\n            \"streams\": [\n                {\n                    \"bits_per_second\": 1048626.3149141972, \n                    \"bytes\": 131072, \n                    \"end\": 13.001081, \n                    \"omitted\": false, \n                    \"seconds\": 0.9999520182609558, \n                    \"sender\": false, \n                    \"socket\": 5, \n                    \"start\": 12.001129\n                }\n            ], \n            \"sum\": {\n                \"bits_per_second\": 1048626.3149141972, \n                \"bytes\": 131072, \n                \"end\": 13.001081, \n                \"omitted\": false, \n                \"seconds\": 0.9999520182609558, \n                \"sender\": false, \n                \"start\": 12.001129\n            }\n        }, \n        {\n            \"streams\": [\n                {\n                    \"bits_per_second\": 2097091.2517597463, \n                    \"bytes\": 262144, \n                    \"end\": 14.00111, \n                    \"omitted\": false, \n                    \"seconds\": 1.0000289678573608, \n                    \"sender\": false, \n                    \"socket\": 5, \n                    \"start\": 13.001081\n                }\n            ], \n            \"sum\": {\n                \"bits_per_second\": 2097091.2517597463, \n                \"bytes\": 262144, \n                \"end\": 14.00111, \n                \"omitted\": false, \n                \"seconds\": 1.0000289678573608, \n                \"sender\": false, \n                \"start\": 13.001081\n            }\n        }, \n        {\n            \"streams\": [\n                {\n                    \"bits_per_second\": 0, \n                    \"bytes\": 0, \n                    \"end\": 15.001052, \n                    \"omitted\": false, \n                    \"seconds\": 0.9999420046806335, \n                    \"sender\": false, \n                    \"socket\": 5, \n                    \"start\": 14.00111\n                }\n            ], \n            \"sum\": {\n                \"bits_per_second\": 0, \n                \"bytes\": 0, \n                \"end\": 15.001052, \n                \"omitted\": false, \n                \"seconds\": 0.9999420046806335, \n                \"sender\": false, \n                \"start\": 14.00111\n            }\n        }, \n        {\n            \"streams\": [\n                {\n                    \"bits_per_second\": 4194048.0156240463, \n                    \"bytes\": 524288, \n                    \"end\": 16.001113, \n                    \"omitted\": false, \n                    \"seconds\": 1.00006103515625, \n                    \"sender\": false, \n                    \"socket\": 5, \n                    \"start\": 15.001052\n                }\n            ], \n            \"sum\": {\n                \"bits_per_second\": 4194048.0156240463, \n                \"bytes\": 524288, \n                \"end\": 16.001113, \n                \"omitted\": false, \n                \"seconds\": 1.00006103515625, \n                \"sender\": false, \n                \"start\": 15.001052\n            }\n        }, \n        {\n            \"streams\": [\n                {\n                    \"bits_per_second\": 6291493.87522801, \n                    \"bytes\": 786432, \n                    \"end\": 17.001107, \n                    \"omitted\": false, \n                    \"seconds\": 0.9999939799308777, \n                    \"sender\": false, \n                    \"socket\": 5, \n                    \"start\": 16.001113\n                }\n            ], \n            \"sum\": {\n                \"bits_per_second\": 6291493.87522801, \n                \"bytes\": 786432, \n                \"end\": 17.001107, \n                \"omitted\": false, \n                \"seconds\": 0.9999939799308777, \n                \"sender\": false, \n                \"start\": 16.001113\n            }\n        }, \n        {\n            \"streams\": [\n                {\n                    \"bits_per_second\": 0, \n                    \"bytes\": 0, \n                    \"end\": 18.001058, \n                    \"omitted\": false, \n                    \"seconds\": 0.9999510049819946, \n                    \"sender\": false, \n                    \"socket\": 5, \n                    \"start\": 17.001107\n                }\n            ], \n            \"sum\": {\n                \"bits_per_second\": 0, \n                \"bytes\": 0, \n                \"end\": 18.001058, \n                \"omitted\": false, \n                \"seconds\": 0.9999510049819946, \n                \"sender\": false, \n                \"start\": 17.001107\n            }\n        }, \n        {\n            \"streams\": [\n                {\n                    \"bits_per_second\": 0, \n                    \"bytes\": 0, \n                    \"end\": 19.001092, \n                    \"omitted\": false, \n                    \"seconds\": 1.000033974647522, \n                    \"sender\": false, \n                    \"socket\": 5, \n                    \"start\": 18.001058\n                }\n            ], \n            \"sum\": {\n                \"bits_per_second\": 0, \n                \"bytes\": 0, \n                \"end\": 19.001092, \n                \"omitted\": false, \n                \"seconds\": 1.000033974647522, \n                \"sender\": false, \n                \"start\": 18.001058\n            }\n        }, \n        {\n            \"streams\": [\n                {\n                    \"bits_per_second\": 0, \n                    \"bytes\": 0, \n                    \"end\": 20.0012, \n                    \"omitted\": false, \n                    \"seconds\": 1.000108003616333, \n                    \"sender\": false, \n                    \"socket\": 5, \n                    \"start\": 19.001092\n                }\n            ], \n            \"sum\": {\n                \"bits_per_second\": 0, \n                \"bytes\": 0, \n                \"end\": 20.0012, \n                \"omitted\": false, \n                \"seconds\": 1.000108003616333, \n                \"sender\": false, \n                \"start\": 19.001092\n            }\n        }, \n        {\n            \"streams\": [\n                {\n                    \"bits_per_second\": 17827538.92118087, \n                    \"bytes\": 2228224, \n                    \"end\": 21.001102, \n                    \"omitted\": false, \n                    \"seconds\": 0.9999020099639893, \n                    \"sender\": false, \n                    \"socket\": 5, \n                    \"start\": 20.0012\n                }\n            ], \n            \"sum\": {\n                \"bits_per_second\": 17827538.92118087, \n                \"bytes\": 2228224, \n                \"end\": 21.001102, \n                \"omitted\": false, \n                \"seconds\": 0.9999020099639893, \n                \"sender\": false, \n                \"start\": 20.0012\n            }\n        }, \n        {\n            \"streams\": [\n                {\n                    \"bits_per_second\": 0, \n                    \"bytes\": 0, \n                    \"end\": 22.001158, \n                    \"omitted\": false, \n                    \"seconds\": 1.0000560283660889, \n                    \"sender\": false, \n                    \"socket\": 5, \n                    \"start\": 21.001102\n                }\n            ], \n            \"sum\": {\n                \"bits_per_second\": 0, \n                \"bytes\": 0, \n                \"end\": 22.001158, \n                \"omitted\": false, \n                \"seconds\": 1.0000560283660889, \n                \"sender\": false, \n                \"start\": 21.001102\n            }\n        }, \n        {\n            \"streams\": [\n                {\n                    \"bits_per_second\": 0, \n                    \"bytes\": 0, \n                    \"end\": 23.0011, \n                    \"omitted\": false, \n                    \"seconds\": 0.9999420046806335, \n                    \"sender\": false, \n                    \"socket\": 5, \n                    \"start\": 22.001158\n                }\n            ], \n            \"sum\": {\n                \"bits_per_second\": 0, \n                \"bytes\": 0, \n                \"end\": 23.0011, \n                \"omitted\": false, \n                \"seconds\": 0.9999420046806335, \n                \"sender\": false, \n                \"start\": 22.001158\n            }\n        }, \n        {\n            \"streams\": [\n                {\n                    \"bits_per_second\": 0, \n                    \"bytes\": 0, \n                    \"end\": 24.001145, \n                    \"omitted\": false, \n                    \"seconds\": 1.0000449419021606, \n                    \"sender\": false, \n                    \"socket\": 5, \n                    \"start\": 23.0011\n                }\n            ], \n            \"sum\": {\n                \"bits_per_second\": 0, \n                \"bytes\": 0, \n                \"end\": 24.001145, \n                \"omitted\": false, \n                \"seconds\": 1.0000449419021606, \n                \"sender\": false, \n                \"start\": 23.0011\n            }\n        }, \n        {\n            \"streams\": [\n                {\n                    \"bits_per_second\": 4194346.000420575, \n                    \"bytes\": 524288, \n                    \"end\": 25.001135, \n                    \"omitted\": false, \n                    \"seconds\": 0.9999899864196777, \n                    \"sender\": false, \n                    \"socket\": 5, \n                    \"start\": 24.001145\n                }\n            ], \n            \"sum\": {\n                \"bits_per_second\": 4194346.000420575, \n                \"bytes\": 524288, \n                \"end\": 25.001135, \n                \"omitted\": false, \n                \"seconds\": 0.9999899864196777, \n                \"sender\": false, \n                \"start\": 24.001145\n            }\n        }, \n        {\n            \"streams\": [\n                {\n                    \"bits_per_second\": 1048670.383494799, \n                    \"bytes\": 131072, \n                    \"end\": 26.001045, \n                    \"omitted\": false, \n                    \"seconds\": 0.999909996986389, \n                    \"sender\": false, \n                    \"socket\": 5, \n                    \"start\": 25.001135\n                }\n            ], \n            \"sum\": {\n                \"bits_per_second\": 1048670.383494799, \n                \"bytes\": 131072, \n                \"end\": 26.001045, \n                \"omitted\": false, \n                \"seconds\": 0.999909996986389, \n                \"sender\": false, \n                \"start\": 25.001135\n            }\n        }, \n        {\n            \"streams\": [\n                {\n                    \"bits_per_second\": 0, \n                    \"bytes\": 0, \n                    \"end\": 27.001035, \n                    \"omitted\": false, \n                    \"seconds\": 0.9999899864196777, \n                    \"sender\": false, \n                    \"socket\": 5, \n                    \"start\": 26.001045\n                }\n            ], \n            \"sum\": {\n                \"bits_per_second\": 0, \n                \"bytes\": 0, \n                \"end\": 27.001035, \n                \"omitted\": false, \n                \"seconds\": 0.9999899864196777, \n                \"sender\": false, \n                \"start\": 26.001045\n            }\n        }, \n        {\n            \"streams\": [\n                {\n                    \"bits_per_second\": 0, \n                    \"bytes\": 0, \n                    \"end\": 28.001102, \n                    \"omitted\": false, \n                    \"seconds\": 1.0000669956207275, \n                    \"sender\": false, \n                    \"socket\": 5, \n                    \"start\": 27.001035\n                }\n            ], \n            \"sum\": {\n                \"bits_per_second\": 0, \n                \"bytes\": 0, \n                \"end\": 28.001102, \n                \"omitted\": false, \n                \"seconds\": 1.0000669956207275, \n                \"sender\": false, \n                \"start\": 27.001035\n            }\n        }, \n        {\n            \"streams\": [\n                {\n                    \"bits_per_second\": 2095882.019533004, \n                    \"bytes\": 262144, \n                    \"end\": 29.001708, \n                    \"omitted\": false, \n                    \"seconds\": 1.0006059408187866, \n                    \"sender\": false, \n                    \"socket\": 5, \n                    \"start\": 28.001102\n                }\n            ], \n            \"sum\": {\n                \"bits_per_second\": 2095882.019533004, \n                \"bytes\": 262144, \n                \"end\": 29.001708, \n                \"omitted\": false, \n                \"seconds\": 1.0006059408187866, \n                \"sender\": false, \n                \"start\": 28.001102\n            }\n        }, \n        {\n            \"streams\": [\n                {\n                    \"bits_per_second\": 0, \n                    \"bytes\": 0, \n                    \"end\": 30.001143, \n                    \"omitted\": false, \n                    \"seconds\": 0.999435007572174, \n                    \"sender\": false, \n                    \"socket\": 5, \n                    \"start\": 29.001708\n                }\n            ], \n            \"sum\": {\n                \"bits_per_second\": 0, \n                \"bytes\": 0, \n                \"end\": 30.001143, \n                \"omitted\": false, \n                \"seconds\": 0.999435007572174, \n                \"sender\": false, \n                \"start\": 29.001708\n            }\n        }, \n        {\n            \"streams\": [\n                {\n                    \"bits_per_second\": 0, \n                    \"bytes\": 0, \n                    \"end\": 31.001137, \n                    \"omitted\": false, \n                    \"seconds\": 0.9999939799308777, \n                    \"sender\": false, \n                    \"socket\": 5, \n                    \"start\": 30.001143\n                }\n            ], \n            \"sum\": {\n                \"bits_per_second\": 0, \n                \"bytes\": 0, \n                \"end\": 31.001137, \n                \"omitted\": false, \n                \"seconds\": 0.9999939799308777, \n                \"sender\": false, \n                \"start\": 30.001143\n            }\n        }, \n        {\n            \"streams\": [\n                {\n                    \"bits_per_second\": 0, \n                    \"bytes\": 0, \n                    \"end\": 32.001132, \n                    \"omitted\": false, \n                    \"seconds\": 0.999994993209839, \n                    \"sender\": false, \n                    \"socket\": 5, \n                    \"start\": 31.001137\n                }\n            ], \n            \"sum\": {\n                \"bits_per_second\": 0, \n                \"bytes\": 0, \n                \"end\": 32.001132, \n                \"omitted\": false, \n                \"seconds\": 0.999994993209839, \n                \"sender\": false, \n                \"start\": 31.001137\n            }\n        }, \n        {\n            \"streams\": [\n                {\n                    \"bits_per_second\": 3145973.4566511367, \n                    \"bytes\": 393216, \n                    \"end\": 33.001054, \n                    \"omitted\": false, \n                    \"seconds\": 0.999921977519989, \n                    \"sender\": false, \n                    \"socket\": 5, \n                    \"start\": 32.001132\n                }\n            ], \n            \"sum\": {\n                \"bits_per_second\": 3145973.4566511367, \n                \"bytes\": 393216, \n                \"end\": 33.001054, \n                \"omitted\": false, \n                \"seconds\": 0.999921977519989, \n                \"sender\": false, \n                \"start\": 32.001132\n            }\n        }, \n        {\n            \"streams\": [\n                {\n                    \"bits_per_second\": 8396290.529444546, \n                    \"bytes\": 1048576, \n                    \"end\": 34.000139, \n                    \"omitted\": false, \n                    \"seconds\": 0.999085009098053, \n                    \"sender\": false, \n                    \"socket\": 5, \n                    \"start\": 33.001054\n                }\n            ], \n            \"sum\": {\n                \"bits_per_second\": 8396290.529444546, \n                \"bytes\": 1048576, \n                \"end\": 34.000139, \n                \"omitted\": false, \n                \"seconds\": 0.999085009098053, \n                \"sender\": false, \n                \"start\": 33.001054\n            }\n        }, \n        {\n            \"streams\": [\n                {\n                    \"bits_per_second\": 0, \n                    \"bytes\": 0, \n                    \"end\": 35.001063, \n                    \"omitted\": false, \n                    \"seconds\": 1.000923991203308, \n                    \"sender\": false, \n                    \"socket\": 5, \n                    \"start\": 34.000139\n                }\n            ], \n            \"sum\": {\n                \"bits_per_second\": 0, \n                \"bytes\": 0, \n                \"end\": 35.001063, \n                \"omitted\": false, \n                \"seconds\": 1.000923991203308, \n                \"sender\": false, \n                \"start\": 34.000139\n            }\n        }, \n        {\n            \"streams\": [\n                {\n                    \"bits_per_second\": 0, \n                    \"bytes\": 0, \n                    \"end\": 36.001102, \n                    \"omitted\": false, \n                    \"seconds\": 1.000038981437683, \n                    \"sender\": false, \n                    \"socket\": 5, \n                    \"start\": 35.001063\n                }\n            ], \n            \"sum\": {\n                \"bits_per_second\": 0, \n                \"bytes\": 0, \n                \"end\": 36.001102, \n                \"omitted\": false, \n                \"seconds\": 1.000038981437683, \n                \"sender\": false, \n                \"start\": 35.001063\n            }\n        }, \n        {\n            \"streams\": [\n                {\n                    \"bits_per_second\": 0, \n                    \"bytes\": 0, \n                    \"end\": 37.001062, \n                    \"omitted\": false, \n                    \"seconds\": 0.9999600052833557, \n                    \"sender\": false, \n                    \"socket\": 5, \n                    \"start\": 36.001102\n                }\n            ], \n            \"sum\": {\n                \"bits_per_second\": 0, \n                \"bytes\": 0, \n                \"end\": 37.001062, \n                \"omitted\": false, \n                \"seconds\": 0.9999600052833557, \n                \"sender\": false, \n                \"start\": 36.001102\n            }\n        }, \n        {\n            \"streams\": [\n                {\n                    \"bits_per_second\": 4198460.364691088, \n                    \"bytes\": 524288, \n                    \"end\": 38.000072, \n                    \"omitted\": false, \n                    \"seconds\": 0.9990100264549255, \n                    \"sender\": false, \n                    \"socket\": 5, \n                    \"start\": 37.001062\n                }\n            ], \n            \"sum\": {\n                \"bits_per_second\": 4198460.364691088, \n                \"bytes\": 524288, \n                \"end\": 38.000072, \n                \"omitted\": false, \n                \"seconds\": 0.9990100264549255, \n                \"sender\": false, \n                \"start\": 37.001062\n            }\n        }, \n        {\n            \"streams\": [\n                {\n                    \"bits_per_second\": 15712016.961882507, \n                    \"bytes\": 1966080, \n                    \"end\": 39.00113, \n                    \"omitted\": false, \n                    \"seconds\": 1.0010579824447632, \n                    \"sender\": false, \n                    \"socket\": 5, \n                    \"start\": 38.000072\n                }\n            ], \n            \"sum\": {\n                \"bits_per_second\": 15712016.961882507, \n                \"bytes\": 1966080, \n                \"end\": 39.00113, \n                \"omitted\": false, \n                \"seconds\": 1.0010579824447632, \n                \"sender\": false, \n                \"start\": 38.000072\n            }\n        }, \n        {\n            \"streams\": [\n                {\n                    \"bits_per_second\": 20971603.750334457, \n                    \"bytes\": 2621440, \n                    \"end\": 40.001126, \n                    \"omitted\": false, \n                    \"seconds\": 0.9999960064888, \n                    \"sender\": false, \n                    \"socket\": 5, \n                    \"start\": 39.00113\n                }\n            ], \n            \"sum\": {\n                \"bits_per_second\": 20971603.750334457, \n                \"bytes\": 2621440, \n                \"end\": 40.001126, \n                \"omitted\": false, \n                \"seconds\": 0.9999960064888, \n                \"sender\": false, \n                \"start\": 39.00113\n            }\n        }, \n        {\n            \"streams\": [\n                {\n                    \"bits_per_second\": 22020690.578554157, \n                    \"bytes\": 2752512, \n                    \"end\": 41.001099, \n                    \"omitted\": false, \n                    \"seconds\": 0.9999729990959167, \n                    \"sender\": false, \n                    \"socket\": 5, \n                    \"start\": 40.001126\n                }\n            ], \n            \"sum\": {\n                \"bits_per_second\": 22020690.578554157, \n                \"bytes\": 2752512, \n                \"end\": 41.001099, \n                \"omitted\": false, \n                \"seconds\": 0.9999729990959167, \n                \"sender\": false, \n                \"start\": 40.001126\n            }\n        }, \n        {\n            \"streams\": [\n                {\n                    \"bits_per_second\": 22020161.625195578, \n                    \"bytes\": 2752512, \n                    \"end\": 42.001096, \n                    \"omitted\": false, \n                    \"seconds\": 0.9999970197677612, \n                    \"sender\": false, \n                    \"socket\": 5, \n                    \"start\": 41.001099\n                }\n            ], \n            \"sum\": {\n                \"bits_per_second\": 22020161.625195578, \n                \"bytes\": 2752512, \n                \"end\": 42.001096, \n                \"omitted\": false, \n                \"seconds\": 0.9999970197677612, \n                \"sender\": false, \n                \"start\": 41.001099\n            }\n        }, \n        {\n            \"streams\": [\n                {\n                    \"bits_per_second\": 20971415.00052571, \n                    \"bytes\": 2621440, \n                    \"end\": 43.001101, \n                    \"omitted\": false, \n                    \"seconds\": 1.0000050067901611, \n                    \"sender\": false, \n                    \"socket\": 5, \n                    \"start\": 42.001096\n                }\n            ], \n            \"sum\": {\n                \"bits_per_second\": 20971415.00052571, \n                \"bytes\": 2621440, \n                \"end\": 43.001101, \n                \"omitted\": false, \n                \"seconds\": 1.0000050067901611, \n                \"sender\": false, \n                \"start\": 42.001096\n            }\n        }, \n        {\n            \"streams\": [\n                {\n                    \"bits_per_second\": 22021064.66760997, \n                    \"bytes\": 2752512, \n                    \"end\": 44.001057, \n                    \"omitted\": false, \n                    \"seconds\": 0.9999560117721558, \n                    \"sender\": false, \n                    \"socket\": 5, \n                    \"start\": 43.001101\n                }\n            ], \n            \"sum\": {\n                \"bits_per_second\": 22021064.66760997, \n                \"bytes\": 2752512, \n                \"end\": 44.001057, \n                \"omitted\": false, \n                \"seconds\": 0.9999560117721558, \n                \"sender\": false, \n                \"start\": 43.001101\n            }\n        }, \n        {\n            \"streams\": [\n                {\n                    \"bits_per_second\": 22020051.375090435, \n                    \"bytes\": 2752512, \n                    \"end\": 45.001059, \n                    \"omitted\": false, \n                    \"seconds\": 1.0000020265579224, \n                    \"sender\": false, \n                    \"socket\": 5, \n                    \"start\": 44.001057\n                }\n            ], \n            \"sum\": {\n                \"bits_per_second\": 22020051.375090435, \n                \"bytes\": 2752512, \n                \"end\": 45.001059, \n                \"omitted\": false, \n                \"seconds\": 1.0000020265579224, \n                \"sender\": false, \n                \"start\": 44.001057\n            }\n        }, \n        {\n            \"streams\": [\n                {\n                    \"bits_per_second\": 17824971.787741892, \n                    \"bytes\": 2228224, \n                    \"end\": 46.001105, \n                    \"omitted\": false, \n                    \"seconds\": 1.0000460147857666, \n                    \"sender\": false, \n                    \"socket\": 5, \n                    \"start\": 45.001059\n                }\n            ], \n            \"sum\": {\n                \"bits_per_second\": 17824971.787741892, \n                \"bytes\": 2228224, \n                \"end\": 46.001105, \n                \"omitted\": false, \n                \"seconds\": 1.0000460147857666, \n                \"sender\": false, \n                \"start\": 45.001059\n            }\n        }, \n        {\n            \"streams\": [\n                {\n                    \"bits_per_second\": 20970450.0545903, \n                    \"bytes\": 2621440, \n                    \"end\": 47.001156, \n                    \"omitted\": false, \n                    \"seconds\": 1.0000510215759277, \n                    \"sender\": false, \n                    \"socket\": 5, \n                    \"start\": 46.001105\n                }\n            ], \n            \"sum\": {\n                \"bits_per_second\": 20970450.0545903, \n                \"bytes\": 2621440, \n                \"end\": 47.001156, \n                \"omitted\": false, \n                \"seconds\": 1.0000510215759277, \n                \"sender\": false, \n                \"start\": 46.001105\n            }\n        }, \n        {\n            \"streams\": [\n                {\n                    \"bits_per_second\": 22022276.278354786, \n                    \"bytes\": 2752512, \n                    \"end\": 48.001057, \n                    \"omitted\": false, \n                    \"seconds\": 0.999900996685028, \n                    \"sender\": false, \n                    \"socket\": 5, \n                    \"start\": 47.001156\n                }\n            ], \n            \"sum\": {\n                \"bits_per_second\": 22022276.278354786, \n                \"bytes\": 2752512, \n                \"end\": 48.001057, \n                \"omitted\": false, \n                \"seconds\": 0.999900996685028, \n                \"sender\": false, \n                \"start\": 47.001156\n            }\n        }, \n        {\n            \"streams\": [\n                {\n                    \"bits_per_second\": 22019172.038770955, \n                    \"bytes\": 2752512, \n                    \"end\": 49.001099, \n                    \"omitted\": false, \n                    \"seconds\": 1.0000419616699219, \n                    \"sender\": false, \n                    \"socket\": 5, \n                    \"start\": 48.001057\n                }\n            ], \n            \"sum\": {\n                \"bits_per_second\": 22019172.038770955, \n                \"bytes\": 2752512, \n                \"end\": 49.001099, \n                \"omitted\": false, \n                \"seconds\": 1.0000419616699219, \n                \"sender\": false, \n                \"start\": 48.001057\n            }\n        }, \n        {\n            \"streams\": [\n                {\n                    \"bits_per_second\": 20972086.265289675, \n                    \"bytes\": 2621440, \n                    \"end\": 50.001072, \n                    \"omitted\": false, \n                    \"seconds\": 0.9999729990959167, \n                    \"sender\": false, \n                    \"socket\": 5, \n                    \"start\": 49.001099\n                }\n            ], \n            \"sum\": {\n                \"bits_per_second\": 20972086.265289675, \n                \"bytes\": 2621440, \n                \"end\": 50.001072, \n                \"omitted\": false, \n                \"seconds\": 0.9999729990959167, \n                \"sender\": false, \n                \"start\": 49.001099\n            }\n        }, \n        {\n            \"streams\": [\n                {\n                    \"bits_per_second\": 22019502.765982494, \n                    \"bytes\": 2752512, \n                    \"end\": 51.001099, \n                    \"omitted\": false, \n                    \"seconds\": 1.0000269412994385, \n                    \"sender\": false, \n                    \"socket\": 5, \n                    \"start\": 50.001072\n                }\n            ], \n            \"sum\": {\n                \"bits_per_second\": 22019502.765982494, \n                \"bytes\": 2752512, \n                \"end\": 51.001099, \n                \"omitted\": false, \n                \"seconds\": 1.0000269412994385, \n                \"sender\": false, \n                \"start\": 50.001072\n            }\n        }, \n        {\n            \"streams\": [\n                {\n                    \"bits_per_second\": 22019523.76487103, \n                    \"bytes\": 2752512, \n                    \"end\": 52.001125, \n                    \"omitted\": false, \n                    \"seconds\": 1.000025987625122, \n                    \"sender\": false, \n                    \"socket\": 5, \n                    \"start\": 51.001099\n                }\n            ], \n            \"sum\": {\n                \"bits_per_second\": 22019523.76487103, \n                \"bytes\": 2752512, \n                \"end\": 52.001125, \n                \"omitted\": false, \n                \"seconds\": 1.000025987625122, \n                \"sender\": false, \n                \"start\": 51.001099\n            }\n        }, \n        {\n            \"streams\": [\n                {\n                    \"bits_per_second\": 1048592.7502675694, \n                    \"bytes\": 131072, \n                    \"end\": 53.001109, \n                    \"omitted\": false, \n                    \"seconds\": 0.9999840259552002, \n                    \"sender\": false, \n                    \"socket\": 5, \n                    \"start\": 52.001125\n                }\n            ], \n            \"sum\": {\n                \"bits_per_second\": 1048592.7502675694, \n                \"bytes\": 131072, \n                \"end\": 53.001109, \n                \"omitted\": false, \n                \"seconds\": 0.9999840259552002, \n                \"sender\": false, \n                \"start\": 52.001125\n            }\n        }, \n        {\n            \"streams\": [\n                {\n                    \"bits_per_second\": 0, \n                    \"bytes\": 0, \n                    \"end\": 54.001096, \n                    \"omitted\": false, \n                    \"seconds\": 0.999987006187439, \n                    \"sender\": false, \n                    \"socket\": 5, \n                    \"start\": 53.001109\n                }\n            ], \n            \"sum\": {\n                \"bits_per_second\": 0, \n                \"bytes\": 0, \n                \"end\": 54.001096, \n                \"omitted\": false, \n                \"seconds\": 0.999987006187439, \n                \"sender\": false, \n                \"start\": 53.001109\n            }\n        }, \n        {\n            \"streams\": [\n                {\n                    \"bits_per_second\": 0, \n                    \"bytes\": 0, \n                    \"end\": 55.000101, \n                    \"omitted\": false, \n                    \"seconds\": 0.9990050196647644, \n                    \"sender\": false, \n                    \"socket\": 5, \n                    \"start\": 54.001096\n                }\n            ], \n            \"sum\": {\n                \"bits_per_second\": 0, \n                \"bytes\": 0, \n                \"end\": 55.000101, \n                \"omitted\": false, \n                \"seconds\": 0.9990050196647644, \n                \"sender\": false, \n                \"start\": 54.001096\n            }\n        }, \n        {\n            \"streams\": [\n                {\n                    \"bits_per_second\": 0, \n                    \"bytes\": 0, \n                    \"end\": 56.001131, \n                    \"omitted\": false, \n                    \"seconds\": 1.0010299682617188, \n                    \"sender\": false, \n                    \"socket\": 5, \n                    \"start\": 55.000101\n                }\n            ], \n            \"sum\": {\n                \"bits_per_second\": 0, \n                \"bytes\": 0, \n                \"end\": 56.001131, \n                \"omitted\": false, \n                \"seconds\": 1.0010299682617188, \n                \"sender\": false, \n                \"start\": 55.000101\n            }\n        }, \n        {\n            \"streams\": [\n                {\n                    \"bits_per_second\": 0, \n                    \"bytes\": 0, \n                    \"end\": 57.001205, \n                    \"omitted\": false, \n                    \"seconds\": 1.000074028968811, \n                    \"sender\": false, \n                    \"socket\": 5, \n                    \"start\": 56.001131\n                }\n            ], \n            \"sum\": {\n                \"bits_per_second\": 0, \n                \"bytes\": 0, \n                \"end\": 57.001205, \n                \"omitted\": false, \n                \"seconds\": 1.000074028968811, \n                \"sender\": false, \n                \"start\": 56.001131\n            }\n        }, \n        {\n            \"streams\": [\n                {\n                    \"bits_per_second\": 0, \n                    \"bytes\": 0, \n                    \"end\": 58.001129, \n                    \"omitted\": false, \n                    \"seconds\": 0.9999240040779114, \n                    \"sender\": false, \n                    \"socket\": 5, \n                    \"start\": 57.001205\n                }\n            ], \n            \"sum\": {\n                \"bits_per_second\": 0, \n                \"bytes\": 0, \n                \"end\": 58.001129, \n                \"omitted\": false, \n                \"seconds\": 0.9999240040779114, \n                \"sender\": false, \n                \"start\": 57.001205\n            }\n        }, \n        {\n            \"streams\": [\n                {\n                    \"bits_per_second\": 0, \n                    \"bytes\": 0, \n                    \"end\": 59.001111, \n                    \"omitted\": false, \n                    \"seconds\": 0.9999819993972778, \n                    \"sender\": false, \n                    \"socket\": 5, \n                    \"start\": 58.001129\n                }\n            ], \n            \"sum\": {\n                \"bits_per_second\": 0, \n                \"bytes\": 0, \n                \"end\": 59.001111, \n                \"omitted\": false, \n                \"seconds\": 0.9999819993972778, \n                \"sender\": false, \n                \"start\": 58.001129\n            }\n        }, \n        {\n            \"streams\": [\n                {\n                    \"bits_per_second\": 0, \n                    \"bytes\": 0, \n                    \"end\": 60.001101, \n                    \"omitted\": false, \n                    \"seconds\": 0.9999899864196777, \n                    \"sender\": false, \n                    \"socket\": 5, \n                    \"start\": 59.001111\n                }\n            ], \n            \"sum\": {\n                \"bits_per_second\": 0, \n                \"bytes\": 0, \n                \"end\": 60.001101, \n                \"omitted\": false, \n                \"seconds\": 0.9999899864196777, \n                \"sender\": false, \n                \"start\": 59.001111\n            }\n        }\n    ], \n    \"start\": {\n        \"accepted_connection\": {\n            \"host\": \"172.16.0.2\", \n            \"port\": 42913\n        }, \n        \"connected\": [\n            {\n                \"local_host\": \"172.16.0.1\", \n                \"local_port\": 5201, \n                \"remote_host\": \"172.16.0.2\", \n                \"remote_port\": 49269, \n                \"socket\": 5\n            }\n        ], \n        \"cookie\": \"h3mvjqjtfbnishq2cil4feo6hmncfnmt7id6\", \n        \"fq_rate\": 0, \n        \"rcvbuf_actual\": 87380, \n        \"sndbuf_actual\": 65536, \n        \"sock_bufsize\": 0, \n        \"system_info\": \"REDACTED\", \n        \"target_bitrate\": 0, \n        \"tcp_mss_default\": 0, \n        \"test_start\": {\n            \"bidir\": 0, \n            \"blksize\": 131072, \n            \"blocks\": 0, \n            \"bytes\": 0, \n            \"duration\": 60, \n            \"fqrate\": 0, \n            \"interval\": 1, \n            \"num_streams\": 1, \n            \"omit\": 0, \n            \"protocol\": \"TCP\", \n            \"reverse\": 0, \n            \"target_bitrate\": 0, \n            \"tos\": 0\n        }, \n        \"timestamp\": {\n            \"time\": \"Sun, 20 Oct 2024 17:40:26 GMT\", \n            \"timesecs\": 1729446026\n        }, \n        \"version\": \"iperf 3.17.1\"\n    }\n}\n","summary":{"streams":[{"end":60.001028,"rtt":50231,"start":0,"stream-id":5,"retransmits":879,"throughput-bits":6521873.325237027,"throughput-bytes":48914888}],"summary":{"end":60.001028,"start":0,"retransmits":879,"throughput-bits":6521873.325237027,"throughput-bytes":48914888,"receiver-throughput-bits":6114758.114302792}},"intervals":[{"streams":[{"end":1.000866,"rtt":93673,"start":0,"omitted":false,"stream-id":5,"retransmits":1,"tcp-window-size":1448,"throughput-bits":23796095.2610922,"throughput-bytes":2977088}],"summary":{"end":1.000866,"start":0,"omitted":false,"retransmits":1,"throughput-bits":23796095.2610922,"throughput-bytes":2977088}},{"streams":[{"end":2.001057,"rtt":93673,"start":1.000866,"omitted":false,"stream-id":5,"retransmits":1,"tcp-window-size":1448,"throughput-bits":0,"throughput-bytes":0}],"summary":{"end":2.001057,"start":1.000866,"omitted":false,"retransmits":1,"throughput-bits":0,"throughput-bytes":0}},{"streams":[{"end":3.001053,"rtt":93673,"start":2.001057,"omitted":false,"stream-id":5,"retransmits":1,"tcp-window-size":1448,"throughput-bits":0,"throughput-bytes":0}],"summary":{"end":3.001053,"start":2.001057,"omitted":false,"retransmits":1,"throughput-bits":0,"throughput-bytes":0}},{"streams":[{"end":4.001052,"rtt":93673,"start":3.001053,"omitted":false,"stream-id":5,"retransmits":0,"tcp-window-size":1448,"throughput-bits":0,"throughput-bytes":0}],"summary":{"end":4.001052,"start":3.001053,"omitted":false,"retransmits":0,"throughput-bits":0,"throughput-bytes":0}},{"streams":[{"end":5.00105,"rtt":93673,"start":4.001052,"omitted":false,"stream-id":5,"retransmits":0,"tcp-window-size":1448,"throughput-bits":0,"throughput-bytes":0}],"summary":{"end":5.00105,"start":4.001052,"omitted":false,"retransmits":0,"throughput-bits":0,"throughput-bytes":0}},{"streams":[{"end":6.001061,"rtt":31905,"start":5.00105,"omitted":false,"stream-id":5,"retransmits":34,"tcp-window-size":1448,"throughput-bits":0,"throughput-bytes":0}],"summary":{"end":6.001061,"start":5.00105,"omitted":false,"retransmits":34,"throughput-bits":0,"throughput-bytes":0}},{"streams":[{"end":7.001053,"rtt":31905,"start":6.001061,"omitted":false,"stream-id":5,"retransmits":1,"tcp-window-size":1448,"throughput-bits":0,"throughput-bytes":0}],"summary":{"end":7.001053,"start":6.001061,"omitted":false,"retransmits":1,"throughput-bits":0,"throughput-bytes":0}},{"streams":[{"end":8.001021,"rtt":31905,"start":7.001053,"omitted":false,"stream-id":5,"retransmits":1,"tcp-window-size":1448,"throughput-bits":0,"throughput-bytes":0}],"summary":{"end":8.001021,"start":7.001053,"omitted":false,"retransmits":1,"throughput-bits":0,"throughput-bytes":0}},{"streams":[{"end":9.001024,"rtt":31167,"start":8.001021,"omitted":false,"stream-id":5,"retransmits":3,"tcp-window-size":2896,"throughput-bits":0,"throughput-bytes":0}],"summary":{"end":9.001024,"start":8.001021,"omitted":false,"retransmits":3,"throughput-bits":0,"throughput-bytes":0}},{"streams":[{"end":10.000128,"rtt":24091,"start":9.001024,"omitted":false,"stream-id":5,"retransmits":343,"tcp-window-size":68056,"throughput-bits":16695919.159899449,"throughput-bytes":2085120}],"summary":{"end":10.000128,"start":9.001024,"omitted":false,"retransmits":343,"throughput-bits":16695919.159899449,"throughput-bytes":2085120}},{"streams":[{"end":11.001022,"rtt":22926,"start":10.000128,"omitted":false,"stream-id":5,"retransmits":48,"tcp-window-size":1448,"throughput-bits":0,"throughput-bytes":0}],"summary":{"end":11.001022,"start":10.000128,"omitted":false,"retransmits":48,"throughput-bits":0,"throughput-bytes":0}},{"streams":[{"end":12.001061,"rtt":22926,"start":11.001022,"omitted":false,"stream-id":5,"retransmits":1,"tcp-window-size":1448,"throughput-bits":0,"throughput-bytes":0}],"summary":{"end":12.001061,"start":11.001022,"omitted":false,"retransmits":1,"throughput-bits":0,"throughput-bytes":0}},{"streams":[{"end":13.00102,"rtt":23568,"start":12.001061,"omitted":false,"stream-id":5,"retransmits":24,"tcp-window-size":18824,"throughput-bits":0,"throughput-bytes":0}],"summary":{"end":13.00102,"start":12.001061,"omitted":false,"retransmits":24,"throughput-bits":0,"throughput-bytes":0}},{"streams":[{"end":14.001062,"rtt":29868,"start":13.00102,"omitted":false,"stream-id":5,"retransmits":5,"tcp-window-size":1448,"throughput-bits":0,"throughput-bytes":0}],"summary":{"end":14.001062,"start":13.00102,"omitted":false,"retransmits":5,"throughput-bits":0,"throughput-bytes":0}},{"streams":[{"end":15.001036,"rtt":29868,"start":14.001062,"omitted":false,"stream-id":5,"retransmits":1,"tcp-window-size":1448,"throughput-bits":0,"throughput-bytes":0}],"summary":{"end":15.001036,"start":14.001062,"omitted":false,"retransmits":1,"throughput-bits":0,"throughput-bytes":0}},{"streams":[{"end":16.000153,"rtt":20185,"start":15.001036,"omitted":false,"stream-id":5,"retransmits":22,"tcp-window-size":36200,"throughput-bits":8347851.012264233,"throughput-bytes":1042560}],"summary":{"end":16.000153,"start":15.001036,"omitted":false,"retransmits":22,"throughput-bits":8347851.012264233,"throughput-bytes":1042560}},{"streams":[{"end":17.001034,"rtt":23151,"start":16.000153,"omitted":false,"stream-id":5,"retransmits":1,"tcp-window-size":1448,"throughput-bits":0,"throughput-bytes":0}],"summary":{"end":17.001034,"start":16.000153,"omitted":false,"retransmits":1,"throughput-bits":0,"throughput-bytes":0}},{"streams":[{"end":18.001024,"rtt":23151,"start":17.001034,"omitted":false,"stream-id":5,"retransmits":1,"tcp-window-size":1448,"throughput-bits":0,"throughput-bytes":0}],"summary":{"end":18.001024,"start":17.001034,"omitted":false,"retransmits":1,"throughput-bits":0,"throughput-bytes":0}},{"streams":[{"end":19.001022,"rtt":23151,"start":18.001024,"omitted":false,"stream-id":5,"retransmits":1,"tcp-window-size":1448,"throughput-bits":0,"throughput-bytes":0}],"summary":{"end":19.001022,"start":18.001024,"omitted":false,"retransmits":1,"throughput-bits":0,"throughput-bytes":0}},{"streams":[{"end":20.001022,"rtt":32991,"start":19.001022,"omitted":false,"stream-id":5,"retransmits":15,"tcp-window-size":11584,"throughput-bits":0,"throughput-bytes":0}],"summary":{"end":20.001022,"start":19.001022,"omitted":false,"retransmits":15,"throughput-bits":0,"throughput-bytes":0}},{"streams":[{"end":21.000068,"rtt":29765,"start":20.001022,"omitted":false,"stream-id":5,"retransmits":25,"tcp-window-size":82536,"throughput-bits":25045332.554493826,"throughput-bytes":3127680}],"summary":{"end":21.000068,"start":20.001022,"omitted":false,"retransmits":25,"throughput-bits":25045332.554493826,"throughput-bytes":3127680}},{"streams":[{"end":22.001022,"rtt":29765,"start":21.000068,"omitted":false,"stream-id":5,"retransmits":2,"tcp-window-size":1448,"throughput-bits":0,"throughput-bytes":0}],"summary":{"end":22.001022,"start":21.000068,"omitted":false,"retransmits":2,"throughput-bits":0,"throughput-bytes":0}},{"streams":[{"end":23.00102,"rtt":29765,"start":22.001022,"omitted":false,"stream-id":5,"retransmits":1,"tcp-window-size":1448,"throughput-bits":0,"throughput-bytes":0}],"summary":{"end":23.00102,"start":22.001022,"omitted":false,"retransmits":1,"throughput-bits":0,"throughput-bytes":0}},{"streams":[{"end":24.001023,"rtt":29765,"start":23.00102,"omitted":false,"stream-id":5,"retransmits":0,"tcp-window-size":1448,"throughput-bits":0,"throughput-bytes":0}],"summary":{"end":24.001023,"start":23.00102,"omitted":false,"retransmits":0,"throughput-bits":0,"throughput-bytes":0}},{"streams":[{"end":25.001023,"rtt":18899,"start":24.001023,"omitted":false,"stream-id":5,"retransmits":57,"tcp-window-size":52128,"throughput-bits":0,"throughput-bytes":0}],"summary":{"end":25.001023,"start":24.001023,"omitted":false,"retransmits":57,"throughput-bits":0,"throughput-bytes":0}},{"streams":[{"end":26.001025,"rtt":20138,"start":25.001023,"omitted":false,"stream-id":5,"retransmits":2,"tcp-window-size":1448,"throughput-bits":0,"throughput-bytes":0}],"summary":{"end":26.001025,"start":25.001023,"omitted":false,"retransmits":2,"throughput-bits":0,"throughput-bytes":0}},{"streams":[{"end":27.001023,"rtt":20138,"start":26.001025,"omitted":false,"stream-id":5,"retransmits":1,"tcp-window-size":1448,"throughput-bits":0,"throughput-bytes":0}],"summary":{"end":27.001023,"start":26.001025,"omitted":false,"retransmits":1,"throughput-bits":0,"throughput-bytes":0}},{"streams":[{"end":28.001032,"rtt":20138,"start":27.001023,"omitted":false,"stream-id":5,"retransmits":0,"tcp-window-size":1448,"throughput-bits":0,"throughput-bytes":0}],"summary":{"end":28.001032,"start":27.001023,"omitted":false,"retransmits":0,"throughput-bits":0,"throughput-bytes":0}},{"streams":[{"end":29.001022,"rtt":24383,"start":28.001032,"omitted":false,"stream-id":5,"retransmits":39,"tcp-window-size":37648,"throughput-bits":0,"throughput-bytes":0}],"summary":{"end":29.001022,"start":28.001032,"omitted":false,"retransmits":39,"throughput-bits":0,"throughput-bytes":0}},{"streams":[{"end":30.001026,"rtt":24383,"start":29.001022,"omitted":false,"stream-id":5,"retransmits":2,"tcp-window-size":1448,"throughput-bits":0,"throughput-bytes":0}],"summary":{"end":30.001026,"start":29.001022,"omitted":false,"retransmits":2,"throughput-bits":0,"throughput-bytes":0}},{"streams":[{"end":31.001023,"rtt":24383,"start":30.001026,"omitted":false,"stream-id":5,"retransmits":1,"tcp-window-size":1448,"throughput-bits":0,"throughput-bytes":0}],"summary":{"end":31.001023,"start":30.001026,"omitted":false,"retransmits":1,"throughput-bits":0,"throughput-bytes":0}},{"streams":[{"end":32.001021,"rtt":24383,"start":31.001023,"omitted":false,"stream-id":5,"retransmits":0,"tcp-window-size":1448,"throughput-bits":0,"throughput-bytes":0}],"summary":{"end":32.001021,"start":31.001023,"omitted":false,"retransmits":0,"throughput-bits":0,"throughput-bytes":0}},{"streams":[{"end":33.000304,"rtt":19454,"start":32.001021,"omitted":false,"stream-id":5,"retransmits":27,"tcp-window-size":34752,"throughput-bits":8346464.28361819,"throughput-bytes":1042560}],"summary":{"end":33.000304,"start":32.001021,"omitted":false,"retransmits":27,"throughput-bits":8346464.28361819,"throughput-bytes":1042560}},{"streams":[{"end":34.000681,"rtt":27508,"start":33.000304,"omitted":false,"stream-id":5,"retransmits":1,"tcp-window-size":1448,"throughput-bits":8337336.332442818,"throughput-bytes":1042560}],"summary":{"end":34.000681,"start":33.000304,"omitted":false,"retransmits":1,"throughput-bits":8337336.332442818,"throughput-bytes":1042560}},{"streams":[{"end":35.001028,"rtt":27508,"start":34.000681,"omitted":false,"stream-id":5,"retransmits":1,"tcp-window-size":1448,"throughput-bits":0,"throughput-bytes":0}],"summary":{"end":35.001028,"start":34.000681,"omitted":false,"retransmits":1,"throughput-bits":0,"throughput-bytes":0}},{"streams":[{"end":36.001025,"rtt":27508,"start":35.001028,"omitted":false,"stream-id":5,"retransmits":1,"tcp-window-size":1448,"throughput-bits":0,"throughput-bytes":0}],"summary":{"end":36.001025,"start":35.001028,"omitted":false,"retransmits":1,"throughput-bits":0,"throughput-bytes":0}},{"streams":[{"end":37.001025,"rtt":27508,"start":36.001025,"omitted":false,"stream-id":5,"retransmits":0,"tcp-window-size":1448,"throughput-bits":0,"throughput-bytes":0}],"summary":{"end":37.001025,"start":36.001025,"omitted":false,"retransmits":0,"throughput-bits":0,"throughput-bytes":0}},{"streams":[{"end":38.001022,"rtt":32065,"start":37.001025,"omitted":false,"stream-id":5,"retransmits":48,"tcp-window-size":2896,"throughput-bits":0,"throughput-bytes":0}],"summary":{"end":38.001022,"start":37.001025,"omitted":false,"retransmits":48,"throughput-bits":0,"throughput-bytes":0}},{"streams":[{"end":39.000346,"rtt":30268,"start":38.001022,"omitted":false,"stream-id":5,"retransmits":32,"tcp-window-size":75296,"throughput-bits":16692243.560646849,"throughput-bytes":2085120}],"summary":{"end":39.000346,"start":38.001022,"omitted":false,"retransmits":32,"throughput-bits":16692243.560646849,"throughput-bytes":2085120}},{"streams":[{"end":40.000107,"rtt":41641,"start":39.000346,"omitted":false,"stream-id":5,"retransmits":0,"tcp-window-size":114392,"throughput-bits":25027421.919878643,"throughput-bytes":3127680}],"summary":{"end":40.000107,"start":39.000346,"omitted":false,"retransmits":0,"throughput-bits":25027421.919878643,"throughput-bytes":3127680}},{"streams":[{"end":41.000342,"rtt":54772,"start":40.000107,"omitted":false,"stream-id":5,"retransmits":0,"tcp-window-size":152040,"throughput-bits":16677041.537143027,"throughput-bytes":2085120}],"summary":{"end":41.000342,"start":40.000107,"omitted":false,"retransmits":0,"throughput-bits":16677041.537143027,"throughput-bytes":2085120}},{"streams":[{"end":42.000172,"rtt":74099,"start":41.000342,"omitted":false,"stream-id":5,"retransmits":0,"tcp-window-size":205616,"throughput-bits":25025694.178988844,"throughput-bytes":3127680}],"summary":{"end":42.000172,"start":41.000342,"omitted":false,"retransmits":0,"throughput-bits":25025694.178988844,"throughput-bytes":3127680}},{"streams":[{"end":43.000396,"rtt":95761,"start":42.000172,"omitted":false,"stream-id":5,"retransmits":0,"tcp-window-size":266432,"throughput-bits":16677224.397544505,"throughput-bytes":2085120}],"summary":{"end":43.000396,"start":42.000172,"omitted":false,"retransmits":0,"throughput-bits":16677224.397544505,"throughput-bytes":2085120}},{"streams":[{"end":44.000233,"rtt":119202,"start":43.000396,"omitted":false,"stream-id":5,"retransmits":0,"tcp-window-size":333040,"throughput-bits":25025519.62776315,"throughput-bytes":3127680}],"summary":{"end":44.000233,"start":43.000396,"omitted":false,"retransmits":0,"throughput-bits":25025519.62776315,"throughput-bytes":3127680}},{"streams":[{"end":45.000069,"rtt":144273,"start":44.000233,"omitted":false,"stream-id":5,"retransmits":0,"tcp-window-size":402544,"throughput-bits":25025543.49787251,"throughput-bytes":3127680}],"summary":{"end":45.000069,"start":44.000233,"omitted":false,"retransmits":0,"throughput-bits":25025543.49787251,"throughput-bytes":3127680}},{"streams":[{"end":46.000148,"rtt":78334,"start":45.000069,"omitted":false,"stream-id":5,"retransmits":68,"tcp-window-size":214304,"throughput-bits":16679641.711857919,"throughput-bytes":2085120}],"summary":{"end":46.000148,"start":45.000069,"omitted":false,"retransmits":68,"throughput-bits":16679641.711857919,"throughput-bytes":2085120}},{"streams":[{"end":47.000376,"rtt":84819,"start":46.000148,"omitted":false,"stream-id":5,"retransmits":0,"tcp-window-size":231680,"throughput-bits":16677156.818233337,"throughput-bytes":2085120}],"summary":{"end":47.000376,"start":46.000148,"omitted":false,"retransmits":0,"throughput-bits":16677156.818233337,"throughput-bytes":2085120}},{"streams":[{"end":48.000221,"rtt":90984,"start":47.000376,"omitted":false,"stream-id":5,"retransmits":0,"tcp-window-size":247608,"throughput-bits":25025318.22552838,"throughput-bytes":3127680}],"summary":{"end":48.000221,"start":47.000376,"omitted":false,"retransmits":0,"throughput-bits":25025318.22552838,"throughput-bytes":3127680}},{"streams":[{"end":49.000069,"rtt":101884,"start":48.000221,"omitted":false,"stream-id":5,"retransmits":0,"tcp-window-size":280912,"throughput-bits":25025243.632930756,"throughput-bytes":3127680}],"summary":{"end":49.000069,"start":48.000221,"omitted":false,"retransmits":0,"throughput-bits":25025243.632930756,"throughput-bytes":3127680}},{"streams":[{"end":50.000286,"rtt":117381,"start":49.000069,"omitted":false,"stream-id":5,"retransmits":0,"tcp-window-size":324352,"throughput-bits":16677341.668825475,"throughput-bytes":2085120}],"summary":{"end":50.000286,"start":49.000069,"omitted":false,"retransmits":0,"throughput-bits":16677341.668825475,"throughput-bytes":2085120}},{"streams":[{"end":51.000122,"rtt":135842,"start":50.000286,"omitted":false,"stream-id":5,"retransmits":0,"tcp-window-size":376480,"throughput-bits":25025543.49787251,"throughput-bytes":3127680}],"summary":{"end":51.000122,"start":50.000286,"omitted":false,"retransmits":0,"throughput-bits":25025543.49787251,"throughput-bytes":3127680}},{"streams":[{"end":52.000309,"rtt":76383,"start":51.000122,"omitted":false,"stream-id":5,"retransmits":7,"tcp-window-size":208512,"throughput-bits":17199023.1054625,"throughput-bytes":2150280}],"summary":{"end":52.000309,"start":51.000122,"omitted":false,"retransmits":7,"throughput-bits":17199023.1054625,"throughput-bytes":2150280}},{"streams":[{"end":53.000972,"rtt":76453,"start":52.000309,"omitted":false,"stream-id":5,"retransmits":1,"tcp-window-size":1448,"throughput-bits":8334953.575140842,"throughput-bytes":1042560}],"summary":{"end":53.000972,"start":52.000309,"omitted":false,"retransmits":1,"throughput-bits":8334953.575140842,"throughput-bytes":1042560}},{"streams":[{"end":54.00103,"rtt":76453,"start":53.000972,"omitted":false,"stream-id":5,"retransmits":1,"tcp-window-size":1448,"throughput-bits":0,"throughput-bytes":0}],"summary":{"end":54.00103,"start":53.000972,"omitted":false,"retransmits":1,"throughput-bits":0,"throughput-bytes":0}},{"streams":[{"end":55.001022,"rtt":76453,"start":54.00103,"omitted":false,"stream-id":5,"retransmits":1,"tcp-window-size":1448,"throughput-bits":0,"throughput-bytes":0}],"summary":{"end":55.001022,"start":54.00103,"omitted":false,"retransmits":1,"throughput-bits":0,"throughput-bytes":0}},{"streams":[{"end":56.001027,"rtt":76453,"start":55.001022,"omitted":false,"stream-id":5,"retransmits":0,"tcp-window-size":1448,"throughput-bits":0,"throughput-bytes":0}],"summary":{"end":56.001027,"start":55.001022,"omitted":false,"retransmits":0,"throughput-bits":0,"throughput-bytes":0}},{"streams":[{"end":57.001022,"rtt":33470,"start":56.001027,"omitted":false,"stream-id":5,"retransmits":54,"tcp-window-size":40544,"throughput-bits":0,"throughput-bytes":0}],"summary":{"end":57.001022,"start":56.001027,"omitted":false,"retransmits":54,"throughput-bits":0,"throughput-bytes":0}},{"streams":[{"end":58.001023,"rtt":33470,"start":57.001022,"omitted":false,"stream-id":5,"retransmits":2,"tcp-window-size":1448,"throughput-bits":0,"throughput-bytes":0}],"summary":{"end":58.001023,"start":57.001022,"omitted":false,"retransmits":2,"throughput-bits":0,"throughput-bytes":0}},{"streams":[{"end":59.001022,"rtt":33470,"start":58.001023,"omitted":false,"stream-id":5,"retransmits":1,"tcp-window-size":1448,"throughput-bits":0,"throughput-bytes":0}],"summary":{"end":59.001022,"start":58.001023,"omitted":false,"retransmits":1,"throughput-bits":0,"throughput-bytes":0}},{"streams":[{"end":60.001028,"rtt":33470,"start":59.001022,"omitted":false,"stream-id":5,"retransmits":0,"tcp-window-size":1448,"throughput-bits":0,"throughput-bytes":0}],"summary":{"end":60.001028,"start":59.001022,"omitted":false,"retransmits":0,"throughput-bits":0,"throughput-bytes":0}}],"succeeded":true}
