{"diags":"Participant 0:\n/usr/bin/iperf3 -p 5201 -B 172.16.0.2 -c 172.16.0.1 -t 10 --json --rsa-public-key-path /var/run/pscheduler-server/runner/tmp/tmp3azm7v5m/tmpz9dz70p1/public-key --username eGZC9bMsYfAO0QBDpxhx\n\n{\n    \"end\": {\n        \"cpu_utilization_percent\": {\n            \"host_system\": 0.292900882746664, \n            \"host_total\": 0.37754971015426786, \n            \"host_user\": 0.08464882740760384, \n            \"remote_system\": 0.48706845929263237, \n            \"remote_total\": 0.684638172797859, \n            \"remote_user\": 0.19756971350522665\n        }, \n        \"receiver_tcp_congestion\": \"htcp\", \n        \"sender_tcp_congestion\": \"htcp\", \n        \"streams\": [\n            {\n                \"receiver\": {\n                    \"bits_per_second\": 11722426.728065632, \n                    \"bytes\": 14897024, \n                    \"end\": 10.166512, \n                    \"seconds\": 10.000118, \n                    \"sender\": true, \n                    \"socket\": 5, \n                    \"start\": 0\n                }, \n                \"sender\": {\n                    \"bits_per_second\": 14260465.326509146, \n                    \"bytes\": 17825792, \n                    \"end\": 10.000118, \n                    \"max_rtt\": 287334, \n                    \"max_snd_cwnd\": 370688, \n                    \"max_snd_wnd\": 0, \n                    \"mean_rtt\": 193784, \n                    \"min_rtt\": 130496, \n                    \"retransmits\": 295, \n                    \"seconds\": 10.000118, \n                    \"sender\": true, \n                    \"socket\": 5, \n                    \"start\": 0\n                }\n            }\n        ], \n        \"sum_received\": {\n            \"bits_per_second\": 11722426.728065632, \n            \"bytes\": 14897024, \n            \"end\": 10.166512, \n            \"seconds\": 10.166512, \n            \"sender\": true, \n            \"start\": 0\n        }, \n        \"sum_sent\": {\n            \"bits_per_second\": 14260465.326509146, \n            \"bytes\": 17825792, \n            \"end\": 10.000118, \n            \"retransmits\": 295, \n            \"seconds\": 10.000118, \n            \"sender\": true, \n            \"start\": 0\n        }\n    }, \n    \"intervals\": [\n        {\n            \"streams\": [\n                {\n                    \"bits_per_second\": 37746319.654683284, \n                    \"bytes\": 4718592, \n                    \"end\": 1.000064, \n                    \"omitted\": false, \n                    \"pmtu\": 1500, \n                    \"retransmits\": 281, \n                    \"rtt\": 287334, \n                    \"rttvar\": 4261, \n                    \"seconds\": 1.0000640153884888, \n                    \"sender\": true, \n                    \"snd_cwnd\": 266432, \n                    \"snd_wnd\": -1, \n                    \"socket\": 5, \n                    \"start\": 0\n                }\n            ], \n            \"sum\": {\n                \"bits_per_second\": 37746319.654683284, \n                \"bytes\": 4718592, \n                \"end\": 1.000064, \n                \"omitted\": false, \n                \"retransmits\": 281, \n                \"seconds\": 1.0000640153884888, \n                \"sender\": true, \n                \"start\": 0\n            }\n        }, \n        {\n            \"streams\": [\n                {\n                    \"bits_per_second\": 10485413.761433134, \n                    \"bytes\": 1310720, \n                    \"end\": 2.000097, \n                    \"omitted\": false, \n                    \"pmtu\": 1500, \n                    \"retransmits\": 4, \n                    \"rtt\": 160026, \n                    \"rttvar\": 2168, \n                    \"seconds\": 1.0000330209732056, \n                    \"sender\": true, \n                    \"snd_cwnd\": 204168, \n                    \"snd_wnd\": -1, \n                    \"socket\": 5, \n                    \"start\": 1.000064\n                }\n            ], \n            \"sum\": {\n                \"bits_per_second\": 10485413.761433134, \n                \"bytes\": 1310720, \n                \"end\": 2.000097, \n                \"omitted\": false, \n                \"retransmits\": 4, \n                \"seconds\": 1.0000330209732056, \n                \"sender\": true, \n                \"start\": 1.000064\n            }\n        }, \n        {\n            \"streams\": [\n                {\n                    \"bits_per_second\": 20971372.50103741, \n                    \"bytes\": 2621440, \n                    \"end\": 3.000104, \n                    \"omitted\": false, \n                    \"pmtu\": 1500, \n                    \"retransmits\": 0, \n                    \"rtt\": 130496, \n                    \"rttvar\": 670, \n                    \"seconds\": 1.0000070333480835, \n                    \"sender\": true, \n                    \"snd_cwnd\": 214304, \n                    \"snd_wnd\": -1, \n                    \"socket\": 5, \n                    \"start\": 2.000097\n                }\n            ], \n            \"sum\": {\n                \"bits_per_second\": 20971372.50103741, \n                \"bytes\": 2621440, \n                \"end\": 3.000104, \n                \"omitted\": false, \n                \"retransmits\": 0, \n                \"seconds\": 1.0000070333480835, \n                \"sender\": true, \n                \"start\": 2.000097\n            }\n        }, \n        {\n            \"streams\": [\n                {\n                    \"bits_per_second\": 10486336.906738574, \n                    \"bytes\": 1310720, \n                    \"end\": 4.000049, \n                    \"omitted\": false, \n                    \"pmtu\": 1500, \n                    \"retransmits\": 0, \n                    \"rtt\": 212469, \n                    \"rttvar\": 5298, \n                    \"seconds\": 0.9999449849128723, \n                    \"sender\": true, \n                    \"snd_cwnd\": 224440, \n                    \"snd_wnd\": -1, \n                    \"socket\": 5, \n                    \"start\": 3.000104\n                }\n            ], \n            \"sum\": {\n                \"bits_per_second\": 10486336.906738574, \n                \"bytes\": 1310720, \n                \"end\": 4.000049, \n                \"omitted\": false, \n                \"retransmits\": 0, \n                \"seconds\": 0.9999449849128723, \n                \"sender\": true, \n                \"start\": 3.000104\n            }\n        }, \n        {\n            \"streams\": [\n                {\n                    \"bits_per_second\": 0, \n                    \"bytes\": 0, \n                    \"end\": 5.001043, \n                    \"omitted\": false, \n                    \"pmtu\": 1500, \n                    \"retransmits\": 0, \n                    \"rtt\": 154365, \n                    \"rttvar\": 5250, \n                    \"seconds\": 1.0009939670562744, \n                    \"sender\": true, \n                    \"snd_cwnd\": 244712, \n                    \"snd_wnd\": -1, \n                    \"socket\": 5, \n                    \"start\": 4.000049\n                }\n            ], \n            \"sum\": {\n                \"bits_per_second\": 0, \n                \"bytes\": 0, \n                \"end\": 5.001043, \n                \"omitted\": false, \n                \"retransmits\": 0, \n                \"seconds\": 1.0009939670562744, \n                \"sender\": true, \n                \"start\": 4.000049\n            }\n        }, \n        {\n            \"streams\": [\n                {\n                    \"bits_per_second\": 10486493.801348375, \n                    \"bytes\": 1310720, \n                    \"end\": 6.000973, \n                    \"omitted\": false, \n                    \"pmtu\": 1500, \n                    \"retransmits\": 0, \n                    \"rtt\": 249419, \n                    \"rttvar\": 2302, \n                    \"seconds\": 0.9999300241470337, \n                    \"sender\": true, \n                    \"snd_cwnd\": 270776, \n                    \"snd_wnd\": -1, \n                    \"socket\": 5, \n                    \"start\": 5.001043\n                }\n            ], \n            \"sum\": {\n                \"bits_per_second\": 10486493.801348375, \n                \"bytes\": 1310720, \n                \"end\": 6.000973, \n                \"omitted\": false, \n                \"retransmits\": 0, \n                \"seconds\": 0.9999300241470337, \n                \"sender\": true, \n                \"start\": 5.001043\n            }\n        }, \n        {\n            \"streams\": [\n                {\n                    \"bits_per_second\": 20990495.904666547, \n                    \"bytes\": 2621440, \n                    \"end\": 7.000069, \n                    \"omitted\": false, \n                    \"pmtu\": 1500, \n                    \"retransmits\": 0, \n                    \"rtt\": 202041, \n                    \"rttvar\": 459, \n                    \"seconds\": 0.9990959763526917, \n                    \"sender\": true, \n                    \"snd_cwnd\": 317112, \n                    \"snd_wnd\": -1, \n                    \"socket\": 5, \n                    \"start\": 6.000973\n                }\n            ], \n            \"sum\": {\n                \"bits_per_second\": 20990495.904666547, \n                \"bytes\": 2621440, \n                \"end\": 7.000069, \n                \"omitted\": false, \n                \"retransmits\": 0, \n                \"seconds\": 0.9990959763526917, \n                \"sender\": true, \n                \"start\": 6.000973\n            }\n        }, \n        {\n            \"streams\": [\n                {\n                    \"bits_per_second\": 10483684.161029879, \n                    \"bytes\": 1310720, \n                    \"end\": 8.000267, \n                    \"omitted\": false, \n                    \"pmtu\": 1500, \n                    \"retransmits\": 0, \n                    \"rtt\": 244150, \n                    \"rttvar\": 2263, \n                    \"seconds\": 1.0001980066299438, \n                    \"sender\": true, \n                    \"snd_cwnd\": 370688, \n                    \"snd_wnd\": -1, \n                    \"socket\": 5, \n                    \"start\": 7.000069\n                }\n            ], \n            \"sum\": {\n                \"bits_per_second\": 10483684.161029879, \n                \"bytes\": 1310720, \n                \"end\": 8.000267, \n                \"omitted\": false, \n                \"retransmits\": 0, \n                \"seconds\": 1.0001980066299438, \n                \"sender\": true, \n                \"start\": 7.000069\n            }\n        }, \n        {\n            \"streams\": [\n                {\n                    \"bits_per_second\": 10487962.337462597, \n                    \"bytes\": 1310720, \n                    \"end\": 9.000057, \n                    \"omitted\": false, \n                    \"pmtu\": 1500, \n                    \"retransmits\": 10, \n                    \"rtt\": 139019, \n                    \"rttvar\": 672, \n                    \"seconds\": 0.9997900128364563, \n                    \"sender\": true, \n                    \"snd_cwnd\": 207064, \n                    \"snd_wnd\": -1, \n                    \"socket\": 5, \n                    \"start\": 8.000267\n                }\n            ], \n            \"sum\": {\n                \"bits_per_second\": 10487962.337462597, \n                \"bytes\": 1310720, \n                \"end\": 9.000057, \n                \"omitted\": false, \n                \"retransmits\": 10, \n                \"seconds\": 0.9997900128364563, \n                \"sender\": true, \n                \"start\": 8.000267\n            }\n        }, \n        {\n            \"streams\": [\n                {\n                    \"bits_per_second\": 10485120.039060116, \n                    \"bytes\": 1310720, \n                    \"end\": 10.000118, \n                    \"omitted\": false, \n                    \"pmtu\": 1500, \n                    \"retransmits\": 0, \n                    \"rtt\": 158525, \n                    \"rttvar\": 6563, \n                    \"seconds\": 1.00006103515625, \n                    \"sender\": true, \n                    \"snd_cwnd\": 217200, \n                    \"snd_wnd\": -1, \n                    \"socket\": 5, \n                    \"start\": 9.000057\n                }\n            ], \n            \"sum\": {\n                \"bits_per_second\": 10485120.039060116, \n                \"bytes\": 1310720, \n                \"end\": 10.000118, \n                \"omitted\": false, \n                \"retransmits\": 0, \n                \"seconds\": 1.00006103515625, \n                \"sender\": true, \n                \"start\": 9.000057\n            }\n        }\n    ], \n    \"start\": {\n        \"connected\": [\n            {\n                \"local_host\": \"172.16.0.2\", \n                \"local_port\": 42571, \n                \"remote_host\": \"172.16.0.1\", \n                \"remote_port\": 5201, \n                \"socket\": 5\n            }\n        ], \n        \"connecting_to\": {\n            \"host\": \"172.16.0.1\", \n            \"port\": 5201\n        }, \n        \"cookie\": \"ztgvh44qmeb33lpqyyfcksadxf22ggpfhdd5\", \n        \"fq_rate\": 0, \n        \"rcvbuf_actual\": 87380, \n        \"sndbuf_actual\": 65536, \n        \"sock_bufsize\": 0, \n        \"system_info\": \"REDACTED\", \n        \"target_bitrate\": 0, \n        \"tcp_mss_default\": 1448, \n        \"test_start\": {\n            \"bidir\": 0, \n            \"blksize\": 131072, \n            \"blocks\": 0, \n            \"bytes\": 0, \n            \"duration\": 10, \n            \"fqrate\": 0, \n            \"num_streams\": 1, \n            \"omit\": 0, \n            \"protocol\": \"TCP\", \n            \"reverse\": 0, \n            \"target_bitrate\": 0, \n            \"tos\": 0\n        }, \n        \"timestamp\": {\n            \"time\": \"Sat, 12 Oct 2024 02:32:18 GMT\", \n            \"timesecs\": 1728700338\n        }, \n        \"version\": \"iperf 3.14\"\n    }\n}\nParticipant 1:\n/usr/bin/iperf3 -s -1 --idle-timeout 10 --json -p 5201 -B 172.16.0.1 --authorized-users-path /var/run/pscheduler-server/runner/tmp/tmp_4p16e83/tmpwtcvf04r/credentials --rsa-private-key-path /var/run/pscheduler-server/runner/tmp/tmp_4p16e83/tmpwtcvf04r/private-key\n\n{\n    \"end\": {\n        \"cpu_utilization_percent\": {\n            \"host_system\": 0.48706845929263237, \n            \"host_total\": 0.684638172797859, \n            \"host_user\": 0.19756971350522665, \n            \"remote_system\": 0, \n            \"remote_total\": 0, \n            \"remote_user\": 0\n        }, \n        \"receiver_tcp_congestion\": \"htcp\", \n        \"streams\": [\n            {\n                \"receiver\": {\n                    \"bits_per_second\": 11722426.728065632, \n                    \"bytes\": 14897024, \n                    \"end\": 10.166512, \n                    \"seconds\": 10.166512, \n                    \"sender\": false, \n                    \"socket\": 5, \n                    \"start\": 0\n                }, \n                \"sender\": {\n                    \"bits_per_second\": 0, \n                    \"bytes\": 0, \n                    \"end\": 10.166512, \n                    \"seconds\": 10.166512, \n                    \"sender\": false, \n                    \"socket\": 5, \n                    \"start\": 0\n                }\n            }\n        ], \n        \"sum_received\": {\n            \"bits_per_second\": 11722426.728065632, \n            \"bytes\": 14897024, \n            \"end\": 10.166512, \n            \"seconds\": 10.166512, \n            \"sender\": false, \n            \"start\": 0\n        }, \n        \"sum_sent\": {\n            \"bits_per_second\": 0, \n            \"bytes\": 0, \n            \"end\": 10.166512, \n            \"seconds\": 10.166512, \n            \"sender\": false, \n            \"start\": 0\n        }\n    }, \n    \"intervals\": [\n        {\n            \"streams\": [\n                {\n                    \"bits_per_second\": 6312939.089874302, \n                    \"bytes\": 789160, \n                    \"end\": 1.000054, \n                    \"omitted\": false, \n                    \"seconds\": 1.0000540018081665, \n                    \"sender\": false, \n                    \"socket\": 5, \n                    \"start\": 0\n                }\n            ], \n            \"sum\": {\n                \"bits_per_second\": 6312939.089874302, \n                \"bytes\": 789160, \n                \"end\": 1.000054, \n                \"omitted\": false, \n                \"seconds\": 1.0000540018081665, \n                \"sender\": false, \n                \"start\": 0\n            }\n        }, \n        {\n            \"streams\": [\n                {\n                    \"bits_per_second\": 17050999.588622477, \n                    \"bytes\": 2131456, \n                    \"end\": 2.000092, \n                    \"omitted\": false, \n                    \"seconds\": 1.0000380277633667, \n                    \"sender\": false, \n                    \"socket\": 5, \n                    \"start\": 1.000054\n                }\n            ], \n            \"sum\": {\n                \"bits_per_second\": 17050999.588622477, \n                \"bytes\": 2131456, \n                \"end\": 2.000092, \n                \"omitted\": false, \n                \"seconds\": 1.0000380277633667, \n                \"sender\": false, \n                \"start\": 1.000054\n            }\n        }, \n        {\n            \"streams\": [\n                {\n                    \"bits_per_second\": 12117215.732019275, \n                    \"bytes\": 1514608, \n                    \"end\": 3.000063, \n                    \"omitted\": false, \n                    \"seconds\": 0.9999709725379944, \n                    \"sender\": false, \n                    \"socket\": 5, \n                    \"start\": 2.000092\n                }\n            ], \n            \"sum\": {\n                \"bits_per_second\": 12117215.732019275, \n                \"bytes\": 1514608, \n                \"end\": 3.000063, \n                \"omitted\": false, \n                \"seconds\": 0.9999709725379944, \n                \"sender\": false, \n                \"start\": 2.000092\n            }\n        }, \n        {\n            \"streams\": [\n                {\n                    \"bits_per_second\": 10055032.464654291, \n                    \"bytes\": 1256864, \n                    \"end\": 4.000051, \n                    \"omitted\": false, \n                    \"seconds\": 0.9999880194664, \n                    \"sender\": false, \n                    \"socket\": 5, \n                    \"start\": 3.000063\n                }\n            ], \n            \"sum\": {\n                \"bits_per_second\": 10055032.464654291, \n                \"bytes\": 1256864, \n                \"end\": 4.000051, \n                \"omitted\": false, \n                \"seconds\": 0.9999880194664, \n                \"sender\": false, \n                \"start\": 3.000063\n            }\n        }, \n        {\n            \"streams\": [\n                {\n                    \"bits_per_second\": 9267506.022068037, \n                    \"bytes\": 1158400, \n                    \"end\": 5.000018, \n                    \"omitted\": false, \n                    \"seconds\": 0.9999669790267944, \n                    \"sender\": false, \n                    \"socket\": 5, \n                    \"start\": 4.000051\n                }\n            ], \n            \"sum\": {\n                \"bits_per_second\": 9267506.022068037, \n                \"bytes\": 1158400, \n                \"end\": 5.000018, \n                \"omitted\": false, \n                \"seconds\": 0.9999669790267944, \n                \"sender\": false, \n                \"start\": 4.000051\n            }\n        }, \n        {\n            \"streams\": [\n                {\n                    \"bits_per_second\": 9313126.332076963, \n                    \"bytes\": 1164192, \n                    \"end\": 6.000062, \n                    \"omitted\": false, \n                    \"seconds\": 1.0000439882278442, \n                    \"sender\": false, \n                    \"socket\": 5, \n                    \"start\": 5.000018\n                }\n            ], \n            \"sum\": {\n                \"bits_per_second\": 9313126.332076963, \n                \"bytes\": 1164192, \n                \"end\": 6.000062, \n                \"omitted\": false, \n                \"seconds\": 1.0000439882278442, \n                \"sender\": false, \n                \"start\": 5.000018\n            }\n        }, \n        {\n            \"streams\": [\n                {\n                    \"bits_per_second\": 12360128, \n                    \"bytes\": 1545016, \n                    \"end\": 7.000062, \n                    \"omitted\": false, \n                    \"seconds\": 1, \n                    \"sender\": false, \n                    \"socket\": 5, \n                    \"start\": 6.000062\n                }\n            ], \n            \"sum\": {\n                \"bits_per_second\": 12360128, \n                \"bytes\": 1545016, \n                \"end\": 7.000062, \n                \"omitted\": false, \n                \"seconds\": 1, \n                \"sender\": false, \n                \"start\": 6.000062\n            }\n        }, \n        {\n            \"streams\": [\n                {\n                    \"bits_per_second\": 13553442.377471797, \n                    \"bytes\": 1694160, \n                    \"end\": 8.00005, \n                    \"omitted\": false, \n                    \"seconds\": 0.9999880194664, \n                    \"sender\": false, \n                    \"socket\": 5, \n                    \"start\": 7.000062\n                }\n            ], \n            \"sum\": {\n                \"bits_per_second\": 13553442.377471797, \n                \"bytes\": 1694160, \n                \"end\": 8.00005, \n                \"omitted\": false, \n                \"seconds\": 0.9999880194664, \n                \"sender\": false, \n                \"start\": 7.000062\n            }\n        }, \n        {\n            \"streams\": [\n                {\n                    \"bits_per_second\": 15152039.079402786, \n                    \"bytes\": 1893984, \n                    \"end\": 9.000039, \n                    \"omitted\": false, \n                    \"seconds\": 0.9999889731407166, \n                    \"sender\": false, \n                    \"socket\": 5, \n                    \"start\": 8.00005\n                }\n            ], \n            \"sum\": {\n                \"bits_per_second\": 15152039.079402786, \n                \"bytes\": 1893984, \n                \"end\": 9.000039, \n                \"omitted\": false, \n                \"seconds\": 0.9999889731407166, \n                \"sender\": false, \n                \"start\": 8.00005\n            }\n        }, \n        {\n            \"streams\": [\n                {\n                    \"bits_per_second\": 12313435.30616243, \n                    \"bytes\": 1539224, \n                    \"end\": 10.000068, \n                    \"omitted\": false, \n                    \"seconds\": 1.0000289678573608, \n                    \"sender\": false, \n                    \"socket\": 5, \n                    \"start\": 9.000039\n                }\n            ], \n            \"sum\": {\n                \"bits_per_second\": 12313435.30616243, \n                \"bytes\": 1539224, \n                \"end\": 10.000068, \n                \"omitted\": false, \n                \"seconds\": 1.0000289678573608, \n                \"sender\": false, \n                \"start\": 9.000039\n            }\n        }, \n        {\n            \"streams\": [\n                {\n                    \"bits_per_second\": 10091562.110091185, \n                    \"bytes\": 209960, \n                    \"end\": 10.166512, \n                    \"omitted\": false, \n                    \"seconds\": 0.16644400358200073, \n                    \"sender\": false, \n                    \"socket\": 5, \n                    \"start\": 10.000068\n                }\n            ], \n            \"sum\": {\n                \"bits_per_second\": 10091562.110091185, \n                \"bytes\": 209960, \n                \"end\": 10.166512, \n                \"omitted\": false, \n                \"seconds\": 0.16644400358200073, \n                \"sender\": false, \n                \"start\": 10.000068\n            }\n        }\n    ], \n    \"start\": {\n        \"accepted_connection\": {\n            \"host\": \"172.16.0.2\", \n            \"port\": 38643\n        }, \n        \"connected\": [\n            {\n                \"local_host\": \"172.16.0.1\", \n                \"local_port\": 5201, \n                \"remote_host\": \"172.16.0.2\", \n                \"remote_port\": 42571, \n                \"socket\": 5\n            }\n        ], \n        \"cookie\": \"ztgvh44qmeb33lpqyyfcksadxf22ggpfhdd5\", \n        \"fq_rate\": 0, \n        \"rcvbuf_actual\": 87380, \n        \"sndbuf_actual\": 65536, \n        \"sock_bufsize\": 0, \n        \"system_info\": \"REDACTED\", \n        \"target_bitrate\": 0, \n        \"tcp_mss_default\": 0, \n        \"test_start\": {\n            \"bidir\": 0, \n            \"blksize\": 131072, \n            \"blocks\": 0, \n            \"bytes\": 0, \n            \"duration\": 10, \n            \"fqrate\": 0, \n            \"num_streams\": 1, \n            \"omit\": 0, \n            \"protocol\": \"TCP\", \n            \"reverse\": 0, \n            \"target_bitrate\": 0, \n            \"tos\": 0\n        }, \n        \"timestamp\": {\n            \"time\": \"Sat, 12 Oct 2024 02:32:18 GMT\", \n            \"timesecs\": 1728700338\n        }, \n        \"version\": \"iperf 3.14\"\n    }\n}\n","summary":{"streams":[{"end":10.000118,"rtt":193784,"start":0,"stream-id":5,"retransmits":295,"throughput-bits":14260465.326509146,"throughput-bytes":17825792}],"summary":{"end":10.000118,"start":0,"retransmits":295,"throughput-bits":14260465.326509146,"throughput-bytes":17825792,"receiver-throughput-bits":11722426.728065632}},"intervals":[{"streams":[{"end":1.000064,"rtt":287334,"start":0,"omitted":false,"stream-id":5,"retransmits":281,"tcp-window-size":266432,"throughput-bits":37746319.654683284,"throughput-bytes":4718592}],"summary":{"end":1.000064,"start":0,"omitted":false,"retransmits":281,"throughput-bits":37746319.654683284,"throughput-bytes":4718592}},{"streams":[{"end":2.000097,"rtt":160026,"start":1.000064,"omitted":false,"stream-id":5,"retransmits":4,"tcp-window-size":204168,"throughput-bits":10485413.761433134,"throughput-bytes":1310720}],"summary":{"end":2.000097,"start":1.000064,"omitted":false,"retransmits":4,"throughput-bits":10485413.761433134,"throughput-bytes":1310720}},{"streams":[{"end":3.000104,"rtt":130496,"start":2.000097,"omitted":false,"stream-id":5,"retransmits":0,"tcp-window-size":214304,"throughput-bits":20971372.50103741,"throughput-bytes":2621440}],"summary":{"end":3.000104,"start":2.000097,"omitted":false,"retransmits":0,"throughput-bits":20971372.50103741,"throughput-bytes":2621440}},{"streams":[{"end":4.000049,"rtt":212469,"start":3.000104,"omitted":false,"stream-id":5,"retransmits":0,"tcp-window-size":224440,"throughput-bits":10486336.906738574,"throughput-bytes":1310720}],"summary":{"end":4.000049,"start":3.000104,"omitted":false,"retransmits":0,"throughput-bits":10486336.906738574,"throughput-bytes":1310720}},{"streams":[{"end":5.001043,"rtt":154365,"start":4.000049,"omitted":false,"stream-id":5,"retransmits":0,"tcp-window-size":244712,"throughput-bits":0,"throughput-bytes":0}],"summary":{"end":5.001043,"start":4.000049,"omitted":false,"retransmits":0,"throughput-bits":0,"throughput-bytes":0}},{"streams":[{"end":6.000973,"rtt":249419,"start":5.001043,"omitted":false,"stream-id":5,"retransmits":0,"tcp-window-size":270776,"throughput-bits":10486493.801348375,"throughput-bytes":1310720}],"summary":{"end":6.000973,"start":5.001043,"omitted":false,"retransmits":0,"throughput-bits":10486493.801348375,"throughput-bytes":1310720}},{"streams":[{"end":7.000069,"rtt":202041,"start":6.000973,"omitted":false,"stream-id":5,"retransmits":0,"tcp-window-size":317112,"throughput-bits":20990495.904666547,"throughput-bytes":2621440}],"summary":{"end":7.000069,"start":6.000973,"omitted":false,"retransmits":0,"throughput-bits":20990495.904666547,"throughput-bytes":2621440}},{"streams":[{"end":8.000267,"rtt":244150,"start":7.000069,"omitted":false,"stream-id":5,"retransmits":0,"tcp-window-size":370688,"throughput-bits":10483684.161029879,"throughput-bytes":1310720}],"summary":{"end":8.000267,"start":7.000069,"omitted":false,"retransmits":0,"throughput-bits":10483684.161029879,"throughput-bytes":1310720}},{"streams":[{"end":9.000057,"rtt":139019,"start":8.000267,"omitted":false,"stream-id":5,"retransmits":10,"tcp-window-size":207064,"throughput-bits":10487962.337462597,"throughput-bytes":1310720}],"summary":{"end":9.000057,"start":8.000267,"omitted":false,"retransmits":10,"throughput-bits":10487962.337462597,"throughput-bytes":1310720}},{"streams":[{"end":10.000118,"rtt":158525,"start":9.000057,"omitted":false,"stream-id":5,"retransmits":0,"tcp-window-size":217200,"throughput-bits":10485120.039060116,"throughput-bytes":1310720}],"summary":{"end":10.000118,"start":9.000057,"omitted":false,"retransmits":0,"throughput-bits":10485120.039060116,"throughput-bytes":1310720}}],"succeeded":true}
