{"diags":"Participant 0:\n/usr/bin/iperf3 -p 5201 -B 172.16.0.2 -c 172.16.0.1 -t 30 --json --rsa-public-key-path /var/run/pscheduler-server/runner/tmp/tmpiuc2d62s/tmprksv3d7q/public-key --username sMyMYOIOpWJKxuhB5uBX\n\n{\n    \"end\": {\n        \"cpu_utilization_percent\": {\n            \"host_system\": 0.12947089084231556, \n            \"host_total\": 0.1648708295900567, \n            \"host_user\": 0.03540326081406504, \n            \"remote_system\": 2.589007738853126, \n            \"remote_total\": 3.0057762803183468, \n            \"remote_user\": 0.41676521991221865\n        }, \n        \"receiver_tcp_congestion\": \"htcp\", \n        \"sender_tcp_congestion\": \"htcp\", \n        \"streams\": [\n            {\n                \"receiver\": {\n                    \"bits_per_second\": 17523499.95462752, \n                    \"bytes\": 65946091, \n                    \"end\": 30.106356, \n                    \"seconds\": 30.000184, \n                    \"sender\": true, \n                    \"socket\": 5, \n                    \"start\": 0\n                }, \n                \"sender\": {\n                    \"bits_per_second\": 18594633.686246723, \n                    \"bytes\": 69730304, \n                    \"end\": 30.000184, \n                    \"max_rtt\": 146499, \n                    \"max_snd_cwnd\": 394834, \n                    \"max_snd_wnd\": 0, \n                    \"mean_rtt\": 91264, \n                    \"min_rtt\": 30799, \n                    \"retransmits\": 717, \n                    \"seconds\": 30.000184, \n                    \"sender\": true, \n                    \"socket\": 5, \n                    \"start\": 0\n                }\n            }\n        ], \n        \"sum_received\": {\n            \"bits_per_second\": 17523499.95462752, \n            \"bytes\": 65946091, \n            \"end\": 30.106356, \n            \"seconds\": 30.106356, \n            \"sender\": true, \n            \"start\": 0\n        }, \n        \"sum_sent\": {\n            \"bits_per_second\": 18594633.686246723, \n            \"bytes\": 69730304, \n            \"end\": 30.000184, \n            \"retransmits\": 717, \n            \"seconds\": 30.000184, \n            \"sender\": true, \n            \"start\": 0\n        }\n    }, \n    \"intervals\": [\n        {\n            \"streams\": [\n                {\n                    \"bits_per_second\": 54520557.5337485, \n                    \"bytes\": 6815744, \n                    \"end\": 1.000099, \n                    \"omitted\": false, \n                    \"pmtu\": 1500, \n                    \"retransmits\": 290, \n                    \"rtt\": 73633, \n                    \"rttvar\": 526, \n                    \"seconds\": 1.0000989437103271, \n                    \"sender\": true, \n                    \"snd_cwnd\": 202720, \n                    \"snd_wnd\": -1, \n                    \"socket\": 5, \n                    \"start\": 0\n                }\n            ], \n            \"sum\": {\n                \"bits_per_second\": 54520557.5337485, \n                \"bytes\": 6815744, \n                \"end\": 1.000099, \n                \"omitted\": false, \n                \"retransmits\": 290, \n                \"seconds\": 1.0000989437103271, \n                \"sender\": true, \n                \"start\": 0\n            }\n        }, \n        {\n            \"streams\": [\n                {\n                    \"bits_per_second\": 10480289.105902344, \n                    \"bytes\": 1310720, \n                    \"end\": 2.000621, \n                    \"omitted\": false, \n                    \"pmtu\": 1500, \n                    \"retransmits\": 1, \n                    \"rtt\": 78086, \n                    \"rttvar\": 492, \n                    \"seconds\": 1.0005220174789429, \n                    \"sender\": true, \n                    \"snd_cwnd\": 1448, \n                    \"snd_wnd\": -1, \n                    \"socket\": 5, \n                    \"start\": 1.000099\n                }\n            ], \n            \"sum\": {\n                \"bits_per_second\": 10480289.105902344, \n                \"bytes\": 1310720, \n                \"end\": 2.000621, \n                \"omitted\": false, \n                \"retransmits\": 1, \n                \"seconds\": 1.0005220174789429, \n                \"sender\": true, \n                \"start\": 1.000099\n            }\n        }, \n        {\n            \"streams\": [\n                {\n                    \"bits_per_second\": 0, \n                    \"bytes\": 0, \n                    \"end\": 3.001064, \n                    \"omitted\": false, \n                    \"pmtu\": 1500, \n                    \"retransmits\": 1, \n                    \"rtt\": 78086, \n                    \"rttvar\": 492, \n                    \"seconds\": 1.0004429817199707, \n                    \"sender\": true, \n                    \"snd_cwnd\": 1448, \n                    \"snd_wnd\": -1, \n                    \"socket\": 5, \n                    \"start\": 2.000621\n                }\n            ], \n            \"sum\": {\n                \"bits_per_second\": 0, \n                \"bytes\": 0, \n                \"end\": 3.001064, \n                \"omitted\": false, \n                \"retransmits\": 1, \n                \"seconds\": 1.0004429817199707, \n                \"sender\": true, \n                \"start\": 2.000621\n            }\n        }, \n        {\n            \"streams\": [\n                {\n                    \"bits_per_second\": 0, \n                    \"bytes\": 0, \n                    \"end\": 4.00106, \n                    \"omitted\": false, \n                    \"pmtu\": 1500, \n                    \"retransmits\": 1, \n                    \"rtt\": 78086, \n                    \"rttvar\": 492, \n                    \"seconds\": 0.9999960064888, \n                    \"sender\": true, \n                    \"snd_cwnd\": 1448, \n                    \"snd_wnd\": -1, \n                    \"socket\": 5, \n                    \"start\": 3.001064\n                }\n            ], \n            \"sum\": {\n                \"bits_per_second\": 0, \n                \"bytes\": 0, \n                \"end\": 4.00106, \n                \"omitted\": false, \n                \"retransmits\": 1, \n                \"seconds\": 0.9999960064888, \n                \"sender\": true, \n                \"start\": 3.001064\n            }\n        }, \n        {\n            \"streams\": [\n                {\n                    \"bits_per_second\": 0, \n                    \"bytes\": 0, \n                    \"end\": 5.000174, \n                    \"omitted\": false, \n                    \"pmtu\": 1500, \n                    \"retransmits\": 0, \n                    \"rtt\": 78086, \n                    \"rttvar\": 492, \n                    \"seconds\": 0.9991139769554138, \n                    \"sender\": true, \n                    \"snd_cwnd\": 1448, \n                    \"snd_wnd\": -1, \n                    \"socket\": 5, \n                    \"start\": 4.00106\n                }\n            ], \n            \"sum\": {\n                \"bits_per_second\": 0, \n                \"bytes\": 0, \n                \"end\": 5.000174, \n                \"omitted\": false, \n                \"retransmits\": 0, \n                \"seconds\": 0.9991139769554138, \n                \"sender\": true, \n                \"start\": 4.00106\n            }\n        }, \n        {\n            \"streams\": [\n                {\n                    \"bits_per_second\": 0, \n                    \"bytes\": 0, \n                    \"end\": 6.000491, \n                    \"omitted\": false, \n                    \"pmtu\": 1500, \n                    \"retransmits\": 9, \n                    \"rtt\": 48600, \n                    \"rttvar\": 7165, \n                    \"seconds\": 1.0003169775009155, \n                    \"sender\": true, \n                    \"snd_cwnd\": 5120, \n                    \"snd_wnd\": -1, \n                    \"socket\": 5, \n                    \"start\": 5.000174\n                }\n            ], \n            \"sum\": {\n                \"bits_per_second\": 0, \n                \"bytes\": 0, \n                \"end\": 6.000491, \n                \"omitted\": false, \n                \"retransmits\": 9, \n                \"seconds\": 1.0003169775009155, \n                \"sender\": true, \n                \"start\": 5.000174\n            }\n        }, \n        {\n            \"streams\": [\n                {\n                    \"bits_per_second\": 10489294.941291694, \n                    \"bytes\": 1310720, \n                    \"end\": 7.000154, \n                    \"omitted\": false, \n                    \"pmtu\": 1500, \n                    \"retransmits\": 221, \n                    \"rtt\": 44841, \n                    \"rttvar\": 928, \n                    \"seconds\": 0.99966299533844, \n                    \"sender\": true, \n                    \"snd_cwnd\": 125367, \n                    \"snd_wnd\": -1, \n                    \"socket\": 5, \n                    \"start\": 6.000491\n                }\n            ], \n            \"sum\": {\n                \"bits_per_second\": 10489294.941291694, \n                \"bytes\": 1310720, \n                \"end\": 7.000154, \n                \"omitted\": false, \n                \"retransmits\": 221, \n                \"seconds\": 0.99966299533844, \n                \"sender\": true, \n                \"start\": 6.000491\n            }\n        }, \n        {\n            \"streams\": [\n                {\n                    \"bits_per_second\": 31459892.091880083, \n                    \"bytes\": 3932160, \n                    \"end\": 8.000071, \n                    \"omitted\": false, \n                    \"pmtu\": 1500, \n                    \"retransmits\": 0, \n                    \"rtt\": 55145, \n                    \"rttvar\": 760, \n                    \"seconds\": 0.999916970729828, \n                    \"sender\": true, \n                    \"snd_cwnd\": 152746, \n                    \"snd_wnd\": -1, \n                    \"socket\": 5, \n                    \"start\": 7.000154\n                }\n            ], \n            \"sum\": {\n                \"bits_per_second\": 31459892.091880083, \n                \"bytes\": 3932160, \n                \"end\": 8.000071, \n                \"omitted\": false, \n                \"retransmits\": 0, \n                \"seconds\": 0.999916970729828, \n                \"sender\": true, \n                \"start\": 7.000154\n            }\n        }, \n        {\n            \"streams\": [\n                {\n                    \"bits_per_second\": 20970932.51645787, \n                    \"bytes\": 2621440, \n                    \"end\": 9.000099, \n                    \"omitted\": false, \n                    \"pmtu\": 1500, \n                    \"retransmits\": 0, \n                    \"rtt\": 65694, \n                    \"rttvar\": 713, \n                    \"seconds\": 1.0000280141830444, \n                    \"sender\": true, \n                    \"snd_cwnd\": 181566, \n                    \"snd_wnd\": -1, \n                    \"socket\": 5, \n                    \"start\": 8.000071\n                }\n            ], \n            \"sum\": {\n                \"bits_per_second\": 20970932.51645787, \n                \"bytes\": 2621440, \n                \"end\": 9.000099, \n                \"omitted\": false, \n                \"retransmits\": 0, \n                \"seconds\": 1.0000280141830444, \n                \"sender\": true, \n                \"start\": 8.000071\n            }\n        }, \n        {\n            \"streams\": [\n                {\n                    \"bits_per_second\": 20971057.51019962, \n                    \"bytes\": 2621440, \n                    \"end\": 10.000121, \n                    \"omitted\": false, \n                    \"pmtu\": 1500, \n                    \"retransmits\": 0, \n                    \"rtt\": 81957, \n                    \"rttvar\": 698, \n                    \"seconds\": 1.000022053718567, \n                    \"sender\": true, \n                    \"snd_cwnd\": 227678, \n                    \"snd_wnd\": -1, \n                    \"socket\": 5, \n                    \"start\": 9.000099\n                }\n            ], \n            \"sum\": {\n                \"bits_per_second\": 20971057.51019962, \n                \"bytes\": 2621440, \n                \"end\": 10.000121, \n                \"omitted\": false, \n                \"retransmits\": 0, \n                \"seconds\": 1.000022053718567, \n                \"sender\": true, \n                \"start\": 9.000099\n            }\n        }, \n        {\n            \"streams\": [\n                {\n                    \"bits_per_second\": 20971037.51110081, \n                    \"bytes\": 2621440, \n                    \"end\": 11.000144, \n                    \"omitted\": false, \n                    \"pmtu\": 1500, \n                    \"retransmits\": 0, \n                    \"rtt\": 102483, \n                    \"rttvar\": 745, \n                    \"seconds\": 1.0000230073928833, \n                    \"sender\": true, \n                    \"snd_cwnd\": 283877, \n                    \"snd_wnd\": -1, \n                    \"socket\": 5, \n                    \"start\": 10.000121\n                }\n            ], \n            \"sum\": {\n                \"bits_per_second\": 20971037.51110081, \n                \"bytes\": 2621440, \n                \"end\": 11.000144, \n                \"omitted\": false, \n                \"retransmits\": 0, \n                \"seconds\": 1.0000230073928833, \n                \"sender\": true, \n                \"start\": 10.000121\n            }\n        }, \n        {\n            \"streams\": [\n                {\n                    \"bits_per_second\": 20971100.00841124, \n                    \"bytes\": 2621440, \n                    \"end\": 12.000164, \n                    \"omitted\": false, \n                    \"pmtu\": 1500, \n                    \"retransmits\": 0, \n                    \"rtt\": 124478, \n                    \"rttvar\": 767, \n                    \"seconds\": 1.0000200271606445, \n                    \"sender\": true, \n                    \"snd_cwnd\": 347281, \n                    \"snd_wnd\": -1, \n                    \"socket\": 5, \n                    \"start\": 11.000144\n                }\n            ], \n            \"sum\": {\n                \"bits_per_second\": 20971100.00841124, \n                \"bytes\": 2621440, \n                \"end\": 12.000164, \n                \"omitted\": false, \n                \"retransmits\": 0, \n                \"seconds\": 1.0000200271606445, \n                \"sender\": true, \n                \"start\": 11.000144\n            }\n        }, \n        {\n            \"streams\": [\n                {\n                    \"bits_per_second\": 20971080.009231374, \n                    \"bytes\": 2621440, \n                    \"end\": 13.000185, \n                    \"omitted\": false, \n                    \"pmtu\": 1500, \n                    \"retransmits\": 5, \n                    \"rtt\": 146499, \n                    \"rttvar\": 591, \n                    \"seconds\": 1.000020980834961, \n                    \"sender\": true, \n                    \"snd_cwnd\": 224796, \n                    \"snd_wnd\": -1, \n                    \"socket\": 5, \n                    \"start\": 12.000164\n                }\n            ], \n            \"sum\": {\n                \"bits_per_second\": 20971080.009231374, \n                \"bytes\": 2621440, \n                \"end\": 13.000185, \n                \"omitted\": false, \n                \"retransmits\": 5, \n                \"seconds\": 1.000020980834961, \n                \"sender\": true, \n                \"start\": 12.000164\n            }\n        }, \n        {\n            \"streams\": [\n                {\n                    \"bits_per_second\": 20970200.083078876, \n                    \"bytes\": 2621440, \n                    \"end\": 14.000248, \n                    \"omitted\": false, \n                    \"pmtu\": 1500, \n                    \"retransmits\": 1, \n                    \"rtt\": 79783, \n                    \"rttvar\": 242, \n                    \"seconds\": 1.0000629425048828, \n                    \"sender\": true, \n                    \"snd_cwnd\": 219032, \n                    \"snd_wnd\": -1, \n                    \"socket\": 5, \n                    \"start\": 13.000185\n                }\n            ], \n            \"sum\": {\n                \"bits_per_second\": 20970200.083078876, \n                \"bytes\": 2621440, \n                \"end\": 14.000248, \n                \"omitted\": false, \n                \"retransmits\": 1, \n                \"seconds\": 1.0000629425048828, \n                \"sender\": true, \n                \"start\": 13.000185\n            }\n        }, \n        {\n            \"streams\": [\n                {\n                    \"bits_per_second\": 20970932.51645787, \n                    \"bytes\": 2621440, \n                    \"end\": 15.000276, \n                    \"omitted\": false, \n                    \"pmtu\": 1500, \n                    \"retransmits\": 0, \n                    \"rtt\": 86148, \n                    \"rttvar\": 437, \n                    \"seconds\": 1.0000280141830444, \n                    \"sender\": true, \n                    \"snd_cwnd\": 236324, \n                    \"snd_wnd\": -1, \n                    \"socket\": 5, \n                    \"start\": 14.000248\n                }\n            ], \n            \"sum\": {\n                \"bits_per_second\": 20970932.51645787, \n                \"bytes\": 2621440, \n                \"end\": 15.000276, \n                \"omitted\": false, \n                \"retransmits\": 0, \n                \"seconds\": 1.0000280141830444, \n                \"sender\": true, \n                \"start\": 14.000248\n            }\n        }, \n        {\n            \"streams\": [\n                {\n                    \"bits_per_second\": 20970827.522866268, \n                    \"bytes\": 2621440, \n                    \"end\": 16.000309, \n                    \"omitted\": false, \n                    \"pmtu\": 1500, \n                    \"retransmits\": 0, \n                    \"rtt\": 93301, \n                    \"rttvar\": 897, \n                    \"seconds\": 1.0000330209732056, \n                    \"sender\": true, \n                    \"snd_cwnd\": 256498, \n                    \"snd_wnd\": -1, \n                    \"socket\": 5, \n                    \"start\": 15.000276\n                }\n            ], \n            \"sum\": {\n                \"bits_per_second\": 20970827.522866268, \n                \"bytes\": 2621440, \n                \"end\": 16.000309, \n                \"omitted\": false, \n                \"retransmits\": 0, \n                \"seconds\": 1.0000330209732056, \n                \"sender\": true, \n                \"start\": 15.000276\n            }\n        }, \n        {\n            \"streams\": [\n                {\n                    \"bits_per_second\": 20970765.02717993, \n                    \"bytes\": 2621440, \n                    \"end\": 17.000345, \n                    \"omitted\": false, \n                    \"pmtu\": 1500, \n                    \"retransmits\": 0, \n                    \"rtt\": 105214, \n                    \"rttvar\": 648, \n                    \"seconds\": 1.0000360012054443, \n                    \"sender\": true, \n                    \"snd_cwnd\": 291082, \n                    \"snd_wnd\": -1, \n                    \"socket\": 5, \n                    \"start\": 16.000309\n                }\n            ], \n            \"sum\": {\n                \"bits_per_second\": 20970765.02717993, \n                \"bytes\": 2621440, \n                \"end\": 17.000345, \n                \"omitted\": false, \n                \"retransmits\": 0, \n                \"seconds\": 1.0000360012054443, \n                \"sender\": true, \n                \"start\": 16.000309\n            }\n        }, \n        {\n            \"streams\": [\n                {\n                    \"bits_per_second\": 20971227.504079584, \n                    \"bytes\": 2621440, \n                    \"end\": 18.000359, \n                    \"omitted\": false, \n                    \"pmtu\": 1500, \n                    \"retransmits\": 0, \n                    \"rtt\": 122588, \n                    \"rttvar\": 637, \n                    \"seconds\": 1.0000139474868774, \n                    \"sender\": true, \n                    \"snd_cwnd\": 338635, \n                    \"snd_wnd\": -1, \n                    \"socket\": 5, \n                    \"start\": 17.000345\n                }\n            ], \n            \"sum\": {\n                \"bits_per_second\": 20971227.504079584, \n                \"bytes\": 2621440, \n                \"end\": 18.000359, \n                \"omitted\": false, \n                \"retransmits\": 0, \n                \"seconds\": 1.0000139474868774, \n                \"sender\": true, \n                \"start\": 17.000345\n            }\n        }, \n        {\n            \"streams\": [\n                {\n                    \"bits_per_second\": 20970785.025759034, \n                    \"bytes\": 2621440, \n                    \"end\": 19.000394, \n                    \"omitted\": false, \n                    \"pmtu\": 1500, \n                    \"retransmits\": 0, \n                    \"rtt\": 142377, \n                    \"rttvar\": 572, \n                    \"seconds\": 1.000035047531128, \n                    \"sender\": true, \n                    \"snd_cwnd\": 394834, \n                    \"snd_wnd\": -1, \n                    \"socket\": 5, \n                    \"start\": 18.000359\n                }\n            ], \n            \"sum\": {\n                \"bits_per_second\": 20970785.025759034, \n                \"bytes\": 2621440, \n                \"end\": 19.000394, \n                \"omitted\": false, \n                \"retransmits\": 0, \n                \"seconds\": 1.000035047531128, \n                \"sender\": true, \n                \"start\": 18.000359\n            }\n        }, \n        {\n            \"streams\": [\n                {\n                    \"bits_per_second\": 20970387.561153747, \n                    \"bytes\": 2621440, \n                    \"end\": 20.000448, \n                    \"omitted\": false, \n                    \"pmtu\": 1500, \n                    \"retransmits\": 6, \n                    \"rtt\": 77685, \n                    \"rttvar\": 208, \n                    \"seconds\": 1.0000540018081665, \n                    \"sender\": true, \n                    \"snd_cwnd\": 213268, \n                    \"snd_wnd\": -1, \n                    \"socket\": 5, \n                    \"start\": 19.000394\n                }\n            ], \n            \"sum\": {\n                \"bits_per_second\": 20970387.561153747, \n                \"bytes\": 2621440, \n                \"end\": 20.000448, \n                \"omitted\": false, \n                \"retransmits\": 6, \n                \"seconds\": 1.0000540018081665, \n                \"sender\": true, \n                \"start\": 19.000394\n            }\n        }, \n        {\n            \"streams\": [\n                {\n                    \"bits_per_second\": 20970745.028638974, \n                    \"bytes\": 2621440, \n                    \"end\": 21.000485, \n                    \"omitted\": false, \n                    \"pmtu\": 1500, \n                    \"retransmits\": 0, \n                    \"rtt\": 84214, \n                    \"rttvar\": 521, \n                    \"seconds\": 1.0000369548797607, \n                    \"sender\": true, \n                    \"snd_cwnd\": 230560, \n                    \"snd_wnd\": -1, \n                    \"socket\": 5, \n                    \"start\": 20.000448\n                }\n            ], \n            \"sum\": {\n                \"bits_per_second\": 20970745.028638974, \n                \"bytes\": 2621440, \n                \"end\": 21.000485, \n                \"omitted\": false, \n                \"retransmits\": 0, \n                \"seconds\": 1.0000369548797607, \n                \"sender\": true, \n                \"start\": 20.000448\n            }\n        }, \n        {\n            \"streams\": [\n                {\n                    \"bits_per_second\": 20971080.009231374, \n                    \"bytes\": 2621440, \n                    \"end\": 22.000506, \n                    \"omitted\": false, \n                    \"pmtu\": 1500, \n                    \"retransmits\": 0, \n                    \"rtt\": 90093, \n                    \"rttvar\": 537, \n                    \"seconds\": 1.000020980834961, \n                    \"sender\": true, \n                    \"snd_cwnd\": 246411, \n                    \"snd_wnd\": -1, \n                    \"socket\": 5, \n                    \"start\": 21.000485\n                }\n            ], \n            \"sum\": {\n                \"bits_per_second\": 20971080.009231374, \n                \"bytes\": 2621440, \n                \"end\": 22.000506, \n                \"omitted\": false, \n                \"retransmits\": 0, \n                \"seconds\": 1.000020980834961, \n                \"sender\": true, \n                \"start\": 21.000485\n            }\n        }, \n        {\n            \"streams\": [\n                {\n                    \"bits_per_second\": 20970765.02717993, \n                    \"bytes\": 2621440, \n                    \"end\": 23.000542, \n                    \"omitted\": false, \n                    \"pmtu\": 1500, \n                    \"retransmits\": 0, \n                    \"rtt\": 101214, \n                    \"rttvar\": 570, \n                    \"seconds\": 1.0000360012054443, \n                    \"sender\": true, \n                    \"snd_cwnd\": 279554, \n                    \"snd_wnd\": -1, \n                    \"socket\": 5, \n                    \"start\": 22.000506\n                }\n            ], \n            \"sum\": {\n                \"bits_per_second\": 20970765.02717993, \n                \"bytes\": 2621440, \n                \"end\": 23.000542, \n                \"omitted\": false, \n                \"retransmits\": 0, \n                \"seconds\": 1.0000360012054443, \n                \"sender\": true, \n                \"start\": 22.000506\n            }\n        }, \n        {\n            \"streams\": [\n                {\n                    \"bits_per_second\": 31471033.51057646, \n                    \"bytes\": 3932160, \n                    \"end\": 24.000105, \n                    \"omitted\": false, \n                    \"pmtu\": 1500, \n                    \"retransmits\": 0, \n                    \"rtt\": 117717, \n                    \"rttvar\": 774, \n                    \"seconds\": 0.999562978744507, \n                    \"sender\": true, \n                    \"snd_cwnd\": 324225, \n                    \"snd_wnd\": -1, \n                    \"socket\": 5, \n                    \"start\": 23.000542\n                }\n            ], \n            \"sum\": {\n                \"bits_per_second\": 31471033.51057646, \n                \"bytes\": 3932160, \n                \"end\": 24.000105, \n                \"omitted\": false, \n                \"retransmits\": 0, \n                \"seconds\": 0.999562978744507, \n                \"sender\": true, \n                \"start\": 23.000542\n            }\n        }, \n        {\n            \"streams\": [\n                {\n                    \"bits_per_second\": 20970912.517597463, \n                    \"bytes\": 2621440, \n                    \"end\": 25.000134, \n                    \"omitted\": false, \n                    \"pmtu\": 1500, \n                    \"retransmits\": 0, \n                    \"rtt\": 136020, \n                    \"rttvar\": 838, \n                    \"seconds\": 1.0000289678573608, \n                    \"sender\": true, \n                    \"snd_cwnd\": 377542, \n                    \"snd_wnd\": -1, \n                    \"socket\": 5, \n                    \"start\": 24.000105\n                }\n            ], \n            \"sum\": {\n                \"bits_per_second\": 20970912.517597463, \n                \"bytes\": 2621440, \n                \"end\": 25.000134, \n                \"omitted\": false, \n                \"retransmits\": 0, \n                \"seconds\": 1.0000289678573608, \n                \"sender\": true, \n                \"start\": 24.000105\n            }\n        }, \n        {\n            \"streams\": [\n                {\n                    \"bits_per_second\": 10480761.134240855, \n                    \"bytes\": 1310720, \n                    \"end\": 26.000611, \n                    \"omitted\": false, \n                    \"pmtu\": 1500, \n                    \"retransmits\": 6, \n                    \"rtt\": 146067, \n                    \"rttvar\": 928, \n                    \"seconds\": 1.0004769563674927, \n                    \"sender\": true, \n                    \"snd_cwnd\": 1441, \n                    \"snd_wnd\": -1, \n                    \"socket\": 5, \n                    \"start\": 25.000134\n                }\n            ], \n            \"sum\": {\n                \"bits_per_second\": 10480761.134240855, \n                \"bytes\": 1310720, \n                \"end\": 26.000611, \n                \"omitted\": false, \n                \"retransmits\": 6, \n                \"seconds\": 1.0004769563674927, \n                \"sender\": true, \n                \"start\": 25.000134\n            }\n        }, \n        {\n            \"streams\": [\n                {\n                    \"bits_per_second\": 20982031.516028177, \n                    \"bytes\": 2621440, \n                    \"end\": 27.00011, \n                    \"omitted\": false, \n                    \"pmtu\": 1500, \n                    \"retransmits\": 176, \n                    \"rtt\": 78481, \n                    \"rttvar\": 677, \n                    \"seconds\": 0.999499022960663, \n                    \"sender\": true, \n                    \"snd_cwnd\": 214709, \n                    \"snd_wnd\": -1, \n                    \"socket\": 5, \n                    \"start\": 26.000611\n                }\n            ], \n            \"sum\": {\n                \"bits_per_second\": 20982031.516028177, \n                \"bytes\": 2621440, \n                \"end\": 27.00011, \n                \"omitted\": false, \n                \"retransmits\": 176, \n                \"seconds\": 0.999499022960663, \n                \"sender\": true, \n                \"start\": 26.000611\n            }\n        }, \n        {\n            \"streams\": [\n                {\n                    \"bits_per_second\": 10480331.561737567, \n                    \"bytes\": 1310720, \n                    \"end\": 28.000628, \n                    \"omitted\": false, \n                    \"pmtu\": 1500, \n                    \"retransmits\": 0, \n                    \"rtt\": 30799, \n                    \"rttvar\": 4150, \n                    \"seconds\": 1.0005179643630981, \n                    \"sender\": true, \n                    \"snd_cwnd\": 226237, \n                    \"snd_wnd\": -1, \n                    \"socket\": 5, \n                    \"start\": 27.00011\n                }\n            ], \n            \"sum\": {\n                \"bits_per_second\": 10480331.561737567, \n                \"bytes\": 1310720, \n                \"end\": 28.000628, \n                \"omitted\": false, \n                \"retransmits\": 0, \n                \"seconds\": 1.0005179643630981, \n                \"sender\": true, \n                \"start\": 27.00011\n            }\n        }, \n        {\n            \"streams\": [\n                {\n                    \"bits_per_second\": 20981926.41127039, \n                    \"bytes\": 2621440, \n                    \"end\": 29.000132, \n                    \"omitted\": false, \n                    \"pmtu\": 1500, \n                    \"retransmits\": 0, \n                    \"rtt\": 88610, \n                    \"rttvar\": 603, \n                    \"seconds\": 0.999504029750824, \n                    \"sender\": true, \n                    \"snd_cwnd\": 243529, \n                    \"snd_wnd\": -1, \n                    \"socket\": 5, \n                    \"start\": 28.000628\n                }\n            ], \n            \"sum\": {\n                \"bits_per_second\": 20981926.41127039, \n                \"bytes\": 2621440, \n                \"end\": 29.000132, \n                \"omitted\": false, \n                \"retransmits\": 0, \n                \"seconds\": 0.999504029750824, \n                \"sender\": true, \n                \"start\": 28.000628\n            }\n        }, \n        {\n            \"streams\": [\n                {\n                    \"bits_per_second\": 20970430.05665008, \n                    \"bytes\": 2621440, \n                    \"end\": 30.000184, \n                    \"omitted\": false, \n                    \"pmtu\": 1500, \n                    \"retransmits\": 0, \n                    \"rtt\": 101937, \n                    \"rttvar\": 329, \n                    \"seconds\": 1.0000519752502441, \n                    \"sender\": true, \n                    \"snd_cwnd\": 280995, \n                    \"snd_wnd\": -1, \n                    \"socket\": 5, \n                    \"start\": 29.000132\n                }\n            ], \n            \"sum\": {\n                \"bits_per_second\": 20970430.05665008, \n                \"bytes\": 2621440, \n                \"end\": 30.000184, \n                \"omitted\": false, \n                \"retransmits\": 0, \n                \"seconds\": 1.0000519752502441, \n                \"sender\": true, \n                \"start\": 29.000132\n            }\n        }\n    ], \n    \"start\": {\n        \"connected\": [\n            {\n                \"local_host\": \"172.16.0.2\", \n                \"local_port\": 46179, \n                \"remote_host\": \"172.16.0.1\", \n                \"remote_port\": 5201, \n                \"socket\": 5\n            }\n        ], \n        \"connecting_to\": {\n            \"host\": \"172.16.0.1\", \n            \"port\": 5201\n        }, \n        \"cookie\": \"3ezavtdwdfyah4rjpg6qh4jntbkrc4ek7yhf\", \n        \"fq_rate\": 0, \n        \"rcvbuf_actual\": 87380, \n        \"sndbuf_actual\": 65536, \n        \"sock_bufsize\": 0, \n        \"system_info\": \"REDACTED\", \n        \"target_bitrate\": 0, \n        \"tcp_mss_default\": 1448, \n        \"test_start\": {\n            \"bidir\": 0, \n            \"blksize\": 131072, \n            \"blocks\": 0, \n            \"bytes\": 0, \n            \"duration\": 30, \n            \"fqrate\": 0, \n            \"num_streams\": 1, \n            \"omit\": 0, \n            \"protocol\": \"TCP\", \n            \"reverse\": 0, \n            \"target_bitrate\": 0, \n            \"tos\": 0\n        }, \n        \"timestamp\": {\n            \"time\": \"Thu, 09 May 2024 01:28:52 GMT\", \n            \"timesecs\": 1715218132\n        }, \n        \"version\": \"iperf 3.14\"\n    }\n}\nParticipant 1:\n/usr/bin/iperf3 -s -1 --idle-timeout 30 --json -p 5201 -B 172.16.0.1 --authorized-users-path /var/run/pscheduler-server/runner/tmp/tmpuc9bqaf0/tmp7hpc03ah/credentials --rsa-private-key-path /var/run/pscheduler-server/runner/tmp/tmpuc9bqaf0/tmp7hpc03ah/private-key\n","summary":{"streams":[{"end":30.000184,"rtt":91264,"start":0,"stream-id":5,"retransmits":717,"throughput-bits":18594633.686246723,"throughput-bytes":69730304}],"summary":{"end":30.000184,"start":0,"retransmits":717,"throughput-bits":18594633.686246723,"throughput-bytes":69730304,"receiver-throughput-bits":17523499.95462752}},"intervals":[{"streams":[{"end":1.000099,"rtt":73633,"start":0,"omitted":false,"stream-id":5,"retransmits":290,"tcp-window-size":202720,"throughput-bits":54520557.5337485,"throughput-bytes":6815744}],"summary":{"end":1.000099,"start":0,"omitted":false,"retransmits":290,"throughput-bits":54520557.5337485,"throughput-bytes":6815744}},{"streams":[{"end":2.000621,"rtt":78086,"start":1.000099,"omitted":false,"stream-id":5,"retransmits":1,"tcp-window-size":1448,"throughput-bits":10480289.105902344,"throughput-bytes":1310720}],"summary":{"end":2.000621,"start":1.000099,"omitted":false,"retransmits":1,"throughput-bits":10480289.105902344,"throughput-bytes":1310720}},{"streams":[{"end":3.001064,"rtt":78086,"start":2.000621,"omitted":false,"stream-id":5,"retransmits":1,"tcp-window-size":1448,"throughput-bits":0,"throughput-bytes":0}],"summary":{"end":3.001064,"start":2.000621,"omitted":false,"retransmits":1,"throughput-bits":0,"throughput-bytes":0}},{"streams":[{"end":4.00106,"rtt":78086,"start":3.001064,"omitted":false,"stream-id":5,"retransmits":1,"tcp-window-size":1448,"throughput-bits":0,"throughput-bytes":0}],"summary":{"end":4.00106,"start":3.001064,"omitted":false,"retransmits":1,"throughput-bits":0,"throughput-bytes":0}},{"streams":[{"end":5.000174,"rtt":78086,"start":4.00106,"omitted":false,"stream-id":5,"retransmits":0,"tcp-window-size":1448,"throughput-bits":0,"throughput-bytes":0}],"summary":{"end":5.000174,"start":4.00106,"omitted":false,"retransmits":0,"throughput-bits":0,"throughput-bytes":0}},{"streams":[{"end":6.000491,"rtt":48600,"start":5.000174,"omitted":false,"stream-id":5,"retransmits":9,"tcp-window-size":5120,"throughput-bits":0,"throughput-bytes":0}],"summary":{"end":6.000491,"start":5.000174,"omitted":false,"retransmits":9,"throughput-bits":0,"throughput-bytes":0}},{"streams":[{"end":7.000154,"rtt":44841,"start":6.000491,"omitted":false,"stream-id":5,"retransmits":221,"tcp-window-size":125367,"throughput-bits":10489294.941291694,"throughput-bytes":1310720}],"summary":{"end":7.000154,"start":6.000491,"omitted":false,"retransmits":221,"throughput-bits":10489294.941291694,"throughput-bytes":1310720}},{"streams":[{"end":8.000071,"rtt":55145,"start":7.000154,"omitted":false,"stream-id":5,"retransmits":0,"tcp-window-size":152746,"throughput-bits":31459892.091880083,"throughput-bytes":3932160}],"summary":{"end":8.000071,"start":7.000154,"omitted":false,"retransmits":0,"throughput-bits":31459892.091880083,"throughput-bytes":3932160}},{"streams":[{"end":9.000099,"rtt":65694,"start":8.000071,"omitted":false,"stream-id":5,"retransmits":0,"tcp-window-size":181566,"throughput-bits":20970932.51645787,"throughput-bytes":2621440}],"summary":{"end":9.000099,"start":8.000071,"omitted":false,"retransmits":0,"throughput-bits":20970932.51645787,"throughput-bytes":2621440}},{"streams":[{"end":10.000121,"rtt":81957,"start":9.000099,"omitted":false,"stream-id":5,"retransmits":0,"tcp-window-size":227678,"throughput-bits":20971057.51019962,"throughput-bytes":2621440}],"summary":{"end":10.000121,"start":9.000099,"omitted":false,"retransmits":0,"throughput-bits":20971057.51019962,"throughput-bytes":2621440}},{"streams":[{"end":11.000144,"rtt":102483,"start":10.000121,"omitted":false,"stream-id":5,"retransmits":0,"tcp-window-size":283877,"throughput-bits":20971037.51110081,"throughput-bytes":2621440}],"summary":{"end":11.000144,"start":10.000121,"omitted":false,"retransmits":0,"throughput-bits":20971037.51110081,"throughput-bytes":2621440}},{"streams":[{"end":12.000164,"rtt":124478,"start":11.000144,"omitted":false,"stream-id":5,"retransmits":0,"tcp-window-size":347281,"throughput-bits":20971100.00841124,"throughput-bytes":2621440}],"summary":{"end":12.000164,"start":11.000144,"omitted":false,"retransmits":0,"throughput-bits":20971100.00841124,"throughput-bytes":2621440}},{"streams":[{"end":13.000185,"rtt":146499,"start":12.000164,"omitted":false,"stream-id":5,"retransmits":5,"tcp-window-size":224796,"throughput-bits":20971080.009231374,"throughput-bytes":2621440}],"summary":{"end":13.000185,"start":12.000164,"omitted":false,"retransmits":5,"throughput-bits":20971080.009231374,"throughput-bytes":2621440}},{"streams":[{"end":14.000248,"rtt":79783,"start":13.000185,"omitted":false,"stream-id":5,"retransmits":1,"tcp-window-size":219032,"throughput-bits":20970200.083078876,"throughput-bytes":2621440}],"summary":{"end":14.000248,"start":13.000185,"omitted":false,"retransmits":1,"throughput-bits":20970200.083078876,"throughput-bytes":2621440}},{"streams":[{"end":15.000276,"rtt":86148,"start":14.000248,"omitted":false,"stream-id":5,"retransmits":0,"tcp-window-size":236324,"throughput-bits":20970932.51645787,"throughput-bytes":2621440}],"summary":{"end":15.000276,"start":14.000248,"omitted":false,"retransmits":0,"throughput-bits":20970932.51645787,"throughput-bytes":2621440}},{"streams":[{"end":16.000309,"rtt":93301,"start":15.000276,"omitted":false,"stream-id":5,"retransmits":0,"tcp-window-size":256498,"throughput-bits":20970827.522866268,"throughput-bytes":2621440}],"summary":{"end":16.000309,"start":15.000276,"omitted":false,"retransmits":0,"throughput-bits":20970827.522866268,"throughput-bytes":2621440}},{"streams":[{"end":17.000345,"rtt":105214,"start":16.000309,"omitted":false,"stream-id":5,"retransmits":0,"tcp-window-size":291082,"throughput-bits":20970765.02717993,"throughput-bytes":2621440}],"summary":{"end":17.000345,"start":16.000309,"omitted":false,"retransmits":0,"throughput-bits":20970765.02717993,"throughput-bytes":2621440}},{"streams":[{"end":18.000359,"rtt":122588,"start":17.000345,"omitted":false,"stream-id":5,"retransmits":0,"tcp-window-size":338635,"throughput-bits":20971227.504079584,"throughput-bytes":2621440}],"summary":{"end":18.000359,"start":17.000345,"omitted":false,"retransmits":0,"throughput-bits":20971227.504079584,"throughput-bytes":2621440}},{"streams":[{"end":19.000394,"rtt":142377,"start":18.000359,"omitted":false,"stream-id":5,"retransmits":0,"tcp-window-size":394834,"throughput-bits":20970785.025759034,"throughput-bytes":2621440}],"summary":{"end":19.000394,"start":18.000359,"omitted":false,"retransmits":0,"throughput-bits":20970785.025759034,"throughput-bytes":2621440}},{"streams":[{"end":20.000448,"rtt":77685,"start":19.000394,"omitted":false,"stream-id":5,"retransmits":6,"tcp-window-size":213268,"throughput-bits":20970387.561153747,"throughput-bytes":2621440}],"summary":{"end":20.000448,"start":19.000394,"omitted":false,"retransmits":6,"throughput-bits":20970387.561153747,"throughput-bytes":2621440}},{"streams":[{"end":21.000485,"rtt":84214,"start":20.000448,"omitted":false,"stream-id":5,"retransmits":0,"tcp-window-size":230560,"throughput-bits":20970745.028638974,"throughput-bytes":2621440}],"summary":{"end":21.000485,"start":20.000448,"omitted":false,"retransmits":0,"throughput-bits":20970745.028638974,"throughput-bytes":2621440}},{"streams":[{"end":22.000506,"rtt":90093,"start":21.000485,"omitted":false,"stream-id":5,"retransmits":0,"tcp-window-size":246411,"throughput-bits":20971080.009231374,"throughput-bytes":2621440}],"summary":{"end":22.000506,"start":21.000485,"omitted":false,"retransmits":0,"throughput-bits":20971080.009231374,"throughput-bytes":2621440}},{"streams":[{"end":23.000542,"rtt":101214,"start":22.000506,"omitted":false,"stream-id":5,"retransmits":0,"tcp-window-size":279554,"throughput-bits":20970765.02717993,"throughput-bytes":2621440}],"summary":{"end":23.000542,"start":22.000506,"omitted":false,"retransmits":0,"throughput-bits":20970765.02717993,"throughput-bytes":2621440}},{"streams":[{"end":24.000105,"rtt":117717,"start":23.000542,"omitted":false,"stream-id":5,"retransmits":0,"tcp-window-size":324225,"throughput-bits":31471033.51057646,"throughput-bytes":3932160}],"summary":{"end":24.000105,"start":23.000542,"omitted":false,"retransmits":0,"throughput-bits":31471033.51057646,"throughput-bytes":3932160}},{"streams":[{"end":25.000134,"rtt":136020,"start":24.000105,"omitted":false,"stream-id":5,"retransmits":0,"tcp-window-size":377542,"throughput-bits":20970912.517597463,"throughput-bytes":2621440}],"summary":{"end":25.000134,"start":24.000105,"omitted":false,"retransmits":0,"throughput-bits":20970912.517597463,"throughput-bytes":2621440}},{"streams":[{"end":26.000611,"rtt":146067,"start":25.000134,"omitted":false,"stream-id":5,"retransmits":6,"tcp-window-size":1441,"throughput-bits":10480761.134240855,"throughput-bytes":1310720}],"summary":{"end":26.000611,"start":25.000134,"omitted":false,"retransmits":6,"throughput-bits":10480761.134240855,"throughput-bytes":1310720}},{"streams":[{"end":27.00011,"rtt":78481,"start":26.000611,"omitted":false,"stream-id":5,"retransmits":176,"tcp-window-size":214709,"throughput-bits":20982031.516028177,"throughput-bytes":2621440}],"summary":{"end":27.00011,"start":26.000611,"omitted":false,"retransmits":176,"throughput-bits":20982031.516028177,"throughput-bytes":2621440}},{"streams":[{"end":28.000628,"rtt":30799,"start":27.00011,"omitted":false,"stream-id":5,"retransmits":0,"tcp-window-size":226237,"throughput-bits":10480331.561737567,"throughput-bytes":1310720}],"summary":{"end":28.000628,"start":27.00011,"omitted":false,"retransmits":0,"throughput-bits":10480331.561737567,"throughput-bytes":1310720}},{"streams":[{"end":29.000132,"rtt":88610,"start":28.000628,"omitted":false,"stream-id":5,"retransmits":0,"tcp-window-size":243529,"throughput-bits":20981926.41127039,"throughput-bytes":2621440}],"summary":{"end":29.000132,"start":28.000628,"omitted":false,"retransmits":0,"throughput-bits":20981926.41127039,"throughput-bytes":2621440}},{"streams":[{"end":30.000184,"rtt":101937,"start":29.000132,"omitted":false,"stream-id":5,"retransmits":0,"tcp-window-size":280995,"throughput-bits":20970430.05665008,"throughput-bytes":2621440}],"summary":{"end":30.000184,"start":29.000132,"omitted":false,"retransmits":0,"throughput-bits":20970430.05665008,"throughput-bytes":2621440}}],"succeeded":true}
