{"diags":"Participant 0:\n/usr/bin/iperf3 -p 5201 -c 172.16.0.1 -t 10 --json --rsa-public-key-path /var/run/pscheduler-server/runner/tmp/tmpkisfnzp3/tmprmyydw7c/public-key --username BNBbY6gUdsV8gYb6cWna\n\n{\n    \"end\": {\n        \"cpu_utilization_percent\": {\n            \"host_system\": 0.1839826976287415, \n            \"host_total\": 0.278108562760814, \n            \"host_user\": 0.09412586513207252, \n            \"remote_system\": 4.30754447058674, \n            \"remote_total\": 4.960017379948877, \n            \"remote_user\": 0.652453051102451\n        }, \n        \"receiver_tcp_congestion\": \"htcp\", \n        \"sender_tcp_congestion\": \"htcp\", \n        \"streams\": [\n            {\n                \"receiver\": {\n                    \"bits_per_second\": 20742665.50375959, \n                    \"bytes\": 26113232, \n                    \"end\": 10.071312, \n                    \"seconds\": 10.000423, \n                    \"sender\": true, \n                    \"socket\": 5, \n                    \"start\": 0\n                }, \n                \"sender\": {\n                    \"bits_per_second\": 23382255.7305826, \n                    \"bytes\": 29229056, \n                    \"end\": 10.000423, \n                    \"max_rtt\": 98317, \n                    \"max_snd_cwnd\": 254848, \n                    \"max_snd_wnd\": 0, \n                    \"mean_rtt\": 66927, \n                    \"min_rtt\": 35960, \n                    \"retransmits\": 406, \n                    \"seconds\": 10.000423, \n                    \"sender\": true, \n                    \"socket\": 5, \n                    \"start\": 0\n                }\n            }\n        ], \n        \"sum_received\": {\n            \"bits_per_second\": 20742665.50375959, \n            \"bytes\": 26113232, \n            \"end\": 10.071312, \n            \"seconds\": 10.071312, \n            \"sender\": true, \n            \"start\": 0\n        }, \n        \"sum_sent\": {\n            \"bits_per_second\": 23382255.7305826, \n            \"bytes\": 29229056, \n            \"end\": 10.000423, \n            \"retransmits\": 406, \n            \"seconds\": 10.000423, \n            \"sender\": true, \n            \"start\": 0\n        }\n    }, \n    \"intervals\": [\n        {\n            \"streams\": [\n                {\n                    \"bits_per_second\": 45044805.7806513, \n                    \"bytes\": 5636096, \n                    \"end\": 1.000976, \n                    \"omitted\": false, \n                    \"pmtu\": 1500, \n                    \"retransmits\": 284, \n                    \"rtt\": 73118, \n                    \"rttvar\": 710, \n                    \"seconds\": 1.0009759664535522, \n                    \"sender\": true, \n                    \"snd_cwnd\": 201272, \n                    \"snd_wnd\": -1, \n                    \"socket\": 5, \n                    \"start\": 0\n                }\n            ], \n            \"sum\": {\n                \"bits_per_second\": 45044805.7806513, \n                \"bytes\": 5636096, \n                \"end\": 1.000976, \n                \"omitted\": false, \n                \"retransmits\": 284, \n                \"seconds\": 1.0009759664535522, \n                \"sender\": true, \n                \"start\": 0\n            }\n        }, \n        {\n            \"streams\": [\n                {\n                    \"bits_per_second\": 31485963.630712736, \n                    \"bytes\": 3932160, \n                    \"end\": 2.000065, \n                    \"omitted\": false, \n                    \"pmtu\": 1500, \n                    \"retransmits\": 0, \n                    \"rtt\": 80157, \n                    \"rttvar\": 470, \n                    \"seconds\": 0.999089002609253, \n                    \"sender\": true, \n                    \"snd_cwnd\": 220096, \n                    \"snd_wnd\": -1, \n                    \"socket\": 5, \n                    \"start\": 1.000976\n                }\n            ], \n            \"sum\": {\n                \"bits_per_second\": 31485963.630712736, \n                \"bytes\": 3932160, \n                \"end\": 2.000065, \n                \"omitted\": false, \n                \"retransmits\": 0, \n                \"seconds\": 0.999089002609253, \n                \"sender\": true, \n                \"start\": 1.000976\n            }\n        }, \n        {\n            \"streams\": [\n                {\n                    \"bits_per_second\": 20971457.500186265, \n                    \"bytes\": 2621440, \n                    \"end\": 3.000068, \n                    \"omitted\": false, \n                    \"pmtu\": 1500, \n                    \"retransmits\": 0, \n                    \"rtt\": 86748, \n                    \"rttvar\": 479, \n                    \"seconds\": 1.0000029802322388, \n                    \"sender\": true, \n                    \"snd_cwnd\": 236024, \n                    \"snd_wnd\": -1, \n                    \"socket\": 5, \n                    \"start\": 2.000065\n                }\n            ], \n            \"sum\": {\n                \"bits_per_second\": 20971457.500186265, \n                \"bytes\": 2621440, \n                \"end\": 3.000068, \n                \"omitted\": false, \n                \"retransmits\": 0, \n                \"seconds\": 1.0000029802322388, \n                \"sender\": true, \n                \"start\": 2.000065\n            }\n        }, \n        {\n            \"streams\": [\n                {\n                    \"bits_per_second\": 10480372.769200707, \n                    \"bytes\": 1310720, \n                    \"end\": 4.000582, \n                    \"omitted\": false, \n                    \"pmtu\": 1500, \n                    \"retransmits\": 0, \n                    \"rtt\": 98317, \n                    \"rttvar\": 10591, \n                    \"seconds\": 1.000514030456543, \n                    \"sender\": true, \n                    \"snd_cwnd\": 254848, \n                    \"snd_wnd\": -1, \n                    \"socket\": 5, \n                    \"start\": 3.000068\n                }\n            ], \n            \"sum\": {\n                \"bits_per_second\": 10480372.769200707, \n                \"bytes\": 1310720, \n                \"end\": 4.000582, \n                \"omitted\": false, \n                \"retransmits\": 0, \n                \"seconds\": 1.000514030456543, \n                \"sender\": true, \n                \"start\": 3.000068\n            }\n        }, \n        {\n            \"streams\": [\n                {\n                    \"bits_per_second\": 20974184.088385843, \n                    \"bytes\": 2621440, \n                    \"end\": 5.000455, \n                    \"omitted\": false, \n                    \"pmtu\": 1500, \n                    \"retransmits\": 61, \n                    \"rtt\": 55184, \n                    \"rttvar\": 762, \n                    \"seconds\": 0.9998729825019836, \n                    \"sender\": true, \n                    \"snd_cwnd\": 152040, \n                    \"snd_wnd\": -1, \n                    \"socket\": 5, \n                    \"start\": 4.000582\n                }\n            ], \n            \"sum\": {\n                \"bits_per_second\": 20974184.088385843, \n                \"bytes\": 2621440, \n                \"end\": 5.000455, \n                \"omitted\": false, \n                \"retransmits\": 61, \n                \"seconds\": 0.9998729825019836, \n                \"sender\": true, \n                \"start\": 4.000582\n            }\n        }, \n        {\n            \"streams\": [\n                {\n                    \"bits_per_second\": 20970955.015221424, \n                    \"bytes\": 2621440, \n                    \"end\": 6.000482, \n                    \"omitted\": false, \n                    \"pmtu\": 1500, \n                    \"retransmits\": 0, \n                    \"rtt\": 63778, \n                    \"rttvar\": 759, \n                    \"seconds\": 1.0000269412994385, \n                    \"sender\": true, \n                    \"snd_cwnd\": 175208, \n                    \"snd_wnd\": -1, \n                    \"socket\": 5, \n                    \"start\": 5.000455\n                }\n            ], \n            \"sum\": {\n                \"bits_per_second\": 20970955.015221424, \n                \"bytes\": 2621440, \n                \"end\": 6.000482, \n                \"omitted\": false, \n                \"retransmits\": 0, \n                \"seconds\": 1.0000269412994385, \n                \"sender\": true, \n                \"start\": 5.000455\n            }\n        }, \n        {\n            \"streams\": [\n                {\n                    \"bits_per_second\": 20970785.025759034, \n                    \"bytes\": 2621440, \n                    \"end\": 7.000517, \n                    \"omitted\": false, \n                    \"pmtu\": 1500, \n                    \"retransmits\": 61, \n                    \"rtt\": 35960, \n                    \"rttvar\": 425, \n                    \"seconds\": 1.000035047531128, \n                    \"sender\": true, \n                    \"snd_cwnd\": 99912, \n                    \"snd_wnd\": -1, \n                    \"socket\": 5, \n                    \"start\": 6.000482\n                }\n            ], \n            \"sum\": {\n                \"bits_per_second\": 20970785.025759034, \n                \"bytes\": 2621440, \n                \"end\": 7.000517, \n                \"omitted\": false, \n                \"retransmits\": 61, \n                \"seconds\": 1.000035047531128, \n                \"sender\": true, \n                \"start\": 6.000482\n            }\n        }, \n        {\n            \"streams\": [\n                {\n                    \"bits_per_second\": 20974791.7603467, \n                    \"bytes\": 2621440, \n                    \"end\": 8.000361, \n                    \"omitted\": false, \n                    \"pmtu\": 1500, \n                    \"retransmits\": 0, \n                    \"rtt\": 47616, \n                    \"rttvar\": 403, \n                    \"seconds\": 0.9998440146446228, \n                    \"sender\": true, \n                    \"snd_cwnd\": 133216, \n                    \"snd_wnd\": -1, \n                    \"socket\": 5, \n                    \"start\": 7.000517\n                }\n            ], \n            \"sum\": {\n                \"bits_per_second\": 20974791.7603467, \n                \"bytes\": 2621440, \n                \"end\": 8.000361, \n                \"omitted\": false, \n                \"retransmits\": 0, \n                \"seconds\": 0.9998440146446228, \n                \"sender\": true, \n                \"start\": 7.000517\n            }\n        }, \n        {\n            \"streams\": [\n                {\n                    \"bits_per_second\": 20970827.522866268, \n                    \"bytes\": 2621440, \n                    \"end\": 9.000394, \n                    \"omitted\": false, \n                    \"pmtu\": 1500, \n                    \"retransmits\": 0, \n                    \"rtt\": 58022, \n                    \"rttvar\": 740, \n                    \"seconds\": 1.0000330209732056, \n                    \"sender\": true, \n                    \"snd_cwnd\": 159280, \n                    \"snd_wnd\": -1, \n                    \"socket\": 5, \n                    \"start\": 8.000361\n                }\n            ], \n            \"sum\": {\n                \"bits_per_second\": 20970827.522866268, \n                \"bytes\": 2621440, \n                \"end\": 9.000394, \n                \"omitted\": false, \n                \"retransmits\": 0, \n                \"seconds\": 1.0000330209732056, \n                \"sender\": true, \n                \"start\": 8.000361\n            }\n        }, \n        {\n            \"streams\": [\n                {\n                    \"bits_per_second\": 20970912.517597463, \n                    \"bytes\": 2621440, \n                    \"end\": 10.000423, \n                    \"omitted\": false, \n                    \"pmtu\": 1500, \n                    \"retransmits\": 0, \n                    \"rtt\": 70375, \n                    \"rttvar\": 508, \n                    \"seconds\": 1.0000289678573608, \n                    \"sender\": true, \n                    \"snd_cwnd\": 194032, \n                    \"snd_wnd\": -1, \n                    \"socket\": 5, \n                    \"start\": 9.000394\n                }\n            ], \n            \"sum\": {\n                \"bits_per_second\": 20970912.517597463, \n                \"bytes\": 2621440, \n                \"end\": 10.000423, \n                \"omitted\": false, \n                \"retransmits\": 0, \n                \"seconds\": 1.0000289678573608, \n                \"sender\": true, \n                \"start\": 9.000394\n            }\n        }\n    ], \n    \"start\": {\n        \"connected\": [\n            {\n                \"local_host\": \"172.16.0.2\", \n                \"local_port\": 59550, \n                \"remote_host\": \"172.16.0.1\", \n                \"remote_port\": 5201, \n                \"socket\": 5\n            }\n        ], \n        \"connecting_to\": {\n            \"host\": \"172.16.0.1\", \n            \"port\": 5201\n        }, \n        \"cookie\": \"lmvodd6q6fqi4rtxomcdmg437t7rxexvuzmw\", \n        \"fq_rate\": 0, \n        \"rcvbuf_actual\": 87380, \n        \"sndbuf_actual\": 65536, \n        \"sock_bufsize\": 0, \n        \"system_info\": \"REDACTED\", \n        \"target_bitrate\": 0, \n        \"tcp_mss_default\": 1448, \n        \"test_start\": {\n            \"bidir\": 0, \n            \"blksize\": 131072, \n            \"blocks\": 0, \n            \"bytes\": 0, \n            \"duration\": 10, \n            \"fqrate\": 0, \n            \"num_streams\": 1, \n            \"omit\": 0, \n            \"protocol\": \"TCP\", \n            \"reverse\": 0, \n            \"target_bitrate\": 0, \n            \"tos\": 0\n        }, \n        \"timestamp\": {\n            \"time\": \"Wed, 11 Sep 2024 18:05:04 GMT\", \n            \"timesecs\": 1726077904\n        }, \n        \"version\": \"iperf 3.14\"\n    }\n}\nParticipant 1:\n/usr/bin/iperf3 -s -1 --idle-timeout 10 --json -p 5201 --authorized-users-path /var/run/pscheduler-server/runner/tmp/tmpqqzjltro/tmp4_m846d3/credentials --rsa-private-key-path /var/run/pscheduler-server/runner/tmp/tmpqqzjltro/tmp4_m846d3/private-key\n\n{\n    \"end\": {\n        \"cpu_utilization_percent\": {\n            \"host_system\": 4.30754447058674, \n            \"host_total\": 4.960017379948877, \n            \"host_user\": 0.652453051102451, \n            \"remote_system\": 0, \n            \"remote_total\": 0, \n            \"remote_user\": 0\n        }, \n        \"receiver_tcp_congestion\": \"htcp\", \n        \"streams\": [\n            {\n                \"receiver\": {\n                    \"bits_per_second\": 20742665.50375959, \n                    \"bytes\": 26113232, \n                    \"end\": 10.071312, \n                    \"seconds\": 10.071312, \n                    \"sender\": false, \n                    \"socket\": 5, \n                    \"start\": 0\n                }, \n                \"sender\": {\n                    \"bits_per_second\": 0, \n                    \"bytes\": 0, \n                    \"end\": 10.071312, \n                    \"seconds\": 10.071312, \n                    \"sender\": false, \n                    \"socket\": 5, \n                    \"start\": 0\n                }\n            }\n        ], \n        \"sum_received\": {\n            \"bits_per_second\": 20742665.50375959, \n            \"bytes\": 26113232, \n            \"end\": 10.071312, \n            \"seconds\": 10.071312, \n            \"sender\": false, \n            \"start\": 0\n        }, \n        \"sum_sent\": {\n            \"bits_per_second\": 0, \n            \"bytes\": 0, \n            \"end\": 10.071312, \n            \"seconds\": 10.071312, \n            \"sender\": false, \n            \"start\": 0\n        }\n    }, \n    \"intervals\": [\n        {\n            \"streams\": [\n                {\n                    \"bits_per_second\": 20327826.298408292, \n                    \"bytes\": 2541240, \n                    \"end\": 1.000103, \n                    \"omitted\": false, \n                    \"seconds\": 1.0001029968261719, \n                    \"sender\": false, \n                    \"socket\": 5, \n                    \"start\": 0\n                }\n            ], \n            \"sum\": {\n                \"bits_per_second\": 20327826.298408292, \n                \"bytes\": 2541240, \n                \"end\": 1.000103, \n                \"omitted\": false, \n                \"seconds\": 1.0001029968261719, \n                \"sender\": false, \n                \"start\": 0\n            }\n        }, \n        {\n            \"streams\": [\n                {\n                    \"bits_per_second\": 21697482.51518113, \n                    \"bytes\": 2712104, \n                    \"end\": 2.000073, \n                    \"omitted\": false, \n                    \"seconds\": 0.999970018863678, \n                    \"sender\": false, \n                    \"socket\": 5, \n                    \"start\": 1.000103\n                }\n            ], \n            \"sum\": {\n                \"bits_per_second\": 21697482.51518113, \n                \"bytes\": 2712104, \n                \"end\": 2.000073, \n                \"omitted\": false, \n                \"seconds\": 0.999970018863678, \n                \"sender\": false, \n                \"start\": 1.000103\n            }\n        }, \n        {\n            \"streams\": [\n                {\n                    \"bits_per_second\": 21673403.049231056, \n                    \"bytes\": 2709208, \n                    \"end\": 3.000085, \n                    \"omitted\": false, \n                    \"seconds\": 1.0000120401382446, \n                    \"sender\": false, \n                    \"socket\": 5, \n                    \"start\": 2.000073\n                }\n            ], \n            \"sum\": {\n                \"bits_per_second\": 21673403.049231056, \n                \"bytes\": 2709208, \n                \"end\": 3.000085, \n                \"omitted\": false, \n                \"seconds\": 1.0000120401382446, \n                \"sender\": false, \n                \"start\": 2.000073\n            }\n        }, \n        {\n            \"streams\": [\n                {\n                    \"bits_per_second\": 18276061.760506112, \n                    \"bytes\": 2284944, \n                    \"end\": 4.000276, \n                    \"omitted\": false, \n                    \"seconds\": 1.0001909732818604, \n                    \"sender\": false, \n                    \"socket\": 5, \n                    \"start\": 3.000085\n                }\n            ], \n            \"sum\": {\n                \"bits_per_second\": 18276061.760506112, \n                \"bytes\": 2284944, \n                \"end\": 4.000276, \n                \"omitted\": false, \n                \"seconds\": 1.0001909732818604, \n                \"sender\": false, \n                \"start\": 3.000085\n            }\n        }, \n        {\n            \"streams\": [\n                {\n                    \"bits_per_second\": 21237060.620833162, \n                    \"bytes\": 2654184, \n                    \"end\": 5.000107, \n                    \"omitted\": false, \n                    \"seconds\": 0.9998310208320618, \n                    \"sender\": false, \n                    \"socket\": 5, \n                    \"start\": 4.000276\n                }\n            ], \n            \"sum\": {\n                \"bits_per_second\": 21237060.620833162, \n                \"bytes\": 2654184, \n                \"end\": 5.000107, \n                \"omitted\": false, \n                \"seconds\": 0.9998310208320618, \n                \"sender\": false, \n                \"start\": 4.000276\n            }\n        }, \n        {\n            \"streams\": [\n                {\n                    \"bits_per_second\": 21697548.474166792, \n                    \"bytes\": 2712104, \n                    \"end\": 6.000074, \n                    \"omitted\": false, \n                    \"seconds\": 0.9999669790267944, \n                    \"sender\": false, \n                    \"socket\": 5, \n                    \"start\": 5.000107\n                }\n            ], \n            \"sum\": {\n                \"bits_per_second\": 21697548.474166792, \n                \"bytes\": 2712104, \n                \"end\": 6.000074, \n                \"omitted\": false, \n                \"seconds\": 0.9999669790267944, \n                \"sender\": false, \n                \"start\": 5.000107\n            }\n        }, \n        {\n            \"streams\": [\n                {\n                    \"bits_per_second\": 17503161.096035708, \n                    \"bytes\": 2187928, \n                    \"end\": 7.000089, \n                    \"omitted\": false, \n                    \"seconds\": 1.0000150203704834, \n                    \"sender\": false, \n                    \"socket\": 5, \n                    \"start\": 6.000074\n                }\n            ], \n            \"sum\": {\n                \"bits_per_second\": 17503161.096035708, \n                \"bytes\": 2187928, \n                \"end\": 7.000089, \n                \"omitted\": false, \n                \"seconds\": 1.0000150203704834, \n                \"sender\": false, \n                \"start\": 6.000074\n            }\n        }, \n        {\n            \"streams\": [\n                {\n                    \"bits_per_second\": 21649652.06543715, \n                    \"bytes\": 2706312, \n                    \"end\": 8.000128, \n                    \"omitted\": false, \n                    \"seconds\": 1.000038981437683, \n                    \"sender\": false, \n                    \"socket\": 5, \n                    \"start\": 7.000089\n                }\n            ], \n            \"sum\": {\n                \"bits_per_second\": 21649652.06543715, \n                \"bytes\": 2706312, \n                \"end\": 8.000128, \n                \"omitted\": false, \n                \"seconds\": 1.000038981437683, \n                \"sender\": false, \n                \"start\": 7.000089\n            }\n        }, \n        {\n            \"streams\": [\n                {\n                    \"bits_per_second\": 21651124.47719314, \n                    \"bytes\": 2706312, \n                    \"end\": 9.000099, \n                    \"omitted\": false, \n                    \"seconds\": 0.9999709725379944, \n                    \"sender\": false, \n                    \"socket\": 5, \n                    \"start\": 8.000128\n                }\n            ], \n            \"sum\": {\n                \"bits_per_second\": 21651124.47719314, \n                \"bytes\": 2706312, \n                \"end\": 9.000099, \n                \"omitted\": false, \n                \"seconds\": 0.9999709725379944, \n                \"sender\": false, \n                \"start\": 8.000128\n            }\n        }, \n        {\n            \"streams\": [\n                {\n                    \"bits_per_second\": 21639647.1993861, \n                    \"bytes\": 2704864, \n                    \"end\": 10.000065, \n                    \"omitted\": false, \n                    \"seconds\": 0.999966025352478, \n                    \"sender\": false, \n                    \"socket\": 5, \n                    \"start\": 9.000099\n                }\n            ], \n            \"sum\": {\n                \"bits_per_second\": 21639647.1993861, \n                \"bytes\": 2704864, \n                \"end\": 10.000065, \n                \"omitted\": false, \n                \"seconds\": 0.999966025352478, \n                \"sender\": false, \n                \"start\": 9.000099\n            }\n        }, \n        {\n            \"streams\": [\n                {\n                    \"bits_per_second\": 21786967.532333538, \n                    \"bytes\": 194032, \n                    \"end\": 10.071312, \n                    \"omitted\": false, \n                    \"seconds\": 0.07124699652194977, \n                    \"sender\": false, \n                    \"socket\": 5, \n                    \"start\": 10.000065\n                }\n            ], \n            \"sum\": {\n                \"bits_per_second\": 21786967.532333538, \n                \"bytes\": 194032, \n                \"end\": 10.071312, \n                \"omitted\": false, \n                \"seconds\": 0.07124699652194977, \n                \"sender\": false, \n                \"start\": 10.000065\n            }\n        }\n    ], \n    \"start\": {\n        \"accepted_connection\": {\n            \"host\": \"172.16.0.2\", \n            \"port\": 59538\n        }, \n        \"connected\": [\n            {\n                \"local_host\": \"172.16.0.1\", \n                \"local_port\": 5201, \n                \"remote_host\": \"172.16.0.2\", \n                \"remote_port\": 59550, \n                \"socket\": 5\n            }\n        ], \n        \"cookie\": \"lmvodd6q6fqi4rtxomcdmg437t7rxexvuzmw\", \n        \"fq_rate\": 0, \n        \"rcvbuf_actual\": 87380, \n        \"sndbuf_actual\": 65536, \n        \"sock_bufsize\": 0, \n        \"system_info\": \"REDACTED\", \n        \"target_bitrate\": 0, \n        \"tcp_mss_default\": 0, \n        \"test_start\": {\n            \"bidir\": 0, \n            \"blksize\": 131072, \n            \"blocks\": 0, \n            \"bytes\": 0, \n            \"duration\": 10, \n            \"fqrate\": 0, \n            \"num_streams\": 1, \n            \"omit\": 0, \n            \"protocol\": \"TCP\", \n            \"reverse\": 0, \n            \"target_bitrate\": 0, \n            \"tos\": 0\n        }, \n        \"timestamp\": {\n            \"time\": \"Wed, 11 Sep 2024 18:05:04 GMT\", \n            \"timesecs\": 1726077904\n        }, \n        \"version\": \"iperf 3.14\"\n    }\n}\n","summary":{"streams":[{"end":10.000423,"rtt":66927,"start":0,"stream-id":5,"retransmits":406,"throughput-bits":23382255.7305826,"throughput-bytes":29229056}],"summary":{"end":10.000423,"start":0,"retransmits":406,"throughput-bits":23382255.7305826,"throughput-bytes":29229056,"receiver-throughput-bits":20742665.50375959}},"intervals":[{"streams":[{"end":1.000976,"rtt":73118,"start":0,"omitted":false,"stream-id":5,"retransmits":284,"tcp-window-size":201272,"throughput-bits":45044805.7806513,"throughput-bytes":5636096}],"summary":{"end":1.000976,"start":0,"omitted":false,"retransmits":284,"throughput-bits":45044805.7806513,"throughput-bytes":5636096}},{"streams":[{"end":2.000065,"rtt":80157,"start":1.000976,"omitted":false,"stream-id":5,"retransmits":0,"tcp-window-size":220096,"throughput-bits":31485963.630712736,"throughput-bytes":3932160}],"summary":{"end":2.000065,"start":1.000976,"omitted":false,"retransmits":0,"throughput-bits":31485963.630712736,"throughput-bytes":3932160}},{"streams":[{"end":3.000068,"rtt":86748,"start":2.000065,"omitted":false,"stream-id":5,"retransmits":0,"tcp-window-size":236024,"throughput-bits":20971457.500186265,"throughput-bytes":2621440}],"summary":{"end":3.000068,"start":2.000065,"omitted":false,"retransmits":0,"throughput-bits":20971457.500186265,"throughput-bytes":2621440}},{"streams":[{"end":4.000582,"rtt":98317,"start":3.000068,"omitted":false,"stream-id":5,"retransmits":0,"tcp-window-size":254848,"throughput-bits":10480372.769200707,"throughput-bytes":1310720}],"summary":{"end":4.000582,"start":3.000068,"omitted":false,"retransmits":0,"throughput-bits":10480372.769200707,"throughput-bytes":1310720}},{"streams":[{"end":5.000455,"rtt":55184,"start":4.000582,"omitted":false,"stream-id":5,"retransmits":61,"tcp-window-size":152040,"throughput-bits":20974184.088385843,"throughput-bytes":2621440}],"summary":{"end":5.000455,"start":4.000582,"omitted":false,"retransmits":61,"throughput-bits":20974184.088385843,"throughput-bytes":2621440}},{"streams":[{"end":6.000482,"rtt":63778,"start":5.000455,"omitted":false,"stream-id":5,"retransmits":0,"tcp-window-size":175208,"throughput-bits":20970955.015221424,"throughput-bytes":2621440}],"summary":{"end":6.000482,"start":5.000455,"omitted":false,"retransmits":0,"throughput-bits":20970955.015221424,"throughput-bytes":2621440}},{"streams":[{"end":7.000517,"rtt":35960,"start":6.000482,"omitted":false,"stream-id":5,"retransmits":61,"tcp-window-size":99912,"throughput-bits":20970785.025759034,"throughput-bytes":2621440}],"summary":{"end":7.000517,"start":6.000482,"omitted":false,"retransmits":61,"throughput-bits":20970785.025759034,"throughput-bytes":2621440}},{"streams":[{"end":8.000361,"rtt":47616,"start":7.000517,"omitted":false,"stream-id":5,"retransmits":0,"tcp-window-size":133216,"throughput-bits":20974791.7603467,"throughput-bytes":2621440}],"summary":{"end":8.000361,"start":7.000517,"omitted":false,"retransmits":0,"throughput-bits":20974791.7603467,"throughput-bytes":2621440}},{"streams":[{"end":9.000394,"rtt":58022,"start":8.000361,"omitted":false,"stream-id":5,"retransmits":0,"tcp-window-size":159280,"throughput-bits":20970827.522866268,"throughput-bytes":2621440}],"summary":{"end":9.000394,"start":8.000361,"omitted":false,"retransmits":0,"throughput-bits":20970827.522866268,"throughput-bytes":2621440}},{"streams":[{"end":10.000423,"rtt":70375,"start":9.000394,"omitted":false,"stream-id":5,"retransmits":0,"tcp-window-size":194032,"throughput-bits":20970912.517597463,"throughput-bytes":2621440}],"summary":{"end":10.000423,"start":9.000394,"omitted":false,"retransmits":0,"throughput-bits":20970912.517597463,"throughput-bytes":2621440}}],"succeeded":true}
