{"diags":"Participant 0:\n/usr/bin/iperf3 -p 5201 -c 172.16.0.1 -t 10 --json --rsa-public-key-path /var/run/pscheduler-server/runner/tmp/tmpw1sjhywc/tmpf_01vfy9/public-key --username kTitOX5SEELID9Iw98Qb\n\n{\n    \"end\": {\n        \"cpu_utilization_percent\": {\n            \"host_system\": 0.2751021151649187, \n            \"host_total\": 0.2751021151649187, \n            \"host_user\": 0, \n            \"remote_system\": 3.327633264568914, \n            \"remote_total\": 3.9617202994636056, \n            \"remote_user\": 0.6341069396860936\n        }, \n        \"receiver_tcp_congestion\": \"htcp\", \n        \"sender_tcp_congestion\": \"htcp\", \n        \"streams\": [\n            {\n                \"receiver\": {\n                    \"bits_per_second\": 18558031.42852764, \n                    \"bytes\": 23308456, \n                    \"end\": 10.047814, \n                    \"seconds\": 10.000445, \n                    \"sender\": true, \n                    \"socket\": 5, \n                    \"start\": 0\n                }, \n                \"sender\": {\n                    \"bits_per_second\": 21180292.676975876, \n                    \"bytes\": 26476544, \n                    \"end\": 10.000445, \n                    \"max_rtt\": 229567, \n                    \"max_snd_cwnd\": 327248, \n                    \"max_snd_wnd\": 0, \n                    \"mean_rtt\": 97515, \n                    \"min_rtt\": 45800, \n                    \"retransmits\": 413, \n                    \"seconds\": 10.000445, \n                    \"sender\": true, \n                    \"socket\": 5, \n                    \"start\": 0\n                }\n            }\n        ], \n        \"sum_received\": {\n            \"bits_per_second\": 18558031.42852764, \n            \"bytes\": 23308456, \n            \"end\": 10.047814, \n            \"seconds\": 10.047814, \n            \"sender\": true, \n            \"start\": 0\n        }, \n        \"sum_sent\": {\n            \"bits_per_second\": 21180292.676975876, \n            \"bytes\": 26476544, \n            \"end\": 10.000445, \n            \"retransmits\": 413, \n            \"seconds\": 10.000445, \n            \"sender\": true, \n            \"start\": 0\n        }\n    }, \n    \"intervals\": [\n        {\n            \"streams\": [\n                {\n                    \"bits_per_second\": 44027118.13228946, \n                    \"bytes\": 5505024, \n                    \"end\": 1.000297, \n                    \"omitted\": false, \n                    \"pmtu\": 1500, \n                    \"retransmits\": 270, \n                    \"rtt\": 152803, \n                    \"rttvar\": 2278, \n                    \"seconds\": 1.000296950340271, \n                    \"sender\": true, \n                    \"snd_cwnd\": 195480, \n                    \"snd_wnd\": -1, \n                    \"socket\": 5, \n                    \"start\": 0\n                }\n            ], \n            \"sum\": {\n                \"bits_per_second\": 44027118.13228946, \n                \"bytes\": 5505024, \n                \"end\": 1.000297, \n                \"omitted\": false, \n                \"retransmits\": 270, \n                \"seconds\": 1.000296950340271, \n                \"sender\": true, \n                \"start\": 0\n            }\n        }, \n        {\n            \"streams\": [\n                {\n                    \"bits_per_second\": 20976407.38873497, \n                    \"bytes\": 2621440, \n                    \"end\": 2.000064, \n                    \"omitted\": false, \n                    \"pmtu\": 1500, \n                    \"retransmits\": 50, \n                    \"rtt\": 55985, \n                    \"rttvar\": 550, \n                    \"seconds\": 0.999767005443573, \n                    \"sender\": true, \n                    \"snd_cwnd\": 118736, \n                    \"snd_wnd\": -1, \n                    \"socket\": 5, \n                    \"start\": 1.000297\n                }\n            ], \n            \"sum\": {\n                \"bits_per_second\": 20976407.38873497, \n                \"bytes\": 2621440, \n                \"end\": 2.000064, \n                \"omitted\": false, \n                \"retransmits\": 50, \n                \"seconds\": 0.999767005443573, \n                \"sender\": true, \n                \"start\": 1.000297\n            }\n        }, \n        {\n            \"streams\": [\n                {\n                    \"bits_per_second\": 10482017.586160833, \n                    \"bytes\": 1310720, \n                    \"end\": 3.000421, \n                    \"omitted\": false, \n                    \"pmtu\": 1500, \n                    \"retransmits\": 0, \n                    \"rtt\": 56801, \n                    \"rttvar\": 464, \n                    \"seconds\": 1.0003570318222046, \n                    \"sender\": true, \n                    \"snd_cwnd\": 141904, \n                    \"snd_wnd\": -1, \n                    \"socket\": 5, \n                    \"start\": 2.000064\n                }\n            ], \n            \"sum\": {\n                \"bits_per_second\": 10482017.586160833, \n                \"bytes\": 1310720, \n                \"end\": 3.000421, \n                \"omitted\": false, \n                \"retransmits\": 0, \n                \"seconds\": 1.0003570318222046, \n                \"sender\": true, \n                \"start\": 2.000064\n            }\n        }, \n        {\n            \"streams\": [\n                {\n                    \"bits_per_second\": 20973826.50364752, \n                    \"bytes\": 2621440, \n                    \"end\": 4.000311, \n                    \"omitted\": false, \n                    \"pmtu\": 1500, \n                    \"retransmits\": 0, \n                    \"rtt\": 67686, \n                    \"rttvar\": 807, \n                    \"seconds\": 0.9998900294303894, \n                    \"sender\": true, \n                    \"snd_cwnd\": 167968, \n                    \"snd_wnd\": -1, \n                    \"socket\": 5, \n                    \"start\": 3.000421\n                }\n            ], \n            \"sum\": {\n                \"bits_per_second\": 20973826.50364752, \n                \"bytes\": 2621440, \n                \"end\": 4.000311, \n                \"omitted\": false, \n                \"retransmits\": 0, \n                \"seconds\": 0.9998900294303894, \n                \"sender\": true, \n                \"start\": 3.000421\n            }\n        }, \n        {\n            \"streams\": [\n                {\n                    \"bits_per_second\": 20972547.550344847, \n                    \"bytes\": 2621440, \n                    \"end\": 5.000262, \n                    \"omitted\": false, \n                    \"pmtu\": 1500, \n                    \"retransmits\": 0, \n                    \"rtt\": 77986, \n                    \"rttvar\": 536, \n                    \"seconds\": 0.9999510049819946, \n                    \"sender\": true, \n                    \"snd_cwnd\": 215752, \n                    \"snd_wnd\": -1, \n                    \"socket\": 5, \n                    \"start\": 4.000311\n                }\n            ], \n            \"sum\": {\n                \"bits_per_second\": 20972547.550344847, \n                \"bytes\": 2621440, \n                \"end\": 5.000262, \n                \"omitted\": false, \n                \"retransmits\": 0, \n                \"seconds\": 0.9999510049819946, \n                \"sender\": true, \n                \"start\": 4.000311\n            }\n        }, \n        {\n            \"streams\": [\n                {\n                    \"bits_per_second\": 20970827.522866268, \n                    \"bytes\": 2621440, \n                    \"end\": 6.000295, \n                    \"omitted\": false, \n                    \"pmtu\": 1500, \n                    \"retransmits\": 0, \n                    \"rtt\": 98493, \n                    \"rttvar\": 722, \n                    \"seconds\": 1.0000330209732056, \n                    \"sender\": true, \n                    \"snd_cwnd\": 273672, \n                    \"snd_wnd\": -1, \n                    \"socket\": 5, \n                    \"start\": 5.000262\n                }\n            ], \n            \"sum\": {\n                \"bits_per_second\": 20970827.522866268, \n                \"bytes\": 2621440, \n                \"end\": 6.000295, \n                \"omitted\": false, \n                \"retransmits\": 0, \n                \"seconds\": 1.0000330209732056, \n                \"sender\": true, \n                \"start\": 5.000262\n            }\n        }, \n        {\n            \"streams\": [\n                {\n                    \"bits_per_second\": 20971205.004731346, \n                    \"bytes\": 2621440, \n                    \"end\": 7.00031, \n                    \"omitted\": false, \n                    \"pmtu\": 1500, \n                    \"retransmits\": 0, \n                    \"rtt\": 123400, \n                    \"rttvar\": 11489, \n                    \"seconds\": 1.0000150203704834, \n                    \"sender\": true, \n                    \"snd_cwnd\": 327248, \n                    \"snd_wnd\": -1, \n                    \"socket\": 5, \n                    \"start\": 6.000295\n                }\n            ], \n            \"sum\": {\n                \"bits_per_second\": 20971205.004731346, \n                \"bytes\": 2621440, \n                \"end\": 7.00031, \n                \"omitted\": false, \n                \"retransmits\": 0, \n                \"seconds\": 1.0000150203704834, \n                \"sender\": true, \n                \"start\": 6.000295\n            }\n        }, \n        {\n            \"streams\": [\n                {\n                    \"bits_per_second\": 20973345.1588304, \n                    \"bytes\": 2621440, \n                    \"end\": 8.000223, \n                    \"omitted\": false, \n                    \"pmtu\": 1500, \n                    \"retransmits\": 61, \n                    \"rtt\": 66634, \n                    \"rttvar\": 663, \n                    \"seconds\": 0.999912977218628, \n                    \"sender\": true, \n                    \"snd_cwnd\": 183896, \n                    \"snd_wnd\": -1, \n                    \"socket\": 5, \n                    \"start\": 7.00031\n                }\n            ], \n            \"sum\": {\n                \"bits_per_second\": 20973345.1588304, \n                \"bytes\": 2621440, \n                \"end\": 8.000223, \n                \"omitted\": false, \n                \"retransmits\": 61, \n                \"seconds\": 0.999912977218628, \n                \"sender\": true, \n                \"start\": 7.00031\n            }\n        }, \n        {\n            \"streams\": [\n                {\n                    \"bits_per_second\": 10480362.779482918, \n                    \"bytes\": 1310720, \n                    \"end\": 9.000738, \n                    \"omitted\": false, \n                    \"pmtu\": 1500, \n                    \"retransmits\": 18, \n                    \"rtt\": 229567, \n                    \"rttvar\": 160735, \n                    \"seconds\": 1.0005149841308594, \n                    \"sender\": true, \n                    \"snd_cwnd\": 98464, \n                    \"snd_wnd\": -1, \n                    \"socket\": 5, \n                    \"start\": 8.000223\n                }\n            ], \n            \"sum\": {\n                \"bits_per_second\": 10480362.779482918, \n                \"bytes\": 1310720, \n                \"end\": 9.000738, \n                \"omitted\": false, \n                \"retransmits\": 18, \n                \"seconds\": 1.0005149841308594, \n                \"sender\": true, \n                \"start\": 8.000223\n            }\n        }, \n        {\n            \"streams\": [\n                {\n                    \"bits_per_second\": 20977666.80111374, \n                    \"bytes\": 2621440, \n                    \"end\": 10.000445, \n                    \"omitted\": false, \n                    \"pmtu\": 1500, \n                    \"retransmits\": 14, \n                    \"rtt\": 45800, \n                    \"rttvar\": 573, \n                    \"seconds\": 0.9997069835662842, \n                    \"sender\": true, \n                    \"snd_cwnd\": 127424, \n                    \"snd_wnd\": -1, \n                    \"socket\": 5, \n                    \"start\": 9.000738\n                }\n            ], \n            \"sum\": {\n                \"bits_per_second\": 20977666.80111374, \n                \"bytes\": 2621440, \n                \"end\": 10.000445, \n                \"omitted\": false, \n                \"retransmits\": 14, \n                \"seconds\": 0.9997069835662842, \n                \"sender\": true, \n                \"start\": 9.000738\n            }\n        }\n    ], \n    \"start\": {\n        \"connected\": [\n            {\n                \"local_host\": \"172.16.0.2\", \n                \"local_port\": 58670, \n                \"remote_host\": \"172.16.0.1\", \n                \"remote_port\": 5201, \n                \"socket\": 5\n            }\n        ], \n        \"connecting_to\": {\n            \"host\": \"172.16.0.1\", \n            \"port\": 5201\n        }, \n        \"cookie\": \"haynwtwrzas4rqwqq4ht5vpim7byl2chenea\", \n        \"fq_rate\": 0, \n        \"rcvbuf_actual\": 87380, \n        \"sndbuf_actual\": 65536, \n        \"sock_bufsize\": 0, \n        \"system_info\": \"REDACTED\", \n        \"target_bitrate\": 0, \n        \"tcp_mss_default\": 1448, \n        \"test_start\": {\n            \"bidir\": 0, \n            \"blksize\": 131072, \n            \"blocks\": 0, \n            \"bytes\": 0, \n            \"duration\": 10, \n            \"fqrate\": 0, \n            \"num_streams\": 1, \n            \"omit\": 0, \n            \"protocol\": \"TCP\", \n            \"reverse\": 0, \n            \"target_bitrate\": 0, \n            \"tos\": 0\n        }, \n        \"timestamp\": {\n            \"time\": \"Wed, 11 Sep 2024 18:09:04 GMT\", \n            \"timesecs\": 1726078144\n        }, \n        \"version\": \"iperf 3.14\"\n    }\n}\nParticipant 1:\n/usr/bin/iperf3 -s -1 --idle-timeout 10 --json -p 5201 --authorized-users-path /var/run/pscheduler-server/runner/tmp/tmpdjy4wj40/tmpjgho8_yl/credentials --rsa-private-key-path /var/run/pscheduler-server/runner/tmp/tmpdjy4wj40/tmpjgho8_yl/private-key\n\n{\n    \"end\": {\n        \"cpu_utilization_percent\": {\n            \"host_system\": 3.327633264568914, \n            \"host_total\": 3.9617202994636056, \n            \"host_user\": 0.6341069396860936, \n            \"remote_system\": 0, \n            \"remote_total\": 0, \n            \"remote_user\": 0\n        }, \n        \"receiver_tcp_congestion\": \"htcp\", \n        \"streams\": [\n            {\n                \"receiver\": {\n                    \"bits_per_second\": 18558031.42852764, \n                    \"bytes\": 23308456, \n                    \"end\": 10.047814, \n                    \"seconds\": 10.047814, \n                    \"sender\": false, \n                    \"socket\": 5, \n                    \"start\": 0\n                }, \n                \"sender\": {\n                    \"bits_per_second\": 0, \n                    \"bytes\": 0, \n                    \"end\": 10.047814, \n                    \"seconds\": 10.047814, \n                    \"sender\": false, \n                    \"socket\": 5, \n                    \"start\": 0\n                }\n            }\n        ], \n        \"sum_received\": {\n            \"bits_per_second\": 18558031.42852764, \n            \"bytes\": 23308456, \n            \"end\": 10.047814, \n            \"seconds\": 10.047814, \n            \"sender\": false, \n            \"start\": 0\n        }, \n        \"sum_sent\": {\n            \"bits_per_second\": 0, \n            \"bytes\": 0, \n            \"end\": 10.047814, \n            \"seconds\": 10.047814, \n            \"sender\": false, \n            \"start\": 0\n        }\n    }, \n    \"intervals\": [\n        {\n            \"streams\": [\n                {\n                    \"bits_per_second\": 16088712.623986708, \n                    \"bytes\": 2011272, \n                    \"end\": 1.000091, \n                    \"omitted\": false, \n                    \"seconds\": 1.0000909566879272, \n                    \"sender\": false, \n                    \"socket\": 5, \n                    \"start\": 0\n                }\n            ], \n            \"sum\": {\n                \"bits_per_second\": 16088712.623986708, \n                \"bytes\": 2011272, \n                \"end\": 1.000091, \n                \"omitted\": false, \n                \"seconds\": 1.0000909566879272, \n                \"sender\": false, \n                \"start\": 0\n            }\n        }, \n        {\n            \"streams\": [\n                {\n                    \"bits_per_second\": 14863460.919815684, \n                    \"bytes\": 1857784, \n                    \"end\": 2.000011, \n                    \"omitted\": false, \n                    \"seconds\": 0.9999200105667114, \n                    \"sender\": false, \n                    \"socket\": 5, \n                    \"start\": 1.000091\n                }\n            ], \n            \"sum\": {\n                \"bits_per_second\": 14863460.919815684, \n                \"bytes\": 1857784, \n                \"end\": 2.000011, \n                \"omitted\": false, \n                \"seconds\": 0.9999200105667114, \n                \"sender\": false, \n                \"start\": 1.000091\n            }\n        }, \n        {\n            \"streams\": [\n                {\n                    \"bits_per_second\": 17014906.203482434, \n                    \"bytes\": 2127112, \n                    \"end\": 3.000128, \n                    \"omitted\": false, \n                    \"seconds\": 1.0001169443130493, \n                    \"sender\": false, \n                    \"socket\": 5, \n                    \"start\": 2.000011\n                }\n            ], \n            \"sum\": {\n                \"bits_per_second\": 17014906.203482434, \n                \"bytes\": 2127112, \n                \"end\": 3.000128, \n                \"omitted\": false, \n                \"seconds\": 1.0001169443130493, \n                \"sender\": false, \n                \"start\": 2.000011\n            }\n        }, \n        {\n            \"streams\": [\n                {\n                    \"bits_per_second\": 19484678.222780876, \n                    \"bytes\": 2435536, \n                    \"end\": 4.000108, \n                    \"omitted\": false, \n                    \"seconds\": 0.9999799728393555, \n                    \"sender\": false, \n                    \"socket\": 5, \n                    \"start\": 3.000128\n                }\n            ], \n            \"sum\": {\n                \"bits_per_second\": 19484678.222780876, \n                \"bytes\": 2435536, \n                \"end\": 4.000108, \n                \"omitted\": false, \n                \"seconds\": 0.9999799728393555, \n                \"sender\": false, \n                \"start\": 3.000128\n            }\n        }, \n        {\n            \"streams\": [\n                {\n                    \"bits_per_second\": 20886327.96649205, \n                    \"bytes\": 2610744, \n                    \"end\": 5.00009, \n                    \"omitted\": false, \n                    \"seconds\": 0.9999819993972778, \n                    \"sender\": false, \n                    \"socket\": 5, \n                    \"start\": 4.000108\n                }\n            ], \n            \"sum\": {\n                \"bits_per_second\": 20886327.96649205, \n                \"bytes\": 2610744, \n                \"end\": 5.00009, \n                \"omitted\": false, \n                \"seconds\": 0.9999819993972778, \n                \"sender\": false, \n                \"start\": 4.000108\n            }\n        }, \n        {\n            \"streams\": [\n                {\n                    \"bits_per_second\": 21662059.341450367, \n                    \"bytes\": 2707760, \n                    \"end\": 6.000091, \n                    \"omitted\": false, \n                    \"seconds\": 1.0000009536743164, \n                    \"sender\": false, \n                    \"socket\": 5, \n                    \"start\": 5.00009\n                }\n            ], \n            \"sum\": {\n                \"bits_per_second\": 21662059.341450367, \n                \"bytes\": 2707760, \n                \"end\": 6.000091, \n                \"omitted\": false, \n                \"seconds\": 1.0000009536743164, \n                \"sender\": false, \n                \"start\": 5.00009\n            }\n        }, \n        {\n            \"streams\": [\n                {\n                    \"bits_per_second\": 18289947.719237924, \n                    \"bytes\": 2286392, \n                    \"end\": 7.000156, \n                    \"omitted\": false, \n                    \"seconds\": 1.0000649690628052, \n                    \"sender\": false, \n                    \"socket\": 5, \n                    \"start\": 6.000091\n                }\n            ], \n            \"sum\": {\n                \"bits_per_second\": 18289947.719237924, \n                \"bytes\": 2286392, \n                \"end\": 7.000156, \n                \"omitted\": false, \n                \"seconds\": 1.0000649690628052, \n                \"sender\": false, \n                \"start\": 6.000091\n            }\n        }, \n        {\n            \"streams\": [\n                {\n                    \"bits_per_second\": 21987707.184100278, \n                    \"bytes\": 2748304, \n                    \"end\": 8.000098, \n                    \"omitted\": false, \n                    \"seconds\": 0.9999420046806335, \n                    \"sender\": false, \n                    \"socket\": 5, \n                    \"start\": 7.000156\n                }\n            ], \n            \"sum\": {\n                \"bits_per_second\": 21987707.184100278, \n                \"bytes\": 2748304, \n                \"end\": 8.000098, \n                \"omitted\": false, \n                \"seconds\": 0.9999420046806335, \n                \"sender\": false, \n                \"start\": 7.000156\n            }\n        }, \n        {\n            \"streams\": [\n                {\n                    \"bits_per_second\": 14463469.327858254, \n                    \"bytes\": 1808552, \n                    \"end\": 9.00044, \n                    \"omitted\": false, \n                    \"seconds\": 1.0003420114517212, \n                    \"sender\": false, \n                    \"socket\": 5, \n                    \"start\": 8.000098\n                }\n            ], \n            \"sum\": {\n                \"bits_per_second\": 14463469.327858254, \n                \"bytes\": 1808552, \n                \"end\": 9.00044, \n                \"omitted\": false, \n                \"seconds\": 1.0003420114517212, \n                \"sender\": false, \n                \"start\": 8.000098\n            }\n        }, \n        {\n            \"streams\": [\n                {\n                    \"bits_per_second\": 20696350.342146516, \n                    \"bytes\": 2586128, \n                    \"end\": 10.000086, \n                    \"omitted\": false, \n                    \"seconds\": 0.999646008014679, \n                    \"sender\": false, \n                    \"socket\": 5, \n                    \"start\": 9.00044\n                }\n            ], \n            \"sum\": {\n                \"bits_per_second\": 20696350.342146516, \n                \"bytes\": 2586128, \n                \"end\": 10.000086, \n                \"omitted\": false, \n                \"seconds\": 0.999646008014679, \n                \"sender\": false, \n                \"start\": 9.00044\n            }\n        }, \n        {\n            \"streams\": [\n                {\n                    \"bits_per_second\": 21601073.494096223, \n                    \"bytes\": 128872, \n                    \"end\": 10.047814, \n                    \"omitted\": false, \n                    \"seconds\": 0.04772799834609032, \n                    \"sender\": false, \n                    \"socket\": 5, \n                    \"start\": 10.000086\n                }\n            ], \n            \"sum\": {\n                \"bits_per_second\": 21601073.494096223, \n                \"bytes\": 128872, \n                \"end\": 10.047814, \n                \"omitted\": false, \n                \"seconds\": 0.04772799834609032, \n                \"sender\": false, \n                \"start\": 10.000086\n            }\n        }\n    ], \n    \"start\": {\n        \"accepted_connection\": {\n            \"host\": \"172.16.0.2\", \n            \"port\": 58664\n        }, \n        \"connected\": [\n            {\n                \"local_host\": \"172.16.0.1\", \n                \"local_port\": 5201, \n                \"remote_host\": \"172.16.0.2\", \n                \"remote_port\": 58670, \n                \"socket\": 5\n            }\n        ], \n        \"cookie\": \"haynwtwrzas4rqwqq4ht5vpim7byl2chenea\", \n        \"fq_rate\": 0, \n        \"rcvbuf_actual\": 87380, \n        \"sndbuf_actual\": 65536, \n        \"sock_bufsize\": 0, \n        \"system_info\": \"REDACTED\", \n        \"target_bitrate\": 0, \n        \"tcp_mss_default\": 0, \n        \"test_start\": {\n            \"bidir\": 0, \n            \"blksize\": 131072, \n            \"blocks\": 0, \n            \"bytes\": 0, \n            \"duration\": 10, \n            \"fqrate\": 0, \n            \"num_streams\": 1, \n            \"omit\": 0, \n            \"protocol\": \"TCP\", \n            \"reverse\": 0, \n            \"target_bitrate\": 0, \n            \"tos\": 0\n        }, \n        \"timestamp\": {\n            \"time\": \"Wed, 11 Sep 2024 18:09:04 GMT\", \n            \"timesecs\": 1726078144\n        }, \n        \"version\": \"iperf 3.14\"\n    }\n}\n","summary":{"streams":[{"end":10.000445,"rtt":97515,"start":0,"stream-id":5,"retransmits":413,"throughput-bits":21180292.676975876,"throughput-bytes":26476544}],"summary":{"end":10.000445,"start":0,"retransmits":413,"throughput-bits":21180292.676975876,"throughput-bytes":26476544,"receiver-throughput-bits":18558031.42852764}},"intervals":[{"streams":[{"end":1.000297,"rtt":152803,"start":0,"omitted":false,"stream-id":5,"retransmits":270,"tcp-window-size":195480,"throughput-bits":44027118.13228946,"throughput-bytes":5505024}],"summary":{"end":1.000297,"start":0,"omitted":false,"retransmits":270,"throughput-bits":44027118.13228946,"throughput-bytes":5505024}},{"streams":[{"end":2.000064,"rtt":55985,"start":1.000297,"omitted":false,"stream-id":5,"retransmits":50,"tcp-window-size":118736,"throughput-bits":20976407.38873497,"throughput-bytes":2621440}],"summary":{"end":2.000064,"start":1.000297,"omitted":false,"retransmits":50,"throughput-bits":20976407.38873497,"throughput-bytes":2621440}},{"streams":[{"end":3.000421,"rtt":56801,"start":2.000064,"omitted":false,"stream-id":5,"retransmits":0,"tcp-window-size":141904,"throughput-bits":10482017.586160833,"throughput-bytes":1310720}],"summary":{"end":3.000421,"start":2.000064,"omitted":false,"retransmits":0,"throughput-bits":10482017.586160833,"throughput-bytes":1310720}},{"streams":[{"end":4.000311,"rtt":67686,"start":3.000421,"omitted":false,"stream-id":5,"retransmits":0,"tcp-window-size":167968,"throughput-bits":20973826.50364752,"throughput-bytes":2621440}],"summary":{"end":4.000311,"start":3.000421,"omitted":false,"retransmits":0,"throughput-bits":20973826.50364752,"throughput-bytes":2621440}},{"streams":[{"end":5.000262,"rtt":77986,"start":4.000311,"omitted":false,"stream-id":5,"retransmits":0,"tcp-window-size":215752,"throughput-bits":20972547.550344847,"throughput-bytes":2621440}],"summary":{"end":5.000262,"start":4.000311,"omitted":false,"retransmits":0,"throughput-bits":20972547.550344847,"throughput-bytes":2621440}},{"streams":[{"end":6.000295,"rtt":98493,"start":5.000262,"omitted":false,"stream-id":5,"retransmits":0,"tcp-window-size":273672,"throughput-bits":20970827.522866268,"throughput-bytes":2621440}],"summary":{"end":6.000295,"start":5.000262,"omitted":false,"retransmits":0,"throughput-bits":20970827.522866268,"throughput-bytes":2621440}},{"streams":[{"end":7.00031,"rtt":123400,"start":6.000295,"omitted":false,"stream-id":5,"retransmits":0,"tcp-window-size":327248,"throughput-bits":20971205.004731346,"throughput-bytes":2621440}],"summary":{"end":7.00031,"start":6.000295,"omitted":false,"retransmits":0,"throughput-bits":20971205.004731346,"throughput-bytes":2621440}},{"streams":[{"end":8.000223,"rtt":66634,"start":7.00031,"omitted":false,"stream-id":5,"retransmits":61,"tcp-window-size":183896,"throughput-bits":20973345.1588304,"throughput-bytes":2621440}],"summary":{"end":8.000223,"start":7.00031,"omitted":false,"retransmits":61,"throughput-bits":20973345.1588304,"throughput-bytes":2621440}},{"streams":[{"end":9.000738,"rtt":229567,"start":8.000223,"omitted":false,"stream-id":5,"retransmits":18,"tcp-window-size":98464,"throughput-bits":10480362.779482918,"throughput-bytes":1310720}],"summary":{"end":9.000738,"start":8.000223,"omitted":false,"retransmits":18,"throughput-bits":10480362.779482918,"throughput-bytes":1310720}},{"streams":[{"end":10.000445,"rtt":45800,"start":9.000738,"omitted":false,"stream-id":5,"retransmits":14,"tcp-window-size":127424,"throughput-bits":20977666.80111374,"throughput-bytes":2621440}],"summary":{"end":10.000445,"start":9.000738,"omitted":false,"retransmits":14,"throughput-bits":20977666.80111374,"throughput-bytes":2621440}}],"succeeded":true}
